Workbook

Sheet Model
CF1: SCENARIO SWITCH ▼ (Bull / Base / Bear) — drives all scenario-linked forecast drivers
B2: C.H. Robinson Worldwide, Inc. (Nasdaq: CHRW) — 3-Statement Financial Model | CF2: Base
B3: US GAAP as reported · USD millions (per-share data in USD; headcount in employees) · Source: C.H. Robinson Forms 10-K / 10-Q and Form 8-K earnings releases (Ex. 99.1; Ex. 99.3 segment recast Jan-2017), Q2-26 earnings presentation (Ex. 99.2), XBRL companyfacts, SEC EDGAR CIK 0001043277 (investor-relations releases are the same documents as filed on EDGAR); RXO deal 8-K 5-Oct-26
B4: Basis notes: calendar fiscal year. Each period as originally reported in its own earnings release. "Gross profits" (to 2008) → "net revenues" (2009–18) → adjusted gross profit (AGP, non-GAAP, 2019+); GAAP gross profit presented from Q1/23 (AGP − direct software amortization). ASC 606 from 2018 (contract assets). Segments (NAST / Global Forwarding / Robinson Fresh / All Other & Corporate) from Q4/16, recast to 2014; Robinson Fresh folded into All Other & Corporate from 2019. T-Chek (payment services) sold Nov-2012; Phoenix International acquired Nov-2012; Freightquote Jan-2015; Prime Distribution 2019; Europe Surface Transportation sold 1-Feb-2025. RXO acquisition (announced 5-Oct-26, close expected 1H27) excluded here — modelled on the RXO PF tab.
CH5: Forecast | CI5: Historical | CJ5: Historical | CK5: Historical
B6: (USDm) | C6: 2006 | D6: 2007 | E6: 2008 | F6: 2009 | G6: 2010 | H6: 2011 | I6: 2012 | J6: Q1/13 | K6: Q2/13 | L6: Q3/13 | M6: Q4/13 | N6: 2013 | O6: Q1/14 | P6: Q2/14 | Q6: Q3/14 | R6: Q4/14 | S6: 2014 | T6: Q1/15 | U6: Q2/15 | V6: Q3/15 | W6: Q4/15 | X6: 2015 | Y6: Q1/16 | Z6: Q2/16 | AA6: Q3/16 | AB6: Q4/16 | AC6: 2016 | AD6: Q1/17 | AE6: Q2/17 | AF6: Q3/17 | AG6: Q4/17 | AH6: 2017 | AI6: Q1/18 | AJ6: Q2/18 | AK6: Q3/18 | AL6: Q4/18 | AM6: 2018 | AN6: Q1/19 | AO6: Q2/19 | AP6: Q3/19 | AQ6: Q4/19 | AR6: 2019 | AS6: Q1/20 | AT6: Q2/20 | AU6: Q3/20 | AV6: Q4/20 | AW6: 2020 | AX6: Q1/21 | AY6: Q2/21 | AZ6: Q3/21 | BA6: Q4/21 | BB6: 2021 | BC6: Q1/22 | BD6: Q2/22 | BE6: Q3/22 | BF6: Q4/22 | BG6: 2022 | BH6: Q1/23 | BI6: Q2/23 | BJ6: Q3/23 | BK6: Q4/23 | BL6: 2023 | BM6: Q1/24 | BN6: Q2/24 | BO6: Q3/24 | BP6: Q4/24 | BQ6: 2024 | BR6: Q1/25 | BS6: Q2/25 | BT6: Q3/25 | BU6: Q4/25 | BV6: 2025 | BW6: Q1/26 | BX6: Q2/26 | BY6: Q3/26E | BZ6: Q4/26E | CA6: 2026E | CB6: 2027E | CC6: 2028E | CD6: 2029E | CE6: 2030E | CF6: Modelling Notes | CH6: 5Y CAGR | CI6: 5Y CAGR | CJ6: 10Y CAGR | CK6: 19Y CAGR
CH7: 25-'30 | CI7: 20-'25 | CJ7: 15-'25 | CK7: 06-'25
B8: SEGMENT P&L — NAST · GLOBAL FORWARDING · ALL OTHER & CORPORATE (volume × AGP-per-shipment build) | CF8: SEGMENT BUILD — modelling logic (volume × AGP per shipment → AGP → AGP margin → revenues; opex via headcount × cost per head)
CN9: SCENARIO INPUT TABLE — driver assumptions per Bull / Base / Bear | CO9: Bull | CP9: Base | CQ9: Bear | CR9: Bull / Bear = Base + Δ (Δ inputs on each block header). Outlook block = high / mid / low end of the FY26 ranges.
B10: North American Surface Transportation (NAST) — truckload, LTL & intermodal brokerage; reportable segment from Q4/16 (recast to 2014) | CF10: NAST — modelling logic
B11: NAST shipment volume y/y % (truckload + LTL) | J11: =IFERROR((J67*J22+J68*J23)/(J67+J68),"") -> 0.095364588 | K11: =IFERROR((K67*K22+K68*K23)/(K67+K68),"") -> 0.088132234 | L11: =IFERROR((L67*L22+L68*L23)/(L67+L68),"") -> 0.11496726 | M11: =IFERROR((M67*M22+M68*M23)/(M67+M68),"") -> 0.064395503 | N11: =IFERROR(AVERAGE(J11,K11,L11,M11),"") -> 0.090714896 | O11: =IFERROR((O67*O22+O68*O23)/(O67+O68),"") -> 0.032709993 | P11: =IFERROR((P67*P22+P68*P23)/(P67+P68),"") -> 0.047226529 | Q11: =IFERROR((Q67*Q22+Q68*Q23)/(Q67+Q68),"") -> 0.020864913 | R11: =IFERROR((R67*R22+R68*R23)/(R67+R68),"") -> 0.031767954 | S11: =IFERROR(AVERAGE(O11,P11,Q11,R11),"") -> 0.033142347 | T11: =IFERROR((T67*T22+T68*T23)/(T67+T68),"") -> 0.10894176 | U11: =IFERROR((U67*U22+U68*U23)/(U67+U68),"") -> 0.12585054 | V11: =IFERROR((V67*V22+V68*V23)/(V67+V68),"") -> 0.12365056 | W11: =IFERROR((W67*W22+W68*W23)/(W67+W68),"") -> 0.11483527 | X11: =IFERROR(AVERAGE(T11,U11,V11,W11),"") -> 0.11831953 | Y11: =IFERROR((Y67*Y22+Y68*Y23)/(Y67+Y68),"") -> 0.045474252 | Z11: =IFERROR((Z67*Z22+Z68*Z23)/(Z67+Z68),"") -> 0.03929209 | AA11: =IFERROR((AA67*AA22+AA68*AA23)/(AA67+AA68),"") -> 0.067864129 | AB11: =IFERROR((AB67*AB22+AB68*AB23)/(AB67+AB68),"") -> 0.087942507 | AC11: =IFERROR(AVERAGE(Y11,Z11,AA11,AB11),"") -> 0.060143245 | AD11: =IFERROR((AD67*AD22+AD68*AD23)/(AD67+AD68),"") -> 0.10392506 | AE11: =IFERROR((AE67*AE22+AE68*AE23)/(AE67+AE68),"") -> 0.076016961 | AF11: =IFERROR((AF67*AF22+AF68*AF23)/(AF67+AF68),"") -> 0.016434927 | AG11: =IFERROR((AG67*AG22+AG68*AG23)/(AG67+AG68),"") -> 0.00059578938 | AH11: =IFERROR(AVERAGE(AD11,AE11,AF11,AG11),"") -> 0.049243186 | AI11: 0.01 | AJ11: =IFERROR((AJ67*AJ22+AJ68*AJ23)/(AJ67+AJ68),"") -> -0.017831084 | AK11: =IFERROR((AK67*AK22+AK68*AK23)/(AK67+AK68),"") -> 0.0072325355 | AL11: =IFERROR((AL67*AL22+AL68*AL23)/(AL67+AL68),"") -> -0.006994319 | AM11: =IFERROR(AVERAGE(AI11,AJ11,AK11,AL11),"") -> -0.0018982168 | AN11: =IFERROR((AN67*AN22+AN68*AN23)/(AN67+AN68),"") -> 0.0061758785 | AO11: =IFERROR((AO67*AO22+AO68*AO23)/(AO67+AO68),"") -> -0.010072157 | AP11: =IFERROR((AP67*AP22+AP68*AP23)/(AP67+AP68),"") -> -0.017488029 | AQ11: =IFERROR((AQ67*AQ22+AQ68*AQ23)/(AQ67+AQ68),"") -> 0.012937462 | AR11: =IFERROR(AVERAGE(AN11,AO11,AP11,AQ11),"") -> -0.0021117113 | AS11: =IFERROR((AS67*AS22+AS68*AS23)/(AS67+AS68),"") -> 0.075 | AT11: =IFERROR((AT67*AT22+AT68*AT23)/(AT67+AT68),"") -> -0.038060609 | AU11: =IFERROR((AU67*AU22+AU68*AU23)/(AU67+AU68),"") -> 0.046697927 | AV11: =IFERROR((AV67*AV22+AV68*AV23)/(AV67+AV68),"") -> 0.035055467 | AW11: =IFERROR(AVERAGE(AS11,AT11,AU11,AV11),"") -> 0.029673196 | AX11: =IFERROR((AX67*AX22+AX68*AX23)/(AX67+AX68),"") -> -0.0030090541 | AY11: 0.16 | AZ11: 0.025 | BA11: 0 | BB11: =IFERROR(AVERAGE(AX11,AY11,AZ11,BA11),"") -> 0.045497736 | BC11: 0.01 | BD11: =IFERROR((BD67*BD22+BD68*BD23)/(BD67+BD68),"") -> 0.0011372843 | BE11: =IFERROR((BE67*BE22+BE68*BE23)/(BE67+BE68),"") -> -0.0007846964 | BF11: -0.02 | BG11: =IFERROR(AVERAGE(BC11,BD11,BE11,BF11),"") -> -0.002411853 | BH11: -0.045 | BI11: -0.025 | BJ11: -0.035 | BK11: -0.01 | BL11: =IFERROR(AVERAGE(BH11,BI11,BJ11,BK11),"") -> -0.02875 | BM11: 0.015 | BN11: 0.015 | BO11: =IFERROR((BO67*BO22+BO68*BO23)/(BO67+BO68),"") -> -0.014673977 | BP11: -0.01 | BQ11: =IFERROR(AVERAGE(BM11,BN11,BO11,BP11),"") -> 0.0013315058 | BR11: -0.01 | BS11: 0.01 | BT11: 0.03 | BU11: 0.01 | BV11: =IFERROR(AVERAGE(BR11,BS11,BT11,BU11),"") -> 0.01 | BW11: 0 | BX11: 0.015 | BY11: =$BX$11 -> 0.015 | BZ11: =$BX$11 -> 0.015 | CA11: =AVERAGE(BW11:BZ11) -> 0.01125 | CB11: =CHOOSE(MATCH($CF$2,{"Bull","Base","Bear"},0),$CO$20,$CP$20,$CQ$20) -> 0.03 | CC11: =CHOOSE(MATCH($CF$2,{"Bull","Base","Bear"},0),$CO$21,$CP$21,$CQ$21) -> 0.035 | CD11: =CHOOSE(MATCH($CF$2,{"Bull","Base","Bear"},0),$CO$22,$CP$22,$CQ$22) -> 0.03 | CE11: =CHOOSE(MATCH($CF$2,{"Bull","Base","Bear"},0),$CO$23,$CP$23,$CQ$23) -> 0.03 | CF11: History: company-stated combined NAST truckload + LTL volume growth (from 2018); earlier quarters = AGP-weighted average of stated TL and LTL volume growth; annual = average of quarters. Q3/26E–Q4/26E: Q2/26 rate (+1.5%). 2027E+: scenario lever NAST_vol. | CN11: FY26 outlook — Q2-26 release & earnings deck (29-Jul-26) | CO11: High | CP11: Mid | CQ11: Low | CR11: CHRW guides operating income (excl. restructuring), tax rate and capex only; no AGP / revenue guidance.
B12: NAST AGP per shipment y/y % (price / mix) | T12: =IFERROR((1+T14)/(1+T11)-1,"") | U12: =IFERROR((1+U14)/(1+U11)-1,"") | V12: =IFERROR((1+V14)/(1+V11)-1,"") | W12: =IFERROR((1+W14)/(1+W11)-1,"") | X12: =IFERROR((1+X14)/(1+X11)-1,"") -> 0.035529255 | Y12: =IFERROR((1+Y14)/(1+Y11)-1,"") -> 0.025404978 | Z12: =IFERROR((1+Z14)/(1+Z11)-1,"") -> -0.03526427 | AA12: =IFERROR((1+AA14)/(1+AA11)-1,"") -> -0.1374788 | ... BX12: =IFERROR((1+BX14)/(1+BX11)-1,"") -> 0.069877054 | BY12: =$BX$12+BY109 -> 0.084715672 | BZ12: =$BX$12+BY109 -> 0.084715672 | CA12: =IFERROR((1+CA14)/(1+CA11)-1,"") -> 0.067873609 | CB12: =CHOOSE(MATCH($CF$2,{"Bull","Base","Bear"},0),$CO$25,$CP$25,$CQ$25) -> 0.04 | CC12: =CHOOSE(MATCH($CF$2,{"Bull","Base","Bear"},0),$CO$26,$CP$26,$CQ$26) -> 0.03 | CD12: =CHOOSE(MATCH($CF$2,{"Bull","Base","Bear"},0),$CO$27,$CP$27,$CQ$27) -> 0.02 | CE12: =CHOOSE(MATCH($CF$2,{"Bull","Base","Bear"},0),$CO$28,$CP$28,$CQ$28) -> 0.02 | CF12: History: implied = (1 + AGP growth) / (1 + volume growth) − 1. Q3/26E–Q4/26E: Q2/26 implied rate + outlook calibration Δ (row "Outlook calibration"). 2027E+: scenario lever NAST_AGPps (contract repricing after the 2026 spot-cost spike, then normalisation). | CN12: FY26 adjusted income from operations target ($m; excl. restructuring & other charges) | CO12: 1040 | CP12: =AVERAGE(CO12,CQ12) -> 1002 | CQ12: 964 | CR12: $964m–$1.04bn "2026 Operating Income Target" (Q2-26 deck slide 17; reiterated). 1H/26 actual $459.2m. Drives the Q3/Q4-26E AGP calibration.
B13: Adjusted gross profit (AGP; "net revenues" to 2018) | S13: 1351.335 | T13: 358.009 | U13: 398.151 | V13: 410.478 | W13: 398.279 | X13: 1564.917 | Y13: 383.798 | Z13: 399.203 | AA13: 378.073 | AB13: 363.281 | AC13: 1524.355 | AD13: 372.44 | AE13: 359.906 | AF13: 377.403 | AG13: 415.315 | AH13: 1525.064 | AI13: 414.769 | AJ13: 436.813 | AK13: 465.522 | AL13: 471.394 | AM13: 1788.498 | AN13: 486.55 | AO13: 486.418 | AP13: 433.76 | AQ13: 390.641 | AR13: 1797.369 | AS13: 372.778 | AT13: 379.556 | AU13: 367.943 | AV13: 396.814 | AW13: 1517.091 | AX13: 421.108 | AY13: 436.596 | AZ13: 460.149 | BA13: 475.1 | BB13: 1792.953 | BC13: 506.1 | BD13: 624.551 | BE13: 563.787 | BF13: 502.266 | BG13: 2196.704 | BH13: 426.655 | BI13: 400.532 | BJ13: 386.51 | BK13: 380.157 | BL13: 1593.854 | BM13: 397.11 | BN13: 419.657 | BO13: 420.664 | BP13: 403.764 | BQ13: 1641.195 | BR13: 418.324 | BS13: 432.248 | BT13: 444.139 | BU13: 411.618 | BV13: 1706.329 | BW13: 431.077 | BX13: 469.389 | BY13: =BT13*(1+BY11)*(1+BY12) -> 488.991 | BZ13: =BU13*(1+BZ11)*(1+BZ12) -> 453.18582 | CA13: =SUM(BW13,BX13,BY13,BZ13) -> 1842.6428 | CB13: =CA13*(1+CB11)*(1+CB12) -> 1973.839 | CC13: =CB13*(1+CC11)*(1+CC12) -> 2104.2111 | CD13: =CC13*(1+CD11)*(1+CD12) -> 2210.6841 | CE13: =CD13*(1+CE11)*(1+CE12) -> 2322.5448 | CF13: Prior-year period × (1 + volume) × (1 + AGP per shipment). Segment AGP as reported (2014–Q3/16 from the FY2016 10-K / 8-K Ex. 99.3 recast). | CH13: =IFERROR((CE13/BV13)^(1/5)-1,"n/m") -> 0.06360474 | CI13: =IFERROR((BV13/AW13)^(1/5)-1,"n/m") -> 0.023788455 | CJ13: =IFERROR((BV13/X13)^(1/10)-1,"n/m") -> 0.0086886785 | CK13: =IFERROR((BV13/C13)^(1/19)-1,"n/m") -> n/m | CN13: FY26 effective tax rate | CO13: 0.18 | CP13: 0.19 | CQ13: 0.2 | CR13: "For 2026, we expect our full-year effective tax rate to be 18% to 20%" (Q2-26 release).
B14: AGP y/y % | D14: =IF(AND(ISNUMBER(D13),ISNUMBER(C13)),IFERROR(D13/C13-1,""),"") | E14: =IF(AND(ISNUMBER(E13),ISNUMBER(D13)),IFERROR(E13/D13-1,""),"") | F14: =IF(AND(ISNUMBER(F13),ISNUMBER(E13)),IFERROR(F13/E13-1,""),"") | G14: =IF(AND(ISNUMBER(G13),ISNUMBER(F13)),IFERROR(G13/F13-1,""),"") | H14: =IF(AND(ISNUMBER(H13),ISNUMBER(G13)),IFERROR(H13/G13-1,""),"") | I14: =IF(AND(ISNUMBER(I13),ISNUMBER(H13)),IFERROR(I13/H13-1,""),"") | N14: =IF(AND(ISNUMBER(N13),ISNUMBER(I13)),IFERROR(N13/I13-1,""),"") | O14: =IF(AND(ISNUMBER(O13),ISNUMBER(J13)),IFERROR(O13/J13-1,""),"") | P14: =IF(AND(ISNUMBER(P13),ISNUMBER(K13)),IFERROR(P13/K13-1,""),"") | Q14: =IF(AND(ISNUMBER(Q13),ISNUMBER(L13)),IFERROR(Q13/L13-1,""),"") | R14: =IF(AND(ISNUMBER(R13),ISNUMBER(M13)),IFERROR(R13/M13-1,""),"") | S14: =IF(AND(ISNUMBER(S13),ISNUMBER(N13)),IFERROR(S13/N13-1,""),"") | T14: =IF(AND(ISNUMBER(T13),ISNUMBER(O13)),IFERROR(T13/O13-1,""),"") | U14: =IF(AND(ISNUMBER(U13),ISNUMBER(P13)),IFERROR(U13/P13-1,""),"") | ... BX14: =IF(AND(ISNUMBER(BX13),ISNUMBER(BS13)),IFERROR(BX13/BS13-1,""),"") -> 0.08592521 | BY14: =IFERROR(BY13/BT13-1,"") -> 0.10098641 | BZ14: =IFERROR(BZ13/BU13-1,"") -> 0.10098641 | CA14: =IFERROR(CA13/BV13-1,"") -> 0.079887188 | CB14: =IFERROR(CB13/CA13-1,"") -> 0.0712 | CC14: =IFERROR(CC13/CB13-1,"") -> 0.06605 | CD14: =IFERROR(CD13/CC13-1,"") -> 0.0506 | CE14: =IFERROR(CE13/CD13-1,"") -> 0.0506 | CN14: FY26 capital expenditures ($m) | CO14: 75 | CP14: 70 | CQ14: 65 | CR14: "Capital expenditures for 2026 are expected to be $65 million to $75 million" (Q2-26 release; cut from $75–85m).
B15: AGP margin % of segment revenues | C15: =IF(AND(ISNUMBER(C13),ISNUMBER(C16)),IFERROR(C13/C16,""),"") | D15: =IF(AND(ISNUMBER(D13),ISNUMBER(D16)),IFERROR(D13/D16,""),"") | E15: =IF(AND(ISNUMBER(E13),ISNUMBER(E16)),IFERROR(E13/E16,""),"") | F15: =IF(AND(ISNUMBER(F13),ISNUMBER(F16)),IFERROR(F13/F16,""),"") | G15: =IF(AND(ISNUMBER(G13),ISNUMBER(G16)),IFERROR(G13/G16,""),"") | H15: =IF(AND(ISNUMBER(H13),ISNUMBER(H16)),IFERROR(H13/H16,""),"") | I15: =IF(AND(ISNUMBER(I13),ISNUMBER(I16)),IFERROR(I13/I16,""),"") | J15: =IF(AND(ISNUMBER(J13),ISNUMBER(J16)),IFERROR(J13/J16,""),"") | ... BX15: =IF(AND(ISNUMBER(BX13),ISNUMBER(BX16)),IFERROR(BX13/BX16,""),"") -> 0.13063008 | BY15: =$BX$15 -> 0.13063008 | BZ15: =$BX$15 -> 0.13063008 | CA15: =IF(AND(ISNUMBER(CA13),ISNUMBER(CA16)),IFERROR(CA13/CA16,""),"") -> 0.13397971 | CB15: 0.135 | CC15: 0.14 | CD15: 0.145 | CE15: 0.145 | CF15: Revenue is an output: AGP ÷ AGP margin. Freight-rate pass-through moves revenue far more than AGP (Q2/26 margin 13.1% vs 14.8% a year earlier as spot costs spiked). Q3/Q4-26E: Q2/26 margin; 2027E+ partial normalisation toward the 2024–25 range (14–15%). | CN15: FY26 point estimates & capital allocation
B16: Total revenues (external) | S16: 8738.747 | T16: 2194.751 | U16: 2319.936 | V16: 2282.235 | W16: 2171.427 | X16: 8968.349 | Y16: 2045.479 | Z16: 2158.615 | AA16: 2252.187 | AB16: 2281.435 | AC16: 8737.716 | AD16: 2259.252 | AE16: 2381.551 | AF16: 2469.42 | AG16: 2618.587 | AH16: 9728.81 | AI16: 2663.011 | AJ16: 2878.904 | AK16: 2931.461 | AL16: 2774.524 | AM16: 11247.9 | AN16: 2796.784 | AO16: 2872.053 | AP16: 2826.308 | AQ16: 2788.547 | AR16: 11283.692 | AS16: 2823.745 | AT16: 2475.292 | AU16: 2923.842 | AV16: 3089.674 | AW16: 11312.553 | AX16: 3211.423 | AY16: 3585.481 | AZ16: 3814.988 | BA16: 3896.025 | BB16: 14507.917 | BC16: 4114.889 | BD16: 4147.046 | BE16: 4002.461 | BF16: 3563.071 | BG16: 15827.467 | BH16: 3304.187 | BI16: 3079.268 | BJ16: 3086.97 | BK16: 3000.65 | BL16: 12471.075 | BM16: 3000.313 | BN16: 2989.909 | BO16: 2934.617 | BP16: 2802.7 | BQ16: 11727.539 | BR16: 2868.42 | BS16: 2918.227 | BT16: 2965.694 | BU16: 2810.373 | BV16: 11562.714 | BW16: 2947.323 | BX16: 3593.269 | BY16: =IF(AND(ISNUMBER(BY13),ISNUMBER(BY15)),IFERROR(BY13/BY15,""),"") -> 3743.3263 | BZ16: =IF(AND(ISNUMBER(BZ13),ISNUMBER(BZ15)),IFERROR(BZ13/BZ15,""),"") -> 3469.2304 | CA16: =SUM(BW16,BX16,BY16,BZ16) -> 13753.149 | CB16: =IF(AND(ISNUMBER(CB13),ISNUMBER(CB15)),IFERROR(CB13/CB15,""),"") -> 14621.03 | CC16: =IF(AND(ISNUMBER(CC13),ISNUMBER(CC15)),IFERROR(CC13/CC15,""),"") -> 15030.079 | CD16: =IF(AND(ISNUMBER(CD13),ISNUMBER(CD15)),IFERROR(CD13/CD15,""),"") -> 15246.098 | CE16: =IF(AND(ISNUMBER(CE13),ISNUMBER(CE15)),IFERROR(CE13/CE15,""),"") -> 16017.55 | CH16: =IFERROR((CE16/BV16)^(1/5)-1,"n/m") -> 0.067351 | CI16: =IFERROR((BV16/AW16)^(1/5)-1,"n/m") -> 0.0043841055 | CJ16: =IFERROR((BV16/X16)^(1/10)-1,"n/m") -> 0.025733946 | CK16: =IFERROR((BV16/C16)^(1/19)-1,"n/m") -> n/m | CN16: 2H/26 share repurchases ($m; ex withholding) | CO16: 350 | CP16: 250 | CQ16: 150 | CR16: 1H/26 repurchases $432m (Q2/26 $226m at $166.89 avg). Standalone case — the RXO PF tab applies the post-close buyback pause.
B17: Revenues y/y % | D17: =IF(AND(ISNUMBER(D16),ISNUMBER(C16)),IFERROR(D16/C16-1,""),"") | E17: =IF(AND(ISNUMBER(E16),ISNUMBER(D16)),IFERROR(E16/D16-1,""),"") | F17: =IF(AND(ISNUMBER(F16),ISNUMBER(E16)),IFERROR(F16/E16-1,""),"") | G17: =IF(AND(ISNUMBER(G16),ISNUMBER(F16)),IFERROR(G16/F16-1,""),"") | H17: =IF(AND(ISNUMBER(H16),ISNUMBER(G16)),IFERROR(H16/G16-1,""),"") | I17: =IF(AND(ISNUMBER(I16),ISNUMBER(H16)),IFERROR(I16/H16-1,""),"") | N17: =IF(AND(ISNUMBER(N16),ISNUMBER(I16)),IFERROR(N16/I16-1,""),"") | O17: =IF(AND(ISNUMBER(O16),ISNUMBER(J16)),IFERROR(O16/J16-1,""),"") | P17: =IF(AND(ISNUMBER(P16),ISNUMBER(K16)),IFERROR(P16/K16-1,""),"") | Q17: =IF(AND(ISNUMBER(Q16),ISNUMBER(L16)),IFERROR(Q16/L16-1,""),"") | R17: =IF(AND(ISNUMBER(R16),ISNUMBER(M16)),IFERROR(R16/M16-1,""),"") | S17: =IF(AND(ISNUMBER(S16),ISNUMBER(N16)),IFERROR(S16/N16-1,""),"") | T17: =IF(AND(ISNUMBER(T16),ISNUMBER(O16)),IFERROR(T16/O16-1,""),"") | U17: =IF(AND(ISNUMBER(U16),ISNUMBER(P16)),IFERROR(U16/P16-1,""),"") | ... BX17: =IF(AND(ISNUMBER(BX16),ISNUMBER(BS16)),IFERROR(BX16/BS16-1,""),"") -> 0.23131922 | BY17: =IFERROR(BY16/BT16-1,"") -> 0.26220923 | BZ17: =IFERROR(BZ16/BU16-1,"") -> 0.23443769 | CA17: =IFERROR(CA16/BV16-1,"") -> 0.18943949 | CB17: =IFERROR(CB16/CA16-1,"") -> 0.063104159 | CC17: =IFERROR(CC16/CB16-1,"") -> 0.027976786 | CD17: =IFERROR(CD16/CC16-1,"") -> 0.014372414 | CE17: =IFERROR(CE16/CD16-1,"") -> 0.0506 | CN17: Minimum net debt / adjusted EBITDA (x) — 2027E+ buyback plug | CO17: 1.5 | CP17: 1.25 | CQ17: 1 | CR17: Standalone: maintain leverage ~1.5x (YE25 ~1.0x; Q2/26 ~1.5x after buybacks & freight-rate working capital). Investment-grade (BBB+/Baa2).
B18: Income from operations (segment, as reported) | S18: 644.708 | T18: 150.093 | U18: 187.063 | V18: 197.209 | W18: 183.964 | X18: 718.329 | Y18: 162.351 | Z18: 182.721 | AA18: 171.733 | AB18: 157.631 | AC18: 674.436 | AD18: 155.877 | AE18: 140.284 | AF18: 151.392 | AG18: 180.557 | AH18: 628.11 | AI18: 174.078 | AJ18: 184.566 | AK18: 204.158 | AL18: 211.044 | AM18: 773.846 | AN18: 211.283 | AO18: 204.732 | AP18: 176.2 | AQ18: 130.548 | AR18: 722.763 | AS18: 98.526 | AT18: 136.846 | AU18: 122.526 | AV18: 150.577 | AW18: 508.475 | AX18: 136.784 | AY18: 151.092 | AZ18: 149.035 | BA18: 148.44 | BB18: 585.351 | BC18: 182.354 | BD18: 276.499 | BE18: 211.899 | BF18: 162.55 | BG18: 833.302 | BH18: 134.022 | BI18: 117.859 | BJ18: 112.121 | BK18: 95.958 | BL18: 459.96 | BM18: 108.895 | BN18: 141.102 | BO18: 148.767 | BP18: 132.528 | BQ18: 531.292 | BR18: 143.671 | BS18: 163.991 | BT18: 172.878 | BU18: 141.296 | BV18: 621.836 | BW18: 145.13 | BX18: 189.845
B19: Operating margin % of AGP (segment, GAAP; mid-cycle target 40%) | C19: =IF(AND(ISNUMBER(C18),ISNUMBER(C13)),IFERROR(C18/C13,""),"") | D19: =IF(AND(ISNUMBER(D18),ISNUMBER(D13)),IFERROR(D18/D13,""),"") | E19: =IF(AND(ISNUMBER(E18),ISNUMBER(E13)),IFERROR(E18/E13,""),"") | F19: =IF(AND(ISNUMBER(F18),ISNUMBER(F13)),IFERROR(F18/F13,""),"") | G19: =IF(AND(ISNUMBER(G18),ISNUMBER(G13)),IFERROR(G18/G13,""),"") | H19: =IF(AND(ISNUMBER(H18),ISNUMBER(H13)),IFERROR(H18/H13,""),"") | I19: =IF(AND(ISNUMBER(I18),ISNUMBER(I13)),IFERROR(I18/I13,""),"") | J19: =IF(AND(ISNUMBER(J18),ISNUMBER(J13)),IFERROR(J18/J13,""),"") | ... BX19: =IF(AND(ISNUMBER(BX18),ISNUMBER(BX13)),IFERROR(BX18/BX13,""),"") -> 0.40445132 | CN19: NAST_vol (NAST truckload + LTL volume y/y) | CO19: 0.02 | CP19: Δ → | CQ19: -0.02 | CR19: Outgrowing the Cass index for 13 straight quarters (Q2/26 +1.5% vs Cass −3.3%). Base assumes freight-cycle recovery from 2027 plus continued share gains.
B20: Average employee headcount | S20: 5447 | T20: 6391 | U20: 6575 | V20: 6723 | W20: 6683 | X20: 6575 | Y20: 6666 | Z20: 6800 | AA20: 6869 | AB20: 6809 | AC20: 6773 | AD20: 6844 | AE20: 7003 | AF20: 6998 | AG20: 6878 | AH20: 6907 | AI20: 6855 | AJ20: 6957 | AK20: 7007 | AL20: 6964 | AM20: 6938 | AN20: 7424 | AO20: 7533 | AP20: 7448 | AQ20: 7154 | AR20: 7354 | AS20: 7038 | AT20: 6960 | AU20: 6702 | AV20: 6555 | AW20: 6811 | AX20: 6537 | AY20: 6580 | AZ20: 6764 | BA20: 7044 | BB20: 6764 | BC20: 7348 | BD20: 7552 | BE20: 7493 | BF20: 7251 | BG20: 7365 | BH20: 6870 | BI20: 6497 | BJ20: 6278 | BK20: 6103 | BL20: 6469 | BM20: 6004 | BN20: 5868 | BO20: 5595 | BP20: 5348 | BQ20: 5696 | BR20: 5280 | BS20: 5283 | BT20: 5187 | BU20: 4970 | BV20: 5158 | BW20: 4752 | BX20: 4671 | CN20: 2027E | CO20: =CP20+$CO$19 -> 0.05 | CP20: 0.03 | CQ20: =CP20+$CQ$19 -> 0.01
B21: AGP per average employee ($000, annualised) | C21: =IFERROR(C13*1/C20*1000,"") | D21: =IFERROR(D13*1/D20*1000,"") | E21: =IFERROR(E13*1/E20*1000,"") | F21: =IFERROR(F13*1/F20*1000,"") | G21: =IFERROR(G13*1/G20*1000,"") | H21: =IFERROR(H13*1/H20*1000,"") | I21: =IFERROR(I13*1/I20*1000,"") | J21: =IFERROR(J13*4/J20*1000,"") | K21: =IFERROR(K13*4/K20*1000,"") | L21: =IFERROR(L13*4/L20*1000,"") | M21: =IFERROR(M13*4/M20*1000,"") | N21: =IFERROR(N13*1/N20*1000,"") | O21: =IFERROR(O13*4/O20*1000,"") | P21: =IFERROR(P13*4/P20*1000,"") | Q21: =IFERROR(Q13*4/Q20*1000,"") | R21: =IFERROR(R13*4/R20*1000,"") | S21: =IFERROR(S13*1/S20*1000,"") -> 248.08794 | T21: =IFERROR(T13*4/T20*1000,"") -> 224.07072 | U21: =IFERROR(U13*4/U20*1000,"") -> 242.22114 | V21: =IFERROR(V13*4/V20*1000,"") -> 244.22311 | W21: =IFERROR(W13*4/W20*1000,"") -> 238.38336 | X21: =IFERROR(X13*1/X20*1000,"") -> 238.01019 | Y21: =IFERROR(Y13*4/Y20*1000,"") -> 230.30183 | Z21: =IFERROR(Z13*4/Z20*1000,"") -> 234.82529 | AA21: =IFERROR(AA13*4/AA20*1000,"") -> 220.16189 | AB21: =IFERROR(AB13*4/AB20*1000,"") -> 213.41225 | AC21: =IFERROR(AC13*1/AC20*1000,"") -> 225.06349 | AD21: =IFERROR(AD13*4/AD20*1000,"") -> 217.67387 | AE21: =IFERROR(AE13*4/AE20*1000,"") -> 205.57247 | AF21: =IFERROR(AF13*4/AF20*1000,"") -> 215.72049 | AG21: =IFERROR(AG13*4/AG20*1000,"") -> 241.53242 | AH21: =IFERROR(AH13*1/AH20*1000,"") -> 220.79977 | AI21: =IFERROR(AI13*4/AI20*1000,"") -> 242.02422 | AJ21: =IFERROR(AJ13*4/AJ20*1000,"") -> 251.15021 | AK21: =IFERROR(AK13*4/AK20*1000,"") -> 265.74682 | AL21: =IFERROR(AL13*4/AL20*1000,"") -> 270.76048 | AM21: =IFERROR(AM13*1/AM20*1000,"") -> 257.78293 | AN21: =IFERROR(AN13*4/AN20*1000,"") -> 262.14978 | AO21: =IFERROR(AO13*4/AO20*1000,"") -> 258.28647 | AP21: =IFERROR(AP13*4/AP20*1000,"") -> 232.95381 | AQ21: =IFERROR(AQ13*4/AQ20*1000,"") -> 218.41823 | AR21: =IFERROR(AR13*1/AR20*1000,"") -> 244.40699 | AS21: =IFERROR(AS13*4/AS20*1000,"") -> 211.86587 | AT21: =IFERROR(AT13*4/AT20*1000,"") -> 218.13563 | AU21: =IFERROR(AU13*4/AU20*1000,"") -> 219.60191 | AV21: =IFERROR(AV13*4/AV20*1000,"") -> 242.14432 | AW21: =IFERROR(AW13*1/AW20*1000,"") -> 222.7413 | AX21: =IFERROR(AX13*4/AX20*1000,"") -> 257.67661 | AY21: =IFERROR(AY13*4/AY20*1000,"") -> 265.4079 | AZ21: =IFERROR(AZ13*4/AZ20*1000,"") -> 272.1165 | BA21: =IFERROR(BA13*4/BA20*1000,"") -> 269.78989 | BB21: =IFERROR(BB13*1/BB20*1000,"") -> 265.07289 | BC21: =IFERROR(BC13*4/BC20*1000,"") -> 275.50354 | BD21: =IFERROR(BD13*4/BD20*1000,"") -> 330.80032 | BE21: =IFERROR(BE13*4/BE20*1000,"") -> 300.9673 | BF21: =IFERROR(BF13*4/BF20*1000,"") -> 277.07406 | BG21: =IFERROR(BG13*1/BG20*1000,"") -> 298.26259 | BH21: =IFERROR(BH13*4/BH20*1000,"") -> 248.4163 | BI21: =IFERROR(BI13*4/BI20*1000,"") -> 246.59504 | BJ21: =IFERROR(BJ13*4/BJ20*1000,"") -> 246.26314 | BK21: =IFERROR(BK13*4/BK20*1000,"") -> 249.16074 | BL21: =IFERROR(BL13*1/BL20*1000,"") -> 246.38337 | BM21: =IFERROR(BM13*4/BM20*1000,"") -> 264.56362 | BN21: =IFERROR(BN13*4/BN20*1000,"") -> 286.06476 | BO21: =IFERROR(BO13*4/BO20*1000,"") -> 300.74281 | BP21: =IFERROR(BP13*4/BP20*1000,"") -> 301.99252 | BQ21: =IFERROR(BQ13*1/BQ20*1000,"") -> 288.13114 | BR21: =IFERROR(BR13*4/BR20*1000,"") -> 316.91212 | BS21: =IFERROR(BS13*4/BS20*1000,"") -> 327.27465 | BT21: =IFERROR(BT13*4/BT20*1000,"") -> 342.50164 | BU21: =IFERROR(BU13*4/BU20*1000,"") -> 331.28209 | BV21: =IFERROR(BV13*1/BV20*1000,"") -> 330.81214 | BW21: =IFERROR(BW13*4/BW20*1000,"") -> 362.85943 | BX21: =IFERROR(BX13*4/BX20*1000,"") -> 401.96018 | CN21: 2028E | CO21: =CP21+$CO$19 -> 0.055 | CP21: 0.035 | CQ21: =CP21+$CQ$19 -> 0.015
B22: Memo: truckload volume y/y % (NAST; company total to Q2/14) | J22: 0.09 | K22: 0.09 | L22: 0.13 | M22: 0.07 | O22: 0.04 | P22: 0.04 | Q22: 0.01 | R22: 0.03 | T22: 0.06 | U22: 0.07 | V22: 0.07 | W22: 0.05 | Y22: 0.03 | Z22: 0.03 | AA22: 0.075 | AB22: 0.1 | AD22: 0.11 | AE22: 0.08 | AF22: 0 | AG22: -0.03 | AI22: -0.07 | AJ22: -0.045 | AK22: -0.005 | AL22: -0.015 | AN22: 0.005 | AO22: -0.025 | AP22: -0.04 | AQ22: 0 | AS22: 0.075 | AT22: -0.045 | AU22: 0.005 | AV22: -0.035 | AX22: -0.065 | AY22: 0.06 | AZ22: 0.045 | BA22: 0.06 | BC22: 0.04 | BD22: 0.02 | BE22: 0.005 | BF22: -0.04 | BH22: -0.035 | BI22: -0.065 | BJ22: -0.06 | BK22: -0.015 | BM22: -0.005 | BN22: 0.015 | BO22: -0.035 | BP22: -0.065 | BR22: -0.045 | BT22: 0.03 | BU22: 0.03 | BW22: -0.035 | BX22: 0.005 | CN22: 2029E | CO22: =CP22+$CO$19 -> 0.05 | CP22: 0.03 | CQ22: =CP22+$CQ$19 -> 0.01
B23: Memo: LTL volume (shipments / orders) y/y % | J23: 0.12 | K23: 0.08 | L23: 0.05 | M23: 0.04 | P23: 0.08 | Q23: 0.07 | R23: 0.04 | T23: 0.28 | U23: 0.33 | V23: 0.32 | W23: 0.36 | Y23: 0.1 | Z23: 0.07 | AA23: 0.045 | AB23: 0.05 | AD23: 0.085 | AE23: 0.065 | AF23: 0.065 | AG23: 0.1 | AI23: 0.08 | AJ23: 0.06 | AK23: 0.045 | AL23: 0.02 | AN23: 0.01 | AO23: 0.035 | AP23: 0.04 | AQ23: 0.045 | AS23: 0.075 | AT23: -0.02 | AU23: 0.135 | AV23: 0.2 | AX23: 0.15 | AY23: 0.235 | AZ23: 0.01 | BA23: -0.04 | BC23: -0.01 | BD23: -0.05 | BE23: -0.015 | BF23: -0.01 | BH23: -0.05 | BI23: 0 | BJ23: -0.02 | BK23: -0.005 | BM23: 0.03 | BN23: 0.015 | BO23: 0.025 | BP23: 0.025 | BR23: 0.01 | BS23: 0.015 | BT23: 0.025 | BU23: 0.005 | BW23: 0.02 | BX23: 0.02 | CN23: 2030E | CO23: =CP23+$CO$19 -> 0.05 | CP23: 0.03 | CQ23: =CP23+$CQ$19 -> 0.01
B24: Memo: truckload AGP per shipment y/y % (per load Q1/21–Q1/22) | AX24: 0.23 | AY24: 0.07 | AZ24: 0.3 | BA24: 0.15 | BC24: 0.15 | BD24: 0.48 | BE24: 0.205 | BF24: 0.065 | BH24: -0.19 | BI24: -0.415 | BJ24: -0.365 | BK24: -0.295 | BM24: -0.095 | BN24: 0.065 | BO24: 0.21 | BP24: 0.17 | BR24: 0.115 | BS24: 0.025 | BU24: -0.03 | BW24: 0.015 | BX24: 0 | CN24: NAST_AGPps (NAST AGP per shipment y/y) | CO24: 0.02 | CP24: Δ → | CQ24: -0.03 | CR24: Contract repricing after the 2026 spot-cost spike (TL cost/mile +29% in Q2/26); company 2026 assumption flat to +4%.
B25: Memo: LTL AGP per order y/y % | AZ25: 0.105 | BA25: 0.235 | BC25: 0.27 | BD25: 0.37 | BE25: 0.245 | BF25: 0.08 | BH25: -0.045 | BI25: -0.19 | BJ25: -0.135 | BK25: -0.085 | BM25: -0.01 | BN25: 0.05 | BO25: 0.01 | BP25: 0.02 | BR25: 0.04 | BS25: 0.03 | BT25: 0.08 | BU25: 0.055 | BW25: 0.085 | BX25: 0.195 | CN25: 2027E | CO25: =CP25+$CO$24 -> 0.06 | CP25: 0.04 | CQ25: =CP25+$CQ$24 -> 0.01
B26: Memo: truckload linehaul price per mile y/y % (ex fuel; all segments) | J26: 0.015 | K26: 0.01 | L26: 0.02 | M26: 0.035 | O26: 0.1 | P26: 0.1 | Q26: 0.1 | R26: 0.12 | T26: 0.06 | U26: 0.03 | V26: 0 | W26: -0.03 | Y26: -0.05 | Z26: -0.075 | AA26: -0.055 | AB26: -0.035 | AD26: -0.04 | AE26: 0 | AF26: 0.065 | AG26: 0.15 | AI26: 0.21 | AJ26: 0.205 | AK26: 0.14 | AL26: 0.015 | AN26: -0.055 | AO26: -0.115 | AP26: -0.125 | AQ26: -0.11 | AS26: -0.085 | AT26: -0.055 | AU26: 0.105 | AV26: 0.29 | AX26: 0.33 | AY26: 0.42 | AZ26: 0.27 | BA26: 0.185 | BC26: 0.205 | BD26: 0.015 | BE26: -0.13 | BF26: -0.21 | BH26: -0.275 | BI26: -0.23 | BJ26: -0.165 | BK26: -0.135 | BM26: -0.075 | BN26: -0.02 | BO26: 0.025 | BP26: 0.06 | BR26: 0.04 | BS26: 0.035 | BT26: -0.015 | BU26: 0.025 | BW26: 0.11 | BX26: 0.255 | CN26: 2028E | CO26: =CP26+$CO$24 -> 0.05 | CP26: 0.03 | CQ26: =CP26+$CQ$24 -> 0
B27: Memo: truckload linehaul cost per mile y/y % (ex fuel; all segments) | J27: 0.025 | K27: 0.01 | L27: 0.04 | M27: 0.05 | O27: 0.12 | P27: 0.09 | Q27: 0.08 | R27: 0.11 | T27: 0.06 | U27: 0.025 | V27: -0.01 | W27: -0.05 | Y27: -0.07 | Z27: -0.08 | AA27: -0.035 | AB27: 0 | AD27: -0.02 | AE27: 0.04 | AF27: 0.085 | AG27: 0.145 | AI27: 0.215 | AJ27: 0.195 | AK27: 0.12 | AL27: -0.01 | AN27: -0.085 | AO27: -0.145 | AP27: -0.12 | AQ27: -0.075 | AS27: -0.025 | AT27: -0.02 | AU27: 0.165 | AV27: 0.325 | AX27: 0.335 | AY27: 0.475 | AZ27: 0.26 | BA27: 0.18 | BC27: 0.21 | BD27: -0.05 | BE27: -0.17 | BF27: -0.24 | BH27: -0.285 | BI27: -0.19 | BJ27: -0.135 | BK27: -0.105 | BM27: -0.075 | BN27: -0.035 | BO27: -0.005 | BP27: 0.04 | BR27: 0.03 | BS27: 0.035 | BT27: -0.015 | BU27: 0.025 | BW27: 0.13 | BX27: 0.29 | CN27: 2029E | CO27: =CP27+$CO$24 -> 0.04 | CP27: 0.02 | CQ27: =CP27+$CQ$24 -> -0.01
CN28: 2030E | CO28: =CP28+$CO$24 -> 0.04 | CP28: 0.02 | CQ28: =CP28+$CQ$24 -> -0.01
B29: Global Forwarding (GF) — ocean, air, customs & other; reportable segment from Q4/16 (recast to 2014) | CF29: GLOBAL FORWARDING — modelling logic | CN29: GF_vol (ocean shipments y/y) | CO29: 0.02 | CP29: Δ → | CQ29: -0.03 | CR29: Ocean +1.0% in Q2/26; trade-policy volatility.
B30: GF volume y/y % (ocean shipments) | U30: 0 | AN30: 0 | AR30: =IFERROR(AVERAGE(AN30,AO30,AP30,AQ30),"") -> 0 | AS30: -0.03 | AT30: -0.085 | AU30: 0.015 | AV30: 0.12 | AW30: =IFERROR(AVERAGE(AS30,AT30,AU30,AV30),"") -> 0.005 | AX30: 0.27 | AY30: 0.29 | AZ30: 0.12 | BA30: 0.05 | BB30: =IFERROR(AVERAGE(AX30,AY30,AZ30,BA30),"") -> 0.1825 | BC30: 0.07 | BD30: 0.025 | BE30: -0.025 | BF30: -0.095 | BG30: =IFERROR(AVERAGE(BC30,BD30,BE30,BF30),"") -> -0.00625 | BH30: -0.145 | BI30: -0.07 | BJ30: -0.005 | BK30: 0.04 | BL30: =IFERROR(AVERAGE(BH30,BI30,BJ30,BK30),"") -> -0.045 | BM30: 0.07 | BN30: 0.04 | BO30: 0.07 | BP30: 0.035 | BQ30: =IFERROR(AVERAGE(BM30,BN30,BO30,BP30),"") -> 0.05375 | BR30: 0.015 | BS30: -0.04 | BT30: -0.07 | BU30: -0.08 | BV30: =IFERROR(AVERAGE(BR30,BS30,BT30,BU30),"") -> -0.04375 | BW30: -0.105 | BX30: 0.01 | BY30: =$BX$30 -> 0.01 | BZ30: =$BX$30 -> 0.01 | CA30: =AVERAGE(BW30:BZ30) -> -0.01875 | CB30: =CHOOSE(MATCH($CF$2,{"Bull","Base","Bear"},0),$CO$30,$CP$30,$CQ$30) -> 0.02 | CC30: =CHOOSE(MATCH($CF$2,{"Bull","Base","Bear"},0),$CO$31,$CP$31,$CQ$31) -> 0.03 | CD30: =CHOOSE(MATCH($CF$2,{"Bull","Base","Bear"},0),$CO$32,$CP$32,$CQ$32) -> 0.03 | CE30: =CHOOSE(MATCH($CF$2,{"Bull","Base","Bear"},0),$CO$33,$CP$33,$CQ$33) -> 0.03 | CF30: Ocean shipment growth as the GF volume proxy (ocean ≈ 55–60% of GF AGP). Disclosed from 2019 (2015 flat). Q3/26E–Q4/26E: Q2/26 rate; 2027E+: scenario lever GF_vol. | CN30: 2027E | CO30: =CP30+$CO$29 -> 0.04 | CP30: 0.02 | CQ30: =CP30+$CQ$29 -> -0.01
B31: GF AGP per shipment y/y % (rate / mix) | AN31: =IFERROR((1+AN33)/(1+AN30)-1,"") -> 0.034127945 | AO31: =IFERROR((1+AO33)/(1+AO30)-1,"") -> -0.01454548 | AP31: =IFERROR((1+AP33)/(1+AP30)-1,"") -> 0.012781411 | AQ31: =IFERROR((1+AQ33)/(1+AQ30)-1,"") -> -0.096317003 | AR31: =IFERROR((1+AR33)/(1+AR30)-1,"") -> -0.018256831 | AS31: =IFERROR((1+AS33)/(1+AS30)-1,"") -> 0.039662314 | AT31: =IFERROR((1+AT33)/(1+AT30)-1,"") -> 0.25477934 | AU31: =IFERROR((1+AU33)/(1+AU30)-1,"") -> 0.14366671 | ... BX31: =IFERROR((1+BX33)/(1+BX30)-1,"") -> -0.0033084585 | BY31: =$BX$31+BY109 -> 0.01153016 | BZ31: =$BX$31+BY109 -> 0.01153016 | CA31: =IFERROR((1+CA33)/(1+CA30)-1,"") -> 0.001134058 | CB31: =CHOOSE(MATCH($CF$2,{"Bull","Base","Bear"},0),$CO$35,$CP$35,$CQ$35) -> 0 | CC31: =CHOOSE(MATCH($CF$2,{"Bull","Base","Bear"},0),$CO$36,$CP$36,$CQ$36) -> 0.01 | CD31: =CHOOSE(MATCH($CF$2,{"Bull","Base","Bear"},0),$CO$37,$CP$37,$CQ$37) -> 0.015 | CE31: =CHOOSE(MATCH($CF$2,{"Bull","Base","Bear"},0),$CO$38,$CP$38,$CQ$38) -> 0.015 | CF31: Implied = (1 + AGP growth) / (1 + volume) − 1 (captures ocean/air rate cycles: 2021–22 spike, 2023 reset, 2024 Red Sea). 2027E+: scenario lever GF_AGPps. | CN31: 2028E | CO31: =CP31+$CO$29 -> 0.05 | CP31: 0.03 | CQ31: =CP31+$CQ$29 -> 0
B32: Adjusted gross profit (AGP) | S32: 350.193 | T32: 86.333 | U32: 94.846 | V32: 94.797 | W32: 89.491 | X32: 365.467 | Y32: 92.866 | Z32: 97.224 | AA32: 93.368 | AB32: 114.079 | AC32: 397.537 | AD32: 106.546 | AE32: 121.023 | AF32: 129.842 | AG32: 127.869 | AH32: 485.28 | AI32: 123.037 | AJ32: 144.031 | AK32: 134.101 | AL32: 142.737 | AM32: 543.906 | AN32: 127.236 | AO32: 141.936 | AP32: 135.815 | AQ32: 128.989 | AR32: 533.976 | AS32: 128.314 | AT32: 162.96 | AU32: 157.657 | AV32: 180.057 | AW32: 628.988 | AX32: 214.3 | AY32: 238.754 | AZ32: 310.898 | BA32: 309.589 | BB32: 1073.541 | BC32: 321.848 | BD32: 324.443 | BE32: 248.433 | BF32: 188.749 | BG32: 1083.473 | BH32: 177.919 | BI32: 179.231 | BJ32: 169.893 | BK32: 162.322 | BL32: 689.365 | BM32: 180.045 | BN32: 184.067 | BO32: 234.636 | BP32: 203.801 | BQ32: 802.549 | BR32: 184.628 | BS32: 187.581 | BT32: 191.755 | BU32: 177.957 | BV32: 741.921 | BW32: 162.291 | BX32: 188.83 | BY32: =BT32*(1+BY30)*(1+BY31) -> 195.90563 | BZ32: =BU32*(1+BZ30)*(1+BZ31) -> 181.80896 | CA32: =SUM(BW32,BX32,BY32,BZ32) -> 728.83559 | CB32: =CA32*(1+CB30)*(1+CB31) -> 743.4123 | CC32: =CB32*(1+CC30)*(1+CC31) -> 773.37181 | CD32: =CC32*(1+CD30)*(1+CD31) -> 808.52156 | CE32: =CD32*(1+CE30)*(1+CE31) -> 845.26887 | CH32: =IFERROR((CE32/BV32)^(1/5)-1,"n/m") -> 0.026425522 | CI32: =IFERROR((BV32/AW32)^(1/5)-1,"n/m") -> 0.033577534 | CJ32: =IFERROR((BV32/X32)^(1/10)-1,"n/m") -> 0.073373699 | CK32: =IFERROR((BV32/C32)^(1/19)-1,"n/m") -> n/m | CN32: 2029E | CO32: =CP32+$CO$29 -> 0.05 | CP32: 0.03 | CQ32: =CP32+$CQ$29 -> 0
B33: AGP y/y % | D33: =IF(AND(ISNUMBER(D32),ISNUMBER(C32)),IFERROR(D32/C32-1,""),"") | E33: =IF(AND(ISNUMBER(E32),ISNUMBER(D32)),IFERROR(E32/D32-1,""),"") | F33: =IF(AND(ISNUMBER(F32),ISNUMBER(E32)),IFERROR(F32/E32-1,""),"") | G33: =IF(AND(ISNUMBER(G32),ISNUMBER(F32)),IFERROR(G32/F32-1,""),"") | H33: =IF(AND(ISNUMBER(H32),ISNUMBER(G32)),IFERROR(H32/G32-1,""),"") | I33: =IF(AND(ISNUMBER(I32),ISNUMBER(H32)),IFERROR(I32/H32-1,""),"") | N33: =IF(AND(ISNUMBER(N32),ISNUMBER(I32)),IFERROR(N32/I32-1,""),"") | O33: =IF(AND(ISNUMBER(O32),ISNUMBER(J32)),IFERROR(O32/J32-1,""),"") | P33: =IF(AND(ISNUMBER(P32),ISNUMBER(K32)),IFERROR(P32/K32-1,""),"") | Q33: =IF(AND(ISNUMBER(Q32),ISNUMBER(L32)),IFERROR(Q32/L32-1,""),"") | R33: =IF(AND(ISNUMBER(R32),ISNUMBER(M32)),IFERROR(R32/M32-1,""),"") | S33: =IF(AND(ISNUMBER(S32),ISNUMBER(N32)),IFERROR(S32/N32-1,""),"") | T33: =IF(AND(ISNUMBER(T32),ISNUMBER(O32)),IFERROR(T32/O32-1,""),"") | U33: =IF(AND(ISNUMBER(U32),ISNUMBER(P32)),IFERROR(U32/P32-1,""),"") | ... BX33: =IF(AND(ISNUMBER(BX32),ISNUMBER(BS32)),IFERROR(BX32/BS32-1,""),"") -> 0.0066584569 | BY33: =IFERROR(BY32/BT32-1,"") -> 0.021645461 | BZ33: =IFERROR(BZ32/BU32-1,"") -> 0.021645461 | CA33: =IFERROR(CA32/BV32-1,"") -> -0.017637206 | CB33: =IFERROR(CB32/CA32-1,"") -> 0.02 | CC33: =IFERROR(CC32/CB32-1,"") -> 0.0403 | CD33: =IFERROR(CD32/CC32-1,"") -> 0.04545 | CE33: =IFERROR(CE32/CD32-1,"") -> 0.04545 | CN33: 2030E | CO33: =CP33+$CO$29 -> 0.05 | CP33: 0.03 | CQ33: =CP33+$CQ$29 -> 0
B34: AGP margin % of segment revenues | C34: =IF(AND(ISNUMBER(C32),ISNUMBER(C35)),IFERROR(C32/C35,""),"") | D34: =IF(AND(ISNUMBER(D32),ISNUMBER(D35)),IFERROR(D32/D35,""),"") | E34: =IF(AND(ISNUMBER(E32),ISNUMBER(E35)),IFERROR(E32/E35,""),"") | F34: =IF(AND(ISNUMBER(F32),ISNUMBER(F35)),IFERROR(F32/F35,""),"") | G34: =IF(AND(ISNUMBER(G32),ISNUMBER(G35)),IFERROR(G32/G35,""),"") | H34: =IF(AND(ISNUMBER(H32),ISNUMBER(H35)),IFERROR(H32/H35,""),"") | I34: =IF(AND(ISNUMBER(I32),ISNUMBER(I35)),IFERROR(I32/I35,""),"") | J34: =IF(AND(ISNUMBER(J32),ISNUMBER(J35)),IFERROR(J32/J35,""),"") | ... BX34: =IF(AND(ISNUMBER(BX32),ISNUMBER(BX35)),IFERROR(BX32/BX35,""),"") -> 0.2106058 | BY34: =$BX$34 -> 0.2106058 | BZ34: =$BX$34 -> 0.2106058 | CA34: =IF(AND(ISNUMBER(CA32),ISNUMBER(CA35)),IFERROR(CA32/CA35,""),"") -> 0.2172515 | CB34: 0.22 | CC34: 0.225 | CD34: 0.225 | CE34: 0.225 | CF34: Q2/26 21.1% (air rates up); 2023–25 range 22–24%. | CN34: GF_AGPps (GF AGP per shipment y/y) | CO34: 0.03 | CP34: Δ → | CQ34: -0.04 | CR34: Company 2026 assumption: GF AGP/shipment reset to 2H/23 levels (−10%); air rates elevated in 2026.
B35: Total revenues (external) | S35: 1708.789 | T35: 411.451 | U35: 431.098 | V35: 420.628 | W35: 376.767 | X35: 1639.944 | Y35: 351.112 | Z35: 356.773 | AA35: 390.83 | AB35: 475.971 | AC35: 1574.686 | AD35: 468.788 | AE35: 528.82 | AF35: 552.134 | AG35: 591.245 | AH35: 2140.987 | AI35: 553.754 | AJ35: 617.597 | AK35: 639.268 | AL35: 677.125 | AM35: 2487.744 | AN35: 537.567 | AO35: 592.483 | AP35: 597.695 | AQ35: 600.168 | AR35: 2327.913 | AS35: 530.384 | AT35: 707.82 | AU35: 831.957 | AV35: 1030.364 | AW35: 3100.525 | AX35: 1156.039 | AY35: 1450.794 | AZ35: 1978.901 | BA35: 2144.056 | BB35: 6729.79 | BC35: 2194.397 | BD35: 2093.19 | BE35: 1511.115 | BF35: 1013.306 | BG35: 6812.008 | BH35: 789.978 | BI35: 779.867 | BJ35: 719.045 | BK35: 708.814 | BL35: 2997.704 | BM35: 858.637 | BN35: 921.223 | BO35: 1141.19 | BP35: 883.968 | BQ35: 3805.018 | BR35: 774.888 | BS35: 797.8 | BT35: 786.347 | BU35: 730.983 | BV35: 3090.018 | BW35: 664.73 | BX35: 896.604 | BY35: =IF(AND(ISNUMBER(BY32),ISNUMBER(BY34)),IFERROR(BY32/BY34,""),"") -> 930.20054 | BZ35: =IF(AND(ISNUMBER(BZ32),ISNUMBER(BZ34)),IFERROR(BZ32/BZ34,""),"") -> 863.26665 | CA35: =SUM(BW35,BX35,BY35,BZ35) -> 3354.8012 | CB35: =IF(AND(ISNUMBER(CB32),ISNUMBER(CB34)),IFERROR(CB32/CB34,""),"") -> 3379.1468 | CC35: =IF(AND(ISNUMBER(CC32),ISNUMBER(CC34)),IFERROR(CC32/CC34,""),"") -> 3437.2081 | CD35: =IF(AND(ISNUMBER(CD32),ISNUMBER(CD34)),IFERROR(CD32/CD34,""),"") -> 3593.4292 | CE35: =IF(AND(ISNUMBER(CE32),ISNUMBER(CE34)),IFERROR(CE32/CE34,""),"") -> 3756.7505 | CH35: =IFERROR((CE35/BV35)^(1/5)-1,"n/m") -> 0.039848978 | CI35: =IFERROR((BV35/AW35)^(1/5)-1,"n/m") -> -0.00067867677 | CJ35: =IFERROR((BV35/X35)^(1/10)-1,"n/m") -> 0.065401243 | CK35: =IFERROR((BV35/C35)^(1/19)-1,"n/m") -> n/m | CN35: 2027E | CO35: =CP35+$CO$34 -> 0.03 | CP35: 0 | CQ35: =CP35+$CQ$34 -> -0.04
B36: Revenues y/y % | D36: =IF(AND(ISNUMBER(D35),ISNUMBER(C35)),IFERROR(D35/C35-1,""),"") | E36: =IF(AND(ISNUMBER(E35),ISNUMBER(D35)),IFERROR(E35/D35-1,""),"") | F36: =IF(AND(ISNUMBER(F35),ISNUMBER(E35)),IFERROR(F35/E35-1,""),"") | G36: =IF(AND(ISNUMBER(G35),ISNUMBER(F35)),IFERROR(G35/F35-1,""),"") | H36: =IF(AND(ISNUMBER(H35),ISNUMBER(G35)),IFERROR(H35/G35-1,""),"") | I36: =IF(AND(ISNUMBER(I35),ISNUMBER(H35)),IFERROR(I35/H35-1,""),"") | N36: =IF(AND(ISNUMBER(N35),ISNUMBER(I35)),IFERROR(N35/I35-1,""),"") | O36: =IF(AND(ISNUMBER(O35),ISNUMBER(J35)),IFERROR(O35/J35-1,""),"") | P36: =IF(AND(ISNUMBER(P35),ISNUMBER(K35)),IFERROR(P35/K35-1,""),"") | Q36: =IF(AND(ISNUMBER(Q35),ISNUMBER(L35)),IFERROR(Q35/L35-1,""),"") | R36: =IF(AND(ISNUMBER(R35),ISNUMBER(M35)),IFERROR(R35/M35-1,""),"") | S36: =IF(AND(ISNUMBER(S35),ISNUMBER(N35)),IFERROR(S35/N35-1,""),"") | T36: =IF(AND(ISNUMBER(T35),ISNUMBER(O35)),IFERROR(T35/O35-1,""),"") | U36: =IF(AND(ISNUMBER(U35),ISNUMBER(P35)),IFERROR(U35/P35-1,""),"") | ... BX36: =IF(AND(ISNUMBER(BX35),ISNUMBER(BS35)),IFERROR(BX35/BS35-1,""),"") -> 0.12384558 | BY36: =IFERROR(BY35/BT35-1,"") -> 0.182939 | BZ36: =IFERROR(BZ35/BU35-1,"") -> 0.1809668 | CA36: =IFERROR(CA35/BV35-1,"") -> 0.085689853 | CB36: =IFERROR(CB35/CA35-1,"") -> 0.0072569493 | CC36: =IFERROR(CC35/CB35-1,"") -> 0.017182222 | CD36: =IFERROR(CD35/CC35-1,"") -> 0.04545 | CE36: =IFERROR(CE35/CD35-1,"") -> 0.04545 | CN36: 2028E | CO36: =CP36+$CO$34 -> 0.04 | CP36: 0.01 | CQ36: =CP36+$CQ$34 -> -0.03
B37: Income from operations (segment, as reported) | S37: 55.591 | T37: 13.973 | U37: 20.904 | V37: 22.477 | W37: 18.727 | X37: 76.081 | Y37: 16.857 | Z37: 22.396 | AA37: 17.047 | AB37: 24.631 | AC37: 80.931 | AD37: 16.206 | AE37: 27.675 | AF37: 31.125 | AG37: 16.836 | AH37: 91.842 | AI37: 8.221 | AJ37: 29.788 | AK37: 23.835 | AL37: 29.782 | AM37: 91.626 | AN37: 14.203 | AO37: 26.618 | AP37: 24.676 | AQ37: 15.03 | AR37: 80.527 | AS37: 11.959 | AT37: 58.775 | AU37: 46.299 | AV37: 58.48 | AW37: 175.513 | AX37: 90.589 | AY37: 108.212 | AZ37: 165.155 | BA37: 146.8 | BB37: 510.756 | BC37: 167.638 | BD37: 167.557 | BE37: 85.953 | BF37: 28.216 | BG37: 449.364 | BH37: 30.116 | BI37: 29.647 | BJ37: 3.491 | BK37: 22.576 | BL37: 85.83 | BM37: 31.552 | BN37: 40.982 | BO37: 88.115 | BP37: 51.827 | BQ37: 212.476 | BR37: 42.943 | BS37: 51.33 | BT37: 49.021 | BU37: 40.489 | BV37: 183.783 | BW37: 31.684 | BX37: 60.97 | CN37: 2029E | CO37: =CP37+$CO$34 -> 0.045 | CP37: 0.015 | CQ37: =CP37+$CQ$34 -> -0.025
B38: Operating margin % of AGP (segment, GAAP; mid-cycle target 30%) | C38: =IF(AND(ISNUMBER(C37),ISNUMBER(C32)),IFERROR(C37/C32,""),"") | D38: =IF(AND(ISNUMBER(D37),ISNUMBER(D32)),IFERROR(D37/D32,""),"") | E38: =IF(AND(ISNUMBER(E37),ISNUMBER(E32)),IFERROR(E37/E32,""),"") | F38: =IF(AND(ISNUMBER(F37),ISNUMBER(F32)),IFERROR(F37/F32,""),"") | G38: =IF(AND(ISNUMBER(G37),ISNUMBER(G32)),IFERROR(G37/G32,""),"") | H38: =IF(AND(ISNUMBER(H37),ISNUMBER(H32)),IFERROR(H37/H32,""),"") | I38: =IF(AND(ISNUMBER(I37),ISNUMBER(I32)),IFERROR(I37/I32,""),"") | J38: =IF(AND(ISNUMBER(J37),ISNUMBER(J32)),IFERROR(J37/J32,""),"") | ... BX38: =IF(AND(ISNUMBER(BX37),ISNUMBER(BX32)),IFERROR(BX37/BX32,""),"") -> 0.32288302 | CN38: 2030E | CO38: =CP38+$CO$34 -> 0.045 | CP38: 0.015 | CQ38: =CP38+$CQ$34 -> -0.025
B39: Average employee headcount | S39: 3202 | T39: 3294 | U39: 3350 | V39: 3422 | W39: 3455 | X39: 3381 | Y39: 3488 | Z39: 3514 | AA39: 3559 | AB39: 3934 | AC39: 3673 | AD39: 3926 | AE39: 4021 | AF39: 4301 | AG39: 4683 | AH39: 4310 | AI39: 4767 | AJ39: 4736 | AK39: 4684 | AL39: 4664 | AM39: 4711 | AN39: 4707 | AO39: 4770 | AP39: 4790 | AQ39: 4824 | AR39: 4766 | AS39: 4824 | AT39: 4726 | AU39: 4607 | AV39: 4626 | AW39: 4708 | AX39: 4735 | AY39: 4909 | AZ39: 5167 | BA39: 5430 | BB39: 5071 | BC39: 5610 | BD39: 5759 | BE39: 5861 | BF39: 5745 | BG39: 5712 | BH39: 5471 | BI39: 5225 | BJ39: 5082 | BK39: 5021 | BL39: 5222 | BM39: 4876 | BN39: 4652 | BO39: 4552 | BP39: 4542 | BQ39: 4678 | BR39: 4514 | BS39: 4436 | BT39: 4245 | BU39: 4007 | BV39: 4284 | BW39: 3848 | BX39: 3699 | CN39: AO_growth (All Other & Corporate AGP y/y) | CO39: 0.02 | CP39: Δ → | CQ39: -0.03 | CR39: Robinson Fresh foodservice wins; Managed Solutions freight under management ($2.1bn in Q2/26).
B40: AGP per average employee ($000, annualised) | C40: =IFERROR(C32*1/C39*1000,"") | D40: =IFERROR(D32*1/D39*1000,"") | E40: =IFERROR(E32*1/E39*1000,"") | F40: =IFERROR(F32*1/F39*1000,"") | G40: =IFERROR(G32*1/G39*1000,"") | H40: =IFERROR(H32*1/H39*1000,"") | I40: =IFERROR(I32*1/I39*1000,"") | J40: =IFERROR(J32*4/J39*1000,"") | K40: =IFERROR(K32*4/K39*1000,"") | L40: =IFERROR(L32*4/L39*1000,"") | M40: =IFERROR(M32*4/M39*1000,"") | N40: =IFERROR(N32*1/N39*1000,"") | O40: =IFERROR(O32*4/O39*1000,"") | P40: =IFERROR(P32*4/P39*1000,"") | Q40: =IFERROR(Q32*4/Q39*1000,"") | R40: =IFERROR(R32*4/R39*1000,"") | S40: =IFERROR(S32*1/S39*1000,"") -> 109.36696 | T40: =IFERROR(T32*4/T39*1000,"") -> 104.83667 | U40: =IFERROR(U32*4/U39*1000,"") -> 113.24896 | V40: =IFERROR(V32*4/V39*1000,"") -> 110.80888 | W40: =IFERROR(W32*4/W39*1000,"") -> 103.60753 | X40: =IFERROR(X32*1/X39*1000,"") -> 108.09435 | Y40: =IFERROR(Y32*4/Y39*1000,"") -> 106.49771 | Z40: =IFERROR(Z32*4/Z39*1000,"") -> 110.67046 | AA40: =IFERROR(AA32*4/AA39*1000,"") -> 104.93734 | AB40: =IFERROR(AB32*4/AB39*1000,"") -> 115.99288 | AC40: =IFERROR(AC32*1/AC39*1000,"") -> 108.23224 | AD40: =IFERROR(AD32*4/AD39*1000,"") -> 108.55425 | AE40: =IFERROR(AE32*4/AE39*1000,"") -> 120.39095 | AF40: =IFERROR(AF32*4/AF39*1000,"") -> 120.75517 | AG40: =IFERROR(AG32*4/AG39*1000,"") -> 109.21973 | AH40: =IFERROR(AH32*1/AH39*1000,"") -> 112.59397 | AI40: =IFERROR(AI32*4/AI39*1000,"") -> 103.24061 | AJ40: =IFERROR(AJ32*4/AJ39*1000,"") -> 121.6478 | AK40: =IFERROR(AK32*4/AK39*1000,"") -> 114.51836 | AL40: =IFERROR(AL32*4/AL39*1000,"") -> 122.41595 | AM40: =IFERROR(AM32*1/AM39*1000,"") -> 115.45447 | AN40: =IFERROR(AN32*4/AN39*1000,"") -> 108.12492 | AO40: =IFERROR(AO32*4/AO39*1000,"") -> 119.0239 | AP40: =IFERROR(AP32*4/AP39*1000,"") -> 113.41545 | AQ40: =IFERROR(AQ32*4/AQ39*1000,"") -> 106.95605 | AR40: =IFERROR(AR32*1/AR39*1000,"") -> 112.03861 | AS40: =IFERROR(AS32*4/AS39*1000,"") -> 106.39635 | AT40: =IFERROR(AT32*4/AT39*1000,"") -> 137.92636 | AU40: =IFERROR(AU32*4/AU39*1000,"") -> 136.88474 | AV40: =IFERROR(AV32*4/AV39*1000,"") -> 155.69131 | AW40: =IFERROR(AW32*1/AW39*1000,"") -> 133.59983 | AX40: =IFERROR(AX32*4/AX39*1000,"") -> 181.03485 | AY40: =IFERROR(AY32*4/AY39*1000,"") -> 194.5439 | AZ40: =IFERROR(AZ32*4/AZ39*1000,"") -> 240.6797 | BA40: =IFERROR(BA32*4/BA39*1000,"") -> 228.0582 | BB40: =IFERROR(BB32*1/BB39*1000,"") -> 211.70203 | BC40: =IFERROR(BC32*4/BC39*1000,"") -> 229.48164 | BD40: =IFERROR(BD32*4/BD39*1000,"") -> 225.34676 | BE40: =IFERROR(BE32*4/BE39*1000,"") -> 169.54991 | BF40: =IFERROR(BF32*4/BF39*1000,"") -> 131.41793 | BG40: =IFERROR(BG32*1/BG39*1000,"") -> 189.68365 | BH40: =IFERROR(BH32*4/BH39*1000,"") -> 130.08152 | BI40: =IFERROR(BI32*4/BI39*1000,"") -> 137.21033 | BJ40: =IFERROR(BJ32*4/BJ39*1000,"") -> 133.72137 | BK40: =IFERROR(BK32*4/BK39*1000,"") -> 129.31448 | BL40: =IFERROR(BL32*1/BL39*1000,"") -> 132.01168 | BM40: =IFERROR(BM32*4/BM39*1000,"") -> 147.69893 | BN40: =IFERROR(BN32*4/BN39*1000,"") -> 158.26913 | BO40: =IFERROR(BO32*4/BO39*1000,"") -> 206.18278 | BP40: =IFERROR(BP32*4/BP39*1000,"") -> 179.48129 | BQ40: =IFERROR(BQ32*1/BQ39*1000,"") -> 171.55814 | BR40: =IFERROR(BR32*4/BR39*1000,"") -> 163.60479 | BS40: =IFERROR(BS32*4/BS39*1000,"") -> 169.14427 | BT40: =IFERROR(BT32*4/BT39*1000,"") -> 180.68787 | BU40: =IFERROR(BU32*4/BU39*1000,"") -> 177.64612 | BV40: =IFERROR(BV32*1/BV39*1000,"") -> 173.18417 | BW40: =IFERROR(BW32*4/BW39*1000,"") -> 168.70166 | BX40: =IFERROR(BX32*4/BX39*1000,"") -> 204.19573 | CN40: 2027E | CO40: =CP40+$CO$39 -> 0.07 | CP40: 0.05 | CQ40: =CP40+$CQ$39 -> 0.02
B41: Memo: ocean AGP per shipment y/y % | AZ41: 1.165 | BA41: 0.78 | BC41: 0.525 | BD41: 0.475 | BE41: -0.24 | BF41: -0.365 | BH41: -0.415 | BI41: -0.495 | BJ41: -0.345 | BK41: -0.205 | BM41: -0.04 | BN41: 0.045 | BO41: 0.47 | BP41: 0.235 | BR41: 0.01 | BS41: -0.035 | BT41: -0.275 | BU41: -0.15 | BW41: -0.125 | BX41: -0.04 | CN41: 2028E | CO41: =CP41+$CO$39 -> 0.07 | CP41: 0.05 | CQ41: =CP41+$CQ$39 -> 0.02
B42: Memo: air metric tons shipped y/y % (shipments in 2020) | AY42: 0.425 | AZ42: 0.505 | BA42: 0.375 | BC42: 0.1 | BD42: -0.06 | BE42: -0.165 | BF42: -0.195 | BH42: -0.185 | BI42: -0.02 | BJ42: -0.02 | BK42: -0.025 | BM42: 0.23 | BN42: 0.11 | BO42: 0.2 | BP42: 0.155 | BR42: -0.03 | BS42: -0.125 | BT42: -0.1 | BU42: -0.125 | BW42: -0.15 | BX42: -0.075 | CN42: 2029E | CO42: =CP42+$CO$39 -> 0.065 | CP42: 0.045 | CQ42: =CP42+$CQ$39 -> 0.015
B43: Memo: air AGP per metric ton y/y % | AZ43: 0.17 | BA43: 0.395 | BC43: 0.215 | BD43: 0.14 | BE43: -0.055 | BF43: -0.4 | BH43: -0.375 | BI43: -0.395 | BJ43: -0.355 | BK43: -0.09 | BM43: -0.205 | BN43: -0.18 | BO43: -0.07 | BP43: 0.26 | BR43: 0.11 | BS43: 0.275 | BT43: 0.17 | BU43: -0.055 | BW43: 0.165 | BX43: 0.335 | CN43: 2030E | CO43: =CP43+$CO$39 -> 0.065 | CP43: 0.045 | CQ43: =CP43+$CQ$39 -> 0.015
B44: Memo: customs transaction volume y/y % | AS44: -0.025 | AT44: -0.17 | AU44: -0.025 | AV44: 0.08 | AX44: 0.135 | AY44: 0.34 | AZ44: 0.105 | BA44: 0.005 | BC44: 0.05 | BD44: 0.105 | BE44: 0.04 | BF44: -0.055 | BH44: -0.14 | BI44: -0.145 | BJ44: -0.08 | BK44: 0.045 | BM44: 0.085 | BN44: 0.06 | BO44: 0.065 | BP44: -0.025 | BR44: 0.015 | BS44: 0.005 | BT44: -0.015 | BU44: 0.03 | BW44: -0.02 | BX44: -0.02 | CN44: PROD (volume per employee y/y — Lean AI) | CO44: 0.02 | CP44: Δ → | CQ44: -0.03 | CR44: >60% productivity gain since end-2022; NAST & GF +15% y/y in Q2/26. Fades as automation matures.
B45: Memo: customs AGP per transaction y/y % | BE45: 0.055 | BK45: -0.075 | BM45: 0.035 | BO45: 0.07 | BP45: 0.145 | BR45: 0.015 | BS45: 0.31 | BT45: 0.305 | BU45: 0.26 | BW45: 0.22 | BX45: -0.075 | CN45: 2027E | CO45: =CP45+$CO$44 -> 0.07 | CP45: 0.05 | CQ45: =CP45+$CQ$44 -> 0.02
CN46: 2028E | CO46: =CP46+$CO$44 -> 0.06 | CP46: 0.04 | CQ46: =CP46+$CQ$44 -> 0.01
B47: All Other & Corporate — Robinson Fresh (sourcing), Managed Solutions, Other Surface Transportation (Europe Surface divested 1-Feb-25); current basis | CF47: ALL OTHER & CORPORATE — modelling logic | CN47: 2029E | CO47: =CP47+$CO$44 -> 0.05 | CP47: 0.03 | CQ47: =CP47+$CQ$44 -> 0
B48: AGP y/y % (growth driver) | D48: =IF(AND(ISNUMBER(D49),ISNUMBER(C49)),IFERROR(D49/C49-1,""),"") | E48: =IF(AND(ISNUMBER(E49),ISNUMBER(D49)),IFERROR(E49/D49-1,""),"") | F48: =IF(AND(ISNUMBER(F49),ISNUMBER(E49)),IFERROR(F49/E49-1,""),"") | G48: =IF(AND(ISNUMBER(G49),ISNUMBER(F49)),IFERROR(G49/F49-1,""),"") | H48: =IF(AND(ISNUMBER(H49),ISNUMBER(G49)),IFERROR(H49/G49-1,""),"") | I48: =IF(AND(ISNUMBER(I49),ISNUMBER(H49)),IFERROR(I49/H49-1,""),"") | N48: =IF(AND(ISNUMBER(N49),ISNUMBER(I49)),IFERROR(N49/I49-1,""),"") | O48: =IF(AND(ISNUMBER(O49),ISNUMBER(J49)),IFERROR(O49/J49-1,""),"") | P48: =IF(AND(ISNUMBER(P49),ISNUMBER(K49)),IFERROR(P49/K49-1,""),"") | Q48: =IF(AND(ISNUMBER(Q49),ISNUMBER(L49)),IFERROR(Q49/L49-1,""),"") | R48: =IF(AND(ISNUMBER(R49),ISNUMBER(M49)),IFERROR(R49/M49-1,""),"") | S48: =IF(AND(ISNUMBER(S49),ISNUMBER(N49)),IFERROR(S49/N49-1,""),"") | T48: =IF(AND(ISNUMBER(T49),ISNUMBER(O49)),IFERROR(T49/O49-1,""),"") | U48: =IF(AND(ISNUMBER(U49),ISNUMBER(P49)),IFERROR(U49/P49-1,""),"") | ... BX48: =IF(AND(ISNUMBER(BX49),ISNUMBER(BS49)),IFERROR(BX49/BS49-1,""),"") -> 0.086441786 | BY48: =$BX$48+BY109 -> 0.1012804 | BZ48: =$BX$48+BY109 -> 0.1012804 | CA48: =IFERROR(CA49/BV49-1,"") -> 0.061432678 | CB48: =CHOOSE(MATCH($CF$2,{"Bull","Base","Bear"},0),$CO$40,$CP$40,$CQ$40) -> 0.05 | CC48: =CHOOSE(MATCH($CF$2,{"Bull","Base","Bear"},0),$CO$41,$CP$41,$CQ$41) -> 0.05 | CD48: =CHOOSE(MATCH($CF$2,{"Bull","Base","Bear"},0),$CO$42,$CP$42,$CQ$42) -> 0.045 | CE48: =CHOOSE(MATCH($CF$2,{"Bull","Base","Bear"},0),$CO$43,$CP$43,$CQ$43) -> 0.045 | CF48: Q3/26E–Q4/26E: Q2/26 y/y + outlook calibration Δ. 2027E+: scenario lever AO_growth (Robinson Fresh foodservice volume, Managed Solutions freight under management). | CN48: 2030E | CO48: =CP48+$CO$44 -> 0.05 | CP48: 0.03 | CQ48: =CP48+$CQ$44 -> 0
B49: Adjusted gross profit (AGP) | S49: =N(S58)+N(S62) -> 306.124 | T49: =N(T58)+N(T62) -> 80.768 | U49: =N(U58)+N(U62) -> 91.021 | V49: =N(V58)+N(V62) -> 83.3 | W49: =N(W58)+N(W62) -> 83.007 | X49: =N(X58)+N(X62) -> 338.096 | Y49: =N(Y58)+N(Y62) -> 86.671 | Z49: =N(Z58)+N(Z62) -> 97.788 | ... AM49: =N(AM58)+N(AM62) -> 372.831 | AN49: 65.014 | AO49: 66.862 | AP49: 63.856 | AQ49: 59.233 | AR49: 254.965 | AS49: 66.861 | AT49: 71.937 | AU49: 63.673 | AV49: 63.707 | AW49: 266.178 | AX49: 66.972 | AY49: 73.826 | AZ49: 73.145 | BA49: 71.652 | BB49: 285.595 | BC49: 78.248 | BD49: 82.619 | BE49: 74.974 | BF49: 77.159 | BG49: 313 | BH49: 81.066 | BI49: 85.733 | BJ49: 78.446 | BK49: 76.144 | BL49: 321.389 | BM49: 80.574 | BN49: 83.685 | BO49: 79.953 | BP49: 77.058 | BQ49: 321.27 | BR49: 70.136 | BS49: 73.402 | BT49: 70.183 | BU49: 67.439 | BV49: 281.16 | BW49: 67.125 | BX49: 79.747 | BY49: =BT49*(1+BY48) -> 77.291163 | BZ49: =BU49*(1+BZ48) -> 74.269249 | CA49: =SUM(BW49,BX49,BY49,BZ49) -> 298.43241 | CB49: =CA49*(1+CB48) -> 313.35403 | CC49: =CB49*(1+CC48) -> 329.02173 | CD49: =CC49*(1+CD48) -> 343.82771 | CE49: =CD49*(1+CE48) -> 359.29996 | CF49: Current basis (2019 resegmentation): 2014–2018 = Robinson Fresh segment + legacy All Other & Corporate (memo rows below). | CH49: =IFERROR((CE49/BV49)^(1/5)-1,"n/m") -> 0.050269435 | CI49: =IFERROR((BV49/AW49)^(1/5)-1,"n/m") -> 0.011011919 | CJ49: =IFERROR((BV49/X49)^(1/10)-1,"n/m") -> -0.01827161 | CK49: =IFERROR((BV49/C49)^(1/19)-1,"n/m") -> n/m | CN49: OSGA (other SG&A % of AGP) | CO49: -0.01 | CP49: Δ → | CQ49: 0.01 | CR49: FY25 20.7%; 1H/26 19.7%.
B50: AGP margin % of revenues | C50: =IF(AND(ISNUMBER(C49),ISNUMBER(C51)),IFERROR(C49/C51,""),"") | D50: =IF(AND(ISNUMBER(D49),ISNUMBER(D51)),IFERROR(D49/D51,""),"") | E50: =IF(AND(ISNUMBER(E49),ISNUMBER(E51)),IFERROR(E49/E51,""),"") | F50: =IF(AND(ISNUMBER(F49),ISNUMBER(F51)),IFERROR(F49/F51,""),"") | G50: =IF(AND(ISNUMBER(G49),ISNUMBER(G51)),IFERROR(G49/G51,""),"") | H50: =IF(AND(ISNUMBER(H49),ISNUMBER(H51)),IFERROR(H49/H51,""),"") | I50: =IF(AND(ISNUMBER(I49),ISNUMBER(I51)),IFERROR(I49/I51,""),"") | J50: =IF(AND(ISNUMBER(J49),ISNUMBER(J51)),IFERROR(J49/J51,""),"") | ... BX50: =IF(AND(ISNUMBER(BX49),ISNUMBER(BX51)),IFERROR(BX49/BX51,""),"") -> 0.17951939 | BY50: =$BX$50 -> 0.17951939 | BZ50: =$BX$50 -> 0.17951939 | CA50: =IF(AND(ISNUMBER(CA49),ISNUMBER(CA51)),IFERROR(CA49/CA51,""),"") -> 0.17665386 | CB50: 0.18 | CC50: 0.18 | CD50: 0.18 | CE50: 0.18 | CN50: 2027E | CO50: =CP50+$CO$49 -> 0.18 | CP50: 0.19 | CQ50: =CP50+$CQ$49 -> 0.2
B51: Total revenues (external) | S51: =N(S57)+N(S61) -> 3022.531 | T51: =N(T57)+N(T61) -> 694.688 | U51: =N(U57)+N(U61) -> 794.054 | V51: =N(V57)+N(V61) -> 716.39 | W51: =N(W57)+N(W61) -> 662.659 | X51: =N(X57)+N(X61) -> 2867.791 | Y51: =N(Y57)+N(Y61) -> 677.352 | Z51: =N(Z57)+N(Z61) -> 784.353 | ... AM51: =N(AM57)+N(AM61) -> 2895.528 | AN51: 416.859 | AO51: 444.304 | AP51: 432.129 | AQ51: 404.611 | AR51: 1697.903 | AS51: 450.879 | AT51: 444.734 | AU51: 469.001 | AV51: 429.414 | AW51: 1794.028 | AX51: 436.407 | AY51: 496.451 | AZ51: 469.806 | BA51: 461.767 | BB51: 1864.431 | BC51: 506.667 | BD51: 558.239 | BE51: 501.8 | BF51: 490.444 | BG51: 2057.15 | BH51: 517.505 | BI51: 562.721 | BJ51: 535.015 | BK51: 512.423 | BL51: 2127.664 | BM51: 553.361 | BN51: 572.216 | BO51: 568.834 | BP51: 497.988 | BQ51: 2192.399 | BR51: 403.432 | BS51: 420.516 | BT51: 384.805 | BU51: 371.278 | BV51: 1580.031 | BW51: 400.881 | BX51: 444.225 | BY51: =IF(AND(ISNUMBER(BY49),ISNUMBER(BY50)),IFERROR(BY49/BY50,""),"") -> 430.54493 | BZ51: =IF(AND(ISNUMBER(BZ49),ISNUMBER(BZ50)),IFERROR(BZ49/BZ50,""),"") -> 413.71158 | CA51: =SUM(BW51,BX51,BY51,BZ51) -> 1689.3625 | CB51: =IF(AND(ISNUMBER(CB49),ISNUMBER(CB50)),IFERROR(CB49/CB50,""),"") -> 1740.8557 | CC51: =IF(AND(ISNUMBER(CC49),ISNUMBER(CC50)),IFERROR(CC49/CC50,""),"") -> 1827.8985 | CD51: =IF(AND(ISNUMBER(CD49),ISNUMBER(CD50)),IFERROR(CD49/CD50,""),"") -> 1910.154 | CE51: =IF(AND(ISNUMBER(CE49),ISNUMBER(CE50)),IFERROR(CE49/CE50,""),"") -> 1996.1109 | CH51: =IFERROR((CE51/BV51)^(1/5)-1,"n/m") -> 0.047861324 | CI51: =IFERROR((BV51/AW51)^(1/5)-1,"n/m") -> -0.02508382 | CJ51: =IFERROR((BV51/X51)^(1/10)-1,"n/m") -> -0.057867879 | CK51: =IFERROR((BV51/C51)^(1/19)-1,"n/m") -> n/m | CN51: 2028E | CO51: =CP51+$CO$49 -> 0.18 | CP51: 0.19 | CQ51: =CP51+$CQ$49 -> 0.2
B52: Income (loss) from operations (incl. corporate; as reported) | AN52: -0.936 | AO52: -3.815 | AP52: 0.209 | AQ52: -8.772 | AR52: -13.314 | AS52: -1.045 | AT52: -6.834 | AU52: -0.586 | AV52: -2.255 | AW52: -10.72 | AX52: -4.044 | AY52: 1.3 | AZ52: -3.421 | BA52: -7.834 | BB52: -13.999 | BC52: -4.518 | BD52: 25.609 | BE52: -10.243 | BF52: -26.732 | BG52: -15.884 | BH52: -3.105 | BI52: -14.883 | BJ52: -2.09 | BK52: -11.105 | BL52: -31.183 | BM52: -13.314 | BN52: -3.994 | BO52: -56.763 | BP52: -0.556 | BQ52: -74.627 | BR52: -9.761 | BS52: 0.598 | BT52: -1.063 | BU52: -0.432 | BV52: -10.658 | BW52: -1.128 | BX52: 4.928 | CN52: 2029E | CO52: =CP52+$CO$49 -> 0.175 | CP52: 0.185 | CQ52: =CP52+$CQ$49 -> 0.195
B53: Average employee headcount (incl. corporate & shared services) | S53: =N(S60)+N(S64) -> 2968 | T53: =N(T60)+N(T64) -> 2880 | U53: =N(U60)+N(U64) -> 2925 | V53: =N(V60)+N(V64) -> 2967 | W53: =N(W60)+N(W64) -> 3020 | X53: =N(X60)+N(X64) -> 2946 | Y53: =N(Y60)+N(Y64) -> 3097 | Z53: =N(Z60)+N(Z64) -> 3208 | ... AM53: =N(AM60)+N(AM64) -> 3555 | AN53: 3250 | AO53: 3409 | AP53: 3544 | AQ53: 3562 | AR53: 3431 | AS53: 3588 | AT53: 3608 | AU53: 3595 | AV53: 3610 | AW53: 3600 | AX53: 3725 | AY53: 3916 | AZ53: 4037 | BA53: 4080 | BB53: 3926 | BC53: 4300 | BD53: 4582 | BE53: 4691 | BF53: 4676 | BG53: 4524 | BH53: 4561 | BI53: 4363 | BJ53: 4217 | BK53: 4195 | BL53: 4350 | BM53: 4110 | BN53: 3954 | BO53: 3938 | BP53: 3979 | BQ53: 4012 | BR53: 3553 | BS53: 3139 | BT53: 3127 | BU53: 3108 | BV53: 3291 | BW53: 3105 | BX53: 3101 | CN53: 2030E | CO53: =CP53+$CO$49 -> 0.175 | CP53: 0.185 | CQ53: =CP53+$CQ$49 -> 0.195
B54: Memo: Robinson Fresh AGP (segment to 2018; within All Other from 2019) | S54: 203.591 | T54: 55.548 | U54: 65.712 | V54: 57.911 | W54: 56.163 | X54: 235.334 | Y54: 58.185 | Z54: 67.82 | AA54: 57.036 | AB54: 51.753 | AC54: 234.794 | AD54: 56.837 | AE54: 60.846 | AF54: 54.253 | AG54: 54.123 | AH54: 226.059 | AI54: 53.87 | AJ54: 55.537 | AK54: 60.34 | AL54: 64.299 | AM54: 234.046 | AN54: 28.658 | AO54: 31.236 | AP54: 26.382 | AQ54: 22.907 | AR54: 109.183 | AS54: 27.458 | AT54: 30.202 | AU54: 24.449 | AV54: 23.591 | AW54: 105.7 | AX54: 24.948 | AY54: 29.94 | AZ54: 26.651 | BA54: 26.004 | BB54: 107.543 | BC54: 30.505 | BD54: 34.981 | BE54: 27.677 | BF54: 28.476 | BG54: 121.639 | BH54: 31.145 | BI54: 37.895 | BJ54: 31.083 | BK54: 31.093 | BL54: 131.216 | BM54: 33.736 | BN54: 39.883 | BO54: 36.708 | BP54: 35.983 | BQ54: 146.31 | BR54: 37.653 | BS54: 44.395 | BT54: 40.195 | BU54: 38.851 | BV54: 161.094 | BW54: 37.517 | BX54: 47.276 | CN54: M&A_spend (bolt-on acquisitions, $m) | CO54: 150 | CP54: Δ → | CQ54: -100 | CR54: Excludes RXO (see RXO PF tab). Base: modest bolt-ons from 2028E.
B55: Memo: Managed Solutions (Managed Services) AGP | AB55: 17.667 | AC55: 64.701 | AD55: 17.193 | AE55: 18.164 | AF55: 18.487 | AG55: 18.322 | AH55: 72.166 | AI55: 18.317 | AJ55: 20.074 | AK55: 20.08 | AL55: 20.318 | AM55: 78.789 | AN55: 20.312 | AO55: 20.099 | AP55: 21.574 | AQ55: 21.38 | AR55: 83.365 | AS55: 22.527 | AT55: 23.503 | AU55: 24.06 | AV55: 24.738 | AW55: 94.828 | AX55: 25.556 | AY55: 26.234 | AZ55: 26.72 | BA55: 26.554 | BB55: 105.064 | BC55: 28.082 | BD55: 27.618 | BE55: 29.595 | BF55: 29.799 | BG55: 115.094 | BH55: 28.97 | BI55: 28.953 | BJ55: 29.427 | BK55: 28.846 | BL55: 116.196 | BM55: 28.936 | BN55: 28.752 | BO55: 27.949 | BP55: 28.133 | BQ55: 113.77 | BR55: 27.846 | BS55: 29.007 | BT55: 29.988 | BU55: 28.588 | BV55: 115.429 | BW55: 29.608 | BX55: 32.471 | CN55: 2027E | CO55: =CP55+$CO$54 -> 150 | CP55: 0 | CQ55: =CP55+$CQ$54 -> -100
B56: Memo: Other Surface Transportation AGP (Europe Surface; divested Feb-25) | AB56: 14.736 | AC56: 56.141 | AD56: 15.55 | AE56: 13.85 | AF56: 13.861 | AG56: 16.22 | AH56: 59.481 | AI56: 15.932 | AJ56: 15.028 | AK56: 14.001 | AL56: 15.035 | AM56: 59.996 | AN56: 16.044 | AO56: 15.527 | AP56: 15.9 | AQ56: 14.946 | AR56: 62.417 | AS56: 16.876 | AT56: 18.232 | AU56: 15.164 | AV56: 15.378 | AW56: 65.65 | AX56: 16.468 | AY56: 17.652 | AZ56: 19.774 | BA56: 19.094 | BB56: 72.988 | BC56: 19.661 | BD56: 20.02 | BE56: 17.702 | BF56: 18.884 | BG56: 76.267 | BH56: 20.951 | BI56: 18.885 | BJ56: 17.936 | BK56: 16.205 | BL56: 73.977 | BM56: 17.902 | BN56: 15.05 | BO56: 15.296 | BP56: 12.942 | BQ56: 61.19 | BR56: 4.637 | BS56: 0 | BT56: 0 | BU56: 0 | BV56: 4.637 | BW56: 0 | BX56: 0 | CN56: 2028E | CO56: =CP56+$CO$54 -> 250 | CP56: 100 | CQ56: =CP56+$CQ$54 -> 0
B57: Memo: Robinson Fresh segment revenues (2014–2018) | S57: 2483.163 | T57: 570.39 | U57: 672.424 | V57: 602.913 | W57: 549.713 | X57: 2395.44 | Y57: 564.093 | Z57: 660.204 | AA57: 590.385 | AB57: 529.449 | AC57: 2344.131 | AD57: 550.445 | AE57: 657.003 | AF57: 613.646 | AG57: 594.646 | AH57: 2415.74 | AI57: 550.469 | AJ57: 621.024 | AK57: 565.59 | AL57: 531.817 | AM57: 2268.9 | CN57: 2029E | CO57: =CP57+$CO$54 -> 300 | CP57: 150 | CQ57: =CP57+$CQ$54 -> 50
B58: Memo: Robinson Fresh segment AGP (2014–2018) | S58: 203.591 | T58: 55.548 | U58: 65.712 | V58: 57.911 | W58: 56.163 | X58: 235.334 | Y58: 58.185 | Z58: 67.82 | AA58: 57.036 | AB58: 51.753 | AC58: 234.794 | AD58: 56.837 | AE58: 60.846 | AF58: 54.253 | AG58: 54.123 | AH58: 226.059 | AI58: 53.87 | AJ58: 55.537 | AK58: 60.34 | AL58: 64.299 | AM58: 234.046 | CN58: 2030E | CO58: =CP58+$CO$54 -> 300 | CP58: 150 | CQ58: =CP58+$CQ$54 -> 50
B59: Memo: Robinson Fresh segment income from operations (2014–2018) | S59: 62.395 | T59: 19.293 | U59: 26.066 | V59: 19.908 | W59: 16.065 | X59: 81.332 | Y59: 17.733 | Z59: 27.311 | AA59: 17.733 | AB59: 12.98 | AC59: 75.757 | AD59: 14.652 | AE59: 14.249 | AF59: 11.586 | AG59: 12.887 | AH59: 53.374 | AI59: 9.307 | AJ59: 9.232 | AK59: 21.411 | AL59: 19.785 | AM59: 59.735
B60: Memo: Robinson Fresh segment average headcount (2014–2018) | S60: 912 | T60: 866 | U60: 890 | V60: 906 | W60: 912 | X60: 892 | Y60: 922 | Z60: 947 | AA60: 956 | AB60: 951 | AC60: 942 | AD60: 961 | AE60: 980 | AF60: 970 | AG60: 935 | AH60: 957 | AI60: 907 | AJ60: 909 | AK60: 914 | AL60: 887 | AM60: 903
B61: Memo: legacy All Other & Corporate revenues (ex Robinson Fresh; to 2018) | S61: 539.368 | T61: 124.298 | U61: 121.63 | V61: 113.477 | W61: 112.946 | X61: 472.351 | Y61: 113.259 | Z61: 124.149 | AA61: 122.352 | AB61: 128.12 | AC61: 487.88 | AD61: 136.64 | AE61: 142.644 | AF61: 149.251 | AG61: 155.308 | AH61: 583.843 | AI61: 158.093 | AJ61: 158.512 | AK61: 155.581 | AL61: 154.442 | AM61: 626.628
B62: Memo: legacy All Other & Corporate AGP (to 2018) | S62: 102.533 | T62: 25.22 | U62: 25.309 | V62: 25.389 | W62: 26.844 | X62: 102.762 | Y62: 28.486 | Z62: 29.968 | AA62: 29.985 | AB62: 32.403 | AC62: 120.842 | AD62: 32.743 | AE62: 32.014 | AF62: 32.348 | AG62: 34.542 | AH62: 131.647 | AI62: 34.249 | AJ62: 35.102 | AK62: 34.081 | AL62: 35.353 | AM62: 138.785
B63: Memo: legacy All Other & Corporate income from operations (to 2018) | S63: -14.276 | T63: -1.434 | U63: -4.938 | V63: -6.883 | W63: -4.177 | X63: -17.432 | Y63: 2.011 | Z63: 1.319 | AA63: 4.754 | AB63: -1.677 | AC63: 6.407 | AD63: 1.223 | AE63: -0.388 | AF63: 0.362 | AG63: 0.596 | AH63: 1.793 | AI63: -0.021 | AJ63: -4.578 | AK63: -3.431 | AL63: -5.094 | AM63: -13.124
B64: Memo: legacy All Other & Corporate average headcount (to 2018) | S64: 2056 | T64: 2014 | U64: 2035 | V64: 2061 | W64: 2108 | X64: 2054 | Y64: 2175 | Z64: 2261 | AA64: 2322 | AB64: 2380 | AC64: 2282 | AD64: 2548 | AE64: 2616 | AF64: 2634 | AG64: 2540 | AH64: 2513 | AI64: 2559 | AJ64: 2627 | AK64: 2686 | AL64: 2728 | AM64: 2652
B66: Adjusted gross profit by service line (consolidated, all segments; "gross profits" to 2008, "net revenues" 2009–18, AGP from 2019) | CF66: SERVICE LINES — history only (forecast is built by segment)
B67: Truckload ("truck" incl. LTL to 2012) | C67: 822.954 | D67: 949.277 | E67: 1030.07 | F67: 1040.703 | G67: 1076.247 | H67: 1236.611 | I67: 1284.28 | J67: 268.604 | K67: 264.335 | L67: 265.509 | M67: 256.117 | N67: 1054.565 | O67: 269.837 | P67: 305.561 | Q67: 307.376 | R67: 295.216 | S67: 1177.99 | T67: 298.38 | U67: 334.546 | V67: 344.715 | W67: 338.892 | X67: 1316.533 | Y67: 321.684 | Z67: 329.74 | AA67: 309.027 | AB67: 296.74 | AC67: 1257.191 | AD67: 304.122 | AE67: 282.718 | AF67: 301.025 | AG67: 342.134 | AH67: 1229.999 | AI67: 330.291 | AJ67: 341.442 | AK67: 378.572 | AL67: 395.611 | AM67: 1445.916 | AN67: 377.993 | AO67: 371.351 | AP67: 317.99 | AQ67: 281.544 | AR67: 1348.878 | AS67: 264.926 | AT67: 278.366 | AU67: 251.072 | AV67: 277.509 | AW67: 1071.873 | AX67: 300.023 | AY67: 308.027 | AZ67: 333.067 | BA67: 339.512 | BB67: 1280.629 | BC67: 359.787 | BD67: 456.26 | BE67: 398.418 | BF67: 346.845 | BG67: 1561.31 | BH67: 288.654 | BI67: 261.147 | BJ67: 245.439 | BK67: 243.839 | BL67: 1039.079 | BM67: 257.413 | BN67: 274.187 | BO67: 279.564 | BP67: 261.527 | BQ67: 1072.691 | BR67: 262.288 | BS67: 267.913 | BT67: 273.885 | BU67: 248.195 | BV67: 1052.281 | BW67: 251.599 | BX67: 264.164
B68: LTL (from 2013) | J68: 58.491 | K68: 60.711 | L68: 61.436 | M68: 58.839 | N68: 239.477 | O68: 60.138 | P68: 67.376 | Q68: 67.968 | R68: 63.402 | S68: 258.884 | T68: 85.37 | U68: 91.524 | V68: 94.19 | W68: 89.622 | X68: 360.706 | Y68: 91.293 | Z68: 99.778 | AA68: 96.447 | AB68: 94.299 | AC68: 381.817 | AD68: 97.623 | AE68: 102.213 | AF68: 101.87 | AG68: 105.306 | AH68: 407.012 | AI68: 112.144 | AJ68: 119.189 | AK68: 122.616 | AL68: 117.326 | AM68: 471.275 | AN68: 116.229 | AO68: 122.991 | AP68: 124.523 | AQ68: 113.605 | AR68: 477.348 | AS68: 113.909 | AT68: 106.956 | AU68: 118.561 | AV68: 117.864 | AW68: 457.29 | AX68: 121.553 | AY68: 129.868 | AZ68: 132.482 | BA68: 139.462 | BB68: 523.365 | BC68: 152.312 | BD68: 168.298 | BE68: 162.13 | BF68: 149.376 | BG68: 632.116 | BH68: 138.637 | BI68: 137.185 | BJ68: 137.949 | BK68: 136.602 | BL68: 550.373 | BM68: 141.136 | BN68: 145.823 | BO68: 143.228 | BP68: 141.982 | BQ68: 572.169 | BR68: 148.411 | BS68: 152.186 | BT68: 158.251 | BU68: 150.888 | BV68: 609.736 | BW68: 163.448 | BX68: 185.309
B69: Intermodal (to Q3/20; then other logistics) | C69: 36.176 | D69: 38.67 | E69: 43.618 | F69: 35.245 | G69: 36.55 | H69: 41.189 | I69: 38.815 | J69: 9.101 | K69: 9.92 | L69: 10.202 | M69: 9.861 | N69: 39.084 | O69: 8.94 | P69: 10.863 | Q69: 10.593 | R69: 10.235 | S69: 40.631 | T69: 10.512 | U69: 11.539 | V69: 10.168 | W69: 8.835 | X69: 41.054 | Y69: 9.264 | Z69: 9.021 | AA69: 7.676 | AB69: 7.521 | AC69: 33.482 | AD69: 7.492 | AE69: 8.308 | AF69: 7.478 | AG69: 5.867 | AH69: 29.145 | AI69: 6.332 | AJ69: 9.181 | AK69: 8.361 | AL69: 8.595 | AM69: 32.469 | AN69: 6.076 | AO69: 6.298 | AP69: 7.11 | AQ69: 8.186 | AR69: 27.67 | AS69: 7.553 | AT69: 7.767 | AU69: 7.455
B70: Ocean | C70: 37.15 | D70: 43.53 | E70: 62.094 | F70: 54.188 | G70: 60.763 | H70: 66.873 | I70: 84.924 | J70: 42.488 | K70: 49.124 | L70: 49.692 | M70: 46.367 | N70: 187.671 | O70: 43.612 | P70: 50.486 | Q70: 57.38 | R70: 56.944 | S70: 208.422 | T70: 50.19 | U70: 59.066 | V70: 58.322 | W70: 56.065 | X70: 223.643 | Y70: 58.669 | Z70: 60.068 | AA70: 56.506 | AB70: 69.033 | AC70: 244.276 | AD70: 62.875 | AE70: 73.438 | AF70: 81.182 | AG70: 73.135 | AH70: 290.63 | AI70: 68.844 | AJ70: 87.035 | AK70: 74.839 | AL70: 82.234 | AM70: 312.952 | AN70: 71.533 | AO70: 85.472 | AP70: 77.879 | AQ70: 73.483 | AR70: 308.367 | AS70: 69.902 | AT70: 78.853 | AU70: 88.927 | AV70: 112.412 | AW70: 350.094 | AX70: 135.51 | AY70: 150.986 | AZ70: 214.926 | BA70: 209.801 | BB70: 711.223 | BC70: 221.463 | BD70: 227.958 | BE70: 160.122 | BF70: 120.296 | BG70: 729.839 | BH70: 110.079 | BI70: 107.497 | BJ70: 104.116 | BK70: 99.191 | BL70: 420.883 | BM70: 112.858 | BN70: 116.659 | BO70: 163.314 | BP70: 127.139 | BQ70: 519.97 | BR70: 115.335 | BS70: 107.902 | BT70: 110.422 | BU70: 99.215 | BV70: 432.874 | BW70: 89.919 | BX70: 104.988
B71: Air | C71: 21.533 | D71: 31.315 | E71: 35.39 | F71: 32.662 | G71: 42.315 | H71: 39.371 | I71: 44.444 | J71: 16.768 | K71: 20.202 | L71: 18.137 | M71: 17.982 | N71: 73.089 | O71: 17.454 | P71: 21.747 | Q71: 20.52 | R71: 19.404 | S71: 79.125 | T71: 20.639 | U71: 19.596 | V71: 20.248 | W71: 18.613 | X71: 79.096 | Y71: 18.409 | Z71: 20.118 | AA71: 19.897 | AB71: 23.743 | AC71: 82.167 | AD71: 21.817 | AE71: 25.82 | AF71: 25.529 | AG71: 27.595 | AH71: 100.761 | AI71: 28.883 | AJ71: 30.905 | AK71: 29.991 | AL71: 30.761 | AM71: 120.54 | AN71: 27.582 | AO71: 26.134 | AP71: 27.121 | AQ71: 25.94 | AR71: 106.777 | AS71: 28.338 | AT71: 52.405 | AU71: 34.977 | AV71: 35.723 | AW71: 151.443 | AX71: 45.894 | AY71: 53.057 | AZ71: 60.552 | BA71: 65.783 | BB71: 225.286 | BC71: 61.434 | BD71: 56.871 | BE71: 47.831 | BF71: 32.03 | BG71: 198.166 | BH71: 31.317 | BI71: 33.728 | BJ71: 30.201 | BK71: 28.224 | BL71: 123.47 | BM71: 30.532 | BN71: 30.906 | BO71: 33.607 | BP71: 40.856 | BQ71: 135.901 | BR71: 32.81 | BS71: 34.461 | BT71: 35.515 | BU71: 33.909 | BV71: 136.695 | BW71: 32.724 | BX71: 42.339
B72: Customs (from 2013; miscellaneous earlier) | J72: 8.606 | K72: 9.769 | L72: 8.932 | M72: 9.271 | N72: 36.578 | O72: 9.332 | P72: 10.312 | Q72: 11.107 | R72: 10.824 | S72: 41.575 | T72: 10.263 | U72: 10.973 | V72: 12.012 | W72: 10.681 | X72: 43.929 | Y72: 10.724 | Z72: 11.605 | AA72: 12.32 | AB72: 15.86 | AC72: 50.509 | AD72: 16.078 | AE72: 16.311 | AF72: 17.421 | AG72: 21.142 | AH72: 70.952 | AI72: 20.655 | AJ72: 20.794 | AK72: 23.305 | AL72: 23.761 | AM72: 88.515 | AN72: 21.878 | AO72: 23.306 | AP72: 23.719 | AQ72: 22.925 | AR72: 91.828 | AS72: 21.193 | AT72: 19.461 | AU72: 22.464 | AV72: 23.977 | AW72: 87.095 | AX72: 24.222 | AY72: 25.513 | AZ72: 25.466 | BA72: 25.338 | BB72: 100.539 | BC72: 27.495 | BD72: 27.82 | BE72: 27.881 | BF72: 24.495 | BG72: 107.691 | BH72: 23.334 | BI72: 25.128 | BJ72: 24.904 | BK72: 23.73 | BL72: 97.096 | BM72: 26.095 | BN72: 26.652 | BO72: 28.266 | BP72: 26.467 | BQ72: 107.48 | BR72: 26.92 | BS72: 35.098 | BT72: 36.358 | BU72: 34.4 | BV72: 132.776 | BW72: 32.32 | BX72: 31.787
B73: Other logistics services ("miscellaneous" to 2012) | C73: 28.152 | D73: 35.24 | E73: 41.407 | F73: 44.784 | G73: 57.254 | H73: 59.872 | I73: 75.674 | J73: 17.194 | K73: 17.084 | L73: 16.07 | M73: 17.583 | N73: 67.931 | O73: 18.566 | P73: 17.207 | Q73: 19.043 | R73: 18.281 | S73: 73.097 | T73: 19.791 | U73: 21.104 | V73: 20.436 | W73: 21.217 | X73: 82.548 | Y73: 24.023 | Z73: 26.171 | AA73: 26.771 | AB73: 28.404 | AC73: 105.369 | AD73: 28.151 | AE73: 29.832 | AF73: 29.58 | AG73: 29.554 | AH73: 117.117 | AI73: 28.889 | AJ73: 31.397 | AK73: 31.188 | AL73: 30.603 | AM73: 122.077 | AN73: 30.385 | AO73: 30.062 | AP73: 30.025 | AQ73: 31.522 | AR73: 121.994 | AS73: 36.184 | AT73: 42.213 | AU73: 42.874 | AV73: 51.113 | AW73: 195.159 | AX73: 51.74 | AY73: 53.692 | AZ73: 53.018 | BA73: 52.508 | BB73: 210.958 | BC73: 55.636 | BD73: 61.561 | BE73: 65.441 | BF73: 68.909 | BG73: 251.547 | BH73: 64.913 | BI73: 66.582 | BJ73: 64.838 | BK73: 59.402 | BL73: 255.735 | BM73: 59.558 | BN73: 57.32 | BO73: 54.338 | BP73: 54.383 | BQ73: 225.599 | BR73: 54.781 | BS73: 56.459 | BT73: 56.421 | BU73: 56.618 | BV73: 224.279 | BW73: 58.391 | BX73: 67.774
B74: Sourcing (Robinson Fresh) | C74: 94.229 | D74: 100.22 | E74: 111.634 | F74: 128.582 | G74: 139.377 | H74: 128.448 | I74: 136.438 | J74: 31.846 | K74: 38.752 | L74: 30.553 | M74: 25.799 | N74: 126.95 | O74: 26.846 | P74: 34.894 | Q74: 29.801 | R74: 24.005 | S74: 115.546 | T74: 29.965 | U74: 35.67 | V74: 28.484 | W74: 26.852 | X74: 120.971 | Y74: 29.269 | Z74: 37.714 | AA74: 29.818 | AB74: 25.916 | AC74: 122.717 | AD74: 30.408 | AE74: 35.149 | AF74: 29.761 | AG74: 27.116 | AH74: 122.434 | AI74: 29.887 | AJ74: 31.54 | AK74: 25.172 | AL74: 24.892 | AM74: 111.491 | AN74: 27.124 | AO74: 29.602 | AP74: 25.064 | AQ74: 21.658 | AR74: 103.448 | AS74: 25.948 | AT74: 28.432 | AU74: 22.943 | AV74: 21.98 | AW74: 99.303 | AX74: 23.438 | AY74: 28.033 | AZ74: 24.681 | BA74: 23.937 | BB74: 100.089 | BC74: 28.069 | BD74: 32.845 | BE74: 25.371 | BF74: 26.223 | BG74: 112.508 | BH74: 28.706 | BI74: 34.229 | BJ74: 27.402 | BK74: 27.635 | BL74: 117.972 | BM74: 30.137 | BN74: 35.862 | BO74: 32.936 | BP74: 32.269 | BQ74: 131.204 | BR74: 32.543 | BS74: 39.212 | BT74: 35.225 | BU74: 33.789 | BV74: 140.769 | BW74: 32.092 | BX74: 41.605
B75: Payment / Information Services (T-Chek; divested Nov-2012) | C75: 42.35 | D75: 45.526 | E75: 50.75 | F75: 45.795 | G75: 55.472 | H75: 60.294 | I75: 52.996 | J75: 2.624 | K75: 2.705 | L75: 2.775 | M75: 2.646 | N75: 10.75 | O75: 2.51 | P75: 2.591 | Q75: 3.776 | R75: 3.505 | S75: 12.382
B76: Total AGP (sum of service lines) | C76: =N(C67)+N(C68)+N(C69)+N(C70)+N(C71)+N(C72)+N(C73)+N(C74)+N(C75) -> 1082.544 | D76: =N(D67)+N(D68)+N(D69)+N(D70)+N(D71)+N(D72)+N(D73)+N(D74)+N(D75) -> 1243.778 | E76: =N(E67)+N(E68)+N(E69)+N(E70)+N(E71)+N(E72)+N(E73)+N(E74)+N(E75) -> 1374.963 | F76: =N(F67)+N(F68)+N(F69)+N(F70)+N(F71)+N(F72)+N(F73)+N(F74)+N(F75) -> 1381.959 | G76: =N(G67)+N(G68)+N(G69)+N(G70)+N(G71)+N(G72)+N(G73)+N(G74)+N(G75) -> 1467.978 | H76: =N(H67)+N(H68)+N(H69)+N(H70)+N(H71)+N(H72)+N(H73)+N(H74)+N(H75) -> 1632.658 | I76: =N(I67)+N(I68)+N(I69)+N(I70)+N(I71)+N(I72)+N(I73)+N(I74)+N(I75) -> 1717.571 | J76: =N(J67)+N(J68)+N(J69)+N(J70)+N(J71)+N(J72)+N(J73)+N(J74)+N(J75) -> 455.722 | ... BX76: =N(BX67)+N(BX68)+N(BX69)+N(BX70)+N(BX71)+N(BX72)+N(BX73)+N(BX74)+N(BX75) -> 737.966
B77: Check: service lines vs consolidated AGP (should be 0) | C77: =IF(ISNUMBER(C67),ROUND(C76-C133,1),"") -> 0 | D77: =IF(ISNUMBER(D67),ROUND(D76-D133,1),"") -> 0 | E77: =IF(ISNUMBER(E67),ROUND(E76-E133,1),"") -> 0 | F77: =IF(ISNUMBER(F67),ROUND(F76-F133,1),"") -> 0 | G77: =IF(ISNUMBER(G67),ROUND(G76-G133,1),"") -> 0 | H77: =IF(ISNUMBER(H67),ROUND(H76-H133,1),"") -> 0 | I77: =IF(ISNUMBER(I67),ROUND(I76-I133,1),"") -> 0 | J77: =IF(ISNUMBER(J67),ROUND(J76-J133,1),"") -> 0 | ... BX77: =IF(ISNUMBER(BX67),ROUND(BX76-BX133,1),"") -> 0
B79: Future acquisitions (M&A lever — bolt-ons, unallocated; deals closed from 2027E) | CF79: M&A LEVER — modelling logic
B80: Acquisition spend (USDm, scenario) | CA80: 0 | CB80: =MAX(0,CHOOSE(MATCH($CF$2,{"Bull","Base","Bear"},0),$CO$55,$CP$55,$CQ$55)) -> 0 | CC80: =MAX(0,CHOOSE(MATCH($CF$2,{"Bull","Base","Bear"},0),$CO$56,$CP$56,$CQ$56)) -> 100 | CD80: =MAX(0,CHOOSE(MATCH($CF$2,{"Bull","Base","Bear"},0),$CO$57,$CP$57,$CQ$57)) -> 150 | CE80: =MAX(0,CHOOSE(MATCH($CF$2,{"Bull","Base","Bear"},0),$CO$58,$CP$58,$CQ$58)) -> 150 | CF80: Scenario lever M&A_spend (CHRW bolt-on cadence: Prime 2019, Combinex 2021, DeSpir Logistics Q2/26 $79m). Excludes RXO (see RXO PF tab).
B81: Purchase multiple — EV / AGP (x) | CB81: 4 | CC81: 4 | CD81: 4 | CE81: 4
B82: Annualised AGP acquired in the year | CB82: =IFERROR(CB80/CB81,0) -> 0 | CC82: =IFERROR(CC80/CC81,0) -> 25 | CD82: =IFERROR(CD80/CD81,0) -> 37.5 | CE82: =IFERROR(CE80/CE81,0) -> 37.5
B83: Growth of acquired businesses after acquisition % | CB83: 0.04 | CC83: 0.04 | CD83: 0.04 | CE83: 0.04
B84: Run-rate AGP of businesses acquired (year end) | CA84: 0 | CB84: =CA84*(1+CB83)+CB82 -> 0 | CC84: =CB84*(1+CC83)+CC82 -> 25 | CD84: =CC84*(1+CD83)+CD82 -> 63.5 | CE84: =CD84*(1+CE83)+CE82 -> 103.54
B85: AGP from future acquisitions | CA85: 0 | CB85: =CA84*(1+CB83)+0.5*CB82 -> 0 | CC85: =CB84*(1+CC83)+0.5*CC82 -> 12.5 | CD85: =CC84*(1+CD83)+0.5*CD82 -> 44.75 | CE85: =CD84*(1+CE83)+0.5*CE82 -> 84.79
B86: AGP margin of acquired businesses (% revenues) | CB86: 0.15 | CC86: 0.15 | CD86: 0.15 | CE86: 0.15
B87: Revenues from future acquisitions | CA87: 0 | CB87: =IFERROR(CB85/CB86,0) -> 0 | CC87: =IFERROR(CC85/CC86,0) -> 83.333333 | CD87: =IFERROR(CD85/CD86,0) -> 298.33333 | CE87: =IFERROR(CE85/CE86,0) -> 565.26667
B88: Operating margin of acquired businesses (% AGP, before amortization) | CB88: 0.25 | CC88: 0.25 | CD88: 0.25 | CE88: 0.25
B89: Operating expenses of acquired businesses (in other SG&A) | CA89: 0 | CB89: =CB85*(1-CB88) -> 0 | CC89: =CC85*(1-CC88) -> 9.375 | CD89: =CD85*(1-CD88) -> 33.5625 | CE89: =CE85*(1-CE88) -> 63.5925
B90: Acquired intangibles % of spend | CB90: 0.25 | CC90: 0.25 | CD90: 0.25 | CE90: 0.25
B91: Intangible amortization life (years) | CB91: 8 | CC91: 8 | CD91: 8 | CE91: 8
B92: Cumulative acquired intangibles (gross) | CA92: 0 | CB92: =CA92+CB80*CB90 -> 0 | CC92: =CB92+CC80*CC90 -> 25 | CD92: =CC92+CD80*CD90 -> 62.5 | CE92: =CD92+CE80*CE90 -> 100
B93: Amortization of future-acquisition intangibles (within D&A) | CA93: 0 | CB93: =(CA92+0.5*CB80*CB90)/CB91 -> 0 | CC93: =(CB92+0.5*CC80*CC90)/CC91 -> 1.5625 | CD93: =(CC92+0.5*CD80*CD90)/CD91 -> 5.46875 | CE93: =(CD92+0.5*CE80*CE90)/CE91 -> 10.15625
B95: Group Total — AGP & revenues (segment build) → adjusted income from operations (CHRW's primary profit metric) | CF95: GROUP TOTAL & FY26 OUTLOOK CALIBRATION
B96: AGP not split by segment (to 2013 & 2014 quarters; pre-segment reporting) | C96: 1082.544 | D96: 1243.778 | E96: 1374.963 | F96: 1381.959 | G96: 1467.978 | H96: 1632.658 | I96: 1717.571 | J96: 455.722 | K96: 472.602 | L96: 463.306 | M96: 444.465 | N96: 1836.095 | O96: 457.235 | P96: 521.037 | Q96: 527.564 | R96: 501.816
B97: Revenues not split by segment (to 2013 & 2014 quarters) | C97: 6556.194 | D97: 7316.223 | E97: 8578.614 | F97: 7577.189 | G97: 9274.305 | H97: 10336.346 | I97: 11359.113 | J97: 2994.267 | K97: 3288.262 | L97: 3316.665 | M97: 3152.882 | N97: 12752.076 | O97: 3142.585 | P97: 3502.918 | Q97: 3467.362 | R97: 3357.202
B98: Adjusted gross profit (segment build) | C98: =N(C13)+N(C32)+N(C49)+N(C96) -> 1082.544 | D98: =N(D13)+N(D32)+N(D49)+N(D96) -> 1243.778 | E98: =N(E13)+N(E32)+N(E49)+N(E96) -> 1374.963 | F98: =N(F13)+N(F32)+N(F49)+N(F96) -> 1381.959 | G98: =N(G13)+N(G32)+N(G49)+N(G96) -> 1467.978 | H98: =N(H13)+N(H32)+N(H49)+N(H96) -> 1632.658 | I98: =N(I13)+N(I32)+N(I49)+N(I96) -> 1717.571 | J98: =N(J13)+N(J32)+N(J49)+N(J96) -> 455.722 | ... BX98: =N(BX13)+N(BX32)+N(BX49)+N(BX96) -> 737.966 | BY98: =N(BY13)+N(BY32)+N(BY49)+N(BY85) -> 762.18779 | BZ98: =N(BZ13)+N(BZ32)+N(BZ49)+N(BZ85) -> 709.26403 | CA98: =N(CA13)+N(CA32)+N(CA49)+N(CA85) -> 2869.9108 | CB98: =N(CB13)+N(CB32)+N(CB49)+N(CB85) -> 3030.6053 | CC98: =N(CC13)+N(CC32)+N(CC49)+N(CC85) -> 3219.1046 | CD98: =N(CD13)+N(CD32)+N(CD49)+N(CD85) -> 3407.7834 | CE98: =N(CE13)+N(CE32)+N(CE49)+N(CE85) -> 3611.9036 | CH98: =IFERROR((CE98/BV98)^(1/5)-1,"n/m") -> 0.057629301 | CI98: =IFERROR((BV98/AW98)^(1/5)-1,"n/m") -> 0.025012214 | CJ98: =IFERROR((BV98/X98)^(1/10)-1,"n/m") -> 0.018669686 | CK98: =IFERROR((BV98/C98)^(1/19)-1,"n/m") -> 0.049876136
B99: Revenues (segment build) | C99: =N(C16)+N(C35)+N(C51)+N(C97) -> 6556.194 | D99: =N(D16)+N(D35)+N(D51)+N(D97) -> 7316.223 | E99: =N(E16)+N(E35)+N(E51)+N(E97) -> 8578.614 | F99: =N(F16)+N(F35)+N(F51)+N(F97) -> 7577.189 | G99: =N(G16)+N(G35)+N(G51)+N(G97) -> 9274.305 | H99: =N(H16)+N(H35)+N(H51)+N(H97) -> 10336.346 | I99: =N(I16)+N(I35)+N(I51)+N(I97) -> 11359.113 | J99: =N(J16)+N(J35)+N(J51)+N(J97) -> 2994.267 | ... BX99: =N(BX16)+N(BX35)+N(BX51)+N(BX97) -> 4934.098 | BY99: =N(BY16)+N(BY35)+N(BY51)+N(BY87) -> 5104.0718 | BZ99: =N(BZ16)+N(BZ35)+N(BZ51)+N(BZ87) -> 4746.2086 | CA99: =N(CA16)+N(CA35)+N(CA51)+N(CA87) -> 18797.312 | CB99: =N(CB16)+N(CB35)+N(CB51)+N(CB87) -> 19741.032 | CC99: =N(CC16)+N(CC35)+N(CC51)+N(CC87) -> 20378.519 | CD99: =N(CD16)+N(CD35)+N(CD51)+N(CD87) -> 21048.014 | CE99: =N(CE16)+N(CE35)+N(CE51)+N(CE87) -> 22335.678 | CH99: =IFERROR((CE99/BV99)^(1/5)-1,"n/m") -> 0.065911969 | CI99: =IFERROR((BV99/AW99)^(1/5)-1,"n/m") -> 0.00031641391 | CJ99: =IFERROR((BV99/X99)^(1/10)-1,"n/m") -> 0.018785778 | CK99: =IFERROR((BV99/C99)^(1/19)-1,"n/m") -> 0.048873691
B100: AGP y/y % | D100: =IF(AND(ISNUMBER(D98),ISNUMBER(C98)),IFERROR(D98/C98-1,""),"") -> 0.1489399 | E100: =IF(AND(ISNUMBER(E98),ISNUMBER(D98)),IFERROR(E98/D98-1,""),"") -> 0.105473 | F100: =IF(AND(ISNUMBER(F98),ISNUMBER(E98)),IFERROR(F98/E98-1,""),"") -> 0.0050881369 | G100: =IF(AND(ISNUMBER(G98),ISNUMBER(F98)),IFERROR(G98/F98-1,""),"") -> 0.062244249 | H100: =IF(AND(ISNUMBER(H98),ISNUMBER(G98)),IFERROR(H98/G98-1,""),"") -> 0.11218152 | I100: =IF(AND(ISNUMBER(I98),ISNUMBER(H98)),IFERROR(I98/H98-1,""),"") -> 0.052009055 | N100: =IF(AND(ISNUMBER(N98),ISNUMBER(I98)),IFERROR(N98/I98-1,""),"") -> 0.069006754 | O100: =IF(AND(ISNUMBER(O98),ISNUMBER(J98)),IFERROR(O98/J98-1,""),"") -> 0.0033200065 | P100: =IF(AND(ISNUMBER(P98),ISNUMBER(K98)),IFERROR(P98/K98-1,""),"") -> 0.10248581 | Q100: =IF(AND(ISNUMBER(Q98),ISNUMBER(L98)),IFERROR(Q98/L98-1,""),"") -> 0.13869451 | R100: =IF(AND(ISNUMBER(R98),ISNUMBER(M98)),IFERROR(R98/M98-1,""),"") -> 0.12903378 | S100: =IF(AND(ISNUMBER(S98),ISNUMBER(N98)),IFERROR(S98/N98-1,""),"") -> 0.093435797 | T100: =IF(AND(ISNUMBER(T98),ISNUMBER(O98)),IFERROR(T98/O98-1,""),"") -> 0.14844664 | U100: =IF(AND(ISNUMBER(U98),ISNUMBER(P98)),IFERROR(U98/P98-1,""),"") -> 0.12087625 | ... BX100: =IF(AND(ISNUMBER(BX98),ISNUMBER(BS98)),IFERROR(BX98/BS98-1,""),"") -> 0.064531159 | BY100: =IFERROR(BY98/BT98-1,"") -> 0.079468372 | BZ100: =IFERROR(BZ98/BU98-1,"") -> 0.079526515 | CA100: =IFERROR(CA98/BV98-1,"") -> 0.051476628 | CB100: =IFERROR(CB98/CA98-1,"") -> 0.055992855 | CC100: =IFERROR(CC98/CB98-1,"") -> 0.062198559 | CD100: =IFERROR(CD98/CC98-1,"") -> 0.058612201 | CE100: =IFERROR(CE98/CD98-1,"") -> 0.059898223
B101: AGP margin % of revenues | C101: =IF(AND(ISNUMBER(C98),ISNUMBER(C99)),IFERROR(C98/C99,""),"") -> 0.16511775 | D101: =IF(AND(ISNUMBER(D98),ISNUMBER(D99)),IFERROR(D98/D99,""),"") -> 0.17000275 | E101: =IF(AND(ISNUMBER(E98),ISNUMBER(E99)),IFERROR(E98/E99,""),"") -> 0.16027799 | F101: =IF(AND(ISNUMBER(F98),ISNUMBER(F99)),IFERROR(F98/F99,""),"") -> 0.18238413 | G101: =IF(AND(ISNUMBER(G98),ISNUMBER(G99)),IFERROR(G98/G99,""),"") -> 0.15828442 | H101: =IF(AND(ISNUMBER(H98),ISNUMBER(H99)),IFERROR(H98/H99,""),"") -> 0.15795311 | I101: =IF(AND(ISNUMBER(I98),ISNUMBER(I99)),IFERROR(I98/I99,""),"") -> 0.15120644 | J101: =IF(AND(ISNUMBER(J98),ISNUMBER(J99)),IFERROR(J98/J99,""),"") -> 0.15219818 | ... CE101: =IF(AND(ISNUMBER(CE98),ISNUMBER(CE99)),IFERROR(CE98/CE99,""),"") -> 0.16171005
B102: Check: segment build vs consolidated AGP (should be 0) | C102: =ROUND(C98-C133,1) -> 0 | D102: =ROUND(D98-D133,1) -> 0 | E102: =ROUND(E98-E133,1) -> 0 | F102: =ROUND(F98-F133,1) -> 0 | G102: =ROUND(G98-G133,1) -> 0 | H102: =ROUND(H98-H133,1) -> 0 | I102: =ROUND(I98-I133,1) -> 0 | J102: =ROUND(J98-J133,1) -> 0 | ... CE102: =ROUND(CE98-CE133,1) -> 0
B103: Check: segment build vs consolidated revenues (should be 0) | C103: =ROUND(C99-C125,1) -> 0 | D103: =ROUND(D99-D125,1) -> 0 | E103: =ROUND(E99-E125,1) -> 0 | F103: =ROUND(F99-F125,1) -> 0 | G103: =ROUND(G99-G125,1) -> 0 | H103: =ROUND(H99-H125,1) -> 0 | I103: =ROUND(I99-I125,1) -> 0 | J103: =ROUND(J99-J125,1) -> 0 | ... CE103: =ROUND(CE99-CE125,1) -> 0
...

Sheet Bull-Base-Bear
B2: C.H. Robinson Worldwide (CHRW) — Bull / Base / Bear Case P&L Summary | J2: Share price ($): | K2: =Model!$CA$394 -> 151.88
B3: Adjusted figures (company current definition: adjusted income from operations & adjusted EPS exclude restructuring, divestiture gains/losses and other company-defined items; adjusted EBITDA = model definition). CHRW standalone — RXO acquisition shown on the RXO PF tab. Margins on AGP (company KPI basis). | J3: As of: | K3: =TODAY() -> 46300
B5: Scenario: | C5: =Model!$CF$2 -> Base | N5: Scenario: | O5: Bull | P5: Snapshot (values) — Model run with switch = Bull | Z5: Scenario: | AA5: Bear | AB5: Snapshot (values) — Model run with switch = Bear
B7: (USDm, except EPS and shares) | C7: 2025A | D7: 2026E | E7: 2027E | F7: 2028E | G7: 2029E | H7: 2030E | I7: 25-'30 CAGR | J7: LT Hist Avg | K7: LT Hist Min | L7: LT Hist Max | N7: (USDm, except EPS and shares) | O7: 2025A | P7: 2026E | Q7: 2027E | R7: 2028E | S7: 2029E | T7: 2030E | U7: 25-'30 CAGR | V7: LT Hist Avg | W7: LT Hist Min | X7: LT Hist Max | Z7: (USDm, except EPS and shares) | AA7: 2025A | AB7: 2026E | AC7: 2027E | AD7: 2028E | AE7: 2029E | AF7: 2030E | AG7: 25-'30 CAGR | AH7: LT Hist Avg | AI7: LT Hist Min | AJ7: LT Hist Max
B9: Revenues | C9: =Model!BV125 -> 16232.763 | D9: =Model!CA125 -> 18797.312 | E9: =Model!CB125 -> 19741.032 | F9: =Model!CC125 -> 20378.519 | G9: =Model!CD125 -> 21048.014 | H9: =Model!CE125 -> 22335.678 | I9: =IFERROR((H9/C9)^(1/5)-1,"n/m") -> 0.065911969 | N9: Revenues | O9: 16232.763 | P9: 19050.409 | Q9: 20909.203 | R9: 22671.381 | S9: 24548.752 | T9: 27234.502 | U9: 0.10903538 | Z9: Revenues | AA9: 16232.763 | AB9: 18544.216 | AC9: 18516.551 | AD9: 18097.874 | AE9: 17626.366 | AF9: 17665.901 | AG9: 0.017064901
B10: Revenues y/y % | D10: =IFERROR(D9/C9-1,"") -> 0.15798601 | E10: =IFERROR(E9/D9-1,"") -> 0.050205035 | F10: =IFERROR(F9/E9-1,"") -> 0.032292475 | G10: =IFERROR(G9/F9-1,"") -> 0.032852979 | H10: =IFERROR(H9/G9-1,"") -> 0.061177466 | N10: Revenues y/y % | P10: 0.17357771 | Q10: 0.097572384 | R10: 0.084277624 | S10: 0.082807971 | T10: 0.10940478 | Z10: Revenues y/y % | AB10: 0.1423943 | AC10: -0.0014918316 | AD10: -0.022610951 | AE10: -0.026053217 | AF10: 0.0022429029
B11: NAST volume y/y % (truckload + LTL) | C11: =Model!BV11 -> 0.01 | D11: =Model!CA11 -> 0.01125 | E11: =Model!CB11 -> 0.03 | F11: =Model!CC11 -> 0.035 | G11: =Model!CD11 -> 0.03 | H11: =Model!CE11 -> 0.03 | N11: NAST volume y/y % (truckload + LTL) | O11: 0.01 | P11: 0.01125 | Q11: 0.05 | R11: 0.055 | S11: 0.05 | T11: 0.05 | Z11: NAST volume y/y % (truckload + LTL) | AA11: 0.01 | AB11: 0.01125 | AC11: 0.01 | AD11: 0.015 | AE11: 0.01 | AF11: 0.01
B12: Adjusted gross profit (AGP) | C12: =Model!BV133 -> 2729.41 | D12: =Model!CA133 -> 2869.9108 | E12: =Model!CB133 -> 3030.6053 | F12: =Model!CC133 -> 3219.1046 | G12: =Model!CD133 -> 3407.7834 | H12: =Model!CE133 -> 3611.9036 | I12: =IFERROR((H12/C12)^(1/5)-1,"n/m") -> 0.057629301 | N12: Adjusted gross profit (AGP) | O12: 2729.41 | P12: 2907.9108 | Q12: 3211.3639 | R12: 3582.1905 | S12: 3973.2957 | T12: 4402.9306 | U12: 0.10035954 | Z12: Adjusted gross profit (AGP) | AA12: 2729.41 | AB12: 2831.9108 | AC12: 2838.7198 | AD12: 2852.0723 | AE12: 2846.1716 | AF12: 2847.5039 | AG12: 0.008507447
B13: AGP y/y % | D13: =IFERROR(D12/C12-1,"") -> 0.051476628 | E13: =IFERROR(E12/D12-1,"") -> 0.055992855 | F13: =IFERROR(F12/E12-1,"") -> 0.062198559 | G13: =IFERROR(G12/F12-1,"") -> 0.058612201 | H13: =IFERROR(H12/G12-1,"") -> 0.059898223 | N13: AGP y/y % | P13: 0.065399051 | Q13: 0.10435433 | R13: 0.11547324 | S13: 0.10918046 | T13: 0.10813062 | Z13: AGP y/y % | AB13: 0.037554205 | AC13: 0.0024043741 | AD13: 0.0047037055 | AE13: -0.0020689195 | AF13: 0.00046810181
B15: Adjusted EBITDA (model definition) | C15: =Model!BV193 -> 936.551 | D15: =Model!CA193 -> 1094.422 | E15: =Model!CB193 -> 1204.0278 | F15: =Model!CC193 -> 1307.9428 | G15: =Model!CD193 -> 1406.6292 | H15: =Model!CE193 -> 1495.3163 | I15: =IFERROR((H15/C15)^(1/5)-1,"n/m") -> 0.098096046 | N15: Adjusted EBITDA (model definition) | O15: 936.551 | P15: 1133.5841 | Q15: 1377.039 | R15: 1614.9314 | S15: 1866.1568 | T15: 2124.8506 | U15: 0.17803825 | Z15: Adjusted EBITDA (model definition) | AA15: 936.551 | AB15: 1055.2598 | AC15: 1005.573 | AD15: 959.43274 | AE15: 896.01798 | AF15: 816.99395 | AG15: -0.026944791
B16: Adjusted EBITDA % of AGP | C16: =IFERROR(C15/Model!BV133,"") -> 0.34313313 | D16: =IFERROR(D15/Model!CA133,"") -> 0.38134355 | E16: =IFERROR(E15/Model!CB133,"") -> 0.39728955 | F16: =IFERROR(F15/Model!CC133,"") -> 0.4063064 | G16: =IFERROR(G15/Model!CD133,"") -> 0.41276955 | H16: =IFERROR(H15/Model!CE133,"") -> 0.41399674 | J16: =IFERROR(AVERAGE(Model!C194,Model!D194,Model!E194,Model!F194,Model!G194,Model!H194,Model!I194,Model!N194,Model!S194,Model!X194,Model!AC194,Model!AH194,Model!AM194,Model!AR194,Model!AW194,Model!BB194,Model!BG194,Model!BL194,Model!BQ194,Model!BV194),"") -> 0.38495897 | K16: =IFERROR(MIN(Model!C194,Model!D194,Model!E194,Model!F194,Model!G194,Model!H194,Model!I194,Model!N194,Model!S194,Model!X194,Model!AC194,Model!AH194,Model!AM194,Model!AR194,Model!AW194,Model!BB194,Model!BG194,Model!BL194,Model!BQ194,Model!BV194),"") -> 0.25018467 | L16: =IFERROR(MAX(Model!C194,Model!D194,Model!E194,Model!F194,Model!G194,Model!H194,Model!I194,Model!N194,Model!S194,Model!X194,Model!AC194,Model!AH194,Model!AM194,Model!AR194,Model!AW194,Model!BB194,Model!BG194,Model!BL194,Model!BQ194,Model!BV194),"") -> 0.44525561 | N16: Adjusted EBITDA % of AGP | O16: 0.34313313 | P16: 0.38982768 | Q16: 0.4288019 | R16: 0.45082232 | S16: 0.46967477 | T16: 0.48259915 | Z16: Adjusted EBITDA % of AGP | AA16: 0.34313313 | AB16: 0.37263173 | AC16: 0.35423468 | AD16: 0.33639846 | AE16: 0.31481517 | AF16: 0.28691583
B18: Income from Operations (GAAP) | C18: =Model!BV139 -> 794.961 | D18: =Model!CA139 -> 947.751 | E18: =Model!CB139 -> 1097.9566 | F18: =Model!CC139 -> 1194.1492 | G18: =Model!CD139 -> 1283.4543 | H18: =Model!CE139 -> 1361.7111 | I18: =IFERROR((H18/C18)^(1/5)-1,"n/m") -> 0.11364771 | N18: Income from Operations (GAAP) | O18: 794.961 | P18: 985.751 | Q18: 1262.9537 | R18: 1483.4198 | S18: 1714.911 | T18: 1952.0704 | U18: 0.19682301 | Z18: Income from Operations (GAAP) | AA18: 794.961 | AB18: 909.751 | AC18: 906.21782 | AD18: 859.61021 | AE18: 795.83948 | AF18: 715.66131 | AG18: -0.020797883
B19: Income from operations y/y % | D19: =IFERROR(D18/C18-1,"") -> 0.19219811 | E19: =IFERROR(E18/D18-1,"") -> 0.15848638 | F19: =IFERROR(F18/E18-1,"") -> 0.0876105 | G19: =IFERROR(G18/F18-1,"") -> 0.074785589 | H19: =IFERROR(H18/G18-1,"") -> 0.06097356 | N19: Income from operations y/y % | P19: 0.23999919 | Q19: 0.28120968 | R19: 0.17456383 | S19: 0.15605242 | T19: 0.13829254 | Z19: Income from operations y/y % | AB19: 0.14439702 | AC19: -0.0038836791 | AD19: -0.051430915 | AE19: -0.074185638 | AF19: -0.10074665
B20: Operating margin (GAAP) % of AGP | C20: =IFERROR(C18/Model!BV133,"") -> 0.29125745 | D20: =IFERROR(D18/Model!CA133,"") -> 0.33023709 | E20: =IFERROR(E18/Model!CB133,"") -> 0.36228955 | F20: =IFERROR(F18/Model!CC133,"") -> 0.37095693 | G20: =IFERROR(G18/Model!CD133,"") -> 0.37662438 | H20: =IFERROR(H18/Model!CE133,"") -> 0.37700649 | J20: =IFERROR(AVERAGE(Model!C231,Model!D231,Model!E231,Model!F231,Model!G231,Model!H231,Model!I231,Model!N231,Model!S231,Model!X231,Model!AC231,Model!AH231,Model!AM231,Model!AR231,Model!AW231,Model!BB231,Model!BG231,Model!BL231,Model!BQ231,Model!BV231),"") -> 0.35214122 | K20: =IFERROR(MIN(Model!C231,Model!D231,Model!E231,Model!F231,Model!G231,Model!H231,Model!I231,Model!N231,Model!S231,Model!X231,Model!AC231,Model!AH231,Model!AM231,Model!AR231,Model!AW231,Model!BB231,Model!BG231,Model!BL231,Model!BQ231,Model!BV231),"") -> 0.1975756 | L20: =IFERROR(MAX(Model!C231,Model!D231,Model!E231,Model!F231,Model!G231,Model!H231,Model!I231,Model!N231,Model!S231,Model!X231,Model!AC231,Model!AH231,Model!AM231,Model!AR231,Model!AW231,Model!BB231,Model!BG231,Model!BL231,Model!BQ231,Model!BV231),"") -> 0.42429791 | N20: Operating margin (GAAP) % of AGP | O20: 0.29125745 | P20: 0.33898942 | Q20: 0.39327643 | R20: 0.41410968 | S20: 0.4316092 | T20: 0.44335707 | Z20: Operating margin (GAAP) % of AGP | AA20: 0.29125745 | AB20: 0.32124988 | AC20: 0.31923468 | AD20: 0.30139846 | AE20: 0.27961753 | AF20: 0.25132935
B22: Adjusted Income from Operations | C22: =Model!BV181 -> 833.733 | D22: =Model!CA181 -> 1002 | E22: =Model!CB181 -> 1097.9566 | F22: =Model!CC181 -> 1194.1492 | G22: =Model!CD181 -> 1283.4543 | H22: =Model!CE181 -> 1361.7111 | I22: =IFERROR((H22/C22)^(1/5)-1,"n/m") -> 0.10309165 | N22: Adjusted Income from Operations | O22: 833.733 | P22: 1040 | Q22: 1262.9537 | R22: 1483.4198 | S22: 1714.911 | T22: 1952.0704 | U22: 0.18547854 | Z22: Adjusted Income from Operations | AA22: 833.733 | AB22: 964 | AC22: 906.21782 | AD22: 859.61021 | AE22: 795.83948 | AF22: 715.66131 | AG22: -0.030079564
B23: Adjusted operating margin % of AGP | C23: =IFERROR(C22/Model!BV133,"") -> 0.30546272 | D23: =IFERROR(D22/Model!CA133,"") -> 0.34913977 | E23: =IFERROR(E22/Model!CB133,"") -> 0.36228955 | F23: =IFERROR(F22/Model!CC133,"") -> 0.37095693 | G23: =IFERROR(G22/Model!CD133,"") -> 0.37662438 | H23: =IFERROR(H22/Model!CE133,"") -> 0.37700649 | J23: =IFERROR(AVERAGE(Model!C182,Model!D182,Model!E182,Model!F182,Model!G182,Model!H182,Model!I182,Model!N182,Model!S182,Model!X182,Model!AC182,Model!AH182,Model!AM182,Model!AR182,Model!AW182,Model!BB182,Model!BG182,Model!BL182,Model!BQ182,Model!BV182),"") -> 0.35525933 | K23: =IFERROR(MIN(Model!C182,Model!D182,Model!E182,Model!F182,Model!G182,Model!H182,Model!I182,Model!N182,Model!S182,Model!X182,Model!AC182,Model!AH182,Model!AM182,Model!AR182,Model!AW182,Model!BB182,Model!BG182,Model!BL182,Model!BQ182,Model!BV182),"") -> 0.21218087 | L23: =IFERROR(MAX(Model!C182,Model!D182,Model!E182,Model!F182,Model!G182,Model!H182,Model!I182,Model!N182,Model!S182,Model!X182,Model!AC182,Model!AH182,Model!AM182,Model!AR182,Model!AW182,Model!BB182,Model!BG182,Model!BL182,Model!BQ182,Model!BV182),"") -> 0.42429791 | N23: Adjusted operating margin % of AGP | O23: 0.30546272 | P23: 0.35764508 | Q23: 0.39327643 | R23: 0.41410968 | S23: 0.4316092 | T23: 0.44335707 | Z23: Adjusted operating margin % of AGP | AA23: 0.30546272 | AB23: 0.3404062 | AC23: 0.31923468 | AD23: 0.30139846 | AE23: 0.27961753 | AF23: 0.25132935
B25: Adjusted Net Income | C25: =Model!BV209 -> 618.196 | D25: =Model!CA209 -> 758.16348 | E25: =Model!CB209 -> 829.79979 | F25: =Model!CC209 -> 896.52203 | G25: =Model!CD209 -> 960.9141 | H25: =Model!CE209 -> 1018.9306 | I25: =IFERROR((H25/C25)^(1/5)-1,"n/m") -> 0.10510536 | N25: Adjusted Net Income | O25: 618.196 | P25: 798.17452 | Q25: 958.93283 | R25: 1107.087 | S25: 1276.7856 | T25: 1452.4948 | U25: 0.1863086 | Z25: Adjusted Net Income | AA25: 618.196 | AB25: 718.91244 | AC25: 679.30166 | AD25: 647.47085 | AE25: 595.95068 | AF25: 534.16718 | AG25: -0.028796582
B27: FDSO (m) | C27: =Model!BV156 -> 121.502 | D27: =Model!CA156 -> 119.72924 | E27: =Model!CB156 -> 114.61473 | F27: =Model!CC156 -> 110.69066 | G27: =Model!CD156 -> 107.43735 | H27: =Model!CE156 -> 104.34231 | I27: =IFERROR((H27/C27)^(1/5)-1,"n/m") -> -0.0299918 | N27: FDSO (m) | O27: 121.502 | P27: 119.56464 | Q27: 112.65618 | R27: 106.70623 | S27: 101.66574 | T27: 96.141679 | U27: -0.04574234 | Z27: FDSO (m) | AA27: 121.502 | AB27: 119.89384 | AC27: 116.89656 | AD27: 115.43471 | AE27: 114.17137 | AF27: 113.64089 | AG27: -0.013288388
B29: Adjusted EPS — Diluted ($) | C29: =Model!BV211 -> 5.0879492 | D29: =Model!CA211 -> 6.3323168 | E29: =Model!CB211 -> 7.2399051 | F29: =Model!CC211 -> 8.099347 | G29: =Model!CD211 -> 8.9439485 | H29: =Model!CE211 -> 9.7652677 | I29: =IFERROR((H29/C29)^(1/5)-1,"n/m") -> 0.13927424 | N29: Adjusted EPS — Diluted ($) | O29: 5.0879492 | P29: 6.6756738 | Q29: 8.5120302 | R29: 10.375093 | S29: 12.558662 | T29: 15.107858 | U29: 0.2431743 | Z29: Adjusted EPS — Diluted ($) | AA29: 5.0879492 | AB29: 5.9962414 | AC29: 5.8111347 | AD29: 5.6089787 | AE29: 5.2197911 | AF29: 4.700484 | AG29: -0.015717048
B30: EPS y/y % | D30: =IFERROR(D29/C29-1,"") -> 0.24457155 | E30: =IFERROR(E29/D29-1,"") -> 0.14332642 | F30: =IFERROR(F29/E29-1,"") -> 0.11870901 | G30: =IFERROR(G29/F29-1,"") -> 0.10428019 | H30: =IFERROR(H29/G29-1,"") -> 0.091829597 | N30: EPS y/y % | P30: 0.31205592 | Q30: 0.2750818 | R30: 0.21887405 | S30: 0.21046263 | T30: 0.20298305 | Z30: EPS y/y % | AB30: 0.17851835 | AC30: -0.030870461 | AD30: -0.034787696 | AE30: -0.069386534 | AF30: -0.099488105
B32: P / E (x) — assumed (adjusted EPS) | G32: 20 | H32: 20 | N32: P / E (x) — assumed (adjusted EPS) | S32: 24 | T32: 24 | Z32: P / E (x) — assumed (adjusted EPS) | AE32: 16 | AF32: 16
B33: Price Target ($) | G33: =G32*G29 -> 178.87897 | H33: =H32*H29 -> 195.30535 | N33: Price Target ($) | S33: 251.17324 | T33: 302.15715 | Z33: Price Target ($) | AE33: 104.39582 | AF33: 94.00968
B34: Upside / (Downside) vs current | G34: =IFERROR(G33/$K$2-1,"") -> 0.17776514 | H34: =IFERROR(H33/$K$2-1,"") -> 0.28591884 | N34: Upside / (Downside) vs current | S34: 0.65376112 | T34: 0.98944661 | Z34: Upside / (Downside) vs current | AE34: -0.31264273 | AF34: -0.3810266
B35: IRR (to Dec-Y-1) | G35: =IFERROR((G33/$K$2)^(1/((DATE(2029-1,12,31)-$K$3)/365.25))-1,"") -> 0.075793306 | H35: =IFERROR((H33/$K$2)^(1/((DATE(2030-1,12,31)-$K$3)/365.25))-1,"") -> 0.080735883 | N35: IRR (to Dec-Y-1) | S35: 0.25184791 | T35: 0.23661149 | Z35: IRR (to Dec-Y-1) | AE35: -0.1541382 | AF35: -0.13765918
B37: Free Cash Flow | C37: =Model!BV264 -> 843.976 | D37: =Model!CA264 -> 703.85523 | E37: =Model!CB264 -> 949.13971 | F37: =Model!CC264 -> 988.09961 | G37: =Model!CD264 -> 1061.1541 | H37: =Model!CE264 -> 1098.1817 | I37: =IFERROR((H37/C37)^(1/5)-1,"n/m") -> 0.054068474 | N37: Free Cash Flow | O37: 843.976 | P37: 726.43385 | Q37: 1036.4882 | R37: 1154.8357 | S37: 1339.689 | T37: 1496.1431 | U37: 0.12131752 | Z37: Free Cash Flow | AA37: 843.976 | AB37: 682.03661 | AC37: 844.89717 | AD37: 782.85442 | AE37: 734.93799 | AF37: 647.65299 | AG37: -0.051576175
B38: FCF % of AGP | C38: =IFERROR(C37/Model!BV133,"") -> 0.30921554 | D38: =IFERROR(D37/Model!CA133,"") -> 0.24525335 | E38: =IFERROR(E37/Model!CB133,"") -> 0.31318486 | F38: =IFERROR(F37/Model!CC133,"") -> 0.30694859 | G38: =IFERROR(G37/Model!CD133,"") -> 0.31139129 | H38: =IFERROR(H37/Model!CE133,"") -> 0.30404514 | J38: =IFERROR(AVERAGE(Model!C266,Model!D266,Model!E266,Model!F266,Model!G266,Model!H266,Model!I266,Model!N266,Model!S266,Model!X266,Model!AC266,Model!AH266,Model!AM266,Model!AR266,Model!AW266,Model!BB266,Model!BG266,Model!BL266,Model!BQ266,Model!BV266),"") -> 0.23275359 | K38: =IFERROR(MIN(Model!C266,Model!D266,Model!E266,Model!F266,Model!G266,Model!H266,Model!I266,Model!N266,Model!S266,Model!X266,Model!AC266,Model!AH266,Model!AM266,Model!AR266,Model!AW266,Model!BB266,Model!BG266,Model!BL266,Model!BQ266,Model!BV266),"") -> 0.0076244675 | L38: =IFERROR(MAX(Model!C266,Model!D266,Model!E266,Model!F266,Model!G266,Model!H266,Model!I266,Model!N266,Model!S266,Model!X266,Model!AC266,Model!AH266,Model!AM266,Model!AR266,Model!AW266,Model!BB266,Model!BG266,Model!BL266,Model!BQ266,Model!BV266),"") -> 0.42348985 | N38: FCF % of AGP | O38: 0.30921554 | P38: 0.24981297 | Q38: 0.32275639 | R38: 0.32238254 | S38: 0.33717325 | T38: 0.3398062 | Z38: FCF % of AGP | AA38: 0.30921554 | AB38: 0.24083972 | AC38: 0.29763317 | AD38: 0.27448618 | AE38: 0.25821985 | AF38: 0.22744587
B39: FCF / share ($) | C39: =IFERROR(C37/C27,"") -> 6.9461902 | D39: =IFERROR(D37/D27,"") -> 5.8787246 | E39: =IFERROR(E37/E27,"") -> 8.2811318 | F39: =IFERROR(F37/F27,"") -> 8.9266759 | G39: =IFERROR(G37/G27,"") -> 9.8769572 | H39: =IFERROR(H37/H27,"") -> 10.524798 | N39: FCF / share ($) | O39: 6.9461902 | P39: 6.0756581 | Q39: 9.2004558 | R39: 10.82257 | S39: 13.17739 | T39: 15.561858 | Z39: FCF / share ($) | AA39: 6.9461902 | AB39: 5.6886708 | AC39: 7.2277333 | AD39: 6.7817938 | AE39: 6.4371481 | AF39: 5.6991193
B40: FCF Yield (on PT) | G40: =IFERROR(G39/G33,"") -> 0.055215866 | H40: =IFERROR(H39/H33,"") -> 0.053888937 | N40: FCF Yield (on PT) | S40: 0.05246335 | T40: 0.05150253 | Z40: FCF Yield (on PT) | AE40: 0.061660974 | AF40: 0.060622686
B41: Adjusted EBITDA — leverage basis | C41: =Model!BV193 -> 936.551 | D41: =Model!CA193 -> 1094.422 | E41: =Model!CB193 -> 1204.0278 | F41: =Model!CC193 -> 1307.9428 | G41: =Model!CD193 -> 1406.6292 | H41: =Model!CE193 -> 1495.3163 | I41: =IFERROR((H41/C41)^(1/5)-1,"n/m") -> 0.098096046 | N41: Adjusted EBITDA — leverage basis | O41: 936.551 | P41: 1133.5841 | Q41: 1377.039 | R41: 1614.9314 | S41: 1866.1568 | T41: 2124.8506 | U41: 0.17803825 | Z41: Adjusted EBITDA — leverage basis | AA41: 936.551 | AB41: 1055.2598 | AC41: 1005.573 | AD41: 959.43274 | AE41: 896.01798 | AF41: 816.99395 | AG41: -0.026944791
B42: Adjusted EBITDA % of revenues | C42: =IFERROR(C41/Model!BV125,"") -> 0.057695107 | D42: =IFERROR(D41/Model!CA125,"") -> 0.058222259 | E42: =IFERROR(E41/Model!CB125,"") -> 0.060991128 | F42: =IFERROR(F41/Model!CC125,"") -> 0.064182428 | G42: =IFERROR(G41/Model!CD125,"") -> 0.066829546 | H42: =IFERROR(H41/Model!CE125,"") -> 0.066947433 | N42: Adjusted EBITDA % of revenues | O42: 0.057695107 | P42: 0.059504451 | Q42: 0.065858033 | R42: 0.071232161 | S42: 0.076018397 | T42: 0.078020541 | Z42: Adjusted EBITDA % of revenues | AA42: 0.057695107 | AB42: 0.056905067 | AC42: 0.054306712 | AD42: 0.05301356 | AE42: 0.050833959 | AF42: 0.046246946
B44: Net Debt | C44: =Model!BV389 -> 928.567 | D44: =Model!CA389 -> 1291.6535 | E44: =Model!CB389 -> 1505.0348 | F44: =Model!CC389 -> 1634.9285 | G44: =Model!CD389 -> 1758.2865 | H44: =Model!CE389 -> 1869.1454 | I44: =IFERROR((H44/C44)^(1/5)-1,"n/m") -> 0.15018041 | N44: Net Debt | O44: 928.567 | P44: 1368.6601 | Q44: 2065.5584 | R44: 2422.3971 | S44: 2799.2351 | T44: 3187.2759 | U44: 0.27973864 | Z44: Net Debt | AA44: 928.567 | AB44: 1213.8869 | AC44: 1005.573 | AD44: 959.43274 | AE44: 896.01798 | AF44: 816.99395 | AG44: -0.025277213
B45: Net Debt / Adjusted EBITDA (x) | C45: =IFERROR(C44/C41,"") -> 0.9914751 | D45: =IFERROR(D44/D41,"") -> 1.1802152 | E45: =IFERROR(E44/E41,"") -> 1.25 | F45: =IFERROR(F44/F41,"") -> 1.25 | G45: =IFERROR(G44/G41,"") -> 1.25 | H45: =IFERROR(H44/H41,"") -> 1.25 | N45: Net Debt / Adjusted EBITDA (x) | O45: 0.9914751 | P45: 1.2073741 | Q45: 1.5 | R45: 1.5 | S45: 1.5 | T45: 1.5 | Z45: Net Debt / Adjusted EBITDA (x) | AA45: 0.9914751 | AB45: 1.1503204 | AC45: 1 | AD45: 1 | AE45: 1 | AF45: 1
B47: ROIC | C47: =Model!BV372 -> 0.2442154 | D47: =Model!CA372 -> 0.27450309 | E47: =Model!CB372 -> 0.29996088 | F47: =Model!CC372 -> 0.31494786 | G47: =Model!CD372 -> 0.32234887 | H47: =Model!CE372 -> 0.32379664 | N47: ROIC | O47: 0.2442154 | P47: 0.28661762 | Q47: 0.32134405 | R47: 0.34359344 | S47: 0.36006826 | T47: 0.37194422 | Z47: ROIC | AA47: 0.2442154 | AB47: 0.26249299 | AC47: 0.2537049 | AD47: 0.24492693 | AE47: 0.22704816 | AF47: 0.20258877
B48: RONTA | C48: =Model!BV383 -> 0.49760768 | D48: =Model!CA383 -> 0.5442441 | E48: =Model!CB383 -> 0.59246664 | F48: =Model!CC383 -> 0.63297041 | G48: =Model!CD383 -> 0.66840501 | H48: =Model!CE383 -> 0.6835234 | N48: RONTA | O48: 0.49760768 | P48: 0.56587459 | Q48: 0.65273636 | R48: 0.72575057 | S48: 0.79493749 | T48: 0.84142541 | Z48: RONTA | AA48: 0.49760768 | AB48: 0.52266636 | AC48: 0.51288253 | AD48: 0.49751507 | AE48: 0.47247036 | AF48: 0.42753018
B50: Implied Market Cap (USDm) | G50: =G33*G27 -> 19218.282 | H50: =H33*H27 -> 20378.612 | N50: Implied Market Cap (USDm) | S50: 25535.713 | T50: 29049.896 | Z50: Implied Market Cap (USDm) | AE50: 11919.014 | AF50: 10683.344
B51: (+) Net Debt | G51: =G44 -> 1758.2865 | H51: =H44 -> 1869.1454 | N51: (+) Net Debt | S51: 2799.2351 | T51: 3187.2759 | Z51: (+) Net Debt | AE51: 896.01798 | AF51: 816.99395
B52: Implied Enterprise Value (USDm) | G52: =G50+G51 -> 20976.569 | H52: =H50+H51 -> 22247.758 | N52: Implied Enterprise Value (USDm) | S52: 28334.948 | T52: 32237.172 | Z52: Implied Enterprise Value (USDm) | AE52: 12815.032 | AF52: 11500.338
B53: Implied EV / Adjusted EBITDA (x) | G53: =IFERROR(G52/G41,"") -> 14.912649 | H53: =IFERROR(H52/H41,"") -> 14.878295 | N53: Implied EV / Adjusted EBITDA (x) | S53: 15.183584 | T53: 15.1715 | Z53: Implied EV / Adjusted EBITDA (x) | AE53: 14.302204 | AF53: 14.076405

Sheet DCF
B2: DCF VALUATION — C.H. ROBINSON WORLDWIDE (CHRW)
B4: 1. WACC BUILD
B5: Risk-free rate (US 10Y govt) | C5: 0.0425 | D5: Assumption (~US 10Y Treasury yield); update to market
B6: Equity risk premium | C6: 0.05 | D6: US implied ERP ~4.5–5.5% (Damodaran)
B7: Levered beta | C7: 1 | D7: 3PL / brokerage peers (EXPD, LSTR, RXO, JBHT) ~0.9–1.2; asset-light, freight-cycle exposed
B8: Cost of equity | C8: =C5+C7*C6 -> 0.0925
B9: Pre-tax cost of debt | C9: 0.05 | D9: Investment grade (BBB+/Baa1); 4.20% 2028 / 4.60% 2033 notes; marginal cost ~5.0% (RXO acquisition financing)
B10: Tax rate | C10: 0.2 | D10: Model 2027E+ effective tax rate
B11: After-tax cost of debt | C11: =C9*(1-C10) -> 0.04
B12: Target D/V | C12: 0.1 | D12: Net debt ~$1.4bn at YE2026E (standalone) vs ~$17.5bn market cap ($151.88 × ~115m shares); ~1.2x net debt / adjusted EBITDA
B13: WACC | C13: =C8*(1-C12)+C11*C12 -> 0.08725
B15: Valuation date (live) | C15: =TODAY() -> 46300 | D15: Periods = (Dec-31-Year − today) / 365.25; cash flows assumed at year-end
B16: 2. UNLEVERED FREE CASH FLOW BUILD (USDm)
D17: 2026E | E17: 2027E | F17: 2028E | G17: 2029E | H17: 2030E | I17: 2031E | J17: 2032E | K17: 2033E | L17: 2034E | M17: 2035E | N17: Terminal
B18: Adjusted EBIT (Model; = adjusted income from operations) | D18: =Model!CA181 -> 1002 | E18: =Model!CB181 -> 1097.9566 | F18: =Model!CC181 -> 1194.1492 | G18: =Model!CD181 -> 1283.4543 | H18: =Model!CE181 -> 1361.7111 | I18: =H18*(1+I$31) -> 1429.7966 | J18: =I18*(1+J$31) -> 1495.9247 | K18: =J18*(1+K$31) -> 1559.5015 | L18: =K18*(1+L$31) -> 1619.9322 | M18: =L18*(1+M$31) -> 1676.6298
B19: y/y % | E19: =IFERROR(E18/D18-1,"") -> 0.095765098 | F19: =IFERROR(F18/E18-1,"") -> 0.0876105 | G19: =IFERROR(G18/F18-1,"") -> 0.074785589 | H19: =IFERROR(H18/G18-1,"") -> 0.06097356 | I19: =IFERROR(I18/H18-1,"") -> 0.05 | J19: =IFERROR(J18/I18-1,"") -> 0.04625 | K19: =IFERROR(K18/J18-1,"") -> 0.0425 | L19: =IFERROR(L18/K18-1,"") -> 0.03875 | M19: =IFERROR(M18/L18-1,"") -> 0.035
B20: (−) Restructuring & other adjusting items (cash; added back in adjusted EBIT) | D20: =-Model!CA180 -> -54.249 | E20: =-Model!CB180 -> 0 | F20: =-Model!CC180 -> 0 | G20: =-Model!CD180 -> 0 | H20: =-Model!CE180 -> 0 | I20: =H20*(1+I$31) -> 0 | J20: =I20*(1+J$31) -> 0 | K20: =J20*(1+K$31) -> 0 | L20: =K20*(1+L$31) -> 0 | M20: =L20*(1+M$31) -> 0
B21: × (1 − tax rate) | D21: =1-$C$10 -> 0.8 | E21: =1-$C$10 -> 0.8 | F21: =1-$C$10 -> 0.8 | G21: =1-$C$10 -> 0.8 | H21: =1-$C$10 -> 0.8 | I21: =1-$C$10 -> 0.8 | J21: =1-$C$10 -> 0.8 | K21: =1-$C$10 -> 0.8 | ... M21: =1-$C$10 -> 0.8
B22: NOPAT = (Adjusted EBIT − adjusting items) × (1 − t) | D22: =(D18+D20)*D21 -> 758.2008 | E22: =(E18+E20)*E21 -> 878.3653 | F22: =(F18+F20)*F21 -> 955.31933 | G22: =(G18+G20)*G21 -> 1026.7634 | H22: =(H18+H20)*H21 -> 1089.3689 | I22: =(I18+I20)*I21 -> 1143.8373 | J22: =(J18+J20)*J21 -> 1196.7398 | K22: =(K18+K20)*K21 -> 1247.6012 | ... M22: =(M18+M20)*M21 -> 1341.3039
B23: plus depreciation & amortization (incl. software) | D23: =Model!CA152 -> 92.421984 | E23: =Model!CB152 -> 106.07119 | F23: =Model!CC152 -> 113.79366 | G23: =Model!CD152 -> 123.17492 | H23: =Model!CE152 -> 133.60523 | I23: =H23*(1+I$31) -> 140.28549 | J23: =I23*(1+J$31) -> 146.77369 | K23: =J23*(1+K$31) -> 153.01157 | L23: =K23*(1+L$31) -> 158.94077 | M23: =L23*(1+M$31) -> 164.5037
B24: − Capex (PP&E + software) and acquisitions (M&A lever, 2027E+) | D24: =D29 -> -70 | E24: =E29+Model!CB248 -> -75.765133 | F24: =F29+Model!CC248 -> -180.47762 | G24: =G29+Model!CD248 -> -235.19459 | H24: =H29+Model!CE248 -> -240.29759 | I24: =I29 -> -94.812469 | J24: =J29 -> -99.197546 | K24: =K29 -> -103.41344 | L24: =L29 -> -107.42071 | M24: =M29 -> -111.18044
B25: − Δ Working capital (CF statement) | D25: =Model!CA244 -> -139.05298 | E25: =Model!CB244 -> -1.8842938 | F25: =Model!CC244 -> -38.311607 | G25: =Model!CD244 -> -39.973856 | H25: =Model!CE244 -> -72.413611 | I25: =H25*(1+I$31) -> -76.034292 | J25: =I25*(1+J$31) -> -79.550878 | K25: =J25*(1+K$31) -> -82.93179 | L25: =K25*(1+L$31) -> -86.145397 | M25: =L25*(1+M$31) -> -89.160486
B26: Unlevered FCF | D26: =D22+D23+D24+D25 -> 641.56981 | E26: =E22+E23+E24+E25 -> 906.78706 | F26: =F22+F23+F24+F25 -> 850.32376 | G26: =G22+G23+G24+G25 -> 874.76992 | H26: =H22+H23+H24+H25 -> 910.26289 | I26: =I22+I23+I24+I25 -> 1113.276 | J26: =J22+J23+J24+J25 -> 1164.7651 | K26: =K22+K23+K24+K25 -> 1214.2676 | ... M26: =M22+M23+M24+M25 -> 1305.4667 | N26: =M26*(1+$C$32) -> 1344.6306
B27: y/y % | E27: =IFERROR(E26/D26-1,"") -> 0.413388 | F27: =IFERROR(F26/E26-1,"") -> -0.062267427 | G27: =IFERROR(G26/F26-1,"") -> 0.028749234 | H27: =IFERROR(H26/G26-1,"") -> 0.040574062 | I27: =IFERROR(I26/H26-1,"") -> 0.22302694 | J27: =IFERROR(J26/I26-1,"") -> 0.04625 | K27: =IFERROR(K26/J26-1,"") -> 0.0425 | L27: =IFERROR(L26/K26-1,"") -> 0.03875 | M27: =IFERROR(M26/L26-1,"") -> 0.035
B28: Terminal Value (Gordon Growth) | N28: =N26/($C$13-$C$32) -> 23486.998
B29: memo: capex (PP&E + software) — fade years carry no new acquisitions | D29: =Model!CA246+Model!CA247 -> -70 | E29: =Model!CB246+Model!CB247 -> -75.765133 | F29: =Model!CC246+Model!CC247 -> -80.477615 | G29: =Model!CD246+Model!CD247 -> -85.194585 | H29: =Model!CE246+Model!CE247 -> -90.29759 | I29: =H29*(1+I$31) -> -94.812469 | J29: =I29*(1+J$31) -> -99.197546 | K29: =J29*(1+K$31) -> -103.41344 | L29: =K29*(1+L$31) -> -107.42071 | M29: =L29*(1+M$31) -> -111.18044
B31: Fade-period growth (2031E–35E) | I31: 0.05 | J31: =I31+($M$31-$I$31)/(COLUMNS($I$31:$M$31)-1) -> 0.04625 | K31: =J31+($M$31-$I$31)/(COLUMNS($I$31:$M$31)-1) -> 0.0425 | L31: =K31+($M$31-$I$31)/(COLUMNS($I$31:$M$31)-1) -> 0.03875 | M31: 0.035
B32: Terminal growth rate | C32: 0.03
B34: Discount period (years) | D34: =(DATE(2026,12,31)-$C$15)/365.25 -> 0.23819302 | E34: =(DATE(2027,12,31)-$C$15)/365.25 -> 1.2375086 | F34: =(DATE(2028,12,31)-$C$15)/365.25 -> 2.2395619 | G34: =(DATE(2029,12,31)-$C$15)/365.25 -> 3.2388775 | H34: =(DATE(2030,12,31)-$C$15)/365.25 -> 4.238193 | I34: =(DATE(2031,12,31)-$C$15)/365.25 -> 5.2375086 | J34: =(DATE(2032,12,31)-$C$15)/365.25 -> 6.2395619 | K34: =(DATE(2033,12,31)-$C$15)/365.25 -> 7.2388775 | L34: =(DATE(2034,12,31)-$C$15)/365.25 -> 8.238193 | M34: =(DATE(2035,12,31)-$C$15)/365.25 -> 9.2375086 | N34: =M34 -> 9.2375086
B35: Discount factor | D35: =1/(1+$C$13)^D34 -> 0.98027197 | E35: =1/(1+$C$13)^E34 -> 0.90165841 | F35: =1/(1+$C$13)^F34 -> 0.82915939 | G35: =1/(1+$C$13)^G34 -> 0.76266439 | H35: =1/(1+$C$13)^H34 -> 0.70150201 | I35: =1/(1+$C$13)^I34 -> 0.64524459 | J35: =1/(1+$C$13)^J34 -> 0.59336286 | K35: =1/(1+$C$13)^K34 -> 0.54577772 | ... N35: =1/(1+$C$13)^N34 -> 0.46174979
B36: PV of UFCF | D36: =D26*D35 -> 628.9129 | E36: =E26*E35 -> 817.61218 | F36: =F26*F35 -> 705.05393 | G36: =G26*G35 -> 667.15587 | H36: =H26*H35 -> 638.55125 | I36: =I26*I35 -> 718.33534 | J36: =J26*J35 -> 691.12832 | K36: =K26*K35 -> 662.72019 | ... M36: =M26*M35 -> 602.79895 | N36: =N28*N35 -> 10845.116
D37: CHRW expenses stock-based compensation (not added back). Adjusted EBIT adds back restructuring; the cash cost is deducted in row 20. Acquisition spend from the Model M&A lever is deducted 2027E–30E; the fade period and terminal value assume no new acquisitions. Standalone CHRW — the RXO acquisition (announced 5-Oct-26) is not in this DCF; see RXO PF tab.
B39: Implied ROIC & incremental ROIC (USDm) | D39: =D17 -> 2026E | E39: =E17 -> 2027E | F39: =F17 -> 2028E | G39: =G17 -> 2029E | H39: =H17 -> 2030E | I39: =I17 -> 2031E | J39: =J17 -> 2032E | K39: =K17 -> 2033E | ... M39: =M17 -> 2035E
B40: NOPAT (row 22) | D40: =D22 -> 758.2008 | E40: =E22 -> 878.3653 | F40: =F22 -> 955.31933 | G40: =G22 -> 1026.7634 | H40: =H22 -> 1089.3689 | I40: =I22 -> 1143.8373 | J40: =J22 -> 1196.7398 | K40: =K22 -> 1247.6012 | ... M40: =M22 -> 1341.3039
B41: Net investment = NOPAT − UFCF | D41: =D40-D26 -> 116.63099 | E41: =E40-E26 -> -28.421759 | F41: =F40-F26 -> 104.99556 | G41: =G40-G26 -> 151.99352 | H41: =H40-H26 -> 179.10598 | I41: =I40-I26 -> 30.561274 | J41: =J40-J26 -> 31.974733 | K41: =K40-K26 -> 33.333659 | ... M41: =M40-M26 -> 35.837225
B42: Opening invested capital | D42: =Model!BV369 -> 2774.214 | E42: =D43 -> 2890.845 | F42: =E43 -> 2862.4232 | G42: =F43 -> 2967.4188 | H42: =G43 -> 3119.4123 | I42: =H43 -> 3298.5183 | J42: =I43 -> 3329.0796 | K42: =J43 -> 3361.0543 | L42: =K43 -> 3394.388 | M42: =L43 -> 3429.0133
B43: Closing invested capital | D43: =D42+D41 -> 2890.845 | E43: =E42+E41 -> 2862.4232 | F43: =F42+F41 -> 2967.4188 | G43: =G42+G41 -> 3119.4123 | H43: =H42+H41 -> 3298.5183 | I43: =I42+I41 -> 3329.0796 | J43: =J42+J41 -> 3361.0543 | K43: =K42+K41 -> 3394.388 | ... M43: =M42+M41 -> 3464.8505
B44: Implied ROIC = NOPAT / opening IC | D44: =IFERROR(D40/D42,"") -> 0.27330292 | E44: =IFERROR(E40/E42,"") -> 0.30384379 | F44: =IFERROR(F40/F42,"") -> 0.33374496 | G44: =IFERROR(G40/G42,"") -> 0.34601231 | H44: =IFERROR(H40/H42,"") -> 0.34922247 | I44: =IFERROR(I40/I42,"") -> 0.34677307 | J44: =IFERROR(J40/J42,"") -> 0.35948068 | K44: =IFERROR(K40/K42,"") -> 0.37119342 | ... M44: =IFERROR(M40/M42,"") -> 0.39116322
B45: Reinvestment rate = net inv. / NOPAT | D45: =IFERROR(D41/D40,"") -> 0.153826 | E45: =IFERROR(E41/E40,"") -> -0.032357562 | F45: =IFERROR(F41/F40,"") -> 0.10990625 | G45: =IFERROR(G41/G40,"") -> 0.14803168 | H45: =IFERROR(H41/H40,"") -> 0.16441261 | I45: =IFERROR(I41/I40,"") -> 0.0267182 | J45: =IFERROR(J41/J40,"") -> 0.0267182 | K45: =IFERROR(K41/K40,"") -> 0.0267182 | ... M45: =IFERROR(M41/M40,"") -> 0.0267182
B46: Incremental ROIC = Δ NOPAT / prior-yr net inv. | E46: =IFERROR((E40-D40)/D41,"") -> 1.0302965 | F46: =IFERROR((F40-E40)/E41,"") -> -2.7075742 | G46: =IFERROR((G40-F40)/F41,"") -> 0.68044894 | H46: =IFERROR((H40-G40)/G41,"") -> 0.41189533 | I46: =IFERROR((I40-H40)/H41,"") -> 0.30411293 | J46: =IFERROR((J40-I40)/I41,"") -> 1.7310298 | K46: =IFERROR((K40-J40)/J41,"") -> 1.590676 | L46: =IFERROR((L40-K40)/K41,"") -> 1.4503223 | M46: =IFERROR((M40-L40)/L41,"") -> 1.3099685
B47: Cumulative incremental ROIC 2026E–35E | C47: =IFERROR((M40-D40)/SUM(D41:L41),"") -> 0.89050657
D48: Opening IC = Model 2025A book invested capital (equity + net debt), rolled forward with DCF net investment (capex + M&A − D&A + ΔWC).
B49: 3. VALUATION SUMMARY
B50: Sum of PV (explicit + fade) | C50: =SUM(D36:M36) -> 6765.4628
B51: PV of Terminal Value | C51: =N36 -> 10845.116
B52: Enterprise Value | C52: =C50+C51 -> 17610.579
B53: Less: net debt (Model 2026E YE, standalone) | C53: =Model!CA389 -> 1291.6535
B54: Less: non-controlling interests (none) | C54: 0
B55: Equity Value | C55: =C52-C53-C54 -> 16318.926
B56: Diluted shares (m, Model 2026E period end) | C56: =Model!CA395 -> 116.86696
B57: Implied share price ($) | C57: =C55/C56 -> 139.63677
B58: Current share price ($) | C58: =Model!CA394 -> 151.88
B59: Implied upside / (downside) | C59: =C57/C58-1 -> -0.080611182
B60: Required discount to DCF value for target IRR (discount closes over N years) | C60: =1-((1+C13)/(1+F60))^F61 -> 0.15492602 | E60: Target IRR | F60: 0.15
B61: Max entry price for target IRR ($) — % vs. current share price | C61: =C57*(1-C60) -> 118.0034 | D61: =C61/C58-1 -> -0.22304844 | E61: Years for discount to close | F61: 3
B64: 4. SENSITIVITY: IMPLIED PRICE ($) — WACC × Terminal Growth
B65: WACC step (across) | C65: 0.005
B66: Terminal growth step (down) | C66: 0.005
B67: g (down) / WACC | D67: =E67-$C$65 -> 0.07725 | E67: =F67-$C$65 -> 0.08225 | F67: =$C$13 -> 0.08725 | G67: =F67+$C$65 -> 0.09225 | H67: =G67+$C$65 -> 0.09725
B68: =B69-$C$66 -> 0.02 | D68: =IFERROR((SUMPRODUCT($D$26:$M$26/(1+D$67)^$D$34:$M$34)+($M$26*(1+$B68)/(D$67-$B68))/(1+D$67)^$M$34-$C$53-$C$54)/$C$56,"") -> 149.47054 | E68: =IFERROR((SUMPRODUCT($D$26:$M$26/(1+E$67)^$D$34:$M$34)+($M$26*(1+$B68)/(E$67-$B68))/(1+E$67)^$M$34-$C$53-$C$54)/$C$56,"") -> 136.28221 | F68: =IFERROR((SUMPRODUCT($D$26:$M$26/(1+F$67)^$D$34:$M$34)+($M$26*(1+$B68)/(F$67-$B68))/(1+F$67)^$M$34-$C$53-$C$54)/$C$56,"") -> 125.0707 | G68: =IFERROR((SUMPRODUCT($D$26:$M$26/(1+G$67)^$D$34:$M$34)+($M$26*(1+$B68)/(G$67-$B68))/(1+G$67)^$M$34-$C$53-$C$54)/$C$56,"") -> 115.42512 | H68: =IFERROR((SUMPRODUCT($D$26:$M$26/(1+H$67)^$D$34:$M$34)+($M$26*(1+$B68)/(H$67-$B68))/(1+H$67)^$M$34-$C$53-$C$54)/$C$56,"") -> 107.04094
B69: =B70-$C$66 -> 0.025 | D69: =IFERROR((SUMPRODUCT($D$26:$M$26/(1+D$67)^$D$34:$M$34)+($M$26*(1+$B69)/(D$67-$B69))/(1+D$67)^$M$34-$C$53-$C$54)/$C$56,"") -> 159.58575 | E69: =IFERROR((SUMPRODUCT($D$26:$M$26/(1+E$67)^$D$34:$M$34)+($M$26*(1+$B69)/(E$67-$B69))/(1+E$67)^$M$34-$C$53-$C$54)/$C$56,"") -> 144.45471 | F69: =IFERROR((SUMPRODUCT($D$26:$M$26/(1+F$67)^$D$34:$M$34)+($M$26*(1+$B69)/(F$67-$B69))/(1+F$67)^$M$34-$C$53-$C$54)/$C$56,"") -> 131.76876 | G69: =IFERROR((SUMPRODUCT($D$26:$M$26/(1+G$67)^$D$34:$M$34)+($M$26*(1+$B69)/(G$67-$B69))/(1+G$67)^$M$34-$C$53-$C$54)/$C$56,"") -> 120.98206 | H69: =IFERROR((SUMPRODUCT($D$26:$M$26/(1+H$67)^$D$34:$M$34)+($M$26*(1+$B69)/(H$67-$B69))/(1+H$67)^$M$34-$C$53-$C$54)/$C$56,"") -> 111.69991
B70: =$C$32 -> 0.03 | D70: =IFERROR((SUMPRODUCT($D$26:$M$26/(1+D$67)^$D$34:$M$34)+($M$26*(1+$B70)/(D$67-$B70))/(1+D$67)^$M$34-$C$53-$C$54)/$C$56,"") -> 171.84174 | E70: =IFERROR((SUMPRODUCT($D$26:$M$26/(1+E$67)^$D$34:$M$34)+($M$26*(1+$B70)/(E$67-$B70))/(1+E$67)^$M$34-$C$53-$C$54)/$C$56,"") -> 154.19134 | F70: =IFERROR((SUMPRODUCT($D$26:$M$26/(1+F$67)^$D$34:$M$34)+($M$26*(1+$B70)/(F$67-$B70))/(1+F$67)^$M$34-$C$53-$C$54)/$C$56,"") -> 139.63677 | G70: =IFERROR((SUMPRODUCT($D$26:$M$26/(1+G$67)^$D$34:$M$34)+($M$26*(1+$B70)/(G$67-$B70))/(1+G$67)^$M$34-$C$53-$C$54)/$C$56,"") -> 127.43168 | H70: =IFERROR((SUMPRODUCT($D$26:$M$26/(1+H$67)^$D$34:$M$34)+($M$26*(1+$B70)/(H$67-$B70))/(1+H$67)^$M$34-$C$53-$C$54)/$C$56,"") -> 117.05167
B71: =B70+$C$66 -> 0.035 | D71: =IFERROR((SUMPRODUCT($D$26:$M$26/(1+D$67)^$D$34:$M$34)+($M$26*(1+$B71)/(D$67-$B71))/(1+D$67)^$M$34-$C$53-$C$54)/$C$56,"") -> 186.99856 | E71: =IFERROR((SUMPRODUCT($D$26:$M$26/(1+E$67)^$D$34:$M$34)+($M$26*(1+$B71)/(E$67-$B71))/(1+E$67)^$M$34-$C$53-$C$54)/$C$56,"") -> 165.98862 | F71: =IFERROR((SUMPRODUCT($D$26:$M$26/(1+F$67)^$D$34:$M$34)+($M$26*(1+$B71)/(F$67-$B71))/(1+F$67)^$M$34-$C$53-$C$54)/$C$56,"") -> 149.01063 | G71: =IFERROR((SUMPRODUCT($D$26:$M$26/(1+G$67)^$D$34:$M$34)+($M$26*(1+$B71)/(G$67-$B71))/(1+G$67)^$M$34-$C$53-$C$54)/$C$56,"") -> 135.00787 | H71: =IFERROR((SUMPRODUCT($D$26:$M$26/(1+H$67)^$D$34:$M$34)+($M$26*(1+$B71)/(H$67-$B71))/(1+H$67)^$M$34-$C$53-$C$54)/$C$56,"") -> 123.26314
B72: =B71+$C$66 -> 0.04 | D72: =IFERROR((SUMPRODUCT($D$26:$M$26/(1+D$67)^$D$34:$M$34)+($M$26*(1+$B72)/(D$67-$B72))/(1+D$67)^$M$34-$C$53-$C$54)/$C$56,"") -> 206.22432 | E72: =IFERROR((SUMPRODUCT($D$26:$M$26/(1+E$67)^$D$34:$M$34)+($M$26*(1+$B72)/(E$67-$B72))/(1+E$67)^$M$34-$C$53-$C$54)/$C$56,"") -> 180.57816 | F72: =IFERROR((SUMPRODUCT($D$26:$M$26/(1+F$67)^$D$34:$M$34)+($M$26*(1+$B72)/(F$67-$B72))/(1+F$67)^$M$34-$C$53-$C$54)/$C$56,"") -> 160.36837 | G72: =IFERROR((SUMPRODUCT($D$26:$M$26/(1+G$67)^$D$34:$M$34)+($M$26*(1+$B72)/(G$67-$B72))/(1+G$67)^$M$34-$C$53-$C$54)/$C$56,"") -> 144.03405 | H72: =IFERROR((SUMPRODUCT($D$26:$M$26/(1+H$67)^$D$34:$M$34)+($M$26*(1+$B72)/(H$67-$B72))/(1+H$67)^$M$34-$C$53-$C$54)/$C$56,"") -> 130.55959
B75: 5. REVERSE DCF
B76: To solve for the market-implied path: Data ▸ What-If Analysis ▸ Goal Seek — set C57 (implied price) to the current price (C58) by changing C32 (terminal growth) or the Model scenario levers (NAST volume / AGP per shipment, GF volume / yield, Lean AI productivity, other SG&A % of AGP, M&A spend).
B78: 6. MAUBOUSSIN EV / NOPAT — TWO-STAGE FRAMEWORK
B79: EV/NOPAT = 1/r + [g × (1 − r/ROIIC) / (r × (r − g))] × [1 − ((1+g)/(1+r))^N]
B80: Formula source: Mauboussin & Rappaport, "Expectations Investing" (2021); Counterpoint Global, "What Does a Price-Earnings Multiple Mean?" (2020).
B82: Input | C82: Value | D82: Rationale (C.H. Robinson characteristics)
B83: r (Cost of capital / WACC) | C83: =$C$13 -> 0.08725 | D83: Linked from Section 1 WACC build
B84: g (NOPAT growth, Stage 1) | C84: 0.08 | D84: Model adjusted EBIT CAGR 2026–30E (~9%): NAST share gains + AGP-per-shipment recovery, Lean AI operating leverage; buybacks add to EPS, not NOPAT
B85: ROIIC (Return on incremental invested capital) | C85: 0.4 | D85: Asset-light brokerage: capex ~2.5% of AGP and working capital the main investment; ROIC 20–33% through the cycle (2019–25)
B86: N (Years of value creation / CAP) | C86: 12 | D86: Scale network (450k carriers, 37m shipments), proprietary data & AI agents vs. digital-broker disruption risk and cyclical freight markets
B88: Calculation | C88: Value
B89: Steady-state component: 1 / r | C89: =1/C83 -> 11.461318
B90: Value-creation factor: 1 − r / ROIIC | C90: =1-C83/C85 -> 0.781875
B91: Growth multiplier: g × (1 − r/ROIIC) / (r × (r − g)) | C91: =C84*C90/(C83*(C83-C84)) -> 98.88351
B92: Time decay: 1 − ((1+g)/(1+r))^N | C92: =1-((1+C84)/(1+C83))^C86 -> 0.077147974
B93: PVGO component (growth value) | C93: =C91*C92 -> 7.6286625
B94: Mauboussin EV / NOPAT (steady-state + PVGO) | C94: =C89+C93 -> 19.089981
B96: VALUATION — Applied to 2028E NOPAT | C96: USDm
B97: 2028E Adjusted EBIT (Model) | C97: =Model!CC181 -> 1194.1492
B98: (−) 2028E restructuring & other adjusting items | C98: =-Model!CC180 -> 0
B99: Tax rate (from WACC build) | C99: =$C$10 -> 0.2
B100: 2028E NOPAT = (Adj. EBIT − adjusting items) × (1 − t) | C100: =(C97+C98)*(1-C99) -> 955.31933
B101: × Mauboussin EV/NOPAT multiple | C101: =C94 -> 19.089981
B102: Implied Enterprise Value (2028E basis) | C102: =C100*C101 -> 18237.027
B103: Less: YE2027 net debt (Model) | C103: =Model!CB389 -> 1505.0348
B104: Implied Equity Value | C104: =C102-C103 -> 16731.993
B105: Diluted shares 2028E (m, Model) | C105: =Model!CC395 -> 109.01881
B106: Implied share price 2028 ($) | C106: =C104/C105 -> 153.47804
B108: Current share price ($) | C108: =C58 -> 151.88
B109: Implied upside / (downside) | C109: =C106/C108-1 -> 0.010521706
B111: MARKET-IMPLIED EV/NOPAT TODAY | C111: USDm
B112: Current market cap (spot × diluted shares) | C112: =C58*C56 -> 17749.754
B113: Plus: YE2026 net debt | C113: =C53+C54 -> 1291.6535
B114: Implied Enterprise Value (today) | C114: =C112+C113 -> 19041.408
B115: CHRW's market-implied EV/NOPAT (on 2028E NOPAT) | C115: =C114/C100 -> 19.931982
B117: Multiple gap (Mauboussin − Market) | C117: =C94-C115 -> -0.84200183
...

Sheet Charts
B2: C.H. Robinson — Historical Operating Performance (2006–2025)
B3: All historicals · USDm · Linked to Model. Volume / price = NAST truckload + LTL volume and implied AGP per shipment y/y (annual = average of quarters; disclosed from 2013 / segment AGP from 2015). Margins and returns on adjusted gross profit (company KPI basis).
C7: 2006 | D7: 2007 | E7: 2008 | F7: 2009 | G7: 2010 | H7: 2011 | I7: 2012 | J7: 2013 | K7: 2014 | L7: 2015 | M7: 2016 | N7: 2017 | O7: 2018 | P7: 2019 | Q7: 2020 | R7: 2021 | S7: 2022 | T7: 2023 | U7: 2024 | V7: 2025
B8: NAST volume % | C8: =IFERROR(Model!C11+0,0) -> 0 | D8: =IFERROR(Model!D11+0,0) -> 0 | E8: =IFERROR(Model!E11+0,0) -> 0 | F8: =IFERROR(Model!F11+0,0) -> 0 | G8: =IFERROR(Model!G11+0,0) -> 0 | H8: =IFERROR(Model!H11+0,0) -> 0 | I8: =IFERROR(Model!I11+0,0) -> 0 | J8: =IFERROR(Model!N11+0,0) -> 0.090714896 | K8: =IFERROR(Model!S11+0,0) -> 0.033142347 | L8: =IFERROR(Model!X11+0,0) -> 0.11831953 | M8: =IFERROR(Model!AC11+0,0) -> 0.060143245 | N8: =IFERROR(Model!AH11+0,0) -> 0.049243186 | O8: =IFERROR(Model!AM11+0,0) -> -0.0018982168 | P8: =IFERROR(Model!AR11+0,0) -> -0.0021117113 | Q8: =IFERROR(Model!AW11+0,0) -> 0.029673196 | R8: =IFERROR(Model!BB11+0,0) -> 0.045497736 | S8: =IFERROR(Model!BG11+0,0) -> -0.002411853 | T8: =IFERROR(Model!BL11+0,0) -> -0.02875 | U8: =IFERROR(Model!BQ11+0,0) -> 0.0013315058 | V8: =IFERROR(Model!BV11+0,0) -> 0.01
B9: NAST AGP per shipment % | C9: =IFERROR(Model!C12+0,0) -> 0 | D9: =IFERROR(Model!D12+0,0) -> 0 | E9: =IFERROR(Model!E12+0,0) -> 0 | F9: =IFERROR(Model!F12+0,0) -> 0 | G9: =IFERROR(Model!G12+0,0) -> 0 | H9: =IFERROR(Model!H12+0,0) -> 0 | I9: =IFERROR(Model!I12+0,0) -> 0 | J9: =IFERROR(Model!N12+0,0) -> 0 | K9: =IFERROR(Model!S12+0,0) -> 0 | L9: =IFERROR(Model!X12+0,0) -> 0.035529255 | M9: =IFERROR(Model!AC12+0,0) -> -0.081180379 | N9: =IFERROR(Model!AH12+0,0) -> -0.046488814 | O9: =IFERROR(Model!AM12+0,0) -> 0.1749667 | P9: =IFERROR(Model!AR12+0,0) -> 0.0070867043 | Q9: =IFERROR(Model!AW12+0,0) -> -0.18026217 | R9: =IFERROR(Model!BB12+0,0) -> 0.13040528 | S9: =IFERROR(Model!BG12+0,0) -> 0.22814984 | T9: =IFERROR(Model!BL12+0,0) -> -0.25295637 | U9: =IFERROR(Model!BQ12+0,0) -> 0.028332987 | V9: =IFERROR(Model!BV12+0,0) -> 0.029393005
C11: =C7 -> 2006 | D11: =D7 -> 2007 | E11: =E7 -> 2008 | F11: =F7 -> 2009 | G11: =G7 -> 2010 | H11: =H7 -> 2011 | I11: =I7 -> 2012 | J11: =J7 -> 2013 | ... V11: =V7 -> 2025
B12: Adjusted income from operations | C12: =Model!C181 -> 417.845 | D12: =Model!D181 -> 509.684 | E12: =Model!E181 -> 571.586 | F12: =Model!F181 -> 584.811 | G12: =Model!G181 -> 622.86 | H12: =Model!H181 -> 692.73 | I12: =Model!I181 -> 675.32 | J12: =Model!N181 -> 682.65 | K12: =Model!S181 -> 748.418 | L12: =Model!X181 -> 858.31 | M12: =Model!AC181 -> 837.531 | N12: =Model!AH181 -> 775.119 | O12: =Model!AM181 -> 912.083 | P12: =Model!AR181 -> 784.176 | Q12: =Model!AW181 -> 673.268 | R12: =Model!BB181 -> 1082.108 | S12: =Model!BG181 -> 1278.17 | T12: =Model!BL181 -> 552.648 | U12: =Model!BQ181 -> 759.349 | V12: =Model!BV181 -> 833.733
B13: Income from operations (GAAP) | C13: =Model!C139 -> 417.845 | D13: =Model!D139 -> 509.684 | E13: =Model!E139 -> 571.586 | F13: =Model!F139 -> 584.811 | G13: =Model!G139 -> 622.86 | H13: =Model!H139 -> 692.73 | I13: =Model!I139 -> 675.32 | J13: =Model!N139 -> 682.65 | K13: =Model!S139 -> 748.418 | L13: =Model!X139 -> 858.31 | M13: =Model!AC139 -> 837.531 | N13: =Model!AH139 -> 775.119 | O13: =Model!AM139 -> 912.083 | P13: =Model!AR139 -> 789.976 | Q13: =Model!AW139 -> 673.268 | R13: =Model!BB139 -> 1082.108 | S13: =Model!BG139 -> 1266.782 | T13: =Model!BL139 -> 514.607 | U13: =Model!BQ139 -> 669.141 | V13: =Model!BV139 -> 794.961
B14: Adj. operating margin % of AGP | C14: =Model!C182 -> 0.38598431 | D14: =Model!D182 -> 0.40978696 | E14: =Model!E182 -> 0.4157101 | F14: =Model!F182 -> 0.42317536 | G14: =Model!G182 -> 0.42429791 | H14: =Model!H182 -> 0.42429584 | I14: =Model!I182 -> 0.39318316 | J14: =Model!N182 -> 0.37179449 | K14: =Model!S182 -> 0.37278273 | L14: =Model!X182 -> 0.37836349 | M14: =Model!AC182 -> 0.36773686 | N14: =Model!AH182 -> 0.32732375 | O14: =Model!AM182 -> 0.33715481 | P14: =Model!AR182 -> 0.30320263 | Q14: =Model!AW182 -> 0.27910293 | R14: =Model!BB182 -> 0.34329868 | S14: =Model!BG182 -> 0.35572141 | T14: =Model!BL182 -> 0.21218087 | U14: =Model!BQ182 -> 0.27462754 | V14: =Model!BV182 -> 0.30546272
B15: GAAP op. margin % of AGP | C15: =Model!C231 -> 0.38598431 | D15: =Model!D231 -> 0.40978696 | E15: =Model!E231 -> 0.4157101 | F15: =Model!F231 -> 0.42317536 | G15: =Model!G231 -> 0.42429791 | H15: =Model!H231 -> 0.42429584 | I15: =Model!I231 -> 0.39318316 | J15: =Model!N231 -> 0.37179449 | K15: =Model!S231 -> 0.37278273 | L15: =Model!X231 -> 0.37836349 | M15: =Model!AC231 -> 0.36773686 | N15: =Model!AH231 -> 0.32732375 | O15: =Model!AM231 -> 0.33715481 | P15: =Model!AR231 -> 0.30544521 | Q15: =Model!AW231 -> 0.27910293 | R15: =Model!BB231 -> 0.34329868 | S15: =Model!BG231 -> 0.35255207 | T15: =Model!BL231 -> 0.1975756 | U15: =Model!BQ231 -> 0.24200275 | V15: =Model!BV231 -> 0.29125745
C17: =C7 -> 2006 | D17: =D7 -> 2007 | E17: =E7 -> 2008 | F17: =F7 -> 2009 | G17: =G7 -> 2010 | H17: =H7 -> 2011 | I17: =I7 -> 2012 | J17: =J7 -> 2013 | ... V17: =V7 -> 2025
B18: ROIC | C18: =IFERROR(Model!C372+0,NA()) -> 0.55184624 | D18: =IFERROR(Model!D372+0,NA()) -> 0.53733272 | E18: =IFERROR(Model!E372+0,NA()) -> 0.58204953 | F18: =IFERROR(Model!F372+0,NA()) -> 0.51772488 | G18: =IFERROR(Model!G372+0,NA()) -> 0.48514175 | H18: =IFERROR(Model!H372+0,NA()) -> 0.49197887 | I18: =IFERROR(Model!I372+0,NA()) -> 0.2702758 | J18: =IFERROR(Model!N372+0,NA()) -> 0.25512631 | K18: =IFERROR(Model!S372+0,NA()) -> 0.22996865 | L18: =IFERROR(Model!X372+0,NA()) -> 0.27699274 | M18: =IFERROR(Model!AC372+0,NA()) -> 0.2353404 | N18: =IFERROR(Model!AH372+0,NA()) -> 0.21011359 | O18: =IFERROR(Model!AM372+0,NA()) -> 0.26865594 | P18: =IFERROR(Model!AR372+0,NA()) -> 0.24796642 | Q18: =IFERROR(Model!AW372+0,NA()) -> 0.19880988 | R18: =IFERROR(Model!BB372+0,NA()) -> 0.24262905 | S18: =IFERROR(Model!BG372+0,NA()) -> 0.3313328 | T18: =IFERROR(Model!BL372+0,NA()) -> 0.1538797 | U18: =IFERROR(Model!BQ372+0,NA()) -> 0.20668331 | V18: =IFERROR(Model!BV372+0,NA()) -> 0.2442154
B19: RONTA | C19: =IFERROR(Model!C383+0,NA()) -> 0.39855674 | D19: =IFERROR(Model!D383+0,NA()) -> 0.43057001 | E19: =IFERROR(Model!E383+0,NA()) -> 0.47056976 | F19: =IFERROR(Model!F383+0,NA()) -> 0.51856216 | G19: =IFERROR(Model!G383+0,NA()) -> 0.46847617 | H19: =IFERROR(Model!H383+0,NA()) -> 0.49943727 | I19: =IFERROR(Model!I383+0,NA()) -> 0.49597148 | J19: =IFERROR(Model!N383+0,NA()) -> 0.45327694 | K19: =IFERROR(Model!S383+0,NA()) -> 0.36147515 | L19: =IFERROR(Model!X383+0,NA()) -> 0.57608128 | M19: =IFERROR(Model!AC383+0,NA()) -> 0.46643286 | N19: =IFERROR(Model!AH383+0,NA()) -> 0.36575791 | O19: =IFERROR(Model!AM383+0,NA()) -> 0.44333216 | P19: =IFERROR(Model!AR383+0,NA()) -> 0.34906399 | Q19: =IFERROR(Model!AW383+0,NA()) -> 0.33900057 | R19: =IFERROR(Model!BB383+0,NA()) -> 0.36696932 | S19: =IFERROR(Model!BG383+0,NA()) -> 0.55644809 | T19: =IFERROR(Model!BL383+0,NA()) -> 0.29524486 | U19: =IFERROR(Model!BQ383+0,NA()) -> 0.39075801 | V19: =IFERROR(Model!BV383+0,NA()) -> 0.49760768
B20: Adj. operating margin % of AGP | C20: =IFERROR(Model!C182+0,NA()) -> 0.38598431 | D20: =IFERROR(Model!D182+0,NA()) -> 0.40978696 | E20: =IFERROR(Model!E182+0,NA()) -> 0.4157101 | F20: =IFERROR(Model!F182+0,NA()) -> 0.42317536 | G20: =IFERROR(Model!G182+0,NA()) -> 0.42429791 | H20: =IFERROR(Model!H182+0,NA()) -> 0.42429584 | I20: =IFERROR(Model!I182+0,NA()) -> 0.39318316 | J20: =IFERROR(Model!N182+0,NA()) -> 0.37179449 | K20: =IFERROR(Model!S182+0,NA()) -> 0.37278273 | L20: =IFERROR(Model!X182+0,NA()) -> 0.37836349 | M20: =IFERROR(Model!AC182+0,NA()) -> 0.36773686 | N20: =IFERROR(Model!AH182+0,NA()) -> 0.32732375 | O20: =IFERROR(Model!AM182+0,NA()) -> 0.33715481 | P20: =IFERROR(Model!AR182+0,NA()) -> 0.30320263 | Q20: =IFERROR(Model!AW182+0,NA()) -> 0.27910293 | R20: =IFERROR(Model!BB182+0,NA()) -> 0.34329868 | S20: =IFERROR(Model!BG182+0,NA()) -> 0.35572141 | T20: =IFERROR(Model!BL182+0,NA()) -> 0.21218087 | U20: =IFERROR(Model!BQ182+0,NA()) -> 0.27462754 | V20: =IFERROR(Model!BV182+0,NA()) -> 0.30546272
B21: FCF % of AGP | C21: =IFERROR(Model!C266+0,NA()) -> 0.27881915 | D21: =IFERROR(Model!D266+0,NA()) -> 0.212833 | E21: =IFERROR(Model!E266+0,NA()) -> 0.30824902 | F21: =IFERROR(Model!F266+0,NA()) -> 0.24465632 | G21: =IFERROR(Model!G266+0,NA()) -> 0.21533156 | H21: =IFERROR(Model!H266+0,NA()) -> 0.23085423 | I21: =IFERROR(Model!I266+0,NA()) -> 0.23852638 | J21: =IFERROR(Model!N266+0,NA()) -> 0.16315659 | K21: =IFERROR(Model!S266+0,NA()) -> 0.24103978 | L21: =IFERROR(Model!X266+0,NA()) -> 0.29698036 | M21: =IFERROR(Model!AC266+0,NA()) -> 0.19230104 | N21: =IFERROR(Model!AH266+0,NA()) -> 0.13621165 | O21: =IFERROR(Model!AM266+0,NA()) -> 0.26948675 | P21: =IFERROR(Model!AR266+0,NA()) -> 0.29577042 | Q21: =IFERROR(Model!AW266+0,NA()) -> 0.18454999 | R21: =IFERROR(Model!BB266+0,NA()) -> 0.0076244675 | S21: =IFERROR(Model!BG266+0,NA()) -> 0.42348985 | T21: =IFERROR(Model!BL266+0,NA()) -> 0.24872649 | U21: =IFERROR(Model!BQ266+0,NA()) -> 0.15724911 | V21: =IFERROR(Model!BV266+0,NA()) -> 0.30921554

Sheet RXO PF
B1: RXO PF — pro forma acquisition analysis (links to Model; scenario switch Model!CF2)
B2: C.H. Robinson (CHRW) acquisition of RXO, Inc. (NYSE: RXO) — Pro Forma Model
B3: USD millions · Sources: joint press release, merger agreement (Ex. 2.1), investor presentation (Ex. 99.2) and Form 8-K filed 5-Oct-2026 (SEC EDGAR CIK 0001043277, acc. 0001193125-26-413203); RXO Forms 10-K / 10-Q and earnings releases (CIK 0001929561); CHRW standalone forecast from the Model tab.
B4: Basis notes: announced 5-Oct-2026; expected close 1H27 (HSR & other antitrust clearances, RXO stockholder vote). Assumed close date is an input. Accretion measured on the company deal definition — adjusted EPS excludes restructuring / divestiture items and amortization of intangibles related to this acquisition. Pre-close CHRW buybacks continue (standalone); repurchases paused after close until leverage is within 1.75–2.25x. Synergy phasing, costs to achieve, fees, PPA and financing mix are model assumptions (not disclosed) — blue cells.
I5: RXO standalone ← → Pro forma (from close)
B6: (USDm) | C6: 2021 | D6: 2022 | E6: 2023 | F6: 2024 | G6: 2025 | H6: LTM Q2/26 | I6: 2026E | J6: 2027E | K6: 2028E | L6: 2029E | M6: 2030E | O6: Modelling notes / sources | Q6: RXO PF SCENARIO INPUTS (follow Model!CF2) | R6: Bull | S6: Base | T6: Bear | U6: Rationale
Q7: Run-rate net cost synergies ($m) | R7: 330 | S7: 300 | T7: 225 | U7: ~$300m net run-rate within two years post-close (press release); 80% cost-to-serve & shared services / 20% third-party spend (deck p.9).
B8: 1. TRANSACTION TERMS & CONSIDERATION | O8: Source / basis | Q8: Synergies realised — 2027E (% of run-rate, annualised, post-close months) | R8: 0.3 | S8: 0.2 | T8: 0.1 | U8: Lean AI operating model applied to RXO from day one; "within two years post-close".
B9: Assumed closing date (input; company: "expected to close in the first half of 2027") | C9: 46568 | O9: Merger agreement outside date 4-Jul-2027 (+2 × 3-month extensions for regulatory approvals). Mid-point of 1H27 guidance assumed. | Q9: Synergies realised — 2028E (% of run-rate) | R9: 0.9 | S9: 0.75 | T9: 0.5
B10: Fraction of 2027E consolidated (close → 31-Dec-27) | C10: =(DATE(2027,12,31)-$C$9)/365 -> 0.50410959 | O10: Drives 2027E consolidation of RXO, synergies, interest and new shares. | Q10: Synergies realised — 2029E (% of run-rate) | R10: 1 | S10: 1 | T10: 0.85 | U10: Full run-rate by mid-2029 (two years post an assumed mid-2027 close).
B11: RXO fully diluted shares (m) | C11: 175.803 | O11: Merger agreement capitalization at 30-Sep-26: 164.96m common + 2.09m RSUs + 4.17m PSUs (at max) + 4.58m pre-funded warrants (MFN, 2024 Coyote PIPE). Reconciles to $5.3bn equity value. | Q11: Synergies realised — 2030E (% of run-rate) | R11: 1 | S11: 1 | T11: 1
B12: Cash per RXO share — standard consideration ($) | C12: 17.25 | O12: Merger agreement / 8-K Item 1.01: $17.25 cash + 0.0856 CHRW shares; elections ($30.25 cash or 0.1992 shares) prorated to ~57% cash / 43% stock. | Q12: RXO standalone revenue growth 2027E–30E (p.a.) | R12: 0.07 | S12: 0.05 | T12: 0.02 | U12: Truck brokerage share gains vs. freight-cycle recovery; 2026E consensus $6.8bn (deck p.5).
B13: Exchange ratio (CHRW shares per RXO share) | C13: 0.0856 | O13: "Exchange Ratio means 0.0856" (merger agreement Ex. 2.1). | Q13: RXO standalone adj. EBITDA margin — 2027E | R13: 0.03 | S13: 0.026 | T13: 0.02 | U13: 2026E consensus $137m (~2.0%); FY25 1.9%; 2021–22 peak 5.9–6.4%.
B14: CHRW share price ($) — Model reference | C14: =Model!$CA$394 -> 151.88 | O14: $151.88 = CHRW 16-day VWAP to 2-Oct-26 used for the $30.25 headline (press release footnote 2). | Q14: RXO standalone adj. EBITDA margin — 2030E (linear from 2027E) | R14: 0.048 | S14: 0.038 | T14: 0.028 | U14: Standalone freight-cycle recovery (2021–22 peak 5.9–6.4%); synergies are modelled separately.
B15: Implied value per RXO share ($) | C15: =$C$12+$C$13*$C$14 -> 30.250928 | O15: Check: $17.25 + 0.0856 × $151.88 = $30.25. | Q15: One-time costs to achieve (× run-rate synergies) | R15: 0.8 | S15: 1 | T15: 1.3 | U15: Not disclosed; industry norm ~1.0x run-rate (severance, systems migration). Excluded from adjusted EPS (restructuring).
B16: Implied equity value ($m) | C16: =$C$11*$C$15 -> 5318.2039 | O16: Investor presentation: "approximately $5.3B implied equity value". | Q16: CHRW pre-close buybacks (% of standalone pace, Jan-27 to close) | R16: 0.5 | S16: 0 | T16: 0 | U16: Company intends to pause repurchases (to reach 1.75–2.25x); Base assumes the pause starts at announcement.
B17: RXO debt refinanced at close — principal, 30-Jun-26 ($m) | C17: 501 | O17: $400m 6.375% senior notes 2031 (101% change-of-control put) + $65m ABL (must be repaid at close) + $36m finance leases / other (RXO 10-Q Q2/26). | Q17: Leverage target for resuming buybacks (net debt / adj. EBITDA, x) | R17: 2.25 | S17: 2 | T17: 1.75 | U17: Company: 1.75–2.25x by end-2028; buybacks paused until within range.
B18: RXO cash, 30-Jun-26 ($m) | C18: 15 | O18: RXO 10-Q Q2/26. | Q18: Active scenario: | R18: =Model!$CF$2 -> Base
B19: Implied enterprise value ($m) | C19: =$C$16+$C$17-$C$18 -> 5804.2039 | O19: Investor presentation: "$5.8B implied enterprise value" (the press release "implied value of $5.8 billion" is EV).
B20: Cash consideration ($m) = shares × $17.25 | C20: =$C$11*$C$12 -> 3032.6017 | O20: Aggregate cash fixed as if all shares took the standard consideration (8-K Item 1.01).
B21: New CHRW shares issued (m) = shares × 0.0856 | C21: =$C$11*$C$13 -> 15.048737
B22: Stock consideration ($m) | C22: =$C$21*$C$14 -> 2285.6021
B23: Cash % of consideration | C23: =$C$20/($C$20+$C$22) -> 0.57023044 | O23: Company: ~57% cash / 43% stock.
B24: CHRW shares outstanding before issuance (m; Model YE2026E) | C24: =Model!$CA$361 -> 115.76696 | O24: Merger agreement rep: 115.46m at 30-Sep-26.
B25: RXO holders' pro forma ownership % | C25: =$C$21/($C$21+$C$24) -> 0.1150377 | O25: Company: "RXO stockholders are expected to own 11% of the combined company".
B26: RXO undisturbed share price, 2-Oct-26 ($; implied by 29% premium) | C26: =$C$15/1.29 -> 23.450332 | O26: 29% premium to the 2-Oct-26 close; 27% to the 90-day VWAP (press release).
B27: Premium paid over undisturbed equity value ($m) | C27: =($C$15-$C$26)*$C$11 -> 1195.5652 | O27: Compare with capitalised synergy value (section 6).
B28: RXO 2026E consensus adjusted EBITDA ($m) | C28: 137 | O28: Investor presentation p.3 (consensus); LTM Q2/26 actual $95m; Q3/26 guidance $35–45m.
B29: EV / RXO 2026E adjusted EBITDA (x) | C29: =$C$19/$C$28 -> 42.366452
B30: EV / (2026E adjusted EBITDA + run-rate synergies) (x) | C30: =$C$19/($C$28+CHOOSE(MATCH(Model!$CF$2,{"Bull","Base","Bear"},0),$R$7,$S$7,$T$7)) -> 13.281931 | O30: Company: 13.2x including ~$300m synergies (deck p.3).
B31: Termination fee payable by RXO ($m) | C31: 175 | O31: Merger agreement §9; no reverse termination fee payable by CHRW identified.
B32: Committed bridge facility ($m; Morgan Stanley Senior Funding, 364-day) | C32: 4500 | O32: To be replaced by permanent financing (bonds, term loans, cash). CHRW expects to keep investment-grade ratings.
B34: 2. SOURCES & USES AT CLOSE ($m) | O34: Basis
B35: Uses
B36: Cash consideration to RXO stockholders | C36: =$C$20 -> 3032.6017
B37: Stock consideration (CHRW shares issued) | C37: =$C$22 -> 2285.6021
B38: Refinance RXO debt (principal) | C38: =$C$17 -> 501
B39: Change-of-control premium on RXO 2031 notes (1% × $400m) | C39: 4 | O39: Assumes all 6.375% notes are put at 101% (holders likely to accept given the coupon vs. CHRW credit).
B40: Transaction, advisory & financing fees (assumption) | C40: 110 | O40: ~1.9% of EV (advisory, bridge commitment & bond issuance). Not disclosed; expensed / capitalised, excluded from adjusted EPS.
B41: Total uses | C41: =SUM(C36:C40) -> 5933.2039
B42: Sources
B43: CHRW common stock issued to RXO holders | C43: =$C$22 -> 2285.6021
B44: RXO cash acquired | C44: =$C$18 -> 15
B45: New CHRW acquisition debt (bonds / term loans; plug) | C45: =$C$41-$C$43-$C$44 -> 3632.6017 | O45: Bridge ($4.5bn) to be refinanced by senior notes and term loans; CHRW cash on hand assumed nil (minimum cash).
B46: Total sources | C46: =$C$43+$C$44+$C$45 -> 5933.2039
B47: Check: sources − uses (should be 0) | C47: =ROUND($C$46-$C$41,1) -> 0
B48: Acquisition debt financing mix (assumption)
B49: Senior notes % of acquisition debt | C49: 0.65 | O49: Permanent mix not disclosed ("new debt financing"; bonds, new term loans and cash).
B50: Senior notes coupon % | C50: 0.0525 | O50: BBB+/Baa1 5–10-year new issue (~T + 110–130bp).
B51: Term loans / revolver rate % (prepayable; SOFR + ~1.1%) | C51: 0.05 | O51: Prepaid first from post-close free cash flow (buyback pause).
B52: Blended cost of acquisition debt % | C52: =$C$49*$C$50+(1-$C$49)*$C$51 -> 0.051625
B53: Tax rate on pro forma adjustments % | C53: 0.24 | O53: US federal + state blended marginal rate.
B55: 3. ILLUSTRATIVE PURCHASE PRICE ALLOCATION ($m) | O55: Basis (preliminary; company has not published a PPA)
B56: Purchase consideration (cash + stock) | C56: =$C$20+$C$22 -> 5318.2039 | O56: Stock valued at the Model reference price; final value at the closing-date price.
B57: RXO book stockholders' equity, 30-Jun-26 | C57: 1506 | O57: RXO 10-Q Q2/26 balance sheet.
B58: (−) existing RXO goodwill | C58: 1111 | O58: Incl. $493m from Coyote (Sep-2024).
B59: (−) existing RXO intangible assets | C59: 432
B60: RXO tangible book value | C60: =$C$57-$C$58-$C$59 -> -37
B61: Fair value of identifiable intangibles (customer relationships, carrier network, trade names, technology) | C61: 1000 | O61: Assumption ~17% of EV (Coyote PPA: intangibles $459m on $1.05bn price, ~44%; RXO legacy relationships largely internally generated).
B62: Weighted-average amortization life (years) | C62: 10
B63: (−) Deferred tax liability on intangible step-up | C63: =-($C$61-$C$59)*$C$53 -> -136.32
B64: Goodwill (residual) | C64: =$C$56-$C$60-$C$61-$C$63 -> 4491.5239
B65: Annual amortization of acquired intangibles (excluded from deal-basis adjusted EPS) | C65: =$C$61/$C$62 -> 100 | O65: Company deal definition of adjusted EPS excludes "amortization of intangibles related to this acquisition".
B66: Memo: RXO historical amortization of acquired intangibles (FY2025) | C66: 47 | O66: RXO adjusted net income reconciliation; replaced by the new PPA amortization.
B68: 4. RXO STANDALONE — HISTORY (as reported) & FORECAST ($m) | O68: Basis
B69: Truck brokerage revenue | C69: 2749 | D69: 2929 | E69: 2358 | F69: 3029 | G69: 4225 | H69: 4579
B70: Managed transportation revenue (incl. freight forwarding, recast) | C70: 1037 | D70: 945 | E70: 690 | F70: 600 | G70: 549 | H70: 537
B71: Last mile revenue | C71: 1016 | D71: 1061 | E71: 1014 | F71: 1055 | G71: 1196 | H71: 1212
B72: Eliminations | C72: -113 | D72: -139 | E72: -135 | F72: -134 | G72: -228 | H72: -239
B73: Total revenues | C73: 4689 | D73: 4796 | E73: 3927 | F73: 4550 | G73: 5742 | H73: 6089 | I73: 6800 | J73: =I73*(1+CHOOSE(MATCH(Model!$CF$2,{"Bull","Base","Bear"},0),$R$12,$S$12,$T$12)) -> 7140 | K73: =J73*(1+CHOOSE(MATCH(Model!$CF$2,{"Bull","Base","Bear"},0),$R$12,$S$12,$T$12)) -> 7497 | L73: =K73*(1+CHOOSE(MATCH(Model!$CF$2,{"Bull","Base","Bear"},0),$R$12,$S$12,$T$12)) -> 7871.85 | M73: =L73*(1+CHOOSE(MATCH(Model!$CF$2,{"Bull","Base","Bear"},0),$R$12,$S$12,$T$12)) -> 8265.4425 | O73: 2026E: consensus $6.8bn (investor presentation p.5). 2027E+: scenario growth. Coyote consolidated from 16-Sep-2024 (FY2024 partial).
B74: Revenues y/y % | D74: =IFERROR(D73/C73-1,"") -> 0.022819364 | E74: =IFERROR(E73/D73-1,"") -> -0.18119266 | F74: =IFERROR(F73/E73-1,"") -> 0.15864528 | G74: =IFERROR(G73/F73-1,"") -> 0.26197802 | I74: =IFERROR(I73/G73-1,"") -> 0.18425636 | J74: =IFERROR(J73/I73-1,"") -> 0.05 | K74: =IFERROR(K73/J73-1,"") -> 0.05 | L74: =IFERROR(L73/K73-1,"") -> 0.05 | M74: =IFERROR(M73/L73-1,"") -> 0.05
B75: Gross margin (company definition; after direct D&A from Q2/23) | C75: 816 | D75: 941 | E75: 717 | F75: 774 | G75: 932 | H75: 900
B76: Gross margin % of revenues | C76: =IFERROR(C75/C73,"") -> 0.17402431 | D76: =IFERROR(D75/D73,"") -> 0.19620517 | E76: =IFERROR(E75/E73,"") -> 0.18258212 | F76: =IFERROR(F75/F73,"") -> 0.17010989 | G76: =IFERROR(G75/G73,"") -> 0.16231278 | H76: =IFERROR(H75/H73,"") -> 0.14780752
B77: Adjusted EBITDA (company definition) | C77: 277 | D77: 306 | E77: 132 | F77: 118 | G77: 109 | H77: 95 | I77: =$C$28 -> 137 | J77: =J73*J78 -> 185.64 | K77: =K73*K78 -> 224.91 | L77: =L73*L78 -> 267.6429 | M77: =M73*M78 -> 314.08682 | O77: RXO definition: net income + interest + taxes + D&A + transaction/integration/restructuring + impairment + other (incl. the Q3/24 $216m PIPE charge).
B78: Adjusted EBITDA margin % of revenues | C78: =IFERROR(C77/C73,"") -> 0.05907443 | D78: =IFERROR(D77/D73,"") -> 0.063803169 | E78: =IFERROR(E77/E73,"") -> 0.033613445 | F78: =IFERROR(F77/F73,"") -> 0.025934066 | G78: =IFERROR(G77/G73,"") -> 0.018982933 | H78: =IFERROR(H77/H73,"") -> 0.015601905 | I78: =IFERROR(I77/I73,"") -> 0.020147059 | J78: =CHOOSE(MATCH(Model!$CF$2,{"Bull","Base","Bear"},0),$R$13,$S$13,$T$13) -> 0.026 | K78: =CHOOSE(MATCH(Model!$CF$2,{"Bull","Base","Bear"},0),$R$13,$S$13,$T$13)+(CHOOSE(MATCH(Model!$CF$2,{"Bull","Base","Bear"},0),$R$14,$S$14,$T$14)-CHOOSE(MATCH(Model!$CF$2,{"Bull","Base","Bear"},0),$R$13,$S$13,$T$13))*(2028-2027)/3 -> 0.03 | L78: =CHOOSE(MATCH(Model!$CF$2,{"Bull","Base","Bear"},0),$R$13,$S$13,$T$13)+(CHOOSE(MATCH(Model!$CF$2,{"Bull","Base","Bear"},0),$R$14,$S$14,$T$14)-CHOOSE(MATCH(Model!$CF$2,{"Bull","Base","Bear"},0),$R$13,$S$13,$T$13))*(2029-2027)/3 -> 0.034 | M78: =CHOOSE(MATCH(Model!$CF$2,{"Bull","Base","Bear"},0),$R$13,$S$13,$T$13)+(CHOOSE(MATCH(Model!$CF$2,{"Bull","Base","Bear"},0),$R$14,$S$14,$T$14)-CHOOSE(MATCH(Model!$CF$2,{"Bull","Base","Bear"},0),$R$13,$S$13,$T$13))*(2030-2027)/3 -> 0.038
B79: Depreciation & amortization (total) | C79: 81 | D79: 86 | E79: 67 | F79: 87 | G79: 116 | H79: 106 | I79: 105 | J79: =J73*0.0155 -> 110.67 | K79: =K73*0.0155 -> 116.2035 | L79: =L73*0.0155 -> 122.01368 | M79: =M73*0.0155 -> 128.11436 | O79: 2026E ~$105m; 2027E+ 1.55% of revenues (FY25 2.0% incl. Coyote intangible amortization).
B80: of which: amortization of acquired intangibles | C80: 24 | D80: 21 | E80: 13 | F80: 28 | G80: 47 | H80: 42 | I80: 42
B81: Adjusted EBIT ex acquired-intangible amortization (= adj. EBITDA − depreciation) | C81: =IFERROR(C77-(C79-N(C80)),"") -> 220 | D81: =IFERROR(D77-(D79-N(D80)),"") -> 241 | E81: =IFERROR(E77-(E79-N(E80)),"") -> 78 | F81: =IFERROR(F77-(F79-N(F80)),"") -> 59 | G81: =IFERROR(G77-(G79-N(G80)),"") -> 40 | H81: =IFERROR(H77-(H79-N(H80)),"") -> 31 | I81: =I77-(I79-N(I80)) -> 74 | J81: =J77-(J79-N(J80)) -> 74.97 | K81: =K77-(K79-N(K80)) -> 108.7065 | L81: =L77-(L79-N(L80)) -> 145.62922 | M81: =M77-(M79-N(M80)) -> 185.97246
B82: Operating income (GAAP) | C82: 192 | D82: 123 | E82: 39 | F82: -56 | G82: -79 | H82: -76
B83: Interest expense | C83: 0 | D83: 4 | E83: 32 | F83: 30 | G83: 35 | H83: 36
B84: Net income (GAAP) | C84: 150 | D84: 92 | E84: 4 | F84: -290 | G84: -100 | H84: -105
B85: Adjusted net income (company definition) | C85: 170 | D85: 181 | E85: 36 | F85: 17 | G85: -7 | H85: -15
B86: Adjusted diluted EPS ($) | C86: 1.48 | D86: 1.56 | E86: 0.3 | F86: 0.12 | G86: -0.04
B87: Capital expenditures | C87: -39 | D87: -57 | E87: -64 | F87: -45 | G87: -59 | H87: -59 | I87: -60 | J87: =-J73*0.009 -> -64.26 | K87: =-K73*0.009 -> -67.473 | L87: =-L73*0.009 -> -70.84665 | M87: =-M73*0.009 -> -74.388982
B88: Cash flow from operations | C88: 155 | D88: 310 | E88: 89 | F88: -12 | G88: 51 | H88: -17
B89: Net debt (period end; carrying) | C89: -29 | D89: 357 | E89: 354 | F89: 333 | G89: 387
B90: Shares outstanding, period end (m) | D90: 116.4 | E90: 117.026 | F90: 162.517 | G90: 164.16
B91: RXO unlevered FCF for PF (adj. EBITDA − capex − tax on adj. EBIT; ΔWC nil) | I91: =I77+I87-MAX(0,I81)*$C$53 -> 59.24 | J91: =J77+J87-MAX(0,J81)*$C$53 -> 103.3872 | K91: =K77+K87-MAX(0,K81)*$C$53 -> 131.34744 | L91: =L77+L87-MAX(0,L81)*$C$53 -> 161.84524 | M91: =M77+M87-MAX(0,M81)*$C$53 -> 195.06444
B93: 5. SYNERGIES & INTEGRATION COSTS ($m; pro forma years) | O93: Basis
B94: Fraction of year consolidated | J94: =$C$10 -> 0.50410959 | K94: =1 -> 1 | L94: =1 -> 1 | M94: =1 -> 1
B95: Run-rate net cost synergies (scenario) | J95: =CHOOSE(MATCH(Model!$CF$2,{"Bull","Base","Bear"},0),$R$7,$S$7,$T$7) -> 300 | K95: =CHOOSE(MATCH(Model!$CF$2,{"Bull","Base","Bear"},0),$R$7,$S$7,$T$7) -> 300 | L95: =CHOOSE(MATCH(Model!$CF$2,{"Bull","Base","Bear"},0),$R$7,$S$7,$T$7) -> 300 | M95: =CHOOSE(MATCH(Model!$CF$2,{"Bull","Base","Bear"},0),$R$7,$S$7,$T$7) -> 300
B96: % of run-rate realised (annualised rate in year) | J96: =CHOOSE(MATCH(Model!$CF$2,{"Bull","Base","Bear"},0),$R$8,$S$8,$T$8) -> 0.2 | K96: =CHOOSE(MATCH(Model!$CF$2,{"Bull","Base","Bear"},0),$R$9,$S$9,$T$9) -> 0.75 | L96: =CHOOSE(MATCH(Model!$CF$2,{"Bull","Base","Bear"},0),$R$10,$S$10,$T$10) -> 1 | M96: =CHOOSE(MATCH(Model!$CF$2,{"Bull","Base","Bear"},0),$R$11,$S$11,$T$11) -> 1
B97: Synergies realised in year (pre-tax) | J97: =J95*J96*J94 -> 30.246575 | K97: =K95*K96*K94 -> 225 | L97: =L95*L96*L94 -> 300 | M97: =M95*M96*M94 -> 300 | O97: Net of dis-synergies per company ("net run-rate cost synergies"). Applied to the consolidated period only in 2027E.
B98: Costs to achieve — phasing % (assumption) | J98: 0.35 | K98: 0.45 | L98: 0.2 | M98: 0
B99: One-time costs to achieve (pre-tax; excluded from adjusted EPS) | J99: =J95*CHOOSE(MATCH(Model!$CF$2,{"Bull","Base","Bear"},0),$R$15,$S$15,$T$15)*J98 -> 105 | K99: =K95*CHOOSE(MATCH(Model!$CF$2,{"Bull","Base","Bear"},0),$R$15,$S$15,$T$15)*K98 -> 135 | L99: =L95*CHOOSE(MATCH(Model!$CF$2,{"Bull","Base","Bear"},0),$R$15,$S$15,$T$15)*L98 -> 60 | M99: =M95*CHOOSE(MATCH(Model!$CF$2,{"Bull","Base","Bear"},0),$R$15,$S$15,$T$15)*M98 -> 0 | O99: Not disclosed. Severance, systems / TMS migration onto the CHRW platform, facilities.
B100: Transaction fees expensed at close (pre-tax; excluded from adjusted EPS) | J100: =$C$40+$C$39 -> 114 | K100: 0 | L100: 0 | M100: 0
B102: 6. PRO FORMA COMBINED — CHRW + RXO ($m; RXO consolidated from close) | O102: Basis
B103: CHRW standalone (Model tab, active scenario)
B104: Revenues | I104: =Model!CA125 -> 18797.312 | J104: =Model!CB125 -> 19741.032 | K104: =Model!CC125 -> 20378.519 | L104: =Model!CD125 -> 21048.014 | M104: =Model!CE125 -> 22335.678
B105: Adjusted gross profit | I105: =Model!CA133 -> 2869.9108 | J105: =Model!CB133 -> 3030.6053 | K105: =Model!CC133 -> 3219.1046 | L105: =Model!CD133 -> 3407.7834 | M105: =Model!CE133 -> 3611.9036
...
