Workbook

Sheet Model
CT1: SCENARIO SWITCH ▼ (Bull / Base / Bear) — drives all scenario-linked forecast drivers
B2: Teledyne Technologies Incorporated (NYSE: TDY) — 3-Statement Financial Model | CT2: Base
B3: US GAAP as reported · USD millions (per-share data in USD) · Source: Teledyne Forms 10-K / 10-Q and Form 8-K earnings releases (Ex. 99.1), SEC EDGAR CIK 0001094285 (investor-relations releases are the same documents as filed on EDGAR)
B4: Basis notes: 52/53-week fiscal year (FY2009, FY2015, FY2020 = 53 weeks). FY2006–07 include Teledyne Continental Motors (piston engines, sold Apr-2011; discontinued from the FY2010 10-K). Segments on the current four-segment basis from FY2008 (FY2010 10-K recast); FY2006–07 legacy segments shown as memo. ASU 2017-07 (2018) recast 2017; ASC 606 from 2018 (2017 not restated). FLIR from 14-May-2021. Q3/26E–Q4/26E = FY26 non-GAAP EPS outlook less 1H/26 actuals.
CV5: Forecast | CW5: Historical | CX5: Historical | CY5: Historical
B6: (USDm) | C6: 2006 | D6: 2007 | E6: 2008 | F6: 2009 | G6: 2010 | H6: 2011 | I6: 2012 | J6: Q1/13 | K6: Q2/13 | L6: 1H/13 | M6: Q3/13 | N6: Q4/13 | O6: 2013 | P6: Q1/14 | Q6: Q2/14 | R6: 1H/14 | S6: Q3/14 | T6: Q4/14 | U6: 2014 | V6: Q1/15 | W6: Q2/15 | X6: 1H/15 | Y6: Q3/15 | Z6: Q4/15 | AA6: 2015 | AB6: Q1/16 | AC6: Q2/16 | AD6: 1H/16 | AE6: Q3/16 | AF6: Q4/16 | AG6: 2016 | AH6: Q1/17 | AI6: Q2/17 | AJ6: 1H/17 | AK6: Q3/17 | AL6: Q4/17 | AM6: 2017 | AN6: Q1/18 | AO6: Q2/18 | AP6: 1H/18 | AQ6: Q3/18 | AR6: Q4/18 | AS6: 2018 | AT6: Q1/19 | AU6: Q2/19 | AV6: 1H/19 | AW6: Q3/19 | AX6: Q4/19 | AY6: 2019 | AZ6: Q1/20 | BA6: Q2/20 | BB6: 1H/20 | BC6: Q3/20 | BD6: Q4/20 | BE6: 2020 | BF6: Q1/21 | BG6: Q2/21 | BH6: 1H/21 | BI6: Q3/21 | BJ6: Q4/21 | BK6: 2021 | BL6: Q1/22 | BM6: Q2/22 | BN6: 1H/22 | BO6: Q3/22 | BP6: Q4/22 | BQ6: 2022 | BR6: Q1/23 | BS6: Q2/23 | BT6: 1H/23 | BU6: Q3/23 | BV6: Q4/23 | BW6: 2023 | BX6: Q1/24 | BY6: Q2/24 | BZ6: 1H/24 | CA6: Q3/24 | CB6: Q4/24 | CC6: 2024 | CD6: Q1/25 | CE6: Q2/25 | CF6: 1H/25 | CG6: Q3/25 | CH6: Q4/25 | CI6: 2025 | CJ6: Q1/26 | CK6: Q2/26 | CL6: 1H/26 | CM6: Q3/26E | CN6: Q4/26E | CO6: 2026E | CP6: 2027E | CQ6: 2028E | CR6: 2029E | CS6: 2030E | CT6: Modelling Notes | CV6: 5Y CAGR | CW6: 5Y CAGR | CX6: 10Y CAGR | CY6: 19Y CAGR
CV7: 25-'30 | CW7: 20-'25 | CX7: 15-'25 | CY7: 06-'25
B8: SEGMENT P&L — BY SEGMENT (four reportable segments; current basis from FY2008) | CT8: SEGMENT BUILD — modelling logic (segment sales → GAAP OI → non-GAAP OI)
DB9: SCENARIO INPUT TABLE — driver assumptions per Bull / Base / Bear | DC9: Bull | DD9: Base | DE9: Bear | DF9: Bull / Bear = Base + Δ (Δ inputs on each block header). Outlook block = high / mid / low end of FY26 ranges.
B10: Digital Imaging (infrared / visible / X-ray sensors, cameras & systems; FLIR from 14-May-2021) | CT10: DIGITAL IMAGING — modelling logic
B11: Net sales | E11: 137.4 | F11: 127.3 | G11: 122.5 | H11: 349.9 | I11: 415.9 | J11: 102.4 | K11: 104.3 | L11: =J11+K11 -> 206.7 | M11: 105.2 | N11: 102.9 | O11: 414.8 | P11: 101.9 | Q11: 103.7 | R11: =P11+Q11 -> 205.6 | S11: 95.6 | T11: 102.4 | U11: 403.6 | V11: 90.4 | W11: 90.8 | X11: =V11+W11 -> 181.2 | Y11: 95.7 | Z11: 102.1 | AA11: 379 | AB11: 89.9 | AC11: 99.4 | AD11: =AB11+AC11 -> 189.3 | AE11: 98.5 | AF11: 110.9 | AG11: 398.7 | AH11: 113.8 | AI11: 200.2 | AJ11: =AH11+AI11 -> 314 | AK11: 197 | AL11: 206.7 | AM11: 710.4 | AN11: 208.3 | AO11: 223 | AP11: =AN11+AO11 -> 431.3 | AQ11: 220.7 | AR11: 223.3 | AS11: 875.3 | AT11: 232.4 | AU11: 248.4 | AV11: =AT11+AU11 -> 480.8 | AW11: 244 | AX11: 268.1 | AY11: 992.9 | AZ11: 246.7 | BA11: 237.6 | BB11: =AZ11+BA11 -> 484.3 | BC11: 239.7 | BD11: 262 | BE11: 986 | BF11: 263.3 | BG11: 579.5 | BH11: =BF11+BG11 -> 842.8 | BI11: 760.6 | BJ11: 809.5 | BK11: 2412.9 | BL11: 750.5 | BM11: 775.8 | BN11: =BL11+BM11 -> 1526.3 | BO11: 777.9 | BP11: 806.7 | BQ11: 3110.9 | BR11: 772.5 | BS11: 793.3 | BT11: =BR11+BS11 -> 1565.8 | BU11: 775.8 | BV11: 802.5 | BW11: 3144.1 | BX11: 740.8 | BY11: 739.4 | BZ11: =BX11+BY11 -> 1480.2 | CA11: 768.4 | CB11: 822.2 | CC11: 3070.8 | CD11: 757 | CE11: 771 | CF11: =CD11+CE11 -> 1528 | CG11: 785.4 | CH11: 850.5 | CI11: 3163.9 | CJ11: 816.9 | CK11: 868.7 | CL11: =CJ11+CK11 -> 1685.6 | CM11: =CG11*CK11/CE11 -> 884.92475 | CN11: =CH11*CK11/CE11 -> 958.27412 | CO11: =SUM(CJ11,CK11,CM11,CN11) -> 3528.7989 | CP11: =CO11*(1+CP12) -> 3740.5268 | CQ11: =CP11*(1+CQ12) -> 3946.2558 | CR11: =CQ11*(1+CR12) -> 4143.5686 | CS11: =CR11*(1+CS12) -> 4350.747 | CT11: Q3/26E–Q4/26E: prior-year quarter × Q2/26 y/y growth of the segment (after the Excelitas A&D anniversary). 2027E+: prior year × (1 + scenario organic growth). | CV11: =IFERROR((CS11/CI11)^(1/5)-1,"n/m") -> 0.065781595 | CW11: =IFERROR((CI11/BE11)^(1/5)-1,"n/m") -> 0.26260983 | CX11: =IFERROR((CI11/AA11)^(1/10)-1,"n/m") -> 0.23639817 | CY11: =IFERROR((CI11/C11)^(1/19)-1,"n/m") -> n/m | DB11: FY26 outlook — Q2-26 release (22-Jul-26) | DC11: High | DD11: Mid | DE11: Low
B12: Net sales y/y % | D12: =IFERROR(D11/C11-1,"") | E12: =IFERROR(E11/D11-1,"") | F12: =IFERROR(F11/E11-1,"") -> -0.073508006 | G12: =IFERROR(G11/F11-1,"") -> -0.037706206 | H12: =IFERROR(H11/G11-1,"") -> 1.8563265 | I12: =IFERROR(I11/H11-1,"") -> 0.18862532 | O12: =IFERROR(O11/I11-1,"") -> -0.0026448666 | P12: =IFERROR(P11/J11-1,"") -> -0.0048828125 | Q12: =IFERROR(Q11/K11-1,"") -> -0.0057526366 | R12: =IFERROR(R11/L11-1,"") -> -0.0053217223 | S12: =IFERROR(S11/M11-1,"") -> -0.091254753 | T12: =IFERROR(T11/N11-1,"") -> -0.0048590865 | U12: =IFERROR(U11/O11-1,"") -> -0.027000964 | V12: =IFERROR(V11/P11-1,"") -> -0.11285574 | ... CO12: =IFERROR(CO11/CI11-1,"") -> 0.11533199 | CP12: =CHOOSE(MATCH($CT$2,{"Bull","Base","Bear"},0),$DC$21,$DD$21,$DE$21) -> 0.06 | CQ12: =CHOOSE(MATCH($CT$2,{"Bull","Base","Bear"},0),$DC$22,$DD$22,$DE$22) -> 0.055 | CR12: =CHOOSE(MATCH($CT$2,{"Bull","Base","Bear"},0),$DC$23,$DD$23,$DE$23) -> 0.05 | CS12: =CHOOSE(MATCH($CT$2,{"Bull","Base","Bear"},0),$DC$24,$DD$24,$DE$24) -> 0.05 | CT12: 2027E–2030E: scenario lever (DI_organicGrowth, Bull/Base/Bear table →). | DB12: FY26 non-GAAP diluted EPS ($) | DC12: 24.65 | DD12: 24.55 | DE12: 24.45
B13: Segment operating income (GAAP) | E13: 14.6 | F13: 11.8 | G13: 5.2 | H13: 16.1 | I13: 24.8 | J13: 5.2 | K13: 7.9 | L13: =J13+K13 -> 13.1 | M13: 11.5 | N13: 3.6 | O13: 28.2 | P13: 9.7 | Q13: 11.7 | R13: =P13+Q13 -> 21.4 | S13: 7.9 | T13: 7.8 | U13: 37.1 | V13: 9.3 | W13: 8.8 | X13: =V13+W13 -> 18.1 | Y13: 10.4 | Z13: 11.5 | AA13: 40 | AB13: 8.2 | AC13: 10.7 | AD13: =AB13+AC13 -> 18.9 | AE13: 11.7 | AF13: 15.3 | AG13: 45.9 | AH13: 15.1 | AI13: 28 | AJ13: =AH13+AI13 -> 43.1 | AK13: 31.4 | AL13: 35.9 | AM13: 110.2 | AN13: 33.8 | AO13: 43.1 | AP13: =AN13+AO13 -> 76.9 | AQ13: 42.3 | AR13: 36.3 | AS13: 155.5 | AT13: 36.6 | AU13: 51.6 | AV13: =AT13+AU13 -> 88.2 | AW13: 41.2 | AX13: 47.1 | AY13: 176.5 | AZ13: 43.8 | BA13: 46.8 | BB13: =AZ13+BA13 -> 90.6 | BC13: 45.5 | BD13: 56.7 | BE13: 192.8 | BF13: 52 | BG13: 84.6 | BH13: =BF13+BG13 -> 136.6 | BI13: 94.9 | BJ13: 94.1 | BK13: 325.6 | BL13: 115.7 | BM13: 117.9 | BN13: =BL13+BM13 -> 233.6 | BO13: 133.7 | BP13: 152 | BQ13: 519.3 | BR13: 122.2 | BS13: 124.6 | BT13: =BR13+BS13 -> 246.8 | BU13: 136.3 | BV13: 134.3 | BW13: 517.4 | BX13: 113.8 | BY13: 113.5 | BZ13: =BX13+BY13 -> 227.3 | CA13: 123.9 | CB13: 90.8 | CC13: 442 | CD13: 122.3 | CE13: 119.6 | CF13: =CD13+CE13 -> 241.9 | CG13: 123.4 | CH13: 162.9 | CI13: 528.2 | CJ13: 141.7 | CK13: 170.2 | CL13: =CJ13+CK13 -> 311.9 | CM13: =CM16-CM14-CM15 -> 157.16457 | CN13: =CN16-CN14-CN15 -> 184.28463 | CO13: =SUM(CJ13,CK13,CM13,CN13) -> 653.3492 | CP13: =CP16-CP14-CP15 -> 738.56181 | CQ13: =CQ16-CQ14-CQ15 -> 811.13208 | CR13: =CR16-CR14-CR15 -> 918.04484 | CS13: =CS16-CS14-CS15 -> 1014.6315 | CT13: Forecast GAAP OI = non-GAAP OI − acquired-intangible amortization − other items. | CV13: =IFERROR((CS13/CI13)^(1/5)-1,"n/m") -> 0.13946763 | CW13: =IFERROR((CI13/BE13)^(1/5)-1,"n/m") -> 0.22331492 | CX13: =IFERROR((CI13/AA13)^(1/10)-1,"n/m") -> 0.2944159 | CY13: =IFERROR((CI13/C13)^(1/19)-1,"n/m") -> n/m | DB13: Q3/26 non-GAAP diluted EPS ($) | DC13: 6.15 | DD13: 6.1 | DE13: 6.05
B14: (+) Acquired intangible asset amortization | AZ14: 4.6 | BA14: 4.4 | BB14: =AZ14+BA14 -> 9 | BC14: 4.5 | BD14: 4.6 | BE14: 18.1 | BF14: 4.6 | BG14: 27.4 | BH14: =BF14+BG14 -> 32 | BI14: 50.1 | BJ14: 46.3 | BK14: 128.4 | BL14: 48.5 | BM14: 46.4 | BN14: =BL14+BM14 -> 94.9 | BO14: 44.7 | BP14: 44.1 | BQ14: 183.7 | BR14: 45.8 | BS14: 45.6 | BT14: =BR14+BS14 -> 91.4 | BU14: 45.4 | BV14: 44.9 | BW14: 181.7 | BX14: 45.8 | BY14: 45.4 | BZ14: =BX14+BY14 -> 91.2 | CA14: 46.1 | CB14: 46.1 | CC14: 183.3 | CD14: 45.4 | CE14: 46.3 | CF14: =CD14+CE14 -> 91.7 | CG14: 46.8 | CH14: 46.8 | CI14: 185.3 | CJ14: 48 | CK14: 47.4 | CL14: =CJ14+CK14 -> 95.4 | CM14: =CM125*$CL$14/($CL$14+$CL$31+$CL$51+$CL$70) -> 47.196127 | CN14: =CN125*$CL$14/($CL$14+$CL$31+$CL$51+$CL$70) -> 47.196127 | CO14: =SUM(CJ14,CK14,CM14,CN14) -> 189.79225 | CP14: =CP371*$CL$14/($CL$14+$CL$31+$CL$51+$CL$70) -> 177.86725 | CQ14: =CQ371*$CL$14/($CL$14+$CL$31+$CL$51+$CL$70) -> 175.43187 | CR14: =CR371*$CL$14/($CL$14+$CL$31+$CL$51+$CL$70) -> 138.56514 | CS14: =CS371*$CL$14/($CL$14+$CL$31+$CL$51+$CL$70) -> 116.56268 | CT14: Disclosed by segment from Q1/21. Forecast = amortization of existing intangibles (10-K schedule) × 1H/26 segment share. | DB14: FY26 GAAP diluted EPS ($, memo) | DC14: 20.99 | DD14: 20.86 | DE14: 20.73
B15: (+) Other segment non-GAAP items (inventory step-up, transaction costs) | BG15: 47.4 | BH15: =N(BF15)+N(BG15) -> 47.4 | BI15: 36.7 | BJ15: 48.2 | BK15: 132.3 | BP15: -4 | BQ15: -4 | BU15: 5.8 | BV15: 3 | BW15: 8.8 | BX15: 2.2 | BY15: 1 | BZ15: =BX15+BY15 -> 3.2 | CA15: 3.7 | CB15: 51 | CC15: 57.9 | CM15: 0 | CN15: 0 | CO15: =SUM(CJ15,CK15,CM15,CN15) -> 0 | CP15: 0 | CQ15: 0 | CR15: 0 | CS15: 0 | DB15: FY26 point estimates (all cases) | DF15: Not guided — analyst estimates: tax rate ≈ 1H/26 ETR before discrete items (Q2-26 21.7%); capex ≈ 2% of sales (FY25 $117m).
B16: Non-GAAP segment operating income | C16: =IF(OR(ISNUMBER(C17),ISNUMBER(C14)),C13+N(C14)+N(C15),"") | D16: =IF(OR(ISNUMBER(D17),ISNUMBER(D14)),D13+N(D14)+N(D15),"") | E16: =IF(OR(ISNUMBER(E17),ISNUMBER(E14)),E13+N(E14)+N(E15),"") | F16: =IF(OR(ISNUMBER(F17),ISNUMBER(F14)),F13+N(F14)+N(F15),"") | G16: =IF(OR(ISNUMBER(G17),ISNUMBER(G14)),G13+N(G14)+N(G15),"") | H16: =IF(OR(ISNUMBER(H17),ISNUMBER(H14)),H13+N(H14)+N(H15),"") | I16: =IF(OR(ISNUMBER(I17),ISNUMBER(I14)),I13+N(I14)+N(I15),"") | J16: =IF(OR(ISNUMBER(J17),ISNUMBER(J14)),J13+N(J14)+N(J15),"") | ... CL16: =IF(OR(ISNUMBER(CL17),ISNUMBER(CL14)),CL13+N(CL14)+N(CL15),"") -> 407.3 | CM16: =CM11*CM20 -> 204.3607 | CN16: =CN11*CN20 -> 231.48075 | CO16: =SUM(CJ16,CK16,CM16,CN16) -> 843.14146 | CP16: =CP11*CP20 -> 916.42907 | CQ16: =CQ11*CQ20 -> 986.56394 | CR16: =CR11*CR20 -> 1056.61 | CS16: =CS11*CS20 -> 1131.1942 | CT16: Company non-GAAP measure from Q1/21 (segment OI excluding acquired-intangible amortization and acquisition items). Forecast = net sales × non-GAAP margin. | CV16: =IFERROR((CS16/CI16)^(1/5)-1,"n/m") -> 0.096550507 | CW16: =IFERROR((CI16/BE16)^(1/5)-1,"n/m") -> 0.27603762 | CX16: =IFERROR((CI16/AA16)^(1/10)-1,"n/m") -> n/m | CY16: =IFERROR((CI16/C16)^(1/19)-1,"n/m") -> n/m | DB16: Tax rate (GAAP & non-GAAP) | DD16: 0.215
B17: Memo: non-GAAP segment operating income as published | AZ17: 48.4 | BA17: 51.2 | BB17: =AZ17+BA17 -> 99.6 | BC17: 50 | BD17: 61.3 | BE17: 210.9 | BF17: 56.6 | BG17: 159.4 | BH17: =BF17+BG17 -> 216 | BI17: 181.7 | BJ17: 188.6 | BK17: 586.3 | BL17: 164.2 | BM17: 164.3 | BN17: =BL17+BM17 -> 328.5 | BO17: 178.4 | BP17: 192.1 | BQ17: 699 | BR17: 168 | BS17: 170.2 | BT17: =BR17+BS17 -> 338.2 | BU17: 187.5 | BV17: 182.2 | BW17: 707.9 | BX17: 161.8 | BY17: 159.9 | BZ17: =BX17+BY17 -> 321.7 | CA17: 173.7 | CB17: 187.9 | CC17: 683.2 | CD17: 167.7 | CE17: 165.9 | CF17: =CD17+CE17 -> 333.6 | CG17: 170.2 | CH17: 209.7 | CI17: 713.5 | CJ17: 189.7 | CK17: 217.6 | CL17: =CJ17+CK17 -> 407.3 | DB17: Capital expenditures ($m) | DD17: 125
B18: Check: build vs published (should be 0) | C18: =IF(ISNUMBER(C17),ROUND(C16-C17,1),"n/p") -> n/p | D18: =IF(ISNUMBER(D17),ROUND(D16-D17,1),"n/p") -> n/p | E18: =IF(ISNUMBER(E17),ROUND(E16-E17,1),"n/p") -> n/p | F18: =IF(ISNUMBER(F17),ROUND(F16-F17,1),"n/p") -> n/p | G18: =IF(ISNUMBER(G17),ROUND(G16-G17,1),"n/p") -> n/p | H18: =IF(ISNUMBER(H17),ROUND(H16-H17,1),"n/p") -> n/p | I18: =IF(ISNUMBER(I17),ROUND(I16-I17,1),"n/p") -> n/p | J18: =IF(ISNUMBER(J17),ROUND(J16-J17,1),"n/p") -> n/p | ... CL18: =IF(ISNUMBER(CL17),ROUND(CL16-CL17,1),"n/p") -> 0
B19: Segment operating margin (GAAP) % | C19: =IFERROR(C13/C11,"") | D19: =IFERROR(D13/D11,"") | E19: =IFERROR(E13/E11,"") -> 0.1062591 | F19: =IFERROR(F13/F11,"") -> 0.092694423 | G19: =IFERROR(G13/G11,"") -> 0.04244898 | H19: =IFERROR(H13/H11,"") -> 0.046013147 | I19: =IFERROR(I13/I11,"") -> 0.059629719 | J19: =IFERROR(J13/J11,"") -> 0.05078125 | ... CS19: =IFERROR(CS13/CS11,"") -> 0.23320858 | CV19: =IFERROR(AVERAGE(CO19,CP19,CQ19,CR19,CS19),"n/m") -> 0.20858173 | CW19: =IFERROR(AVERAGE(BK19,BQ19,BW19,CC19,CI19),"n/m") -> 0.15546301 | CX19: =IFERROR(AVERAGE(AG19,AM19,AS19,AY19,BE19,BK19,BQ19,BW19,CC19,CI19),"n/m") -> 0.15985161 | CY19: =IFERROR(AVERAGE(C19,D19,E19,F19,G19,H19,I19,O19,U19,AA19,AG19,AM19,AS19,AY19,BE19,BK19,BQ19,BW19,CC19,CI19),"n/m") -> 0.12283387
B20: Non-GAAP segment operating margin % | C20: =IFERROR(C16/C11,"") | D20: =IFERROR(D16/D11,"") | E20: =IFERROR(E16/E11,"") | F20: =IFERROR(F16/F11,"") | G20: =IFERROR(G16/G11,"") | H20: =IFERROR(H16/H11,"") | I20: =IFERROR(I16/I11,"") | J20: =IFERROR(J16/J11,"") | ... CL20: =IFERROR(CL16/CL11,"") -> 0.24163503 | CM20: =CG20+$CL$20-$CF$20+CM102 -> 0.23093568 | CN20: =CH20+$CL$20-$CF$20+CN102 -> 0.24156006 | CO20: =IFERROR(CO16/CO11,"") -> 0.23893157 | CP20: =CHOOSE(MATCH($CT$2,{"Bull","Base","Bear"},0),$DC$45,$DD$45,$DE$45) -> 0.245 | CQ20: =CHOOSE(MATCH($CT$2,{"Bull","Base","Bear"},0),$DC$46,$DD$46,$DE$46) -> 0.25 | CR20: =CHOOSE(MATCH($CT$2,{"Bull","Base","Bear"},0),$DC$47,$DD$47,$DE$47) -> 0.255 | CS20: =CHOOSE(MATCH($CT$2,{"Bull","Base","Bear"},0),$DC$48,$DD$48,$DE$48) -> 0.26 | CT20: Q3/Q4-26E: prior-year quarter margin + 1H/26 vs 1H/25 change + outlook calibration Δ. 2027E+: scenario lever (DI_margin). | CV20: =IFERROR(AVERAGE(CO20,CP20,CQ20,CR20,CS20),"n/m") -> 0.24978631 | CW20: =IFERROR(AVERAGE(BK20,BQ20,BW20,CC20,CI20),"n/m") -> 0.22816537 | CX20: =IFERROR(AVERAGE(AG20,AM20,AS20,AY20,BE20,BK20,BQ20,BW20,CC20,CI20),"n/m") -> 0.2257869 | CY20: =IFERROR(AVERAGE(C20,D20,E20,F20,G20,H20,I20,O20,U20,AA20,AG20,AM20,AS20,AY20,BE20,BK20,BQ20,BW20,CC20,CI20),"n/m") -> 0.2257869 | DB20: DI_organicGrowth (Digital Imaging sales y/y) | DC20: 0.03 | DD20: Δ → | DE20: -0.04 | DF20: Digital Imaging: defense IR / unmanned systems, space sensors, industrial machine vision; commercial IR and semis capex cyclical.
B21: Segment operating income (GAAP) y/y % | D21: =IFERROR(D13/C13-1,"") | E21: =IFERROR(E13/D13-1,"") | F21: =IFERROR(F13/E13-1,"") -> -0.19178082 | G21: =IFERROR(G13/F13-1,"") -> -0.55932203 | H21: =IFERROR(H13/G13-1,"") -> 2.0961538 | I21: =IFERROR(I13/H13-1,"") -> 0.54037267 | O21: =IFERROR(O13/I13-1,"") -> 0.13709677 | P21: =IFERROR(P13/J13-1,"") -> 0.86538462 | Q21: =IFERROR(Q13/K13-1,"") -> 0.48101266 | R21: =IFERROR(R13/L13-1,"") -> 0.63358779 | S21: =IFERROR(S13/M13-1,"") -> -0.31304348 | T21: =IFERROR(T13/N13-1,"") -> 1.1666667 | U21: =IFERROR(U13/O13-1,"") -> 0.31560284 | V21: =IFERROR(V13/P13-1,"") -> -0.041237113 | ... CO21: =IFERROR(CO13/CI13-1,"") -> 0.23693526 | CP21: =IFERROR(CP13/CO13-1,"") -> 0.1304243 | CQ21: =IFERROR(CQ13/CP13-1,"") -> 0.098258891 | CR21: =IFERROR(CR13/CQ13-1,"") -> 0.13180685 | CS21: =IFERROR(CS13/CR13-1,"") -> 0.10520913 | DB21: 2027E | DC21: =DD21+$DC$20 -> 0.09 | DD21: 0.06 | DE21: =DD21+$DE$20 -> 0.02
B22: Incremental non-GAAP margin (ΔOI / ΔSales) | D22: =IFERROR((D16-C16)/(D11-C11),"") | E22: =IFERROR((E16-D16)/(E11-D11),"") | F22: =IFERROR((F16-E16)/(F11-E11),"") | G22: =IFERROR((G16-F16)/(G11-F11),"") | H22: =IFERROR((H16-G16)/(H11-G11),"") | I22: =IFERROR((I16-H16)/(I11-H11),"") | O22: =IFERROR((O16-I16)/(O11-I11),"") | P22: =IFERROR((P16-J16)/(P11-J11),"") | Q22: =IFERROR((Q16-K16)/(Q11-K11),"") | R22: =IFERROR((R16-L16)/(R11-L11),"") | S22: =IFERROR((S16-M16)/(S11-M11),"") | T22: =IFERROR((T16-N16)/(T11-N11),"") | U22: =IFERROR((U16-O16)/(U11-O11),"") | V22: =IFERROR((V16-P16)/(V11-P11),"") | ... CO22: =IFERROR((CO16-CI16)/(CO11-CI11),"") -> 0.35528051 | CP22: =IFERROR((CP16-CO16)/(CP11-CO11),"") -> 0.34614049 | CQ22: =IFERROR((CQ16-CP16)/(CQ11-CP11),"") -> 0.34090909 | CR22: =IFERROR((CR16-CQ16)/(CR11-CQ11),"") -> 0.355 | CS22: =IFERROR((CS16-CR16)/(CS11-CR11),"") -> 0.36 | DB22: 2028E | DC22: =DD22+$DC$20 -> 0.085 | DD22: 0.055 | DE22: =DD22+$DE$20 -> 0.015
B23: Segment D&A (annual, 10-K segment note) | E23: 10 | F23: 9.6 | G23: 9.3 | H23: 26.9 | I23: 30.5 | O23: 30.3 | U23: 29.6 | AA23: 26.1 | AG23: 26.2 | AM23: 49.6 | AS23: 50.8 | AY23: 48.5 | BE23: 49.2 | BK23: 309.2 | BQ23: 279 | BW23: 268.9 | CC23: 261.2 | CI23: 262.5 | DB23: 2029E | DC23: =DD23+$DC$20 -> 0.08 | DD23: 0.05 | DE23: =DD23+$DE$20 -> 0.01
B24: Segment capital expenditures (annual) | E24: 7.1 | F24: 5.7 | G24: 11.3 | H24: 13.8 | I24: 23.5 | O24: 20.2 | U24: 10.3 | AA24: 9.2 | AG24: 12.5 | AM24: 23.4 | AS24: 35.8 | AY24: 45.2 | BE24: 33.4 | BK24: 64.2 | BQ24: 63.9 | BW24: 78.2 | CC24: 54.7 | CI24: 67.7 | DB24: 2030E | DC24: =DD24+$DC$20 -> 0.08 | DD24: 0.05 | DE24: =DD24+$DE$20 -> 0.01
B25: Segment capex % of sales | C25: =IFERROR(C24/C11,"") | D25: =IFERROR(D24/D11,"") | E25: =IFERROR(E24/E11,"") -> 0.051673945 | F25: =IFERROR(F24/F11,"") -> 0.044776119 | G25: =IFERROR(G24/G11,"") -> 0.092244898 | H25: =IFERROR(H24/H11,"") -> 0.03943984 | I25: =IFERROR(I24/I11,"") -> 0.056503967 | O25: =IFERROR(O24/O11,"") -> 0.048698168 | U25: =IFERROR(U24/U11,"") -> 0.025520317 | AA25: =IFERROR(AA24/AA11,"") -> 0.024274406 | AG25: =IFERROR(AG24/AG11,"") -> 0.031351894 | AM25: =IFERROR(AM24/AM11,"") -> 0.032939189 | AS25: =IFERROR(AS24/AS11,"") -> 0.040900263 | AY25: =IFERROR(AY24/AY11,"") -> 0.045523215 | BE25: =IFERROR(BE24/BE11,"") -> 0.033874239 | BK25: =IFERROR(BK24/BK11,"") -> 0.026606987 | BQ25: =IFERROR(BQ24/BQ11,"") -> 0.02054068 | BW25: =IFERROR(BW24/BW11,"") -> 0.024871982 | CC25: =IFERROR(CC24/CC11,"") -> 0.017812948 | CI25: =IFERROR(CI24/CI11,"") -> 0.021397642
DB26: INST_organicGrowth (Instrumentation sales y/y) | DC26: 0.02 | DD26: Δ → | DE26: -0.03 | DF26: Instrumentation: marine (offshore energy, defense subsea), environmental (regulation), ETM.
B27: Instrumentation (marine, environmental, electronic test & measurement) | CT27: INSTRUMENTATION — modelling logic | DB27: 2027E | DC27: =DD27+$DC$26 -> 0.065 | DD27: 0.045 | DE27: =DD27+$DE$26 -> 0.015
B28: Net sales | E28: 549.2 | F28: 538.4 | G28: 573.2 | H28: 648.2 | I28: 804.7 | J28: 232.7 | K28: 257.7 | L28: =J28+K28 -> 490.4 | M28: 256.6 | N28: 275.8 | O28: 1022.8 | P28: 258.9 | Q28: 276.6 | R28: =P28+Q28 -> 535.5 | S28: 280.4 | T28: 299.6 | U28: 1115.5 | V28: 270.3 | W28: 271.3 | X28: =V28+W28 -> 541.6 | Y28: 243.2 | Z28: 266.3 | AA28: 1051.1 | AB28: 223.7 | AC28: 220.1 | AD28: =AB28+AC28 -> 443.8 | AE28: 208.3 | AF28: 224.6 | AG28: 876.7 | AH28: 232.8 | AI28: 233.8 | AJ28: =AH28+AI28 -> 466.6 | AK28: 232.5 | AL28: 254.8 | AM28: 953.9 | AN28: 239 | AO28: 262.6 | AP28: =AN28+AO28 -> 501.6 | AQ28: 256.2 | AR28: 263.4 | AS28: 1021.2 | AT28: 256.5 | AU28: 264.1 | AV28: =AT28+AU28 -> 520.6 | AW28: 282.9 | AX28: 301.6 | AY28: 1105.1 | AZ28: 285.1 | BA28: 263.1 | BB28: =AZ28+BA28 -> 548.2 | BC28: 263.5 | BD28: 282.8 | BE28: 1094.5 | BF28: 286.5 | BG28: 291.1 | BH28: =BF28+BG28 -> 577.6 | BI28: 287.1 | BJ28: 302.2 | BK28: 1166.9 | BL28: 308.9 | BM28: 312.5 | BN28: =BL28+BM28 -> 621.4 | BO28: 306.4 | BP28: 326.2 | BQ28: 1254 | BR28: 333.5 | BS28: 328.4 | BT28: =BR28+BS28 -> 661.9 | BU28: 329.1 | BV28: 335.2 | BW28: 1326.2 | BX28: 330.4 | BY28: 333.5 | BZ28: =BX28+BY28 -> 663.9 | CA28: 349.8 | CB28: 368.9 | CC28: 1382.6 | CD28: 343.3 | CE28: 367.6 | CF28: =CD28+CE28 -> 710.9 | CG28: 363.6 | CH28: 382.6 | CI28: 1457.1 | CJ28: 361.4 | CK28: 387.8 | CL28: =CJ28+CK28 -> 749.2 | CM28: =CG28*CK28/CE28 -> 383.5802 | CN28: =CH28*CK28/CE28 -> 403.62427 | CO28: =SUM(CJ28,CK28,CM28,CN28) -> 1536.4045 | CP28: =CO28*(1+CP29) -> 1605.5427 | CQ28: =CP28*(1+CQ29) -> 1677.7921 | CR28: =CQ28*(1+CR29) -> 1753.2927 | CS28: =CR28*(1+CS29) -> 1832.1909 | CT28: Q3/26E–Q4/26E: prior-year quarter × Q2/26 y/y growth of the segment (after the Excelitas A&D anniversary). 2027E+: prior year × (1 + scenario organic growth). | CV28: =IFERROR((CS28/CI28)^(1/5)-1,"n/m") -> 0.046878481 | CW28: =IFERROR((CI28/BE28)^(1/5)-1,"n/m") -> 0.05889944 | CX28: =IFERROR((CI28/AA28)^(1/10)-1,"n/m") -> 0.03320032 | CY28: =IFERROR((CI28/C28)^(1/19)-1,"n/m") -> n/m | DB28: 2028E | DC28: =DD28+$DC$26 -> 0.065 | DD28: 0.045 | DE28: =DD28+$DE$26 -> 0.015
B29: Net sales y/y % | D29: =IFERROR(D28/C28-1,"") | E29: =IFERROR(E28/D28-1,"") | F29: =IFERROR(F28/E28-1,"") -> -0.019664967 | G29: =IFERROR(G28/F28-1,"") -> 0.064635958 | H29: =IFERROR(H28/G28-1,"") -> 0.13084438 | I29: =IFERROR(I28/H28-1,"") -> 0.24143783 | O29: =IFERROR(O28/I28-1,"") -> 0.27103268 | P29: =IFERROR(P28/J28-1,"") -> 0.11259132 | Q29: =IFERROR(Q28/K28-1,"") -> 0.073341094 | R29: =IFERROR(R28/L28-1,"") -> 0.091965742 | S29: =IFERROR(S28/M28-1,"") -> 0.092751364 | T29: =IFERROR(T28/N28-1,"") -> 0.086294416 | U29: =IFERROR(U28/O28-1,"") -> 0.090633555 | V29: =IFERROR(V28/P28-1,"") -> 0.044032445 | ... CO29: =IFERROR(CO28/CI28-1,"") -> 0.054426231 | CP29: =CHOOSE(MATCH($CT$2,{"Bull","Base","Bear"},0),$DC$27,$DD$27,$DE$27) -> 0.045 | CQ29: =CHOOSE(MATCH($CT$2,{"Bull","Base","Bear"},0),$DC$28,$DD$28,$DE$28) -> 0.045 | CR29: =CHOOSE(MATCH($CT$2,{"Bull","Base","Bear"},0),$DC$29,$DD$29,$DE$29) -> 0.045 | CS29: =CHOOSE(MATCH($CT$2,{"Bull","Base","Bear"},0),$DC$30,$DD$30,$DE$30) -> 0.045 | CT29: 2027E–2030E: scenario lever (INST_organicGrowth, Bull/Base/Bear table →). | DB29: 2029E | DC29: =DD29+$DC$26 -> 0.065 | DD29: 0.045 | DE29: =DD29+$DE$26 -> 0.015
B30: Segment operating income (GAAP) | E30: 102.9 | F30: 95.5 | G30: 113.9 | H30: 129.3 | I30: 146 | J30: 36.6 | K30: 41.1 | L30: =J30+K30 -> 77.7 | M30: 39.9 | N30: 44.4 | O30: 162 | P30: 37.5 | Q30: 43.8 | R30: =P30+Q30 -> 81.3 | S30: 46.9 | T30: 53.4 | U30: 181.6 | V30: 42.1 | W30: 45.7 | X30: =V30+W30 -> 87.8 | Y30: 38.6 | Z30: 44.6 | AA30: 171 | AB30: 31.4 | AC30: 20.1 | AD30: =AB30+AC30 -> 51.5 | AE30: 28.1 | AF30: 30.2 | AG30: 109.8 | AH30: 30.2 | AI30: 30.5 | AJ30: =AH30+AI30 -> 60.7 | AK30: 34.6 | AL30: 30.7 | AM30: 126 | AN30: 27.8 | AO30: 40.9 | AP30: =AN30+AO30 -> 68.7 | AQ30: 35.7 | AR30: 43 | AS30: 147.4 | AT30: 39.9 | AU30: 49 | AV30: =AT30+AU30 -> 88.9 | AW30: 52 | AX30: 59.5 | AY30: 200.4 | AZ30: 50.8 | BA30: 48.5 | BB30: =AZ30+BA30 -> 99.3 | BC30: 50.7 | BD30: 63.2 | BE30: 213.2 | BF30: 59.4 | BG30: 64.6 | BH30: =BF30+BG30 -> 124 | BI30: 63 | BJ30: 66.7 | BK30: 253.7 | BL30: 71.6 | BM30: 73.6 | BN30: =BL30+BM30 -> 145.2 | BO30: 71.1 | BP30: 79 | BQ30: 295.3 | BR30: 80.7 | BS30: 81.4 | BT30: =BR30+BS30 -> 162.1 | BU30: 85.5 | BV30: 90.7 | BW30: 338.3 | BX30: 86 | BY30: 87.2 | BZ30: =BX30+BY30 -> 173.2 | CA30: 96.3 | CB30: 100.8 | CC30: 370.3 | CD30: 92.7 | CE30: 101.6 | CF30: =CD30+CE30 -> 194.3 | CG30: 98.8 | CH30: 107.3 | CI30: 400.4 | CJ30: 88.4 | CK30: 101.4 | CL30: =CJ30+CK30 -> 189.8 | CM30: =CM33-CM31-CM32 -> 93.176288 | CN30: =CN33-CN31-CN32 -> 93.588926 | CO30: =SUM(CJ30,CK30,CM30,CN30) -> 376.56521 | CP30: =CP33-CP31-CP32 -> 420.63191 | CQ30: =CQ33-CQ31-CQ32 -> 448.70435 | CR30: =CR33-CR31-CR32 -> 480.89996 | CS30: =CS33-CS31-CS32 -> 513.74377 | CT30: Forecast GAAP OI = non-GAAP OI − acquired-intangible amortization − other items. | CV30: =IFERROR((CS30/CI30)^(1/5)-1,"n/m") -> 0.051115645 | CW30: =IFERROR((CI30/BE30)^(1/5)-1,"n/m") -> 0.13433511 | CX30: =IFERROR((CI30/AA30)^(1/10)-1,"n/m") -> 0.088804221 | CY30: =IFERROR((CI30/C30)^(1/19)-1,"n/m") -> n/m | DB30: 2030E | DC30: =DD30+$DC$26 -> 0.065 | DD30: 0.045 | DE30: =DD30+$DE$26 -> 0.015
B31: (+) Acquired intangible asset amortization | AZ31: 4.8 | BA31: 5.1 | BB31: =AZ31+BA31 -> 9.9 | BC31: 5.1 | BD31: 4.8 | BE31: 19.8 | BF31: 5 | BG31: 5.2 | BH31: =BF31+BG31 -> 10.2 | BI31: 5 | BJ31: 4.9 | BK31: 20.1 | BL31: 4.9 | BM31: 4.7 | BN31: =BL31+BM31 -> 9.6 | BO31: 4 | BP31: 3.6 | BQ31: 17.2 | BR31: 3.7 | BS31: 3.5 | BT31: =BR31+BS31 -> 7.2 | BU31: 3.5 | BV31: 3.5 | BW31: 14.2 | BX31: 3.4 | BY31: 3.5 | BZ31: =BX31+BY31 -> 6.9 | CA31: 3.5 | CB31: 3.4 | CC31: 13.9 | CD31: 3.2 | CE31: 3.3 | CF31: =CD31+CE31 -> 6.5 | CG31: 3.3 | CH31: 3.1 | CI31: 12.9 | CJ31: 3.5 | CK31: 3.4 | CL31: =CJ31+CK31 -> 6.9 | CM31: =CM125*$CL$31/($CL$14+$CL$31+$CL$51+$CL$70) -> 3.4135563 | CN31: =CN125*$CL$31/($CL$14+$CL$31+$CL$51+$CL$70) -> 3.4135563 | CO31: =SUM(CJ31,CK31,CM31,CN31) -> 13.727113 | CP31: =CP371*$CL$31/($CL$14+$CL$31+$CL$51+$CL$70) -> 12.864613 | CQ31: =CQ371*$CL$31/($CL$14+$CL$31+$CL$51+$CL$70) -> 12.688468 | CR31: =CR371*$CL$31/($CL$14+$CL$31+$CL$51+$CL$70) -> 10.022007 | CS31: =CS371*$CL$31/($CL$14+$CL$31+$CL$51+$CL$70) -> 8.4306338 | CT31: Disclosed by segment from Q1/21. Forecast = amortization of existing intangibles (10-K schedule) × 1H/26 segment share.
B32: (+) Other segment non-GAAP items (inventory step-up, transaction costs) | CB32: 3 | CC32: 3 | CM32: 0 | CN32: 0 | CO32: =SUM(CJ32,CK32,CM32,CN32) -> 0 | CP32: 0 | CQ32: 0 | CR32: 0 | CS32: 0 | DB32: ADE_organicGrowth (Aerospace and Defense Electronics sales y/y) | DC32: 0.03 | DD32: Δ → | DE32: -0.04 | DF32: A&DE: defense electronics (budget growth), commercial aerospace build rates.
B33: Non-GAAP segment operating income | C33: =IF(OR(ISNUMBER(C34),ISNUMBER(C31)),C30+N(C31)+N(C32),"") | D33: =IF(OR(ISNUMBER(D34),ISNUMBER(D31)),D30+N(D31)+N(D32),"") | E33: =IF(OR(ISNUMBER(E34),ISNUMBER(E31)),E30+N(E31)+N(E32),"") | F33: =IF(OR(ISNUMBER(F34),ISNUMBER(F31)),F30+N(F31)+N(F32),"") | G33: =IF(OR(ISNUMBER(G34),ISNUMBER(G31)),G30+N(G31)+N(G32),"") | H33: =IF(OR(ISNUMBER(H34),ISNUMBER(H31)),H30+N(H31)+N(H32),"") | I33: =IF(OR(ISNUMBER(I34),ISNUMBER(I31)),I30+N(I31)+N(I32),"") | J33: =IF(OR(ISNUMBER(J34),ISNUMBER(J31)),J30+N(J31)+N(J32),"") | ... CL33: =IF(OR(ISNUMBER(CL34),ISNUMBER(CL31)),CL30+N(CL31)+N(CL32),"") -> 196.7 | CM33: =CM28*CM37 -> 96.589844 | CN33: =CN28*CN37 -> 97.002482 | CO33: =SUM(CJ33,CK33,CM33,CN33) -> 390.29233 | CP33: =CP28*CP37 -> 433.49652 | CQ33: =CQ28*CQ37 -> 461.39282 | CR33: =CR28*CR37 -> 490.92196 | CS33: =CS28*CS37 -> 522.17441 | CT33: Company non-GAAP measure from Q1/21 (segment OI excluding acquired-intangible amortization and acquisition items). Forecast = net sales × non-GAAP margin. | CV33: =IFERROR((CS33/CI33)^(1/5)-1,"n/m") -> 0.047876342 | CW33: =IFERROR((CI33/BE33)^(1/5)-1,"n/m") -> 0.12145512 | CX33: =IFERROR((CI33/AA33)^(1/10)-1,"n/m") -> n/m | CY33: =IFERROR((CI33/C33)^(1/19)-1,"n/m") -> n/m | DB33: 2027E | DC33: =DD33+$DC$32 -> 0.09 | DD33: 0.06 | DE33: =DD33+$DE$32 -> 0.02
B34: Memo: non-GAAP segment operating income as published | AZ34: 55.6 | BA34: 53.6 | BB34: =AZ34+BA34 -> 109.2 | BC34: 55.8 | BD34: 68 | BE34: 233 | BF34: 64.4 | BG34: 69.8 | BH34: =BF34+BG34 -> 134.2 | BI34: 68 | BJ34: 71.6 | BK34: 273.8 | BL34: 76.5 | BM34: 78.3 | BN34: =BL34+BM34 -> 154.8 | BO34: 75.1 | BP34: 82.6 | BQ34: 312.5 | BR34: 84.4 | BS34: 84.9 | BT34: =BR34+BS34 -> 169.3 | BU34: 89 | BV34: 94.2 | BW34: 352.5 | BX34: 89.4 | BY34: 90.7 | BZ34: =BX34+BY34 -> 180.1 | CA34: 99.8 | CB34: 107.2 | CC34: 387.2 | CD34: 95.9 | CE34: 104.9 | CF34: =CD34+CE34 -> 200.8 | CG34: 102.1 | CH34: 110.4 | CI34: 413.3 | CJ34: 91.9 | CK34: 104.8 | CL34: =CJ34+CK34 -> 196.7 | DB34: 2028E | DC34: =DD34+$DC$32 -> 0.085 | DD34: 0.055 | DE34: =DD34+$DE$32 -> 0.015
B35: Check: build vs published (should be 0) | C35: =IF(ISNUMBER(C34),ROUND(C33-C34,1),"n/p") -> n/p | D35: =IF(ISNUMBER(D34),ROUND(D33-D34,1),"n/p") -> n/p | E35: =IF(ISNUMBER(E34),ROUND(E33-E34,1),"n/p") -> n/p | F35: =IF(ISNUMBER(F34),ROUND(F33-F34,1),"n/p") -> n/p | G35: =IF(ISNUMBER(G34),ROUND(G33-G34,1),"n/p") -> n/p | H35: =IF(ISNUMBER(H34),ROUND(H33-H34,1),"n/p") -> n/p | I35: =IF(ISNUMBER(I34),ROUND(I33-I34,1),"n/p") -> n/p | J35: =IF(ISNUMBER(J34),ROUND(J33-J34,1),"n/p") -> n/p | ... CL35: =IF(ISNUMBER(CL34),ROUND(CL33-CL34,1),"n/p") -> 0 | DB35: 2029E | DC35: =DD35+$DC$32 -> 0.08 | DD35: 0.05 | DE35: =DD35+$DE$32 -> 0.01
B36: Segment operating margin (GAAP) % | C36: =IFERROR(C30/C28,"") | D36: =IFERROR(D30/D28,"") | E36: =IFERROR(E30/E28,"") -> 0.18736344 | F36: =IFERROR(F30/F28,"") -> 0.17737741 | G36: =IFERROR(G30/G28,"") -> 0.198709 | H36: =IFERROR(H30/H28,"") -> 0.19947547 | I36: =IFERROR(I30/I28,"") -> 0.18143407 | J36: =IFERROR(J30/J28,"") -> 0.15728406 | ... CS36: =IFERROR(CS30/CS28,"") -> 0.28039861 | CV36: =IFERROR(AVERAGE(CO36,CP36,CQ36,CR36,CS36),"n/m") -> 0.26584048 | CW36: =IFERROR(AVERAGE(BK36,BQ36,BW36,CC36,CI36),"n/m") -> 0.25012219 | CX36: =IFERROR(AVERAGE(AG36,AM36,AS36,AY36,BE36,BK36,BQ36,BW36,CC36,CI36),"n/m") -> 0.20284159 | CY36: =IFERROR(AVERAGE(C36,D36,E36,F36,G36,H36,I36,O36,U36,AA36,AG36,AM36,AS36,AY36,BE36,BK36,BQ36,BW36,CC36,CI36),"n/m") -> 0.19203598 | DB36: 2030E | DC36: =DD36+$DC$32 -> 0.08 | DD36: 0.05 | DE36: =DD36+$DE$32 -> 0.01
B37: Non-GAAP segment operating margin % | C37: =IFERROR(C33/C28,"") | D37: =IFERROR(D33/D28,"") | E37: =IFERROR(E33/E28,"") | F37: =IFERROR(F33/F28,"") | G37: =IFERROR(G33/G28,"") | H37: =IFERROR(H33/H28,"") | I37: =IFERROR(I33/I28,"") | J37: =IFERROR(J33/J28,"") | ... CL37: =IFERROR(CL33/CL28,"") -> 0.26254672 | CM37: =CG37+$CL$37-$CF$37+CM102 -> 0.25181134 | CN37: =CH37+$CL$37-$CF$37+CN102 -> 0.24032867 | CO37: =IFERROR(CO33/CO28,"") -> 0.25402968 | CP37: =CHOOSE(MATCH($CT$2,{"Bull","Base","Bear"},0),$DC$51,$DD$51,$DE$51) -> 0.27 | CQ37: =CHOOSE(MATCH($CT$2,{"Bull","Base","Bear"},0),$DC$52,$DD$52,$DE$52) -> 0.275 | CR37: =CHOOSE(MATCH($CT$2,{"Bull","Base","Bear"},0),$DC$53,$DD$53,$DE$53) -> 0.28 | CS37: =CHOOSE(MATCH($CT$2,{"Bull","Base","Bear"},0),$DC$54,$DD$54,$DE$54) -> 0.285 | CT37: Q3/Q4-26E: prior-year quarter margin + 1H/26 vs 1H/25 change + outlook calibration Δ. 2027E+: scenario lever (INST_margin). | CV37: =IFERROR(AVERAGE(CO37,CP37,CQ37,CR37,CS37),"n/m") -> 0.27280594 | CW37: =IFERROR(AVERAGE(BK37,BQ37,BW37,CC37,CI37),"n/m") -> 0.26266721 | CX37: =IFERROR(AVERAGE(AG37,AM37,AS37,AY37,BE37,BK37,BQ37,BW37,CC37,CI37),"n/m") -> 0.25436977 | CY37: =IFERROR(AVERAGE(C37,D37,E37,F37,G37,H37,I37,O37,U37,AA37,AG37,AM37,AS37,AY37,BE37,BK37,BQ37,BW37,CC37,CI37),"n/m") -> 0.25436977
B38: Segment operating income (GAAP) y/y % | D38: =IFERROR(D30/C30-1,"") | E38: =IFERROR(E30/D30-1,"") | F38: =IFERROR(F30/E30-1,"") -> -0.07191448 | G38: =IFERROR(G30/F30-1,"") -> 0.19267016 | H38: =IFERROR(H30/G30-1,"") -> 0.13520632 | I38: =IFERROR(I30/H30-1,"") -> 0.129157 | O38: =IFERROR(O30/I30-1,"") -> 0.10958904 | P38: =IFERROR(P30/J30-1,"") -> 0.024590164 | Q38: =IFERROR(Q30/K30-1,"") -> 0.065693431 | R38: =IFERROR(R30/L30-1,"") -> 0.046332046 | S38: =IFERROR(S30/M30-1,"") -> 0.1754386 | T38: =IFERROR(T30/N30-1,"") -> 0.2027027 | U38: =IFERROR(U30/O30-1,"") -> 0.12098765 | V38: =IFERROR(V30/P30-1,"") -> 0.12266667 | ... CO38: =IFERROR(CO30/CI30-1,"") -> -0.059527438 | CP38: =IFERROR(CP30/CO30-1,"") -> 0.11702274 | CQ38: =IFERROR(CQ30/CP30-1,"") -> 0.066738751 | CR38: =IFERROR(CR30/CQ30-1,"") -> 0.071752372 | CS38: =IFERROR(CS30/CR30-1,"") -> 0.068296567 | DB38: ES_organicGrowth (Engineered Systems sales y/y) | DC38: 0.03 | DD38: Δ → | DE38: -0.04 | DF38: Engineered Systems: US Government programs (missile defense, space), energy systems.
B39: Incremental non-GAAP margin (ΔOI / ΔSales) | D39: =IFERROR((D33-C33)/(D28-C28),"") | E39: =IFERROR((E33-D33)/(E28-D28),"") | F39: =IFERROR((F33-E33)/(F28-E28),"") | G39: =IFERROR((G33-F33)/(G28-F28),"") | H39: =IFERROR((H33-G33)/(H28-G28),"") | I39: =IFERROR((I33-H33)/(I28-H28),"") | O39: =IFERROR((O33-I33)/(O28-I28),"") | P39: =IFERROR((P33-J33)/(P28-J28),"") | Q39: =IFERROR((Q33-K33)/(Q28-K28),"") | R39: =IFERROR((R33-L33)/(R28-L28),"") | S39: =IFERROR((S33-M33)/(S28-M28),"") | T39: =IFERROR((T33-N33)/(T28-N28),"") | U39: =IFERROR((U33-O33)/(U28-O28),"") | V39: =IFERROR((V33-P33)/(V28-P28),"") | ... CO39: =IFERROR((CO33-CI33)/(CO28-CI28),"") -> -0.29011827 | CP39: =IFERROR((CP33-CO33)/(CP28-CO28),"") -> 0.6248961 | CQ39: =IFERROR((CQ33-CP33)/(CQ28-CP28),"") -> 0.38611111 | CR39: =IFERROR((CR33-CQ33)/(CR28-CQ28),"") -> 0.39111111 | CS39: =IFERROR((CS33-CR33)/(CS28-CR28),"") -> 0.39611111 | DB39: 2027E | DC39: =DD39+$DC$38 -> 0.07 | DD39: 0.04 | DE39: =DD39+$DE$38 -> 0
B40: Memo: Marine instrumentation sales | E40: 320.9 | F40: 335.1 | G40: 353.4 | H40: 404.4 | I40: 473.7 | J40: 127.1 | K40: 145.6 | L40: =J40+K40 -> 272.7 | M40: 151.6 | N40: 156.1 | O40: 580.4 | P40: 150.6 | Q40: 160.1 | R40: =P40+Q40 -> 310.7 | S40: 167.4 | T40: 176.7 | U40: 654.8 | V40: 159.5 | W40: 161.8 | X40: =V40+W40 -> 321.3 | Y40: 136.5 | Z40: 156.2 | AA40: 614 | AB40: 112.9 | AC40: 103.8 | AD40: =AB40+AC40 -> 216.7 | AE40: 97.6 | AF40: 104.4 | AG40: 418.7 | AM40: 430.7 | AS40: 433 | AY40: 450.2 | BE40: 426.3 | BF40: 102 | BG40: 104.9 | BH40: =BF40+BG40 -> 206.9 | BI40: 104.7 | BJ40: 112.5 | BK40: 424.1 | BL40: 111.9 | BM40: 115.3 | BN40: =BL40+BM40 -> 227.2 | BO40: 110 | BP40: 123.5 | BQ40: 460.7 | BR40: 128.2 | BS40: 127.4 | BT40: =BR40+BS40 -> 255.6 | BU40: 132.5 | BV40: 141.6 | BW40: 529.7 | BX40: 147.8 | BY40: 147.8 | BZ40: =BX40+BY40 -> 295.6 | CA40: 164.4 | CB40: 171.5 | CC40: 631.5 | CD40: 161.8 | CE40: 171.5 | CF40: =CD40+CE40 -> 333.3 | CG40: 169.7 | CH40: 177.1 | CI40: 680.1 | CJ40: 175.3 | CK40: 181.2 | CL40: =CJ40+CK40 -> 356.5 | DB40: 2028E | DC40: =DD40+$DC$38 -> 0.07 | DD40: 0.04 | DE40: =DD40+$DE$38 -> 0
B41: Memo: Environmental instrumentation sales | E41: 228.3 | F41: 203.3 | G41: 219.8 | H41: 243.8 | I41: 250.2 | J41: 60.1 | K41: 63 | L41: =J41+K41 -> 123.1 | M41: 57.1 | N41: 68.4 | O41: 248.6 | P41: 61.3 | Q41: 69.4 | R41: =P41+Q41 -> 130.7 | S41: 66.1 | T41: 71.6 | U41: 268.4 | V41: 67.7 | W41: 67.7 | X41: =V41+W41 -> 135.4 | Y41: 67.4 | Z41: 65.9 | AA41: 268.7 | AB41: 68.7 | AC41: 67.9 | AD41: =AB41+AC41 -> 136.6 | AE41: 63.8 | AF41: 69.7 | AG41: 270.1 | AM41: 314.3 | AS41: 339.6 | AY41: 391.4 | BE41: 411.3 | BF41: 114.8 | BG41: 112.8 | BH41: =BF41+BG41 -> 227.6 | BI41: 108 | BJ41: 110.7 | BK41: 446.3 | BL41: 114 | BM41: 115.5 | BN41: =BL41+BM41 -> 229.5 | BO41: 114.8 | BP41: 120.7 | BQ41: 465 | BR41: 117.9 | BS41: 115.3 | BT41: =BR41+BS41 -> 233.2 | BU41: 113 | BV41: 111.9 | BW41: 458.1 | BX41: 111.1 | BY41: 113.5 | BZ41: =BX41+BY41 -> 224.6 | CA41: 109 | CB41: 113.8 | CC41: 447.4 | CD41: 108.9 | CE41: 119.9 | CF41: =CD41+CE41 -> 228.8 | CG41: 117.1 | CH41: 120.7 | CI41: 466.6 | CJ41: 116.2 | CK41: 127.1 | CL41: =CJ41+CK41 -> 243.3 | DB41: 2029E | DC41: =DD41+$DC$38 -> 0.07 | DD41: 0.04 | DE41: =DD41+$DE$38 -> 0
B42: Memo: Electronic test & measurement sales | H42: 0 | I42: 80.8 | J42: 45.5 | K42: 49.1 | L42: =J42+K42 -> 94.6 | M42: 47.9 | N42: 51.3 | O42: 193.8 | P42: 47 | Q42: 47.1 | R42: =P42+Q42 -> 94.1 | S42: 46.9 | T42: 51.3 | U42: 192.3 | V42: 43.1 | W42: 41.8 | X42: =V42+W42 -> 84.9 | Y42: 39.3 | Z42: 44.2 | AA42: 168.4 | AB42: 42.1 | AC42: 48.4 | AD42: =AB42+AC42 -> 90.5 | AE42: 46.9 | AF42: 50.5 | AG42: 187.9 | AM42: 208.9 | AS42: 248.6 | AY42: 263.5 | BE42: 256.9 | BF42: 69.7 | BG42: 73.4 | BH42: =BF42+BG42 -> 143.1 | BI42: 74.4 | BJ42: 79 | BK42: 296.5 | BL42: 83 | BM42: 81.7 | BN42: =BL42+BM42 -> 164.7 | BO42: 81.6 | BP42: 82 | BQ42: 328.3 | BR42: 87.4 | BS42: 85.7 | BT42: =BR42+BS42 -> 173.1 | BU42: 83.6 | BV42: 81.7 | BW42: 338.4 | BX42: 71.5 | BY42: 72.2 | BZ42: =BX42+BY42 -> 143.7 | CA42: 76.4 | CB42: 83.6 | CC42: 303.7 | CD42: 72.6 | CE42: 76.2 | CF42: =CD42+CE42 -> 148.8 | CG42: 76.8 | CH42: 84.8 | CI42: 310.4 | CJ42: 69.9 | CK42: 79.5 | CL42: =CJ42+CK42 -> 149.4 | DB42: 2030E | DC42: =DD42+$DC$38 -> 0.07 | DD42: 0.04 | DE42: =DD42+$DE$38 -> 0
B43: Segment D&A (annual, 10-K segment note) | E43: 16.8 | F43: 16 | G43: 16.6 | H43: 17.4 | I43: 26.1 | O43: 38.2 | U43: 41.1 | AA43: 41.2 | AG43: 37.3 | AM43: 38.2 | AS43: 37 | AY43: 35.9 | BE43: 38.3 | BK43: 38.1 | BQ43: 32.6 | BW43: 27.7 | CC43: 29.2 | CI43: 27.7
B44: Segment capital expenditures (annual) | E44: 12.5 | F44: 16.1 | G44: 6.4 | H44: 9.5 | I44: 14.4 | O44: 22 | U44: 17 | AA44: 20.9 | AG44: 50.9 | AM44: 13.7 | AS44: 14.8 | AY44: 18.9 | BE44: 18 | BK44: 13.3 | BQ44: 9.3 | BW44: 14 | CC44: 15 | CI44: 15.1 | DB44: DI_margin (Digital Imaging non-GAAP OI margin) | DC44: 0.01 | DD44: Δ → | DE44: -0.02 | DF44: FY25 non-GAAP margin 22.6%; 1H/26 ~24% (mix, tariff refunds).
B45: Segment capex % of sales | C45: =IFERROR(C44/C28,"") | D45: =IFERROR(D44/D28,"") | E45: =IFERROR(E44/E28,"") -> 0.022760379 | F45: =IFERROR(F44/F28,"") -> 0.029903418 | G45: =IFERROR(G44/G28,"") -> 0.011165387 | H45: =IFERROR(H44/H28,"") -> 0.01465597 | I45: =IFERROR(I44/I28,"") -> 0.017894868 | O45: =IFERROR(O44/O28,"") -> 0.021509582 | U45: =IFERROR(U44/U28,"") -> 0.015239803 | AA45: =IFERROR(AA44/AA28,"") -> 0.019883931 | AG45: =IFERROR(AG44/AG28,"") -> 0.058058629 | AM45: =IFERROR(AM44/AM28,"") -> 0.014362092 | AS45: =IFERROR(AS44/AS28,"") -> 0.014492754 | AY45: =IFERROR(AY44/AY28,"") -> 0.017102525 | BE45: =IFERROR(BE44/BE28,"") -> 0.016445866 | BK45: =IFERROR(BK44/BK28,"") -> 0.01139772 | BQ45: =IFERROR(BQ44/BQ28,"") -> 0.0074162679 | BW45: =IFERROR(BW44/BW28,"") -> 0.010556477 | CC45: =IFERROR(CC44/CC28,"") -> 0.010849125 | CI45: =IFERROR(CI44/CI28,"") -> 0.01036305 | DB45: 2027E | DC45: =DD45+$DC$44 -> 0.255 | DD45: 0.245 | DE45: =DD45+$DE$44 -> 0.225
DB46: 2028E | DC46: =DD46+$DC$44 -> 0.26 | DD46: 0.25 | DE46: =DD46+$DE$44 -> 0.23
B47: Aerospace and Defense Electronics (aerospace & defense electronics; Excelitas A&D from Dec-2024) | CT47: AEROSPACE AND DEFENSE ELECTRONICS — modelling logic | DB47: 2029E | DC47: =DD47+$DC$44 -> 0.265 | DD47: 0.255 | DE47: =DD47+$DE$44 -> 0.235
B48: Net sales | E48: 604.1 | F48: 579.2 | G48: 614.7 | H48: 639.2 | I48: 605.3 | J48: 163.1 | K48: 169.5 | L48: =J48+K48 -> 332.6 | M48: 143.1 | N48: 149.4 | O48: 625.1 | P48: 153.3 | Q48: 152.2 | R48: =P48+Q48 -> 305.5 | S48: 151.8 | T48: 145.7 | U48: 603 | V48: 141.2 | W48: 147 | X48: =V48+W48 -> 288.2 | Y48: 151.3 | Z48: 153.9 | AA48: 593.4 | AB48: 152.6 | AC48: 158 | AD48: =AB48+AC48 -> 310.6 | AE48: 153.5 | AF48: 151.8 | AG48: 615.9 | AH48: 151.9 | AI48: 161.1 | AJ48: =AH48+AI48 -> 313 | AK48: 159.6 | AL48: 173.4 | AM48: 591.2 | AN48: 156.4 | AO48: 157.5 | AP48: =AN48+AO48 -> 313.9 | AQ48: 160.3 | AR48: 166 | AS48: 640.2 | AT48: 166.6 | AU48: 176 | AV48: =AT48+AU48 -> 342.6 | AW48: 177.1 | AX48: 170.4 | AY48: 690.1 | AZ48: 156.3 | BA48: 143.1 | BB48: =AZ48+BA48 -> 299.4 | BC48: 144.8 | BD48: 145.2 | BE48: 589.4 | BF48: 151.2 | BG48: 152.4 | BH48: =BF48+BG48 -> 303.6 | BI48: 161.8 | BJ48: 163.3 | BK48: 628.7 | BL48: 166.2 | BM48: 168.8 | BN48: =BL48+BM48 -> 335 | BO48: 169.5 | BP48: 177.9 | BQ48: 682.4 | BR48: 173.2 | BS48: 186 | BT48: =BR48+BS48 -> 359.2 | BU48: 183.3 | BV48: 184 | BW48: 726.5 | BX48: 185.7 | BY48: 194.4 | BZ48: =BX48+BY48 -> 380.1 | CA48: 200.2 | CB48: 196.5 | CC48: 776.8 | CD48: 242.5 | CE48: 264.8 | CF48: =CD48+CE48 -> 507.3 | CG48: 275.5 | CH48: 275.9 | CI48: 1058.7 | CJ48: 277.5 | CK48: 286.4 | CL48: =CJ48+CK48 -> 563.9 | CM48: =CG48*CK48/CE48 -> 297.97281 | CN48: =CH48*CK48/CE48 -> 298.40544 | CO48: =SUM(CJ48,CK48,CM48,CN48) -> 1160.2782 | CP48: =CO48*(1+CP49) -> 1229.8949 | CQ48: =CP48*(1+CQ49) -> 1297.5392 | CR48: =CQ48*(1+CR49) -> 1362.4161 | CS48: =CR48*(1+CS49) -> 1430.5369 | CT48: Q3/26E–Q4/26E: prior-year quarter × Q2/26 y/y growth of the segment (after the Excelitas A&D anniversary). 2027E+: prior year × (1 + scenario organic growth). | CV48: =IFERROR((CS48/CI48)^(1/5)-1,"n/m") -> 0.062050657 | CW48: =IFERROR((CI48/BE48)^(1/5)-1,"n/m") -> 0.12427501 | CX48: =IFERROR((CI48/AA48)^(1/10)-1,"n/m") -> 0.059601433 | CY48: =IFERROR((CI48/C48)^(1/19)-1,"n/m") -> n/m | DB48: 2030E | DC48: =DD48+$DC$44 -> 0.27 | DD48: 0.26 | DE48: =DD48+$DE$44 -> 0.24
B49: Net sales y/y % | D49: =IFERROR(D48/C48-1,"") | E49: =IFERROR(E48/D48-1,"") | F49: =IFERROR(F48/E48-1,"") -> -0.041218341 | G49: =IFERROR(G48/F48-1,"") -> 0.061291436 | H49: =IFERROR(H48/G48-1,"") -> 0.039856841 | I49: =IFERROR(I48/H48-1,"") -> -0.053035044 | O49: =IFERROR(O48/I48-1,"") -> 0.032711052 | P49: =IFERROR(P48/J48-1,"") -> -0.060085837 | Q49: =IFERROR(Q48/K48-1,"") -> -0.1020649 | R49: =IFERROR(R48/L48-1,"") -> -0.081479254 | S49: =IFERROR(S48/M48-1,"") -> 0.060796646 | T49: =IFERROR(T48/N48-1,"") -> -0.02476573 | U49: =IFERROR(U48/O48-1,"") -> -0.035354343 | V49: =IFERROR(V48/P48-1,"") -> -0.078930202 | ... CO49: =IFERROR(CO48/CI48-1,"") -> 0.095946205 | CP49: =CHOOSE(MATCH($CT$2,{"Bull","Base","Bear"},0),$DC$33,$DD$33,$DE$33) -> 0.06 | CQ49: =CHOOSE(MATCH($CT$2,{"Bull","Base","Bear"},0),$DC$34,$DD$34,$DE$34) -> 0.055 | CR49: =CHOOSE(MATCH($CT$2,{"Bull","Base","Bear"},0),$DC$35,$DD$35,$DE$35) -> 0.05 | CS49: =CHOOSE(MATCH($CT$2,{"Bull","Base","Bear"},0),$DC$36,$DD$36,$DE$36) -> 0.05 | CT49: 2027E–2030E: scenario lever (ADE_organicGrowth, Bull/Base/Bear table →).
B50: Segment operating income (GAAP) | E50: 68.7 | F50: 60.1 | G50: 57.8 | H50: 87.4 | I50: 80.5 | J50: 20.2 | K50: 20.6 | L50: =J50+K50 -> 40.8 | M50: 9.3 | N50: 15.6 | O50: 65.7 | P50: 23.8 | Q50: 22.9 | R50: =P50+Q50 -> 46.7 | S50: 21.6 | T50: 20 | U50: 88.3 | V50: 19.4 | W50: 20.6 | X50: =V50+W50 -> 40 | Y50: 23.5 | Z50: 21.3 | AA50: 84.8 | AB50: 24.1 | AC50: 28 | AD50: =AB50+AC50 -> 52.1 | AE50: 31.5 | AF50: 28.5 | AG50: 112.1 | AH50: 24.8 | AI50: 29.2 | AJ50: =AH50+AI50 -> 54 | AK50: 28.2 | AL50: 34.1 | AM50: 113 | AN50: 30.8 | AO50: 32.6 | AP50: =AN50+AO50 -> 63.4 | AQ50: 33 | AR50: 35.4 | AS50: 131.8 | AT50: 32.5 | AU50: 38.6 | AV50: =AT50+AU50 -> 71.1 | AW50: 39.5 | AX50: 32.8 | AY50: 143.4 | AZ50: 13.4 | BA50: 17.5 | BB50: =AZ50+BA50 -> 30.9 | BC50: 26.7 | BD50: 23.2 | BE50: 80.8 | BF50: 28.3 | BG50: 28.4 | BH50: =BF50+BG50 -> 56.7 | BI50: 35.9 | BJ50: 40.6 | BK50: 133.2 | BL50: 42.9 | BM50: 44.1 | BN50: =BL50+BM50 -> 87 | BO50: 44.3 | BP50: 52.8 | BQ50: 184.1 | BR50: 47 | BS50: 53.2 | BT50: =BR50+BS50 -> 100.2 | BU50: 49.4 | BV50: 50 | BW50: 199.6 | BX50: 51.9 | BY50: 57.1 | BZ50: =BX50+BY50 -> 109 | CA50: 56.3 | CB50: 56.4 | CC50: 221.7 | CD50: 55.7 | CE50: 66.6 | CF50: =CD50+CE50 -> 122.3 | CG50: 70.4 | CH50: 69.4 | CI50: 262.1 | CJ50: 71.4 | CK50: 74.5 | CL50: =CJ50+CK50 -> 145.9 | CM50: =CM53-CM51-CM52 -> 78.317838 | CN50: =CN53-CN51-CN52 -> 70.200006 | CO50: =SUM(CJ50,CK50,CM50,CN50) -> 294.41784 | CP50: =CP53-CP51-CP52 -> 323.30245 | CQ50: =CQ53-CQ51-CQ52 -> 346.42392 | CR50: =CR53-CR51-CR52 -> 373.23816 | CS50: =CS53-CS51-CS52 -> 401.04902 | CT50: Forecast GAAP OI = non-GAAP OI − acquired-intangible amortization − other items. | CV50: =IFERROR((CS50/CI50)^(1/5)-1,"n/m") -> 0.088794924 | CW50: =IFERROR((CI50/BE50)^(1/5)-1,"n/m") -> 0.26535135 | CX50: =IFERROR((CI50/AA50)^(1/10)-1,"n/m") -> 0.11945623 | CY50: =IFERROR((CI50/C50)^(1/19)-1,"n/m") -> n/m | DB50: INST_margin (Instrumentation non-GAAP OI margin) | DC50: 0.01 | DD50: Δ → | DE50: -0.02 | DF50: FY25 28.4%; 1H/26 26.3% (unfavourable mix) — recovery assumed gradual.
B51: (+) Acquired intangible asset amortization | AZ51: 0.2 | BA51: 0.2 | BB51: =AZ51+BA51 -> 0.4 | BC51: 0.3 | BD51: 0.2 | BE51: 0.9 | BF51: 0.2 | BG51: 0.2 | BH51: =BF51+BG51 -> 0.4 | BI51: 0.2 | BJ51: 0.2 | BK51: 0.8 | BL51: 0.2 | BM51: 0.2 | BN51: =BL51+BM51 -> 0.4 | BO51: 0.2 | BP51: 0.2 | BQ51: 0.8 | BR51: 0.2 | BS51: 0.2 | BT51: =BR51+BS51 -> 0.4 | BU51: 0.2 | BV51: 0.2 | BW51: 0.8 | BX51: 0.2 | BY51: 0.2 | BZ51: =BX51+BY51 -> 0.4 | CA51: 0.2 | CB51: 0.2 | CC51: 0.8 | CD51: 3.4 | CE51: 5 | CF51: =CD51+CE51 -> 8.4 | CG51: 5 | CH51: 5 | CI51: 18.4 | CJ51: 6.1 | CK51: 5.2 | CL51: =CJ51+CK51 -> 11.3 | CM51: =CM125*$CL$51/($CL$14+$CL$31+$CL$51+$CL$70) -> 5.5903169 | CN51: =CN125*$CL$51/($CL$14+$CL$31+$CL$51+$CL$70) -> 5.5903169 | CO51: =SUM(CJ51,CK51,CM51,CN51) -> 22.480634 | CP51: =CP371*$CL$51/($CL$14+$CL$31+$CL$51+$CL$70) -> 21.068134 | CQ51: =CQ371*$CL$51/($CL$14+$CL$31+$CL$51+$CL$70) -> 20.779665 | CR51: =CR371*$CL$51/($CL$14+$CL$31+$CL$51+$CL$70) -> 16.412852 | CS51: =CS371*$CL$51/($CL$14+$CL$31+$CL$51+$CL$70) -> 13.80669 | CT51: Disclosed by segment from Q1/21. Forecast = amortization of existing intangibles (10-K schedule) × 1H/26 segment share. | DB51: 2027E | DC51: =DD51+$DC$50 -> 0.28 | DD51: 0.27 | DE51: =DD51+$DE$50 -> 0.25
B52: (+) Other segment non-GAAP items (inventory step-up, transaction costs) | CD52: 3.8 | CE52: 1.8 | CF52: =CD52+CE52 -> 5.6 | CG52: 1.9 | CH52: 0.7 | CI52: 8.2 | CM52: 0 | CN52: 0 | CO52: =SUM(CJ52,CK52,CM52,CN52) -> 0 | CP52: 0 | CQ52: 0 | CR52: 0 | CS52: 0 | DB52: 2028E | DC52: =DD52+$DC$50 -> 0.285 | DD52: 0.275 | DE52: =DD52+$DE$50 -> 0.255
B53: Non-GAAP segment operating income | C53: =IF(OR(ISNUMBER(C54),ISNUMBER(C51)),C50+N(C51)+N(C52),"") | D53: =IF(OR(ISNUMBER(D54),ISNUMBER(D51)),D50+N(D51)+N(D52),"") | E53: =IF(OR(ISNUMBER(E54),ISNUMBER(E51)),E50+N(E51)+N(E52),"") | F53: =IF(OR(ISNUMBER(F54),ISNUMBER(F51)),F50+N(F51)+N(F52),"") | G53: =IF(OR(ISNUMBER(G54),ISNUMBER(G51)),G50+N(G51)+N(G52),"") | H53: =IF(OR(ISNUMBER(H54),ISNUMBER(H51)),H50+N(H51)+N(H52),"") | I53: =IF(OR(ISNUMBER(I54),ISNUMBER(I51)),I50+N(I51)+N(I52),"") | J53: =IF(OR(ISNUMBER(J54),ISNUMBER(J51)),J50+N(J51)+N(J52),"") | ... CL53: =IF(OR(ISNUMBER(CL54),ISNUMBER(CL51)),CL50+N(CL51)+N(CL52),"") -> 157.2 | CM53: =CM48*CM57 -> 83.908155 | CN53: =CN48*CN57 -> 75.790323 | CO53: =SUM(CJ53,CK53,CM53,CN53) -> 316.89848 | CP53: =CP48*CP57 -> 344.37058 | CQ53: =CQ48*CQ57 -> 367.20358 | CR53: =CR48*CR57 -> 389.65101 | CS53: =CS48*CS57 -> 414.85571 | CT53: Company non-GAAP measure from Q1/21 (segment OI excluding acquired-intangible amortization and acquisition items). Forecast = net sales × non-GAAP margin. | CV53: =IFERROR((CS53/CI53)^(1/5)-1,"n/m") -> 0.075201985 | CW53: =IFERROR((CI53/BE53)^(1/5)-1,"n/m") -> 0.28719678 | CX53: =IFERROR((CI53/AA53)^(1/10)-1,"n/m") -> n/m | CY53: =IFERROR((CI53/C53)^(1/19)-1,"n/m") -> n/m | DB53: 2029E | DC53: =DD53+$DC$50 -> 0.29 | DD53: 0.28 | DE53: =DD53+$DE$50 -> 0.26
B54: Memo: non-GAAP segment operating income as published | AZ54: 13.6 | BA54: 17.7 | BB54: =AZ54+BA54 -> 31.3 | BC54: 27 | BD54: 23.4 | BE54: 81.7 | BF54: 28.5 | BG54: 28.6 | BH54: =BF54+BG54 -> 57.1 | BI54: 36.1 | BJ54: 40.8 | BK54: 134 | BL54: 43.1 | BM54: 44.3 | BN54: =BL54+BM54 -> 87.4 | BO54: 44.5 | BP54: 53 | BQ54: 184.9 | BR54: 47.2 | BS54: 53.4 | BT54: =BR54+BS54 -> 100.6 | BU54: 49.6 | BV54: 50.2 | BW54: 200.4 | BX54: 52.1 | BY54: 57.3 | BZ54: =BX54+BY54 -> 109.4 | CA54: 56.5 | CB54: 56.6 | CC54: 222.5 | CD54: 62.9 | CE54: 73.4 | CF54: =CD54+CE54 -> 136.3 | CG54: 77.3 | CH54: 75.1 | CI54: 288.7 | CJ54: 77.5 | CK54: 79.7 | CL54: =CJ54+CK54 -> 157.2 | DB54: 2030E | DC54: =DD54+$DC$50 -> 0.295 | DD54: 0.285 | DE54: =DD54+$DE$50 -> 0.265
B55: Check: build vs published (should be 0) | C55: =IF(ISNUMBER(C54),ROUND(C53-C54,1),"n/p") -> n/p | D55: =IF(ISNUMBER(D54),ROUND(D53-D54,1),"n/p") -> n/p | E55: =IF(ISNUMBER(E54),ROUND(E53-E54,1),"n/p") -> n/p | F55: =IF(ISNUMBER(F54),ROUND(F53-F54,1),"n/p") -> n/p | G55: =IF(ISNUMBER(G54),ROUND(G53-G54,1),"n/p") -> n/p | H55: =IF(ISNUMBER(H54),ROUND(H53-H54,1),"n/p") -> n/p | I55: =IF(ISNUMBER(I54),ROUND(I53-I54,1),"n/p") -> n/p | J55: =IF(ISNUMBER(J54),ROUND(J53-J54,1),"n/p") -> n/p | ... CL55: =IF(ISNUMBER(CL54),ROUND(CL53-CL54,1),"n/p") -> 0
B56: Segment operating margin (GAAP) % | C56: =IFERROR(C50/C48,"") | D56: =IFERROR(D50/D48,"") | E56: =IFERROR(E50/E48,"") -> 0.11372289 | F56: =IFERROR(F50/F48,"") -> 0.10376381 | G56: =IFERROR(G50/G48,"") -> 0.094029608 | H56: =IFERROR(H50/H48,"") -> 0.13673342 | I56: =IFERROR(I50/I48,"") -> 0.1329919 | J56: =IFERROR(J50/J48,"") -> 0.1238504 | ... CS56: =IFERROR(CS50/CS48,"") -> 0.2803486 | CV56: =IFERROR(AVERAGE(CO56,CP56,CQ56,CR56,CS56),"n/m") -> 0.26758093 | CW56: =IFERROR(AVERAGE(BK56,BQ56,BW56,CC56,CI56),"n/m") -> 0.25787204 | CX56: =IFERROR(AVERAGE(AG56,AM56,AS56,AY56,BE56,BK56,BQ56,BW56,CC56,CI56),"n/m") -> 0.22132646 | CY56: =IFERROR(AVERAGE(C56,D56,E56,F56,G56,H56,I56,O56,U56,AA56,AG56,AM56,AS56,AY56,BE56,BK56,BQ56,BW56,CC56,CI56),"n/m") -> 0.17716385 | DB56: ADE_margin (Aerospace and Defense Electronics non-GAAP OI margin) | DC56: 0.01 | DD56: Δ → | DE56: -0.02 | DF56: FY25 27.3% (incl. Excelitas A&D).
B57: Non-GAAP segment operating margin % | C57: =IFERROR(C53/C48,"") | D57: =IFERROR(D53/D48,"") | E57: =IFERROR(E53/E48,"") | F57: =IFERROR(F53/F48,"") | G57: =IFERROR(G53/G48,"") | H57: =IFERROR(H53/H48,"") | I57: =IFERROR(I53/I48,"") | J57: =IFERROR(J53/J48,"") | ... CL57: =IFERROR(CL53/CL48,"") -> 0.27877283 | CM57: =CG57+$CL$57-$CF$57+CM102 -> 0.28159668 | CN57: =CH57+$CL$57-$CF$57+CN102 -> 0.25398439 | CO57: =IFERROR(CO53/CO48,"") -> 0.27312283 | CP57: =CHOOSE(MATCH($CT$2,{"Bull","Base","Bear"},0),$DC$57,$DD$57,$DE$57) -> 0.28 | CQ57: =CHOOSE(MATCH($CT$2,{"Bull","Base","Bear"},0),$DC$58,$DD$58,$DE$58) -> 0.283 | CR57: =CHOOSE(MATCH($CT$2,{"Bull","Base","Bear"},0),$DC$59,$DD$59,$DE$59) -> 0.286 | CS57: =CHOOSE(MATCH($CT$2,{"Bull","Base","Bear"},0),$DC$60,$DD$60,$DE$60) -> 0.29 | CT57: Q3/Q4-26E: prior-year quarter margin + 1H/26 vs 1H/25 change + outlook calibration Δ. 2027E+: scenario lever (ADE_margin). | CV57: =IFERROR(AVERAGE(CO57,CP57,CQ57,CR57,CS57),"n/m") -> 0.28242457 | CW57: =IFERROR(AVERAGE(BK57,BQ57,BW57,CC57,CI57),"n/m") -> 0.26381224 | CX57: =IFERROR(AVERAGE(AG57,AM57,AS57,AY57,BE57,BK57,BQ57,BW57,CC57,CI57),"n/m") -> 0.24294612 | CY57: =IFERROR(AVERAGE(C57,D57,E57,F57,G57,H57,I57,O57,U57,AA57,AG57,AM57,AS57,AY57,BE57,BK57,BQ57,BW57,CC57,CI57),"n/m") -> 0.24294612 | DB57: 2027E | DC57: =DD57+$DC$56 -> 0.29 | DD57: 0.28 | DE57: =DD57+$DE$56 -> 0.26
B58: Segment operating income (GAAP) y/y % | D58: =IFERROR(D50/C50-1,"") | E58: =IFERROR(E50/D50-1,"") | F58: =IFERROR(F50/E50-1,"") -> -0.12518195 | G58: =IFERROR(G50/F50-1,"") -> -0.038269551 | H58: =IFERROR(H50/G50-1,"") -> 0.51211073 | I58: =IFERROR(I50/H50-1,"") -> -0.078947368 | O58: =IFERROR(O50/I50-1,"") -> -0.18385093 | P58: =IFERROR(P50/J50-1,"") -> 0.17821782 | Q58: =IFERROR(Q50/K50-1,"") -> 0.11165049 | R58: =IFERROR(R50/L50-1,"") -> 0.14460784 | S58: =IFERROR(S50/M50-1,"") -> 1.3225806 | T58: =IFERROR(T50/N50-1,"") -> 0.28205128 | U58: =IFERROR(U50/O50-1,"") -> 0.34398782 | V58: =IFERROR(V50/P50-1,"") -> -0.18487395 | ... CO58: =IFERROR(CO50/CI50-1,"") -> 0.12330349 | CP58: =IFERROR(CP50/CO50-1,"") -> 0.098107526 | CQ58: =IFERROR(CQ50/CP50-1,"") -> 0.071516526 | CR58: =IFERROR(CR50/CQ50-1,"") -> 0.077402972 | CS58: =IFERROR(CS50/CR50-1,"") -> 0.074512371 | DB58: 2028E | DC58: =DD58+$DC$56 -> 0.293 | DD58: 0.283 | DE58: =DD58+$DE$56 -> 0.263
B59: Incremental non-GAAP margin (ΔOI / ΔSales) | D59: =IFERROR((D53-C53)/(D48-C48),"") | E59: =IFERROR((E53-D53)/(E48-D48),"") | F59: =IFERROR((F53-E53)/(F48-E48),"") | G59: =IFERROR((G53-F53)/(G48-F48),"") | H59: =IFERROR((H53-G53)/(H48-G48),"") | I59: =IFERROR((I53-H53)/(I48-H48),"") | O59: =IFERROR((O53-I53)/(O48-I48),"") | P59: =IFERROR((P53-J53)/(P48-J48),"") | Q59: =IFERROR((Q53-K53)/(Q48-K48),"") | R59: =IFERROR((R53-L53)/(R48-L48),"") | S59: =IFERROR((S53-M53)/(S48-M48),"") | T59: =IFERROR((T53-N53)/(T48-N48),"") | U59: =IFERROR((U53-O53)/(U48-O48),"") | V59: =IFERROR((V53-P53)/(V48-P48),"") | ... CO59: =IFERROR((CO53-CI53)/(CO48-CI48),"") -> 0.27760351 | CP59: =IFERROR((CP53-CO53)/(CP48-CO48),"") -> 0.39461951 | CQ59: =IFERROR((CQ53-CP53)/(CQ48-CP48),"") -> 0.33754545 | CR59: =IFERROR((CR53-CQ53)/(CR48-CQ48),"") -> 0.346 | CS59: =IFERROR((CS53-CR53)/(CS48-CR48),"") -> 0.37 | DB59: 2029E | DC59: =DD59+$DC$56 -> 0.296 | DD59: 0.286 | DE59: =DD59+$DE$56 -> 0.266
B60: Memo: Aerospace electronics sales | DB60: 2030E | DC60: =DD60+$DC$56 -> 0.3 | DD60: 0.29 | DE60: =DD60+$DE$56 -> 0.27
B61: Memo: Defense electronics sales
B62: Segment D&A (annual, 10-K segment note) | E62: 15.5 | F62: 14 | G62: 16 | H62: 15.8 | I62: 17.1 | O62: 16.5 | U62: 15.9 | AA62: 15 | AG62: 14.4 | AM62: 14 | AS62: 13.8 | AY62: 14.3 | BE62: 13.7 | BK62: 13.2 | BQ62: 12.4 | BW62: 11.5 | CC62: 10.5 | CI62: 35.9 | DB62: ES_margin (Engineered Systems non-GAAP OI margin) | DC62: 0.01 | DD62: Δ → | DE62: -0.02 | DF62: FY25 10.7%; program-mix driven.
B63: Segment capital expenditures (annual) | E63: 14.5 | F63: 8.4 | G63: 9.7 | H63: 12.5 | I63: 12.6 | O63: 15.3 | U63: 8.8 | AA63: 9.1 | AG63: 12.6 | AM63: 9.3 | AS63: 18.7 | AY63: 19 | BE63: 10.4 | BK63: 8.4 | BQ63: 8 | BW63: 10.9 | CC63: 7.2 | CI63: 19.4 | DB63: 2027E | DC63: =DD63+$DC$62 -> 0.125 | DD63: 0.115 | DE63: =DD63+$DE$62 -> 0.095
B64: Segment capex % of sales | C64: =IFERROR(C63/C48,"") | D64: =IFERROR(D63/D48,"") | E64: =IFERROR(E63/E48,"") -> 0.024002649 | F64: =IFERROR(F63/F48,"") -> 0.014502762 | G64: =IFERROR(G63/G48,"") -> 0.015780055 | H64: =IFERROR(H63/H48,"") -> 0.019555695 | I64: =IFERROR(I63/I48,"") -> 0.020816124 | O64: =IFERROR(O63/O48,"") -> 0.024476084 | U64: =IFERROR(U63/U48,"") -> 0.014593698 | AA64: =IFERROR(AA63/AA48,"") -> 0.015335356 | AG64: =IFERROR(AG63/AG48,"") -> 0.020457867 | AM64: =IFERROR(AM63/AM48,"") -> 0.015730717 | AS64: =IFERROR(AS63/AS48,"") -> 0.029209622 | AY64: =IFERROR(AY63/AY48,"") -> 0.027532242 | BE64: =IFERROR(BE63/BE48,"") -> 0.017645063 | BK64: =IFERROR(BK63/BK48,"") -> 0.013360903 | BQ64: =IFERROR(BQ63/BQ48,"") -> 0.011723329 | BW64: =IFERROR(BW63/BW48,"") -> 0.015003441 | CC64: =IFERROR(CC63/CC48,"") -> 0.0092687951 | CI64: =IFERROR(CI63/CI48,"") -> 0.01832436 | DB64: 2028E | DC64: =DD64+$DC$62 -> 0.13 | DD64: 0.12 | DE64: =DD64+$DE$62 -> 0.1
DB65: 2029E | DC65: =DD65+$DC$62 -> 0.13 | DD65: 0.12 | DE65: =DD65+$DE$62 -> 0.1
B66: Engineered Systems (engineered products & services, energy systems) | CT66: ENGINEERED SYSTEMS — modelling logic | DB66: 2030E | DC66: =DD66+$DC$62 -> 0.135 | DD66: 0.125 | DE66: =DD66+$DE$62 -> 0.105
B67: Net sales | E67: 431.3 | F67: 407.2 | G67: 333.8 | H67: 304.6 | I67: 301.4 | J67: 71.2 | K67: 69.5 | L67: =J67+K67 -> 140.7 | M67: 66.7 | N67: 68.5 | O67: 275.9 | P67: 59.4 | Q67: 64.6 | R67: =P67+Q67 -> 124 | S67: 73.3 | T67: 74.6 | U67: 271.9 | V67: 63.1 | W67: 68.6 | X67: =V67+W67 -> 131.7 | Y67: 65.2 | Z67: 77.7 | AA67: 274.6 | AB67: 64.3 | AC67: 62.2 | AD67: =AB67+AC67 -> 126.5 | AE67: 66.5 | AF67: 65.6 | AG67: 258.6 | AH67: 67.6 | AI67: 76 | AJ67: =AH67+AI67 -> 143.6 | AK67: 73.1 | AL67: 69.5 | AM67: 348.3 | AN67: 91.9 | AO67: 89.4 | AP67: =AN67+AO67 -> 181.3 | AQ67: 88.1 | AR67: 95.7 | AS67: 365.1 | AT67: 89.7 | AU67: 93.5 | AV67: =AT67+AU67 -> 183.2 | AW67: 98.2 | AX67: 94.1 | AY67: 375.5 | AZ67: 96.5 | BA67: 99.5 | BB67: =AZ67+BA67 -> 196 | BC67: 101 | BD67: 119.3 | BE67: 416.3 | BF67: 104.7 | BG67: 98 | BH67: =BF67+BG67 -> 202.7 | BI67: 102.4 | BJ67: 100.7 | BK67: 405.8 | BL67: 95.4 | BM67: 98.7 | BN67: =BL67+BM67 -> 194.1 | BO67: 109.8 | BP67: 107.4 | BQ67: 411.3 | BR67: 104.1 | BS67: 117 | BT67: =BR67+BS67 -> 221.1 | BU67: 114.3 | BV67: 103.3 | BW67: 438.7 | BX67: 93.2 | BY67: 106.8 | BZ67: =BX67+BY67 -> 200 | CA67: 125.1 | CB67: 114.7 | CC67: 439.8 | CD67: 107.1 | CE67: 110.3 | CF67: =CD67+CE67 -> 217.4 | CG67: 115 | CH67: 103.3 | CI67: 435.7 | CJ67: 104.3 | CK67: 119.6 | CL67: =CJ67+CK67 -> 223.9 | CM67: =CG67*CK67/CE67 -> 124.69628 | CN67: =CH67*CK67/CE67 -> 112.00979 | CO67: =SUM(CJ67,CK67,CM67,CN67) -> 460.60607 | CP67: =CO67*(1+CP68) -> 479.03032 | CQ67: =CP67*(1+CQ68) -> 498.19153 | CR67: =CQ67*(1+CR68) -> 518.11919 | CS67: =CR67*(1+CS68) -> 538.84396 | CT67: Q3/26E–Q4/26E: prior-year quarter × Q2/26 y/y growth of the segment (after the Excelitas A&D anniversary). 2027E+: prior year × (1 + scenario organic growth). | CV67: =IFERROR((CS67/CI67)^(1/5)-1,"n/m") -> 0.043410233 | CW67: =IFERROR((CI67/BE67)^(1/5)-1,"n/m") -> 0.0091511741 | CX67: =IFERROR((CI67/AA67)^(1/10)-1,"n/m") -> 0.047245982 | CY67: =IFERROR((CI67/C67)^(1/19)-1,"n/m") -> n/m
B68: Net sales y/y % | D68: =IFERROR(D67/C67-1,"") | E68: =IFERROR(E67/D67-1,"") | F68: =IFERROR(F67/E67-1,"") -> -0.055877579 | G68: =IFERROR(G67/F67-1,"") -> -0.1802554 | H68: =IFERROR(H67/G67-1,"") -> -0.087477531 | I68: =IFERROR(I67/H67-1,"") -> -0.010505581 | O68: =IFERROR(O67/I67-1,"") -> -0.084605176 | P68: =IFERROR(P67/J67-1,"") -> -0.16573034 | Q68: =IFERROR(Q67/K67-1,"") -> -0.070503597 | R68: =IFERROR(R67/L67-1,"") -> -0.11869225 | S68: =IFERROR(S67/M67-1,"") -> 0.098950525 | T68: =IFERROR(T67/N67-1,"") -> 0.089051095 | U68: =IFERROR(U67/O67-1,"") -> -0.014498007 | V68: =IFERROR(V67/P67-1,"") -> 0.062289562 | ... CO68: =IFERROR(CO67/CI67-1,"") -> 0.057163356 | CP68: =CHOOSE(MATCH($CT$2,{"Bull","Base","Bear"},0),$DC$39,$DD$39,$DE$39) -> 0.04 | CQ68: =CHOOSE(MATCH($CT$2,{"Bull","Base","Bear"},0),$DC$40,$DD$40,$DE$40) -> 0.04 | CR68: =CHOOSE(MATCH($CT$2,{"Bull","Base","Bear"},0),$DC$41,$DD$41,$DE$41) -> 0.04 | CS68: =CHOOSE(MATCH($CT$2,{"Bull","Base","Bear"},0),$DC$42,$DD$42,$DE$42) -> 0.04 | CT68: 2027E–2030E: scenario lever (ES_organicGrowth, Bull/Base/Bear table →). | DB68: M&A_spend (acquisition spend, $m) | DC68: 750 | DD68: Δ → | DE68: -500 | DF68: Acquisition spend ($m). Teledyne 2017–25 ex FLIR averaged ~$0.4bn p.a.; balance-sheet capacity (~1x leverage, ~$1.1bn FCF) supports $1bn+ p.a.
B69: Segment operating income (GAAP) | E69: 42 | F69: 31.3 | G69: 30.4 | H69: 28.1 | I69: 28.5 | J69: 6.4 | K69: 5.7 | L69: =J69+K69 -> 12.1 | M69: 2.7 | N69: 7.2 | O69: 22 | P69: 6.1 | Q69: 6.8 | R69: =P69+Q69 -> 12.9 | S69: 8.5 | T69: 10 | U69: 31.4 | V69: 6.7 | W69: 4.8 | X69: =V69+W69 -> 11.5 | Y69: 5.9 | Z69: 8.7 | AA69: 26.1 | AB69: 8 | AC69: 5.6 | AD69: =AB69+AC69 -> 13.6 | AE69: 8.6 | AF69: 9.9 | AG69: 32.1 | AH69: 7.4 | AI69: 7.7 | AJ69: =AH69+AI69 -> 15.1 | AK69: 8.6 | AL69: 8.3 | AM69: 35.5 | AN69: 8.9 | AO69: 8.7 | AP69: =AN69+AO69 -> 17.6 | AQ69: 9.6 | AR69: 10.7 | AS69: 37.9 | AT69: 6.4 | AU69: 9 | AV69: =AT69+AU69 -> 15.4 | AW69: 10.6 | AX69: 10.5 | AY69: 36.5 | AZ69: 11.4 | BA69: 10.8 | BB69: =AZ69+BA69 -> 22.2 | BC69: 12.5 | BD69: 15.4 | BE69: 50.1 | BF69: 14.9 | BG69: 11 | BH69: =BF69+BG69 -> 25.9 | BI69: 11.5 | BJ69: 11.2 | BK69: 48.6 | BL69: 9.4 | BM69: 8.6 | BN69: =BL69+BM69 -> 18 | BO69: 11.9 | BP69: 9.3 | BQ69: 39.2 | BR69: 10 | BS69: 11.5 | BT69: =BR69+BS69 -> 21.5 | BU69: 10.9 | BV69: 12.3 | BW69: 44.7 | BX69: 2.7 | BY69: 7.5 | BZ69: =BX69+BY69 -> 10.2 | CA69: 12.9 | CB69: 9.8 | CC69: 32.9 | CD69: 10.8 | CE69: 12.1 | CF69: =CD69+CE69 -> 22.9 | CG69: 12.2 | CH69: 11.5 | CI69: 46.6 | CJ69: 11.7 | CK69: 15.1 | CL69: =CJ69+CK69 -> 26.8 | CM69: =CM72-CM70-CM71 -> 13.887159 | CN69: =CN72-CN70-CN71 -> 10.907013 | CO69: =SUM(CJ69,CK69,CM69,CN69) -> 51.594172 | CP69: =CP72-CP70-CP71 -> 55.088486 | CQ69: =CQ72-CQ70-CQ71 -> 59.782984 | CR69: =CR72-CR70-CR71 -> 62.174303 | CS69: =CS72-CS70-CS71 -> 67.355495 | CT69: Forecast GAAP OI = non-GAAP OI − acquired-intangible amortization − other items. | CV69: =IFERROR((CS69/CI69)^(1/5)-1,"n/m") -> 0.076458826 | CW69: =IFERROR((CI69/BE69)^(1/5)-1,"n/m") -> -0.014379704 | CX69: =IFERROR((CI69/AA69)^(1/10)-1,"n/m") -> 0.05967952 | CY69: =IFERROR((CI69/C69)^(1/19)-1,"n/m") -> n/m | DB69: 2027E | DC69: =MAX(0,DD69+$DC$68) -> 1500 | DD69: 750 | DE69: =MAX(0,DD69+$DE$68) -> 250
B70: (+) Acquired intangible asset amortization | AZ70: 0 | BA70: 0 | BB70: =AZ70+BA70 -> 0 | BC70: 0 | BD70: 0 | BE70: 0 | BF70: 0 | BG70: 0 | BH70: =BF70+BG70 -> 0 | BI70: 0 | BJ70: 0 | BK70: 0 | BL70: 0 | BM70: 0 | BN70: =BL70+BM70 -> 0 | BO70: 0 | BP70: 0 | BQ70: 0 | BR70: 0 | BS70: 0 | BT70: =BR70+BS70 -> 0 | BU70: 0 | BV70: 0 | BW70: 0 | BX70: 0 | BY70: 0 | BZ70: =BX70+BY70 -> 0 | CA70: 0 | CB70: 0 | CC70: 0 | CD70: 0 | CE70: 0 | CF70: =CD70+CE70 -> 0 | CG70: 0 | CH70: 0 | CI70: 0 | CJ70: 0 | CK70: 0 | CL70: =CJ70+CK70 -> 0 | CM70: =CM125*$CL$70/($CL$14+$CL$31+$CL$51+$CL$70) -> 0 | CN70: =CN125*$CL$70/($CL$14+$CL$31+$CL$51+$CL$70) -> 0 | CO70: =SUM(CJ70,CK70,CM70,CN70) -> 0 | CP70: =CP371*$CL$70/($CL$14+$CL$31+$CL$51+$CL$70) -> 0 | CQ70: =CQ371*$CL$70/($CL$14+$CL$31+$CL$51+$CL$70) -> 0 | CR70: =CR371*$CL$70/($CL$14+$CL$31+$CL$51+$CL$70) -> 0 | CS70: =CS371*$CL$70/($CL$14+$CL$31+$CL$51+$CL$70) -> 0 | CT70: Disclosed by segment from Q1/21. Forecast = amortization of existing intangibles (10-K schedule) × 1H/26 segment share. | DB70: 2028E | DC70: =MAX(0,DD70+$DC$68) -> 1750 | DD70: 1000 | DE70: =MAX(0,DD70+$DE$68) -> 500
B71: (+) Other segment non-GAAP items (inventory step-up, transaction costs) | CM71: 0 | CN71: 0 | CO71: =SUM(CJ71,CK71,CM71,CN71) -> 0 | CP71: 0 | CQ71: 0 | CR71: 0 | CS71: 0 | DB71: 2029E | DC71: =MAX(0,DD71+$DC$68) -> 1750 | DD71: 1000 | DE71: =MAX(0,DD71+$DE$68) -> 500
B72: Non-GAAP segment operating income | C72: =IF(OR(ISNUMBER(C73),ISNUMBER(C70)),C69+N(C70)+N(C71),"") | D72: =IF(OR(ISNUMBER(D73),ISNUMBER(D70)),D69+N(D70)+N(D71),"") | E72: =IF(OR(ISNUMBER(E73),ISNUMBER(E70)),E69+N(E70)+N(E71),"") | F72: =IF(OR(ISNUMBER(F73),ISNUMBER(F70)),F69+N(F70)+N(F71),"") | G72: =IF(OR(ISNUMBER(G73),ISNUMBER(G70)),G69+N(G70)+N(G71),"") | H72: =IF(OR(ISNUMBER(H73),ISNUMBER(H70)),H69+N(H70)+N(H71),"") | I72: =IF(OR(ISNUMBER(I73),ISNUMBER(I70)),I69+N(I70)+N(I71),"") | J72: =IF(OR(ISNUMBER(J73),ISNUMBER(J70)),J69+N(J70)+N(J71),"") | ... CL72: =IF(OR(ISNUMBER(CL73),ISNUMBER(CL70)),CL69+N(CL70)+N(CL71),"") -> 26.8 | CM72: =CM67*CM76 -> 13.887159 | CN72: =CN67*CN76 -> 10.907013 | CO72: =SUM(CJ72,CK72,CM72,CN72) -> 51.594172 | CP72: =CP67*CP76 -> 55.088486 | CQ72: =CQ67*CQ76 -> 59.782984 | CR72: =CR67*CR76 -> 62.174303 | CS72: =CS67*CS76 -> 67.355495 | CT72: Company non-GAAP measure from Q1/21 (segment OI excluding acquired-intangible amortization and acquisition items). Forecast = net sales × non-GAAP margin. | CV72: =IFERROR((CS72/CI72)^(1/5)-1,"n/m") -> 0.076458826 | CW72: =IFERROR((CI72/BE72)^(1/5)-1,"n/m") -> -0.014379704 | CX72: =IFERROR((CI72/AA72)^(1/10)-1,"n/m") -> n/m | CY72: =IFERROR((CI72/C72)^(1/19)-1,"n/m") -> n/m | DB72: 2030E | DC72: =MAX(0,DD72+$DC$68) -> 1750 | DD72: 1000 | DE72: =MAX(0,DD72+$DE$68) -> 500
B73: Memo: non-GAAP segment operating income as published | AZ73: 11.4 | BA73: 10.8 | BB73: =AZ73+BA73 -> 22.2 | BC73: 12.5 | BD73: 15.4 | BE73: 50.1 | BF73: 14.9 | BG73: 11 | BH73: =BF73+BG73 -> 25.9 | BI73: 11.5 | BJ73: 11.2 | BK73: 48.6 | BL73: 9.4 | BM73: 8.6 | BN73: =BL73+BM73 -> 18 | BO73: 11.9 | BP73: 9.3 | BQ73: 39.2 | BR73: 10 | BS73: 11.5 | BT73: =BR73+BS73 -> 21.5 | BU73: 10.9 | BV73: 12.3 | BW73: 44.7 | BX73: 2.7 | BY73: 7.5 | BZ73: =BX73+BY73 -> 10.2 | CA73: 12.9 | CB73: 9.8 | CC73: 32.9 | CD73: 10.8 | CE73: 12.1 | CF73: =CD73+CE73 -> 22.9 | CG73: 12.2 | CH73: 11.5 | CI73: 46.6 | CJ73: 11.7 | CK73: 15.1 | CL73: =CJ73+CK73 -> 26.8
B74: Check: build vs published (should be 0) | C74: =IF(ISNUMBER(C73),ROUND(C72-C73,1),"n/p") -> n/p | D74: =IF(ISNUMBER(D73),ROUND(D72-D73,1),"n/p") -> n/p | E74: =IF(ISNUMBER(E73),ROUND(E72-E73,1),"n/p") -> n/p | F74: =IF(ISNUMBER(F73),ROUND(F72-F73,1),"n/p") -> n/p | G74: =IF(ISNUMBER(G73),ROUND(G72-G73,1),"n/p") -> n/p | H74: =IF(ISNUMBER(H73),ROUND(H72-H73,1),"n/p") -> n/p | I74: =IF(ISNUMBER(I73),ROUND(I72-I73,1),"n/p") -> n/p | J74: =IF(ISNUMBER(J73),ROUND(J72-J73,1),"n/p") -> n/p | ... CL74: =IF(ISNUMBER(CL73),ROUND(CL72-CL73,1),"n/p") -> 0 | DB74: Buybacks ($m) | DC74: 250 | DD74: Δ → | DE74: -250 | DF74: Repurchases are opportunistic (M&A first).
B75: Segment operating margin (GAAP) % | C75: =IFERROR(C69/C67,"") | D75: =IFERROR(D69/D67,"") | E75: =IFERROR(E69/E67,"") -> 0.097380014 | F75: =IFERROR(F69/F67,"") -> 0.076866405 | G75: =IFERROR(G69/G67,"") -> 0.091072499 | H75: =IFERROR(H69/H67,"") -> 0.092252134 | I75: =IFERROR(I69/I67,"") -> 0.094558726 | J75: =IFERROR(J69/J67,"") -> 0.08988764 | ... CS75: =IFERROR(CS69/CS67,"") -> 0.125 | CV75: =IFERROR(AVERAGE(CO75,CP75,CQ75,CR75,CS75),"n/m") -> 0.11840273 | CW75: =IFERROR(AVERAGE(BK75,BQ75,BW75,CC75,CI75),"n/m") -> 0.0997448 | CX75: =IFERROR(AVERAGE(AG75,AM75,AS75,AY75,BE75,BK75,BQ75,BW75,CC75,CI75),"n/m") -> 0.10461344 | CY75: =IFERROR(AVERAGE(C75,D75,E75,F75,G75,H75,I75,O75,U75,AA75,AG75,AM75,AS75,AY75,BE75,BK75,BQ75,BW75,CC75,CI75),"n/m") -> 0.099363009 | DB75: 2H/26E | DC75: =MAX(0,DD75+$DC$74) -> 250 | DD75: 0 | DE75: =MAX(0,DD75+$DE$74) -> 0
B76: Non-GAAP segment operating margin % | C76: =IFERROR(C72/C67,"") | D76: =IFERROR(D72/D67,"") | E76: =IFERROR(E72/E67,"") | F76: =IFERROR(F72/F67,"") | G76: =IFERROR(G72/G67,"") | H76: =IFERROR(H72/H67,"") | I76: =IFERROR(I72/I67,"") | J76: =IFERROR(J72/J67,"") | ... CL76: =IFERROR(CL72/CL67,"") -> 0.11969629 | CM76: =CG76+$CL$76-$CF$76+CM102 -> 0.11136786 | CN76: =CH76+$CL$76-$CF$76+CN102 -> 0.097375535 | CO76: =IFERROR(CO72/CO67,"") -> 0.11201366 | CP76: =CHOOSE(MATCH($CT$2,{"Bull","Base","Bear"},0),$DC$63,$DD$63,$DE$63) -> 0.115 | CQ76: =CHOOSE(MATCH($CT$2,{"Bull","Base","Bear"},0),$DC$64,$DD$64,$DE$64) -> 0.12 | CR76: =CHOOSE(MATCH($CT$2,{"Bull","Base","Bear"},0),$DC$65,$DD$65,$DE$65) -> 0.12 | CS76: =CHOOSE(MATCH($CT$2,{"Bull","Base","Bear"},0),$DC$66,$DD$66,$DE$66) -> 0.125 | CT76: Q3/Q4-26E: prior-year quarter margin + 1H/26 vs 1H/25 change + outlook calibration Δ. 2027E+: scenario lever (ES_margin). | CV76: =IFERROR(AVERAGE(CO76,CP76,CQ76,CR76,CS76),"n/m") -> 0.11840273 | CW76: =IFERROR(AVERAGE(BK76,BQ76,BW76,CC76,CI76),"n/m") -> 0.0997448 | CX76: =IFERROR(AVERAGE(AG76,AM76,AS76,AY76,BE76,BK76,BQ76,BW76,CC76,CI76),"n/m") -> 0.10317832 | CY76: =IFERROR(AVERAGE(C76,D76,E76,F76,G76,H76,I76,O76,U76,AA76,AG76,AM76,AS76,AY76,BE76,BK76,BQ76,BW76,CC76,CI76),"n/m") -> 0.10317832 | DB76: 2027E | DC76: =MAX(0,DD76+$DC$74) -> 500 | DD76: 250 | DE76: =MAX(0,DD76+$DE$74) -> 0
B77: Segment operating income (GAAP) y/y % | D77: =IFERROR(D69/C69-1,"") | E77: =IFERROR(E69/D69-1,"") | F77: =IFERROR(F69/E69-1,"") -> -0.2547619 | G77: =IFERROR(G69/F69-1,"") -> -0.028753994 | H77: =IFERROR(H69/G69-1,"") -> -0.075657895 | I77: =IFERROR(I69/H69-1,"") -> 0.014234875 | O77: =IFERROR(O69/I69-1,"") -> -0.22807018 | P77: =IFERROR(P69/J69-1,"") -> -0.046875 | Q77: =IFERROR(Q69/K69-1,"") -> 0.19298246 | R77: =IFERROR(R69/L69-1,"") -> 0.066115702 | S77: =IFERROR(S69/M69-1,"") -> 2.1481481 | T77: =IFERROR(T69/N69-1,"") -> 0.38888889 | U77: =IFERROR(U69/O69-1,"") -> 0.42727273 | V77: =IFERROR(V69/P69-1,"") -> 0.098360656 | ... CO77: =IFERROR(CO69/CI69-1,"") -> 0.10717108 | CP77: =IFERROR(CP69/CO69-1,"") -> 0.06772692 | CQ77: =IFERROR(CQ69/CP69-1,"") -> 0.085217391 | CR77: =IFERROR(CR69/CQ69-1,"") -> 0.04 | CS77: =IFERROR(CS69/CR69-1,"") -> 0.083333333 | DB77: 2028E | DC77: =MAX(0,DD77+$DC$74) -> 500 | DD77: 250 | DE77: =MAX(0,DD77+$DE$74) -> 0
B78: Incremental non-GAAP margin (ΔOI / ΔSales) | D78: =IFERROR((D72-C72)/(D67-C67),"") | E78: =IFERROR((E72-D72)/(E67-D67),"") | F78: =IFERROR((F72-E72)/(F67-E67),"") | G78: =IFERROR((G72-F72)/(G67-F67),"") | H78: =IFERROR((H72-G72)/(H67-G67),"") | I78: =IFERROR((I72-H72)/(I67-H67),"") | O78: =IFERROR((O72-I72)/(O67-I67),"") | P78: =IFERROR((P72-J72)/(P67-J67),"") | Q78: =IFERROR((Q72-K72)/(Q67-K67),"") | R78: =IFERROR((R72-L72)/(R67-L67),"") | S78: =IFERROR((S72-M72)/(S67-M67),"") | T78: =IFERROR((T72-N72)/(T67-N67),"") | U78: =IFERROR((U72-O72)/(U67-O67),"") | V78: =IFERROR((V72-P72)/(V67-P67),"") | ... CO78: =IFERROR((CO72-CI72)/(CO67-CI67),"") -> 0.20052024 | CP78: =IFERROR((CP72-CO72)/(CP67-CO67),"") -> 0.18965851 | CQ78: =IFERROR((CQ72-CP72)/(CQ67-CP67),"") -> 0.245 | CR78: =IFERROR((CR72-CQ72)/(CR67-CQ67),"") -> 0.12 | CS78: =IFERROR((CS72-CR72)/(CS67-CR67),"") -> 0.25 | DB78: 2029E | DC78: =MAX(0,DD78+$DC$74) -> 500 | DD78: 250 | DE78: =MAX(0,DD78+$DE$74) -> 0
B79: Memo: Engineered products & services sales | E79: 361.2 | F79: 346.9 | G79: 279.9 | H79: 246.2 | I79: 241.3 | J79: 58.6 | K79: 53.7 | L79: =J79+K79 -> 112.3 | M79: 51.1 | N79: 54.1 | O79: 217.5 | P79: 47.6 | Q79: 50.3 | R79: =P79+Q79 -> 97.9 | S79: 57.1 | T79: 56.4 | U79: 211.4 | V79: 49.1 | W79: 53.5 | X79: =V79+W79 -> 102.6 | Y79: 53.1 | Z79: 59.7 | AA79: 215.4 | AB79: 52.8 | AC79: 49.5 | AD79: =AB79+AC79 -> 102.3 | AE79: 51.3 | DB79: 2030E | DC79: =MAX(0,DD79+$DC$74) -> 500 | DD79: 250 | DE79: =MAX(0,DD79+$DE$74) -> 0
B80: Memo: Energy systems sales | E80: 38.3 | F80: 31.8 | G80: 36.9 | H80: 34.6 | I80: 35.5 | J80: 6.6 | K80: 7.1 | L80: =J80+K80 -> 13.7 | M80: 9.2 | N80: 9.5 | O80: 32.4 | P80: 5.7 | Q80: 7.6 | R80: =P80+Q80 -> 13.3 | S80: 10 | T80: 10.7 | U80: 34 | V80: 8.4 | W80: 11.1 | X80: =V80+W80 -> 19.5 | Y80: 8 | Z80: 13 | AA80: 40.5 | AB80: 6.5 | AC80: 9.3 | AD80: =AB80+AC80 -> 15.8 | AE80: 10.9
B81: Segment D&A (annual, 10-K segment note) | E81: 2.6 | F81: 2.7 | G81: 3.1 | H81: 4 | I81: 4.4 | O81: 4.2 | U81: 3.7 | AA81: 3.5 | AG81: 4.1 | AM81: 4.6 | AS81: 4.3 | AY81: 6 | BE81: 9.2 | BK81: 7.2 | BQ81: 4.4 | BW81: 4.4 | CC81: 4.6 | CI81: 4.6 | DB81: Min. net debt / adj. EBITDA (x) — buyback plug | DC81: 1.5 | DD81: 1 | DE81: 1 | DF81: Surplus cash above this leverage floor goes to buybacks (Model row 390–393).
B82: Segment capital expenditures (annual) | E82: 4 | F82: 3.3 | G82: 3.6 | H82: 5.9 | I82: 4.2 | O82: 3.6 | U82: 4.3 | AA82: 5.7 | AG82: 5.9 | AM82: 7.4 | AS82: 13.6 | AY82: 3.6 | BE82: 7.5 | BK82: 12.9 | BQ82: 5.3 | BW82: 3.4 | CC82: 2.4 | CI82: 4.7
B83: Segment capex % of sales | C83: =IFERROR(C82/C67,"") | D83: =IFERROR(D82/D67,"") | E83: =IFERROR(E82/E67,"") -> 0.009274287 | F83: =IFERROR(F82/F67,"") -> 0.0081041257 | G83: =IFERROR(G82/G67,"") -> 0.010784901 | H83: =IFERROR(H82/H67,"") -> 0.019369665 | I83: =IFERROR(I82/I67,"") -> 0.01393497 | O83: =IFERROR(O82/O67,"") -> 0.013048206 | U83: =IFERROR(U82/U67,"") -> 0.015814638 | AA83: =IFERROR(AA82/AA67,"") -> 0.020757465 | AG83: =IFERROR(AG82/AG67,"") -> 0.022815159 | AM83: =IFERROR(AM82/AM67,"") -> 0.021246052 | AS83: =IFERROR(AS82/AS67,"") -> 0.037250068 | AY83: =IFERROR(AY82/AY67,"") -> 0.009587217 | BE83: =IFERROR(BE82/BE67,"") -> 0.018015854 | BK83: =IFERROR(BK82/BK67,"") -> 0.031789059 | BQ83: =IFERROR(BQ82/BQ67,"") -> 0.012885971 | BW83: =IFERROR(BW82/BW67,"") -> 0.007750171 | CC83: =IFERROR(CC82/CC67,"") -> 0.0054570259 | CI83: =IFERROR(CI82/CI67,"") -> 0.010787239
B85: Legacy segments (as originally reported, FY2006–07; superseded by the FY2010 10-K recast) | CT85: LEGACY SEGMENTS — memo only (not comparable with the current basis)
B86: Electronics and Communications — net sales | C86: 899.4 | D86: 1071.6 | E86: 1276.6 | F86: 1232.2
B87: Electronics and Communications — operating profit | C87: 109.3 | D87: 143.2 | E87: 183 | F87: 163.9
B88: Systems Engineering Solutions / Engineered Systems — net sales | C88: 283 | D88: 301.7 | E88: 361.2 | F88: 347
B89: Systems Engineering Solutions / Engineered Systems — operating profit | C89: 24.5 | D89: 26.2 | E89: 35 | F89: 31.5
B90: Aerospace Engines and Components (piston engines sold Apr-2011) — net sales | C90: 181.6 | D90: 180.7 | E90: 171 | F90: 113.1
B91: Aerospace Engines and Components (piston engines sold Apr-2011) — operating profit | C91: 15.5 | D91: 19.2 | E91: -9.7 | F91: -5.4
B92: Energy (and Power) Systems — net sales | C92: 69.2 | D92: 68.3 | E92: 84.2 | F92: 72.9
B93: Energy (and Power) Systems — operating profit | C93: 6 | D93: 6.3 | E93: 10.2 | F93: 3.3
B94: Corporate expense (legacy basis) | C94: 27.7 | D94: 32.6 | E94: 29.6 | F94: 27.3
B96: Corporate & reconciling items | CT96: CORPORATE — modelling logic
B97: Corporate expense (GAAP) | E97: 29.6 | F97: 27.3 | G97: 28.8 | H97: 33.7 | I97: 36.7 | J97: 9.5 | K97: 10.4 | L97: =J97+K97 -> 19.9 | M97: 10.4 | N97: 7.3 | O97: 37.6 | P97: 11.1 | Q97: 10.9 | R97: =P97+Q97 -> 22 | S97: 10.6 | T97: 11.3 | U97: 43.9 | V97: 10.2 | W97: 11 | X97: =V97+W97 -> 21.2 | Y97: 8.9 | Z97: 10.1 | AA97: 40.2 | AB97: 10.8 | AC97: 10.8 | AD97: =AB97+AC97 -> 21.6 | AE97: 11.1 | AF97: 13.4 | AG97: 46.1 | AH97: 22.7 | AI97: 12.6 | AJ97: =AH97+AI97 -> 35.3 | AK97: 13.3 | AL97: 14.4 | AM97: 63 | AN97: 12.9 | AO97: 13.8 | AP97: =AN97+AO97 -> 26.7 | AQ97: 15.1 | AR97: 14.2 | AS97: 56 | AT97: 18.1 | AU97: 16.3 | AV97: =AT97+AU97 -> 34.4 | AW97: 14.6 | AX97: 16.1 | AY97: 65.1 | AZ97: 15.4 | BA97: 13.8 | BB97: =AZ97+BA97 -> 29.2 | BC97: 12.9 | BD97: 14.7 | BE97: 56.8 | BF97: 19.4 | BG97: 84.2 | BH97: =BF97+BG97 -> 103.6 | BI97: 15.7 | BJ97: 17.5 | BK97: 136.8 | BL97: 16.1 | BM97: 14.7 | BN97: =BL97+BM97 -> 30.8 | BO97: 15.8 | BP97: 19.3 | BQ97: 65.9 | BR97: 17.4 | BS97: 14.6 | BT97: =BR97+BS97 -> 32 | BU97: 17.8 | BV97: 15.8 | BW97: 65.6 | BX97: 20.1 | BY97: 18.3 | BZ97: =BX97+BY97 -> 38.4 | CA97: 18.7 | CB97: 20.7 | CC97: 77.8 | CD97: 22.2 | CE97: 21.7 | CF97: =CD97+CE97 -> 43.9 | CG97: 22 | CH97: 21.6 | CI97: 87.5 | CJ97: 19 | CK97: 28 | CL97: =CJ97+CK97 -> 47 | CM97: =CM99+CM98 -> 23.8 | CN97: =CN99+CN98 -> 23.8 | CO97: =SUM(CJ97,CK97,CM97,CN97) -> 94.6 | CP97: =CP99+CP98 -> 101.92993 | CQ97: =CQ99+CQ98 -> 109.42422 | CR97: =CR99+CR98 -> 117.37569 | CS97: =CS99+CS98 -> 126.47988 | CT97: Forecast = non-GAAP corporate expense + corporate adjusting items.
B98: Corporate non-GAAP items (transaction & integration costs) | BF98: 5.9 | BG98: 70.5 | BH98: =BF98+BG98 -> 76.4 | BI98: 0.3 | BJ98: 0.4 | BK98: 77.1 | CD98: 3.6 | CE98: 1.3 | CF98: =CD98+CE98 -> 4.9 | CG98: 0.2 | CH98: 0.3 | CI98: 5.4 | CJ98: 0.2 | CK98: 0.2 | CL98: =CJ98+CK98 -> 0.4 | CM98: 0.5 | CN98: 0.5 | CO98: =SUM(CJ98,CK98,CM98,CN98) -> 1.4 | CP98: 5 | CQ98: 5 | CR98: 5 | CS98: 5 | CT98: Acquisition transaction / integration costs recorded at corporate (input).
B99: Non-GAAP corporate expense | C99: =IF(ISNUMBER(C97),C97-N(C98),"") | D99: =IF(ISNUMBER(D97),D97-N(D98),"") | E99: =IF(ISNUMBER(E97),E97-N(E98),"") -> 29.6 | F99: =IF(ISNUMBER(F97),F97-N(F98),"") -> 27.3 | G99: =IF(ISNUMBER(G97),G97-N(G98),"") -> 28.8 | H99: =IF(ISNUMBER(H97),H97-N(H98),"") -> 33.7 | I99: =IF(ISNUMBER(I97),I97-N(I98),"") -> 36.7 | J99: =IF(ISNUMBER(J97),J97-N(J98),"") -> 9.5 | ... CL99: =IF(ISNUMBER(CL97),CL97-N(CL98),"") -> 46.6 | CM99: =CL99/2 -> 23.3 | CN99: =CL99/2 -> 23.3 | CO99: =SUM(CJ99,CK99,CM99,CN99) -> 93.2 | CP99: =CP152*CP100 -> 96.929929 | CQ99: =CQ152*CQ100 -> 104.42422 | CR99: =CR152*CR100 -> 112.37569 | CS99: =CS152*CS100 -> 121.47988 | CT99: Q3/Q4-26E at the 1H/26 run-rate; 2027E+: % of sales input.
B100: Non-GAAP corporate expense % of sales | C100: =IFERROR(C99/C152,"") | D100: =IFERROR(D99/D152,"") | E100: =IFERROR(E99/E152,"") -> 0.017189315 | F100: =IFERROR(F99/F152,"") -> 0.016524423 | G100: =IFERROR(G99/G152,"") -> 0.017516117 | H100: =IFERROR(H99/H152,"") -> 0.017354138 | I100: =IFERROR(I99/I152,"") -> 0.017251916 | J100: =IFERROR(J99/J152,"") -> 0.016684229 | ... CO100: =IFERROR(CO99/CO152,"") -> 0.013939392 | CP100: 0.0135 | CQ100: 0.0133 | CR100: 0.0131 | CS100: 0.013
B101: Other reconciling items to operating income (signed) | E101: 0 | F101: 0 | G101: 0 | H101: 0 | I101: 0 | CM101: 0 | CN101: 0 | CO101: =SUM(CJ101,CK101,CM101,CN101) -> 0 | CP101: 0 | CQ101: 0 | CR101: 0 | CS101: 0
B102: Outlook calibration: Δ non-GAAP margin applied to all segments (Q3/Q4-26E) | CM102: =((CM103+CM170)/(1-$DD$16)+CM161-CM162-CM163+CM99-CM101-(CM11*(CG20+$CL$20-$CF$20)+CM28*(CG37+$CL$37-$CF$37)+CM48*(CG57+$CL$57-$CF$57)+CM67*(CG76+$CL$76-$CF$76)))/(CM11+CM28+CM48+CM67) -> -0.0090795987 | CN102: =((CN103+CN170)/(1-$DD$16)+CN161-CN162-CN163+CN99-CN101-(CN11*(CH20+$CL$20-$CF$20)+CN28*(CH37+$CL$37-$CF$37)+CN48*(CH57+$CL$57-$CF$57)+CN67*(CH76+$CL$76-$CF$76)))/(CN11+CN28+CN48+CN67) -> -0.028311205 | CO102: =SUM(CJ102,CK102,CM102,CN102) -> -0.037390804 | CT102: Solves the margin shift (vs prior-year quarter + 1H/26 drift) so that non-GAAP net income equals the FY26 / Q3 non-GAAP EPS outlook (scenario: high / mid / low) × diluted shares.
...

Sheet Bull-Base-Bear
B2: Teledyne Technologies (TDY) — Bull / Base / Bear Case P&L Summary | J2: Share price ($): | K2: =Model!$CO$432 -> 615
B3: Non-GAAP figures (company current definition) · USD millions · Live panel linked to Model — toggle scenario via Model!CT2. Bull and Bear panels are value snapshots generated from the Model with the switch set to each case. | J3: As of: | K3: =TODAY() -> 46299
B5: Scenario: | C5: =Model!CT2 -> Base | N5: Scenario: | O5: Bull | P5: Snapshot (values) — Model run with switch = Bull | Z5: Scenario: | AA5: Bear | AB5: Snapshot (values) — Model run with switch = Bear
B7: (USDm, except EPS and shares) | C7: 2025A | D7: 2026E | E7: 2027E | F7: 2028E | G7: 2029E | H7: 2030E | I7: 25-'30 CAGR | J7: LT Hist Avg | K7: LT Hist Min | L7: LT Hist Max | N7: (USDm, except EPS and shares) | O7: 2025A | P7: 2026E | Q7: 2027E | R7: 2028E | S7: 2029E | T7: 2030E | U7: 25-'30 CAGR | V7: LT Hist Avg | W7: LT Hist Min | X7: LT Hist Max | Z7: (USDm, except EPS and shares) | AA7: 2025A | AB7: 2026E | AC7: 2027E | AD7: 2028E | AE7: 2029E | AF7: 2030E | AG7: 25-'30 CAGR | AH7: LT Hist Avg | AI7: LT Hist Min | AJ7: LT Hist Max
B9: Net Sales | C9: =Model!CI152 -> 6115.4 | D9: =Model!CO152 -> 6686.0877 | E9: =Model!CP152 -> 7179.9947 | F9: =Model!CQ152 -> 7851.4452 | G9: =Model!CR152 -> 8578.2966 | H9: =Model!CS152 -> 9344.6061 | I9: =IFERROR((H9/C9)^(1/5)-1,"n/m") -> 0.088496974 | N9: Net Sales | O9: 6115.4 | P9: 6686.0877 | Q9: 7490.2133 | R9: 8637.18 | S9: 9881.1415 | T9: 11209.549 | U9: 0.12884069 | Z9: Net Sales | AA9: 6115.4 | AB9: 6686.0877 | AC9: 6844.5819 | AD9: 7069.7166 | AE9: 7323.9719 | AF9: 7589.9868 | AG9: 0.044150812
B10: Net sales y/y % | D10: =IFERROR(D9/C9-1,"") -> 0.093319759 | E10: =IFERROR(E9/D9-1,"") -> 0.073870864 | F10: =IFERROR(F9/E9-1,"") -> 0.093516851 | G10: =IFERROR(G9/F9-1,"") -> 0.09257549 | H10: =IFERROR(H9/G9-1,"") -> 0.089331197 | N10: Net sales y/y % | P10: 0.093319759 | Q10: 0.12026849 | R10: 0.1531287 | S10: 0.14402403 | T10: 0.13443867 | Z10: Net sales y/y % | AB10: 0.093319759 | AC10: 0.023705085 | AD10: 0.032892387 | AE10: 0.035964004 | AF10: 0.036321127
B11: Organic growth % | C11: =Model!CI247 -> 0.030917108 | D11: =Model!CO247 -> 0.083263181 | E11: =Model!CP247 -> 0.055175327 | F11: =Model!CQ247 -> 0.052894722 | G11: =Model!CR247 -> 0.050120461 | H11: =Model!CS247 -> 0.050473444 | N11: Organic growth % | O11: 0.030917108 | P11: 0.083263181 | Q11: 0.082877414 | R11: 0.080812116 | S11: 0.076486557 | T11: 0.075403658 | Z11: Organic growth % | AA11: 0.030917108 | AB11: 0.083263181 | AC11: 0.017473239 | AD11: 0.014629767 | AE11: 0.012389273 | AF11: 0.013564805
B12: Non-GAAP Operating Income | C12: =Model!CI200 -> 1380 | D12: =Model!CO200 -> 1508.7264 | E12: =Model!CP200 -> 1677.4547 | F12: =Model!CQ200 -> 1856.8524 | G12: =Model!CR200 -> 2047.1616 | H12: =Model!CS200 -> 2252.5574 | I12: =IFERROR((H12/C12)^(1/5)-1,"n/m") -> 0.10295897 | N12: Non-GAAP Operating Income | O12: 1380 | P12: 1509.911 | Q12: 1816.2376 | R12: 2101.7855 | S12: 2409.556 | T12: 2745.51 | U12: 0.14748968 | Z12: Non-GAAP Operating Income | AA12: 1380 | AB12: 1502.7551 | AC12: 1467.1168 | AD12: 1546.1906 | AE12: 1628.4057 | AF12: 1716.413 | AG12: 0.044596439
B13: Non-GAAP operating margin % | C13: =IFERROR(C12/C9,"") -> 0.22565981 | D13: =IFERROR(D12/D9,"") -> 0.22565161 | E13: =IFERROR(E12/E9,"") -> 0.23362896 | F13: =IFERROR(F12/F9,"") -> 0.23649817 | G13: =IFERROR(G12/G9,"") -> 0.2386443 | H13: =IFERROR(H12/H9,"") -> 0.24105429 | J13: =IFERROR(AVERAGE(Model!C201,Model!D201,Model!E201,Model!F201,Model!G201,Model!H201,Model!I201,Model!O201,Model!U201,Model!AA201,Model!AG201,Model!AM201,Model!AS201,Model!AY201,Model!BE201,Model!BK201,Model!BQ201,Model!BW201,Model!CC201,Model!CI201),"") -> 0.15299587 | K13: =IFERROR(MIN(Model!C201,Model!D201,Model!E201,Model!F201,Model!G201,Model!H201,Model!I201,Model!O201,Model!U201,Model!AA201,Model!AG201,Model!AM201,Model!AS201,Model!AY201,Model!BE201,Model!BK201,Model!BQ201,Model!BW201,Model!CC201,Model!CI201),"") -> 0.092659782 | L13: =IFERROR(MAX(Model!C201,Model!D201,Model!E201,Model!F201,Model!G201,Model!H201,Model!I201,Model!O201,Model!U201,Model!AA201,Model!AG201,Model!AM201,Model!AS201,Model!AY201,Model!BE201,Model!BK201,Model!BQ201,Model!BW201,Model!CC201,Model!CI201),"") -> 0.22565981 | N13: Non-GAAP operating margin % | O13: 0.22565981 | P13: 0.22582878 | Q13: 0.24248142 | R13: 0.24334163 | S13: 0.24385401 | T13: 0.244926 | V13: 0.15299587 | W13: 0.092659782 | X13: 0.22565981 | Z13: Non-GAAP operating margin % | AA13: 0.22565981 | AB13: 0.22475851 | AC13: 0.21434718 | AD13: 0.21870617 | AE13: 0.22233915 | AF13: 0.22614176 | AH13: 0.15299587 | AI13: 0.092659782 | AJ13: 0.22565981
B15: Operating Income (GAAP) | C15: =Model!CI160 -> 1149.8 | D15: =Model!CO160 -> 1281.3264 | E15: =Model!CP160 -> 1449.7172 | F15: =Model!CQ160 -> 1606.4941 | G15: =Model!CR160 -> 1811.5366 | H15: =Model!CS160 -> 2013.9657 | I15: =IFERROR((H15/C15)^(1/5)-1,"n/m") -> 0.11862869 | N15: Operating Income (GAAP) | O15: 1149.8 | P15: 1282.511 | Q15: 1577.5626 | R15: 1818.6146 | S15: 2119.2435 | T15: 2430.3558 | U15: 0.16147405 | Z15: Operating Income (GAAP) | AA15: 1149.8 | AB15: 1275.3551 | AC15: 1246.671 | AD15: 1317.7073 | AE15: 1429.239 | AF15: 1528.863 | AG15: 0.058642323
B16: Operating income y/y % | D16: =IFERROR(D15/C15-1,"") -> 0.11439071 | E16: =IFERROR(E15/D15-1,"") -> 0.13141912 | F16: =IFERROR(F15/E15-1,"") -> 0.10814308 | G16: =IFERROR(G15/F15-1,"") -> 0.1276335 | H16: =IFERROR(H15/G15-1,"") -> 0.11174446 | N16: Operating income y/y % | P16: 0.11542094 | Q16: 0.23005776 | R16: 0.15280031 | S16: 0.1653065 | T16: 0.14680349 | Z16: Operating income y/y % | AB16: 0.10919733 | AC16: -0.022491077 | AD16: 0.056980808 | AE16: 0.084640745 | AF16: 0.069704192
B17: Operating margin (GAAP) % | C17: =IFERROR(C15/C9,"") -> 0.18801714 | D17: =IFERROR(D15/D9,"") -> 0.19164069 | E17: =IFERROR(E15/E9,"") -> 0.20191063 | F17: =IFERROR(F15/F9,"") -> 0.20461126 | G17: =IFERROR(G15/G9,"") -> 0.21117672 | H17: =IFERROR(H15/H9,"") -> 0.21552174 | J17: =IFERROR(AVERAGE(Model!C256,Model!D256,Model!E256,Model!F256,Model!G256,Model!H256,Model!I256,Model!O256,Model!U256,Model!AA256,Model!AG256,Model!AM256,Model!AS256,Model!AY256,Model!BE256,Model!BK256,Model!BQ256,Model!BW256,Model!CC256,Model!CI256),"") -> 0.13250642 | K17: =IFERROR(MIN(Model!C256,Model!D256,Model!E256,Model!F256,Model!G256,Model!H256,Model!I256,Model!O256,Model!U256,Model!AA256,Model!AG256,Model!AM256,Model!AS256,Model!AY256,Model!BE256,Model!BK256,Model!BQ256,Model!BW256,Model!CC256,Model!CI256),"") -> 0.08728719 | L17: =IFERROR(MAX(Model!C256,Model!D256,Model!E256,Model!F256,Model!G256,Model!H256,Model!I256,Model!O256,Model!U256,Model!AA256,Model!AG256,Model!AM256,Model!AS256,Model!AY256,Model!BE256,Model!BK256,Model!BQ256,Model!BW256,Model!CC256,Model!CI256),"") -> 0.18801714 | N17: Operating margin (GAAP) % | O17: 0.18801714 | P17: 0.19181785 | Q17: 0.21061651 | R17: 0.21055653 | S17: 0.21447355 | T17: 0.2168112 | V17: 0.13250642 | W17: 0.08728719 | X17: 0.18801714 | Z17: Operating margin (GAAP) % | AA17: 0.18801714 | AB17: 0.19074759 | AC17: 0.18213983 | AD17: 0.18638757 | AE17: 0.19514535 | AF17: 0.20143157 | AH17: 0.13250642 | AI17: 0.08728719 | AJ17: 0.18801714
B19: Non-GAAP Net Income (attributable to Teledyne) | C19: =Model!CI242 -> 1042.3 | D19: =Model!CO242 -> 1150.7812 | E19: =Model!CP242 -> 1300.7681 | F19: =Model!CQ242 -> 1420.6008 | G19: =Model!CR242 -> 1545.8904 | H19: =Model!CS242 -> 1699.0408 | I19: =IFERROR((H19/C19)^(1/5)-1,"n/m") -> 0.10266151 | N19: Non-GAAP Net Income (attributable to Teledyne) | O19: 1042.3 | P19: 1151.7111 | Q19: 1403.6283 | R19: 1567.826 | S19: 1774.3121 | T19: 2017.991 | U19: 0.14126184 | Z19: Non-GAAP Net Income (attributable to Teledyne) | AA19: 1042.3 | AB19: 1146.0938 | AC19: 1135.6883 | AD19: 1183.8803 | AE19: 1230.1973 | AF19: 1296.5845 | AG19: 0.044627887
B21: FDSO (m) | C21: =Model!CI179 -> 47.4 | D21: =Model!CO179 -> 46.875 | E21: =Model!CP179 -> 46.121231 | F21: =Model!CQ179 -> 44.756121 | G21: =Model!CR179 -> 43.934855 | H21: =Model!CS179 -> 42.989737 | I21: =IFERROR((H21/C21)^(1/5)-1,"n/m") -> -0.019342646 | N21: FDSO (m) | O21: 47.4 | P21: 46.722561 | Q21: 45.571071 | R21: 44.342901 | S21: 43.991208 | T21: 43.336178 | U21: -0.017767153 | Z21: FDSO (m) | AA21: 47.4 | AB21: 46.875 | AC21: 45.996745 | AD21: 44.355263 | AE21: 43.301528 | AF21: 42.26211 | AG21: -0.022684995
B23: Non-GAAP EPS — Diluted ($) | C23: =Model!CI243 -> 21.989451 | D23: =Model!CO243 -> 24.55 | E23: =Model!CP243 -> 28.203239 | F23: =Model!CQ243 -> 31.740928 | G23: =Model!CR243 -> 35.185967 | H23: =Model!CS243 -> 39.52201 | I23: =IFERROR((H23/C23)^(1/5)-1,"n/m") -> 0.12441059 | N23: Non-GAAP EPS — Diluted ($) | O23: 21.989451 | P23: 24.65 | Q23: 30.800863 | R23: 35.356866 | S23: 40.333334 | T23: 46.565966 | U23: 0.1619056 | Z23: Non-GAAP EPS — Diluted ($) | AA23: 21.989451 | AB23: 24.45 | AC23: 24.690623 | AD23: 26.690863 | AE23: 28.410022 | AF23: 30.679596 | AG23: 0.068875319
B24: EPS y/y % | D24: =IFERROR(D23/C23-1,"") -> 0.1164444 | E24: =IFERROR(E23/D23-1,"") -> 0.14880811 | F24: =IFERROR(F23/E23-1,"") -> 0.12543555 | G24: =IFERROR(G23/F23-1,"") -> 0.10853617 | H24: =IFERROR(H23/G23-1,"") -> 0.12323217 | N24: EPS y/y % | P24: 0.12099204 | Q24: 0.2495279 | R24: 0.14791804 | S24: 0.14074969 | T24: 0.15452806 | Z24: EPS y/y % | AB24: 0.11189677 | AC24: 0.0098414369 | AD24: 0.081012141 | AE24: 0.064409989 | AF24: 0.079886412
B26: P / E (x) — assumed (non-GAAP EPS) | G26: 23 | H26: 23 | N26: P / E (x) — assumed (non-GAAP EPS) | S26: 25 | T26: 25 | Z26: P / E (x) — assumed (non-GAAP EPS) | AD26: 18 | AE26: 18 | AF26: 18
B27: Price Target ($) | G27: =G26*G23 -> 809.27724 | H27: =H26*H23 -> 909.00623 | N27: Price Target ($) | S27: =S26*S23 -> 1008.3334 | T27: =T26*T23 -> 1164.1491 | Z27: Price Target ($) | AD27: =AD26*AD23 -> 480.43554 | AE27: =AE26*AE23 -> 511.38039 | AF27: =AF26*AF23 -> 552.23273
B28: Upside / (Downside) vs current | G28: =IFERROR(G27/$K$2-1,"") -> 0.31589795 | H28: =IFERROR(H27/$K$2-1,"") -> 0.47805891 | N28: Upside / (Downside) vs current | S28: =IFERROR(S27/$K$2-1,"") -> 0.63956643 | T28: =IFERROR(T27/$K$2-1,"") -> 0.89292544 | Z28: Upside / (Downside) vs current | AD28: =IFERROR(AD27/$K$2-1,"") -> -0.218804 | AE28: =IFERROR(AE27/$K$2-1,"") -> -0.16848717 | AF28: =IFERROR(AF27/$K$2-1,"") -> -0.1020606
B29: IRR (to Dec-Y-1) | G29: =IFERROR((G27/$K$2)^(1/((DATE(2029-1,12,31)-$K$3)/365.25))-1,"") -> 0.13023724 | H29: =IFERROR((H27/$K$2)^(1/((DATE(2030-1,12,31)-$K$3)/365.25))-1,"") -> 0.12810077 | N29: IRR (to Dec-Y-1) | S29: =IFERROR((S27/$K$2)^(1/((DATE(2029-1,12,31)-$K$3)/365.25))-1,"") -> 0.24670255 | T29: =IFERROR((T27/$K$2)^(1/((DATE(2030-1,12,31)-$K$3)/365.25))-1,"") -> 0.21756571 | Z29: IRR (to Dec-Y-1) | AD29: =IFERROR((AD27/$K$2)^(1/((DATE(2029-1,12,31)-$K$3)/365.25))-1,"") -> -0.10427621 | AE29: =IFERROR((AE27/$K$2)^(1/((DATE(2029-1,12,31)-$K$3)/365.25))-1,"") -> -0.078990942 | AF29: =IFERROR((AF27/$K$2)^(1/((DATE(2030-1,12,31)-$K$3)/365.25))-1,"") -> -0.032664198
B31: Free Cash Flow | C31: =Model!CI291 -> 1074 | D31: =Model!CO291 -> 1111.2015 | E31: =Model!CP291 -> 1299.6122 | F31: =Model!CQ291 -> 1409.7857 | G31: =Model!CR291 -> 1531.7869 | H31: =Model!CS291 -> 1674.6891 | I31: =IFERROR((H31/C31)^(1/5)-1,"n/m") -> 0.092913983 | N31: Free Cash Flow | O31: 1074 | P31: 1112.1314 | Q31: 1356.7676 | R31: 1495.263 | S31: 1703.478 | T31: 1939.2194 | U31: 0.12544566 | Z31: Free Cash Flow | AA31: 1074 | AB31: 1106.514 | AC31: 1185.0146 | AD31: 1232.7018 | AE31: 1270.5212 | AF31: 1323.946 | AG31: 0.042733193
B32: FCF % | C32: =IFERROR(C31/C9,"") -> 0.1756222 | D32: =IFERROR(D31/D9,"") -> 0.16619608 | E32: =IFERROR(E31/E9,"") -> 0.18100462 | F32: =IFERROR(F31/F9,"") -> 0.17955748 | G32: =IFERROR(G31/G9,"") -> 0.17856539 | H32: =IFERROR(H31/H9,"") -> 0.17921452 | J32: =IFERROR(AVERAGE(Model!C294,Model!D294,Model!E294,Model!F294,Model!G294,Model!H294,Model!I294,Model!O294,Model!U294,Model!AA294,Model!AG294,Model!AM294,Model!AS294,Model!AY294,Model!BE294,Model!BK294,Model!BQ294,Model!BW294,Model!CC294,Model!CI294),"") -> 0.10310692 | K32: =IFERROR(MIN(Model!C294,Model!D294,Model!E294,Model!F294,Model!G294,Model!H294,Model!I294,Model!O294,Model!U294,Model!AA294,Model!AG294,Model!AM294,Model!AS294,Model!AY294,Model!BE294,Model!BK294,Model!BQ294,Model!BW294,Model!CC294,Model!CI294),"") -> 0.036282445 | L32: =IFERROR(MAX(Model!C294,Model!D294,Model!E294,Model!F294,Model!G294,Model!H294,Model!I294,Model!O294,Model!U294,Model!AA294,Model!AG294,Model!AM294,Model!AS294,Model!AY294,Model!BE294,Model!BK294,Model!BQ294,Model!BW294,Model!CC294,Model!CI294),"") -> 0.19544974 | N32: FCF % | O32: 0.1756222 | P32: 0.16633515 | Q32: 0.18113871 | R32: 0.17311935 | S32: 0.17239688 | T32: 0.17299709 | V32: 0.10310692 | W32: 0.036282445 | X32: 0.19544974 | Z32: FCF % | AA32: 0.1756222 | AB32: 0.16549499 | AC32: 0.17313177 | AD32: 0.17436368 | AE32: 0.17347435 | AF32: 0.17443324 | AH32: 0.10310692 | AI32: 0.036282445 | AJ32: 0.19544974
B33: FCF / share ($) | C33: =IFERROR(C31/C21,"") -> 22.658228 | D33: =IFERROR(D31/D21,"") -> 23.705633 | E33: =IFERROR(E31/E21,"") -> 28.178177 | F33: =IFERROR(F31/F21,"") -> 31.499283 | G33: =IFERROR(G31/G21,"") -> 34.864957 | H33: =IFERROR(H31/H21,"") -> 38.955556 | N33: FCF / share ($) | O33: 22.658228 | P33: 23.802878 | Q33: 29.772563 | R33: 33.720459 | S33: 38.723146 | T33: 44.748278 | Z33: FCF / share ($) | AA33: 22.658228 | AB33: 23.605633 | AC33: 25.76301 | AD33: 27.791557 | AE33: 29.341256 | AF33: 31.327021
B34: FCF Yield (on PT) | E34: =IFERROR(E33/E$27,"") | F34: =IFERROR(F33/F$27,"") | G34: =IFERROR(G33/G$27,"") -> 0.043081599 | H34: =IFERROR(H33/H$27,"") -> 0.042855103 | N34: FCF Yield (on PT) | Q34: =IFERROR(Q33/Q$27,"") | R34: =IFERROR(R33/R$27,"") | S34: =IFERROR(S33/S$27,"") -> 0.038403119 | T34: =IFERROR(T33/T$27,"") -> 0.038438613 | Z34: FCF Yield (on PT) | AC34: =IFERROR(AC33/AC$27,"") | AD34: =IFERROR(AD33/AD$27,"") -> 0.057846589 | AE34: =IFERROR(AE33/AE$27,"") -> 0.057376577 | AF34: =IFERROR(AF33/AF$27,"") -> 0.056727932
B35: Adjusted EBITDA (model) | C35: =Model!CI211 -> 1504 | D35: =Model!CO211 -> 1635.4591 | E35: =Model!CP211 -> 1827.4646 | F35: =Model!CQ211 -> 2019.9556 | G35: =Model!CR211 -> 2224.4384 | H35: =Model!CS211 -> 2444.7772 | I35: =IFERROR((H35/C35)^(1/5)-1,"n/m") -> 0.10204237 | N35: Adjusted EBITDA (model) | O35: 1504 | P35: 1636.6436 | Q35: 1972.2968 | R35: 2280.2105 | S35: 2612.2382 | T35: 2974.0962 | U35: 0.14609715 | Z35: Adjusted EBITDA (model) | AA35: 1504 | AB35: 1629.4877 | AC35: 1610.5862 | AD35: 1694.0501 | AE35: 1781.2232 | AF35: 1874.4177 | AG35: 0.045017851
B36: Adjusted EBITDA margin % | C36: =IFERROR(C35/C9,"") -> 0.24593649 | D36: =IFERROR(D35/D9,"") -> 0.24460629 | E36: =IFERROR(E35/E9,"") -> 0.25452172 | F36: =IFERROR(F35/F9,"") -> 0.25727182 | G36: =IFERROR(G35/G9,"") -> 0.25931003 | H36: =IFERROR(H35/H9,"") -> 0.26162443 | J36: =IFERROR(AVERAGE(Model!C257,Model!D257,Model!E257,Model!F257,Model!G257,Model!H257,Model!I257,Model!O257,Model!U257,Model!AA257,Model!AG257,Model!AM257,Model!AS257,Model!AY257,Model!BE257,Model!BK257,Model!BQ257,Model!BW257,Model!CC257,Model!CI257),"") -> 0.17677599 | K36: =IFERROR(MIN(Model!C257,Model!D257,Model!E257,Model!F257,Model!G257,Model!H257,Model!I257,Model!O257,Model!U257,Model!AA257,Model!AG257,Model!AM257,Model!AS257,Model!AY257,Model!BE257,Model!BK257,Model!BQ257,Model!BW257,Model!CC257,Model!CI257),"") -> 0.11310354 | L36: =IFERROR(MAX(Model!C257,Model!D257,Model!E257,Model!F257,Model!G257,Model!H257,Model!I257,Model!O257,Model!U257,Model!AA257,Model!AG257,Model!AM257,Model!AS257,Model!AY257,Model!BE257,Model!BK257,Model!BQ257,Model!BW257,Model!CC257,Model!CI257),"") -> 0.24593649 | N36: Adjusted EBITDA margin % | O36: 0.24593649 | P36: 0.24478345 | Q36: 0.2633165 | R36: 0.26399942 | S36: 0.26436604 | T36: 0.26531809 | V36: 0.17677599 | W36: 0.11310354 | X36: 0.24593649 | Z36: Adjusted EBITDA margin % | AA36: 0.24593649 | AB36: 0.24371319 | AC36: 0.23530819 | AD36: 0.23962065 | AE36: 0.24320453 | AF36: 0.24695929 | AH36: 0.17677599 | AI36: 0.11310354 | AJ36: 0.24593649
B38: Net Debt | C38: =Model!CI426 -> 2123 | D38: =Model!CO426 -> 1023.2985 | E38: =Model!CP426 -> 1827.4646 | F38: =Model!CQ426 -> 2019.9556 | G38: =Model!CR426 -> 2224.4384 | H38: =Model!CS426 -> 2444.7772 | N38: Net Debt | O38: 2123 | P38: 1272.3686 | Q38: 2958.4451 | R38: 3420.3157 | S38: 3918.3573 | T38: 4461.1443 | Z38: Net Debt | AA38: 2123 | AB38: 1027.986 | AC38: 1610.5862 | AD38: 1694.0501 | AE38: 1781.2232 | AF38: 1874.4177
B39: Net Debt / Adjusted EBITDA (x) | C39: =IFERROR(C38/C35,"") -> 1.4115691 | D39: =IFERROR(D38/D35,"") -> 0.62569494 | E39: =IFERROR(E38/E35,"") -> 1 | F39: =IFERROR(F38/F35,"") -> 1 | G39: =IFERROR(G38/G35,"") -> 1 | H39: =IFERROR(H38/H35,"") -> 1 | N39: Net Debt / Adjusted EBITDA (x) | O39: 1.4115691 | P39: 0.77742556 | Q39: 1.5 | R39: 1.5 | S39: 1.5 | T39: 1.5 | Z39: Net Debt / Adjusted EBITDA (x) | AA39: 1.4115691 | AB39: 0.6308645 | AC39: 1 | AD39: 1 | AE39: 1 | AF39: 1
B41: ROIC | C41: =Model!CI406 -> 0.089368681 | D41: =Model!CO406 -> 0.094730158 | E41: =Model!CP406 -> 0.099584771 | F41: =Model!CQ406 -> 0.10342747 | G41: =Model!CR406 -> 0.10725735 | H41: =Model!CS406 -> 0.11131318 | J41: =IFERROR(AVERAGE(Model!C406,Model!D406,Model!E406,Model!F406,Model!G406,Model!H406,Model!I406,Model!O406,Model!U406,Model!AA406,Model!AG406,Model!AM406,Model!AS406,Model!AY406,Model!BE406,Model!BK406,Model!BQ406,Model!BW406,Model!CC406,Model!CI406),"") -> 0.12004492 | K41: =IFERROR(MIN(Model!C406,Model!D406,Model!E406,Model!F406,Model!G406,Model!H406,Model!I406,Model!O406,Model!U406,Model!AA406,Model!AG406,Model!AM406,Model!AS406,Model!AY406,Model!BE406,Model!BK406,Model!BQ406,Model!BW406,Model!CC406,Model!CI406),"") -> 0.072912591 | L41: =IFERROR(MAX(Model!C406,Model!D406,Model!E406,Model!F406,Model!G406,Model!H406,Model!I406,Model!O406,Model!U406,Model!AA406,Model!AG406,Model!AM406,Model!AS406,Model!AY406,Model!BE406,Model!BK406,Model!BQ406,Model!BW406,Model!CC406,Model!CI406),"") -> 0.17057143 | N41: ROIC | O41: 0.089368681 | P41: 0.094803833 | Q41: 0.10174979 | R41: 0.10526119 | S41: 0.10909992 | T41: 0.11344562 | V41: 0.12004492 | W41: 0.072912591 | X41: 0.17057143 | Z41: ROIC | AA41: 0.089368681 | AB41: 0.094358765 | AC41: 0.090856829 | AD41: 0.093379181 | AE41: 0.095730451 | AF41: 0.098122886 | AH41: 0.12004492 | AI41: 0.072912591 | AJ41: 0.17057143
B42: RONTA | C42: =Model!CI418 -> 0.36576729 | D42: =Model!CO418 -> 0.30983055 | E42: =Model!CP418 -> 0.40811295 | F42: =Model!CQ418 -> 0.43874808 | G42: =Model!CR418 -> 0.46954886 | H42: =Model!CS418 -> 0.49969959 | J42: =IFERROR(AVERAGE(Model!C418,Model!D418,Model!E418,Model!F418,Model!G418,Model!H418,Model!I418,Model!O418,Model!U418,Model!AA418,Model!AG418,Model!AM418,Model!AS418,Model!AY418,Model!BE418,Model!BK418,Model!BQ418,Model!BW418,Model!CC418,Model!CI418),"") -> 0.28276514 | K42: =IFERROR(MIN(Model!C418,Model!D418,Model!E418,Model!F418,Model!G418,Model!H418,Model!I418,Model!O418,Model!U418,Model!AA418,Model!AG418,Model!AM418,Model!AS418,Model!AY418,Model!BE418,Model!BK418,Model!BQ418,Model!BW418,Model!CC418,Model!CI418),"") -> 0.19588641 | L42: =IFERROR(MAX(Model!C418,Model!D418,Model!E418,Model!F418,Model!G418,Model!H418,Model!I418,Model!O418,Model!U418,Model!AA418,Model!AG418,Model!AM418,Model!AS418,Model!AY418,Model!BE418,Model!BK418,Model!BQ418,Model!BW418,Model!CC418,Model!CI418),"") -> 0.37213017 | N42: RONTA | O42: 0.36576729 | P42: 0.33150542 | Q42: 0.43509613 | R42: 0.47863414 | S42: 0.52173753 | T42: 0.56329799 | V42: 0.28276514 | W42: 0.19588641 | X42: 0.37213017 | Z42: RONTA | AA42: 0.36576729 | AB42: 0.30899184 | AC42: 0.35038685 | AD42: 0.3758629 | AE42: 0.39611395 | AF42: 0.41227791 | AH42: 0.28276514 | AI42: 0.19588641 | AJ42: 0.37213017
B44: Implied Market Cap (USDm) | E44: =E27*E21 -> 0 | F44: =F27*F21 -> 0 | G44: =G27*G21 -> 35555.478 | H44: =H27*H21 -> 39077.939 | N44: Implied Market Cap (USDm) | Q44: =Q27*Q21 -> 0 | R44: =R27*R21 -> 0 | S44: =S27*S21 -> 44357.802 | T44: =T27*T21 -> 50449.775 | Z44: Implied Market Cap (USDm) | AC44: =AC27*AC21 -> 0 | AD44: =AD27*AD21 -> 21309.845 | AE44: =AE27*AE21 -> 22143.552 | AF44: =AF27*AF21 -> 23338.52
B45: (+) Net Debt & NCI | E45: =E38+Model!CP436 -> 1827.4646 | F45: =F38+Model!CQ436 -> 2019.9556 | G45: =G38+Model!CR436 -> 2224.4384 | H45: =H38+Model!CS436 -> 2444.7772 | N45: (+) Net Debt & NCI | Q45: =Q38+Model!CP436 -> 2958.4451 | R45: =R38+Model!CQ436 -> 3420.3157 | S45: =S38+Model!CR436 -> 3918.3573 | T45: =T38+Model!CS436 -> 4461.1443 | Z45: (+) Net Debt & NCI | AC45: =AC38+Model!CP436 -> 1610.5862 | AD45: =AD38+Model!CQ436 -> 1694.0501 | AE45: =AE38+Model!CR436 -> 1781.2232 | AF45: =AF38+Model!CS436 -> 1874.4177
B46: Implied Enterprise Value (USDm) | E46: =E44+E45 -> 1827.4646 | F46: =F44+F45 -> 2019.9556 | G46: =G44+G45 -> 37779.917 | H46: =H44+H45 -> 41522.716 | N46: Implied Enterprise Value (USDm) | Q46: =Q44+Q45 -> 2958.4451 | R46: =R44+R45 -> 3420.3157 | S46: =S44+S45 -> 48276.159 | T46: =T44+T45 -> 54910.919 | Z46: Implied Enterprise Value (USDm) | AC46: =AC44+AC45 -> 1610.5862 | AD46: =AD44+AD45 -> 23003.895 | AE46: =AE44+AE45 -> 23924.775 | AF46: =AF44+AF45 -> 25212.938
B47: Implied EV / Adjusted EBITDA (x) | E47: =IFERROR(E46/E35,"") -> 1 | F47: =IFERROR(F46/F35,"") -> 1 | G47: =IFERROR(G46/G35,"") -> 16.984025 | H47: =IFERROR(H46/H35,"") -> 16.984253 | N47: Implied EV / Adjusted EBITDA (x) | Q47: =IFERROR(Q46/Q35,"") -> 1.5 | R47: =IFERROR(R46/R35,"") -> 1.5 | S47: =IFERROR(S46/S35,"") -> 18.480764 | T47: =IFERROR(T46/T35,"") -> 18.463061 | Z47: Implied EV / Adjusted EBITDA (x) | AC47: =IFERROR(AC46/AC35,"") -> 1 | AD47: =IFERROR(AD46/AD35,"") -> 13.579229 | AE47: =IFERROR(AE46/AE35,"") -> 13.431655 | AF47: =IFERROR(AF46/AF35,"") -> 13.451078

Sheet DCF
B2: DCF VALUATION — TELEDYNE TECHNOLOGIES (TDY)
B4: 1. WACC BUILD
B5: Risk-free rate (US 10Y govt) | C5: 0.055 | D5: Assumption (~US 10Y Treasury yield); update to market
B6: Equity risk premium | C6: 0.05 | D6: US implied ERP ~4.5–5.5% (Damodaran)
B7: Levered beta | C7: 1 | D7: Diversified instrumentation / A&D electronics peers (AME, KEYS, LHX) ~0.9–1.1; ~25% US Government sales dampen cyclicality
B8: Cost of equity | C8: =C5+C7*C6 -> 0.105
B9: Pre-tax cost of debt | C9: 0.0475 | D9: BBB-rated (investment grade); FLIR-acquisition notes 1.6%–2.75% fixed coupons; marginal cost ~4.5–5.0%
B10: Tax rate | C10: 0.215 | D10: Model 2027E+ effective tax rate (FY26 outlook rate in the scenario table)
B11: After-tax cost of debt | C11: =C9*(1-C10) -> 0.0372875
B12: Target D/V | C12: 0.2 | D12: Net debt ~$1.7bn vs ~$29bn market cap; leverage 1.1x at 30-Jun-26
B13: WACC | C13: =C8*(1-C12)+C11*C12 -> 0.0914575
B15: Valuation date (live) | C15: =TODAY() -> 46299 | D15: Periods = (Dec-31-Year − today) / 365.25; cash flows assumed at year-end
B16: 2. UNLEVERED FREE CASH FLOW BUILD (USDm)
D17: 2026E | E17: 2027E | F17: 2028E | G17: 2029E | H17: 2030E | I17: 2031E | J17: 2032E | K17: 2033E | L17: 2034E | M17: 2035E | N17: Terminal | P17: CAGR 26–30E | Q17: CAGR 26–35E
B18: Non-GAAP operating income (Model, current definition) | D18: =Model!CO200 -> 1508.7264 | E18: =Model!CP200 -> 1677.4547 | F18: =Model!CQ200 -> 1856.8524 | G18: =Model!CR200 -> 2047.1616 | H18: =Model!CS200 -> 2252.5574 | I18: =H18*(1+I$31) -> 2410.2364 | J18: =I18*(1+J$31) -> 2566.9018 | K18: =J18*(1+K$31) -> 2720.9159 | L18: =K18*(1+L$31) -> 2870.5663 | M18: =L18*(1+M$31) -> 3014.0946 | P18: =IFERROR(($H18/$D18)^(1/(VALUE(LEFT($H$17,4))-VALUE(LEFT($D$17,4))))-1,"n/m") -> 0.10539206 | Q18: =IFERROR(($M18/$D18)^(1/(VALUE(LEFT($M$17,4))-VALUE(LEFT($D$17,4))))-1,"n/m") -> 0.079926112
B19: y/y % | E19: =IFERROR(E18/D18-1,"") -> 0.11183492 | F19: =IFERROR(F18/E18-1,"") -> 0.10694638 | G19: =IFERROR(G18/F18-1,"") -> 0.10249017 | H19: =IFERROR(H18/G18-1,"") -> 0.10033201 | I19: =IFERROR(I18/H18-1,"") -> 0.07 | J19: =IFERROR(J18/I18-1,"") -> 0.065 | K19: =IFERROR(K18/J18-1,"") -> 0.06 | L19: =IFERROR(L18/K18-1,"") -> 0.055 | M19: =IFERROR(M18/L18-1,"") -> 0.05
B20: (−) Transaction & integration costs (cash, excluded from non-GAAP) | D20: =-Model!CO98 -> -1.4 | E20: =-Model!CP98 -> -5 | F20: =-Model!CQ98 -> -5 | G20: =-Model!CR98 -> -5 | H20: =-Model!CS98 -> -5 | I20: =H20*(1+I$31) -> -5.35 | J20: =I20*(1+J$31) -> -5.69775 | K20: =J20*(1+K$31) -> -6.039615 | L20: =K20*(1+L$31) -> -6.3717938 | M20: =L20*(1+M$31) -> -6.6903835
B21: × (1 − tax rate) | D21: =1-$C$10 -> 0.785 | E21: =1-$C$10 -> 0.785 | F21: =1-$C$10 -> 0.785 | G21: =1-$C$10 -> 0.785 | H21: =1-$C$10 -> 0.785 | I21: =1-$C$10 -> 0.785 | J21: =1-$C$10 -> 0.785 | K21: =1-$C$10 -> 0.785 | ... M21: =1-$C$10 -> 0.785
B22: NOPAT = (Non-GAAP OI − transaction costs) × (1 − t) | D22: =(D18+D20)*D21 -> 1183.2512 | E22: =(E18+E20)*E21 -> 1312.877 | F22: =(F18+F20)*F21 -> 1453.7042 | G22: =(G18+G20)*G21 -> 1603.0968 | H22: =(H18+H20)*H21 -> 1764.3326 | I22: =(I18+I20)*I21 -> 1887.8359 | J22: =(J18+J20)*J21 -> 2010.5452 | K22: =(K18+K20)*K21 -> 2131.1779 | ... M22: =(M18+M20)*M21 -> 2360.8123
B23: plus depreciation (D&A ex acquired-intangible amortization) | D23: =Model!CO140 -> 123.03264 | E23: =Model!CP140 -> 140.0099 | F23: =Model!CQ140 -> 153.10318 | G23: =Model!CR140 -> 167.27678 | H23: =Model!CS140 -> 182.21982 | I23: =H23*(1+I$31) -> 194.97521 | J23: =I23*(1+J$31) -> 207.6486 | K23: =J23*(1+K$31) -> 220.10751 | L23: =K23*(1+L$31) -> 232.21342 | M23: =L23*(1+M$31) -> 243.82409
B24: − Capex (PP&E) and acquisitions (M&A lever, 2027E+) | D24: =D29 -> -125 | E24: =E29+Model!CP273 -> -893.59989 | F24: =F29+Model!CQ273 -> -1157.0289 | G24: =G29+Model!CR273 -> -1171.5659 | H24: =H29+Model!CS273 -> -1186.8921 | I24: =I29 -> -199.97457 | J24: =J29 -> -212.97292 | K24: =K29 -> -225.75129 | L24: =L29 -> -238.16761 | M24: =M29 -> -250.07599
B25: − Δ Working capital (CF statement) | D25: =Model!CO270 -> -97.350979 | E25: =Model!CP270 -> -62.754196 | F25: =Model!CQ270 -> -81.757991 | G25: =Model!CR270 -> -85.945166 | H25: =Model!CS270 -> -101.4884 | I25: =H25*(1+I$31) -> -108.59258 | J25: =I25*(1+J$31) -> -115.6511 | K25: =J25*(1+K$31) -> -122.59017 | L25: =K25*(1+L$31) -> -129.33263 | M25: =L25*(1+M$31) -> -135.79926
B26: Unlevered FCF | D26: =D22+D23+D24+D25 -> 1083.9329 | E26: =E22+E23+E24+E25 -> 496.53277 | F26: =F22+F23+F24+F25 -> 368.02046 | G26: =G22+G23+G24+G25 -> 512.86252 | H26: =H22+H23+H24+H25 -> 658.17187 | I26: =I22+I23+I24+I25 -> 1774.2439 | J26: =J22+J23+J24+J25 -> 1889.5698 | K26: =K22+K23+K24+K25 -> 2002.9439 | ... M26: =M22+M23+M24+M25 -> 2218.7612 | N26: =M26*(1+$C$32) -> 2318.6054 | P26: =IFERROR(($H26/$D26)^(1/(VALUE(LEFT($H$17,4))-VALUE(LEFT($D$17,4))))-1,"n/m") -> -0.11725711 | Q26: =IFERROR(($M26/$D26)^(1/(VALUE(LEFT($M$17,4))-VALUE(LEFT($D$17,4))))-1,"n/m") -> 0.082848183
B27: y/y % | E27: =IFERROR(E26/D26-1,"") -> -0.54191559 | F27: =IFERROR(F26/E26-1,"") -> -0.2588194 | G27: =IFERROR(G26/F26-1,"") -> 0.3935707 | H27: =IFERROR(H26/G26-1,"") -> 0.28333002 | I27: =IFERROR(I26/H26-1,"") -> 1.6957152 | J27: =IFERROR(J26/I26-1,"") -> 0.065 | K27: =IFERROR(K26/J26-1,"") -> 0.06 | L27: =IFERROR(L26/K26-1,"") -> 0.055 | M27: =IFERROR(M26/L26-1,"") -> 0.05
B28: Terminal Value (Gordon Growth) | N28: =N26/($C$13-$C$32) -> 49908.097
B29: memo: PP&E capex only (fade years carry no new acquisitions) | D29: =Model!CO272 -> -125 | E29: =Model!CP272 -> -143.59989 | F29: =Model!CQ272 -> -157.0289 | G29: =Model!CR272 -> -171.56593 | H29: =Model!CS272 -> -186.89212 | I29: =H29*(1+I$31) -> -199.97457 | J29: =I29*(1+J$31) -> -212.97292 | K29: =J29*(1+K$31) -> -225.75129 | L29: =K29*(1+L$31) -> -238.16761 | M29: =L29*(1+M$31) -> -250.07599
B31: Fade-period growth (2031E–35E) | I31: 0.07 | J31: =I31+($M$31-$I$31)/(COLUMNS($I$31:$M$31)-1) -> 0.065 | K31: =J31+($M$31-$I$31)/(COLUMNS($I$31:$M$31)-1) -> 0.06 | L31: =K31+($M$31-$I$31)/(COLUMNS($I$31:$M$31)-1) -> 0.055 | M31: 0.05
B32: Terminal growth rate | C32: 0.045
B34: Discount period (years) | D34: =(DATE(2026,12,31)-$C$15)/365.25 -> 0.24093087 | E34: =(DATE(2027,12,31)-$C$15)/365.25 -> 1.2402464 | F34: =(DATE(2028,12,31)-$C$15)/365.25 -> 2.2422998 | G34: =(DATE(2029,12,31)-$C$15)/365.25 -> 3.2416153 | H34: =(DATE(2030,12,31)-$C$15)/365.25 -> 4.2409309 | I34: =(DATE(2031,12,31)-$C$15)/365.25 -> 5.2402464 | J34: =(DATE(2032,12,31)-$C$15)/365.25 -> 6.2422998 | K34: =(DATE(2033,12,31)-$C$15)/365.25 -> 7.2416153 | L34: =(DATE(2034,12,31)-$C$15)/365.25 -> 8.2409309 | M34: =(DATE(2035,12,31)-$C$15)/365.25 -> 9.2402464 | N34: =M34 -> 9.2402464
B35: Discount factor | D35: =1/(1+$C$13)^D34 -> 0.97913592 | E35: =1/(1+$C$13)^E34 -> 0.89714402 | F35: =1/(1+$C$13)^F34 -> 0.82182111 | G35: =1/(1+$C$13)^G34 -> 0.75300261 | H35: =1/(1+$C$13)^H34 -> 0.68994689 | I35: =1/(1+$C$13)^I34 -> 0.63217141 | J35: =1/(1+$C$13)^J34 -> 0.57909521 | K35: =1/(1+$C$13)^K34 -> 0.53060234 | ... N35: =1/(1+$C$13)^N34 -> 0.44545879
B36: PV of UFCF | D36: =D26*D35 -> 1061.3176 | E36: =E26*E35 -> 445.4614 | F36: =F26*F35 -> 302.44698 | G36: =G26*G35 -> 386.18682 | H36: =H26*H35 -> 454.10364 | I36: =I26*I35 -> 1121.6263 | J36: =J26*J35 -> 1094.2408 | K36: =K26*K35 -> 1062.7667 | ... M36: =M26*M35 -> 988.36665 | N36: =N28*N35 -> 22232
D37: Teledyne's non-GAAP operating income already expenses stock-based compensation (only acquired-intangible amortization and acquisition items are excluded). Acquisition spend from the M&A lever is deducted in 2027E–30E so that acquired sales / profit in the Model are paid for; the fade period and terminal value assume no new acquisitions. Operating-lease costs sit inside operating income (lease liabilities not deducted as debt).
B39: Implied ROIC & incremental ROIC (USDm) | D39: =D17 -> 2026E | E39: =E17 -> 2027E | F39: =F17 -> 2028E | G39: =G17 -> 2029E | H39: =H17 -> 2030E | I39: =I17 -> 2031E | J39: =J17 -> 2032E | K39: =K17 -> 2033E | ... M39: =M17 -> 2035E | N39: Terminal
B40: NOPAT (row 22) | D40: =D22 -> 1183.2512 | E40: =E22 -> 1312.877 | F40: =F22 -> 1453.7042 | G40: =G22 -> 1603.0968 | H40: =H22 -> 1764.3326 | I40: =I22 -> 1887.8359 | J40: =J22 -> 2010.5452 | K40: =K22 -> 2131.1779 | ... M40: =M22 -> 2360.8123 | N40: =M40*(1+$C$32) -> 2467.0489
B41: Net investment = NOPAT − UFCF | D41: =D40-D26 -> 99.318335 | E41: =E40-E26 -> 816.34419 | F41: =F40-F26 -> 1085.6837 | G41: =G40-G26 -> 1090.2343 | H41: =H40-H26 -> 1106.1607 | I41: =I40-I26 -> 113.59195 | J41: =J40-J26 -> 120.97542 | K41: =K40-K26 -> 128.23395 | ... N41: =N40-N26 -> 148.44346
B42: Opening invested capital | D42: =Model!CI403 -> 12636.9 | E42: =D43 -> 12736.218 | F42: =E43 -> 13552.563 | G42: =F43 -> 14638.246 | H42: =G43 -> 15728.481 | I42: =H43 -> 16834.641 | J42: =I43 -> 16948.233 | K42: =J43 -> 17069.209 | L42: =K43 -> 17197.443 | ... N42: =M43 -> 17474.781
B43: Closing invested capital | D43: =D42+D41 -> 12736.218 | E43: =E42+E41 -> 13552.563 | F43: =F42+F41 -> 14638.246 | G43: =G42+G41 -> 15728.481 | H43: =H42+H41 -> 16834.641 | I43: =I42+I41 -> 16948.233 | J43: =J42+J41 -> 17069.209 | K43: =K42+K41 -> 17197.443 | ... M43: =M42+M41 -> 17474.781
B44: Implied ROIC = NOPAT / opening IC | D44: =IFERROR(D40/D42,"") -> 0.093634614 | E44: =IFERROR(E40/E42,"") -> 0.10308217 | F44: =IFERROR(F40/F42,"") -> 0.10726416 | G44: =IFERROR(G40/G42,"") -> 0.10951427 | H44: =IFERROR(H40/H42,"") -> 0.11217438 | I44: =IFERROR(I40/I42,"") -> 0.11213995 | J44: =IFERROR(J40/J42,"") -> 0.1186286 | K44: =IFERROR(K40/K42,"") -> 0.12485511 | ... N44: =IFERROR(N40/N42,"") -> 0.14117767
B45: Reinvestment rate = net inv. / NOPAT | D45: =IFERROR(D41/D40,"") -> 0.08393681 | E45: =IFERROR(E41/E40,"") -> 0.62179794 | F45: =IFERROR(F41/F40,"") -> 0.74683951 | G45: =IFERROR(G41/G40,"") -> 0.68008014 | H45: =IFERROR(H41/H40,"") -> 0.62695702 | I45: =IFERROR(I41/I40,"") -> 0.060170458 | J45: =IFERROR(J41/J40,"") -> 0.060170458 | K45: =IFERROR(K41/K40,"") -> 0.060170458 | ... N45: =IFERROR(N41/N40,"") -> 0.060170458
B46: Incremental ROIC = Δ NOPAT / prior-yr net inv. | E46: =IFERROR((E40-D40)/D41,"") -> 1.3051539 | F46: =IFERROR((F40-E40)/E41,"") -> 0.1725096 | G46: =IFERROR((G40-F40)/F41,"") -> 0.13760238 | H46: =IFERROR((H40-G40)/G41,"") -> 0.1478909 | I46: =IFERROR((I40-H40)/H41,"") -> 0.1116504 | J46: =IFERROR((J40-I40)/I41,"") -> 1.0802643 | K46: =IFERROR((K40-J40)/J41,"") -> 0.99716709 | L46: =IFERROR((L40-K40)/K41,"") -> 0.91406983 | M46: =IFERROR((M40-L40)/L41,"") -> 0.83097257 | N46: =IFERROR($C$32/N45,"") -> 0.74787532
B47: Cumulative incremental ROIC 2026E–35E | C47: =IFERROR((M40-D40)/SUM(D41:L41),"") -> 0.25076743
D48: Opening IC = Model 2025A book IC (equity + net debt, Model!CI403), rolled forward with DCF net investment (capex + M&A − D&A + ΔWC). Terminal incremental ROIC = g ÷ reinvestment rate. Cumulative = (NOPAT 2035E − 2026E) / Σ net investment 2026E–34E.
B49: 3. VALUATION SUMMARY
B50: Sum of PV (explicit + fade) | C50: =SUM(D36:M36) -> 7943.8461
B51: PV of Terminal Value | C51: =N36 -> 22232
B52: Enterprise Value | C52: =C50+C51 -> 30175.846
B53: Less: net debt (Model 2026E YE) | C53: =Model!CO426 -> 1023.2985
B54: Less: non-controlling interests (Model 2026E) | C54: =Model!CO436 -> 0
B55: Equity Value | C55: =C52-C53-C54 -> 29152.548
B56: Diluted shares (m, Model 2026E) | C56: =Model!CO179 -> 46.875
B57: Implied share price ($) | C57: =C55/C56 -> 621.92102
B58: Current share price ($) | C58: =Model!CO432 -> 615
B59: Implied upside / (downside) | C59: =C57/C58-1 -> 0.011253693
B62: 4. SENSITIVITY: IMPLIED PRICE ($) — WACC × Terminal Growth
B63: WACC step (across) | C63: 0.005
B64: Terminal growth step (down) | C64: 0.005
B65: g (down) / WACC | D65: =E65-$C$63 -> 0.0814575 | E65: =F65-$C$63 -> 0.0864575 | F65: =$C$13 -> 0.0914575 | G65: =F65+$C$63 -> 0.0964575 | H65: =G65+$C$63 -> 0.1014575
B66: =B67-$C$64 -> 0.035 | D66: =IFERROR((SUMPRODUCT($D$26:$M$26/(1+D$65)^$D$34:$M$34)+($M$26*(1+$B66)/(D$65-$B66))/(1+D$65)^$M$34-$C$53-$C$54)/$C$56,"") -> 667.7358 | E66: =IFERROR((SUMPRODUCT($D$26:$M$26/(1+E$65)^$D$34:$M$34)+($M$26*(1+$B66)/(E$65-$B66))/(1+E$65)^$M$34-$C$53-$C$54)/$C$56,"") -> 594.36619 | F66: =IFERROR((SUMPRODUCT($D$26:$M$26/(1+F$65)^$D$34:$M$34)+($M$26*(1+$B66)/(F$65-$B66))/(1+F$65)^$M$34-$C$53-$C$54)/$C$56,"") -> 534.1793 | G66: =IFERROR((SUMPRODUCT($D$26:$M$26/(1+G$65)^$D$34:$M$34)+($M$26*(1+$B66)/(G$65-$B66))/(1+G$65)^$M$34-$C$53-$C$54)/$C$56,"") -> 483.95234 | H66: =IFERROR((SUMPRODUCT($D$26:$M$26/(1+H$65)^$D$34:$M$34)+($M$26*(1+$B66)/(H$65-$B66))/(1+H$65)^$M$34-$C$53-$C$54)/$C$56,"") -> 441.43259
B67: =B68-$C$64 -> 0.04 | D67: =IFERROR((SUMPRODUCT($D$26:$M$26/(1+D$65)^$D$34:$M$34)+($M$26*(1+$B67)/(D$65-$B67))/(1+D$65)^$M$34-$C$53-$C$54)/$C$56,"") -> 732.18744 | E67: =IFERROR((SUMPRODUCT($D$26:$M$26/(1+E$65)^$D$34:$M$34)+($M$26*(1+$B67)/(E$65-$B67))/(1+E$65)^$M$34-$C$53-$C$54)/$C$56,"") -> 644.35593 | F67: =IFERROR((SUMPRODUCT($D$26:$M$26/(1+F$65)^$D$34:$M$34)+($M$26*(1+$B67)/(F$65-$B67))/(1+F$65)^$M$34-$C$53-$C$54)/$C$56,"") -> 573.78734 | G67: =IFERROR((SUMPRODUCT($D$26:$M$26/(1+G$65)^$D$34:$M$34)+($M$26*(1+$B67)/(G$65-$B67))/(1+G$65)^$M$34-$C$53-$C$54)/$C$56,"") -> 515.88981 | H67: =IFERROR((SUMPRODUCT($D$26:$M$26/(1+H$65)^$D$34:$M$34)+($M$26*(1+$B67)/(H$65-$B67))/(1+H$65)^$M$34-$C$53-$C$54)/$C$56,"") -> 467.56599
B68: =$C$32 -> 0.045 | D68: =IFERROR((SUMPRODUCT($D$26:$M$26/(1+D$65)^$D$34:$M$34)+($M$26*(1+$B68)/(D$65-$B68))/(1+D$65)^$M$34-$C$53-$C$54)/$C$56,"") -> 814.31766 | E68: =IFERROR((SUMPRODUCT($D$26:$M$26/(1+E$65)^$D$34:$M$34)+($M$26*(1+$B68)/(E$65-$B68))/(1+E$65)^$M$34-$C$53-$C$54)/$C$56,"") -> 706.40374 | F68: =IFERROR((SUMPRODUCT($D$26:$M$26/(1+F$65)^$D$34:$M$34)+($M$26*(1+$B68)/(F$65-$B68))/(1+F$65)^$M$34-$C$53-$C$54)/$C$56,"") -> 621.92102 | G68: =IFERROR((SUMPRODUCT($D$26:$M$26/(1+G$65)^$D$34:$M$34)+($M$26*(1+$B68)/(G$65-$B68))/(1+G$65)^$M$34-$C$53-$C$54)/$C$56,"") -> 554.03384 | H68: =IFERROR((SUMPRODUCT($D$26:$M$26/(1+H$65)^$D$34:$M$34)+($M$26*(1+$B68)/(H$65-$B68))/(1+H$65)^$M$34-$C$53-$C$54)/$C$56,"") -> 498.32825
B69: =B68+$C$64 -> 0.05 | D69: =IFERROR((SUMPRODUCT($D$26:$M$26/(1+D$65)^$D$34:$M$34)+($M$26*(1+$B69)/(D$65-$B69))/(1+D$65)^$M$34-$C$53-$C$54)/$C$56,"") -> 922.55619 | E69: =IFERROR((SUMPRODUCT($D$26:$M$26/(1+E$65)^$D$34:$M$34)+($M$26*(1+$B69)/(E$65-$B69))/(1+E$65)^$M$34-$C$53-$C$54)/$C$56,"") -> 785.47077 | F69: =IFERROR((SUMPRODUCT($D$26:$M$26/(1+F$65)^$D$34:$M$34)+($M$26*(1+$B69)/(F$65-$B69))/(1+F$65)^$M$34-$C$53-$C$54)/$C$56,"") -> 681.66508 | G69: =IFERROR((SUMPRODUCT($D$26:$M$26/(1+G$65)^$D$34:$M$34)+($M$26*(1+$B69)/(G$65-$B69))/(1+G$65)^$M$34-$C$53-$C$54)/$C$56,"") -> 600.3884 | H69: =IFERROR((SUMPRODUCT($D$26:$M$26/(1+H$65)^$D$34:$M$34)+($M$26*(1+$B69)/(H$65-$B69))/(1+H$65)^$M$34-$C$53-$C$54)/$C$56,"") -> 535.06869
B70: =B69+$C$64 -> 0.055 | D70: =IFERROR((SUMPRODUCT($D$26:$M$26/(1+D$65)^$D$34:$M$34)+($M$26*(1+$B70)/(D$65-$B70))/(1+D$65)^$M$34-$C$53-$C$54)/$C$56,"") -> 1071.7051 | E70: =IFERROR((SUMPRODUCT($D$26:$M$26/(1+E$65)^$D$34:$M$34)+($M$26*(1+$B70)/(E$65-$B70))/(1+E$65)^$M$34-$C$53-$C$54)/$C$56,"") -> 889.67235 | F70: =IFERROR((SUMPRODUCT($D$26:$M$26/(1+F$65)^$D$34:$M$34)+($M$26*(1+$B70)/(F$65-$B70))/(1+F$65)^$M$34-$C$53-$C$54)/$C$56,"") -> 757.79645 | G70: =IFERROR((SUMPRODUCT($D$26:$M$26/(1+G$65)^$D$34:$M$34)+($M$26*(1+$B70)/(G$65-$B70))/(1+G$65)^$M$34-$C$53-$C$54)/$C$56,"") -> 657.92419 | H70: =IFERROR((SUMPRODUCT($D$26:$M$26/(1+H$65)^$D$34:$M$34)+($M$26*(1+$B70)/(H$65-$B70))/(1+H$65)^$M$34-$C$53-$C$54)/$C$56,"") -> 579.71753
B73: 5. REVERSE DCF
B74: To solve for the market-implied path: Data ▸ What-If Analysis ▸ Goal Seek — set C45 to the current price (C46) by changing C30 (terminal growth) or the Model scenario levers (segment organic growth, non-GAAP margins, M&A spend).
B76: 6. MAUBOUSSIN EV / NOPAT — TWO-STAGE FRAMEWORK
B77: EV/NOPAT = 1/r + [g × (1 − r/ROIIC) / (r × (r − g))] × [1 − ((1+g)/(1+r))^N]
B78: Formula source: Mauboussin & Rappaport, "Expectations Investing" (2021); Counterpoint Global, "What Does a Price-Earnings Multiple Mean?" (2020).
B80: Input | C80: Value | D80: Rationale (Teledyne characteristics)
B81: r (Cost of capital / WACC) | C81: =$C$13 -> 0.0914575 | D81: Linked from Section 1 WACC build
B82: g (NOPAT growth, Stage 1) | C82: 0.08 | D82: Model non-GAAP OI CAGR 2025–30E: mid-single-digit organic growth + margin expansion + bolt-on M&A
B83: ROIIC (Return on incremental invested capital) | C83: 0.75 | D83: Organic growth is capital-light (capex ~2% of sales); acquired growth earns ~8–10% after-tax on purchase price (FLIR goodwill-heavy base: ROIC ~7–9%)
B84: N (Years of value creation / CAP) | C84: 12 | D84: Niche leadership in IR imaging, marine instruments and space-qualified sensors; decentralised serial-acquirer model with disciplined capital allocation
B86: Calculation | C86: Value
B87: Steady-state component: 1 / r | C87: =1/C81 -> 10.93404
B88: Value-creation factor: 1 − r / ROIIC | C88: =1-C81/C83 -> 0.87805667
B89: Growth multiplier: g × (1 − r/ROIIC) / (r × (r − g)) | C89: =C82*C88/(C81*(C81-C82)) -> 67.035266
B90: Time decay: 1 − ((1+g)/(1+r))^N | C90: =1-((1+C82)/(1+C81))^C84 -> 0.11894481
B91: PVGO component (growth value) | C91: =C89*C90 -> 7.9734973
B92: Mauboussin EV / NOPAT (steady-state + PVGO) | C92: =C87+C91 -> 18.907538
B94: VALUATION — Applied to 2028E NOPAT | C94: USDm
B95: 2028E Non-GAAP operating income (Model) | C95: =Model!CQ200 -> 1856.8524
B96: (−) 2028E transaction & integration costs | C96: =-Model!CQ98 -> -5
B97: Tax rate (from WACC build) | C97: =$C$10 -> 0.215
B98: 2028E NOPAT = (OI − transaction costs) × (1 − t) | C98: =(C95+C96)*(1-C97) -> 1453.7042
B99: × Mauboussin EV/NOPAT multiple | C99: =C92 -> 18.907538
B100: Implied Enterprise Value (2028E basis) | C100: =C98*C99 -> 27485.966
B101: Less: YE2027 net debt + NCI (Model) | C101: =Model!CP426+Model!CP436 -> 1827.4646
B102: Implied Equity Value | C102: =C100-C101 -> 25658.502
B103: Diluted shares 2028E (m, Model) | C103: =Model!CQ179 -> 44.756121
B104: Implied share price 2028 ($) | C104: =C102/C103 -> 573.29593
B106: Current share price ($) | C106: =C58 -> 615
B107: Implied upside / (downside) | C107: =C104/C106-1 -> -0.067811503
B109: MARKET-IMPLIED EV/NOPAT TODAY | C109: USDm
B110: Current market cap (spot × diluted shares) | C110: =C58*C56 -> 28828.125
B111: Plus: YE2026 net debt & NCI | C111: =C53+C54 -> 1023.2985
B112: Implied Enterprise Value (today) | C112: =C110+C111 -> 29851.423
B113: TDY's market-implied EV/NOPAT (on 2028E NOPAT) | C113: =C112/C98 -> 20.534731
B115: Multiple gap (Mauboussin − Market) | C115: =C92-C113 -> -1.6271929
B116: Implied re-rating headroom | C116: =C92/C113-1 -> -0.079241015

Sheet Charts
B2: Teledyne Technologies — Historical Operating Performance (2006–2025)
B3: All historicals · USDm · Linked to Model. M&A % = disclosed incremental sales from acquisitions (e.g. DALSA 2011, e2v 2017, FLIR 2021, Excelitas A&D 2025). Non-GAAP OI on the current definition (model memo series) for all years.
C7: 2006 | D7: 2007 | E7: 2008 | F7: 2009 | G7: 2010 | H7: 2011 | I7: 2012 | J7: 2013 | K7: 2014 | L7: 2015 | M7: 2016 | N7: 2017 | O7: 2018 | P7: 2019 | Q7: 2020 | R7: 2021 | S7: 2022 | T7: 2023 | U7: 2024 | V7: 2025
B8: Organic % | C8: =IFERROR(Model!C247+0,0) -> 0 | D8: =IFERROR(Model!D247+0,0) -> 0.019257605 | E8: =IFERROR(Model!E247+0,0) -> -0.02662886 | F8: =IFERROR(Model!F247+0,0) -> -0.063763066 | G8: =IFERROR(Model!G247+0,0) -> -0.020095636 | H8: =IFERROR(Model!H247+0,0) -> 0.029254349 | I8: =IFERROR(Model!I247+0,0) -> 0.00242031 | J8: =IFERROR(Model!O247+0,0) -> 0.018474122 | K8: =IFERROR(Model!U247+0,0) -> 0.00068417002 | L8: =IFERROR(Model!AA247+0,0) -> -0.056307435 | M8: =IFERROR(Model!AG247+0,0) -> -0.075453636 | N8: =IFERROR(Model!AM247+0,0) -> 0.072515001 | O8: =IFERROR(Model!AS247+0,0) -> 0.07024349 | P8: =IFERROR(Model!AY247+0,0) -> 0.044351782 | Q8: =IFERROR(Model!BE247+0,0) -> -0.046244784 | R8: =IFERROR(Model!BK247+0,0) -> 0.082463871 | S8: =IFERROR(Model!BQ247+0,0) -> 0.054309429 | T8: =IFERROR(Model!BW247+0,0) -> 0.014124501 | U8: =IFERROR(Model!CC247+0,0) -> -0.0026439535 | V8: =IFERROR(Model!CI247+0,0) -> 0.030917108
B9: M&A % | C9: =IFERROR(Model!C248+0,0) -> 0 | D9: =IFERROR(Model!D248+0,0) -> 0.1126849 | E9: =IFERROR(Model!E248+0,0) -> 0.088084818 | F9: =IFERROR(Model!F248+0,0) -> 0.023170732 | G9: =IFERROR(Model!G248+0,0) -> 0.015313843 | H9: =IFERROR(Model!H248+0,0) -> 0.15180635 | I9: =IFERROR(Model!I248+0,0) -> 0.093053195 | J9: =IFERROR(Model!O248+0,0) -> 0.080853664 | K9: =IFERROR(Model!U248+0,0) -> 0.023005217 | L9: =IFERROR(Model!AA248+0,0) -> 0.016248956 | M9: =IFERROR(Model!AG248+0,0) -> 0.01096558 | N9: =IFERROR(Model!AM248+0,0) -> 0.1386111 | O9: =IFERROR(Model!AS248+0,0) -> 0.044204624 | P9: =IFERROR(Model!AY248+0,0) -> 0.045868082 | Q9: =IFERROR(Model!BE248+0,0) -> 0.021778986 | R9: =IFERROR(Model!BK248+0,0) -> 0.41267578 | S9: =IFERROR(Model!BQ248+0,0) -> 0.12866524 | T9: =IFERROR(Model!BW248+0,0) -> 0.018283076 | U9: =IFERROR(Model!CC248+0,0) -> 0.0087658593 | V9: =IFERROR(Model!CI248+0,0) -> 0.047636684
C11: =C7 -> 2006 | D11: =D7 -> 2007 | E11: =E7 -> 2008 | F11: =F7 -> 2009 | G11: =G7 -> 2010 | H11: =H7 -> 2011 | I11: =I7 -> 2012 | J11: =J7 -> 2013 | ... V11: =V7 -> 2025
B12: Non-GAAP Operating Income | C12: =Model!C200 -> 132.8 | D12: =Model!D200 -> 168.7 | E12: =Model!E200 -> 214.4 | F12: =Model!F200 -> 183.8 | G12: =Model!G200 -> 192.6 | H12: =Model!H200 -> 251.8 | I12: =Model!I200 -> 272.5 | J12: =Model!O200 -> 271.8 | K12: =Model!U200 -> 326.5 | L12: =Model!AA200 -> 312.3 | M12: =Model!AG200 -> 284 | N12: =Model!AM200 -> 381.8 | O12: =Model!AS200 -> 456.1 | P12: =Model!AY200 -> 528.2 | Q12: =Model!BE200 -> 518.9 | R12: =Model!BK200 -> 983 | S12: =Model!BQ200 -> 1169.7 | T12: =Model!BW200 -> 1239.9 | U12: =Model!CC200 -> 1248 | V12: =Model!CI200 -> 1380
B13: Operating Income (GAAP) | C13: =Model!C160 -> 125.1 | D13: =Model!D160 -> 162.3 | E13: =Model!E160 -> 198.6 | F13: =Model!F160 -> 171.4 | G13: =Model!G160 -> 178.5 | H13: =Model!H160 -> 227.2 | I13: =Model!I160 -> 243.1 | J13: =Model!O160 -> 240.3 | K13: =Model!U160 -> 294.5 | L13: =Model!AA160 -> 281.7 | M13: =Model!AG160 -> 253.8 | N13: =Model!AM160 -> 321.7 | O13: =Model!AS160 -> 416.6 | P13: =Model!AY160 -> 491.7 | Q13: =Model!BE160 -> 480.1 | R13: =Model!BK160 -> 624.3 | S13: =Model!BQ160 -> 972 | T13: =Model!BW160 -> 1034.4 | U13: =Model!CC160 -> 989.1 | V13: =Model!CI160 -> 1149.8
B14: Non-GAAP Op. Margin % | C14: =Model!C254 -> 0.092659782 | D14: =Model!D254 -> 0.10398816 | E14: =Model!E254 -> 0.12450639 | F14: =Model!F254 -> 0.11125235 | G14: =Model!G254 -> 0.11713903 | H14: =Model!H254 -> 0.12966682 | I14: =Model!I254 -> 0.12809665 | J14: =Model!O254 -> 0.11622338 | K14: =Model!U254 -> 0.13638262 | L14: =Model!AA254 -> 0.13589487 | M14: =Model!AG254 -> 0.13209917 | N14: =Model!AM254 -> 0.14663185 | O14: =Model!AS254 -> 0.1571783 | P14: =Model!AY254 -> 0.16696169 | Q14: =Model!BE254 -> 0.16813557 | R14: =Model!BK254 -> 0.2130334 | S14: =Model!BQ254 -> 0.21428571 | T14: =Model!BW254 -> 0.22001597 | U14: =Model!CC254 -> 0.22010582 | V14: =Model!CI254 -> 0.22565981
B15: GAAP Op. Margin % | C15: =Model!C256 -> 0.08728719 | D15: =Model!D256 -> 0.10004315 | E15: =Model!E256 -> 0.11533101 | F15: =Model!F256 -> 0.10374675 | G15: =Model!G256 -> 0.10856344 | H15: =Model!H256 -> 0.11699882 | I15: =Model!I256 -> 0.11427631 | J15: =Model!O256 -> 0.10275378 | K15: =Model!U256 -> 0.12301587 | L15: =Model!AA256 -> 0.12257952 | M15: =Model!AG256 -> 0.118052 | N15: =Model!AM256 -> 0.1235502 | O15: =Model!AS256 -> 0.14356606 | P15: =Model!AY256 -> 0.1554242 | Q15: =Model!BE256 -> 0.15556348 | R15: =Model!BK256 -> 0.13529679 | S15: =Model!BQ256 -> 0.17806764 | T15: =Model!BW256 -> 0.18355071 | U15: =Model!CC256 -> 0.17444444 | V15: =Model!CI256 -> 0.18801714
C17: =C7 -> 2006 | D17: =D7 -> 2007 | E17: =E7 -> 2008 | F17: =F7 -> 2009 | G17: =G7 -> 2010 | H17: =H7 -> 2011 | I17: =I7 -> 2012 | J17: =J7 -> 2013 | ... V17: =V7 -> 2025
B18: ROIC | C18: =IFERROR(Model!C406+0,NA()) -> 0.13522695 | D18: =IFERROR(Model!D406+0,NA()) -> 0.17057143 | E18: =IFERROR(Model!E406+0,NA()) -> 0.15990165 | F18: =IFERROR(Model!F406+0,NA()) -> 0.14391273 | G18: =IFERROR(Model!G406+0,NA()) -> 0.13596164 | H18: =IFERROR(Model!H406+0,NA()) -> 0.13554815 | I18: =IFERROR(Model!I406+0,NA()) -> 0.11330227 | J18: =IFERROR(Model!O406+0,NA()) -> 0.11164521 | K18: =IFERROR(Model!U406+0,NA()) -> 0.12278983 | L18: =IFERROR(Model!AA406+0,NA()) -> 0.11593578 | M18: =IFERROR(Model!AG406+0,NA()) -> 0.10835326 | N18: =IFERROR(Model!AM406+0,NA()) -> 0.10248101 | O18: =IFERROR(Model!AS406+0,NA()) -> 0.13634943 | P18: =IFERROR(Model!AY406+0,NA()) -> 0.13327747 | Q18: =IFERROR(Model!BE406+0,NA()) -> 0.1331728 | R18: =IFERROR(Model!BK406+0,NA()) -> 0.072912591 | S18: =IFERROR(Model!BQ406+0,NA()) -> 0.088705901 | T18: =IFERROR(Model!BW406+0,NA()) -> 0.096969559 | U18: =IFERROR(Model!CC406+0,NA()) -> 0.094512134 | V18: =IFERROR(Model!CI406+0,NA()) -> 0.089368681
B19: RONTA | C19: =IFERROR(Model!C418+0,NA()) -> 0.19588641 | D19: =IFERROR(Model!D418+0,NA()) -> 0.23264547 | E19: =IFERROR(Model!E418+0,NA()) -> 0.2243491 | F19: =IFERROR(Model!F418+0,NA()) -> 0.26515082 | G19: =IFERROR(Model!G418+0,NA()) -> 0.23841984 | H19: =IFERROR(Model!H418+0,NA()) -> 0.28462601 | I19: =IFERROR(Model!I418+0,NA()) -> 0.26087498 | J19: =IFERROR(Model!O418+0,NA()) -> 0.21781571 | K19: =IFERROR(Model!U418+0,NA()) -> 0.25431461 | L19: =IFERROR(Model!AA418+0,NA()) -> 0.24654637 | M19: =IFERROR(Model!AG418+0,NA()) -> 0.2373812 | N19: =IFERROR(Model!AM418+0,NA()) -> 0.26657898 | O19: =IFERROR(Model!AS418+0,NA()) -> 0.33715084 | P19: =IFERROR(Model!AY418+0,NA()) -> 0.31240707 | Q19: =IFERROR(Model!BE418+0,NA()) -> 0.23847787 | R19: =IFERROR(Model!BK418+0,NA()) -> 0.37213017 | S19: =IFERROR(Model!BQ418+0,NA()) -> 0.36071193 | T19: =IFERROR(Model!BW418+0,NA()) -> 0.37209118 | U19: =IFERROR(Model!CC418+0,NA()) -> 0.37197694 | V19: =IFERROR(Model!CI418+0,NA()) -> 0.36576729
B20: Non-GAAP op. margin % | C20: =IFERROR(Model!C254+0,NA()) -> 0.092659782 | D20: =IFERROR(Model!D254+0,NA()) -> 0.10398816 | E20: =IFERROR(Model!E254+0,NA()) -> 0.12450639 | F20: =IFERROR(Model!F254+0,NA()) -> 0.11125235 | G20: =IFERROR(Model!G254+0,NA()) -> 0.11713903 | H20: =IFERROR(Model!H254+0,NA()) -> 0.12966682 | I20: =IFERROR(Model!I254+0,NA()) -> 0.12809665 | J20: =IFERROR(Model!O254+0,NA()) -> 0.11622338 | K20: =IFERROR(Model!U254+0,NA()) -> 0.13638262 | L20: =IFERROR(Model!AA254+0,NA()) -> 0.13589487 | M20: =IFERROR(Model!AG254+0,NA()) -> 0.13209917 | N20: =IFERROR(Model!AM254+0,NA()) -> 0.14663185 | O20: =IFERROR(Model!AS254+0,NA()) -> 0.1571783 | P20: =IFERROR(Model!AY254+0,NA()) -> 0.16696169 | Q20: =IFERROR(Model!BE254+0,NA()) -> 0.16813557 | R20: =IFERROR(Model!BK254+0,NA()) -> 0.2130334 | S20: =IFERROR(Model!BQ254+0,NA()) -> 0.21428571 | T20: =IFERROR(Model!BW254+0,NA()) -> 0.22001597 | U20: =IFERROR(Model!CC254+0,NA()) -> 0.22010582 | V20: =IFERROR(Model!CI254+0,NA()) -> 0.22565981
B21: FCF margin % | C21: =IFERROR(Model!C294+0,NA()) -> 0.036282445 | D21: =IFERROR(Model!D294+0,NA()) -> 0.077914073 | E21: =IFERROR(Model!E294+0,NA()) -> 0.047735192 | F21: =IFERROR(Model!F294+0,NA()) -> 0.073482235 | G21: =IFERROR(Model!G294+0,NA()) -> 0.067388396 | H21: =IFERROR(Model!H294+0,NA()) -> 0.09006643 | I21: =IFERROR(Model!I294+0,NA()) -> 0.058242843 | J21: =IFERROR(Model!O294+0,NA()) -> 0.055888138 | K21: =IFERROR(Model!U294+0,NA()) -> 0.10208855 | L21: =IFERROR(Model!AA294+0,NA()) -> 0.071015186 | M21: =IFERROR(Model!AG294+0,NA()) -> 0.10670264 | N21: =IFERROR(Model!AM294+0,NA()) -> 0.1214379 | O21: =IFERROR(Model!AS294+0,NA()) -> 0.12409539 | P21: =IFERROR(Model!AY294+0,NA()) -> 0.12444683 | Q21: =IFERROR(Model!BE294+0,NA()) -> 0.17740263 | R21: =IFERROR(Model!BK294+0,NA()) -> 0.15668682 | S21: =IFERROR(Model!BQ294+0,NA()) -> 0.072216319 | T21: =IFERROR(Model!BW294+0,NA()) -> 0.12797445 | U21: =IFERROR(Model!CC294+0,NA()) -> 0.19544974 | V21: =IFERROR(Model!CI294+0,NA()) -> 0.1756222

Sheet Sheet1
