Workbook

Sheet Model
AA1: SCENARIO SWITCH ▼ (Bull / Base / Bear) — drives all scenario-linked forecast drivers
B2: Karman Holdings Inc. (NYSE: KRMN) — 3-Statement Financial Model | AA2: Base
B3: US GAAP as reported · USD millions (per-share data in USD) · Source: Karman Forms 10-K / 10-Q, IPO prospectus (Form 424B4, 13-Feb-2025) and Form 8-K earnings releases (Ex. 99.1), SEC EDGAR CIK 0002040127 (investor-relations releases at investors.karman-sd.com are the same documents as filed on EDGAR)
B4: Basis notes: calendar fiscal year. IPO 14-Feb-2025 with Corporate Conversion (TCFIII Spaceco Holdings LLC → Karman Holdings Inc.) — pre-IPO per-unit data (159–167m units) not comparable with ~132m post-IPO shares. One reportable segment; revenue by end market (2024 quarters on the 2025 recast basis; Maritime Defense Systems disclosed from Q1-26). Quarterly data from Q1/24 (first quarters reported, as comparatives in the 2025 10-Qs); FY2022–23 annual only. Acquisitions: RMS (Feb-24), MTI (Apr-25), ISP (May-25), Five Axis (Oct-25), Seemann Composites & Materials Sciences (Q1-26), Walker Precision Engineering (28-Aug-26, after the FY26 outlook). Q3/26E–Q4/26E = FY26 revenue / Adj. EBITDA outlook less 1H/26 actuals.
AC5: Forecast | AD5: Historical
B6: (USDm) | C6: 2022 | D6: 2023 | E6: Q1/24 | F6: Q2/24 | G6: 1H/24 | H6: Q3/24 | I6: Q4/24 | J6: 2024 | K6: Q1/25 | L6: Q2/25 | M6: 1H/25 | N6: Q3/25 | O6: Q4/25 | P6: 2025 | Q6: Q1/26 | R6: Q2/26 | S6: 1H/26 | T6: Q3/26E | U6: Q4/26E | V6: 2026E | W6: 2027E | X6: 2028E | Y6: 2029E | Z6: 2030E | AA6: Modelling Notes | AC6: 5Y CAGR | AD6: 3Y CAGR
AC7: 25-'30 | AD7: 22-'25
B8: END-MARKET REVENUE BUILD — one reportable segment (revenue disaggregated by end market; no segment profit is disclosed) | AA8: END-MARKET BUILD — Karman reports a single operating / reportable segment (ASC 280; CODM = CEO). Revenue is disaggregated by end market in every release; profitability is managed and guided at the consolidated level (Adj. EBITDA), so margins are modelled at group level below.
AG9: SCENARIO INPUT TABLE — driver assumptions per Bull / Base / Bear | AH9: Bull | AI9: Base | AJ9: Bear | AK9: Bull / Bear = Base + Δ (Δ inputs on each block header). Outlook block = high / mid / low end of FY26 ranges.
B10: Hypersonics & Strategic Missile Defense (interceptors — THAAD, SM-3, GMD/NGI; hypersonic test & strategic deterrent programs) | AA10: HYPERSONICS & STRATEGIC MISSILE DEFENSE — modelling logic
B11: Revenue | C11: 72.296 | D11: 100.093 | E11: 24.822 | F11: 28.741 | G11: =E11+F11 -> 53.563 | H11: 26.927 | I11: 34.104 | J11: 114.594 | K11: 30.056 | L11: 34.96 | M11: =K11+L11 -> 65.016 | N11: 36.608 | O11: 48.363 | P11: 149.987 | Q11: 35.688 | R11: 43.417 | S11: =Q11+R11 -> 79.105 | T11: =IFERROR($S11/$S48,0)*T48 -> 45.594981 | U11: =IFERROR($S11/$S48,0)*U48 -> 50.351516 | V11: =SUM(Q11,R11,T11,U11) -> 175.0515 | W11: =V11*(1+W12) -> 206.56077 | X11: =W11*(1+X12) -> 237.54488 | Y11: =X11*(1+Y12) -> 268.42572 | Z11: =Y11*(1+Z12) -> 297.95254 | AA11: Q3/26E–Q4/26E: end-market share of 1H/26 revenue × the outlook-implied 2H/26 quarterly revenue (group block). 2027E–2030E: prior year × (1 + scenario growth lever). | AC11: =IFERROR(IF(AND(Z11>0,P11>0),(Z11/P11)^(1/5)-1,"n/m"),"n/m") -> 0.147146 | AD11: =IFERROR(IF(AND(P11>0,C11>0),(P11/C11)^(1/3)-1,"n/m"),"n/m") -> 0.27540011 | AG11: FY26 outlook — Q2-26 release (6-Aug-26) | AH11: High | AI11: Mid | AJ11: Low
B12: Revenue y/y % | D12: =IFERROR(D11/C11-1,"") -> 0.38448877 | J12: =IFERROR(J11/D11-1,"") -> 0.14487527 | K12: =IFERROR(K11/E11-1,"") -> 0.21086133 | L12: =IFERROR(L11/F11-1,"") -> 0.21638078 | M12: =IFERROR(M11/G11-1,"") -> 0.21382297 | N12: =IFERROR(N11/H11-1,"") -> 0.35952761 | O12: =IFERROR(O11/I11-1,"") -> 0.41810345 | P12: =IFERROR(P11/J11-1,"") -> 0.30885561 | Q12: =IFERROR(Q11/K11-1,"") -> 0.18738355 | ... V12: =IFERROR(V11/P11-1,"") -> 0.16711113 | W12: =CHOOSE(MATCH($AA$2,{"Bull","Base","Bear"},0),$AH$22,$AI$22,$AJ$22) -> 0.18 | X12: =CHOOSE(MATCH($AA$2,{"Bull","Base","Bear"},0),$AH$23,$AI$23,$AJ$23) -> 0.15 | Y12: =CHOOSE(MATCH($AA$2,{"Bull","Base","Bear"},0),$AH$24,$AI$24,$AJ$24) -> 0.13 | Z12: =CHOOSE(MATCH($AA$2,{"Bull","Base","Bear"},0),$AH$25,$AI$25,$AJ$25) -> 0.11 | AA12: 2027E–2030E: scenario lever (HSMD_growth, Bull / Base / Bear table →). Q1-26 onward includes acquisitions (no end-market organic split disclosed). | AC12: =IFERROR(AVERAGE(V12,W12,X12,Y12,Z12),"n/m") -> 0.14742223 | AD12: =IFERROR(AVERAGE(C12,D12,J12,P12),"n/m") -> 0.27940655 | AG12: FY26 revenue ($m) | AH12: 745 | AI12: 737.5 | AJ12: 730 | AK12: Raised from $720–735m (Q1-26) and $715–730m (FY25 release); excludes acquisitions after 6-Aug-26 (Walker).
B13: Mix — % of total revenue | C13: =IFERROR(C11/C92,"") -> 0.31945561 | D13: =IFERROR(D11/D92,"") -> 0.35657719 | E13: =IFERROR(E11/E92,"") -> 0.29903862 | F13: =IFERROR(F11/F92,"") -> 0.33797434 | G13: =IFERROR(G11/G92,"") -> 0.318742 | H13: =IFERROR(H11/H92,"") -> 0.3132212 | I13: =IFERROR(I11/I92,"") -> 0.37379162 | J13: =IFERROR(J11/J92,"") -> 0.33191504 | ... Z13: =IFERROR(Z11/Z92,"") -> 0.17605531 | AC13: =IFERROR(AVERAGE(V13,W13,X13,Y13,Z13),"n/m") -> 0.20248364 | AD13: =IFERROR(AVERAGE(C13,D13,J13,P13),"n/m") -> 0.33151347 | AG13: FY26 Adjusted EBITDA ($m) | AH13: 222.5 | AI13: 218.75 | AJ13: 215 | AK13: Raised from $208.5–219.5m (Q1-26) and $207–218m (FY25 release).
B15: Space & Launch (payload fairings / separation systems, interstage & propulsion components for legacy and new-space launch providers) | AA15: SPACE & LAUNCH — modelling logic | AG15: FY26 point estimates (all cases) | AK15: Not guided — analyst estimates.
B16: Revenue | C16: 79.664 | D16: 94.643 | E16: 30.256 | F16: 28.512 | G16: =E16+F16 -> 58.768 | H16: 27.64 | I16: 28.628 | J16: 115.036 | K16: 33.871 | L16: 39.597 | M16: =K16+L16 -> 73.468 | N16: 40.697 | O16: 35.66 | P16: 149.825 | Q16: 43.854 | R16: 42.072 | S16: =Q16+R16 -> 85.926 | T16: =IFERROR($S16/$S48,0)*T48 -> 49.526506 | U16: =IFERROR($S16/$S48,0)*U48 -> 54.693185 | V16: =SUM(Q16,R16,T16,U16) -> 190.14569 | W16: =V16*(1+W17) -> 218.66755 | X16: =W16*(1+X17) -> 247.09433 | Y16: =X16*(1+Y17) -> 274.2747 | Z16: =Y16*(1+Z17) -> 301.70217 | AA16: Q3/26E–Q4/26E: end-market share of 1H/26 revenue × the outlook-implied 2H/26 quarterly revenue (group block). 2027E–2030E: prior year × (1 + scenario growth lever). | AC16: =IFERROR(IF(AND(Z16>0,P16>0),(Z16/P16)^(1/5)-1,"n/m"),"n/m") -> 0.15026745 | AD16: =IFERROR(IF(AND(P16>0,C16>0),(P16/C16)^(1/3)-1,"n/m"),"n/m") -> 0.23435683 | AG16: Tax rate (GAAP), 2H/26E | AI16: 0.24 | AK16: 1H/26 ETR 21.8%; Q2-26 27.2% (§162(m)).
B17: Revenue y/y % | D17: =IFERROR(D16/C16-1,"") -> 0.18802721 | J17: =IFERROR(J16/D16-1,"") -> 0.21547288 | K17: =IFERROR(K16/E16-1,"") -> 0.11948043 | L17: =IFERROR(L16/F16-1,"") -> 0.38878367 | M17: =IFERROR(M16/G16-1,"") -> 0.25013613 | N17: =IFERROR(N16/H16-1,"") -> 0.47239508 | O17: =IFERROR(O16/I16-1,"") -> 0.24563365 | P17: =IFERROR(P16/J16-1,"") -> 0.30241837 | Q17: =IFERROR(Q16/K16-1,"") -> 0.29473591 | ... V17: =IFERROR(V16/P16-1,"") -> 0.26911858 | W17: =CHOOSE(MATCH($AA$2,{"Bull","Base","Bear"},0),$AH$28,$AI$28,$AJ$28) -> 0.15 | X17: =CHOOSE(MATCH($AA$2,{"Bull","Base","Bear"},0),$AH$29,$AI$29,$AJ$29) -> 0.13 | Y17: =CHOOSE(MATCH($AA$2,{"Bull","Base","Bear"},0),$AH$30,$AI$30,$AJ$30) -> 0.11 | Z17: =CHOOSE(MATCH($AA$2,{"Bull","Base","Bear"},0),$AH$31,$AI$31,$AJ$31) -> 0.1 | AA17: 2027E–2030E: scenario lever (SL_growth, Bull / Base / Bear table →). Q1-26 onward includes acquisitions (no end-market organic split disclosed). | AC17: =IFERROR(AVERAGE(V17,W17,X17,Y17,Z17),"n/m") -> 0.15182372 | AD17: =IFERROR(AVERAGE(C17,D17,J17,P17),"n/m") -> 0.23530616 | AG17: Capital expenditures ($m) | AI17: 36.5 | AK17: Investor Update 16-Sep-26: ~$35–38m 2026 capital investments.
B18: Mix — % of total revenue | C18: =IFERROR(C16/C92,"") -> 0.35201273 | D18: =IFERROR(D16/D92,"") -> 0.33716179 | E18: =IFERROR(E16/E92,"") -> 0.36450377 | F18: =IFERROR(F16/F92,"") -> 0.33528146 | G18: =IFERROR(G16/G92,"") -> 0.34971585 | H18: =IFERROR(H16/H92,"") -> 0.32151498 | I18: =IFERROR(I16/I92,"") -> 0.31377277 | J18: =IFERROR(J16/J92,"") -> 0.33319527 | ... Z18: =IFERROR(Z16/Z92,"") -> 0.17827091 | AC18: =IFERROR(AVERAGE(V18,W18,X18,Y18,Z18),"n/m") -> 0.21190562 | AD18: =IFERROR(AVERAGE(C18,D18,J18,P18),"n/m") -> 0.33503306 | AG18: Share-based compensation per quarter, 2H/26E ($m) | AI18: 1.5 | AK18: Q2-26 RSU / PSU expense $1.4m.
AG19: Transaction + integration costs, 2H/26E total ($m) | AI19: 6 | AK19: Walker deal / integration; 1H/26 $7.0m.
B20: Tactical Missiles & Integrated Defense Systems (tactical SRMs, PrSM / GMLRS content, UAS / counter-UAS launchers; “Missile & Integrated Defense Systems” in the S-1) | AA20: TACTICAL MISSILES & INTEGRATED DEFENSE SYSTEMS — modelling logic
B21: Revenue | C21: 74.351 | D21: 85.969 | E21: 27.928 | F21: 27.786 | G21: =E21+F21 -> 55.714 | H21: 31.401 | I21: 28.506 | J21: 115.621 | K21: 36.197 | L21: 40.54 | M21: =K21+L21 -> 76.737 | N21: 44.482 | O21: 50.469 | P21: 171.688 | Q21: 45.26 | R21: 63.012 | S21: =Q21+R21 -> 108.272 | T21: =IFERROR($S21/$S48,0)*T48 -> 62.406418 | U21: =IFERROR($S21/$S48,0)*U48 -> 68.916748 | V21: =SUM(Q21,R21,T21,U21) -> 239.59517 | W21: =V21*(1+W22) -> 297.09801 | X21: =W21*(1+X22) -> 350.57565 | Y21: =X21*(1+Y22) -> 403.162 | Z21: =Y21*(1+Z22) -> 451.54143 | AA21: Q3/26E–Q4/26E: end-market share of 1H/26 revenue × the outlook-implied 2H/26 quarterly revenue (group block). 2027E–2030E: prior year × (1 + scenario growth lever). | AC21: =IFERROR(IF(AND(Z21>0,P21>0),(Z21/P21)^(1/5)-1,"n/m"),"n/m") -> 0.2133652 | AD21: =IFERROR(IF(AND(P21>0,C21>0),(P21/C21)^(1/3)-1,"n/m"),"n/m") -> 0.32175525 | AG21: HSMD_growth (Hypersonics & Strategic Missile Defense revenue y/y) | AH21: 0.05 | AI21: Δ → | AJ21: -0.08 | AK21: Interceptor ramps (THAAD, SM-3, PAC-3 MSE content; $90bn+ prime awards), NGI and hypersonic test programs; FY25 +30.9%, 1H/26 +21.7%.
B22: Revenue y/y % | D22: =IFERROR(D21/C21-1,"") -> 0.15625883 | J22: =IFERROR(J21/D21-1,"") -> 0.34491503 | K22: =IFERROR(K21/E21-1,"") -> 0.29608278 | L22: =IFERROR(L21/F21-1,"") -> 0.45900813 | M22: =IFERROR(M21/G21-1,"") -> 0.37733783 | N22: =IFERROR(N21/H21-1,"") -> 0.41657909 | O22: =IFERROR(O21/I21-1,"") -> 0.77046937 | P22: =IFERROR(P21/J21-1,"") -> 0.48492056 | Q22: =IFERROR(Q21/K21-1,"") -> 0.25037987 | ... V22: =IFERROR(V21/P21-1,"") -> 0.39552658 | W22: =CHOOSE(MATCH($AA$2,{"Bull","Base","Bear"},0),$AH$34,$AI$34,$AJ$34) -> 0.24 | X22: =CHOOSE(MATCH($AA$2,{"Bull","Base","Bear"},0),$AH$35,$AI$35,$AJ$35) -> 0.18 | Y22: =CHOOSE(MATCH($AA$2,{"Bull","Base","Bear"},0),$AH$36,$AI$36,$AJ$36) -> 0.15 | Z22: =CHOOSE(MATCH($AA$2,{"Bull","Base","Bear"},0),$AH$37,$AI$37,$AJ$37) -> 0.12 | AA22: 2027E–2030E: scenario lever (TMIDS_growth, Bull / Base / Bear table →). Q1-26 onward includes acquisitions (no end-market organic split disclosed). | AC22: =IFERROR(AVERAGE(V22,W22,X22,Y22,Z22),"n/m") -> 0.21710532 | AD22: =IFERROR(AVERAGE(C22,D22,J22,P22),"n/m") -> 0.32869814 | AG22: 2027E | AH22: =AI22+$AH$21 -> 0.23 | AI22: 0.18 | AJ22: =AI22+$AJ$21 -> 0.1
B23: Mix — % of total revenue | C23: =IFERROR(C21/C92,"") -> 0.32853608 | D23: =IFERROR(D21/D92,"") -> 0.30626102 | E23: =IFERROR(E21/E92,"") -> 0.33645761 | F23: =IFERROR(F21/F92,"") -> 0.3267442 | G23: =IFERROR(G21/G92,"") -> 0.33154215 | H23: =IFERROR(H21/H92,"") -> 0.36526382 | I23: =IFERROR(I21/I92,"") -> 0.31243561 | J23: =IFERROR(J21/J92,"") -> 0.33488969 | ... Z23: =IFERROR(Z21/Z92,"") -> 0.26680849 | AC23: =IFERROR(AVERAGE(V23,W23,X23,Y23,Z23),"n/m") -> 0.29458418 | AD23: =IFERROR(AVERAGE(C23,D23,J23,P23),"n/m") -> 0.33345457 | AG23: 2028E | AH23: =AI23+$AH$21 -> 0.2 | AI23: 0.15 | AJ23: =AI23+$AJ$21 -> 0.07
B24: Memo: as originally reported in the IPO prospectus (9M/24 basis before the 2025 recast) | C24: 74.351 | D24: 85.969 | AA24: The 2025 recast moved c.$7m of 9M/24 revenue from Space & Launch into Hypersonics; FY2022–23 were not restated. | AG24: 2029E | AH24: =AI24+$AH$21 -> 0.18 | AI24: 0.13 | AJ24: =AI24+$AJ$21 -> 0.05
AG25: 2030E | AH25: =AI25+$AH$21 -> 0.16 | AI25: 0.11 | AJ25: =AI25+$AJ$21 -> 0.03
B26: Maritime Defense Systems (Columbia / Virginia-class submarine content — Seemann Composites & Materials Sciences, acquired Q1-26; separately disclosed from Q1-26) | AA26: MARITIME DEFENSE SYSTEMS — modelling logic
B27: Revenue | G27: =E27+F27 -> 0 | M27: =K27+L27 -> 0 | Q27: 26.408 | R27: 33.562 | S27: =Q27+R27 -> 59.97 | T27: =IFERROR($S27/$S48,0)*T48 -> 34.565843 | U27: =IFERROR($S27/$S48,0)*U48 -> 38.171802 | V27: =SUM(Q27,R27,T27,U27) -> 132.70765 | W27: =V27*(1+W28) -> 159.24917 | X27: =W27*(1+X28) -> 186.32153 | Y27: =X27*(1+Y28) -> 212.40655 | Z27: =Y27*(1+Z28) -> 237.89533 | AA27: Q3/26E–Q4/26E: end-market share of 1H/26 revenue × the outlook-implied 2H/26 quarterly revenue (group block). 2027E–2030E: prior year × (1 + scenario growth lever). | AC27: =IFERROR(IF(AND(Z27>0,P27>0),(Z27/P27)^(1/5)-1,"n/m"),"n/m") -> n/m | AD27: =IFERROR(IF(AND(P27>0,C27>0),(P27/C27)^(1/3)-1,"n/m"),"n/m") -> n/m | AG27: SL_growth (Space & Launch revenue y/y) | AH27: 0.05 | AI27: Δ → | AJ27: -0.08 | AK27: Legacy + emerging launch providers; new multi-year LTA (Q2-26) vs launch-schedule timing; FY25 +30.2%, 1H/26 +17.0%.
B28: Revenue y/y % | D28: =IFERROR(D27/C27-1,"") | J28: =IFERROR(J27/D27-1,"") | K28: =IFERROR(K27/E27-1,"") | L28: =IFERROR(L27/F27-1,"") | M28: =IFERROR(M27/G27-1,"") | N28: =IFERROR(N27/H27-1,"") | O28: =IFERROR(O27/I27-1,"") | P28: =IFERROR(P27/J27-1,"") | Q28: =IFERROR(Q27/K27-1,"") | ... V28: =IFERROR(V27/P27-1,"") | W28: =CHOOSE(MATCH($AA$2,{"Bull","Base","Bear"},0),$AH$40,$AI$40,$AJ$40) -> 0.2 | X28: =CHOOSE(MATCH($AA$2,{"Bull","Base","Bear"},0),$AH$41,$AI$41,$AJ$41) -> 0.17 | Y28: =CHOOSE(MATCH($AA$2,{"Bull","Base","Bear"},0),$AH$42,$AI$42,$AJ$42) -> 0.14 | Z28: =CHOOSE(MATCH($AA$2,{"Bull","Base","Bear"},0),$AH$43,$AI$43,$AJ$43) -> 0.12 | AA28: 2027E–2030E: scenario lever (MDS_growth, Bull / Base / Bear table →). Q1-26 onward includes acquisitions (no end-market organic split disclosed). | AC28: =IFERROR(AVERAGE(V28,W28,X28,Y28,Z28),"n/m") -> 0.1575 | AD28: =IFERROR(AVERAGE(C28,D28,J28,P28),"n/m") -> n/m | AG28: 2027E | AH28: =AI28+$AH$27 -> 0.2 | AI28: 0.15 | AJ28: =AI28+$AJ$27 -> 0.07
B29: Mix — % of total revenue | C29: =IFERROR(C27/C92,"") -> 0 | D29: =IFERROR(D27/D92,"") -> 0 | E29: =IFERROR(E27/E92,"") -> 0 | F29: =IFERROR(F27/F92,"") -> 0 | G29: =IFERROR(G27/G92,"") -> 0 | H29: =IFERROR(H27/H92,"") -> 0 | I29: =IFERROR(I27/I92,"") -> 0 | J29: =IFERROR(J27/J92,"") -> 0 | ... Z29: =IFERROR(Z27/Z92,"") -> 0.14056848 | AC29: =IFERROR(AVERAGE(V29,W29,X29,Y29,Z29),"n/m") -> 0.15777151 | AD29: =IFERROR(AVERAGE(C29,D29,J29,P29),"n/m") -> 0 | AG29: 2028E | AH29: =AI29+$AH$27 -> 0.18 | AI29: 0.13 | AJ29: =AI29+$AJ$27 -> 0.05
AG30: 2029E | AH30: =AI30+$AH$27 -> 0.16 | AI30: 0.11 | AJ30: =AI30+$AJ$27 -> 0.03
B31: Acquisitions after the FY26 outlook & future acquisitions (M&A lever — Walker Precision Engineering closed 28-Aug-26; scenario spend 2027E+) | AA31: M&A LEVER — Walker (closed 28-Aug-26, ~$95m / £70m cash, funded by a $100m term-loan add-on) is excluded from the FY26 outlook (“excluding the impact of any future acquisitions”). Acquired sales = spend ÷ EV/sales; mid-year convention 2027E+. | AG31: 2030E | AH31: =AI31+$AH$27 -> 0.15 | AI31: 0.1 | AJ31: =AI31+$AJ$27 -> 0.02
B32: Acquisition spend (USDm; 2026E = Walker, scenario 2027E+) | V32: 95 | W32: =CHOOSE(MATCH($AA$2,{"Bull","Base","Bear"},0),$AH$52,$AI$52,$AJ$52) -> 200 | X32: =CHOOSE(MATCH($AA$2,{"Bull","Base","Bear"},0),$AH$53,$AI$53,$AJ$53) -> 225 | Y32: =CHOOSE(MATCH($AA$2,{"Bull","Base","Bear"},0),$AH$54,$AI$54,$AJ$54) -> 250 | Z32: =CHOOSE(MATCH($AA$2,{"Bull","Base","Bear"},0),$AH$55,$AI$55,$AJ$55) -> 250 | AA32: 2026E: Walker ~$95m (8-K 28-Aug-26). 2027E+: scenario lever (M&A_spend). Since IPO Karman has closed ~2.5 deals p.a. at ~10x EBITDA (Investor Update 16-Sep-26).
B33: Purchase multiple — EV / sales (x) | V33: 2.6 | W33: 2.8 | X33: 2.8 | Y33: 2.8 | Z33: 2.8 | AA33: ~10x EBITDA × ~27% acquired EBITDA margin ≈ 2.6–2.8x sales (Investor Update 16-Sep-26: average ~10x, ~27% margin). | AG33: TMIDS_growth (Tactical Missiles & Integrated Defense Systems revenue y/y) | AH33: 0.05 | AI33: Δ → | AJ33: -0.08 | AK33: UAS / C-UAS, tactical SRMs (ISP), PrSM / GMLRS munitions replenishment, European footprint; FY25 +48.5%, 1H/26 +41.1% (incl. acquisitions).
B34: Annualised sales acquired in the year | V34: =IFERROR(V32/V33,0) -> 36.538462 | W34: =IFERROR(W32/W33,0) -> 71.428571 | X34: =IFERROR(X32/X33,0) -> 80.357143 | Y34: =IFERROR(Y32/Y33,0) -> 89.285714 | Z34: =IFERROR(Z32/Z33,0) -> 89.285714 | AG34: 2027E | AH34: =AI34+$AH$33 -> 0.29 | AI34: 0.24 | AJ34: =AI34+$AJ$33 -> 0.16
B35: Growth of acquired businesses after acquisition % | W35: 0.12 | X35: 0.12 | Y35: 0.12 | Z35: 0.12 | AA35: Acquired businesses grew ~25% under Karman ownership (Investor Update); 12% assumed post-integration. | AG35: 2028E | AH35: =AI35+$AH$33 -> 0.23 | AI35: 0.18 | AJ35: =AI35+$AJ$33 -> 0.1
B36: Run-rate sales of businesses acquired (year end) | V36: =V34 -> 36.538462 | W36: =V36*(1+W35)+W34 -> 112.35165 | X36: =W36*(1+X35)+X34 -> 206.19099 | Y36: =X36*(1+Y35)+Y34 -> 320.21962 | Z36: =Y36*(1+Z35)+Z34 -> 447.93169 | AG36: 2029E | AH36: =AI36+$AH$33 -> 0.2 | AI36: 0.15 | AJ36: =AI36+$AJ$33 -> 0.07
B37: Net sales from post-outlook / future acquisitions | T37: 3 | U37: 9 | V37: =SUM(Q37,R37,T37,U37) -> 12 | W37: =V36*(1+W35)+0.5*W34 -> 76.637363 | X37: =W36*(1+X35)+0.5*X34 -> 166.01242 | Y37: =X36*(1+Y35)+0.5*Y34 -> 275.57676 | Z37: =Y36*(1+Z35)+0.5*Z34 -> 403.28883 | AA37: Q3/26E: ~1 month of Walker (~$36m annual run-rate est. = $95m ÷ 2.6x); Q4/26E full quarter. 2027E+: opening run-rate × (1+g) + ½ of sales acquired in the year. | AG37: 2030E | AH37: =AI37+$AH$33 -> 0.17 | AI37: 0.12 | AJ37: =AI37+$AJ$33 -> 0.04
B38: Adjusted EBITDA margin of acquired businesses % | V38: 0.27 | W38: 0.27 | X38: 0.27 | Y38: 0.27 | Z38: 0.27
B39: Adjusted EBITDA from post-outlook / future acquisitions | T39: =T37*$V38 -> 0.81 | U39: =U37*$V38 -> 2.43 | V39: =SUM(Q39,R39,T39,U39) -> 3.24 | W39: =W37*W38 -> 20.692088 | X39: =X37*X38 -> 44.823353 | Y39: =Y37*Y38 -> 74.405727 | Z39: =Z37*Z38 -> 108.88799 | AG39: MDS_growth (Maritime Defense Systems revenue y/y) | AH39: 0.05 | AI39: Δ → | AJ39: -0.08 | AK39: Columbia / Virginia-class submarine build-rate ramp ($76bn+ awards); disclosed from Q1-26 (Seemann / MSC).
B40: Acquired intangibles % of spend | V40: 0.45 | W40: 0.45 | X40: 0.45 | Y40: 0.45 | Z40: 0.45 | AA40: Karman acquisitions 2024–26: identified intangibles ≈ 30–55% of consideration (customer relationships, backlog, know-how). | AG40: 2027E | AH40: =AI40+$AH$39 -> 0.25 | AI40: 0.2 | AJ40: =AI40+$AJ$39 -> 0.12
B41: Amortization life (years) | V41: 12 | W41: 12 | X41: 12 | Y41: 12 | Z41: 12 | AG41: 2028E | AH41: =AI41+$AH$39 -> 0.22 | AI41: 0.17 | AJ41: =AI41+$AJ$39 -> 0.09
B42: Cumulative acquired intangibles (gross) | V42: =V32*V40 -> 42.75 | W42: =V42+W32*W40 -> 132.75 | X42: =W42+X32*X40 -> 234 | Y42: =X42+Y32*Y40 -> 346.5 | Z42: =Y42+Z32*Z40 -> 459 | AG42: 2029E | AH42: =AI42+$AH$39 -> 0.19 | AI42: 0.14 | AJ42: =AI42+$AJ$39 -> 0.06
B43: Amortization of post-outlook / future-acquisition intangibles | T43: =$V42/$V41/12 -> 0.296875 | U43: =$V42/$V41/4 -> 0.890625 | V43: =SUM(Q43,R43,T43,U43) -> 1.1875 | W43: =(V42+0.5*W32*W40)/W41 -> 7.3125 | X43: =(W42+0.5*X32*X40)/X41 -> 15.28125 | Y43: =(X42+0.5*Y32*Y40)/Y41 -> 24.1875 | Z43: =(Y42+0.5*Z32*Z40)/Z41 -> 33.5625 | AG43: 2030E | AH43: =AI43+$AH$39 -> 0.17 | AI43: 0.12 | AJ43: =AI43+$AJ$39 -> 0.04
B44: Adjusted EBITA from post-outlook / future acquisitions | T44: =T39-T43 -> 0.513125 | U44: =U39-U43 -> 1.539375 | V44: =SUM(Q44,R44,T44,U44) -> 2.0525 | W44: =W39-W43 -> 13.379588 | X44: =X39-X43 -> 29.542103 | Y44: =Y39-Y43 -> 50.218227 | Z44: =Z39-Z43 -> 75.325485
B45: Incremental acquisition sales (first 12 months of ownership) | T45: =T37 -> 3 | U45: =U37 -> 9 | V45: =SUM(Q45,R45,T45,U45) -> 12 | W45: =0.5*W34+0.5*V34 -> 53.983516 | X45: =0.5*X34+0.5*W34 -> 75.892857 | Y45: =0.5*Y34+0.5*X34 -> 84.821429 | Z45: =0.5*Z34+0.5*Y34 -> 89.285714 | AG45: ADJ_EBITDA_margin (Adjusted EBITDA margin, outlook / organic basis) | AH45: 0.01 | AI45: Δ → | AJ45: -0.02 | AK45: FY25 30.8%; FY26 outlook mid 29.7%; IPO target ~30%+; operating leverage vs capacity-ramp costs.
AG46: 2027E | AH46: =AI46+$AH$45 -> 0.31 | AI46: 0.3 | AJ46: =AI46+$AJ$45 -> 0.28
B47: Group Total — Adjusted EBITDA (Karman's primary profit measure and guidance metric) | AA47: GROUP TOTAL — Q3/26E–Q4/26E are calibrated to the FY26 outlook (scenario end-point: High / Mid / Low) less 1H/26 actuals; 2H split by the prior-year Q3:Q4 revenue pattern. 2027E+: end-market revenue × Adj. EBITDA margin lever + M&A lever. | AG47: 2028E | AH47: =AI47+$AH$45 -> 0.313 | AI47: 0.303 | AJ47: =AI47+$AJ$45 -> 0.283
B48: Net sales — end-market build (outlook basis) | C48: =N(C11)+N(C16)+N(C21)+N(C27) -> 226.311 | D48: =N(D11)+N(D16)+N(D21)+N(D27) -> 280.705 | E48: =N(E11)+N(E16)+N(E21)+N(E27) -> 83.006 | F48: =N(F11)+N(F16)+N(F21)+N(F27) -> 85.039 | G48: =E48+F48 -> 168.045 | H48: =N(H11)+N(H16)+N(H21)+N(H27) -> 85.968 | I48: =N(I11)+N(I16)+N(I21)+N(I27) -> 91.238 | J48: =N(J11)+N(J16)+N(J21)+N(J27) -> 345.251 | K48: =N(K11)+N(K16)+N(K21)+N(K27) -> 100.124 | L48: =N(L11)+N(L16)+N(L21)+N(L27) -> 115.097 | M48: =K48+L48 -> 215.221 | N48: =N(N11)+N(N16)+N(N21)+N(N27) -> 121.787 | O48: =N(O11)+N(O16)+N(O21)+N(O27) -> 134.492 | P48: =N(P11)+N(P16)+N(P21)+N(P27) -> 471.5 | Q48: =N(Q11)+N(Q16)+N(Q21)+N(Q27) -> 151.21 | R48: =N(R11)+N(R16)+N(R21)+N(R27) -> 182.063 | S48: =Q48+R48 -> 333.273 | T48: =($V76-$S48)*N92/(N92+O92) -> 192.09375 | U48: =($V76-$S48)*O92/(N92+O92) -> 212.13325 | V48: =SUM(Q48,R48,T48,U48) -> 737.5 | W48: =N(W11)+N(W16)+N(W21)+N(W27) -> 881.57549 | X48: =N(X11)+N(X16)+N(X21)+N(X27) -> 1021.5364 | Y48: =N(Y11)+N(Y16)+N(Y21)+N(Y27) -> 1158.269 | Z48: =N(Z11)+N(Z16)+N(Z21)+N(Z27) -> 1289.0915 | AC48: =IFERROR(IF(AND(Z48>0,P48>0),(Z48/P48)^(1/5)-1,"n/m"),"n/m") -> 0.22281402 | AD48: =IFERROR(IF(AND(P48>0,C48>0),(P48/C48)^(1/3)-1,"n/m"),"n/m") -> 0.27719932 | AG48: 2029E | AH48: =AI48+$AH$45 -> 0.316 | AI48: 0.306 | AJ48: =AI48+$AJ$45 -> 0.286
B49: Net sales (end-market build + post-outlook / future acquisitions) | C49: =C48 -> 226.311 | D49: =D48 -> 280.705 | E49: =E48 -> 83.006 | F49: =F48 -> 85.039 | G49: =E49+F49 -> 168.045 | H49: =H48 -> 85.968 | I49: =I48 -> 91.238 | J49: =J48 -> 345.251 | K49: =K48 -> 100.124 | L49: =L48 -> 115.097 | M49: =K49+L49 -> 215.221 | N49: =N48 -> 121.787 | O49: =O48 -> 134.492 | P49: =P48 -> 471.5 | Q49: =Q48 -> 151.21 | R49: =R48 -> 182.063 | S49: =Q49+R49 -> 333.273 | T49: =T48+T37 -> 195.09375 | U49: =U48+U37 -> 221.13325 | V49: =SUM(Q49,R49,T49,U49) -> 749.5 | W49: =W48+W37 -> 958.21285 | X49: =X48+X37 -> 1187.5488 | Y49: =Y48+Y37 -> 1433.8457 | Z49: =Z48+Z37 -> 1692.3803 | AC49: =IFERROR(IF(AND(Z49>0,P49>0),(Z49/P49)^(1/5)-1,"n/m"),"n/m") -> 0.29122895 | AD49: =IFERROR(IF(AND(P49>0,C49>0),(P49/C49)^(1/3)-1,"n/m"),"n/m") -> 0.27719932 | AG49: 2030E | AH49: =AI49+$AH$45 -> 0.32 | AI49: 0.31 | AJ49: =AI49+$AJ$45 -> 0.29
B50: Net sales y/y % | D50: =IFERROR(D49/C49-1,"") -> 0.24035067 | J50: =IFERROR(J49/D49-1,"") -> 0.22994247 | K50: =IFERROR(K49/E49-1,"") -> 0.20622606 | L50: =IFERROR(L49/F49-1,"") -> 0.35346135 | M50: =IFERROR(M49/G49-1,"") -> 0.28073433 | N50: =IFERROR(N49/H49-1,"") -> 0.41665503 | O50: =IFERROR(O49/I49-1,"") -> 0.47407878 | P50: =IFERROR(P49/J49-1,"") -> 0.36567309 | Q50: =IFERROR(Q49/K49-1,"") -> 0.51022732 | ... V50: =IFERROR(V49/P49-1,"") -> 0.58960764 | W50: =IFERROR(W49/V49-1,"") -> 0.27846945 | X50: =IFERROR(X49/W49-1,"") -> 0.23933717 | Y50: =IFERROR(Y49/X49-1,"") -> 0.20739941 | Z50: =IFERROR(Z49/Y49-1,"") -> 0.18030851 | AC50: =IFERROR(AVERAGE(V50,W50,X50,Y50,Z50),"n/m") -> 0.29902444 | AD50: =IFERROR(AVERAGE(C50,D50,J50,P50),"n/m") -> 0.27865541
B51: Adjusted EBITDA — outlook basis | C51: =C146 -> 60.291 | D51: =D146 -> 81.861 | E51: =E146 -> 24.297 | F51: =F146 -> 27.424 | G51: =E51+F51 -> 51.721 | H51: =H146 -> 28.065 | I51: =I146 -> 26.359 | J51: =J146 -> 106.145 | K51: =K146 -> 30.319 | L51: =L146 -> 35.281 | M51: =K51+L51 -> 65.6 | N51: =N146 -> 37.725 | O51: =O146 -> 41.977 | P51: =P146 -> 145.302 | Q51: =Q146 -> 44.786 | R51: =R146 -> 54.58 | S51: =Q51+R51 -> 99.366 | T51: =($V77-$S51)*T48/($V76-$S48) -> 56.732776 | U51: =($V77-$S51)*U48/($V76-$S48) -> 62.651224 | V51: =SUM(Q51,R51,T51,U51) -> 218.75 | W51: =W48*W52 -> 264.47265 | X51: =X48*X52 -> 309.52553 | Y51: =Y48*Y52 -> 354.4303 | Z51: =Z48*Z52 -> 399.61836 | AA51: Historical = company-published Adj. EBITDA. 2H/26E = FY26 Adj. EBITDA outlook − 1H/26 actual, split pro rata to quarterly revenue. | AC51: =IFERROR(IF(AND(Z51>0,P51>0),(Z51/P51)^(1/5)-1,"n/m"),"n/m") -> 0.22426312 | AD51: =IFERROR(IF(AND(P51>0,C51>0),(P51/C51)^(1/3)-1,"n/m"),"n/m") -> 0.34072498 | AG51: M&A_spend (acquisition spend, $m) | AH51: 150 | AI51: Δ → | AJ51: -150 | AK51: Since IPO: ~2.5 deals p.a., $5–15m EBITDA each at ~10x (~$300m in 2026). Funded by revolver / term-loan add-ons.
B52: Adjusted EBITDA margin — outlook basis % | C52: =IFERROR(C51/C48,"") -> 0.26640773 | D52: =IFERROR(D51/D48,"") -> 0.29162644 | E52: =IFERROR(E51/E48,"") -> 0.29271378 | F52: =IFERROR(F51/F48,"") -> 0.32248733 | G52: =IFERROR(G51/G48,"") -> 0.30778065 | H52: =IFERROR(H51/H48,"") -> 0.32645868 | I52: =IFERROR(I51/I48,"") -> 0.28890375 | J52: =IFERROR(J51/J48,"") -> 0.30744299 | ... V52: =IFERROR(V51/V48,"") -> 0.29661017 | W52: =CHOOSE(MATCH($AA$2,{"Bull","Base","Bear"},0),$AH$46,$AI$46,$AJ$46) -> 0.3 | X52: =CHOOSE(MATCH($AA$2,{"Bull","Base","Bear"},0),$AH$47,$AI$47,$AJ$47) -> 0.303 | Y52: =CHOOSE(MATCH($AA$2,{"Bull","Base","Bear"},0),$AH$48,$AI$48,$AJ$48) -> 0.306 | Z52: =CHOOSE(MATCH($AA$2,{"Bull","Base","Bear"},0),$AH$49,$AI$49,$AJ$49) -> 0.31 | AA52: 2027E–2030E: scenario lever (ADJ_EBITDA_margin). FY25 30.8%; 1H/26 29.8%; FY26 outlook mid-point 29.7% (incl. Seemann / MSC dilution). | AC52: =IFERROR(AVERAGE(V52,W52,X52,Y52,Z52),"n/m") -> 0.30312203 | AD52: =IFERROR(AVERAGE(C52,D52,J52,P52),"n/m") -> 0.29341171 | AG52: 2027E | AH52: =MAX(0,AI52+$AH$51) -> 350 | AI52: 200 | AJ52: =MAX(0,AI52+$AJ$51) -> 50
B53: Adjusted EBITDA — post-outlook / future acquisitions | T53: =T39 -> 0.81 | U53: =U39 -> 2.43 | V53: =SUM(Q53,R53,T53,U53) -> 3.24 | W53: =W39 -> 20.692088 | X53: =X39 -> 44.823353 | Y53: =Y39 -> 74.405727 | Z53: =Z39 -> 108.88799 | AG53: 2028E | AH53: =MAX(0,AI53+$AH$51) -> 375 | AI53: 225 | AJ53: =MAX(0,AI53+$AJ$51) -> 75
B54: Adjusted EBITDA (group build) | C54: =C146 -> 60.291 | D54: =D146 -> 81.861 | E54: =E146 -> 24.297 | F54: =F146 -> 27.424 | G54: =E54+F54 -> 51.721 | H54: =H146 -> 28.065 | I54: =I146 -> 26.359 | J54: =J146 -> 106.145 | K54: =K146 -> 30.319 | L54: =L146 -> 35.281 | M54: =K54+L54 -> 65.6 | N54: =N146 -> 37.725 | O54: =O146 -> 41.977 | P54: =P146 -> 145.302 | Q54: =Q146 -> 44.786 | R54: =R146 -> 54.58 | S54: =Q54+R54 -> 99.366 | T54: =T51+T53 -> 57.542776 | U54: =U51+U53 -> 65.081224 | V54: =SUM(Q54,R54,T54,U54) -> 221.99 | W54: =W51+W53 -> 285.16474 | X54: =X51+X53 -> 354.34888 | Y54: =Y51+Y53 -> 428.83603 | Z54: =Z51+Z53 -> 508.50635 | AC54: =IFERROR(IF(AND(Z54>0,P54>0),(Z54/P54)^(1/5)-1,"n/m"),"n/m") -> 0.28470956 | AD54: =IFERROR(IF(AND(P54>0,C54>0),(P54/C54)^(1/3)-1,"n/m"),"n/m") -> 0.34072498 | AG54: 2029E | AH54: =MAX(0,AI54+$AH$51) -> 400 | AI54: 250 | AJ54: =MAX(0,AI54+$AJ$51) -> 100
B55: Adjusted EBITDA margin % | C55: =IFERROR(C54/C49,"") -> 0.26640773 | D55: =IFERROR(D54/D49,"") -> 0.29162644 | E55: =IFERROR(E54/E49,"") -> 0.29271378 | F55: =IFERROR(F54/F49,"") -> 0.32248733 | G55: =IFERROR(G54/G49,"") -> 0.30778065 | H55: =IFERROR(H54/H49,"") -> 0.32645868 | I55: =IFERROR(I54/I49,"") -> 0.28890375 | J55: =IFERROR(J54/J49,"") -> 0.30744299 | ... Z55: =IFERROR(Z54/Z49,"") -> 0.30046813 | AC55: =IFERROR(AVERAGE(V55,W55,X55,Y55,Z55),"n/m") -> 0.29834413 | AD55: =IFERROR(AVERAGE(C55,D55,J55,P55),"n/m") -> 0.29341171 | AG55: 2030E | AH55: =MAX(0,AI55+$AH$51) -> 400 | AI55: 250 | AJ55: =MAX(0,AI55+$AJ$51) -> 100
B56: Adjusted EBITDA y/y % | D56: =IFERROR(D54/C54-1,"") -> 0.35776484 | J56: =IFERROR(J54/D54-1,"") -> 0.2966492 | K56: =IFERROR(K54/E54-1,"") -> 0.24784953 | L56: =IFERROR(L54/F54-1,"") -> 0.28650088 | M56: =IFERROR(M54/G54-1,"") -> 0.26834361 | N56: =IFERROR(N54/H54-1,"") -> 0.34420096 | O56: =IFERROR(O54/I54-1,"") -> 0.5925111 | P56: =IFERROR(P54/J54-1,"") -> 0.36890103 | Q56: =IFERROR(Q54/K54-1,"") -> 0.47715954 | ... V56: =IFERROR(V54/P54-1,"") -> 0.52778351 | W56: =IFERROR(W54/V54-1,"") -> 0.2845837 | X56: =IFERROR(X54/W54-1,"") -> 0.24261114 | Y56: =IFERROR(Y54/X54-1,"") -> 0.21020851 | Z56: =IFERROR(Z54/Y54-1,"") -> 0.1857827 | AC56: =IFERROR(AVERAGE(V56,W56,X56,Y56,Z56),"n/m") -> 0.29019391 | AD56: =IFERROR(AVERAGE(C56,D56,J56,P56),"n/m") -> 0.34110502
B57: Incremental Adj. EBITDA margin (ΔAdj. EBITDA / ΔSales) | D57: =IFERROR((D54-C54)/(D49-C49),"") -> 0.39655109 | J57: =IFERROR((J54-D54)/(J49-D49),"") -> 0.37622781 | K57: =IFERROR((K54-E54)/(K49-E49),"") -> 0.35179343 | L57: =IFERROR((L54-F54)/(L49-F49),"") -> 0.26139464 | M57: =IFERROR((M54-G54)/(M49-G49),"") -> 0.2941962 | N57: =IFERROR((N54-H54)/(N49-H49),"") -> 0.26968927 | O57: =IFERROR((O54-I54)/(O49-I49),"") -> 0.36107643 | P57: =IFERROR((P54-J54)/(P49-J49),"") -> 0.31015691 | Q57: =IFERROR((Q54-K54)/(Q49-K49),"") -> 0.28318913 | ... V57: =IFERROR((V54-P54)/(V49-P49),"") -> 0.27585612 | W57: =IFERROR((W54-V54)/(W49-V49),"") -> 0.30268732 | X57: =IFERROR((X54-W54)/(X49-W49),"") -> 0.3016716 | Y57: =IFERROR((Y54-X54)/(Y49-X49),"") -> 0.30242826 | Z57: =IFERROR((Z54-Y54)/(Z49-Y49),"") -> 0.30816115 | AC57: =IFERROR(AVERAGE(V57,W57,X57,Y57,Z57),"n/m") -> 0.29816089 | AD57: =IFERROR(AVERAGE(C57,D57,J57,P57),"n/m") -> 0.3609786 | AG57: Buybacks ($m) | AH57: 0 | AI57: Δ → | AJ57: 0 | AK57: No repurchase authorisation; capital priority is organic capacity and M&A.
B58: (−) Share-based compensation (excluded from Adj. EBITDA) | C58: 1.603 | D58: 1.291 | E58: 0.251 | F58: 0.246 | G58: =E58+F58 -> 0.497 | H58: 0.248 | I58: 0.248 | J58: 0.993 | K58: 8.084 | L58: 0 | M58: =K58+L58 -> 8.084 | N58: 0 | O58: 0 | P58: 8.084 | Q58: 0 | R58: 1.444 | S58: =Q58+R58 -> 1.444 | T58: =$AI$18 -> 1.5 | U58: =$AI$18 -> 1.5 | V58: =SUM(Q58,R58,T58,U58) -> 4.444 | W58: =W49*W87 -> 7.6657028 | X58: =X49*X87 -> 9.5003905 | Y58: =Y49*Y87 -> 11.470766 | Z58: =Z49*Z87 -> 13.539043 | AA58: Pre-IPO P / Phantom Units (fully vested at IPO — $8.1m in Q1-25); RSU / PSU expense from Q2-26. 2H/26E per quarter from the point-estimate table; 2027E+ % of sales. | AG58: 2027E | AH58: =MAX(0,AI58+$AH$57) -> 0 | AI58: 0 | AJ58: =MAX(0,AI58+$AJ$57) -> 0
B59: (−) Transaction-related expenses | C59: 0.251 | D59: 0.356 | E59: 2.011 | F59: 0.079 | G59: =E59+F59 -> 2.09 | H59: 1.074 | I59: 1.612 | J59: 4.776 | K59: 1.962 | L59: 3.904 | M59: =K59+L59 -> 5.866 | N59: 3.533 | O59: 3.342 | P59: 12.741 | Q59: 2.263 | R59: 1.392 | S59: =Q59+R59 -> 3.655 | T59: =$AI$19/4 -> 1.5 | U59: =$AI$19/4 -> 1.5 | V59: =SUM(Q59,R59,T59,U59) -> 6.655 | W59: =W32*W88 -> 6 | X59: =X32*X88 -> 6.75 | Y59: =Y32*Y88 -> 7.5 | Z59: =Z32*Z88 -> 7.5 | AG59: 2028E | AH59: =MAX(0,AI59+$AH$57) -> 0 | AI59: 0 | AJ59: =MAX(0,AI59+$AJ$57) -> 0
B60: (−) Integration expenses and non-recurring restructuring costs | C60: 3.507 | D60: 2.739 | E60: 0.416 | F60: 0.476 | G60: =E60+F60 -> 0.892 | H60: 0.849 | I60: 0.514 | J60: 2.255 | K60: 0.261 | L60: 0.38 | M60: =K60+L60 -> 0.641 | N60: 0.559 | O60: 1.079 | P60: 2.279 | Q60: 1.41 | R60: 1.94 | S60: =Q60+R60 -> 3.35 | T60: =$AI$19/4 -> 1.5 | U60: =$AI$19/4 -> 1.5 | V60: =SUM(Q60,R60,T60,U60) -> 6.35 | W60: 2 | X60: 2 | Y60: 2 | Z60: 2 | AG60: 2029E | AH60: =MAX(0,AI60+$AH$57) -> 0 | AI60: 0 | AJ60: =MAX(0,AI60+$AJ$57) -> 0
B61: (−) Lender and administrative agent fees | C61: 0 | D61: 0.5 | E61: 0 | F61: 0 | G61: =E61+F61 -> 0 | H61: 0 | I61: 0.1 | J61: 0.1 | K61: 1.26 | L61: 0.206 | M61: =K61+L61 -> 1.466 | N61: 0 | O61: 0.106 | P61: 1.572 | Q61: 0.735 | R61: 0.045 | S61: =Q61+R61 -> 0.78 | T61: 0.5 | U61: 0 | V61: =SUM(Q61,R61,T61,U61) -> 1.28 | W61: 0 | X61: 0 | Y61: 0 | Z61: 0 | AA61: Q3/26E: Fifth / Sixth credit-agreement amendments (repricing 3-Aug-26; $100m incremental 26-Aug-26). | AG61: 2030E | AH61: =MAX(0,AI61+$AH$57) -> 0 | AI61: 0 | AJ61: =MAX(0,AI61+$AJ$57) -> 0
B62: (−) Other non-recurring costs (included in Adj. EBITDA bridge) | C62: -0.281 | D62: 0.739 | E62: 0 | F62: 0 | G62: =E62+F62 -> 0 | H62: 0 | I62: 0 | J62: 0 | K62: 0 | L62: 0 | M62: =K62+L62 -> 0 | N62: 0.8 | O62: 0 | P62: 0.8 | Q62: 2.468 | R62: 0.034 | S62: =Q62+R62 -> 2.502 | T62: 0 | U62: 0 | V62: =SUM(Q62,R62,T62,U62) -> 2.502 | W62: 0 | X62: 0 | Y62: 0 | Z62: 0
B63: EBITDA (company definition: NI + tax + D&A + interest) | C63: =C138 -> 55.211 | D63: =D138 -> 76.236 | E63: =E138 -> 21.619 | F63: =F138 -> 26.623 | G63: =E63+F63 -> 48.242 | H63: =H138 -> 25.894 | I63: =I138 -> 23.885 | J63: =J138 -> 98.021 | K63: =K138 -> 18.752 | L63: =L138 -> 30.791 | M63: =K63+L63 -> 49.543 | N63: =N138 -> 32.833 | O63: =O138 -> 37.45 | P63: =P138 -> 119.826 | Q63: =Q138 -> 37.91 | R63: =R138 -> 49.725 | S63: =Q63+R63 -> 87.635 | T63: =T54-T58-T59-T60-T61-T62 -> 52.542776 | U63: =U54-U58-U59-U60-U61-U62 -> 60.581224 | V63: =SUM(Q63,R63,T63,U63) -> 200.759 | W63: =W54-W58-W59-W60-W61-W62 -> 269.49903 | X63: =X54-X58-X59-X60-X61-X62 -> 336.09849 | Y63: =Y54-Y58-Y59-Y60-Y61-Y62 -> 407.86526 | Z63: =Z54-Z58-Z59-Z60-Z61-Z62 -> 485.4673 | AC63: =IFERROR(IF(AND(Z63>0,P63>0),(Z63/P63)^(1/5)-1,"n/m"),"n/m") -> 0.32288406 | AD63: =IFERROR(IF(AND(P63>0,C63>0),(P63/C63)^(1/3)-1,"n/m"),"n/m") -> 0.29471789 | AG63: Min. net debt / adj. EBITDA (x) — buyback plug | AH63: 2.5 | AI63: 2 | AJ63: 2 | AK63: Surplus cash below this leverage floor goes to buybacks (Model leverage-targeted buyback rows).
B64: (−) Depreciation of PP&E (total D&A − ROU − acquired-intangible amortization) | C64: =C106-C65-C66 -> 5.599 | D64: =D106-D65-D66 -> 8.009 | E64: =E106-E65-E66 -> 1.937 | F64: =F106-F65-F66 -> 2.295 | G64: =E64+F64 -> 4.232 | H64: =H106-H65-H66 -> 2.186 | I64: =I106-I65-I66 -> 3.396 | J64: =J106-J65-J66 -> 9.813 | K64: =K106-K65-K66 -> 2.176 | L64: =L106-L65-L66 -> 3.676 | M64: =K64+L64 -> 5.852 | N64: =N106-N65-N66 -> 3.262 | O64: =O106-O65-O66 -> 3.46 | P64: =P106-P65-P66 -> 12.574 | Q64: =Q106-Q65-Q66 -> 3.903 | R64: =R106-R65-R66 -> 4.062 | S64: =Q64+R64 -> 7.965 | T64: =R64*1.04 -> 4.22448 | U64: =T64*1.04 -> 4.3934592 | V64: =SUM(Q64,R64,T64,U64) -> 16.582939 | W64: =W49*W85 -> 22.997109 | X64: =X49*X85 -> 30.876269 | Y64: =Y49*Y85 -> 38.713835 | Z64: =Z49*Z85 -> 47.386649 | AA64: Q3/Q4-26E: Q2/26 run-rate +4% q/q (capacity additions — capex ~$35–38m in 2026 per the Investor Update); 2027E+ % of sales.
B65: (−) Amortization of finance-lease right-of-use assets | C65: 4.527 | D65: 4.764 | E65: 1.513 | F65: 1.611 | G65: =E65+F65 -> 3.124 | H65: 1.65 | I65: 1.472 | J65: 6.246 | K65: 2.293 | L65: 1.131 | M65: =K65+L65 -> 3.424 | N65: 1.708 | O65: 1.831 | P65: 6.963 | Q65: 1.829 | R65: 1.914 | S65: =Q65+R65 -> 3.743 | T65: =$R65 -> 1.914 | U65: =$R65 -> 1.914 | V65: =SUM(Q65,R65,T65,U65) -> 7.571 | W65: =V65*(1+W86) -> 7.94955 | X65: =W65*(1+X86) -> 8.3470275 | Y65: =X65*(1+Y86) -> 8.7643789 | Z65: =Y65*(1+Z86) -> 9.2025978
B66: (−) Amortization of acquired intangible assets | C66: 24.856 | D66: 14.406 | E66: 3.9 | F66: 4.4 | G66: =E66+F66 -> 8.3 | H66: 4.3 | I66: 4.3 | J66: 16.9 | K66: 4.4 | L66: 5.5 | M66: =K66+L66 -> 9.9 | N66: 6 | O66: 7.3 | P66: 23.2 | Q66: 10.9 | R66: 9.2 | S66: =Q66+R66 -> 20.1 | T66: =($V297-$S66)/2+T43 -> 9.496875 | U66: =($V297-$S66)/2+U43 -> 10.090625 | V66: =SUM(Q66,R66,T66,U66) -> 39.6875 | W66: =W297+W43 -> 40.3125 | X66: =X297+X43 -> 41.28125 | Y66: =Y297+Y43 -> 48.1875 | Z66: =Z297+Z43 -> 57.0625 | AA66: Existing intangibles: FY2025 10-K schedule ($29.3m 2026E) + Seemann / MSC (Q2-26 run-rate $9.2m / qtr) — see schedule row; plus post-outlook / future acquisitions.
B67: Total depreciation & amortization | C67: =C64+C65+C66 -> 34.982 | D67: =D64+D65+D66 -> 27.179 | E67: =E64+E65+E66 -> 7.35 | F67: =F64+F65+F66 -> 8.306 | G67: =G64+G65+G66 -> 15.656 | H67: =H64+H65+H66 -> 8.136 | I67: =I64+I65+I66 -> 9.168 | J67: =J64+J65+J66 -> 32.959 | ... Z67: =Z64+Z65+Z66 -> 113.65175 | AC67: =IFERROR(IF(AND(Z67>0,P67>0),(Z67/P67)^(1/5)-1,"n/m"),"n/m") -> 0.21605836 | AD67: =IFERROR(IF(AND(P67>0,C67>0),(P67/C67)^(1/3)-1,"n/m"),"n/m") -> 0.069021564
B68: (−) Other income (expense) — inside company EBITDA | C68: =C99 -> -0.206 | D68: =D99 -> 0.563 | E68: =E99 -> 0.77 | F68: =F99 -> 0.036 | G68: =E68+F68 -> 0.806 | H68: =H99 -> 0.351 | I68: =I99 -> 0.345 | J68: =J99 -> 1.502 | K68: =K99 -> -0.08 | L68: =L99 -> 0.38 | M68: =K68+L68 -> 0.3 | N68: =N99 -> 0.051 | O68: =O99 -> 3.796 | P68: =P99 -> 4.147 | Q68: =Q99 -> -0.174 | R68: =R99 -> -0.28 | S68: =Q68+R68 -> -0.454 | T68: =T99 -> 0 | U68: =U99 -> 0 | V68: =SUM(Q68,R68,T68,U68) -> -0.454 | W68: =W99 -> 0 | X68: =X99 -> 0 | Y68: =Y99 -> 0 | Z68: =Z99 -> 0
B69: Operating income (GAAP; EBITDA − D&A − other income) | C69: =C63-C67-C68 -> 20.435 | D69: =D63-D67-D68 -> 48.494 | E69: =E63-E67-E68 -> 13.499 | F69: =F63-F67-F68 -> 18.281 | G69: =G63-G67-G68 -> 31.78 | H69: =H63-H67-H68 -> 17.407 | I69: =I63-I67-I68 -> 14.372 | J69: =J63-J67-J68 -> 63.56 | ... Z69: =Z63-Z67-Z68 -> 371.81556 | AC69: =IFERROR(IF(AND(Z69>0,P69>0),(Z69/P69)^(1/5)-1,"n/m"),"n/m") -> 0.38506443 | AD69: =IFERROR(IF(AND(P69>0,C69>0),(P69/C69)^(1/3)-1,"n/m"),"n/m") -> 0.52827324
B70: Adjusted EBITA (model: Adj. EBITDA − depreciation − ROU amortization − other income) | C70: =C54-C64-C65-C68 -> 50.371 | D70: =D54-D64-D65-D68 -> 68.525 | E70: =E54-E64-E65-E68 -> 20.077 | F70: =F54-F64-F65-F68 -> 23.482 | G70: =G54-G64-G65-G68 -> 43.559 | H70: =H54-H64-H65-H68 -> 23.878 | I70: =I54-I64-I65-I68 -> 21.146 | J70: =J54-J64-J65-J68 -> 88.584 | ... Z70: =Z54-Z64-Z65-Z68 -> 451.9171 | AA70: Model measure analogous to TDY non-GAAP operating income: operating income before acquired-intangible amortization and the company’s Adj. EBITDA add-backs (incl. SBC). | AC70: =IFERROR(IF(AND(Z70>0,P70>0),(Z70/P70)^(1/5)-1,"n/m"),"n/m") -> 0.30020605 | AD70: =IFERROR(IF(AND(P70>0,C70>0),(P70/C70)^(1/3)-1,"n/m"),"n/m") -> 0.3415466
B71: Adjusted EBITA margin % | C71: =IFERROR(C70/C49,"") -> 0.22257425 | D71: =IFERROR(D70/D49,"") -> 0.24411749 | E71: =IFERROR(E70/E49,"") -> 0.24187408 | F71: =IFERROR(F70/F49,"") -> 0.27613213 | G71: =IFERROR(G70/G49,"") -> 0.25921033 | H71: =IFERROR(H70/H49,"") -> 0.27775451 | I71: =IFERROR(I70/I49,"") -> 0.23176747 | J71: =IFERROR(J70/J49,"") -> 0.25657855 | ... Z71: =IFERROR(Z70/Z49,"") -> 0.26703046 | AC71: =IFERROR(AVERAGE(V71,W71,X71,Y71,Z71),"n/m") -> 0.2656449 | AD71: =IFERROR(AVERAGE(C71,D71,J71,P71),"n/m") -> 0.24530219
B72: Incremental sales from acquisitions (disclosed / derived) | J72: 11.692 | R72: 38.882 | T72: 38 | U72: 30 | V72: =SUM(Q72,R72,T72,U72) -> 106.882 | W72: =W45 -> 53.983516 | X72: =X45 -> 75.892857 | Y72: =Y45 -> 84.821429 | Z72: =Z45 -> 89.285714 | AA72: Q3/26E: Five Axis, Seemann / MSC (not in the Q3/25 base) ≈ Q2/26 level; Q4/26E lower as Five Axis (closed 28-Oct-25) laps. Excludes Walker (in M&A lever). 2027E+: M&A lever first-12-month sales.
B73: Backlog (period end; “funded backlog” to Q3-25 — same definition) | C73: 265.321 | D73: 428.719 | G73: =IF(ISNUMBER(F73),F73,"") | H73: 550.603 | I73: =IF(ISNUMBER(J73),J73,"") -> 579.8 | J73: 579.8 | K73: 636.35 | L73: 719.3 | M73: =IF(ISNUMBER(L73),L73,"") -> 719.3 | N73: 758.2 | O73: =IF(ISNUMBER(P73),P73,"") -> 801.1 | P73: 801.1 | Q73: 1026.903 | R73: 1322.124 | S73: =IF(ISNUMBER(R73),R73,"") -> 1322.124
B74: Implied book-to-bill ((revenue + Δ backlog) / revenue; incl. acquired backlog) | D74: =IFERROR((D92+D73-C73)/D92,"") -> 1.5820986 | J74: =IFERROR((J92+J73-D73)/J92,"") -> 1.4375976 | K74: =IFERROR((K92+K73-I73)/K92,"") -> 1.5647996 | L74: =IFERROR((L92+L73-K73)/L92,"") -> 1.7206965 | M74: =IFERROR((M92+M73-I73)/M92,"") -> 1.6481709 | N74: =IFERROR((N92+N73-L73)/N92,"") -> 1.3194101 | O74: =IFERROR((O92+O73-N73)/O92,"") -> 1.3189781 | P74: =IFERROR((P92+P73-J73)/P92,"") -> 1.4693531 | Q74: =IFERROR((Q92+Q73-O73)/Q92,"") -> 2.4933073 | R74: =IFERROR((R92+R73-Q73)/R92,"") -> 2.6215321 | S74: =IFERROR((S92+S73-O73)/S92,"") -> 2.563355 | AA74: Q2/26 includes ~$345m of acquired backlog (Seemann / MSC); Investor Update: ~1.6x organic book-to-bill over the last 18 months.
B75: Memo: FY26 outlook (scenario end-point; Q2-26 release 6-Aug-26 — revenue / Adj. EBITDA)
B76: FY26 revenue outlook ($m) | V76: =CHOOSE(MATCH($AA$2,{"Bull","Base","Bear"},0),$AH$12,$AI$12,$AJ$12) -> 737.5
B77: FY26 Adjusted EBITDA outlook ($m) | V77: =CHOOSE(MATCH($AA$2,{"Bull","Base","Bear"},0),$AH$13,$AI$13,$AJ$13) -> 218.75
B78: Check: end-market build vs consolidated revenue (should be 0) | C78: =ROUND(C48+N(C37)-C92,1) -> 0 | D78: =ROUND(D48+N(D37)-D92,1) -> 0 | E78: =ROUND(E48+N(E37)-E92,1) -> 0 | F78: =ROUND(F48+N(F37)-F92,1) -> 0 | G78: =ROUND(G48+N(G37)-G92,1) -> 0 | H78: =ROUND(H48+N(H37)-H92,1) -> 0 | I78: =ROUND(I48+N(I37)-I92,1) -> 0 | J78: =ROUND(J48+N(J37)-J92,1) -> 0 | ... Z78: =ROUND(Z48+N(Z37)-Z92,1) -> 0
B79: Check: group Adj. EBITDA vs company-definition bridge (should be 0) | C79: =ROUND(C54-C146,1) -> 0 | D79: =ROUND(D54-D146,1) -> 0 | E79: =ROUND(E54-E146,1) -> 0 | F79: =ROUND(F54-F146,1) -> 0 | G79: =ROUND(G54-G146,1) -> 0 | H79: =ROUND(H54-H146,1) -> 0 | I79: =ROUND(I54-I146,1) -> 0 | J79: =ROUND(J54-J146,1) -> 0 | ... Z79: =ROUND(Z54-Z146,1) -> 0
B80: Check: group operating income vs income statement (should be 0) | C80: =ROUND(C69-C97,1) -> 0 | D80: =ROUND(D69-D97,1) -> 0 | E80: =ROUND(E69-E97,1) -> 0 | F80: =ROUND(F69-F97,1) -> 0 | G80: =ROUND(G69-G97,1) -> 0 | H80: =ROUND(H69-H97,1) -> 0 | I80: =ROUND(I69-I97,1) -> 0 | J80: =ROUND(J69-J97,1) -> 0 | ... Z80: =ROUND(Z69-Z97,1) -> 0
B82: Cost drivers (% of sales) | AA82: % OF SALES drivers — inputs that drive the forecast cost lines (blue = input).
B83: Cost of goods sold % of revenue | C83: =IFERROR(C93/C92,"") -> 0.64232248 | D83: =IFERROR(D93/D92,"") -> 0.62398604 | E83: =IFERROR(E93/E92,"") -> 0.65062767 | F83: =IFERROR(F93/F92,"") -> 0.59319841 | G83: =IFERROR(G93/G92,"") -> 0.62156565 | H83: =IFERROR(H93/H92,"") -> 0.60701656 | I83: =IFERROR(I93/I92,"") -> 0.61931432 | J83: =IFERROR(J93/J92,"") -> 0.61734796 | ... S83: =IFERROR(S93/S92,"") -> 0.57362583 | T83: =$S83 -> 0.57362583 | U83: =$S83 -> 0.57362583 | V83: =IFERROR(V93/V92,"") -> 0.57362583 | W83: 0.575 | X83: 0.575 | Y83: 0.575 | Z83: 0.575 | AA83: COGS includes allocated depreciation (~$3m / qtr). Q3/Q4-26E at the 1H/26 ratio; 2027E+ input (FY25 59.7%, 1H/26 57.4%). | AC83: =IFERROR(AVERAGE(V83,W83,X83,Y83,Z83),"n/m") -> 0.57472517 | AD83: =IFERROR(AVERAGE(C83,D83,J83,P83),"n/m") -> 0.62015802
B84: D&A allocated to cost of goods sold % of revenue | C84: =IFERROR(C107/C92,"") -> 0.01988423 | D84: =IFERROR(D107/D92,"") -> 0.023868474 | E84: =IFERROR(E107/E92,"") -> 0.022889912 | F84: =IFERROR(F107/F92,"") -> 0.023518621 | G84: =IFERROR(G107/G92,"") -> 0.023208069 | H84: =IFERROR(H107/H92,"") -> 0.033733482 | I84: =IFERROR(I107/I92,"") -> 0.021920691 | J84: =IFERROR(J107/J92,"") -> 0.025488702 | ... S84: =IFERROR(S107/S92,"") -> 0.018003259 | T84: =$S84 -> 0.018003259 | U84: =$S84 -> 0.018003259 | V84: =IFERROR(V107/V92,"") -> 0.018003259 | W84: 0.016 | X84: 0.016 | Y84: 0.016 | Z84: 0.016 | AC84: =IFERROR(AVERAGE(V84,W84,X84,Y84,Z84),"n/m") -> 0.016400652 | AD84: =IFERROR(AVERAGE(C84,D84,J84,P84),"n/m") -> 0.023301868
B85: Depreciation of PP&E % of revenue | C85: =IFERROR(C64/C92,"") -> 0.0247404 | D85: =IFERROR(D64/D92,"") -> 0.028531733 | E85: =IFERROR(E64/E92,"") -> 0.023335662 | F85: =IFERROR(F64/F92,"") -> 0.026987617 | G85: =IFERROR(G64/G92,"") -> 0.025183731 | H85: =IFERROR(H64/H92,"") -> 0.025428066 | I85: =IFERROR(I64/I92,"") -> 0.037221333 | J85: =IFERROR(J64/J92,"") -> 0.0284228 | ... V85: =IFERROR(V64/V92,"") -> 0.022125336 | W85: 0.024 | X85: 0.026 | Y85: 0.027 | Z85: 0.028 | AA85: Rising with the 2026 capacity build (capex 5%+ of sales vs depreciation ~2%). | AC85: =IFERROR(AVERAGE(V85,W85,X85,Y85,Z85),"n/m") -> 0.025425067 | AD85: =IFERROR(AVERAGE(C85,D85,J85,P85),"n/m") -> 0.027090753
B86: Finance-lease ROU amortization growth % | W86: 0.05 | X86: 0.05 | Y86: 0.05 | Z86: 0.05
B87: Share-based compensation % of revenue | C87: =IFERROR(C58/C92,"") -> 0.0070832045 | D87: =IFERROR(D58/D92,"") -> 0.0045991343 | E87: =IFERROR(E58/E92,"") -> 0.0030238778 | F87: =IFERROR(F58/F92,"") -> 0.0028927904 | G87: =IFERROR(G58/G92,"") -> 0.0029575411 | H87: =IFERROR(H58/H92,"") -> 0.0028847943 | I87: =IFERROR(I58/I92,"") -> 0.0027181657 | J87: =IFERROR(J58/J92,"") -> 0.0028761684 | ... V87: =IFERROR(V58/V92,"") -> 0.0059292862 | W87: 0.008 | X87: 0.008 | Y87: 0.008 | Z87: 0.008 | AA87: Q2/26 RSU / PSU run-rate 0.8% of sales. | AC87: =IFERROR(AVERAGE(V87,W87,X87,Y87,Z87),"n/m") -> 0.0075858572 | AD87: =IFERROR(AVERAGE(C87,D87,J87,P87),"n/m") -> 0.007925947
B88: Transaction-related expenses % of acquisition spend | W88: 0.03 | X88: 0.03 | Y88: 0.03 | Z88: 0.03
B89: G&A % of revenue (incl. adjusting items & SBC) | C89: =IFERROR(C95/C92,"") -> 0.1327206 | D89: =IFERROR(D95/D92,"") -> 0.13046793 | E89: =IFERROR(E95/E92,"") -> 0.12154543 | F89: =IFERROR(F95/F92,"") -> 0.11751079 | G89: =IFERROR(G95/G92,"") -> 0.1195037 | H89: =IFERROR(H95/H92,"") -> 0.13012982 | I89: =IFERROR(I95/I92,"") -> 0.14415046 | J89: =IFERROR(J95/J92,"") -> 0.12866291 | ... Z89: =IFERROR(Z95/Z92,"") -> 0.15414527 | AC89: =IFERROR(AVERAGE(V89,W89,X89,Y89,Z89),"n/m") -> 0.1608577 | AD89: =IFERROR(AVERAGE(C89,D89,J89,P89),"n/m") -> 0.14337962
B91: CONSOLIDATED INCOME STATEMENT (US GAAP) | AA91: CONSOLIDATED IS — forecast logic
B92: Revenue | C92: 226.31 | D92: 280.705 | E92: 83.006 | F92: 85.039 | G92: =E92+F92 -> 168.045 | H92: 85.968 | I92: 91.238 | J92: 345.251 | K92: 100.124 | L92: 115.097 | M92: =K92+L92 -> 215.221 | N92: 121.787 | O92: 134.492 | P92: 471.5 | Q92: 151.21 | R92: 182.063 | S92: =Q92+R92 -> 333.273 | T92: =T49 -> 195.09375 | U92: =U49 -> 221.13325 | V92: =SUM(Q92,R92,T92,U92) -> 749.5 | W92: =W49 -> 958.21285 | X92: =X49 -> 1187.5488 | Y92: =Y49 -> 1433.8457 | Z92: =Z49 -> 1692.3803 | AA92: Forecast linked to the end-market build. | AC92: =IFERROR(IF(AND(Z92>0,P92>0),(Z92/P92)^(1/5)-1,"n/m"),"n/m") -> 0.29122895 | AD92: =IFERROR(IF(AND(P92>0,C92>0),(P92/C92)^(1/3)-1,"n/m"),"n/m") -> 0.2772012
B93: Cost of goods sold (incl. allocated D&A) | C93: 145.364 | D93: 175.156 | E93: 54.006 | F93: 50.445 | G93: =E93+F93 -> 104.451 | H93: 52.184 | I93: 56.505 | J93: 213.14 | K93: 60.673 | L93: 68.076 | M93: =K93+L93 -> 128.749 | N93: 71.847 | O93: 80.878 | P93: 281.474 | Q93: 87.345 | R93: 103.829 | S93: =Q93+R93 -> 191.174 | T93: =T92*T83 -> 111.91081 | U93: =U92*U83 -> 126.84774 | V93: =SUM(Q93,R93,T93,U93) -> 429.93256 | W93: =W92*W83 -> 550.97239 | X93: =X92*X83 -> 682.84056 | Y93: =Y92*Y83 -> 824.46129 | Z93: =Z92*Z83 -> 973.11868 | AC93: =IFERROR(IF(AND(Z93>0,P93>0),(Z93/P93)^(1/5)-1,"n/m"),"n/m") -> 0.28157936 | AD93: =IFERROR(IF(AND(P93>0,C93>0),(P93/C93)^(1/3)-1,"n/m"),"n/m") -> 0.2464087
B94: Gross profit | C94: =C92-C93 -> 80.946 | D94: =D92-D93 -> 105.549 | E94: =E92-E93 -> 29 | F94: =F92-F93 -> 34.594 | G94: =G92-G93 -> 63.594 | H94: =H92-H93 -> 33.784 | I94: =I92-I93 -> 34.733 | J94: =J92-J93 -> 132.111 | ... Z94: =Z92-Z93 -> 719.26164 | AC94: =IFERROR(IF(AND(Z94>0,P94>0),(Z94/P94)^(1/5)-1,"n/m"),"n/m") -> 0.30501281 | AD94: =IFERROR(IF(AND(P94>0,C94>0),(P94/C94)^(1/3)-1,"n/m"),"n/m") -> 0.32904355
B95: General and administrative expenses (incl. transaction, integration, SBC) | C95: 30.036 | D95: 36.623 | E95: 10.089 | F95: 9.993 | G95: =E95+F95 -> 20.082 | H95: 11.187 | I95: 13.152 | J95: 44.421 | K95: 23.288 | L95: 19.43 | M95: =K95+L95 -> 42.718 | N95: 19.996 | O95: 22.942 | P95: 85.656 | Q95: 28.637 | R95: 31.339 | S95: =Q95+R95 -> 59.976 | T95: =T94-T96-T69 -> 34.152482 | U95: =U94-U96-U69 -> 37.685403 | V95: =SUM(Q95,R95,T95,U95) -> 131.81389 | W95: =W94-W96-W69 -> 153.07284 | X95: =X94-X96-X69 -> 187.61054 | Y95: =Y94-Y96-Y69 -> 224.4607 | Z95: =Z94-Z96-Z69 -> 260.87242 | AA95: Forecast G&A is the balancing line so that operating income equals the group build (Adj. EBITDA − add-backs − D&A − other income). | AC95: =IFERROR(IF(AND(Z95>0,P95>0),(Z95/P95)^(1/5)-1,"n/m"),"n/m") -> 0.24949371 | AD95: =IFERROR(IF(AND(P95>0,C95>0),(P95/C95)^(1/3)-1,"n/m"),"n/m") -> 0.41809469
B96: Depreciation and amortization expense (opex line; excl. D&A in COGS) | C96: 30.475 | D96: 20.432 | E96: 5.412 | F96: 6.32 | G96: =E96+F96 -> 11.732 | H96: 5.19 | I96: 7.209 | J96: 24.13 | K96: 6.2 | L96: 7.487 | M96: =K96+L96 -> 13.687 | N96: 8.132 | O96: 9.609 | P96: 31.428 | Q96: 13.776 | R96: 12.066 | S96: =Q96+R96 -> 25.842 | T96: =T67-T92*T84 -> 12.123032 | U96: =U67-U92*U84 -> 12.416965 | V96: =SUM(Q96,R96,T96,U96) -> 50.381997 | W96: =W67-W92*W84 -> 55.927753 | X96: =X67-X92*X84 -> 61.503766 | Y96: =Y67-Y92*Y84 -> 72.724182 | Z96: =Z67-Z92*Z84 -> 86.573662 | AC96: =IFERROR(IF(AND(Z96>0,P96>0),(Z96/P96)^(1/5)-1,"n/m"),"n/m") -> 0.22465514 | AD96: =IFERROR(IF(AND(P96>0,C96>0),(P96/C96)^(1/3)-1,"n/m"),"n/m") -> 0.010317037
B97: Net operating income | C97: =C94-C95-C96 -> 20.435 | D97: =D94-D95-D96 -> 48.494 | E97: =E94-E95-E96 -> 13.499 | F97: =F94-F95-F96 -> 18.281 | G97: =G94-G95-G96 -> 31.78 | H97: =H94-H95-H96 -> 17.407 | I97: =I94-I95-I96 -> 14.372 | J97: =J94-J95-J96 -> 63.56 | ... Z97: =Z94-Z95-Z96 -> 371.81556 | AC97: =IFERROR(IF(AND(Z97>0,P97>0),(Z97/P97)^(1/5)-1,"n/m"),"n/m") -> 0.38506443 | AD97: =IFERROR(IF(AND(P97>0,C97>0),(P97/C97)^(1/3)-1,"n/m"),"n/m") -> 0.52827324
B98: Interest expense, net (incl. finance-lease interest & debt-cost amortization) | C98: 37.501 | D98: 47.867 | E98: 12.06 | F98: 13.401 | G98: =E98+F98 -> 25.461 | H98: 12.533 | I98: 12.739 | J98: 50.733 | K98: 11.373 | L98: 11.893 | M98: =K98+L98 -> 23.266 | N98: 10.002 | O98: 11.299 | P98: 44.567 | Q98: 12.646 | R98: 15.284 | S98: =Q98+R98 -> 27.93 | T98: =(R304*2/3+(R304+100)*1/3)*T314/4+R309*$V315/4+$V302/4 -> 14.8124 | U98: =V304*U314/4+R309*$V315/4+$V302/4 -> 15.401889 | V98: =SUM(Q98,R98,T98,U98) -> 58.14429 | W98: =W314*(V304+0.5*(W305+W306))+W315*V309+W316*V313+W302-W317*V242 -> 57.155941 | X98: =X314*(W304+0.5*(X305+X306))+X315*W309+X316*W313+X302-X317*W242 -> 63.36122 | Y98: =Y314*(X304+0.5*(Y305+Y306))+Y315*X309+Y316*X313+Y302-Y317*X242 -> 70.027667 | Z98: =Z314*(Y304+0.5*(Z305+Z306))+Z315*Y309+Z316*Y313+Z302-Z317*Y242 -> 75.610381 | AA98: Q3/26E: term loan $764m (30-Jun) + $100m add-on from 26-Aug; SOFR + 2.75% to 3-Aug, SOFR + 2.25% after (Fifth Amendment). 2027E+: rate × average principal + finance-lease rate × opening lease liability + revolver − interest income on opening cash. | AC98: =IFERROR(IF(AND(Z98>0,P98>0),(Z98/P98)^(1/5)-1,"n/m"),"n/m") -> 0.11151059 | AD98: =IFERROR(IF(AND(P98>0,C98>0),(P98/C98)^(1/3)-1,"n/m"),"n/m") -> 0.059229784
B99: Other income (expense), net | C99: -0.206 | D99: 0.563 | E99: 0.77 | F99: 0.036 | G99: =E99+F99 -> 0.806 | H99: 0.351 | I99: 0.345 | J99: 1.502 | K99: -0.08 | L99: 0.38 | M99: =K99+L99 -> 0.3 | N99: 0.051 | O99: 3.796 | P99: 4.147 | Q99: -0.174 | R99: -0.28 | S99: =Q99+R99 -> -0.454 | T99: 0 | U99: 0 | V99: =SUM(Q99,R99,T99,U99) -> -0.454 | W99: 0 | X99: 0 | Y99: 0 | Z99: 0
B100: Income before provision for income taxes | C100: =C97-C98+C99 -> -17.272 | D100: =D97-D98+D99 -> 1.19 | E100: =E97-E98+E99 -> 2.209 | F100: =F97-F98+F99 -> 4.916 | G100: =G97-G98+G99 -> 7.125 | H100: =H97-H98+H99 -> 5.225 | I100: =I97-I98+I99 -> 1.978 | J100: =J97-J98+J99 -> 14.329 | ... Z100: =Z97-Z98+Z99 -> 296.20517 | AC100: =IFERROR(IF(AND(Z100>0,P100>0),(Z100/P100)^(1/5)-1,"n/m"),"n/m") -> 0.55554679 | AD100: =IFERROR(IF(AND(P100>0,C100>0),(P100/C100)^(1/3)-1,"n/m"),"n/m") -> n/m
B101: Provision for income taxes | C101: -3.173 | D101: -3.169 | E101: 0.087 | F101: 0.312 | G101: =E101+F101 -> 0.399 | H101: 0.933 | I101: 0.295 | J101: 1.628 | K101: 3.308 | L101: 1.784 | M101: =K101+L101 -> 5.092 | N101: 4.217 | O101: 5.847 | P101: 15.156 | Q101: 0.838 | R101: 5.233 | S101: =Q101+R101 -> 6.071 | T101: =T100*$AI$16 -> 5.302805 | U101: =U100*$AI$16 -> 6.9075 | V101: =SUM(Q101,R101,T101,U101) -> 18.281305 | W101: =W100*W102 -> 34.565564 | X101: =X100*X102 -> 47.097017 | Y101: =Y100*Y102 -> 59.332111 | Z101: =Z100*Z102 -> 72.570268 | AA101: Q3/Q4-26E at the point-estimate rate (1H/26 ETR 21.8%; Q2-26 27.2% incl. §162(m)); 2027E+ input.
B102: Effective tax rate | C102: =IFERROR(C101/C100,"") -> 0.18370774 | D102: =IFERROR(D101/D100,"") -> -2.6630252 | E102: =IFERROR(E101/E100,"") -> 0.039384337 | F102: =IFERROR(F101/F100,"") -> 0.063466233 | G102: =IFERROR(G101/G100,"") -> 0.056 | H102: =IFERROR(H101/H100,"") -> 0.17856459 | I102: =IFERROR(I101/I100,"") -> 0.14914055 | J102: =IFERROR(J101/J100,"") -> 0.11361574 | ... V102: =IFERROR(V101/V100,"") -> 0.23207498 | W102: 0.245 | X102: 0.245 | Y102: 0.245 | Z102: 0.245 | AC102: =IFERROR(AVERAGE(V102,W102,X102,Y102,Z102),"n/m") -> 0.242415 | AD102: =IFERROR(AVERAGE(C102,D102,J102,P102),"n/m") -> -0.47491968
B103: Net income | C103: =C100-C101 -> -14.099 | D103: =D100-D101 -> 4.359 | E103: =E100-E101 -> 2.122 | F103: =F100-F101 -> 4.604 | G103: =G100-G101 -> 6.726 | H103: =H100-H101 -> 4.292 | I103: =I100-I101 -> 1.683 | J103: =J100-J101 -> 12.701 | ... Z103: =Z100-Z101 -> 223.63491 | AC103: =IFERROR(IF(AND(Z103>0,P103>0),(Z103/P103)^(1/5)-1,"n/m"),"n/m") -> 0.66712421 | AD103: =IFERROR(IF(AND(P103>0,C103>0),(P103/C103)^(1/3)-1,"n/m"),"n/m") -> n/m
...

Sheet Bull-Base-Bear
B2: Karman Holdings (KRMN) — Bull / Base / Bear Case P&L Summary | J2: Share price ($): | K2: =Model!$V$362 -> 34.14
B3: Company non-GAAP definitions (Adj. EBITDA, Adj. EPS) plus model Adj. EBITA · USD millions · Live panel linked to Model — toggle scenario via Model!AA2. Bull and Bear panels are value snapshots generated from the Model with the switch set to each case. | J3: As of: | K3: =TODAY() -> 46299
B5: Scenario: | C5: =Model!AA2 -> Base | N5: Scenario: | O5: Bull | P5: Snapshot (values) — Model run with switch = Bull | Z5: Scenario: | AA5: Bear | AB5: Snapshot (values) — Model run with switch = Bear
B7: (USDm, except EPS and shares) | C7: 2025A | D7: 2026E | E7: 2027E | F7: 2028E | G7: 2029E | H7: 2030E | I7: 25-'30 CAGR | J7: LT Hist Avg | K7: LT Hist Min | L7: LT Hist Max | N7: (USDm, except EPS and shares) | O7: 2025A | P7: 2026E | Q7: 2027E | R7: 2028E | S7: 2029E | T7: 2030E | U7: 25-'30 CAGR | V7: LT Hist Avg | W7: LT Hist Min | X7: LT Hist Max | Z7: (USDm, except EPS and shares) | AA7: 2025A | AB7: 2026E | AC7: 2027E | AD7: 2028E | AE7: 2029E | AF7: 2030E | AG7: 25-'30 CAGR | AH7: LT Hist Avg | AI7: LT Hist Min | AJ7: LT Hist Max
B9: Revenue | C9: =Model!P92 -> 471.5 | D9: =Model!V92 -> 749.5 | E9: =Model!W92 -> 958.21285 | F9: =Model!X92 -> 1187.5488 | G9: =Model!Y92 -> 1433.8457 | H9: =Model!Z92 -> 1692.3803 | I9: =IFERROR(IF(AND(H9>0,C9>0),(H9/C9)^(1/5)-1,"n/m"),"n/m") -> 0.29122895 | N9: Revenue | O9: 471.5 | P9: 757 | Q9: 1031.2137 | R9: 1374.2551 | S9: 1757.167 | T9: 2176.446 | U9: 0.35785451 | Z9: Revenue | AA9: 471.5 | AB9: 742 | AC9: 864.06197 | AD9: 957.59955 | AE9: 1047.3093 | AF9: 1130.2887 | AG9: 0.19108167
B10: Revenue y/y % | D10: =IFERROR(D9/C9-1,"") -> 0.58960764 | E10: =IFERROR(E9/D9-1,"") -> 0.27846945 | F10: =IFERROR(F9/E9-1,"") -> 0.23933717 | G10: =IFERROR(G9/F9-1,"") -> 0.20739941 | H10: =IFERROR(H9/G9-1,"") -> 0.18030851 | N10: Revenue y/y % | P10: 0.60551432 | Q10: 0.36223744 | R10: 0.33265784 | S10: 0.27863235 | T10: 0.23861076 | Z10: Revenue y/y % | AB10: 0.57370095 | AC10: 0.164504 | AD10: 0.10825332 | AE10: 0.093681929 | AF10: 0.079231061
B11: Organic growth % (where disclosed / modelled) | C11: =Model!P180 | D11: =Model!V180 -> 0.36292259 | E11: =Model!W180 -> 0.20644341 | F11: =Model!X180 -> 0.16013466 | G11: =Model!Y180 -> 0.13597377 | H11: =Model!Z180 -> 0.11803842 | N11: Organic growth % (where disclosed / modelled) | P11: 0.37882927 | Q11: 0.25554097 | R11: 0.20711231 | S11: 0.17792844 | T11: 0.15731107 | Z11: Organic growth % (where disclosed / modelled) | AB11: 0.34701591 | AC11: 0.12784928 | AD11: 0.082420191 | AE11: 0.061048246 | AF11: 0.04513007
B12: Adjusted EBITDA (company definition) | C12: =Model!P146 -> 145.302 | D12: =Model!V146 -> 221.99 | E12: =Model!W146 -> 285.16474 | F12: =Model!X146 -> 354.34888 | G12: =Model!Y146 -> 428.83603 | H12: =Model!Z146 -> 508.50635 | I12: =IFERROR(IF(AND(H12>0,C12>0),(H12/C12)^(1/5)-1,"n/m"),"n/m") -> 0.28470956 | N12: Adjusted EBITDA (company definition) | O12: 145.302 | P12: 225.74 | Q12: 315.53934 | R12: 419.27152 | S12: 535.5049 | T12: 664.83578 | U12: 0.35546578 | Z12: Adjusted EBITDA (company definition) | AA12: 145.302 | AB12: 218.24 | AC12: 241.43883 | AD12: 269.97072 | AE12: 297.58501 | AF12: 324.30295 | AG12: 0.1741832
B13: Adjusted EBITDA margin % | C13: =IFERROR(C12/C9,"") -> 0.30816967 | D13: =IFERROR(D12/D9,"") -> 0.29618412 | E13: =IFERROR(E12/E9,"") -> 0.29760062 | F13: =IFERROR(F12/F9,"") -> 0.29838679 | G13: =IFERROR(G12/G9,"") -> 0.29908101 | H13: =IFERROR(H12/H9,"") -> 0.30046813 | J13: =IFERROR(AVERAGE(Model!C188,Model!D188,Model!J188,Model!P188),"") -> 0.293412 | K13: =IFERROR(MIN(Model!C188,Model!D188,Model!J188,Model!P188),"") -> 0.26640891 | L13: =IFERROR(MAX(Model!C188,Model!D188,Model!J188,Model!P188),"") -> 0.30816967 | N13: Adjusted EBITDA margin % | O13: 0.30816967 | P13: 0.29820343 | Q13: 0.3059883 | R13: 0.30509003 | S13: 0.3047547 | T13: 0.30546854 | V13: 0.293412 | W13: 0.26640891 | X13: 0.30816967 | Z13: Adjusted EBITDA margin % | AA13: 0.30816967 | AB13: 0.29412399 | AC13: 0.27942305 | AD13: 0.28192445 | AE13: 0.28414242 | AF13: 0.28692045 | AH13: 0.293412 | AI13: 0.26640891 | AJ13: 0.30816967
B15: Operating Income (GAAP) | C15: =Model!P97 -> 72.942 | D15: =Model!V97 -> 137.37156 | E15: =Model!W97 -> 198.23987 | F15: =Model!X97 -> 255.59394 | G15: =Model!Y97 -> 312.19955 | H15: =Model!Z97 -> 371.81556 | I15: =IFERROR(IF(AND(H15>0,C15>0),(H15/C15)^(1/5)-1,"n/m"),"n/m") -> 0.38506443 | N15: Operating Income (GAAP) | O15: 72.942 | P15: 141.12156 | Q15: 218.96595 | R15: 301.23107 | S15: 388.98968 | T15: 486.53113 | U15: 0.46159347 | Z15: Operating Income (GAAP) | AA15: 72.942 | AB15: 133.62156 | AC15: 164.8393 | AD15: 191.97156 | AE15: 213.0398 | AF15: 232.03496 | AG15: 0.26041961
B16: Operating income y/y % | D16: =IFERROR(D15/C15-1,"") -> 0.88329852 | E16: =IFERROR(E15/D15-1,"") -> 0.44309254 | F16: =IFERROR(F15/E15-1,"") -> 0.2893165 | G16: =IFERROR(G15/F15-1,"") -> 0.22146694 | H16: =IFERROR(H15/G15-1,"") -> 0.19095481 | N16: Operating income y/y % | P16: 0.93470923 | Q16: 0.55161229 | R16: 0.37569825 | S16: 0.29133317 | T16: 0.25075589 | Z16: Operating income y/y % | AB16: 0.83188781 | AC16: 0.23362802 | AD16: 0.16459826 | AE16: 0.10974668 | AF16: 0.089162485
B17: Operating margin (GAAP) % | C17: =IFERROR(C15/C9,"") -> 0.15470201 | D17: =IFERROR(D15/D9,"") -> 0.18328427 | E17: =IFERROR(E15/E9,"") -> 0.20688501 | F17: =IFERROR(F15/F9,"") -> 0.21522816 | G17: =IFERROR(G15/G9,"") -> 0.2177358 | H17: =IFERROR(H15/H9,"") -> 0.21969976 | J17: =IFERROR(AVERAGE(Model!C191,Model!D191,Model!J191,Model!P191),"") -> 0.15046358 | K17: =IFERROR(MIN(Model!C191,Model!D191,Model!J191,Model!P191),"") -> 0.090296496 | L17: =IFERROR(MAX(Model!C191,Model!D191,Model!J191,Model!P191),"") -> 0.18409795 | N17: Operating margin (GAAP) % | O17: 0.15470201 | P17: 0.18642214 | Q17: 0.21233808 | R17: 0.21919589 | S17: 0.2213732 | T17: 0.22354386 | V17: 0.15046358 | W17: 0.090296496 | X17: 0.18409795 | Z17: Operating margin (GAAP) % | AA17: 0.15470201 | AB17: 0.18008297 | AC17: 0.19077255 | AD17: 0.20047165 | AE17: 0.20341632 | AF17: 0.20528822 | AH17: 0.15046358 | AI17: 0.090296496 | AJ17: 0.18409795
B19: Adjusted Net Income (company definition, not tax-effected) | C19: =Model!P167 -> 48.95914 | D19: =Model!V167 -> 81.298166 | E19: =Model!W167 -> 122.18407 | F19: =Model!X167 -> 163.38609 | G19: =Model!Y167 -> 203.81054 | H19: =Model!Z167 -> 246.67395 | I19: =IFERROR(IF(AND(H19>0,C19>0),(H19/C19)^(1/5)-1,"n/m"),"n/m") -> 0.38184045 | N19: Adjusted Net Income (company definition, not tax-effected) | O19: 48.95914 | P19: 84.148166 | Q19: 142.92601 | R19: 196.91101 | S19: 255.15002 | T19: 321.88526 | U19: 0.45738221 | Z19: Adjusted Net Income (company definition, not tax-effected) | AA19: 48.95914 | AB19: 78.448166 | AC19: 91.703684 | AD19: 114.26933 | AE19: 132.41108 | AF19: 148.08914 | AG19: 0.24777961
B21: FDSO (m) | C21: =Model!P110 -> 132.322 | D21: =Model!V110 -> 132.55225 | E21: =Model!W110 -> 133.17244 | F21: =Model!X110 -> 133.57244 | G21: =Model!Y110 -> 133.97243 | H21: =Model!Z110 -> 134.37243 | I21: =IFERROR(IF(AND(H21>0,C21>0),(H21/C21)^(1/5)-1,"n/m"),"n/m") -> 0.0030801267 | N21: FDSO (m) | O21: 132.322 | P21: 132.55225 | Q21: 133.17244 | R21: 133.57244 | S21: 133.97243 | T21: 134.37243 | U21: 0.0030801267 | Z21: FDSO (m) | AA21: 132.322 | AB21: 132.55225 | AC21: 133.17244 | AD21: 133.57244 | AE21: 133.97243 | AF21: 134.37243 | AG21: 0.0030801267
B23: Adjusted EPS — Diluted ($, company definition) | C23: =Model!P169 -> 0.37 | D23: =Model!V169 -> 0.6133292 | E23: =Model!W169 -> 0.91748771 | F23: =Model!X169 -> 1.2232022 | G23: =Model!Y169 -> 1.5212871 | H23: =Model!Z169 -> 1.8357482 | I23: =IFERROR(IF(AND(H23>0,C23>0),(H23/C23)^(1/5)-1,"n/m"),"n/m") -> 0.37759728 | N23: Adjusted EPS — Diluted ($, company definition) | O23: 0.37 | P23: 0.63483016 | Q23: 1.0732402 | R23: 1.4741889 | S23: 1.9044964 | T23: 2.3954709 | U23: 0.45290707 | Z23: Adjusted EPS — Diluted ($, company definition) | AA23: 0.37 | AB23: 0.59182825 | AC23: 0.6886086 | AD23: 0.85548585 | AE23: 0.98834566 | AF23: 1.1020797 | AG23: 0.24394809
B24: EPS y/y % | D24: =IFERROR(D23/C23-1,"") -> 0.65764649 | E24: =IFERROR(E23/D23-1,"") -> 0.49591395 | F24: =IFERROR(F23/E23-1,"") -> 0.33320825 | G24: =IFERROR(G23/F23-1,"") -> 0.24369226 | H24: =IFERROR(H23/G23-1,"") -> 0.20670724 | N24: EPS y/y % | P24: 0.71575718 | Q24: 0.69059426 | R24: 0.37358711 | S24: 0.29189435 | T24: 0.25779759 | Z24: EPS y/y % | AB24: 0.5995358 | AC24: 0.16352777 | AD24: 0.24233977 | AE24: 0.15530334 | AF24: 0.11507519
B26: P / E (x) — assumed (Adjusted EPS, company definition) | G26: 40 | H26: 40 | N26: P / E (x) — assumed (Adjusted EPS, company definition) | S26: 50 | T26: 50 | Z26: P / E (x) — assumed (Adjusted EPS, company definition) | AE26: 28 | AF26: 28
B27: Price Target ($) | G27: =G26*G23 -> 60.851484 | H27: =H26*H23 -> 73.429926 | N27: Price Target ($) | S27: =S26*S23 -> 95.224818 | T27: =T26*T23 -> 119.77355 | Z27: Price Target ($) | AE27: =AE26*AE23 -> 27.673679 | AF27: =AF26*AF23 -> 30.858232
B28: Upside / (Downside) vs current | G28: =IFERROR(G27/$K$2-1,"") -> 0.78241019 | H28: =IFERROR(H27/$K$2-1,"") -> 1.1508473 | N28: Upside / (Downside) vs current | S28: =IFERROR(S27/$K$2-1,"") -> 1.7892448 | T28: =IFERROR(T27/$K$2-1,"") -> 2.5083054 | Z28: Upside / (Downside) vs current | AE28: =IFERROR(AE27/$K$2-1,"") -> -0.18940602 | AF28: =IFERROR(AF27/$K$2-1,"") -> -0.096126764
B29: IRR (to Dec-Y-1) | G29: =IFERROR((G27/$K$2)^(1/((DATE(2029-1,12,31)-$K$3)/365.25))-1,"") -> 0.29402319 | H29: =IFERROR((H27/$K$2)^(1/((DATE(2030-1,12,31)-$K$3)/365.25))-1,"") -> 0.2665027 | N29: IRR (to Dec-Y-1) | S29: =IFERROR((S27/$K$2)^(1/((DATE(2029-1,12,31)-$K$3)/365.25))-1,"") -> 0.58006148 | T29: =IFERROR((T27/$K$2)^(1/((DATE(2030-1,12,31)-$K$3)/365.25))-1,"") -> 0.4728418 | Z29: IRR (to Dec-Y-1) | AE29: =IFERROR((AE27/$K$2)^(1/((DATE(2029-1,12,31)-$K$3)/365.25))-1,"") -> -0.089397207 | AF29: =IFERROR((AF27/$K$2)^(1/((DATE(2030-1,12,31)-$K$3)/365.25))-1,"") -> -0.0306967
B31: Free Cash Flow (CFO − capex) | C31: =Model!P222 -> -42.455 | D31: =Model!V222 -> 26.93171 | E31: =Model!W222 -> 80.815266 | F31: =Model!X222 -> 123.84979 | G31: =Model!Y222 -> 167.42287 | H31: =Model!Z222 -> 216.77556 | I31: =IFERROR(IF(AND(H31>0,C31>0),(H31/C31)^(1/5)-1,"n/m"),"n/m") -> n/m | N31: Free Cash Flow (CFO − capex) | O31: -42.455 | P31: 27.3621 | Q31: 77.520145 | R31: 123.76448 | S31: 183.91667 | T31: 255.42836 | Z31: Free Cash Flow (CFO − capex) | AA31: -42.455 | AB31: 26.50132 | AC31: 81.425899 | AD31: 115.42073 | AE31: 137.10073 | AF31: 159.31182
B32: FCF % | C32: =IFERROR(C31/C9,"") -> -0.090042418 | D32: =IFERROR(D31/D9,"") -> 0.035932902 | E32: =IFERROR(E31/E9,"") -> 0.084339576 | F32: =IFERROR(F31/F9,"") -> 0.10429028 | G32: =IFERROR(G31/G9,"") -> 0.11676492 | H32: =IFERROR(H31/H9,"") -> 0.12808915 | J32: =IFERROR(AVERAGE(Model!C224,Model!D224,Model!J224,Model!P224),"") -> -0.041102648 | K32: =IFERROR(MIN(Model!C224,Model!D224,Model!J224,Model!P224),"") -> -0.12002121 | L32: =IFERROR(MAX(Model!C224,Model!D224,Model!J224,Model!P224),"") -> 0.03299918 | N32: FCF % | O32: -0.090042418 | P32: 0.036145443 | Q32: 0.075173693 | R32: 0.090059323 | S32: 0.10466659 | T32: 0.11736031 | V32: -0.041102648 | W32: -0.12002121 | X32: 0.03299918 | Z32: FCF % | AA32: -0.090042418 | AB32: 0.035716065 | AC32: 0.09423618 | AD32: 0.12053131 | AE32: 0.13090758 | AF32: 0.1409479 | AH32: -0.041102648 | AI32: -0.12002121 | AJ32: 0.03299918
B33: FCF / share ($) | C33: =IFERROR(C31/C21,"") -> -0.32084612 | D33: =IFERROR(D31/D21,"") -> 0.20317807 | E33: =IFERROR(E31/E21,"") -> 0.6068468 | F33: =IFERROR(F31/F21,"") -> 0.92721071 | G33: =IFERROR(G31/G21,"") -> 1.2496815 | H33: =IFERROR(H31/H21,"") -> 1.6132442 | N33: FCF / share ($) | O33: -0.32084612 | P33: 0.20642502 | Q33: 0.58210354 | R33: 0.92657203 | S33: 1.3727949 | T33: 1.9008985 | Z33: FCF / share ($) | AA33: -0.32084612 | AB33: 0.19993112 | AC33: 0.61143208 | AD33: 0.8641059 | AE33: 1.0233503 | AF33: 1.185599
B34: FCF Yield (on PT) | E34: =IFERROR(E33/E$27,"") | F34: =IFERROR(F33/F$27,"") | G34: =IFERROR(G33/G$27,"") -> 0.020536582 | H34: =IFERROR(H33/H$27,"") -> 0.021969847 | N34: FCF Yield (on PT) | Q34: =IFERROR(Q33/Q$27,"") | R34: =IFERROR(R33/R$27,"") | S34: =IFERROR(S33/S$27,"") -> 0.014416356 | T34: =IFERROR(T33/T$27,"") -> 0.015870771 | Z34: FCF Yield (on PT) | AC34: =IFERROR(AC33/AC$27,"") | AD34: =IFERROR(AD33/AD$27,"") | AE34: =IFERROR(AE33/AE$27,"") -> 0.036979192 | AF34: =IFERROR(AF33/AF$27,"") -> 0.038420833
B35: Adjusted EBITA (model, ex-amortization) | C35: =Model!P124 -> 121.618 | D35: =Model!V124 -> 198.29006 | E35: =Model!W124 -> 254.21808 | F35: =Model!X124 -> 315.12558 | G35: =Model!Y124 -> 381.35782 | H35: =Model!Z124 -> 451.9171 | I35: =IFERROR(IF(AND(H35>0,C35>0),(H35/C35)^(1/5)-1,"n/m"),"n/m") -> 0.30020605 | N35: Adjusted EBITA (model, ex-amortization) | O35: 121.618 | P35: 202.04006 | Q35: 282.84066 | R35: 375.19386 | S35: 479.29701 | T35: 594.6927 | U35: 0.37359578 | Z35: Adjusted EBITA (model, ex-amortization) | AA35: 121.618 | AB35: 194.54006 | AC35: 212.7518 | AD35: 236.72611 | AE35: 260.54328 | AF35: 283.45227 | AG35: 0.1843946
B36: Adjusted EBITA margin % | C36: =IFERROR(C35/C9,"") -> 0.25793849 | D36: =IFERROR(D35/D9,"") -> 0.26456312 | E36: =IFERROR(E35/E9,"") -> 0.26530439 | F36: =IFERROR(F35/F9,"") -> 0.265358 | G36: =IFERROR(G35/G9,"") -> 0.26596851 | H36: =IFERROR(H35/H9,"") -> 0.26703046 | J36: =IFERROR(AVERAGE(Model!C189,Model!D189,Model!J189,Model!P189),"") -> 0.24530244 | K36: =IFERROR(MIN(Model!C189,Model!D189,Model!J189,Model!P189),"") -> 0.22257523 | L36: =IFERROR(MAX(Model!C189,Model!D189,Model!J189,Model!P189),"") -> 0.25793849 | N36: Adjusted EBITA margin % | O36: 0.25793849 | P36: 0.26689572 | Q36: 0.27427937 | R36: 0.27301617 | S36: 0.27276691 | T36: 0.27324028 | V36: 0.24530244 | W36: 0.22257523 | X36: 0.25793849 | Z36: Adjusted EBITA margin % | AA36: 0.25793849 | AB36: 0.26218337 | AC36: 0.24622285 | AD36: 0.24720783 | AE36: 0.24877395 | AF36: 0.25077864 | AH36: 0.24530244 | AI36: 0.22257523 | AJ36: 0.25793849
B38: Net Debt (incl. finance leases) | C38: =Model!P356 -> 546.585 | D38: =Model!V356 -> 853.07829 | E38: =Model!W356 -> 982.41257 | F38: =Model!X356 -> 1094.1098 | G38: =Model!Y356 -> 1187.6513 | H38: =Model!Z356 -> 1232.2784 | N38: Net Debt (incl. finance leases) | O38: 546.585 | P38: 852.6479 | Q38: 1135.2773 | R38: 1397.0598 | S38: 1624.1076 | T38: 1780.0818 | Z38: Net Debt (incl. finance leases) | AA38: 546.585 | AB38: 853.50868 | AC38: 832.23233 | AD38: 802.35863 | AE38: 776.22228 | AF38: 728.31306
B39: Net Debt / Adjusted EBITDA (x) | C39: =IFERROR(C38/C12,"") -> 3.761717 | D39: =IFERROR(D38/D12,"") -> 3.8428681 | E39: =IFERROR(E38/E12,"") -> 3.4450703 | F39: =IFERROR(F38/F12,"") -> 3.0876627 | G39: =IFERROR(G38/G12,"") -> 2.7694765 | H39: =IFERROR(H38/H12,"") -> 2.4233294 | N39: Net Debt / Adjusted EBITDA (x) | O39: 3.761717 | P39: 3.7771237 | Q39: 3.5978947 | R39: 3.3321124 | S39: 3.0328528 | T39: 2.6774759 | Z39: Net Debt / Adjusted EBITDA (x) | AA39: 3.761717 | AB39: 3.9108719 | AC39: 3.4469696 | AD39: 2.9720209 | AE39: 2.6084052 | AF39: 2.2457799
B41: ROIC (Adj. EBITA NOPAT / book IC) | C41: =Model!P336 -> 0.098155446 | D41: =Model!V336 -> 0.11602219 | E41: =Model!W336 -> 0.12443802 | F41: =Model!X336 -> 0.13153862 | G41: =Model!Y336 -> 0.13732976 | H41: =Model!Z336 -> 0.14345682 | J41: =IFERROR(AVERAGE(Model!C336,Model!D336,Model!J336,Model!P336),"") -> 0.089771413 | K41: =IFERROR(MIN(Model!C336,Model!D336,Model!J336,Model!P336),"") -> 0.065972883 | L41: =IFERROR(MAX(Model!C336,Model!D336,Model!J336,Model!P336),"") -> 0.10622211 | N41: ROIC (Adj. EBITA NOPAT / book IC) | O41: 0.098155446 | P41: 0.11799656 | Q41: 0.12456174 | R41: 0.13115558 | S41: 0.13769708 | T41: 0.14521734 | V41: 0.089771413 | W41: 0.065972883 | X41: 0.10622211 | Z41: ROIC (Adj. EBITA NOPAT / book IC) | AA41: 0.098155446 | AB41: 0.11404046 | AC41: 0.11781391 | AD41: 0.12381188 | AE41: 0.12733523 | AF41: 0.13049165 | AH41: 0.089771413 | AI41: 0.065972883 | AJ41: 0.10622211
B42: RONTA | C42: =Model!P348 -> 0.23564509 | D42: =Model!V348 -> 0.27158545 | E42: =Model!W348 -> 0.32966582 | F42: =Model!X348 -> 0.36123323 | G42: =Model!Y348 -> 0.39043687 | H42: =Model!Z348 -> 0.41724046 | J42: =IFERROR(AVERAGE(Model!C348,Model!D348,Model!J348,Model!P348),"") -> 0.23811586 | K42: =IFERROR(MIN(Model!C348,Model!D348,Model!J348,Model!P348),"") -> 0.19146647 | L42: =IFERROR(MAX(Model!C348,Model!D348,Model!J348,Model!P348),"") -> 0.27925921 | N42: RONTA | O42: 0.23564509 | P42: 0.27530757 | Q42: 0.35206037 | R42: 0.3938364 | S42: 0.43060615 | T42: 0.46313302 | V42: 0.23811586 | W42: 0.19146647 | X42: 0.27925921 | Z42: RONTA | AA42: 0.23564509 | AB42: 0.26782489 | AC42: 0.25947861 | AD42: 0.2631675 | AE42: 0.26837015 | AF42: 0.26567351 | AH42: 0.23811586 | AI42: 0.19146647 | AJ42: 0.27925921
B44: Implied Market Cap (USDm) | G44: =IFERROR(G27*G21,"") -> 8152.4215 | H44: =IFERROR(H27*H21,"") -> 9866.958 | N44: Implied Market Cap (USDm) | S44: =IFERROR(S27*S21,"") -> 12757.501 | T44: =IFERROR(T27*T21,"") -> 16094.263 | Z44: Implied Market Cap (USDm) | AE44: =IFERROR(AE27*AE21,"") -> 3707.5101 | AF44: =IFERROR(AF27*AF21,"") -> 4146.4958
B45: (+) Net Debt (incl. finance leases) | G45: =G38 -> 1187.6513 | H45: =H38 -> 1232.2784 | N45: (+) Net Debt (incl. finance leases) | S45: =S38 -> 1624.1076 | T45: =T38 -> 1780.0818 | Z45: (+) Net Debt (incl. finance leases) | AE45: =AE38 -> 776.22228 | AF45: =AF38 -> 728.31306
B46: Implied Enterprise Value (USDm) | G46: =IFERROR(G44+G45,"") -> 9340.0728 | H46: =IFERROR(H44+H45,"") -> 11099.236 | N46: Implied Enterprise Value (USDm) | S46: =IFERROR(S44+S45,"") -> 14381.608 | T46: =IFERROR(T44+T45,"") -> 17874.345 | Z46: Implied Enterprise Value (USDm) | AE46: =IFERROR(AE44+AE45,"") -> 4483.7324 | AF46: =IFERROR(AF44+AF45,"") -> 4874.8089
B47: Implied EV / Adjusted EBITDA (x) | G47: =IFERROR(G46/G12,"") -> 21.780056 | H47: =IFERROR(H46/H12,"") -> 21.827134 | N47: Implied EV / Adjusted EBITDA (x) | S47: =IFERROR(S46/S12,"") -> 26.856166 | T47: =IFERROR(T46/T12,"") -> 26.885353 | Z47: Implied EV / Adjusted EBITDA (x) | AE47: =IFERROR(AE46/AE12,"") -> 15.067064 | AF47: =IFERROR(AF46/AF12,"") -> 15.031651

Sheet DCF
B2: DCF VALUATION — KARMAN HOLDINGS (KRMN)
B4: 1. WACC BUILD
B5: Risk-free rate (US 10Y govt) | C5: 0.045 | D5: Assumption (~US 10Y Treasury yield); update to market
B6: Equity risk premium | C6: 0.05 | D6: US implied ERP ~4.5–5.5% (Damodaran)
B7: Levered beta | C7: 1.3 | D7: Short trading history since the Feb-2025 IPO; high-growth defense-tech peers (AVAV, KTOS, MRCY) ~1.2–1.5
B8: Cost of equity | C8: =C5+C7*C6 -> 0.11
B9: Pre-tax cost of debt | C9: 0.06 | D9: Citi Term Loan B at SOFR + 2.25% (Fifth Amendment, 3-Aug-26) ≈ 5.9–6.0%; finance leases ~8.2%
B10: Tax rate | C10: 0.245 | D10: Model 2027E+ effective tax rate
B11: After-tax cost of debt | C11: =C9*(1-C10) -> 0.0453
B12: Target D/V | C12: 0.2 | D12: Net debt incl. leases ~$0.95bn vs ~$4.5bn market cap at $34.14; ~4x Adj. EBITDA, deleveraging with growth
B13: WACC | C13: =C8*(1-C12)+C11*C12 -> 0.09706
B15: Valuation date (live) | C15: =TODAY() -> 46299 | D15: Periods = (Dec-31-Year − today) / 365.25; cash flows assumed at year-end
B16: 2. UNLEVERED FREE CASH FLOW BUILD (USDm)
D17: 2026E | E17: 2027E | F17: 2028E | G17: 2029E | H17: 2030E | I17: 2031E | J17: 2032E | K17: 2033E | L17: 2034E | M17: 2035E | N17: Terminal | P17: CAGR 26–30E | Q17: CAGR 26–35E
B18: Adjusted EBITA (Model; before acquired-intangible amortization) | D18: =Model!V124 -> 198.29006 | E18: =Model!W124 -> 254.21808 | F18: =Model!X124 -> 315.12558 | G18: =Model!Y124 -> 381.35782 | H18: =Model!Z124 -> 451.9171 | I18: =H18*(1+I$31) -> 519.70466 | J18: =I18*(1+J$31) -> 585.96701 | K18: =J18*(1+K$31) -> 647.49354 | L18: =K18*(1+L$31) -> 700.91176 | M18: =L18*(1+M$31) -> 742.96647 | P18: =IFERROR(IF(AND($H18>0,$D18>0),($H18/$D18)^(1/(VALUE(LEFT($H$17,4))-VALUE(LEFT($D$17,4))))-1,"n/m"),"n/m") -> 0.22868189 | Q18: =IFERROR(IF(AND($M18>0,$D18>0),($M18/$D18)^(1/(VALUE(LEFT($M$17,4))-VALUE(LEFT($D$17,4))))-1,"n/m"),"n/m") -> 0.15808629
B19: y/y % | E19: =IFERROR(E18/D18-1,"") -> 0.28205154 | F19: =IFERROR(F18/E18-1,"") -> 0.23958762 | G19: =IFERROR(G18/F18-1,"") -> 0.21017727 | H19: =IFERROR(H18/G18-1,"") -> 0.18502121 | I19: =IFERROR(I18/H18-1,"") -> 0.15 | J19: =IFERROR(J18/I18-1,"") -> 0.1275 | K19: =IFERROR(K18/J18-1,"") -> 0.105 | L19: =IFERROR(L18/K18-1,"") -> 0.0825 | M19: =IFERROR(M18/L18-1,"") -> 0.06
B20: (−) SBC, transaction, integration & other items excluded from Adj. EBITA | D20: =-(Model!V123-Model!V117) -> -21.231 | E20: =-(Model!W123-Model!W117) -> -15.665703 | F20: =-(Model!X123-Model!X117) -> -18.25039 | G20: =-(Model!Y123-Model!Y117) -> -20.970766 | H20: =-(Model!Z123-Model!Z117) -> -23.039043 | I20: =H20*(1+I$31) -> -26.494899 | J20: =I20*(1+J$31) -> -29.872999 | K20: =J20*(1+K$31) -> -33.009663 | L20: =K20*(1+L$31) -> -35.732961 | M20: =L20*(1+M$31) -> -37.876938
B21: × (1 − tax rate) | D21: =1-$C$10 -> 0.755 | E21: =1-$C$10 -> 0.755 | F21: =1-$C$10 -> 0.755 | G21: =1-$C$10 -> 0.755 | H21: =1-$C$10 -> 0.755 | I21: =1-$C$10 -> 0.755 | J21: =1-$C$10 -> 0.755 | K21: =1-$C$10 -> 0.755 | ... M21: =1-$C$10 -> 0.755
B22: NOPAT = (Adj. EBITA − excluded costs) × (1 − t) | D22: =(D18+D20)*D21 -> 133.67959 | E22: =(E18+E20)*E21 -> 180.10704 | F22: =(F18+F20)*F21 -> 224.14077 | G22: =(G18+G20)*G21 -> 272.09222 | H22: =(H18+H20)*H21 -> 323.80293 | I22: =(I18+I20)*I21 -> 372.37337 | J22: =(J18+J20)*J21 -> 419.85098 | K22: =(K18+K20)*K21 -> 463.93533 | ... M22: =(M18+M20)*M21 -> 532.34259
B23: plus depreciation of PP&E and finance-lease ROU amortization | D23: =Model!V64+Model!V65 -> 24.153939 | E23: =Model!W64+Model!W65 -> 30.946659 | F23: =Model!X64+Model!X65 -> 39.223296 | G23: =Model!Y64+Model!Y65 -> 47.478213 | H23: =Model!Z64+Model!Z65 -> 56.589247 | I23: =H23*(1+I$31) -> 65.077634 | J23: =I23*(1+J$31) -> 73.375032 | K23: =J23*(1+K$31) -> 81.07941 | L23: =K23*(1+L$31) -> 87.768462 | M23: =L23*(1+M$31) -> 93.03457
B24: − Capex (PP&E) and acquisitions (M&A lever, 2027E+) | D24: =D29 -> -36.5 | E24: =E29+Model!W205 -> -243.11958 | F24: =F29+Model!X205 -> -272.50195 | G24: =G29+Model!Y205 -> -300.1846 | H24: =H29+Model!Z205 -> -309.23331 | I24: =I29 -> -68.118308 | J24: =J29 -> -76.803392 | K24: =K29 -> -84.867748 | L24: =L29 -> -91.869337 | M24: =M29 -> -97.381498
B25: − Δ Working capital (CF statement) | D25: =Model!V202 -> -64.345695 | E25: =Model!W202 -> -57.661512 | F25: =Model!X202 -> -59.796709 | G25: =Model!Y202 -> -67.34065 | H25: =Model!Z202 -> -68.457452 | I25: =H25*(1+I$31) -> -78.72607 | J25: =I25*(1+J$31) -> -88.763644 | K25: =J25*(1+K$31) -> -98.083827 | L25: =K25*(1+L$31) -> -106.17574 | M25: =L25*(1+M$31) -> -112.54629
B26: Unlevered FCF | D26: =D22+D23+D24+D25 -> 56.987835 | E26: =E22+E23+E24+E25 -> -89.727389 | F26: =F22+F23+F24+F25 -> -68.934595 | G26: =G22+G23+G24+G25 -> -47.954815 | H26: =H22+H23+H24+H25 -> 2.7014158 | I26: =I22+I23+I24+I25 -> 290.60663 | J26: =J22+J23+J24+J25 -> 327.65897 | K26: =K22+K23+K24+K25 -> 362.06317 | ... M26: =M22+M23+M24+M25 -> 415.44938 | N26: =M26*(1+$C$32) -> 432.06735 | P26: =IFERROR(IF(AND($H26>0,$D26>0),($H26/$D26)^(1/(VALUE(LEFT($H$17,4))-VALUE(LEFT($D$17,4))))-1,"n/m"),"n/m") -> -0.53339185 | Q26: =IFERROR(IF(AND($M26>0,$D26>0),($M26/$D26)^(1/(VALUE(LEFT($M$17,4))-VALUE(LEFT($D$17,4))))-1,"n/m"),"n/m") -> 0.24698018
B27: y/y % | E27: =IFERROR(E26/D26-1,"") -> -2.5745007 | F27: =IFERROR(F26/E26-1,"") -> -0.23173296 | G27: =IFERROR(G26/F26-1,"") -> -0.30434327 | H27: =IFERROR(H26/G26-1,"") -> -1.0563325 | I27: =IFERROR(I26/H26-1,"") -> 106.57567 | J27: =IFERROR(J26/I26-1,"") -> 0.1275 | K27: =IFERROR(K26/J26-1,"") -> 0.105 | L27: =IFERROR(L26/K26-1,"") -> 0.0825 | M27: =IFERROR(M26/L26-1,"") -> 0.06
B28: Terminal Value (Gordon Growth) | N28: =N26/($C$13-$C$32) -> 7572.1583
B29: memo: PP&E capex only (fade years carry no new acquisitions) | D29: =Model!V204 -> -36.5 | E29: =Model!W204 -> -43.119578 | F29: =Model!X204 -> -47.501952 | G29: =Model!Y204 -> -50.1846 | H29: =Model!Z204 -> -59.233311 | I29: =H29*(1+I$31) -> -68.118308 | J29: =I29*(1+J$31) -> -76.803392 | K29: =J29*(1+K$31) -> -84.867748 | L29: =K29*(1+L$31) -> -91.869337 | M29: =L29*(1+M$31) -> -97.381498
B31: Fade-period growth (2031E–35E) | I31: 0.15 | J31: =I31+($M$31-$I$31)/(COLUMNS($I$31:$M$31)-1) -> 0.1275 | K31: =J31+($M$31-$I$31)/(COLUMNS($I$31:$M$31)-1) -> 0.105 | L31: =K31+($M$31-$I$31)/(COLUMNS($I$31:$M$31)-1) -> 0.0825 | M31: 0.06
B32: Terminal growth rate | C32: 0.04
B34: Discount period (years) | D34: =(DATE(2026,12,31)-$C$15)/365.25 -> 0.24093087 | E34: =(DATE(2027,12,31)-$C$15)/365.25 -> 1.2402464 | F34: =(DATE(2028,12,31)-$C$15)/365.25 -> 2.2422998 | G34: =(DATE(2029,12,31)-$C$15)/365.25 -> 3.2416153 | H34: =(DATE(2030,12,31)-$C$15)/365.25 -> 4.2409309 | I34: =(DATE(2031,12,31)-$C$15)/365.25 -> 5.2402464 | J34: =(DATE(2032,12,31)-$C$15)/365.25 -> 6.2422998 | K34: =(DATE(2033,12,31)-$C$15)/365.25 -> 7.2416153 | L34: =(DATE(2034,12,31)-$C$15)/365.25 -> 8.2409309 | M34: =(DATE(2035,12,31)-$C$15)/365.25 -> 9.2402464 | N34: =M34 -> 9.2402464
B35: Discount factor | D35: =1/(1+$C$13)^D34 -> 0.97792885 | E35: =1/(1+$C$13)^E34 -> 0.89146524 | F35: =1/(1+$C$13)^F34 -> 0.81244024 | G35: =1/(1+$C$13)^G34 -> 0.74060831 | H35: =1/(1+$C$13)^H34 -> 0.67512741 | I35: =1/(1+$C$13)^I34 -> 0.61543599 | J35: =1/(1+$C$13)^J34 -> 0.56087994 | K35: =1/(1+$C$13)^K34 -> 0.51128972 | ... N35: =1/(1+$C$13)^N34 -> 0.42487519
B36: PV of UFCF | D36: =D26*D35 -> 55.730048 | E36: =E26*E35 -> -79.988849 | F36: =F26*F35 -> -56.005239 | G36: =G26*G35 -> -35.515735 | H36: =H26*H35 -> 1.8237999 | I36: =I26*I35 -> 178.84978 | J36: =J26*J35 -> 183.77734 | K36: =K26*K35 -> 185.11917 | ... M36: =M26*M35 -> 176.51413 | N36: =N28*N35 -> 3217.2222
D37: Adjusted EBITA follows Karman’s Adj. EBITDA definition, which excludes SBC and transaction / integration costs; those are deducted again here (row 20) so NOPAT bears them. Acquisition spend from the M&A lever is deducted in 2027E–30E so that acquired sales / profit in the Model are paid for; the fade period and terminal value assume no new acquisitions. Finance-lease liabilities are treated as debt (net debt) and lease ROU amortization is added back with depreciation; lease interest sits below EBITA.
B39: Implied ROIC & incremental ROIC (USDm) | D39: =D17 -> 2026E | E39: =E17 -> 2027E | F39: =F17 -> 2028E | G39: =G17 -> 2029E | H39: =H17 -> 2030E | I39: =I17 -> 2031E | J39: =J17 -> 2032E | K39: =K17 -> 2033E | ... M39: =M17 -> 2035E | N39: Terminal
B40: NOPAT (row 22) | D40: =D22 -> 133.67959 | E40: =E22 -> 180.10704 | F40: =F22 -> 224.14077 | G40: =G22 -> 272.09222 | H40: =H22 -> 323.80293 | I40: =I22 -> 372.37337 | J40: =J22 -> 419.85098 | K40: =K22 -> 463.93533 | ... M40: =M22 -> 532.34259 | N40: =M40*(1+$C$32) -> 553.6363
B41: Net investment = NOPAT − UFCF | D41: =D40-D26 -> 76.691756 | E41: =E40-E26 -> 269.83443 | F41: =F40-F26 -> 293.07536 | G41: =G40-G26 -> 320.04704 | H41: =H40-H26 -> 321.10152 | I41: =I40-I26 -> 81.766744 | J41: =J40-J26 -> 92.192004 | K41: =K40-K26 -> 101.87216 | ... N41: =N40-N26 -> 121.56894
B42: Opening invested capital | D42: =Model!P333 -> 929.276 | E42: =D43 -> 1005.9678 | F42: =E43 -> 1275.8022 | G42: =F43 -> 1568.8776 | H42: =G43 -> 1888.9246 | I42: =H43 -> 2210.0261 | J42: =I43 -> 2291.7929 | K42: =J43 -> 2383.9849 | L42: =K43 -> 2485.857 | ... N42: =M43 -> 2713.0269
B43: Closing invested capital | D43: =D42+D41 -> 1005.9678 | E43: =E42+E41 -> 1275.8022 | F43: =F42+F41 -> 1568.8776 | G43: =G42+G41 -> 1888.9246 | H43: =H42+H41 -> 2210.0261 | I43: =I42+I41 -> 2291.7929 | J43: =J42+J41 -> 2383.9849 | K43: =K42+K41 -> 2485.857 | ... M43: =M42+M41 -> 2713.0269
B44: Implied ROIC = NOPAT / opening IC | D44: =IFERROR(D40/D42,"") -> 0.14385348 | E44: =IFERROR(E40/E42,"") -> 0.17903858 | F44: =IFERROR(F40/F42,"") -> 0.17568615 | G44: =IFERROR(G40/G42,"") -> 0.17343114 | H44: =IFERROR(H40/H42,"") -> 0.17142184 | I44: =IFERROR(I40/I42,"") -> 0.16849275 | J44: =IFERROR(J40/J42,"") -> 0.18319761 | K44: =IFERROR(K40/K42,"") -> 0.19460498 | ... N44: =IFERROR(N40/N42,"") -> 0.20406591
B45: Reinvestment rate = net inv. / NOPAT | D45: =IFERROR(D41/D40,"") -> 0.57369831 | E45: =IFERROR(E41/E40,"") -> 1.4981892 | F45: =IFERROR(F41/F40,"") -> 1.3075505 | G45: =IFERROR(G41/G40,"") -> 1.1762447 | H45: =IFERROR(H41/H40,"") -> 0.99165722 | I45: =IFERROR(I41/I40,"") -> 0.21958268 | J45: =IFERROR(J41/J40,"") -> 0.21958268 | K45: =IFERROR(K41/K40,"") -> 0.21958268 | ... N45: =IFERROR(N41/N40,"") -> 0.21958268
B46: Incremental ROIC = Δ NOPAT / prior-yr net inv. | E46: =IFERROR((E40-D40)/D41,"") -> 0.60537735 | F46: =IFERROR((F40-E40)/E41,"") -> 0.16318795 | G46: =IFERROR((G40-F40)/F41,"") -> 0.16361475 | H46: =IFERROR((H40-G40)/G41,"") -> 0.16157222 | I46: =IFERROR((I40-H40)/H41,"") -> 0.15126194 | J46: =IFERROR((J40-I40)/I41,"") -> 0.58064688 | K46: =IFERROR((K40-J40)/J41,"") -> 0.47817978 | L46: =IFERROR((L40-K40)/K41,"") -> 0.37571269 | M46: =IFERROR((M40-L40)/L41,"") -> 0.27324559 | N46: =IFERROR($C$32/N45,"") -> 0.18216373
B47: Cumulative incremental ROIC 2026E–35E | C47: =IFERROR((M40-D40)/SUM(D41:L41),"") -> 0.2391704
D48: Opening IC = Model 2025A book IC (equity + net debt incl. finance leases), rolled forward with DCF net investment (capex + M&A − D&A + ΔWC). Terminal incremental ROIC = g ÷ reinvestment rate. Cumulative = (NOPAT 2035E − 2026E) / Σ net investment 2026E–34E.
B49: 3. VALUATION SUMMARY
B50: Sum of PV (explicit + fade) | C50: =SUM(D36:M36) -> 792.97834
B51: PV of Terminal Value | C51: =N36 -> 3217.2222
B52: Enterprise Value | C52: =C50+C51 -> 4010.2005
B53: Less: net debt incl. finance leases (Model 2026E YE) | C53: =Model!V356 -> 853.07829
B54: Less: non-controlling interests (none) | C54: 0
B55: Equity Value | C55: =C52-C53-C54 -> 3157.1223
B56: Diluted shares (m, Model 2026E) | C56: =Model!V110 -> 132.55225
B57: Implied share price ($) | C57: =C55/C56 -> 23.817945
B58: Current share price ($) | C58: =Model!V362 -> 34.14
B59: Implied upside / (downside) | C59: =C57/C58-1 -> -0.30234489
B62: 4. SENSITIVITY: IMPLIED PRICE ($) — WACC × Terminal Growth
B63: WACC step (across) | C63: 0.005
B64: Terminal growth step (down) | C64: 0.005
B65: g (down) / WACC | D65: =E65-$C$63 -> 0.08706 | E65: =F65-$C$63 -> 0.09206 | F65: =$C$13 -> 0.09706 | G65: =F65+$C$63 -> 0.10206 | H65: =G65+$C$63 -> 0.10706
B66: =B67-$C$64 -> 0.03 | D66: =IFERROR((SUMPRODUCT($D$26:$M$26/(1+D$65)^$D$34:$M$34)+($M$26*(1+$B66)/(D$65-$B66))/(1+D$65)^$M$34-$C$53-$C$54)/$C$56,"") -> 26.154014 | E66: =IFERROR((SUMPRODUCT($D$26:$M$26/(1+E$65)^$D$34:$M$34)+($M$26*(1+$B66)/(E$65-$B66))/(1+E$65)^$M$34-$C$53-$C$54)/$C$56,"") -> 22.819759 | F66: =IFERROR((SUMPRODUCT($D$26:$M$26/(1+F$65)^$D$34:$M$34)+($M$26*(1+$B66)/(F$65-$B66))/(1+F$65)^$M$34-$C$53-$C$54)/$C$56,"") -> 20.00002 | G66: =IFERROR((SUMPRODUCT($D$26:$M$26/(1+G$65)^$D$34:$M$34)+($M$26*(1+$B66)/(G$65-$B66))/(1+G$65)^$M$34-$C$53-$C$54)/$C$56,"") -> 17.587197 | H66: =IFERROR((SUMPRODUCT($D$26:$M$26/(1+H$65)^$D$34:$M$34)+($M$26*(1+$B66)/(H$65-$B66))/(1+H$65)^$M$34-$C$53-$C$54)/$C$56,"") -> 15.501634
B67: =B68-$C$64 -> 0.035 | D67: =IFERROR((SUMPRODUCT($D$26:$M$26/(1+D$65)^$D$34:$M$34)+($M$26*(1+$B67)/(D$65-$B67))/(1+D$65)^$M$34-$C$53-$C$54)/$C$56,"") -> 28.805731 | E67: =IFERROR((SUMPRODUCT($D$26:$M$26/(1+E$65)^$D$34:$M$34)+($M$26*(1+$B67)/(E$65-$B67))/(1+E$65)^$M$34-$C$53-$C$54)/$C$56,"") -> 24.961648 | F67: =IFERROR((SUMPRODUCT($D$26:$M$26/(1+F$65)^$D$34:$M$34)+($M$26*(1+$B67)/(F$65-$B67))/(1+F$65)^$M$34-$C$53-$C$54)/$C$56,"") -> 21.755183 | G67: =IFERROR((SUMPRODUCT($D$26:$M$26/(1+G$65)^$D$34:$M$34)+($M$26*(1+$B67)/(G$65-$B67))/(1+G$65)^$M$34-$C$53-$C$54)/$C$56,"") -> 19.043198 | H67: =IFERROR((SUMPRODUCT($D$26:$M$26/(1+H$65)^$D$34:$M$34)+($M$26*(1+$B67)/(H$65-$B67))/(1+H$65)^$M$34-$C$53-$C$54)/$C$56,"") -> 16.722299
B68: =$C$32 -> 0.04 | D68: =IFERROR((SUMPRODUCT($D$26:$M$26/(1+D$65)^$D$34:$M$34)+($M$26*(1+$B68)/(D$65-$B68))/(1+D$65)^$M$34-$C$53-$C$54)/$C$56,"") -> 32.020924 | E68: =IFERROR((SUMPRODUCT($D$26:$M$26/(1+E$65)^$D$34:$M$34)+($M$26*(1+$B68)/(E$65-$B68))/(1+E$65)^$M$34-$C$53-$C$54)/$C$56,"") -> 27.514964 | F68: =IFERROR((SUMPRODUCT($D$26:$M$26/(1+F$65)^$D$34:$M$34)+($M$26*(1+$B68)/(F$65-$B68))/(1+F$65)^$M$34-$C$53-$C$54)/$C$56,"") -> 23.817945 | G68: =IFERROR((SUMPRODUCT($D$26:$M$26/(1+G$65)^$D$34:$M$34)+($M$26*(1+$B68)/(G$65-$B68))/(1+G$65)^$M$34-$C$53-$C$54)/$C$56,"") -> 20.73381 | H68: =IFERROR((SUMPRODUCT($D$26:$M$26/(1+H$65)^$D$34:$M$34)+($M$26*(1+$B68)/(H$65-$B68))/(1+H$65)^$M$34-$C$53-$C$54)/$C$56,"") -> 18.12499
B69: =B68+$C$64 -> 0.045 | D69: =IFERROR((SUMPRODUCT($D$26:$M$26/(1+D$65)^$D$34:$M$34)+($M$26*(1+$B69)/(D$65-$B69))/(1+D$65)^$M$34-$C$53-$C$54)/$C$56,"") -> 36.000547 | E69: =IFERROR((SUMPRODUCT($D$26:$M$26/(1+E$65)^$D$34:$M$34)+($M$26*(1+$B69)/(E$65-$B69))/(1+E$65)^$M$34-$C$53-$C$54)/$C$56,"") -> 30.610845 | F69: =IFERROR((SUMPRODUCT($D$26:$M$26/(1+F$65)^$D$34:$M$34)+($M$26*(1+$B69)/(F$65-$B69))/(1+F$65)^$M$34-$C$53-$C$54)/$C$56,"") -> 26.276936 | G69: =IFERROR((SUMPRODUCT($D$26:$M$26/(1+G$65)^$D$34:$M$34)+($M$26*(1+$B69)/(G$65-$B69))/(1+G$65)^$M$34-$C$53-$C$54)/$C$56,"") -> 22.72071 | H69: =IFERROR((SUMPRODUCT($D$26:$M$26/(1+H$65)^$D$34:$M$34)+($M$26*(1+$B69)/(H$65-$B69))/(1+H$65)^$M$34-$C$53-$C$54)/$C$56,"") -> 19.753703
B70: =B69+$C$64 -> 0.05 | D70: =IFERROR((SUMPRODUCT($D$26:$M$26/(1+D$65)^$D$34:$M$34)+($M$26*(1+$B70)/(D$65-$B70))/(1+D$65)^$M$34-$C$53-$C$54)/$C$56,"") -> 41.054002 | E70: =IFERROR((SUMPRODUCT($D$26:$M$26/(1+E$65)^$D$34:$M$34)+($M$26*(1+$B70)/(E$65-$B70))/(1+E$65)^$M$34-$C$53-$C$54)/$C$56,"") -> 34.44279 | F70: =IFERROR((SUMPRODUCT($D$26:$M$26/(1+F$65)^$D$34:$M$34)+($M$26*(1+$B70)/(F$65-$B70))/(1+F$65)^$M$34-$C$53-$C$54)/$C$56,"") -> 29.258449 | G70: =IFERROR((SUMPRODUCT($D$26:$M$26/(1+G$65)^$D$34:$M$34)+($M$26*(1+$B70)/(G$65-$B70))/(1+G$65)^$M$34-$C$53-$C$54)/$C$56,"") -> 25.089265 | H70: =IFERROR((SUMPRODUCT($D$26:$M$26/(1+H$65)^$D$34:$M$34)+($M$26*(1+$B70)/(H$65-$B70))/(1+H$65)^$M$34-$C$53-$C$54)/$C$56,"") -> 21.667854
B73: 5. REVERSE DCF
B74: To solve for the market-implied path: Data ▸ What-If Analysis ▸ Goal Seek — set C57 (implied price) to the current price (C58) by changing C32 (terminal growth) or the Model scenario levers (end-market growth, Adj. EBITDA margin, M&A spend).
B76: 6. MAUBOUSSIN EV / NOPAT — TWO-STAGE FRAMEWORK
B77: EV/NOPAT = 1/r + [g × (1 − r/ROIIC) / (r × (r − g))] × [1 − ((1+g)/(1+r))^N]
B78: Formula source: Mauboussin & Rappaport, "Expectations Investing" (2021); Counterpoint Global, "What Does a Price-Earnings Multiple Mean?" (2020).
B80: Input | C80: Value | D80: Rationale (Karman characteristics)
B81: r (Cost of capital / WACC) | C81: =$C$13 -> 0.09706 | D81: Linked from Section 1 WACC build
B82: g (NOPAT growth, Stage 1) | C82: 0.12 | D82: Model Adj. EBITA CAGR 2025–30E well above this; 12% assumes growth normalises after the munitions / interceptor ramp
B83: ROIIC (Return on incremental invested capital) | C83: 0.25 | D83: Organic growth needs contract-asset and capacity investment (capex ~4–5% of sales); acquisitions at ~10x EBITDA earn ~7–8% after tax
B84: N (Years of value creation / CAP) | C84: 12 | D84: IP-rich, sole-source subsystem positions on long-lived missile, launch and submarine programs; high qualification barriers
B86: Calculation | C86: Value
B87: Steady-state component: 1 / r | C87: =1/C81 -> 10.302905
B88: Value-creation factor: 1 − r / ROIIC | C88: =1-C81/C83 -> 0.61176
B89: Growth multiplier: g × (1 − r/ROIIC) / (r × (r − g)) | C89: =C82*C88/(C81*(C81-C82)) -> -32.970735
B90: Time decay: 1 − ((1+g)/(1+r))^N | C90: =1-((1+C82)/(1+C81))^C84 -> -0.28189279
B91: PVGO component (growth value) | C91: =C89*C90 -> 9.2942125
B92: Mauboussin EV / NOPAT (steady-state + PVGO) | C92: =C87+C91 -> 19.597118
B94: VALUATION — Applied to 2028E NOPAT | C94: USDm
B95: 2028E Adjusted EBITA (Model) | C95: =Model!X124 -> 315.12558
B96: (−) 2028E SBC, transaction & integration costs | C96: =-(Model!X123-Model!X117) -> -18.25039
B97: Tax rate (from WACC build) | C97: =$C$10 -> 0.245
B98: 2028E NOPAT = (EBITA − excluded costs) × (1 − t) | C98: =(C95+C96)*(1-C97) -> 224.14077
B99: × Mauboussin EV/NOPAT multiple | C99: =C92 -> 19.597118
B100: Implied Enterprise Value (2028E basis) | C100: =C98*C99 -> 4392.5131
B101: Less: YE2027 net debt incl. finance leases (Model) | C101: =Model!W356 -> 982.41257
B102: Implied Equity Value | C102: =C100-C101 -> 3410.1005
B103: Diluted shares 2028E (m, Model) | C103: =Model!X110 -> 133.57244
B104: Implied share price 2028 ($) | C104: =C102/C103 -> 25.529972
B106: Current share price ($) | C106: =C58 -> 34.14
B107: Implied upside / (downside) | C107: =C104/C106-1 -> -0.25219766
B109: MARKET-IMPLIED EV/NOPAT TODAY | C109: USDm
B110: Current market cap (spot × diluted shares) | C110: =C58*C56 -> 4525.3338
B111: Plus: YE2026 net debt incl. finance leases | C111: =C53+C54 -> 853.07829
B112: Implied Enterprise Value (today) | C112: =C110+C111 -> 5378.4121
B113: KRMN's market-implied EV/NOPAT (on 2028E NOPAT) | C113: =C112/C98 -> 23.995689
B115: Multiple gap (Mauboussin − Market) | C115: =C92-C113 -> -4.3985707
B116: Implied re-rating headroom | C116: =C92/C113-1 -> -0.18330671

Sheet Charts
B2: Karman Holdings — Operating Performance (2022A–2030E)
B3: USDm · Linked to Model (Base / live scenario). 2022–25 actual, 2026E–30E forecast. M&A % = disclosed / derived incremental acquisition sales (FY24 RMS) and the M&A lever; organic split not disclosed for 2022–23 and 2025. Adj. EBITDA = company definition; Adj. EBITA = model.
C7: 2022 | D7: 2023 | E7: 2024 | F7: 2025 | G7: 2026E | H7: 2027E | I7: 2028E | J7: 2029E | K7: 2030E
B8: Organic % | C8: =IFERROR(Model!C180+0,0) -> 0 | D8: =IFERROR(Model!D180+0,0) -> 0 | E8: =IFERROR(Model!J180+0,0) -> 0.1882902 | F8: =IFERROR(Model!P180+0,0) -> 0 | G8: =IFERROR(Model!V180+0,0) -> 0.36292259 | H8: =IFERROR(Model!W180+0,0) -> 0.20644341 | I8: =IFERROR(Model!X180+0,0) -> 0.16013466 | J8: =IFERROR(Model!Y180+0,0) -> 0.13597377 | K8: =IFERROR(Model!Z180+0,0) -> 0.11803842
B9: M&A % | C9: =IFERROR(Model!C181+0,0) -> 0 | D9: =IFERROR(Model!D181+0,0) -> 0 | E9: =IFERROR(Model!J181+0,0) -> 0.041652268 | F9: =IFERROR(Model!P181+0,0) -> 0 | G9: =IFERROR(Model!V181+0,0) -> 0.22668505 | H9: =IFERROR(Model!W181+0,0) -> 0.072026039 | I9: =IFERROR(Model!X181+0,0) -> 0.079202504 | J9: =IFERROR(Model!Y181+0,0) -> 0.071425636 | K9: =IFERROR(Model!Z181+0,0) -> 0.062270098
C11: 2022 | D11: 2023 | E11: 2024 | F11: 2025 | G11: 2026E | H11: 2027E | I11: 2028E | J11: 2029E | K11: 2030E
B12: Adjusted EBITDA | C12: =Model!C146 -> 60.291 | D12: =Model!D146 -> 81.861 | E12: =Model!J146 -> 106.145 | F12: =Model!P146 -> 145.302 | G12: =Model!V146 -> 221.99 | H12: =Model!W146 -> 285.16474 | I12: =Model!X146 -> 354.34888 | J12: =Model!Y146 -> 428.83603 | K12: =Model!Z146 -> 508.50635
B13: Operating Income (GAAP) | C13: =Model!C97 -> 20.435 | D13: =Model!D97 -> 48.494 | E13: =Model!J97 -> 63.56 | F13: =Model!P97 -> 72.942 | G13: =Model!V97 -> 137.37156 | H13: =Model!W97 -> 198.23987 | I13: =Model!X97 -> 255.59394 | J13: =Model!Y97 -> 312.19955 | K13: =Model!Z97 -> 371.81556
B14: Adj. EBITDA Margin % | C14: =Model!C188 -> 0.26640891 | D14: =Model!D188 -> 0.29162644 | E14: =Model!J188 -> 0.30744299 | F14: =Model!P188 -> 0.30816967 | G14: =Model!V188 -> 0.29618412 | H14: =Model!W188 -> 0.29760062 | I14: =Model!X188 -> 0.29838679 | J14: =Model!Y188 -> 0.29908101 | K14: =Model!Z188 -> 0.30046813
B15: GAAP Op. Margin % | C15: =Model!C191 -> 0.090296496 | D15: =Model!D191 -> 0.17275788 | E15: =Model!J191 -> 0.18409795 | F15: =Model!P191 -> 0.15470201 | G15: =Model!V191 -> 0.18328427 | H15: =Model!W191 -> 0.20688501 | I15: =Model!X191 -> 0.21522816 | J15: =Model!Y191 -> 0.2177358 | K15: =Model!Z191 -> 0.21969976
C17: 2022 | D17: 2023 | E17: 2024 | F17: 2025 | G17: 2026E | H17: 2027E | I17: 2028E | J17: 2029E | K17: 2030E
B18: ROIC | C18: =IFERROR(Model!C336+0,NA()) -> 0.065972883 | D18: =IFERROR(Model!D336+0,NA()) -> 0.088735214 | E18: =IFERROR(Model!J336+0,NA()) -> 0.10622211 | F18: =IFERROR(Model!P336+0,NA()) -> 0.098155446 | G18: =IFERROR(Model!V336+0,NA()) -> 0.11602219 | H18: =IFERROR(Model!W336+0,NA()) -> 0.12443802 | I18: =IFERROR(Model!X336+0,NA()) -> 0.13153862 | J18: =IFERROR(Model!Y336+0,NA()) -> 0.13732976 | K18: =IFERROR(Model!Z336+0,NA()) -> 0.14345682
B19: RONTA | C19: =IFERROR(Model!C348+0,NA()) -> 0.19146647 | D19: =IFERROR(Model!D348+0,NA()) -> 0.24609268 | E19: =IFERROR(Model!J348+0,NA()) -> 0.27925921 | F19: =IFERROR(Model!P348+0,NA()) -> 0.23564509 | G19: =IFERROR(Model!V348+0,NA()) -> 0.27158545 | H19: =IFERROR(Model!W348+0,NA()) -> 0.32966582 | I19: =IFERROR(Model!X348+0,NA()) -> 0.36123323 | J19: =IFERROR(Model!Y348+0,NA()) -> 0.39043687 | K19: =IFERROR(Model!Z348+0,NA()) -> 0.41724046
B20: Adj. EBITDA margin % | C20: =IFERROR(Model!C188+0,NA()) -> 0.26640891 | D20: =IFERROR(Model!D188+0,NA()) -> 0.29162644 | E20: =IFERROR(Model!J188+0,NA()) -> 0.30744299 | F20: =IFERROR(Model!P188+0,NA()) -> 0.30816967 | G20: =IFERROR(Model!V188+0,NA()) -> 0.29618412 | H20: =IFERROR(Model!W188+0,NA()) -> 0.29760062 | I20: =IFERROR(Model!X188+0,NA()) -> 0.29838679 | J20: =IFERROR(Model!Y188+0,NA()) -> 0.29908101 | K20: =IFERROR(Model!Z188+0,NA()) -> 0.30046813
B21: FCF margin % | C21: =IFERROR(Model!C224+0,NA()) -> -0.12002121 | D21: =IFERROR(Model!D224+0,NA()) -> 0.012653854 | E21: =IFERROR(Model!J224+0,NA()) -> 0.03299918 | F21: =IFERROR(Model!P224+0,NA()) -> -0.090042418 | G21: =IFERROR(Model!V224+0,NA()) -> 0.035932902 | H21: =IFERROR(Model!W224+0,NA()) -> 0.084339576 | I21: =IFERROR(Model!X224+0,NA()) -> 0.10429028 | J21: =IFERROR(Model!Y224+0,NA()) -> 0.11676492 | K21: =IFERROR(Model!Z224+0,NA()) -> 0.12808915
