Workbook

Sheet Model
CK1: SCENARIO SWITCH ▼ (Bull / Base / Bear) — drives all scenario-linked forecast drivers
B2: Cintas Corporation (NASDAQ: CTAS) — 3-Statement Financial Model | CK2: Base
B3: US GAAP as reported · USD millions (per-share data in USD, restated for the 4-for-1 split of Sep-2024; shares in millions) · Fiscal years end 31-May · Source: Cintas Forms 10-K / 10-Q and Form 8-K earnings releases (Ex. 99), merger 8-K (10-Mar-2026), S-4 / 424B3 (UniFirst pro forma), UniFirst 10-K / 8-K, SEC EDGAR CIK 0000723254 (investor-relations releases are the same documents as filed on EDGAR)
B4: Basis notes: fiscal year ends 31-May (Q1 = Jun–Aug). Quarters as originally reported. Segments: Rental / Uniform Direct Sales / First Aid, Safety & Fire / Document Management to FY2015; UR&FS / First Aid & Safety / All Other from FY2016 (FY2015 recast). Shred-it partnership Apr-2014 (Document Shredding deconsolidated); document storage sold FY2015–16; Shred-it stake sold FY2017 (discontinued operations FY2015–2020); G&K Services acquired 21-Mar-2017; 4-for-1 stock split 11-Sep-2024. UniFirst acquisition pending (FTC Second Request) — modelled from an assumed 31-Dec-2026 close (toggle); NOT in company FY27 guidance.
CM5: Forecast | CN5: Historical | CO5: Historical | CP5: Historical
B6: (USDm) | C6: FY2006 | D6: FY2007 | E6: FY2008 | F6: FY2009 | G6: FY2010 | H6: FY2011 | I6: FY2012 | J6: Q1/13 | K6: Q2/13 | L6: Q3/13 | M6: Q4/13 | N6: FY2013 | O6: Q1/14 | P6: Q2/14 | Q6: Q3/14 | R6: Q4/14 | S6: FY2014 | T6: Q1/15 | U6: Q2/15 | V6: Q3/15 | W6: Q4/15 | X6: FY2015 | Y6: Q1/16 | Z6: Q2/16 | AA6: Q3/16 | AB6: Q4/16 | AC6: FY2016 | AD6: Q1/17 | AE6: Q2/17 | AF6: Q3/17 | AG6: Q4/17 | AH6: FY2017 | AI6: Q1/18 | AJ6: Q2/18 | AK6: Q3/18 | AL6: Q4/18 | AM6: FY2018 | AN6: Q1/19 | AO6: Q2/19 | AP6: Q3/19 | AQ6: Q4/19 | AR6: FY2019 | AS6: Q1/20 | AT6: Q2/20 | AU6: Q3/20 | AV6: Q4/20 | AW6: FY2020 | AX6: Q1/21 | AY6: Q2/21 | AZ6: Q3/21 | BA6: Q4/21 | BB6: FY2021 | BC6: Q1/22 | BD6: Q2/22 | BE6: Q3/22 | BF6: Q4/22 | BG6: FY2022 | BH6: Q1/23 | BI6: Q2/23 | BJ6: Q3/23 | BK6: Q4/23 | BL6: FY2023 | BM6: Q1/24 | BN6: Q2/24 | BO6: Q3/24 | BP6: Q4/24 | BQ6: FY2024 | BR6: Q1/25 | BS6: Q2/25 | BT6: Q3/25 | BU6: Q4/25 | BV6: FY2025 | BW6: Q1/26 | BX6: Q2/26 | BY6: Q3/26 | BZ6: Q4/26 | CA6: FY2026 | CB6: Q1/27 | CC6: Q2/27E | CD6: Q3/27E | CE6: Q4/27E | CF6: FY2027E | CG6: FY2028E | CH6: FY2029E | CI6: FY2030E | CJ6: FY2031E | CK6: Modelling Notes | CM6: 5Y CAGR | CN6: 5Y CAGR | CO6: 10Y CAGR | CP6: 20Y CAGR
CM7: 26-'31 | CN7: 21-'26 | CO7: 16-'26 | CP7: 06-'26
B8: SEGMENT P&L — UNIFORM RENTAL & FACILITY SERVICES · FIRST AID & SAFETY · ALL OTHER · UNIFIRST (organic growth + M&A build) | CK8: SEGMENT BUILD — modelling logic (organic growth → revenues → gross margin → S&A → segment operating income)
CS9: SCENARIO INPUT TABLE — driver assumptions per Bull / Base / Bear | CT9: Bull | CU9: Base | CV9: Bear | CW9: Bull / Bear = Base + Δ (Δ inputs on each block header). Outlook block = high / mid / low end of FY27 ranges. Blue = input.
B10: Uniform Rental & Facility Services (UR&FS) — reportable segment: uniform & garment rental, mats, mops, shop towels, restroom & hygiene, water, Clean Room; legacy "Rental Uniforms & Ancillary Products" segment to FY2014 (FY2015 recast incl. storage) | CK10: UR&FS — modelling logic
B11: Revenues | C11: 2568.776 | D11: 2734.629 | E11: 2834.568 | F11: 2755.015 | G11: 2569.357 | H11: 2692.248 | I11: 2912.261 | J11: 754.843 | K11: 755.839 | L11: 748.887 | M11: 785.018 | N11: 3044.587 | O11: 792.866 | P11: 804.316 | Q11: 801.702 | R11: 825.046 | S11: 3223.93 | T11: 873.698 | U11: 891.475 | V11: 883.401 | W11: 891.269 | X11: 3539.843 | Y11: 938.408 | Z11: 937.704 | AA11: 936.565 | AB11: 965.124 | AC11: 3777.801 | AD11: 999.596 | AE11: 1005.565 | AF11: 993.398 | AG11: 1220.015 | AH11: 4202.49 | AI11: 1311.784 | AJ11: 1308.038 | AK11: 1284.516 | AL11: 1342.786 | AM11: 5247.124 | AN11: 1374.938 | AO11: 1390.778 | AP11: 1358.322 | AQ11: 1428.392 | AR11: 5552.43 | AS11: 1454.527 | AT11: 1469.977 | AU11: 1448.021 | AV11: 1270.97 | AW11: 5643.494 | AX11: 1394.411 | AY11: 1410.488 | AZ11: 1417.865 | BA11: 1466.868 | BB11: 5689.632 | BC11: 1508.176 | BD11: 1535.271 | BE11: 1553.32 | BF11: 1630.213 | BG11: 6226.98 | BH11: 1697.772 | BI11: 1709.987 | BJ11: 1716.165 | BK11: 1773.206 | BL11: 6897.13 | BM11: 1826.825 | BN11: 1850.542 | BO11: 1876.642 | BP11: 1911.19 | BQ11: 7465.199 | BR11: 1933.839 | BS11: 1990.41 | BT11: 2021.144 | BU11: 2030.68 | BV11: 7976.073 | BW11: 2091.066 | BX11: 2155.4 | BY11: 2177.453 | BZ11: 2197.705 | CA11: 8621.624 | CB11: 2294.736 | CC11: =BX11*(1+CC12) -> 2294.0821 | CD11: =BY11*(1+CD12) -> 2317.554 | CE11: =BZ11*(1+CE12) -> 2339.1091 | CF11: =SUM(CB11,CC11,CD11,CE11) -> 9245.4812 | CG11: =CF11*(1+CG12) -> 9892.6649 | CH11: =CG11*(1+CH12) -> 10535.688 | CI11: =CH11*(1+CI12) -> 11220.508 | CJ11: =CI11*(1+CJ12) -> 11893.738 | CK11: Q2–Q4/27E: prior-year quarter × (1 + Q1/27 y/y growth ex-workday effect + revenue-outlook calibration Δ). FY28E+: prior year × (1 + scenario organic growth URFS_org); bolt-on M&A modelled separately (Future acquisitions block). | CM11: =IFERROR((CJ11/CA11)^(1/5)-1,"n/m") -> 0.066463166 | CN11: =IFERROR((CA11/BB11)^(1/5)-1,"n/m") -> 0.086678264 | CO11: =IFERROR((CA11/AC11)^(1/10)-1,"n/m") -> 0.08601294 | CP11: =IFERROR((CA11/C11)^(1/20)-1,"n/m") -> 0.062412428 | CS11: FY27 outlook — Q1/27 release (23-Sep-26); legacy Cintas, excludes UniFirst | CT11: High | CU11: Mid | CV11: Low | CW11: Company guidance excludes the UniFirst acquisition — the model adds UniFirst separately.
B12: Revenues y/y % | D12: =IF(AND(ISNUMBER(D11),ISNUMBER(C11)),IFERROR(D11/C11-1,""),"") -> 0.064564991 | E12: =IF(AND(ISNUMBER(E11),ISNUMBER(D11)),IFERROR(E11/D11-1,""),"") -> 0.036545725 | F12: =IF(AND(ISNUMBER(F11),ISNUMBER(E11)),IFERROR(F11/E11-1,""),"") -> -0.0280653 | G12: =IF(AND(ISNUMBER(G11),ISNUMBER(F11)),IFERROR(G11/F11-1,""),"") -> -0.067389107 | H12: =IF(AND(ISNUMBER(H11),ISNUMBER(G11)),IFERROR(H11/G11-1,""),"") -> 0.047829476 | I12: =IF(AND(ISNUMBER(I11),ISNUMBER(H11)),IFERROR(I11/H11-1,""),"") -> 0.081720926 | N12: =IF(AND(ISNUMBER(N11),ISNUMBER(I11)),IFERROR(N11/I11-1,""),"") -> 0.045437548 | O12: =IF(AND(ISNUMBER(O11),ISNUMBER(J11)),IFERROR(O11/J11-1,""),"") -> 0.050372064 | P12: =IF(AND(ISNUMBER(P11),ISNUMBER(K11)),IFERROR(P11/K11-1,""),"") -> 0.064136675 | Q12: =IF(AND(ISNUMBER(Q11),ISNUMBER(L11)),IFERROR(Q11/L11-1,""),"") -> 0.070524659 | R12: =IF(AND(ISNUMBER(R11),ISNUMBER(M11)),IFERROR(R11/M11-1,""),"") -> 0.050989914 | S12: =IF(AND(ISNUMBER(S11),ISNUMBER(N11)),IFERROR(S11/N11-1,""),"") -> 0.058905526 | T12: =IF(AND(ISNUMBER(T11),ISNUMBER(O11)),IFERROR(T11/O11-1,""),"") -> 0.10194913 | U12: =IF(AND(ISNUMBER(U11),ISNUMBER(P11)),IFERROR(U11/P11-1,""),"") -> 0.10836413 | ... CB12: =IF(AND(ISNUMBER(CB11),ISNUMBER(BW11)),IFERROR(CB11/BW11-1,""),"") -> 0.097400082 | CC12: =$CB$12-$CB$109+CC114 -> 0.064341707 | CD12: =$CB$12-$CB$109+CD114 -> 0.064341707 | CE12: =$CB$12-$CB$109+CE114 -> 0.064341707 | CF12: =IFERROR(CF11/CA11-1,"") -> 0.072359598 | CG12: =CHOOSE(MATCH($CK$2,{"Bull","Base","Bear"},0),$CT$76,$CU$76,$CV$76) -> 0.07 | CH12: =CHOOSE(MATCH($CK$2,{"Bull","Base","Bear"},0),$CT$77,$CU$77,$CV$77) -> 0.065 | CI12: =CHOOSE(MATCH($CK$2,{"Bull","Base","Bear"},0),$CT$78,$CU$78,$CV$78) -> 0.065 | CJ12: =CHOOSE(MATCH($CK$2,{"Bull","Base","Bear"},0),$CT$79,$CU$79,$CV$79) -> 0.06 | CK12: Q2–Q4/27E: Q1/27 y/y less the Q1 extra-workday effect (row "Workday effect") + calibration Δ (Group block). FY28E+: scenario lever. | CS12: FY27 revenues ($m) | CT12: 12270 | CU12: 12210 | CV12: 12150 | CW12: Raised to $12.15–12.27bn in the Q1/27 release (from $12.10–12.25bn); excludes UniFirst & future M&A.
B13: Organic growth % (company-disclosed, segment) | AA13: 0.061 | AE13: 0.065 | AF13: 0.073 | AG13: 0.08 | AI13: 0.081 | AJ13: 0.073 | AK13: 0.065 | AL13: 0.053 | AN13: 0.049 | AO13: 0.066 | AP13: 0.062 | AQ13: 0.068 | AS13: 0.075 | AT13: 0.058 | AU13: 0.048 | AV13: -0.096 | AX13: -0.054 | AY13: -0.036 | AZ13: 0 | BA13: 0.137 | BD13: 0.083 | BE13: 0.089 | BF13: 0.105 | BH13: 0.123 | BI13: 0.113 | BJ13: 0.108 | BL13: 0.108 | BM13: 0.076 | BN13: 0.079 | BO13: 0.071 | BR13: 0.07 | BS13: 0.069 | BT13: 0.07 | BW13: 0.073 | BX13: 0.078 | BY13: 0.073 | CC13: =CC12 -> 0.064341707 | CD13: =CD12 -> 0.064341707 | CE13: =CE12 -> 0.064341707 | CF13: =CF12 -> 0.072359598 | CG13: =CG12 -> 0.07 | CH13: =CH12 -> 0.065 | CI13: =CI12 -> 0.065 | CJ13: =CJ12 -> 0.06 | CK13: Segment organic growth as disclosed in releases (FY2016–21) and 10-Q MD&A (FY2022+); blank where not disclosed. Forecast: no acquisition/FX/workday effect assumed inside segments. | CS13: FY27 adjusted diluted EPS ($) | CT13: 5.54 | CU13: 5.495 | CV13: 5.45 | CW13: Raised to $5.45–5.54 (from $5.36–5.50); excludes UniFirst transaction costs; FY26 adj. $4.94.
B14: Acquisitions, FX & workday effects % (derived = y/y − organic) | C14: =IF(AND(ISNUMBER(C12),ISNUMBER(C13)),C12-C13,"") | D14: =IF(AND(ISNUMBER(D12),ISNUMBER(D13)),D12-D13,"") | E14: =IF(AND(ISNUMBER(E12),ISNUMBER(E13)),E12-E13,"") | F14: =IF(AND(ISNUMBER(F12),ISNUMBER(F13)),F12-F13,"") | G14: =IF(AND(ISNUMBER(G12),ISNUMBER(G13)),G12-G13,"") | H14: =IF(AND(ISNUMBER(H12),ISNUMBER(H13)),H12-H13,"") | I14: =IF(AND(ISNUMBER(I12),ISNUMBER(I13)),I12-I13,"") | J14: =IF(AND(ISNUMBER(J12),ISNUMBER(J13)),J12-J13,"") | ... CB14: =IF(AND(ISNUMBER(CB12),ISNUMBER(CB13)),CB12-CB13,"")
B15: Gross margin (GAAP) | C15: 1161.947 | D15: 1219.444 | E15: 1252.951 | F15: 1192.785 | G15: 1119.781 | H15: 1161.792 | I15: 1263.71 | J15: 326.695 | K15: 316.937 | L15: 314.078 | M15: 330.58 | N15: 1288.29 | O15: 338.135 | P15: 345.204 | Q15: 351.616 | R15: 359.548 | S15: 1394.503 | T15: 383.023 | U15: 385.652 | V15: 382.128 | W15: 381.408 | X15: 1532.211 | Y15: 419.905 | Z15: 411.613 | AA15: 411.909 | AB15: 427.581 | AC15: 1671.008 | AD15: 458.664 | AE15: 449.813 | AF15: 446.86 | AG15: 543.626 | AH15: 1894.716 | AI15: 604.921 | AJ15: 584.078 | AK15: 566.378 | AL15: 604.788 | AM15: 2360.165 | AN15: 628.485 | AO15: 629.659 | AP15: 609.351 | AQ15: 657.336 | AR15: 2524.831 | AS15: 685.851 | AT15: 685.04 | AU15: 663.091 | AV15: 554.368 | AW15: 2588.349 | AX15: 678.999 | AY15: 670.677 | AZ15: 656.015 | BA15: 700.427 | BB15: 2706.118 | BC15: 728.875 | BD15: 718.01 | BE15: 719.238 | BF15: 744.424 | BG15: 2910.547 | BH15: 807.006 | BI15: 803.26 | BJ15: 808.172 | BK15: 846.517 | BL15: 3264.955 | BM15: 879.242 | BN15: 876.311 | BO15: 916.434 | BP15: 928.141 | BQ15: 3600.128 | BR15: 952.676 | BS15: 976.358 | BT15: 1011.484 | BU15: 994.667 | BV15: 3935.185 | BW15: 1038.513 | BX15: 1074.182 | BY15: 1094.434 | BZ15: 1102.398 | CA15: 4309.527 | CB15: 1165.852 | CC15: =CC11*CC17 -> 1140.795 | CD15: =CD11*CD17 -> 1162.3245 | CE15: =CE11*CE17 -> 1170.7774 | CF15: =SUM(CB15,CC15,CD15,CE15) -> 4639.7489 | CG15: =CG11*CG17 -> 5045.2591 | CH15: =CH11*CH17 -> 5404.808 | CI15: =CI11*CI17 -> 5789.7821 | CJ15: =CJ11*CJ17 -> 6172.8502 | CM15: =IFERROR((CJ15/CA15)^(1/5)-1,"n/m") -> 0.074511892 | CN15: =IFERROR((CA15/BB15)^(1/5)-1,"n/m") -> 0.097530442 | CO15: =IFERROR((CA15/AC15)^(1/10)-1,"n/m") -> 0.099373104 | CP15: =IFERROR((CA15/C15)^(1/20)-1,"n/m") -> 0.067731768 | CS15: Point estimates & structural inputs (all cases)
B16: Gross margin % before outlook calibration (Q2–Q4/27E helper) | CC16: =BX17+($CB$17-$BW$17) -> 0.50977992 | CD16: =BY17+($CB$17-$BW$17) -> 0.51403328 | CE16: =BZ17+($CB$17-$BW$17) -> 0.51302537 | CK16: Prior-year quarter margin + (Q1/27 − Q1/26 margin drift). | CS16: FY27 interest expense, net — guidance ($m) | CU16: 103 | CW16: Q1/27 release: ~$103.0m (FY26 $101.2m), incl. bridge-loan fee amortization; excludes UniFirst funding.
B17: Gross margin % | C17: =IF(AND(ISNUMBER(C15),ISNUMBER(C11)),IFERROR(C15/C11,""),"") -> 0.45233489 | D17: =IF(AND(ISNUMBER(D15),ISNUMBER(D11)),IFERROR(D15/D11,""),"") -> 0.44592667 | E17: =IF(AND(ISNUMBER(E15),ISNUMBER(E11)),IFERROR(E15/E11,""),"") -> 0.44202538 | F17: =IF(AND(ISNUMBER(F15),ISNUMBER(F11)),IFERROR(F15/F11,""),"") -> 0.43295046 | G17: =IF(AND(ISNUMBER(G15),ISNUMBER(G11)),IFERROR(G15/G11,""),"") -> 0.43582149 | H17: =IF(AND(ISNUMBER(H15),ISNUMBER(H11)),IFERROR(H15/H11,""),"") -> 0.43153231 | I17: =IF(AND(ISNUMBER(I15),ISNUMBER(I11)),IFERROR(I15/I11,""),"") -> 0.43392745 | J17: =IF(AND(ISNUMBER(J15),ISNUMBER(J11)),IFERROR(J15/J11,""),"") -> 0.43279861 | ... CB17: =IF(AND(ISNUMBER(CB15),ISNUMBER(CB11)),IFERROR(CB15/CB11,""),"") -> 0.50805496 | CC17: =CC16+CC120 -> 0.49727733 | CD17: =CD16+CD120 -> 0.50153069 | CE17: =CE16+CE120 -> 0.50052278 | CF17: =IF(AND(ISNUMBER(CF15),ISNUMBER(CF11)),IFERROR(CF15/CF11,""),"") -> 0.50183963 | CG17: =CHOOSE(MATCH($CK$2,{"Bull","Base","Bear"},0),$CT$94,$CU$94,$CV$94) -> 0.51 | CH17: =CHOOSE(MATCH($CK$2,{"Bull","Base","Bear"},0),$CT$95,$CU$95,$CV$95) -> 0.513 | CI17: =CHOOSE(MATCH($CK$2,{"Bull","Base","Bear"},0),$CT$96,$CU$96,$CV$96) -> 0.516 | CJ17: =CHOOSE(MATCH($CK$2,{"Bull","Base","Bear"},0),$CT$97,$CU$97,$CV$97) -> 0.519 | CK17: Q2–Q4/27E: helper + uniform margin calibration Δ (solved to the FY27 adjusted EPS guidance). FY28E+: scenario lever URFS_GM (level). | CS17: FY27 effective tax rate — guidance | CU17: 0.204 | CW17: Q1/27 release: 20.4% (FY26 20.2%).
B18: Selling & administrative expenses (segment) | D18: 757.058 | E18: 801.691 | F18: 769.275 | G18: 786.145 | H18: 822.23 | I18: 834.21 | J18: 209.788 | K18: 200.886 | L18: 211.531 | M18: 213.044 | N18: 835.249 | O18: 220.742 | P18: 219.134 | Q18: 223.234 | R18: 224.334 | S18: 887.444 | T18: 238.207 | U18: 226.085 | V18: 229.963 | W18: 231.921 | X18: 926.176 | Y18: 254.524 | Z18: 242.318 | AA18: 244.407 | AB18: 256.82 | AC18: 998.069 | AD18: 270.632 | AE18: 269.105 | AF18: 264.973 | AG18: 336.4 | AH18: 1138.345 | AI18: 382.04 | AJ18: 367.19 | AK18: 383.27 | AL18: 368.144 | AM18: 1500.644 | AN18: 392.101 | AO18: 378.921 | AP18: 369.414 | AQ18: 393.275 | AR18: 1533.711 | AS18: 416.84 | AT18: 398.68 | AU18: 391.462 | AV18: 376.809 | AW18: 1583.791 | AX18: 363.971 | AY18: 355.068 | AZ18: 372.612 | BA18: 388.627 | BB18: 1480.278 | BC18: 399.493 | BD18: 380.395 | BE18: 363.248 | BF18: 413.921 | BG18: 1557.057 | BH18: 442.235 | BI18: 434.165 | BJ18: 448.177 | BK18: 461.621 | BL18: 1786.198 | BM18: 472.713 | BN18: 476.7 | BO18: 496.027 | BP18: 495.187 | BQ18: 1940.627 | BR18: 506.238 | BS18: 503.999 | BT18: 522.001 | BU18: 529.558 | BV18: 2061.795 | BW18: 538.576 | BX18: 548.451 | BY18: 573.409 | BZ18: 572.93 | CA18: 2232.515 | CB18: 590.764 | CC18: =CC11*CC19 -> 583.47 | CD18: =CD11*CD19 -> 610.03109 | CE18: =CE11*CE19 -> 609.51874 | CF18: =SUM(CB18,CC18,CD18,CE18) -> 2393.7838 | CG18: =CG11*CG19 -> 2541.4994 | CH18: =CH11*CH19 -> 2685.6254 | CI18: =CI11*CI19 -> 2837.7501 | CJ18: =CJ11*CJ19 -> 2984.2276 | CS18: FY27 guidance diluted shares (m; ex-future buybacks) | CU18: 404.29 | CW18: Q1/27 weighted diluted shares 404.3m (guidance excludes future buybacks).
B19: S&A % of revenues | C19: =IF(AND(ISNUMBER(C18),ISNUMBER(C11)),IFERROR(C18/C11,""),"") | D19: =IF(AND(ISNUMBER(D18),ISNUMBER(D11)),IFERROR(D18/D11,""),"") -> 0.27684121 | E19: =IF(AND(ISNUMBER(E18),ISNUMBER(E11)),IFERROR(E18/E11,""),"") -> 0.28282652 | F19: =IF(AND(ISNUMBER(F18),ISNUMBER(F11)),IFERROR(F18/F11,""),"") -> 0.27922715 | G19: =IF(AND(ISNUMBER(G18),ISNUMBER(G11)),IFERROR(G18/G11,""),"") -> 0.30596955 | H19: =IF(AND(ISNUMBER(H18),ISNUMBER(H11)),IFERROR(H18/H11,""),"") -> 0.30540649 | I19: =IF(AND(ISNUMBER(I18),ISNUMBER(I11)),IFERROR(I18/I11,""),"") -> 0.28644754 | J19: =IF(AND(ISNUMBER(J18),ISNUMBER(J11)),IFERROR(J18/J11,""),"") -> 0.27792269 | ... CB19: =IF(AND(ISNUMBER(CB18),ISNUMBER(CB11)),IFERROR(CB18/CB11,""),"") -> 0.25744312 | CC19: =BX19+($CB$19-$BW$19) -> 0.25433702 | CD19: =BY19+($CB$19-$BW$19) -> 0.26322195 | CE19: =BZ19+($CB$19-$BW$19) -> 0.2605773 | CF19: =IF(AND(ISNUMBER(CF18),ISNUMBER(CF11)),IFERROR(CF18/CF11,""),"") -> 0.25891392 | CG19: =$CF$19+(CG124-$CF$123) -> 0.25690745 | CH19: =$CF$19+(CH124-$CF$123) -> 0.25490745 | CI19: =$CF$19+(CI124-$CF$123) -> 0.25290745 | CJ19: =$CF$19+(CJ124-$CF$123) -> 0.25090745 | CK19: Q2–Q4/27E: prior-year quarter + Q1 drift. FY28E+: FY27E segment ratio + Δ of the consolidated legacy S&A lever SA_pct vs FY27E. | CS19: Effective tax rate FY28E+ | CU19: 0.21 | CW19: Higher UniFirst mix (US-heavy, fewer stock-comp benefits).
B20: Segment operating income (before special items) | C20: =IF(AND(ISNUMBER(C15),ISNUMBER(C18)),C15-C18,"") | D20: =IF(AND(ISNUMBER(D15),ISNUMBER(D18)),D15-D18,"") -> 462.386 | E20: =IF(AND(ISNUMBER(E15),ISNUMBER(E18)),E15-E18,"") -> 451.26 | F20: =IF(AND(ISNUMBER(F15),ISNUMBER(F18)),F15-F18,"") -> 423.51 | G20: =IF(AND(ISNUMBER(G15),ISNUMBER(G18)),G15-G18,"") -> 333.636 | H20: =IF(AND(ISNUMBER(H15),ISNUMBER(H18)),H15-H18,"") -> 339.562 | I20: =IF(AND(ISNUMBER(I15),ISNUMBER(I18)),I15-I18,"") -> 429.5 | J20: =IF(AND(ISNUMBER(J15),ISNUMBER(J18)),J15-J18,"") -> 116.907 | ... CB20: =IF(AND(ISNUMBER(CB15),ISNUMBER(CB18)),CB15-CB18,"") -> 575.088 | CC20: =CC15-CC18 -> 557.32502 | CD20: =CD15-CD18 -> 552.29339 | CE20: =CE15-CE18 -> 561.25865 | CF20: =CF15-CF18 -> 2245.9651 | CG20: =CG15-CG18 -> 2503.7598 | CH20: =CH15-CH18 -> 2719.1826 | CI20: =CI15-CI18 -> 2952.032 | CJ20: =CJ15-CJ18 -> 3188.6226 | CM20: =IFERROR((CJ20/CA20)^(1/5)-1,"n/m") -> 0.08951402 | CN20: =IFERROR((CA20/BB20)^(1/5)-1,"n/m") -> 0.11122254 | CO20: =IFERROR((CA20/AC20)^(1/10)-1,"n/m") -> 0.11929955 | CP20: =IFERROR((CA20/C20)^(1/20)-1,"n/m") -> n/m | CS20: UniFirst included (1 = yes, 0 = no) | CU20: 1 | CW20: Default ON per your instruction; set 0 for standalone Cintas (matches company guidance basis).
B21: Segment operating margin % | C21: =IF(AND(ISNUMBER(C20),ISNUMBER(C11)),IFERROR(C20/C11,""),"") | D21: =IF(AND(ISNUMBER(D20),ISNUMBER(D11)),IFERROR(D20/D11,""),"") -> 0.16908546 | E21: =IF(AND(ISNUMBER(E20),ISNUMBER(E11)),IFERROR(E20/E11,""),"") -> 0.15919886 | F21: =IF(AND(ISNUMBER(F20),ISNUMBER(F11)),IFERROR(F20/F11,""),"") -> 0.1537233 | G21: =IF(AND(ISNUMBER(G20),ISNUMBER(G11)),IFERROR(G20/G11,""),"") -> 0.12985194 | H21: =IF(AND(ISNUMBER(H20),ISNUMBER(H11)),IFERROR(H20/H11,""),"") -> 0.12612582 | I21: =IF(AND(ISNUMBER(I20),ISNUMBER(I11)),IFERROR(I20/I11,""),"") -> 0.14747991 | J21: =IF(AND(ISNUMBER(J20),ISNUMBER(J11)),IFERROR(J20/J11,""),"") -> 0.15487591 | ... CJ21: =IF(AND(ISNUMBER(CJ20),ISNUMBER(CJ11)),IFERROR(CJ20/CJ11,""),"") -> 0.26809255 | CS21: UniFirst assumed closing date | CU21: 46387 | CW21: "Prior to the end of calendar 2026" (Q1/27 release); FTC Second Request 11-Jun-26.
B22: Memo: segment operating income / income before taxes as reported (incl. segment special items) | D22: 462.386 | E22: 451.26 | F22: 370.524 | G22: 336.516 | H22: 339.562 | I22: 429.5 | J22: 116.907 | K22: 116.051 | L22: 102.547 | M22: 117.536 | N22: 453.041 | O22: 117.393 | P22: 126.07 | Q22: 128.382 | R22: 135.214 | S22: 507.059 | T22: 144.816 | U22: 159.567 | V22: 152.165 | W22: 149.487 | X22: 606.035 | Y22: 165.381 | Z22: 169.295 | AA22: 167.502 | AB22: 170.761 | AC22: 672.939 | AD22: 185.245 | AE22: 177.361 | AF22: 172.543 | AG22: 143.48 | AH22: 677.147 | AI22: 218.91 | AJ22: 203.814 | AK22: 173.287 | AL22: 221.613 | AM22: 817.624 | AN22: 231.534 | AO22: 242.891 | AP22: 239.138 | AQ22: 263.147 | AR22: 976.71 | AS22: 269.011 | AT22: 286.36 | AU22: 271.629 | AV22: 177.559 | AW22: 1004.558 | AX22: 315.028 | AY22: 315.609 | AZ22: 283.403 | BA22: 311.8 | BB22: 1225.84 | BC22: 329.382 | BD22: 337.615 | BE22: 355.99 | BF22: 330.503 | BG22: 1353.49 | BH22: 364.771 | BI22: 369.095 | BJ22: 359.995 | BK22: 384.896 | BL22: 1478.757 | BM22: 406.529 | BN22: 399.611 | BO22: 420.407 | BP22: 432.954 | BQ22: 1659.501 | BR22: 446.438 | BS22: 472.359 | BT22: 489.483 | BU22: 465.109 | BV22: 1873.39 | BW22: 499.937 | BX22: 525.731 | BY22: 521.025 | BZ22: 529.468 | CA22: 2077.012 | CB22: 575.088 | CS22: CTAS shares issued to UNF holders (m) | CU22: 14.071 | CW22: 424B3 pro forma: 18.227m UNF shares × 0.7720.
CS23: UniFirst acquisition debt ($m) | CU23: 2800 | CW23: 424B3 pro forma permanent financing $2.8bn.
B24: First Aid & Safety Services (FA&S) — reportable segment from FY2016 (FY2015 recast); first aid cabinets, safety products & training, eyewash, AEDs | CK24: FIRST AID & SAFETY — modelling logic | CS24: Interest rate on acquisition debt | CU24: 0.05 | CW24: 424B3 assumption (±1/8% = $3.5m p.a.).
B25: Revenues | T25: 79.924 | U25: 82.271 | V25: 79.471 | W25: 84.927 | X25: 326.593 | Y25: 99.488 | Z25: 120.438 | AA25: 119.064 | AB25: 122.793 | AC25: 461.783 | AD25: 124.839 | AE25: 124.797 | AF25: 124.239 | AG25: 134.358 | AH25: 508.233 | AI25: 140.582 | AJ25: 139.09 | AK25: 137.327 | AL25: 147.707 | AM25: 564.706 | AN25: 153.417 | AO25: 153.348 | AP25: 149.17 | AQ25: 163.535 | AR25: 619.47 | AS25: 172.09 | AT25: 169.667 | AU25: 170.541 | AV25: 196.27 | AW25: 708.569 | AX25: 204.481 | AY25: 194.419 | AZ25: 198.474 | BA25: 186.917 | BB25: 784.291 | BC25: 199.116 | BD25: 202.16 | BE25: 212.958 | BF25: 218.224 | BG25: 832.458 | BH25: 234.161 | BI25: 235.974 | BJ25: 231.605 | BK25: 249.756 | BL25: 951.496 | BM25: 260.693 | BN25: 266.401 | BO25: 262.602 | BP25: 277.638 | BQ25: 1067.334 | BR25: 292.567 | BS25: 299.367 | BT25: 301.759 | BU25: 324.397 | BV25: 1218.09 | BW25: 334.657 | BX25: 342.24 | BY25: 346.823 | BZ25: 368.133 | CA25: 1391.853 | CB25: 388.517 | CC25: =BX25*(1+CC26) -> 386.00652 | CD25: =BY25*(1+CD26) -> 391.1756 | CE25: =BZ25*(1+CE26) -> 415.21078 | CF25: =SUM(CB25,CC25,CD25,CE25) -> 1580.9099 | CG25: =CF25*(1+CG26) -> 1770.6191 | CH25: =CG25*(1+CH26) -> 1965.3872 | CI25: =CH25*(1+CI26) -> 2161.9259 | CJ25: =CI25*(1+CJ26) -> 2356.4992 | CK25: Q2–Q4/27E: prior-year quarter × (1 + Q1/27 y/y growth ex-workday effect + revenue-outlook calibration Δ). FY28E+: prior year × (1 + scenario organic growth FAS_org); bolt-on M&A modelled separately (Future acquisitions block). | CM25: =IFERROR((CJ25/CA25)^(1/5)-1,"n/m") -> 0.11105303 | CN25: =IFERROR((CA25/BB25)^(1/5)-1,"n/m") -> 0.12156185 | CO25: =IFERROR((CA25/AC25)^(1/10)-1,"n/m") -> 0.11664607 | CP25: =IFERROR((CA25/C25)^(1/20)-1,"n/m") -> n/m | CS25: Run-rate cost synergies ($m) | CU25: 375 | CW25: Deal 8-K: ~$375m within four years.
B26: Revenues y/y % | D26: =IF(AND(ISNUMBER(D25),ISNUMBER(C25)),IFERROR(D25/C25-1,""),"") | E26: =IF(AND(ISNUMBER(E25),ISNUMBER(D25)),IFERROR(E25/D25-1,""),"") | F26: =IF(AND(ISNUMBER(F25),ISNUMBER(E25)),IFERROR(F25/E25-1,""),"") | G26: =IF(AND(ISNUMBER(G25),ISNUMBER(F25)),IFERROR(G25/F25-1,""),"") | H26: =IF(AND(ISNUMBER(H25),ISNUMBER(G25)),IFERROR(H25/G25-1,""),"") | I26: =IF(AND(ISNUMBER(I25),ISNUMBER(H25)),IFERROR(I25/H25-1,""),"") | N26: =IF(AND(ISNUMBER(N25),ISNUMBER(I25)),IFERROR(N25/I25-1,""),"") | O26: =IF(AND(ISNUMBER(O25),ISNUMBER(J25)),IFERROR(O25/J25-1,""),"") | P26: =IF(AND(ISNUMBER(P25),ISNUMBER(K25)),IFERROR(P25/K25-1,""),"") | Q26: =IF(AND(ISNUMBER(Q25),ISNUMBER(L25)),IFERROR(Q25/L25-1,""),"") | R26: =IF(AND(ISNUMBER(R25),ISNUMBER(M25)),IFERROR(R25/M25-1,""),"") | S26: =IF(AND(ISNUMBER(S25),ISNUMBER(N25)),IFERROR(S25/N25-1,""),"") | T26: =IF(AND(ISNUMBER(T25),ISNUMBER(O25)),IFERROR(T25/O25-1,""),"") | U26: =IF(AND(ISNUMBER(U25),ISNUMBER(P25)),IFERROR(U25/P25-1,""),"") | ... CB26: =IF(AND(ISNUMBER(CB25),ISNUMBER(BW25)),IFERROR(CB25/BW25-1,""),"") -> 0.1609409 | CC26: =$CB$26-$CB$109+CC114 -> 0.12788253 | CD26: =$CB$26-$CB$109+CD114 -> 0.12788253 | CE26: =$CB$26-$CB$109+CE114 -> 0.12788253 | CF26: =IFERROR(CF25/CA25-1,"") -> 0.13583108 | CG26: =CHOOSE(MATCH($CK$2,{"Bull","Base","Bear"},0),$CT$82,$CU$82,$CV$82) -> 0.12 | CH26: =CHOOSE(MATCH($CK$2,{"Bull","Base","Bear"},0),$CT$83,$CU$83,$CV$83) -> 0.11 | CI26: =CHOOSE(MATCH($CK$2,{"Bull","Base","Bear"},0),$CT$84,$CU$84,$CV$84) -> 0.1 | CJ26: =CHOOSE(MATCH($CK$2,{"Bull","Base","Bear"},0),$CT$85,$CU$85,$CV$85) -> 0.09 | CK26: Q2–Q4/27E: Q1/27 y/y less the Q1 extra-workday effect (row "Workday effect") + calibration Δ (Group block). FY28E+: scenario lever. | CS26: Share of synergies in cost of sales | CU26: 0.65 | CW26: Material, production & delivery (vs G&A).
B27: Organic growth % (company-disclosed, segment) | AG27: 0.092 | AI27: 0.119 | AJ27: 0.108 | AK27: 0.1 | AL27: 0.094 | AN27: 0.09 | AO27: 0.102 | AP27: 0.086 | AQ27: 0.107 | AS27: 0.138 | AT27: 0.106 | AU27: 0.125 | AV27: 0.219 | AX27: 0.171 | AY27: 0.145 | AZ27: 0.177 | BA27: -0.068 | BD27: 0.032 | BE27: 0.062 | BH27: 0.158 | BI27: 0.151 | BJ27: 0.078 | BL27: 0.131 | BM27: 0.11 | BN27: 0.127 | BO27: 0.115 | BQ27: 0.116 | BR27: 0.14 | BS27: 0.123 | BT27: 0.15 | BV27: 0.15 | BW27: 0.141 | BX27: 0.141 | BY27: 0.146 | CA27: 0.14 | CC27: =CC26 -> 0.12788253 | CD27: =CD26 -> 0.12788253 | CE27: =CE26 -> 0.12788253 | CF27: =CF26 -> 0.13583108 | CG27: =CG26 -> 0.12 | CH27: =CH26 -> 0.11 | CI27: =CI26 -> 0.1 | CJ27: =CJ26 -> 0.09 | CK27: Segment organic growth as disclosed in releases (FY2016–21) and 10-Q MD&A (FY2022+); blank where not disclosed. Forecast: no acquisition/FX/workday effect assumed inside segments. | CS27: Net PP&E step-up depreciation ($m p.a.) | CU27: 0.405 | CW27: $27.936m new − $27.531m eliminated (424B3).
B28: Acquisitions, FX & workday effects % (derived = y/y − organic) | C28: =IF(AND(ISNUMBER(C26),ISNUMBER(C27)),C26-C27,"") | D28: =IF(AND(ISNUMBER(D26),ISNUMBER(D27)),D26-D27,"") | E28: =IF(AND(ISNUMBER(E26),ISNUMBER(E27)),E26-E27,"") | F28: =IF(AND(ISNUMBER(F26),ISNUMBER(F27)),F26-F27,"") | G28: =IF(AND(ISNUMBER(G26),ISNUMBER(G27)),G26-G27,"") | H28: =IF(AND(ISNUMBER(H26),ISNUMBER(H27)),H26-H27,"") | I28: =IF(AND(ISNUMBER(I26),ISNUMBER(I27)),I26-I27,"") | J28: =IF(AND(ISNUMBER(J26),ISNUMBER(J27)),J26-J27,"") | ... CB28: =IF(AND(ISNUMBER(CB26),ISNUMBER(CB27)),CB26-CB27,"") | CS28: PPA intangible amortization yrs 1–3 ($m p.a.) | CU28: 98.257 | CW28: Customer relationships $1,241m/15y + trade names $50m/3y.
B29: Gross margin (GAAP) | T29: 36.655 | U29: 38.396 | V29: 37.584 | W29: 39.704 | X29: 152.339 | Y29: 42.111 | Z29: 52.027 | AA29: 50.241 | AB29: 52.631 | AC29: 197.01 | AD29: 57.126 | AE29: 57.545 | AF29: 55.681 | AG29: 59.814 | AH29: 230.166 | AI29: 66.775 | AJ29: 65.26 | AK29: 64.348 | AL29: 69.402 | AM29: 265.785 | AN29: 73.485 | AO29: 73.67 | AP29: 71.89 | AQ29: 78.029 | AR29: 297.074 | AS29: 84.287 | AT29: 82.074 | AU29: 81.91 | AV29: 90.389 | AW29: 338.661 | AX29: 82.104 | AY29: 83.597 | AZ29: 86.341 | BA29: 80.294 | BB29: 332.336 | BC29: 89.275 | BD29: 88.034 | BE29: 94.204 | BF29: 100.68 | BG29: 372.193 | BH29: 116.137 | BI29: 119.153 | BJ29: 119.408 | BK29: 127.39 | BL29: 482.088 | BM29: 145.776 | BN29: 145.316 | BO29: 147.732 | BP29: 153.832 | BQ29: 592.656 | BR29: 168.803 | BS29: 171.485 | BT29: 172.133 | BU29: 184.189 | BV29: 696.61 | BW29: 190.168 | BX29: 197.602 | BY29: 201.647 | BZ29: 213.066 | CA29: 802.483 | CB29: 223.817 | CC29: =CC25*CC31 -> 221.06929 | CD29: =CD25*CD31 -> 225.60744 | CE29: =CE25*CE31 -> 238.37449 | CF29: =SUM(CB29,CC29,CD29,CE29) -> 908.86821 | CG29: =CG25*CG31 -> 1030.5003 | CH29: =CH25*CH31 -> 1149.7515 | CI29: =CI25*CI31 -> 1271.2124 | CJ29: =CJ25*CJ31 -> 1390.3345 | CM29: =IFERROR((CJ29/CA29)^(1/5)-1,"n/m") -> 0.11618632 | CN29: =IFERROR((CA29/BB29)^(1/5)-1,"n/m") -> 0.19281115 | CO29: =IFERROR((CA29/AC29)^(1/10)-1,"n/m") -> 0.1507865 | CP29: =IFERROR((CA29/C29)^(1/20)-1,"n/m") -> n/m | CS29: PPA intangible amortization yr 4+ ($m p.a.) | CU29: 82.733333 | CW29: Customer relationships only.
B30: Gross margin % before outlook calibration (Q2–Q4/27E helper) | CC30: =BX31+($CB$31-$BW$31) -> 0.58521128 | CD30: =BY31+($CB$31-$BW$31) -> 0.58924468 | CE30: =BZ31+($CB$31-$BW$31) -> 0.58660736 | CK30: Prior-year quarter margin + (Q1/27 − Q1/26 margin drift). | CS30: UniFirst standalone gross margin (Cintas presentation) | CU30: 0.318 | CW30: LTM cost of revenues ex-D&A 63.3% + ~85% of D&A in cost of sales.
B31: Gross margin % | C31: =IF(AND(ISNUMBER(C29),ISNUMBER(C25)),IFERROR(C29/C25,""),"") | D31: =IF(AND(ISNUMBER(D29),ISNUMBER(D25)),IFERROR(D29/D25,""),"") | E31: =IF(AND(ISNUMBER(E29),ISNUMBER(E25)),IFERROR(E29/E25,""),"") | F31: =IF(AND(ISNUMBER(F29),ISNUMBER(F25)),IFERROR(F29/F25,""),"") | G31: =IF(AND(ISNUMBER(G29),ISNUMBER(G25)),IFERROR(G29/G25,""),"") | H31: =IF(AND(ISNUMBER(H29),ISNUMBER(H25)),IFERROR(H29/H25,""),"") | I31: =IF(AND(ISNUMBER(I29),ISNUMBER(I25)),IFERROR(I29/I25,""),"") | J31: =IF(AND(ISNUMBER(J29),ISNUMBER(J25)),IFERROR(J29/J25,""),"") | ... CB31: =IF(AND(ISNUMBER(CB29),ISNUMBER(CB25)),IFERROR(CB29/CB25,""),"") -> 0.57608033 | CC31: =CC30+CC120 -> 0.5727087 | CD31: =CD30+CD120 -> 0.57674209 | CE31: =CE30+CE120 -> 0.57410477 | CF31: =IF(AND(ISNUMBER(CF29),ISNUMBER(CF25)),IFERROR(CF29/CF25,""),"") -> 0.57490197 | CG31: =CHOOSE(MATCH($CK$2,{"Bull","Base","Bear"},0),$CT$100,$CU$100,$CV$100) -> 0.582 | CH31: =CHOOSE(MATCH($CK$2,{"Bull","Base","Bear"},0),$CT$101,$CU$101,$CV$101) -> 0.585 | CI31: =CHOOSE(MATCH($CK$2,{"Bull","Base","Bear"},0),$CT$102,$CU$102,$CV$102) -> 0.588 | CJ31: =CHOOSE(MATCH($CK$2,{"Bull","Base","Bear"},0),$CT$103,$CU$103,$CV$103) -> 0.59 | CK31: Q2–Q4/27E: helper + uniform margin calibration Δ (solved to the FY27 adjusted EPS guidance). FY28E+: scenario lever FAS_GM (level). | CS31: UniFirst standalone S&A % of revenue | CU31: 0.25 | CW31: LTM SG&A ex merger costs 24.3% + non-production D&A.
B32: Selling & administrative expenses (segment) | T32: 27.508 | U32: 26.619 | V32: 26.286 | W32: 26.813 | X32: 107.226 | Y32: 33.519 | Z32: 37.18 | AA32: 37.607 | AB32: 39.197 | AC32: 147.503 | AD32: 45.615 | AE32: 42.766 | AF32: 43.446 | AG32: 45.551 | AH32: 177.378 | AI32: 47.364 | AJ32: 47.285 | AK32: 47.643 | AL32: 48.275 | AM32: 190.567 | AN32: 51.502 | AO32: 52.342 | AP32: 50.268 | AQ32: 52.878 | AR32: 206.99 | AS32: 59.518 | AT32: 57.434 | AU32: 57.218 | AV32: 57.599 | AW32: 231.769 | AX32: 63.577 | AY32: 62.091 | AZ32: 60.521 | BA32: 64.964 | BB32: 251.153 | BC32: 63.547 | BD32: 65.957 | BE32: 67.9 | BF32: 68.026 | BG32: 265.43 | BH32: 75.291 | BI32: 73.658 | BJ32: 72.137 | BK32: 80.312 | BL32: 301.398 | BM32: 86.196 | BN32: 86.785 | BO32: 90.015 | BP32: 90.507 | BQ32: 353.503 | BR32: 97.515 | BS32: 96.262 | BT32: 100.6 | BU32: 107.505 | BV32: 401.882 | BW32: 109.841 | BX32: 110.598 | BY32: 114.306 | BZ32: 114.475 | CA32: 449.084 | CB32: 124.275 | CC32: =CC25*CC33 -> 121.5186 | CD32: =CD25*CD33 -> 125.65763 | CE32: =CE25*CE33 -> 125.64756 | CF32: =SUM(CB32,CC32,CD32,CE32) -> 497.0988 | CG32: =CG25*CG33 -> 553.19796 | CH32: =CH25*CH33 -> 610.11896 | CI32: =CI25*CI33 -> 666.807 | CJ32: =CJ25*CJ33 -> 722.10664 | CS32: UniFirst standalone D&A % of revenue | CU32: 0.05 | CW32: LTM D&A 5.7% less acquired-intangible amortization (~0.7%).
B33: S&A % of revenues | C33: =IF(AND(ISNUMBER(C32),ISNUMBER(C25)),IFERROR(C32/C25,""),"") | D33: =IF(AND(ISNUMBER(D32),ISNUMBER(D25)),IFERROR(D32/D25,""),"") | E33: =IF(AND(ISNUMBER(E32),ISNUMBER(E25)),IFERROR(E32/E25,""),"") | F33: =IF(AND(ISNUMBER(F32),ISNUMBER(F25)),IFERROR(F32/F25,""),"") | G33: =IF(AND(ISNUMBER(G32),ISNUMBER(G25)),IFERROR(G32/G25,""),"") | H33: =IF(AND(ISNUMBER(H32),ISNUMBER(H25)),IFERROR(H32/H25,""),"") | I33: =IF(AND(ISNUMBER(I32),ISNUMBER(I25)),IFERROR(I32/I25,""),"") | J33: =IF(AND(ISNUMBER(J32),ISNUMBER(J25)),IFERROR(J32/J25,""),"") | ... CB33: =IF(AND(ISNUMBER(CB32),ISNUMBER(CB25)),IFERROR(CB32/CB25,""),"") -> 0.31987017 | CC33: =BX33+($CB$33-$BW$33) -> 0.31480972 | CD33: =BY33+($CB$33-$BW$33) -> 0.32123075 | CE33: =BZ33+($CB$33-$BW$33) -> 0.30261152 | CF33: =IF(AND(ISNUMBER(CF32),ISNUMBER(CF25)),IFERROR(CF32/CF25,""),"") -> 0.31443841 | CG33: =$CF$33+(CG124-$CF$123) -> 0.31243194 | CH33: =$CF$33+(CH124-$CF$123) -> 0.31043194 | CI33: =$CF$33+(CI124-$CF$123) -> 0.30843194 | CJ33: =$CF$33+(CJ124-$CF$123) -> 0.30643194 | CK33: Q2–Q4/27E: prior-year quarter + Q1 drift. FY28E+: FY27E segment ratio + Δ of the consolidated legacy S&A lever SA_pct vs FY27E. | CS33: UniFirst revenue mapped to UR&FS line | CU33: 0.95 | CW33: U&F Service Solutions + Specialty Garments ~95% of UNF revenue.
B34: Segment operating income (before special items) | C34: =IF(AND(ISNUMBER(C29),ISNUMBER(C32)),C29-C32,"") | D34: =IF(AND(ISNUMBER(D29),ISNUMBER(D32)),D29-D32,"") | E34: =IF(AND(ISNUMBER(E29),ISNUMBER(E32)),E29-E32,"") | F34: =IF(AND(ISNUMBER(F29),ISNUMBER(F32)),F29-F32,"") | G34: =IF(AND(ISNUMBER(G29),ISNUMBER(G32)),G29-G32,"") | H34: =IF(AND(ISNUMBER(H29),ISNUMBER(H32)),H29-H32,"") | I34: =IF(AND(ISNUMBER(I29),ISNUMBER(I32)),I29-I32,"") | J34: =IF(AND(ISNUMBER(J29),ISNUMBER(J32)),J29-J32,"") | ... CB34: =IF(AND(ISNUMBER(CB29),ISNUMBER(CB32)),CB29-CB32,"") -> 99.542 | CC34: =CC29-CC32 -> 99.550685 | CD34: =CD29-CD32 -> 99.949803 | CE34: =CE29-CE32 -> 112.72692 | CF34: =CF29-CF32 -> 411.76941 | CG34: =CG29-CG32 -> 477.30235 | CH34: =CH29-CH32 -> 539.63254 | CI34: =CI29-CI32 -> 604.40543 | CJ34: =CJ29-CJ32 -> 668.22791 | CM34: =IFERROR((CJ34/CA34)^(1/5)-1,"n/m") -> 0.13587845 | CN34: =IFERROR((CA34/BB34)^(1/5)-1,"n/m") -> 0.34202326 | CO34: =IFERROR((CA34/AC34)^(1/10)-1,"n/m") -> 0.21719419 | CP34: =IFERROR((CA34/C34)^(1/20)-1,"n/m") -> n/m | CS34: Pre-close transaction costs per quarter ($m) | CU34: 15 | CW34: Q1/27 $14.4m; Q4/26 $14.0m.
B35: Segment operating margin % | C35: =IF(AND(ISNUMBER(C34),ISNUMBER(C25)),IFERROR(C34/C25,""),"") | D35: =IF(AND(ISNUMBER(D34),ISNUMBER(D25)),IFERROR(D34/D25,""),"") | E35: =IF(AND(ISNUMBER(E34),ISNUMBER(E25)),IFERROR(E34/E25,""),"") | F35: =IF(AND(ISNUMBER(F34),ISNUMBER(F25)),IFERROR(F34/F25,""),"") | G35: =IF(AND(ISNUMBER(G34),ISNUMBER(G25)),IFERROR(G34/G25,""),"") | H35: =IF(AND(ISNUMBER(H34),ISNUMBER(H25)),IFERROR(H34/H25,""),"") | I35: =IF(AND(ISNUMBER(I34),ISNUMBER(I25)),IFERROR(I34/I25,""),"") | J35: =IF(AND(ISNUMBER(J34),ISNUMBER(J25)),IFERROR(J34/J25,""),"") | ... CJ35: =IF(AND(ISNUMBER(CJ34),ISNUMBER(CJ25)),IFERROR(CJ34/CJ25,""),"") -> 0.28356806 | CS35: Costs at closing ($m): transaction + retention | CU35: 72.7 | CW35: Cintas transaction costs $34.0m + retention bonuses $38.7m (424B3).
B36: Memo: segment operating income / income before taxes as reported (incl. segment special items) | T36: 9.147 | U36: 11.777 | V36: 11.298 | W36: 12.891 | X36: 45.113 | Y36: 8.592 | Z36: 14.847 | AA36: 12.634 | AB36: 13.434 | AC36: 49.507 | AD36: 11.511 | AE36: 14.779 | AF36: 12.235 | AG36: 14.263 | AH36: 52.788 | AI36: 19.411 | AJ36: 17.975 | AK36: 16.705 | AL36: 21.127 | AM36: 75.218 | AN36: 21.983 | AO36: 21.328 | AP36: 21.622 | AQ36: 25.151 | AR36: 90.084 | AS36: 24.769 | AT36: 24.64 | AU36: 24.692 | AV36: 32.79 | AW36: 106.892 | AX36: 18.527 | AY36: 21.506 | AZ36: 25.82 | BA36: 15.33 | BB36: 81.183 | BC36: 25.728 | BD36: 22.077 | BE36: 26.304 | BF36: 32.654 | BG36: 106.763 | BH36: 40.846 | BI36: 45.495 | BJ36: 47.271 | BK36: 47.078 | BL36: 180.69 | BM36: 59.58 | BN36: 58.531 | BO36: 57.717 | BP36: 63.325 | BQ36: 239.153 | BR36: 71.288 | BS36: 75.223 | BT36: 71.533 | BU36: 76.684 | BV36: 294.728 | BW36: 80.327 | BX36: 87.004 | BY36: 87.341 | BZ36: 98.591 | CA36: 353.399 | CB36: 99.542 | CS36: Integration costs to achieve synergies ($m, total) | CU36: 350 | CW36: Not disclosed; "proportional to G&K" (~$138m for a $2.2bn deal) → ~$350m.
CS37: … phasing FY27E | CU37: 0.15
B38: All Other — Fire Protection Services + Uniform Direct Sale (from FY2016; FY2015 recast) | CK38: ALL OTHER (FIRE + UNIFORM DIRECT SALE) — modelling logic | CS38: … phasing FY28E | CU38: 0.45
B39: Revenues | T39: 148.455 | U39: 149.633 | V39: 145.975 | W39: 166.387 | X39: 610.45 | Y39: 160.994 | Z39: 160.938 | AA39: 160.454 | AB39: 183.488 | AC39: 665.874 | AD39: 169.695 | AE39: 166.561 | AF39: 163.498 | AG39: 175.914 | AH39: 612.658 | AI39: 159.137 | AJ39: 159.313 | AK39: 167.295 | AL39: 179.057 | AM39: 664.802 | AN39: 169.62 | AO39: 174.142 | AP39: 174.838 | AQ39: 201.803 | AR39: 720.403 | AS39: 184.522 | AT39: 204.105 | AU39: 192.086 | AV39: 152.344 | AW39: 733.057 | AX39: 147.683 | AY39: 152.141 | AZ39: 160.717 | BA39: 181.876 | BB39: 642.417 | BC39: 189.658 | BD39: 184.85 | BE39: 194.264 | BF39: 226.249 | BG39: 795.021 | BH39: 234.521 | BI39: 228.897 | BJ39: 242.216 | BK39: 261.509 | BL39: 967.143 | BM39: 254.812 | BN39: 260.234 | BO39: 266.929 | BP39: 282.107 | BQ39: 1064.082 | BR39: 275.181 | BS39: 272.006 | BT39: 286.256 | BU39: 312.575 | BV39: 1146.018 | BW39: 292.399 | BX39: 302.352 | BY39: 317.168 | BZ39: 339.365 | CA39: 1251.284 | CB39: 330.728 | CC39: =BX39*(1+CC40) -> 331.99042 | CD39: =BY39*(1+CD40) -> 348.25878 | CE39: =BZ39*(1+CE40) -> 372.63166 | CF39: =SUM(CB39,CC39,CD39,CE39) -> 1383.6089 | CG39: =CF39*(1+CG40) -> 1508.1337 | CH39: =CG39*(1+CH40) -> 1628.7843 | CI39: =CH39*(1+CI40) -> 1759.0871 | CJ39: =CI39*(1+CJ40) -> 1882.2232 | CK39: Q2–Q4/27E: prior-year quarter × (1 + Q1/27 y/y growth ex-workday effect + revenue-outlook calibration Δ). FY28E+: prior year × (1 + scenario organic growth OTH_org); bolt-on M&A modelled separately (Future acquisitions block). | CM39: =IFERROR((CJ39/CA39)^(1/5)-1,"n/m") -> 0.085083216 | CN39: =IFERROR((CA39/BB39)^(1/5)-1,"n/m") -> 0.14263566 | CO39: =IFERROR((CA39/AC39)^(1/10)-1,"n/m") -> 0.065114712 | CP39: =IFERROR((CA39/C39)^(1/20)-1,"n/m") -> n/m | CS39: … phasing FY29E | CU39: 0.3
B40: Revenues y/y % | D40: =IF(AND(ISNUMBER(D39),ISNUMBER(C39)),IFERROR(D39/C39-1,""),"") | E40: =IF(AND(ISNUMBER(E39),ISNUMBER(D39)),IFERROR(E39/D39-1,""),"") | F40: =IF(AND(ISNUMBER(F39),ISNUMBER(E39)),IFERROR(F39/E39-1,""),"") | G40: =IF(AND(ISNUMBER(G39),ISNUMBER(F39)),IFERROR(G39/F39-1,""),"") | H40: =IF(AND(ISNUMBER(H39),ISNUMBER(G39)),IFERROR(H39/G39-1,""),"") | I40: =IF(AND(ISNUMBER(I39),ISNUMBER(H39)),IFERROR(I39/H39-1,""),"") | N40: =IF(AND(ISNUMBER(N39),ISNUMBER(I39)),IFERROR(N39/I39-1,""),"") | O40: =IF(AND(ISNUMBER(O39),ISNUMBER(J39)),IFERROR(O39/J39-1,""),"") | P40: =IF(AND(ISNUMBER(P39),ISNUMBER(K39)),IFERROR(P39/K39-1,""),"") | Q40: =IF(AND(ISNUMBER(Q39),ISNUMBER(L39)),IFERROR(Q39/L39-1,""),"") | R40: =IF(AND(ISNUMBER(R39),ISNUMBER(M39)),IFERROR(R39/M39-1,""),"") | S40: =IF(AND(ISNUMBER(S39),ISNUMBER(N39)),IFERROR(S39/N39-1,""),"") | T40: =IF(AND(ISNUMBER(T39),ISNUMBER(O39)),IFERROR(T39/O39-1,""),"") | U40: =IF(AND(ISNUMBER(U39),ISNUMBER(P39)),IFERROR(U39/P39-1,""),"") | ... CB40: =IF(AND(ISNUMBER(CB39),ISNUMBER(BW39)),IFERROR(CB39/BW39-1,""),"") -> 0.13108458 | CC40: =$CB$40-$CB$109+CC114 -> 0.098026204 | CD40: =$CB$40-$CB$109+CD114 -> 0.098026204 | CE40: =$CB$40-$CB$109+CE114 -> 0.098026204 | CF40: =IFERROR(CF39/CA39-1,"") -> 0.10575126 | CG40: =CHOOSE(MATCH($CK$2,{"Bull","Base","Bear"},0),$CT$88,$CU$88,$CV$88) -> 0.09 | CH40: =CHOOSE(MATCH($CK$2,{"Bull","Base","Bear"},0),$CT$89,$CU$89,$CV$89) -> 0.08 | CI40: =CHOOSE(MATCH($CK$2,{"Bull","Base","Bear"},0),$CT$90,$CU$90,$CV$90) -> 0.08 | CJ40: =CHOOSE(MATCH($CK$2,{"Bull","Base","Bear"},0),$CT$91,$CU$91,$CV$91) -> 0.07 | CK40: Q2–Q4/27E: Q1/27 y/y less the Q1 extra-workday effect (row "Workday effect") + calibration Δ (Group block). FY28E+: scenario lever. | CS40: … phasing FY30E | CU40: 0.1
B41: Organic growth % (company-disclosed, segment) | CC41: =CC40 -> 0.098026204 | CD41: =CD40 -> 0.098026204 | CE41: =CE40 -> 0.098026204 | CF41: =CF40 -> 0.10575126 | CG41: =CG40 -> 0.09 | CH41: =CH40 -> 0.08 | CI41: =CI40 -> 0.08 | CJ41: =CJ40 -> 0.07 | CK41: Cintas does not disclose All Other organic growth. | CS41: Bolt-on EV / sales (x) | CU41: 2 | CW41: Tuck-in uniform / first-aid / fire businesses.
B42: Acquisitions, FX & workday effects % (derived = y/y − organic) | C42: =IF(AND(ISNUMBER(C40),ISNUMBER(C41)),C40-C41,"") | D42: =IF(AND(ISNUMBER(D40),ISNUMBER(D41)),D40-D41,"") | E42: =IF(AND(ISNUMBER(E40),ISNUMBER(E41)),E40-E41,"") | F42: =IF(AND(ISNUMBER(F40),ISNUMBER(F41)),F40-F41,"") | G42: =IF(AND(ISNUMBER(G40),ISNUMBER(G41)),G40-G41,"") | H42: =IF(AND(ISNUMBER(H40),ISNUMBER(H41)),H40-H41,"") | I42: =IF(AND(ISNUMBER(I40),ISNUMBER(I41)),I40-I41,"") | J42: =IF(AND(ISNUMBER(J40),ISNUMBER(J41)),J40-J41,"") | ... CB42: =IF(AND(ISNUMBER(CB40),ISNUMBER(CB41)),CB40-CB41,"") | CS42: Bolt-on operating margin (after amortization) | CU42: 0.15
B43: Gross margin (GAAP) | T43: 58.268 | U43: 57.376 | V43: 55.595 | W43: 65.548 | X43: 236.787 | Y43: 62.128 | Z43: 63.76 | AA43: 62.458 | AB43: 73.506 | AC43: 261.852 | AD43: 67.984 | AE43: 64.069 | AF43: 63.883 | AG43: 75.286 | AH43: 255.413 | AI43: 67.657 | AJ43: 67.031 | AK43: 69.737 | AL43: 78.148 | AM43: 282.573 | AN43: 72.742 | AO43: 71.829 | AP43: 73.912 | AQ43: 88.2 | AR43: 306.683 | AS43: 79.004 | AT43: 85.277 | AU43: 79.394 | AV43: 63.063 | AW43: 306.738 | AX43: 65.098 | AY43: 65.61 | AZ43: 67.16 | BA43: 78.329 | BB43: 276.197 | BC43: 84.606 | BD43: 79.097 | BE43: 84.712 | BF43: 101.091 | BG43: 349.506 | BH43: 104.969 | BI43: 100.034 | BJ43: 106.451 | BK43: 114.871 | BL43: 426.325 | BM43: 116.553 | BN43: 119.921 | BO43: 123.682 | BP43: 133.476 | BQ43: 493.632 | BR43: 130.652 | BS43: 128.86 | BT43: 135.724 | BU43: 147.133 | BV43: 542.369 | BW43: 137.88 | BX43: 140.701 | BY43: 152.375 | BZ43: 164.827 | CA43: 595.783 | CB43: 163.874 | CC43: =CC39*CC45 -> 158.29294 | CD43: =CD39*CD45 -> 171.29748 | CE43: =CE39*CE45 -> 185.24904 | CF43: =SUM(CB43,CC43,CD43,CE43) -> 678.71346 | CG43: =CG39*CG45 -> 745.01802 | CH43: =CH39*CH45 -> 811.1346 | CI43: =CI39*CI45 -> 881.30263 | CJ43: =CJ39*CJ45 -> 948.64049 | CM43: =IFERROR((CJ43/CA43)^(1/5)-1,"n/m") -> 0.097495403 | CN43: =IFERROR((CA43/BB43)^(1/5)-1,"n/m") -> 0.16620213 | CO43: =IFERROR((CA43/AC43)^(1/10)-1,"n/m") -> 0.085683459 | CP43: =IFERROR((CA43/C43)^(1/20)-1,"n/m") -> n/m | CS43: Bolt-on gross margin | CU43: 0.45
B44: Gross margin % before outlook calibration (Q2–Q4/27E helper) | CC44: =BX45+($CB$45-$BW$45) -> 0.4893023 | CD44: =BY45+($CB$45-$BW$45) -> 0.50437097 | CE44: =BZ45+($CB$45-$BW$45) -> 0.50963974 | CK44: Prior-year quarter margin + (Q1/27 − Q1/26 margin drift). | CS44: Goodwill % of bolt-on spend | CU44: 0.7 | CW44: FY2026 acquisitions mostly goodwill & service contracts.
B45: Gross margin % | C45: =IF(AND(ISNUMBER(C43),ISNUMBER(C39)),IFERROR(C43/C39,""),"") | D45: =IF(AND(ISNUMBER(D43),ISNUMBER(D39)),IFERROR(D43/D39,""),"") | E45: =IF(AND(ISNUMBER(E43),ISNUMBER(E39)),IFERROR(E43/E39,""),"") | F45: =IF(AND(ISNUMBER(F43),ISNUMBER(F39)),IFERROR(F43/F39,""),"") | G45: =IF(AND(ISNUMBER(G43),ISNUMBER(G39)),IFERROR(G43/G39,""),"") | H45: =IF(AND(ISNUMBER(H43),ISNUMBER(H39)),IFERROR(H43/H39,""),"") | I45: =IF(AND(ISNUMBER(I43),ISNUMBER(I39)),IFERROR(I43/I39,""),"") | J45: =IF(AND(ISNUMBER(J43),ISNUMBER(J39)),IFERROR(J43/J39,""),"") | ... CB45: =IF(AND(ISNUMBER(CB43),ISNUMBER(CB39)),IFERROR(CB43/CB39,""),"") -> 0.49549479 | CC45: =CC44+CC120 -> 0.47679971 | CD45: =CD44+CD120 -> 0.49186838 | CE45: =CE44+CE120 -> 0.49713715 | CF45: =IF(AND(ISNUMBER(CF43),ISNUMBER(CF39)),IFERROR(CF43/CF39,""),"") -> 0.49053853 | CG45: =CHOOSE(MATCH($CK$2,{"Bull","Base","Bear"},0),$CT$106,$CU$106,$CV$106) -> 0.494 | CH45: =CHOOSE(MATCH($CK$2,{"Bull","Base","Bear"},0),$CT$107,$CU$107,$CV$107) -> 0.498 | CI45: =CHOOSE(MATCH($CK$2,{"Bull","Base","Bear"},0),$CT$108,$CU$108,$CV$108) -> 0.501 | CJ45: =CHOOSE(MATCH($CK$2,{"Bull","Base","Bear"},0),$CT$109,$CU$109,$CV$109) -> 0.504 | CK45: Q2–Q4/27E: helper + uniform margin calibration Δ (solved to the FY27 adjusted EPS guidance). FY28E+: scenario lever OTH_GM (level). | CS45: Bolt-on intangible life (years) | CU45: 10
B46: Selling & administrative expenses (segment) | T46: 48.743 | U46: 47.137 | V46: 45.441 | W46: 50.207 | X46: 191.528 | Y46: 50.594 | Z46: 47.553 | AA46: 49.642 | AB46: 54.761 | AC46: 202.55 | AD46: 57.779 | AE46: 53.351 | AF46: 53.966 | AG46: 55.721 | AH46: 211.657 | AI46: 56.879 | AJ46: 53.609 | AK46: 59.705 | AL46: 55.388 | AM46: 225.581 | AN46: 61.031 | AO46: 60.408 | AP46: 56.417 | AQ46: 62.087 | AR46: 239.943 | AS46: 66.638 | AT46: 61.813 | AU46: 61.063 | AV46: 65.978 | AW46: 255.492 | AX46: 48.947 | AY46: 49.853 | AZ46: 49.915 | BA46: 49.013 | BB46: 197.728 | BC46: 45.615 | BD46: 57.561 | BE46: 59.401 | BF46: 59.812 | BG46: 222.389 | BH46: 70.466 | BI46: 69.69 | BJ46: 66.905 | BK46: 76.047 | BL46: 283.108 | BM46: 82.106 | BN46: 78.38 | BO46: 81.006 | BP46: 82.161 | BQ46: 323.653 | BR46: 87.347 | BS46: 85.052 | BT46: 86.887 | BU46: 91.474 | BV46: 350.761 | BW46: 100.285 | BX46: 97.722 | BY46: 100.837 | BZ46: 105.827 | CA46: 404.546 | CB46: 112.205 | CC46: =CC39*CC47 -> 106.07082 | CD46: =CD39*CD47 -> 109.43087 | CE46: =CE39*CE47 -> 114.81969 | CF46: =SUM(CB46,CC46,CD46,CE46) -> 442.52638 | CG46: =CG39*CG47 -> 479.32773 | CH46: =CH39*CH47 -> 514.41638 | CI46: =CI39*CI47 -> 552.05152 | CJ46: =CJ39*CJ47 -> 586.93068 | CS46: Legacy D&A % of legacy revenues (FY28E+) | CU46: 0.043 | CW46: FY26 4.6%; Q1/27 4.2%.
B47: S&A % of revenues | C47: =IF(AND(ISNUMBER(C46),ISNUMBER(C39)),IFERROR(C46/C39,""),"") | D47: =IF(AND(ISNUMBER(D46),ISNUMBER(D39)),IFERROR(D46/D39,""),"") | E47: =IF(AND(ISNUMBER(E46),ISNUMBER(E39)),IFERROR(E46/E39,""),"") | F47: =IF(AND(ISNUMBER(F46),ISNUMBER(F39)),IFERROR(F46/F39,""),"") | G47: =IF(AND(ISNUMBER(G46),ISNUMBER(G39)),IFERROR(G46/G39,""),"") | H47: =IF(AND(ISNUMBER(H46),ISNUMBER(H39)),IFERROR(H46/H39,""),"") | I47: =IF(AND(ISNUMBER(I46),ISNUMBER(I39)),IFERROR(I46/I39,""),"") | J47: =IF(AND(ISNUMBER(J46),ISNUMBER(J39)),IFERROR(J46/J39,""),"") | ... CB47: =IF(AND(ISNUMBER(CB46),ISNUMBER(CB39)),IFERROR(CB46/CB39,""),"") -> 0.33926671 | CC47: =BX47+($CB$47-$BW$47) -> 0.31949964 | CD47: =BY47+($CB$47-$BW$47) -> 0.31422288 | CE47: =BZ47+($CB$47-$BW$47) -> 0.30813187 | CF47: =IF(AND(ISNUMBER(CF46),ISNUMBER(CF39)),IFERROR(CF46/CF39,""),"") -> 0.31983489 | CG47: =$CF$47+(CG124-$CF$123) -> 0.31782842 | CH47: =$CF$47+(CH124-$CF$123) -> 0.31582842 | CI47: =$CF$47+(CI124-$CF$123) -> 0.31382842 | CJ47: =$CF$47+(CJ124-$CF$123) -> 0.31182842 | CK47: Q2–Q4/27E: prior-year quarter + Q1 drift. FY28E+: FY27E segment ratio + Δ of the consolidated legacy S&A lever SA_pct vs FY27E. | CS47: Dividend per share growth FY28E+ | CU47: 0.12 | CW47: 10-yr DPS CAGR ~17%; FY27 +15.6%.
B48: Segment operating income (before special items) | C48: =IF(AND(ISNUMBER(C43),ISNUMBER(C46)),C43-C46,"") | D48: =IF(AND(ISNUMBER(D43),ISNUMBER(D46)),D43-D46,"") | E48: =IF(AND(ISNUMBER(E43),ISNUMBER(E46)),E43-E46,"") | F48: =IF(AND(ISNUMBER(F43),ISNUMBER(F46)),F43-F46,"") | G48: =IF(AND(ISNUMBER(G43),ISNUMBER(G46)),G43-G46,"") | H48: =IF(AND(ISNUMBER(H43),ISNUMBER(H46)),H43-H46,"") | I48: =IF(AND(ISNUMBER(I43),ISNUMBER(I46)),I43-I46,"") | J48: =IF(AND(ISNUMBER(J43),ISNUMBER(J46)),J43-J46,"") | ... CB48: =IF(AND(ISNUMBER(CB43),ISNUMBER(CB46)),CB43-CB46,"") -> 51.669 | CC48: =CC43-CC46 -> 52.222114 | CD48: =CD43-CD46 -> 61.866606 | CE48: =CE43-CE46 -> 70.429355 | CF48: =CF43-CF46 -> 236.18708 | CG48: =CG43-CG46 -> 265.69029 | CH48: =CH43-CH46 -> 296.71822 | CI48: =CI43-CI46 -> 329.25112 | CJ48: =CJ43-CJ46 -> 361.70981 | CM48: =IFERROR((CJ48/CA48)^(1/5)-1,"n/m") -> 0.13594596 | CN48: =IFERROR((CA48/BB48)^(1/5)-1,"n/m") -> 0.19501886 | CO48: =IFERROR((CA48/AC48)^(1/10)-1,"n/m") -> 0.12421728 | CP48: =IFERROR((CA48/C48)^(1/20)-1,"n/m") -> n/m | CS48: Tax rate on adjusting items (forecast) | CU48: 0.25 | CW48: 424B3 blended statutory rate.
B49: Segment operating margin % | C49: =IF(AND(ISNUMBER(C48),ISNUMBER(C39)),IFERROR(C48/C39,""),"") | D49: =IF(AND(ISNUMBER(D48),ISNUMBER(D39)),IFERROR(D48/D39,""),"") | E49: =IF(AND(ISNUMBER(E48),ISNUMBER(E39)),IFERROR(E48/E39,""),"") | F49: =IF(AND(ISNUMBER(F48),ISNUMBER(F39)),IFERROR(F48/F39,""),"") | G49: =IF(AND(ISNUMBER(G48),ISNUMBER(G39)),IFERROR(G48/G39,""),"") | H49: =IF(AND(ISNUMBER(H48),ISNUMBER(H39)),IFERROR(H48/H39,""),"") | I49: =IF(AND(ISNUMBER(I48),ISNUMBER(I39)),IFERROR(I48/I39,""),"") | J49: =IF(AND(ISNUMBER(J48),ISNUMBER(J39)),IFERROR(J48/J39,""),"") | ... CJ49: =IF(AND(ISNUMBER(CJ48),ISNUMBER(CJ39)),IFERROR(CJ48/CJ39,""),"") -> 0.19217158 | CS49: Capex % of revenues FY27E | CU49: 0.037 | CW49: FY26 3.5%; Q1/27 3.6%; + UniFirst from closing.
B50: Memo: segment operating income / income before taxes as reported (incl. segment special items) | T50: 9.525 | U50: 10.239 | V50: 10.154 | W50: 15.341 | X50: 45.259 | Y50: 11.534 | Z50: 16.207 | AA50: 12.816 | AB50: 18.745 | AC50: 59.302 | AD50: 10.205 | AE50: 10.718 | AF50: 9.917 | AG50: 19.565 | AH50: 43.756 | AI50: 10.778 | AJ50: 13.422 | AK50: 10.032 | AL50: 22.76 | AM50: 56.992 | AN50: 11.711 | AO50: 11.421 | AP50: 17.495 | AQ50: 26.113 | AR50: 66.74 | AS50: 12.366 | AT50: 23.464 | AU50: 18.331 | AV50: -2.915 | AW50: 51.246 | AX50: 16.151 | AY50: 15.757 | AZ50: 17.245 | BA50: 29.316 | BB50: 78.469 | BC50: 38.991 | BD50: 21.536 | BE50: 25.311 | BF50: 41.279 | BG50: 127.117 | BH50: 34.503 | BI50: 30.344 | BJ50: 39.546 | BK50: 38.824 | BL50: 143.217 | BM50: 34.447 | BN50: 41.541 | BO50: 42.676 | BP50: 51.315 | BQ50: 169.979 | BR50: 43.305 | BS50: 43.808 | BT50: 48.837 | BU50: 55.659 | BV50: 191.608 | BW50: 37.595 | BX50: 42.979 | BY50: 51.538 | BZ50: 59 | CA50: 191.237 | CB50: 51.669 | CS50: Capex % of revenues FY28E+ | CU50: 0.039 | CW50: UniFirst ~6.3% of revenue + integration/automation.
CS51: FY27E buybacks after Q1 ($m) | CU51: 229 | CW51: $544.7m repurchased in Q1 and to 22-Sep-2026 (Q1 $315.7m) → $229.0m; assumed paused thereafter.
B52: Legacy reportable segments to FY2015 (as originally reported; memo — not forecast) | CK52: LEGACY SEGMENTS — historical disclosure only | CS52: Net diluted share reduction per quarter, Q2–Q4/27E (m) | CU52: 1 | CW52: Sep-2026 buybacks ($229m ≈ 1.1m shares) roll through Q2; modest net reduction thereafter.
B53: Memo: Uniform Direct Sales — revenues | D53: 501.443 | E53: 517.49 | F53: 428.369 | G53: 386.37 | H53: 419.222 | I53: 433.994 | J53: 100.279 | K53: 110.203 | L53: 126.129 | M53: 124.717 | N53: 461.328 | O53: 107.462 | P53: 121.883 | Q53: 107.678 | R53: 118.462 | S53: 455.485 | CS53: Shares issued under equity plans (m p.a.) | CU53: 1.2
B54: Memo: Uniform Direct Sales — income before income taxes | D54: 63.315 | E54: 64.766 | F54: 3.22 | G54: 40.104 | H54: 48.255 | I54: 49.037 | J54: 8.741 | K54: 10.404 | L54: 16.05 | M54: 18.051 | N54: 53.246 | O54: 8.681 | P54: 13.864 | Q54: 9.254 | R54: 14.91 | S54: 46.709 | CS54: DSO (days) | CU54: 50.391158 | CW54: FY2026 level.
B55: Memo: First Aid, Safety & Fire Protection — revenues | D55: 362.417 | E55: 403.552 | F55: 378.097 | G55: 338.651 | H55: 377.663 | I55: 415.703 | J55: 110.841 | K55: 111.513 | L55: 112.878 | M55: 125.36 | N55: 460.592 | O55: 125.875 | P55: 124.585 | Q55: 126.743 | R55: 137.226 | S55: 514.429 | CS55: Inventory days | CU55: 29.323324 | CW55: FY2026 level.
B56: Memo: First Aid, Safety & Fire Protection — income before income taxes | D56: 38.268 | E56: 35.638 | F56: 15.947 | G56: 13.442 | H56: 21.456 | I56: 35.127 | J56: 9.021 | K56: 9.654 | L56: 10.53 | M56: 13.877 | N56: 43.082 | O56: 11.446 | P56: 10.585 | Q56: 10.654 | R56: 16.267 | S56: 48.952 | CS56: Garments in service % of UR&FS-line revenue | CU56: 0.14802014 | CW56: FY2026 level.
B57: Memo: Document Management (shredding & storage; Shred-it JV Apr-2014, storage sold FY2015–16) — revenues | D57: 108.411 | E57: 182.29 | F57: 213.204 | G57: 252.961 | H57: 321.251 | I57: 340.042 | J57: 85.362 | K57: 82.831 | L57: 87.78 | M57: 93.991 | N57: 349.964 | O57: 94.14 | P57: 92.969 | Q57: 94.114 | R57: 76.745 | S57: 357.968 | CS57: Prepaid & other CA % of revenue | CU57: 0.025408884 | CW57: FY2026 level.
B58: Memo: Document Management (shredding & storage; Shred-it JV Apr-2014, storage sold FY2015–16) — income before income taxes | D58: 7.204 | E58: 25.791 | F58: 19.374 | G58: 24.276 | H58: 31.07 | I58: 25.963 | J58: 4.625 | K58: 2.914 | L58: 3.896 | M58: 4.407 | N58: 15.842 | O58: 2.55 | P58: 2.453 | Q58: 1.872 | R58: 63.856 | S58: 70.731 | CS58: Payable days | CU58: 30.290314 | CW58: FY2026 level.
B59: Other services — legacy segments (UDS + FAS&FP + Document Mgmt; IS "other services" line where no segment data) | C59: 834.832 | D59: =SUM(D53,D55,D57) -> 972.271 | E59: =SUM(E53,E55,E57) -> 1103.332 | F59: =SUM(F53,F55,F57) -> 1019.67 | G59: =SUM(G53,G55,G57) -> 977.982 | H59: =SUM(H53,H55,H57) -> 1118.136 | I59: =SUM(I53,I55,I57) -> 1189.739 | J59: =SUM(J53,J55,J57) -> 296.482 | K59: =SUM(K53,K55,K57) -> 304.547 | ... S59: =SUM(S53,S55,S57) -> 1327.882 | CS59: Accrued compensation % of revenue | CU59: 0.02104279 | CW59: FY2026 level.
B60: Other services — legacy gross margin | C60: 292.845 | D60: 361.911 | E60: 428.649 | F60: 358.086 | G60: 378.036 | H60: 447.495 | I60: 474.898 | J60: 119.18 | K60: 115.099 | L60: 127.863 | M60: 136.635 | N60: 498.777 | O60: 127.845 | P60: 131.715 | Q60: 127.509 | R60: 132.814 | S60: 519.883 | CS60: Accrued liabilities % of revenue | CU60: 0.078936251 | CW60: FY2026 level.
CS61: Deferred tax rate on PPA amortization | CU61: 0.25 | CW61: 424B3.
B62: UniFirst Corporation (NYSE: UNF) — pending acquisition (merger agreement 10-Mar-2026; $155.00 cash + 0.7720 CTAS shares per UNF share; FTC Second Request 11-Jun-2026) | CK62: UNIFIRST — modelling logic (toggle & closing date in the scenario table; NOT in company FY27 guidance) | CS62: Depreciation share of legacy D&A | CU62: 0.62 | CW62: FY2026: $318.6m of $512.8m.
B63: Transaction included (1 = consolidate from closing; 0 = standalone Cintas) | CC63: =$CU$20 -> 1 | CD63: =$CU$20 -> 1 | CE63: =$CU$20 -> 1 | CF63: =$CU$20 -> 1 | CG63: =$CU$20 -> 1 | CH63: =$CU$20 -> 1 | CI63: =$CU$20 -> 1 | CJ63: =$CU$20 -> 1 | CK63: Switch in the scenario table (point estimates). 0 removes UniFirst revenues, earnings, financing, share issuance and PPA from all statements. | CS63: Legacy intangible amortization FY27E ($m) | CU63: 58 | CW63: Service contracts (est. from 10-K schedule).
B64: Days consolidated in period (assumed closing date → scenario table) | CC64: =MAX(0,DATE(2026,11,30)-MAX(DATE(2026,9,1),$CU$21)+1)*CC63 -> 0 | CD64: =MAX(0,DATE(2027,2,28)-MAX(DATE(2026,12,1),$CU$21)+1)*CD63 -> 60 | CE64: =MAX(0,DATE(2027,5,31)-MAX(DATE(2027,3,1),$CU$21)+1)*CE63 -> 92 | CF64: =SUM(CB64,CC64,CD64,CE64) -> 152 | CG64: =365*CG63 -> 365 | CH64: =365*CH63 -> 365 | CI64: =365*CI63 -> 365 | CJ64: =365*CJ63 -> 365 | CK64: Base: closing assumed 31-Dec-2026 (company: "prior to the end of calendar 2026"; outside date 10-Jan-2027, extendable to Sep-2027). Q3/27E = 31-Dec to 28-Feb. | CS64: Note maturities FY27E ($m) | CU64: -1000 | CW64: 3.70% senior notes due 2027.
B65: UniFirst revenue run-rate, annualised (standalone; UNF fiscal year ends Aug) | CA65: 2492.672 | CC65: =$CF$65 -> 2567.4522 | CD65: =$CF$65 -> 2567.4522 | CE65: =$CF$65 -> 2567.4522 | CF65: =CA65*(1+CF66) -> 2567.4522 | CG65: =CF65*(1+CG66) -> 2644.4757 | CH65: =CG65*(1+CH66) -> 2737.0324 | CI65: =CH65*(1+CI66) -> 2832.8285 | CJ65: =CI65*(1+CJ66) -> 2931.9775 | CK65: FY2026 column = UNF LTM to 30-May-2026 ($2,492.7m: Q4/FY25 614.4 + Q1–Q3/FY26 1,878.2; 8-K Ex.99 earnings releases). UNF FY26 (ended 29-Aug-26) not yet reported on EDGAR. | CS65: Note maturities FY28E ($m) | CU65: -400 | CW65: 4.20% senior notes due 1-May-2028.
B66: UniFirst standalone revenue growth % | CA66: 0.033 | CF66: =CHOOSE(MATCH($CK$2,{"Bull","Base","Bear"},0),$CT$118,$CU$118,$CV$118) -> 0.03 | CG66: =CHOOSE(MATCH($CK$2,{"Bull","Base","Bear"},0),$CT$119,$CU$119,$CV$119) -> 0.03 | CH66: =CHOOSE(MATCH($CK$2,{"Bull","Base","Bear"},0),$CT$120,$CU$120,$CV$120) -> 0.035 | CI66: =CHOOSE(MATCH($CK$2,{"Bull","Base","Bear"},0),$CT$121,$CU$121,$CV$121) -> 0.035 | CJ66: =CHOOSE(MATCH($CK$2,{"Bull","Base","Bear"},0),$CT$122,$CU$122,$CV$122) -> 0.035 | CK66: FY2026 column: UNF 9M/FY26 y/y +3.3% (1,878.2 vs 1,817.9). Forecast: scenario lever UNF_g. | CS66: % of maturities refinanced | CU66: 1
B67: Revenues (consolidated from closing) | CC67: =CC65*CC64/365 -> 0 | CD67: =CD65*CD64/365 -> 422.04693 | CE67: =CE65*CE64/365 -> 647.13863 | CF67: =SUM(CB67,CC67,CD67,CE67) -> 1069.1856 | CG67: =CG65*CG63 -> 2644.4757 | CH67: =CH65*CH63 -> 2737.0324 | CI67: =CI65*CI63 -> 2832.8285 | CJ67: =CJ65*CJ63 -> 2931.9775 | CS67: Minimum cash balance ($m) | CU67: 250 | CW67: Cintas runs ~$150–350m cash.
B68: Standalone gross margin % (Cintas presentation: cost of sales incl. production D&A; before synergies) | CC68: =$CF$68 -> 0.318 | CD68: =$CF$68 -> 0.318 | CE68: =$CF$68 -> 0.318 | CF68: =$CU$30 -> 0.318 | CG68: =CF68 -> 0.318 | CH68: =CG68 -> 0.318 | CI68: =CH68 -> 0.318 | CJ68: =CI68 -> 0.318 | CK68: UNF LTM: cost of revenues ex-D&A 63.3% of revenue + ~85% of D&A (5.7%) in cost of sales → ~31.8% gross margin on Cintas presentation. | CS68: Blended rate on notes & term debt FY28E+ | CU68: 0.048
B69: Cost synergies realised — % of $375m run-rate (scenario) | CC69: =$CF$69 -> 0.03 | CD69: =$CF$69 -> 0.03 | CE69: =$CF$69 -> 0.03 | CF69: =CHOOSE(MATCH($CK$2,{"Bull","Base","Bear"},0),$CT$125,$CU$125,$CV$125) -> 0.03 | CG69: =MIN(1,CHOOSE(MATCH($CK$2,{"Bull","Base","Bear"},0),$CT$126,$CU$126,$CV$126)) -> 0.25 | CH69: =MIN(1,CHOOSE(MATCH($CK$2,{"Bull","Base","Bear"},0),$CT$127,$CU$127,$CV$127)) -> 0.55 | CI69: =MIN(1,CHOOSE(MATCH($CK$2,{"Bull","Base","Bear"},0),$CT$128,$CU$128,$CV$128)) -> 0.85 | CJ69: =MIN(1,CHOOSE(MATCH($CK$2,{"Bull","Base","Bear"},0),$CT$129,$CU$129,$CV$129)) -> 1 | CK69: ~$375m run-rate operating cost synergies "within four years" (deal 8-K 11-Mar-2026): material cost, production, delivery & G&A. No annual phasing disclosed → scenario lever UNF_syn. | CS69: Rate on CP / revolver | CU69: 0.045 | CW69: SOFR + 70–114bp revolver; A2/P2 CP.
B70: (+) Cost synergies realised (USDm) | CC70: =$CU$25*CC69*CC64/365 -> 0 | CD70: =$CU$25*CD69*CD64/365 -> 1.8493151 | CE70: =$CU$25*CE69*CE64/365 -> 2.8356164 | CF70: =SUM(CB70,CC70,CD70,CE70) -> 4.6849315 | CG70: =$CU$25*CG69*CG63 -> 93.75 | CH70: =$CU$25*CH69*CH63 -> 206.25 | CI70: =$CU$25*CI69*CI63 -> 318.75 | CJ70: =$CU$25*CJ69*CJ63 -> 375 | CS70: Yield on cash | CU70: 0.035
B71: Gross margin (GAAP; incl. cost-of-sales share of synergies & PP&E step-up depreciation) | CC71: =CC67*CC68+CC70*$CU$26-$CU$27*CC64/365 -> 0 | CD71: =CD67*CD68+CD70*$CU$26-$CU$27*CD64/365 -> 135.3464 | CE71: =CE67*CE68+CE70*$CU$26-$CU$27*CE64/365 -> 207.53115 | CF71: =SUM(CB71,CC71,CD71,CE71) -> 342.87756 | CG71: =CG67*CG68+CG70*$CU$26-$CU$27*CG63 -> 901.47578 | CH71: =CH67*CH68+CH70*$CU$26-$CU$27*CH63 -> 1004.0338 | CI71: =CI67*CI68+CI70*$CU$26-$CU$27*CI63 -> 1107.622 | CJ71: =CJ67*CJ68+CJ70*$CU$26-$CU$27*CJ63 -> 1175.7138 | CK71: Synergy split input: 65% cost of sales (material, production, delivery) / 35% S&A. Net PP&E step-up depreciation: buildings FV $558.7m / 20y = $27.9m vs $27.5m eliminated (424B3 pro forma note) → +$0.4m p.a. | CS71: Dilutive securities (m shares) | CU71: 4 | CW71: Q1/27 diluted − basic = 4.2m.
B72: Standalone S&A % of revenues (before synergies & PPA amortization) | CC72: =$CF$72 -> 0.25 | CD72: =$CF$72 -> 0.25 | CE72: =$CF$72 -> 0.25 | CF72: =$CU$31 -> 0.25 | CG72: =CF72 -> 0.25 | CH72: =CG72 -> 0.25 | CI72: =CH72 -> 0.25 | CJ72: =CI72 -> 0.25 | CK72: UNF LTM SG&A ex merger costs $605.4m (24.3%) + non-production D&A (~0.8%). | CS72: Share price ($) — valuation input | CU72: 198.95 | CW72: Latest observable on EDGAR: Form 4 phantom-unit credit price 15-Sep-2026 ($198.95). Overwrite with live price.
B73: (+) Amortization of acquired intangibles (PPA; within S&A) | CC73: =$CU$28*CC64/365 -> 0 | CD73: =$CU$28*CD64/365 -> 16.151836 | CE73: =$CU$28*CE64/365 -> 24.766148 | CF73: =SUM(CB73,CC73,CD73,CE73) -> 40.917984 | CG73: =($CU$28)*CG63 -> 98.257 | CH73: =($CU$28)*CH63 -> 98.257 | CI73: =($CU$29)*CI63 -> 82.733333 | CJ73: =($CU$29)*CJ63 -> 82.733333 | CK73: Customer relationships $1,241m / 15y ($82.7m) + trade names $50m / 3y ($16.7m) = $98.3m p.a. for three years, then $82.7m (424B3 pro forma note). Not adjusted out (company adjusted EPS excludes only transaction & integration costs). | CS73: Share-price appreciation % p.a. (buyback pricing) | CU73: 0.08
B74: S&A (USDm; consolidated in the S&A line) | CC74: =CC67*CC72-CC70*(1-$CU$26)+CC73 -> 0 | CD74: =CD67*CD72-CD70*(1-$CU$26)+CD73 -> 121.01631 | CE74: =CE67*CE72-CE70*(1-$CU$26)+CE73 -> 185.55834 | CF74: =SUM(CB74,CC74,CD74,CE74) -> 306.57465 | CG74: =CG67*CG72-CG70*(1-$CU$26)+CG73 -> 726.56343 | CH74: =CH67*CH72-CH70*(1-$CU$26)+CH73 -> 710.32759 | CI74: =CI67*CI72-CI70*(1-$CU$26)+CI73 -> 679.37796 | CJ74: =CJ67*CJ72-CJ70*(1-$CU$26)+CJ73 -> 684.47771
B75: Operating income contribution (before transaction & integration costs) | CC75: =CC71-CC74 -> 0 | CD75: =CD71-CD74 -> 14.330095 | CE75: =CE71-CE74 -> 21.972813 | CF75: =CF71-CF74 -> 36.302908 | CG75: =CG71-CG74 -> 174.91235 | CH75: =CH71-CH74 -> 293.7062 | CI75: =CI71-CI74 -> 428.24401 | CJ75: =CJ71-CJ74 -> 491.23614 | CS75: URFS_org (UR&FS organic revenue growth) | CT75: 0.015 | CU75: Δ → | CV75: -0.02 | CW75: FY26 UR&FS organic ~7.5%; Q1/27 ~8%. Bull: share gains from UniFirst disruption, hygiene/water penetration; Bear: employment slowdown.
B76: Standalone D&A % of revenues (excl. UNF acquired-intangible amortization) | CC76: =$CF$76 -> 0.05 | CD76: =$CF$76 -> 0.05 | CE76: =$CF$76 -> 0.05 | CF76: =$CU$32 -> 0.05 | CG76: =CF76 -> 0.05 | CH76: =CG76 -> 0.05 | CI76: =CH76 -> 0.05 | CJ76: =CI76 -> 0.05 | CK76: UNF LTM D&A $142.2m less ~$17m acquired-intangible amortization (eliminated in PPA) ≈ 5.0% of revenue. | CS76: FY2028E | CT76: =CU76+$CT$75 -> 0.085 | CU76: 0.07 | CV76: =CU76+$CV$75 -> 0.05
B77: D&A of UniFirst (standalone D&A + PP&E step-up + PPA amortization) | CC77: =CC67*CC76+$CU$27*CC64/365+CC73 -> 0 | CD77: =CD67*CD76+$CU$27*CD64/365+CD73 -> 37.320757 | CE77: =CE67*CE76+$CU$27*CE64/365+CE73 -> 57.225161 | CF77: =SUM(CB77,CC77,CD77,CE77) -> 94.545919 | CG77: =CG67*CG76+$CU$27*CG63+CG73 -> 230.88579 | CH77: =CH67*CH76+$CU$27*CH63+CH73 -> 235.51362 | CI77: =CI67*CI76+$CU$27*CI63+CI73 -> 224.77976 | CJ77: =CJ67*CJ76+$CU$27*CJ63+CJ73 -> 229.73721 | CS77: FY2029E | CT77: =CU77+$CT$75 -> 0.08 | CU77: 0.065 | CV77: =CU77+$CV$75 -> 0.045
B78: Memo: UniFirst Adjusted EBITDA contribution (OI + D&A) | CC78: =CC75+CC77 -> 0 | CD78: =CD75+CD77 -> 51.650853 | CE78: =CE75+CE77 -> 79.197974 | CF78: =CF75+CF77 -> 130.84883 | CG78: =CG75+CG77 -> 405.79814 | CH78: =CH75+CH77 -> 529.21982 | CI78: =CI75+CI77 -> 653.02376 | CJ78: =CJ75+CJ77 -> 720.97335 | CK78: Cross-check: UNF LTM Adjusted EBITDA $320.3m (12.8%) incl. $12.8m SBC add-back; Cintas basis (no SBC add-back) ≈ $307m. Deal: EV $5.5bn ≈ 8.0x TTM EBITDA incl. $375m synergies. | CS78: FY2030E | CT78: =CU78+$CT$75 -> 0.08 | CU78: 0.065 | CV78: =CU78+$CV$75 -> 0.045
B79: Memo: UniFirst Adjusted EBITDA margin % | CC79: =IF(AND(ISNUMBER(CC78),ISNUMBER(CC67)),IFERROR(CC78/CC67,""),"") | CD79: =IF(AND(ISNUMBER(CD78),ISNUMBER(CD67)),IFERROR(CD78/CD67,""),"") -> 0.12238178 | CE79: =IF(AND(ISNUMBER(CE78),ISNUMBER(CE67)),IFERROR(CE78/CE67,""),"") -> 0.12238178 | CF79: =IF(AND(ISNUMBER(CF78),ISNUMBER(CF67)),IFERROR(CF78/CF67,""),"") -> 0.12238178 | CG79: =IF(AND(ISNUMBER(CG78),ISNUMBER(CG67)),IFERROR(CG78/CG67,""),"") -> 0.15345126 | CH79: =IF(AND(ISNUMBER(CH78),ISNUMBER(CH67)),IFERROR(CH78/CH67,""),"") -> 0.19335534 | CI79: =IF(AND(ISNUMBER(CI78),ISNUMBER(CI67)),IFERROR(CI78/CI67,""),"") -> 0.23052005 | CJ79: =IF(AND(ISNUMBER(CJ78),ISNUMBER(CJ67)),IFERROR(CJ78/CJ67,""),"") -> 0.24590003 | CS79: FY2031E | CT79: =CU79+$CT$75 -> 0.075 | CU79: 0.06 | CV79: =CU79+$CV$75 -> 0.04
B80: Transaction, retention & integration costs (one-time; excluded from adjusted results) | BZ80: 14.024 | CA80: 15.136 | CB80: 14.412 | CC80: =$CU$34 -> 15 | CD80: =$CU$34+($CU$35+$CU$36*$CU$37*0.4)*IF(CD64>0,1,0) -> 108.7 | CE80: =$CU$34*IF(CD64>0,0,1)+$CU$36*$CU$37*0.6*CE63 -> 31.5 | CF80: =SUM(CB80,CC80,CD80,CE80) -> 169.612 | CG80: =$CU$36*$CU$38*CG63 -> 157.5 | CH80: =$CU$36*$CU$39*CH63 -> 105 | CI80: =$CU$36*$CU$40*CI63 -> 35 | CJ80: =$CU$36*0*CJ63 -> 0 | CK80: Pre-close: ~$15m per quarter of transaction costs (Q1/27 $14.4m). At close: Cintas transaction costs $34.0m + retention bonuses $38.7m (424B3). Integration (severance, retention, lease exits): not quantified on EDGAR — CFO: "in line on a proportional basis with G&K" (~$138m on a $2.2bn deal) → $350m input phased 15/45/30/10%.
CS81: FAS_org (First Aid & Safety organic growth) | CT81: 0.03 | CU81: Δ → | CV81: -0.04 | CW81: FY26 14.0%; runway in AEDs, eyewash, safety training.
B82: Future acquisitions (M&A lever — tuck-in uniform, first-aid & fire businesses; unallocated; deals closed from FY2028E) | CK82: M&A LEVER — acquired sales = spend ÷ EV/sales; mid-year convention | CS82: FY2028E | CT82: =CU82+$CT$81 -> 0.15 | CU82: 0.12 | CV82: =CU82+$CV$81 -> 0.08
B83: Acquisition spend (USDm, scenario) | N83: 69.37 | S83: 33.441 | X83: 15.495 | AC83: 156.579 | AH83: 2102.371 | AM83: 19.346 | AR83: 9.813 | AW83: 53.72 | BB83: 10.038 | BG83: 164.228 | BL83: 46.357 | BQ83: 186.837 | BV83: 232.899 | CA83: 164.548 | CG83: =CHOOSE(MATCH($CK$2,{"Bull","Base","Bear"},0),$CT$132,$CU$132,$CV$132) -> 300 | CH83: =CHOOSE(MATCH($CK$2,{"Bull","Base","Bear"},0),$CT$133,$CU$133,$CV$133) -> 350 | CI83: =CHOOSE(MATCH($CK$2,{"Bull","Base","Bear"},0),$CT$134,$CU$134,$CV$134) -> 400 | CJ83: =CHOOSE(MATCH($CK$2,{"Bull","Base","Bear"},0),$CT$135,$CU$135,$CV$135) -> 450 | CK83: Historical: cash paid for acquisitions (CF statement; FY2017 incl. G&K $2.1bn). Cintas spends ~$100–400m p.a. on tuck-ins outside large deals. FY27E bolt-ons inside legacy run-rate (guidance excludes future acquisitions). | CS83: FY2029E | CT83: =CU83+$CT$81 -> 0.14 | CU83: 0.11 | CV83: =CU83+$CV$81 -> 0.07
B84: Purchase multiple — EV / sales (x) | CG84: =$CU$41 -> 2 | CH84: =$CU$41 -> 2 | CI84: =$CU$41 -> 2 | CJ84: =$CU$41 -> 2 | CS84: FY2030E | CT84: =CU84+$CT$81 -> 0.13 | CU84: 0.1 | CV84: =CU84+$CV$81 -> 0.06
B85: Annualised sales acquired in the year | CG85: =IFERROR(CG83/CG84,0) -> 150 | CH85: =IFERROR(CH83/CH84,0) -> 175 | CI85: =IFERROR(CI83/CI84,0) -> 200 | CJ85: =IFERROR(CJ83/CJ84,0) -> 225 | CS85: FY2031E | CT85: =CU85+$CT$81 -> 0.12 | CU85: 0.09 | CV85: =CU85+$CV$81 -> 0.05
B86: Growth of acquired businesses after acquisition % | CG86: =CG12 -> 0.07 | CH86: =CH12 -> 0.065 | CI86: =CI12 -> 0.065 | CJ86: =CJ12 -> 0.06
B87: Run-rate sales of businesses acquired (year end) | CG87: =CG85 -> 150 | CH87: =CG87*(1+CH86)+CH85 -> 334.75 | CI87: =CH87*(1+CI86)+CI85 -> 556.50875 | CJ87: =CI87*(1+CJ86)+CJ85 -> 814.89927 | CS87: OTH_org (All Other: Fire Protection + Uniform Direct Sale) | CT87: 0.02 | CU87: Δ → | CV87: -0.03 | CW87: FY26 +9.2% reported; fire inspection is recurring/regulatory.
B88: Revenues from future acquisitions | CG88: =CG85*0.5 -> 75 | CH88: =CG87*(1+CH86)+CH85*0.5 -> 247.25 | CI88: =CH87*(1+CI86)+CI85*0.5 -> 456.50875 | CJ88: =CI87*(1+CJ86)+CJ85*0.5 -> 702.39927 | CK88: Mid-year convention: deals close evenly through the year (half a year of sales in year 1). | CS88: FY2028E | CT88: =CU88+$CT$87 -> 0.11 | CU88: 0.09 | CV88: =CU88+$CV$87 -> 0.06
B89: Operating margin of acquired businesses % (after intangible amortization) | CG89: =$CU$42 -> 0.15 | CH89: =$CU$42 -> 0.15 | CI89: =$CU$42 -> 0.15 | CJ89: =$CU$42 -> 0.15 | CS89: FY2029E | CT89: =CU89+$CT$87 -> 0.1 | CU89: 0.08 | CV89: =CU89+$CV$87 -> 0.05
B90: Gross margin of acquired businesses % | CG90: =$CU$43 -> 0.45 | CH90: =$CU$43 -> 0.45 | CI90: =$CU$43 -> 0.45 | CJ90: =$CU$43 -> 0.45 | CS90: FY2030E | CT90: =CU90+$CT$87 -> 0.1 | CU90: 0.08 | CV90: =CU90+$CV$87 -> 0.05
B91: Gross margin from future acquisitions | CG91: =CG88*CG90 -> 33.75 | CH91: =CH88*CH90 -> 111.2625 | CI91: =CI88*CI90 -> 205.42894 | CJ91: =CJ88*CJ90 -> 316.07967 | CS91: FY2031E | CT91: =CU91+$CT$87 -> 0.09 | CU91: 0.07 | CV91: =CU91+$CV$87 -> 0.04
B92: S&A of future acquisitions (incl. amortization) | CG92: =CG91-CG88*CG89 -> 22.5 | CH92: =CH91-CH88*CH89 -> 74.175 | CI92: =CI91-CI88*CI89 -> 136.95263 | CJ92: =CJ91-CJ88*CJ89 -> 210.71978
B93: Goodwill % of spend (balance: acquired intangibles; tangible assets negligible) | CG93: =$CU$44 -> 0.7 | CH93: =$CU$44 -> 0.7 | CI93: =$CU$44 -> 0.7 | CJ93: =$CU$44 -> 0.7 | CS93: URFS_GM (UR&FS gross margin, level) | CT93: 0.0075 | CU93: Δ → | CV93: -0.01 | CW93: FY26 50.0%; Q1/27 50.8% (SAP, SmartTruck routing, garment reuse).
B94: Intangible amortization life (years) | CG94: =$CU$45 -> 10 | CH94: =$CU$45 -> 10 | CI94: =$CU$45 -> 10 | CJ94: =$CU$45 -> 10 | CS94: FY2028E | CT94: =CU94+$CT$93 -> 0.5175 | CU94: 0.51 | CV94: =CU94+$CV$93 -> 0.5
B95: Cumulative acquired intangibles (gross) | CG95: =CG83*(1-CG93) -> 90 | CH95: =CG95+CH83*(1-CH93) -> 195 | CI95: =CH95+CI83*(1-CI93) -> 315 | CJ95: =CI95+CJ83*(1-CJ93) -> 450 | CS95: FY2029E | CT95: =CU95+$CT$93 -> 0.5205 | CU95: 0.513 | CV95: =CU95+$CV$93 -> 0.503
B96: Amortization of future-acquisition intangibles (within S&A) | CG96: =IFERROR(CG83*(1-CG93)/CG94*0.5,0) -> 4.5 | CH96: =IFERROR(CG95/CH94+CH83*(1-CH93)/CH94*0.5,0) -> 14.25 | CI96: =IFERROR(CH95/CI94+CI83*(1-CI93)/CI94*0.5,0) -> 25.5 | CJ96: =IFERROR(CI95/CJ94+CJ83*(1-CJ93)/CJ94*0.5,0) -> 38.25 | CS96: FY2030E | CT96: =CU96+$CT$93 -> 0.5235 | CU96: 0.516 | CV96: =CU96+$CV$93 -> 0.506
B97: D&A of acquired businesses (amortization + 1.5% of sales depreciation) | CG97: =CG96+CG88*0.015 -> 5.625 | CH97: =CH96+CH88*0.015 -> 17.95875 | CI97: =CI96+CI88*0.015 -> 32.347631 | CJ97: =CJ96+CJ88*0.015 -> 48.785989 | CS97: FY2031E | CT97: =CU97+$CT$93 -> 0.5265 | CU97: 0.519 | CV97: =CU97+$CV$93 -> 0.509
B99: Group Total — revenues & gross margin (segment build) → adjusted operating income (Cintas' guided profit metric: adjusted diluted EPS) | CK99: GROUP TOTAL (CONSOLIDATED) — modelling logic | CS99: FAS_GM (First Aid & Safety gross margin) | CT99: 0.01 | CU99: Δ → | CV99: -0.015 | CW99: FY26 57.7%.
B100: Revenues (segment build) | C100: =SUM(C11,C59) -> 3403.608 | D100: =SUM(D11,D59) -> 3706.9 | E100: =SUM(E11,E59) -> 3937.9 | F100: =SUM(F11,F59) -> 3774.685 | G100: =SUM(G11,G59) -> 3547.339 | H100: =SUM(H11,H59) -> 3810.384 | I100: =SUM(I11,I59) -> 4102 | J100: =SUM(J11,J59) -> 1051.325 | ... S100: =SUM(S11,S59) -> 4551.812 | T100: =SUM(T11,T25,T39) -> 1102.077 | U100: =SUM(U11,U25,U39) -> 1123.379 | V100: =SUM(V11,V25,V39) -> 1108.847 | W100: =SUM(W11,W25,W39) -> 1142.583 | X100: =SUM(X11,X25,X39) -> 4476.886 | Y100: =SUM(Y11,Y25,Y39) -> 1198.89 | Z100: =SUM(Z11,Z25,Z39) -> 1219.08 | AA100: =SUM(AA11,AA25,AA39) -> 1216.083 | ... CB100: =SUM(CB11,CB25,CB39) -> 3013.981 | CC100: =SUM(CC11,CC25,CC39,CC67) -> 3012.079 | CD100: =SUM(CD11,CD25,CD39,CD67) -> 3479.0353 | CE100: =SUM(CE11,CE25,CE39,CE67) -> 3774.0902 | CF100: =SUM(CF11,CF25,CF39,CF67) -> 13279.186 | CG100: =SUM(CG11,CG25,CG39,CG67,CG88) -> 15890.893 | CH100: =SUM(CH11,CH25,CH39,CH67,CH88) -> 17114.142 | CI100: =SUM(CI11,CI25,CI39,CI67,CI88) -> 18430.858 | CJ100: =SUM(CJ11,CJ25,CJ39,CJ67,CJ88) -> 19766.838 | CK100: Σ UR&FS + FA&S + All Other (legacy: Rental + other services) + UniFirst + future M&A. Historical rows tie to consolidated revenues (check below). | CM100: =IFERROR((CJ100/CA100)^(1/5)-1,"n/m") -> 0.11903338 | CN100: =IFERROR((CA100/BB100)^(1/5)-1,"n/m") -> 0.096208231 | CO100: =IFERROR((CA100/AC100)^(1/10)-1,"n/m") -> 0.086686425 | CP100: =IFERROR((CA100/C100)^(1/20)-1,"n/m") -> 0.061668965 | CS100: FY2028E | CT100: =CU100+$CT$99 -> 0.592 | CU100: 0.582 | CV100: =CU100+$CV$99 -> 0.567
B101: Gross margin (segment build) | C101: =SUM(C15,C60) -> 1454.792 | D101: =SUM(D15,D60) -> 1581.355 | E101: =SUM(E15,E60) -> 1681.6 | F101: =SUM(F15,F60) -> 1550.871 | G101: =SUM(G15,G60) -> 1497.817 | H101: =SUM(H15,H60) -> 1609.287 | I101: =SUM(I15,I60) -> 1738.608 | J101: =SUM(J15,J60) -> 445.875 | ... S101: =SUM(S15,S60) -> 1914.386 | T101: =SUM(T15,T29,T43) -> 477.946 | U101: =SUM(U15,U29,U43) -> 481.424 | V101: =SUM(V15,V29,V43) -> 475.307 | W101: =SUM(W15,W29,W43) -> 486.66 | X101: =SUM(X15,X29,X43) -> 1921.337 | Y101: =SUM(Y15,Y29,Y43) -> 524.144 | Z101: =SUM(Z15,Z29,Z43) -> 527.4 | AA101: =SUM(AA15,AA29,AA43) -> 524.608 | ... CB101: =SUM(CB15,CB29,CB43) -> 1553.543 | CC101: =SUM(CC15,CC29,CC43,CC71) -> 1520.1572 | CD101: =SUM(CD15,CD29,CD43,CD71) -> 1694.5758 | CE101: =SUM(CE15,CE29,CE43,CE71) -> 1801.9321 | CF101: =SUM(CF15,CF29,CF43,CF71) -> 6570.2081 | CG101: =SUM(CG15,CG29,CG43,CG71,CG91) -> 7756.0032 | CH101: =SUM(CH15,CH29,CH43,CH71,CH91) -> 8480.9904 | CI101: =SUM(CI15,CI29,CI43,CI71,CI91) -> 9255.348 | CJ101: =SUM(CJ15,CJ29,CJ43,CJ71,CJ91) -> 10003.619 | CK101: FY2009 legacy gross margin includes the $27.5m inventory valuation charge recorded in cost of sales (segment GM as reported). | CM101: =IFERROR((CJ101/CA101)^(1/5)-1,"n/m") -> 0.1187622 | CN101: =IFERROR((CA101/BB101)^(1/5)-1,"n/m") -> 0.11482341 | CO101: =IFERROR((CA101/AC101)^(1/10)-1,"n/m") -> 0.10359954 | CP101: =IFERROR((CA101/C101)^(1/20)-1,"n/m") -> 0.070738369 | CS101: FY2029E | CT101: =CU101+$CT$99 -> 0.595 | CU101: 0.585 | CV101: =CU101+$CV$99 -> 0.57
...

Sheet Bull-Base-Bear
B2: Cintas Corporation (CTAS) — Bull / Base / Bear Case P&L Summary | J2: Share price ($): | K2: =Model!$CF$380 -> 198.95
B3: Adjusted figures (company definition: adjusted diluted EPS excl. acquisition transaction & integration costs; model Adjusted EBITDA) · USD millions · Fiscal years end 31-May · Live panel linked to Model — toggle scenario via Model!CK2. Bull and Bear panels are value snapshots generated from the Model with the switch set to each case. UniFirst consolidated from an assumed 31-Dec-2026 close (toggle in the Model scenario table). | J3: As of: | K3: =TODAY() -> 46301
B5: Scenario: | C5: =Model!$CK$2 -> Base | N5: Scenario: | O5: Bull | P5: Snapshot (values) — Model run with switch = Bull | Z5: Scenario: | AA5: Bear | AB5: Snapshot (values) — Model run with switch = Bear
B7: (USDm, except EPS and shares) | C7: FY2026A | D7: FY2027E | E7: FY2028E | F7: FY2029E | G7: FY2030E | H7: FY2031E | I7: 26-'31 CAGR | J7: LT Hist Avg | K7: LT Hist Min | L7: LT Hist Max | N7: (USDm, except EPS and shares) | O7: FY2026A | P7: FY2027E | Q7: FY2028E | R7: FY2029E | S7: FY2030E | T7: FY2031E | U7: 26-'31 CAGR | V7: LT Hist Avg | W7: LT Hist Min | X7: LT Hist Max | Z7: (USDm, except EPS and shares) | AA7: FY2026A | AB7: FY2027E | AC7: FY2028E | AD7: FY2029E | AE7: FY2030E | AF7: FY2031E | AG7: 26-'31 CAGR | AH7: LT Hist Avg | AI7: LT Hist Min | AJ7: LT Hist Max
B9: Revenues | C9: =Model!CA132 -> 11264.761 | D9: =Model!CF132 -> 13279.186 | E9: =Model!CG132 -> 15890.893 | F9: =Model!CH132 -> 17114.142 | G9: =Model!CI132 -> 18430.858 | H9: =Model!CJ132 -> 19766.838 | I9: =IFERROR((H9/C9)^(1/5)-1,"n/m") -> 0.11903338 | N9: Revenues | O9: 11264.761 | P9: 13354.756 | Q9: 16298.01 | R9: 17933.15 | S9: 19718.624 | T9: 21580.14 | U9: 0.13884981 | Z9: Revenues | AA9: 11264.761 | AB9: 13193.234 | AC9: 15361.134 | AD9: 16077.674 | AE9: 16836.295 | AF9: 17566.473 | AG9: 0.092930426
B10: Revenues y/y % | D10: =IFERROR(D9/C9-1,"") -> 0.17882533 | E10: =IFERROR(E9/D9-1,"") -> 0.19667681 | F10: =IFERROR(F9/E9-1,"") -> 0.076977967 | G10: =IFERROR(G9/F9-1,"") -> 0.076937312 | H10: =IFERROR(H9/G9-1,"") -> 0.072486013 | N10: Revenues y/y % | P10: 0.18553392 | Q10: 0.22038995 | R10: 0.10032755 | S10: 0.099562786 | T10: 0.094403931 | Z10: Revenues y/y % | AB10: 0.17119524 | AC10: 0.16431907 | AD10: 0.046646265 | AE10: 0.047184728 | AF10: 0.043369283
B11: Organic revenue growth % (legacy Cintas; FY2027E ex-workday) | C11: =Model!CA214 -> 0.083 | D11: =Model!CF214 -> 0.080064896 | E11: =Model!CG214 -> 0.078740186 | F11: =Model!CH214 -> 0.072766807 | G11: =Model!CI214 -> 0.071597399 | H11: =Model!CJ214 -> 0.065445203 | N11: Aggregates shipments y/y % | O11: 0.083 | P11: 0.08539124 | Q11: 0.09624695 | R11: 0.090442418 | S11: 0.089413151 | T11: 0.083379498 | Z11: Aggregates shipments y/y % | AA11: 0.083 | AB11: 0.074738551 | AC11: 0.055018388 | AD11: 0.048883585 | AE11: 0.047598508 | AF11: 0.041368417
B12: Adjusted EBITDA (model; excl. transaction & integration costs) | C12: =Model!CA185 -> 3134.494 | D12: =Model!CF185 -> 3540.5833 | E12: =Model!CG185 -> 4235.7965 | F12: =Model!CH185 -> 4747.3834 | G12: =Model!CI185 -> 5290.6216 | H12: =Model!CJ185 -> 5787.3754 | I12: =IFERROR((H12/C12)^(1/5)-1,"n/m") -> 0.13047989 | N12: Adjusted EBITDA (continuing operations) | O12: 3134.494 | P12: 3583.4274 | Q12: 4551.225 | R12: 5185.9633 | S12: 5871.0407 | T12: 6490.211 | U12: 0.15669344 | Z12: Adjusted EBITDA (continuing operations) | AA12: 3134.494 | AB12: 3480.8979 | AC12: 3792.5525 | AD12: 4161.1723 | AE12: 4544.2724 | AF12: 4865.7725 | AG12: 0.091935213
B13: Adjusted EBITDA margin % | C13: =IFERROR(C12/C9,"") -> 0.27825659 | D13: =IFERROR(D12/D9,"") -> 0.26662654 | E13: =IFERROR(E12/E9,"") -> 0.26655496 | F13: =IFERROR(F12/F9,"") -> 0.27739535 | G13: =IFERROR(G12/G9,"") -> 0.28705238 | H13: =IFERROR(H12/H9,"") -> 0.29278206 | J13: =IFERROR(AVERAGE(Model!C186,Model!D186,Model!E186,Model!F186,Model!G186,Model!H186,Model!I186,Model!N186,Model!S186,Model!X186,Model!AC186,Model!AH186,Model!AM186,Model!AR186,Model!AW186,Model!BB186,Model!BG186,Model!BL186,Model!BQ186,Model!BV186,Model!CA186),"") -> 0.21130165 | K13: =IFERROR(MIN(Model!C186,Model!D186,Model!E186,Model!F186,Model!G186,Model!H186,Model!I186,Model!N186,Model!S186,Model!X186,Model!AC186,Model!AH186,Model!AM186,Model!AR186,Model!AW186,Model!BB186,Model!BG186,Model!BL186,Model!BQ186,Model!BV186,Model!CA186),"") -> 0.16633757 | L13: =IFERROR(MAX(Model!C186,Model!D186,Model!E186,Model!F186,Model!G186,Model!H186,Model!I186,Model!N186,Model!S186,Model!X186,Model!AC186,Model!AH186,Model!AM186,Model!AR186,Model!AW186,Model!BB186,Model!BG186,Model!BL186,Model!BQ186,Model!BV186,Model!CA186),"") -> 0.27825659 | N13: Adjusted EBITDA margin % | O13: 0.27825659 | P13: 0.26832593 | Q13: 0.27925035 | R13: 0.28918307 | S13: 0.29774089 | T13: 0.30074926 | V13: 0.21130165 | W13: 0.16633757 | X13: 0.27825659 | Z13: Adjusted EBITDA margin % | AA13: 0.27825659 | AB13: 0.26383962 | AC13: 0.24689273 | AD13: 0.25881681 | AE13: 0.26990929 | AF13: 0.27699201 | AH13: 0.21130165 | AI13: 0.16633757 | AJ13: 0.27825659
B15: Operating Income (GAAP) | C15: =Model!CA143 -> 2606.512 | D15: =Model!CF143 -> 2760.6125 | E15: =Model!CG143 -> 3275.4148 | F15: =Model!CH143 -> 3781.3271 | G15: =Model!CI143 -> 4347.4089 | H15: =Model!CJ143 -> 4815.1564 | I15: =IFERROR((H15/C15)^(1/5)-1,"n/m") -> 0.130603 | N15: Earnings from Operations (GAAP) | O15: 2606.512 | P15: 2800.1433 | Q15: 3571.1942 | R15: 4179.3287 | S15: 4864.1748 | T15: 5429.1156 | U15: 0.1580675 | Z15: Earnings from Operations (GAAP) | AA15: 2606.512 | AB15: 2704.7593 | AC15: 2857.438 | AD15: 3245.6335 | AE15: 3678.8189 | AF15: 4000.4025 | AG15: 0.089453734
B16: Operating income y/y % | D16: =IFERROR(D15/C15-1,"") -> 0.059121329 | E16: =IFERROR(E15/D15-1,"") -> 0.18648119 | F16: =IFERROR(F15/E15-1,"") -> 0.15445748 | G16: =IFERROR(G15/F15-1,"") -> 0.14970453 | H16: =IFERROR(H15/G15-1,"") -> 0.10759225 | N16: Earnings from operations y/y % | P16: 0.07428751 | Q16: 0.27536123 | R16: 0.17028885 | S16: 0.16386509 | T16: 0.11614319 | Z16: Earnings from operations y/y % | AB16: 0.037693021 | AC16: 0.056448177 | AD16: 0.13585436 | AE16: 0.13346714 | AF16: 0.087414901
B17: Operating margin (GAAP) % | C17: =IFERROR(C15/C9,"") -> 0.23138636 | D17: =IFERROR(D15/D9,"") -> 0.20789019 | E17: =IFERROR(E15/E9,"") -> 0.20611898 | F17: =IFERROR(F15/F9,"") -> 0.22094751 | G17: =IFERROR(G15/G9,"") -> 0.23587664 | H17: =IFERROR(H15/H9,"") -> 0.24359771 | J17: =IFERROR(AVERAGE(Model!C223,Model!D223,Model!E223,Model!F223,Model!G223,Model!H223,Model!I223,Model!N223,Model!S223,Model!X223,Model!AC223,Model!AH223,Model!AM223,Model!AR223,Model!AW223,Model!BB223,Model!BG223,Model!BL223,Model!BQ223,Model!BV223,Model!CA223),"") -> 0.16172099 | K17: =IFERROR(MIN(Model!C223,Model!D223,Model!E223,Model!F223,Model!G223,Model!H223,Model!I223,Model!N223,Model!S223,Model!X223,Model!AC223,Model!AH223,Model!AM223,Model!AR223,Model!AW223,Model!BB223,Model!BG223,Model!BL223,Model!BQ223,Model!BV223,Model!CA223),"") -> 0.10837063 | L17: =IFERROR(MAX(Model!C223,Model!D223,Model!E223,Model!F223,Model!G223,Model!H223,Model!I223,Model!N223,Model!S223,Model!X223,Model!AC223,Model!AH223,Model!AM223,Model!AR223,Model!AW223,Model!BB223,Model!BG223,Model!BL223,Model!BQ223,Model!BV223,Model!CA223),"") -> 0.23138636 | N17: Operating margin (GAAP) % | O17: 0.23138636 | P17: 0.20967386 | Q17: 0.21911842 | R17: 0.23305046 | S17: 0.24667922 | T17: 0.25157926 | V17: 0.16172099 | W17: 0.10837063 | X17: 0.23138636 | Z17: Operating margin (GAAP) % | AA17: 0.23138636 | AB17: 0.20501109 | AC17: 0.18601738 | AD17: 0.20187208 | AE17: 0.21850526 | AF17: 0.22772941 | AH17: 0.16172099 | AI17: 0.10837063 | AJ17: 0.23138636
B19: Adjusted Income from Continuing Operations (company definition) | C19: =Model!CA204 -> 2006.6128 | D19: =Model!CF204 -> 2198.8669 | E19: =Model!CG204 -> 2534.0651 | F19: =Model!CH204 -> 2863.4046 | G19: =Model!CI204 -> 3235.3756 | H19: =Model!CJ204 -> 3554.506 | I19: =IFERROR((H19/C19)^(1/5)-1,"n/m") -> 0.12114848 | N19: Adjusted Net Earnings (continuing ops, attributable to MLM) | O19: 2006.6128 | P19: 2230.3335 | Q19: 2768.1088 | R19: 3082.9111 | S19: 3531.9508 | T19: 3909.3837 | U19: 0.14269136 | Z19: Adjusted Net Earnings (continuing ops, attributable to MLM) | AA19: 2006.6128 | AB19: 2154.4078 | AC19: 2203.2598 | AD19: 2499.9927 | AE19: 2792.5323 | AF19: 3012.3888 | AG19: 0.084649668
B21: FDSO (m) | C21: =Model!CA161 -> 406.197 | D21: =Model!CF161 -> 408.65292 | E21: =Model!CG161 -> 412.24106 | F21: =Model!CH161 -> 404.10611 | G21: =Model!CI161 -> 396.46197 | H21: =Model!CJ161 -> 388.66912 | I21: =IFERROR((H21/C21)^(1/5)-1,"n/m") -> -0.0087831742 | N21: FDSO (m) | O21: 406.197 | P21: 408.65292 | Q21: 406.01869 | R21: 390.64137 | S21: 380.77091 | T21: 370.63671 | U21: -0.018156333 | Z21: FDSO (m) | AA21: 406.197 | AB21: 408.65292 | AC21: 417.28008 | AD21: 416.05183 | AE21: 411.48676 | AF21: 406.20651 | AG21: 4.6800254e-06
B23: Adjusted EPS — Diluted ($) | C23: =Model!CA206 -> 4.9399991 | D23: =Model!CF206 -> 5.380769 | E23: =Model!CG206 -> 6.1470469 | F23: =Model!CH206 -> 7.0857742 | G23: =Model!CI206 -> 8.1606204 | H23: =Model!CJ206 -> 9.1453264 | I23: =IFERROR((H23/C23)^(1/5)-1,"n/m") -> 0.13108298 | N23: Adjusted EPS — Diluted ($) | O23: 4.9399991 | P23: 5.4577697 | Q23: 6.8176881 | R23: 7.8919215 | S23: 9.2757895 | T23: 10.547751 | U23: 0.1638221 | Z23: Adjusted EPS — Diluted ($) | AA23: 4.9399991 | AB23: 5.2719747 | AC23: 5.2800504 | AD23: 6.0088492 | AE23: 6.7864451 | AF23: 7.4159048 | AG23: 0.084644592
B24: EPS y/y % | D24: =IFERROR(D23/C23-1,"") -> 0.089224684 | E24: =IFERROR(E23/D23-1,"") -> 0.14241047 | F24: =IFERROR(F23/E23-1,"") -> 0.15271192 | G24: =IFERROR(G23/F23-1,"") -> 0.15169073 | H24: =IFERROR(H23/G23-1,"") -> 0.12066558 | N24: EPS y/y % | P24: 0.10481186 | Q24: 0.2491711 | R24: 0.15756564 | S24: 0.17535247 | T24: 0.13712703 | Z24: EPS y/y % | AB24: 0.067201546 | AC24: 0.0015318177 | AD24: 0.13802875 | AE24: 0.12940846 | AF24: 0.092752493
B26: P / E (x) — assumed (adjusted EPS; CTAS 5-yr range ~30–50x) | F26: 35 | G26: 35 | H26: 35 | N26: P / E (x) — assumed (adjusted EPS) | R26: 35 | S26: 35 | T26: 35 | Z26: P / E (x) — assumed (adjusted EPS) | AD26: 35 | AE26: 35 | AF26: 35
B27: Price Target ($) | F27: =F26*F23 -> 248.0021 | G27: =G26*G23 -> 285.62171 | H27: =H26*H23 -> 320.08642 | N27: Price Target ($) | R27: 276.21725 | S27: 324.65263 | T27: 369.17128 | Z27: Price Target ($) | AD27: 210.30972 | AE27: 237.52558 | AF27: 259.55667
B28: Upside / (Downside) vs current | F28: =IFERROR(F27/$K$2-1,"") -> 0.24655489 | G28: =IFERROR(G27/$K$2-1,"") -> 0.43564571 | H28: =IFERROR(H27/$K$2-1,"") -> 0.60887874 | N28: Upside / (Downside) vs current | R28: 0.38837524 | S28: 0.63183026 | T28: 0.8555983 | Z28: Upside / (Downside) vs current | AD28: 0.057098375 | AE28: 0.19389585 | AF28: 0.30463267
B29: IRR (to May-Y-1) | F29: =IFERROR((F27/$K$2)^(1/((DATE(2029-1,5,31)-$K$3)/365.25))-1,"") -> 0.14281109 | G29: =IFERROR((G27/$K$2)^(1/((DATE(2030-1,5,31)-$K$3)/365.25))-1,"") -> 0.14619304 | H29: =IFERROR((H27/$K$2)^(1/((DATE(2031-1,5,31)-$K$3)/365.25))-1,"") -> 0.13917023 | N29: IRR (to Dec-Y-1) | R29: 0.21988658 | S29: 0.20294967 | T29: 0.18458497 | Z29: IRR (to Dec-Y-1) | AD29: 0.03420639 | AE29: 0.069156586 | AF29: 0.075584347
B31: Free Cash Flow | C31: =Model!CA256 -> 1881.175 | D31: =Model!CF256 -> 2009.9481 | E31: =Model!CG256 -> 2397.711 | F31: =Model!CH256 -> 2757.8852 | G31: =Model!CI256 -> 3159.1046 | H31: =Model!CJ256 -> 3506.6834 | I31: =IFERROR((H31/C31)^(1/5)-1,"n/m") -> 0.13264411 | N31: Free Cash Flow | O31: 1881.175 | P31: 2023.6158 | Q31: 2588.0985 | R31: 2927.4937 | S31: 3401.5983 | T31: 3803.2115 | U31: 0.1511827 | Z31: Free Cash Flow | AA31: 1881.175 | AB31: 1988.1156 | AC31: 2125.8818 | AD31: 2458.9521 | AE31: 2784.0009 | AF31: 3035.2445 | AG31: 0.10040587
B32: FCF % | C32: =IFERROR(C31/C9,"") -> 0.16699644 | D32: =IFERROR(D31/D9,"") -> 0.1513608 | E32: =IFERROR(E31/E9,"") -> 0.15088585 | F32: =IFERROR(F31/F9,"") -> 0.16114657 | G32: =IFERROR(G31/G9,"") -> 0.17140301 | H32: =IFERROR(H31/H9,"") -> 0.17740235 | J32: =IFERROR(AVERAGE(Model!C260,Model!D260,Model!E260,Model!F260,Model!G260,Model!H260,Model!I260,Model!N260,Model!S260,Model!X260,Model!AC260,Model!AH260,Model!AM260,Model!AR260,Model!AW260,Model!BB260,Model!BG260,Model!BL260,Model!BQ260,Model!BV260,Model!CA260),"") -> 0.11193542 | K32: =IFERROR(MIN(Model!C260,Model!D260,Model!E260,Model!F260,Model!G260,Model!H260,Model!I260,Model!N260,Model!S260,Model!X260,Model!AC260,Model!AH260,Model!AM260,Model!AR260,Model!AW260,Model!BB260,Model!BG260,Model!BL260,Model!BQ260,Model!BV260,Model!CA260),"") -> 0.03882614 | L32: =IFERROR(MAX(Model!C260,Model!D260,Model!E260,Model!F260,Model!G260,Model!H260,Model!I260,Model!N260,Model!S260,Model!X260,Model!AC260,Model!AH260,Model!AM260,Model!AR260,Model!AW260,Model!BB260,Model!BG260,Model!BL260,Model!BQ260,Model!BV260,Model!CA260),"") -> 0.1740522 | N32: FCF % | O32: 0.16699644 | P32: 0.15152773 | Q32: 0.15879843 | R32: 0.16324482 | S32: 0.17250688 | T32: 0.17623665 | V32: 0.11193542 | W32: 0.03882614 | X32: 0.1740522 | Z32: FCF % | AA32: 0.16699644 | AB32: 0.15069205 | AC32: 0.13839354 | AD32: 0.15294203 | AE32: 0.1653571 | AF32: 0.17278623 | AH32: 0.11193542 | AI32: 0.03882614 | AJ32: 0.1740522
B33: FCF / share ($) | C33: =IFERROR(C31/C21,"") -> 4.6311888 | D33: =IFERROR(D31/D21,"") -> 4.9184725 | E33: =IFERROR(E31/E21,"") -> 5.8162837 | F33: =IFERROR(F31/F21,"") -> 6.8246561 | G33: =IFERROR(G31/G21,"") -> 7.9682413 | H33: =IFERROR(H31/H21,"") -> 9.0222845 | N33: FCF / share ($) | O33: 4.6311888 | P33: 4.9519182 | Q33: 6.3743335 | R33: 7.4940699 | S33: 8.933451 | T33: 10.261292 | Z33: FCF / share ($) | AA33: 4.6311888 | AB33: 4.8650468 | AC33: 5.0946162 | AD33: 5.9102062 | AE33: 6.7657122 | AF33: 7.4721711
B34: FCF Yield (on PT) | F34: =IFERROR(F33/F$27,"") -> 0.027518542 | G34: =IFERROR(G33/G$27,"") -> 0.027897884 | H34: =IFERROR(H33/H$27,"") -> 0.028187026 | N34: FCF Yield (on PT) | R34: 0.027131071 | S34: 0.027516952 | T34: 0.027795477 | Z34: FCF Yield (on PT) | AD34: 0.028102392 | AE34: 0.028484141 | AF34: 0.028788207
B35: Adjusted EBITDA — pro forma (FY2027E incl. UniFirst full year) | C35: =Model!CA194 -> 3134.494 | D35: =Model!CF194 -> 3717.3788 | E35: =Model!CG194 -> 4235.7965 | F35: =Model!CH194 -> 4747.3834 | G35: =Model!CI194 -> 5290.6216 | H35: =Model!CJ194 -> 5787.3754 | I35: =IFERROR((H35/C35)^(1/5)-1,"n/m") -> 0.13047989 | N35: Adjusted EBITDA — pro forma (2026E incl. LNA full year) | O35: 3134.494 | P35: 3762.7976 | Q35: 4551.225 | R35: 5185.9633 | S35: 5871.0407 | T35: 6490.211 | U35: 0.15669344 | Z35: Adjusted EBITDA — pro forma (2026E incl. LNA full year) | AA35: 3134.494 | AB35: 3653.4022 | AC35: 3792.5525 | AD35: 4161.1723 | AE35: 4544.2724 | AF35: 4865.7725 | AG35: 0.091935213
B36: Adjusted EBITDA (pro forma) % of revenues | C36: =IFERROR(C35/C9,"") -> 0.27825659 | D36: =IFERROR(D35/D9,"") -> 0.27994027 | E36: =IFERROR(E35/E9,"") -> 0.26655496 | F36: =IFERROR(F35/F9,"") -> 0.27739535 | G36: =IFERROR(G35/G9,"") -> 0.28705238 | H36: =IFERROR(H35/H9,"") -> 0.29278206 | J36: =IFERROR(AVERAGE(Model!C221,Model!D221,Model!E221,Model!F221,Model!G221,Model!H221,Model!I221,Model!N221,Model!S221,Model!X221,Model!AC221,Model!AH221,Model!AM221,Model!AR221,Model!AW221,Model!BB221,Model!BG221,Model!BL221,Model!BQ221,Model!BV221,Model!CA221),"") -> 0.21130165 | K36: =IFERROR(MIN(Model!C221,Model!D221,Model!E221,Model!F221,Model!G221,Model!H221,Model!I221,Model!N221,Model!S221,Model!X221,Model!AC221,Model!AH221,Model!AM221,Model!AR221,Model!AW221,Model!BB221,Model!BG221,Model!BL221,Model!BQ221,Model!BV221,Model!CA221),"") -> 0.16633757 | L36: =IFERROR(MAX(Model!C221,Model!D221,Model!E221,Model!F221,Model!G221,Model!H221,Model!I221,Model!N221,Model!S221,Model!X221,Model!AC221,Model!AH221,Model!AM221,Model!AR221,Model!AW221,Model!BB221,Model!BG221,Model!BL221,Model!BQ221,Model!BV221,Model!CA221),"") -> 0.27825659 | N36: Adjusted EBITDA (pro forma) % of revenues | O36: 0.27825659 | P36: 0.28175711 | Q36: 0.27925035 | R36: 0.28918307 | S36: 0.29774089 | T36: 0.30074926 | V36: 0.21130165 | W36: 0.16633757 | X36: 0.27825659 | Z36: Adjusted EBITDA (pro forma) % of revenues | AA36: 0.27825659 | AB36: 0.27691483 | AC36: 0.24689273 | AD36: 0.25881681 | AE36: 0.26990929 | AF36: 0.27699201 | AH36: 0.21130165 | AI36: 0.16633757 | AJ36: 0.27825659
B38: Net Debt | C38: =Model!CA389 -> 2139.055 | D38: =Model!CF389 -> 4265.6506 | E38: =Model!CG389 -> 5294.7456 | F38: =Model!CH389 -> 5934.2292 | G38: =Model!CI389 -> 6613.2771 | H38: =Model!CJ389 -> 7234.2192 | N38: Net Debt | O38: 2139.055 | P38: 4251.9828 | Q38: 7964.6438 | R38: 9075.4358 | S38: 10274.321 | T38: 11357.869 | Z38: Net Debt | AA38: 2139.055 | AB38: 4287.4831 | AC38: 3222.9808 | AD38: 3120.8792 | AE38: 3408.2043 | AF38: 3649.3294
B39: Net Debt / Adjusted EBITDA (x) | C39: =IFERROR(C38/C35,"") -> 0.68242434 | D39: =IFERROR(D38/D35,"") -> 1.1474888 | E39: =IFERROR(E38/E35,"") -> 1.25 | F39: =IFERROR(F38/F35,"") -> 1.25 | G39: =IFERROR(G38/G35,"") -> 1.25 | H39: =IFERROR(H38/H35,"") -> 1.25 | N39: Net Debt / Adjusted EBITDA (x) | O39: 0.68242434 | P39: 1.1300057 | Q39: 1.75 | R39: 1.75 | S39: 1.75 | T39: 1.75 | Z39: Net Debt / Adjusted EBITDA (x) | AA39: 0.68242434 | AB39: 1.173559 | AC39: 0.84981838 | AD39: 0.75 | AE39: 0.75 | AF39: 0.75
B40: Share repurchases ($m) | D40: =Model!CF269 -> 544.71 | E40: =Model!CG269 -> 2165.4265 | F40: =Model!CH269 -> 1993.7879 | G40: =Model!CI269 -> 2279.7427 | H40: =Model!CJ269 -> 2406.051 | N40: Share repurchases ($m) | P40: 544.71 | Q40: 4839.38 | R40: 2467.175 | S40: 2884.4019 | T40: 3020.4887 | AB40: 544.71 | AC40: 0 | AD40: 1126.9745 | AE40: 1672.5501 | AF40: 1701.6553
B41: Implied avg buyback price ($) | D41: =Model!CF268 -> 198.95 | E41: =Model!CG268 -> 214.866 | F41: =Model!CH268 -> 232.05528 | G41: =Model!CI268 -> 250.6197 | H41: =Model!CJ268 -> 270.66928 | N41: Implied avg buyback price ($) | P41: 198.95 | Q41: 214.866 | R41: 232.05528 | S41: 250.6197 | T41: 270.66928 | AB41: 198.95 | AC41: 214.866 | AD41: 232.05528 | AE41: 250.6197 | AF41: 270.66928
B42: Shares repurchased (m) | D42: =Model!CF270 -> 2.7379241 | E42: =Model!CG270 -> 10.078032 | F42: =Model!CH270 -> 8.5918663 | G42: =Model!CI270 -> 9.0964225 | H42: =Model!CJ270 -> 8.8892653 | N42: Shares repurchased (m) | P42: 2.7379241 | Q42: 22.522781 | R42: 10.631842 | S42: 11.509079 | T42: 11.159333 | AB42: 2.7379241 | AC42: 0 | AD42: 4.8564916 | AE42: 6.6736575 | AF42: 6.2868433
B44: ROIC | C44: =Model!CA390 -> 0.287517 | D44: =Model!CF390 -> 0.18308741 | E44: =Model!CG390 -> 0.2048718 | F44: =Model!CH390 -> 0.22262944 | G44: =Model!CI390 -> 0.23991568 | H44: =Model!CJ390 -> 0.25138704 | J44: =IFERROR(AVERAGE(Model!C390,Model!D390,Model!E390,Model!F390,Model!G390,Model!H390,Model!I390,Model!N390,Model!S390,Model!X390,Model!AC390,Model!AH390,Model!AM390,Model!AR390,Model!AW390,Model!BB390,Model!BG390,Model!BL390,Model!BQ390,Model!BV390,Model!CA390),"") -> 0.16312603 | K44: =IFERROR(MIN(Model!C390,Model!D390,Model!E390,Model!F390,Model!G390,Model!H390,Model!I390,Model!N390,Model!S390,Model!X390,Model!AC390,Model!AH390,Model!AM390,Model!AR390,Model!AW390,Model!BB390,Model!BG390,Model!BL390,Model!BQ390,Model!BV390,Model!CA390),"") -> 0.090413146 | L44: =IFERROR(MAX(Model!C390,Model!D390,Model!E390,Model!F390,Model!G390,Model!H390,Model!I390,Model!N390,Model!S390,Model!X390,Model!AC390,Model!AH390,Model!AM390,Model!AR390,Model!AW390,Model!BB390,Model!BG390,Model!BL390,Model!BQ390,Model!BV390,Model!CA390),"") -> 0.287517 | N44: ROIC | O44: 0.287517 | P44: 0.18528404 | Q44: 0.21813324 | R44: 0.23643235 | S44: 0.25425001 | T44: 0.26473558 | V44: 0.16312603 | W44: 0.090413146 | X44: 0.287517 | Z44: ROIC | AA44: 0.287517 | AB44: 0.1799342 | AC44: 0.18392833 | AD44: 0.20011311 | AE44: 0.21599548 | AF44: 0.22587688 | AH44: 0.16312603 | AI44: 0.090413146 | AJ44: 0.287517
B45: RONTA | C45: =Model!CA401 -> 0.4178046 | D45: =Model!CF401 -> 0.30047212 | E45: =Model!CG401 -> 0.36792426 | F45: =Model!CH401 -> 0.39844708 | G45: =Model!CI401 -> 0.42908117 | H45: =Model!CJ401 -> 0.4502397 | J45: =IFERROR(AVERAGE(Model!C401,Model!D401,Model!E401,Model!F401,Model!G401,Model!H401,Model!I401,Model!N401,Model!S401,Model!X401,Model!AC401,Model!AH401,Model!AM401,Model!AR401,Model!AW401,Model!BB401,Model!BG401,Model!BL401,Model!BQ401,Model!BV401,Model!CA401),"") -> 0.24978395 | K45: =IFERROR(MIN(Model!C401,Model!D401,Model!E401,Model!F401,Model!G401,Model!H401,Model!I401,Model!N401,Model!S401,Model!X401,Model!AC401,Model!AH401,Model!AM401,Model!AR401,Model!AW401,Model!BB401,Model!BG401,Model!BL401,Model!BQ401,Model!BV401,Model!CA401),"") -> 0.11892781 | L45: =IFERROR(MAX(Model!C401,Model!D401,Model!E401,Model!F401,Model!G401,Model!H401,Model!I401,Model!N401,Model!S401,Model!X401,Model!AC401,Model!AH401,Model!AM401,Model!AR401,Model!AW401,Model!BB401,Model!BG401,Model!BL401,Model!BQ401,Model!BV401,Model!CA401),"") -> 0.42247204 | N45: RONTA | O45: 0.4178046 | P45: 0.30326184 | Q45: 0.39593559 | R45: 0.43175728 | S45: 0.46737679 | T45: 0.48995258 | V45: 0.24978395 | W45: 0.11892781 | X45: 0.42247204 | Z45: RONTA | AA45: 0.4178046 | AB45: 0.29648263 | AC45: 0.26359059 | AD45: 0.28188056 | AE45: 0.31308484 | AF45: 0.33617157 | AH45: 0.24978395 | AI45: 0.11892781 | AJ45: 0.42247204
B47: Implied Market Cap (USDm) | F47: =F27*F21 -> 100219.16 | G47: =G27*G21 -> 113238.15 | H47: =H27*H21 -> 124407.71 | N47: Implied Market Cap (USDm) | R47: 107901.89 | S47: 123618.28 | T47: 136828.43 | Z47: Implied Market Cap (USDm) | AD47: 87499.745 | AE47: 97738.63 | AF47: 105433.61
B48: (+) Net Debt | F48: =F38 -> 5934.2292 | G48: =G38 -> 6613.2771 | H48: =H38 -> 7234.2192 | N48: (+) Net Debt & NCI | R48: 9075.4358 | S48: 10274.321 | T48: 11357.869 | Z48: (+) Net Debt & NCI | AD48: 3120.8792 | AE48: 3408.2043 | AF48: 3649.3294
B49: Implied Enterprise Value (USDm) | F49: =F47+F48 -> 106153.39 | G49: =G47+G48 -> 119851.42 | H49: =H47+H48 -> 131641.93 | N49: Implied Enterprise Value (USDm) | R49: 116977.32 | S49: 133892.6 | T49: 148186.3 | Z49: Implied Enterprise Value (USDm) | AD49: 90620.624 | AE49: 101146.83 | AF49: 109082.94
B50: Implied EV / Adjusted EBITDA (x) | F50: =IFERROR(F49/F35,"") -> 22.3604 | G50: =IFERROR(G49/G35,"") -> 22.653562 | H50: =IFERROR(H49/H35,"") -> 22.746395 | N50: Implied EV / Adjusted EBITDA (x) | R50: 22.556527 | S50: 22.805599 | T50: 22.832278 | Z50: Implied EV / Adjusted EBITDA (x) | AD50: 21.777667 | AE50: 22.258092 | AF50: 22.418421

Sheet DCF
B2: DCF VALUATION — CINTAS CORPORATION (CTAS)
B4: 1. WACC BUILD
B5: Risk-free rate (US 10Y govt) | C5: 0.045 | D5: Assumption (~US 10Y Treasury yield); update to market
B6: Equity risk premium | C6: 0.05 | D6: US implied ERP ~4.5–5.5% (Damodaran)
B7: Levered beta | C7: 0.95 | D7: Business-services / uniform peers (UniFirst, Aramark, Vestis, Rollins, ABM) ~0.8–1.1; recurring route-based revenue and >90% retention dampen cyclicality
B8: Cost of equity | C8: =C5+C7*C6 -> 0.0925
B9: Pre-tax cost of debt | C9: 0.05 | D9: A3/A- rated; UniFirst acquisition debt assumed at 5.0% (424B3); 4.0% 2032 and 6.15% 2036 notes outstanding
B10: Tax rate | C10: 0.21 | D10: Model FY2028E+ effective tax rate
B11: After-tax cost of debt | C11: =C9*(1-C10) -> 0.0395
B12: Target D/V | C12: 0.06 | D12: Net debt ~$4.3bn at FY2027E YE (post-UniFirst) vs ~$82bn market cap ($198.95 × ~413m shares) — ~5% D/V; 6% target
B13: WACC | C13: =C8*(1-C12)+C11*C12 -> 0.08932
B15: Valuation date (live) | C15: =TODAY() -> 46301 | D15: Periods = (31-May-FY − today) / 365.25; cash flows assumed at fiscal year-end
B16: 2. UNLEVERED FREE CASH FLOW BUILD (USDm)
D17: FY2027E | E17: FY2028E | F17: FY2029E | G17: FY2030E | H17: FY2031E | I17: FY2032E | J17: FY2033E | K17: FY2034E | L17: FY2035E | M17: FY2036E | N17: Terminal | P17: CAGR 27–31E | Q17: CAGR 27–36E
B18: Adj. EBIT less transaction & integration costs | D18: =Model!CF192-Model!CF141 -> 2760.6125 | E18: =Model!CG192-Model!CG141 -> 3275.4148 | F18: =Model!CH192-Model!CH141 -> 3781.3271 | G18: =Model!CI192-Model!CI141 -> 4347.4089 | H18: =Model!CJ192-Model!CJ141 -> 4815.1564 | I18: =H18*(1+I$26) -> 5152.2173 | J18: =I18*(1+J$26) -> 5487.1114 | K18: =J18*(1+K$26) -> 5816.3381 | L18: =K18*(1+L$26) -> 6136.2367 | M18: =L18*(1+M$26) -> 6443.0485 | P18: =(H18/D18)^(1/(COLUMNS(D18:H18)-1))-1 -> 0.14921487 | Q18: =(M18/D18)^(1/(COLUMNS(D18:M18)-1))-1 -> 0.098748867
B19: × (1 − tax rate) | D19: =1-$C$10 -> 0.79 | E19: =1-$C$10 -> 0.79 | F19: =1-$C$10 -> 0.79 | G19: =1-$C$10 -> 0.79 | H19: =1-$C$10 -> 0.79 | I19: =1-$C$10 -> 0.79 | J19: =1-$C$10 -> 0.79 | K19: =1-$C$10 -> 0.79 | ... M19: =1-$C$10 -> 0.79
B20: NOPAT | D20: =D18*D19 -> 2180.8838 | E20: =E18*E19 -> 2587.5777 | F20: =F18*F19 -> 2987.2484 | G20: =G18*G19 -> 3434.453 | H20: =H18*H19 -> 3803.9735 | I20: =I18*I19 -> 4070.2517 | J20: =J18*J19 -> 4334.818 | K20: =K18*K19 -> 4594.9071 | ... M20: =M18*M19 -> 5090.0084
B21: plus D&A (incl. UniFirst purchase accounting) | D21: =Model!CF157 -> 610.35888 | E21: =Model!CG157 -> 802.88175 | F21: =Model!CH157 -> 861.05634 | G21: =Model!CI157 -> 908.21279 | H21: =Model!CJ157 -> 972.21901 | I21: =H21*(1+I$26) -> 1040.2743 | J21: =I21*(1+J$26) -> 1107.8922 | K21: =J21*(1+K$26) -> 1174.3657 | L21: =K21*(1+L$26) -> 1238.9558 | M21: =L21*(1+M$26) -> 1300.9036
B22: − Capex and bolt-on acquisitions (M&A FY2028E–31E) | D22: =Model!CF237 -> -491.32987 | E22: =Model!CG237+Model!CG238 -> -919.74484 | F22: =Model!CH237+Model!CH238 -> -1017.4515 | G22: =Model!CI237+Model!CI238 -> -1118.8035 | H22: =Model!CJ237+Model!CJ238 -> -1220.9067 | I22: =Model!CJ237*(1+I$26) -> -824.87013 | J22: =I22*(1+J$26) -> -878.48669 | K22: =J22*(1+K$26) -> -931.19589 | L22: =K22*(1+L$26) -> -982.41167 | M22: =L22*(1+M$26) -> -1031.5322
B23: − Δ Working capital (CF statement) | D23: =Model!CF235 -> -307.19689 | E23: =Model!CG235 -> -339.26755 | F23: =Model!CH235 -> -368.43887 | G23: =Model!CI235 -> -402.12689 | H23: =Model!CJ235 -> -422.40592 | I23: =H23*(1+I$26) -> -451.97434 | J23: =I23*(1+J$26) -> -481.35267 | K23: =J23*(1+K$26) -> -510.23383 | L23: =K23*(1+L$26) -> -538.29669 | M23: =L23*(1+M$26) -> -565.21153
B24: Unlevered FCF | D24: =D20+D21+D22+D23 -> 1992.716 | E24: =E20+E21+E22+E23 -> 2131.447 | F24: =F20+F21+F22+F23 -> 2462.4143 | G24: =G20+G21+G22+G23 -> 2821.7354 | H24: =H20+H21+H22+H23 -> 3132.8799 | I24: =I20+I21+I22+I23 -> 3833.6815 | J24: =J20+J21+J22+J23 -> 4082.8708 | K24: =K20+K21+K22+K23 -> 4327.8431 | ... M24: =M20+M21+M22+M23 -> 4794.1682 | N24: =M24*(1+$C$27) -> 4985.9349 | P24: =(H24/D24)^(1/(COLUMNS(D24:H24)-1))-1 -> 0.11975907 | Q24: =(M24/D24)^(1/(COLUMNS(D24:M24)-1))-1 -> 0.10246065
B25: Terminal Value (Gordon Growth) | N25: =N24/($C$13-$C$27) -> 101093.57
B26: Fade-period growth (FY2032E–36E; 7% → 5% linear) | I26: 0.07 | J26: =I26+($M$26-$I$26)/4 -> 0.065 | K26: =J26+($M$26-$I$26)/4 -> 0.06 | L26: =K26+($M$26-$I$26)/4 -> 0.055 | M26: 0.05
B27: Terminal growth rate | C27: 0.04
B29: Discount period (years) | D29: =(DATE(2027,5,31)-$C$15)/365.25 -> 0.64887064 | E29: =(DATE(2028,5,31)-$C$15)/365.25 -> 1.650924 | F29: =(DATE(2029,5,31)-$C$15)/365.25 -> 2.6502396 | G29: =(DATE(2030,5,31)-$C$15)/365.25 -> 3.6495551 | H29: =(DATE(2031,5,31)-$C$15)/365.25 -> 4.6488706 | I29: =(DATE(2032,5,31)-$C$15)/365.25 -> 5.650924 | J29: =(DATE(2033,5,31)-$C$15)/365.25 -> 6.6502396 | K29: =(DATE(2034,5,31)-$C$15)/365.25 -> 7.6495551 | L29: =(DATE(2035,5,31)-$C$15)/365.25 -> 8.6488706 | M29: =(DATE(2036,5,31)-$C$15)/365.25 -> 9.650924 | N29: =M29 -> 9.650924
B30: Discount factor | D30: =1/(1+$C$13)^D29 -> 0.94599949 | E30: =1/(1+$C$13)^E29 -> 0.86827866 | F30: =1/(1+$C$13)^F29 -> 0.79712987 | G30: =1/(1+$C$13)^G29 -> 0.73181118 | H30: =1/(1+$C$13)^H29 -> 0.67184485 | I30: =1/(1+$C$13)^I29 -> 0.61664785 | J30: =1/(1+$C$13)^J29 -> 0.56611827 | K30: =1/(1+$C$13)^K29 -> 0.51972921 | ... N30: =1/(1+$C$13)^N29 -> 0.4379407
B31: PV of UFCF | D31: =D24*D30 -> 1885.1083 | E31: =E24*E30 -> 1850.69 | F31: =F24*F30 -> 1962.864 | G31: =G24*G30 -> 2064.9775 | H31: =H24*H30 -> 2104.8093 | I31: =I24*I30 -> 2364.0315 | J31: =J24*J30 -> 2311.3878 | K31: =K24*K30 -> 2249.3065 | ... M31: =M24*M30 -> 2099.5614 | N31: =N25*N30 -> 44272.989
D32: Cintas' adjusted EBIT expenses stock-based compensation and deducts all D&A incl. ~$98m p.a. of UniFirst PPA amortization; transaction & integration costs deducted as cash costs. UniFirst consideration is captured through FY2027E net debt and the 14.07m shares issued.
B33: IMPLIED ROIC — invested capital roll-forward (USDm)
B34: Opening invested capital | D34: =Model!CA387+Model!CF335+Model!CF336 -> 12630.598 | E34: =D38 -> 12818.766 | F34: =E38 -> 13274.897 | G34: =F38 -> 13799.731 | H34: =G38 -> 14412.448 | I34: =H38 -> 15083.542 | J34: =I38 -> 15320.112 | K34: =J38 -> 15572.059 | L34: =K38 -> 15839.123 | M34: =L38 -> 16120.876
B35: plus Capex and acquisitions | D35: =-D22 -> 491.32987 | E35: =-E22 -> 919.74484 | F35: =-F22 -> 1017.4515 | G35: =-G22 -> 1118.8035 | H35: =-H22 -> 1220.9067 | I35: =-I22 -> 824.87013 | J35: =-J22 -> 878.48669 | K35: =-K22 -> 931.19589 | ... M35: =-M22 -> 1031.5322
B36: less DD&A | D36: =-D21 -> -610.35888 | E36: =-E21 -> -802.88175 | F36: =-F21 -> -861.05634 | G36: =-G21 -> -908.21279 | H36: =-H21 -> -972.21901 | I36: =-I21 -> -1040.2743 | J36: =-J21 -> -1107.8922 | K36: =-K21 -> -1174.3657 | ... M36: =-M21 -> -1300.9036
B37: plus Δ Working capital investment | D37: =-D23 -> 307.19689 | E37: =-E23 -> 339.26755 | F37: =-F23 -> 368.43887 | G37: =-G23 -> 402.12689 | H37: =-H23 -> 422.40592 | I37: =-I23 -> 451.97434 | J37: =-J23 -> 481.35267 | K37: =-K23 -> 510.23383 | ... M37: =-M23 -> 565.21153
B38: Closing invested capital | D38: =SUM(D34:D37) -> 12818.766 | E38: =SUM(E34:E37) -> 13274.897 | F38: =SUM(F34:F37) -> 13799.731 | G38: =SUM(G34:G37) -> 14412.448 | H38: =SUM(H34:H37) -> 15083.542 | I38: =SUM(I34:I37) -> 15320.112 | J38: =SUM(J34:J37) -> 15572.059 | K38: =SUM(K34:K37) -> 15839.123 | ... M38: =SUM(M34:M37) -> 16416.716
B39: NOPAT (row 20) | D39: =D20 -> 2180.8838 | E39: =E20 -> 2587.5777 | F39: =F20 -> 2987.2484 | G39: =G20 -> 3434.453 | H39: =H20 -> 3803.9735 | I39: =I20 -> 4070.2517 | J39: =J20 -> 4334.818 | K39: =K20 -> 4594.9071 | ... M39: =M20 -> 5090.0084
B40: Implied ROIC (NOPAT / avg. invested capital) | D40: =IFERROR(D39/AVERAGE(D34,D38),"") -> 0.17139005 | E40: =IFERROR(E39/AVERAGE(E34,E38),"") -> 0.19832997 | F40: =IFERROR(F39/AVERAGE(F34,F38),"") -> 0.22066774 | G40: =IFERROR(G39/AVERAGE(G34,G38),"") -> 0.24347308 | H40: =IFERROR(H39/AVERAGE(H34,H38),"") -> 0.25793157 | I40: =IFERROR(I39/AVERAGE(I34,I38),"") -> 0.26774754 | J40: =IFERROR(J39/AVERAGE(J34,J38),"") -> 0.28064185 | K40: =IFERROR(K39/AVERAGE(K34,K38),"") -> 0.29256505 | ... M40: =IFERROR(M39/AVERAGE(M34,M38),"") -> 0.3128694
B41: Reinvestment rate (net investment / NOPAT) | D41: =IFERROR(SUM(D35:D37)/D39,"") -> 0.086280561 | E41: =IFERROR(SUM(E35:E37)/E39,"") -> 0.17627709 | F41: =IFERROR(SUM(F35:F37)/F39,"") -> 0.17569148 | G41: =IFERROR(SUM(G35:G37)/G39,"") -> 0.17840325 | H41: =IFERROR(SUM(H35:H37)/H39,"") -> 0.1764191 | I41: =IFERROR(SUM(I35:I37)/I39,"") -> 0.058121744 | J41: =IFERROR(SUM(J35:J37)/J39,"") -> 0.058121744 | K41: =IFERROR(SUM(K35:K37)/K39,"") -> 0.058121744 | ... M41: =IFERROR(SUM(M35:M37)/M39,"") -> 0.058121744
B42: Implied terminal RONIC (g / reinvestment rate) | N42: =IFERROR($C$27/M41,"") -> 0.68821059
D43: Opening IC = Model FY2026A book IC (equity + net debt) + UniFirst total consideration ($5.35bn cash & shares), rolled forward with capex + M&A − D&A + ΔNWC.
B44: 3. VALUATION SUMMARY
B45: Sum of PV (explicit + fade) | C45: =SUM(D31:M31) -> 21071.304
B46: PV of Terminal Value | C46: =N31 -> 44272.989
B47: Enterprise Value | C47: =C45+C46 -> 65344.293
B48: Less: Net debt (Model FY2027E YE, post-UniFirst) | C48: =Model!CF389 -> 4265.6506 | D48: FY2027E year-end net debt includes the UniFirst cash consideration and $2.8bn acquisition debt; no non-controlling interests.
B49: Equity Value | C49: =C47-C48 -> 61078.643
B50: Diluted shares (m, Model FY2027E incl. UniFirst shares) | C50: =Model!CF413 -> 416.68008
B51: Implied share price ($) | C51: =C49/C50 -> 146.58403
B52: Current share price ($) | C52: =Model!CF412 -> 198.95
B53: Implied upside / (downside) | C53: =C51/C52-1 -> -0.26321174
B54: Required discount to DCF value for target IRR | C54: =1-((1+C13)/(1+H54))^H55 -> 0.15009005 | D54: vs. current | E54: Target IRR | H54: 0.15
B55: Max entry price for target IRR ($) | C55: =C51*(1-C54) -> 124.58322 | D55: =C55/C52-1 -> -0.37379633 | E55: Years for discount to close | H55: 3
B58: 4. SENSITIVITY: IMPLIED PRICE ($) — WACC × Terminal Growth
D60: WACC →
B61: Terminal growth ↓ | D61: =F61-0.01 -> 0.07932 | E61: =F61-0.005 -> 0.08432 | F61: =$C$13 -> 0.08932 | G61: =F61+0.005 -> 0.09432 | H61: =F61+0.01 -> 0.09932
B62: =B64-0.01 -> 0.03 | D62: {=IFERROR((SUMPRODUCT($D$24:$M$24/(1+D$61)^$D$29:$M$29)+($M$24*(1+$B62)/(D$61-$B62))/(1+D$61)^$M$29-$C$48)/$C$50,"")} -> 157.91273 | E62: {=IFERROR((SUMPRODUCT($D$24:$M$24/(1+E$61)^$D$29:$M$29)+($M$24*(1+$B62)/(E$61-$B62))/(1+E$61)^$M$29-$C$48)/$C$50,"")} -> 141.46838 | F62: {=IFERROR((SUMPRODUCT($D$24:$M$24/(1+F$61)^$D$29:$M$29)+($M$24*(1+$B62)/(F$61-$B62))/(1+F$61)^$M$29-$C$48)/$C$50,"")} -> 127.82298 | G62: {=IFERROR((SUMPRODUCT($D$24:$M$24/(1+G$61)^$D$29:$M$29)+($M$24*(1+$B62)/(G$61-$B62))/(1+G$61)^$M$29-$C$48)/$C$50,"")} -> 116.32294 | H62: {=IFERROR((SUMPRODUCT($D$24:$M$24/(1+H$61)^$D$29:$M$29)+($M$24*(1+$B62)/(H$61-$B62))/(1+H$61)^$M$29-$C$48)/$C$50,"")} -> 106.50328
B63: =B64-0.005 -> 0.035 | D63: {=IFERROR((SUMPRODUCT($D$24:$M$24/(1+D$61)^$D$29:$M$29)+($M$24*(1+$B63)/(D$61-$B63))/(1+D$61)^$M$29-$C$48)/$C$50,"")} -> 171.51082 | E63: {=IFERROR((SUMPRODUCT($D$24:$M$24/(1+E$61)^$D$29:$M$29)+($M$24*(1+$B63)/(E$61-$B63))/(1+E$61)^$M$29-$C$48)/$C$50,"")} -> 152.12828 | F63: {=IFERROR((SUMPRODUCT($D$24:$M$24/(1+F$61)^$D$29:$M$29)+($M$24*(1+$B63)/(F$61-$B63))/(1+F$61)^$M$29-$C$48)/$C$50,"")} -> 136.34005 | G63: {=IFERROR((SUMPRODUCT($D$24:$M$24/(1+G$61)^$D$29:$M$29)+($M$24*(1+$B63)/(G$61-$B63))/(1+G$61)^$M$29-$C$48)/$C$50,"")} -> 123.23645 | H63: {=IFERROR((SUMPRODUCT($D$24:$M$24/(1+H$61)^$D$29:$M$29)+($M$24*(1+$B63)/(H$61-$B63))/(1+H$61)^$M$29-$C$48)/$C$50,"")} -> 112.19068
B64: =$C$27 -> 0.04 | D64: {=IFERROR((SUMPRODUCT($D$24:$M$24/(1+D$61)^$D$29:$M$29)+($M$24*(1+$B64)/(D$61-$B64))/(1+D$61)^$M$29-$C$48)/$C$50,"")} -> 188.56721 | E64: {=IFERROR((SUMPRODUCT($D$24:$M$24/(1+E$61)^$D$29:$M$29)+($M$24*(1+$B64)/(E$61-$B64))/(1+E$61)^$M$29-$C$48)/$C$50,"")} -> 165.19339 | F64: {=IFERROR((SUMPRODUCT($D$24:$M$24/(1+F$61)^$D$29:$M$29)+($M$24*(1+$B64)/(F$61-$B64))/(1+F$61)^$M$29-$C$48)/$C$50,"")} -> 146.58403 | G64: {=IFERROR((SUMPRODUCT($D$24:$M$24/(1+G$61)^$D$29:$M$29)+($M$24*(1+$B64)/(G$61-$B64))/(1+G$61)^$M$29-$C$48)/$C$50,"")} -> 131.4227 | H64: {=IFERROR((SUMPRODUCT($D$24:$M$24/(1+H$61)^$D$29:$M$29)+($M$24*(1+$B64)/(H$61-$B64))/(1+H$61)^$M$29-$C$48)/$C$50,"")} -> 118.83686
B65: =B64+0.005 -> 0.045 | D65: {=IFERROR((SUMPRODUCT($D$24:$M$24/(1+D$61)^$D$29:$M$29)+($M$24*(1+$B65)/(D$61-$B65))/(1+D$61)^$M$29-$C$48)/$C$50,"")} -> 210.59341 | E65: {=IFERROR((SUMPRODUCT($D$24:$M$24/(1+E$61)^$D$29:$M$29)+($M$24*(1+$B65)/(E$61-$B65))/(1+E$61)^$M$29-$C$48)/$C$50,"")} -> 181.58127 | F65: {=IFERROR((SUMPRODUCT($D$24:$M$24/(1+F$61)^$D$29:$M$29)+($M$24*(1+$B65)/(F$61-$B65))/(1+F$61)^$M$29-$C$48)/$C$50,"")} -> 159.13937 | G65: {=IFERROR((SUMPRODUCT($D$24:$M$24/(1+G$61)^$D$29:$M$29)+($M$24*(1+$B65)/(G$61-$B65))/(1+G$61)^$M$29-$C$48)/$C$50,"")} -> 141.26877 | H65: {=IFERROR((SUMPRODUCT($D$24:$M$24/(1+H$61)^$D$29:$M$29)+($M$24*(1+$B65)/(H$61-$B65))/(1+H$61)^$M$29-$C$48)/$C$50,"")} -> 126.70655
B66: =B64+0.01 -> 0.05 | D66: {=IFERROR((SUMPRODUCT($D$24:$M$24/(1+D$61)^$D$29:$M$29)+($M$24*(1+$B66)/(D$61-$B66))/(1+D$61)^$M$29-$C$48)/$C$50,"")} -> 240.13197 | E66: {=IFERROR((SUMPRODUCT($D$24:$M$24/(1+E$61)^$D$29:$M$29)+($M$24*(1+$B66)/(E$61-$B66))/(1+E$61)^$M$29-$C$48)/$C$50,"")} -> 202.74417 | F66: {=IFERROR((SUMPRODUCT($D$24:$M$24/(1+F$61)^$D$29:$M$29)+($M$24*(1+$B66)/(F$61-$B66))/(1+F$61)^$M$29-$C$48)/$C$50,"")} -> 174.88782 | G66: {=IFERROR((SUMPRODUCT($D$24:$M$24/(1+G$61)^$D$29:$M$29)+($M$24*(1+$B66)/(G$61-$B66))/(1+G$61)^$M$29-$C$48)/$C$50,"")} -> 153.33643 | H66: {=IFERROR((SUMPRODUCT($D$24:$M$24/(1+H$61)^$D$29:$M$29)+($M$24*(1+$B66)/(H$61-$B66))/(1+H$61)^$M$29-$C$48)/$C$50,"")} -> 136.17189
B69: 5. REVERSE DCF
B70: To solve for the market-implied path: Data ▸ What-If Analysis ▸ Goal Seek — set C51 to the current price (C52) by changing C27 (terminal growth) or the fade-period growth inputs (I26:M26).
B72: 6. MAUBOUSSIN EV / NOPAT — TWO-STAGE FRAMEWORK
B73: EV/NOPAT = 1/r + [g × (1 − r/ROIIC) / (r × (r − g))] × [1 − ((1+g)/(1+r))^N]
B74: Formula source: Mauboussin & Rappaport, "Expectations Investing" (2021); Counterpoint Global, "What Does a Price-Earnings Multiple Mean?" (2020).
B76: Input | C76: Value | D76: Rationale (Cintas characteristics)
B77: r (Cost of capital / WACC) | C77: =$C$13 -> 0.08932 | D77: Linked from Section 1 WACC build
B78: g (NOPAT growth, Stage 1) | C78: 0.1 | D78: Model adjusted EBIT CAGR FY2027–31E: high-single-digit organic growth, margin expansion and UniFirst synergies → ~10% NOPAT growth
B79: ROIIC (Return on incremental invested capital) | C79: 0.25 | D79: Route density and garment reuse earn ~25–30% ROIC on organic investment (FY2026 ROIC ~29%); acquired growth earns less (goodwill)
B80: N (Years of value creation / CAP) | C80: 15 | D80: Largest North American route network (~1.5m customers combined), high retention, cross-sell runway (first aid, fire, hygiene); regulatory moats in fire inspection
B82: Calculation | C82: Value
B83: Steady-state component: 1 / r | C83: =1/C77 -> 11.195701
B84: Value-creation factor: 1 − r / ROIIC | C84: =1-C77/C79 -> 0.64272
B85: Growth multiplier: g × (1 − r/ROIIC) / (r × (r − g)) | C85: =C78*C84/(C77*(C77-C78)) -> -67.375476
B86: Time decay: 1 − ((1+g)/(1+r))^N | C86: =1-((1+C78)/(1+C77))^C80 -> -0.15759893
B87: PVGO component (growth value) | C87: =C85*C86 -> 10.618303
B88: Mauboussin EV / NOPAT (steady-state + PVGO) | C88: =C83+C87 -> 21.814004
B90: VALUATION — Applied to FY2029E NOPAT | C90: USDm
B91: FY2029E Adj. EBIT less transaction & integration costs | C91: =Model!CH192-Model!CH141 -> 3781.3271
B92: Tax rate (from WACC build) | C92: =$C$10 -> 0.21
B93: FY2029E NOPAT | C93: =C91*(1-C92) -> 2987.2484
B94: × Mauboussin EV/NOPAT multiple | C94: =C88 -> 21.814004
B95: Implied Enterprise Value (FY2029E basis) | C95: =C93*C94 -> 65163.847
B96: Less: FY2028E YE net debt (Model) | C96: =Model!CG389 -> 5294.7456
B97: Implied Equity Value | C97: =C95-C96 -> 59869.102
B98: Diluted shares FY2029E (m, Model) | C98: =Model!CH413 -> 400.41018
B99: Implied share price FY2029 ($) | C99: =C97/C98 -> 149.51943
B101: Current share price ($) | C101: =C52 -> 198.95
B102: Implied upside / (downside) | C102: =C99/C101-1 -> -0.24845725
B104: MARKET-IMPLIED EV/NOPAT TODAY | C104: USDm
B105: Current market cap (spot × diluted shares) | C105: =C52*C50 -> 82898.501
B106: Plus: FY2027E YE net debt | C106: =C48 -> 4265.6506
B107: Implied Enterprise Value (today) | C107: =C105+C106 -> 87164.152
B108: CTAS market-implied EV/NOPAT (on FY2029E NOPAT) | C108: =C107/C93 -> 29.178743
B110: Multiple gap (Mauboussin − Market) | C110: =C88-C108 -> -7.3647389
B111: Implied re-rating headroom | C111: =C88/C108-1 -> -0.25240083

Sheet Charts
B2: Cintas Corporation — Historical Operating Performance (FY2006–FY2026)
B3: All historicals · USDm · fiscal years ending 31-May · Linked to Model. Organic growth = company-published organic revenue growth (FY2007–09: reported growth — organic not disclosed in releases); acquisitions/FX/workdays = reported growth − organic.
C7: FY2006 | D7: FY2007 | E7: FY2008 | F7: FY2009 | G7: FY2010 | H7: FY2011 | I7: FY2012 | J7: FY2013 | K7: FY2014 | L7: FY2015 | M7: FY2016 | N7: FY2017 | O7: FY2018 | P7: FY2019 | Q7: FY2020 | R7: FY2021 | S7: FY2022 | T7: FY2023 | U7: FY2024 | V7: FY2025 | W7: FY2026
B8: Organic revenue growth % | C8: =IF(ISNUMBER(Model!C108),Model!C108,IF(ISNUMBER(Model!C106),Model!C106,0)) -> 0 | D8: =IF(ISNUMBER(Model!D108),Model!D108,IF(ISNUMBER(Model!D106),Model!D106,0)) -> 0.089108969 | E8: =IF(ISNUMBER(Model!E108),Model!E108,IF(ISNUMBER(Model!E106),Model!E106,0)) -> 0.062316221 | F8: =IF(ISNUMBER(Model!F108),Model!F108,IF(ISNUMBER(Model!F106),Model!F106,0)) -> -0.041447218 | G8: =IF(ISNUMBER(Model!G108),Model!G108,IF(ISNUMBER(Model!G106),Model!G106,0)) -> -0.064 | H8: =IF(ISNUMBER(Model!H108),Model!H108,IF(ISNUMBER(Model!H106),Model!H106,0)) -> 0.051 | I8: =IF(ISNUMBER(Model!I108),Model!I108,IF(ISNUMBER(Model!I106),Model!I106,0)) -> 0.061 | J8: =IF(ISNUMBER(Model!N108),Model!N108,IF(ISNUMBER(Model!N106),Model!N106,0)) -> 0.049 | K8: =IF(ISNUMBER(Model!S108),Model!S108,IF(ISNUMBER(Model!S106),Model!S106,0)) -> 0.059 | L8: =IF(ISNUMBER(Model!X108),Model!X108,IF(ISNUMBER(Model!X106),Model!X106,0)) -> 0.071 | M8: =IF(ISNUMBER(Model!AC108),Model!AC108,IF(ISNUMBER(Model!AC106),Model!AC106,0)) -> 0.067 | N8: =IF(ISNUMBER(Model!AH108),Model!AH108,IF(ISNUMBER(Model!AH106),Model!AH106,0)) -> 0.067 | O8: =IF(ISNUMBER(Model!AM108),Model!AM108,IF(ISNUMBER(Model!AM106),Model!AM106,0)) -> 0.071 | P8: =IF(ISNUMBER(Model!AR108),Model!AR108,IF(ISNUMBER(Model!AR106),Model!AR106,0)) -> 0.065 | Q8: =IF(ISNUMBER(Model!AW108),Model!AW108,IF(ISNUMBER(Model!AW106),Model!AW106,0)) -> 0.031 | R8: =IF(ISNUMBER(Model!BB108),Model!BB108,IF(ISNUMBER(Model!BB106),Model!BB106,0)) -> 0.002 | S8: =IF(ISNUMBER(Model!BG108),Model!BG108,IF(ISNUMBER(Model!BG106),Model!BG106,0)) -> 0.102 | T8: =IF(ISNUMBER(Model!BL108),Model!BL108,IF(ISNUMBER(Model!BL106),Model!BL106,0)) -> 0.122 | U8: =IF(ISNUMBER(Model!BQ108),Model!BQ108,IF(ISNUMBER(Model!BQ106),Model!BQ106,0)) -> 0.08 | V8: =IF(ISNUMBER(Model!BV108),Model!BV108,IF(ISNUMBER(Model!BV106),Model!BV106,0)) -> 0.08 | W8: =IF(ISNUMBER(Model!CA108),Model!CA108,IF(ISNUMBER(Model!CA106),Model!CA106,0)) -> 0.083
B9: Acquisitions, divestitures, FX & workdays % | C9: =IF(ISNUMBER(Model!C107),Model!C107,0) -> 0 | D9: =IF(ISNUMBER(Model!D107),Model!D107,0) -> 0 | E9: =IF(ISNUMBER(Model!E107),Model!E107,0) -> 0 | F9: =IF(ISNUMBER(Model!F107),Model!F107,0) -> 0 | G9: =IF(ISNUMBER(Model!G107),Model!G107,0) -> 0.0037708683 | H9: =IF(ISNUMBER(Model!H107),Model!H107,0) -> 0.023152766 | I9: =IF(ISNUMBER(Model!I107),Model!I107,0) -> 0.015531919 | J9: =IF(ISNUMBER(Model!N107),Model!N107,0) -> 0.0032844954 | K9: =IF(ISNUMBER(Model!S107),Model!S107,0) -> -0.0044783781 | L9: =IF(ISNUMBER(Model!X107),Model!X107,0) -> -0.087460697 | M9: =IF(ISNUMBER(Model!AC107),Model!AC107,0) -> 0.028729934 | N9: =IF(ISNUMBER(Model!AH107),Model!AH107,0) -> 0.018195511 | O9: =IF(ISNUMBER(Model!AM107),Model!AM107,0) -> 0.14563882 | P9: =IF(ISNUMBER(Model!AR107),Model!AR107,0) -> -0.00081988293 | Q9: =IF(ISNUMBER(Model!AW107),Model!AW107,0) -> -0.0030243002 | R9: =IF(ISNUMBER(Model!BB107),Model!BB107,0) -> 0.002406418 | S9: =IF(ISNUMBER(Model!BG107),Model!BG107,0) -> 0.0017217165 | T9: =IF(ISNUMBER(Model!BL107),Model!BL107,0) -> 0.00039035177 | U9: =IF(ISNUMBER(Model!BQ107),Model!BQ107,0) -> 0.0085737818 | V9: =IF(ISNUMBER(Model!BV107),Model!BV107,0) -> -0.0025178878 | W9: =IF(ISNUMBER(Model!CA107),Model!CA107,0) -> 0.0064162298
C11: =C7 -> FY2006 | D11: =D7 -> FY2007 | E11: =E7 -> FY2008 | F11: =F7 -> FY2009 | G11: =G7 -> FY2010 | H11: =H7 -> FY2011 | I11: =I7 -> FY2012 | J11: =J7 -> FY2013 | ... W11: =W7 -> FY2026
B12: Adjusted EBITDA | C12: =Model!C185 -> 707.491 | D12: =Model!D185 -> 753.323 | E12: =Model!E185 -> 769.358 | F12: =Model!F185 -> 695.754 | G12: =Model!G185 -> 604.599 | H12: =Model!H185 -> 633.81 | I12: =Model!I185 -> 733.792 | J12: =Model!N185 -> 754.588 | K12: =Model!S185 -> 802.496 | L12: =Model!X185 -> 851.489 | M12: =Model!AC185 -> 947.027 | N12: =Model!AH185 -> 1049.51 | O12: =Model!AM185 -> 1311.147 | P12: =Model!AR185 -> 1508.037 | Q12: =Model!AW185 -> 1541.749 | R12: =Model!BB185 -> 1751.413 | S12: =Model!BG185 -> 1944.791 | T12: =Model!BL185 -> 2211.826 | U12: =Model!BQ185 -> 2511.017 | V12: =Model!BV185 -> 2853.909 | W12: =Model!CA185 -> 3134.494
B13: Operating Income (GAAP) | C13: =Model!C143 -> 546.838 | D13: =Model!D143 -> 577.397 | E13: =Model!E143 -> 577.455 | F13: =Model!F143 -> 409.065 | G13: =Model!G143 -> 390.809 | H13: =Model!H143 -> 440.343 | I13: =Model!I143 -> 539.627 | J13: =Model!N143 -> 565.211 | K13: =Model!S143 -> 567.01 | L13: =Model!X143 -> 696.407 | M13: =Model!AC143 -> 781.748 | N13: =Model!AH143 -> 773.691 | O13: =Model!AM143 -> 949.834 | P13: =Model!AR143 -> 1133.534 | Q13: =Model!AW143 -> 1162.696 | R13: =Model!BB143 -> 1385.492 | S13: =Model!BG143 -> 1587.37 | T13: =Model!BL143 -> 1802.664 | U13: =Model!BQ143 -> 2068.633 | V13: =Model!BV143 -> 2359.726 | W13: =Model!CA143 -> 2606.512
B14: Adj. EBITDA Margin % | C14: =Model!C221 -> 0.20786501 | D14: =Model!D221 -> 0.20322183 | E14: =Model!E221 -> 0.19537266 | F14: =Model!F221 -> 0.18432108 | G14: =Model!G221 -> 0.17043733 | H14: =Model!H221 -> 0.16633757 | I14: =Model!I221 -> 0.1788864 | J14: =Model!N221 -> 0.17481595 | K14: =Model!S221 -> 0.17630254 | L14: =Model!X221 -> 0.19019671 | M14: =Model!AC221 -> 0.19305578 | N14: =Model!AH221 -> 0.19715102 | O14: =Model!AM221 -> 0.20244272 | P14: =Model!AR221 -> 0.21880016 | Q14: =Model!AW221 -> 0.21760379 | R14: =Model!BB221 -> 0.24611148 | S14: =Model!BG221 -> 0.24760343 | T14: =Model!BL221 -> 0.25089428 | U14: =Model!BQ221 -> 0.26165653 | V14: =Model!BV221 -> 0.27600184 | W14: =Model!CA221 -> 0.27825659
B15: GAAP Op. Margin % | C15: =Model!C223 -> 0.16066421 | D15: =Model!D223 -> 0.15576277 | E15: =Model!E223 -> 0.14664034 | F15: =Model!F223 -> 0.10837063 | G15: =Model!G223 -> 0.11016962 | H15: =Model!H223 -> 0.11556394 | I15: =Model!I223 -> 0.13155217 | J15: =Model!N223 -> 0.13094285 | K15: =Model!S223 -> 0.12456797 | L15: =Model!X223 -> 0.15555612 | M15: =Model!AC223 -> 0.1593629 | N15: =Model!AH223 -> 0.14533827 | O15: =Model!AM223 -> 0.14665555 | P15: =Model!AR223 -> 0.16446375 | Q15: =Model!AW223 -> 0.16410392 | R15: =Model!BB223 -> 0.19469165 | S15: =Model!BG223 -> 0.20209794 | T15: =Model!BL223 -> 0.20448176 | U15: =Model!BQ223 -> 0.21555861 | V15: =Model!BV223 -> 0.22820935 | W15: =Model!CA223 -> 0.23138636
C17: =C7 -> FY2006 | D17: =D7 -> FY2007 | E17: =E7 -> FY2008 | F17: =F7 -> FY2009 | G17: =G7 -> FY2010 | H17: =H7 -> FY2011 | I17: =I7 -> FY2012 | J17: =J7 -> FY2013 | ... W17: =W7 -> FY2026
B18: ROIC | C18: =IFERROR(Model!C390+0,NA()) -> 0.12935645 | D18: =IFERROR(Model!D390+0,NA()) -> 0.12511602 | E18: =IFERROR(Model!E390+0,NA()) -> 0.12139796 | F18: =IFERROR(Model!F390+0,NA()) -> 0.10684681 | G18: =IFERROR(Model!G390+0,NA()) -> 0.093676214 | H18: =IFERROR(Model!H390+0,NA()) -> 0.090413146 | I18: =IFERROR(Model!I390+0,NA()) -> 0.11058117 | J18: =IFERROR(Model!N390+0,NA()) -> 0.11312451 | K18: =IFERROR(Model!S390+0,NA()) -> 0.12640889 | L18: =IFERROR(Model!X390+0,NA()) -> 0.15631579 | M18: =IFERROR(Model!AC390+0,NA()) -> 0.16960235 | N18: =IFERROR(Model!AH390+0,NA()) -> 0.10818076 | O18: =IFERROR(Model!AM390+0,NA()) -> 0.17766481 | P18: =IFERROR(Model!AR390+0,NA()) -> 0.1596812 | Q18: =IFERROR(Model!AW390+0,NA()) -> 0.17103044 | R18: =IFERROR(Model!BB390+0,NA()) -> 0.20506706 | S18: =IFERROR(Model!BG390+0,NA()) -> 0.21185785 | T18: =IFERROR(Model!BL390+0,NA()) -> 0.23050852 | U18: =IFERROR(Model!BQ390+0,NA()) -> 0.25539029 | V18: =IFERROR(Model!BV390+0,NA()) -> 0.27590929 | W18: =IFERROR(Model!CA390+0,NA()) -> 0.287517
B19: RONTA | C19: =IFERROR(Model!C401+0,NA()) -> 0.20158201 | D19: =IFERROR(Model!D401+0,NA()) -> 0.2063609 | E19: =IFERROR(Model!E401+0,NA()) -> 0.1848696 | F19: =IFERROR(Model!F401+0,NA()) -> 0.15924901 | G19: =IFERROR(Model!G401+0,NA()) -> 0.12133033 | H19: =IFERROR(Model!H401+0,NA()) -> 0.11892781 | I19: =IFERROR(Model!I401+0,NA()) -> 0.15837102 | J19: =IFERROR(Model!N401+0,NA()) -> 0.16301309 | K19: =IFERROR(Model!S401+0,NA()) -> 0.15012245 | L19: =IFERROR(Model!X401+0,NA()) -> 0.18753029 | M19: =IFERROR(Model!AC401+0,NA()) -> 0.22991418 | N19: =IFERROR(Model!AH401+0,NA()) -> 0.20961788 | O19: =IFERROR(Model!AM401+0,NA()) -> 0.34473923 | P19: =IFERROR(Model!AR401+0,NA()) -> 0.2798589 | Q19: =IFERROR(Model!AW401+0,NA()) -> 0.27801834 | R19: =IFERROR(Model!BB401+0,NA()) -> 0.30314383 | S19: =IFERROR(Model!BG401+0,NA()) -> 0.35472976 | T19: =IFERROR(Model!BL401+0,NA()) -> 0.36672923 | U19: =IFERROR(Model!BQ401+0,NA()) -> 0.38707844 | V19: =IFERROR(Model!BV401+0,NA()) -> 0.42247204 | W19: =IFERROR(Model!CA401+0,NA()) -> 0.4178046
B20: Adj. EBITDA margin % | C20: =IFERROR(Model!C221+0,NA()) -> 0.20786501 | D20: =IFERROR(Model!D221+0,NA()) -> 0.20322183 | E20: =IFERROR(Model!E221+0,NA()) -> 0.19537266 | F20: =IFERROR(Model!F221+0,NA()) -> 0.18432108 | G20: =IFERROR(Model!G221+0,NA()) -> 0.17043733 | H20: =IFERROR(Model!H221+0,NA()) -> 0.16633757 | I20: =IFERROR(Model!I221+0,NA()) -> 0.1788864 | J20: =IFERROR(Model!N221+0,NA()) -> 0.17481595 | K20: =IFERROR(Model!S221+0,NA()) -> 0.17630254 | L20: =IFERROR(Model!X221+0,NA()) -> 0.19019671 | M20: =IFERROR(Model!AC221+0,NA()) -> 0.19305578 | N20: =IFERROR(Model!AH221+0,NA()) -> 0.19715102 | O20: =IFERROR(Model!AM221+0,NA()) -> 0.20244272 | P20: =IFERROR(Model!AR221+0,NA()) -> 0.21880016 | Q20: =IFERROR(Model!AW221+0,NA()) -> 0.21760379 | R20: =IFERROR(Model!BB221+0,NA()) -> 0.24611148 | S20: =IFERROR(Model!BG221+0,NA()) -> 0.24760343 | T20: =IFERROR(Model!BL221+0,NA()) -> 0.25089428 | U20: =IFERROR(Model!BQ221+0,NA()) -> 0.26165653 | V20: =IFERROR(Model!BV221+0,NA()) -> 0.27600184 | W20: =IFERROR(Model!CA221+0,NA()) -> 0.27825659
B21: FCF margin % | C21: =IFERROR(Model!C260+0,NA()) -> 0.089685416 | D21: =IFERROR(Model!D260+0,NA()) -> 0.072450565 | E21: =IFERROR(Model!E260+0,NA()) -> 0.089948958 | F21: =IFERROR(Model!F260+0,NA()) -> 0.096280882 | G21: =IFERROR(Model!G260+0,NA()) -> 0.12699491 | H21: =IFERROR(Model!H260+0,NA()) -> 0.041542795 | I21: =IFERROR(Model!I260+0,NA()) -> 0.075343735 | J21: =IFERROR(Model!N260+0,NA()) -> 0.082535479 | K21: =IFERROR(Model!S260+0,NA()) -> 0.1015835 | L21: =IFERROR(Model!X260+0,NA()) -> 0.08098397 | M21: =IFERROR(Model!AC260+0,NA()) -> 0.03882614 | N21: =IFERROR(Model!AH260+0,NA()) -> 0.09215384 | O21: =IFERROR(Model!AM260+0,NA()) -> 0.10691684 | P21: =IFERROR(Model!AR260+0,NA()) -> 0.11478645 | Q21: =IFERROR(Model!AW260+0,NA()) -> 0.14977784 | R21: =IFERROR(Model!BB260+0,NA()) -> 0.17105282 | S21: =IFERROR(Model!BG260+0,NA()) -> 0.16512315 | T21: =IFERROR(Model!BL260+0,NA()) -> 0.14368627 | U21: =IFERROR(Model!BQ260+0,NA()) -> 0.1740522 | V21: =IFERROR(Model!BV260+0,NA()) -> 0.16992169 | W21: =IFERROR(Model!CA260+0,NA()) -> 0.16699644
