Workbook

Sheet Model
B2: Moog Inc. — 3-Statement Financial Model | CO2: SCENARIO TOGGLE
B3: US GAAP as reported · USD millions · Fiscal year ends late September · Source: Moog 10-K and 10-Q filings (SEC EDGAR) | CO3: Base
B4: Segment structure changed in FY22: legacy 3 segments (Aircraft Controls, Space and Defense Controls, Industrial Systems) → current 4 segments (Military Aircraft, Commercial Aircraft, Space and Defense, Industrial).
CN5: FY20-FY25 | CO5: Selected scenario KPIs (FY30E)
B6: ($M) | C6: Q1/10 | D6: Q2/10 | E6: Q3/10 | F6: Q4/10 | G6: FY10 | H6: Q1/11 | I6: Q2/11 | J6: Q3/11 | K6: Q4/11 | L6: FY11 | M6: Q1/12 | N6: Q2/12 | O6: Q3/12 | P6: Q4/12 | Q6: FY12 | R6: Q1/13 | S6: Q2/13 | T6: Q3/13 | U6: Q4/13 | V6: FY13 | W6: Q1/14 | X6: Q2/14 | Y6: Q3/14 | Z6: Q4/14 | AA6: FY14 | AB6: Q1/15 | AC6: Q2/15 | AD6: Q3/15 | AE6: Q4/15 | AF6: FY15 | AG6: Q1/16 | AH6: Q2/16 | AI6: Q3/16 | AJ6: Q4/16 | AK6: FY16 | AL6: Q1/17 | AM6: Q2/17 | AN6: Q3/17 | AO6: Q4/17 | AP6: FY17 | AQ6: Q1/18 | AR6: Q2/18 | AS6: Q3/18 | AT6: Q4/18 | AU6: FY18 | AV6: Q1/19 | AW6: Q2/19 | AX6: Q3/19 | AY6: Q4/19 | AZ6: FY19 | BA6: Q1/20 | BB6: Q2/20 | BC6: Q3/20 | BD6: Q4/20 | BE6: FY20 | BF6: Q1/21 | BG6: Q2/21 | BH6: Q3/21 | BI6: Q4/21 | BJ6: FY21 | BK6: Q1/22 | BL6: Q2/22 | BM6: Q3/22 | BN6: Q4/22 | BO6: FY22 | BP6: Q1/23 | BQ6: Q2/23 | BR6: Q3/23 | BS6: Q4/23 | BT6: FY23 | BU6: Q1/24 | BV6: Q2/24 | BW6: Q3/24 | BX6: Q4/24 | BY6: FY24 | BZ6: Q1/25 | CA6: Q2/25 | CB6: Q3/25 | CC6: Q4/25 | CD6: FY25 | CE6: Q1/26 | CF6: Q2/26 | CG6: Q3/26E | CH6: Q4/26E | CI6: FY26E | CJ6: FY27E | CK6: FY28E | CL6: FY29E | CM6: FY30E | CN6: 5Y CAGR | CO6: FY30E Revenue ($M) | CP6: =CM98 -> 5581.8999 | CQ6: Modeling Comments & Assumptions
CO7: FY30E GAAP EBIT ($M) | CP7: =CM102 -> 757.94422
B8: SEGMENT P&L — LEGACY STRUCTURE (FY10–FY21) | CO8: FY30E EBIT margin % | CP8: =CM102/CM98 -> 0.13578606 | CQ8: Segment forecast assumptions
B9: Pre-FY22 reporting — 3 reportable segments: Aircraft Controls, Space and Defense Controls, Industrial Systems. (Components and Medical Devices were separate segments in early years; combined into Industrial Systems by FY15.) | CO9: FY30E ROIC | CP9: =CM284 -> 0
CO10: FY30E Adj EPS ($) | CP10: =CM156 -> 18.427098
B11: Aircraft Controls
B12: Net sales | G12: 756.55 | L12: 850.49 | Q12: 963.421 | V12: 1059.587 | AA12: 1117.656 | AF12: 1086.547 | AK12: 1063.718 | AP12: 1124.885 | AU12: 1193.505 | AZ12: 1302.972 | BE12: 1205.75 | BF12: 286.774 | BG12: 304.361 | BH12: 272.131 | BI12: =BJ12-SUM(BF12:BH12) -> 297.972 | BJ12: 1161.238 | BK12: 303.317 | BL12: 311.268 | BM12: 318.017 | BN12: =BO12-SUM(BK12:BM12) -> 323.859 | BO12: 1256.461 | BP12: 310.259 | BQ12: 347.004 | BR12: 355.025
B13: Operating profit | G13: 76.374 | L13: 83.776 | Q13: 104.582 | V13: 126.751 | AA13: 115.726 | AF13: 100.006 | AK13: 98.509 | AP13: 114.016 | AU13: 129.772 | AZ13: 122.701 | BE13: 34.67 | BF13: 27.922 | BG13: 22.018 | BH13: 20.545 | BI13: =BJ13-SUM(BF13:BH13) -> 26.193 | BJ13: 96.678 | BK13: 41.915 | BL13: 12.441 | BM13: 34.453 | BN13: =BO13-SUM(BK13:BM13) -> 34.811 | BO13: 123.62 | BP13: 29.718 | BQ13: 31.862 | BR13: 37.888
B14: Sales y/y % | L14: =L12/G12-1 -> 0.12416892 | Q14: =Q12/L12-1 -> 0.13278345 | V14: =V12/Q12-1 -> 0.099817214 | AA14: =AA12/V12-1 -> 0.054803428 | AF14: =AF12/AA12-1 -> -0.027834146 | AK14: =AK12/AF12-1 -> -0.021010596 | AP14: =AP12/AK12-1 -> 0.057503022 | AU14: =AU12/AP12-1 -> 0.061001791 | AZ14: =AZ12/AU12-1 -> 0.091718929 | BE14: =BE12/AZ12-1 -> -0.074615571 | BJ14: =BJ12/BE12-1 -> -0.036916442 | BK14: =BK12/BF12-1 -> 0.057686541 | BL14: =BL12/BG12-1 -> 0.022693446 | BM14: =BM12/BH12-1 -> 0.16861732 | BP14: =BP12/BK12-1 -> 0.022886947 | BQ14: =BQ12/BL12-1 -> 0.11480782 | BR14: =BR12/BM12-1 -> 0.11637114
B15: Operating margin % | G15: =G13/G12 -> 0.10095037 | L15: =L13/L12 -> 0.098503216 | Q15: =Q13/Q12 -> 0.10855275 | V15: =V13/V12 -> 0.11962302 | AA15: =AA13/AA12 -> 0.10354349 | AF15: =AF13/AF12 -> 0.092040197 | AK15: =AK13/AK12 -> 0.092608191 | AP15: =AP13/AP12 -> 0.10135792 | AU15: =AU13/AU12 -> 0.10873184 | AZ15: =AZ13/AZ12 -> 0.094170097 | BE15: =BE13/BE12 -> 0.028753888 | BF15: =BF13/BF12 -> 0.09736587 | BG15: =BG13/BG12 -> 0.072341726 | BH15: =BH13/BH12 -> 0.075496728 | BI15: =BI13/BI12 -> 0.087904233 | BJ15: =BJ13/BJ12 -> 0.083254251 | BK15: =BK13/BK12 -> 0.13818876 | BL15: =BL13/BL12 -> 0.039968773 | BM15: =BM13/BM12 -> 0.10833698 | BO15: =BO13/BO12 -> 0.098387455 | BP15: =BP13/BP12 -> 0.09578449 | BQ15: =BQ13/BQ12 -> 0.091820267 | BR15: =BR13/BR12 -> 0.10671925
B16: Backlog ($M) | G16: 567 | L16: 641 | Q16: 658 | V16: 671 | AA16: 715 | AF16: 678 | AK16: 632 | AP16: 571 | AU16: 755 | BO16: 5200
B17: Book-to-bill (Bookings / Sales)
B19: Space and Defense Controls
B20: Net sales | G20: 325.474 | L20: 355.762 | Q20: 358.755 | V20: 395.945 | AA20: 394.505 | AF20: 381.444 | AK20: 366.091 | AP20: 394.264 | AU20: 580.877 | AZ20: 683.468 | BE20: 770.114 | BF20: 188.162 | BG20: 206.168 | BH20: 204.887 | BI20: =BJ20-SUM(BF20:BH20) -> 200.018 | BJ20: 799.235 | BK20: 207.856 | BL20: 223.349 | BM20: 223.644 | BN20: =BO20-SUM(BK20:BM20) -> 217.494 | BO20: 872.343 | BP20: 217.785 | BQ20: 245.853 | BR20: 242.402
B21: Operating profit | G21: 35.844 | L21: 49.245 | Q21: 42.854 | V21: 25.35 | AA21: 26.119 | AF21: 33.236 | AK21: 41.419 | AP21: 37.591 | AU21: 67.615 | AZ21: 88.99 | BE21: 101.667 | BF21: 23.046 | BG21: 26.652 | BH21: 21.339 | BI21: =BJ21-SUM(BF21:BH21) -> 16.963 | BJ21: 88 | BK21: 21.299 | BL21: 24.075 | BM21: 25.368 | BN21: =BO21-SUM(BK21:BM21) -> 16.102 | BO21: 86.844 | BP21: 20.294 | BQ21: 27.507 | BR21: 18.585
B22: Sales y/y % | L22: =L20/G20-1 -> 0.093058124 | Q22: =Q20/L20-1 -> 0.0084129277 | V22: =V20/Q20-1 -> 0.10366406 | AA22: =AA20/V20-1 -> -0.0036368688 | AF22: =AF20/AA20-1 -> -0.033107312 | AK22: =AK20/AF20-1 -> -0.040249683 | AP22: =AP20/AK20-1 -> 0.076956276 | AU22: =AU20/AP20-1 -> 0.47331991 | AZ22: =AZ20/AU20-1 -> 0.17661398 | BE22: =BE20/AZ20-1 -> 0.12677404 | BJ22: =BJ20/BE20-1 -> 0.037813882 | BK22: =BK20/BF20-1 -> 0.10466513 | BL22: =BL20/BG20-1 -> 0.08333495 | BM22: =BM20/BH20-1 -> 0.091548024 | BP22: =BP20/BK20-1 -> 0.047768648 | BQ22: =BQ20/BL20-1 -> 0.10075711 | BR22: =BR20/BM20-1 -> 0.083874372
B23: Operating margin % | G23: =G21/G20 -> 0.11012861 | L23: =L21/L20 -> 0.13842119 | Q23: =Q21/Q20 -> 0.11945199 | V23: =V21/V20 -> 0.064024044 | AA23: =AA21/AA20 -> 0.066207019 | AF23: =AF21/AF20 -> 0.087132056 | AK23: =AK21/AK20 -> 0.11313854 | AP23: =AP21/AP20 -> 0.095344744 | AU23: =AU21/AU20 -> 0.11640158 | AZ23: =AZ21/AZ20 -> 0.13020361 | BE23: =BE21/BE20 -> 0.13201552 | BF23: =BF21/BF20 -> 0.12247957 | BG23: =BG21/BG20 -> 0.12927321 | BH23: =BH21/BH20 -> 0.10415009 | BI23: =BI21/BI20 -> 0.084807367 | BJ23: =BJ21/BJ20 -> 0.11010529 | BK23: =BK21/BK20 -> 0.10246998 | BL23: =BL21/BL20 -> 0.10779095 | BM23: =BM21/BM20 -> 0.11343027 | BO23: =BO21/BO20 -> 0.099552584 | BP23: =BP21/BP20 -> 0.093183644 | BQ23: =BQ21/BQ20 -> 0.11188393 | BR23: =BR21/BR20 -> 0.076670159
B24: Backlog ($M) | G24: 213 | L24: 223 | Q24: 204 | V24: 254 | AA24: 254 | AF24: 250 | AK24: 277 | AP24: 282 | AU24: 454
B26: Industrial Systems
B27: Net sales | G27: 545.672 | L27: 629.312 | Q27: 633.713 | V27: 592.112 | AA27: 590.971 | AF27: 521.505 | AK27: 514.984 | AP27: 477.325 | AU27: 935.086 | AZ27: 918.223 | BE27: 908.69 | BF27: 209.018 | BG27: 225.873 | BH27: 230.334 | BI27: =BJ27-SUM(BF27:BH27) -> 226.295 | BJ27: 891.52 | BK27: 212.913 | BL27: 236.17 | BM27: 231.25 | BN27: =BO27-SUM(BK27:BM27) -> 226.646 | BO27: 906.979 | BP27: 232.059 | BQ27: 243.935 | BR27: 252.749
B28: Operating profit | G28: 48.109 | L28: 62.805 | Q28: 63.243 | V28: 42.254 | AA28: 58.108 | AF28: 45.021 | AK28: 48.542 | AP28: 46.091 | AU28: 64.964 | AZ28: 109.451 | BE28: 80.025 | BF28: 19.898 | BG28: 23.813 | BH28: 23.004 | BI28: =BJ28-SUM(BF28:BH28) -> 19.285 | BJ28: 86 | BK28: 17.191 | BL28: 20.723 | BM28: 19.484 | BN28: =BO28-SUM(BK28:BM28) -> 14.986 | BO28: 72.384 | BP28: 36.751 | BQ28: 24.397 | BR28: 28.035
B29: Sales y/y % | L29: =L27/G27-1 -> 0.15327889 | Q29: =Q27/L27-1 -> 0.0069933515 | V29: =V27/Q27-1 -> -0.065646436 | AA29: =AA27/V27-1 -> -0.0019270003 | AF29: =AF27/AA27-1 -> -0.11754553 | AK29: =AK27/AF27-1 -> -0.012504195 | AP29: =AP27/AK27-1 -> -0.073126544 | AU29: =AU27/AP27-1 -> 0.95901325 | AZ29: =AZ27/AU27-1 -> -0.018033635 | BE29: =BE27/AZ27-1 -> -0.01038201 | BJ29: =BJ27/BE27-1 -> -0.018895333 | BK29: =BK27/BF27-1 -> 0.018634759 | BL29: =BL27/BG27-1 -> 0.045587565 | BM29: =BM27/BH27-1 -> 0.0039768336 | BP29: =BP27/BK27-1 -> 0.089924053 | BQ29: =BQ27/BL27-1 -> 0.032878858 | BR29: =BR27/BM27-1 -> 0.092968649
B30: Operating margin % | G30: =G28/G27 -> 0.088164685 | L30: =L28/L27 -> 0.099799464 | Q30: =Q28/Q27 -> 0.099797542 | V30: =V28/V27 -> 0.071361499 | AA30: =AA28/AA27 -> 0.098326314 | AF30: =AF28/AF27 -> 0.08632899 | AK30: =AK28/AK27 -> 0.094259239 | AP30: =AP28/AP27 -> 0.096561043 | AU30: =AU28/AU27 -> 0.069473824 | AZ30: =AZ28/AZ27 -> 0.11919871 | BE30: =BE28/BE27 -> 0.088066337 | BF30: =BF28/BF27 -> 0.095197543 | BG30: =BG28/BG27 -> 0.1054265 | BH30: =BH28/BH27 -> 0.099872359 | BI30: =BI28/BI27 -> 0.085220619 | BJ30: =BJ28/BJ27 -> 0.096464465 | BK30: =BK28/BK27 -> 0.080741899 | BL30: =BL28/BL27 -> 0.087746115 | BM30: =BM28/BM27 -> 0.084255135 | BO30: =BO28/BO27 -> 0.079807802 | BP30: =BP28/BP27 -> 0.15836921 | BQ30: =BQ28/BQ27 -> 0.10001435 | BR30: =BR28/BR27 -> 0.11092032
B31: Backlog ($M) | G31: 233 | L31: 284 | Q31: 234 | V31: 187 | AA31: 182 | AF31: 178 | AK31: 145 | AP31: 164 | AU31: 272
B33: Components (separate segment FY10–FY14, then merged into Industrial)
B34: Net sales | G34: 359.992 | L34: 353.142 | Q34: 374.081 | V34: 438.572 | AA34: 449.891 | AF34: 437.468 | AK34: 467.144 | AP34: 501.05 | AU34: 359.992 | AZ34: 359.992 | BE34: 359.992 | BF34: 359.992 | BG34: 359.992 | BH34: 359.992 | BI34: 359.992 | BJ34: 359.992
B35: Operating profit | G35: 60.159 | L35: 50.353 | Q35: 57.303 | V35: 74.425 | AA35: 72.768 | AF35: 58.693 | AK35: 49.772 | AP35: 52.454 | AU35: 60.159 | AZ35: 60.159 | BE35: 60.159 | BF35: 60.159 | BG35: 60.159 | BH35: 60.159 | BI35: 60.159 | BJ35: 60.159
B36: Operating margin % | L36: =L34/G34-1 -> -0.019028201 | Q36: =Q34/L34-1 -> 0.059293429 | V36: =V34/Q34-1 -> 0.17239849 | AA36: =AA34/V34-1 -> 0.025808761 | AF36: =AF34/AA34-1 -> -0.027613355 | AK36: =AK34/AF34-1 -> 0.067835819 | AP36: =AP34/AK34-1 -> 0.072581474
G37: =G35/G34 -> 0.16711205 | L37: =L35/L34 -> 0.1425857 | Q37: =Q35/Q34 -> 0.1531834 | V37: =V35/V34 -> 0.16969848 | AA37: =AA35/AA34 -> 0.16174585 | AF37: =AF35/AF34 -> 0.13416524 | AK37: =AK35/AK34 -> 0.10654531 | AP37: =AP35/AP34 -> 0.10468815 | AU37: =AU35/AU34 -> 0.16711205 | AZ37: =AZ35/AZ34 -> 0.16711205 | BE37: =BE35/BE34 -> 0.16711205 | BF37: =BF35/BF34 -> 0.16711205 | BG37: =BG35/BG34 -> 0.16711205 | BH37: =BH35/BH34 -> 0.16711205 | BI37: =BI35/BI34 -> 0.16711205 | BJ37: =BJ35/BJ34 -> 0.16711205
B38: Medical Devices (separate segment FY10–FY16, divested/merged)
B39: Net sales | G39: 126.564 | L39: 141.974 | Q39: 139.566 | V39: 124.095 | AA39: 95.362 | AF39: 98.568 | AK39: 126.564 | AP39: 126.564 | AU39: 126.564 | AZ39: 126.564 | BE39: 126.564 | BF39: 126.564 | BG39: 126.564 | BH39: 126.564 | BI39: 126.564 | BJ39: 126.564
B40: Operating profit | G40: -4.044 | L40: 0.241 | Q40: 5.443 | V40: -41.236 | AA40: 2.996 | AF40: 8.557 | AK40: -4.044 | AP40: -4.044 | AU40: -4.044 | AZ40: -4.044 | BE40: -4.044 | BF40: -4.044 | BG40: -4.044 | BH40: -4.044 | BI40: -4.044 | BJ40: -4.044
B41: Operating margin % | G41: =G40/G39 -> -0.031952214 | L41: =L40/L39 -> 0.0016974939 | Q41: =Q40/Q39 -> 0.03899947 | V41: =V40/V39 -> -0.33229381 | AA41: =AA40/AA39 -> 0.031417126 | AF41: =AF40/AF39 -> 0.086813165 | AK41: =AK40/AK39 -> -0.031952214 | AP41: =AP40/AP39 -> -0.031952214 | AU41: =AU40/AU39 -> -0.031952214 | AZ41: =AZ40/AZ39 -> -0.031952214 | BE41: =BE40/BE39 -> -0.031952214 | BF41: =BF40/BF39 -> -0.031952214 | BG41: =BG40/BG39 -> -0.031952214 | BH41: =BH40/BH39 -> -0.031952214 | BI41: =BI40/BI39 -> -0.031952214 | BJ41: =BJ40/BJ39 -> -0.031952214
B43: Legacy Group Total (consolidated, FY10–FY21)
B44: Net sales | G44: =G12+G20+G27+G34+G39 -> 2114.252 | L44: =L12+L20+L27+L34+L39 -> 2330.68 | Q44: =Q12+Q20+Q27+Q34+Q39 -> 2469.536 | V44: =V12+V20+V27+V34+V39 -> 2610.311 | AA44: =AA12+AA20+AA27+AA34+AA39 -> 2648.385 | AF44: =AF12+AF20+AF27+AF34+AF39 -> 2525.532 | AK44: =AK12+AK20+AK27+AK34 -> 2411.937 | AP44: =AP12+AP20+AP27+AP34 -> 2497.524 | AU44: =AU12+AU20+AU27 -> 2709.468 | AZ44: =AZ12+AZ20+AZ27 -> 2904.663 | BE44: =BE12+BE20+BE27 -> 2884.554 | BF44: =BF12+BF20+BF27 -> 683.954 | BG44: =BG12+BG20+BG27 -> 736.402 | BH44: =BH12+BH20+BH27 -> 707.352 | BJ44: =BJ12+BJ20+BJ27 -> 2851.993 | BK44: =BK12+BK20+BK27 -> 724.086 | BL44: =BL12+BL20+BL27 -> 770.787 | BM44: =BM12+BM20+BM27 -> 772.911 | BO44: =BO12+BO20+BO27 -> 3035.783 | BP44: =BP12+BP20+BP27 -> 760.103 | BQ44: =BQ12+BQ20+BQ27 -> 836.792 | BR44: =BR12+BR20+BR27 -> 850.176
B45: Operating profit | G45: =G13+G21+G28+G35+G40 -> 216.442 | L45: =L13+L21+L28+L35+L40 -> 246.42 | Q45: =Q13+Q21+Q28+Q35+Q40 -> 273.425 | V45: =V13+V21+V28+V35+V40 -> 227.544 | AA45: =AA13+AA21+AA28+AA35+AA40 -> 275.717 | AF45: =AF13+AF21+AF28+AF35+AF40 -> 245.513 | AK45: =AK13+AK21+AK28+AK35 -> 238.242 | AP45: =AP13+AP21+AP28+AP35 -> 250.152 | AU45: =AU13+AU21+AU28 -> 262.351 | AZ45: =AZ13+AZ21+AZ28 -> 321.142 | BE45: =BE13+BE21+BE28 -> 216.362 | BF45: =BF13+BF21+BF28 -> 70.866 | BG45: =BG13+BG21+BG28 -> 72.483 | BH45: =BH13+BH21+BH28 -> 64.888 | BJ45: =BJ13+BJ21+BJ28 -> 270.678 | BK45: =BK13+BK21+BK28 -> 80.405 | BL45: =BL13+BL21+BL28 -> 57.239 | BM45: =BM13+BM21+BM28 -> 79.305 | BO45: =BO13+BO21+BO28 -> 282.848 | BP45: =BP13+BP21+BP28 -> 86.763 | BQ45: =BQ13+BQ21+BQ28 -> 83.766 | BR45: =BR13+BR21+BR28 -> 84.508
B46: Sales y/y % | L46: =L44/G44-1 -> 0.10236623 | Q46: =Q44/L44-1 -> 0.059577462 | V46: =V44/Q44-1 -> 0.057004636 | AA46: =AA44/V44-1 -> 0.014586001 | AF46: =AF44/AA44-1 -> -0.046387893 | AK46: =AK44/AF44-1 -> -0.044978642 | AP46: =AP44/AK44-1 -> 0.035484758 | AU46: =AU44/AP44-1 -> 0.084861647 | AZ46: =AZ44/AU44-1 -> 0.072041818 | BE46: =BE44/AZ44-1 -> -0.0069230062 | BJ46: =BJ44/BE44-1 -> -0.011288054 | BK46: =BK44/BF44-1 -> 0.058676461 | BL46: =BL44/BG44-1 -> 0.046693246 | BM46: =BM44/BH44-1 -> 0.092682285 | BO46: =BO44/BJ44-1 -> 0.064442655 | BP46: =BP44/BK44-1 -> 0.049741329 | BQ46: =BQ44/BL44-1 -> 0.085633255 | BR46: =BR44/BM44-1 -> 0.099966232
B47: Operating margin % | G47: =G45/G44 -> 0.10237285 | L47: =L45/L44 -> 0.1057288 | Q47: =Q45/Q44 -> 0.11071918 | V47: =V45/V44 -> 0.087171222 | AA47: =AA45/AA44 -> 0.1041076 | AF47: =AF45/AF44 -> 0.097212389 | AK47: =AK45/AK44 -> 0.098776212 | AP47: =AP45/AP44 -> 0.10016 | AU47: =AU45/AU44 -> 0.096827495 | AZ47: =AZ45/AZ44 -> 0.11056085 | BE47: =BE45/BE44 -> 0.075007089 | BF47: =BF45/BF44 -> 0.10361223 | BG47: =BG45/BG44 -> 0.098428576 | BH47: =BH45/BH44 -> 0.091733677 | BJ47: =BJ45/BJ44 -> 0.094908368 | BK47: =BK45/BK44 -> 0.11104344 | BL47: =BL45/BL44 -> 0.074260464 | BM47: =BM45/BM44 -> 0.1026056 | BO47: =BO45/BO44 -> 0.09317135 | BP47: =BP45/BP44 -> 0.11414637 | BQ47: =BQ45/BQ44 -> 0.10010373 | BR47: =BR45/BR44 -> 0.099400595
B50: SEGMENT P&L — CURRENT STRUCTURE (FY22–present, includes forecast) | CQ50: Current 4-segment structure drives consolidated revenue. Sums from segments flow to Group Total row 86, which feeds IS Net sales (row 95). Mix shift toward Space & Defense and Military Aircraft expected through FY30E given U.S. defense budgets and Moog's exposure to Patriot, JASSM, hypersonics programs.
B51: Effective Q1 FY22: Aircraft Controls split into Military Aircraft + Commercial Aircraft; Space and Defense renamed; Industrial Systems renamed Industrial. FY21 restated comparatives used where Moog disclosed them.
B53: Military Aircraft
B54: Net sales | BK54: 185.949 | BL54: 192.089 | BM54: 180.891 | BN54: =BO54-BK54-BL54-BM54 -> -558.929 | BP54: 177.8 | BQ54: 182.753 | BR54: 176.217 | BS54: =BT54-BP54-BQ54-BR54 -> 410.481 | BT54: 947.251 | BU54: 186.244 | BV54: 202.5 | BW54: 207.177 | BX54: =BY54-BU54-BV54-BW54 -> 422.227 | BY54: 1018.148 | BZ54: 213.42 | CA54: 213.849 | CB54: 224.662 | CC54: =CD54-BZ54-CA54-CB54 -> 461.097 | CD54: 1113.028 | CE54: 247.411 | CF54: 235.489 | CG54: =CB54*(1+CG55) -> 247.1282 | CH54: =CI54-CE54-CF54-CG54 -> 219.9542 | CI54: =888*(1+CI55) -> 949.9824 | CJ54: =CI54*(1+CJ55) -> 1016.4812 | CK54: =CJ54*(1+CK55) -> 1077.47 | CL54: =CK54*(1+CL55) -> 1136.7309 | CM54: =CL54*(1+CM55) -> 1193.5674 | CO54: 0.062945583 | CQ54: Military Aircraft: ~7-8% organic growth FY26E–FY30E driven by F-35 sustainment, F/A-18, CH-53K ramp, and new program wins (B-21, NGAD work). Backlog supports near-term; aftermarket mix improving margins. | CT54: SCENARIO ASSUMPTION TABLES
B55: Sales y/y % | BK55: =IFERROR(BK54/BF54-1,"") | BL55: =IFERROR(BL54/BG54-1,"") | BM55: =IFERROR(BM54/BH54-1,"") | BN55: =IFERROR(BN54/BI54-1,"") | BO55: =IFERROR(BO54/BJ54-1,"") | BP55: =IFERROR(BP54/BK54-1,"") -> -0.043823844 | BQ55: =IFERROR(BQ54/BL54-1,"") -> -0.048602471 | BR55: =IFERROR(BR54/BM54-1,"") -> -0.025838765 | ... CF55: =IFERROR(CF54/CA54-1,"") -> 0.1011929 | CG55: 0.1 | CH55: =IFERROR(CH54/CC54-1,"") -> -0.52297629 | CI55: 0.0698 | CJ55: =CHOOSE(MATCH($CO$3,{"Base";"Bull";"Bear"},0),CV58,CV68,CV78) -> 0.07 | CK55: =CHOOSE(MATCH($CO$3,{"Base";"Bull";"Bear"},0),CW58,CW68,CW78) -> 0.06 | CL55: =CHOOSE(MATCH($CO$3,{"Base";"Bull";"Bear"},0),CX58,CX68,CX78) -> 0.055 | CM55: =CHOOSE(MATCH($CO$3,{"Base";"Bull";"Bear"},0),CY58,CY68,CY78) -> 0.05 | CQ55: Op margin ramping from ~10.5% (FY24) toward 12-13% by FY30E via aftermarket mix, program maturity, and operational leverage from prior restructuring. | CT55: Case →
B56: EBIT | BN56: =BO56-BK56-BL56-BM56 -> 0 | BP56: 15.201 | BQ56: 16.181 | BR56: 18.143 | BS56: =BT56-BP56-BQ56-BR56 -> 46.582 | BT56: 96.107 | BU56: 19.589 | BV56: 16.769 | BW56: 23.965 | BX56: =BY56-BU56-BV56-BW56 -> 66.562 | BY56: 126.885 | BZ56: 22.916 | CA56: 23.722 | CB56: 17.994 | CC56: =CD56-BZ56-CA56-CB56 -> 66.505 | CD56: 131.137 | CE56: 28.131 | CF56: 32.262 | CG56: =CG54*CG58 -> 34.597948 | CH56: =CH54*CH58 -> 30.133725 | CI56: =CI54*CI58 -> 131.09757 | CJ56: =CJ54*CJ58 -> 121.97774 | CK56: =CK54*CK58 -> 134.68375 | CL56: =CL54*CL58 -> 147.77502 | CM56: =CM54*CM58 -> 155.16377 | CT56: Driver | CU56: FY26E | CV56: FY27E | CW56: FY28E | CX56: FY29E | CY56: FY30E
B57: EBIT y/y % | BK57: =IFERROR(BK56/BF56-1,"") | BL57: =IFERROR(BL56/BG56-1,"") | BM57: =IFERROR(BM56/BH56-1,"") | BN57: =IFERROR(BN56/BI56-1,"") | BO57: =IFERROR(BO56/BJ56-1,"") | BP57: =IFERROR(BP56/BK56-1,"") | BQ57: =IFERROR(BQ56/BL56-1,"") | BR57: =IFERROR(BR56/BM56-1,"") | ... CI57: =IFERROR(CI56/CD56-1,"") -> -0.00030066877 | CJ57: =IFERROR(CJ56/CI56-1,"") -> -0.069565217 | CK57: =IFERROR(CK56/CJ56-1,"") -> 0.10416667 | CL57: =IFERROR(CL56/CK56-1,"") -> 0.0972 | CM57: =IFERROR(CM56/CL56-1,"") -> 0.05 | CT57: BASE CASE
B58: EBIT % | BK58: =IFERROR(BK56/BK54,"") -> 0 | BL58: =IFERROR(BL56/BL54,"") -> 0 | BM58: =IFERROR(BM56/BM54,"") -> 0 | BN58: =IFERROR(BN56/BN54,"") -> 0 | BO58: =IFERROR(BO56/BO54,"") | BP58: =IFERROR(BP56/BP54,"") -> 0.085494938 | BQ58: =IFERROR(BQ56/BQ54,"") -> 0.08854027 | BR58: =IFERROR(BR56/BR54,"") -> 0.10295828 | ... CF58: =IFERROR(CF56/CF54,"") -> 0.13700003 | CG58: 0.14 | CH58: 0.137 | CI58: 0.138 | CJ58: =CHOOSE(MATCH($CO$3,{"Base";"Bull";"Bear"},0),CV59,CV69,CV79) -> 0.12 | CK58: =CHOOSE(MATCH($CO$3,{"Base";"Bull";"Bear"},0),CW59,CW69,CW79) -> 0.125 | CL58: =CHOOSE(MATCH($CO$3,{"Base";"Bull";"Bear"},0),CX59,CX69,CX79) -> 0.13 | CM58: =CHOOSE(MATCH($CO$3,{"Base";"Bull";"Bear"},0),CY59,CY69,CY79) -> 0.13 | CT58: Military Aircraft sales y/y % | CU58: 0.08 | CV58: 0.07 | CW58: 0.06 | CX58: 0.055 | CY58: 0.05
B59: Incremental EBIT (ΔEBIT / ΔSales) | BK59: =IFERROR((BK56-BF56)/(BK54-BF54),"") -> 0 | BL59: =IFERROR((BL56-BG56)/(BL54-BG54),"") -> 0 | BM59: =IFERROR((BM56-BH56)/(BM54-BH54),"") -> 0 | BN59: =IFERROR((BN56-BI56)/(BN54-BI54),"") -> 0 | BO59: =IFERROR((BO56-BJ56)/(BO54-BJ54),"") | BP59: =IFERROR((BP56-BK56)/(BP54-BK54),"") -> -1.8653823 | BQ59: =IFERROR((BQ56-BL56)/(BQ54-BL54),"") -> -1.7331834 | BR59: =IFERROR((BR56-BM56)/(BR54-BM54),"") -> -3.8816859 | ... CD59: =IFERROR((CD56-BY56)/(CD54-BY54),"") -> 0.044814503 | CI59: =IFERROR((CI56-CD56)/(CI54-CD54),"") -> 0.00024182683 | CJ59: =IFERROR((CJ56-CI56)/(CJ54-CI54),"") -> -0.13714286 | CK59: =IFERROR((CK56-CJ56)/(CK54-CJ54),"") -> 0.20833333 | CL59: =IFERROR((CL56-CK56)/(CL54-CK54),"") -> 0.22090909 | CM59: =IFERROR((CM56-CL56)/(CM54-CL54),"") -> 0.13 | CT59: Military Aircraft EBIT margin % | CU59: 0.115 | CV59: 0.12 | CW59: 0.125 | CX59: 0.13 | CY59: 0.13
B60: Backlog ($M) | CT60: Commercial Aircraft sales y/y % | CU60: 0.1 | CV60: 0.085 | CW60: 0.07 | CX60: 0.055 | CY60: 0.045
B61: Backlog y/y % | BK61: =IFERROR(BK60/BF60-1,"") | BL61: =IFERROR(BL60/BG60-1,"") | BM61: =IFERROR(BM60/BH60-1,"") | BN61: =IFERROR(BN60/BI60-1,"") | BO61: =IFERROR(BO60/BJ60-1,"") | BP61: =IFERROR(BP60/BK60-1,"") | BQ61: =IFERROR(BQ60/BL60-1,"") | BR61: =IFERROR(BR60/BM60-1,"") | ... CD61: =IFERROR(CD60/BY60-1,"") | CI61: =IFERROR(CI60/CD60-1,"") | CJ61: =IFERROR(CJ60/CI60-1,"") | CK61: =IFERROR(CK60/CJ60-1,"") | CL61: =IFERROR(CL60/CK60-1,"") | CM61: =IFERROR(CM60/CL60-1,"") | CT61: Commercial Aircraft EBIT margin % | CU61: 0.125 | CV61: 0.13 | CW61: 0.135 | CX61: 0.14 | CY61: 0.14
B62: Book-to-bill (Bookings / Sales) | BK62: =IFERROR((BK54+BK60-BF60)/BK54,"") -> 1 | BL62: =IFERROR((BL54+BL60-BG60)/BL54,"") -> 1 | BM62: =IFERROR((BM54+BM60-BH60)/BM54,"") -> 1 | BN62: =IFERROR((BN54+BN60-BI60)/BN54,"") -> 1 | BO62: =IFERROR((BO54+BO60-BJ60)/BO54,"") | BP62: =IFERROR((BP54+BP60-BK60)/BP54,"") -> 1 | BQ62: =IFERROR((BQ54+BQ60-BL60)/BQ54,"") -> 1 | BR62: =IFERROR((BR54+BR60-BM60)/BR54,"") -> 1 | ... CD62: =IFERROR((CD54+CD60-BY60)/CD54,"") -> 1 | CI62: =IFERROR((CI54+CI60-CD60)/CI54,"") -> 1 | CJ62: =IFERROR((CJ54+CJ60-CI60)/CJ54,"") -> 1 | CK62: =IFERROR((CK54+CK60-CJ60)/CK54,"") -> 1 | CL62: =IFERROR((CL54+CL60-CK60)/CL54,"") -> 1 | CM62: =IFERROR((CM54+CM60-CL60)/CM54,"") -> 1 | CT62: Space & Defense sales y/y % | CU62: 0.15 | CV62: 0.12 | CW62: 0.1 | CX62: 0.1 | CY62: 0.1
CT63: Space & Defense EBIT margin % | CU63: 0.125 | CV63: 0.13 | CW63: 0.135 | CX63: 0.14 | CY63: 0.14
B64: Commercial Aircraft | CT64: Industrial sales y/y % | CU64: 0.03 | CV64: 0.04 | CW64: 0.04 | CX64: 0.035 | CY64: 0.035
B65: Net sales | BK65: 117.368 | BL65: 119.179 | BM65: 137.126 | BN65: =BO65-BK65-BL65-BM65 -> -373.673 | BP65: 132.459 | BQ65: 164.251 | BR65: 178.808 | BS65: =BT65-BP65-BQ65-BR65 -> 244.814 | BT65: 720.332 | BU65: 194.222 | BV65: 207.594 | BW65: 189.365 | BX65: =BY65-BU65-BV65-BW65 -> 220.385 | BY65: 811.566 | BZ65: 220.923 | CA65: 216.381 | CB65: 219.436 | CC65: =CD65-BZ65-CA65-CB65 -> 231.396 | CD65: 888.136 | CE65: 267.843 | CF65: 247.007 | CG65: =CB65*(1+CG66) -> 247.96268 | CH65: =CI65-CE65-CF65-CG65 -> 287.18332 | CI65: =904*(1+CI66) -> 1049.996 | CJ65: =CI65*(1+CJ66) -> 1139.2457 | CK65: =CJ65*(1+CK66) -> 1218.9929 | CL65: =CK65*(1+CL66) -> 1286.0375 | CM65: =CL65*(1+CM66) -> 1343.9091 | CO65: 0.070816341 | CQ65: Commercial Aircraft: high-single-digit growth FY26E–FY30E on 737 MAX ramp, 787 build-rate recovery, and Airbus A320neo demand. Aftermarket strong post-COVID. Risk: OEM build-rate volatility. | CT65: Industrial EBIT margin % | CU65: 0.115 | CV65: 0.12 | CW65: 0.125 | CX65: 0.125 | CY65: 0.13
B66: Sales y/y % | BK66: =IFERROR(BK65/BF65-1,"") | BL66: =IFERROR(BL65/BG65-1,"") | BM66: =IFERROR(BM65/BH65-1,"") | BN66: =IFERROR(BN65/BI65-1,"") | BO66: =IFERROR(BO65/BJ65-1,"") | BP66: =IFERROR(BP65/BK65-1,"") -> 0.12857849 | BQ66: =IFERROR(BQ65/BL65-1,"") -> 0.37818743 | BR66: =IFERROR(BR65/BM65-1,"") -> 0.30396861 | ... CF66: =IFERROR(CF65/CA65-1,"") -> 0.14153738 | CG66: 0.13 | CH66: =IFERROR(CH65/CC65-1,"") -> 0.24109025 | CI66: 0.1615 | CJ66: =CHOOSE(MATCH($CO$3,{"Base";"Bull";"Bear"},0),CV60,CV70,CV80) -> 0.085 | CK66: =CHOOSE(MATCH($CO$3,{"Base";"Bull";"Bear"},0),CW60,CW70,CW80) -> 0.07 | CL66: =CHOOSE(MATCH($CO$3,{"Base";"Bull";"Bear"},0),CX60,CX70,CX80) -> 0.055 | CM66: =CHOOSE(MATCH($CO$3,{"Base";"Bull";"Bear"},0),CY60,CY70,CY80) -> 0.045 | CQ66: Margin expansion from ~10-11% to ~13% by FY30E as commercial aftermarket scales and OE volumes leverage fixed cost base.
B67: EBIT | BN67: =BO67-BK67-BL67-BM67 -> 0 | BP67: 14.517 | BQ67: 15.681 | BR67: 19.745 | BS67: =BT67-BP67-BQ67-BR67 -> 10.682 | BT67: 60.625 | BU67: 20.626 | BV67: 24.845 | BW67: 24.367 | BX67: =BY67-BU67-BV67-BW67 -> 15.665 | BY67: 85.503 | BZ67: 24.204 | CA67: 25.591 | CB67: 32.623 | CC67: =CD67-BZ67-CA67-CB67 -> 16.339 | CD67: 98.757 | CE67: 28.391 | CF67: 29.394 | CG67: =CG65*CG69 -> 29.259596 | CH67: =CH65*CH69 -> 33.026082 | CI67: =CI65*CI69 -> 120.74954 | CJ67: =CJ65*CJ69 -> 148.10194 | CK67: =CK65*CK69 -> 164.56404 | CL67: =CL65*CL69 -> 180.04524 | CM67: =CM65*CM69 -> 188.14728 | CT67: BULL CASE
B68: EBIT y/y % | BK68: =IFERROR(BK67/BF67-1,"") | BL68: =IFERROR(BL67/BG67-1,"") | BM68: =IFERROR(BM67/BH67-1,"") | BN68: =IFERROR(BN67/BI67-1,"") | BO68: =IFERROR(BO67/BJ67-1,"") | BP68: =IFERROR(BP67/BK67-1,"") | BQ68: =IFERROR(BQ67/BL67-1,"") | BR68: =IFERROR(BR67/BM67-1,"") | ... CI68: =IFERROR(CI67/CD67-1,"") -> 0.22269348 | CJ68: =IFERROR(CJ67/CI67-1,"") -> 0.22652174 | CK68: =IFERROR(CK67/CJ67-1,"") -> 0.11115385 | CL68: =IFERROR(CL67/CK67-1,"") -> 0.094074074 | CM68: =IFERROR(CM67/CL67-1,"") -> 0.045 | CT68: Military Aircraft sales y/y % | CU68: 0.12 | CV68: 0.1 | CW68: 0.08 | CX68: 0.07 | CY68: 0.065
B69: EBIT % | BK69: =IFERROR(BK67/BK65,"") -> 0 | BL69: =IFERROR(BL67/BL65,"") -> 0 | BM69: =IFERROR(BM67/BM65,"") -> 0 | BN69: =IFERROR(BN67/BN65,"") -> 0 | BO69: =IFERROR(BO67/BO65,"") | BP69: =IFERROR(BP67/BP65,"") -> 0.10959618 | BQ69: =IFERROR(BQ67/BQ65,"") -> 0.095469738 | BR69: =IFERROR(BR67/BR65,"") -> 0.11042571 | ... CF69: =IFERROR(CF67/CF65,"") -> 0.11900068 | CG69: 0.118 | CH69: 0.115 | CI69: 0.115 | CJ69: =CHOOSE(MATCH($CO$3,{"Base";"Bull";"Bear"},0),CV61,CV71,CV81) -> 0.13 | CK69: =CHOOSE(MATCH($CO$3,{"Base";"Bull";"Bear"},0),CW61,CW71,CW81) -> 0.135 | CL69: =CHOOSE(MATCH($CO$3,{"Base";"Bull";"Bear"},0),CX61,CX71,CX81) -> 0.14 | CM69: =CHOOSE(MATCH($CO$3,{"Base";"Bull";"Bear"},0),CY61,CY71,CY81) -> 0.14 | CT69: Military Aircraft EBIT margin % | CU69: 0.13 | CV69: 0.135 | CW69: 0.14 | CX69: 0.145 | CY69: 0.15
B70: Incremental EBIT (ΔEBIT / ΔSales) | BK70: =IFERROR((BK67-BF67)/(BK65-BF65),"") -> 0 | BL70: =IFERROR((BL67-BG67)/(BL65-BG65),"") -> 0 | BM70: =IFERROR((BM67-BH67)/(BM65-BH65),"") -> 0 | BN70: =IFERROR((BN67-BI67)/(BN65-BI65),"") -> 0 | BO70: =IFERROR((BO67-BJ67)/(BO65-BJ65),"") | BP70: =IFERROR((BP67-BK67)/(BP65-BK65),"") -> 0.96196408 | BQ70: =IFERROR((BQ67-BL67)/(BQ65-BL65),"") -> 0.34791001 | BR70: =IFERROR((BR67-BM67)/(BR65-BM65),"") -> 0.47370568 | ... CD70: =IFERROR((CD67-BY67)/(CD65-BY65),"") -> 0.17309651 | CI70: =IFERROR((CI67-CD67)/(CI65-CD65),"") -> 0.13587384 | CJ70: =IFERROR((CJ67-CI67)/(CJ65-CI65),"") -> 0.30647059 | CK70: =IFERROR((CK67-CJ67)/(CK65-CJ65),"") -> 0.20642857 | CL70: =IFERROR((CL67-CK67)/(CL65-CK65),"") -> 0.23090909 | CM70: =IFERROR((CM67-CL67)/(CM65-CL65),"") -> 0.14 | CT70: Commercial Aircraft sales y/y % | CU70: 0.14 | CV70: 0.115 | CW70: 0.09 | CX70: 0.075 | CY70: 0.06
B71: Backlog ($M) | CT71: Commercial Aircraft EBIT margin % | CU71: 0.14 | CV71: 0.145 | CW71: 0.15 | CX71: 0.155 | CY71: 0.155
B72: Backlog y/y % | BK72: =IFERROR(BK71/BF71-1,"") | BL72: =IFERROR(BL71/BG71-1,"") | BM72: =IFERROR(BM71/BH71-1,"") | BN72: =IFERROR(BN71/BI71-1,"") | BO72: =IFERROR(BO71/BJ71-1,"") | BP72: =IFERROR(BP71/BK71-1,"") | BQ72: =IFERROR(BQ71/BL71-1,"") | BR72: =IFERROR(BR71/BM71-1,"") | ... CD72: =IFERROR(CD71/BY71-1,"") | CI72: =IFERROR(CI71/CD71-1,"") | CJ72: =IFERROR(CJ71/CI71-1,"") | CK72: =IFERROR(CK71/CJ71-1,"") | CL72: =IFERROR(CL71/CK71-1,"") | CM72: =IFERROR(CM71/CL71-1,"") | CT72: Space & Defense sales y/y % | CU72: 0.2 | CV72: 0.16 | CW72: 0.13 | CX72: 0.12 | CY72: 0.12
B73: Book-to-bill (Bookings / Sales) | BK73: =IFERROR((BK65+BK71-BF71)/BK65,"") -> 1 | BL73: =IFERROR((BL65+BL71-BG71)/BL65,"") -> 1 | BM73: =IFERROR((BM65+BM71-BH71)/BM65,"") -> 1 | BN73: =IFERROR((BN65+BN71-BI71)/BN65,"") -> 1 | BO73: =IFERROR((BO65+BO71-BJ71)/BO65,"") | BP73: =IFERROR((BP65+BP71-BK71)/BP65,"") -> 1 | BQ73: =IFERROR((BQ65+BQ71-BL71)/BQ65,"") -> 1 | BR73: =IFERROR((BR65+BR71-BM71)/BR65,"") -> 1 | ... CD73: =IFERROR((CD65+CD71-BY71)/CD65,"") -> 1 | CI73: =IFERROR((CI65+CI71-CD71)/CI65,"") -> 1 | CJ73: =IFERROR((CJ65+CJ71-CI71)/CJ65,"") -> 1 | CK73: =IFERROR((CK65+CK71-CJ71)/CK65,"") -> 1 | CL73: =IFERROR((CL65+CL71-CK71)/CL65,"") -> 1 | CM73: =IFERROR((CM65+CM71-CL71)/CM65,"") -> 1 | CT73: Space & Defense EBIT margin % | CU73: 0.14 | CV73: 0.145 | CW73: 0.15 | CX73: 0.155 | CY73: 0.155
CT74: Industrial sales y/y % | CU74: 0.05 | CV74: 0.055 | CW74: 0.055 | CX74: 0.05 | CY74: 0.05
B75: Space and Defense | CT75: Industrial EBIT margin % | CU75: 0.13 | CV75: 0.135 | CW75: 0.14 | CX75: 0.14 | CY75: 0.145
B76: Net sales | BK76: 207.856 | BL76: 223.349 | BM76: 223.644 | BN76: =BO76-BK76-BL76-BM76 -> -654.849 | BP76: 217.785 | BQ76: 245.853 | BR76: 242.402 | BS76: =BT76-BP76-BQ76-BR76 -> -40.157 | BT76: 665.883 | BU76: 230.128 | BV76: 266.787 | BW76: 258.409 | BX76: =BY76-BU76-BV76-BW76 -> 32.776 | BY76: 788.1 | BZ76: 247.784 | CA76: 270.184 | CB76: 287.705 | CC76: =CD76-BZ76-CA76-CB76 -> 98.206 | CD76: 903.879 | CE76: 324.278 | CF76: 313.593 | CG76: =CB76*(1+CG77) -> 325.10665 | CH76: =CI76-CE76-CF76-CG76 -> 302.05815 | CI76: =1113*(1+CI77) -> 1265.0358 | CJ76: =CI76*(1+CJ77) -> 1416.8401 | CK76: =CJ76*(1+CK77) -> 1558.5241 | CL76: =CK76*(1+CL77) -> 1714.3765 | CM76: =CL76*(1+CM77) -> 1885.8142 | CO76: 0.071894328 | CQ76: Space & Defense: strongest growth segment, 9-11% CAGR through FY30E. Drivers: hypersonics, missile defense (Patriot/THAAD), space launch (vehicle/satellite actuation), Golden Dome architecture. Backlog +30% YoY in FY25.
B77: Sales y/y % | BK77: =IFERROR(BK76/BF76-1,"") | BL77: =IFERROR(BL76/BG76-1,"") | BM77: =IFERROR(BM76/BH76-1,"") | BN77: =IFERROR(BN76/BI76-1,"") | BO77: =IFERROR(BO76/BJ76-1,"") | BP77: =IFERROR(BP76/BK76-1,"") -> 0.047768648 | BQ77: =IFERROR(BQ76/BL76-1,"") -> 0.10075711 | BR77: =IFERROR(BR76/BM76-1,"") -> 0.083874372 | ... CF77: =IFERROR(CF76/CA76-1,"") -> 0.16066458 | CG77: 0.13 | CH77: =IFERROR(CH76/CC76-1,"") -> 2.0757606 | CI77: 0.1366 | CJ77: =CHOOSE(MATCH($CO$3,{"Base";"Bull";"Bear"},0),CV62,CV72,CV82) -> 0.12 | CK77: =CHOOSE(MATCH($CO$3,{"Base";"Bull";"Bear"},0),CW62,CW72,CW82) -> 0.1 | CL77: =CHOOSE(MATCH($CO$3,{"Base";"Bull";"Bear"},0),CX62,CX72,CX82) -> 0.1 | CM77: =CHOOSE(MATCH($CO$3,{"Base";"Bull";"Bear"},0),CY62,CY72,CY82) -> 0.1 | CQ77: Op margin expansion from 12% (FY24) toward 14-15% via scale and mix. Management has cited margin upside on defense contracts as volumes ramp. | CT77: BEAR CASE
B78: EBIT | BN78: =BO78-BK78-BL78-BM78 -> 0 | BP78: 20.294 | BQ78: 27.507 | BR78: 18.585 | BS78: =BT78-BP78-BQ78-BR78 -> 19.651 | BT78: 86.037 | BU78: 25.297 | BV78: 42.243 | BW78: 32.635 | BX78: =BY78-BU78-BV78-BW78 -> -1.298 | BY78: 98.877 | BZ78: 28.539 | CA78: 32.781 | CB78: 38.261 | CC78: =CD78-BZ78-CA78-CB78 -> 12.212 | CD78: 111.793 | CE78: 42.805 | CF78: 43.276 | CG78: =CG76*CG80 -> 45.514931 | CH78: =CH76*CH80 -> 42.288141 | CI78: =CI76*CI80 -> 175.83998 | CJ78: =CJ76*CJ80 -> 184.18921 | CK78: =CK76*CK80 -> 210.40075 | CL78: =CL76*CL80 -> 240.01271 | CM78: =CM76*CM80 -> 264.01398 | CT78: Military Aircraft sales y/y % | CU78: 0.04 | CV78: 0.03 | CW78: 0.02 | CX78: 0.02 | CY78: 0.02
B79: EBIT y/y % | BK79: =IFERROR(BK78/BF78-1,"") | BL79: =IFERROR(BL78/BG78-1,"") | BM79: =IFERROR(BM78/BH78-1,"") | BN79: =IFERROR(BN78/BI78-1,"") | BO79: =IFERROR(BO78/BJ78-1,"") | BP79: =IFERROR(BP78/BK78-1,"") | BQ79: =IFERROR(BQ78/BL78-1,"") | BR79: =IFERROR(BR78/BM78-1,"") | ... CI79: =IFERROR(CI78/CD78-1,"") -> 0.57290686 | CJ79: =IFERROR(CJ78/CI78-1,"") -> 0.047482014 | CK79: =IFERROR(CK78/CJ78-1,"") -> 0.14230769 | CL79: =IFERROR(CL78/CK78-1,"") -> 0.14074074 | CM79: =IFERROR(CM78/CL78-1,"") -> 0.1 | CT79: Military Aircraft EBIT margin % | CU79: 0.095 | CV79: 0.1 | CW79: 0.105 | CX79: 0.11 | CY79: 0.11
B80: EBIT % | BK80: =IFERROR(BK78/BK76,"") -> 0 | BL80: =IFERROR(BL78/BL76,"") -> 0 | BM80: =IFERROR(BM78/BM76,"") -> 0 | BN80: =IFERROR(BN78/BN76,"") -> 0 | BO80: =IFERROR(BO78/BO76,"") | BP80: =IFERROR(BP78/BP76,"") -> 0.093183644 | BQ80: =IFERROR(BQ78/BQ76,"") -> 0.11188393 | BR80: =IFERROR(BR78/BR76,"") -> 0.076670159 | ... CF80: =IFERROR(CF78/CF76,"") -> 0.13800053 | CG80: 0.14 | CH80: 0.14 | CI80: 0.139 | CJ80: =CHOOSE(MATCH($CO$3,{"Base";"Bull";"Bear"},0),CV63,CV73,CV83) -> 0.13 | CK80: =CHOOSE(MATCH($CO$3,{"Base";"Bull";"Bear"},0),CW63,CW73,CW83) -> 0.135 | CL80: =CHOOSE(MATCH($CO$3,{"Base";"Bull";"Bear"},0),CX63,CX73,CX83) -> 0.14 | CM80: =CHOOSE(MATCH($CO$3,{"Base";"Bull";"Bear"},0),CY63,CY73,CY83) -> 0.14 | CT80: Commercial Aircraft sales y/y % | CU80: 0.05 | CV80: 0.04 | CW80: 0.03 | CX80: 0.02 | CY80: 0.02
B81: Incremental EBIT (ΔEBIT / ΔSales) | BK81: =IFERROR((BK78-BF78)/(BK76-BF76),"") -> 0 | BL81: =IFERROR((BL78-BG78)/(BL76-BG76),"") -> 0 | BM81: =IFERROR((BM78-BH78)/(BM76-BH76),"") -> 0 | BN81: =IFERROR((BN78-BI78)/(BN76-BI76),"") -> 0 | BO81: =IFERROR((BO78-BJ78)/(BO76-BJ76),"") | BP81: =IFERROR((BP78-BK78)/(BP76-BK76),"") -> 2.0439118 | BQ81: =IFERROR((BQ78-BL78)/(BQ76-BL76),"") -> 1.222316 | BR81: =IFERROR((BR78-BM78)/(BR76-BM76),"") -> 0.99077727 | ... CD81: =IFERROR((CD78-BY78)/(CD76-BY76),"") -> 0.11155736 | CI81: =IFERROR((CI78-CD78)/(CI76-CD76),"") -> 0.17733842 | CJ81: =IFERROR((CJ78-CI78)/(CJ76-CI76),"") -> 0.055 | CK81: =IFERROR((CK78-CJ78)/(CK76-CJ76),"") -> 0.185 | CL81: =IFERROR((CL78-CK78)/(CL76-CK76),"") -> 0.19 | CM81: =IFERROR((CM78-CL78)/(CM76-CL76),"") -> 0.14 | CT81: Commercial Aircraft EBIT margin % | CU81: 0.105 | CV81: 0.11 | CW81: 0.115 | CX81: 0.12 | CY81: 0.12
B82: Backlog ($M) | CT82: Space & Defense sales y/y % | CU82: 0.08 | CV82: 0.06 | CW82: 0.05 | CX82: 0.05 | CY82: 0.05
B83: Backlog y/y % | BK83: =IFERROR(BK82/BF82-1,"") | BL83: =IFERROR(BL82/BG82-1,"") | BM83: =IFERROR(BM82/BH82-1,"") | BN83: =IFERROR(BN82/BI82-1,"") | BO83: =IFERROR(BO82/BJ82-1,"") | BP83: =IFERROR(BP82/BK82-1,"") | BQ83: =IFERROR(BQ82/BL82-1,"") | BR83: =IFERROR(BR82/BM82-1,"") | ... CD83: =IFERROR(CD82/BY82-1,"") | CI83: =IFERROR(CI82/CD82-1,"") | CJ83: =IFERROR(CJ82/CI82-1,"") | CK83: =IFERROR(CK82/CJ82-1,"") | CL83: =IFERROR(CL82/CK82-1,"") | CM83: =IFERROR(CM82/CL82-1,"") | CT83: Space & Defense EBIT margin % | CU83: 0.105 | CV83: 0.11 | CW83: 0.115 | CX83: 0.12 | CY83: 0.12
B84: Book-to-bill (Bookings / Sales) | BK84: =IFERROR((BK76+BK82-BF82)/BK76,"") -> 1 | BL84: =IFERROR((BL76+BL82-BG82)/BL76,"") -> 1 | BM84: =IFERROR((BM76+BM82-BH82)/BM76,"") -> 1 | BN84: =IFERROR((BN76+BN82-BI82)/BN76,"") -> 1 | BO84: =IFERROR((BO76+BO82-BJ82)/BO76,"") | BP84: =IFERROR((BP76+BP82-BK82)/BP76,"") -> 1 | BQ84: =IFERROR((BQ76+BQ82-BL82)/BQ76,"") -> 1 | BR84: =IFERROR((BR76+BR82-BM82)/BR76,"") -> 1 | ... CD84: =IFERROR((CD76+CD82-BY82)/CD76,"") -> 1 | CI84: =IFERROR((CI76+CI82-CD82)/CI76,"") -> 1 | CJ84: =IFERROR((CJ76+CJ82-CI82)/CJ76,"") -> 1 | CK84: =IFERROR((CK76+CK82-CJ82)/CK76,"") -> 1 | CL84: =IFERROR((CL76+CL82-CK82)/CL76,"") -> 1 | CM84: =IFERROR((CM76+CM82-CL82)/CM76,"") -> 1 | CT84: Industrial sales y/y % | CU84: 0.01 | CV84: 0.01 | CW84: 0.015 | CX84: 0.015 | CY84: 0.02
CT85: Industrial EBIT margin % | CU85: 0.1 | CV85: 0.105 | CW85: 0.11 | CX85: 0.11 | CY85: 0.115
B86: Industrial
B87: Net sales | BK87: 212.913 | BL87: 236.17 | BM87: 231.25 | BN87: =BO87-BK87-BL87-BM87 -> -680.333 | BP87: 232.059 | BQ87: 243.935 | BR87: 252.749 | BS87: =BT87-BP87-BQ87-BR87 -> 253.981 | BT87: 982.724 | BU87: 246.256 | BV87: 253.422 | BW87: 249.784 | BX87: =BY87-BU87-BV87-BW87 -> 241.684 | BY87: 991.146 | BZ87: 228.188 | CA87: 234.426 | CB87: 239.56 | CC87: =CD87-BZ87-CA87-CB87 -> 253.407 | CD87: 955.581 | CE87: 260.814 | CF87: 255.858 | CG87: =CB87*(1+CG88) -> 256.3292 | CH87: =CI87-CE87-CF87-CG87 -> 226.9748 | CI87: =956*(1+CI88) -> 999.976 | CJ87: =CI87*(1+CJ88) -> 1039.975 | CK87: =CJ87*(1+CK88) -> 1081.574 | CL87: =CK87*(1+CL88) -> 1119.4291 | CM87: =CL87*(1+CM88) -> 1158.6092 | CO87: 0.035993238 | CQ87: Industrial: low-single-digit growth FY26E–FY30E. Drivers: medical devices, simulation & test, industrial automation. Energy exposure declining post-divestitures. More cyclical than aerospace/defense.
B88: Sales y/y % | BK88: =IFERROR(BK87/BF87-1,"") | BL88: =IFERROR(BL87/BG87-1,"") | BM88: =IFERROR(BM87/BH87-1,"") | BN88: =IFERROR(BN87/BI87-1,"") | BO88: =IFERROR(BO87/BJ87-1,"") | BP88: =IFERROR(BP87/BK87-1,"") -> 0.089924053 | BQ88: =IFERROR(BQ87/BL87-1,"") -> 0.032878858 | BR88: =IFERROR(BR87/BM87-1,"") -> 0.092968649 | ... CF88: =IFERROR(CF87/CA87-1,"") -> 0.091423306 | CG88: 0.07 | CH88: =IFERROR(CH87/CC87-1,"") -> -0.1043073 | CI88: 0.046 | CJ88: =CHOOSE(MATCH($CO$3,{"Base";"Bull";"Bear"},0),CV64,CV74,CV84) -> 0.04 | CK88: =CHOOSE(MATCH($CO$3,{"Base";"Bull";"Bear"},0),CW64,CW74,CW84) -> 0.04 | CL88: =CHOOSE(MATCH($CO$3,{"Base";"Bull";"Bear"},0),CX64,CX74,CX84) -> 0.035 | CM88: =CHOOSE(MATCH($CO$3,{"Base";"Bull";"Bear"},0),CY64,CY74,CY84) -> 0.035 | CQ88: Margin steady ~10-11%. Limited upside without portfolio actions; management focused on selective divestitures of low-margin product lines.
B89: EBIT | BN89: =BO89-BK89-BL89-BM89 -> 0 | BP89: 36.751 | BQ89: 24.397 | BR89: 28.035 | BS89: =BT89-BP89-BQ89-BR89 -> 12.086 | BT89: 101.269 | BU89: 29.024 | BV89: 28.155 | BW89: 24.413 | BX89: =BY89-BU89-BV89-BW89 -> 11.608 | BY89: 93.2 | BZ89: 25.498 | CA89: 27.213 | CB89: 22.989 | CC89: =CD89-BZ89-CA89-CB89 -> 32.219 | CD89: 107.919 | CE89: 36.253 | CF89: 33.005 | CG89: =CG87*CG91 -> 37.424063 | CH89: =CH87*CH91 -> 35.181094 | CI89: =CI87*CI91 -> 142.99657 | CJ89: =CJ87*CJ91 -> 124.797 | CK89: =CK87*CK91 -> 135.19676 | CL89: =CL87*CL91 -> 139.92864 | CM89: =CM87*CM91 -> 150.61919
B90: EBIT y/y % | BK90: =IFERROR(BK89/BF89-1,"") | BL90: =IFERROR(BL89/BG89-1,"") | BM90: =IFERROR(BM89/BH89-1,"") | BN90: =IFERROR(BN89/BI89-1,"") | BO90: =IFERROR(BO89/BJ89-1,"") | BP90: =IFERROR(BP89/BK89-1,"") | BQ90: =IFERROR(BQ89/BL89-1,"") | BR90: =IFERROR(BR89/BM89-1,"") | ... CI90: =IFERROR(CI89/CD89-1,"") -> 0.32503607 | CJ90: =IFERROR(CJ89/CI89-1,"") -> -0.12727273 | CK90: =IFERROR(CK89/CJ89-1,"") -> 0.083333333 | CL90: =IFERROR(CL89/CK89-1,"") -> 0.035 | CM90: =IFERROR(CM89/CL89-1,"") -> 0.0764
B91: EBIT % | BK91: =IFERROR(BK89/BK87,"") -> 0 | BL91: =IFERROR(BL89/BL87,"") -> 0 | BM91: =IFERROR(BM89/BM87,"") -> 0 | BN91: =IFERROR(BN89/BN87,"") -> 0 | BO91: =IFERROR(BO89/BO87,"") | BP91: =IFERROR(BP89/BP87,"") -> 0.15836921 | BQ91: =IFERROR(BQ89/BQ87,"") -> 0.10001435 | BR91: =IFERROR(BR89/BR87,"") -> 0.11092032 | ... CF91: =IFERROR(CF89/CF87,"") -> 0.12899733 | CG91: 0.146 | CH91: 0.155 | CI91: 0.143 | CJ91: =CHOOSE(MATCH($CO$3,{"Base";"Bull";"Bear"},0),CV65,CV75,CV85) -> 0.12 | CK91: =CHOOSE(MATCH($CO$3,{"Base";"Bull";"Bear"},0),CW65,CW75,CW85) -> 0.125 | CL91: =CHOOSE(MATCH($CO$3,{"Base";"Bull";"Bear"},0),CX65,CX75,CX85) -> 0.125 | CM91: =CHOOSE(MATCH($CO$3,{"Base";"Bull";"Bear"},0),CY65,CY75,CY85) -> 0.13
B92: Incremental EBIT (ΔEBIT / ΔSales) | BK92: =IFERROR((BK89-BF89)/(BK87-BF87),"") -> 0 | BL92: =IFERROR((BL89-BG89)/(BL87-BG87),"") -> 0 | BM92: =IFERROR((BM89-BH89)/(BM87-BH87),"") -> 0 | BN92: =IFERROR((BN89-BI89)/(BN87-BI87),"") -> 0 | BO92: =IFERROR((BO89-BJ89)/(BO87-BJ87),"") | BP92: =IFERROR((BP89-BK89)/(BP87-BK87),"") -> 1.9195132 | BQ92: =IFERROR((BQ89-BL89)/(BQ87-BL87),"") -> 3.1419189 | BR92: =IFERROR((BR89-BM89)/(BR87-BM87),"") -> 1.3040141 | ... CD92: =IFERROR((CD89-BY89)/(CD87-BY87),"") -> -0.41386194 | CI92: =IFERROR((CI89-CD89)/(CI87-CD87),"") -> 0.79012429 | CJ92: =IFERROR((CJ89-CI89)/(CJ87-CI87),"") -> -0.455 | CK92: =IFERROR((CK89-CJ89)/(CK87-CJ87),"") -> 0.25 | CL92: =IFERROR((CL89-CK89)/(CL87-CK87),"") -> 0.125 | CM92: =IFERROR((CM89-CL89)/(CM87-CL87),"") -> 0.27285714
B93: Backlog ($M)
B94: Backlog y/y % | BK94: =IFERROR(BK93/BF93-1,"") | BL94: =IFERROR(BL93/BG93-1,"") | BM94: =IFERROR(BM93/BH93-1,"") | BN94: =IFERROR(BN93/BI93-1,"") | BO94: =IFERROR(BO93/BJ93-1,"") | BP94: =IFERROR(BP93/BK93-1,"") | BQ94: =IFERROR(BQ93/BL93-1,"") | BR94: =IFERROR(BR93/BM93-1,"") | ... CD94: =IFERROR(CD93/BY93-1,"") | CI94: =IFERROR(CI93/CD93-1,"") | CJ94: =IFERROR(CJ93/CI93-1,"") | CK94: =IFERROR(CK93/CJ93-1,"") | CL94: =IFERROR(CL93/CK93-1,"") | CM94: =IFERROR(CM93/CL93-1,"")
B95: Book-to-bill (Bookings / Sales) | BK95: =IFERROR((BK87+BK93-BF93)/BK87,"") -> 1 | BL95: =IFERROR((BL87+BL93-BG93)/BL87,"") -> 1 | BM95: =IFERROR((BM87+BM93-BH93)/BM87,"") -> 1 | BN95: =IFERROR((BN87+BN93-BI93)/BN87,"") -> 1 | BO95: =IFERROR((BO87+BO93-BJ93)/BO87,"") | BP95: =IFERROR((BP87+BP93-BK93)/BP87,"") -> 1 | BQ95: =IFERROR((BQ87+BQ93-BL93)/BQ87,"") -> 1 | BR95: =IFERROR((BR87+BR93-BM93)/BR87,"") -> 1 | ... CD95: =IFERROR((CD87+CD93-BY93)/CD87,"") -> 1 | CI95: =IFERROR((CI87+CI93-CD93)/CI87,"") -> 1 | CJ95: =IFERROR((CJ87+CJ93-CI93)/CJ87,"") -> 1 | CK95: =IFERROR((CK87+CK93-CJ93)/CK87,"") -> 1 | CL95: =IFERROR((CL87+CL93-CK93)/CL87,"") -> 1 | CM95: =IFERROR((CM87+CM93-CL93)/CM87,"") -> 1
B97: Group Total (consolidated, FY22–forecast)
B98: Net sales | G98: =G114 -> 2114.252 | L98: =L114 -> 2330.68 | Q98: =Q114 -> 2469.536 | V98: =V114 -> 2610.311 | AA98: =AA114 -> 2648.385 | AF98: =AF114 -> 2525.532 | AK98: =AK114 -> 2411.937 | AP98: =AP114 -> 2497.524 | AU98: =AU114 -> 2709.468 | AZ98: =AZ114 -> 2904.663 | BE98: =BE114 -> 2884.554 | BJ98: =BJ114 -> 2851.993 | BK98: =BK54+BK65+BK76+BK87 -> 724.086 | BL98: =BL54+BL65+BL76+BL87 -> 770.787 | BM98: =BM54+BM65+BM76+BM87 -> 772.911 | BN98: =BN54+BN65+BN76+BN87 -> -2267.784 | BO98: =BO114 -> 3035.783 | BP98: =BP54+BP65+BP76+BP87 -> 760.103 | BQ98: =BQ54+BQ65+BQ76+BQ87 -> 836.792 | BR98: =BR54+BR65+BR76+BR87 -> 850.176 | BS98: =BS54+BS65+BS76+BS87 -> 869.119 | BT98: =BT54+BT65+BT76+BT87 -> 3316.19 | BU98: =BU54+BU65+BU76+BU87 -> 856.85 | BV98: =BV54+BV65+BV76+BV87 -> 930.303 | BW98: =BW54+BW65+BW76+BW87 -> 904.735 | ... CM98: =CM54+CM65+CM76+CM87 -> 5581.8999 | CO98: 0.060561927
B99: Sales y/y % | L99: =IFERROR(L98/G98-1,"") -> 0.10236623 | Q99: =IFERROR(Q98/L98-1,"") -> 0.059577462 | V99: =IFERROR(V98/Q98-1,"") -> 0.057004636 | AA99: =IFERROR(AA98/V98-1,"") -> 0.014586001 | AF99: =IFERROR(AF98/AA98-1,"") -> -0.046387893 | AK99: =IFERROR(AK98/AF98-1,"") -> -0.044978642 | AP99: =IFERROR(AP98/AK98-1,"") -> 0.035484758 | AU99: =IFERROR(AU98/AP98-1,"") -> 0.084861647 | AZ99: =IFERROR(AZ98/AU98-1,"") -> 0.072041818 | BE99: =IFERROR(BE98/AZ98-1,"") -> -0.0069230062 | BJ99: =IFERROR(BJ98/BE98-1,"") -> -0.011288054 | BK99: =IFERROR(BK98/BF98-1,"") | BL99: =IFERROR(BL98/BG98-1,"") | BM99: =IFERROR(BM98/BH98-1,"") | BN99: =IFERROR(BN98/BI98-1,"") | BO99: =IFERROR(BO98/BJ98-1,"") -> 0.064442655 | BP99: =IFERROR(BP98/BK98-1,"") -> 0.049741329 | BQ99: =IFERROR(BQ98/BL98-1,"") -> 0.085633255 | ... CI99: =IFERROR(CI98/CD98-1,"") -> 0.10474115 | CJ99: =IFERROR(CJ98/CI98-1,"") -> 0.081489464 | CK99: =IFERROR(CK98/CJ98-1,"") -> 0.070247399 | CL99: =IFERROR(CL98/CK98-1,"") -> 0.064825079 | CM99: =IFERROR(CM98/CL98-1,"") -> 0.061889341
B100: Sales - Acquisition contribution y/y % | L100: 0.007 | Q100: 0.009 | V100: 0.04 | AA100: 0.008 | AF100: 0.004 | AK100: 0 | AP100: 0.005 | AU100: 0.016 | AZ100: 0 | BE100: 0 | BJ100: -0.014 | BO100: 0.004 | BT100: 0.002 | BY100: 0.002 | CD100: -0.011 | CI100: 0 | CJ100: 0 | CK100: 0 | CL100: 0 | CM100: 0
B101: Sales - Organic y/y % (implied) | L101: =IFERROR(L99-L100,"") -> 0.095366227 | Q101: =IFERROR(Q99-Q100,"") -> 0.050577462 | V101: =IFERROR(V99-V100,"") -> 0.017004636 | AA101: =IFERROR(AA99-AA100,"") -> 0.0065860014 | AF101: =IFERROR(AF99-AF100,"") -> -0.050387893 | AK101: =IFERROR(AK99-AK100,"") -> -0.044978642 | AP101: =IFERROR(AP99-AP100,"") -> 0.030484758 | AU101: =IFERROR(AU99-AU100,"") -> 0.068861647 | AZ101: =IFERROR(AZ99-AZ100,"") -> 0.072041818 | BE101: =IFERROR(BE99-BE100,"") -> -0.0069230062 | BJ101: =IFERROR(BJ99-BJ100,"") -> 0.0027119465 | BO101: =IFERROR(BO99-BO100,"") -> 0.060442655 | BT101: =IFERROR(BT99-BT100,"") -> 0.090367274 | BY101: =IFERROR(BY99-BY100,"") -> 0.08628505 | CD101: =IFERROR(CD99-CD100,"") -> 0.080733109 | CI101: =IFERROR(CI99-CI100,"") -> 0.10474115 | CJ101: =IFERROR(CJ99-CJ100,"") -> 0.081489464 | CK101: =IFERROR(CK99-CK100,"") -> 0.070247399 | CL101: =IFERROR(CL99-CL100,"") -> 0.064825079 | CM101: =IFERROR(CM99-CM100,"") -> 0.061889341
B102: EBIT | BK102: =BK56+BK67+BK78+BK89 -> 0 | BL102: =BL56+BL67+BL78+BL89 -> 0 | BM102: =BM56+BM67+BM78+BM89 -> 0 | BN102: =BN56+BN67+BN78+BN89 -> 0 | BO102: =BO56+BO67+BO78+BO89 -> 0 | BP102: =BP56+BP67+BP78+BP89 -> 86.763 | BQ102: =BQ56+BQ67+BQ78+BQ89 -> 83.766 | BR102: =BR56+BR67+BR78+BR89 -> 84.508 | ... CM102: =CM56+CM67+CM78+CM89 -> 757.94422 | CO102: 0.092175741
B103: EBIT y/y % | BK103: =IFERROR(BK102/BF102-1,"") | BL103: =IFERROR(BL102/BG102-1,"") | BM103: =IFERROR(BM102/BH102-1,"") | BN103: =IFERROR(BN102/BI102-1,"") | BO103: =IFERROR(BO102/BJ102-1,"") | BP103: =IFERROR(BP102/BK102-1,"") | BQ103: =IFERROR(BQ102/BL102-1,"") | BR103: =IFERROR(BR102/BM102-1,"") | ... CI103: =IFERROR(CI102/CD102-1,"") -> 0.26929724 | CJ103: =IFERROR(CJ102/CI102-1,"") -> 0.014688064 | CK103: =IFERROR(CK102/CJ102-1,"") -> 0.11359572 | CL103: =IFERROR(CL102/CK102-1,"") -> 0.097568075 | CM103: =IFERROR(CM102/CL102-1,"") -> 0.070903261
B104: EBIT % | BK104: =IFERROR(BK102/BK98,"") -> 0 | BL104: =IFERROR(BL102/BL98,"") -> 0 | BM104: =IFERROR(BM102/BM98,"") -> 0 | BN104: =IFERROR(BN102/BN98,"") -> 0 | BO104: =IFERROR(BO102/BO98,"") -> 0 | BP104: =IFERROR(BP102/BP98,"") -> 0.11414637 | BQ104: =IFERROR(BQ102/BQ98,"") -> 0.10010373 | BR104: =IFERROR(BR102/BR98,"") -> 0.099400595 | ... CM104: =IFERROR(CM102/CM98,"") -> 0.13578606
B105: Incremental EBIT (ΔEBIT / ΔSales) | BK105: =IFERROR((BK102-BF102)/(BK98-BF98),"") -> 0 | BL105: =IFERROR((BL102-BG102)/(BL98-BG98),"") -> 0 | BM105: =IFERROR((BM102-BH102)/(BM98-BH98),"") -> 0 | BN105: =IFERROR((BN102-BI102)/(BN98-BI98),"") -> 0 | BO105: =IFERROR((BO102-BJ102)/(BO98-BJ98),"") -> 0 | BP105: =IFERROR((BP102-BK102)/(BP98-BK98),"") -> 2.4089458 | BQ105: =IFERROR((BQ102-BL102)/(BQ98-BL98),"") -> 1.2690857 | BR105: =IFERROR((BR102-BM102)/(BR98-BM98),"") -> 1.0937423 | ... CF105: =IFERROR((CF102-CA102)/(CF98-CA98),"") -> 0.24447727 | CI105: =IFERROR((CI102-CD102)/(CI98-CD98),"") -> 0.29942576 | CJ105: =IFERROR((CJ102-CI102)/(CJ98-CI98),"") -> 0.024117955 | CK105: =IFERROR((CK102-CJ102)/(CK98-CJ98),"") -> 0.20301091 | CL105: =IFERROR((CL102-CK102)/(CL98-CK98),"") -> 0.19660552 | CM105: =IFERROR((CM102-CL102)/(CM98-CL98),"") -> 0.15425334
B106: Twelve-month backlog ($M) | BF106: 1898 | BG106: 1900 | BH106: 2000 | BI106: 1900 | BJ106: 1900 | BK106: 2200 | BL106: 2300 | BM106: 2200 | BN106: 2000 | BO106: 2000 | BP106: 2343 | BQ106: 2300 | BR106: 2300 | BS106: 2420 | BT106: 2420 | BU106: 2500 | BV106: 2500 | BW106: 2450 | BX106: 2500 | BY106: 2500 | BZ106: 2500 | CA106: 2490 | CB106: 2650 | CC106: 3000 | CD106: 3000 | CE106: 3260 | CF106: 3310 | CG106: =ROUND((CE106+CF106+CI106)/3,0) -> 3295 | CH106: =CI106 -> 3314.2235 | CI106: =CD106*(1+CI99) -> 3314.2235 | CJ106: =CI106*(1+CJ99) -> 3584.2977 | CK106: =CJ106*(1+CK99) -> 3836.0853 | CL106: =CK106*(1+CL99) -> 4084.7599 | CM106: =CL106*(1+CM99) -> 4337.563
B107: 12-mo backlog y/y % | BK107: =IFERROR(BK106/BF106-1,"") -> 0.15911486 | BL107: =IFERROR(BL106/BG106-1,"") -> 0.21052632 | BM107: =IFERROR(BM106/BH106-1,"") -> 0.1 | BN107: =IFERROR(BN106/BI106-1,"") -> 0.052631579 | BO107: =IFERROR(BO106/BJ106-1,"") -> 0.052631579 | BP107: =IFERROR(BP106/BK106-1,"") -> 0.065 | BQ107: =IFERROR(BQ106/BL106-1,"") -> 0 | BR107: =IFERROR(BR106/BM106-1,"") -> 0.045454545 | ... CI107: =IFERROR(CI106/CD106-1,"") -> 0.10474115 | CJ107: =IFERROR(CJ106/CI106-1,"") -> 0.081489464 | CK107: =IFERROR(CK106/CJ106-1,"") -> 0.070247399 | CL107: =IFERROR(CL106/CK106-1,"") -> 0.064825079 | CM107: =IFERROR(CM106/CL106-1,"") -> 0.061889341
B108: Total backlog ($M) | BT108: 5150 | BY108: 5060 | CD108: 6010 | CE108: =CE106*2 -> 6520 | CF108: =CF106*2 -> 6620 | CG108: =CG106*2 -> 6590 | CH108: =CI108 -> 6639.4943 | CI108: =CD108*(1+CI99) -> 6639.4943 | CJ108: =CI108*(1+CJ99) -> 7180.5431 | CK108: =CJ108*(1+CK99) -> 7684.9576 | CL108: =CK108*(1+CL99) -> 8183.1356 | CM108: =CL108*(1+CM99) -> 8689.5845
B109: Total backlog y/y % | BK109: =IFERROR(BK108/BF108-1,"") | BL109: =IFERROR(BL108/BG108-1,"") | BM109: =IFERROR(BM108/BH108-1,"") | BN109: =IFERROR(BN108/BI108-1,"") | BO109: =IFERROR(BO108/BJ108-1,"") | BP109: =IFERROR(BP108/BK108-1,"") | BQ109: =IFERROR(BQ108/BL108-1,"") | BR109: =IFERROR(BR108/BM108-1,"") | ... CI109: =IFERROR(CI108/CD108-1,"") -> 0.10474115 | CJ109: =IFERROR(CJ108/CI108-1,"") -> 0.081489464 | CK109: =IFERROR(CK108/CJ108-1,"") -> 0.070247399 | CL109: =IFERROR(CL108/CK108-1,"") -> 0.064825079 | CM109: =IFERROR(CM108/CL108-1,"") -> 0.061889341
...

Sheet Moog-Bull-Base-Bear
B2: Moog Inc. — Bull / Base / Bear Case P&L Summary | J2: Share price ($): | K2: 345
B3: Adjusted figures · $ millions · Linked to Model — toggle scenario via Model!CK3 | J3: As of: | K3: =TODAY() -> 46169
B5: Scenario: | C5: =Model!CO3 -> Base | N5: Scenario: | O5: Bull | Z5: Scenario: | AA5: Bear
B7: ($M, except EPS and shares) | C7: FY25A | D7: FY26E | E7: FY27E | F7: FY28E | G7: FY29E | H7: FY30E | I7: 25-'30 CAGR | J7: LT Hist Avg | K7: LT Hist Min | L7: LT Hist Max | N7: ($M, except EPS and shares) | O7: FY25A | P7: FY26E | Q7: FY27E | R7: FY28E | S7: FY29E | T7: FY30E | U7: 25-'30 CAGR | V7: LT Hist Avg | W7: LT Hist Min | X7: LT Hist Max | Z7: ($M, except EPS and shares) | AA7: FY25A | AB7: FY26E | AC7: FY27E | AD7: FY28E | AE7: FY29E | AF7: FY30E | AG7: 25-'30 CAGR | AH7: LT Hist Avg | AI7: LT Hist Min | AJ7: LT Hist Max
B9: Revenue | C9: =Model!CD114 -> 3860.624 | D9: =Model!CI114 -> 4264.9902 | E9: =Model!CJ114 -> 4612.542 | F9: =Model!CK114 -> 4936.561 | G9: =Model!CL114 -> 5256.574 | H9: =Model!CM114 -> 5581.8999 | I9: =IFERROR((H9/C9)^(1/5)-1,"n/m") -> 0.076526953 | N9: Revenue | O9: 3860.624 | P9: 4264.9902 | Q9: 4738.1424 | R9: 5175.8989 | S9: 5605.2429 | T9: 6047.3405 | U9: 0.093909475 | Z9: Revenue | AA9: 3860.624 | AB9: 4264.9902 | AC9: 4421.3914 | AD9: 4555.9175 | AE9: 4684.1497 | AF9: 4822.1843 | AG9: 0.045483682
B10: Revenue y/y % | D10: =IFERROR(D9/C9-1,"") -> 0.10474115 | E10: =IFERROR(E9/D9-1,"") -> 0.081489464 | F10: =IFERROR(F9/E9-1,"") -> 0.070247399 | G10: =IFERROR(G9/F9-1,"") -> 0.064825079 | H10: =IFERROR(H9/G9-1,"") -> 0.061889341 | N10: Revenue y/y % | P10: 0.10474115 | Q10: 0.11093863 | R10: 0.092389911 | S10: 0.082950609 | T10: 0.078872163 | Z10: Revenue y/y % | AB10: 0.10474115 | AC10: 0.036670945 | AD10: 0.030426179 | AE10: 0.028146311 | AF10: 0.029468425
B12: Gross Profit | C12: =Model!CD116 -> 1057.348 | D12: =Model!CI116 -> 1194.1973 | E12: =Model!CJ116 -> 1314.5745 | F12: =Model!CK116 -> 1431.6027 | G12: =Model!CL116 -> 1550.6893 | H12: =Model!CM116 -> 1674.57 | I12: =IFERROR((H12/C12)^(1/5)-1,"n/m") -> 0.096319327 | N12: Gross Profit | O12: 1057.348 | P12: 1194.1973 | Q12: 1350.3706 | R12: 1501.0107 | S12: 1653.5467 | T12: 1814.2022 | U12: 0.11402143 | Z12: Gross Profit | AA12: 1057.348 | AB12: 1194.1973 | AC12: 1260.0966 | AD12: 1321.2161 | AE12: 1381.8242 | AF12: 1446.6553 | AG12: 0.064705313
B13: GP % | C13: =IFERROR(C12/C9,"") -> 0.27388008 | D13: =IFERROR(D12/D9,"") -> 0.28 | E13: =IFERROR(E12/E9,"") -> 0.285 | F13: =IFERROR(F12/F9,"") -> 0.29 | G13: =IFERROR(G12/G9,"") -> 0.295 | H13: =IFERROR(H12/H9,"") -> 0.3 | J13: =AVERAGE(Model!AF165,Model!AK165,Model!AP165,Model!AU165,Model!AZ165,Model!BE165,Model!BJ165,Model!BO165,Model!BT165,Model!BY165,Model!CD165) -> 0.2792281 | K13: =MIN(Model!AF165,Model!AK165,Model!AP165,Model!AU165,Model!AZ165,Model!BE165,Model!BJ165,Model!BO165,Model!BT165,Model!BY165,Model!CD165) -> 0.2578201 | L13: =MAX(Model!AF165,Model!AK165,Model!AP165,Model!AU165,Model!AZ165,Model!BE165,Model!BJ165,Model!BO165,Model!BT165,Model!BY165,Model!CD165) -> 0.29502553 | N13: GP % | O13: 0.27388008 | P13: 0.28 | Q13: 0.285 | R13: 0.29 | S13: 0.295 | T13: 0.3 | V13: 0.2792281 | W13: 0.2578201 | X13: 0.29502553 | Z13: GP % | AA13: 0.27388008 | AB13: 0.28 | AC13: 0.285 | AD13: 0.29 | AE13: 0.295 | AF13: 0.3 | AH13: 0.2792281 | AI13: 0.2578201 | AJ13: 0.29502553
B15: EBIT (Adjusted Operating Profit) | C15: =IF(ISNUMBER(Model!CD150),IF(Model!CD150>0,Model!CD150,Model!CD126),Model!CD126) -> 501.268 | D15: =IF(ISNUMBER(Model!CI150),IF(Model!CI150>0,Model!CI150,Model!CI126),Model!CI126) -> 511.84054 | E15: =IF(ISNUMBER(Model!CJ150),IF(Model!CJ150>0,Model!CJ150,Model!CJ126),Model!CJ126) -> 567.74948 | F15: =IF(ISNUMBER(Model!CK150),IF(Model!CK150>0,Model!CK150,Model!CK126),Model!CK126) -> 626.56643 | G15: =IF(ISNUMBER(Model!CL150),IF(Model!CL150>0,Model!CL150,Model!CL126),Model!CL126) -> 702.82692 | H15: =IF(ISNUMBER(Model!CM150),IF(Model!CM150>0,Model!CM150,Model!CM126),Model!CM126) -> 785.68656 | I15: =IFERROR((H15/C15)^(1/5)-1,"n/m") -> 0.094046721 | N15: EBIT (Adjusted Operating Profit) | O15: 501.268 | P15: 511.84054 | Q15: 582.82153 | R15: 656.48366 | S15: 749.02555 | T15: 850.84825 | U15: 0.11162019 | Z15: EBIT (Adjusted Operating Profit) | AA15: 501.268 | AB15: 511.84054 | AC15: 544.81141 | AD15: 578.98598 | AE15: 626.9807 | AF15: 679.32637 | AG15: 0.062678022
B16: EBIT y/y % | D16: =IFERROR(D15/C15-1,"") -> 0.021091591 | E16: =IFERROR(E15/D15-1,"") -> 0.10923117 | F16: =IFERROR(F15/E15-1,"") -> 0.10359665 | G16: =IFERROR(G15/F15-1,"") -> 0.12171174 | H16: =IFERROR(H15/G15-1,"") -> 0.11789481 | N16: EBIT y/y % | P16: 0.021091591 | Q16: 0.13867794 | R16: 0.12638883 | S16: 0.14096601 | T16: 0.13594023 | Z16: EBIT y/y % | AB16: 0.021091591 | AC16: 0.064416303 | AD16: 0.062727329 | AE16: 0.08289445 | AF16: 0.083488482
B17: EBIT % | C17: =IFERROR(C15/C9,"") -> 0.12984119 | D17: =IFERROR(D15/D9,"") -> 0.12000978 | E17: =IFERROR(E15/E9,"") -> 0.1230882 | F17: =IFERROR(F15/F9,"") -> 0.12692367 | G17: =IFERROR(G15/G9,"") -> 0.13370437 | H17: =IFERROR(H15/H9,"") -> 0.14075612 | J17: =AVERAGE(Model!AF151,Model!AK151,Model!AP151,Model!AU151,Model!AZ151,Model!BE151,Model!BJ151,Model!BO151,Model!BT151,Model!BY151,Model!CD151) -> 0.10480017 | K17: =MIN(Model!AF151,Model!AK151,Model!AP151,Model!AU151,Model!AZ151,Model!BE151,Model!BJ151,Model!BO151,Model!BT151,Model!BY151,Model!CD151) -> 0.084259871 | L17: =MAX(Model!AF151,Model!AK151,Model!AP151,Model!AU151,Model!AZ151,Model!BE151,Model!BJ151,Model!BO151,Model!BT151,Model!BY151,Model!CD151) -> 0.12984119 | N17: EBIT % | O17: 0.12984119 | P17: 0.12000978 | Q17: 0.12300634 | R17: 0.12683471 | S17: 0.13362945 | T17: 0.14069792 | V17: 0.10480017 | W17: 0.084259871 | X17: 0.12984119 | Z17: EBIT % | AA17: 0.12984119 | AB17: 0.12000978 | AC17: 0.12322171 | AD17: 0.12708439 | AE17: 0.13385155 | AF17: 0.14087524 | AH17: 0.10480017 | AI17: 0.084259871 | AJ17: 0.12984119
B19: Net Income (Adjusted Earnings) | C19: =Model!CD155 -> 278.685 | D19: =Model!CI155 -> 335.35121 | E19: =Model!CJ155 -> 382.98355 | F19: =Model!CK155 -> 429.88671 | G19: =Model!CL155 -> 490.10664 | H19: =Model!CM155 -> 556.03985 | I19: =IFERROR((H19/C19)^(1/5)-1,"n/m") -> 0.14814956 | N19: Net Income (Adjusted Earnings) | O19: 278.685 | P19: 335.79881 | Q19: 396.13347 | R19: 456.31 | S19: 530.92955 | T19: 612.64891 | U19: 0.17062991 | Z19: Net Income (Adjusted Earnings) | AA19: 278.685 | AB19: 335.79881 | AC19: 367.05573 | AD19: 397.02427 | AE19: 437.56524 | AF19: 481.43467 | AG19: 0.11553899
B21: Diluted shares ('000) | C21: =Model!CD139 -> 32082.601 | D21: =Model!CI139 -> 31647.818 | E21: =Model!CJ139 -> 31241.48 | F21: =Model!CK139 -> 30861.724 | G21: =Model!CL139 -> 30506.811 | H21: =Model!CM139 -> 30175.118 | I21: =IFERROR((H21/C21)^(1/5)-1,"n/m") -> -0.012184399 | N21: Diluted shares ('000) | O21: 32082.601 | P21: 31647.818 | Q21: 31241.48 | R21: 30861.724 | S21: 30506.811 | T21: 30175.118 | U21: -0.012184399 | Z21: Diluted shares ('000) | AA21: 32082.601 | AB21: 31647.818 | AC21: 31241.48 | AD21: 30861.724 | AE21: 30506.811 | AF21: 30175.118 | AG21: -0.012184399
B23: Adjusted EPS — Diluted ($) | C23: =Model!CD156 -> 8.686484 | D23: =Model!CI156 -> 10.596345 | E23: =Model!CJ156 -> 12.258816 | F23: =Model!CK156 -> 13.929446 | G23: =Model!CL156 -> 16.065482 | H23: =Model!CM156 -> 18.427098 | I23: =IFERROR((H23/C23)^(1/5)-1,"n/m") -> 0.16231163 | N23: Adjusted EPS — Diluted ($) | O23: 8.686484 | P23: 10.610488 | Q23: 12.679728 | R23: 14.785629 | S23: 17.403639 | T23: 20.303116 | U23: 0.18506926 | Z23: Adjusted EPS — Diluted ($) | AA23: 8.686484 | AB23: 10.610488 | AC23: 11.748987 | AD23: 12.864618 | AE23: 14.343198 | AF23: 15.954691 | AG23: 0.12929882
B24: EPS y/y % | D24: =IFERROR(D23/C23-1,"") -> 0.21986585 | E24: =IFERROR(E23/D23-1,"") -> 0.15689096 | F24: =IFERROR(F23/E23-1,"") -> 0.13627987 | G24: =IFERROR(G23/F23-1,"") -> 0.15334684 | H24: =IFERROR(H23/G23-1,"") -> 0.14699935 | N24: EPS y/y % | P24: 0.22149404 | Q24: 0.19501834 | R24: 0.16608408 | S24: 0.17706451 | T24: 0.16660173 | Z24: EPS y/y % | AB24: 0.22149404 | AC24: 0.10729935 | AD24: 0.094955491 | AE24: 0.11493388 | AF24: 0.1123524
B26: P / E (x) — assumed | E26: 20 | F26: =E26 -> 20 | G26: =F26 -> 20 | H26: =G26 -> 20 | N26: P / E (x) — assumed | R26: 25 | S26: 22 | T26: 22 | Z26: P / E (x) — assumed | AC26: 18 | AD26: 18 | AE26: 18 | AF26: 18
B27: Price Target ($) | F27: =F26*F23 -> 278.58892 | G27: =G26*G23 -> 321.30965 | H27: =H26*H23 -> 368.54196 | N27: Price Target ($) | R27: =R26*R23 -> 369.64073 | S27: =S26*S23 -> 382.88007 | T27: =T26*T23 -> 446.66855 | Z27: Price Target ($) | AC27: 211.48176 | AD27: 231.56312 | AE27: 258.17757 | AF27: 287.18443
B28: Upside / (Downside) vs current | F28: =IFERROR(F27/$K$2-1,"") -> -0.19249589 | G28: =IFERROR(G27/$K$2-1,"") -> -0.068667695 | H28: =IFERROR(H27/$K$2-1,"") -> 0.068237552 | N28: Upside / (Downside) vs current | R28: =IFERROR(R27/$K$2-1,"") -> 0.071422412 | S28: =IFERROR(S27/$K$2-1,"") -> 0.1097973 | T28: =IFERROR(T27/$K$2-1,"") -> 0.29469144 | Z28: Upside / (Downside) vs current | AC28: -0.31780076 | AD28: -0.2530222 | AE28: -0.16716914 | AF28: -0.073598601
B29: IRR (to Dec-Y-1) | F29: =IFERROR((F27/$K$2)^(1/((DATE(2025+3,12,31)-$K$3)/365.25))-1,"") -> -0.078995024 | G29: =IFERROR((G27/$K$2)^(1/((DATE(2025+4,12,31)-$K$3)/365.25))-1,"") -> -0.019580174 | H29: =IFERROR((H27/$K$2)^(1/((DATE(2025+5,12,31)-$K$3)/365.25))-1,"") -> 0.014463458 | N29: IRR (to Dec-Y-1) | R29: =IFERROR((R27/$K$2)^(1/((DATE(2025+3,12,31)-$K$3)/365.25))-1,"") -> 0.026907319 | S29: =IFERROR((S27/$K$2)^(1/((DATE(2025+4,12,31)-$K$3)/365.25))-1,"") -> 0.029381342 | T29: =IFERROR((T27/$K$2)^(1/((DATE(2025+5,12,31)-$K$3)/365.25))-1,"") -> 0.057792966 | Z29: IRR (to Dec-Y-1) | AC29: -0.21273051 | AD29: -0.10609752 | AE29: -0.049539387 | AF29: -0.016483182
B31: Free Cash Flow | C31: =Model!CD210 -> 128.355 | D31: =Model!CI210 -> 209.52566 | E31: =Model!CJ210 -> 279.69608 | F31: =Model!CK210 -> 368.97287 | G31: =Model!CL210 -> 412.69993 | H31: =Model!CM210 -> 429.97726 | I31: =IFERROR((H31/C31)^(1/5)-1,"n/m") -> 0.27352226 | N31: Free Cash Flow | O31: 128.355 | P31: 209.97327 | Q31: 255.88546 | R31: 364.4777 | S31: 424.28432 | T31: 452.07033 | U31: 0.2863485 | Z31: Free Cash Flow | AA31: 128.355 | AB31: 209.97327 | AC31: 320.01831 | AD31: 387.72396 | AE31: 411.44649 | AF31: 410.861 | AG31: 0.26199149
B32: FCF % | C32: =IFERROR(C31/C9,"") -> 0.033247216 | D32: =IFERROR(D31/D9,"") -> 0.04912688 | E32: =IFERROR(E31/E9,"") -> 0.060638166 | F32: =IFERROR(F31/F9,"") -> 0.074742897 | G32: =IFERROR(G31/G9,"") -> 0.078511199 | H32: =IFERROR(H31/H9,"") -> 0.077030629 | J32: =AVERAGE(IFERROR(Model!AF210/Model!AF114,NA()),IFERROR(Model!AK210/Model!AK114,NA()),IFERROR(Model!AP210/Model!AP114,NA()),IFERROR(Model!AU210/Model!AU114,NA()),IFERROR(Model!AZ210/Model!AZ114,NA()),IFERROR(Model!BE210/Model!BE114,NA()),IFERROR(Model!BJ210/Model!BJ114,NA()),IFERROR(Model!BO210/Model!BO114,NA()),IFERROR(Model!BT210/Model!BT114,NA()),IFERROR(Model!BY210/Model!BY114,NA()),IFERROR(Model!CD210/Model!CD114,NA())) -> 0.046677948 | K32: =MIN(IFERROR(Model!AF210/Model!AF114,99),IFERROR(Model!AK210/Model!AK114,99),IFERROR(Model!AP210/Model!AP114,99),IFERROR(Model!AU210/Model!AU114,99),IFERROR(Model!AZ210/Model!AZ114,99),IFERROR(Model!BE210/Model!BE114,99),IFERROR(Model!BJ210/Model!BJ114,99),IFERROR(Model!BO210/Model!BO114,99),IFERROR(Model!BT210/Model!BT114,99),IFERROR(Model!BY210/Model!BY114,99),IFERROR(Model!CD210/Model!CD114,99)) -> -0.011355803 | L32: =MAX(IFERROR(Model!AF210/Model!AF114,-99),IFERROR(Model!AK210/Model!AK114,-99),IFERROR(Model!AP210/Model!AP114,-99),IFERROR(Model!AU210/Model!AU114,-99),IFERROR(Model!AZ210/Model!AZ114,-99),IFERROR(Model!BE210/Model!BE114,-99),IFERROR(Model!BJ210/Model!BJ114,-99),IFERROR(Model!BO210/Model!BO114,-99),IFERROR(Model!BT210/Model!BT114,-99),IFERROR(Model!BY210/Model!BY114,-99),IFERROR(Model!CD210/Model!CD114,-99)) -> 0.10636294 | N32: FCF % | O32: 0.033247216 | P32: 0.049231828 | Q32: 0.054005439 | R32: 0.070418242 | S32: 0.075694189 | T32: 0.07475523 | V32: 0.046677948 | W32: -0.011355803 | X32: 0.10636294 | Z32: FCF % | AA32: 0.033247216 | AB32: 0.049231828 | AC32: 0.072379547 | AD32: 0.085103376 | AE32: 0.087838031 | AF32: 0.085202262 | AH32: 0.046677948 | AI32: -0.011355803 | AJ32: 0.10636294
B33: FCF / share ($) | C33: =IFERROR(C31*1000/C21,"") -> 4.0007666 | D33: =IFERROR(D31*1000/D21,"") -> 6.6205405 | E33: =IFERROR(E31*1000/E21,"") -> 8.9527157 | F33: =IFERROR(F31*1000/F21,"") -> 11.955679 | G33: =IFERROR(G31*1000/G21,"") -> 13.528124 | H33: =IFERROR(H31*1000/H21,"") -> 14.249398 | N33: FCF / share ($) | O33: 4.0007666 | P33: 6.6346837 | Q33: 8.1905679 | R33: 11.810024 | S33: 13.907855 | T33: 14.98156 | Z33: FCF / share ($) | AA33: 4.0007666 | AB33: 6.6346837 | AC33: 10.243379 | AD33: 12.563263 | AE33: 13.487037 | AF33: 13.615887
B34: FCF Yield (on PT) | D34: =IFERROR(D33/D27,"") | E34: =IFERROR(E33/E27,"") | F34: =IFERROR(F33/F27,"") -> 0.042915129 | G34: =IFERROR(G33/G27,"") -> 0.042103075 | H34: =IFERROR(H33/H27,"") -> 0.038664249 | N34: FCF Yield (on PT) | Q34: 0.029361713 | R34: 0.036306827 | S34: 0.036324312 | T34: 0.033540664 | Z34: FCF Yield (on PT) | AC34: 0.048436228 | AD34: 0.054254163 | AE34: 0.052239384 | AF34: 0.047411648
B35: EBITDA (before special items) | C35: =IF(ISNUMBER(Model!CD150),IF(Model!CD150>0,Model!CD150,Model!CD126),Model!CD126)+Model!CD176+Model!CD177 -> 604.996 | D35: =IF(ISNUMBER(Model!CI150),IF(Model!CI150>0,Model!CI150,Model!CI126),Model!CI126)+Model!CI176+Model!CI177 -> 626.43313 | E35: =IF(ISNUMBER(Model!CJ150),IF(Model!CJ150>0,Model!CJ150,Model!CJ126),Model!CJ126)+Model!CJ176+Model!CJ177 -> 691.68016 | F35: =IF(ISNUMBER(Model!CK150),IF(Model!CK150>0,Model!CK150,Model!CK126),Model!CK126)+Model!CK176+Model!CK177 -> 759.20291 | G35: =IF(ISNUMBER(Model!CL150),IF(Model!CL150>0,Model!CL150,Model!CL126),Model!CL126)+Model!CL176+Model!CL177 -> 844.06158 | H35: =IF(ISNUMBER(Model!CM150),IF(Model!CM150>0,Model!CM150,Model!CM126),Model!CM126)+Model!CM176+Model!CM177 -> 935.66214 | I35: =IFERROR((H35/C35)^(1/5)-1,"n/m") -> 0.091121996 | N35: EBITDA (before special items) | O35: 604.996 | P35: 626.43313 | Q35: 710.12687 | R35: 795.55073 | S35: 899.62831 | T35: 1013.3294 | U35: 0.10866318 | Z35: EBITDA (before special items) | AA35: 604.996 | AB35: 626.43313 | AC35: 663.60622 | AD35: 701.39526 | AE35: 752.83535 | AF35: 808.88976 | AG35: 0.059808423
B36: EBITDA % | C36: =IFERROR(C35/C9,"") -> 0.15670938 | D36: =IFERROR(D35/D9,"") -> 0.14687798 | E36: =IFERROR(E35/E9,"") -> 0.14995639 | F36: =IFERROR(F35/F9,"") -> 0.15379186 | G36: =IFERROR(G35/G9,"") -> 0.16057257 | H36: =IFERROR(H35/H9,"") -> 0.16762431 | J36: =AVERAGE(IFERROR((IF(ISNUMBER(Model!AF150),IF(Model!AF150>0,Model!AF150,Model!AF126),Model!AF126)+Model!AF176+Model!AF177)/Model!AF114,NA()),IFERROR((IF(ISNUMBER(Model!AK150),IF(Model!AK150>0,Model!AK150,Model!AK126),Model!AK126)+Model!AK176+Model!AK177)/Model!AK114,NA()),IFERROR((IF(ISNUMBER(Model!AP150),IF(Model!AP150>0,Model!AP150,Model!AP126),Model!AP126)+Model!AP176+Model!AP177)/Model!AP114,NA()),IFERROR((IF(ISNUMBER(Model!AU150),IF(Model!AU150>0,Model!AU150,Model!AU126),Model!AU126)+Model!AU176+Model!AU177)/Model!AU114,NA()),IFERROR((IF(ISNUMBER(Model!AZ150),IF(Model!AZ150>0,Model!AZ150,Model!AZ126),Model!AZ126)+Model!AZ176+Model!AZ177)/Model!AZ114,NA()),IFERROR((IF(ISNUMBER(Model!BE150),IF(Model!BE150>0,Model!BE150,Model!BE126),Model!BE126)+Model!BE176+Model!BE177)/Model!BE114,NA()),IFERROR((IF(ISNUMBER(Model!BJ150),IF(Model!BJ150>0,Model!BJ150,Model!BJ126),Model!BJ126)+Model!BJ176+Model!BJ177)/Model!BJ114,NA()),IFERROR((IF(ISNUMBER(Model!BO150),IF(Model!BO150>0,Model!BO150,Model!BO126),Model!BO126)+Model!BO176+Model!BO177)/Model!BO114,NA()),IFERROR((IF(ISNUMBER(Model!BT150),IF(Model!BT150>0,Model!BT150,Model!BT126),Model!BT126)+Model!BT176+Model!BT177)/Model!BT114,NA()),IFERROR((IF(ISNUMBER(Model!BY150),IF(Model!BY150>0,Model!BY150,Model!BY126),Model!BY126)+Model!BY176+Model!BY177)/Model!BY114,NA()),IFERROR((IF(ISNUMBER(Model!CD150),IF(Model!CD150>0,Model!CD150,Model!CD126),Model!CD126)+Model!CD176+Model!CD177)/Model!CD114,NA())) -> 0.13674468 | K36: =MIN(IFERROR((IF(ISNUMBER(Model!AF150),IF(Model!AF150>0,Model!AF150,Model!AF126),Model!AF126)+Model!AF176+Model!AF177)/Model!AF114,99),IFERROR((IF(ISNUMBER(Model!AK150),IF(Model!AK150>0,Model!AK150,Model!AK126),Model!AK126)+Model!AK176+Model!AK177)/Model!AK114,99),IFERROR((IF(ISNUMBER(Model!AP150),IF(Model!AP150>0,Model!AP150,Model!AP126),Model!AP126)+Model!AP176+Model!AP177)/Model!AP114,99),IFERROR((IF(ISNUMBER(Model!AU150),IF(Model!AU150>0,Model!AU150,Model!AU126),Model!AU126)+Model!AU176+Model!AU177)/Model!AU114,99),IFERROR((IF(ISNUMBER(Model!AZ150),IF(Model!AZ150>0,Model!AZ150,Model!AZ126),Model!AZ126)+Model!AZ176+Model!AZ177)/Model!AZ114,99),IFERROR((IF(ISNUMBER(Model!BE150),IF(Model!BE150>0,Model!BE150,Model!BE126),Model!BE126)+Model!BE176+Model!BE177)/Model!BE114,99),IFERROR((IF(ISNUMBER(Model!BJ150),IF(Model!BJ150>0,Model!BJ150,Model!BJ126),Model!BJ126)+Model!BJ176+Model!BJ177)/Model!BJ114,99),IFERROR((IF(ISNUMBER(Model!BO150),IF(Model!BO150>0,Model!BO150,Model!BO126),Model!BO126)+Model!BO176+Model!BO177)/Model!BO114,99),IFERROR((IF(ISNUMBER(Model!BT150),IF(Model!BT150>0,Model!BT150,Model!BT126),Model!BT126)+Model!BT176+Model!BT177)/Model!BT114,99),IFERROR((IF(ISNUMBER(Model!BY150),IF(Model!BY150>0,Model!BY150,Model!BY126),Model!BY126)+Model!BY176+Model!BY177)/Model!BY114,99),IFERROR((IF(ISNUMBER(Model!CD150),IF(Model!CD150>0,Model!CD150,Model!CD126),Model!CD126)+Model!CD176+Model!CD177)/Model!CD114,99)) -> 0.12528449 | L36: =MAX(IFERROR((IF(ISNUMBER(Model!AF150),IF(Model!AF150>0,Model!AF150,Model!AF126),Model!AF126)+Model!AF176+Model!AF177)/Model!AF114,-99),IFERROR((IF(ISNUMBER(Model!AK150),IF(Model!AK150>0,Model!AK150,Model!AK126),Model!AK126)+Model!AK176+Model!AK177)/Model!AK114,-99),IFERROR((IF(ISNUMBER(Model!AP150),IF(Model!AP150>0,Model!AP150,Model!AP126),Model!AP126)+Model!AP176+Model!AP177)/Model!AP114,-99),IFERROR((IF(ISNUMBER(Model!AU150),IF(Model!AU150>0,Model!AU150,Model!AU126),Model!AU126)+Model!AU176+Model!AU177)/Model!AU114,-99),IFERROR((IF(ISNUMBER(Model!AZ150),IF(Model!AZ150>0,Model!AZ150,Model!AZ126),Model!AZ126)+Model!AZ176+Model!AZ177)/Model!AZ114,-99),IFERROR((IF(ISNUMBER(Model!BE150),IF(Model!BE150>0,Model!BE150,Model!BE126),Model!BE126)+Model!BE176+Model!BE177)/Model!BE114,-99),IFERROR((IF(ISNUMBER(Model!BJ150),IF(Model!BJ150>0,Model!BJ150,Model!BJ126),Model!BJ126)+Model!BJ176+Model!BJ177)/Model!BJ114,-99),IFERROR((IF(ISNUMBER(Model!BO150),IF(Model!BO150>0,Model!BO150,Model!BO126),Model!BO126)+Model!BO176+Model!BO177)/Model!BO114,-99),IFERROR((IF(ISNUMBER(Model!BT150),IF(Model!BT150>0,Model!BT150,Model!BT126),Model!BT126)+Model!BT176+Model!BT177)/Model!BT114,-99),IFERROR((IF(ISNUMBER(Model!BY150),IF(Model!BY150>0,Model!BY150,Model!BY126),Model!BY126)+Model!BY176+Model!BY177)/Model!BY114,-99),IFERROR((IF(ISNUMBER(Model!CD150),IF(Model!CD150>0,Model!CD150,Model!CD126),Model!CD126)+Model!CD176+Model!CD177)/Model!CD114,-99)) -> 0.15670938 | N36: EBITDA % | O36: 0.15670938 | P36: 0.14687798 | Q36: 0.14987453 | R36: 0.15370291 | S36: 0.16049765 | T36: 0.16756612 | V36: 0.13674468 | W36: 0.12528449 | X36: 0.15670938 | Z36: EBITDA % | AA36: 0.15670938 | AB36: 0.14687798 | AC36: 0.15008991 | AD36: 0.15395258 | AE36: 0.16071975 | AF36: 0.16774344 | AH36: 0.13674468 | AI36: 0.12528449 | AJ36: 0.15670938
B38: Net Debt | C38: =Model!CD331 -> 883.473 | D38: =Model!CI331 -> 833.94734 | E38: =Model!CJ331 -> 724.25125 | F38: =Model!CK331 -> 530.27838 | G38: =Model!CL331 -> 297.57845 | H38: =Model!CM331 -> 52.60119 | N38: Net Debt | O38: 883.473 | P38: 833.49973 | Q38: 747.61427 | R38: 558.13657 | S38: 313.85226 | T38: 46.781922 | Z38: Net Debt | AA38: 883.473 | AB38: 833.49973 | AC38: 683.48142 | AD38: 470.75747 | AE38: 239.31098 | AF38: 13.449972
B39: Net Debt / EBITDA (x) | C39: =IFERROR(C38/C35,"") -> 1.4602956 | D39: =IFERROR(D38/D35,"") -> 1.3312631 | E39: =IFERROR(E38/E35,"") -> 1.0470898 | F39: =IFERROR(F38/F35,"") -> 0.69846726 | G39: =IFERROR(G38/G35,"") -> 0.35255538 | H39: =IFERROR(H38/H35,"") -> 0.056218145 | N39: Net Debt / EBITDA (x) | O39: 1.4602956 | P39: 1.3305486 | Q39: 1.0527897 | R39: 0.70157257 | S39: 0.34886881 | T39: 0.04616655 | Z39: Net Debt / EBITDA (x) | AA39: 1.4602956 | AB39: 1.3305486 | AC39: 1.0299503 | AD39: 0.67117287 | AE39: 0.31787957 | AF39: 0.016627695
B41: ROIC | C41: =Model!CD332 -> 0.13102097 | D41: =Model!CI332 -> 0.12994009 | E41: =Model!CJ332 -> 0.14017825 | F41: =Model!CK332 -> 0.15132045 | G41: =Model!CL332 -> 0.16501807 | H41: =Model!CM332 -> 0.17672425 | J41: =AVERAGE(Model!AF332,Model!AK332,Model!AP332,Model!AU332,Model!AZ332,Model!BE332,Model!BJ332,Model!BO332,Model!BT332,Model!BY332,Model!CD332) -> 0.10649688 | K41: =MIN(Model!AF332,Model!AK332,Model!AP332,Model!AU332,Model!AZ332,Model!BE332,Model!BJ332,Model!BO332,Model!BT332,Model!BY332,Model!CD332) -> 0.078655447 | L41: =MAX(Model!AF332,Model!AK332,Model!AP332,Model!AU332,Model!AZ332,Model!BE332,Model!BJ332,Model!BO332,Model!BT332,Model!BY332,Model!CD332) -> 0.13418059 | N41: ROIC | O41: 0.13102097 | P41: 0.12994009 | Q41: 0.14220323 | R41: 0.15521947 | S41: 0.17077484 | T41: 0.18424991 | V41: 0.10649688 | W41: 0.078655447 | X41: 0.13418059 | Z41: ROIC | AA41: 0.13102097 | AB41: 0.12994009 | AC41: 0.13700201 | AD41: 0.14475876 | AE41: 0.15476995 | AF41: 0.16309349 | AH41: 0.10649688 | AI41: 0.078655447 | AJ41: 0.13418059
B42: RONTA | C42: =Model!CD346 -> 0.16117724 | D42: =Model!CI346 -> 0.15804571 | E42: =Model!CJ346 -> 0.16882625 | F42: =Model!CK346 -> 0.18092714 | G42: =Model!CL346 -> 0.1956496 | H42: =Model!CM346 -> 0.20725913 | J42: =AVERAGE(Model!AF346,Model!AK346,Model!AP346,Model!AU346,Model!AZ346,Model!BE346,Model!BJ346,Model!BO346,Model!BT346,Model!BY346,Model!CD346) -> 0.14509836 | K42: =MIN(Model!AF346,Model!AK346,Model!AP346,Model!AU346,Model!AZ346,Model!BE346,Model!BJ346,Model!BO346,Model!BT346,Model!BY346,Model!CD346) -> 0.11691297 | L42: =MAX(Model!AF346,Model!AK346,Model!AP346,Model!AU346,Model!AZ346,Model!BE346,Model!BJ346,Model!BO346,Model!BT346,Model!BY346,Model!CD346) -> 0.17231893 | N42: RONTA | O42: 0.16117724 | P42: 0.15804571 | Q42: 0.17083277 | R42: 0.18476789 | S42: 0.2012659 | T42: 0.21449288 | V42: 0.14509836 | W42: 0.11691297 | X42: 0.17231893 | Z42: RONTA | AA42: 0.16117724 | AB42: 0.15804571 | AC42: 0.16565843 | AD42: 0.17438244 | AE42: 0.18547154 | AF42: 0.19387151 | AH42: 0.14509836 | AI42: 0.11691297 | AJ42: 0.17231893
B44: Implied Market Cap ($M) | E44: =E27*E21/1000 -> 0 | F44: =F27*F21/1000 -> 8597.7341 | G44: =G27*G21/1000 -> 9802.1328 | H44: =H27*H21/1000 -> 11120.797 | N44: Implied Market Cap ($M) | Q44: 8714.9364 | R44: 10038.82 | S44: 11680.45 | T44: 13478.276 | Z44: Implied Market Cap ($M) | AC44: 6607.0032 | AD44: 7146.4369 | AE44: 7876.1743 | AF44: 8665.8241
B45: (+) Net Debt | E45: =E38 -> 724.25125 | F45: =F38 -> 530.27838 | G45: =G38 -> 297.57845 | H45: =H38 -> 52.60119 | N45: (+) Net Debt | Q45: 747.61427 | R45: 558.13657 | S45: 313.85226 | T45: 46.781922 | Z45: (+) Net Debt | AC45: 683.48142 | AD45: 470.75747 | AE45: 239.31098 | AF45: 13.449972
B46: Implied Enterprise Value ($M) | E46: =E44+E45 -> 724.25125 | F46: =F44+F45 -> 9128.0125 | G46: =G44+G45 -> 10099.711 | H46: =H44+H45 -> 11173.398 | N46: Implied Enterprise Value ($M) | Q46: 9462.5506 | R46: 10596.957 | S46: 11994.302 | T46: 13525.058 | Z46: Implied Enterprise Value ($M) | AC46: 7290.4846 | AD46: 7617.1944 | AE46: 8115.4853 | AF46: 8679.2741
B47: Implied EV / EBITDA (x) | E47: =IFERROR(E46/E35,"") -> 1.0470898 | F47: =IFERROR(F46/F35,"") -> 12.023153 | G47: =IFERROR(G46/G35,"") -> 11.965609 | H47: =IFERROR(H46/H35,"") -> 11.941702 | N47: Implied EV / EBITDA (x) | Q47: 13.325155 | R47: 13.320278 | S47: 13.332509 | T47: 13.347149 | Z47: Implied EV / EBITDA (x) | AC47: 10.986161 | AD47: 10.86006 | AE47: 10.779894 | AF47: 10.72986

Sheet Moog-DCF
B2: DCF VALUATION — Moog Inc.
B4: 1. WACC BUILD
B5: Risk-free rate (US 10Y govt) | C5: 0.043 | D5: US 10Y Treasury
B6: Equity risk premium | C6: 0.055 | D6: Damodaran global ERP estimate
B7: Levered beta | C7: 1.02 | D7: Moog reported beta ~0.9-1.0; industrial A&D peer median
B8: Cost of equity | C8: =C5+C7*C6 -> 0.0991
B9: Pre-tax cost of debt | C9: 0.05 | D9: Moog senior notes 5-7Y yield
B10: Tax rate | C10: 0.24 | D10: Long-run normalised effective tax rate
B11: After-tax cost of debt | C11: =C9*(1-C10) -> 0.038
B12: Target D/V | C12: 0.2 | D12: Target leverage; net debt / total capital
B13: WACC | C13: =C8*(1-C12)+C11*C12 -> 0.08688
B15: Valuation date (live) | C15: =TODAY() -> 46169
B16: 2. UNLEVERED FREE CASH FLOW BUILD (explicit FY26-FY30, fade FY31-FY40 over CAP = C68 years)
D17: FY26E | E17: FY27E | F17: FY28E | G17: FY29E | H17: FY30E | I17: FY31E | J17: FY32E | K17: FY33E | L17: FY34E | M17: FY35E | N17: FY36E | O17: FY37E | P17: FY38E | Q17: FY39E | R17: FY40E | S17: Terminal | T17: FY26E-40E CAGR
B18: EBIT before special items | D18: =IF(ISNUMBER(Model!CI150),IF(Model!CI150>0,Model!CI150,Model!CI126),Model!CI126) -> 511.84054 | E18: =IF(ISNUMBER(Model!CJ150),IF(Model!CJ150>0,Model!CJ150,Model!CJ126),Model!CJ126) -> 567.74948 | F18: =IF(ISNUMBER(Model!CK150),IF(Model!CK150>0,Model!CK150,Model!CK126),Model!CK126) -> 626.56643 | G18: =IF(ISNUMBER(Model!CL150),IF(Model!CL150>0,Model!CL150,Model!CL126),Model!CL126) -> 702.82692 | H18: =IF(ISNUMBER(Model!CM150),IF(Model!CM150>0,Model!CM150,Model!CM126),Model!CM126) -> 785.68656 | I18: =H18*(1+(H18/G18-1)+(($C$27-(H18/G18-1))*1/10)) -> 871.80199 | J18: =I18*(1+(H18/G18-1)+(($C$27-(H18/G18-1))*2/10)) -> 960.12935 | K18: =J18*(1+(H18/G18-1)+(($C$27-(H18/G18-1))*3/10)) -> 1049.4467 | L18: =K18*(1+(H18/G18-1)+(($C$27-(H18/G18-1))*4/10)) -> 1138.3735 | M18: =L18*(1+(H18/G18-1)+(($C$27-(H18/G18-1))*5/10)) -> 1225.3992 | N18: =M18*(1+(H18/G18-1)+(($C$27-(H18/G18-1))*6/10)) -> 1308.9199 | O18: =N18*(1+(H18/G18-1)+(($C$27-(H18/G18-1))*7/10)) -> 1387.2829 | P18: =O18*(1+(H18/G18-1)+(($C$27-(H18/G18-1))*8/10)) -> 1458.8375 | Q18: =P18*(1+(H18/G18-1)+(($C$27-(H18/G18-1))*9/10)) -> 1521.9898 | R18: =Q18*(1+$C$27) -> 1575.2595 | T18: =IFERROR((R18/D18)^(1/14)-1,"n/m") -> 0.083609173
B19: × (1 − tax rate) | D19: =1-$C$10 -> 0.76 | E19: =1-$C$10 -> 0.76 | F19: =1-$C$10 -> 0.76 | G19: =1-$C$10 -> 0.76 | H19: =1-$C$10 -> 0.76 | I19: =1-$C$10 -> 0.76 | J19: =1-$C$10 -> 0.76 | K19: =1-$C$10 -> 0.76 | ... R19: =1-$C$10 -> 0.76
B20: NOPAT | D20: =D18*D19 -> 388.99881 | E20: =E18*E19 -> 431.4896 | F20: =F18*F19 -> 476.19048 | G20: =G18*G19 -> 534.14846 | H20: =H18*H19 -> 597.12179 | I20: =I18*I19 -> 662.56952 | J20: =J18*J19 -> 729.69831 | K20: =K18*K19 -> 797.57949 | ... R20: =R18*R19 -> 1197.1972 | T20: =IFERROR((R20/D20)^(1/14)-1,"n/m") -> 0.083609173
B21: plus D&A | D21: =Model!CI176+Model!CI177 -> 114.59259 | E21: =Model!CJ176+Model!CJ177 -> 123.93068 | F21: =Model!CK176+Model!CK177 -> 132.63649 | G21: =Model!CL176+Model!CL177 -> 141.23466 | H21: =Model!CM176+Model!CM177 -> 149.97558 | I21: =H21*(I18/H18) -> 166.4137 | J21: =I21*(J18/I18) -> 183.27404 | K21: =J21*(K18/J18) -> 200.32336 | L21: =K21*(L18/K18) -> 217.29814 | M21: =L21*(M18/L18) -> 233.91002 | N21: =M21*(N18/M18) -> 249.85284 | O21: =N21*(O18/N18) -> 264.81114 | P21: =O21*(P18/O18) -> 278.46982 | ... R21: =Q21*(R18/Q18) -> 300.693
B22: − Capex (PP&E + intangibles) | D22: =-ABS(Model!CI189) -> -159.89029 | E22: =-ABS(Model!CJ189) -> -172.91967 | F22: =-ABS(Model!CK189) -> -185.06682 | G22: =-ABS(Model!CL189) -> -197.06379 | H22: =-ABS(Model!CM189) -> -209.25994 | I22: =H22*(I18/H18) -> -232.19595 | J22: =I22*(J18/I18) -> -255.72107 | K22: =J22*(K18/J18) -> -279.50988 | L22: =K22*(L18/K18) -> -303.19467 | M22: =L22*(M18/L18) -> -326.37312 | N22: =M22*(N18/M18) -> -348.61803 | O22: =N22*(O18/N18) -> -369.48925 | P22: =O22*(P18/O18) -> -388.54712 | ... R22: =Q22*(R18/Q18) -> -419.55497
B23: − Δ Working capital | D23: =Model!CI180+Model!CI181+Model!CI182+Model!CI183+Model!CI184 -> -67.35243 | E23: =Model!CJ180+Model!CJ181+Model!CJ182+Model!CJ183+Model!CJ184 -> -50.733396 | F23: =Model!CK180+Model!CK181+Model!CK182+Model!CK183+Model!CK184 -> -11.773445 | G23: =Model!CL180+Model!CL181+Model!CL182+Model!CL183+Model!CL184 -> -29.770872 | H23: =Model!CM180+Model!CM181+Model!CM182+Model!CM183+Model!CM184 -> -78.57375 | I23: =H23*(I18/H18) -> -87.185852 | J23: =I23*(J18/I18) -> -96.01916 | K23: =J23*(K18/J18) -> -104.95147 | L23: =K23*(L18/K18) -> -113.84473 | M23: =L23*(M18/L18) -> -122.54787 | N23: =M23*(N18/M18) -> -130.90048 | O23: =N23*(O18/N18) -> -138.73728 | P23: =O23*(P18/O18) -> -145.89321 | ... R23: =Q23*(R18/Q18) -> -157.53616
B24: Unlevered FCF | D24: =D20+D21+D22+D23 -> 276.34868 | E24: =E20+E21+E22+E23 -> 331.76722 | F24: =F20+F21+F22+F23 -> 411.9867 | G24: =G20+G21+G22+G23 -> 448.54845 | H24: =H20+H21+H22+H23 -> 459.26367 | I24: =I20+I21+I22+I23 -> 509.60142 | J24: =J20+J21+J22+J23 -> 561.23211 | K24: =K20+K21+K22+K23 -> 613.4415 | ... R24: =R20+R21+R22+R23 -> 920.79906 | S24: =R24*(1+$C$27) -> 953.02703 | T24: =IFERROR((R24/D24)^(1/14)-1,"n/m") -> 0.089773513
B25: Terminal Value (Gordon Growth) | S25: =S24/($C$13-$C$27) -> 18369.835
B27: Terminal growth rate | C27: 0.035
B29: Discount period (year #) | D29: =(DATE(2026+0,12,31)-$C$15)/365.25 -> 0.59685147 | E29: =(DATE(2026+1,12,31)-$C$15)/365.25 -> 1.596167 | F29: =(DATE(2026+2,12,31)-$C$15)/365.25 -> 2.5982204 | G29: =(DATE(2026+3,12,31)-$C$15)/365.25 -> 3.5975359 | H29: =(DATE(2026+4,12,31)-$C$15)/365.25 -> 4.5968515 | I29: =(DATE(2031,12,31)-$C$15)/365.25 -> 5.596167 | J29: =(DATE(2032,12,31)-$C$15)/365.25 -> 6.5982204 | K29: =(DATE(2033,12,31)-$C$15)/365.25 -> 7.5975359 | L29: =(DATE(2034,12,31)-$C$15)/365.25 -> 8.5968515 | M29: =(DATE(2035,12,31)-$C$15)/365.25 -> 9.596167 | N29: =(DATE(2036,12,31)-$C$15)/365.25 -> 10.59822 | O29: =(DATE(2037,12,31)-$C$15)/365.25 -> 11.597536 | P29: =(DATE(2038,12,31)-$C$15)/365.25 -> 12.596851 | Q29: =(DATE(2039,12,31)-$C$15)/365.25 -> 13.596167 | R29: =(DATE(2040,12,31)-$C$15)/365.25 -> 14.59822 | S29: =R29 -> 14.59822
B30: Discount factor | D30: =1/(1+$C$13)^D29 -> 0.9514916 | E30: =1/(1+$C$13)^E29 -> 0.87548383 | F30: =1/(1+$C$13)^F29 -> 0.80536404 | G30: =1/(1+$C$13)^G29 -> 0.74102934 | H30: =1/(1+$C$13)^H29 -> 0.68183387 | I30: =1/(1+$C$13)^I29 -> 0.6273671 | J30: =1/(1+$C$13)^J29 -> 0.57711963 | K30: =1/(1+$C$13)^K29 -> 0.53101772 | ... S30: =1/(1+$C$13)^S29 -> 0.29635555
B31: PV of UFCF | D31: =D24*D30 -> 262.94345 | E31: =E24*E30 -> 290.45684 | F31: =F24*F30 -> 331.79928 | G31: =G24*G30 -> 332.38756 | H31: =H24*H30 -> 313.14153 | I31: =I24*I30 -> 319.70716 | J31: =J24*J30 -> 323.89807 | K31: =K24*K30 -> 325.74831 | ... R31: =R24*R30 -> 272.88391 | S31: =S25*S30 -> 5444.0025
B34: 3. VALUATION SUMMARY
B35: Sum of PV (explicit + fade) | C35: =SUM(D31:R31) -> 4630.2895
B36: PV of Terminal Value | C36: =S31 -> 5444.0025
B37: Enterprise Value | C37: =C35+C36 -> 10074.292
B38: Less: Net debt (Model FY26E YE) | C38: =Model!CI331 -> 833.94734
B39: Equity Value | C39: =C37-C38 -> 9240.3447
B40: Diluted shares ('000) | C40: =Model!CI139 -> 31647.818
B41: Implied share price ($) | C41: =C39*1000/C40 -> 291.97414
B42: Current share price ($) | C42: 345
B43: Implied upside / (downside) | C43: =C41/C42-1 -> -0.15369813
B46: 4. SENSITIVITY: IMPLIED PRICE — WACC × Terminal Growth
B48: WACC (across):
B49: g (down) / WACC → | D49: 0.07 | E49: 0.075 | F49: 0.08 | G49: 0.085 | H49: 0.09
B50: 0.02 | D50: {=IFERROR((SUMPRODUCT($D$24:$M$24/(1+D$49)^$D$29:$M$29)+($M$24*(1+$B50)/(D$49-$B50))/(1+D$49)^$M$29-$C$38)*1000/$C$40,"")} -> 322.86878 | E50: {=IFERROR((SUMPRODUCT($D$24:$M$24/(1+E$49)^$D$29:$M$29)+($M$24*(1+$B50)/(E$49-$B50))/(1+E$49)^$M$29-$C$38)*1000/$C$40,"")} -> 288.701 | F50: {=IFERROR((SUMPRODUCT($D$24:$M$24/(1+F$49)^$D$29:$M$29)+($M$24*(1+$B50)/(F$49-$B50))/(1+F$49)^$M$29-$C$38)*1000/$C$40,"")} -> 260.30422 | G50: {=IFERROR((SUMPRODUCT($D$24:$M$24/(1+G$49)^$D$29:$M$29)+($M$24*(1+$B50)/(G$49-$B50))/(1+G$49)^$M$29-$C$38)*1000/$C$40,"")} -> 236.34392 | H50: {=IFERROR((SUMPRODUCT($D$24:$M$24/(1+H$49)^$D$29:$M$29)+($M$24*(1+$B50)/(H$49-$B50))/(1+H$49)^$M$29-$C$38)*1000/$C$40,"")} -> 215.86696
B51: 0.0225 | D51: {=IFERROR((SUMPRODUCT($D$24:$M$24/(1+D$49)^$D$29:$M$29)+($M$24*(1+$B51)/(D$49-$B51))/(1+D$49)^$M$29-$C$38)*1000/$C$40,"")} -> 336.18666 | E51: {=IFERROR((SUMPRODUCT($D$24:$M$24/(1+E$49)^$D$29:$M$29)+($M$24*(1+$B51)/(E$49-$B51))/(1+E$49)^$M$29-$C$38)*1000/$C$40,"")} -> 299.22479 | F51: {=IFERROR((SUMPRODUCT($D$24:$M$24/(1+F$49)^$D$29:$M$29)+($M$24*(1+$B51)/(F$49-$B51))/(1+F$49)^$M$29-$C$38)*1000/$C$40,"")} -> 268.76775 | G51: {=IFERROR((SUMPRODUCT($D$24:$M$24/(1+G$49)^$D$29:$M$29)+($M$24*(1+$B51)/(G$49-$B51))/(1+G$49)^$M$29-$C$38)*1000/$C$40,"")} -> 243.25161 | H51: {=IFERROR((SUMPRODUCT($D$24:$M$24/(1+H$49)^$D$29:$M$29)+($M$24*(1+$B51)/(H$49-$B51))/(1+H$49)^$M$29-$C$38)*1000/$C$40,"")} -> 221.57596
B52: 0.025 | D52: {=IFERROR((SUMPRODUCT($D$24:$M$24/(1+D$49)^$D$29:$M$29)+($M$24*(1+$B52)/(D$49-$B52))/(1+D$49)^$M$29-$C$38)*1000/$C$40,"")} -> 350.98431 | E52: {=IFERROR((SUMPRODUCT($D$24:$M$24/(1+E$49)^$D$29:$M$29)+($M$24*(1+$B52)/(E$49-$B52))/(1+E$49)^$M$29-$C$38)*1000/$C$40,"")} -> 310.80096 | F52: {=IFERROR((SUMPRODUCT($D$24:$M$24/(1+F$49)^$D$29:$M$29)+($M$24*(1+$B52)/(F$49-$B52))/(1+F$49)^$M$29-$C$38)*1000/$C$40,"")} -> 278.00069 | G52: {=IFERROR((SUMPRODUCT($D$24:$M$24/(1+G$49)^$D$29:$M$29)+($M$24*(1+$B52)/(G$49-$B52))/(1+G$49)^$M$29-$C$38)*1000/$C$40,"")} -> 250.73495 | H52: {=IFERROR((SUMPRODUCT($D$24:$M$24/(1+H$49)^$D$29:$M$29)+($M$24*(1+$B52)/(H$49-$B52))/(1+H$49)^$M$29-$C$38)*1000/$C$40,"")} -> 227.72412
B53: 0.0275 | D53: {=IFERROR((SUMPRODUCT($D$24:$M$24/(1+D$49)^$D$29:$M$29)+($M$24*(1+$B53)/(D$49-$B53))/(1+D$49)^$M$29-$C$38)*1000/$C$40,"")} -> 367.52285 | E53: {=IFERROR((SUMPRODUCT($D$24:$M$24/(1+E$49)^$D$29:$M$29)+($M$24*(1+$B53)/(E$49-$B53))/(1+E$49)^$M$29-$C$38)*1000/$C$40,"")} -> 323.59568 | F53: {=IFERROR((SUMPRODUCT($D$24:$M$24/(1+F$49)^$D$29:$M$29)+($M$24*(1+$B53)/(F$49-$B53))/(1+F$49)^$M$29-$C$38)*1000/$C$40,"")} -> 288.11295 | G53: {=IFERROR((SUMPRODUCT($D$24:$M$24/(1+G$49)^$D$29:$M$29)+($M$24*(1+$B53)/(G$49-$B53))/(1+G$49)^$M$29-$C$38)*1000/$C$40,"")} -> 258.86902 | H53: {=IFERROR((SUMPRODUCT($D$24:$M$24/(1+H$49)^$D$29:$M$29)+($M$24*(1+$B53)/(H$49-$B53))/(1+H$49)^$M$29-$C$38)*1000/$C$40,"")} -> 234.36413
B54: 0.03 | D54: {=IFERROR((SUMPRODUCT($D$24:$M$24/(1+D$49)^$D$29:$M$29)+($M$24*(1+$B54)/(D$49-$B54))/(1+D$49)^$M$29-$C$38)*1000/$C$40,"")} -> 386.12872 | E54: {=IFERROR((SUMPRODUCT($D$24:$M$24/(1+E$49)^$D$29:$M$29)+($M$24*(1+$B54)/(E$49-$B54))/(1+E$49)^$M$29-$C$38)*1000/$C$40,"")} -> 337.81203 | F54: {=IFERROR((SUMPRODUCT($D$24:$M$24/(1+F$49)^$D$29:$M$29)+($M$24*(1+$B54)/(F$49-$B54))/(1+F$49)^$M$29-$C$38)*1000/$C$40,"")} -> 299.23644 | G54: {=IFERROR((SUMPRODUCT($D$24:$M$24/(1+G$49)^$D$29:$M$29)+($M$24*(1+$B54)/(G$49-$B54))/(1+G$49)^$M$29-$C$38)*1000/$C$40,"")} -> 267.74254 | H54: {=IFERROR((SUMPRODUCT($D$24:$M$24/(1+H$49)^$D$29:$M$29)+($M$24*(1+$B54)/(H$49-$B54))/(1+H$49)^$M$29-$C$38)*1000/$C$40,"")} -> 241.55748
B57: 5. REVERSE DCF
B58: At current $310 share price, the market is pricing Moog's long-term FCF below the model's projection. To solve for break-even FCF: Data tab > What-If Analysis > Goal Seek. Set C41 to 310 by changing E18 (FY27 EBIT).
B60: 6. MAUBOUSSIN EV / NOPAT — TWO-STAGE FRAMEWORK | E60: IMPLIED P/E — DERIVED FROM EV/NOPAT FRAMEWORK
B61: EV/NOPAT = 1/r + [g × (1 − r/ROIIC) / (r × (r − g))] × [1 − ((1+g)/(1+r))^N] | E61: P/E = (EV/NOPAT × NOPAT − Net Debt) / Net Income
B62: Formula source: Mauboussin & Rappaport, "Expectations Investing" (2021); Counterpoint Global, "What Does a Price-Earnings Multiple Mean?" 2020. | E62: Translates the Mauboussin EV/NOPAT multiple into a P/E that includes capital-structure and tax effects.
B64: Input | C64: Value | D64: Rationale (Moog characteristics) | E64: Step | F64: Value | G64: Note
B65: r (Cost of capital / WACC) | C65: =$C$13 -> 0.08688 | D65: Linked from Section 1 WACC build | E65: FY28E Adj EBIT ($M) | F65: =C79 -> 626.56643 | G65: Linked to Model CK150
B66: g (NOPAT growth, Stage 1) | C66: 0.08 | D66: Moog NOPAT CAGR FY24-FY30E = ~12-14%; conservatively normalised to 8% steady-state post strong A&D backlog cycle | E66: × (1 − t) | F66: =1-$C$10 -> 0.76 | G66: Tax shield from WACC build
B67: ROIIC (Return on incremental invested capital) | C67: 0.2 | D67: Moog ROIC trends to ~13-15% in forecast; ROIIC on incremental capital typically higher in mature A&D — use 18% | E67: = NOPAT ($M) | F67: =F65*F66 -> 476.19048 | G67: EBIT-derived NOPAT
B68: N (Years of value creation / CAP) | C68: 15 | D68: Top-tier A&D supplier with multi-decade flight programs (F-35, V-22, missiles, space launch); CAP 8-12 years typical for entrenched defense compounders | E68: EV/NOPAT (Mauboussin) | F68: =C76 -> 18.387901 | G68: From section 6 above
E69: Implied EV ($M) | F69: =F67*F68 -> 8756.1435 | G69: NOPAT × multiple
B70: Calculation | C70: Value | E70: Less: YE FY27E Net debt ($M) | F70: =C84 -> 724.25125 | G70: Forward into 2028
B71: Steady-state component: 1 / r | C71: =1/C65 -> 11.510129 | E71: Implied Equity Value ($M) | F71: =F69-F70 -> 8031.8923 | G71: EV less net debt
B72: Value-creation factor: 1 − r / ROIIC | C72: =1-C65/C67 -> 0.5656 | E72: FY28E Net Income (GAAP, $M) | F72: =Model!CK133 -> 418.17665 | G72: Linked to Model CK133
B73: Growth multiplier: g × (1 − r/ROIIC) / (r × (r − g)) | C73: =C66*C72/(C65*(C65-C66)) -> 75.699173 | E73: FY28E Adj Net Earnings ($M) | F73: =Model!CK155 -> 429.88671 | G73: Linked to Model CK155 (after-tax adj add-back)
B74: Time decay: 1 − ((1+g)/(1+r))^N | C74: =1-((1+C66)/(1+C65))^C68 -> 0.090856635
B75: PVGO component (growth value) | C75: =C73*C74 -> 6.8777722 | E75: Implied P/E on GAAP NI (×) | F75: =IFERROR(F71/F72,"n/a") -> 19.206936 | G75: Implied Equity Value / FY28E GAAP NI
B76: Mauboussin EV / NOPAT (steady-state + PVGO) | C76: =C71+C75 -> 18.387901 | E76: Implied P/E on Adj NE (×) | F76: =IFERROR(F71/F73,"n/a") -> 18.683742 | G76: Implied Equity Value / FY28E Adj NE
B78: VALUATION — Applied to FY28E NOPAT | C78: $M | E78: Cross-check: Market-implied P/E today
B79: FY28E Adj EBIT (Model CG146) | C79: =IF(ISNUMBER(Model!CK150),IF(Model!CK150>0,Model!CK150,Model!CK126),Model!CK126) -> 626.56643 | E79: Current price ($) | F79: =$C$42 -> 345
B80: Tax rate (cash, from WACC build) | C80: =$C$10 -> 0.24 | E80: FY28E Adj EPS ($) | F80: =Model!CK156 -> 13.929446 | G80: Linked to Model CK156
B81: FY28E NOPAT = EBIT × (1 − t) | C81: =C79*(1-C80) -> 476.19048 | E81: Market P/E on FY28E Adj EPS (×) | F81: =IFERROR(F79/F80,"n/a") -> 24.767676 | G81: Current valuation on Adj EPS
B82: × Mauboussin EV/NOPAT multiple | C82: =C76 -> 18.387901
B83: Implied Enterprise Value (FY28E basis) | C83: =C81*C82 -> 8756.1435 | E83: P/E Gap (Mauboussin − Market, ×) | F83: =F76-F81 -> -6.083934 | G83: Positive = re-rating headroom; Negative = stock priced richer than framework
B84: Less: YE FY27E Net debt (forward into 2028) | C84: =Model!CJ331 -> 724.25125 | E84: Implied re-rating ($) | F84: =F83*F80 -> -84.745829 | G84: P/E gap × FY28E Adj EPS
B85: Implied Equity Value | C85: =C83-C84 -> 8031.8923
B86: Diluted shares FY28E ('000) | C86: =Model!CK139 -> 30861.724
B87: Implied share price 2028 ($) | C87: =C85*1000/C86 -> 260.25417
B89: Current share price | C89: =C42 -> 345
B90: Implied upside / (downside) | C90: =C87/C89-1 -> -0.24564009
B92: MARKET-IMPLIED EV/NOPAT TODAY | C92: $M
B93: Current Market Cap (Spot × FDSO) | C93: =C42*C40/1000 -> 10918.497
B94: Plus: YE FY26E Net debt | C94: =C38 -> 833.94734
B95: Implied Enterprise Value (today) | C95: =C93+C94 -> 11752.445
B96: Moog's Market-Implied EV/NOPAT (on FY28E NOPAT) | C96: =C95/C81 -> 24.680133
B98: Multiple Gap (Mauboussin − Market) | C98: =C76-C96 -> -6.2922323
B99: Implied re-rating headroom | C99: =C76/C96-1 -> -0.25495131
B102: 7. REVERSE FRAMEWORK — EXIT MULTIPLE → IMPLIED REVENUE GROWTH
B103: Given a target FY30 exit P/E and required equity IRR, back out the FY30 revenue (and CAGR) needed to justify the current price using the model's average incremental EBIT margin.
B105: Inputs | C105: Value | D105: Note
B106: Current share price ($) | C106: =C42 -> 345 | D106: Linked to Section 1 / sensitivity
B107: Target equity IRR (per year) | C107: 0.15 | D107: Hardcoded hurdle rate
B108: Years to FY30 exit | C108: 5 | D108: FY26→FY30 = 5 fiscal years
B109: FY30E target price ($) | C109: =C106*(1+C107)^C108 -> 693.91823 | D109: Current price compounded at IRR over CAP
B110: FY30E diluted shares ('000) | C110: =Model!CM139 -> 30175.118 | D110: Model FY30E diluted shares (after buybacks)
B111: Tax rate (steady-state) | C111: =C10 -> 0.24 | D111: From WACC build
B112: FY25 Adj EBIT ($M) | C112: =Model!CD150 -> 501.268 | D112: Model FY25 reconciliation
B113: FY25 Revenue ($M) | C113: =Model!CD114 -> 3860.624
B114: Model-derived incremental EBIT margin FY26-FY30 | C114: =IFERROR((Model!CM150-Model!CD150)/(Model!CM114-Model!CD114),"n/a") -> 0.16523706 | D114: Reference only — from Model base case
B115: → Incremental EBIT margin used (override) | C115: 0.25 | D115: Edit to flex scenarios
B117: Scenario A: Exit at 25x P/E in FY30 | C117: Scenario B: Exit at Mauboussin P/E | D117: Note
B118: Exit P/E multiple (×) | C118: 25 | D118: =F76 -> 18.683742
B119: Required FY30E Adj NE ($M) | C119: =$C$109*$C$110/1000/C118 -> 837.56257 | D119: =$C$109*$C$110/1000/D118 -> 1120.7104 | E119: Target NE = Target price × shares / P/E
B120: Required FY30E Adj EBIT ($M, pre-tax) | C120: =C119/(1-$C$111) -> 1102.056 | D120: =D119/(1-$C$111) -> 1474.619 | E120: EBIT = NE / (1-t); ignores interest — conservative proxy
B121: Δ EBIT vs FY25 ($M) | C121: =C120-$C$112 -> 600.78802 | D121: =D120-$C$112 -> 973.35098
B122: Δ Revenue needed ($M) | C122: =C121/$C$115 -> 2403.1521 | D122: =D121/$C$115 -> 3893.4039 | E122: Δ EBIT / avg incremental margin
...

Sheet Moog-Charts
B2: Moog Inc. — Historical Operating Performance (FY15–FY25)
B3: All historicals · $M · Linked to Model.
C7: 2015 | D7: 2016 | E7: 2017 | F7: 2018 | G7: 2019 | H7: 2020 | I7: 2021 | J7: 2022 | K7: 2023 | L7: 2024 | M7: 2025
B8: Revenue y/y % | C8: 0 | D8: =IFERROR(Model!AK114/Model!AF114-1,"") -> -0.044978642 | E8: =IFERROR(Model!AP114/Model!AK114-1,"") -> 0.035484758 | F8: =IFERROR(Model!AU114/Model!AP114-1,"") -> 0.084861647 | G8: =IFERROR(Model!AZ114/Model!AU114-1,"") -> 0.072041818 | H8: =IFERROR(Model!BE114/Model!AZ114-1,"") -> -0.0069230062 | I8: =IFERROR(Model!BJ114/Model!BE114-1,"") -> -0.011288054 | J8: =IFERROR(Model!BO114/Model!BJ114-1,"") -> 0.064442655 | K8: =IFERROR(Model!BT114/Model!BO114-1,"") -> 0.092367274 | L8: =IFERROR(Model!BY114/Model!BT114-1,"") -> 0.08828505 | M8: =IFERROR(Model!CD114/Model!BY114-1,"") -> 0.069733109
B11: Year | C11: 2015 | D11: 2016 | E11: 2017 | F11: 2018 | G11: 2019 | H11: 2020 | I11: 2021 | J11: 2022 | K11: 2023 | L11: 2024 | M11: 2025
B12: Gross Profit ($M) | C12: =Model!AF116 -> 736.704 | D12: =Model!AK116 -> 711.583 | E12: =Model!AP116 -> 731.522 | F12: =Model!AU116 -> 774.091 | G12: =Model!AZ116 -> 815.832 | H12: =Model!BE116 -> 743.696 | I12: =Model!BJ116 -> 775.723 | J12: =Model!BO116 -> 820.801 | K12: =Model!BT116 -> 897.755 | L12: =Model!BY116 -> 1012.408 | M12: =Model!CD116 -> 1057.348
B13: Adj EBIT ($M) | C13: =IF(ISNUMBER(Model!AF150),IF(Model!AF150>0,Model!AF150,Model!AF126),Model!AF126) -> 212.801 | D13: =IF(ISNUMBER(Model!AK150),IF(Model!AK150>0,Model!AK150,Model!AK126),Model!AK126) -> 204.1 | E13: =IF(ISNUMBER(Model!AP150),IF(Model!AP150>0,Model!AP150,Model!AP126),Model!AP126) -> 250.152 | F13: =IF(ISNUMBER(Model!AU150),IF(Model!AU150>0,Model!AU150,Model!AU126),Model!AU126) -> 294.534 | G13: =IF(ISNUMBER(Model!AZ150),IF(Model!AZ150>0,Model!AZ150,Model!AZ126),Model!AZ126) -> 321.142 | H13: =IF(ISNUMBER(Model!BE150),IF(Model!BE150>0,Model!BE150,Model!BE126),Model!BE126) -> 287.609 | I13: =IF(ISNUMBER(Model!BJ150),IF(Model!BJ150>0,Model!BJ150,Model!BJ126),Model!BJ126) -> 277.863 | J13: =IF(ISNUMBER(Model!BO150),IF(Model!BO150>0,Model!BO150,Model!BO126),Model!BO126) -> 308.279 | K13: =IF(ISNUMBER(Model!BT150),IF(Model!BT150>0,Model!BT150,Model!BT126),Model!BT126) -> 361.806 | L13: =IF(ISNUMBER(Model!BY150),IF(Model!BY150>0,Model!BY150,Model!BY126),Model!BY126) -> 457.862 | M13: =IF(ISNUMBER(Model!CD150),IF(Model!CD150>0,Model!CD150,Model!CD126),Model!CD126) -> 501.268
B14: Gross margin % | C14: =IFERROR(Model!AF116/Model!AF114,"") -> 0.2917025 | D14: =IFERROR(Model!AK116/Model!AK114,"") -> 0.29502553 | E14: =IFERROR(Model!AP116/Model!AP114,"") -> 0.29289889 | F14: =IFERROR(Model!AU116/Model!AU114,"") -> 0.28569852 | G14: =IFERROR(Model!AZ116/Model!AZ114,"") -> 0.28086976 | H14: =IFERROR(Model!BE116/Model!BE114,"") -> 0.2578201 | I14: =IFERROR(Model!BJ116/Model!BJ114,"") -> 0.2719933 | J14: =IFERROR(Model!BO116/Model!BO114,"") -> 0.27037539 | K14: =IFERROR(Model!BT116/Model!BT114,"") -> 0.27071881 | L14: =IFERROR(Model!BY116/Model!BY114,"") -> 0.28052625 | M14: =IFERROR(Model!CD116/Model!CD114,"") -> 0.27388008
B15: Adj EBIT margin % | C15: =IFERROR(IF(ISNUMBER(Model!AF150),IF(Model!AF150>0,Model!AF150,Model!AF126),Model!AF126)/Model!AF114,"") -> 0.084259871 | D15: =IFERROR(IF(ISNUMBER(Model!AK150),IF(Model!AK150>0,Model!AK150,Model!AK126),Model!AK126)/Model!AK114,"") -> 0.084620784 | E15: =IFERROR(IF(ISNUMBER(Model!AP150),IF(Model!AP150>0,Model!AP150,Model!AP126),Model!AP126)/Model!AP114,"") -> 0.10016 | F15: =IFERROR(IF(ISNUMBER(Model!AU150),IF(Model!AU150>0,Model!AU150,Model!AU126),Model!AU126)/Model!AU114,"") -> 0.10870547 | G15: =IFERROR(IF(ISNUMBER(Model!AZ150),IF(Model!AZ150>0,Model!AZ150,Model!AZ126),Model!AZ126)/Model!AZ114,"") -> 0.11056085 | H15: =IFERROR(IF(ISNUMBER(Model!BE150),IF(Model!BE150>0,Model!BE150,Model!BE126),Model!BE126)/Model!BE114,"") -> 0.099706575 | I15: =IFERROR(IF(ISNUMBER(Model!BJ150),IF(Model!BJ150>0,Model!BJ150,Model!BJ126),Model!BJ126)/Model!BJ114,"") -> 0.097427658 | J15: =IFERROR(IF(ISNUMBER(Model!BO150),IF(Model!BO150>0,Model!BO150,Model!BO126),Model!BO126)/Model!BO114,"") -> 0.10154843 | K15: =IFERROR(IF(ISNUMBER(Model!BT150),IF(Model!BT150>0,Model!BT150,Model!BT126),Model!BT126)/Model!BT114,"") -> 0.10910292 | L15: =IFERROR(IF(ISNUMBER(Model!BY150),IF(Model!BY150>0,Model!BY150,Model!BY126),Model!BY126)/Model!BY114,"") -> 0.12686813 | M15: =IFERROR(IF(ISNUMBER(Model!CD150),IF(Model!CD150>0,Model!CD150,Model!CD126),Model!CD126)/Model!CD114,"") -> 0.12984119
B17: Year | C17: 2015 | D17: 2016 | E17: 2017 | F17: 2018 | G17: 2019 | H17: 2020 | I17: 2021 | J17: 2022 | K17: 2023 | L17: 2024 | M17: 2025
B18: ROIC | C18: =IFERROR(Model!AF332,NA()) -> 0.086747663 | D18: =IFERROR(Model!AK332,NA()) -> 0.08644435 | E18: =IFERROR(Model!AP332,NA()) -> 0.10728565 | F18: =IFERROR(Model!AU332,NA()) -> 0.078655447 | G18: =IFERROR(Model!AZ332,NA()) -> 0.11954878 | H18: =IFERROR(Model!BE332,NA()) -> 0.10329086 | I18: =IFERROR(Model!BJ332,NA()) -> 0.097316191 | J18: =IFERROR(Model!BO332,NA()) -> 0.1092484 | K18: =IFERROR(Model!BT332,NA()) -> 0.11772679 | L18: =IFERROR(Model!BY332,NA()) -> 0.13418059 | M18: =IFERROR(Model!CD332,NA()) -> 0.13102097
B19: RONTA | C19: =IFERROR(Model!AF346,NA()) -> 0.11831713 | D19: =IFERROR(Model!AK346,NA()) -> 0.11691297 | E19: =IFERROR(Model!AP346,NA()) -> 0.15983766 | F19: =IFERROR(Model!AU346,NA()) -> 0.121688 | G19: =IFERROR(Model!AZ346,NA()) -> 0.17231893 | H19: =IFERROR(Model!BE346,NA()) -> 0.1415721 | I19: =IFERROR(Model!BJ346,NA()) -> 0.13520954 | J19: =IFERROR(Model!BO346,NA()) -> 0.14857474 | K19: =IFERROR(Model!BT346,NA()) -> 0.15213141 | L19: =IFERROR(Model!BY346,NA()) -> 0.16834227 | M19: =IFERROR(Model!CD346,NA()) -> 0.16117724
B20: EBIT / GP (conv ratio) | C20: =IFERROR(IF(ISNUMBER(Model!AF150),IF(Model!AF150>0,Model!AF150,Model!AF126),Model!AF126)/Model!AF116,NA()) -> 0.2888555 | D20: =IFERROR(IF(ISNUMBER(Model!AK150),IF(Model!AK150>0,Model!AK150,Model!AK126),Model!AK126)/Model!AK116,NA()) -> 0.28682529 | E20: =IFERROR(IF(ISNUMBER(Model!AP150),IF(Model!AP150>0,Model!AP150,Model!AP126),Model!AP126)/Model!AP116,NA()) -> 0.34196101 | F20: =IFERROR(IF(ISNUMBER(Model!AU150),IF(Model!AU150>0,Model!AU150,Model!AU126),Model!AU126)/Model!AU116,NA()) -> 0.38049015 | G20: =IFERROR(IF(ISNUMBER(Model!AZ150),IF(Model!AZ150>0,Model!AZ150,Model!AZ126),Model!AZ126)/Model!AZ116,NA()) -> 0.39363742 | H20: =IFERROR(IF(ISNUMBER(Model!BE150),IF(Model!BE150>0,Model!BE150,Model!BE126),Model!BE126)/Model!BE116,NA()) -> 0.38672925 | I20: =IFERROR(IF(ISNUMBER(Model!BJ150),IF(Model!BJ150>0,Model!BJ150,Model!BJ126),Model!BJ126)/Model!BJ116,NA()) -> 0.35819874 | J20: =IFERROR(IF(ISNUMBER(Model!BO150),IF(Model!BO150>0,Model!BO150,Model!BO126),Model!BO126)/Model!BO116,NA()) -> 0.37558312 | K20: =IFERROR(IF(ISNUMBER(Model!BT150),IF(Model!BT150>0,Model!BT150,Model!BT126),Model!BT126)/Model!BT116,NA()) -> 0.40301196 | L20: =IFERROR(IF(ISNUMBER(Model!BY150),IF(Model!BY150>0,Model!BY150,Model!BY126),Model!BY126)/Model!BY116,NA()) -> 0.45225048 | M20: =IFERROR(IF(ISNUMBER(Model!CD150),IF(Model!CD150>0,Model!CD150,Model!CD126),Model!CD126)/Model!CD116,NA()) -> 0.47408044
B21: Incremental EBIT margin | D21: =IFERROR((IF(ISNUMBER(Model!AK150),IF(Model!AK150>0,Model!AK150,Model!AK126),Model!AK126)-IF(ISNUMBER(Model!AF150),IF(Model!AF150>0,Model!AF150,Model!AF126),Model!AF126))/(Model!AK114-Model!AF114),NA()) -> 0.076596681 | E21: =IFERROR((IF(ISNUMBER(Model!AP150),IF(Model!AP150>0,Model!AP150,Model!AP126),Model!AP126)-IF(ISNUMBER(Model!AK150),IF(Model!AK150>0,Model!AK150,Model!AK126),Model!AK126))/(Model!AP114-Model!AK114),NA()) -> 0.53807237 | F21: =IFERROR((IF(ISNUMBER(Model!AU150),IF(Model!AU150>0,Model!AU150,Model!AU126),Model!AU126)-IF(ISNUMBER(Model!AP150),IF(Model!AP150>0,Model!AP150,Model!AP126),Model!AP126))/(Model!AU114-Model!AP114),NA()) -> 0.20940437 | G21: =IFERROR((IF(ISNUMBER(Model!AZ150),IF(Model!AZ150>0,Model!AZ150,Model!AZ126),Model!AZ126)-IF(ISNUMBER(Model!AU150),IF(Model!AU150>0,Model!AU150,Model!AU126),Model!AU126))/(Model!AZ114-Model!AU114),NA()) -> 0.13631497 | H21: =IFERROR((IF(ISNUMBER(Model!BE150),IF(Model!BE150>0,Model!BE150,Model!BE126),Model!BE126)-IF(ISNUMBER(Model!AZ150),IF(Model!AZ150>0,Model!AZ150,Model!AZ126),Model!AZ126))/(Model!BE114-Model!AZ114),NA()) -> 1.6675618 | I21: =IFERROR((IF(ISNUMBER(Model!BJ150),IF(Model!BJ150>0,Model!BJ150,Model!BJ126),Model!BJ126)-IF(ISNUMBER(Model!BE150),IF(Model!BE150>0,Model!BE150,Model!BE126),Model!BE126))/(Model!BJ114-Model!BE114),NA()) -> 0.29931513 | J21: =IFERROR((IF(ISNUMBER(Model!BO150),IF(Model!BO150>0,Model!BO150,Model!BO126),Model!BO126)-IF(ISNUMBER(Model!BJ150),IF(Model!BJ150>0,Model!BJ150,Model!BJ126),Model!BJ126))/(Model!BO114-Model!BJ114),NA()) -> 0.16549323 | K21: =IFERROR((IF(ISNUMBER(Model!BT150),IF(Model!BT150>0,Model!BT150,Model!BT126),Model!BT126)-IF(ISNUMBER(Model!BO150),IF(Model!BO150>0,Model!BO150,Model!BO126),Model!BO126))/(Model!BT114-Model!BO114),NA()) -> 0.19089038 | L21: =IFERROR((IF(ISNUMBER(Model!BY150),IF(Model!BY150>0,Model!BY150,Model!BY126),Model!BY126)-IF(ISNUMBER(Model!BT150),IF(Model!BT150>0,Model!BT150,Model!BT126),Model!BT126))/(Model!BY114-Model!BT114),NA()) -> 0.32809373 | M21: =IFERROR((IF(ISNUMBER(Model!CD150),IF(Model!CD150>0,Model!CD150,Model!CD126),Model!CD126)-IF(ISNUMBER(Model!BY150),IF(Model!BY150>0,Model!BY150,Model!BY126),Model!BY126))/(Model!CD114-Model!BY114),NA()) -> 0.172476

Sheet Model_DSV_ref
B2: DSV A/S — 3-Statement Financial Model | BU2: SCENARIO → | BV2: Base
B3: IFRS as reported · DKK millions · Source: DSV Annual Reports 2018–2025 (investor.dsv.com/download-library)
B4: Schenker acquisition closed 30 April 2025 — figures from Q2 2025 onward include Schenker contribution and are not directly comparable to prior periods.
BX5: Forecast | BY5: Historical | BZ5: Historical
B6: (DKKm) | C6: Q1/15 | D6: Q2/15 | E6: 1H/15 | F6: Q3/15 | G6: Q4/15 | H6: 2015 | I6: Q1/16 | J6: Q2/16 | K6: 1H/16 | L6: Q3/16 | M6: Q4/16 | N6: 2016 | O6: Q1/17 | P6: Q2/17 | Q6: 1H/17 | R6: Q3/17 | S6: Q4/17 | T6: 2017 | U6: Q1/18 | V6: Q2/18 | W6: 1H/18 | X6: Q3/18 | Y6: Q4/18 | Z6: 2018 | AA6: Q1/19 | AB6: Q2/19 | AC6: 1H/19 | AD6: Q3/19 | AE6: Q4/19 | AF6: 2019 | AG6: Q1/20 | AH6: Q2/20 | AI6: 1H/20 | AJ6: Q3/20 | AK6: Q4/20 | AL6: 2020 | AM6: Q1/21 | AN6: Q2/21 | AO6: 1H/21 | AP6: Q3/21 | AQ6: Q4/21 | AR6: 2021 | AS6: Q1/22 | AT6: Q2/22 | AU6: 1H/22 | AV6: Q3/22 | AW6: Q4/22 | AX6: 2022 | AY6: Q1/23 | AZ6: Q2/23 | BA6: 1H/23 | BB6: Q3/23 | BC6: Q4/23 | BD6: 2023 | BE6: Q1/24 | BF6: Q2/24 | BG6: 1H/24 | BH6: Q3/24 | BI6: Q4/24 | BJ6: 2024 | BK6: Q1/25 | BL6: Q2/25 | BM6: 1H/25 | BN6: Q3/25 | BO6: Q4/25 | BP6: 2025 | BQ6: 2026E | BR6: 2027E | BS6: 2028E | BT6: 2029E | BU6: 2030E | BV6: Modelling Notes | BX6: 5Y CAGR | BY6: 5Y CAGR | BZ6: 10Y CAGR
BX7: 25-'30 | BY7: 20-'25 | BZ7: 15-'25
B8: SEGMENT P&L — BY DIVISION
CC9: SCENARIO INPUT TABLE — driver assumptions per Bull/Base/Bear | CD9: Bull | CE9: Base | CF9: Bear
B10: Air & Sea | BV10: AIR & SEA — modelling logic
B11: Revenue | H11: 21685 | N11: 32100 | T11: 34587 | Z11: 36350 | AF11: 50527 | AL11: 73032 | AR11: 130899 | AX11: 172868 | BD11: 92438 | BJ11: 103926 | BP11: 132991 | BQ11: =BQ13-BQ12 -> 151500.78 | BR11: =BR13-BR12 -> 160590.83 | BS11: =BS13-BS12 -> 168620.37 | BT11: =BT13-BT12 -> 175365.19 | BU11: =BU13-BU12 -> 182379.79 | CC11: AS_revGrowth
B12: Intersegment revenue | H12: -408 | N12: -716 | T12: 617 | Z12: 622 | AF12: 624 | AL12: 657 | AR12: 1002 | AX12: 1563 | BD12: 534 | BJ12: 570 | BP12: 4329 | BQ12: =BQ13*BQ37 -> 4685.5912 | BR12: =BR13*BR37 -> 4966.7267 | BS12: =BS13*BS37 -> 5215.063 | BT12: =BT13*BT37 -> 5423.6655 | BU12: =BU13*BU37 -> 5640.6121 | CC12: 2026E | CD12: 0.18 | CE12: 0.18 | CF12: 0.03
B13: Divisional revenue | C13: 5421 | D13: 5703 | E13: 11124 | F13: 5379 | G13: 5182 | H13: 21277 | I13: 7055 | J13: 8416 | K13: 15471 | L13: 8282 | M13: 8347 | N13: 31384 | T13: 35204 | Z13: 36972 | AF13: 51151 | AG13: 16674 | AH13: 19144 | AI13: 35818 | AJ13: 17910 | AK13: 19961 | AL13: 73689 | AM13: 22924 | AN13: 25948 | AO13: 48872 | AP13: 36861 | AQ13: 46168 | AR13: 131901 | AS13: 45887 | AT13: 47282 | AU13: 93169 | AV13: 45339 | AW13: 35923 | AX13: 174431 | AY13: 26213 | AZ13: 22993 | BA13: 49206 | BB13: 21912 | BC13: 21854 | BD13: 92972 | BE13: 22716 | BF13: 24616 | BG13: 47332 | BH13: 28416 | BI13: 28748 | BJ13: 104496 | BK13: 26108 | BL13: 34475 | BM13: 60583 | BN13: 38688 | BP13: 132361.33 | BQ13: =BP13*(1+BQ21) -> 156186.37 | BR13: =BQ13*(1+BR21) -> 165557.56 | BS13: =BR13*(1+BS21) -> 173835.43 | BT13: =BS13*(1+BT21) -> 180788.85 | BU13: =BT13*(1+BU21) -> 188020.4 | BX13: =IFERROR((BU13/BP13)^(1/5)-1,"n/m") -> 0.072725909 | BY13: =IFERROR((BP13/AL13)^(1/5)-1,"n/m") -> 0.12427278 | BZ13: =IFERROR((BP13/H13)^(1/10)-1,"n/m") -> 0.20056333 | CC13: 2027E | CD13: 0.08 | CE13: 0.06 | CF13: 0
B14: Direct costs | C14: 4195 | D14: 4351 | E14: 8546 | F14: 4012 | G14: 3836 | H14: n/a | I14: 5178 | J14: 6108 | K14: 11286 | L14: 6159 | M14: 6317 | N14: n/a | T14: 26580 | Z14: 27779 | AF14: 38634 | AG14: 12799 | AH14: 14481 | AI14: 27280 | AJ14: 13607 | AK14: 15893 | AL14: 56780 | AM14: 18136 | AN14: 20806 | AO14: 38942 | AP14: 30547 | AQ14: 38643 | AR14: 108132 | AS14: 37250 | AT14: 37707 | AU14: 74957 | AV14: 36204 | AW14: 28646 | AX14: 139807 | AY14: 19186 | AZ14: 16239 | BA14: 35425 | BB14: 15702 | BC14: 15875 | BD14: 67002 | BE14: 16953 | BF14: 18544 | BG14: 35497 | BH14: 21958 | BI14: 22320 | BJ14: 79775 | BK14: 19735 | BL14: 25989 | BM14: 45724 | BN14: 29528 | BP14: 100336 | BQ14: =BQ13*BQ38 -> 117920.71 | BR14: =BR13*BR38 -> 124168.17 | BS14: =BS13*BS38 -> 129507.4 | BT14: =BT13*BT38 -> 134687.69 | BU14: =BU13*BU38 -> 140075.2 | BV14: =BQ13-BQ14 -> 38265.661 | CC14: 2028E | CD14: 0.07 | CE14: 0.05 | CF14: 0.01
B15: Gross profit | C15: 1226 | D15: 1352 | E15: 2578 | F15: 1367 | G15: 1346 | H15: n/a | I15: 1877 | J15: 2308 | K15: 4185 | L15: 2123 | M15: 2030 | N15: n/a | T15: =T13-T14 -> 8624 | Z15: =Z13-Z14 -> 9193 | AF15: =AF13-AF14 -> 12517 | AG15: 3875 | AH15: 4663 | AI15: 8538 | AJ15: 4303 | AK15: 4068 | AL15: =AL13-AL14 -> 16909 | AM15: 4788 | AN15: 5142 | AO15: 9930 | AP15: 6314 | AQ15: 7525 | AR15: =AR13-AR14 -> 23769 | AS15: 8637 | AT15: 9575 | AU15: 18212 | AV15: 9135 | AW15: 7277 | AX15: =AX13-AX14 -> 34624 | AY15: 7027 | AZ15: 6754 | BA15: 13781 | BB15: 6210 | BC15: 5979 | BD15: =BD13-BD14 -> 25970 | BE15: 5763 | BF15: 6072 | BG15: 11835 | BH15: 6458 | BI15: 6428 | BJ15: =BJ13-BJ14 -> 24721 | BK15: 6373 | BL15: 8486 | BM15: 14859 | BN15: 9160 | BP15: =BP13-BP14 -> 32025.333 | BQ15: =BQ13*BQ25 -> 38265.661 | BR15: =BR13*BR25 -> 41389.389 | BS15: =BS13*BS25 -> 44328.036 | BT15: =BT13*BT25 -> 46101.157 | BU15: =BU13*BU25 -> 47945.203 | BX15: =IFERROR((BU15/BP15)^(1/5)-1,"n/m") -> 0.084052464 | BY15: =IFERROR((BP15/AL15)^(1/5)-1,"n/m") -> 0.13625327 | BZ15: =IFERROR((BP15/H15)^(1/10)-1,"n/m") -> n/m | CC15: 2029E | CD15: 0.06 | CE15: 0.04 | CF15: 0.01
B16: Other external costs | C16: 264 | D16: 257 | E16: 521 | F16: 258 | G16: 266 | H16: n/a | I16: 479 | J16: 640 | K16: 1119 | L16: 550 | M16: 508 | N16: n/a | T16: 1798 | Z16: 1854 | AF16: 2267 | AG16: 797 | AH16: 736 | AI16: 1533 | AJ16: 692 | AK16: 645 | AL16: 2870 | AM16: 753 | AN16: 663 | AO16: 1416 | AP16: 814 | AQ16: 1136 | AR16: 3366 | AS16: 1076 | AT16: 1028 | AU16: 2104 | AV16: 1097 | AW16: 1043 | AX16: 4244 | AY16: 1023 | AZ16: 883 | BA16: 1906 | BB16: 762 | BC16: 906 | BD16: 3574 | BE16: 908 | BF16: 890 | BG16: 1798 | BH16: 956 | BI16: 978 | BJ16: 3732 | BK16: 1009 | BL16: 1375 | BM16: 2384 | BN16: 1596 | BP16: 5306.6667 | BQ16: =BQ13*BQ39 -> 6247.4549 | BR16: =BR13*BR39 -> 6291.1871 | BS16: =BS13*BS39 -> 6258.0756 | BT16: =BT13*BT39 -> 6146.8209 | BU16: =BU13*BU39 -> 6204.6734 | CC16: 2030E | CD16: 0.06 | CE16: 0.04 | CF16: 0.01
B17: Staff costs | C17: 545 | D17: 565 | E17: 1110 | F17: 544 | G17: 561 | H17: n/a | I17: 937 | J17: 1078 | K17: 2015 | L17: 898 | M17: 911 | N17: n/a | T17: 3490 | Z17: 3560 | AF17: 5093 | AG17: 1679 | AH17: 1530 | AI17: 3209 | AJ17: 1394 | AK17: 1445 | AL17: 6048 | AM17: 1445 | AN17: 1435 | AO17: 2880 | AP17: 1698 | AQ17: 2020 | AR17: 6598 | AS17: 2033 | AT17: 2082 | AU17: 4115 | AV17: 2276 | AW17: 2080 | AX17: 8471 | AY17: 2093 | AZ17: 2005 | BA17: 4098 | BB17: 1873 | BC17: 1906 | BD17: 7877 | BE17: 1943 | BF17: 1994 | BG17: 3937 | BH17: 1957 | BI17: 2051 | BJ17: 7945 | BK17: 2117 | BL17: 3252 | BM17: 5369 | BN17: 3599 | BP17: 11957.333 | BQ17: =BQ13*BQ40 -> 14056.774 | BR17: =BR13*BR40 -> 14403.507 | BS17: =BS13*BS40 -> 14602.176 | BT17: =BT13*BT40 -> 14824.686 | BU17: =BU13*BU40 -> 15041.632
B18: EBITDA before special items | C18: 417 | D18: 530 | E18: 947 | F18: 565 | G18: 519 | H18: n/a | I18: 461 | J18: 590 | K18: 1051 | L18: 675 | M18: 611 | N18: n/a | T18: =T15-T16-T17 -> 3336 | Z18: =Z15-Z16-Z17 -> 3779 | AF18: =AF15-AF16-AF17 -> 5157 | AG18: 1399 | AH18: 2397 | AI18: 3796 | AJ18: 2217 | AK18: 1978 | AL18: =AL15-AL16-AL17 -> 7991 | AM18: 2590 | AN18: 3044 | AO18: 5634 | AP18: 3802 | AQ18: 4369 | AR18: =AR15-AR16-AR17 -> 13805 | AS18: 5528 | AT18: 6465 | AU18: 11993 | AV18: 5762 | AW18: 4154 | AX18: =AX15-AX16-AX17 -> 21909 | AY18: 3911 | AZ18: 3866 | BA18: 7777 | BB18: 3575 | BC18: 3167 | BD18: =BD15-BD16-BD17 -> 14519 | BE18: 2912 | BF18: 3188 | BG18: 6100 | BH18: 3545 | BI18: 3399 | BJ18: =BJ15-BJ16-BJ17 -> 13044 | BK18: 3247 | BL18: 3859 | BM18: 7106 | BN18: 3965 | BP18: =BP15-BP16-BP17 -> 14761.333 | BQ18: =BQ15-BQ16-BQ17 -> 17961.433 | BR18: =BR15-BR16-BR17 -> 20694.694 | BS18: =BS15-BS16-BS17 -> 23467.784 | BT18: =BT15-BT16-BT17 -> 25129.65 | BU18: =BU15-BU16-BU17 -> 26698.897 | BX18: =IFERROR((BU18/BP18)^(1/5)-1,"n/m") -> 0.12583189 | BY18: =IFERROR((BP18/AL18)^(1/5)-1,"n/m") -> 0.13058935 | BZ18: =IFERROR((BP18/H18)^(1/10)-1,"n/m") -> n/m | CC18: Road_revGrowth
B19: Amortisation and depreciation | C19: 29 | D19: 28 | E19: 57 | F19: 24 | G19: 27 | H19: 108 | I19: 47 | J19: 56 | K19: 103 | L19: 49 | M19: 42 | N19: 194 | T19: 111 | Z19: 86 | AF19: 651 | AG19: 269 | AH19: 285 | AI19: 554 | AJ19: 223 | AK19: 188 | AL19: 965 | AM19: 197 | AN19: 201 | AO19: 398 | AP19: 281 | AQ19: 358 | AR19: 1037 | AS19: 304 | AT19: 302 | AU19: 606 | AV19: 307 | AW19: 338 | AX19: 1251 | AY19: 285 | AZ19: 292 | BA19: 577 | BB19: 294 | BC19: 285 | BD19: 1156 | BE19: 285 | BF19: 290 | BG19: 575 | BH19: 285 | BI19: 296 | BJ19: 1156 | BK19: 298 | BL19: 398 | BM19: 696 | BN19: 433 | BP19: 1505.3333 | BQ19: =BQ13*BQ41 -> 2030.4229 | BR19: =BR13*BR41 -> 2152.2482 | BS19: =BS13*BS41 -> 2172.9429 | BT19: =BT13*BT41 -> 2259.8606 | BU19: =BU13*BU41 -> 2256.2449 | CC19: 2026E | CD19: 0.12 | CE19: 0.1 | CF19: 0.02
B20: EBIT before special items | C20: 388 | D20: 502 | E20: 890 | F20: 541 | G20: 492 | H20: 1923 | I20: 414 | J20: 534 | K20: 948 | L20: 626 | M20: 569 | N20: 2143 | T20: =T18-T19 -> 3225 | Z20: =Z18-Z19 -> 3693 | AF20: =AF18-AF19 -> 4506 | AG20: 1130 | AH20: 2112 | AI20: 3242 | AJ20: 1994 | AK20: 1790 | AL20: =AL18-AL19 -> 7026 | AM20: 2393 | AN20: 2843 | AO20: 5236 | AP20: 3521 | AQ20: 4011 | AR20: =AR18-AR19 -> 12768 | AS20: 5224 | AT20: 6163 | AU20: 11387 | AV20: 5455 | AW20: 3816 | AX20: =AX18-AX19 -> 20658 | AY20: 3626 | AZ20: 3574 | BA20: 7200 | BB20: 3281.3212 | BC20: 2882 | BD20: =BD18-BD19 -> 13363 | BE20: 2627 | BF20: 2898 | BG20: 5525 | BH20: 3260 | BI20: 3103 | BJ20: =BJ18-BJ19 -> 11888 | BK20: 2949 | BL20: 3461 | BM20: 6410 | BN20: 3532 | BP20: =BP18-BP19 -> 13256 | BQ20: =BQ18-BQ19 -> 15931.01 | BR20: =BR18-BR19 -> 18542.446 | BS20: =BS18-BS19 -> 21294.841 | BT20: =BT18-BT19 -> 22869.79 | BU20: =BU18-BU19 -> 24442.653 | BX20: =IFERROR((BU20/BP20)^(1/5)-1,"n/m") -> 0.13017883 | BY20: =IFERROR((BP20/AL20)^(1/5)-1,"n/m") -> 0.13537903 | BZ20: =IFERROR((BP20/H20)^(1/10)-1,"n/m") -> 0.21295118 | CC20: 2027E | CD20: 0.05 | CE20: 0.04 | CF20: 0
B21: Revenue y/y % | N21: =IFERROR(N11/H11-1,"") -> 0.48028591 | T21: =IFERROR(T11/N11-1,"") -> 0.077476636 | Z21: =IFERROR(Z11/T11-1,"") -> 0.050972909 | AF21: =IFERROR(AF11/Z11-1,"") -> 0.39001376 | AL21: =IFERROR(AL11/AF11-1,"") -> 0.44540543 | AR21: =IFERROR(AR11/AL11-1,"") -> 0.7923513 | AX21: =IFERROR(AX11/AR11-1,"") -> 0.32062124 | BD21: =IFERROR(BD11/AX11-1,"") -> -0.4652683 | BJ21: =IFERROR(BJ11/BD11-1,"") -> 0.12427789 | BP21: =IFERROR(BP11/BJ11-1,"") -> 0.27967015 | BQ21: =CHOOSE(MATCH($BV$2,{"Bull","Base","Bear"},0),CD12,CE12,CF12) -> 0.18 | BR21: =CHOOSE(MATCH($BV$2,{"Bull","Base","Bear"},0),CD13,CE13,CF13) -> 0.06 | BS21: =CHOOSE(MATCH($BV$2,{"Bull","Base","Bear"},0),CD14,CE14,CF14) -> 0.05 | BT21: =CHOOSE(MATCH($BV$2,{"Bull","Base","Bear"},0),CD15,CE15,CF15) -> 0.04 | BU21: =CHOOSE(MATCH($BV$2,{"Bull","Base","Bear"},0),CD16,CE16,CF16) -> 0.04 | BV21: Rev growth: 15% in 2026 (full-year Schenker carryover + 3% organic) tapering to 4-6% by 2027-30. Per CMD slide 142: ~3% market growth + share gains. A&S was Schenker's 3rd-largest segment so partial-year 2025 (8mo) becomes full-year 2026. | CC21: 2028E | CD21: 0.05 | CE21: 0.04 | CF21: 0.01
B22: Gross profit y/y % | N22: =IFERROR(N15/H15-1,"") | T22: =IFERROR(T15/N15-1,"") | Z22: =IFERROR(Z15/T15-1,"") -> 0.065978664 | AF22: =IFERROR(AF15/Z15-1,"") -> 0.36157946 | AL22: =IFERROR(AL15/AF15-1,"") -> 0.3508828 | AR22: =IFERROR(AR15/AL15-1,"") -> 0.40570111 | AX22: =IFERROR(AX15/AR15-1,"") -> 0.45668728 | BD22: =IFERROR(BD15/AX15-1,"") -> -0.24994224 | BJ22: =IFERROR(BJ15/BD15-1,"") -> -0.048093955 | BP22: =IFERROR(BP15/BJ15-1,"") -> 0.29547079 | BQ22: =IFERROR(BQ15/BP15-1,"n/a") -> 0.19485599 | BR22: =IFERROR(BR15/BQ15-1,"n/a") -> 0.081632653 | BS22: =IFERROR(BS15/BR15-1,"n/a") -> 0.071 | BT22: =IFERROR(BT15/BS15-1,"n/a") -> 0.04 | BU22: =IFERROR(BU15/BT15-1,"n/a") -> 0.04 | CC22: 2029E | CD22: 0.04 | CE22: 0.03 | CF22: 0.01
B23: EBITDA before special items y/y % | N23: =IFERROR(N18/H18-1,"") | T23: =IFERROR(T18/N18-1,"") | Z23: =IFERROR(Z18/T18-1,"") -> 0.13279376 | AF23: =IFERROR(AF18/Z18-1,"") -> 0.36464673 | AL23: =IFERROR(AL18/AF18-1,"") -> 0.54954431 | AR23: =IFERROR(AR18/AL18-1,"") -> 0.72756851 | AX23: =IFERROR(AX18/AR18-1,"") -> 0.58703368 | BD23: =IFERROR(BD18/AX18-1,"") -> -0.3373043 | BJ23: =IFERROR(BJ18/BD18-1,"") -> -0.10159102 | BP23: =IFERROR(BP18/BJ18-1,"") -> 0.13165696 | BQ23: =IFERROR(BQ18/BP18-1,"n/a") -> 0.21678933 | BR23: =IFERROR(BR18/BQ18-1,"n/a") -> 0.15217391 | BS23: =IFERROR(BS18/BR18-1,"n/a") -> 0.134 | BT23: =IFERROR(BT18/BS18-1,"n/a") -> 0.070814815 | BU23: =IFERROR(BU18/BT18-1,"n/a") -> 0.062446043 | CC23: 2030E | CD23: 0.04 | CE23: 0.03 | CF23: 0.01
B24: EBIT before special items y/y % | N24: =IFERROR(N20/H20-1,"") -> 0.11440458 | T24: =IFERROR(T20/N20-1,"") -> 0.50489967 | Z24: =IFERROR(Z20/T20-1,"") -> 0.14511628 | AF24: =IFERROR(AF20/Z20-1,"") -> 0.22014622 | AL24: =IFERROR(AL20/AF20-1,"") -> 0.55925433 | AR24: =IFERROR(AR20/AL20-1,"") -> 0.81725021 | AX24: =IFERROR(AX20/AR20-1,"") -> 0.61795113 | BD24: =IFERROR(BD20/AX20-1,"") -> -0.35313196 | BJ24: =IFERROR(BJ20/BD20-1,"") -> -0.11037941 | BP24: =IFERROR(BP20/BJ20-1,"") -> 0.11507402 | BQ24: =IFERROR(BQ20/BP20-1,"n/a") -> 0.20179617 | BR24: =IFERROR(BR20/BQ20-1,"n/a") -> 0.16392157 | BS24: =IFERROR(BS20/BR20-1,"n/a") -> 0.1484375 | BT24: =IFERROR(BT20/BS20-1,"n/a") -> 0.073959184 | BU24: =IFERROR(BU20/BT20-1,"n/a") -> 0.068774704
B25: GP % | H25: =IFERROR(H15/H11,"") | I25: =IFERROR(I15/I11,"") | J25: =IFERROR(J15/J11,"") | K25: =IFERROR(K15/K11,"") | L25: =IFERROR(L15/L11,"") | M25: =IFERROR(M15/M11,"") | N25: =IFERROR(N15/N11,"") | O25: =IFERROR(O15/O11,"") | ... BP25: =IFERROR(BP15/BP11,"") -> 0.24080828 | BQ25: 0.245 | BR25: 0.25 | BS25: 0.255 | BT25: 0.255 | BU25: 0.255 | BV25: GP margin: 24.5% in 2026 expanding to 25.5% by 2030. CMD slide 143 guides 'stable yields including value-added services'. Slight expansion reflects mix shift toward higher-margin VAS (40% of GP from VAS per CMD slide 101) as Schenker's lower-VAS business is integrated. | BX25: =IFERROR(AVERAGE(BQ25,BR25,BS25,BT25,BU25),"n/m") -> 0.252 | BY25: =IFERROR(AVERAGE(AR25,AX25,BD25,BJ25,BP25),"n/m") -> 0.22829976 | BZ25: =IFERROR(AVERAGE(N25,T25,Z25,AF25,AL25,AR25,AX25,BD25,BJ25,BP25),"n/m") -> 0.235889 | CC25: CL_revGrowth
B26: EBITDA % | H26: =IFERROR(H18/H11,"") | I26: =IFERROR(I18/I11,"") | J26: =IFERROR(J18/J11,"") | K26: =IFERROR(K18/K11,"") | L26: =IFERROR(L18/L11,"") | M26: =IFERROR(M18/M11,"") | N26: =IFERROR(N18/N11,"") | O26: =IFERROR(O18/O11,"") | ... BP26: =IFERROR(BP18/BP11,"") -> 0.11099498 | BQ26: =IFERROR(BQ18/BQ11,"n/a") -> 0.1185567 | BR26: =IFERROR(BR18/BR11,"n/a") -> 0.12886598 | BS26: =IFERROR(BS18/BS11,"n/a") -> 0.13917526 | BT26: =IFERROR(BT18/BT11,"n/a") -> 0.14329897 | BU26: =IFERROR(BU18/BU11,"n/a") -> 0.14639175 | CC26: 2026E | CD26: 0.2 | CE26: 0.18 | CF26: 0.05
B27: EBIT % | H27: =IFERROR(H20/H11,"") -> 0.08867881 | I27: =IFERROR(I20/I11,"") | J27: =IFERROR(J20/J11,"") | K27: =IFERROR(K20/K11,"") | L27: =IFERROR(L20/L11,"") | M27: =IFERROR(M20/M11,"") | N27: =IFERROR(N20/N11,"") -> 0.066760125 | O27: =IFERROR(O20/O11,"") | ... BP27: =IFERROR(BP20/BP11,"") -> 0.099675918 | BQ27: =IFERROR(BQ20/BQ11,"n/a") -> 0.10515464 | BR27: =IFERROR(BR20/BR11,"n/a") -> 0.11546392 | BS27: =IFERROR(BS20/BS11,"n/a") -> 0.12628866 | BT27: =IFERROR(BT20/BT11,"n/a") -> 0.13041237 | BU27: =IFERROR(BU20/BU11,"n/a") -> 0.13402062 | BX27: =IFERROR(AVERAGE(BQ27,BR27,BS27,BT27,BU27),"n/m") -> 0.12226804 | BY27: =IFERROR(AVERAGE(AR27,AX27,BD27,BJ27,BP27),"n/m") -> 0.11513384 | BZ27: =IFERROR(AVERAGE(N27,T27,Z27,AF27,AL27,AR27,AX27,BD27,BJ27,BP27),"n/m") -> 0.10226525 | CC27: 2027E | CD27: 0.09 | CE27: 0.07 | CF27: 0.02
B28: Incremental EBIT % (ΔEBIT / ΔRev) | N28: =IFERROR((N20-H20)/(N11-H11),"") -> 0.02112338 | T28: =IFERROR((T20-N20)/(T11-N11),"") -> 0.43506232 | Z28: =IFERROR((Z20-T20)/(Z11-T11),"") -> 0.26545661 | AF28: =IFERROR((AF20-Z20)/(AF11-Z11),"") -> 0.057346406 | AL28: =IFERROR((AL20-AF20)/(AL11-AF11),"") -> 0.11197512 | AR28: =IFERROR((AR20-AL20)/(AR11-AL11),"") -> 0.099227539 | AX28: =IFERROR((AX20-AR20)/(AX11-AR11),"") -> 0.1879959 | BD28: =IFERROR((BD20-AX20)/(BD11-AX11),"") -> 0.090699988 | BJ28: =IFERROR((BJ20-BD20)/(BJ11-BD11),"") -> -0.12839485 | BP28: =IFERROR((BP20-BJ20)/(BP11-BJ11),"") -> 0.047066919 | BQ28: =IFERROR((BQ20-BP20)/(BQ11-BP11),"n/a") -> 0.14451872 | BR28: =IFERROR((BR20-BQ20)/(BR11-BQ11),"n/a") -> 0.28728522 | BS28: =IFERROR((BS20-BR20)/(BS11-BR11),"n/a") -> 0.34278351 | BT28: =IFERROR((BT20-BS20)/(BT11-BS11),"n/a") -> 0.23350515 | BU28: =IFERROR((BU20-BT20)/(BU11-BT11),"n/a") -> 0.2242268 | CC28: 2028E | CD28: 0.07 | CE28: 0.06 | CF28: 0.02
B29: EBIT / GP | H29: =IFERROR(H20/H15,"") | I29: =IFERROR(I20/I15,"") -> 0.22056473 | J29: =IFERROR(J20/J15,"") -> 0.23136915 | K29: =IFERROR(K20/K15,"") -> 0.2265233 | L29: =IFERROR(L20/L15,"") -> 0.29486576 | M29: =IFERROR(M20/M15,"") -> 0.28029557 | N29: =IFERROR(N20/N15,"") | O29: =IFERROR(O20/O15,"") | ... BU29: =IFERROR(BU20/BU15,"") -> 0.50980392 | BV29: EBIT/GP (Conversion Ratio): 45% → 50% → 53% → 54% → 55%. Hits DSV's 2030 target of >55% (CMD slide 143). FRONT-LOADED — Schenker synergies hit hardest 2026-27 per CMD slide 136 (55% integration done end-26, 100% end-27, full DKK 9bn impact 2027). | BX29: =IFERROR(AVERAGE(BQ29,BR29,BS29,BT29,BU29),"n/m") -> 0.47012021 | BY29: =IFERROR(AVERAGE(AR29,AX29,BD29,BJ29,BP29),"n/m") -> 0.50863454 | BZ29: =IFERROR(AVERAGE(N29,T29,Z29,AF29,AL29,AR29,AX29,BD29,BJ29,BP29),"n/m") -> 0.45492851 | CC29: 2029E | CD29: 0.06 | CE29: 0.05 | CF29: 0.02
B30: Operating metrics — Air & Sea | CC30: 2030E | CD30: 0.06 | CE30: 0.05 | CF30: 0.02
B31: Sea freight — TEU shipped ('000) | Z31: 1442 | AF31: 1907 | AL31: 2205 | AR31: 2494 | AX31: 2665 | BD31: 2519 | BJ31: 2686 | BP31: 3695 | BQ31: =BP31*(1+CHOOSE(MATCH($BV$2,{"Bull","Base","Bear"},0),CD68,CE68,CF68)) -> 4249.25 | BR31: =BQ31*(1+CHOOSE(MATCH($BV$2,{"Bull","Base","Bear"},0),CD69,CE69,CF69)) -> 4355.4812 | BS31: =BR31*(1+CHOOSE(MATCH($BV$2,{"Bull","Base","Bear"},0),CD70,CE70,CF70)) -> 4464.3683 | BT31: =BS31*(1+CHOOSE(MATCH($BV$2,{"Bull","Base","Bear"},0),CD71,CE71,CF71)) -> 4575.9775 | BU31: =BT31*(1+CHOOSE(MATCH($BV$2,{"Bull","Base","Bear"},0),CD72,CE72,CF72)) -> 4690.3769
B32: Air freight — tonnes shipped ('000) | Z32: 689 | AF32: 1071 | AL32: 1272 | AR32: 1511 | AX32: 1558 | BD32: 1306 | BJ32: 1398 | BP32: 2013 | BQ32: =BP32*(1+CHOOSE(MATCH($BV$2,{"Bull","Base","Bear"},0),CD82,CE82,CF82)) -> 2314.95 | BR32: =BQ32*(1+CHOOSE(MATCH($BV$2,{"Bull","Base","Bear"},0),CD83,CE83,CF83)) -> 2384.3985 | BS32: =BR32*(1+CHOOSE(MATCH($BV$2,{"Bull","Base","Bear"},0),CD84,CE84,CF84)) -> 2455.9305 | BT32: =BS32*(1+CHOOSE(MATCH($BV$2,{"Bull","Base","Bear"},0),CD85,CE85,CF85)) -> 2529.6084 | BU32: =BT32*(1+CHOOSE(MATCH($BV$2,{"Bull","Base","Bear"},0),CD86,CE86,CF86)) -> 2605.4966 | CC32: AS_convRatio
B33: Sea revenue per TEU (DKK) | H33: =IFERROR(H13*1000/(H31+H32),"n/a") -> n/a | N33: =IFERROR(N13*1000/(N31+N32),"n/a") -> n/a | T33: =IFERROR(T13*1000/(T31+T32),"n/a") -> n/a | Z33: =IFERROR(Z13*1000/(Z31+Z32),"n/a") -> 17349.601 | AF33: =IFERROR(AF13*1000/(AF31+AF32),"n/a") -> 17176.293 | AL33: =IFERROR(AL13*1000/(AL31+AL32),"n/a") -> 21193.27 | AR33: =IFERROR(AR13*1000/(AR31+AR32),"n/a") -> 32934.082 | AX33: =IFERROR(AX13*1000/(AX31+AX32),"n/a") -> 41304.996 | BD33: =IFERROR(BD13*1000/(BD31+BD32),"n/a") -> 24306.405 | BJ33: =IFERROR(BJ13*1000/(BJ31+BJ32),"n/a") -> 25586.68 | BP33: 16738 | BQ33: =BP33*(1+CHOOSE(MATCH($BV$2,{"Bull","Base","Bear"},0),CD75,CE75,CF75)) -> 16235.86 | BR33: =BQ33*(1+CHOOSE(MATCH($BV$2,{"Bull","Base","Bear"},0),CD76,CE76,CF76)) -> 16073.501 | BS33: =BR33*(1+CHOOSE(MATCH($BV$2,{"Bull","Base","Bear"},0),CD77,CE77,CF77)) -> 16073.501 | BT33: =BS33*(1+CHOOSE(MATCH($BV$2,{"Bull","Base","Bear"},0),CD78,CE78,CF78)) -> 16073.501 | BU33: =BT33*(1+CHOOSE(MATCH($BV$2,{"Bull","Base","Bear"},0),CD79,CE79,CF79)) -> 16073.501 | CC33: 2026E | CD33: 0.48 | CE33: 0.45 | CF33: 0.42
B34: Air revenue per tonne (DKK) | H34: =IFERROR(H15*1000/(H31+H32),"n/a") -> n/a | N34: =IFERROR(N15*1000/(N31+N32),"n/a") -> n/a | T34: =IFERROR(T15*1000/(T31+T32),"n/a") -> n/a | Z34: =IFERROR(Z15*1000/(Z31+Z32),"n/a") -> 4313.9371 | AF34: =IFERROR(AF15*1000/(AF31+AF32),"n/a") -> 4203.1565 | AL34: =IFERROR(AL15*1000/(AL31+AL32),"n/a") -> 4863.1004 | AR34: =IFERROR(AR15*1000/(AR31+AR32),"n/a") -> 5934.8315 | AX34: =IFERROR(AX15*1000/(AX31+AX32),"n/a") -> 8198.9107 | BD34: =IFERROR(BD15*1000/(BD31+BD32),"n/a") -> 6789.5425 | BJ34: =IFERROR(BJ15*1000/(BJ31+BJ32),"n/a") -> 6053.1342 | BP34: 38620 | BQ34: =BP34*(1+CHOOSE(MATCH($BV$2,{"Bull","Base","Bear"},0),CD89,CE89,CF89)) -> 37847.6 | BR34: =BQ34*(1+CHOOSE(MATCH($BV$2,{"Bull","Base","Bear"},0),CD90,CE90,CF90)) -> 37847.6 | BS34: =BR34*(1+CHOOSE(MATCH($BV$2,{"Bull","Base","Bear"},0),CD91,CE91,CF91)) -> 38226.076 | BT34: =BS34*(1+CHOOSE(MATCH($BV$2,{"Bull","Base","Bear"},0),CD92,CE92,CF92)) -> 38608.337 | BU34: =BT34*(1+CHOOSE(MATCH($BV$2,{"Bull","Base","Bear"},0),CD93,CE93,CF93)) -> 38994.42 | CC34: 2027E | CD34: 0.53 | CE34: 0.5 | CF34: 0.45
B35: Implied A&S revenue check (Sea + Air) | H35: =IFERROR(H20*1000/(H31+H32),"n/a") -> n/a | N35: =IFERROR(N20*1000/(N31+N32),"n/a") -> n/a | T35: =IFERROR(T20*1000/(T31+T32),"n/a") -> n/a | Z35: =IFERROR(Z20*1000/(Z31+Z32),"n/a") -> 1732.9892 | AF35: =IFERROR(AF20*1000/(AF31+AF32),"n/a") -> 1513.096 | AL35: =IFERROR(AL20*1000/(AL31+AL32),"n/a") -> 2020.7075 | AR35: =IFERROR(AR20*1000/(AR31+AR32),"n/a") -> 3188.015 | AX35: =IFERROR(AX20*1000/(AX31+AX32),"n/a") -> 4891.7831 | BD35: =IFERROR(BD20*1000/(BD31+BD32),"n/a") -> 3493.5948 | BJ35: =IFERROR(BJ20*1000/(BJ31+BJ32),"n/a") -> 2910.8717 | BP35: =BP31*BP33/1000+BP32*BP34/1000 -> 139588.97 | BQ35: =BQ31*BQ33/1000+BQ32*BQ34/1000 -> 156605.53 | BR35: =BR31*BR33/1000+BR32*BR34/1000 -> 160251.59 | BS35: =BS31*BS33/1000+BS32*BS34/1000 -> 165638.61 | BT35: =BT31*BT33/1000+BT32*BT34/1000 -> 171215.95 | BU35: =BU31*BU33/1000+BU32*BU34/1000 -> 176990.61 | CC35: 2028E | CD35: 0.56 | CE35: 0.53 | CF35: 0.48
B36: % of Revenue — Air & Sea | BV36: % OF REVENUE drivers — hardcoded inputs that drive cost structure of forecast P&L | CC36: 2029E | CD36: 0.58 | CE36: 0.54 | CF36: 0.5
B37: Intersegment revenue % of Rev | H37: =IFERROR(H12/H11,"n/a") -> -0.018814849 | N37: =IFERROR(N12/N11,"n/a") -> -0.022305296 | T37: =IFERROR(T12/T11,"n/a") -> 0.017839072 | Z37: =IFERROR(Z12/Z11,"n/a") -> 0.017111417 | AF37: =IFERROR(AF12/AF11,"n/a") -> 0.012349833 | AL37: =IFERROR(AL12/AL11,"n/a") -> 0.0089960565 | AR37: =IFERROR(AR12/AR11,"n/a") -> 0.0076547567 | AX37: =IFERROR(AX12/AX11,"n/a") -> 0.0090415809 | BD37: =IFERROR(BD12/BD11,"n/a") -> 0.005776845 | BJ37: =IFERROR(BJ12/BJ11,"n/a") -> 0.0054846718 | BP37: =IFERROR(BP12/BP11,"n/a") -> 0.032551075 | BQ37: 0.03 | BR37: 0.03 | BS37: 0.03 | BT37: 0.03 | BU37: 0.03 | BV37: Intersegment ~3% stable (held flat at recent historical avg). Mostly Air & Sea acting as sub-contractor to Road on multi-modal shipments. | CC37: 2030E | CD37: 0.6 | CE37: 0.55 | CF37: 0.51
B38: Direct costs % of Rev | H38: =IFERROR(H14/H11,"n/a") -> n/a | N38: =IFERROR(N14/N11,"n/a") -> n/a | T38: =IFERROR(T14/T11,"n/a") -> 0.76849683 | Z38: =IFERROR(Z14/Z11,"n/a") -> 0.76420908 | AF38: =IFERROR(AF14/AF11,"n/a") -> 0.7646209 | AL38: =IFERROR(AL14/AL11,"n/a") -> 0.77746741 | AR38: =IFERROR(AR14/AR11,"n/a") -> 0.82607201 | AX38: =IFERROR(AX14/AX11,"n/a") -> 0.80875003 | BD38: =IFERROR(BD14/BD11,"n/a") -> 0.72483178 | BJ38: =IFERROR(BJ14/BJ11,"n/a") -> 0.76761349 | BP38: =IFERROR(BP14/BP11,"n/a") -> 0.75445707 | BQ38: 0.755 | BR38: 0.75 | BS38: 0.745 | BT38: 0.745 | BU38: 0.745 | BV38: Direct costs = carrier/space costs passed through. Inverse of GP%: 75.5% → 74.5% as GP margin expands modestly.
B39: Other external costs % of Rev | H39: =IFERROR(H16/H11,"n/a") -> n/a | N39: =IFERROR(N16/N11,"n/a") -> n/a | T39: =IFERROR(T16/T11,"n/a") -> 0.05198485 | Z39: =IFERROR(Z16/Z11,"n/a") -> 0.051004127 | AF39: =IFERROR(AF16/AF11,"n/a") -> 0.044867101 | AL39: =IFERROR(AL16/AL11,"n/a") -> 0.039297842 | AR39: =IFERROR(AR16/AR11,"n/a") -> 0.025714482 | AX39: =IFERROR(AX16/AX11,"n/a") -> 0.024550524 | BD39: =IFERROR(BD16/BD11,"n/a") -> 0.038663753 | BJ39: =IFERROR(BJ16/BJ11,"n/a") -> 0.035910167 | BP39: =IFERROR(BP16/BP11,"n/a") -> 0.03990245 | BQ39: 0.04 | BR39: 0.038 | BS39: 0.036 | BT39: 0.034 | BU39: 0.033 | BV39: Other ext costs: 4.0% → 3.3%. Productivity gains from AI/tech (DKK ~9bn group productivity savings by 2030 per CMD slide 147) plus office/IT consolidation post-Schenker. | CC39: Road_convRatio
B40: Staff costs % of Rev | H40: =IFERROR(H17/H11,"n/a") -> n/a | N40: =IFERROR(N17/N11,"n/a") -> n/a | T40: =IFERROR(T17/T11,"n/a") -> 0.10090496 | Z40: =IFERROR(Z17/Z11,"n/a") -> 0.097936726 | AF40: =IFERROR(AF17/AF11,"n/a") -> 0.10079759 | AL40: =IFERROR(AL17/AL11,"n/a") -> 0.082813013 | AR40: =IFERROR(AR17/AR11,"n/a") -> 0.050405274 | AX40: =IFERROR(AX17/AX11,"n/a") -> 0.049002707 | BD40: =IFERROR(BD17/BD11,"n/a") -> 0.085213873 | BJ40: =IFERROR(BJ17/BJ11,"n/a") -> 0.076448627 | BP40: =IFERROR(BP17/BP11,"n/a") -> 0.089910846 | BQ40: 0.09 | BR40: 0.087 | BS40: 0.084 | BT40: 0.082 | BU40: 0.08 | BV40: Staff costs: 9.0% → 8.0%. Same productivity drivers as Other ext, but operating leverage stronger given staff is largest opex line. Schenker FTE reductions (combined 75k+ headcount integration) flow through here. | CC40: 2026E | CD40: 0.25 | CE40: 0.22 | CF40: 0.18
B41: Amortisation & depreciation % of Rev | H41: =IFERROR(H19/H11,"n/a") -> 0.0049804012 | N41: =IFERROR(N19/N11,"n/a") -> 0.0060436137 | T41: =IFERROR(T19/T11,"n/a") -> 0.0032092983 | Z41: =IFERROR(Z19/Z11,"n/a") -> 0.0023658872 | AF41: =IFERROR(AF19/AF11,"n/a") -> 0.012884201 | AL41: =IFERROR(AL19/AL11,"n/a") -> 0.013213386 | AR41: =IFERROR(AR19/AR11,"n/a") -> 0.0079221384 | AX41: =IFERROR(AX19/AX11,"n/a") -> 0.0072367355 | BD41: =IFERROR(BD19/BD11,"n/a") -> 0.012505679 | BJ41: =IFERROR(BJ19/BJ11,"n/a") -> 0.011123299 | BP41: =IFERROR(BP19/BP11,"n/a") -> 0.011319062 | BQ41: 0.013 | BR41: 0.013 | BS41: 0.0125 | BT41: 0.0125 | BU41: 0.012 | BV41: A&D: 3.5% → 3.3%. A&S is asset-light — D&A largely RoU lease amortisation on warehouses and office space. Held roughly stable. | CC41: 2027E | CD41: 0.3 | CE41: 0.28 | CF41: 0.22
CC42: 2028E | CD42: 0.33 | CE42: 0.31 | CF42: 0.24
CC43: 2029E | CD43: 0.35 | CE43: 0.33 | CF43: 0.25
B44: Road | BV44: ROAD — modelling logic | CC44: 2030E | CD44: 0.38 | CE44: 0.35 | CF44: 0.25
B45: Revenue | H45: 24718 | N45: 28323 | T45: 29232 | Z45: 29688 | AF45: 30042 | AL45: 28410 | AR45: 33077 | AX45: 38746 | BD45: 35509 | BJ45: 37740 | BP45: 72017 | BQ45: =BQ47-BQ46 -> 77188.203 | BR45: =BR47-BR46 -> 80275.731 | BS45: =BS47-BS46 -> 83486.76 | BT45: =BT47-BT46 -> 85991.363 | BU45: =BU47-BU46 -> 88571.104
B46: Intersegment revenue | H46: -1018 | N46: -1189 | T46: 1395 | Z46: 1555 | AF46: 1579 | AL46: 1985 | AR46: 2339 | AX46: 2761 | BD46: 2646 | BJ46: 2767 | BP46: 5960 | BQ46: =BQ47*BQ71 -> 2387.264 | BR46: =BR47*BR71 -> 2482.7546 | BS46: =BS47*BS71 -> 2582.0647 | BT46: =BT47*BT71 -> 2659.5267 | BU46: =BU47*BU71 -> 2739.3125 | CC46: CL_convRatio
B47: Divisional revenue | C47: 6122 | D47: 6298 | E47: 12420 | F47: 6044 | G47: 6254 | H47: 23700 | I47: 6688 | J47: 7368 | K47: 14056 | L47: 7111 | M47: 7156 | N47: 27134 | T47: 30627 | Z47: 31243 | AF47: 31621 | AG47: 7921 | AH47: 6987 | AI47: 14908 | AJ47: 7521 | AK47: 7966 | AL47: 30395 | AM47: 8056 | AN47: 8663 | AO47: 16719 | AP47: 8783 | AQ47: 9914 | AR47: 35416 | AS47: 10188 | AT47: 10835 | AU47: 21023 | AV47: 10406 | AW47: 10078 | AX47: 41507 | AY47: 10094 | AZ47: 9650 | BA47: 19744 | BB47: 9036 | BC47: 9375 | BD47: 38155 | BE47: 10425 | BF47: 10561 | BG47: 20986 | BH47: 9967 | BI47: 9554 | BJ47: 40507 | BK47: 10164 | BL47: 20674 | BM47: 30838 | BN47: 23418 | BP47: 72341.333 | BQ47: =BP47*(1+BQ55) -> 79575.467 | BR47: =BQ47*(1+BR55) -> 82758.485 | BS47: =BR47*(1+BS55) -> 86068.825 | BT47: =BS47*(1+BT55) -> 88650.889 | BU47: =BT47*(1+BU55) -> 91310.416 | BX47: =IFERROR((BU47/BP47)^(1/5)-1,"n/m") -> 0.047675439 | BY47: =IFERROR((BP47/AL47)^(1/5)-1,"n/m") -> 0.18936971 | BZ47: =IFERROR((BP47/H47)^(1/10)-1,"n/m") -> 0.11805667 | CC47: 2026E | CD47: 0.26 | CE47: 0.23 | CF47: 0.2
B48: Direct costs | C48: 4990 | D48: 5115 | E48: 10105 | F48: 4966 | G48: 5150 | H48: n/a | I48: 5431 | J48: 6009 | K48: 11440 | L48: 5864 | M48: 5925 | N48: n/a | T48: 25340 | Z48: 25935 | AF48: 25465 | AG48: 6386 | AH48: 5556 | AI48: 11942 | AJ48: 5936 | AK48: 6379 | AL48: 24257 | AM48: 6399 | AN48: 6895 | AO48: 13294 | AP48: 7038 | AQ48: 7989 | AR48: 28321 | AS48: 8250 | AT48: 8761 | AU48: 17011 | AV48: 8417 | AW48: 8168 | AX48: 33596 | AY48: 8118 | AZ48: 7627 | BA48: 15745 | BB48: 7112 | BC48: 7438 | BD48: 30295 | BE48: 8461 | BF48: 8500 | BG48: 16961 | BH48: 8033 | BI48: 7803 | BJ48: 32797 | BK48: 8208 | BL48: 16418 | BM48: 24626 | BN48: 18397 | BP48: 57364 | BQ48: =BQ47*BQ72 -> 62466.741 | BR48: =BR47*BR72 -> 64717.136 | BS48: =BS47*BS72 -> 67133.683 | BT48: =BT47*BT72 -> 69147.694 | BU48: =BU47*BU72 -> 71222.125 | CC48: 2027E | CD48: 0.3 | CE48: 0.27 | CF48: 0.22
B49: Gross profit | C49: 1132 | D49: 1183 | E49: 2315 | F49: 1078 | G49: 1104 | H49: n/a | I49: 1257 | J49: 1359 | K49: 2616 | L49: 1247 | M49: 1231 | N49: n/a | T49: =T47-T48 -> 5287 | U49: =U47-U48 -> 0 | V49: =V47-V48 -> 0 | W49: =W47-W48 -> 0 | X49: =X47-X48 -> 0 | Y49: =Y47-Y48 -> 0 | Z49: =Z47-Z48 -> 5308 | AA49: =AA47-AA48 -> 0 | ... BP49: =BP47-BP48 -> 14977.333 | BQ49: =BQ47*BQ59 -> 17108.725 | BR49: =BR47*BR59 -> 18041.35 | BS49: =BS47*BS59 -> 18935.141 | BT49: =BT47*BT59 -> 19503.196 | BU49: =BU47*BU59 -> 20088.292 | BX49: =IFERROR((BU49/BP49)^(1/5)-1,"n/m") -> 0.060478093 | BY49: =IFERROR((BP49/AL49)^(1/5)-1,"n/m") -> 0.19531267 | BZ49: =IFERROR((BP49/H49)^(1/10)-1,"n/m") -> n/m | CC49: 2028E | CD49: 0.32 | CE49: 0.3 | CF49: 0.24
B50: Other external costs | C50: 274 | D50: 273 | E50: 547 | F50: 238 | G50: 264 | H50: n/a | I50: 332 | J50: 314 | K50: 646 | L50: 304 | M50: 274 | N50: n/a | T50: 1269 | Z50: 1326 | AF50: 1060 | AG50: 287 | AH50: 242 | AI50: 529 | AJ50: 251 | AK50: 241 | AL50: 1021 | AM50: 258 | AN50: 272 | AO50: 530 | AP50: 282 | AQ50: 310 | AR50: 1122 | AS50: 341 | AT50: 373 | AU50: 714 | AV50: 342 | AW50: 369 | AX50: 1425 | AY50: 363 | AZ50: 367 | BA50: 730 | BB50: 354 | BC50: 344 | BD50: 1428 | BE50: 324 | BF50: 319 | BG50: 643 | BH50: 307 | BI50: 257 | BJ50: 1207 | BK50: 312 | BL50: 974 | BM50: 1286 | BN50: 1281 | BP50: 3422.6667 | BQ50: =BQ47*BQ73 -> 1591.5093 | BR50: =BR47*BR73 -> 1655.1697 | BS50: =BS47*BS73 -> 1721.3765 | BT50: =BT47*BT73 -> 1773.0178 | BU50: =BU47*BU73 -> 1826.2083 | CC50: 2029E | CD50: 0.35 | CE50: 0.33 | CF50: 0.25
B51: Staff costs | C51: 606 | D51: 619 | E51: 1225 | F51: 568 | G51: 611 | H51: n/a | I51: 670 | J51: 691 | K51: 1361 | L51: 612 | M51: 689 | N51: n/a | T51: 2672 | Z51: 2706 | AF51: 2864 | AG51: 757 | AH51: 686 | AI51: 1443 | AJ51: 650 | AK51: 705.7 | AL51: 2799 | AM51: 742 | AN51: 779 | AO51: 1521 | AP51: 761 | AQ51: 867 | AR51: 3149 | AS51: 871 | AT51: 904 | AU51: 1775 | AV51: 895 | AW51: 873 | AX51: 3543 | AY51: 902 | AZ51: 918 | BA51: 1820 | BB51: 838 | BC51: 916 | BD51: 3574 | BE51: 937 | BF51: 963 | BG51: 1900 | BH51: 881 | BI51: 919 | BJ51: 3700 | BK51: 975 | BL51: 2267 | BM51: 3242 | BN51: 2416 | BP51: 7544 | BQ51: =BQ47*BQ74 -> 11140.565 | BR51: =BR47*BR74 -> 11172.396 | BS51: =BS47*BS74 -> 11188.947 | BT51: =BT47*BT74 -> 11347.314 | BU51: =BU47*BU74 -> 11413.802 | CC51: 2030E | CD51: 0.37 | CE51: 0.35 | CF51: 0.25
B52: EBITDA before special items | C52: 252 | D52: 291 | E52: 543 | F52: 272 | G52: 229 | H52: n/a | I52: 255 | J52: 354 | K52: 609 | L52: 331 | M52: 268 | N52: n/a | T52: =T49-T50-T51 -> 1346 | U52: =U49-U50-U51 -> 0 | V52: =V49-V50-V51 -> 0 | W52: =W49-W50-W51 -> 0 | X52: =X49-X50-X51 -> 0 | Y52: =Y49-Y50-Y51 -> 0 | Z52: =Z49-Z50-Z51 -> 1276 | AA52: =AA49-AA50-AA51 -> 0 | ... BU52: =BU49-BU50-BU51 -> 6848.2812 | BX52: =IFERROR((BU52/BP52)^(1/5)-1,"n/m") -> 0.11294321 | BY52: =IFERROR((BP52/AL52)^(1/5)-1,"n/m") -> 0.11588805 | BZ52: =IFERROR((BP52/H52)^(1/10)-1,"n/m") -> n/m
B53: Amortisation and depreciation | C53: 32 | D53: 32 | E53: 64 | F53: 30 | G53: 32 | H53: 126 | I53: 36 | J53: 44 | K53: 80 | L53: 41 | M53: 38 | N53: 159 | T53: 145 | Z53: 129 | AF53: 981 | AG53: 232 | AH53: 240 | AI53: 472 | AJ53: 236 | AK53: 220 | AL53: 928 | AM53: 254 | AN53: 241 | AO53: 495 | AP53: 237 | AQ53: 235 | AR53: 967 | AS53: 228 | AT53: 231 | AU53: 459 | AV53: 227 | AW53: 217 | AX53: 903 | AY53: 216 | AZ53: 213 | BA53: 429 | BB53: 210 | BC53: 210 | BD53: 849 | BE53: 213 | BF53: 230 | BG53: 443 | BH53: 232 | BI53: 264 | BJ53: 939 | BK53: 261 | BL53: 495 | BM53: 756 | BN53: 526 | BP53: 1709.3333 | BQ53: =BQ47*BQ75 -> 1989.3867 | BR53: =BR47*BR75 -> 2068.9621 | BS53: =BS47*BS75 -> 2151.7206 | BT53: =BT47*BT75 -> 2216.2722 | BU53: =BU47*BU75 -> 2282.7604 | CC53: Special_items
B54: EBIT before special items | C54: 220 | D54: 259 | E54: 479 | F54: 242 | G54: 197 | H54: 918 | I54: 219 | J54: 310 | K54: 529 | L54: 290 | M54: 230 | N54: 1049 | T54: =T52-T53 -> 1201 | U54: =U52-U53 -> 0 | V54: =V52-V53 -> 0 | W54: =W52-W53 -> 0 | X54: =X52-X53 -> 0 | Y54: =Y52-Y53 -> 0 | Z54: =Z52-Z53 -> 1147 | AA54: =AA52-AA53 -> 0 | ... BU54: =BU52-BU53 -> 4565.5208 | BX54: =IFERROR((BU54/BP54)^(1/5)-1,"n/m") -> 0.14683822 | BY54: =IFERROR((BP54/AL54)^(1/5)-1,"n/m") -> 0.10609632 | BZ54: =IFERROR((BP54/H54)^(1/10)-1,"n/m") -> 0.096260295 | CC54: 2026E | CD54: 2500 | CE54: 3000 | CF54: 4000
B55: Revenue y/y % | N55: =IFERROR(N45/H45-1,"") -> 0.14584513 | T55: =IFERROR(T45/N45-1,"") -> 0.032094058 | Z55: =IFERROR(Z45/T45-1,"") -> 0.015599343 | AF55: =IFERROR(AF45/Z45-1,"") -> 0.01192401 | AL55: =IFERROR(AL45/AF45-1,"") -> -0.054323946 | AR55: =IFERROR(AR45/AL45-1,"") -> 0.16427314 | AX55: =IFERROR(AX45/AR45-1,"") -> 0.17138797 | BD55: =IFERROR(BD45/AX45-1,"") -> -0.083544108 | BJ55: =IFERROR(BJ45/BD45-1,"") -> 0.062829142 | BP55: =IFERROR(BP45/BJ45-1,"") -> 0.90824059 | BQ55: =CHOOSE(MATCH($BV$2,{"Bull","Base","Bear"},0),CD19,CE19,CF19) -> 0.1 | BR55: =CHOOSE(MATCH($BV$2,{"Bull","Base","Bear"},0),CD20,CE20,CF20) -> 0.04 | BS55: =CHOOSE(MATCH($BV$2,{"Bull","Base","Bear"},0),CD21,CE21,CF21) -> 0.04 | BT55: =CHOOSE(MATCH($BV$2,{"Bull","Base","Bear"},0),CD22,CE22,CF22) -> 0.03 | BU55: =CHOOSE(MATCH($BV$2,{"Bull","Base","Bear"},0),CD23,CE23,CF23) -> 0.03 | BV55: Rev growth: 10% in 2026 (Schenker full-year carryover + 3% organic) tapering to 3-4%. Road absorbed largest Schenker contribution (2025 reported Road +93% YoY). 2026 first full year, then GDP-level growth. Per CMD slide 144: 2-3% market + share gains. | CC55: 2027E | CD55: 1500 | CE55: 2000 | CF55: 3500
B56: Gross profit y/y % | N56: =IFERROR(N49/H49-1,"") | T56: =IFERROR(T49/N49-1,"") | Z56: =IFERROR(Z49/T49-1,"") -> 0.0039720068 | AF56: =IFERROR(AF49/Z49-1,"") -> 0.15975885 | AL56: =IFERROR(AL49/AF49-1,"") -> -0.0029239766 | AR56: =IFERROR(AR49/AL49-1,"") -> 0.15591398 | AX56: =IFERROR(AX49/AR49-1,"") -> 0.11501057 | BD56: =IFERROR(BD49/AX49-1,"") -> -0.0064467198 | BJ56: =IFERROR(BJ49/BD49-1,"") -> -0.019083969 | BP56: =IFERROR(BP49/BJ49-1,"") -> 0.94258539 | BQ56: =IFERROR(BQ49/BP49-1,"n/a") -> 0.14230784 | BR56: =IFERROR(BR49/BQ49-1,"n/a") -> 0.054511628 | BS56: =IFERROR(BS49/BR49-1,"n/a") -> 0.049541284 | BT56: =IFERROR(BT49/BS49-1,"n/a") -> 0.03 | BU56: =IFERROR(BU49/BT49-1,"n/a") -> 0.03 | CC56: 2028E | CD56: 300 | CE56: 500 | CF56: 2000
B57: EBITDA before special items y/y % | N57: =IFERROR(N52/H52-1,"") | T57: =IFERROR(T52/N52-1,"") | Z57: =IFERROR(Z52/T52-1,"") -> -0.052005944 | AF57: =IFERROR(AF52/Z52-1,"") -> 0.7492163 | AL57: =IFERROR(AL52/AF52-1,"") -> 0.038530466 | AR57: =IFERROR(AR52/AL52-1,"") -> 0.21829163 | AX57: =IFERROR(AX52/AR52-1,"") -> 0.04213881 | BD57: =IFERROR(BD52/AX52-1,"") -> -0.028882093 | BJ57: =IFERROR(BJ52/BD52-1,"") -> -0.019244227 | BP57: =IFERROR(BP52/BJ52-1,"") -> 0.4308479 | BQ57: =IFERROR(BQ52/BP52-1,"n/a") -> 0.09125266 | BR57: =IFERROR(BR52/BQ52-1,"n/a") -> 0.19127273 | BS57: =IFERROR(BS52/BR52-1,"n/a") -> 0.15555556 | BT57: =IFERROR(BT52/BS52-1,"n/a") -> 0.059428571 | BU57: =IFERROR(BU52/BT52-1,"n/a") -> 0.072916667 | CC57: 2029E | CD57: 200 | CE57: 300 | CF57: 1000
B58: EBIT before special items y/y % | N58: =IFERROR(N54/H54-1,"") -> 0.14270153 | T58: =IFERROR(T54/N54-1,"") -> 0.1448999 | Z58: =IFERROR(Z54/T54-1,"") -> -0.044962531 | AF58: =IFERROR(AF54/Z54-1,"") -> 0.090671316 | AL58: =IFERROR(AL54/AF54-1,"") -> 0.11111111 | AR58: =IFERROR(AR54/AL54-1,"") -> 0.33597122 | AX58: =IFERROR(AX54/AR54-1,"") -> 0.098546042 | BD58: =IFERROR(BD54/AX54-1,"") -> -0.015196078 | BJ58: =IFERROR(BJ54/BD54-1,"") -> -0.072175212 | BP58: =IFERROR(BP54/BJ54-1,"") -> 0.23462089 | BQ58: =IFERROR(BQ54/BP54-1,"n/a") -> 0.037339513 | BR58: =IFERROR(BR54/BQ54-1,"n/a") -> 0.31733333 | BS58: =IFERROR(BS54/BR54-1,"n/a") -> 0.23157895 | BT58: =IFERROR(BT54/BS54-1,"n/a") -> 0.075777778 | BU58: =IFERROR(BU54/BT54-1,"n/a") -> 0.095744681 | CC58: 2030E | CD58: 200 | CE58: 300 | CF58: 500
B59: GP % | H59: =IFERROR(H49/H45,"") | I59: =IFERROR(I49/I45,"") | J59: =IFERROR(J49/J45,"") | K59: =IFERROR(K49/K45,"") | L59: =IFERROR(L49/L45,"") | M59: =IFERROR(M49/M45,"") | N59: =IFERROR(N49/N45,"") | O59: =IFERROR(O49/O45,"") | ... BP59: =IFERROR(BP49/BP45,"") -> 0.20796941 | BQ59: 0.215 | BR59: 0.218 | BS59: 0.22 | BT59: 0.22 | BU59: 0.22 | BV59: GP margin: 21.5% → 22.0%. Slight expansion reflects groupage mix benefit from Schenker (groupage = higher GP than FTL/LTL per 2025 AR p.29). Asset-light model preserved. | BX59: =IFERROR(AVERAGE(BQ59,BR59,BS59,BT59,BU59),"n/m") -> 0.2186 | BY59: =IFERROR(AVERAGE(AR59,AX59,BD59,BJ59,BP59),"n/m") -> 0.21045794 | BZ59: =IFERROR(AVERAGE(N59,T59,Z59,AF59,AL59,AR59,AX59,BD59,BJ59,BP59),"n/m") -> 0.20365664
B60: EBITDA % | H60: =IFERROR(H52/H45,"") | I60: =IFERROR(I52/I45,"") | J60: =IFERROR(J52/J45,"") | K60: =IFERROR(K52/K45,"") | L60: =IFERROR(L52/L45,"") | M60: =IFERROR(M52/M45,"") | N60: =IFERROR(N52/N45,"") | O60: =IFERROR(O52/O45,"") | ... BP60: =IFERROR(BP52/BP45,"") -> 0.055690555 | BQ60: =IFERROR(BQ52/BQ45,"n/a") -> 0.056701031 | BR60: =IFERROR(BR52/BR45,"n/a") -> 0.064948454 | BS60: =IFERROR(BS52/BS45,"n/a") -> 0.072164948 | BT60: =IFERROR(BT52/BT45,"n/a") -> 0.074226804 | BU60: =IFERROR(BU52/BU45,"n/a") -> 0.077319588 | CC60: Buybacks
B61: EBIT % | H61: =IFERROR(H54/H45,"") -> 0.037138927 | I61: =IFERROR(I54/I45,"") | J61: =IFERROR(J54/J45,"") | K61: =IFERROR(K54/K45,"") | L61: =IFERROR(L54/L45,"") | M61: =IFERROR(M54/M45,"") | N61: =IFERROR(N54/N45,"") -> 0.037037037 | O61: =IFERROR(O54/O45,"") | ... BP61: =IFERROR(BP54/BP45,"") -> 0.031955418 | BQ61: =IFERROR(BQ54/BQ45,"n/a") -> 0.030927835 | BR61: =IFERROR(BR54/BR45,"n/a") -> 0.039175258 | BS61: =IFERROR(BS54/BS45,"n/a") -> 0.046391753 | BT61: =IFERROR(BT54/BT45,"n/a") -> 0.048453608 | BU61: =IFERROR(BU54/BU45,"n/a") -> 0.051546392 | BX61: =IFERROR(AVERAGE(BQ61,BR61,BS61,BT61,BU61),"n/m") -> 0.043298969 | BY61: =IFERROR(AVERAGE(AR61,AX61,BD61,BJ61,BP61),"n/m") -> 0.049343103 | BZ61: =IFERROR(AVERAGE(N61,T61,Z61,AF61,AL61,AR61,AX61,BD61,BJ61,BP61),"n/m") -> 0.045404094 | CC61: 2026E | CD61: -3000 | CE61: -2000 | CF61: -1000
B62: Incremental EBIT % (ΔEBIT / ΔRev) | N62: =IFERROR((N54-H54)/(N45-H45),"") -> 0.036338419 | T62: =IFERROR((T54-N54)/(T45-N45),"") -> 0.16721672 | Z62: =IFERROR((Z54-T54)/(Z45-T45),"") -> -0.11842105 | AF62: =IFERROR((AF54-Z54)/(AF45-Z45),"") -> 0.29378531 | AL62: =IFERROR((AL54-AF54)/(AL45-AF45),"") -> -0.085171569 | AR62: =IFERROR((AR54-AL54)/(AR45-AL45),"") -> 0.10006428 | AX62: =IFERROR((AX54-AR54)/(AX45-AR45),"") -> 0.032280826 | BD62: =IFERROR((BD54-AX54)/(BD45-AX45),"") -> 0.0095767686 | BJ62: =IFERROR((BJ54-BD54)/(BJ45-BD45),"") -> -0.064993277 | BP62: =IFERROR((BP54-BJ54)/(BP45-BJ45),"") -> 0.012758798 | BQ62: =IFERROR((BQ54-BP54)/(BQ45-BP45),"n/a") -> 0.016617153 | BR62: =IFERROR((BR54-BQ54)/(BR45-BQ45),"n/a") -> 0.24536082 | BS62: =IFERROR((BS54-BR54)/(BS45-BR45),"n/a") -> 0.22680412 | BT62: =IFERROR((BT54-BS54)/(BT45-BS45),"n/a") -> 0.11718213 | BU62: =IFERROR((BU54-BT54)/(BU45-BT45),"n/a") -> 0.15463918 | CC62: 2027E | CD62: -7000 | CE62: -5000 | CF62: -2000
B63: EBIT / GP | H63: =IFERROR(H54/H49,"") | I63: =IFERROR(I54/I49,"") -> 0.17422434 | J63: =IFERROR(J54/J49,"") -> 0.2281089 | K63: =IFERROR(K54/K49,"") -> 0.20221713 | L63: =IFERROR(L54/L49,"") -> 0.23255814 | M63: =IFERROR(M54/M49,"") -> 0.18683997 | N63: =IFERROR(N54/N49,"") | O63: =IFERROR(O54/O49,"") | ... BU63: =IFERROR(BU54/BU49,"") -> 0.22727273 | BV63: EBIT/GP (Conversion Ratio): 22% → 28% → 31% → 33% → 35%. Hits DSV's 2030 target of >35% (CMD slide 144). Front-loaded synergies; STAR TMS rollout, network rightsizing, and groupage consolidation drive the structural conv ratio uplift. | BX63: =IFERROR(AVERAGE(BQ63,BR63,BS63,BT63,BU63),"n/m") -> 0.19186027 | BY63: =IFERROR(AVERAGE(AR63,AX63,BD63,BJ63,BP63),"n/m") -> 0.23412374 | BZ63: =IFERROR(AVERAGE(N63,T63,Z63,AF63,AL63,AR63,AX63,BD63,BJ63,BP63),"n/m") -> 0.22706035 | CC63: 2028E | CD63: -15000 | CE63: -10000 | CF63: -3000
B64: Operating metrics — Road | CC64: 2029E | CD64: -20000 | CE64: -15000 | CF64: -5000
B65: Number of shipments (m) | AF65: 25 | AL65: 22 | AR65: 23 | AX65: 26 | BD65: 26 | BJ65: 25 | BP65: 36 | CC65: 2030E | CD65: -25000 | CE65: -18000 | CF65: -8000
B66: Revenue per shipment (DKK) | H66: =IFERROR(H47/H65,"n/a") -> n/a | N66: =IFERROR(N47/N65,"n/a") -> n/a | T66: =IFERROR(T47/T65,"n/a") -> n/a | Z66: =IFERROR(Z47/Z65,"n/a") -> n/a | AF66: =IFERROR(AF47/AF65,"n/a") -> 1264.84 | AL66: =IFERROR(AL47/AL65,"n/a") -> 1381.5909 | AR66: =IFERROR(AR47/AR65,"n/a") -> 1539.8261 | AX66: =IFERROR(AX47/AX65,"n/a") -> 1596.4231 | BD66: =IFERROR(BD47/BD65,"n/a") -> 1467.5 | BJ66: =IFERROR(BJ47/BJ65,"n/a") -> 1620.28 | BP66: =IFERROR(BP47/BP65,"n/a") -> 2009.4815
B67: GP per shipment (DKK) | H67: =IFERROR(H49/H65,"n/a") -> n/a | N67: =IFERROR(N49/N65,"n/a") -> n/a | T67: =IFERROR(T49/T65,"n/a") -> n/a | Z67: =IFERROR(Z49/Z65,"n/a") -> n/a | AF67: =IFERROR(AF49/AF65,"n/a") -> 246.24 | AL67: =IFERROR(AL49/AL65,"n/a") -> 279 | AR67: =IFERROR(AR49/AR65,"n/a") -> 308.47826 | AX67: =IFERROR(AX49/AX65,"n/a") -> 304.26923 | BD67: =IFERROR(BD49/BD65,"n/a") -> 302.30769 | BJ67: =IFERROR(BJ49/BJ65,"n/a") -> 308.4 | BP67: =IFERROR(BP49/BP65,"n/a") -> 416.03704 | CC67: SeaTEU_growth
B68: EBIT per shipment (DKK) | H68: =IFERROR(H54/H65,"n/a") -> n/a | N68: =IFERROR(N54/N65,"n/a") -> n/a | T68: =IFERROR(T54/T65,"n/a") -> n/a | Z68: =IFERROR(Z54/Z65,"n/a") -> n/a | AF68: =IFERROR(AF54/AF65,"n/a") -> 50.04 | AL68: =IFERROR(AL54/AL65,"n/a") -> 63.181818 | AR68: =IFERROR(AR54/AR65,"n/a") -> 80.73913 | AX68: =IFERROR(AX54/AX65,"n/a") -> 78.461538 | BD68: =IFERROR(BD54/BD65,"n/a") -> 77.269231 | BJ68: =IFERROR(BJ54/BJ65,"n/a") -> 74.56 | BP68: =IFERROR(BP54/BP65,"n/a") -> 63.925926 | CC68: 2026E | CD68: 0.2 | CE68: 0.15 | CF68: 0.05
B69: Avg fleet size / leased trucks (#k) | AF69: 22 | AL69: 21 | AR69: 22 | AX69: 23 | BD69: 22 | BJ69: 21 | BP69: 30 | CC69: 2027E | CD69: 0.04 | CE69: 0.025 | CF69: 0.01
B70: % of Revenue — Road | BV70: % OF REVENUE drivers — Road cost structure | CC70: 2028E | CD70: 0.03 | CE70: 0.025 | CF70: 0.01
B71: Intersegment revenue % of Rev | H71: =IFERROR(H46/H45,"n/a") -> -0.041184562 | N71: =IFERROR(N46/N45,"n/a") -> -0.041980016 | T71: =IFERROR(T46/T45,"n/a") -> 0.047721675 | Z71: =IFERROR(Z46/Z45,"n/a") -> 0.052378065 | AF71: =IFERROR(AF46/AF45,"n/a") -> 0.05255975 | AL71: =IFERROR(AL46/AL45,"n/a") -> 0.069869764 | AR71: =IFERROR(AR46/AR45,"n/a") -> 0.070713789 | AX71: =IFERROR(AX46/AX45,"n/a") -> 0.071258969 | BD71: =IFERROR(BD46/BD45,"n/a") -> 0.07451632 | BJ71: =IFERROR(BJ46/BJ45,"n/a") -> 0.073317435 | BP71: =IFERROR(BP46/BP45,"n/a") -> 0.082758238 | BQ71: 0.03 | BR71: 0.03 | BS71: 0.03 | BT71: 0.03 | BU71: 0.03 | BV71: Intersegment ~3% stable. Internal cross-charging mostly to Solutions for warehouse-to-door movements. | CC71: 2029E | CD71: 0.03 | CE71: 0.025 | CF71: 0.01
B72: Direct costs % of Rev | H72: =IFERROR(H48/H45,"n/a") -> n/a | N72: =IFERROR(N48/N45,"n/a") -> n/a | T72: =IFERROR(T48/T45,"n/a") -> 0.86685824 | Z72: =IFERROR(Z48/Z45,"n/a") -> 0.87358529 | AF72: =IFERROR(AF48/AF45,"n/a") -> 0.84764663 | AL72: =IFERROR(AL48/AL45,"n/a") -> 0.85381908 | AR72: =IFERROR(AR48/AR45,"n/a") -> 0.85621429 | AX72: =IFERROR(AX48/AX45,"n/a") -> 0.86708305 | BD72: =IFERROR(BD48/BD45,"n/a") -> 0.85316399 | BJ72: =IFERROR(BJ48/BJ45,"n/a") -> 0.86902491 | BP72: =IFERROR(BP48/BP45,"n/a") -> 0.79653415 | BQ72: 0.785 | BR72: 0.782 | BS72: 0.78 | BT72: 0.78 | BU72: 0.78 | BV72: Direct costs = haulier fees pass-through. Inverse of GP%: 78.5% → 78.0%. Asset-light Road model means most cost is 3rd-party haulier (drivers, trucks, fuel). | CC72: 2030E | CD72: 0.03 | CE72: 0.025 | CF72: 0.01
B73: Other external costs % of Rev | H73: =IFERROR(H50/H45,"n/a") -> n/a | N73: =IFERROR(N50/N45,"n/a") -> n/a | T73: =IFERROR(T50/T45,"n/a") -> 0.04341133 | Z73: =IFERROR(Z50/Z45,"n/a") -> 0.044664511 | AF73: =IFERROR(AF50/AF45,"n/a") -> 0.035283936 | AL73: =IFERROR(AL50/AL45,"n/a") -> 0.03593805 | AR73: =IFERROR(AR50/AR45,"n/a") -> 0.033920851 | AX73: =IFERROR(AX50/AX45,"n/a") -> 0.03677799 | BD73: =IFERROR(BD50/BD45,"n/a") -> 0.040215157 | BJ73: =IFERROR(BJ50/BJ45,"n/a") -> 0.031981982 | BP73: =IFERROR(BP50/BP45,"n/a") -> 0.047525816 | BQ73: 0.02 | BR73: 0.02 | BS73: 0.02 | BT73: 0.02 | BU73: 0.02 | BV73: Other ext: 2.0% stable. Smaller line for Road — mostly IT systems, depots.
B74: Staff costs % of Rev | H74: =IFERROR(H51/H45,"n/a") -> n/a | N74: =IFERROR(N51/N45,"n/a") -> n/a | T74: =IFERROR(T51/T45,"n/a") -> 0.091406678 | Z74: =IFERROR(Z51/Z45,"n/a") -> 0.091147939 | AF74: =IFERROR(AF51/AF45,"n/a") -> 0.0953332 | AL74: =IFERROR(AL51/AL45,"n/a") -> 0.098521647 | AR74: =IFERROR(AR51/AR45,"n/a") -> 0.095202104 | AX74: =IFERROR(AX51/AX45,"n/a") -> 0.091441697 | BD74: =IFERROR(BD51/BD45,"n/a") -> 0.10065054 | BJ74: =IFERROR(BJ51/BJ45,"n/a") -> 0.098039216 | BP74: =IFERROR(BP51/BP45,"n/a") -> 0.10475304 | BQ74: 0.14 | BR74: 0.135 | BS74: 0.13 | BT74: 0.128 | BU74: 0.125 | BV74: Staff: 14.0% → 12.5%. Larger expense given Road's higher labour intensity (drivers + dispatch + sales). Schenker integration synergies + STAR TMS workflow automation drive efficiency. | CC74: SeaRate_growth
B75: Amortisation & depreciation % of Rev | H75: =IFERROR(H53/H45,"n/a") -> 0.0050974998 | N75: =IFERROR(N53/N45,"n/a") -> 0.0056138121 | T75: =IFERROR(T53/T45,"n/a") -> 0.0049603175 | Z75: =IFERROR(Z53/Z45,"n/a") -> 0.00434519 | AF75: =IFERROR(AF53/AF45,"n/a") -> 0.032654284 | AL75: =IFERROR(AL53/AL45,"n/a") -> 0.032664555 | AR75: =IFERROR(AR53/AR45,"n/a") -> 0.029234816 | AX75: =IFERROR(AX53/AX45,"n/a") -> 0.023305632 | BD75: =IFERROR(BD53/BD45,"n/a") -> 0.023909431 | BJ75: =IFERROR(BJ53/BJ45,"n/a") -> 0.024880763 | BP75: =IFERROR(BP53/BP45,"n/a") -> 0.023735137 | BQ75: 0.025 | BR75: 0.025 | BS75: 0.025 | BT75: 0.025 | BU75: 0.025 | BV75: A&D: 3.0% → 2.7%. Slight decline as DSV consolidates Schenker depot footprint (network rightsizing per 2025 AR). | CC75: 2026E | CD75: 0.1 | CE75: -0.03 | CF75: -0.2
CC76: 2027E | CD76: 0.05 | CE76: -0.01 | CF76: -0.08
CC77: 2028E | CD77: 0.02 | CE77: 0 | CF77: -0.03
B78: Solutions (renamed Contract Logistics in FY2025) | BV78: CONTRACT LOGISTICS — modelling logic | CC78: 2029E | CD78: 0.02 | CE78: 0 | CF78: -0.02
B79: Revenue | H79: 5960 | N79: 9683 | T79: 10968 | Z79: 12879 | AF79: 14046 | AL79: 13747 | AR79: 17989 | AX79: 23826 | BD79: 22482 | BJ79: 25009 | BP79: 42106 | BQ79: =BQ81-BQ80 -> 45008.724 | BR79: =BR81-BR80 -> 48159.335 | BS79: =BS81-BS80 -> 51048.895 | BT79: =BT81-BT80 -> 53601.34 | BU79: =BU81-BU80 -> 56281.407 | CC79: 2030E | CD79: 0.02 | CE79: 0 | CF79: -0.02
B80: Intersegment revenue | H80: -156 | N80: -375 | T80: 394 | Z80: 350 | AF80: 344 | AL80: 861 | AR80: 745 | AX80: 583 | BD80: 658 | BJ80: 615 | BP80: 1357 | BQ80: =BQ81*BQ105 -> 1392.0224 | BR80: =BR81*BR105 -> 1489.464 | BS80: =BS81*BS105 -> 1578.8318 | BT80: =BT81*BT105 -> 1657.7734 | BU80: =BU81*BU105 -> 1740.6621
B81: Divisional revenue | C81: 1440 | D81: 1500 | E81: 2940 | F81: 1476 | G81: 1544 | H81: 5804 | I81: 2043 | J81: 2406 | K81: 4449 | L81: 2492 | M81: 2742 | N81: 9308 | T81: 11362 | Z81: 13229 | AF81: 14390 | AG81: 3441 | AH81: 3256 | AI81: 6697 | AJ81: 3388 | AK81: 4523 | AL81: 14608 | AM81: 3609 | AN81: 3997 | AO81: 7606 | AP81: 4739 | AQ81: 6389 | AR81: 18734 | AS81: 6162 | AT81: 6182 | AU81: 12344 | AV81: 5841 | AW81: 6224 | AX81: 24409 | AY81: 5625 | AZ81: 5898 | BA81: 11523 | BB81: 5538 | BC81: 6079 | BD81: 23140 | BE81: 5989 | BF81: 6916 | BG81: 12905 | BH81: 6619 | BI81: 6100 | BJ81: 25624 | BK81: 6325 | BL81: 10054 | BM81: 16379 | BN81: 13113 | BP81: 39322.667 | BQ81: =BP81*(1+BQ89) -> 46400.747 | BR81: =BQ81*(1+BR89) -> 49648.799 | BS81: =BR81*(1+BS89) -> 52627.727 | BT81: =BS81*(1+BT89) -> 55259.113 | BU81: =BT81*(1+BU89) -> 58022.069 | BX81: =IFERROR((BU81/BP81)^(1/5)-1,"n/m") -> 0.080911282 | BY81: =IFERROR((BP81/AL81)^(1/5)-1,"n/m") -> 0.2190189 | BZ81: =IFERROR((BP81/H81)^(1/10)-1,"n/m") -> 0.21085337 | CC81: AirTon_growth
B82: Direct costs | C82: 1110 | D82: 1142 | E82: =C82+D82 -> 2252 | F82: 1117 | G82: 1171 | H82: n/a | I82: 1507 | J82: 1737 | K82: =I82+J82 -> 3244 | L82: 1808 | M82: 2015 | N82: n/a | T82: 8632 | Z82: 10194 | AF82: 9421 | AG82: 2185 | AH82: 1985 | AI82: =AG82+AH82 -> 4170 | AJ82: 2075 | AK82: 2994 | AL82: 9239 | AM82: 2261 | AN82: 2620 | AO82: =AM82+AN82 -> 4881 | AP82: 3022 | AQ82: 4178 | AR82: 12081 | AS82: 3840 | AT82: 3858 | AU82: =AS82+AT82 -> 7698 | AV82: 3516 | AW82: 3877 | AX82: 15091 | AY82: 3340 | AZ82: 3525 | BA82: =AY82+AZ82 -> 6865 | BB82: 3157 | BC82: 3608 | BD82: 13630 | BE82: 3588 | BF82: 4340 | BG82: =BE82+BF82 -> 7928 | BH82: 4032 | BI82: 3608 | BJ82: 15568 | BK82: 3747 | BL82: 5423 | BM82: =BK82+BL82 -> 9170 | BN82: 7303 | BP82: =(BK82+BL82+BN82)*4/3 -> 21964 | BQ82: =BQ81*BQ106 -> 26494.826 | BR82: =BR81*BR106 -> 28299.815 | BS82: =BS81*BS106 -> 29892.549 | BT82: =BT81*BT106 -> 31276.658 | BU82: =BU81*BU106 -> 32782.469 | CC82: 2026E | CD82: 0.2 | CE82: 0.15 | CF82: 0.05
B83: Gross profit | C83: 330 | D83: 358 | E83: =C83+D83 -> 688 | F83: 359 | G83: 373 | H83: n/a | I83: 536 | J83: 669 | K83: =I83+J83 -> 1205 | L83: 684 | M83: 727 | N83: n/a | T83: =T81-T82 -> 2730 | U83: =U81-U82 -> 0 | V83: =V81-V82 -> 0 | W83: =W81-W82 -> 0 | X83: =X81-X82 -> 0 | Y83: =Y81-Y82 -> 0 | Z83: =Z81-Z82 -> 3035 | AA83: =AA81-AA82 -> 0 | ... BP83: =BP81-BP82 -> 17358.667 | BQ83: =BQ81*BQ93 -> 19905.92 | BR83: =BR81*BR93 -> 21348.984 | BS83: =BS81*BS93 -> 22735.178 | BT83: =BT81*BT93 -> 23982.455 | BU83: =BU81*BU93 -> 25239.6 | BX83: =IFERROR((BU83/BP83)^(1/5)-1,"n/m") -> 0.077738062 | BY83: =IFERROR((BP83/AL83)^(1/5)-1,"n/m") -> 0.26451677 | BZ83: =IFERROR((BP83/H83)^(1/10)-1,"n/m") -> n/m | CC83: 2027E | CD83: 0.04 | CE83: 0.03 | CF83: 0.01
B84: Other external costs | C84: 125 | D84: 117 | E84: =C84+D84 -> 242 | F84: 113 | G84: 131 | H84: n/a | I84: 165 | J84: 192 | K84: =I84+J84 -> 357 | L84: 202 | M84: 242 | N84: n/a | T84: 884 | Z84: 955 | AF84: 1088 | AG84: 289 | AH84: 244 | AI84: =AG84+AH84 -> 533 | AJ84: 255 | AK84: 301 | AL84: 1089 | AM84: 281 | AN84: 297 | AO84: =AM84+AN84 -> 578 | AP84: 348 | AQ84: 412 | AR84: 1338 | AS84: 423 | AT84: 405 | AU84: =AS84+AT84 -> 828 | AV84: 448 | AW84: 483 | AX84: 1759 | AY84: 453 | AZ84: 420 | BA84: =AY84+AZ84 -> 873 | BB84: 453 | BC84: 456 | BD84: 1782 | BE84: 437 | BF84: 448 | BG84: =BE84+BF84 -> 885 | BH84: 467 | BI84: 442 | BJ84: 1794 | BK84: 514 | BL84: 1246 | BM84: =BK84+BL84 -> 1760 | BN84: 1662 | BP84: =(BK84+BL84+BN84)*4/3 -> 4562.6667 | BQ84: =BQ81*BQ107 -> 1160.0187 | BR84: =BR81*BR107 -> 1241.22 | BS84: =BS81*BS107 -> 1315.6932 | BT84: =BT81*BT107 -> 1381.4778 | BU84: =BU81*BU107 -> 1450.5517 | CC84: 2028E | CD84: 0.04 | CE84: 0.03 | CF84: 0.01
B85: Staff costs | C85: 133 | D85: 136 | E85: =C85+D85 -> 269 | F85: 132 | G85: 139 | H85: n/a | I85: 273 | J85: 322 | K85: =I85+J85 -> 595 | L85: 311 | M85: 282 | N85: n/a | T85: 1087 | Z85: 1141 | AF85: 1306 | AG85: 385 | AH85: 365 | AI85: =AG85+AH85 -> 750 | AJ85: 344 | AK85: 355 | AL85: 1449 | AM85: 377 | AN85: 377 | AO85: =AM85+AN85 -> 754 | AP85: 418 | AQ85: 492 | AR85: 1664 | AS85: 525 | AT85: 552 | AU85: =AS85+AT85 -> 1077 | AV85: 600 | AW85: 577 | AX85: 2254 | AY85: 588 | AZ85: 613 | BA85: =AY85+AZ85 -> 1201 | BB85: 599 | BC85: 618 | BD85: 2418 | BE85: 650 | BF85: 658 | BG85: =BE85+BF85 -> 1308 | BH85: 654 | BI85: 669 | BJ85: 2631 | BK85: 726 | BL85: 1445 | BM85: =BK85+BL85 -> 2171 | BN85: 1673 | BP85: =(BK85+BL85+BN85)*4/3 -> 5125.3333 | BQ85: =BQ81*BQ108 -> 8120.1307 | BR85: =BR81*BR108 -> 8440.2958 | BS85: =BS81*BS108 -> 8683.5749 | BT85: =BT81*BT108 -> 8841.4581 | BU85: =BU81*BU108 -> 9167.4869 | CC85: 2029E | CD85: 0.04 | CE85: 0.03 | CF85: 0.01
B86: EBITDA before special items | C86: 72 | D86: 105 | E86: =C86+D86 -> 177 | F86: 114 | G86: 103 | H86: n/a | I86: 98 | J86: 155 | K86: =I86+J86 -> 253 | L86: 171 | M86: 203 | N86: n/a | T86: =T83-T84-T85 -> 759 | U86: =U83-U84-U85 -> 0 | V86: =V83-V84-V85 -> 0 | W86: =W83-W84-W85 -> 0 | X86: =X83-X84-X85 -> 0 | Y86: =Y83-Y84-Y85 -> 0 | Z86: =Z83-Z84-Z85 -> 939 | AA86: =AA83-AA84-AA85 -> 0 | ... BU86: =BU83-BU84-BU85 -> 14621.561 | BX86: =IFERROR((BU86/BP86)^(1/5)-1,"n/m") -> 0.13771145 | BY86: =IFERROR((BP86/AL86)^(1/5)-1,"n/m") -> 0.22061485 | BZ86: =IFERROR((BP86/H86)^(1/10)-1,"n/m") -> n/m | CC86: 2030E | CD86: 0.04 | CE86: 0.03 | CF86: 0.01
B87: Amortisation and depreciation | C87: 36 | D87: 37 | E87: 73 | F87: 39 | G87: 40 | H87: 152 | I87: 51 | J87: 65 | K87: 116 | L87: 66 | M87: 61 | N87: 243 | T87: 265 | Z87: 230 | AF87: 1562 | AG87: 423 | AH87: 428 | AI87: 851 | AJ87: 402 | AK87: 417 | AL87: 1670 | AM87: 427 | AN87: 425 | AO87: 852 | AP87: 465 | AQ87: 559 | AR87: 1876 | AS87: 585 | AT87: 614 | AU87: 1199 | AV87: 664 | AW87: 741 | AX87: 2604 | AY87: 696 | AZ87: 727 | BA87: 1423 | BB87: 745 | BC87: 787 | BD87: 2955 | BE87: 814 | BF87: 809 | BG87: 1623 | BH87: 830 | BI87: 850 | BJ87: 3303 | BK87: 868 | BL87: 1216 | BM87: 2084 | BN87: 1377 | BP87: 4614.6667 | BQ87: =BQ81*BQ109 -> 4872.0784 | BR87: =BR81*BR109 -> 4964.8799 | BS87: =BS81*BS109 -> 5104.8895 | BT87: =BT81*BT109 -> 5304.8749 | BU87: =BU81*BU109 -> 5512.0965
B88: EBIT before special items | C88: 36 | D88: 68 | E88: 104 | F88: 75 | G88: 63 | H88: 242 | I88: 47 | J88: 90 | K88: 137 | L88: 105 | M88: 142 | N88: 384 | T88: =T86-T87 -> 494 | U88: =U86-U87 -> 0 | V88: =V86-V87 -> 0 | W88: =W86-W87 -> 0 | X88: =X86-X87 -> 0 | Y88: =Y86-Y87 -> 0 | Z88: =Z86-Z87 -> 709 | AA88: =AA86-AA87 -> 0 | ... BU88: =BU86-BU87 -> 9109.4648 | BX88: =IFERROR((BU88/BP88)^(1/5)-1,"n/m") -> 0.24413613 | BY88: =IFERROR((BP88/AL88)^(1/5)-1,"n/m") -> 0.21356831 | BZ88: =IFERROR((BP88/H88)^(1/10)-1,"n/m") -> 0.2886465 | CC88: AirRate_growth
B89: Revenue y/y % | N89: =IFERROR(N79/H79-1,"") -> 0.62466443 | T89: =IFERROR(T79/N79-1,"") -> 0.13270681 | Z89: =IFERROR(Z79/T79-1,"") -> 0.17423414 | AF89: =IFERROR(AF79/Z79-1,"") -> 0.090612625 | AL89: =IFERROR(AL79/AF79-1,"") -> -0.021287199 | AR89: =IFERROR(AR79/AL79-1,"") -> 0.30857642 | AX89: =IFERROR(AX79/AR79-1,"") -> 0.32447607 | BD89: =IFERROR(BD79/AX79-1,"") -> -0.056408965 | BJ89: =IFERROR(BJ79/BD79-1,"") -> 0.11240103 | BP89: =IFERROR(BP79/BJ79-1,"") -> 0.68363389 | BQ89: =CHOOSE(MATCH($BV$2,{"Bull","Base","Bear"},0),CD26,CE26,CF26) -> 0.18 | BR89: =CHOOSE(MATCH($BV$2,{"Bull","Base","Bear"},0),CD27,CE27,CF27) -> 0.07 | BS89: =CHOOSE(MATCH($BV$2,{"Bull","Base","Bear"},0),CD28,CE28,CF28) -> 0.06 | BT89: =CHOOSE(MATCH($BV$2,{"Bull","Base","Bear"},0),CD29,CE29,CF29) -> 0.05 | BU89: =CHOOSE(MATCH($BV$2,{"Bull","Base","Bear"},0),CD30,CE30,CF30) -> 0.05 | BV89: Rev growth: 18% in 2026 (full-year Schenker + 6% organic) tapering to 5-7%. CL is the highest-growth segment per CMD slide 145 (mid-single digit market + share gains). 2025 reported CL +72% YoY (Schenker contribution). Largest sqm capacity expansion via Schenker's 8.5m sqm addition. | CC89: 2026E | CD89: 0.08 | CE89: -0.02 | CF89: -0.15
B90: Gross profit y/y % | N90: =IFERROR(N83/H83-1,"") | T90: =IFERROR(T83/N83-1,"") | Z90: =IFERROR(Z83/T83-1,"") -> 0.11172161 | AF90: =IFERROR(AF83/Z83-1,"") -> 0.63723229 | AL90: =IFERROR(AL83/AF83-1,"") -> 0.080499094 | AR90: =IFERROR(AR83/AL83-1,"") -> 0.23915068 | AX90: =IFERROR(AX83/AR83-1,"") -> 0.40057117 | BD90: =IFERROR(BD83/AX83-1,"") -> 0.02060528 | BJ90: =IFERROR(BJ83/BD83-1,"") -> 0.057413249 | BP90: =IFERROR(BP83/BJ83-1,"") -> 0.72619995 | BQ90: =IFERROR(BQ83/BP83-1,"n/a") -> 0.14674247 | BR90: =IFERROR(BR83/BQ83-1,"n/a") -> 0.072494172 | BS90: =IFERROR(BS83/BR83-1,"n/a") -> 0.064930233 | BT90: =IFERROR(BT83/BS83-1,"n/a") -> 0.054861111 | BU90: =IFERROR(BU83/BT83-1,"n/a") -> 0.052419355 | CC90: 2027E | CD90: 0.03 | CE90: 0 | CF90: -0.05
B91: EBITDA before special items y/y % | N91: =IFERROR(N86/H86-1,"") | T91: =IFERROR(T86/N86-1,"") | Z91: =IFERROR(Z86/T86-1,"") -> 0.23715415 | AF91: =IFERROR(AF86/Z86-1,"") -> 1.742279 | AL91: =IFERROR(AL86/AF86-1,"") -> 0.099417476 | AR91: =IFERROR(AR86/AL86-1,"") -> 0.2896503 | AX91: =IFERROR(AX86/AR86-1,"") -> 0.45302657 | BD91: =IFERROR(BD86/AX86-1,"") -> 0.00094250707 | BJ91: =IFERROR(BJ86/BD86-1,"") -> 0.060451977 | BP91: =IFERROR(BP86/BJ86-1,"") -> 0.36222104 | BQ91: =IFERROR(BQ86/BP86-1,"n/a") -> 0.38524739 | BR91: =IFERROR(BR86/BQ86-1,"n/a") -> 0.098034934 | BS91: =IFERROR(BS86/BR86-1,"n/a") -> 0.091574468 | BT91: =IFERROR(BT86/BS86-1,"n/a") -> 0.080371901 | BU91: =IFERROR(BU86/BT86-1,"n/a") -> 0.062650602 | CC91: 2028E | CD91: 0.02 | CE91: 0.01 | CF91: -0.02
B92: EBIT before special items y/y % | N92: =IFERROR(N88/H88-1,"") -> 0.58677686 | T92: =IFERROR(T88/N88-1,"") -> 0.28645833 | Z92: =IFERROR(Z88/T88-1,"") -> 0.43522267 | AF92: =IFERROR(AF88/Z88-1,"") -> 0.42877292 | AL92: =IFERROR(AL88/AF88-1,"") -> 0.14610069 | AR92: =IFERROR(AR88/AL88-1,"") -> 0.52885444 | AX92: =IFERROR(AX88/AR88-1,"") -> 0.52169014 | BD92: =IFERROR(BD88/AX88-1,"") -> -0.1281007 | BJ92: =IFERROR(BJ88/BD88-1,"") -> -0.011464968 | BP92: =IFERROR(BP88/BJ88-1,"") -> 0.31271478 | BQ92: =IFERROR(BQ88/BP88-1,"n/a") -> 0.88275281 | BR92: =IFERROR(BR88/BQ88-1,"n/a") -> 0.16491935 | BS92: =IFERROR(BS88/BR88-1,"n/a") -> 0.13851852 | BT92: =IFERROR(BT88/BS88-1,"n/a") -> 0.10793103 | BU92: =IFERROR(BU88/BT88-1,"n/a") -> 0.07745098 | CC92: 2029E | CD92: 0.02 | CE92: 0.01 | CF92: -0.01
B93: GP % | H93: =IFERROR(H83/H79,"") | N93: =IFERROR(N83/N79,"") | T93: =IFERROR(T83/T79,"") -> 0.24890591 | Z93: =IFERROR(Z83/Z79,"") -> 0.23565494 | AF93: =IFERROR(AF83/AF79,"") -> 0.3537662 | AL93: =IFERROR(AL83/AL79,"") -> 0.39055794 | AR93: =IFERROR(AR83/AR79,"") -> 0.36983712 | AX93: =IFERROR(AX83/AX79,"") -> 0.39108537 | BD93: =IFERROR(BD83/BD79,"") -> 0.42300507 | BJ93: =IFERROR(BJ83/BJ79,"") -> 0.40209525 | BP93: =IFERROR(BP83/BP79,"") -> 0.41226112 | BQ93: 0.429 | BR93: 0.43 | BS93: 0.432 | BT93: 0.434 | BU93: 0.435 | BV93: GP margin: 42.9% → 43.5%. Highest absolute GP margin of any segment because CL revenue is largely services (not freight pass-through). Stable/slight expansion as warehouse utilisation improves (CMD slide 145: 'consolidation of physical infrastructure'). | BX93: =IFERROR(AVERAGE(BQ93,BR93,BS93,BT93,BU93),"n/m") -> 0.432 | BY93: =IFERROR(AVERAGE(AR93,AX93,BD93,BJ93,BP93),"n/m") -> 0.39965679 | BZ93: =IFERROR(AVERAGE(N93,T93,Z93,AF93,AL93,AR93,AX93,BD93,BJ93,BP93),"n/m") -> 0.35857432 | CC93: 2030E | CD93: 0.02 | CE93: 0.01 | CF93: -0.01
B94: EBITDA % | H94: =IFERROR(H86/H79,"") | N94: =IFERROR(N86/N79,"") | T94: =IFERROR(T86/T79,"") -> 0.069201313 | Z94: =IFERROR(Z86/Z79,"") -> 0.072909387 | AF94: =IFERROR(AF86/AF79,"") -> 0.18332621 | AL94: =IFERROR(AL86/AL79,"") -> 0.20593584 | AR94: =IFERROR(AR86/AR79,"") -> 0.20295736 | AX94: =IFERROR(AX86/AX79,"") -> 0.22265592 | BD94: =IFERROR(BD86/BD79,"") -> 0.23618895 | BJ94: =IFERROR(BJ86/BJ79,"") -> 0.22515894 | BP94: =IFERROR(BP86/BP79,"") -> 0.18217515 | BQ94: =IFERROR(BQ86/BQ79,"n/a") -> 0.23608247 | BR94: =IFERROR(BR86/BR79,"n/a") -> 0.24226804 | BS94: =IFERROR(BS86/BS79,"n/a") -> 0.24948454 | BT94: =IFERROR(BT86/BT79,"n/a") -> 0.25670103 | BU94: =IFERROR(BU86/BU79,"n/a") -> 0.25979381
B95: EBIT % | H95: =IFERROR(H88/H79,"") -> 0.040604027 | N95: =IFERROR(N88/N79,"") -> 0.039657131 | T95: =IFERROR(T88/T79,"") -> 0.045040117 | Z95: =IFERROR(Z88/Z79,"") -> 0.055050858 | AF95: =IFERROR(AF88/AF79,"") -> 0.072120177 | AL95: =IFERROR(AL88/AL79,"") -> 0.08445479 | AR95: =IFERROR(AR88/AR79,"") -> 0.09867141 | AX95: =IFERROR(AX88/AX79,"") -> 0.11336355 | BD95: =IFERROR(BD88/BD79,"") -> 0.10475047 | BJ95: =IFERROR(BJ88/BJ79,"") -> 0.093086489 | BP95: =IFERROR(BP88/BP79,"") -> 0.07257873 | BQ95: =IFERROR(BQ88/BQ79,"n/a") -> 0.12783505 | BR95: =IFERROR(BR88/BR79,"n/a") -> 0.13917526 | BS95: =IFERROR(BS88/BS79,"n/a") -> 0.14948454 | BT95: =IFERROR(BT88/BT79,"n/a") -> 0.15773196 | BU95: =IFERROR(BU88/BU79,"n/a") -> 0.16185567 | BX95: =IFERROR(AVERAGE(BQ95,BR95,BS95,BT95,BU95),"n/m") -> 0.14721649 | BY95: =IFERROR(AVERAGE(AR95,AX95,BD95,BJ95,BP95),"n/m") -> 0.09649013 | BZ95: =IFERROR(AVERAGE(N95,T95,Z95,AF95,AL95,AR95,AX95,BD95,BJ95,BP95),"n/m") -> 0.077877372
B96: Incremental EBIT % (ΔEBIT / ΔRev) | N96: =IFERROR((N88-H88)/(N79-H79),"") -> 0.038141284 | T96: =IFERROR((T88-N88)/(T79-N79),"") -> 0.085603113 | Z96: =IFERROR((Z88-T88)/(Z79-T79),"") -> 0.11250654 | AF96: =IFERROR((AF88-Z88)/(AF79-Z79),"") -> 0.260497 | AL96: =IFERROR((AL88-AF88)/(AL79-AF79),"") -> -0.49498328 | AR96: =IFERROR((AR88-AL88)/(AR79-AL79),"") -> 0.14474305 | AX96: =IFERROR((AX88-AR88)/(AX79-AR79),"") -> 0.15864314 | BD96: =IFERROR((BD88-AX88)/(BD79-AX79),"") -> 0.25744048 | BJ96: =IFERROR((BJ88-BD88)/(BJ79-BD79),"") -> -0.010684606 | BP96: =IFERROR((BP88-BJ88)/(BP79-BJ79),"") -> 0.04258057 | BQ96: =IFERROR((BQ88-BP88)/(BQ79-BP79),"n/a") -> 0.92936577 | BR96: =IFERROR((BR88-BQ88)/(BR79-BQ79),"n/a") -> 0.3011782 | BS96: =IFERROR((BS88-BR88)/(BS79-BR79),"n/a") -> 0.32130584 | BT96: =IFERROR((BT88-BS88)/(BT79-BS79),"n/a") -> 0.32268041 | BU96: =IFERROR((BU88-BT88)/(BU79-BT79),"n/a") -> 0.2443299
B97: EBIT / GP | H97: =IFERROR(H88/H83,"") | N97: =IFERROR(N88/N83,"") | T97: =IFERROR(T88/T83,"") -> 0.18095238 | Z97: =IFERROR(Z88/Z83,"") -> 0.23360791 | AF97: =IFERROR(AF88/AF83,"") -> 0.20386396 | AL97: =IFERROR(AL88/AL83,"") -> 0.21624139 | AR97: =IFERROR(AR88/AR83,"") -> 0.26679693 | AX97: =IFERROR(AX88/AX83,"") -> 0.28986907 | BD97: =IFERROR(BD88/BD83,"") -> 0.24763407 | BJ97: =IFERROR(BJ88/BJ83,"") -> 0.23150358 | BP97: =IFERROR(BP88/BP83,"") -> 0.17605039 | BQ97: =IFERROR(BQ88/BQ83,"") -> 0.28904429 | BR97: =IFERROR(BR88/BR83,"") -> 0.31395349 | BS97: =IFERROR(BS88/BS83,"") -> 0.33564815 | BT97: =IFERROR(BT88/BT83,"") -> 0.35253456 | BU97: =IFERROR(BU88/BU83,"") -> 0.36091954 | BV97: EBIT/GP (Conversion Ratio): 23% → 27% → 30% → 33% → 35%. Hits DSV's 2030 target of >35% (CMD slide 145). Drivers: warehouse consolidation, utilisation improvement (target 80-85%), Schenker dilution unwinds as synergies land. | BX97: =IFERROR(AVERAGE(BQ97,BR97,BS97,BT97,BU97),"n/m") -> 0.33042001 | BY97: =IFERROR(AVERAGE(AR97,AX97,BD97,BJ97,BP97),"n/m") -> 0.24237081 | BZ97: =IFERROR(AVERAGE(N97,T97,Z97,AF97,AL97,AR97,AX97,BD97,BJ97,BP97),"n/m") -> 0.22739107
B98: Operating metrics — Solutions / Contract Logistics
B99: Warehouse capacity (m sqm) | AF99: 5 | AL99: 6 | AR99: 7.4 | AX99: 8 | BD99: 8 | BJ99: 9 | BP99: 17.5
B100: Revenue per sqm (DKK/sqm) | H100: =IFERROR(H81/H99,"n/a") -> n/a | N100: =IFERROR(N81/N99,"n/a") -> n/a | T100: =IFERROR(T81/T99,"n/a") -> n/a | Z100: =IFERROR(Z81/Z99,"n/a") -> n/a | AF100: =IFERROR(AF81/AF99,"n/a") -> 2878 | AL100: =IFERROR(AL81/AL99,"n/a") -> 2434.6667 | AR100: =IFERROR(AR81/AR99,"n/a") -> 2531.6216 | AX100: =IFERROR(AX81/AX99,"n/a") -> 3051.125 | BD100: =IFERROR(BD81/BD99,"n/a") -> 2892.5 | BJ100: =IFERROR(BJ81/BJ99,"n/a") -> 2847.1111 | BP100: =IFERROR(BP81/BP99,"n/a") -> 2247.0095
B101: GP per sqm (DKK/sqm) | H101: =IFERROR(H83/H99,"n/a") -> n/a | N101: =IFERROR(N83/N99,"n/a") -> n/a | T101: =IFERROR(T83/T99,"n/a") -> n/a | Z101: =IFERROR(Z83/Z99,"n/a") -> n/a | AF101: =IFERROR(AF83/AF99,"n/a") -> 993.8 | AL101: =IFERROR(AL83/AL99,"n/a") -> 894.83333 | AR101: =IFERROR(AR83/AR99,"n/a") -> 899.05405 | AX101: =IFERROR(AX83/AX99,"n/a") -> 1164.75 | BD101: =IFERROR(BD83/BD99,"n/a") -> 1188.75 | BJ101: =IFERROR(BJ83/BJ99,"n/a") -> 1117.3333 | BP101: =IFERROR(BP83/BP99,"n/a") -> 991.92381
...

Sheet Bull-Base-Bear
B2: DSV A/S — Bull / Base / Bear Case P&L Summary | J2: Share price (DKK): | K2: 1525
B3: Adjusted figures · DKK millions · Linked to Model — toggle scenario via Model!BV2 | J3: As of: | K3: =TODAY() -> 46169
B5: Scenario: | C5: =Model_DSV_ref!BV2 -> Base | N5: Scenario: | O5: Bull | Z5: Scenario: | AA5: Bear
B7: (DKKm, except EPS and shares) | C7: 2025A | D7: 2026E | E7: 2027E | F7: 2028E | G7: 2029E | H7: 2030E | I7: 25-'30 CAGR | J7: LT Hist Avg | K7: LT Hist Min | L7: LT Hist Max | N7: (DKKm, except EPS and shares) | O7: 2025A | P7: 2026E | Q7: 2027E | R7: 2028E | S7: 2029E | T7: 2030E | U7: 25-'30 CAGR | V7: LT Hist Avg | W7: LT Hist Min | X7: LT Hist Max | Z7: (DKKm, except EPS and shares) | AA7: 2025A | AB7: 2026E | AC7: 2027E | AD7: 2028E | AE7: 2029E | AF7: 2030E | AG7: 25-'30 CAGR | AH7: LT Hist Avg | AI7: LT Hist Min | AJ7: LT Hist Max
B9: Revenue | C9: =Model_DSV_ref!BP146 -> 247331 | D9: =Model_DSV_ref!BQ146 -> 272331.92 | E9: =Model_DSV_ref!BR146 -> 288134.17 | F9: =Model_DSV_ref!BS146 -> 302701.32 | G9: =Model_DSV_ref!BT146 -> 314868.19 | H9: =Model_DSV_ref!BU146 -> 327522.22 | I9: =IFERROR((H9/C9)^(1/5)-1,"n/m") -> 0.057772919 | N9: Revenue | O9: 247331 | P9: 274565.2 | Q9: 295358.07 | R9: 315019.82 | S9: 332724.3 | T9: 351419.6 | U9: 0.072777077 | Z9: Revenue | AA9: 247331 | AB9: 241578.47 | AC9: 242404.24 | AD9: 245347.74 | AE9: 248329.09 | AF9: 251348.85 | AG9: 0.0032280561
B10: Revenue y/y % | D10: =IFERROR(D9/C9-1,"") -> 0.10108284 | E10: =IFERROR(E9/D9-1,"") -> 0.058025711 | F10: =IFERROR(F9/E9-1,"") -> 0.050556812 | G10: =IFERROR(G9/F9-1,"") -> 0.040194303 | H10: =IFERROR(H9/G9-1,"") -> 0.040188361 | N10: Revenue y/y % | P10: 0.11011236 | Q10: 0.075730182 | R10: 0.066569176 | S10: 0.056201186 | T10: 0.056188546 | Z10: Revenue y/y % | AB10: -0.02325844 | AC10: 0.0034182517 | AD10: 0.012142918 | AE10: 0.012151539 | AF10: 0.012160306
B12: Gross Profit | C12: =Model_DSV_ref!BP148 -> 66859 | D12: =Model_DSV_ref!BQ148 -> 74572.307 | E12: =Model_DSV_ref!BR148 -> 80071.722 | F12: =Model_DSV_ref!BS148 -> 85290.355 | G12: =Model_DSV_ref!BT148 -> 88878.808 | H12: =Model_DSV_ref!BU148 -> 92565.095 | I12: =IFERROR((H12/C12)^(1/5)-1,"n/m") -> 0.067228648 | N12: Gross Profit | O12: 66859 | P12: 75220.763 | Q12: 82124.964 | R12: 88743.52 | S12: 93834.245 | T12: 99159.855 | U12: 0.082019784 | Z12: Gross Profit | AA12: 66859 | AB12: 66270.732 | AC12: 67570.13 | AD12: 69357.447 | AE12: 70331.307 | AF12: 71276.554 | AG12: 0.012878526
B13: GP % | C13: =IFERROR(C12/C9,"") -> 0.27032196 | D13: =IFERROR(D12/D9,"") -> 0.27382874 | E13: =IFERROR(E12/E9,"") -> 0.27789735 | F13: =IFERROR(F12/F9,"") -> 0.28176407 | G13: =IFERROR(G12/G9,"") -> 0.28227306 | H13: =IFERROR(H12/H9,"") -> 0.28262233 | J13: =AVERAGE(Model_DSV_ref!H139,Model_DSV_ref!N139,Model_DSV_ref!T139,Model_DSV_ref!Z139,Model_DSV_ref!AF139,Model_DSV_ref!AL139,Model_DSV_ref!AR139,Model_DSV_ref!AX139,Model_DSV_ref!BD139,Model_DSV_ref!BJ139,Model_DSV_ref!BP139) -> 0.2399598 | K13: =MIN(Model_DSV_ref!H139,Model_DSV_ref!N139,Model_DSV_ref!T139,Model_DSV_ref!Z139,Model_DSV_ref!AF139,Model_DSV_ref!AL139,Model_DSV_ref!AR139,Model_DSV_ref!AX139,Model_DSV_ref!BD139,Model_DSV_ref!BJ139,Model_DSV_ref!BP139) -> 0.20632892 | L13: =MAX(Model_DSV_ref!H139,Model_DSV_ref!N139,Model_DSV_ref!T139,Model_DSV_ref!Z139,Model_DSV_ref!AF139,Model_DSV_ref!AL139,Model_DSV_ref!AR139,Model_DSV_ref!AX139,Model_DSV_ref!BD139,Model_DSV_ref!BJ139,Model_DSV_ref!BP139) -> 0.2905992 | N13: GP % | O13: 0.27032196 | P13: 0.27396321 | Q13: 0.27805221 | R13: 0.28170774 | S13: 0.28201801 | T13: 0.28216939 | V13: 0.2399598 | W13: 0.20632892 | X13: 0.2905992 | Z13: GP % | AA13: 0.27032196 | AB13: 0.27432384 | AC13: 0.27874978 | AD13: 0.28269039 | AE13: 0.28321816 | AF13: 0.28357621 | AH13: 0.2399598 | AI13: 0.20632892 | AJ13: 0.2905992
B15: EBIT (Adjusted Operating Profit) | C15: =Model_DSV_ref!BP188 -> 15084 | D15: =Model_DSV_ref!BQ188 -> 21150.633 | E15: =Model_DSV_ref!BR188 -> 26468.523 | F15: =Model_DSV_ref!BS188 -> 32377.625 | G15: =Model_DSV_ref!BT188 -> 35269.692 | H15: =Model_DSV_ref!BU188 -> 37896.305 | I15: =IFERROR((H15/C15)^(1/5)-1,"n/m") -> 0.20230892 | N15: EBIT (Adjusted Operating Profit) | O15: 15084 | P15: 21791.558 | Q15: 27647.356 | R15: 33888.277 | S15: 37372.225 | T15: 40781.498 | U15: 0.22008287 | Z15: EBIT (Adjusted Operating Profit) | AA15: 15084 | AB15: 17318.004 | AC15: 20337.288 | AD15: 24528.782 | AE15: 26912.932 | AF15: 28656.775 | AG15: 0.13695207
B16: EBIT y/y % | D16: =IFERROR(D15/C15-1,"") -> 0.40218996 | E16: =IFERROR(E15/D15-1,"") -> 0.25142934 | F16: =IFERROR(F15/E15-1,"") -> 0.22325014 | G16: =IFERROR(G15/F15-1,"") -> 0.089323033 | H16: =IFERROR(H15/G15-1,"") -> 0.074472226 | N16: EBIT y/y % | P16: 0.44468035 | Q16: 0.26871864 | R16: 0.225733 | S16: 0.10280687 | T16: 0.091224794 | Z16: EBIT y/y % | AB16: 0.14810424 | AC16: 0.17434362 | AD16: 0.20609899 | AE16: 0.097198019 | AF16: 0.06479575
B17: EBIT % | C17: =IFERROR(C15/C9,"") -> 0.060987098 | D17: =IFERROR(D15/D9,"") -> 0.077664907 | E17: =IFERROR(E15/E9,"") -> 0.091861798 | F17: =IFERROR(F15/F9,"") -> 0.10696229 | G17: =IFERROR(G15/G9,"") -> 0.11201415 | H17: =IFERROR(H15/H9,"") -> 0.11570606 | J17: =AVERAGE(Model_DSV_ref!H141,Model_DSV_ref!N141,Model_DSV_ref!T141,Model_DSV_ref!Z141,Model_DSV_ref!AF141,Model_DSV_ref!AL141,Model_DSV_ref!AR141,Model_DSV_ref!AX141,Model_DSV_ref!BD141,Model_DSV_ref!BJ141,Model_DSV_ref!BP141) -> 0.080616919 | K17: =MIN(Model_DSV_ref!H141,Model_DSV_ref!N141,Model_DSV_ref!T141,Model_DSV_ref!Z141,Model_DSV_ref!AF141,Model_DSV_ref!AL141,Model_DSV_ref!AR141,Model_DSV_ref!AX141,Model_DSV_ref!BD141,Model_DSV_ref!BJ141,Model_DSV_ref!BP141) -> 0.051293784 | L17: =MAX(Model_DSV_ref!H141,Model_DSV_ref!N141,Model_DSV_ref!T141,Model_DSV_ref!Z141,Model_DSV_ref!AF141,Model_DSV_ref!AL141,Model_DSV_ref!AR141,Model_DSV_ref!AX141,Model_DSV_ref!BD141,Model_DSV_ref!BJ141,Model_DSV_ref!BP141) -> 0.11753822 | N17: EBIT % | O17: 0.060987098 | P17: 0.079367518 | Q17: 0.093606232 | R17: 0.10757506 | S17: 0.1123219 | T17: 0.11604788 | V17: 0.080616919 | W17: 0.051293784 | X17: 0.11753822 | Z17: EBIT % | AA17: 0.060987098 | AB17: 0.071686871 | AC17: 0.083898234 | AD17: 0.09997558 | AE17: 0.10837607 | AF17: 0.11401196 | AH17: 0.080616919 | AI17: 0.051293784 | AJ17: 0.11753822
B19: Net Income (Adjusted Earnings) | C19: =Model_DSV_ref!BP178 -> 12022 | D19: =Model_DSV_ref!BQ178 -> 16038.475 | E19: =Model_DSV_ref!BR178 -> 19321.142 | F19: =Model_DSV_ref!BS178 -> 22648.469 | G19: =Model_DSV_ref!BT178 -> 24671.519 | H19: =Model_DSV_ref!BU178 -> 26662.729 | I19: =IFERROR((H19/C19)^(1/5)-1,"n/m") -> 0.17269635 | N19: Net Income (Adjusted Earnings) | O19: 12022 | P19: 16144.169 | Q19: 19830.267 | R19: 23631.458 | S19: 26173.419 | T19: 28751.624 | U19: 0.19052119 | Z19: Net Income (Adjusted Earnings) | AA19: 12022 | AB19: 13914.003 | AC19: 15847.716 | AD19: 17886.837 | AE19: 18928.949 | AF19: 19883.081 | AG19: 0.10586317
B21: FDSO ('000) | C21: =Model_DSV_ref!BP169 -> 236159 | D21: =Model_DSV_ref!BQ169 -> 235097.21 | E21: =Model_DSV_ref!BR169 -> 232317.33 | F21: =Model_DSV_ref!BS169 -> 227121.29 | G21: =Model_DSV_ref!BT169 -> 219837.12 | H21: =Model_DSV_ref!BU169 -> 211667.96 | I21: =IFERROR((H21/C21)^(1/5)-1,"n/m") -> -0.021659291 | N21: FDSO ('000) | O21: 236159 | P21: 234502.32 | Q21: 230610.48 | R21: 222816.42 | S21: 213104.2 | T21: 201758.14 | U21: -0.030996572 | Z21: FDSO ('000) | AA21: 236159 | AB21: 235692.11 | AC21: 234580.15 | AD21: 233021.34 | AE21: 230593.28 | AF21: 226962.55 | AG21: -0.0079125884
B23: Adjusted EPS — Diluted (DKK) | C23: =Model_DSV_ref!BP180 -> 50.897912 | D23: =Model_DSV_ref!BQ180 -> 68.220609 | E23: =Model_DSV_ref!BR180 -> 83.16703 | F23: =Model_DSV_ref!BS180 -> 99.719708 | G23: =Model_DSV_ref!BT180 -> 112.22636 | H23: =Model_DSV_ref!BU180 -> 125.96488 | I23: =IFERROR((H23/C23)^(1/5)-1,"n/m") -> 0.19869833 | N23: Adjusted EPS — Diluted (DKK) | O23: 50.897912 | P23: 68.844389 | Q23: 85.990312 | R23: 106.05797 | S23: 122.81982 | T23: 142.5054 | U23: 0.22864458 | Z23: Adjusted EPS — Diluted (DKK) | AA23: 50.897912 | AB23: 59.03466 | AC23: 67.557787 | AD23: 76.76051 | AE23: 82.088031 | AF23: 87.605121 | AG23: 0.11472029
B24: EPS y/y % | D24: =IFERROR(D23/C23-1,"") -> 0.34034201 | E24: =IFERROR(E23/D23-1,"") -> 0.21908953 | F24: =IFERROR(F23/E23-1,"") -> 0.19902932 | G24: =IFERROR(G23/F23-1,"") -> 0.12541803 | H24: =IFERROR(H23/G23-1,"") -> 0.12241794 | N24: EPS y/y % | P24: 0.35259752 | Q24: 0.2490533 | R24: 0.23337117 | S24: 0.15804418 | T24: 0.16028015 | Z24: EPS y/y % | AB24: 0.15986408 | AC24: 0.14437496 | AD24: 0.13622002 | AE24: 0.069404453 | AF24: 0.067209435
B26: P / E (x) — assumed | E26: 18 | F26: =E26 -> 18 | G26: =F26 -> 18 | H26: =G26 -> 18 | N26: P / E (x) — assumed | Q26: 20 | R26: 20 | S26: 20 | T26: 20 | Z26: P / E (x) — assumed | AC26: 15 | AD26: 15 | AE26: 15 | AF26: 15
B27: Price Target (DKK) | E27: =E26*E23 -> 1497.0065 | F27: =F26*F23 -> 1794.9547 | G27: =G26*G23 -> 2020.0744 | H27: =H26*H23 -> 2267.3678 | N27: Price Target (DKK) | Q27: 1719.8062 | R27: 2121.1594 | S27: 2456.3963 | T27: 2850.1079 | Z27: Price Target (DKK) | AC27: 1013.3668 | AD27: 1151.4076 | AE27: 1231.3205 | AF27: 1314.0768
B28: Upside / (Downside) vs current | E28: =IFERROR(E27/$K$2-1,"") -> -0.018356362 | F28: =IFERROR(F27/$K$2-1,"") -> 0.1770195 | G28: =IFERROR(G27/$K$2-1,"") -> 0.32463897 | H28: =IFERROR(H27/$K$2-1,"") -> 0.48679855 | N28: Upside / (Downside) vs current | Q28: =Q27/$K$2-1 -> 0.12774179 | R28: =R27/$K$2-1 -> 0.39092421 | S28: =S27/$K$2-1 -> 0.61075169 | T28: =T27/$K$2-1 -> 0.86892321 | Z28: Upside / (Downside) vs current | AC28: =AC27/$K$2-1 -> -0.33549718 | AD28: =AD27/$K$2-1 -> -0.24497859 | AE28: =AE27/$K$2-1 -> -0.19257675 | AF28: =AF27/$K$2-1 -> -0.13831029
B29: IRR (to Dec-Y-1) | F29: =IFERROR((F27/$K$2)^(1/((DATE(VALUE(LEFT(F$7,4))-1,12,31)-$K$3)/365.25))-1,"") -> 0.10750583 | G29: =IFERROR((G27/$K$2)^(1/((DATE(VALUE(LEFT(G$7,4))-1,12,31)-$K$3)/365.25))-1,"") -> 0.11427594 | H29: =IFERROR((H27/$K$2)^(1/((DATE(VALUE(LEFT(H$7,4))-1,12,31)-$K$3)/365.25))-1,"") -> 0.1165562 | N29: IRR (to Dec-Y-1) | R29: =IFERROR((R27/$K$2)^(1/((DATE(VALUE(LEFT(R$7,4))-1,12,31)-$K$3)/365.25))-1,"") -> 0.22964499 | S29: =IFERROR((S27/$K$2)^(1/((DATE(VALUE(LEFT(S$7,4))-1,12,31)-$K$3)/365.25))-1,"") -> 0.20138145 | T29: =IFERROR((T27/$K$2)^(1/((DATE(VALUE(LEFT(T$7,4))-1,12,31)-$K$3)/365.25))-1,"") -> 0.18985419 | Z29: IRR (to Dec-Y-1) | AD29: =IFERROR((AD27/$K$2)^(1/((DATE(VALUE(LEFT(AD$7,4))-1,12,31)-$K$3)/365.25))-1,"") -> -0.16142604 | AE29: =IFERROR((AE27/$K$2)^(1/((DATE(VALUE(LEFT(AE$7,4))-1,12,31)-$K$3)/365.25))-1,"") -> -0.079030517 | AF29: =IFERROR((AF27/$K$2)^(1/((DATE(VALUE(LEFT(AF$7,4))-1,12,31)-$K$3)/365.25))-1,"") -> -0.040533935
B31: Free Cash Flow | C31: =Model_DSV_ref!BP243 -> 19745 | D31: =Model_DSV_ref!BQ243 -> 20369.643 | E31: =Model_DSV_ref!BR243 -> 26050.088 | F31: =Model_DSV_ref!BS243 -> 30241.281 | G31: =Model_DSV_ref!BT243 -> 28395.23 | H31: =Model_DSV_ref!BU243 -> 30401.26 | I31: =IFERROR((H31/C31)^(1/5)-1,"n/m") -> 0.090151584 | N31: Free Cash Flow | O31: 19745 | P31: 20741.23 | Q31: 26712.032 | R31: 31215.878 | S31: 29800.606 | T31: 32393.437 | U31: 0.10407857 | Z31: Free Cash Flow | AA31: 19745 | AB31: 19574.593 | AC31: 21866.207 | AD31: 24385.753 | AE31: 21992.769 | AF31: 23269.21 | AG31: 0.033391533
B32: FCF % | C32: =IFERROR(C31/C9,"") -> 0.07983229 | D32: =IFERROR(D31/D9,"") -> 0.074797119 | E32: =IFERROR(E31/E9,"") -> 0.090409574 | F32: =IFERROR(F31/F9,"") -> 0.099904688 | G32: =IFERROR(G31/G9,"") -> 0.090181323 | H32: =IFERROR(H31/H9,"") -> 0.092821977 | J32: =AVERAGE(IFERROR(Model_DSV_ref!H243/Model_DSV_ref!H146,NA()),IFERROR(Model_DSV_ref!N243/Model_DSV_ref!N146,NA()),IFERROR(Model_DSV_ref!T243/Model_DSV_ref!T146,NA()),IFERROR(Model_DSV_ref!Z243/Model_DSV_ref!Z146,NA()),IFERROR(Model_DSV_ref!AF243/Model_DSV_ref!AF146,NA()),IFERROR(Model_DSV_ref!AL243/Model_DSV_ref!AL146,NA()),IFERROR(Model_DSV_ref!AR243/Model_DSV_ref!AR146,NA()),IFERROR(Model_DSV_ref!AX243/Model_DSV_ref!AX146,NA()),IFERROR(Model_DSV_ref!BD243/Model_DSV_ref!BD146,NA()),IFERROR(Model_DSV_ref!BJ243/Model_DSV_ref!BJ146,NA()),IFERROR(Model_DSV_ref!BP243/Model_DSV_ref!BP146,NA())) -> 0.070534883 | K32: =MIN(IFERROR(Model_DSV_ref!H243/Model_DSV_ref!H146,99),IFERROR(Model_DSV_ref!N243/Model_DSV_ref!N146,99),IFERROR(Model_DSV_ref!T243/Model_DSV_ref!T146,99),IFERROR(Model_DSV_ref!Z243/Model_DSV_ref!Z146,99),IFERROR(Model_DSV_ref!AF243/Model_DSV_ref!AF146,99),IFERROR(Model_DSV_ref!AL243/Model_DSV_ref!AL146,99),IFERROR(Model_DSV_ref!AR243/Model_DSV_ref!AR146,99),IFERROR(Model_DSV_ref!AX243/Model_DSV_ref!AX146,99),IFERROR(Model_DSV_ref!BD243/Model_DSV_ref!BD146,99),IFERROR(Model_DSV_ref!BJ243/Model_DSV_ref!BJ146,99),IFERROR(Model_DSV_ref!BP243/Model_DSV_ref!BP146,99)) -> 0.019307128 | L32: =MAX(IFERROR(Model_DSV_ref!H243/Model_DSV_ref!H146,-99),IFERROR(Model_DSV_ref!N243/Model_DSV_ref!N146,-99),IFERROR(Model_DSV_ref!T243/Model_DSV_ref!T146,-99),IFERROR(Model_DSV_ref!Z243/Model_DSV_ref!Z146,-99),IFERROR(Model_DSV_ref!AF243/Model_DSV_ref!AF146,-99),IFERROR(Model_DSV_ref!AL243/Model_DSV_ref!AL146,-99),IFERROR(Model_DSV_ref!AR243/Model_DSV_ref!AR146,-99),IFERROR(Model_DSV_ref!AX243/Model_DSV_ref!AX146,-99),IFERROR(Model_DSV_ref!BD243/Model_DSV_ref!BD146,-99),IFERROR(Model_DSV_ref!BJ243/Model_DSV_ref!BJ146,-99),IFERROR(Model_DSV_ref!BP243/Model_DSV_ref!BP146,-99)) -> 0.11098806 | N32: FCF % | O32: 0.07983229 | P32: 0.075542093 | Q32: 0.090439484 | R32: 0.099091793 | S32: 0.089565462 | T32: 0.092178801 | V32: 0.070534883 | W32: 0.019307128 | X32: 0.11098806 | Z32: FCF % | AA32: 0.07983229 | AB32: 0.08102789 | AC32: 0.090205545 | AD32: 0.099392615 | AE32: 0.088563 | AF32: 0.092577348 | AH32: 0.070534883 | AI32: 0.019307128 | AJ32: 0.11098806
B33: FCF / share (DKK) | C33: =IFERROR(C31*1000/C21,"") -> 83.608924 | D33: =IFERROR(D31*1000/D21,"") -> 86.64349 | E33: =IFERROR(E31*1000/E21,"") -> 112.13149 | F33: =IFERROR(F31*1000/F21,"") -> 133.15036 | G33: =IFERROR(G31*1000/G21,"") -> 129.16485 | H33: =IFERROR(H31*1000/H21,"") -> 143.62712 | N33: FCF / share (DKK) | O33: 83.608924 | P33: 88.447868 | Q33: 115.83182 | R33: 140.09685 | S33: 139.84054 | T33: 160.55579 | Z33: FCF / share (DKK) | AA33: 83.608924 | AB33: 83.051545 | AC33: 93.214223 | AD33: 104.6503 | AE33: 95.374717 | AF33: 102.52445
B34: FCF Yield (on PT) | E34: =IFERROR(E33/E$27,"") -> 0.074903806 | F34: =IFERROR(F33/F$27,"") -> 0.074180343 | G34: =IFERROR(G33/G$27,"") -> 0.063940641 | H34: =IFERROR(H33/H$27,"") -> 0.063345313 | N34: FCF Yield (on PT) | Q34: 0.067351668 | R34: 0.066047297 | S34: 0.056929144 | T34: 0.056333231 | Z34: FCF Yield (on PT) | AC34: 0.091984682 | AD34: 0.090889009 | AE34: 0.077457266 | AF34: 0.078020133
B35: EBITDA (before special items) | C35: =Model_DSV_ref!BP209 -> 28244 | D35: =Model_DSV_ref!BQ209 -> 33433.188 | E35: =Model_DSV_ref!BR209 -> 38045.28 | F35: =Model_DSV_ref!BS209 -> 42697.844 | G35: =Model_DSV_ref!BT209 -> 45741.367 | H35: =Model_DSV_ref!BU209 -> 48638.073 | I35: =IFERROR((H35/C35)^(1/5)-1,"n/m") -> 0.11483356 | N35: EBITDA (before special items) | O35: 28244 | P35: 33692.861 | Q35: 39001.12 | R35: 44406.573 | S35: 48277.178 | T35: 52095.623 | U35: 0.13025128 | Z35: EBITDA (before special items) | AA35: 28244 | AB35: 29661.017 | AC35: 32056.434 | AD35: 34670.61 | AE35: 36130.123 | AF35: 37379.371 | AG35: 0.057648012
B36: EBITDA % | C36: =IFERROR(C35/C9,"") -> 0.11419515 | D36: =IFERROR(D35/D9,"") -> 0.12276632 | E36: =IFERROR(E35/E9,"") -> 0.13204015 | F36: =IFERROR(F35/F9,"") -> 0.14105602 | G36: =IFERROR(G35/G9,"") -> 0.14527148 | H36: =IFERROR(H35/H9,"") -> 0.14850312 | J36: =AVERAGE(Model_DSV_ref!H140,Model_DSV_ref!N140,Model_DSV_ref!T140,Model_DSV_ref!Z140,Model_DSV_ref!AF140,Model_DSV_ref!AL140,Model_DSV_ref!AR140,Model_DSV_ref!AX140,Model_DSV_ref!BD140,Model_DSV_ref!BJ140,Model_DSV_ref!BP140) -> 0.10460533 | K36: =MIN(Model_DSV_ref!H140,Model_DSV_ref!N140,Model_DSV_ref!T140,Model_DSV_ref!Z140,Model_DSV_ref!AF140,Model_DSV_ref!AL140,Model_DSV_ref!AR140,Model_DSV_ref!AX140,Model_DSV_ref!BD140,Model_DSV_ref!BJ140,Model_DSV_ref!BP140) -> 0.062733405 | L36: =MAX(Model_DSV_ref!H140,Model_DSV_ref!N140,Model_DSV_ref!T140,Model_DSV_ref!Z140,Model_DSV_ref!AF140,Model_DSV_ref!AL140,Model_DSV_ref!AR140,Model_DSV_ref!AX140,Model_DSV_ref!BD140,Model_DSV_ref!BJ140,Model_DSV_ref!BP140) -> 0.15251517 | N36: EBITDA % | O36: 0.11419515 | P36: 0.12271352 | Q36: 0.13204691 | R36: 0.14096438 | S36: 0.14509664 | T36: 0.14824336 | V36: 0.10460533 | W36: 0.062733405 | X36: 0.15251517 | Z36: EBITDA % | AA36: 0.11419515 | AB36: 0.12278005 | AC36: 0.1322437 | AD36: 0.14131212 | AE36: 0.14549291 | AF36: 0.14871511 | AH36: 0.10460533 | AI36: 0.062733405 | AJ36: 0.15251517
B38: Net Debt | C38: =Model_DSV_ref!BP379 -> 53826 | D38: =Model_DSV_ref!BQ379 -> 42265.08 | E38: =Model_DSV_ref!BR379 -> 28425.856 | F38: =Model_DSV_ref!BS379 -> 15841.547 | G38: =Model_DSV_ref!BT379 -> 10321.469 | H38: =Model_DSV_ref!BU379 -> 5995.3565 | N38: Net Debt | O38: 53826 | P38: 42941.562 | Q38: 30528.807 | R38: 22083.2 | S38: 20315.435 | T38: 21213.536 | Z38: Net Debt | AA38: 53826 | AB38: 41772.682 | AC38: 28657.497 | AD38: 14340.052 | AE38: 4595.6779 | AF38: -3291.3487
B39: Net Debt / EBITDA (x) | C39: =IFERROR(C38/C35,"") -> 1.9057499 | D39: =IFERROR(D38/D35,"") -> 1.2641654 | E39: =IFERROR(E38/E35,"") -> 0.74715854 | F39: =IFERROR(F38/F35,"") -> 0.37101514 | G39: =IFERROR(G38/G35,"") -> 0.22564846 | H39: =IFERROR(H38/H35,"") -> 0.12326468 | N39: Net Debt / EBITDA (x) | O39: 1.9057499 | P39: 1.2745003 | Q39: 0.78276745 | R39: 0.49729574 | S39: 0.42080826 | T39: 0.40720379 | Z39: Net Debt / EBITDA (x) | AA39: 1.9057499 | AB39: 1.4083361 | AC39: 0.89397019 | AD39: 0.4136083 | AE39: 0.12719796 | AF39: -0.088052543
B41: ROIC | C41: =Model_DSV_ref!BP357 -> 0.086897782 | D41: =Model_DSV_ref!BQ357 -> 0.10626437 | E41: =Model_DSV_ref!BR357 -> 0.12403677 | F41: =Model_DSV_ref!BS357 -> 0.14120658 | G41: =Model_DSV_ref!BT357 -> 0.14974914 | H41: =Model_DSV_ref!BU357 -> 0.15762606 | J41: =AVERAGE(Model_DSV_ref!H357,Model_DSV_ref!N357,Model_DSV_ref!T357,Model_DSV_ref!Z357,Model_DSV_ref!AF357,Model_DSV_ref!AL357,Model_DSV_ref!AR357,Model_DSV_ref!AX357,Model_DSV_ref!BD357,Model_DSV_ref!BJ357,Model_DSV_ref!BP357) -> 0.1532729 | K41: =MIN(Model_DSV_ref!H357,Model_DSV_ref!N357,Model_DSV_ref!T357,Model_DSV_ref!Z357,Model_DSV_ref!AF357,Model_DSV_ref!AL357,Model_DSV_ref!AR357,Model_DSV_ref!AX357,Model_DSV_ref!BD357,Model_DSV_ref!BJ357,Model_DSV_ref!BP357) -> 0.086897782 | L41: =MAX(Model_DSV_ref!H357,Model_DSV_ref!N357,Model_DSV_ref!T357,Model_DSV_ref!Z357,Model_DSV_ref!AF357,Model_DSV_ref!AL357,Model_DSV_ref!AR357,Model_DSV_ref!AX357,Model_DSV_ref!BD357,Model_DSV_ref!BJ357,Model_DSV_ref!BP357) -> 0.22859953 | N41: ROIC | O41: 0.086897782 | P41: 0.10686652 | Q41: 0.12690842 | R41: 0.14660886 | S41: 0.15770211 | T41: 0.16827452 | V41: 0.1532729 | W41: 0.086897782 | X41: 0.22859953 | Z41: ROIC | AA41: 0.086897782 | AB41: 0.094078427 | AC41: 0.10446087 | AD41: 0.11504889 | AE41: 0.11924722 | AF41: 0.12276983 | AH41: 0.1532729 | AI41: 0.086897782 | AJ41: 0.22859953
B42: RONTA | C42: =Model_DSV_ref!BP371 -> 0.20133681 | D42: =Model_DSV_ref!BQ371 -> 0.21367006 | E42: =Model_DSV_ref!BR371 -> 0.22146343 | F42: =Model_DSV_ref!BS371 -> 0.22292824 | G42: =Model_DSV_ref!BT371 -> 0.2268189 | H42: =Model_DSV_ref!BU371 -> 0.2300744 | J42: =AVERAGE(Model_DSV_ref!H371,Model_DSV_ref!N371,Model_DSV_ref!T371,Model_DSV_ref!Z371,Model_DSV_ref!AF371,Model_DSV_ref!AL371,Model_DSV_ref!AR371,Model_DSV_ref!AX371,Model_DSV_ref!BD371,Model_DSV_ref!BJ371,Model_DSV_ref!BP371) -> 0.33779764 | K42: =MIN(Model_DSV_ref!H371,Model_DSV_ref!N371,Model_DSV_ref!T371,Model_DSV_ref!Z371,Model_DSV_ref!AF371,Model_DSV_ref!AL371,Model_DSV_ref!AR371,Model_DSV_ref!AX371,Model_DSV_ref!BD371,Model_DSV_ref!BJ371,Model_DSV_ref!BP371) -> 0.09857738 | L42: =MAX(Model_DSV_ref!H371,Model_DSV_ref!N371,Model_DSV_ref!T371,Model_DSV_ref!Z371,Model_DSV_ref!AF371,Model_DSV_ref!AL371,Model_DSV_ref!AR371,Model_DSV_ref!AX371,Model_DSV_ref!BD371,Model_DSV_ref!BJ371,Model_DSV_ref!BP371) -> 0.62210874 | N42: RONTA | O42: 0.20133681 | P42: 0.21652431 | Q42: 0.23137707 | R42: 0.24473275 | S42: 0.26002506 | T42: 0.27810641 | V42: 0.33779764 | W42: 0.09857738 | X42: 0.62210874 | Z42: RONTA | AA42: 0.20133681 | AB42: 0.18876005 | AC42: 0.18805393 | AD42: 0.18054847 | AE42: 0.17392065 | AF42: 0.16868577 | AH42: 0.33779764 | AI42: 0.09857738 | AJ42: 0.62210874
B44: Implied Market Cap (DKKm) | E44: =E27*E21/1000 -> 347780.56 | F44: =F27*F21/1000 -> 407672.43 | G44: =G27*G21/1000 -> 444087.35 | H44: =H27*H21/1000 -> 479929.12 | N44: Implied Market Cap (DKKm) | Q44: 396605.35 | R44: 472629.15 | S44: 523468.37 | T44: 575032.47 | Z44: Implied Market Cap (DKKm) | AC44: 237715.74 | AD44: 268302.55 | AE44: 283934.23 | AF44: 298246.22
B45: (+) Net Debt | E45: =E38 -> 28425.856 | F45: =F38 -> 15841.547 | G45: =G38 -> 10321.469 | H45: =H38 -> 5995.3565 | N45: (+) Net Debt | Q45: 30528.807 | R45: 22083.2 | S45: 20315.435 | T45: 21213.536 | Z45: (+) Net Debt | AC45: 28657.497 | AD45: 14340.052 | AE45: 4595.6779 | AF45: -3291.3487
B46: Implied Enterprise Value (DKKm) | E46: =E44+E45 -> 376206.42 | F46: =F44+F45 -> 423513.98 | G46: =G44+G45 -> 454408.82 | H46: =H44+H45 -> 485924.47 | N46: Implied Enterprise Value (DKKm) | Q46: 427134.15 | R46: 494712.35 | S46: 543783.81 | T46: 596246.01 | Z46: Implied Enterprise Value (DKKm) | AC46: 266373.24 | AD46: 282642.61 | AE46: 288529.91 | AF46: 294954.87
B47: Implied EV / EBITDA (x) | E47: =IFERROR(E46/E35,"") -> 9.8883861 | F47: =IFERROR(F46/F35,"") -> 9.9188609 | G47: =IFERROR(G46/G35,"") -> 9.9343078 | H47: =IFERROR(H46/H35,"") -> 9.9906193 | N47: Implied EV / EBITDA (x) | Q47: 10.951843 | R47: 11.140521 | S47: 11.263786 | T47: 11.445223 | Z47: Implied EV / EBITDA (x) | AC47: 8.3095092 | AD47: 8.1522247 | AE47: 7.9858546 | AF47: 7.8908463

Sheet DCF
B2: DCF VALUATION
B4: 1. WACC BUILD
B5: Risk-free rate (US 10Y govt) | C5: 0.04
B6: Equity risk premium | C6: 0.055 | D6: Damodaran global ERP estimate
B7: Levered beta | C7: 0.9 | D7: DSV reported beta ~0.4; industry unlevered ~0.9 — blended to 0.9 as DSV de-risks post-Schenker
B8: Cost of equity | C8: =C5+C7*C6 -> 0.0895
B9: Pre-tax cost of debt | C9: 0.045 | D9: DSV A3/A- bonds, 5Y yield + spread
B10: Tax rate | C10: 0.25 | D10: Normalised per CMD slide 142
B11: After-tax cost of debt | C11: =C9*(1-C10) -> 0.03375
B12: Target D/V | C12: 0.15 | D12: Target leverage; net debt / total capital
B13: WACC | C13: =C8*(1-C12)+C11*C12 -> 0.0811375
B15: Valuation date (live) | C15: =TODAY() -> 46169 | D15: Periods = (Dec-31-Year − today) / 365.25; valuation point YE 2026
B16: 2. UNLEVERED FREE CASH FLOW BUILD
D17: 2026E | E17: 2027E | F17: 2028E | G17: 2029E | H17: 2030E | I17: 2031E | J17: 2032E | K17: 2033E | L17: 2034E | M17: 2035E | N17: Terminal
B18: EBIT before special items | D18: =Model_DSV_ref!BQ153 -> 24150.633 | E18: =Model_DSV_ref!BR153 -> 28468.523 | F18: =Model_DSV_ref!BS153 -> 32877.625 | G18: =Model_DSV_ref!BT153 -> 35569.692 | H18: =Model_DSV_ref!BU153 -> 38196.305 | I18: =H18*(1+0.04) -> 39724.157 | J18: =I18*(1+0.035) -> 41114.503 | K18: =J18*(1+0.03) -> 42347.938 | L18: =K18*(1+0.0275) -> 43512.506 | M18: =L18*(1+0.025) -> 44600.319
B19: × (1 − tax rate) | D19: =1-$C$10 -> 0.75 | E19: =1-$C$10 -> 0.75 | F19: =1-$C$10 -> 0.75 | G19: =1-$C$10 -> 0.75 | H19: =1-$C$10 -> 0.75 | I19: =1-$C$10 -> 0.75 | J19: =1-$C$10 -> 0.75 | K19: =1-$C$10 -> 0.75 | ... M19: =1-$C$10 -> 0.75
B20: NOPAT | D20: =D18*D19 -> 18112.975 | E20: =E18*E19 -> 21351.392 | F20: =F18*F19 -> 24658.219 | G20: =G18*G19 -> 26677.269 | H20: =H18*H19 -> 28647.229 | I20: =I18*I19 -> 29793.118 | J20: =J18*J19 -> 30835.877 | K20: =K18*K19 -> 31760.953 | ... M20: =M18*M19 -> 33450.239
B21: plus D&A | D21: =Model_DSV_ref!BQ152 -> 9282.5546 | E21: =Model_DSV_ref!BR152 -> 9576.7569 | F21: =Model_DSV_ref!BS152 -> 9820.2197 | G21: =Model_DSV_ref!BT152 -> 10171.674 | H21: =Model_DSV_ref!BU152 -> 10441.768 | I21: =H21*(1+0.04) -> 10859.439 | J21: =I21*(1+0.035) -> 11239.52 | K21: =J21*(1+0.03) -> 11576.705 | L21: =K21*(1+0.0275) -> 11895.065 | M21: =L21*(1+0.025) -> 12192.441
B22: − Capex (intangibles + PP&E) | D22: =-(Model_DSV_ref!BQ146)*0.017 -> -4629.6426 | E22: =-(Model_DSV_ref!BR146)*0.017 -> -4898.2809 | F22: =-(Model_DSV_ref!BS146)*0.017 -> -5145.9224 | G22: =-(Model_DSV_ref!BT146)*0.017 -> -5352.7592 | H22: =-(Model_DSV_ref!BU146)*0.017 -> -5567.8778 | I22: =H22*(1+0.04) -> -5790.5929 | J22: =I22*(1+0.035) -> -5993.2637 | K22: =J22*(1+0.03) -> -6173.0616 | L22: =K22*(1+0.0275) -> -6342.8208 | M22: =L22*(1+0.025) -> -6501.3913
B23: − Δ Working capital | D23: =Model_DSV_ref!BQ213 -> -1370.494 | E23: =Model_DSV_ref!BR213 -> 62.969628 | F23: =Model_DSV_ref!BS213 -> -282.73504 | G23: =Model_DSV_ref!BT213 -> -935.20476 | H23: =Model_DSV_ref!BU213 -> -964.10906 | I23: =H23*(1+0.04) -> -1002.6734 | J23: =I23*(1+0.035) -> -1037.767 | K23: =J23*(1+0.03) -> -1068.9 | L23: =K23*(1+0.0275) -> -1098.2947 | M23: =L23*(1+0.025) -> -1125.7521
B24: Unlevered FCF | D24: =D20+D21+D22+D23 -> 21395.393 | E24: =E20+E21+E22+E23 -> 26092.838 | F24: =F20+F21+F22+F23 -> 29049.781 | G24: =G20+G21+G22+G23 -> 30560.98 | H24: =H20+H21+H22+H23 -> 32557.01 | I24: =H24*(1+0.04) -> 33859.291 | J24: =I24*(1+0.035) -> 35044.366 | K24: =J24*(1+0.03) -> 36095.697 | L24: =K24*(1+0.0275) -> 37088.329 | M24: =L24*(1+0.025) -> 38015.537 | N24: =M24*(1+$C$27) -> 38965.925
B25: Terminal Value (Gordon Growth) | N25: =N24/($C$13-$C$27) -> 694115.79
B27: Terminal growth rate | C27: 0.025
B29: Discount period (year #) | D29: =(DATE(2026,12,31)-$C$15)/365.25 -> 0.59685147 | E29: =(DATE(2027,12,31)-$C$15)/365.25 -> 1.596167 | F29: =(DATE(2028,12,31)-$C$15)/365.25 -> 2.5982204 | G29: =(DATE(2029,12,31)-$C$15)/365.25 -> 3.5975359 | H29: =(DATE(2030,12,31)-$C$15)/365.25 -> 4.5968515 | I29: =(DATE(2031,12,31)-$C$15)/365.25 -> 5.596167 | J29: =(DATE(2032,12,31)-$C$15)/365.25 -> 6.5982204 | K29: =(DATE(2033,12,31)-$C$15)/365.25 -> 7.5975359 | L29: =(DATE(2034,12,31)-$C$15)/365.25 -> 8.5968515 | M29: =(DATE(2035,12,31)-$C$15)/365.25 -> 9.596167 | N29: =M29 -> 9.596167
B30: Discount factor | D30: =1/(1+$C$13)^D29 -> 0.9545048 | E30: =1/(1+$C$13)^E29 -> 0.88291801 | F30: =1/(1+$C$13)^F29 -> 0.81652573 | G30: =1/(1+$C$13)^G29 -> 0.75528721 | H30: =1/(1+$C$13)^H29 -> 0.69864152 | I30: =1/(1+$C$13)^I29 -> 0.64624419 | J30: =1/(1+$C$13)^J29 -> 0.59764893 | K30: =1/(1+$C$13)^K29 -> 0.55282593 | ... N30: =1/(1+$C$13)^N29 -> 0.47301283
B31: PV of UFCF | D31: =D24*D30 -> 20422.005 | E31: =E24*E30 -> 23037.837 | F31: =F24*F30 -> 23719.893 | G31: =G24*G30 -> 23082.317 | H31: =H24*H30 -> 22745.679 | I31: =I24*I30 -> 21881.37 | J31: =J24*J30 -> 20944.228 | K31: =K24*K30 -> 19954.637 | ... M31: =M24*M30 -> 17981.837 | N31: =N25*N30 -> 328325.68
B34: 3. VALUATION SUMMARY
B35: Sum of PV (explicit + fade) | C35: =SUM(D31:M31) -> 212735.46
B36: PV of Terminal Value | C36: =N31 -> 328325.68
B37: Enterprise Value | C37: =C35+C36 -> 541061.14
B38: Less: Net debt (Model BQ 2026YE) | C38: =Model_DSV_ref!BQ356 -> 42265.08
B39: Equity Value | C39: =C37-C38 -> 498796.06
B40: Diluted shares ('000) | C40: =Model_DSV_ref!BQ168 -> 234597.21
B41: Implied share price (DKK) | C41: =C39*1000/C40 -> 2126.1807
B42: Current share price (DKK) | C42: 1571
B43: Implied upside / (downside) | C43: =C41/C42-1 -> 0.35339318
B46: 4. SENSITIVITY: IMPLIED PRICE - WACC x Terminal Growth
B48: WACC (across):
B49: g (down) / WACC | D49: 0.065 | E49: 0.07 | F49: 0.075 | G49: 0.08 | H49: 0.085
B50: 0.02 | D50: {=IFERROR((SUMPRODUCT($D$24:$M$24/(1+D$49)^$D$29:$M$29)+($M$24*(1+$B50)/(D$49-$B50))/(1+D$49)^$M$29-$C$38)*1000/$C$40,"")} -> 2804.2428 | E50: {=IFERROR((SUMPRODUCT($D$24:$M$24/(1+E$49)^$D$29:$M$29)+($M$24*(1+$B50)/(E$49-$B50))/(1+E$49)^$M$29-$C$38)*1000/$C$40,"")} -> 2501.4386 | F50: {=IFERROR((SUMPRODUCT($D$24:$M$24/(1+F$49)^$D$29:$M$29)+($M$24*(1+$B50)/(F$49-$B50))/(1+F$49)^$M$29-$C$38)*1000/$C$40,"")} -> 2253.839 | G50: {=IFERROR((SUMPRODUCT($D$24:$M$24/(1+G$49)^$D$29:$M$29)+($M$24*(1+$B50)/(G$49-$B50))/(1+G$49)^$M$29-$C$38)*1000/$C$40,"")} -> 2047.6382 | H50: {=IFERROR((SUMPRODUCT($D$24:$M$24/(1+H$49)^$D$29:$M$29)+($M$24*(1+$B50)/(H$49-$B50))/(1+H$49)^$M$29-$C$38)*1000/$C$40,"")} -> 1873.2788
B51: 0.0225 | D51: {=IFERROR((SUMPRODUCT($D$24:$M$24/(1+D$49)^$D$29:$M$29)+($M$24*(1+$B51)/(D$49-$B51))/(1+D$49)^$M$29-$C$38)*1000/$C$40,"")} -> 2927.5178 | E51: {=IFERROR((SUMPRODUCT($D$24:$M$24/(1+E$49)^$D$29:$M$29)+($M$24*(1+$B51)/(E$49-$B51))/(1+E$49)^$M$29-$C$38)*1000/$C$40,"")} -> 2596.79 | F51: {=IFERROR((SUMPRODUCT($D$24:$M$24/(1+F$49)^$D$29:$M$29)+($M$24*(1+$B51)/(F$49-$B51))/(1+F$49)^$M$29-$C$38)*1000/$C$40,"")} -> 2329.1856 | G51: {=IFERROR((SUMPRODUCT($D$24:$M$24/(1+G$49)^$D$29:$M$29)+($M$24*(1+$B51)/(G$49-$B51))/(1+G$49)^$M$29-$C$38)*1000/$C$40,"")} -> 2108.2341 | H51: {=IFERROR((SUMPRODUCT($D$24:$M$24/(1+H$49)^$D$29:$M$29)+($M$24*(1+$B51)/(H$49-$B51))/(1+H$49)^$M$29-$C$38)*1000/$C$40,"")} -> 1922.7355
B52: 0.025 | D52: {=IFERROR((SUMPRODUCT($D$24:$M$24/(1+D$49)^$D$29:$M$29)+($M$24*(1+$B52)/(D$49-$B52))/(1+D$49)^$M$29-$C$38)*1000/$C$40,"")} -> 3066.2022 | E52: {=IFERROR((SUMPRODUCT($D$24:$M$24/(1+E$49)^$D$29:$M$29)+($M$24*(1+$B52)/(E$49-$B52))/(1+E$49)^$M$29-$C$38)*1000/$C$40,"")} -> 2702.7359 | F52: {=IFERROR((SUMPRODUCT($D$24:$M$24/(1+F$49)^$D$29:$M$29)+($M$24*(1+$B52)/(F$49-$B52))/(1+F$49)^$M$29-$C$38)*1000/$C$40,"")} -> 2412.0669 | G52: {=IFERROR((SUMPRODUCT($D$24:$M$24/(1+G$49)^$D$29:$M$29)+($M$24*(1+$B52)/(G$49-$B52))/(1+G$49)^$M$29-$C$38)*1000/$C$40,"")} -> 2174.3387 | H52: {=IFERROR((SUMPRODUCT($D$24:$M$24/(1+H$49)^$D$29:$M$29)+($M$24*(1+$B52)/(H$49-$B52))/(1+H$49)^$M$29-$C$38)*1000/$C$40,"")} -> 1976.3136
B53: 0.0275 | D53: {=IFERROR((SUMPRODUCT($D$24:$M$24/(1+D$49)^$D$29:$M$29)+($M$24*(1+$B53)/(D$49-$B53))/(1+D$49)^$M$29-$C$38)*1000/$C$40,"")} -> 3223.3778 | E53: {=IFERROR((SUMPRODUCT($D$24:$M$24/(1+E$49)^$D$29:$M$29)+($M$24*(1+$B53)/(E$49-$B53))/(1+E$49)^$M$29-$C$38)*1000/$C$40,"")} -> 2821.1461 | F53: {=IFERROR((SUMPRODUCT($D$24:$M$24/(1+F$49)^$D$29:$M$29)+($M$24*(1+$B53)/(F$49-$B53))/(1+F$49)^$M$29-$C$38)*1000/$C$40,"")} -> 2503.6726 | G53: {=IFERROR((SUMPRODUCT($D$24:$M$24/(1+G$49)^$D$29:$M$29)+($M$24*(1+$B53)/(G$49-$B53))/(1+G$49)^$M$29-$C$38)*1000/$C$40,"")} -> 2246.7389 | H53: {=IFERROR((SUMPRODUCT($D$24:$M$24/(1+H$49)^$D$29:$M$29)+($M$24*(1+$B53)/(H$49-$B53))/(1+H$49)^$M$29-$C$38)*1000/$C$40,"")} -> 2034.5506
B54: 0.03 | D54: {=IFERROR((SUMPRODUCT($D$24:$M$24/(1+D$49)^$D$29:$M$29)+($M$24*(1+$B54)/(D$49-$B54))/(1+D$49)^$M$29-$C$38)*1000/$C$40,"")} -> 3403.0071 | E54: {=IFERROR((SUMPRODUCT($D$24:$M$24/(1+E$49)^$D$29:$M$29)+($M$24*(1+$B54)/(E$49-$B54))/(1+E$49)^$M$29-$C$38)*1000/$C$40,"")} -> 2954.3575 | F54: {=IFERROR((SUMPRODUCT($D$24:$M$24/(1+F$49)^$D$29:$M$29)+($M$24*(1+$B54)/(F$49-$B54))/(1+F$49)^$M$29-$C$38)*1000/$C$40,"")} -> 2605.4566 | G54: {=IFERROR((SUMPRODUCT($D$24:$M$24/(1+G$49)^$D$29:$M$29)+($M$24*(1+$B54)/(G$49-$B54))/(1+G$49)^$M$29-$C$38)*1000/$C$40,"")} -> 2326.3792 | H54: {=IFERROR((SUMPRODUCT($D$24:$M$24/(1+H$49)^$D$29:$M$29)+($M$24*(1+$B54)/(H$49-$B54))/(1+H$49)^$M$29-$C$38)*1000/$C$40,"")} -> 2098.0819
B57: 5. REVERSE DCF
B58: At current DKK 1,571, market implies materially lower long-term FCF than model. To run: Data tab > What-If Analysis > Goal Seek. Set C41 to 1571 by changing E18 (2027 EBIT).
B60: 6. MAUBOUSSIN EV / NOPAT — TWO-STAGE FRAMEWORK
B61: EV/NOPAT = 1/r + [g × (1 − r/ROIIC) / (r × (r − g))] × [1 − ((1+g)/(1+r))^N]
B62: Formula source: Mauboussin & Rappaport, "Expectations Investing" (2021); Counterpoint Global, "What Does a Price-Earnings Multiple Mean?" 2020.
B64: Input | C64: Value | D64: Rationale (DSV characteristics)
B65: r (Cost of capital / WACC) | C65: =$C$13 -> 0.0811375 | D65: Linked from Section 1 WACC build
B66: g (NOPAT growth, Stage 1) | C66: 0.07 | D66: DSV NOPAT CAGR 2024–2030E = ~15%; conservatively normalised to 7% post-Schenker integration (in line with global logistics market growth + share gains)
B67: ROIIC (Return on incremental invested capital) | C67: 0.25 | D67: Asset-light forwarding model; pre-Schenker DSV ROIIC was 25–35%; post-Schenker ROIC reset lower but incremental capital is asset-light. Use 25%.
B68: N (Years of value creation / CAP) | C68: 8 | D68: Top-3 global forwarder with scale moat + 5+ yr Schenker integration runway; competitive advantage period 7–10 yrs typical for high-ROIC compounders
B70: Calculation | C70: Value
B71: Steady-state component: 1 / r | C71: =1/C65 -> 12.324757
B72: Value-creation factor: 1 − r / ROIIC | C72: =1-C65/C67 -> 0.67545
B73: Growth multiplier: g × (1 − r/ROIIC) / (r × (r − g)) | C73: =C66*C72/(C65*(C65-C66)) -> 52.321707
B74: Time decay: 1 − ((1+g)/(1+r))^N | C74: =1-((1+C66)/(1+C65))^C68 -> 0.079502168
B75: PVGO component (growth value) | C75: =C73*C74 -> 4.1596891
B76: Mauboussin EV / NOPAT (steady-state + PVGO) | C76: =C71+C75 -> 16.484446
B78: VALUATION — Applied to 2028E NOPAT | C78: DKKm
B79: 2028E EBIT (Model BS153) | C79: =Model_DSV_ref!BS153 -> 32877.625
B80: Tax rate (cash, from WACC build) | C80: =$C$10 -> 0.25
B81: 2028E NOPAT = EBIT × (1 − t) | C81: =C79*(1-C80) -> 24658.219
B82: × Mauboussin EV/NOPAT multiple | C82: =C76 -> 16.484446
B83: Implied Enterprise Value (2028E basis) | C83: =C81*C82 -> 406477.08
B84: Less: YE2027 Net debt (forward into 2028) | C84: =Model_DSV_ref!BR356 -> 28425.856
B85: Implied Equity Value | C85: =C83-C84 -> 378051.23
B86: Diluted shares 2028E ('000) | C86: =Model_DSV_ref!BS168 -> 226621.29
B87: Implied share price 2028 (DKK) | C87: =C85*1000/C86 -> 1668.207
B89: Current share price | C89: =C42 -> 1571
B90: Implied upside / (downside) | C90: =C87/C89-1 -> 0.061875897
B92: MARKET-IMPLIED EV/NOPAT TODAY | C92: DKKm
B93: Current Market Cap (Spot × FDSO) | C93: =C42*C40/1000 -> 368552.22
B94: Plus: YE2026 Net debt | C94: =C38 -> 42265.08
B95: Implied Enterprise Value (today) | C95: =C93+C94 -> 410817.3
B96: DSV's Market-Implied EV/NOPAT (on 2028E NOPAT) | C96: =C95/C81 -> 16.660461
B98: Multiple Gap (Mauboussin − Market) | C98: =C76-C96 -> -0.17601485
