Workbook

Sheet Model
CF1: SCENARIO SWITCH ▼ (Bull / Base / Bear) — drives all scenario-linked forecast drivers
B2: Lincoln Electric Holdings, Inc. (Nasdaq: LECO) — 3-Statement Financial Model | CF2: Base
B3: US GAAP as reported · USD millions (per-share data in USD; shares in millions) · Source: Lincoln Electric Forms 10-K / 10-Q and Form 8-K earnings releases (Ex. 99.1), SEC EDGAR CIK 0000059527 (investor-relations releases are the same documents as filed on EDGAR); FY26 outlook from public coverage of the Q2-26 call (ir.lincolnelectric.com slides not reachable from the build environment)
B4: Basis notes: calendar fiscal year. Net sales = external sales. Segments: Americas / International Welding / Harris from 2016 (2013–Q3/15 recast by LECO, 8-K 10-Feb-2016); legacy North America / Europe / Asia Pacific / South America Welding + Harris to Q4/15 (memo). Per-share data restated for the 2-for-1 split (31-May-2011). Venezuela deconsolidated Jul-2016. ASU 2017-07 (2018): pension settlements below operating income. Adjusted EBITDA is model-derived (LECO publishes Adjusted EBIT / adjusted operating income / adjusted EPS).
CH5: Forecast | CI5: Historical | CJ5: Historical | CK5: Historical
B6: (USDm) | C6: 2006 | D6: 2007 | E6: 2008 | F6: 2009 | G6: 2010 | H6: 2011 | I6: 2012 | J6: Q1/13 | K6: Q2/13 | L6: Q3/13 | M6: Q4/13 | N6: 2013 | O6: Q1/14 | P6: Q2/14 | Q6: Q3/14 | R6: Q4/14 | S6: 2014 | T6: Q1/15 | U6: Q2/15 | V6: Q3/15 | W6: Q4/15 | X6: 2015 | Y6: Q1/16 | Z6: Q2/16 | AA6: Q3/16 | AB6: Q4/16 | AC6: 2016 | AD6: Q1/17 | AE6: Q2/17 | AF6: Q3/17 | AG6: Q4/17 | AH6: 2017 | AI6: Q1/18 | AJ6: Q2/18 | AK6: Q3/18 | AL6: Q4/18 | AM6: 2018 | AN6: Q1/19 | AO6: Q2/19 | AP6: Q3/19 | AQ6: Q4/19 | AR6: 2019 | AS6: Q1/20 | AT6: Q2/20 | AU6: Q3/20 | AV6: Q4/20 | AW6: 2020 | AX6: Q1/21 | AY6: Q2/21 | AZ6: Q3/21 | BA6: Q4/21 | BB6: 2021 | BC6: Q1/22 | BD6: Q2/22 | BE6: Q3/22 | BF6: Q4/22 | BG6: 2022 | BH6: Q1/23 | BI6: Q2/23 | BJ6: Q3/23 | BK6: Q4/23 | BL6: 2023 | BM6: Q1/24 | BN6: Q2/24 | BO6: Q3/24 | BP6: Q4/24 | BQ6: 2024 | BR6: Q1/25 | BS6: Q2/25 | BT6: Q3/25 | BU6: Q4/25 | BV6: 2025 | BW6: Q1/26 | BX6: Q2/26 | BY6: Q3/26E | BZ6: Q4/26E | CA6: 2026E | CB6: 2027E | CC6: 2028E | CD6: 2029E | CE6: 2030E | CF6: Modelling Notes | CH6: 5Y CAGR | CI6: 5Y CAGR | CJ6: 10Y CAGR | CK6: 19Y CAGR
CH7: 25-'30 | CI7: 20-'25 | CJ7: 15-'25 | CK7: 06-'25
B8: SEGMENT P&L — AMERICAS WELDING · INTERNATIONAL WELDING · THE HARRIS PRODUCTS GROUP (net sales build: volume + price + acquisitions + FX → segment Adjusted EBIT) | CF8: SEGMENT BUILD — modelling logic (prior-period net sales × (1 + volume + price + acquisitions + FX) → net sales × Adjusted EBIT margin → segment Adjusted EBIT)
B9: Americas Welding (arc welding equipment & consumables, cutting, automation — U.S., Canada, Mexico, South America) | CF9: AW — modelling logic | CN9: SCENARIO INPUT TABLE — driver assumptions per Bull / Base / Bear | CO9: Bull | CP9: Base | CQ9: Bear | CR9: Bull / Bear = Base + Δ (Δ inputs on each block header). Outlook block = high / mid / low end of FY26 ranges.
B10: Net sales (external customers) | N10: 1848.663 | O10: 441.849 | P10: 465.524 | Q10: 469.39 | R10: 460.907 | S10: 1837.67 | T10: 448.837 | U10: 451.001 | V10: 454.172 | W10: 387.34 | X10: 1741.35 | Y10: 359.008 | Z10: 388.372 | AA10: 377.52 | AB10: 370.082 | AC10: 1494.982 | AD10: 383.324 | AE10: 405.147 | AF10: 398.289 | AG10: 423.019 | AH10: 1609.779 | AI10: 434.772 | AJ10: 462.515 | AK10: 454.01 | AL10: 455.217 | AM10: 1806.514 | AN10: 457.719 | AO10: 476.607 | AP10: 443.521 | AQ10: 437.899 | AR10: 1815.746 | AS10: 418.535 | AT10: 333.229 | AU10: 371.535 | AV10: 386.571 | AW10: 1509.87 | AX10: 425.242 | AY10: 457.468 | AZ10: 461.508 | BA10: 480.263 | BB10: 1824.481 | BC10: 534.055 | BD10: 595.659 | BE10: 585.628 | BF10: 573.592 | BG10: 2288.934 | BH10: 658.645 | BI10: 676.966 | BJ10: 665.228 | BK10: 654.707 | BL10: 2655.546 | BM10: 624.099 | BN10: 648.936 | BO10: 637.026 | BP10: 654.786 | BQ10: 2564.847 | BR10: 653.107 | BS10: 696.73 | BT10: 691.794 | BU10: 681.93 | BV10: 2723.561 | BW10: 706.225 | BX10: 774.438 | BY10: =BT10*(1+BY17) -> 772.94345 | BZ10: =BU10*(1+BZ17) -> 761.92238 | CA10: =SUM(BW10:BZ10) -> 3015.5288 | CB10: =CA10*(1+CB17) -> 3196.4606 | CC10: =CB10*(1+CC17) -> 3372.2659 | CD10: =CC10*(1+CD17) -> 3540.8792 | CE10: =CD10*(1+CE17) -> 3717.9231 | CF10: Q3/Q4-26E: prior-year quarter × (1 + volume + price + acquisitions + FX). 2027E+: prior year × (1 + Σ drivers). Current 3-segment structure from 2016 (2013–Q3/15 recast by LECO in the 8-K of 10-Feb-2016; Q4/15 derived = FY15 recast − 9M/15 recast). | CH10: =IFERROR((CE10/BV10)^(1/5)-1,"n/m") -> 0.064223048 | CI10: =IFERROR((BV10/AW10)^(1/5)-1,"n/m") -> 0.12522536 | CJ10: =IFERROR((BV10/X10)^(1/10)-1,"n/m") -> 0.045743331 | CK10: =IFERROR((BV10/C10)^(1/19)-1,"n/m") -> n/m
B11: Net sales y/y % | D11: =IF(AND(ISNUMBER(D10),ISNUMBER(C10)),IFERROR(D10/C10-1,""),"") | E11: =IF(AND(ISNUMBER(E10),ISNUMBER(D10)),IFERROR(E10/D10-1,""),"") | F11: =IF(AND(ISNUMBER(F10),ISNUMBER(E10)),IFERROR(F10/E10-1,""),"") | G11: =IF(AND(ISNUMBER(G10),ISNUMBER(F10)),IFERROR(G10/F10-1,""),"") | H11: =IF(AND(ISNUMBER(H10),ISNUMBER(G10)),IFERROR(H10/G10-1,""),"") | I11: =IF(AND(ISNUMBER(I10),ISNUMBER(H10)),IFERROR(I10/H10-1,""),"") | N11: =IF(AND(ISNUMBER(N10),ISNUMBER(I10)),IFERROR(N10/I10-1,""),"") | O11: =IF(AND(ISNUMBER(O10),ISNUMBER(J10)),IFERROR(O10/J10-1,""),"") | P11: =IF(AND(ISNUMBER(P10),ISNUMBER(K10)),IFERROR(P10/K10-1,""),"") | Q11: =IF(AND(ISNUMBER(Q10),ISNUMBER(L10)),IFERROR(Q10/L10-1,""),"") | R11: =IF(AND(ISNUMBER(R10),ISNUMBER(M10)),IFERROR(R10/M10-1,""),"") | S11: =IF(AND(ISNUMBER(S10),ISNUMBER(N10)),IFERROR(S10/N10-1,""),"") -> -0.0059464597 | T11: =IF(AND(ISNUMBER(T10),ISNUMBER(O10)),IFERROR(T10/O10-1,""),"") -> 0.015815358 | U11: =IF(AND(ISNUMBER(U10),ISNUMBER(P10)),IFERROR(U10/P10-1,""),"") -> -0.031197103 | ... BX11: =IF(AND(ISNUMBER(BX10),ISNUMBER(BS10)),IFERROR(BX10/BS10-1,""),"") -> 0.11153244 | BY11: =IFERROR(BY10/BT10-1,"") -> 0.11730291 | BZ11: =IFERROR(BZ10/BU10-1,"") -> 0.11730291 | CA11: =IFERROR(CA10/BV10-1,"") -> 0.10720077 | CB11: =IFERROR(CB10/CA10-1,"") -> 0.06 | CC11: =IFERROR(CC10/CB10-1,"") -> 0.055 | CD11: =IFERROR(CD10/CC10-1,"") -> 0.05 | CE11: =IFERROR(CE10/CD10-1,"") -> 0.05 | CN11: FY26 outlook — Q2-26 call (30-Jul-26); Q3 update at Jefferies conf. (10-Sep-26) | CO11: High | CP11: Mid | CQ11: Low | CR11: LECO publishes its outlook on the earnings call / slides (not in the 8-K); figures from public coverage of the call — see sources in note column.
B12: Volume % before outlook calibration (Q3/Q4-26E helper) | BY12: =$BX$13 -> 0.071339 | BZ12: =$BX$13 -> 0.071339 | CF12: Q2/26 y/y volume held for Q3/Q4-26E before the FY26 net-sales calibration (Group block). | CN12: FY26 net sales growth % (y/y) | CO12: 0.13 | CP12: 0.115 | CQ12: 0.1 | CR12: Raised on Q2-26 call to "low-double-digit" net sales growth (from high-single-digit in Q1-26). Drives the Q3/Q4-26E volume calibration.
B13: Volume % (company: change in net sales due to volume) | Y13: -0.189519 | Z13: -0.133035 | AA13: -0.179091 | AB13: -0.057611 | AC13: -0.142829 | AD13: 0.041116 | AE13: 0.017421 | AF13: 0.022253 | AG13: 0.100999 | AH13: 0.045021 | AI13: 0.074511 | AJ13: 0.076572 | AK13: 0.057958 | AL13: -0.000972 | AM13: 0.051099 | AN13: -0.028509 | AO13: -0.036228 | AP13: -0.045384 | AQ13: -0.064868 | AR13: -0.043888 | AS13: -0.082347 | AT13: -0.291718 | AU13: -0.155636 | AV13: -0.124257 | AW13: -0.165313 | AX13: -0.009055 | AY13: 0.27094 | AZ13: 0.113962 | BA13: 0.092503 | BB13: 0.109013 | BC13: 0.051745 | BD13: 0.098988 | BE13: 0.113803 | BF13: 0.076525 | BG13: 0.085811 | BH13: 0.10982 | BI13: 0.057724 | BJ13: 0.003538 | BK13: 0.025722 | BL13: 0.047996 | BM13: -0.064759 | BN13: -0.067455 | BO13: -0.086124 | BP13: -0.07155 | BQ13: -0.072472 | BR13: -0.039641 | BS13: -0.034435 | BT13: -0.023564 | BU13: -0.06931 | BV13: -0.041905 | BW13: -0.004035 | BX13: 0.071339 | BY13: =BY12+BY118 -> 0.077109914 | BZ13: =BZ12+BZ118 -> 0.077109914 | CA13: =IFERROR(SUMPRODUCT(BR10:BU10,BW13:BZ13)/SUM(BR10:BU10),"") -> 0.05617516 | CB13: =CHOOSE(MATCH($CF$2,{"Bull","Base","Bear"},0),$CO$27,$CP$27,$CQ$27) -> 0.03 | CC13: =CHOOSE(MATCH($CF$2,{"Bull","Base","Bear"},0),$CO$28,$CP$28,$CQ$28) -> 0.03 | CD13: =CHOOSE(MATCH($CF$2,{"Bull","Base","Bear"},0),$CO$29,$CP$29,$CQ$29) -> 0.025 | CE13: =CHOOSE(MATCH($CF$2,{"Bull","Base","Bear"},0),$CO$30,$CP$30,$CQ$30) -> 0.025 | CF13: Historical = LECO "Change in Net Sales by Segment" table (8-K Ex.99.1) ÷ prior-year segment net sales. Q3/Q4-26E: Q2/26 y/y + FY26 calibration Δ. 2027E–30E: scenario lever (Bull/Base/Bear table →). | CN13: 2H/26 incremental Adjusted EBIT margin % (Δ Adj. EBIT / Δ net sales, 2H y/y) | CO13: 0.27 | CP13: 0.23 | CQ13: 0.18 | CR13: Q2-26 call: "mid-20% incremental margin" for the balance of 2026; 10-Sep-26 Jefferies: Q3 incrementals tracking "low 20s" on inflation / supply-chain costs. Drives the Q3/Q4-26E margin calibration.
B14: Price % | Y14: 0.178951 | Z14: 0.429502 | AA14: -0.012429 | AB14: -0.000454 | AC14: 0.154021 | AD14: 0.015376 | AE14: 0.027057 | AF14: 0.024362 | AG14: 0.029139 | AH14: 0.024087 | AI14: 0.046128 | AJ14: 0.054198 | AK14: 0.090708 | AL14: 0.083377 | AM14: 0.068977 | AN14: 0.063086 | AO14: 0.025078 | AP14: -0.012341 | AQ14: -0.016957 | AR14: 0.014229 | AS14: -0.01178 | AT14: -0.002948 | AU14: -0.001538 | AV14: 0.011793 | AW14: -0.001275 | AX14: 0.021659 | AY14: 0.082016 | AZ14: 0.118312 | BA14: 0.146454 | BB14: 0.090714 | BC14: 0.198047 | BD14: 0.196416 | BE14: 0.151434 | BF14: 0.114454 | BG14: 0.163843 | BH14: 0.046248 | BI14: 0.010029 | BJ14: 0.005956 | BK14: 0.005167 | BL14: 0.016219 | BM14: 0.003468 | BN14: 0.009634 | BO14: 0.003766 | BP14: -0.000826 | BQ14: 0.004056 | BR14: 0.021421 | BS14: 0.06513 | BT14: 0.095577 | BU14: 0.103796 | BV14: 0.071927 | BW14: 0.075759 | BX14: 0.036859 | BY14: =$BX$14 -> 0.036859 | BZ14: =$BX$14 -> 0.036859 | CA14: =IFERROR(SUMPRODUCT(BR10:BU10,BW14:BZ14)/SUM(BR10:BU10),"") -> 0.046187178 | CB14: =CHOOSE(MATCH($CF$2,{"Bull","Base","Bear"},0),$CO$32,$CP$32,$CQ$32) -> 0.03 | CC14: =CHOOSE(MATCH($CF$2,{"Bull","Base","Bear"},0),$CO$33,$CP$33,$CQ$33) -> 0.025 | CD14: =CHOOSE(MATCH($CF$2,{"Bull","Base","Bear"},0),$CO$34,$CP$34,$CQ$34) -> 0.025 | CE14: =CHOOSE(MATCH($CF$2,{"Bull","Base","Bear"},0),$CO$35,$CP$35,$CQ$35) -> 0.025 | CF14: Q3/Q4-26E: Q2/26 y/y price held. 2027E–30E: scenario lever. | CN14: Memo: FY26 organic sales growth (company) | CO14: HSD–LDD | CP14: HSD–LDD | CQ14: HSD–LDD | CR14: High-single-digit to low-double-digit organic growth; ~1/3 volume, ~2/3 price & mix; neutral price/cost in 2H; ~$10m LIFO headwind (FY).
B15: Acquisitions % (inorganic contribution, first 12 months) | Y15: 0.015545 | Z15: 0.036193 | AA15: 0.027082 | AB15: 0.018671 | AC15: 0.024597 | AD15: 0.009298 | AE15: 0.003486 | AF15: 0.00302 | AG15: 0.007128 | AH15: 0.005666 | AI15: 0.009407 | AJ15: 0.010019 | AK15: 0.002882 | AL15: 0.006692 | AM15: 0.007233 | AN15: 0.029257 | AO15: 0.046511 | AP15: 0.038281 | AQ15: 0.042727 | AR15: 0.039337 | AS15: 0.013524 | AT15: 0 | AU15: 0 | AV15: 0 | AW15: 0.003409 | AX15: 0 | AY15: 0 | AZ15: 0 | BA15: 0 | BB15: 0 | BC15: 0.004104 | BD15: 0.011885 | BE15: 0.010236 | BF15: 0.01186 | BG15: 0.009648 | BH15: 0.084727 | BI15: 0.073779 | BJ15: 0.123216 | BK15: 0.106588 | BL15: 0.097204 | BM15: 0.006322 | BN15: 0.018347 | BO15: 0.045416 | BP15: 0.082939 | BQ15: 0.03807 | BR15: 0.075833 | BS15: 0.046525 | BT15: 0.01388 | BU15: 0 | BV15: 0.033671 | BW15: 0 | BX15: 0 | BY15: 0 | BZ15: 0 | CA15: =IFERROR(SUMPRODUCT(BR10:BU10,BW15:BZ15)/SUM(BR10:BU10),"") -> 0 | CB15: 0 | CC15: 0 | CD15: 0 | CE15: 0 | CF15: Q3/Q4-26E: input — 2025 bolt-ons anniversary during 2H/26 (International Welding +7.0% in Q2/26, fading). 2027E+: 0% here; future bolt-ons modelled in the unallocated M&A block. | CN15: FY26 point estimates (all cases)
B16: Foreign exchange % | Y16: -0.205115 | Z16: -0.471527 | AA16: -0.004335 | AB16: -0.005161 | AC16: -0.177271 | AD16: 0.001941 | AE16: -0.004771 | AF16: 0.00538 | AG16: 0.005774 | AH16: 0.002015 | AI16: 0.004169 | AJ16: 0.00081 | AK16: -0.011647 | AL16: -0.012983 | AM16: -0.005097 | AN16: -0.011054 | AO16: -0.004893 | AP16: -0.003659 | AQ16: 0.001054 | AR16: -0.004567 | AS16: -0.005003 | AT16: -0.006164 | AU16: -0.005132 | AV16: -0.00475 | AW16: -0.005278 | AX16: 0.003421 | AY16: 0.019878 | AZ16: 0.009891 | BA16: 0.003409 | BB16: 0.008642 | BC16: 0.001989 | BD16: -0.005211 | BE16: -0.006529 | BF16: -0.00851 | BG16: -0.004734 | BH16: -0.007505 | BI16: -0.005033 | BJ16: 0.003212 | BK16: 0.003938 | BL16: -0.001252 | BM16: 0.002519 | BN16: -0.001931 | BO16: -0.005452 | BP16: -0.010443 | BQ16: -0.003808 | BR16: -0.011133 | BS16: -0.00357 | BT16: 8.2e-05 | BU16: 0.006969 | BV16: -0.001813 | BW16: 0.009606 | BX16: 0.003334 | BY16: =$BX$16 -> 0.003334 | BZ16: =$BX$16 -> 0.003334 | CA16: =IFERROR(SUMPRODUCT(BR10:BU10,BW16:BZ16)/SUM(BR10:BU10),"") -> 0.0048380189 | CB16: 0 | CC16: 0 | CD16: 0 | CE16: 0 | CF16: Q3/Q4-26E: Q2/26 FX translation held; 2027E+: constant currency (0%). | CN16: Interest expense, net ($m) | CP16: 52.5 | CR16: FY26 outlook: interest expense, net $50–55m (Q1-26 call; maintained on Q2-26 call).
B17: Net sales growth % (volume + price + acquisitions + FX) | C17: =IF(ISNUMBER(C13),C13+C14+C15+C16,"") | D17: =IF(ISNUMBER(D13),D13+D14+D15+D16,"") | E17: =IF(ISNUMBER(E13),E13+E14+E15+E16,"") | F17: =IF(ISNUMBER(F13),F13+F14+F15+F16,"") | G17: =IF(ISNUMBER(G13),G13+G14+G15+G16,"") | H17: =IF(ISNUMBER(H13),H13+H14+H15+H16,"") | I17: =IF(ISNUMBER(I13),I13+I14+I15+I16,"") | J17: =IF(ISNUMBER(J13),J13+J14+J15+J16,"") | ... BX17: =IF(ISNUMBER(BX13),BX13+BX14+BX15+BX16,"") -> 0.111532 | BY17: =BY13+BY14+BY15+BY16 -> 0.11730291 | BZ17: =BZ13+BZ14+BZ15+BZ16 -> 0.11730291 | CA17: =CA13+CA14+CA15+CA16 -> 0.10720036 | CB17: =CB13+CB14+CB15+CB16 -> 0.06 | CC17: =CC13+CC14+CC15+CC16 -> 0.055 | CD17: =CD13+CD14+CD15+CD16 -> 0.05 | CE17: =CE13+CE14+CE15+CE16 -> 0.05 | CN17: Tax rate (GAAP) | CP17: 0.225 | CR17: FY26 outlook: "low-to-mid 20%" effective tax rate; 1H/26 actual 22.6%.
B18: Organic growth % (volume + price) | C18: =IF(ISNUMBER(C13),C13+C14,"") | D18: =IF(ISNUMBER(D13),D13+D14,"") | E18: =IF(ISNUMBER(E13),E13+E14,"") | F18: =IF(ISNUMBER(F13),F13+F14,"") | G18: =IF(ISNUMBER(G13),G13+G14,"") | H18: =IF(ISNUMBER(H13),H13+H14,"") | I18: =IF(ISNUMBER(I13),I13+I14,"") | J18: =IF(ISNUMBER(J13),J13+J14,"") | ... BX18: =IF(ISNUMBER(BX13),BX13+BX14,"") -> 0.108198 | BY18: =BY13+BY14 -> 0.11396891 | BZ18: =BZ13+BZ14 -> 0.11396891 | CA18: =CA13+CA14 -> 0.10236234 | CB18: =CB13+CB14 -> 0.06 | CC18: =CC13+CC14 -> 0.055 | CD18: =CD13+CD14 -> 0.05 | CE18: =CE13+CE14 -> 0.05 | CN18: Capital expenditures ($m) | CO18: 130 | CP18: 120 | CQ18: 110 | CR18: FY26 outlook: elevated capex $110–130m (1H/26: $70.6m).
B19: Check: Σ drivers vs reported y/y % (≈0; ≠0 where LECO recast the prior-year base) | C19: =IF(AND(ISNUMBER(C17),ISNUMBER(C11)),ROUND(C17-C11,3),"") | D19: =IF(AND(ISNUMBER(D17),ISNUMBER(D11)),ROUND(D17-D11,3),"") | E19: =IF(AND(ISNUMBER(E17),ISNUMBER(E11)),ROUND(E17-E11,3),"") | F19: =IF(AND(ISNUMBER(F17),ISNUMBER(F11)),ROUND(F17-F11,3),"") | G19: =IF(AND(ISNUMBER(G17),ISNUMBER(G11)),ROUND(G17-G11,3),"") | H19: =IF(AND(ISNUMBER(H17),ISNUMBER(H11)),ROUND(H17-H11,3),"") | I19: =IF(AND(ISNUMBER(I17),ISNUMBER(I11)),ROUND(I17-I11,3),"") | J19: =IF(AND(ISNUMBER(J17),ISNUMBER(J11)),ROUND(J17-J11,3),"") | ... BX19: =IF(AND(ISNUMBER(BX17),ISNUMBER(BX11)),ROUND(BX17-BX11,3),"") -> 0 | CN19: Rationalization & asset impairment charges — 2H/26 ($m) | CP19: 6 | CR19: 1H/26 $5.6m (Americas & International Welding programmes); 2H assumed at the 1H run-rate.
B20: Memo: inter-segment sales (eliminated in Corporate / Eliminations) | N20: 105.811 | O20: 28.217 | P20: 28.989 | Q20: 27.244 | R20: 26.074 | S20: 110.524 | T20: 23.023 | U20: 23.902 | V20: 25.571 | W20: 20.042 | X20: 92.538 | Y20: 23.831 | Z20: 23.456 | AA20: 22.386 | AB20: 23.939 | AC20: 93.612 | AD20: 22.46 | AE20: 27.374 | AF20: 25.546 | AG20: 22.002 | AH20: 97.382 | AI20: 26.586 | AJ20: 31.24 | AK20: 31.845 | AL20: 29.265 | AM20: 118.936 | AN20: 29.388 | AO20: 34.811 | AP20: 31.101 | AQ20: 28.042 | AR20: 123.342 | AS20: 24.783 | AT20: 27.493 | AU20: 29.368 | AV20: 27.734 | AW20: 109.378 | AX20: 32.748 | AY20: 39.765 | AZ20: 37.48 | BA20: 30.657 | BB20: 140.65 | BC20: 28.156 | BD20: 29.031 | BE20: 35.353 | BF20: 29.479 | BG20: 122.019 | BH20: 32.318 | BI20: 30.85 | BJ20: 28.875 | BK20: 35.493 | BL20: 127.536 | BM20: 29.978 | BN20: 37.8 | BO20: 30.845 | BP20: 37.134 | BQ20: 135.758 | BR20: 30.372 | BS20: 43.391 | BT20: 30.058 | BU20: 25.101 | BV20: 128.922 | BW20: 36.709 | BX20: 28.904 | CN20: Rationalization & asset impairment charges — 2027E+ ($m p.a.) | CP20: 12 | CR20: 2019–25 average ex 2023 gain ≈ $25m; RISE restructuring tapering. Treated as a special item (excluded from Adjusted EBIT).
B21: EBIT (GAAP segment result = operating income + other income) | N21: 364.186 | O21: 66.07 | P21: 92.494 | Q21: 83.444 | R21: 89.6 | S21: 331.608 | T21: 75.415 | U21: 79.421 | V21: -83.413 | W21: 72.027 | X21: 143.45 | Y21: 61.438 | Z21: 65.201 | AA21: 68.285 | AB21: 71.709 | AC21: 266.633 | AD21: 68.723 | AE21: 74.498 | AF21: 68.813 | AG21: 70.59 | AH21: 282.624 | AI21: 76.681 | AJ21: 88.158 | AK21: 85.021 | AL21: 84.198 | AM21: 334.058 | AN21: 80.416 | AO21: 83.072 | AP21: 74.11 | AQ21: 75.006 | AR21: 312.604 | AS21: 69.512 | AT21: 20.695 | AU21: 52.076 | AV21: 68.456 | AW21: 210.739 | AX21: 72.177 | AY21: 82.484 | AZ21: 10.983 | BA21: 40.258 | BB21: 205.902 | BC21: 115.303 | BD21: 117.606 | BE21: 119.157 | BF21: 113.813 | BG21: 465.879 | BH21: 129.668 | BI21: 136.913 | BJ21: 132.42 | BK21: 129.409 | BL21: 528.411 | BM21: 136.1 | BN21: 136.297 | BO21: 102.158 | BP21: 127.813 | BQ21: 502.367 | BR21: 122.063 | BS21: 137.01 | BT21: 127.24 | BU21: 137.816 | BV21: 524.129 | BW21: 126.895 | BX21: 157.083 | CN21: 2H/26 share repurchases ($m) | CO21: 200 | CP21: 150 | CQ21: 100 | CR21: 1H/26: $132.8m (Q1 $57m, Q2 $76m); 4.9m shares left under authorisation (31-Mar-26).
B22: Special items in segment EBIT (rationalization, impairments, acquisition costs) | C22: =IF(AND(ISNUMBER(C23),ISNUMBER(C21)),C23-C21,"") | D22: =IF(AND(ISNUMBER(D23),ISNUMBER(D21)),D23-D21,"") | E22: =IF(AND(ISNUMBER(E23),ISNUMBER(E21)),E23-E21,"") | F22: =IF(AND(ISNUMBER(F23),ISNUMBER(F21)),F23-F21,"") | G22: =IF(AND(ISNUMBER(G23),ISNUMBER(G21)),G23-G21,"") | H22: =IF(AND(ISNUMBER(H23),ISNUMBER(H21)),H23-H21,"") | I22: =IF(AND(ISNUMBER(I23),ISNUMBER(I21)),I23-I21,"") | J22: =IF(AND(ISNUMBER(J23),ISNUMBER(J21)),J23-J21,"") | ... BX22: =IF(AND(ISNUMBER(BX23),ISNUMBER(BX21)),BX23-BX21,"") -> 1.012 | CN22: Memo: cash conversion target (FCF / adjusted NI) | CO22: 1 | CP22: 1 | CQ22: 1 | CR22: Company target ~100% cash conversion through the cycle.
B23: Adjusted EBIT (company segment profit measure) | N23: 377.436 | O23: 83.688 | P23: 95.941 | Q23: 84.026 | R23: 89.6 | S23: 353.255 | T23: 75.415 | U23: 79.421 | V23: 82.765 | W23: 79.088 | X23: 316.689 | Y23: 61.438 | Z23: 65.201 | AA23: 68.285 | AB23: 71.709 | AC23: 266.633 | AD23: 68.723 | AE23: 74.498 | AF23: 74.096 | AG23: 74.549 | AH23: 291.866 | AI23: 77.439 | AJ23: 88.158 | AK23: 89.253 | AL23: 85.894 | AM23: 340.744 | AN23: 81.752 | AO23: 84.851 | AP23: 74.11 | AQ23: 75.006 | AR23: 315.719 | AS23: 70.702 | AT23: 46.702 | AU23: 59.12 | AV23: 69.204 | AW23: 245.728 | AX23: 76.617 | AY23: 84.134 | AZ23: 84.557 | BA23: 83.708 | BB23: 329.016 | BC23: 111.568 | BD23: 118.067 | BE23: 118.804 | BF23: 114.38 | BG23: 462.819 | BH23: 132.453 | BI23: 139.87 | BJ23: 136.476 | BK23: 129.469 | BL23: 538.269 | BM23: 136.1 | BN23: 136.651 | BO23: 125.515 | BP23: 131.923 | BQ23: 530.188 | BR23: 124.198 | BS23: 137.915 | BT23: 131.615 | BU23: 141.111 | BV23: 534.839 | BW23: 127.468 | BX23: 158.095 | BY23: =BY10*BY25 -> 156.25246 | BZ23: =BZ10*BZ25 -> 166.73121 | CA23: =SUM(BW23:BZ23) -> 608.54666 | CB23: =CB10*CB25 -> 655.27441 | CC23: =CC10*CC25 -> 701.4313 | CD23: =CD10*CD25 -> 743.58463 | CE23: =CE10*CE25 -> 780.76386 | CF23: Net sales × Adjusted EBIT margin. Forecast special items are modelled at group level (EBIT bridge), not allocated to segments. | CH23: =IFERROR((CE23/BV23)^(1/5)-1,"n/m") -> 0.078597295 | CI23: =IFERROR((BV23/AW23)^(1/5)-1,"n/m") -> 0.16829814 | CJ23: =IFERROR((BV23/X23)^(1/10)-1,"n/m") -> 0.053801977 | CK23: =IFERROR((BV23/C23)^(1/19)-1,"n/m") -> n/m
B24: Adj. EBIT margin before outlook calibration % (Q3/Q4-26E helper) | BY24: =BT25+($BX$25-$BS$25) -> 0.19644719 | BZ24: =BU25+($BX$25-$BS$25) -> 0.21312433 | CF24: Prior-year quarter margin + Q2/26 y/y margin change. | CN24: Minimum net debt / Adjusted EBITDA (x) — buyback floor 2027E+ | CO24: 1.25 | CP24: 1 | CQ24: 0.75 | CR24: LECO runs ~0.5–1.0x net leverage (YE25 net debt $985m vs model Adj. EBITDA $851m); excess cash returned via buybacks.
B25: Adjusted EBIT margin % (on external net sales) | C25: =IF(AND(ISNUMBER(C23),ISNUMBER(C10)),IFERROR(C23/C10,""),"") | D25: =IF(AND(ISNUMBER(D23),ISNUMBER(D10)),IFERROR(D23/D10,""),"") | E25: =IF(AND(ISNUMBER(E23),ISNUMBER(E10)),IFERROR(E23/E10,""),"") | F25: =IF(AND(ISNUMBER(F23),ISNUMBER(F10)),IFERROR(F23/F10,""),"") | G25: =IF(AND(ISNUMBER(G23),ISNUMBER(G10)),IFERROR(G23/G10,""),"") | H25: =IF(AND(ISNUMBER(H23),ISNUMBER(H10)),IFERROR(H23/H10,""),"") | I25: =IF(AND(ISNUMBER(I23),ISNUMBER(I10)),IFERROR(I23/I10,""),"") | J25: =IF(AND(ISNUMBER(J23),ISNUMBER(J10)),IFERROR(J23/J10,""),"") | ... BX25: =IF(AND(ISNUMBER(BX23),ISNUMBER(BX10)),IFERROR(BX23/BX10,""),"") -> 0.20414158 | BY25: =BY24+BY123 -> 0.20215251 | BZ25: =BZ24+BZ123 -> 0.21882965 | CA25: =IFERROR(CA23/CA10,"") -> 0.20180429 | CB25: =CHOOSE(MATCH($CF$2,{"Bull","Base","Bear"},0),$CO$37,$CP$37,$CQ$37) -> 0.205 | CC25: =CHOOSE(MATCH($CF$2,{"Bull","Base","Bear"},0),$CO$38,$CP$38,$CQ$38) -> 0.208 | CD25: =CHOOSE(MATCH($CF$2,{"Bull","Base","Bear"},0),$CO$39,$CP$39,$CQ$39) -> 0.21 | CE25: =CHOOSE(MATCH($CF$2,{"Bull","Base","Bear"},0),$CO$40,$CP$40,$CQ$40) -> 0.21 | CF25: LECO reports segment margins on total sales incl. inter-segment; the model uses external net sales (slightly higher). 2027E–30E: scenario lever. | CH25: =IFERROR(AVERAGE(CA25,CB25,CC25,CD25,CE25),"n/m") -> 0.20696086 | CI25: =IFERROR(AVERAGE(BB25,BG25,BL25,BQ25,BV25),"n/m") -> 0.19766338 | CJ25: =IFERROR(AVERAGE(AC25,AH25,AM25,AR25,AW25,BB25,BG25,BL25,BQ25,BV25),"n/m") -> 0.18732228 | CK25: =IFERROR(AVERAGE(C25,D25,E25,F25,G25,H25,I25,N25,S25,X25,AC25,AH25,AM25,AR25,AW25,BB25,BG25,BL25,BQ25,BV25),"n/m") -> 0.18857567
B26: Incremental Adj. EBIT margin % (Δ Adj. EBIT / Δ net sales, y/y) | D26: =IF(AND(ISNUMBER(D23),ISNUMBER(C23)),IFERROR((D23-C23)/(D10-C10),""),"") | E26: =IF(AND(ISNUMBER(E23),ISNUMBER(D23)),IFERROR((E23-D23)/(E10-D10),""),"") | F26: =IF(AND(ISNUMBER(F23),ISNUMBER(E23)),IFERROR((F23-E23)/(F10-E10),""),"") | G26: =IF(AND(ISNUMBER(G23),ISNUMBER(F23)),IFERROR((G23-F23)/(G10-F10),""),"") | H26: =IF(AND(ISNUMBER(H23),ISNUMBER(G23)),IFERROR((H23-G23)/(H10-G10),""),"") | I26: =IF(AND(ISNUMBER(I23),ISNUMBER(H23)),IFERROR((I23-H23)/(I10-H10),""),"") | N26: =IF(AND(ISNUMBER(N23),ISNUMBER(I23)),IFERROR((N23-I23)/(N10-I10),""),"") | O26: =IF(AND(ISNUMBER(O23),ISNUMBER(J23)),IFERROR((O23-J23)/(O10-J10),""),"") | P26: =IF(AND(ISNUMBER(P23),ISNUMBER(K23)),IFERROR((P23-K23)/(P10-K10),""),"") | Q26: =IF(AND(ISNUMBER(Q23),ISNUMBER(L23)),IFERROR((Q23-L23)/(Q10-L10),""),"") | R26: =IF(AND(ISNUMBER(R23),ISNUMBER(M23)),IFERROR((R23-M23)/(R10-M10),""),"") | S26: =IF(AND(ISNUMBER(S23),ISNUMBER(N23)),IFERROR((S23-N23)/(S10-N10),""),"") -> 2.1996725 | T26: =IF(AND(ISNUMBER(T23),ISNUMBER(O23)),IFERROR((T23-O23)/(T10-O10),""),"") -> -1.1838867 | U26: =IF(AND(ISNUMBER(U23),ISNUMBER(P23)),IFERROR((U23-P23)/(U10-P10),""),"") -> 1.137506 | ... CA26: =IF(AND(ISNUMBER(CA23),ISNUMBER(BV23)),IFERROR((CA23-BV23)/(CA10-BV10),""),"") -> 0.25245132 | CB26: =IF(AND(ISNUMBER(CB23),ISNUMBER(CA23)),IFERROR((CB23-CA23)/(CB10-CA10),""),"") -> 0.25826178 | CC26: =IF(AND(ISNUMBER(CC23),ISNUMBER(CB23)),IFERROR((CC23-CB23)/(CC10-CB10),""),"") -> 0.26254545 | CD26: =IF(AND(ISNUMBER(CD23),ISNUMBER(CC23)),IFERROR((CD23-CC23)/(CD10-CC10),""),"") -> 0.25 | CE26: =IF(AND(ISNUMBER(CE23),ISNUMBER(CD23)),IFERROR((CE23-CD23)/(CE10-CD10),""),"") -> 0.21 | CN26: AW_vol (Americas Welding volume y/y) | CO26: 0.02 | CP26: Δ → | CQ26: -0.02 | CR26: Americas volume inflected +7.1% in Q2/26 after 9 quarters of declines; consumables lead equipment. 2016–25 avg ≈ −0.5% (incl. 2020/2024–25 downturns).
CN27: 2027E | CO27: =CP27+$CO$26 -> 0.05 | CP27: 0.03 | CQ27: =CP27+$CQ$26 -> 0.01
B28: International Welding (Europe, Middle East, Asia Pacific — welding equipment, consumables, automation) | CF28: IW — modelling logic | CN28: 2028E | CO28: =CP28+$CO$26 -> 0.05 | CP28: 0.03 | CQ28: =CP28+$CQ$26 -> 0.01
B29: Net sales (external customers) | N29: 695.831 | O29: 170.742 | P29: 185.588 | Q29: 168.004 | R29: 157.09 | S29: 681.424 | T29: 139.247 | U29: 141.927 | V29: 128.072 | W29: 121.214 | X29: 530.46 | Y29: 124.305 | Z29: 132.815 | AA29: 119.564 | AB29: 130.605 | AC29: 507.289 | AD29: 128.888 | AE29: 141.498 | AF29: 197.617 | AG29: 256.021 | AH29: 724.024 | AI29: 247.32 | AJ29: 243.373 | AK29: 209.622 | AL29: 219.456 | AM29: 919.771 | AN29: 218.086 | AO29: 212.306 | AP29: 205.378 | AQ29: 218.606 | AR29: 854.376 | AS29: 197.923 | AT29: 177.167 | AU29: 196.937 | AV29: 214.782 | AW29: 786.809 | AX29: 223.079 | AY29: 252.352 | AZ29: 227.165 | BA29: 245.529 | BB29: 948.125 | BC29: 258.041 | BD29: 236.629 | BE29: 216.497 | BF29: 243.114 | BG29: 954.281 | BH29: 252.416 | BI29: 253.403 | BJ29: 242.01 | BK29: 292.177 | BL29: 1040.006 | BM29: 235.761 | BN29: 238.758 | BO29: 216.224 | BP29: 242.979 | BQ29: 933.722 | BR29: 219.061 | BS29: 232.824 | BT29: 219.629 | BU29: 259.351 | BV29: 930.865 | BW29: 227.035 | BX29: 243.292 | BY29: =BT29*(1+BY36) -> 223.1828 | BZ29: =BU29*(1+BZ36) -> 254.47025 | CA29: =SUM(BW29:BZ29) -> 947.98005 | CB29: =CA29*(1+CB36) -> 981.15935 | CC29: =CB29*(1+CC36) -> 1015.4999 | CD29: =CC29*(1+CD36) -> 1051.0424 | CE29: =CD29*(1+CE36) -> 1087.8289 | CF29: Q3/Q4-26E: prior-year quarter × (1 + volume + price + acquisitions + FX). 2027E+: prior year × (1 + Σ drivers). Current 3-segment structure from 2016 (2013–Q3/15 recast by LECO in the 8-K of 10-Feb-2016; Q4/15 derived = FY15 recast − 9M/15 recast). | CH29: =IFERROR((CE29/BV29)^(1/5)-1,"n/m") -> 0.031655693 | CI29: =IFERROR((BV29/AW29)^(1/5)-1,"n/m") -> 0.034197483 | CJ29: =IFERROR((BV29/X29)^(1/10)-1,"n/m") -> 0.057848333 | CK29: =IFERROR((BV29/C29)^(1/19)-1,"n/m") -> n/m | CN29: 2029E | CO29: =CP29+$CO$26 -> 0.045 | CP29: 0.025 | CQ29: =CP29+$CQ$26 -> 0.005
B30: Net sales y/y % | D30: =IF(AND(ISNUMBER(D29),ISNUMBER(C29)),IFERROR(D29/C29-1,""),"") | E30: =IF(AND(ISNUMBER(E29),ISNUMBER(D29)),IFERROR(E29/D29-1,""),"") | F30: =IF(AND(ISNUMBER(F29),ISNUMBER(E29)),IFERROR(F29/E29-1,""),"") | G30: =IF(AND(ISNUMBER(G29),ISNUMBER(F29)),IFERROR(G29/F29-1,""),"") | H30: =IF(AND(ISNUMBER(H29),ISNUMBER(G29)),IFERROR(H29/G29-1,""),"") | I30: =IF(AND(ISNUMBER(I29),ISNUMBER(H29)),IFERROR(I29/H29-1,""),"") | N30: =IF(AND(ISNUMBER(N29),ISNUMBER(I29)),IFERROR(N29/I29-1,""),"") | O30: =IF(AND(ISNUMBER(O29),ISNUMBER(J29)),IFERROR(O29/J29-1,""),"") | P30: =IF(AND(ISNUMBER(P29),ISNUMBER(K29)),IFERROR(P29/K29-1,""),"") | Q30: =IF(AND(ISNUMBER(Q29),ISNUMBER(L29)),IFERROR(Q29/L29-1,""),"") | R30: =IF(AND(ISNUMBER(R29),ISNUMBER(M29)),IFERROR(R29/M29-1,""),"") | S30: =IF(AND(ISNUMBER(S29),ISNUMBER(N29)),IFERROR(S29/N29-1,""),"") -> -0.02070474 | T30: =IF(AND(ISNUMBER(T29),ISNUMBER(O29)),IFERROR(T29/O29-1,""),"") -> -0.18445959 | U30: =IF(AND(ISNUMBER(U29),ISNUMBER(P29)),IFERROR(U29/P29-1,""),"") -> -0.23525767 | ... BX30: =IF(AND(ISNUMBER(BX29),ISNUMBER(BS29)),IFERROR(BX29/BS29-1,""),"") -> 0.044961001 | BY30: =IFERROR(BY29/BT29-1,"") -> 0.016180914 | BZ30: =IFERROR(BZ29/BU29-1,"") -> -0.018819086 | CA30: =IFERROR(CA29/BV29-1,"") -> 0.018386178 | CB30: =IFERROR(CB29/CA29-1,"") -> 0.035 | CC30: =IFERROR(CC29/CB29-1,"") -> 0.035 | CD30: =IFERROR(CD29/CC29-1,"") -> 0.035 | CE30: =IFERROR(CE29/CD29-1,"") -> 0.035 | CN30: 2030E | CO30: =CP30+$CO$26 -> 0.045 | CP30: 0.025 | CQ30: =CP30+$CQ$26 -> 0.005
B31: Volume % before outlook calibration (Q3/Q4-26E helper) | BY31: =$BX$32 -> -0.04695 | BZ31: =$BX$32 -> -0.04695 | CF31: Q2/26 y/y volume held for Q3/Q4-26E before the FY26 net-sales calibration (Group block). | CN31: AW_price (Americas Welding price y/y) | CO31: 0.01 | CP31: Δ → | CQ31: -0.01 | CR31: Price +7.2% (2025) and +5.6% (1H/26) on tariff / steel inflation; normalises to ~2–3% (2016–25 avg ≈ +5.1% incl. 2021–22 inflation).
B32: Volume % (company: change in net sales due to volume) | Y32: -0.070537 | Z32: -0.036019 | AA32: -0.049363 | AB32: 0.104171 | AC32: -0.016267 | AD32: 0.026926 | AE32: 0.032956 | AF32: 0.066809 | AG32: -0.02457 | AH32: 0.024647 | AI32: -0.036753 | AJ32: -0.045011 | AK32: -0.104541 | AL32: -0.137481 | AM32: -0.092487 | AN32: -0.072445 | AO32: -0.096765 | AP32: -0.061854 | AQ32: -0.077811 | AR32: -0.077747 | AS32: -0.139885 | AT32: -0.209377 | AU32: -0.053384 | AV32: -0.033581 | AW32: -0.10916 | AX32: 0.05684 | AY32: 0.254534 | AZ32: 0.03784 | BA32: -0.008213 | BB32: 0.078841 | BC32: -0.00459 | BD32: -0.066819 | BE32: 0.024379 | BF32: 0.013558 | BG32: -0.009512 | BH32: -0.056801 | BI32: 0.03806 | BJ32: 0.029081 | BK32: 0.048841 | BL32: 0.013119 | BM32: -0.048618 | BN32: -0.037715 | BO32: -0.119412 | BP32: -0.157199 | BQ32: -0.09294 | BR32: -0.057889 | BS32: -0.067734 | BT32: -0.042428 | BU32: -0.035538 | BV32: -0.05101 | BW32: -0.098744 | BX32: -0.04695 | BY32: =BY31+BY118 -> -0.041179086 | BZ32: =BZ31+BZ118 -> -0.041179086 | CA32: =IFERROR(SUMPRODUCT(BR29:BU29,BW32:BZ32)/SUM(BR29:BU29),"") -> -0.056169267 | CB32: =CHOOSE(MATCH($CF$2,{"Bull","Base","Bear"},0),$CO$42,$CP$42,$CQ$42) -> 0.02 | CC32: =CHOOSE(MATCH($CF$2,{"Bull","Base","Bear"},0),$CO$43,$CP$43,$CQ$43) -> 0.02 | CD32: =CHOOSE(MATCH($CF$2,{"Bull","Base","Bear"},0),$CO$44,$CP$44,$CQ$44) -> 0.02 | CE32: =CHOOSE(MATCH($CF$2,{"Bull","Base","Bear"},0),$CO$45,$CP$45,$CQ$45) -> 0.02 | CF32: Historical = LECO "Change in Net Sales by Segment" table (8-K Ex.99.1) ÷ prior-year segment net sales. Q3/Q4-26E: Q2/26 y/y + FY26 calibration Δ. 2027E–30E: scenario lever (Bull/Base/Bear table →). | CN32: 2027E | CO32: =CP32+$CO$31 -> 0.04 | CP32: 0.03 | CQ32: =CP32+$CQ$31 -> 0.02
B33: Price % | Y33: -0.022299 | Z33: -0.027359 | AA33: -0.009799 | AB33: -0.001526 | AC33: -0.015888 | AD33: 0.025735 | AE33: 0.033302 | AF33: 0.028821 | AG33: 0.05558 | AH33: 0.036127 | AI33: 0.054458 | AJ33: 0.054927 | AK33: 0.052425 | AL33: 0.037598 | AM33: 0.048033 | AN33: 0.026181 | AO33: 0.011657 | AP33: 0.002896 | AQ33: -0.003463 | AR33: 0.009958 | AS33: -0.007754 | AT33: -0.006029 | AU33: 0.000341 | AV33: 0.005036 | AW33: -0.002107 | AX33: 0.023342 | AY33: 0.08304 | AZ33: 0.107674 | BA33: 0.139304 | BB33: 0.089548 | BC33: 0.233953 | BD33: 0.185507 | BE33: 0.138358 | BF33: 0.116878 | BG33: 0.167837 | BH33: 0.057623 | BI33: 0.004222 | BJ33: 0.002203 | BK33: -0.006803 | BL33: 0.015395 | BM33: -0.015886 | BN33: -0.012427 | BO33: -0.005574 | BP33: 0.000325 | BQ33: -0.008089 | BR33: 0.003512 | BS33: 0.003568 | BT33: 0.00043 | BU33: 0.005305 | BV33: 0.003279 | BW33: 0.001356 | BX33: 0.016218 | BY33: =$BX$33 -> 0.016218 | BZ33: =$BX$33 -> 0.016218 | CA33: =IFERROR(SUMPRODUCT(BR29:BU29,BW33:BZ33)/SUM(BR29:BU29),"") -> 0.012720517 | CB33: =CHOOSE(MATCH($CF$2,{"Bull","Base","Bear"},0),$CO$47,$CP$47,$CQ$47) -> 0.015 | CC33: =CHOOSE(MATCH($CF$2,{"Bull","Base","Bear"},0),$CO$48,$CP$48,$CQ$48) -> 0.015 | CD33: =CHOOSE(MATCH($CF$2,{"Bull","Base","Bear"},0),$CO$49,$CP$49,$CQ$49) -> 0.015 | CE33: =CHOOSE(MATCH($CF$2,{"Bull","Base","Bear"},0),$CO$50,$CP$50,$CQ$50) -> 0.015 | CF33: Q3/Q4-26E: Q2/26 y/y price held. 2027E–30E: scenario lever. | CN33: 2028E | CO33: =CP33+$CO$31 -> 0.035 | CP33: 0.025 | CQ33: =CP33+$CQ$31 -> 0.015
B34: Acquisitions % (inorganic contribution, first 12 months) | Y34: 0.024884 | Z34: 0.026084 | AA34: 0.011353 | AB34: 0 | AC34: 0.016254 | AD34: 0 | AE34: 0 | AF34: 0.514536 | AG34: 0.856858 | AH34: 0.341876 | AI34: 0.798724 | AJ34: 0.680702 | AK34: 0.143378 | AL34: 0 | AM34: 0.314351 | AN34: 0 | AO34: 0 | AP34: 0.083069 | AQ34: 0.08953 | AR34: 0.040294 | AS34: 0.083921 | AT34: 0.071684 | AU34: 0 | AV34: 0 | AW34: 0.039234 | AX34: 0 | AY34: 0.020235 | AZ34: 0.017117 | BA34: 0.081557 | BB34: 0.031104 | BC34: 0.079039 | BD34: 0 | BE34: 0 | BF34: 0 | BG34: 0.018597 | BH34: 0.028507 | BI34: 0.025394 | BJ34: 0.048795 | BK34: 0.124012 | BL34: 0.056669 | BM34: 0 | BN34: 0.000225 | BO34: 0.004397 | BP34: 0.001845 | BQ34: 0.001596 | BR34: 0.003457 | BS34: 0.001319 | BT34: 0.036388 | BU34: 0.045761 | BV34: 0.021545 | BW34: 0.072099 | BX34: 0.06955 | BY34: 0.035 | BZ34: 0 | CA34: =IFERROR(SUMPRODUCT(BR29:BU29,BW34:BZ34)/SUM(BR29:BU29),"") -> 0.042620577 | CB34: 0 | CC34: 0 | CD34: 0 | CE34: 0 | CF34: Q3/Q4-26E: input — 2025 bolt-ons anniversary during 2H/26 (International Welding +7.0% in Q2/26, fading). 2027E+: 0% here; future bolt-ons modelled in the unallocated M&A block. | CN34: 2029E | CO34: =CP34+$CO$31 -> 0.035 | CP34: 0.025 | CQ34: =CP34+$CQ$31 -> 0.015
B35: Foreign exchange % | Y35: -0.039355 | Z35: -0.026908 | AA35: -0.018622 | AB35: -0.02517 | AC35: -0.02778 | AD35: -0.015792 | AE35: -0.000881 | AF35: 0.042647 | AG35: 0.072402 | AH35: 0.024592 | AI35: 0.102446 | AJ35: 0.029357 | AK35: -0.030514 | AL35: -0.042938 | AM35: 0.000463 | AN35: -0.071939 | AO35: -0.042544 | AP35: -0.044356 | AQ35: -0.01213 | AR35: -0.043604 | AS35: -0.028736 | AT35: -0.021789 | AU35: 0.011944 | AV35: 0.011052 | AW35: -0.007051 | AX35: 0.046917 | AY35: 0.066564 | AZ35: -0.00914 | BA35: -0.069494 | BB35: 0.005532 | BC35: -0.151677 | BD35: -0.180993 | BE35: -0.209698 | BF35: -0.140273 | BG35: -0.170428 | BH35: -0.051128 | BI35: 0.003212 | BJ35: 0.037765 | BK35: 0.035761 | BL35: 0.00465 | BM35: -0.001478 | BN35: -0.007877 | BO35: 0.014041 | BP35: -0.013355 | BQ35: -0.002762 | BR35: -0.019914 | BS35: 0.037992 | BT35: 0.021357 | BU35: 0.051852 | BV35: 0.023126 | BW35: 0.061691 | BX35: 0.006142 | BY35: =$BX$35 -> 0.006142 | BZ35: =$BX$35 -> 0.006142 | CA35: =IFERROR(SUMPRODUCT(BR29:BU29,BW35:BZ35)/SUM(BR29:BU29),"") -> 0.019214378 | CB35: 0 | CC35: 0 | CD35: 0 | CE35: 0 | CF35: Q3/Q4-26E: Q2/26 FX translation held; 2027E+: constant currency (0%). | CN35: 2030E | CO35: =CP35+$CO$31 -> 0.035 | CP35: 0.025 | CQ35: =CP35+$CQ$31 -> 0.015
B36: Net sales growth % (volume + price + acquisitions + FX) | C36: =IF(ISNUMBER(C32),C32+C33+C34+C35,"") | D36: =IF(ISNUMBER(D32),D32+D33+D34+D35,"") | E36: =IF(ISNUMBER(E32),E32+E33+E34+E35,"") | F36: =IF(ISNUMBER(F32),F32+F33+F34+F35,"") | G36: =IF(ISNUMBER(G32),G32+G33+G34+G35,"") | H36: =IF(ISNUMBER(H32),H32+H33+H34+H35,"") | I36: =IF(ISNUMBER(I32),I32+I33+I34+I35,"") | J36: =IF(ISNUMBER(J32),J32+J33+J34+J35,"") | ... BX36: =IF(ISNUMBER(BX32),BX32+BX33+BX34+BX35,"") -> 0.04496 | BY36: =BY32+BY33+BY34+BY35 -> 0.016180914 | BZ36: =BZ32+BZ33+BZ34+BZ35 -> -0.018819086 | CA36: =CA32+CA33+CA34+CA35 -> 0.018386205 | CB36: =CB32+CB33+CB34+CB35 -> 0.035 | CC36: =CC32+CC33+CC34+CC35 -> 0.035 | CD36: =CD32+CD33+CD34+CD35 -> 0.035 | CE36: =CE32+CE33+CE34+CE35 -> 0.035 | CN36: AW_mgn (Americas Welding Adj. EBIT margin, on external sales) | CO36: 0.015 | CP36: Δ → | CQ36: -0.015 | CR36: FY25 19.6%, 1H/26 19.3%; company guides 19–20% EBIT margin for the rest of 2026. RISE: ~19% avg / >20% peak (enterprise).
B37: Organic growth % (volume + price) | C37: =IF(ISNUMBER(C32),C32+C33,"") | D37: =IF(ISNUMBER(D32),D32+D33,"") | E37: =IF(ISNUMBER(E32),E32+E33,"") | F37: =IF(ISNUMBER(F32),F32+F33,"") | G37: =IF(ISNUMBER(G32),G32+G33,"") | H37: =IF(ISNUMBER(H32),H32+H33,"") | I37: =IF(ISNUMBER(I32),I32+I33,"") | J37: =IF(ISNUMBER(J32),J32+J33,"") | ... BX37: =IF(ISNUMBER(BX32),BX32+BX33,"") -> -0.030732 | BY37: =BY32+BY33 -> -0.024961086 | BZ37: =BZ32+BZ33 -> -0.024961086 | CA37: =CA32+CA33 -> -0.04344875 | CB37: =CB32+CB33 -> 0.035 | CC37: =CC32+CC33 -> 0.035 | CD37: =CD32+CD33 -> 0.035 | CE37: =CE32+CE33 -> 0.035 | CN37: 2027E | CO37: =CP37+$CO$36 -> 0.22 | CP37: 0.205 | CQ37: =CP37+$CQ$36 -> 0.19
B38: Check: Σ drivers vs reported y/y % (≈0; ≠0 where LECO recast the prior-year base) | C38: =IF(AND(ISNUMBER(C36),ISNUMBER(C30)),ROUND(C36-C30,3),"") | D38: =IF(AND(ISNUMBER(D36),ISNUMBER(D30)),ROUND(D36-D30,3),"") | E38: =IF(AND(ISNUMBER(E36),ISNUMBER(E30)),ROUND(E36-E30,3),"") | F38: =IF(AND(ISNUMBER(F36),ISNUMBER(F30)),ROUND(F36-F30,3),"") | G38: =IF(AND(ISNUMBER(G36),ISNUMBER(G30)),ROUND(G36-G30,3),"") | H38: =IF(AND(ISNUMBER(H36),ISNUMBER(H30)),ROUND(H36-H30,3),"") | I38: =IF(AND(ISNUMBER(I36),ISNUMBER(I30)),ROUND(I36-I30,3),"") | J38: =IF(AND(ISNUMBER(J36),ISNUMBER(J30)),ROUND(J36-J30,3),"") | ... BX38: =IF(AND(ISNUMBER(BX36),ISNUMBER(BX30)),ROUND(BX36-BX30,3),"") -> 0 | CN38: 2028E | CO38: =CP38+$CO$36 -> 0.223 | CP38: 0.208 | CQ38: =CP38+$CQ$36 -> 0.193
B39: Memo: inter-segment sales (eliminated in Corporate / Eliminations) | N39: 22.668 | O39: 5.988 | P39: 6.08 | Q39: 4.715 | R39: 4.825 | S39: 21.608 | T39: 5.027 | U39: 5.311 | V39: 5.4 | W39: 3.009 | X39: 18.747 | Y39: 4.426 | Z39: 3.841 | AA39: 3.688 | AB39: 4.02 | AC39: 15.975 | AD39: 4.285 | AE39: 5.478 | AF39: 5.451 | AG39: 3.646 | AH39: 18.86 | AI39: 4.509 | AJ39: 5.497 | AK39: 3.663 | AL39: 4.907 | AM39: 18.576 | AN39: 4.209 | AO39: 4.188 | AP39: 4.441 | AQ39: 4.853 | AR39: 17.691 | AS39: 4.483 | AT39: 4.286 | AU39: 4.898 | AV39: 4.827 | AW39: 18.494 | AX39: 4.285 | AY39: 6.897 | AZ39: 7.078 | BA39: 8.071 | BB39: 26.331 | BC39: 6.228 | BD39: 9.527 | BE39: 9.994 | BF39: 5.754 | BG39: 31.503 | BH39: 6.753 | BI39: 8.292 | BJ39: 4.896 | BK39: 11.557 | BL39: 31.498 | BM39: 8.408 | BN39: 8.849 | BO39: 7.371 | BP39: 11.233 | BQ39: 35.861 | BR39: 6.832 | BS39: 7.641 | BT39: 9.83 | BU39: 5.857 | BV39: 30.16 | BW39: 5.807 | BX39: 7.564 | CN39: 2029E | CO39: =CP39+$CO$36 -> 0.225 | CP39: 0.21 | CQ39: =CP39+$CQ$36 -> 0.195
B40: EBIT (GAAP segment result = operating income + other income) | N40: 29.921 | O40: 8.284 | P40: 14.471 | Q40: -13.757 | R40: 10.183 | S40: 19.181 | T40: 10.934 | U40: 9.778 | V40: -5.676 | W40: 2.804 | X40: 17.84 | Y40: 6.233 | Z40: 9.67 | AA40: 5.796 | AB40: 7.447 | AC40: 29.146 | AD40: 9.605 | AE40: 9.496 | AF40: 8.298 | AG40: 4.246 | AH40: 31.645 | AI40: 4.798 | AJ40: 4.734 | AK40: 8.085 | AL40: 11.371 | AM40: 28.988 | AN40: 11.138 | AO40: 17.805 | AP40: 14.681 | AQ40: 4.501 | AR40: 48.125 | AS40: 0.478 | AT40: 9.117 | AU40: 11.031 | AV40: 4.949 | AW40: 25.575 | AX40: 14.207 | AY40: 27.526 | AZ40: 22.417 | BA40: 26.824 | BB40: 90.974 | BC40: 35.74 | BD40: 34.855 | BE40: 16.861 | BF40: 21.02 | BG40: 108.476 | BH40: 29.296 | BI40: 30.519 | BJ40: 22.369 | BK40: 64.035 | BL40: 146.218 | BM40: 24.707 | BN40: -5.525 | BO40: 17.175 | BP40: 32.013 | BQ40: 68.37 | BR40: 21.6 | BS40: 28.999 | BT40: 23.059 | BU40: 25.485 | BV40: 99.143 | BW40: 20.89 | BX40: 24.313 | CN40: 2030E | CO40: =CP40+$CO$36 -> 0.225 | CP40: 0.21 | CQ40: =CP40+$CQ$36 -> 0.195
B41: Special items in segment EBIT (rationalization, impairments, acquisition costs) | C41: =IF(AND(ISNUMBER(C42),ISNUMBER(C40)),C42-C40,"") | D41: =IF(AND(ISNUMBER(D42),ISNUMBER(D40)),D42-D40,"") | E41: =IF(AND(ISNUMBER(E42),ISNUMBER(E40)),E42-E40,"") | F41: =IF(AND(ISNUMBER(F42),ISNUMBER(F40)),F42-F40,"") | G41: =IF(AND(ISNUMBER(G42),ISNUMBER(G40)),G42-G40,"") | H41: =IF(AND(ISNUMBER(H42),ISNUMBER(H40)),H42-H40,"") | I41: =IF(AND(ISNUMBER(I42),ISNUMBER(I40)),I42-I40,"") | J41: =IF(AND(ISNUMBER(J42),ISNUMBER(J40)),J42-J40,"") | ... BX41: =IF(AND(ISNUMBER(BX42),ISNUMBER(BX40)),BX42-BX40,"") -> 2.282 | CN41: IW_vol (International Welding volume y/y) | CO41: 0.02 | CP41: Δ → | CQ41: -0.02 | CR41: International volumes −5.1% (2025), −7.2% (1H/26): Europe weak; Asia Pacific improving.
B42: Adjusted EBIT (company segment profit measure) | N42: 38.037 | O42: 8.314 | P42: 15.328 | Q42: 14.729 | R42: 10.349 | S42: 48.72 | T42: 10.934 | U42: 11.017 | V42: 9.268 | W42: 3.292 | X42: 34.511 | Y42: 6.233 | Z42: 9.67 | AA42: 5.796 | AB42: 7.447 | AC42: 29.146 | AD42: 9.605 | AE42: 9.496 | AF42: 10.612 | AG42: 12.008 | AH42: 41.721 | AI42: 14.973 | AJ42: 16.276 | AK42: 10.721 | AL42: 12.303 | AM42: 54.273 | AN42: 13.337 | AO42: 15.178 | AP42: 10.184 | AQ42: 11.582 | AR42: 50.281 | AS42: 6.615 | AT42: 9.682 | AU42: 13.432 | AV42: 15.25 | AW42: 44.979 | AX42: 18.816 | AY42: 29.997 | AZ42: 29.032 | BA42: 28.363 | BB42: 106.208 | BC42: 37.087 | BD42: 35.009 | BE42: 25.225 | BF42: 22.836 | BG42: 120.157 | BH42: 29.598 | BI42: 33.774 | BJ42: 30.239 | BK42: 42.888 | BL42: 136.497 | BM42: 27.776 | BN42: 25.709 | BO42: 20.101 | BP42: 32.53 | BQ42: 106.117 | BR42: 23.012 | BS42: 30.55 | BT42: 25.821 | BU42: 31.202 | BV42: 110.585 | BW42: 22.662 | BX42: 26.595 | BY42: =BY29*BY44 -> 22.624008 | BZ42: =BZ29*BZ44 -> 26.493258 | CA42: =SUM(BW42:BZ42) -> 98.374266 | CB42: =CB29*CB44 -> 112.83333 | CC42: =CC29*CC44 -> 121.85999 | CD42: =CD29*CD44 -> 131.3803 | CE42: =CE29*CE44 -> 135.97861 | CF42: Net sales × Adjusted EBIT margin. Forecast special items are modelled at group level (EBIT bridge), not allocated to segments. | CH42: =IFERROR((CE42/BV42)^(1/5)-1,"n/m") -> 0.04220914 | CI42: =IFERROR((BV42/AW42)^(1/5)-1,"n/m") -> 0.19711889 | CJ42: =IFERROR((BV42/X42)^(1/10)-1,"n/m") -> 0.12350205 | CK42: =IFERROR((BV42/C42)^(1/19)-1,"n/m") -> n/m | CN42: 2027E | CO42: =CP42+$CO$41 -> 0.04 | CP42: 0.02 | CQ42: =CP42+$CQ$41 -> 0
B43: Adj. EBIT margin before outlook calibration % (Q3/Q4-26E helper) | BY43: =BT44+($BX$44-$BS$44) -> 0.095664535 | BZ43: =BU44+($BX$44-$BS$44) -> 0.098406093 | CF43: Prior-year quarter margin + Q2/26 y/y margin change. | CN43: 2028E | CO43: =CP43+$CO$41 -> 0.04 | CP43: 0.02 | CQ43: =CP43+$CQ$41 -> 0
B44: Adjusted EBIT margin % (on external net sales) | C44: =IF(AND(ISNUMBER(C42),ISNUMBER(C29)),IFERROR(C42/C29,""),"") | D44: =IF(AND(ISNUMBER(D42),ISNUMBER(D29)),IFERROR(D42/D29,""),"") | E44: =IF(AND(ISNUMBER(E42),ISNUMBER(E29)),IFERROR(E42/E29,""),"") | F44: =IF(AND(ISNUMBER(F42),ISNUMBER(F29)),IFERROR(F42/F29,""),"") | G44: =IF(AND(ISNUMBER(G42),ISNUMBER(G29)),IFERROR(G42/G29,""),"") | H44: =IF(AND(ISNUMBER(H42),ISNUMBER(H29)),IFERROR(H42/H29,""),"") | I44: =IF(AND(ISNUMBER(I42),ISNUMBER(I29)),IFERROR(I42/I29,""),"") | J44: =IF(AND(ISNUMBER(J42),ISNUMBER(J29)),IFERROR(J42/J29,""),"") | ... BX44: =IF(AND(ISNUMBER(BX42),ISNUMBER(BX29)),IFERROR(BX42/BX29,""),"") -> 0.10931309 | BY44: =BY43+BY123 -> 0.10136986 | BZ44: =BZ43+BZ123 -> 0.10411142 | CA44: =IFERROR(CA42/CA29,"") -> 0.10377251 | CB44: =CHOOSE(MATCH($CF$2,{"Bull","Base","Bear"},0),$CO$52,$CP$52,$CQ$52) -> 0.115 | CC44: =CHOOSE(MATCH($CF$2,{"Bull","Base","Bear"},0),$CO$53,$CP$53,$CQ$53) -> 0.12 | CD44: =CHOOSE(MATCH($CF$2,{"Bull","Base","Bear"},0),$CO$54,$CP$54,$CQ$54) -> 0.125 | CE44: =CHOOSE(MATCH($CF$2,{"Bull","Base","Bear"},0),$CO$55,$CP$55,$CQ$55) -> 0.125 | CF44: LECO reports segment margins on total sales incl. inter-segment; the model uses external net sales (slightly higher). 2027E–30E: scenario lever. | CH44: =IFERROR(AVERAGE(CA44,CB44,CC44,CD44,CE44),"n/m") -> 0.1177545 | CI44: =IFERROR(AVERAGE(BB44,BG44,BL44,BQ44,BV44),"n/m") -> 0.12032531 | CJ44: =IFERROR(AVERAGE(AC44,AH44,AM44,AR44,AW44,BB44,BG44,BL44,BQ44,BV44),"n/m") -> 0.089172933 | CK44: =IFERROR(AVERAGE(C44,D44,E44,F44,G44,H44,I44,N44,S44,X44,AC44,AH44,AM44,AR44,AW44,BB44,BG44,BL44,BQ44,BV44),"n/m") -> 0.083303802 | CN44: 2029E | CO44: =CP44+$CO$41 -> 0.04 | CP44: 0.02 | CQ44: =CP44+$CQ$41 -> 0
B45: Incremental Adj. EBIT margin % (Δ Adj. EBIT / Δ net sales, y/y) | D45: =IF(AND(ISNUMBER(D42),ISNUMBER(C42)),IFERROR((D42-C42)/(D29-C29),""),"") | E45: =IF(AND(ISNUMBER(E42),ISNUMBER(D42)),IFERROR((E42-D42)/(E29-D29),""),"") | F45: =IF(AND(ISNUMBER(F42),ISNUMBER(E42)),IFERROR((F42-E42)/(F29-E29),""),"") | G45: =IF(AND(ISNUMBER(G42),ISNUMBER(F42)),IFERROR((G42-F42)/(G29-F29),""),"") | H45: =IF(AND(ISNUMBER(H42),ISNUMBER(G42)),IFERROR((H42-G42)/(H29-G29),""),"") | I45: =IF(AND(ISNUMBER(I42),ISNUMBER(H42)),IFERROR((I42-H42)/(I29-H29),""),"") | N45: =IF(AND(ISNUMBER(N42),ISNUMBER(I42)),IFERROR((N42-I42)/(N29-I29),""),"") | O45: =IF(AND(ISNUMBER(O42),ISNUMBER(J42)),IFERROR((O42-J42)/(O29-J29),""),"") | P45: =IF(AND(ISNUMBER(P42),ISNUMBER(K42)),IFERROR((P42-K42)/(P29-K29),""),"") | Q45: =IF(AND(ISNUMBER(Q42),ISNUMBER(L42)),IFERROR((Q42-L42)/(Q29-L29),""),"") | R45: =IF(AND(ISNUMBER(R42),ISNUMBER(M42)),IFERROR((R42-M42)/(R29-M29),""),"") | S45: =IF(AND(ISNUMBER(S42),ISNUMBER(N42)),IFERROR((S42-N42)/(S29-N29),""),"") -> -0.74151454 | T45: =IF(AND(ISNUMBER(T42),ISNUMBER(O42)),IFERROR((T42-O42)/(T29-O29),""),"") -> -0.083187808 | U45: =IF(AND(ISNUMBER(U42),ISNUMBER(P42)),IFERROR((U42-P42)/(U29-P29),""),"") -> 0.098738004 | ... CA45: =IF(AND(ISNUMBER(CA42),ISNUMBER(BV42)),IFERROR((CA42-BV42)/(CA29-BV29),""),"") -> -0.71345011 | CB45: =IF(AND(ISNUMBER(CB42),ISNUMBER(CA42)),IFERROR((CB42-CA42)/(CB29-CA29),""),"") -> 0.43578552 | CC45: =IF(AND(ISNUMBER(CC42),ISNUMBER(CB42)),IFERROR((CC42-CB42)/(CC29-CB29),""),"") -> 0.26285714 | CD45: =IF(AND(ISNUMBER(CD42),ISNUMBER(CC42)),IFERROR((CD42-CC42)/(CD29-CC29),""),"") -> 0.26785714 | CE45: =IF(AND(ISNUMBER(CE42),ISNUMBER(CD42)),IFERROR((CE42-CD42)/(CE29-CD29),""),"") -> 0.125 | CN45: 2030E | CO45: =CP45+$CO$41 -> 0.04 | CP45: 0.02 | CQ45: =CP45+$CQ$41 -> 0
CN46: IW_price (International Welding price y/y) | CO46: 0.01 | CP46: Δ → | CQ46: -0.01 | CR46: International pricing +0.3% (2025), +0.9% (1H/26).
B47: The Harris Products Group (brazing & soldering alloys, gas-control equipment, HVAC/R & retail; metals pass-through pricing) | CF47: HPG — modelling logic | CN47: 2027E | CO47: =CP47+$CO$46 -> 0.025 | CP47: 0.015 | CQ47: =CP47+$CQ$46 -> 0.005
B48: Net sales (external customers) | N48: 308.177 | O48: 72.471 | P48: 77.419 | Q48: 78.383 | R48: 65.957 | S48: 294.23 | T48: 69.816 | U48: 71.812 | V48: 62.922 | W48: 59.431 | X48: 263.981 | Y48: 67.409 | Z48: 71.231 | AA48: 70.562 | AB48: 63.141 | AC48: 272.343 | AD48: 68.685 | AE48: 80.213 | AF48: 73.585 | AG48: 68.145 | AH48: 290.628 | AI48: 75.604 | AJ48: 84.164 | AK48: 73.467 | AL48: 69.154 | AM48: 302.389 | AN48: 83.369 | AO48: 88.095 | AP48: 81.884 | AQ48: 79.802 | AR48: 333.15 | AS48: 85.533 | AT48: 80.331 | AU48: 100.416 | AV48: 92.441 | AW48: 358.721 | AX48: 108.7 | AY48: 116.634 | AZ48: 117.781 | BA48: 118.459 | BB48: 461.574 | BC48: 133.352 | BD48: 137.301 | BE48: 133.115 | BF48: 114.228 | BG48: 517.996 | BH48: 128.282 | BI48: 130.196 | BJ48: 125.976 | BK48: 111.63 | BL48: 496.084 | BM48: 121.337 | BN48: 133.989 | BO48: 130.509 | BP48: 124.266 | BQ48: 510.101 | BR48: 132.22 | BS48: 159.119 | BT48: 149.804 | BU48: 137.434 | BV48: 578.577 | BW48: 188.174 | BX48: 201.933 | BY48: =BT48*(1+BY55) -> 190.97612 | BZ48: =BU48*(1+BZ55) -> 175.20635 | CA48: =SUM(BW48:BZ48) -> 756.28947 | CB48: =CA48*(1+CB55) -> 778.97815 | CC48: =CB48*(1+CC55) -> 817.92706 | CD48: =CC48*(1+CD55) -> 858.82341 | CE48: =CD48*(1+CE55) -> 901.76458 | CF48: Q3/Q4-26E: prior-year quarter × (1 + volume + price + acquisitions + FX). 2027E+: prior year × (1 + Σ drivers). Current 3-segment structure from 2016 (2013–Q3/15 recast by LECO in the 8-K of 10-Feb-2016; Q4/15 derived = FY15 recast − 9M/15 recast). | CH48: =IFERROR((CE48/BV48)^(1/5)-1,"n/m") -> 0.092814382 | CI48: =IFERROR((BV48/AW48)^(1/5)-1,"n/m") -> 0.10032473 | CJ48: =IFERROR((BV48/X48)^(1/10)-1,"n/m") -> 0.081630312 | CK48: =IFERROR((BV48/C48)^(1/19)-1,"n/m") -> n/m | CN48: 2028E | CO48: =CP48+$CO$46 -> 0.025 | CP48: 0.015 | CQ48: =CP48+$CQ$46 -> 0.005
B49: Net sales y/y % | D49: =IF(AND(ISNUMBER(D48),ISNUMBER(C48)),IFERROR(D48/C48-1,""),"") | E49: =IF(AND(ISNUMBER(E48),ISNUMBER(D48)),IFERROR(E48/D48-1,""),"") | F49: =IF(AND(ISNUMBER(F48),ISNUMBER(E48)),IFERROR(F48/E48-1,""),"") | G49: =IF(AND(ISNUMBER(G48),ISNUMBER(F48)),IFERROR(G48/F48-1,""),"") | H49: =IF(AND(ISNUMBER(H48),ISNUMBER(G48)),IFERROR(H48/G48-1,""),"") | I49: =IF(AND(ISNUMBER(I48),ISNUMBER(H48)),IFERROR(I48/H48-1,""),"") | N49: =IF(AND(ISNUMBER(N48),ISNUMBER(I48)),IFERROR(N48/I48-1,""),"") | O49: =IF(AND(ISNUMBER(O48),ISNUMBER(J48)),IFERROR(O48/J48-1,""),"") | P49: =IF(AND(ISNUMBER(P48),ISNUMBER(K48)),IFERROR(P48/K48-1,""),"") | Q49: =IF(AND(ISNUMBER(Q48),ISNUMBER(L48)),IFERROR(Q48/L48-1,""),"") | R49: =IF(AND(ISNUMBER(R48),ISNUMBER(M48)),IFERROR(R48/M48-1,""),"") | S49: =IF(AND(ISNUMBER(S48),ISNUMBER(N48)),IFERROR(S48/N48-1,""),"") -> -0.04525646 | T49: =IF(AND(ISNUMBER(T48),ISNUMBER(O48)),IFERROR(T48/O48-1,""),"") -> -0.036635344 | U49: =IF(AND(ISNUMBER(U48),ISNUMBER(P48)),IFERROR(U48/P48-1,""),"") -> -0.072424082 | ... BX49: =IF(AND(ISNUMBER(BX48),ISNUMBER(BS48)),IFERROR(BX48/BS48-1,""),"") -> 0.26906906 | BY49: =IFERROR(BY48/BT48-1,"") -> 0.27483991 | BZ49: =IFERROR(BZ48/BU48-1,"") -> 0.27483991 | CA49: =IFERROR(CA48/BV48-1,"") -> 0.30715439 | CB49: =IFERROR(CB48/CA48-1,"") -> 0.03 | CC49: =IFERROR(CC48/CB48-1,"") -> 0.05 | CD49: =IFERROR(CD48/CC48-1,"") -> 0.05 | CE49: =IFERROR(CE48/CD48-1,"") -> 0.05 | CN49: 2029E | CO49: =CP49+$CO$46 -> 0.025 | CP49: 0.015 | CQ49: =CP49+$CQ$46 -> 0.005
B50: Volume % before outlook calibration (Q3/Q4-26E helper) | BY50: =$BX$51 -> -0.081593 | BZ50: =$BX$51 -> -0.081593 | CF50: Q2/26 y/y volume held for Q3/Q4-26E before the FY26 net-sales calibration (Group block). | CN50: 2030E | CO50: =CP50+$CO$46 -> 0.025 | CP50: 0.015 | CQ50: =CP50+$CQ$46 -> 0.005
B51: Volume % (company: change in net sales due to volume) | Y51: 0.019909 | Z51: 0.010249 | AA51: 0.083198 | AB51: 0.039071 | AC51: 0.036681 | AD51: -0.029432 | AE51: 0.111131 | AF51: 0.071568 | AG51: 0.069369 | AH51: 0.056407 | AI51: 0.092888 | AJ51: 0.035194 | AK51: 0.002365 | AL51: 0.045785 | AM51: 0.043 | AN51: 0.039165 | AO51: -0.004955 | AP51: 0.046674 | AQ51: 0.056757 | AR51: 0.032733 | AS51: 0.033586 | AT51: -0.078222 | AU51: 0.127754 | AV51: 0.073582 | AW51: 0.036746 | AX51: 0.1361 | AY51: 0.229314 | AZ51: -0.012817 | BA51: 0.054056 | BB51: 0.094146 | BC51: 0.028905 | BD51: -0.004921 | BE51: 0.11113 | BF51: -0.023949 | BG51: 0.027775 | BH51: -0.037622 | BI51: -0.064479 | BJ51: -0.112076 | BK51: -0.069195 | BL51: -0.070836 | BM51: -0.069035 | BN51: -0.019378 | BO51: -0.029585 | BP51: 0.027385 | BQ51: -0.024288 | BR51: 0.006486 | BS51: 0.109494 | BT51: 0.022972 | BU51: -0.088753 | BV51: 0.01456 | BW51: -0.010399 | BX51: -0.081593 | BY51: =BY50+BY118 -> -0.075822086 | BZ51: =BZ50+BZ118 -> -0.075822086 | CA51: =IFERROR(SUMPRODUCT(BR48:BU48,BW51:BZ51)/SUM(BR48:BU48),"") -> -0.062458301 | CB51: =CHOOSE(MATCH($CF$2,{"Bull","Base","Bear"},0),$CO$57,$CP$57,$CQ$57) -> 0.03 | CC51: =CHOOSE(MATCH($CF$2,{"Bull","Base","Bear"},0),$CO$58,$CP$58,$CQ$58) -> 0.03 | CD51: =CHOOSE(MATCH($CF$2,{"Bull","Base","Bear"},0),$CO$59,$CP$59,$CQ$59) -> 0.03 | CE51: =CHOOSE(MATCH($CF$2,{"Bull","Base","Bear"},0),$CO$60,$CP$60,$CQ$60) -> 0.03 | CF51: Historical = LECO "Change in Net Sales by Segment" table (8-K Ex.99.1) ÷ prior-year segment net sales. Q3/Q4-26E: Q2/26 y/y + FY26 calibration Δ. 2027E–30E: scenario lever (Bull/Base/Bear table →). | CN51: IW_mgn (International Welding Adj. EBIT margin) | CO51: 0.015 | CP51: Δ → | CQ51: -0.015 | CR51: FY25 11.9%, 1H/26 10.5%; 2022–23 peak 12.6–13.1% after the 2020–21 restructuring.
B52: Price % | Y52: -0.034433 | Z52: -0.011266 | AA52: 0.035377 | AB52: 0.015177 | AC52: -0.000322 | AD52: 0.040321 | AE52: 0.009715 | AF52: -0.036904 | AG52: -0.001014 | AH52: 0.002725 | AI52: -0.007221 | AJ52: 0.014636 | AK52: 0.010233 | AL52: -0.015452 | AM52: 0.001301 | AN52: 0.005952 | AO52: -0.007545 | AP52: 0.010358 | AQ52: 0.032912 | AR52: 0.009432 | AS52: 0.003874 | AT52: 0.003156 | AU52: 0.115676 | AV52: 0.106489 | AW52: 0.055744 | AX52: 0.145476 | AY52: 0.211363 | AZ52: 0.085733 | BA52: 0.069536 | BB52: 0.123938 | BC52: 0.061849 | BD52: 0.041326 | BE52: -0.004916 | BF52: -0.000819 | BG52: 0.023543 | BH52: 0.004237 | BI52: 0.010255 | BJ52: 0.046809 | BK52: 0.036121 | BL52: 0.023803 | BM52: 0.011249 | BN52: 0.051676 | BO52: 0.070633 | BP52: 0.098289 | BQ52: 0.056525 | BR52: 0.095058 | BS52: 0.073573 | BT52: 0.118245 | BU52: 0.178416 | BV52: 0.115654 | BW52: 0.414325 | BX52: 0.342222 | BY52: =$BX$52 -> 0.342222 | BZ52: =$BX$52 -> 0.342222 | CA52: =IFERROR(SUMPRODUCT(BR48:BU48,BW52:BZ52)/SUM(BR48:BU48),"") -> 0.35869942 | CB52: =CHOOSE(MATCH($CF$2,{"Bull","Base","Bear"},0),$CO$62,$CP$62,$CQ$62) -> 0 | CC52: =CHOOSE(MATCH($CF$2,{"Bull","Base","Bear"},0),$CO$63,$CP$63,$CQ$63) -> 0.02 | CD52: =CHOOSE(MATCH($CF$2,{"Bull","Base","Bear"},0),$CO$64,$CP$64,$CQ$64) -> 0.02 | CE52: =CHOOSE(MATCH($CF$2,{"Bull","Base","Bear"},0),$CO$65,$CP$65,$CQ$65) -> 0.02 | CF52: Q3/Q4-26E: Q2/26 y/y price held. 2027E–30E: scenario lever. | CN52: 2027E | CO52: =CP52+$CO$51 -> 0.13 | CP52: 0.115 | CQ52: =CP52+$CQ$51 -> 0.1
B53: Acquisitions % (inorganic contribution, first 12 months) | Y53: 0 | Z53: 0 | AA53: 0 | AB53: 0 | AC53: 0 | AD53: 0 | AE53: 0 | AF53: 0 | AG53: 0 | AH53: 0 | AI53: 0 | AJ53: 0 | AK53: 0 | AL53: 0 | AM53: 0 | AN53: 0.076372 | AO53: 0.067202 | AP53: 0.064873 | AQ53: 0.069931 | AR53: 0.069553 | AS53: 0 | AT53: 0 | AU53: 0 | AV53: 0 | AW53: 0 | AX53: 0 | AY53: 0 | AZ53: 0.098391 | BA53: 0.163055 | BB53: 0.069561 | BC53: 0.142153 | BD53: 0.157818 | BE53: 0.047138 | BF53: 0 | BG53: 0.085384 | BH53: 0 | BI53: 0 | BJ53: 0 | BK53: 0 | BL53: 0 | BM53: 0 | BN53: 0 | BO53: 0 | BP53: 0 | BQ53: 0 | BR53: 0 | BS53: 0 | BT53: 0 | BU53: 0 | BV53: 0 | BW53: 0 | BX53: 0 | BY53: 0 | BZ53: 0 | CA53: =IFERROR(SUMPRODUCT(BR48:BU48,BW53:BZ53)/SUM(BR48:BU48),"") -> 0 | CB53: 0 | CC53: 0 | CD53: 0 | CE53: 0 | CF53: Q3/Q4-26E: input — 2025 bolt-ons anniversary during 2H/26 (International Welding +7.0% in Q2/26, fading). 2027E+: 0% here; future bolt-ons modelled in the unallocated M&A block. | CN53: 2028E | CO53: =CP53+$CO$51 -> 0.135 | CP53: 0.12 | CQ53: =CP53+$CQ$51 -> 0.105
B54: Foreign exchange % | Y54: -0.019952 | Z54: -0.007074 | AA54: 0.002845 | AB54: 0.008178 | AC54: -0.004682 | AD54: 0.00804 | AE54: 0.005251 | AF54: 0.008177 | AG54: 0.010896 | AH54: 0.008008 | AI54: 0.015069 | AJ54: -0.000573 | AK54: -0.014201 | AL54: -0.015526 | AM54: -0.003833 | AN54: -0.018782 | AO54: -0.007996 | AP54: -0.007337 | AQ54: -0.005625 | AR54: -0.00999 | AS54: -0.011503 | AT54: -0.013065 | AU54: -0.01711 | AV54: -0.021691 | AW54: -0.015735 | AX54: -0.010721 | AY54: 0.011241 | AZ54: 0.001623 | BA54: -0.005193 | BB54: -0.000923 | BC54: -0.006118 | BD54: -0.017028 | BE54: -0.023162 | BF54: -0.010949 | BG54: -0.014464 | BH54: -0.004634 | BI54: 0.002476 | BJ54: 0.011637 | BK54: 0.01033 | BL54: 0.004732 | BM54: 0.003648 | BN54: -0.003164 | BO54: -0.005064 | BP54: -0.012479 | BQ54: -0.003981 | BR54: -0.011851 | BS54: 0.004485 | BT54: 0.006628 | BU54: 0.016304 | BV54: 0.004027 | BW54: 0.019263 | BX54: 0.00844 | BY54: =$BX$54 -> 0.00844 | BZ54: =$BX$54 -> 0.00844 | CA54: =IFERROR(SUMPRODUCT(BR48:BU48,BW54:BZ54)/SUM(BR48:BU48),"") -> 0.010913339 | CB54: 0 | CC54: 0 | CD54: 0 | CE54: 0 | CF54: Q3/Q4-26E: Q2/26 FX translation held; 2027E+: constant currency (0%). | CN54: 2029E | CO54: =CP54+$CO$51 -> 0.14 | CP54: 0.125 | CQ54: =CP54+$CQ$51 -> 0.11
B55: Net sales growth % (volume + price + acquisitions + FX) | C55: =IF(ISNUMBER(C51),C51+C52+C53+C54,"") | D55: =IF(ISNUMBER(D51),D51+D52+D53+D54,"") | E55: =IF(ISNUMBER(E51),E51+E52+E53+E54,"") | F55: =IF(ISNUMBER(F51),F51+F52+F53+F54,"") | G55: =IF(ISNUMBER(G51),G51+G52+G53+G54,"") | H55: =IF(ISNUMBER(H51),H51+H52+H53+H54,"") | I55: =IF(ISNUMBER(I51),I51+I52+I53+I54,"") | J55: =IF(ISNUMBER(J51),J51+J52+J53+J54,"") | ... BX55: =IF(ISNUMBER(BX51),BX51+BX52+BX53+BX54,"") -> 0.269069 | BY55: =BY51+BY52+BY53+BY54 -> 0.27483991 | BZ55: =BZ51+BZ52+BZ53+BZ54 -> 0.27483991 | CA55: =CA51+CA52+CA53+CA54 -> 0.30715446 | CB55: =CB51+CB52+CB53+CB54 -> 0.03 | CC55: =CC51+CC52+CC53+CC54 -> 0.05 | CD55: =CD51+CD52+CD53+CD54 -> 0.05 | CE55: =CE51+CE52+CE53+CE54 -> 0.05 | CN55: 2030E | CO55: =CP55+$CO$51 -> 0.14 | CP55: 0.125 | CQ55: =CP55+$CQ$51 -> 0.11
B56: Organic growth % (volume + price) | C56: =IF(ISNUMBER(C51),C51+C52,"") | D56: =IF(ISNUMBER(D51),D51+D52,"") | E56: =IF(ISNUMBER(E51),E51+E52,"") | F56: =IF(ISNUMBER(F51),F51+F52,"") | G56: =IF(ISNUMBER(G51),G51+G52,"") | H56: =IF(ISNUMBER(H51),H51+H52,"") | I56: =IF(ISNUMBER(I51),I51+I52,"") | J56: =IF(ISNUMBER(J51),J51+J52,"") | ... BX56: =IF(ISNUMBER(BX51),BX51+BX52,"") -> 0.260629 | BY56: =BY51+BY52 -> 0.26639991 | BZ56: =BZ51+BZ52 -> 0.26639991 | CA56: =CA51+CA52 -> 0.29624112 | CB56: =CB51+CB52 -> 0.03 | CC56: =CC51+CC52 -> 0.05 | CD56: =CD51+CD52 -> 0.05 | CE56: =CE51+CE52 -> 0.05 | CN56: HPG_vol (Harris Products Group volume y/y) | CO56: 0.02 | CP56: Δ → | CQ56: -0.02 | CR56: HVAC/R, brazing & retail; volume +1.5% (2025), −4.9% (1H/26).
B57: Check: Σ drivers vs reported y/y % (≈0; ≠0 where LECO recast the prior-year base) | C57: =IF(AND(ISNUMBER(C55),ISNUMBER(C49)),ROUND(C55-C49,3),"") | D57: =IF(AND(ISNUMBER(D55),ISNUMBER(D49)),ROUND(D55-D49,3),"") | E57: =IF(AND(ISNUMBER(E55),ISNUMBER(E49)),ROUND(E55-E49,3),"") | F57: =IF(AND(ISNUMBER(F55),ISNUMBER(F49)),ROUND(F55-F49,3),"") | G57: =IF(AND(ISNUMBER(G55),ISNUMBER(G49)),ROUND(G55-G49,3),"") | H57: =IF(AND(ISNUMBER(H55),ISNUMBER(H49)),ROUND(H55-H49,3),"") | I57: =IF(AND(ISNUMBER(I55),ISNUMBER(I49)),ROUND(I55-I49,3),"") | J57: =IF(AND(ISNUMBER(J55),ISNUMBER(J49)),ROUND(J55-J49,3),"") | ... BX57: =IF(AND(ISNUMBER(BX55),ISNUMBER(BX49)),ROUND(BX55-BX49,3),"") -> 0 | CN57: 2027E | CO57: =CP57+$CO$56 -> 0.05 | CP57: 0.03 | CQ57: =CP57+$CQ$56 -> 0.01
B58: Memo: inter-segment sales (eliminated in Corporate / Eliminations) | N58: 9.605 | O58: 2.118 | P58: 2.262 | Q58: 2.009 | R58: 1.821 | S58: 8.21 | T58: 2.011 | U58: 2.716 | V58: 2.307 | W58: 2.278 | X58: 9.312 | Y58: 2.303 | Z58: 2.824 | AA58: 1.856 | AB58: 1.726 | AC58: 8.709 | AD58: 2.3 | AE58: 2.399 | AF58: 2.064 | AG58: 1.427 | AH58: 8.19 | AI58: 1.907 | AJ58: 2.003 | AK58: 1.537 | AL58: 1.522 | AM58: 6.969 | AN58: 1.867 | AO58: 2.113 | AP58: 1.857 | AQ58: 1.65 | AR58: 7.487 | AS58: 1.725 | AT58: 1.753 | AU58: 1.898 | AV58: 1.658 | AW58: 7.034 | AX58: 2.147 | AY58: 2.284 | AZ58: 1.945 | BA58: 1.72 | BB58: 8.096 | BC58: 3.062 | BD58: 2.866 | BE58: 2.642 | BF58: 2.47 | BG58: 11.04 | BH58: 2.897 | BI58: 2.867 | BJ58: 2.299 | BK58: 2.578 | BL58: 10.641 | BM58: 3.093 | BN58: 3.272 | BO58: 3.155 | BP58: 2.801 | BQ58: 12.321 | BR58: 3.984 | BS58: 5.11 | BT58: 3.441 | BU58: 2.549 | BV58: 15.084 | BW58: 4.664 | BX58: 4.972 | CN58: 2028E | CO58: =CP58+$CO$56 -> 0.05 | CP58: 0.03 | CQ58: =CP58+$CQ$56 -> 0.01
B59: EBIT (GAAP segment result = operating income + other income) | N59: 27.826 | O59: 6.058 | P59: 7.178 | Q59: 8.947 | R59: 6.38 | S59: 28.563 | T59: 7.549 | U59: 8.25 | V59: 6.422 | W59: 5.661 | X59: 27.882 | Y59: 7.711 | Z59: 9.284 | AA59: 8.757 | AB59: 6.628 | AC59: 32.38 | AD59: 8.46 | AE59: 9.787 | AF59: 9.244 | AG59: 8.951 | AH59: 36.442 | AI59: 9.225 | AJ59: 10.157 | AK59: 8.676 | AL59: 8.506 | AM59: 36.564 | AN59: 10.519 | AO59: 13.488 | AP59: 11.038 | AQ59: 8.886 | AR59: 43.931 | AS59: 12.492 | AT59: 11.713 | AU59: 17.587 | AV59: 13.362 | AW59: 55.154 | AX59: 18.697 | AY59: 18.212 | AZ59: 15.433 | BA59: 12.32 | BB59: 64.662 | BC59: 19.598 | BD59: 17.922 | BE59: 14.432 | BF59: 12.056 | BG59: 64.008 | BH59: 18.983 | BI59: 19.51 | BJ59: 20.405 | BK59: 15.246 | BL59: 74.144 | BM59: 18.342 | BN59: 25.063 | BO59: 20.69 | BP59: 20.278 | BQ59: 84.373 | BR59: 24.151 | BS59: 31.798 | BT59: 27.762 | BU59: 22.829 | BV59: 106.54 | BW59: 40.991 | BX59: 42.066 | CN59: 2029E | CO59: =CP59+$CO$56 -> 0.05 | CP59: 0.03 | CQ59: =CP59+$CQ$56 -> 0.01
B60: Special items in segment EBIT (rationalization, impairments, acquisition costs) | C60: =IF(AND(ISNUMBER(C61),ISNUMBER(C59)),C61-C59,"") | D60: =IF(AND(ISNUMBER(D61),ISNUMBER(D59)),D61-D59,"") | E60: =IF(AND(ISNUMBER(E61),ISNUMBER(E59)),E61-E59,"") | F60: =IF(AND(ISNUMBER(F61),ISNUMBER(F59)),F61-F59,"") | G60: =IF(AND(ISNUMBER(G61),ISNUMBER(G59)),G61-G59,"") | H60: =IF(AND(ISNUMBER(H61),ISNUMBER(H59)),H61-H59,"") | I60: =IF(AND(ISNUMBER(I61),ISNUMBER(I59)),I61-I59,"") | J60: =IF(AND(ISNUMBER(J61),ISNUMBER(J59)),J61-J59,"") | ... BX60: =IF(AND(ISNUMBER(BX61),ISNUMBER(BX59)),BX61-BX59,"") -> 0.187 | CN60: 2030E | CO60: =CP60+$CO$56 -> 0.05 | CP60: 0.03 | CQ60: =CP60+$CQ$56 -> 0.01
B61: Adjusted EBIT (company segment profit measure) | N61: 27.826 | O61: 6.058 | P61: 7.178 | Q61: 8.947 | R61: 6.38 | S61: 28.563 | T61: 7.549 | U61: 8.25 | V61: 6.422 | W61: 5.661 | X61: 27.882 | Y61: 7.711 | Z61: 9.284 | AA61: 8.757 | AB61: 6.628 | AC61: 32.38 | AD61: 8.46 | AE61: 9.787 | AF61: 9.244 | AG61: 8.951 | AH61: 36.442 | AI61: 9.225 | AJ61: 10.157 | AK61: 8.676 | AL61: 8.506 | AM61: 36.564 | AN61: 10.519 | AO61: 13.488 | AP61: 11.038 | AQ61: 10.656 | AR61: 45.701 | AS61: 12.492 | AT61: 11.713 | AU61: 17.587 | AV61: 13.362 | AW61: 55.154 | AX61: 18.697 | AY61: 18.212 | AZ61: 15.98 | BA61: 15.558 | BB61: 68.447 | BC61: 19.598 | BD61: 17.922 | BE61: 14.432 | BF61: 12.056 | BG61: 64.008 | BH61: 18.983 | BI61: 19.51 | BJ61: 20.405 | BK61: 15.246 | BL61: 74.144 | BM61: 19.878 | BN61: 24.923 | BO61: 21.959 | BP61: 21.567 | BQ61: 88.328 | BR61: 24.329 | BS61: 31.884 | BT61: 28.078 | BU61: 23.317 | BV61: 107.608 | BW61: 40.809 | BX61: 42.253 | BY61: =BY48*BY63 -> 38.577412 | BZ61: =BZ48*BZ63 -> 32.278139 | CA61: =SUM(BW61:BZ61) -> 153.91755 | CB61: =CB48*CB63 -> 151.90074 | CC61: =CC48*CC63 -> 159.49578 | CD61: =CD48*CD63 -> 167.47057 | CE61: =CE48*CE63 -> 175.84409 | CF61: Net sales × Adjusted EBIT margin. Forecast special items are modelled at group level (EBIT bridge), not allocated to segments. | CH61: =IFERROR((CE61/BV61)^(1/5)-1,"n/m") -> 0.10320608 | CI61: =IFERROR((BV61/AW61)^(1/5)-1,"n/m") -> 0.14301916 | CJ61: =IFERROR((BV61/X61)^(1/10)-1,"n/m") -> 0.14459558 | CK61: =IFERROR((BV61/C61)^(1/19)-1,"n/m") -> n/m | CN61: HPG_price (Harris Products Group price y/y) | CO61: 0.01 | CP61: Δ → | CQ61: -0.01 | CR61: Harris price +11.6% (2025), +37.5% (1H/26) = silver / copper pass-through; 2027E assumes metals plateau (0%).
B62: Adj. EBIT margin before outlook calibration % (Q3/Q4-26E helper) | BY62: =BT63+($BX$63-$BS$63) -> 0.19629591 | BZ62: =BU63+($BX$63-$BS$63) -> 0.17852395 | CF62: Prior-year quarter margin + Q2/26 y/y margin change. | CN62: 2027E | CO62: =CP62+$CO$61 -> 0.01 | CP62: 0 | CQ62: =CP62+$CQ$61 -> -0.01
B63: Adjusted EBIT margin % (on external net sales) | C63: =IF(AND(ISNUMBER(C61),ISNUMBER(C48)),IFERROR(C61/C48,""),"") | D63: =IF(AND(ISNUMBER(D61),ISNUMBER(D48)),IFERROR(D61/D48,""),"") | E63: =IF(AND(ISNUMBER(E61),ISNUMBER(E48)),IFERROR(E61/E48,""),"") | F63: =IF(AND(ISNUMBER(F61),ISNUMBER(F48)),IFERROR(F61/F48,""),"") | G63: =IF(AND(ISNUMBER(G61),ISNUMBER(G48)),IFERROR(G61/G48,""),"") | H63: =IF(AND(ISNUMBER(H61),ISNUMBER(H48)),IFERROR(H61/H48,""),"") | I63: =IF(AND(ISNUMBER(I61),ISNUMBER(I48)),IFERROR(I61/I48,""),"") | J63: =IF(AND(ISNUMBER(J61),ISNUMBER(J48)),IFERROR(J61/J48,""),"") | ... BX63: =IF(AND(ISNUMBER(BX61),ISNUMBER(BX48)),IFERROR(BX61/BX48,""),"") -> 0.20924267 | BY63: =BY62+BY123 -> 0.20200124 | BZ63: =BZ62+BZ123 -> 0.18422928 | CA63: =IFERROR(CA61/CA48,"") -> 0.20351672 | CB63: =CHOOSE(MATCH($CF$2,{"Bull","Base","Bear"},0),$CO$67,$CP$67,$CQ$67) -> 0.195 | CC63: =CHOOSE(MATCH($CF$2,{"Bull","Base","Bear"},0),$CO$68,$CP$68,$CQ$68) -> 0.195 | CD63: =CHOOSE(MATCH($CF$2,{"Bull","Base","Bear"},0),$CO$69,$CP$69,$CQ$69) -> 0.195 | CE63: =CHOOSE(MATCH($CF$2,{"Bull","Base","Bear"},0),$CO$70,$CP$70,$CQ$70) -> 0.195 | CF63: LECO reports segment margins on total sales incl. inter-segment; the model uses external net sales (slightly higher). 2027E–30E: scenario lever. | CH63: =IFERROR(AVERAGE(CA63,CB63,CC63,CD63,CE63),"n/m") -> 0.19670334 | CI63: =IFERROR(AVERAGE(BB63,BG63,BL63,BQ63,BV63),"n/m") -> 0.15609254 | CJ63: =IFERROR(AVERAGE(AC63,AH63,AM63,AR63,AW63,BB63,BG63,BL63,BQ63,BV63),"n/m") -> 0.14365948 | CK63: =IFERROR(AVERAGE(C63,D63,E63,F63,G63,H63,I63,N63,S63,X63,AC63,AH63,AM63,AR63,AW63,BB63,BG63,BL63,BQ63,BV63),"n/m") -> 0.13304503 | CN63: 2028E | CO63: =CP63+$CO$61 -> 0.03 | CP63: 0.02 | CQ63: =CP63+$CQ$61 -> 0.01
B64: Incremental Adj. EBIT margin % (Δ Adj. EBIT / Δ net sales, y/y) | D64: =IF(AND(ISNUMBER(D61),ISNUMBER(C61)),IFERROR((D61-C61)/(D48-C48),""),"") | E64: =IF(AND(ISNUMBER(E61),ISNUMBER(D61)),IFERROR((E61-D61)/(E48-D48),""),"") | F64: =IF(AND(ISNUMBER(F61),ISNUMBER(E61)),IFERROR((F61-E61)/(F48-E48),""),"") | G64: =IF(AND(ISNUMBER(G61),ISNUMBER(F61)),IFERROR((G61-F61)/(G48-F48),""),"") | H64: =IF(AND(ISNUMBER(H61),ISNUMBER(G61)),IFERROR((H61-G61)/(H48-G48),""),"") | I64: =IF(AND(ISNUMBER(I61),ISNUMBER(H61)),IFERROR((I61-H61)/(I48-H48),""),"") | N64: =IF(AND(ISNUMBER(N61),ISNUMBER(I61)),IFERROR((N61-I61)/(N48-I48),""),"") | O64: =IF(AND(ISNUMBER(O61),ISNUMBER(J61)),IFERROR((O61-J61)/(O48-J48),""),"") | P64: =IF(AND(ISNUMBER(P61),ISNUMBER(K61)),IFERROR((P61-K61)/(P48-K48),""),"") | Q64: =IF(AND(ISNUMBER(Q61),ISNUMBER(L61)),IFERROR((Q61-L61)/(Q48-L48),""),"") | R64: =IF(AND(ISNUMBER(R61),ISNUMBER(M61)),IFERROR((R61-M61)/(R48-M48),""),"") | S64: =IF(AND(ISNUMBER(S61),ISNUMBER(N61)),IFERROR((S61-N61)/(S48-N48),""),"") -> -0.052842905 | T64: =IF(AND(ISNUMBER(T61),ISNUMBER(O61)),IFERROR((T61-O61)/(T48-O48),""),"") -> -0.56158192 | U64: =IF(AND(ISNUMBER(U61),ISNUMBER(P61)),IFERROR((U61-P61)/(U48-P48),""),"") -> -0.19118958 | ... CA64: =IF(AND(ISNUMBER(CA61),ISNUMBER(BV61)),IFERROR((CA61-BV61)/(CA48-BV48),""),"") -> 0.26058696 | CB64: =IF(AND(ISNUMBER(CB61),ISNUMBER(CA61)),IFERROR((CB61-CA61)/(CB48-CA48),""),"") -> -0.088890622 | CC64: =IF(AND(ISNUMBER(CC61),ISNUMBER(CB61)),IFERROR((CC61-CB61)/(CC48-CB48),""),"") -> 0.195 | CD64: =IF(AND(ISNUMBER(CD61),ISNUMBER(CC61)),IFERROR((CD61-CC61)/(CD48-CC48),""),"") -> 0.195 | CE64: =IF(AND(ISNUMBER(CE61),ISNUMBER(CD61)),IFERROR((CE61-CD61)/(CE48-CD48),""),"") -> 0.195 | CN64: 2029E | CO64: =CP64+$CO$61 -> 0.03 | CP64: 0.02 | CQ64: =CP64+$CQ$61 -> 0.01
CN65: 2030E | CO65: =CP65+$CO$61 -> 0.03 | CP65: 0.02 | CQ65: =CP65+$CQ$61 -> 0.01
B66: Corporate / Eliminations (unallocated corporate costs, inter-segment eliminations) | CN66: HPG_mgn (Harris Products Group Adj. EBIT margin) | CO66: 0.015 | CP66: Δ → | CQ66: -0.015 | CR66: FY25 18.6%, 1H/26 21.3% (metals price inflation); structural step-up from 9–12% (2013–19) on automation / mix.
B67: Corporate / Eliminations — Adjusted EBIT | F67: -3.344 | G67: -6.675 | H67: 0.426 | I67: -4.886 | J67: -0.603 | K67: -1.538 | L67: -0.822 | M67: -1.387 | N67: -5.948 | O67: 2.67 | P67: 0.785 | Q67: -0.302 | R67: 0.649 | S67: 3.802 | T67: 0.06 | U67: 0.634 | V67: -0.748 | W67: -0.221 | X67: -0.275 | Y67: 1.197 | Z67: -0.298 | AA67: 0.913 | AB67: -1.248 | AC67: 0.564 | AD67: 0.064 | AE67: -0.265 | AF67: 0.57 | AG67: -0.06 | AH67: 0.309 | AI67: -0.158 | AJ67: -3.186 | AK67: -1.099 | AL67: -4.444 | AM67: -8.887 | AN67: -3.042 | AO67: -3.969 | AP67: -1.632 | AQ67: -2.305 | AR67: -10.948 | AS67: -1.099 | AT67: -1.964 | AU67: -1.839 | AV67: -0.553 | AW67: -5.455 | AX67: -1.456 | AY67: -3.888 | AZ67: -4.704 | BA67: -2.355 | BB67: -12.403 | BC67: -4.801 | BD67: -3.984 | BE67: -1.685 | BF67: 0.437 | BG67: -10.033 | BH67: -9.374 | BI67: -2.183 | BJ67: -2.952 | BK67: -2.997 | BL67: -17.536 | BM67: -10.078 | BN67: -6.264 | BO67: 4.503 | BP67: 0.812 | BQ67: -11.028 | BR67: -1.65 | BS67: -1.2 | BT67: 2.034 | BU67: 0.416 | BV67: -0.4 | BW67: -1.395 | BX67: -3.044 | BY67: =BY102*BY68 -> -2.2197119 | BZ67: =BZ102*BZ68 -> -2.2281199 | CA67: =SUM(BW67:BZ67) -> -8.8868318 | CB67: =CB102*CB68 -> -9.9131961 | CC67: =CC102*CC68 -> -10.411386 | CD67: =CD102*CD68 -> -10.90149 | CE67: =CE102*CE68 -> -11.415033 | CN67: 2027E | CO67: =CP67+$CO$66 -> 0.21 | CP67: 0.195 | CQ67: =CP67+$CQ$66 -> 0.18
B68: Corporate / Eliminations % of segment net sales | C68: =IF(AND(ISNUMBER(C67),ISNUMBER(C103)),IFERROR(C67/C103,""),"") | D68: =IF(AND(ISNUMBER(D67),ISNUMBER(D103)),IFERROR(D67/D103,""),"") | E68: =IF(AND(ISNUMBER(E67),ISNUMBER(E103)),IFERROR(E67/E103,""),"") | F68: =IF(AND(ISNUMBER(F67),ISNUMBER(F103)),IFERROR(F67/F103,""),"") -> -0.0019337472 | G68: =IF(AND(ISNUMBER(G67),ISNUMBER(G103)),IFERROR(G67/G103,""),"") -> -0.0032243698 | H68: =IF(AND(ISNUMBER(H67),ISNUMBER(H103)),IFERROR(H67/H103,""),"") -> 0.00015809344 | I68: =IF(AND(ISNUMBER(I67),ISNUMBER(I103)),IFERROR(I67/I103,""),"") -> -0.001712363 | J68: =IF(AND(ISNUMBER(J67),ISNUMBER(J103)),IFERROR(J67/J103,""),"") -> -0.00083916317 | ... BX68: =IF(AND(ISNUMBER(BX67),ISNUMBER(BX103)),IFERROR(BX67/BX103,""),"") -> -0.0024957714 | BY68: =AVERAGE($BW$68,$BX$68) -> -0.0018698572 | BZ68: =AVERAGE($BW$68,$BX$68) -> -0.0018698572 | CA68: =IFERROR(CA67/CA102,"") -> -0.0018828838 | CB68: -0.002 | CC68: -0.002 | CD68: -0.002 | CE68: -0.002 | CF68: 2023–25 range −0.4% to −0.01% of sales; Q3/Q4-26E = 1H/26 average; 2027E+ input. | CN68: 2028E | CO68: =CP68+$CO$66 -> 0.21 | CP68: 0.195 | CQ68: =CP68+$CQ$66 -> 0.18
B69: Memo: Corporate / Eliminations — EBIT (GAAP) | F69: -3.344 | G69: -6.675 | H69: 0.426 | I69: -4.886 | J69: -0.603 | K69: -1.538 | L69: -0.822 | M69: -1.387 | N69: -5.948 | O69: 2.67 | P69: 0.785 | Q69: -0.302 | R69: 0.649 | S69: 3.802 | T69: 0.06 | U69: 0.634 | V69: -0.748 | W69: -0.221 | X69: -0.275 | Y69: 1.197 | Z69: -34.646 | AA69: 0.913 | AB69: -1.248 | AC69: -33.784 | AD69: -3.551 | AE69: -4.763 | AF69: 48.882 | AG69: -5.611 | AH69: 34.957 | AI69: -2.065 | AJ69: -3.974 | AK69: -2.069 | AL69: -5.277 | AM69: -13.385 | AN69: -3.832 | AO69: -4.983 | AP69: -1.632 | AQ69: -2.305 | AR69: -12.752 | AS69: -1.099 | AT69: -1.964 | AU69: -1.839 | AV69: -0.553 | AW69: -5.455 | AX69: -2.569 | AY69: -4.698 | AZ69: -4.704 | BA69: -2.355 | BB69: -14.326 | BC69: -4.801 | BD69: -3.984 | BE69: -4.753 | BF69: -2.498 | BG69: -16.036 | BH69: -9.374 | BI69: -2.183 | BJ69: -2.952 | BK69: -2.997 | BL69: -17.536 | BM69: -11.84 | BN69: -8.55 | BO69: 3.893 | BP69: -1.679 | BQ69: -18.175 | BR69: -2.452 | BS69: -1.629 | BT69: 1.582 | BU69: -0.302 | BV69: -2.801 | BW69: -2.048 | BX69: -3.059 | CN69: 2029E | CO69: =CP69+$CO$66 -> 0.21 | CP69: 0.195 | CQ69: =CP69+$CQ$66 -> 0.18
CN70: 2030E | CO70: =CP70+$CO$66 -> 0.21 | CP70: 0.195 | CQ70: =CP70+$CQ$66 -> 0.18
B71: Legacy segments (as originally reported to Q4/15: North America · Europe · Asia Pacific · South America Welding · Harris) — memo | CN71: M&A_spend (bolt-on acquisitions, $m) | CO71: 150 | CP71: Δ → | CQ71: -150 | CR71: RISE: 300–400 bp of revenue CAGR from bolt-ons (2030 sales > $6bn); 2021–25 spend $0.1–0.3bn p.a.
B72: North America Welding — net sales | D72: 1248.382 | E72: 1313.881 | F72: 858.18 | G72: 1013.193 | H72: 1309.499 | I72: 1580.818 | J72: 419.554 | K72: 419.069 | L72: 404.113 | M72: 410.033 | N72: 1652.769 | O72: 401.906 | P72: 429.49 | Q72: 439.621 | R72: 429.907 | S72: 1700.924 | T72: 412.988 | U72: 415.075 | V72: 408.416 | W72: 373.878 | X72: 1610.357 | CN72: 2027E | CO72: =CP72+$CO$71 -> 350 | CP72: 200 | CQ72: =CP72+$CQ$71 -> 50
B73: Europe Welding — net sales | D73: 474.388 | E73: 538.57 | F73: 346.383 | G73: 359.925 | H73: 508.692 | I73: 452.227 | J73: 110.491 | K73: 108.661 | L73: 98.522 | M73: 111.874 | N73: 429.548 | O73: 105.406 | P73: 115.574 | Q73: 107.507 | R73: 97.288 | S73: 425.775 | T73: 88.416 | U73: 90.903 | V73: 80.596 | W73: 76.909 | X73: 336.824 | CN73: 2028E | CO73: =CP73+$CO$71 -> 350 | CP73: 200 | CQ73: =CP73+$CQ$71 -> 50
B74: Asia Pacific Welding — net sales | D74: 178.12 | E74: 230.661 | F74: 208.28 | G74: 324.092 | H74: 376.276 | I74: 324.482 | J74: 70.039 | K74: 69.239 | L74: 63.834 | M74: 63.17 | N74: 266.282 | O74: 61.286 | P74: 66.997 | Q74: 57.404 | R74: 58.113 | S74: 243.8 | T74: 49.25 | U74: 49.043 | V74: 45.505 | W74: 42.817 | X74: 186.615 | CN74: 2029E | CO74: =CP74+$CO$71 -> 350 | CP74: 200 | CQ74: =CP74+$CQ$71 -> 50
B75: South America Welding (incl. Venezuela to 2015) — net sales | D75: 101.426 | E75: 116.061 | F75: 99.171 | G75: 117.419 | H75: 156.684 | I75: 161.483 | J75: 36.374 | K75: 44.503 | L75: 51.715 | M75: 63.303 | N75: 195.895 | O75: 43.993 | P75: 39.051 | Q75: 32.862 | R75: 32.689 | S75: 148.595 | T75: 37.43 | U75: 37.907 | V75: 47.727 | W75: 14.95 | X75: 138.014 | CN75: 2030E | CO75: =CP75+$CO$71 -> 350 | CP75: 200 | CQ75: =CP75+$CQ$71 -> 50
B76: The Harris Products Group (legacy basis) — net sales | D76: 278.468 | E76: 279.958 | F76: 217.271 | G76: 255.543 | H76: 343.458 | I76: 334.357 | J76: 82.115 | K76: 85.96 | L76: 73.691 | M76: 66.411 | N76: 308.177 | O76: 72.471 | P76: 77.419 | Q76: 78.383 | R76: 65.957 | S76: 294.23 | T76: 69.816 | U76: 71.812 | V76: 62.922 | W76: 59.431 | X76: 263.981
B77: North America Welding — EBIT, as adjusted | F77: 134.544 | G77: 162.192 | H77: 227.924 | I77: 293.07 | J77: 76.66 | K77: 82.777 | L77: 75.225 | M77: 83.845 | N77: 318.507 | O77: 71.364 | P77: 91.195 | Q77: 84.45 | R77: 88.456 | S77: 335.465 | T77: 71.184 | U77: 77.494 | V77: 79.743 | W77: 78.325 | X77: 306.746 | CN77: RISE 2030 targets (company, Q4-25 call / May-26 conference) — memo
B78: Europe Welding — EBIT, as adjusted | F78: -2.196 | G78: 17.023 | H78: 36.171 | I78: 37.299 | J78: 10.701 | K78: 9.532 | L78: 7.881 | M78: 8.133 | N78: 36.247 | O78: 9.292 | P78: 14.899 | Q78: 15.221 | R78: 9.41 | S78: 48.822 | T78: 8.748 | U78: 9.481 | V78: 8.337 | W78: 4.751 | X78: 31.317 | CN78: 2030 net sales > $6bn; revenue CAGR high-single to low-double digit incl. 300–400 bp from acquisitions
B79: Asia Pacific Welding — EBIT, as adjusted | F79: -18.835 | G79: 1.752 | H79: 2.629 | I79: 7.247 | J79: 2.293 | K79: 0.653 | L79: -0.979 | M79: -0.152 | N79: 1.815 | O79: -0.64 | P79: 0.365 | Q79: -0.304 | R79: 1.9 | S79: 1.321 | T79: 3.128 | U79: 2.244 | V79: 2.006 | W79: 0.014 | X79: 7.392 | CN79: Operating margin ~19% average through the cycle, peaks > 20%; incrementals into the high-20s
B80: South America Welding — EBIT, as adjusted | F80: 10.648 | G80: 7.554 | H80: 12.895 | I80: 18.301 | J80: 5.112 | K80: 11.065 | L80: 15.942 | M80: 25.187 | N80: 57.306 | O80: 11.765 | P80: 4.995 | Q80: -0.59 | R80: -0.217 | S80: 15.953 | T80: 3.15 | U80: 1.378 | V80: 1.845 | W80: -0.804 | X80: 5.569 | CN80: EPS CAGR mid-teens %; 100–125 bp of enterprise-driven margin gains over five years
B81: The Harris Products Group (legacy) — EBIT, as adjusted | F81: 1.009 | G81: 12.311 | H81: 25.151 | I81: 29.477 | J81: 7.151 | K81: 7.343 | L81: 6.917 | M81: 6.415 | N81: 27.826 | O81: 6.058 | P81: 7.178 | Q81: 8.947 | R81: 6.38 | S81: 28.563 | T81: 7.549 | U81: 8.25 | V81: 6.422 | W81: 5.661 | X81: 27.882
B82: Corporate / Eliminations (legacy) — EBIT, as adjusted | F82: -3.344 | G82: -6.675 | H82: 0.426 | I82: -4.886 | J82: -0.603 | K82: -1.538 | L82: -0.822 | M82: -1.387 | N82: -4.35 | O82: 2.891 | P82: 0.6 | Q82: -0.324 | R82: 1.049 | S82: 4.216 | T82: 0.199 | U82: 0.475 | V82: -0.646 | W82: -0.127 | X82: -0.099
B84: Future acquisitions (M&A lever — bolt-ons, unallocated; deal-level assumptions in rows below)
B85: Acquisition spend (USDm, scenario) | CB85: =CHOOSE(MATCH($CF$2,{"Bull","Base","Bear"},0),$CO$72,$CP$72,$CQ$72) -> 200 | CC85: =CHOOSE(MATCH($CF$2,{"Bull","Base","Bear"},0),$CO$73,$CP$73,$CQ$73) -> 200 | CD85: =CHOOSE(MATCH($CF$2,{"Bull","Base","Bear"},0),$CO$74,$CP$74,$CQ$74) -> 200 | CE85: =CHOOSE(MATCH($CF$2,{"Bull","Base","Bear"},0),$CO$75,$CP$75,$CQ$75) -> 200 | CF85: Scenario lever (M&A_spend). Cash outflow in CF "Acquisitions"; allocated to PP&E / intangibles / goodwill below.
B86: Purchase multiple — EV / sales (x) | CB86: 1.6 | CC86: 1.6 | CD86: 1.6 | CE86: 1.6 | CF86: LECO bolt-ons (Fori, RedViking, Inrotech, Vanair, Alloy Steel) priced ~1.2–2.0x sales.
B87: Annualised sales acquired in the year | CB87: =IFERROR(CB85/CB86,0) -> 125 | CC87: =IFERROR(CC85/CC86,0) -> 125 | CD87: =IFERROR(CD85/CD86,0) -> 125 | CE87: =IFERROR(CE85/CE86,0) -> 125
B88: Growth of acquired businesses after acquisition % | CB88: 0.04 | CC88: 0.04 | CD88: 0.04 | CE88: 0.04
B89: Run-rate sales of businesses acquired (year end) | CA89: 0 | CB89: =CA89*(1+CB88)+CB87 -> 125 | CC89: =CB89*(1+CC88)+CC87 -> 255 | CD89: =CC89*(1+CD88)+CD87 -> 390.2 | CE89: =CD89*(1+CE88)+CE87 -> 530.808
B90: Net sales from future acquisitions (half-year convention in year of purchase) | CA90: 0 | CB90: =CA89*(1+CB88)+0.5*CB87 -> 62.5 | CC90: =CB89*(1+CC88)+0.5*CC87 -> 192.5 | CD90: =CC89*(1+CD88)+0.5*CD87 -> 327.7 | CE90: =CD89*(1+CE88)+0.5*CE87 -> 468.308
B91: Adjusted EBIT margin of acquired businesses % (after D&A) | CB91: 0.13 | CC91: 0.13 | CD91: 0.13 | CE91: 0.13 | CF91: Automation / cutting bolt-ons below Americas Welding margin initially (purchase-accounting amortization included).
B92: Adjusted EBIT from future acquisitions | CA92: 0 | CB92: =CB90*CB91 -> 8.125 | CC92: =CC90*CC91 -> 25.025 | CD92: =CD90*CD91 -> 42.601 | CE92: =CE90*CE91 -> 60.88004
B93: D&A of acquired businesses % of sales (incl. step-ups) | CB93: 0.05 | CC93: 0.05 | CD93: 0.05 | CE93: 0.05
B94: D&A from future acquisitions | CA94: 0 | CB94: =CB90*CB93 -> 3.125 | CC94: =CC90*CC93 -> 9.625 | CD94: =CD90*CD93 -> 16.385 | CE94: =CE90*CE93 -> 23.4154
B95: PP&E % of spend | CB95: 0.15 | CC95: 0.15 | CD95: 0.15 | CE95: 0.15
B96: Acquired intangibles % of spend | CB96: 0.35 | CC96: 0.35 | CD96: 0.35 | CE96: 0.35
B97: Intangible amortization life (years) | CB97: 12 | CC97: 12 | CD97: 12 | CE97: 12
B98: Cumulative acquired intangibles (gross) | CA98: 0 | CB98: =CA98+CB85*CB96 -> 70 | CC98: =CB98+CC85*CC96 -> 140 | CD98: =CC98+CD85*CD96 -> 210 | CE98: =CD98+CE85*CE96 -> 280
B99: Amortization of future-acquisition intangibles (within D&A) | CA99: 0 | CB99: =(CA98+0.5*CB85*CB96)/CB97 -> 2.9166667 | CC99: =(CB98+0.5*CC85*CC96)/CC97 -> 8.75 | CD99: =(CC98+0.5*CD85*CD96)/CD97 -> 14.583333 | CE99: =(CD98+0.5*CE85*CE96)/CE97 -> 20.416667
B101: Group Total — net sales & Adjusted EBIT (segment build) → ties to consolidated statements
B102: Net sales — segment build ex future M&A | C102: =IF(ISNUMBER(C10),N(C10)+N(C29)+N(C48),IF(ISNUMBER(C72),N(C72)+N(C73)+N(C74)+N(C75)+N(C76),"")) | D102: =IF(ISNUMBER(D10),N(D10)+N(D29)+N(D48),IF(ISNUMBER(D72),N(D72)+N(D73)+N(D74)+N(D75)+N(D76),"")) -> 2280.784 | E102: =IF(ISNUMBER(E10),N(E10)+N(E29)+N(E48),IF(ISNUMBER(E72),N(E72)+N(E73)+N(E74)+N(E75)+N(E76),"")) -> 2479.131 | F102: =IF(ISNUMBER(F10),N(F10)+N(F29)+N(F48),IF(ISNUMBER(F72),N(F72)+N(F73)+N(F74)+N(F75)+N(F76),"")) -> 1729.285 | G102: =IF(ISNUMBER(G10),N(G10)+N(G29)+N(G48),IF(ISNUMBER(G72),N(G72)+N(G73)+N(G74)+N(G75)+N(G76),"")) -> 2070.172 | H102: =IF(ISNUMBER(H10),N(H10)+N(H29)+N(H48),IF(ISNUMBER(H72),N(H72)+N(H73)+N(H74)+N(H75)+N(H76),"")) -> 2694.609 | I102: =IF(ISNUMBER(I10),N(I10)+N(I29)+N(I48),IF(ISNUMBER(I72),N(I72)+N(I73)+N(I74)+N(I75)+N(I76),"")) -> 2853.367 | J102: =IF(ISNUMBER(J10),N(J10)+N(J29)+N(J48),IF(ISNUMBER(J72),N(J72)+N(J73)+N(J74)+N(J75)+N(J76),"")) -> 718.573 | ... CE102: =IF(ISNUMBER(CE10),N(CE10)+N(CE29)+N(CE48),IF(ISNUMBER(CE72),N(CE72)+N(CE73)+N(CE74)+N(CE75)+N(CE76),"")) -> 5707.5166
...

Sheet Bull-Base-Bear
B2: Lincoln Electric (LECO) — Bull / Base / Bear Case P&L Summary | J2: Share price ($): | K2: =Model!$CA$382 -> 275.54
B3: Adjusted figures (company current definitions: Adjusted EBIT, adjusted net income / EPS; Adjusted EBITDA model-derived) · USD millions · Live panel linked to Model — toggle scenario via Model!CF2. Bull and Bear panels are value snapshots generated from the Model with the switch set to each case. 2026E = 1H/26 actual + 2H/26E calibrated to the FY26 outlook range end-points. | J3: As of: | K3: =TODAY() -> 46302
B5: Scenario: | C5: =Model!$CF$2 -> Base | N5: Scenario: | O5: Bull | P5: Snapshot (values) — Model run with switch = Bull | Z5: Scenario: | AA5: Bear | AB5: Snapshot (values) — Model run with switch = Bear
B7: (USDm, except EPS and shares) | C7: 2025A | D7: 2026E | E7: 2027E | F7: 2028E | G7: 2029E | H7: 2030E | I7: 25-'30 CAGR | J7: LT Hist Avg | K7: LT Hist Min | L7: LT Hist Max | N7: (USDm, except EPS and shares) | O7: 2025A | P7: 2026E | Q7: 2027E | R7: 2028E | S7: 2029E | T7: 2030E | U7: 25-'30 CAGR | V7: LT Hist Avg | W7: LT Hist Min | X7: LT Hist Max | Z7: (USDm, except EPS and shares) | AA7: 2025A | AB7: 2026E | AC7: 2027E | AD7: 2028E | AE7: 2029E | AF7: 2030E | AG7: 25-'30 CAGR | AH7: LT Hist Avg | AI7: LT Hist Min | AJ7: LT Hist Max
B9: Net sales | C9: =Model!BV133 -> 4233.003 | D9: =Model!CA133 -> 4719.7983 | E9: =Model!CB133 -> 5019.0981 | F9: =Model!CC133 -> 5398.1929 | G9: =Model!CD133 -> 5778.445 | H9: =Model!CE133 -> 6175.8246 | I9: =IFERROR((H9/C9)^(1/5)-1,"n/m") -> 0.078472998 | N9: Net sales | O9: 4233.003 | P9: 4783.2934 | Q9: 5276.1656 | R9: 5918.2946 | S9: 6585.0381 | T9: 7294.5929 | U9: 0.11498878 | Z9: Net sales | AA9: 4233.003 | AB9: 4656.3033 | AC9: 4765.8402 | AD9: 4894.588 | AE9: 5011.1703 | AF9: 5130.6896 | AG9: 0.039215061
B10: Net sales y/y % | D10: =IFERROR(D9/C9-1,"") -> 0.115 | E10: =IFERROR(E9/D9-1,"") -> 0.063413666 | F10: =IFERROR(F9/E9-1,"") -> 0.075530466 | G10: =IFERROR(G9/F9-1,"") -> 0.070440637 | H10: =IFERROR(H9/G9-1,"") -> 0.068769299 | N10: Net sales y/y % | P10: 0.13 | Q10: 0.10304035 | R10: 0.12170372 | S10: 0.11265803 | T10: 0.10775258 | Z10: Net sales y/y % | AB10: 0.1 | AC10: 0.023524433 | AD10: 0.027014714 | AE10: 0.023818618 | AF10: 0.023850563
B11: Organic growth % (volume + price) | C11: =Model!BV113 -> 0.024661 | D11: =Model!CA113 -> 0.096797252 | E11: =Model!CB113 -> 0.050171575 | F11: =Model!CC113 -> 0.050255198 | G11: =Model!CD113 -> 0.047073877 | H11: =Model!CE113 -> 0.047107618 | J11: =IFERROR(AVERAGE(Model!C113,Model!D113,Model!E113,Model!F113,Model!G113,Model!H113,Model!I113,Model!N113,Model!S113,Model!X113,Model!AC113,Model!AH113,Model!AM113,Model!AR113,Model!AW113,Model!BB113,Model!BG113,Model!BL113,Model!BQ113,Model!BV113),"n/a") -> 0.043153188 | K11: =IFERROR(MIN(Model!C113,Model!D113,Model!E113,Model!F113,Model!G113,Model!H113,Model!I113,Model!N113,Model!S113,Model!X113,Model!AC113,Model!AH113,Model!AM113,Model!AR113,Model!AW113,Model!BB113,Model!BG113,Model!BL113,Model!BQ113,Model!BV113),"n/a") -> -0.122112 | L11: =IFERROR(MAX(Model!C113,Model!D113,Model!E113,Model!F113,Model!G113,Model!H113,Model!I113,Model!N113,Model!S113,Model!X113,Model!AC113,Model!AH113,Model!AM113,Model!AR113,Model!AW113,Model!BB113,Model!BG113,Model!BL113,Model!BQ113,Model!BV113),"n/a") -> 0.216856 | N11: Organic growth % (volume + price) | O11: 0.024661 | P11: 0.11179725 | Q11: 0.080174308 | R11: 0.08024885 | S11: 0.07706703 | T11: 0.07709989 | V11: 0.043153188 | W11: -0.122112 | X11: 0.216856 | Z11: Organic growth % (volume + price) | AA11: 0.024661 | AB11: 0.081797252 | AC11: 0.020168767 | AD11: 0.020261779 | AE11: 0.017080977 | AF11: 0.01711565 | AH11: 0.043153188 | AI11: -0.122112 | AJ11: 0.216856
B12: Adjusted EBIT (company definition) | C12: =Model!BV178 -> 752.632 | D12: =Model!CA178 -> 851.95165 | E12: =Model!CB178 -> 918.22028 | F12: =Model!CC178 -> 997.40069 | G12: =Model!CD178 -> 1074.135 | H12: =Model!CE178 -> 1142.0516 | I12: =IFERROR((H12/C12)^(1/5)-1,"n/m") -> 0.086977633 | N12: Adjusted EBIT (company definition) | O12: 752.632 | P12: 878.64569 | Q12: 1040.246 | R12: 1169.8671 | S12: 1302.1525 | T12: 1429.943 | U12: 0.1369653 | Z12: Adjusted EBIT (company definition) | AA12: 752.632 | AB12: 828.58457 | AC12: 803.13472 | AD12: 839.01994 | AE12: 869.75815 | AF12: 889.97456 | AG12: 0.034091534
B13: Adjusted EBIT margin % | C13: =IFERROR(C12/C9,"") -> 0.17780096 | D13: =IFERROR(D12/D9,"") -> 0.18050594 | E13: =IFERROR(E12/E9,"") -> 0.18294528 | F13: =IFERROR(F12/F9,"") -> 0.18476566 | G13: =IFERROR(G12/G9,"") -> 0.18588651 | H13: =IFERROR(H12/H9,"") -> 0.18492293 | J13: =IFERROR(AVERAGE(Model!C179,Model!D179,Model!E179,Model!F179,Model!G179,Model!H179,Model!I179,Model!N179,Model!S179,Model!X179,Model!AC179,Model!AH179,Model!AM179,Model!AR179,Model!AW179,Model!BB179,Model!BG179,Model!BL179,Model!BQ179,Model!BV179),"n/a") -> 0.1391968 | K13: =IFERROR(MIN(Model!C179,Model!D179,Model!E179,Model!F179,Model!G179,Model!H179,Model!I179,Model!N179,Model!S179,Model!X179,Model!AC179,Model!AH179,Model!AM179,Model!AR179,Model!AW179,Model!BB179,Model!BG179,Model!BL179,Model!BQ179,Model!BV179),"n/a") -> 0.070647695 | L13: =IFERROR(MAX(Model!C179,Model!D179,Model!E179,Model!F179,Model!G179,Model!H179,Model!I179,Model!N179,Model!S179,Model!X179,Model!AC179,Model!AH179,Model!AM179,Model!AR179,Model!AW179,Model!BB179,Model!BG179,Model!BL179,Model!BQ179,Model!BV179),"n/a") -> 0.1780154 | N13: Adjusted EBIT margin % | O13: 0.17780096 | P13: 0.18369053 | Q13: 0.19715946 | R13: 0.19766963 | S13: 0.19774412 | T13: 0.1960278 | V13: 0.1391968 | W13: 0.070647695 | X13: 0.1780154 | Z13: Adjusted EBIT margin % | AA13: 0.17780096 | AB13: 0.17794901 | AC13: 0.16851902 | AD13: 0.17141789 | AE13: 0.17356388 | AF13: 0.173461 | AH13: 0.1391968 | AI13: 0.070647695 | AJ13: 0.1780154
B15: Operating income (GAAP) | C15: =Model!BV140 -> 718.059 | D15: =Model!CA140 -> 838.98165 | E15: =Model!CB140 -> 901.22028 | F15: =Model!CC140 -> 980.40069 | G15: =Model!CD140 -> 1057.135 | H15: =Model!CE140 -> 1125.0516 | I15: =IFERROR((H15/C15)^(1/5)-1,"n/m") -> 0.093962564 | N15: Operating income (GAAP) | O15: 718.059 | P15: 865.67569 | Q15: 1023.246 | R15: 1152.8671 | S15: 1285.1525 | T15: 1412.943 | U15: 0.14496682 | Z15: Operating income (GAAP) | AA15: 718.059 | AB15: 815.61457 | AC15: 786.13472 | AD15: 822.01994 | AE15: 852.75815 | AF15: 872.97456 | AG15: 0.039844243
B16: Operating income y/y % | D16: =IFERROR(D15/C15-1,"") -> 0.16840211 | E16: =IFERROR(E15/D15-1,"") -> 0.074183546 | F16: =IFERROR(F15/E15-1,"") -> 0.087859101 | G16: =IFERROR(G15/F15-1,"") -> 0.078268325 | H16: =IFERROR(H15/G15-1,"") -> 0.064245878 | N16: Operating income y/y % | P16: 0.20557738 | Q16: 0.18202002 | R16: 0.12667642 | S16: 0.11474471 | T16: 0.099436029 | Z16: Operating income y/y % | AB16: 0.13586011 | AC16: -0.036144345 | AD16: 0.045647671 | AE16: 0.03739351 | AF16: 0.023707085
B17: Operating margin (GAAP) % | C17: =IFERROR(C15/C9,"") -> 0.16963347 | D17: =IFERROR(D15/D9,"") -> 0.17775794 | E17: =IFERROR(E15/E9,"") -> 0.17955821 | F17: =IFERROR(F15/F9,"") -> 0.18161646 | G17: =IFERROR(G15/G9,"") -> 0.18294455 | H17: =IFERROR(H15/H9,"") -> 0.18217026 | J17: =IFERROR(AVERAGE(Model!C224,Model!D224,Model!E224,Model!F224,Model!G224,Model!H224,Model!I224,Model!N224,Model!S224,Model!X224,Model!AC224,Model!AH224,Model!AM224,Model!AR224,Model!AW224,Model!BB224,Model!BG224,Model!BL224,Model!BQ224,Model!BV224),"n/a") -> 0.12583033 | K17: =IFERROR(MIN(Model!C224,Model!D224,Model!E224,Model!F224,Model!G224,Model!H224,Model!I224,Model!N224,Model!S224,Model!X224,Model!AC224,Model!AH224,Model!AM224,Model!AR224,Model!AW224,Model!BB224,Model!BG224,Model!BL224,Model!BQ224,Model!BV224),"n/a") -> 0.053765574 | L17: =IFERROR(MAX(Model!C224,Model!D224,Model!E224,Model!F224,Model!G224,Model!H224,Model!I224,Model!N224,Model!S224,Model!X224,Model!AC224,Model!AH224,Model!AM224,Model!AR224,Model!AW224,Model!BB224,Model!BG224,Model!BL224,Model!BQ224,Model!BV224),"n/a") -> 0.17125748 | N17: Operating margin (GAAP) % | O17: 0.16963347 | P17: 0.18097901 | Q17: 0.19393743 | R17: 0.19479718 | S17: 0.19516251 | T17: 0.19369731 | V17: 0.12583033 | W17: 0.053765574 | X17: 0.17125748 | Z17: Operating margin (GAAP) % | AA17: 0.16963347 | AB17: 0.17516354 | AC17: 0.16495197 | AD17: 0.16794466 | AE17: 0.17017146 | AF17: 0.17014761 | AH17: 0.12583033 | AI17: 0.053765574 | AJ17: 0.17125748
B19: Adjusted net income (attributable to Lincoln Electric) | C19: =Model!BV202 -> 551.331 | D19: =Model!CA202 -> 618.90333 | E19: =Model!CB202 -> 671.31629 | F19: =Model!CC202 -> 728.02672 | G19: =Model!CD202 -> 783.47776 | H19: =Model!CE202 -> 832.22228 | I19: =IFERROR((H19/C19)^(1/5)-1,"n/m") -> 0.085838872 | N19: Adjusted net income (attributable to Lincoln Electric) | O19: 551.331 | P19: 639.59121 | Q19: 763.47965 | R19: 844.57701 | S19: 938.94057 | T19: 1029.6657 | U19: 0.13307006 | Z19: Adjusted net income (attributable to Lincoln Electric) | AA19: 551.331 | AB19: 600.79384 | AC19: 584.15758 | AD19: 615.47462 | AE19: 638.55873 | AF19: 653.61848 | AG19: 0.034623602
B21: FDSO (m) | C21: =Model!BV157 -> 55.875 | D21: =Model!CA157 -> 55.019654 | E21: =Model!CB157 -> 53.999769 | F21: =Model!CC157 -> 52.983105 | G21: =Model!CD157 -> 51.942963 | H21: =Model!CE157 -> 50.871901 | I21: =IFERROR((H21/C21)^(1/5)-1,"n/m") -> -0.018586367 | N21: FDSO (m) | O21: 55.875 | P21: 54.974288 | Q21: 53.321162 | R21: 51.749417 | S21: 50.527746 | T21: 49.152485 | U21: -0.02531207 | Z21: FDSO (m) | AA21: 55.875 | AB21: 55.065019 | AC21: 54.547289 | AD21: 53.892911 | AE21: 52.900409 | AF21: 51.97857 | AG21: -0.014353105
B23: Adjusted EPS — Diluted ($) | C23: =Model!BV206 -> 9.8672215 | D23: =Model!CA206 -> 11.248768 | E23: =Model!CB206 -> 12.431836 | F23: =Model!CC206 -> 13.740733 | G23: =Model!CD206 -> 15.083424 | H23: =Model!CE206 -> 16.359174 | I23: =IFERROR((H23/C23)^(1/5)-1,"n/m") -> 0.10640288 | N23: Adjusted EPS — Diluted ($) | O23: 9.8672215 | P23: 11.63437 | Q23: 14.318511 | R23: 16.320513 | S23: 18.582673 | T23: 20.948395 | U23: 0.16249522 | Z23: Adjusted EPS — Diluted ($) | AA23: 9.8672215 | AB23: 10.910626 | AC23: 10.709195 | AD23: 11.420326 | AE23: 12.07096 | AF23: 12.574768 | AG23: 0.049689911
B24: EPS y/y % | D24: =IFERROR(D23/C23-1,"") -> 0.14001375 | E24: =IFERROR(E23/D23-1,"") -> 0.10517313 | F24: =IFERROR(F23/E23-1,"") -> 0.1052859 | G24: =IFERROR(G23/F23-1,"") -> 0.097716116 | H24: =IFERROR(H23/G23-1,"") -> 0.084579558 | N24: EPS y/y % | P24: 0.17909282 | Q24: 0.23070792 | R24: 0.1398191 | S24: 0.13860841 | T24: 0.12730797 | Z24: EPS y/y % | AB24: 0.10574454 | AC24: -0.018461908 | AD24: 0.066403751 | AE24: 0.056971592 | AF24: 0.041737201
B26: P / E (x) — assumed (adjusted EPS) | G26: 22 | H26: 22 | N26: P / E (x) — assumed (adjusted EPS) | S26: 22 | T26: 22 | Z26: P / E (x) — assumed (adjusted EPS) | AE26: 22 | AF26: 22
B27: Price Target ($) | G27: =G26*G23 -> 331.83534 | H27: =H26*H23 -> 359.90182 | N27: Price Target ($) | S27: 408.8188 | T27: 460.86469 | Z27: Price Target ($) | AE27: 265.56112 | AF27: 276.6449
B28: Upside / (Downside) vs current | G28: =IFERROR(G27/$K$2-1,"") -> 0.20430913 | H28: =IFERROR(H27/$K$2-1,"") -> 0.30616907 | N28: Upside / (Downside) vs current | S28: 0.48370038 | T28: 0.67258726 | Z28: Upside / (Downside) vs current | AE28: -0.036215706 | AF28: 0.0040099534
B29: IRR (to Dec-Y-1) | G29: =IFERROR((G27/$K$2)^(1/((DATE(2029-1,12,31)-$K$3)/365.25))-1,"") -> 0.086773777 | H29: =IFERROR((H27/$K$2)^(1/((DATE(2030-1,12,31)-$K$3)/365.25))-1,"") -> 0.086113825 | N29: IRR (to Dec-Y-1) | S29: 0.19315352 | T29: 0.17243251 | Z29: IRR (to Dec-Y-1) | AE29: -0.016375781 | AF29: 0.0012384519
B31: Free Cash Flow | C31: =Model!BV258 -> 534.199 | D31: =Model!CA258 -> 502.70628 | E31: =Model!CB258 -> 634.35813 | F31: =Model!CC258 -> 683.90773 | G31: =Model!CD258 -> 746.80176 | H31: =Model!CE258 -> 799.76997 | I31: =IFERROR((H31/C31)^(1/5)-1,"n/m") -> 0.084057714 | N31: Free Cash Flow | O31: 534.199 | P31: 505.90227 | Q31: 704.2469 | R31: 766.66549 | S31: 870.66708 | T31: 967.60723 | U31: 0.12615769 | Z31: Free Cash Flow | AA31: 534.199 | AB31: 502.42593 | AC31: 569.16104 | AD31: 603.62197 | AE31: 630.42953 | AF31: 646.00641 | AG31: 0.03873975
B32: FCF % | C32: =IFERROR(C31/C9,"") -> 0.12619859 | D32: =IFERROR(D31/D9,"") -> 0.10651012 | E32: =IFERROR(E31/E9,"") -> 0.12638887 | F32: =IFERROR(F31/F9,"") -> 0.12669198 | G32: =IFERROR(G31/G9,"") -> 0.12923923 | H32: =IFERROR(H31/H9,"") -> 0.12950011 | J32: =IFERROR(AVERAGE(Model!C260,Model!D260,Model!E260,Model!F260,Model!G260,Model!H260,Model!I260,Model!N260,Model!S260,Model!X260,Model!AC260,Model!AH260,Model!AM260,Model!AR260,Model!AW260,Model!BB260,Model!BG260,Model!BL260,Model!BQ260,Model!BV260),"n/a") -> 0.094282002 | K32: =IFERROR(MIN(Model!C260,Model!D260,Model!E260,Model!F260,Model!G260,Model!H260,Model!I260,Model!N260,Model!S260,Model!X260,Model!AC260,Model!AH260,Model!AM260,Model!AR260,Model!AW260,Model!BB260,Model!BG260,Model!BL260,Model!BQ260,Model!BV260),"n/a") -> 0.021642921 | L32: =IFERROR(MAX(Model!C260,Model!D260,Model!E260,Model!F260,Model!G260,Model!H260,Model!I260,Model!N260,Model!S260,Model!X260,Model!AC260,Model!AH260,Model!AM260,Model!AR260,Model!AW260,Model!BB260,Model!BG260,Model!BL260,Model!BQ260,Model!BV260),"n/a") -> 0.13754892 | N32: FCF % | O32: 0.12619859 | P32: 0.10576442 | Q32: 0.13347703 | R32: 0.12954162 | S32: 0.13221899 | T32: 0.13264719 | V32: 0.094282002 | W32: 0.021642921 | X32: 0.13754892 | Z32: FCF % | AA32: 0.12619859 | AB32: 0.10790232 | AC32: 0.11942512 | AD32: 0.12332437 | AE32: 0.12580485 | AF32: 0.12591025 | AH32: 0.094282002 | AI32: 0.021642921 | AJ32: 0.13754892
B33: FCF / share ($) | C33: =IFERROR(C31/C21,"") -> 9.5606085 | D33: =IFERROR(D31/D21,"") -> 9.1368492 | E33: =IFERROR(E31/E21,"") -> 11.747423 | F33: =IFERROR(F31/F21,"") -> 12.908034 | G33: =IFERROR(G31/G21,"") -> 14.377342 | H33: =IFERROR(H31/H21,"") -> 15.721252 | N33: FCF / share ($) | O33: 9.5606085 | P33: 9.2025252 | Q33: 13.207644 | R33: 14.814959 | S33: 17.231465 | T33: 19.685825 | Z33: FCF / share ($) | AA33: 9.5606085 | AB33: 9.1242306 | AC33: 10.434268 | AD33: 11.200396 | AE33: 11.91729 | AF33: 12.428322
B34: FCF Yield (on PT) | G34: =IFERROR(G33/G$27,"") -> 0.043326737 | H34: =IFERROR(H33/H$27,"") -> 0.043682056 | N34: FCF Yield (on PT) | S34: 0.042149394 | T34: 0.042714978 | Z34: FCF Yield (on PT) | AE34: 0.044875884 | AF34: 0.04492518
B35: Adjusted EBITDA (model-derived = Adjusted EBIT + D&A) | C35: =Model!BV184 -> 851.178 | D35: =Model!CA184 -> 954.57683 | E35: =Model!CB184 -> 1036.7845 | F35: =Model!CC184 -> 1131.1841 | G35: =Model!CD184 -> 1223.4242 | H35: =Model!CE184 -> 1307.5109 | I35: =IFERROR((H35/C35)^(1/5)-1,"n/m") -> 0.089644894 | N35: Adjusted EBITDA (model-derived = Adjusted EBIT + D&A) | O35: 851.178 | P35: 982.6228 | Q35: 1167.0665 | R35: 1322.8317 | S35: 1482.2822 | T35: 1638.6956 | U35: 0.13997566 | Z35: Adjusted EBITDA (model-derived = Adjusted EBIT + D&A) | AA35: 851.178 | AB35: 929.85782 | AC35: 913.53029 | AD35: 954.00171 | AE35: 989.11132 | AF35: 1013.8343 | AG35: 0.035593499
B36: Adjusted EBITDA % of net sales | C36: =IFERROR(C35/C9,"") -> 0.20108136 | D36: =IFERROR(D35/D9,"") -> 0.2022495 | E36: =IFERROR(E35/E9,"") -> 0.2065679 | F36: =IFERROR(F35/F9,"") -> 0.20954867 | G36: =IFERROR(G35/G9,"") -> 0.21172205 | H36: =IFERROR(H35/H9,"") -> 0.21171439 | J36: =IFERROR(AVERAGE(Model!C185,Model!D185,Model!E185,Model!F185,Model!G185,Model!H185,Model!I185,Model!N185,Model!S185,Model!X185,Model!AC185,Model!AH185,Model!AM185,Model!AR185,Model!AW185,Model!BB185,Model!BG185,Model!BL185,Model!BQ185,Model!BV185),"n/a") -> 0.1641208 | K36: =IFERROR(MIN(Model!C185,Model!D185,Model!E185,Model!F185,Model!G185,Model!H185,Model!I185,Model!N185,Model!S185,Model!X185,Model!AC185,Model!AH185,Model!AM185,Model!AR185,Model!AW185,Model!BB185,Model!BG185,Model!BL185,Model!BQ185,Model!BV185),"n/a") -> 0.10337683 | L36: =IFERROR(MAX(Model!C185,Model!D185,Model!E185,Model!F185,Model!G185,Model!H185,Model!I185,Model!N185,Model!S185,Model!X185,Model!AC185,Model!AH185,Model!AM185,Model!AR185,Model!AW185,Model!BB185,Model!BG185,Model!BL185,Model!BQ185,Model!BV185),"n/a") -> 0.20108136 | N36: Adjusted EBITDA % of net sales | O36: 0.20108136 | P36: 0.20542809 | Q36: 0.22119597 | R36: 0.22351568 | S36: 0.22509849 | T36: 0.22464524 | V36: 0.1641208 | W36: 0.10337683 | X36: 0.20108136 | Z36: Adjusted EBITDA % of net sales | AA36: 0.20108136 | AB36: 0.19969872 | AC36: 0.19168295 | AD36: 0.1949095 | AE36: 0.1973813 | AF36: 0.19760195 | AH36: 0.1641208 | AI36: 0.10337683 | AJ36: 0.20108136
B38: Net Debt | C38: =Model!BV377 -> 985.219 | D38: =Model!CA377 -> 926.17462 | E38: =Model!CB377 -> 1036.7845 | F38: =Model!CC377 -> 1131.1841 | G38: =Model!CD377 -> 1223.4242 | H38: =Model!CE377 -> 1307.5109 | N38: Net Debt | O38: 985.219 | P38: 972.83527 | Q38: 1458.8332 | R38: 1653.5396 | S38: 1852.8527 | T38: 2048.3695 | Z38: Net Debt | AA38: 985.219 | AB38: 876.59832 | AC38: 685.14772 | AD38: 715.50128 | AE38: 741.83349 | AF38: 760.3757
B39: Net Debt / Adjusted EBITDA (x) | C39: =IFERROR(C38/C35,"") -> 1.157477 | D39: =IFERROR(D38/D35,"") -> 0.97024628 | E39: =IFERROR(E38/E35,"") -> 1 | F39: =IFERROR(F38/F35,"") -> 1 | G39: =IFERROR(G38/G35,"") -> 1 | H39: =IFERROR(H38/H35,"") -> 1 | N39: Net Debt / Adjusted EBITDA (x) | O39: 1.157477 | P39: 0.99003938 | Q39: 1.25 | R39: 1.25 | S39: 1.25 | T39: 1.25 | Z39: Net Debt / Adjusted EBITDA (x) | AA39: 1.157477 | AB39: 0.94272296 | AC39: 0.75 | AD39: 0.75 | AE39: 0.75 | AF39: 0.75
B40: Share repurchases ($m) | D40: =Model!CA269 -> 150 | E40: =Model!CB269 -> 378.88408 | F40: =Model!CC269 -> 404.99127 | G40: =Model!CD269 -> 458.22859 | H40: =Model!CE269 -> 495.5639 | N40: Share repurchases ($m) | P40: 200 | Q40: 674.76867 | R40: 442.23043 | S40: 544.02808 | T40: 630.97022 | Z40: Share repurchases ($m) | AB40: 100 | AC40: 161.01865 | AD40: 407.41576 | AE40: 422.53848 | AF40: 422.23109
B41: Implied avg buyback price ($) | D41: =Model!CA268 -> 275.54 | E41: =Model!CB268 -> 297.5832 | F41: =Model!CC268 -> 321.38986 | G41: =Model!CD268 -> 347.10104 | H41: =Model!CE268 -> 374.86913 | N41: Implied avg buyback price ($) | P41: 275.54 | Q41: 297.5832 | R41: 321.38986 | S41: 347.10104 | T41: 374.86913 | Z41: Implied avg buyback price ($) | AB41: 275.54 | AC41: 297.5832 | AD41: 321.38986 | AE41: 347.10104 | AF41: 374.86913
B42: Shares repurchased (m) | D42: =Model!CA270 -> 0.54438557 | E42: =Model!CB270 -> 1.2732039 | F42: =Model!CC270 -> 1.2601246 | G42: =Model!CD270 -> 1.3201591 | H42: =Model!CE270 -> 1.3219651 | N42: Shares repurchased (m) | P42: 0.72584743 | Q42: 2.2674959 | R42: 1.3759937 | S42: 1.5673479 | T42: 1.6831747 | Z42: Shares repurchased (m) | AB42: 0.36292371 | AC42: 0.54108783 | AD42: 1.2676684 | AE42: 1.2173357 | AF42: 1.1263427
B44: ROIC | C44: =Model!BV360 -> 0.2362566 | D44: =Model!CA360 -> 0.25778089 | E44: =Model!CB360 -> 0.2514502 | F44: =Model!CC360 -> 0.24986307 | G44: =Model!CD360 -> 0.24837312 | H44: =Model!CE360 -> 0.24535598 | J44: =IFERROR(AVERAGE(Model!C360,Model!D360,Model!E360,Model!F360,Model!G360,Model!H360,Model!I360,Model!N360,Model!S360,Model!X360,Model!AC360,Model!AH360,Model!AM360,Model!AR360,Model!AW360,Model!BB360,Model!BG360,Model!BL360,Model!BQ360,Model!BV360),"n/a") -> 0.23179901 | K44: =IFERROR(MIN(Model!C360,Model!D360,Model!E360,Model!F360,Model!G360,Model!H360,Model!I360,Model!N360,Model!S360,Model!X360,Model!AC360,Model!AH360,Model!AM360,Model!AR360,Model!AW360,Model!BB360,Model!BG360,Model!BL360,Model!BQ360,Model!BV360),"n/a") -> 0.083557813 | L44: =IFERROR(MAX(Model!C360,Model!D360,Model!E360,Model!F360,Model!G360,Model!H360,Model!I360,Model!N360,Model!S360,Model!X360,Model!AC360,Model!AH360,Model!AM360,Model!AR360,Model!AW360,Model!BB360,Model!BG360,Model!BL360,Model!BQ360,Model!BV360),"n/a") -> 0.29017761 | N44: ROIC | O44: 0.2362566 | P44: 0.26406088 | Q44: 0.26674222 | R44: 0.26101585 | S44: 0.25754856 | T44: 0.25414622 | V44: 0.23179901 | W44: 0.083557813 | X44: 0.29017761 | Z44: ROIC | AA44: 0.2362566 | AB44: 0.25246252 | AC44: 0.23596817 | AD44: 0.23946796 | AE44: 0.24161855 | AF44: 0.24080356 | AH44: 0.23179901 | AI44: 0.083557813 | AJ44: 0.29017761
B45: RONTA | C45: =Model!BV371 -> 0.31737086 | D45: =Model!CA371 -> 0.30543268 | E45: =Model!CB371 -> 0.3109893 | F45: =Model!CC371 -> 0.31971892 | G45: =Model!CD371 -> 0.32677931 | H45: =Model!CE371 -> 0.33015636 | J45: =IFERROR(AVERAGE(Model!C371,Model!D371,Model!E371,Model!F371,Model!G371,Model!H371,Model!I371,Model!N371,Model!S371,Model!X371,Model!AC371,Model!AH371,Model!AM371,Model!AR371,Model!AW371,Model!BB371,Model!BG371,Model!BL371,Model!BQ371,Model!BV371),"n/a") -> 0.21940908 | K45: =IFERROR(MIN(Model!C371,Model!D371,Model!E371,Model!F371,Model!G371,Model!H371,Model!I371,Model!N371,Model!S371,Model!X371,Model!AC371,Model!AH371,Model!AM371,Model!AR371,Model!AW371,Model!BB371,Model!BG371,Model!BL371,Model!BQ371,Model!BV371),"n/a") -> 0.051913482 | L45: =IFERROR(MAX(Model!C371,Model!D371,Model!E371,Model!F371,Model!G371,Model!H371,Model!I371,Model!N371,Model!S371,Model!X371,Model!AC371,Model!AH371,Model!AM371,Model!AR371,Model!AW371,Model!BB371,Model!BG371,Model!BL371,Model!BQ371,Model!BV371),"n/a") -> 0.33289966 | N45: RONTA | O45: 0.31737086 | P45: 0.31248139 | Q45: 0.34241662 | R45: 0.35558269 | S45: 0.36710171 | T45: 0.37491692 | V45: 0.21940908 | W45: 0.051913482 | X45: 0.33289966 | Z45: RONTA | AA45: 0.31737086 | AB45: 0.29627521 | AC45: 0.25526365 | AD45: 0.26293359 | AE45: 0.26854879 | AF45: 0.2698047 | AH45: 0.21940908 | AI45: 0.051913482 | AJ45: 0.33289966
B47: Implied Market Cap (USDm) | G47: =G27*G21 -> 17236.511 | H47: =H27*H21 -> 18308.89 | N47: Implied Market Cap (USDm) | S47: 20656.693 | T47: 22652.645 | Z47: Implied Market Cap (USDm) | AE47: 14048.292 | AF47: 14379.606
B48: (+) Net Debt & NCI | G48: =G38+Model!CD306 -> 1223.4242 | H48: =H38+Model!CE306 -> 1307.5109 | N48: (+) Net Debt & NCI | S48: 1852.8527 | T48: 2048.3695 | Z48: (+) Net Debt & NCI | AE48: 741.83349 | AF48: 760.3757
B49: Implied Enterprise Value (USDm) | G49: =G47+G48 -> 18459.935 | H49: =H47+H48 -> 19616.401 | N49: Implied Enterprise Value (USDm) | S49: 22509.545 | T49: 24701.014 | Z49: Implied Enterprise Value (USDm) | AE49: 14790.126 | AF49: 15139.982
B50: Implied EV / Adjusted EBITDA (x) | G50: =IFERROR(G49/G35,"") -> 15.088744 | H50: =IFERROR(H49/H35,"") -> 15.002858 | N50: Implied EV / Adjusted EBITDA (x) | S50: 15.185736 | T50: 15.073583 | Z50: Implied EV / Adjusted EBITDA (x) | AE50: 14.952944 | AF50: 14.93339

Sheet DCF
B2: DCF VALUATION — LINCOLN ELECTRIC HOLDINGS (LECO)
B4: 1. WACC BUILD
B5: Risk-free rate (US 10Y govt) | C5: 0.055 | D5: Assumption kept consistent with prior coverage models (MLM, Oct-2026); update to market
B6: Equity risk premium | C6: 0.05 | D6: US implied ERP ~4.5–5.5% (Damodaran); consistent with prior models
B7: Levered beta | C7: 1.1 | D7: Welding / industrial-machinery peers (ESAB, ITW, Kennametal, Timken) ~1.0–1.3; consumables (~2/3 of sales) and Harris HVAC/R dampen cyclicality
B8: Cost of equity | C8: =C5+C7*C6 -> 0.11
B9: Pre-tax cost of debt | C9: 0.0575 | D9: Senior unsecured private-placement notes; 2024 series priced 5.55–5.74%; marginal cost ~5.75%
B10: Tax rate | C10: 0.23 | D10: Model 2027E+ effective tax rate
B11: After-tax cost of debt | C11: =C9*(1-C10) -> 0.044275
B12: Target D/V | C12: 0.1 | D12: Total debt ~$1.2bn vs ~$15bn market cap ($275.54 × ~55m shares); net leverage ~1.0x Adjusted EBITDA
B13: WACC | C13: =C8*(1-C12)+C11*C12 -> 0.1034275
B15: Valuation date (live) | C15: =TODAY() -> 46302 | D15: Periods = (Dec-31-Year − today) / 365.25; cash flows assumed at year-end
B16: 2. UNLEVERED FREE CASH FLOW BUILD (USDm)
D17: 2026E | E17: 2027E | F17: 2028E | G17: 2029E | H17: 2030E | I17: 2031E | J17: 2032E | K17: 2033E | L17: 2034E | M17: 2035E | N17: Terminal | P17: CAGR 26–30E | Q17: CAGR 26–35E
B18: Adj. EBIT less rationalization & acquisition costs (cash special items) | D18: =Model!CA178-Model!CA171-Model!CA172 -> 839.63965 | E18: =Model!CB178-Model!CB171-Model!CB172 -> 906.22028 | F18: =Model!CC178-Model!CC171-Model!CC172 -> 985.40069 | G18: =Model!CD178-Model!CD171-Model!CD172 -> 1062.135 | H18: =Model!CE178-Model!CE171-Model!CE172 -> 1130.0516 | I18: =H18*(1+I$26) -> 1197.8547 | J18: =I18*(1+J$26) -> 1263.7367 | K18: =J18*(1+K$26) -> 1326.9235 | L18: =K18*(1+L$26) -> 1386.6351 | M18: =L18*(1+M$26) -> 1442.1005 | P18: =(H18/D18)^(1/(COLUMNS(D18:H18)-1))-1 -> 0.077088357 | Q18: =(M18/D18)^(1/(COLUMNS(D18:M18)-1))-1 -> 0.061940751
B19: × (1 − tax rate) | D19: =1-$C$10 -> 0.77 | E19: =1-$C$10 -> 0.77 | F19: =1-$C$10 -> 0.77 | G19: =1-$C$10 -> 0.77 | H19: =1-$C$10 -> 0.77 | I19: =1-$C$10 -> 0.77 | J19: =1-$C$10 -> 0.77 | K19: =1-$C$10 -> 0.77 | ... M19: =1-$C$10 -> 0.77
B20: NOPAT | D20: =D18*D19 -> 646.52253 | E20: =E18*E19 -> 697.78962 | F20: =F18*F19 -> 758.75853 | G20: =G18*G19 -> 817.84396 | H20: =H18*H19 -> 870.13971 | I20: =I18*I19 -> 922.34809 | J20: =J18*J19 -> 973.07724 | K20: =K18*K19 -> 1021.7311 | ... M20: =M18*M19 -> 1110.4174
B21: plus D&A | D21: =Model!CA152 -> 102.62518 | E21: =Model!CB152 -> 118.56426 | F21: =Model!CC152 -> 133.78344 | G21: =Model!CD152 -> 149.28924 | H21: =Model!CE152 -> 165.45937 | I21: =H21*(1+I$26) -> 175.38693 | J21: =I21*(1+J$26) -> 185.03321 | K21: =J21*(1+K$26) -> 194.28487 | L21: =K21*(1+L$26) -> 203.02769 | M21: =L21*(1+M$26) -> 211.1488
B22: − Capex (PP&E) and acquisitions (bolt-on M&A) | D22: =Model!CA239+Model!CA240 -> -119.86 | E22: =Model!CB239+Model!CB240 -> -325.47745 | F22: =Model!CC239+Model!CC240 -> -334.95482 | G22: =Model!CD239+Model!CD240 -> -344.46113 | H22: =Model!CE239+Model!CE240 -> -354.39562 | I22: =H22*(1+I$26) -> -375.65935 | J22: =I22*(1+J$26) -> -396.32062 | K22: =J22*(1+K$26) -> -416.13665 | L22: =K22*(1+L$26) -> -434.8628 | M22: =L22*(1+M$26) -> -452.25731
B23: − Δ Working capital (CF statement) | D23: =Model!CA237 -> -120.60623 | E23: =Model!CB237 -> -45.90046 | F23: =Model!CC237 -> -60.698567 | G23: =Model!CD237 -> -61.156335 | H23: =Model!CE237 -> -65.155182 | I23: =H23*(1+I$26) -> -69.064493 | J23: =I23*(1+J$26) -> -72.86304 | K23: =J23*(1+K$26) -> -76.506192 | L23: =K23*(1+L$26) -> -79.948971 | M23: =L23*(1+M$26) -> -83.14693
B24: Unlevered FCF | D24: =D20+D21+D22+D23 -> 508.68148 | E24: =E20+E21+E22+E23 -> 444.97596 | F24: =F20+F21+F22+F23 -> 496.88858 | G24: =G20+G21+G22+G23 -> 561.51573 | H24: =H20+H21+H22+H23 -> 616.04828 | I24: =I20+I21+I22+I23 -> 653.01118 | J24: =J20+J21+J22+J23 -> 688.92679 | K24: =K20+K21+K22+K23 -> 723.37313 | ... M24: =M20+M21+M22+M23 -> 786.16192 | N24: =M24*(1+$C$27) -> 809.74678 | P24: =(H24/D24)^(1/(COLUMNS(D24:H24)-1))-1 -> 0.049040381 | Q24: =(M24/D24)^(1/(COLUMNS(D24:M24)-1))-1 -> 0.049560172
B25: Terminal Value (Gordon Growth) | N25: =N24/($C$13-$C$27) -> 11027.841
B26: Fade-period growth (2031E–35E; 6% → 4% linear) | I26: 0.06 | J26: =I26+($M$26-$I$26)/4 -> 0.055 | K26: =J26+($M$26-$I$26)/4 -> 0.05 | L26: =K26+($M$26-$I$26)/4 -> 0.045 | M26: 0.04
B27: Terminal growth rate | C27: 0.03 | D27: Long-run nominal GDP-type growth for welding consumables / automation; below MLM (4%) given lower pricing power
B29: Discount period (years) | D29: =(DATE(2026,12,31)-$C$15)/365.25 -> 0.23271732 | E29: =(DATE(2027,12,31)-$C$15)/365.25 -> 1.2320329 | F29: =(DATE(2028,12,31)-$C$15)/365.25 -> 2.2340862 | G29: =(DATE(2029,12,31)-$C$15)/365.25 -> 3.2334018 | H29: =(DATE(2030,12,31)-$C$15)/365.25 -> 4.2327173 | I29: =(DATE(2031,12,31)-$C$15)/365.25 -> 5.2320329 | J29: =(DATE(2032,12,31)-$C$15)/365.25 -> 6.2340862 | K29: =(DATE(2033,12,31)-$C$15)/365.25 -> 7.2334018 | L29: =(DATE(2034,12,31)-$C$15)/365.25 -> 8.2327173 | M29: =(DATE(2035,12,31)-$C$15)/365.25 -> 9.2320329 | N29: =M29 -> 9.2320329
B30: Discount factor | D30: =1/(1+$C$13)^D29 -> 0.97735598 | E30: =1/(1+$C$13)^E29 -> 0.88580521 | F30: =1/(1+$C$13)^F29 -> 0.80261386 | G30: =1/(1+$C$13)^G29 -> 0.72743151 | H30: =1/(1+$C$13)^H29 -> 0.65929163 | I30: =1/(1+$C$13)^I29 -> 0.59753454 | J30: =1/(1+$C$13)^J29 -> 0.54141645 | K30: =1/(1+$C$13)^K29 -> 0.49070095 | ... N30: =1/(1+$C$13)^N29 -> 0.4030768
B31: PV of UFCF | D31: =D24*D30 -> 497.16289 | E31: =E24*E30 -> 394.16203 | F31: =F24*F30 -> 398.80966 | G31: =G24*G30 -> 408.46424 | H31: =H24*H30 -> 406.15548 | I31: =I24*I30 -> 390.19674 | J31: =J24*J30 -> 372.9963 | K31: =K24*K30 -> 354.95988 | ... M31: =M24*M30 -> 316.88363 | N31: =N25*N30 -> 4445.0668
D32: LECO's Adjusted EBIT expenses stock-based compensation; rationalization and acquisition transaction costs are deducted as recurring cash items. 2026E is the full fiscal year (1H/26 actual + 2H/26E); net debt is taken at YE2026E. 2027E–30E capex includes bolt-on M&A per the scenario lever.
B33: IMPLIED ROIC — invested capital roll-forward (USDm)
B34: Opening invested capital | D34: =Model!BV357 -> 2455.013 | E34: =D38 -> 2592.8541 | F34: =E38 -> 2845.6677 | G34: =F38 -> 3107.5377 | H34: =G38 -> 3363.8659 | I34: =H38 -> 3617.9573 | J34: =I38 -> 3887.2942 | K34: =J38 -> 4171.4447 | L34: =K38 -> 4469.8027 | M34: =L38 -> 4781.5867
B35: plus Capex and acquisitions | D35: =-D22 -> 119.86 | E35: =-E22 -> 325.47745 | F35: =-F22 -> 334.95482 | G35: =-G22 -> 344.46113 | H35: =-H22 -> 354.39562 | I35: =-I22 -> 375.65935 | J35: =-J22 -> 396.32062 | K35: =-K22 -> 416.13665 | ... M35: =-M22 -> 452.25731
B36: less D&A | D36: =-D21 -> -102.62518 | E36: =-E21 -> -118.56426 | F36: =-F21 -> -133.78344 | G36: =-G21 -> -149.28924 | H36: =-H21 -> -165.45937 | I36: =-I21 -> -175.38693 | J36: =-J21 -> -185.03321 | K36: =-K21 -> -194.28487 | ... M36: =-M21 -> -211.1488
B37: plus Δ Working capital investment | D37: =-D23 -> 120.60623 | E37: =-E23 -> 45.90046 | F37: =-F23 -> 60.698567 | G37: =-G23 -> 61.156335 | H37: =-H23 -> 65.155182 | I37: =-I23 -> 69.064493 | J37: =-J23 -> 72.86304 | K37: =-K23 -> 76.506192 | ... M37: =-M23 -> 83.14693
B38: Closing invested capital | D38: =SUM(D34:D37) -> 2592.8541 | E38: =SUM(E34:E37) -> 2845.6677 | F38: =SUM(F34:F37) -> 3107.5377 | G38: =SUM(G34:G37) -> 3363.8659 | H38: =SUM(H34:H37) -> 3617.9573 | I38: =SUM(I34:I37) -> 3887.2942 | J38: =SUM(J34:J37) -> 4171.4447 | K38: =SUM(K34:K37) -> 4469.8027 | ... M38: =SUM(M34:M37) -> 5105.8422
B39: NOPAT (row 20) | D39: =D20 -> 646.52253 | E39: =E20 -> 697.78962 | F39: =F20 -> 758.75853 | G39: =G20 -> 817.84396 | H39: =H20 -> 870.13971 | I39: =I20 -> 922.34809 | J39: =J20 -> 973.07724 | K39: =K20 -> 1021.7311 | ... M39: =M20 -> 1110.4174
B40: Implied ROIC (NOPAT / avg. invested capital) | D40: =IFERROR(D39/AVERAGE(D34,D38),"") -> 0.25615672 | E40: =IFERROR(E39/AVERAGE(E34,E38),"") -> 0.25661003 | F40: =IFERROR(F39/AVERAGE(F34,F38),"") -> 0.25490756 | G40: =IFERROR(G39/AVERAGE(G34,G38),"") -> 0.25275628 | H40: =IFERROR(H39/AVERAGE(H34,H38),"") -> 0.24925859 | I40: =IFERROR(I39/AVERAGE(I34,I38),"") -> 0.24578739 | J40: =IFERROR(J39/AVERAGE(J34,J38),"") -> 0.24149616 | K40: =IFERROR(K39/AVERAGE(K34,K38),"") -> 0.23647769 | ... M40: =IFERROR(M39/AVERAGE(M34,M38),"") -> 0.22461195
B41: Reinvestment rate (net investment / NOPAT) | D41: =IFERROR(SUM(D35:D37)/D39,"") -> 0.21320378 | E41: =IFERROR(SUM(E35:E37)/E39,"") -> 0.36230642 | F41: =IFERROR(SUM(F35:F37)/F39,"") -> 0.3451295 | G41: =IFERROR(SUM(G35:G37)/G39,"") -> 0.31341948 | H41: =IFERROR(SUM(H35:H37)/H39,"") -> 0.29201222 | I41: =IFERROR(SUM(I35:I37)/I39,"") -> 0.29201222 | J41: =IFERROR(SUM(J35:J37)/J39,"") -> 0.29201222 | K41: =IFERROR(SUM(K35:K37)/K39,"") -> 0.29201222 | ... M41: =IFERROR(SUM(M35:M37)/M39,"") -> 0.29201222
B42: Implied terminal RONIC (g / reinvestment rate) | N42: =IFERROR($C$27/M41,"") -> 0.10273543
D43: Opening IC = Model 2025A book invested capital (total equity incl. NCI + net debt), rolled forward with capex + M&A − D&A + ΔWC.
B44: 3. VALUATION SUMMARY
B45: Sum of PV (explicit + fade) | C45: =SUM(D31:M31) -> 3875.9779
B46: PV of Terminal Value | C46: =N31 -> 4445.0668
B47: Enterprise Value | C47: =C45+C46 -> 8321.0447
B48: Less: Net debt + NCI (Model 2026E YE) | C48: =Model!CA377+Model!CA306 -> 926.17462 | D48: Net debt at YE2026E after 2H/26 buybacks; NCI ~$0 (Model balance sheet).
B49: Equity Value | C49: =C47-C48 -> 7394.8701
B50: Diluted shares (m, Model 2026E YE) | C50: =Model!CA383 -> 54.501371
B51: Implied share price ($) | C51: =C49/C50 -> 135.68227
B52: Current share price ($) | C52: =Model!CA382 -> 275.54
B53: Implied upside / (downside) | C53: =C51/C52-1 -> -0.50757685
B54: Required discount to DCF value for target IRR | C54: =1-((1+C13)/(1+H54))^H55 -> 0.11663968 | D54: vs. current | E54: Target IRR | H54: 0.15
B55: Max entry price for target IRR ($) | C55: =C51*(1-C54) -> 119.85634 | D55: =C55/C52-1 -> -0.56501293 | E55: Years for discount to close | H55: 3
B58: 4. SENSITIVITY: IMPLIED PRICE ($) — WACC × Terminal Growth
D60: WACC →
B61: Terminal growth ↓ | D61: =F61-0.01 -> 0.0934275 | E61: =F61-0.005 -> 0.0984275 | F61: =$C$13 -> 0.1034275 | G61: =F61+0.005 -> 0.1084275 | H61: =F61+0.01 -> 0.1134275
B62: =B64-0.01 -> 0.02 | D62: {=IFERROR((SUMPRODUCT($D$24:$M$24/(1+D$61)^$D$29:$M$29)+($M$24*(1+$B62)/(D$61-$B62))/(1+D$61)^$M$29-$C$48)/$C$50,"")} -> 144.92229 | E62: {=IFERROR((SUMPRODUCT($D$24:$M$24/(1+E$61)^$D$29:$M$29)+($M$24*(1+$B62)/(E$61-$B62))/(1+E$61)^$M$29-$C$48)/$C$50,"")} -> 134.42978 | F62: {=IFERROR((SUMPRODUCT($D$24:$M$24/(1+F$61)^$D$29:$M$29)+($M$24*(1+$B62)/(F$61-$B62))/(1+F$61)^$M$29-$C$48)/$C$50,"")} -> 125.20934 | G62: {=IFERROR((SUMPRODUCT($D$24:$M$24/(1+G$61)^$D$29:$M$29)+($M$24*(1+$B62)/(G$61-$B62))/(1+G$61)^$M$29-$C$48)/$C$50,"")} -> 117.04475 | H62: {=IFERROR((SUMPRODUCT($D$24:$M$24/(1+H$61)^$D$29:$M$29)+($M$24*(1+$B62)/(H$61-$B62))/(1+H$61)^$M$29-$C$48)/$C$50,"")} -> 109.76605
B63: =B64-0.005 -> 0.025 | D63: {=IFERROR((SUMPRODUCT($D$24:$M$24/(1+D$61)^$D$29:$M$29)+($M$24*(1+$B63)/(D$61-$B63))/(1+D$61)^$M$29-$C$48)/$C$50,"")} -> 151.8035 | E63: {=IFERROR((SUMPRODUCT($D$24:$M$24/(1+E$61)^$D$29:$M$29)+($M$24*(1+$B63)/(E$61-$B63))/(1+E$61)^$M$29-$C$48)/$C$50,"")} -> 140.21228 | F63: {=IFERROR((SUMPRODUCT($D$24:$M$24/(1+F$61)^$D$29:$M$29)+($M$24*(1+$B63)/(F$61-$B63))/(1+F$61)^$M$29-$C$48)/$C$50,"")} -> 130.11197 | G63: {=IFERROR((SUMPRODUCT($D$24:$M$24/(1+G$61)^$D$29:$M$29)+($M$24*(1+$B63)/(G$61-$B63))/(1+G$61)^$M$29-$C$48)/$C$50,"")} -> 121.23409 | H63: {=IFERROR((SUMPRODUCT($D$24:$M$24/(1+H$61)^$D$29:$M$29)+($M$24*(1+$B63)/(H$61-$B63))/(1+H$61)^$M$29-$C$48)/$C$50,"")} -> 113.37092
B64: =$C$27 -> 0.03 | D64: {=IFERROR((SUMPRODUCT($D$24:$M$24/(1+D$61)^$D$29:$M$29)+($M$24*(1+$B64)/(D$61-$B64))/(1+D$61)^$M$29-$C$48)/$C$50,"")} -> 159.7696 | E64: {=IFERROR((SUMPRODUCT($D$24:$M$24/(1+E$61)^$D$29:$M$29)+($M$24*(1+$B64)/(E$61-$B64))/(1+E$61)^$M$29-$C$48)/$C$50,"")} -> 146.83984 | F64: {=IFERROR((SUMPRODUCT($D$24:$M$24/(1+F$61)^$D$29:$M$29)+($M$24*(1+$B64)/(F$61-$B64))/(1+F$61)^$M$29-$C$48)/$C$50,"")} -> 135.68227 | G64: {=IFERROR((SUMPRODUCT($D$24:$M$24/(1+G$61)^$D$29:$M$29)+($M$24*(1+$B64)/(G$61-$B64))/(1+G$61)^$M$29-$C$48)/$C$50,"")} -> 125.95761 | H64: {=IFERROR((SUMPRODUCT($D$24:$M$24/(1+H$61)^$D$29:$M$29)+($M$24*(1+$B64)/(H$61-$B64))/(1+H$61)^$M$29-$C$48)/$C$50,"")} -> 117.40789
B65: =B64+0.005 -> 0.035 | D65: {=IFERROR((SUMPRODUCT($D$24:$M$24/(1+D$61)^$D$29:$M$29)+($M$24*(1+$B65)/(D$61-$B65))/(1+D$61)^$M$29-$C$48)/$C$50,"")} -> 169.09912 | E65: {=IFERROR((SUMPRODUCT($D$24:$M$24/(1+E$61)^$D$29:$M$29)+($M$24*(1+$B65)/(E$61-$B65))/(1+E$61)^$M$29-$C$48)/$C$50,"")} -> 154.51231 | F65: {=IFERROR((SUMPRODUCT($D$24:$M$24/(1+F$61)^$D$29:$M$29)+($M$24*(1+$B65)/(F$61-$B65))/(1+F$61)^$M$29-$C$48)/$C$50,"")} -> 142.06663 | G65: {=IFERROR((SUMPRODUCT($D$24:$M$24/(1+G$61)^$D$29:$M$29)+($M$24*(1+$B65)/(G$61-$B65))/(1+G$61)^$M$29-$C$48)/$C$50,"")} -> 131.32441 | H65: {=IFERROR((SUMPRODUCT($D$24:$M$24/(1+H$61)^$D$29:$M$29)+($M$24*(1+$B65)/(H$61-$B65))/(1+H$61)^$M$29-$C$48)/$C$50,"")} -> 121.9596
B66: =B64+0.01 -> 0.04 | D66: {=IFERROR((SUMPRODUCT($D$24:$M$24/(1+D$61)^$D$29:$M$29)+($M$24*(1+$B66)/(D$61-$B66))/(1+D$61)^$M$29-$C$48)/$C$50,"")} -> 180.17484 | E66: {=IFERROR((SUMPRODUCT($D$24:$M$24/(1+E$61)^$D$29:$M$29)+($M$24*(1+$B66)/(E$61-$B66))/(1+E$61)^$M$29-$C$48)/$C$50,"")} -> 163.49793 | F66: {=IFERROR((SUMPRODUCT($D$24:$M$24/(1+F$61)^$D$29:$M$29)+($M$24*(1+$B66)/(F$61-$B66))/(1+F$61)^$M$29-$C$48)/$C$50,"")} -> 149.45754 | G66: {=IFERROR((SUMPRODUCT($D$24:$M$24/(1+G$61)^$D$29:$M$29)+($M$24*(1+$B66)/(G$61-$B66))/(1+G$61)^$M$29-$C$48)/$C$50,"")} -> 137.47551 | H66: {=IFERROR((SUMPRODUCT($D$24:$M$24/(1+H$61)^$D$29:$M$29)+($M$24*(1+$B66)/(H$61-$B66))/(1+H$61)^$M$29-$C$48)/$C$50,"")} -> 127.1312
B69: 5. REVERSE DCF
B70: To solve for the market-implied path: Data ▸ What-If Analysis ▸ Goal Seek — set C51 to the current price (C52) by changing C27 (terminal growth) or the fade-period growth inputs (I26:M26).
B72: 6. MAUBOUSSIN EV / NOPAT — TWO-STAGE FRAMEWORK
B73: EV/NOPAT = 1/r + [g × (1 − r/ROIIC) / (r × (r − g))] × [1 − ((1+g)/(1+r))^N]
B74: Formula source: Mauboussin & Rappaport, "Expectations Investing" (2021); Counterpoint Global, "What Does a Price-Earnings Multiple Mean?" (2020).
B76: Input | C76: Value | D76: Rationale (Lincoln Electric characteristics)
B77: r (Cost of capital / WACC) | C77: =$C$13 -> 0.1034275 | D77: Linked from Section 1 WACC build
B78: g (NOPAT growth, Stage 1) | C78: 0.07 | D78: Model Adjusted EBIT CAGR 2026–30E ~7%: mid-single-digit organic growth (price + volume recovery), bolt-on M&A, RISE margin gains (100–125 bp)
B79: ROIIC (Return on incremental invested capital) | C79: 0.25 | D79: Book ROIC 21–29% (2014–25); asset-light consumables model (capex ~2.5% of sales), bolt-ons at ~1.6x sales earn lower returns
B80: N (Years of value creation / CAP) | C80: 10 | D80: #1 global arc-welding share (~20% of consumables & equipment), distribution / brand moat; automation and cyclicality limit CAP vs. aggregates
B82: Calculation | C82: Value
B83: Steady-state component: 1 / r | C83: =1/C77 -> 9.6686084
B84: Value-creation factor: 1 − r / ROIIC | C84: =1-C77/C79 -> 0.58629
B85: Growth multiplier: g × (1 − r/ROIIC) / (r × (r − g)) | C85: =C78*C84/(C77*(C77-C78)) -> 11.870543
B86: Time decay: 1 − ((1+g)/(1+r))^N | C86: =1-((1+C78)/(1+C77))^C80 -> 0.26480974
B87: PVGO component (growth value) | C87: =C85*C86 -> 3.1434356
B88: Mauboussin EV / NOPAT (steady-state + PVGO) | C88: =C83+C87 -> 12.812044
B90: VALUATION — Applied to 2028E NOPAT | C90: USDm
B91: 2028E Adj. EBIT less rationalization & acquisition costs | C91: =F18 -> 985.40069
B92: Tax rate (from WACC build) | C92: =$C$10 -> 0.23
B93: 2028E NOPAT | C93: =C91*(1-C92) -> 758.75853
B94: × Mauboussin EV/NOPAT multiple | C94: =C88 -> 12.812044
B95: Implied Enterprise Value (2028E basis) | C95: =C93*C94 -> 9721.2477
B96: Less: YE2027 net debt + NCI (Model) | C96: =Model!CB377+Model!CB306 -> 1036.7845
B97: Implied Equity Value | C97: =C95-C96 -> 8684.4631
B98: Diluted shares 2028E (m, Model) | C98: =Model!CC383 -> 52.478043
B99: Implied share price 2028 ($) | C99: =C97/C98 -> 165.48756
B101: Current share price ($) | C101: =C52 -> 275.54
B102: Implied upside / (downside) | C102: =C99/C101-1 -> -0.39940641
B104: MARKET-IMPLIED EV/NOPAT TODAY | C104: USDm
B105: Current market cap (spot × diluted shares) | C105: =C52*C50 -> 15017.308
B106: Plus: YE2026 net debt + NCI | C106: =C48 -> 926.17462
B107: Implied Enterprise Value (today) | C107: =C105+C106 -> 15943.483
B108: LECO market-implied EV/NOPAT (on 2028E NOPAT) | C108: =C107/C93 -> 21.012591
B110: Multiple gap (Mauboussin − Market) | C110: =C88-C108 -> -8.2005468
B111: Implied re-rating headroom | C111: =C88/C108-1 -> -0.39026824

Sheet Charts
B2: Lincoln Electric — Historical Operating Performance (2006–2025)
B3: All historicals · USDm · Linked to Model. Volume / price = consolidated "change in net sales" drivers (company-reported, from 2010; legacy 5-segment basis to 2015). Adjusted EBIT = company definition (EBIT, as adjusted to 2017); Adjusted EBITDA model-derived.
C7: 2006 | D7: 2007 | E7: 2008 | F7: 2009 | G7: 2010 | H7: 2011 | I7: 2012 | J7: 2013 | K7: 2014 | L7: 2015 | M7: 2016 | N7: 2017 | O7: 2018 | P7: 2019 | Q7: 2020 | R7: 2021 | S7: 2022 | T7: 2023 | U7: 2024 | V7: 2025
B8: Volume % | C8: =IFERROR(Model!C109+0,0) -> 0 | D8: =IFERROR(Model!D109+0,0) -> 0 | E8: =IFERROR(Model!E109+0,0) -> 0 | F8: =IFERROR(Model!F109+0,0) -> 0 | G8: =IFERROR(Model!G109+0,0) -> 0.140552 | H8: =IFERROR(Model!H109+0,0) -> 0.147826 | I8: =IFERROR(Model!I109+0,0) -> 0.012918 | J8: =IFERROR(Model!N109+0,0) -> -0.0266 | K8: =IFERROR(Model!S109+0,0) -> -0.020299 | L8: =IFERROR(Model!X109+0,0) -> -0.079624 | M8: =IFERROR(Model!AC109+0,0) -> -0.097666 | N8: =IFERROR(Model!AH109+0,0) -> 0.041841 | O8: =IFERROR(Model!AM109+0,0) -> 0.01059 | P8: =IFERROR(Model!AR109+0,0) -> -0.046521 | Q8: =IFERROR(Model!AW109+0,0) -> -0.126925 | R8: =IFERROR(Model!BB109+0,0) -> 0.098064 | S8: =IFERROR(Model!BG109+0,0) -> 0.049584 | T8: =IFERROR(Model!BL109+0,0) -> 0.022781 | U8: =IFERROR(Model!BQ109+0,0) -> -0.071848 | V8: =IFERROR(Model!BV109+0,0) -> -0.036841
B9: Price % | C9: =IFERROR(Model!C110+0,0) -> 0 | D9: =IFERROR(Model!D110+0,0) -> 0 | E9: =IFERROR(Model!E110+0,0) -> 0 | F9: =IFERROR(Model!F110+0,0) -> 0 | G9: =IFERROR(Model!G110+0,0) -> 0.003581 | H9: =IFERROR(Model!H110+0,0) -> 0.06903 | I9: =IFERROR(Model!I110+0,0) -> 0.016997 | J9: =IFERROR(Model!N110+0,0) -> 0.000744 | K9: =IFERROR(Model!S110+0,0) -> 0.017501 | L9: =IFERROR(Model!X110+0,0) -> 0.039514 | M9: =IFERROR(Model!AC110+0,0) -> 0.102411 | N9: =IFERROR(Model!AH110+0,0) -> 0.024214 | O9: =IFERROR(Model!AM110+0,0) -> 0.055705 | P9: =IFERROR(Model!AR110+0,0) -> 0.012453 | Q9: =IFERROR(Model!AW110+0,0) -> 0.004813 | R9: =IFERROR(Model!BB110+0,0) -> 0.094857 | S9: =IFERROR(Model!BG110+0,0) -> 0.14499 | T9: =IFERROR(Model!BL110+0,0) -> 0.017055 | U9: =IFERROR(Model!BQ110+0,0) -> 0.007252 | V9: =IFERROR(Model!BV110+0,0) -> 0.061502
B12: Adjusted EBIT | C12: =IFERROR(Model!C178+0,0) -> 236.927 | D12: =IFERROR(Model!D178+0,0) -> 290.105 | E12: =IFERROR(Model!E178+0,0) -> 322.49 | F12: =IFERROR(Model!F178+0,0) -> 122.17 | G12: =IFERROR(Model!G178+0,0) -> 194.157 | H12: =IFERROR(Model!H178+0,0) -> 305.196 | I12: =IFERROR(Model!I178+0,0) -> 380.508 | J12: =IFERROR(Model!N178+0,0) -> 437.351 | K12: =IFERROR(Model!S178+0,0) -> 434.34 | L12: =IFERROR(Model!X178+0,0) -> 378.807 | M12: =IFERROR(Model!AC178+0,0) -> 328.723 | N12: =IFERROR(Model!AH178+0,0) -> 370.338 | O12: =IFERROR(Model!AM178+0,0) -> 422.694 | P12: =IFERROR(Model!AR178+0,0) -> 400.753 | Q12: =IFERROR(Model!AW178+0,0) -> 340.406 | R12: =IFERROR(Model!BB178+0,0) -> 491.268 | S12: =IFERROR(Model!BG178+0,0) -> 636.951 | T12: =IFERROR(Model!BL178+0,0) -> 731.374 | U12: =IFERROR(Model!BQ178+0,0) -> 713.605 | V12: =IFERROR(Model!BV178+0,0) -> 752.632
B13: Operating income (GAAP) | C13: =IFERROR(Model!C140+0,0) -> 232.97 | D13: =IFERROR(Model!D140+0,0) -> 277.632 | E13: =IFERROR(Model!E140+0,0) -> 295.404 | F13: =IFERROR(Model!F140+0,0) -> 92.976 | G13: =IFERROR(Model!G140+0,0) -> 186.43 | H13: =IFERROR(Model!H140+0,0) -> 296.68 | I13: =IFERROR(Model!I140+0,0) -> 362.081 | J13: =IFERROR(Model!N140+0,0) -> 406.985 | K13: =IFERROR(Model!S140+0,0) -> 373.747 | L13: =IFERROR(Model!X140+0,0) -> 181.7 | M13: =IFERROR(Model!AC140+0,0) -> 288.274 | N13: =IFERROR(Model!AH140+0,0) -> 377.711 | O13: =IFERROR(Model!AM140+0,0) -> 375.539 | P13: =IFERROR(Model!AR140+0,0) -> 370.91 | Q13: =IFERROR(Model!AW140+0,0) -> 282.071 | R13: =IFERROR(Model!BB140+0,0) -> 461.669 | S13: =IFERROR(Model!BG140+0,0) -> 612.336 | T13: =IFERROR(Model!BL140+0,0) -> 717.849 | U13: =IFERROR(Model!BQ140+0,0) -> 636.462 | V13: =IFERROR(Model!BV140+0,0) -> 718.059
B14: Adj. EBIT Margin % | C14: =IFERROR(Model!C179+0,0) -> 0.12015072 | D14: =IFERROR(Model!D179+0,0) -> 0.1271953 | E14: =IFERROR(Model!E179+0,0) -> 0.13008187 | F14: =IFERROR(Model!F179+0,0) -> 0.070647695 | G14: =IFERROR(Model!G179+0,0) -> 0.093787859 | H14: =IFERROR(Model!H179+0,0) -> 0.1132617 | I14: =IFERROR(Model!I179+0,0) -> 0.13335403 | J14: =IFERROR(Model!N179+0,0) -> 0.15331281 | K14: =IFERROR(Model!S179+0,0) -> 0.15438677 | L14: =IFERROR(Model!X179+0,0) -> 0.14938416 | M14: =IFERROR(Model!AC179+0,0) -> 0.14451815 | N14: =IFERROR(Model!AH179+0,0) -> 0.14111173 | O14: =IFERROR(Model!AM179+0,0) -> 0.13956405 | P14: =IFERROR(Model!AR179+0,0) -> 0.1334388 | Q14: =IFERROR(Model!AW179+0,0) -> 0.12819387 | R14: =IFERROR(Model!BB179+0,0) -> 0.15189878 | S14: =IFERROR(Model!BG179+0,0) -> 0.16934732 | T14: =IFERROR(Model!BL179+0,0) -> 0.17448414 | U14: =IFERROR(Model!BQ179+0,0) -> 0.1780154 | V14: =IFERROR(Model!BV179+0,0) -> 0.17780096
B15: GAAP Op. Margin % | C15: =IFERROR(Model!C224+0,0) -> 0.11814404 | D15: =IFERROR(Model!D224+0,0) -> 0.12172656 | E15: =IFERROR(Model!E224+0,0) -> 0.11915627 | F15: =IFERROR(Model!F224+0,0) -> 0.053765574 | G15: =IFERROR(Model!G224+0,0) -> 0.090055319 | H15: =IFERROR(Model!H224+0,0) -> 0.11010132 | I15: =IFERROR(Model!I224+0,0) -> 0.12689605 | J15: =IFERROR(Model!N224+0,0) -> 0.14266805 | K15: =IFERROR(Model!S224+0,0) -> 0.1328489 | L15: =IFERROR(Model!X224+0,0) -> 0.07165417 | M15: =IFERROR(Model!AC224+0,0) -> 0.12673535 | N15: =IFERROR(Model!AH224+0,0) -> 0.1439211 | O15: =IFERROR(Model!AM224+0,0) -> 0.12399453 | P15: =IFERROR(Model!AR224+0,0) -> 0.12350197 | Q15: =IFERROR(Model!AW224+0,0) -> 0.10622543 | R15: =IFERROR(Model!BB224+0,0) -> 0.14274685 | S15: =IFERROR(Model!BG224+0,0) -> 0.16280288 | T15: =IFERROR(Model!BL224+0,0) -> 0.17125748 | U15: =IFERROR(Model!BQ224+0,0) -> 0.15877136 | V15: =IFERROR(Model!BV224+0,0) -> 0.16963347
B18: ROIC | C18: =IFERROR(Model!C360+0,0) -> 0.19476495 | D18: =IFERROR(Model!D360+0,0) -> 0.20488842 | E18: =IFERROR(Model!E360+0,0) -> 0.26763136 | F18: =IFERROR(Model!F360+0,0) -> 0.083557813 | G18: =IFERROR(Model!G360+0,0) -> 0.15572345 | H18: =IFERROR(Model!H360+0,0) -> 0.23494606 | I18: =IFERROR(Model!I360+0,0) -> 0.24248782 | J18: =IFERROR(Model!N360+0,0) -> 0.24507617 | K18: =IFERROR(Model!S360+0,0) -> 0.2721731 | L18: =IFERROR(Model!X360+0,0) -> 0.28921378 | M18: =IFERROR(Model!AC360+0,0) -> 0.22634364 | N18: =IFERROR(Model!AH360+0,0) -> 0.19073415 | O18: =IFERROR(Model!AM360+0,0) -> 0.26722135 | P18: =IFERROR(Model!AR360+0,0) -> 0.23320506 | Q18: =IFERROR(Model!AW360+0,0) -> 0.2124149 | R18: =IFERROR(Model!BB360+0,0) -> 0.29017761 | S18: =IFERROR(Model!BG360+0,0) -> 0.2486177 | T18: =IFERROR(Model!BL360+0,0) -> 0.28737639 | U18: =IFERROR(Model!BQ360+0,0) -> 0.25316987 | V18: =IFERROR(Model!BV360+0,0) -> 0.2362566
B19: RONTA | C19: =IFERROR(Model!C371+0,0) -> 0.16956362 | D19: =IFERROR(Model!D371+0,0) -> 0.16359995 | E19: =IFERROR(Model!E371+0,0) -> 0.17412272 | F19: =IFERROR(Model!F371+0,0) -> 0.051913482 | G19: =IFERROR(Model!G371+0,0) -> 0.10283675 | H19: =IFERROR(Model!H371+0,0) -> 0.15183721 | I19: =IFERROR(Model!I371+0,0) -> 0.18883062 | J19: =IFERROR(Model!N371+0,0) -> 0.22061848 | K19: =IFERROR(Model!S371+0,0) -> 0.24388808 | L19: =IFERROR(Model!X371+0,0) -> 0.2560709 | M19: =IFERROR(Model!AC371+0,0) -> 0.19668898 | N19: =IFERROR(Model!AH371+0,0) -> 0.16486362 | O19: =IFERROR(Model!AM371+0,0) -> 0.23801363 | P19: =IFERROR(Model!AR371+0,0) -> 0.23999028 | Q19: =IFERROR(Model!AW371+0,0) -> 0.20479808 | R19: =IFERROR(Model!BB371+0,0) -> 0.31924751 | S19: =IFERROR(Model!BG371+0,0) -> 0.3266686 | T19: =IFERROR(Model!BL371+0,0) -> 0.33289966 | U19: =IFERROR(Model!BQ371+0,0) -> 0.32435858 | V19: =IFERROR(Model!BV371+0,0) -> 0.31737086
B20: Adj. EBITDA margin % | C20: =IFERROR(Model!C185+0,0) -> 0.14440379 | D20: =IFERROR(Model!D185+0,0) -> 0.15026193 | E20: =IFERROR(Model!E185+0,0) -> 0.15304355 | F20: =IFERROR(Model!F185+0,0) -> 0.10337683 | G20: =IFERROR(Model!G185+0,0) -> 0.12149425 | H20: =IFERROR(Model!H185+0,0) -> 0.13628953 | I20: =IFERROR(Model!I185+0,0) -> 0.15625119 | J20: =IFERROR(Model!N185+0,0) -> 0.17745965 | K20: =IFERROR(Model!S185+0,0) -> 0.17912867 | L20: =IFERROR(Model!X185+0,0) -> 0.17462559 | M20: =IFERROR(Model!AC185+0,0) -> 0.17312652 | N20: =IFERROR(Model!AH185+0,0) -> 0.16706593 | O20: =IFERROR(Model!AM185+0,0) -> 0.16345107 | P20: =IFERROR(Model!AR185+0,0) -> 0.16057154 | Q20: =IFERROR(Model!AW185+0,0) -> 0.15850644 | R20: =IFERROR(Model!BB185+0,0) -> 0.17698891 | S20: =IFERROR(Model!BG185+0,0) -> 0.19010101 | T20: =IFERROR(Model!BL185+0,0) -> 0.19516103 | U20: =IFERROR(Model!BQ185+0,0) -> 0.20002719 | V20: =IFERROR(Model!BV185+0,0) -> 0.20108136
B21: FCF margin % | C21: =IFERROR(Model!C260+0,0) -> 0.021642921 | D21: =IFERROR(Model!D260+0,0) -> 0.082515047 | E21: =IFERROR(Model!E260+0,0) -> 0.0746322 | F21: =IFERROR(Model!F260+0,0) -> 0.12268018 | G21: =IFERROR(Model!G260+0,0) -> 0.046572459 | H21: =IFERROR(Model!H260+0,0) -> 0.047392776 | I21: =IFERROR(Model!I260+0,0) -> 0.096296411 | J21: =IFERROR(Model!N260+0,0) -> 0.092151882 | K21: =IFERROR(Model!S260+0,0) -> 0.11684115 | L21: =IFERROR(Model!X260+0,0) -> 0.10267053 | M21: =IFERROR(Model!AC260+0,0) -> 0.11145891 | N21: =IFERROR(Model!AH260+0,0) -> 0.10409456 | O21: =IFERROR(Model!AM260+0,0) -> 0.085154757 | P21: =IFERROR(Model!AR260+0,0) -> 0.11106886 | Q21: =IFERROR(Model!AW260+0,0) -> 0.11002523 | R21: =IFERROR(Model!BB260+0,0) -> 0.093542103 | S21: =IFERROR(Model!BG260+0,0) -> 0.082819868 | T21: =IFERROR(Model!BL260+0,0) -> 0.13754892 | U21: =IFERROR(Model!BQ260+0,0) -> 0.12033268 | V21: =IFERROR(Model!BV260+0,0) -> 0.12619859
