Workbook

Sheet Model
CF1: SCENARIO SWITCH ▼ (Bull / Base / Bear) — drives all scenario-linked forecast drivers
B2: Amazon.com, Inc. (NASDAQ: AMZN) — 3-Statement Financial Model | CF2: Base
B3: US GAAP as reported · USD millions (per-share data in USD; shares in millions, split-adjusted) · Fiscal years ended 31 December · Source: Amazon.com Forms 10-K / 10-Q, Form 8-K earnings releases (Ex. 99.1, incl. the 23-Apr-2015 AWS recast Ex. 99.3) and financing 8-Ks, SEC EDGAR (CIK 0001018724); XBRL company facts; the investor-relations releases are the same documents as filed on EDGAR. Guidance: Q3-26 only (8-K 30-Jul-2026); the ~$200bn 2026 capex figure is from the call and UNVERIFIED (information row only).
B4: Basis notes: as originally reported. Segments NA / International to 2014 (AWS inside NA), AWS from 2015 (FY2013–14 recast); 2015 segment OI restated for SBC allocation (2016 releases). 20-for-1 split 6-Jun-2022. ASC 606 (2018, modified retrospective), ASC 842 (2019). Acquisitions: Whole Foods 28-Aug-17 ($13.2bn), MGM 17-Mar-22 ($6.1bn + $2.5bn debt), One Medical 22-Feb-23 ($3.5bn). Q3/26E calibrated to Q3-26 guidance (net sales, operating income); Q4/26E carries the Q3 Δs (no guidance).
CH5: Forecast | CI5: Historical | CJ5: Historical | CK5: Historical
B6: (USDm) | C6: 2006 | D6: 2007 | E6: 2008 | F6: 2009 | G6: 2010 | H6: 2011 | I6: 2012 | J6: Q1/13 | K6: Q2/13 | L6: Q3/13 | M6: Q4/13 | N6: 2013 | O6: Q1/14 | P6: Q2/14 | Q6: Q3/14 | R6: Q4/14 | S6: 2014 | T6: Q1/15 | U6: Q2/15 | V6: Q3/15 | W6: Q4/15 | X6: 2015 | Y6: Q1/16 | Z6: Q2/16 | AA6: Q3/16 | AB6: Q4/16 | AC6: 2016 | AD6: Q1/17 | AE6: Q2/17 | AF6: Q3/17 | AG6: Q4/17 | AH6: 2017 | AI6: Q1/18 | AJ6: Q2/18 | AK6: Q3/18 | AL6: Q4/18 | AM6: 2018 | AN6: Q1/19 | AO6: Q2/19 | AP6: Q3/19 | AQ6: Q4/19 | AR6: 2019 | AS6: Q1/20 | AT6: Q2/20 | AU6: Q3/20 | AV6: Q4/20 | AW6: 2020 | AX6: Q1/21 | AY6: Q2/21 | AZ6: Q3/21 | BA6: Q4/21 | BB6: 2021 | BC6: Q1/22 | BD6: Q2/22 | BE6: Q3/22 | BF6: Q4/22 | BG6: 2022 | BH6: Q1/23 | BI6: Q2/23 | BJ6: Q3/23 | BK6: Q4/23 | BL6: 2023 | BM6: Q1/24 | BN6: Q2/24 | BO6: Q3/24 | BP6: Q4/24 | BQ6: 2024 | BR6: Q1/25 | BS6: Q2/25 | BT6: Q3/25 | BU6: Q4/25 | BV6: 2025 | BW6: Q1/26 | BX6: Q2/26 | BY6: Q3/26E | BZ6: Q4/26E | CA6: 2026E | CB6: 2027E | CC6: 2028E | CD6: 2029E | CE6: 2030E | CF6: Modelling Notes | CH6: 5Y CAGR | CI6: 5Y CAGR | CJ6: 10Y CAGR | CK6: 19Y CAGR
CH7: 25-'30 | CI7: 20-'25 | CJ7: 15-'25 | CK7: 06-'25
B8: NET SALES BUILD — GROUPS OF SIMILAR PRODUCTS & SERVICES → SEGMENTS (NORTH AMERICA · INTERNATIONAL · AWS) | CF8: NET SALES BUILD — modelling logic (product-group net sales → retail groups split NA / International by the NA share; AWS group = AWS segment → segment operating income at segment margins → GAAP P&L)
CN9: SCENARIO INPUT TABLE — driver assumptions per Bull / Base / Bear | CO9: Bull | CP9: Base | CQ9: Bear | CR9: Bull / Bear = Base + Δ (Δ inputs on each block header). Outlook block = high / mid / low end of the Q3-26 guidance ranges.
B10: Net sales by groups of similar products and services (supplemental release table; from Q2-16; advertising services split out of "Other" from Q3-20) | CF10: PRODUCT GROUPS — modelling logic: Q3/Q4-26E = prior-year quarter × (1 + growth); 2027E+ = prior year × (1 + scenario lever)
B11: Online stores | Z11: 20378 | AA11: 21590 | AB11: 29548 | AD11: 22826 | AE11: 23754 | AF11: 26392 | AG11: 35383 | AH11: 108355 | AI11: 26939 | AJ11: 27165 | AK11: 29061 | AL11: 39822 | AM11: 122987 | AN11: 29498 | AO11: 31053 | AP11: 35039 | AQ11: 45657 | AR11: 141247 | AS11: 36652 | AT11: 45896 | AU11: 48350 | AV11: 66451 | AW11: 197349 | AX11: 52901 | AY11: 53157 | AZ11: 49942 | BA11: 66075 | BB11: 222075 | BC11: 51129 | BD11: 50855 | BE11: 53489 | BF11: 64531 | BG11: 220004 | BH11: 51096 | BI11: 52966 | BJ11: 57267 | BK11: 70543 | BL11: 231872 | BM11: 54670 | BN11: 55392 | BO11: 61411 | BP11: 75556 | BQ11: 247029 | BR11: 57407 | BS11: 61485 | BT11: 67407 | BU11: 82988 | BV11: 269287 | BW11: 64254 | BX11: 70432 | BY11: =BT11*(1+BY12) -> 68792.361 | BZ11: =BU11*(1+BZ12) -> 89380.837 | CA11: =SUM(BW11:BZ11) -> 292859.2 | CB11: =CA11*(1+CB12) -> 317752.23 | CC11: =CB11*(1+CC12) -> 343172.41 | CD11: =CC11*(1+CD12) -> 368910.34 | CE11: =CD11*(1+CE12) -> 394734.06 | CF11: Latest release presenting each quarter (Amazon re-presents the groups). FY = Σ quarters. Q3/Q4-26E: prior-year quarter × (1 + growth). | CH11: =IFERROR((CE11/BV11)^(1/5)-1,"n/m") -> 0.07948806 | CI11: =IFERROR((BV11/AW11)^(1/5)-1,"n/m") -> 0.064133442 | CJ11: =IFERROR((BV11/X11)^(1/10)-1,"n/m") -> n/m | CK11: =IFERROR((BV11/C11)^(1/19)-1,"n/m") -> n/m | CN11: Q3-26 guidance — Q2-26 release (8-K, 30-Jul-2026) | CO11: High | CP11: Mid | CQ11: Low | CR11: Net sales $197.0–202.0bn (+9–12% y/y; ~80 bp FX headwind; Prime Day in Q2 in 2026 vs Q3 in 2025 — ex Prime Day growth ~400 bp higher); operating income $22.5–26.5bn (assumes no energy-derivative remeasurement, acquisitions, restructurings or legal settlements). Amazon guides one quarter ahead.
B12: y/y % | D12: =IF(AND(ISNUMBER(D11),ISNUMBER(C11)),IFERROR(D11/C11-1,""),"") | E12: =IF(AND(ISNUMBER(E11),ISNUMBER(D11)),IFERROR(E11/D11-1,""),"") | F12: =IF(AND(ISNUMBER(F11),ISNUMBER(E11)),IFERROR(F11/E11-1,""),"") | G12: =IF(AND(ISNUMBER(G11),ISNUMBER(F11)),IFERROR(G11/F11-1,""),"") | H12: =IF(AND(ISNUMBER(H11),ISNUMBER(G11)),IFERROR(H11/G11-1,""),"") | I12: =IF(AND(ISNUMBER(I11),ISNUMBER(H11)),IFERROR(I11/H11-1,""),"") | N12: =IF(AND(ISNUMBER(N11),ISNUMBER(I11)),IFERROR(N11/I11-1,""),"") | O12: =IF(AND(ISNUMBER(O11),ISNUMBER(J11)),IFERROR(O11/J11-1,""),"") | P12: =IF(AND(ISNUMBER(P11),ISNUMBER(K11)),IFERROR(P11/K11-1,""),"") | Q12: =IF(AND(ISNUMBER(Q11),ISNUMBER(L11)),IFERROR(Q11/L11-1,""),"") | R12: =IF(AND(ISNUMBER(R11),ISNUMBER(M11)),IFERROR(R11/M11-1,""),"") | S12: =IF(AND(ISNUMBER(S11),ISNUMBER(N11)),IFERROR(S11/N11-1,""),"") | T12: =IF(AND(ISNUMBER(T11),ISNUMBER(O11)),IFERROR(T11/O11-1,""),"") | U12: =IF(AND(ISNUMBER(U11),ISNUMBER(P11)),IFERROR(U11/P11-1,""),"") | ... BX12: =IF(AND(ISNUMBER(BX11),ISNUMBER(BS11)),IFERROR(BX11/BS11-1,""),"") -> 0.14551517 | BY12: =BY13+BY32+BY114 -> 0.020552184 | BZ12: =BZ13+BZ32+BZ114 -> 0.077033265 | CA12: =IF(AND(ISNUMBER(CA11),ISNUMBER(BV11)),IFERROR(CA11/BV11-1,""),"") -> 0.087535595 | CB12: =CHOOSE(MATCH($CF$2,{"Bull","Base","Bear"},0),$CO$32,$CP$32,$CQ$32) -> 0.085 | CC12: =CHOOSE(MATCH($CF$2,{"Bull","Base","Bear"},0),$CO$33,$CP$33,$CQ$33) -> 0.08 | CD12: =CHOOSE(MATCH($CF$2,{"Bull","Base","Bear"},0),$CO$34,$CP$34,$CQ$34) -> 0.075 | CE12: =CHOOSE(MATCH($CF$2,{"Bull","Base","Bear"},0),$CO$35,$CP$35,$CQ$35) -> 0.07 | CF12: Q3/Q4-26E: Q1-26 y/y (before the Prime Day shift) + Prime Day timing shift (Q3 only; online stores, third-party seller services, advertising) + net-sales guidance calibration Δ (retail groups only). 2027E+: scenario lever. | CN12: Q3-26 net sales ($m) | CO12: 202000 | CP12: 199500 | CQ12: 197000 | CR12: Guided $197.0–202.0bn. Drives the Q3/26E net-sales calibration (retail product groups).
B13: Q3/Q4-26E growth before calibration (Q1-26 y/y) | BY13: =IFERROR(BW11/BR11-1,0) -> 0.11927117 | BZ13: =IFERROR(BW11/BR11-1,0) -> 0.11927117 | CN13: Q3-26 operating income ($m) | CO13: 26500 | CP13: 24500 | CQ13: 22500 | CR13: Guided $22.5–26.5bn (Q3-25 $17.4bn incl. $4.3bn special charges). Drives the segment-margin calibration.
B14: Physical stores | Z14: 0 | AA14: 0 | AB14: 0 | AD14: 0 | AE14: 0 | AF14: 1276 | AG14: 4522 | AH14: 5798 | AI14: 4263 | AJ14: 4312 | AK14: 4248 | AL14: 4401 | AM14: 17224 | AN14: 4307 | AO14: 4330 | AP14: 4192 | AQ14: 4363 | AR14: 17192 | AS14: 4640 | AT14: 3774 | AU14: 3788 | AV14: 4022 | AW14: 16224 | AX14: 3920 | AY14: 4198 | AZ14: 4269 | BA14: 4688 | BB14: 17075 | BC14: 4591 | BD14: 4721 | BE14: 4694 | BF14: 4957 | BG14: 18963 | BH14: 4895 | BI14: 5024 | BJ14: 4959 | BK14: 5152 | BL14: 20030 | BM14: 5202 | BN14: 5206 | BO14: 5228 | BP14: 5579 | BQ14: 21215 | BR14: 5533 | BS14: 5595 | BT14: 5578 | BU14: 5855 | BV14: 22561 | BW14: 5785 | BX14: 5794 | BY14: =BT14*(1+BY15) -> 5596.4465 | BZ14: =BU14*(1+BZ15) -> 5874.3625 | CA14: =SUM(BW14:BZ14) -> 23049.809 | CB14: =CA14*(1+CB15) -> 24202.299 | CC14: =CB14*(1+CC15) -> 25412.414 | CD14: =CC14*(1+CD15) -> 26555.973 | CE14: =CD14*(1+CE15) -> 27618.212 | CF14: Whole Foods Market from 28-Aug-2017 (blank before = 0). | CH14: =IFERROR((CE14/BV14)^(1/5)-1,"n/m") -> 0.041279798 | CI14: =IFERROR((BV14/AW14)^(1/5)-1,"n/m") -> 0.068169275 | CJ14: =IFERROR((BV14/X14)^(1/10)-1,"n/m") -> n/m | CK14: =IFERROR((BV14/C14)^(1/19)-1,"n/m") -> n/m
B15: y/y % | D15: =IF(AND(ISNUMBER(D14),ISNUMBER(C14)),IFERROR(D14/C14-1,""),"") | E15: =IF(AND(ISNUMBER(E14),ISNUMBER(D14)),IFERROR(E14/D14-1,""),"") | F15: =IF(AND(ISNUMBER(F14),ISNUMBER(E14)),IFERROR(F14/E14-1,""),"") | G15: =IF(AND(ISNUMBER(G14),ISNUMBER(F14)),IFERROR(G14/F14-1,""),"") | H15: =IF(AND(ISNUMBER(H14),ISNUMBER(G14)),IFERROR(H14/G14-1,""),"") | I15: =IF(AND(ISNUMBER(I14),ISNUMBER(H14)),IFERROR(I14/H14-1,""),"") | N15: =IF(AND(ISNUMBER(N14),ISNUMBER(I14)),IFERROR(N14/I14-1,""),"") | O15: =IF(AND(ISNUMBER(O14),ISNUMBER(J14)),IFERROR(O14/J14-1,""),"") | P15: =IF(AND(ISNUMBER(P14),ISNUMBER(K14)),IFERROR(P14/K14-1,""),"") | Q15: =IF(AND(ISNUMBER(Q14),ISNUMBER(L14)),IFERROR(Q14/L14-1,""),"") | R15: =IF(AND(ISNUMBER(R14),ISNUMBER(M14)),IFERROR(R14/M14-1,""),"") | S15: =IF(AND(ISNUMBER(S14),ISNUMBER(N14)),IFERROR(S14/N14-1,""),"") | T15: =IF(AND(ISNUMBER(T14),ISNUMBER(O14)),IFERROR(T14/O14-1,""),"") | U15: =IF(AND(ISNUMBER(U14),ISNUMBER(P14)),IFERROR(U14/P14-1,""),"") | ... BX15: =IF(AND(ISNUMBER(BX14),ISNUMBER(BS14)),IFERROR(BX14/BS14-1,""),"") -> 0.035567471 | BY15: =BY16+BY114 -> 0.0033070086 | BZ15: =BZ16+BZ114 -> 0.0033070086 | CA15: =IF(AND(ISNUMBER(CA14),ISNUMBER(BV14)),IFERROR(CA14/BV14-1,""),"") -> 0.021666107 | CB15: =CHOOSE(MATCH($CF$2,{"Bull","Base","Bear"},0),$CO$37,$CP$37,$CQ$37) -> 0.05 | CC15: =CHOOSE(MATCH($CF$2,{"Bull","Base","Bear"},0),$CO$38,$CP$38,$CQ$38) -> 0.05 | CD15: =CHOOSE(MATCH($CF$2,{"Bull","Base","Bear"},0),$CO$39,$CP$39,$CQ$39) -> 0.045 | CE15: =CHOOSE(MATCH($CF$2,{"Bull","Base","Bear"},0),$CO$40,$CP$40,$CQ$40) -> 0.04 | CN15: Q3/26E–Q4/26E point estimates (all cases)
B16: Q3/Q4-26E growth before calibration (Q1-26 y/y) | BY16: =IFERROR(BW14/BR14-1,0) -> 0.045544912 | BZ16: =IFERROR(BW14/BR14-1,0) -> 0.045544912 | CN16: Prime Day timing shift on Q3-26 total growth (pp) | CP16: -0.04 | CR16: Guidance: "nearly 400 basis points" (8-K 30-Jul-2026).
B17: Third-party seller services | Z17: 5083 | AA17: 5652 | AB17: 7456 | AD17: 6438 | AE17: 6991 | AF17: 7928 | AG17: 10523 | AH17: 31880 | AI17: 9265 | AJ17: 9702 | AK17: 10395 | AL17: 13383 | AM17: 42745 | AN17: 11141 | AO17: 11962 | AP17: 13212 | AQ17: 17446 | AR17: 53761 | AS17: 14479 | AT17: 18195 | AU17: 20436 | AV17: 27327 | AW17: 80437 | AX17: 23709 | AY17: 25085 | AZ17: 24252 | BA17: 30320 | BB17: 103366 | BC17: 25335 | BD17: 27376 | BE17: 28666 | BF17: 36339 | BG17: 117716 | BH17: 29820 | BI17: 32332 | BJ17: 34342 | BK17: 43559 | BL17: 140053 | BM17: 34596 | BN17: 36201 | BO17: 37864 | BP17: 47485 | BQ17: 156146 | BR17: 36512 | BS17: 40348 | BT17: 42486 | BU17: 52816 | BV17: 172162 | BW17: 41578 | BX17: 46780 | BY17: =BT17*(1+BY18) -> 44186.711 | BZ17: =BU17*(1+BZ18) -> 57913.325 | CA17: =SUM(BW17:BZ17) -> 190458.04 | CB17: =CA17*(1+CB18) -> 211408.42 | CC17: =CB17*(1+CC18) -> 232549.26 | CD17: =CC17*(1+CD18) -> 254641.44 | CE17: =CD17*(1+CE18) -> 277559.17 | CH17: =IFERROR((CE17/BV17)^(1/5)-1,"n/m") -> 0.10023044 | CI17: =IFERROR((BV17/AW17)^(1/5)-1,"n/m") -> 0.16438416 | CJ17: =IFERROR((BV17/X17)^(1/10)-1,"n/m") -> n/m | CK17: =IFERROR((BV17/C17)^(1/19)-1,"n/m") -> n/m | CN17: Gross capex per quarter, Q3/Q4-26E ($m) | CP17: 54208 | CR17: Q2-26 purchases of P&E $54.2bn (Q1 $44.2bn); held at the Q2 run-rate (assumption).
B18: y/y % | D18: =IF(AND(ISNUMBER(D17),ISNUMBER(C17)),IFERROR(D17/C17-1,""),"") | E18: =IF(AND(ISNUMBER(E17),ISNUMBER(D17)),IFERROR(E17/D17-1,""),"") | F18: =IF(AND(ISNUMBER(F17),ISNUMBER(E17)),IFERROR(F17/E17-1,""),"") | G18: =IF(AND(ISNUMBER(G17),ISNUMBER(F17)),IFERROR(G17/F17-1,""),"") | H18: =IF(AND(ISNUMBER(H17),ISNUMBER(G17)),IFERROR(H17/G17-1,""),"") | I18: =IF(AND(ISNUMBER(I17),ISNUMBER(H17)),IFERROR(I17/H17-1,""),"") | N18: =IF(AND(ISNUMBER(N17),ISNUMBER(I17)),IFERROR(N17/I17-1,""),"") | O18: =IF(AND(ISNUMBER(O17),ISNUMBER(J17)),IFERROR(O17/J17-1,""),"") | P18: =IF(AND(ISNUMBER(P17),ISNUMBER(K17)),IFERROR(P17/K17-1,""),"") | Q18: =IF(AND(ISNUMBER(Q17),ISNUMBER(L17)),IFERROR(Q17/L17-1,""),"") | R18: =IF(AND(ISNUMBER(R17),ISNUMBER(M17)),IFERROR(R17/M17-1,""),"") | S18: =IF(AND(ISNUMBER(S17),ISNUMBER(N17)),IFERROR(S17/N17-1,""),"") | T18: =IF(AND(ISNUMBER(T17),ISNUMBER(O17)),IFERROR(T17/O17-1,""),"") | U18: =IF(AND(ISNUMBER(U17),ISNUMBER(P17)),IFERROR(U17/P17-1,""),"") | ... BX18: =IF(AND(ISNUMBER(BX17),ISNUMBER(BS17)),IFERROR(BX17/BS17-1,""),"") -> 0.15941311 | BY18: =BY19+BY32+BY114 -> 0.04002992 | BZ18: =BZ19+BZ32+BZ114 -> 0.096511001 | CA18: =IF(AND(ISNUMBER(CA17),ISNUMBER(BV17)),IFERROR(CA17/BV17-1,""),"") -> 0.10627221 | CB18: =CHOOSE(MATCH($CF$2,{"Bull","Base","Bear"},0),$CO$42,$CP$42,$CQ$42) -> 0.11 | CC18: =CHOOSE(MATCH($CF$2,{"Bull","Base","Bear"},0),$CO$43,$CP$43,$CQ$43) -> 0.1 | CD18: =CHOOSE(MATCH($CF$2,{"Bull","Base","Bear"},0),$CO$44,$CP$44,$CQ$44) -> 0.095 | CE18: =CHOOSE(MATCH($CF$2,{"Bull","Base","Bear"},0),$CO$45,$CP$45,$CQ$45) -> 0.09 | CN18: Proceeds from P&E sales and incentives, % of gross capex | CP18: 0.02 | CR18: 1H-26 2.1%; FY2025 2.7%.
B19: Q3/Q4-26E growth before calibration (Q1-26 y/y) | BY19: =IFERROR(BW17/BR17-1,0) -> 0.1387489 | BZ19: =IFERROR(BW17/BR17-1,0) -> 0.1387489 | CN19: Other operating expense (income), net per quarter ($m) | CP19: 300 | CR19: 1H-26 $537m.
B20: Subscription services | Z20: 1431 | AA20: 1532 | AB20: 2130 | AD20: 1939 | AE20: 2165 | AF20: 2441 | AG20: 3177 | AH20: 9722 | AI20: 3102 | AJ20: 3408 | AK20: 3698 | AL20: 3959 | AM20: 14167 | AN20: 4342 | AO20: 4676 | AP20: 4957 | AQ20: 5235 | AR20: 19210 | AS20: 5556 | AT20: 6018 | AU20: 6572 | AV20: 7061 | AW20: 25207 | AX20: 7580 | AY20: 7917 | AZ20: 8148 | BA20: 8123 | BB20: 31768 | BC20: 8410 | BD20: 8716 | BE20: 8903 | BF20: 9189 | BG20: 35218 | BH20: 9657 | BI20: 9894 | BJ20: 10170 | BK20: 10488 | BL20: 40209 | BM20: 10722 | BN20: 10866 | BO20: 11278 | BP20: 11508 | BQ20: 44374 | BR20: 11715 | BS20: 12208 | BT20: 12574 | BU20: 13122 | BV20: 49619 | BW20: 13427 | BX20: 13730 | BY20: =BT20*(1+BY21) -> 13880.433 | BZ20: =BU20*(1+BZ21) -> 14485.37 | CA20: =SUM(BW20:BZ20) -> 55522.802 | CB20: =CA20*(1+CB21) -> 61630.31 | CC20: =CB20*(1+CC21) -> 67793.342 | CD20: =CC20*(1+CD21) -> 74233.709 | CE20: =CD20*(1+CE21) -> 80914.743 | CH20: =IFERROR((CE20/BV20)^(1/5)-1,"n/m") -> 0.10274711 | CI20: =IFERROR((BV20/AW20)^(1/5)-1,"n/m") -> 0.14505242 | CJ20: =IFERROR((BV20/X20)^(1/10)-1,"n/m") -> n/m | CK20: =IFERROR((BV20/C20)^(1/19)-1,"n/m") -> n/m | CN20: Interest income yield on cash & marketable securities (annual) | CP20: 0.036 | CR20: Q2-26 $1,295m on $143.1bn opening cash and securities (3.6%).
B21: y/y % | D21: =IF(AND(ISNUMBER(D20),ISNUMBER(C20)),IFERROR(D20/C20-1,""),"") | E21: =IF(AND(ISNUMBER(E20),ISNUMBER(D20)),IFERROR(E20/D20-1,""),"") | F21: =IF(AND(ISNUMBER(F20),ISNUMBER(E20)),IFERROR(F20/E20-1,""),"") | G21: =IF(AND(ISNUMBER(G20),ISNUMBER(F20)),IFERROR(G20/F20-1,""),"") | H21: =IF(AND(ISNUMBER(H20),ISNUMBER(G20)),IFERROR(H20/G20-1,""),"") | I21: =IF(AND(ISNUMBER(I20),ISNUMBER(H20)),IFERROR(I20/H20-1,""),"") | N21: =IF(AND(ISNUMBER(N20),ISNUMBER(I20)),IFERROR(N20/I20-1,""),"") | O21: =IF(AND(ISNUMBER(O20),ISNUMBER(J20)),IFERROR(O20/J20-1,""),"") | P21: =IF(AND(ISNUMBER(P20),ISNUMBER(K20)),IFERROR(P20/K20-1,""),"") | Q21: =IF(AND(ISNUMBER(Q20),ISNUMBER(L20)),IFERROR(Q20/L20-1,""),"") | R21: =IF(AND(ISNUMBER(R20),ISNUMBER(M20)),IFERROR(R20/M20-1,""),"") | S21: =IF(AND(ISNUMBER(S20),ISNUMBER(N20)),IFERROR(S20/N20-1,""),"") | T21: =IF(AND(ISNUMBER(T20),ISNUMBER(O20)),IFERROR(T20/O20-1,""),"") | U21: =IF(AND(ISNUMBER(U20),ISNUMBER(P20)),IFERROR(U20/P20-1,""),"") | ... BX21: =IF(AND(ISNUMBER(BX20),ISNUMBER(BS20)),IFERROR(BX20/BS20-1,""),"") -> 0.12467235 | BY21: =BY22+BY114 -> 0.10389953 | BZ21: =BZ22+BZ114 -> 0.10389953 | CA21: =IF(AND(ISNUMBER(CA20),ISNUMBER(BV20)),IFERROR(CA20/BV20-1,""),"") -> 0.11898269 | CB21: =CHOOSE(MATCH($CF$2,{"Bull","Base","Bear"},0),$CO$47,$CP$47,$CQ$47) -> 0.11 | CC21: =CHOOSE(MATCH($CF$2,{"Bull","Base","Bear"},0),$CO$48,$CP$48,$CQ$48) -> 0.1 | CD21: =CHOOSE(MATCH($CF$2,{"Bull","Base","Bear"},0),$CO$49,$CP$49,$CQ$49) -> 0.095 | CE21: =CHOOSE(MATCH($CF$2,{"Bull","Base","Bear"},0),$CO$50,$CP$50,$CQ$50) -> 0.09 | CN21: Q3/26E interest expense ($m) | CP21: 1750 | CR21: Q2-26 $1,314m on $122bn opening debt; + $25.0bn July notes (4.60–6.25%) from 9-Jul (assumption).
B22: Q3/Q4-26E growth before calibration (Q1-26 y/y) | BY22: =IFERROR(BW20/BR20-1,0) -> 0.14613743 | BZ22: =IFERROR(BW20/BR20-1,0) -> 0.14613743 | CN22: Q4/26E interest expense ($m) | CP22: 1950 | CR22: Full quarter of the July notes + £4.25bn September notes (5.20–6.65%) (assumption).
B23: Advertising services | AU23: 4982 | AV23: 7350 | AX23: 6381 | AY23: 7451 | AZ23: 7612 | BA23: 9716 | BB23: 31160 | BC23: 7877 | BD23: 8757 | BE23: 9548 | BF23: 11557 | BG23: 37739 | BH23: 9509 | BI23: 10683 | BJ23: 12060 | BK23: 14654 | BL23: 46906 | BM23: 11824 | BN23: 12771 | BO23: 14331 | BP23: 17288 | BQ23: 56214 | BR23: 13921 | BS23: 15694 | BT23: 17703 | BU23: 21317 | BV23: 68635 | BW23: 17243 | BX23: 19809 | BY23: =BT23*(1+BY24) -> 20179.885 | BZ23: =BU23*(1+BZ24) -> 25503.539 | CA23: =SUM(BW23:BZ23) -> 82735.424 | CB23: =CA23*(1+CB24) -> 98455.155 | CC23: =CB23*(1+CC24) -> 115192.53 | CD23: =CC23*(1+CD24) -> 132471.41 | CE23: =CD23*(1+CE24) -> 149692.69 | CH23: =IFERROR((CE23/BV23)^(1/5)-1,"n/m") -> 0.16877521 | CI23: =IFERROR((BV23/AW23)^(1/5)-1,"n/m") -> n/m | CJ23: =IFERROR((BV23/X23)^(1/10)-1,"n/m") -> n/m | CK23: =IFERROR((BV23/C23)^(1/19)-1,"n/m") -> n/m | CN23: Q3/Q4-26E effective tax rate | CP23: 0.19 | CR23: FY2025 19.6%; FY2024 13.5% (assumption; no investment marks forecast).
B24: y/y % | D24: =IF(AND(ISNUMBER(D23),ISNUMBER(C23)),IFERROR(D23/C23-1,""),"") | E24: =IF(AND(ISNUMBER(E23),ISNUMBER(D23)),IFERROR(E23/D23-1,""),"") | F24: =IF(AND(ISNUMBER(F23),ISNUMBER(E23)),IFERROR(F23/E23-1,""),"") | G24: =IF(AND(ISNUMBER(G23),ISNUMBER(F23)),IFERROR(G23/F23-1,""),"") | H24: =IF(AND(ISNUMBER(H23),ISNUMBER(G23)),IFERROR(H23/G23-1,""),"") | I24: =IF(AND(ISNUMBER(I23),ISNUMBER(H23)),IFERROR(I23/H23-1,""),"") | N24: =IF(AND(ISNUMBER(N23),ISNUMBER(I23)),IFERROR(N23/I23-1,""),"") | O24: =IF(AND(ISNUMBER(O23),ISNUMBER(J23)),IFERROR(O23/J23-1,""),"") | P24: =IF(AND(ISNUMBER(P23),ISNUMBER(K23)),IFERROR(P23/K23-1,""),"") | Q24: =IF(AND(ISNUMBER(Q23),ISNUMBER(L23)),IFERROR(Q23/L23-1,""),"") | R24: =IF(AND(ISNUMBER(R23),ISNUMBER(M23)),IFERROR(R23/M23-1,""),"") | S24: =IF(AND(ISNUMBER(S23),ISNUMBER(N23)),IFERROR(S23/N23-1,""),"") | T24: =IF(AND(ISNUMBER(T23),ISNUMBER(O23)),IFERROR(T23/O23-1,""),"") | U24: =IF(AND(ISNUMBER(U23),ISNUMBER(P23)),IFERROR(U23/P23-1,""),"") | ... BX24: =IF(AND(ISNUMBER(BX23),ISNUMBER(BS23)),IFERROR(BX23/BS23-1,""),"") -> 0.26220212 | BY24: =BY25+BY32+BY114 -> 0.1399133 | BZ24: =BZ25+BZ32+BZ114 -> 0.19639438 | CA24: =IF(AND(ISNUMBER(CA23),ISNUMBER(BV23)),IFERROR(CA23/BV23-1,""),"") -> 0.20544072 | CB24: =CHOOSE(MATCH($CF$2,{"Bull","Base","Bear"},0),$CO$52,$CP$52,$CQ$52) -> 0.19 | CC24: =CHOOSE(MATCH($CF$2,{"Bull","Base","Bear"},0),$CO$53,$CP$53,$CQ$53) -> 0.17 | CD24: =CHOOSE(MATCH($CF$2,{"Bull","Base","Bear"},0),$CO$54,$CP$54,$CQ$54) -> 0.15 | CE24: =CHOOSE(MATCH($CF$2,{"Bull","Base","Bear"},0),$CO$55,$CP$55,$CQ$55) -> 0.13 | CN24: Shares issued under equity plans per quarter (m) | CP24: 30 | CR24: Shares outstanding +52m in 1H-26; +138m in 2025.
B25: Q3/Q4-26E growth before calibration (Q1-26 y/y) | BY25: =IFERROR(BW23/BR23-1,0) -> 0.23863228 | BZ25: =IFERROR(BW23/BR23-1,0) -> 0.23863228 | CN25: 2H-26E deferred income taxes ($m) | CP25: 4000 | CR25: 1H-26 $30.5bn incl. deferred tax on Anthropic gains; underlying ~$2bn a quarter (assumption).
B26: AWS | Z26: 2886 | AA26: 3231 | AB26: 3536 | AD26: 3661 | AE26: 4100 | AF26: 4584 | AG26: 5113 | AH26: 17458 | AI26: 5442 | AJ26: 6105 | AK26: 6679 | AL26: 7430 | AM26: 25656 | AN26: 7696 | AO26: 8381 | AP26: 8995 | AQ26: 9954 | AR26: 35026 | AS26: 10219 | AT26: 10808 | AU26: 11601 | AV26: 12742 | AW26: 45370 | AX26: 13503 | AY26: 14809 | AZ26: 16110 | BA26: 17780 | BB26: 62202 | BC26: 18441 | BD26: 19739 | BE26: 20538 | BF26: 21378 | BG26: 80096 | BH26: 21354 | BI26: 22140 | BJ26: 23059 | BK26: 24204 | BL26: 90757 | BM26: 25037 | BN26: 26281 | BO26: 27452 | BP26: 28786 | BQ26: 107556 | BR26: 29267 | BS26: 30873 | BT26: 33006 | BU26: 35579 | BV26: 128725 | BW26: 37587 | BX26: 42232 | BY26: =BT26*(1+BY27) -> 45149.788 | BZ26: =BU26*(1+BZ27) -> 48669.463 | CA26: =SUM(BW26:BZ26) -> 173638.25 | CB26: =CA26*(1+CB27) -> 222256.96 | CC26: =CB26*(1+CC27) -> 275598.63 | CD26: =CC26*(1+CD27) -> 330718.36 | CE26: =CD26*(1+CE27) -> 386940.48 | CH26: =IFERROR((CE26/BV26)^(1/5)-1,"n/m") -> 0.24622441 | CI26: =IFERROR((BV26/AW26)^(1/5)-1,"n/m") -> 0.23190956 | CJ26: =IFERROR((BV26/X26)^(1/10)-1,"n/m") -> n/m | CK26: =IFERROR((BV26/C26)^(1/19)-1,"n/m") -> n/m | CN26: 2H-26E principal repayments of finance leases & financing obligations ($m) | CP26: -1000 | CR26: 1H-26 −$1,037m.
B27: y/y % | D27: =IF(AND(ISNUMBER(D26),ISNUMBER(C26)),IFERROR(D26/C26-1,""),"") | E27: =IF(AND(ISNUMBER(E26),ISNUMBER(D26)),IFERROR(E26/D26-1,""),"") | F27: =IF(AND(ISNUMBER(F26),ISNUMBER(E26)),IFERROR(F26/E26-1,""),"") | G27: =IF(AND(ISNUMBER(G26),ISNUMBER(F26)),IFERROR(G26/F26-1,""),"") | H27: =IF(AND(ISNUMBER(H26),ISNUMBER(G26)),IFERROR(H26/G26-1,""),"") | I27: =IF(AND(ISNUMBER(I26),ISNUMBER(H26)),IFERROR(I26/H26-1,""),"") | N27: =IF(AND(ISNUMBER(N26),ISNUMBER(I26)),IFERROR(N26/I26-1,""),"") | O27: =IF(AND(ISNUMBER(O26),ISNUMBER(J26)),IFERROR(O26/J26-1,""),"") | P27: =IF(AND(ISNUMBER(P26),ISNUMBER(K26)),IFERROR(P26/K26-1,""),"") | Q27: =IF(AND(ISNUMBER(Q26),ISNUMBER(L26)),IFERROR(Q26/L26-1,""),"") | R27: =IF(AND(ISNUMBER(R26),ISNUMBER(M26)),IFERROR(R26/M26-1,""),"") | S27: =IF(AND(ISNUMBER(S26),ISNUMBER(N26)),IFERROR(S26/N26-1,""),"") | T27: =IF(AND(ISNUMBER(T26),ISNUMBER(O26)),IFERROR(T26/O26-1,""),"") | U27: =IF(AND(ISNUMBER(U26),ISNUMBER(P26)),IFERROR(U26/P26-1,""),"") | ... BX27: =IF(AND(ISNUMBER(BX26),ISNUMBER(BS26)),IFERROR(BX26/BS26-1,""),"") -> 0.36792667 | BY27: =BY28 -> 0.36792667 | BZ27: =BZ28 -> 0.36792667 | CA27: =IF(AND(ISNUMBER(CA26),ISNUMBER(BV26)),IFERROR(CA26/BV26-1,""),"") -> 0.34890853 | CB27: =CHOOSE(MATCH($CF$2,{"Bull","Base","Bear"},0),$CO$57,$CP$57,$CQ$57) -> 0.28 | CC27: =CHOOSE(MATCH($CF$2,{"Bull","Base","Bear"},0),$CO$58,$CP$58,$CQ$58) -> 0.24 | CD27: =CHOOSE(MATCH($CF$2,{"Bull","Base","Bear"},0),$CO$59,$CP$59,$CQ$59) -> 0.2 | CE27: =CHOOSE(MATCH($CF$2,{"Bull","Base","Bear"},0),$CO$60,$CP$60,$CQ$60) -> 0.17 | CF27: Q3/Q4-26E: Q2-26 y/y (+37%, the fastest in 18 quarters; not part of the calibration Δ). 2027E+: scenario lever. | CN27: 2H-26E P&E acquired under finance leases ($m; non-cash) | CP27: 1500 | CR27: 1H-26 $2,128m; FY2025 $2,911m.
B28: Q3/Q4-26E growth (Q2-26 y/y) | BY28: =IFERROR(BX26/BS26-1,0) -> 0.36792667 | BZ28: =IFERROR(BX26/BS26-1,0) -> 0.36792667
B29: Other | Z29: 626 | AA29: 709 | AB29: 1071 | AD29: 850 | AE29: 945 | AF29: 1123 | AG29: 1735 | AH29: 4653 | AI29: 2031 | AJ29: 2194 | AK29: 2495 | AL29: 3388 | AM29: 10108 | AN29: 2716 | AO29: 3002 | AP29: 3586 | AQ29: 4782 | AR29: 14086 | AS29: 3906 | AT29: 4221 | AU29: 416 | AV29: 602 | AW29: 21477 | AX29: 524 | AY29: 463 | AZ29: 479 | BA29: 710 | BB29: 2176 | BC29: 661 | BD29: 1070 | BE29: 1263 | BF29: 1253 | BG29: 4247 | BH29: 1027 | BI29: 1344 | BJ29: 1226 | BK29: 1361 | BL29: 4958 | BM29: 1262 | BN29: 1260 | BO29: 1313 | BP29: 1590 | BQ29: 5425 | BR29: 1312 | BS29: 1499 | BT29: 1415 | BU29: 1709 | BV29: 5935 | BW29: 1645 | BX29: 1829 | BY29: =BT29*(1+BY30) -> 1714.3759 | BZ29: =BU29*(1+BZ30) -> 2070.5784 | CA29: =SUM(BW29:BZ29) -> 7258.9543 | CB29: =CA29*(1+CB30) -> 7839.6706 | CC29: =CB29*(1+CC30) -> 8388.4476 | CD29: =CC29*(1+CD30) -> 8891.7544 | CE29: =CD29*(1+CE30) -> 9425.2597 | CF29: Includes advertising services until Q2-20 (split out from Q3-20 in the Q4-21 release). | CH29: =IFERROR((CE29/BV29)^(1/5)-1,"n/m") -> 0.096918902 | CI29: =IFERROR((BV29/AW29)^(1/5)-1,"n/m") -> -0.22680432 | CJ29: =IFERROR((BV29/X29)^(1/10)-1,"n/m") -> n/m | CK29: =IFERROR((BV29/C29)^(1/19)-1,"n/m") -> n/m | CN29: Target net debt / adjusted EBITDA (x) — buyback floor 2027E+ | CO29: 0.25 | CP29: 0 | CQ29: -0.25 | CR29: Amazon has not repurchased shares since 2022 ($10bn authorization of Mar-2022, $6bn used) and has financed the AI build-out with $66bn of notes in 1H-26. Target = net debt / adjusted EBITDA up to which surplus cash is returned via buybacks (model assumption; no company target): Base 0.0x (free cash flow beyond net-debt neutrality returned), Bull 0.25x, Bear −0.25x (keeps a net-cash cushion). Net debt was −$54bn at YE2025 and +$9bn at 30-Jun-2026.
B30: y/y % | D30: =IF(AND(ISNUMBER(D29),ISNUMBER(C29)),IFERROR(D29/C29-1,""),"") | E30: =IF(AND(ISNUMBER(E29),ISNUMBER(D29)),IFERROR(E29/D29-1,""),"") | F30: =IF(AND(ISNUMBER(F29),ISNUMBER(E29)),IFERROR(F29/E29-1,""),"") | G30: =IF(AND(ISNUMBER(G29),ISNUMBER(F29)),IFERROR(G29/F29-1,""),"") | H30: =IF(AND(ISNUMBER(H29),ISNUMBER(G29)),IFERROR(H29/G29-1,""),"") | I30: =IF(AND(ISNUMBER(I29),ISNUMBER(H29)),IFERROR(I29/H29-1,""),"") | N30: =IF(AND(ISNUMBER(N29),ISNUMBER(I29)),IFERROR(N29/I29-1,""),"") | O30: =IF(AND(ISNUMBER(O29),ISNUMBER(J29)),IFERROR(O29/J29-1,""),"") | P30: =IF(AND(ISNUMBER(P29),ISNUMBER(K29)),IFERROR(P29/K29-1,""),"") | Q30: =IF(AND(ISNUMBER(Q29),ISNUMBER(L29)),IFERROR(Q29/L29-1,""),"") | R30: =IF(AND(ISNUMBER(R29),ISNUMBER(M29)),IFERROR(R29/M29-1,""),"") | S30: =IF(AND(ISNUMBER(S29),ISNUMBER(N29)),IFERROR(S29/N29-1,""),"") | T30: =IF(AND(ISNUMBER(T29),ISNUMBER(O29)),IFERROR(T29/O29-1,""),"") | U30: =IF(AND(ISNUMBER(U29),ISNUMBER(P29)),IFERROR(U29/P29-1,""),"") | ... BX30: =IF(AND(ISNUMBER(BX29),ISNUMBER(BS29)),IFERROR(BX29/BS29-1,""),"") -> 0.22014676 | BY30: =BY31+BY114 -> 0.21157307 | BZ30: =BZ31+BZ114 -> 0.21157307 | CA30: =IF(AND(ISNUMBER(CA29),ISNUMBER(BV29)),IFERROR(CA29/BV29-1,""),"") -> 0.2230757 | CB30: =CHOOSE(MATCH($CF$2,{"Bull","Base","Bear"},0),$CO$62,$CP$62,$CQ$62) -> 0.08 | CC30: =CHOOSE(MATCH($CF$2,{"Bull","Base","Bear"},0),$CO$63,$CP$63,$CQ$63) -> 0.07 | CD30: =CHOOSE(MATCH($CF$2,{"Bull","Base","Bear"},0),$CO$64,$CP$64,$CQ$64) -> 0.06 | CE30: =CHOOSE(MATCH($CF$2,{"Bull","Base","Bear"},0),$CO$65,$CP$65,$CQ$65) -> 0.06
B31: Q3/Q4-26E growth before calibration (Q1-26 y/y) | BY31: =IFERROR(BW29/BR29-1,0) -> 0.25381098 | BZ31: =IFERROR(BW29/BR29-1,0) -> 0.25381098 | CN31: ONLINE (Online stores y/y) | CO31: 0.02 | CP31: Δ → | CQ31: -0.03 | CR31: FY2025 +9.0%; 1H-26 +13.3% (Q1 +11.9%, Q2 incl. Prime Day). Faster delivery, everyday essentials; maturing category.
B32: Prime Day timing shift — pp of growth on online stores, third-party seller services and advertising (Q3/26E) | BY32: =$CP$16*$BT$144/($BT$11+$BT$17+$BT$23) -> -0.056481081 | BZ32: =0 -> 0 | CF32: Guidance (30-Jul-2026): "excluding the impact of Prime Day in both 2025 and 2026, Q3-26 y/y growth would be nearly 400 bp higher" (Prime Day in Q3 in 2025, Q2 in 2026). −4.0 pp of total Q3 net sales allocated to the Prime-Day-sensitive groups pro rata to Q3-25 revenue. | CN32: 2027E | CO32: =CP32+$CO$31 -> 0.105 | CP32: 0.085 | CQ32: =CP32+$CQ$31 -> 0.055
B33: Not split by product group (before Q2-16) | C33: =IF(ISNUMBER(C11),ROUND(C144-(C11+C14+C17+C20+N(C23)+C26+C29),0),C144) -> 10711 | D33: =IF(ISNUMBER(D11),ROUND(D144-(D11+D14+D17+D20+N(D23)+D26+D29),0),D144) -> 14835 | E33: =IF(ISNUMBER(E11),ROUND(E144-(E11+E14+E17+E20+N(E23)+E26+E29),0),E144) -> 19166 | F33: =IF(ISNUMBER(F11),ROUND(F144-(F11+F14+F17+F20+N(F23)+F26+F29),0),F144) -> 24509 | G33: =IF(ISNUMBER(G11),ROUND(G144-(G11+G14+G17+G20+N(G23)+G26+G29),0),G144) -> 34204 | H33: =IF(ISNUMBER(H11),ROUND(H144-(H11+H14+H17+H20+N(H23)+H26+H29),0),H144) -> 48077 | I33: =IF(ISNUMBER(I11),ROUND(I144-(I11+I14+I17+I20+N(I23)+I26+I29),0),I144) -> 61093 | J33: =IF(ISNUMBER(J11),ROUND(J144-(J11+J14+J17+J20+N(J23)+J26+J29),0),J144) -> 16070 | ... BX33: =IF(ISNUMBER(BX11),ROUND(BX144-(BX11+BX14+BX17+BX20+N(BX23)+BX26+BX29),0),BX144) -> 0 | BY33: =0 -> 0 | BZ33: =0 -> 0 | CA33: =SUM(BW33:BZ33) -> 0 | CB33: =0 -> 0 | CC33: =0 -> 0 | CD33: =0 -> 0 | CE33: =0 -> 0 | CN33: 2028E | CO33: =CP33+$CO$31 -> 0.1 | CP33: 0.08 | CQ33: =CP33+$CQ$31 -> 0.05
B34: Net sales (Σ product groups) | C34: =N(C11)+N(C14)+N(C17)+N(C20)+N(C23)+N(C26)+N(C29)+C33 -> 10711 | D34: =N(D11)+N(D14)+N(D17)+N(D20)+N(D23)+N(D26)+N(D29)+D33 -> 14835 | E34: =N(E11)+N(E14)+N(E17)+N(E20)+N(E23)+N(E26)+N(E29)+E33 -> 19166 | F34: =N(F11)+N(F14)+N(F17)+N(F20)+N(F23)+N(F26)+N(F29)+F33 -> 24509 | G34: =N(G11)+N(G14)+N(G17)+N(G20)+N(G23)+N(G26)+N(G29)+G33 -> 34204 | H34: =N(H11)+N(H14)+N(H17)+N(H20)+N(H23)+N(H26)+N(H29)+H33 -> 48077 | I34: =N(I11)+N(I14)+N(I17)+N(I20)+N(I23)+N(I26)+N(I29)+I33 -> 61093 | J34: =N(J11)+N(J14)+N(J17)+N(J20)+N(J23)+N(J26)+N(J29)+J33 -> 16070 | ... BX34: =N(BX11)+N(BX14)+N(BX17)+N(BX20)+N(BX23)+N(BX26)+N(BX29)+BX33 -> 200606 | BY34: =BY11+BY14+BY17+BY20+BY23+BY26+BY29+N(BY96) -> 199500 | BZ34: =BZ11+BZ14+BZ17+BZ20+BZ23+BZ26+BZ29+N(BZ96) -> 243897.47 | CA34: =CA11+CA14+CA17+CA20+CA23+CA26+CA29+N(CA96) -> 825522.47 | CB34: =CB11+CB14+CB17+CB20+CB23+CB26+CB29+N(CB96) -> 943961.71 | CC34: =CC11+CC14+CC17+CC20+CC23+CC26+CC29+N(CC96) -> 1069423.7 | CD34: =CD11+CD14+CD17+CD20+CD23+CD26+CD29+N(CD96) -> 1198711.7 | CE34: =CE11+CE14+CE17+CE20+CE23+CE26+CE29+N(CE96) -> 1330223 | CF34: Σ groups (+ future acquisitions from 2027E). | CN34: 2029E | CO34: =CP34+$CO$31 -> 0.095 | CP34: 0.075 | CQ34: =CP34+$CQ$31 -> 0.045
B35: Check: product groups vs consolidated net sales (should be 0; ±2 rounding) | C35: =IF(ISNUMBER(C11),IF(ABS(C34-C144)<=2.01,0,ROUND(C34-C144,0)),"") | D35: =IF(ISNUMBER(D11),IF(ABS(D34-D144)<=2.01,0,ROUND(D34-D144,0)),"") | E35: =IF(ISNUMBER(E11),IF(ABS(E34-E144)<=2.01,0,ROUND(E34-E144,0)),"") | F35: =IF(ISNUMBER(F11),IF(ABS(F34-F144)<=2.01,0,ROUND(F34-F144,0)),"") | G35: =IF(ISNUMBER(G11),IF(ABS(G34-G144)<=2.01,0,ROUND(G34-G144,0)),"") | H35: =IF(ISNUMBER(H11),IF(ABS(H34-H144)<=2.01,0,ROUND(H34-H144,0)),"") | I35: =IF(ISNUMBER(I11),IF(ABS(I34-I144)<=2.01,0,ROUND(I34-I144,0)),"") | J35: =IF(ISNUMBER(J11),IF(ABS(J34-J144)<=2.01,0,ROUND(J34-J144,0)),"") | ... BX35: =IF(ISNUMBER(BX11),IF(ABS(BX34-BX144)<=2.01,0,ROUND(BX34-BX144,0)),"") -> 0 | CN35: 2030E | CO35: =CP35+$CO$31 -> 0.09 | CP35: 0.07 | CQ35: =CP35+$CQ$31 -> 0.04
B36: Advertising services % of net sales | C36: =IF(AND(ISNUMBER(C23),ISNUMBER(C144)),IFERROR(C23/C144,""),"") | D36: =IF(AND(ISNUMBER(D23),ISNUMBER(D144)),IFERROR(D23/D144,""),"") | E36: =IF(AND(ISNUMBER(E23),ISNUMBER(E144)),IFERROR(E23/E144,""),"") | F36: =IF(AND(ISNUMBER(F23),ISNUMBER(F144)),IFERROR(F23/F144,""),"") | G36: =IF(AND(ISNUMBER(G23),ISNUMBER(G144)),IFERROR(G23/G144,""),"") | H36: =IF(AND(ISNUMBER(H23),ISNUMBER(H144)),IFERROR(H23/H144,""),"") | I36: =IF(AND(ISNUMBER(I23),ISNUMBER(I144)),IFERROR(I23/I144,""),"") | J36: =IF(AND(ISNUMBER(J23),ISNUMBER(J144)),IFERROR(J23/J144,""),"") | ... CE36: =IF(AND(ISNUMBER(CE23),ISNUMBER(CE144)),IFERROR(CE23/CE144,""),"") -> 0.11253203 | CH36: =IFERROR(AVERAGE(CA36,CB36,CC36,CD36,CE36),"n/m") -> 0.10705599 | CI36: =IFERROR(AVERAGE(BB36,BG36,BL36,BQ36,BV36),"n/m") -> 0.081040907 | CJ36: =IFERROR(AVERAGE(AC36,AH36,AM36,AR36,AW36,BB36,BG36,BL36,BQ36,BV36),"n/m") -> 0.081040907 | CK36: =IFERROR(AVERAGE(C36,D36,E36,F36,G36,H36,I36,N36,S36,X36,AC36,AH36,AM36,AR36,AW36,BB36,BG36,BL36,BQ36,BV36),"n/m") -> 0.081040907 | CN36: PHYS (Physical stores y/y) | CO36: 0.02 | CP36: Δ → | CQ36: -0.03 | CR36: FY2025 +6.3%; 1H-26 +4.6% (Whole Foods, Amazon Fresh).
B37: AWS % of net sales | C37: =IF(AND(ISNUMBER(C26),ISNUMBER(C144)),IFERROR(C26/C144,""),"") | D37: =IF(AND(ISNUMBER(D26),ISNUMBER(D144)),IFERROR(D26/D144,""),"") | E37: =IF(AND(ISNUMBER(E26),ISNUMBER(E144)),IFERROR(E26/E144,""),"") | F37: =IF(AND(ISNUMBER(F26),ISNUMBER(F144)),IFERROR(F26/F144,""),"") | G37: =IF(AND(ISNUMBER(G26),ISNUMBER(G144)),IFERROR(G26/G144,""),"") | H37: =IF(AND(ISNUMBER(H26),ISNUMBER(H144)),IFERROR(H26/H144,""),"") | I37: =IF(AND(ISNUMBER(I26),ISNUMBER(I144)),IFERROR(I26/I144,""),"") | J37: =IF(AND(ISNUMBER(J26),ISNUMBER(J144)),IFERROR(J26/J144,""),"") | ... CE37: =IF(AND(ISNUMBER(CE26),ISNUMBER(CE144)),IFERROR(CE26/CE144,""),"") -> 0.29088391 | CH37: =IFERROR(AVERAGE(CA37,CB37,CC37,CD37,CE37),"n/m") -> 0.254055 | CI37: =IFERROR(AVERAGE(BB37,BG37,BL37,BQ37,BV37),"n/m") -> 0.15885436 | CJ37: =IFERROR(AVERAGE(AC37,AH37,AM37,AR37,AW37,BB37,BG37,BL37,BQ37,BV37),"n/m") -> 0.13832987 | CK37: =IFERROR(AVERAGE(C37,D37,E37,F37,G37,H37,I37,N37,S37,X37,AC37,AH37,AM37,AR37,AW37,BB37,BG37,BL37,BQ37,BV37),"n/m") -> 0.13832987 | CN37: 2027E | CO37: =CP37+$CO$36 -> 0.07 | CP37: 0.05 | CQ37: =CP37+$CQ$36 -> 0.02
B38: Third-party seller services + subscriptions + advertising % of net sales | C38: =IF(AND(ISNUMBER(C23),ISNUMBER(C17)),IFERROR((C17+C20+C23)/C144,""),"") | D38: =IF(AND(ISNUMBER(D23),ISNUMBER(D17)),IFERROR((D17+D20+D23)/D144,""),"") | E38: =IF(AND(ISNUMBER(E23),ISNUMBER(E17)),IFERROR((E17+E20+E23)/E144,""),"") | F38: =IF(AND(ISNUMBER(F23),ISNUMBER(F17)),IFERROR((F17+F20+F23)/F144,""),"") | G38: =IF(AND(ISNUMBER(G23),ISNUMBER(G17)),IFERROR((G17+G20+G23)/G144,""),"") | H38: =IF(AND(ISNUMBER(H23),ISNUMBER(H17)),IFERROR((H17+H20+H23)/H144,""),"") | I38: =IF(AND(ISNUMBER(I23),ISNUMBER(I17)),IFERROR((I17+I20+I23)/I144,""),"") | J38: =IF(AND(ISNUMBER(J23),ISNUMBER(J17)),IFERROR((J17+J20+J23)/J144,""),"") | ... CE38: =IF(AND(ISNUMBER(CE23),ISNUMBER(CE17)),IFERROR((CE17+CE20+CE23)/CE144,""),"") -> 0.38201609 | CH38: =IFERROR(AVERAGE(CA38,CB38,CC38,CD38,CE38),"n/m") -> 0.38943681 | CI38: =IFERROR(AVERAGE(BB38,BG38,BL38,BQ38,BV38),"n/m") -> 0.38553229 | CJ38: =IFERROR(AVERAGE(AC38,AH38,AM38,AR38,AW38,BB38,BG38,BL38,BQ38,BV38),"n/m") -> 0.38553229 | CK38: =IFERROR(AVERAGE(C38,D38,E38,F38,G38,H38,I38,N38,S38,X38,AC38,AH38,AM38,AR38,AW38,BB38,BG38,BL38,BQ38,BV38),"n/m") -> 0.38553229 | CN38: 2028E | CO38: =CP38+$CO$36 -> 0.07 | CP38: 0.05 | CQ38: =CP38+$CQ$36 -> 0.02
B39: Memo: worldwide net sales y/y growth excluding F/X, as published | C39: 0.3 | D39: 0.37 | E39: 0.24 | F39: 0.37 | G39: 0.37 | H39: 0.34 | I39: 0.23 | J39: 0.24 | K39: 0.25 | L39: 0.26 | M39: 0.22 | N39: 0.22 | O39: 0.23 | P39: 0.22 | Q39: 0.2 | R39: 0.18 | S39: 0.18 | T39: 0.22 | U39: 0.27 | V39: 0.3 | W39: 0.26 | X39: 0.26 | Y39: 0.29 | Z39: 0.3 | AA39: 0.29 | AB39: 0.24 | AC39: 0.24 | AD39: 0.24 | AE39: 0.26 | AF39: 0.33 | AG39: 0.36 | AH39: 0.36 | AI39: 0.39 | AJ39: 0.37 | AK39: 0.3 | AL39: 0.21 | AM39: 0.21 | AN39: 0.19 | AO39: 0.21 | AP39: 0.25 | AQ39: 0.21 | AR39: 0.21 | AS39: 0.27 | AT39: 0.41 | AU39: 0.36 | AV39: 0.42 | AW39: 0.42 | AX39: 0.41 | AY39: 0.24 | AZ39: 0.15 | BA39: 0.1 | BB39: 0.1 | BC39: 0.09 | BD39: 0.1 | BE39: 0.19 | BF39: 0.12 | BG39: 0.12 | BH39: 0.11 | BI39: 0.11 | BJ39: 0.11 | BK39: 0.13 | BL39: 0.13 | BM39: 0.13 | BN39: 0.11 | BO39: 0.11 | BP39: 0.11 | BQ39: 0.11 | BR39: 0.1 | BS39: 0.12 | BT39: 0.12 | BU39: 0.12 | BV39: 0.12 | BW39: 0.15 | BX39: 0.2 | CN39: 2029E | CO39: =CP39+$CO$36 -> 0.065 | CP39: 0.045 | CQ39: =CP39+$CQ$36 -> 0.015
CN40: 2030E | CO40: =CP40+$CO$36 -> 0.06 | CP40: 0.04 | CQ40: =CP40+$CQ$36 -> 0.01
B41: Segments — North America · International · AWS (segment operating income as reported; AWS a segment from Q1-15, recast FY2013–14) | CF41: SEGMENTS — modelling logic: NA + International = retail product groups; NA share driver; AWS = AWS group; segment OI = net sales × margin | CN41: TP (Third-party seller services y/y) | CO41: 0.02 | CP41: Δ → | CQ41: -0.03 | CR41: FY2025 +10.3%; 1H-26 +16.3% (fulfilment fees, mix shift to 3P).
B42: North America + International net sales (= retail product groups) | C42: =IF(ISNUMBER(C44),C44+C50,"") | D42: =IF(ISNUMBER(D44),D44+D50,"") | E42: =IF(ISNUMBER(E44),E44+E50,"") | F42: =IF(ISNUMBER(F44),F44+F50,"") | G42: =IF(ISNUMBER(G44),G44+G50,"") | H42: =IF(ISNUMBER(H44),H44+H50,"") | I42: =IF(ISNUMBER(I44),I44+I50,"") | J42: =IF(ISNUMBER(J44),J44+J50,"") | ... BX42: =IF(ISNUMBER(BX44),BX44+BX50,"") -> 158374 | BY42: =BY11+BY14+BY17+BY20+BY23+BY29 -> 154350.21 | BZ42: =BZ11+BZ14+BZ17+BZ20+BZ23+BZ29 -> 195228.01 | CA42: =SUM(BW42:BZ42) -> 651884.22 | CB42: =CB11+CB14+CB17+CB20+CB23+CB29 -> 721288.08 | CC42: =CC11+CC14+CC17+CC20+CC23+CC29 -> 792508.4 | CD42: =CD11+CD14+CD17+CD20+CD23+CD29 -> 865704.63 | CE42: =CE11+CE14+CE17+CE20+CE23+CE29 -> 939944.14 | CN42: 2027E | CO42: =CP42+$CO$41 -> 0.13 | CP42: 0.11 | CQ42: =CP42+$CQ$41 -> 0.08
B43: North America share of NA + International net sales | C43: =IF(AND(ISNUMBER(C44),ISNUMBER(C42)),IFERROR(C44/C42,""),"") | D43: =IF(AND(ISNUMBER(D44),ISNUMBER(D42)),IFERROR(D44/D42,""),"") | E43: =IF(AND(ISNUMBER(E44),ISNUMBER(E42)),IFERROR(E44/E42,""),"") | F43: =IF(AND(ISNUMBER(F44),ISNUMBER(F42)),IFERROR(F44/F42,""),"") | G43: =IF(AND(ISNUMBER(G44),ISNUMBER(G42)),IFERROR(G44/G42,""),"") | H43: =IF(AND(ISNUMBER(H44),ISNUMBER(H42)),IFERROR(H44/H42,""),"") | I43: =IF(AND(ISNUMBER(I44),ISNUMBER(I42)),IFERROR(I44/I42,""),"") | J43: =IF(AND(ISNUMBER(J44),ISNUMBER(J42)),IFERROR(J44/J42,""),"") | ... BX43: =IF(AND(ISNUMBER(BX44),ISNUMBER(BX42)),IFERROR(BX44/BX42,""),"") -> 0.73356106 | BY43: =BT43+IFERROR(SUM(BW44:BX44)/SUM(BW42:BX42)-SUM(BR44:BS44)/SUM(BR42:BS42),0) -> 0.7178711 | BZ43: =BU43+IFERROR(SUM(BW44:BX44)/SUM(BW42:BX42)-SUM(BR44:BS44)/SUM(BR42:BS42),0) -> 0.71049143 | CA43: =IF(AND(ISNUMBER(CA44),ISNUMBER(CA42)),IFERROR(CA44/CA42,""),"") -> 0.72072827 | CB43: =CA43 -> 0.72072827 | CC43: =CB43 -> 0.72072827 | CD43: =CC43 -> 0.72072827 | CE43: =CD43 -> 0.72072827 | CF43: Q3/Q4-26E: prior-year quarter share + 1H-26 y/y drift. 2027E+: held at the prior-year share. | CH43: =IFERROR(AVERAGE(CA43,CB43,CC43,CD43,CE43),"n/m") -> 0.72072827 | CI43: =IFERROR(AVERAGE(BB43,BG43,BL43,BQ43,BV43),"n/m") -> 0.71976073 | CJ43: =IFERROR(AVERAGE(AC43,AH43,AM43,AR43,AW43,BB43,BG43,BL43,BQ43,BV43),"n/m") -> 0.69762608 | CK43: =IFERROR(AVERAGE(C43,D43,E43,F43,G43,H43,I43,N43,S43,X43,AC43,AH43,AM43,AR43,AW43,BB43,BG43,BL43,BQ43,BV43),"n/m") -> 0.67708336 | CN43: 2028E | CO43: =CP43+$CO$41 -> 0.12 | CP43: 0.1 | CQ43: =CP43+$CQ$41 -> 0.07
B44: North America — segment net sales | N44: 41410 | O44: 10808 | P44: 10994 | Q44: 11699 | R44: 17333 | S44: 50834 | T44: 13406 | U44: 13796 | V44: 15006 | W44: 21501 | X44: 63708 | Y44: 16996 | Z44: 17674 | AA44: 18874 | AB44: 26240 | AC44: 79785 | AD44: 20992 | AE44: 22370 | AF44: 25446 | AG44: 37302 | AH44: 106110 | AI44: 30725 | AJ44: 32169 | AK44: 34348 | AL44: 44124 | AM44: 141366 | AN44: 35812 | AO44: 38653 | AP44: 42638 | AQ44: 53670 | AR44: 170773 | AS44: 46127 | AT44: 55436 | AU44: 59373 | AV44: 75346 | AW44: 236282 | AX44: 64366 | AY44: 67550 | AZ44: 65557 | BA44: 82360 | BB44: 279833 | BC44: 69244 | BD44: 74430 | BE44: 78843 | BF44: 93363 | BG44: 315880 | BH44: 76881 | BI44: 82546 | BJ44: 87887 | BK44: 105514 | BL44: 352828 | BM44: 86341 | BN44: 90033 | BO44: 95537 | BP44: 115586 | BQ44: 387497 | BR44: 92887 | BS44: 100068 | BT44: 106267 | BU44: 127083 | BV44: 426305 | BW44: 104143 | BX44: 116177 | BY44: =BY42*BY43 -> 110803.56 | BZ44: =BZ42*BZ43 -> 138707.83 | CA44: =SUM(BW44:BZ44) -> 469831.39 | CB44: =CB42*CB43 -> 519852.71 | CC44: =CC42*CC43 -> 571183.21 | CD44: =CD42*CD43 -> 623937.79 | CE44: =CE42*CE43 -> 677444.31 | CF44: U.S. / Canada consumer-facing sales (incl. Whole Foods from Aug-2017). Forecast = retail groups × NA share. | CH44: =IFERROR((CE44/BV44)^(1/5)-1,"n/m") -> 0.097060642 | CI44: =IFERROR((BV44/AW44)^(1/5)-1,"n/m") -> 0.12527315 | CJ44: =IFERROR((BV44/X44)^(1/10)-1,"n/m") -> 0.20935177 | CK44: =IFERROR((BV44/C44)^(1/19)-1,"n/m") -> n/m | CN44: 2029E | CO44: =CP44+$CO$41 -> 0.115 | CP44: 0.095 | CQ44: =CP44+$CQ$41 -> 0.065
B45: y/y % | D45: =IF(AND(ISNUMBER(D44),ISNUMBER(C44)),IFERROR(D44/C44-1,""),"") | E45: =IF(AND(ISNUMBER(E44),ISNUMBER(D44)),IFERROR(E44/D44-1,""),"") | F45: =IF(AND(ISNUMBER(F44),ISNUMBER(E44)),IFERROR(F44/E44-1,""),"") | G45: =IF(AND(ISNUMBER(G44),ISNUMBER(F44)),IFERROR(G44/F44-1,""),"") | H45: =IF(AND(ISNUMBER(H44),ISNUMBER(G44)),IFERROR(H44/G44-1,""),"") | I45: =IF(AND(ISNUMBER(I44),ISNUMBER(H44)),IFERROR(I44/H44-1,""),"") | N45: =IF(AND(ISNUMBER(N44),ISNUMBER(I44)),IFERROR(N44/I44-1,""),"") | O45: =IF(AND(ISNUMBER(O44),ISNUMBER(J44)),IFERROR(O44/J44-1,""),"") | P45: =IF(AND(ISNUMBER(P44),ISNUMBER(K44)),IFERROR(P44/K44-1,""),"") | Q45: =IF(AND(ISNUMBER(Q44),ISNUMBER(L44)),IFERROR(Q44/L44-1,""),"") | R45: =IF(AND(ISNUMBER(R44),ISNUMBER(M44)),IFERROR(R44/M44-1,""),"") | S45: =IF(AND(ISNUMBER(S44),ISNUMBER(N44)),IFERROR(S44/N44-1,""),"") -> 0.22757788 | T45: =IF(AND(ISNUMBER(T44),ISNUMBER(O44)),IFERROR(T44/O44-1,""),"") -> 0.2403775 | U45: =IF(AND(ISNUMBER(U44),ISNUMBER(P44)),IFERROR(U44/P44-1,""),"") -> 0.25486629 | ... CA45: =IF(AND(ISNUMBER(CA44),ISNUMBER(BV44)),IFERROR(CA44/BV44-1,""),"") -> 0.10210151 | CB45: =IF(AND(ISNUMBER(CB44),ISNUMBER(CA44)),IFERROR(CB44/CA44-1,""),"") -> 0.10646655 | CC45: =IF(AND(ISNUMBER(CC44),ISNUMBER(CB44)),IFERROR(CC44/CB44-1,""),"") -> 0.098740463 | CD45: =IF(AND(ISNUMBER(CD44),ISNUMBER(CC44)),IFERROR(CD44/CC44-1,""),"") -> 0.092360185 | CE45: =IF(AND(ISNUMBER(CE44),ISNUMBER(CD44)),IFERROR(CE44/CD44-1,""),"") -> 0.085756172 | CN45: 2030E | CO45: =CP45+$CO$41 -> 0.11 | CP45: 0.09 | CQ45: =CP45+$CQ$41 -> 0.06
B46: North America — segment operating income | N46: 1166 | O46: 290 | P46: 329 | Q46: -60 | R46: 733 | S46: 1292 | T46: 254 | U46: 348 | V46: 186 | W46: 636 | X46: 1425 | Y46: 588 | Z46: 702 | AA46: 255 | AB46: 816 | AC46: 2361 | AD46: 596 | AE46: 436 | AF46: 112 | AG46: 1692 | AH46: 2837 | AI46: 1149 | AJ46: 1835 | AK46: 2032 | AL46: 2251 | AM46: 7267 | AN46: 2287 | AO46: 1564 | AP46: 1282 | AQ46: 1900 | AR46: 7033 | AS46: 1312 | AT46: 2141 | AU46: 2252 | AV46: 2946 | AW46: 8651 | AX46: 3450 | AY46: 3147 | AZ46: 880 | BA46: -206 | BB46: 7271 | BC46: -1568 | BD46: -627 | BE46: -412 | BF46: -240 | BG46: -2847 | BH46: 898 | BI46: 3211 | BJ46: 4307 | BK46: 6461 | BL46: 14877 | BM46: 4983 | BN46: 5065 | BO46: 5663 | BP46: 9256 | BQ46: 24967 | BR46: 5841 | BS46: 7517 | BT46: 4789 | BU46: 11472 | BV46: 29619 | BW46: 8267 | BX46: 9123 | BY46: =BY44*BY47 -> 7386.3106 | BZ46: =BZ44*BZ47 -> 12453.98 | CA46: =SUM(BW46:BZ46) -> 37230.291 | CB46: =CB44*CB47 -> 44187.48 | CC46: =CC44*CC47 -> 51406.489 | CD46: =CD44*CD47 -> 59274.09 | CE46: =CE44*CE47 -> 67744.431 | CF46: Segment operating income as reported (from 2016 after allocated stock-based compensation; 2015 restated on that basis in the 2016 releases; FY2013–14 before SBC). Forecast = segment net sales × margin (excludes special charges, forecast nil). | CH46: =IFERROR((CE46/BV46)^(1/5)-1,"n/m") -> 0.17994195 | CI46: =IFERROR((BV46/AW46)^(1/5)-1,"n/m") -> 0.27908915 | CJ46: =IFERROR((BV46/X46)^(1/10)-1,"n/m") -> 0.35448922 | CK46: =IFERROR((BV46/C46)^(1/19)-1,"n/m") -> n/m | CN46: SUBS (Subscription services y/y) | CO46: 0.02 | CP46: Δ → | CQ46: -0.03 | CR46: FY2025 +11.8%; 1H-26 +14.6% (Prime, video, music).
B47: Segment operating margin % | C47: =IF(AND(ISNUMBER(C46),ISNUMBER(C44)),IFERROR(C46/C44,""),"") | D47: =IF(AND(ISNUMBER(D46),ISNUMBER(D44)),IFERROR(D46/D44,""),"") | E47: =IF(AND(ISNUMBER(E46),ISNUMBER(E44)),IFERROR(E46/E44,""),"") | F47: =IF(AND(ISNUMBER(F46),ISNUMBER(F44)),IFERROR(F46/F44,""),"") | G47: =IF(AND(ISNUMBER(G46),ISNUMBER(G44)),IFERROR(G46/G44,""),"") | H47: =IF(AND(ISNUMBER(H46),ISNUMBER(H44)),IFERROR(H46/H44,""),"") | I47: =IF(AND(ISNUMBER(I46),ISNUMBER(I44)),IFERROR(I46/I44,""),"") | J47: =IF(AND(ISNUMBER(J46),ISNUMBER(J44)),IFERROR(J46/J44,""),"") | ... BX47: =IF(AND(ISNUMBER(BX46),ISNUMBER(BX44)),IFERROR(BX46/BX44,""),"") -> 0.078526731 | BY47: =BY48+BY120 -> 0.066661313 | BZ47: =BZ48+BZ120 -> 0.089785704 | CA47: =IF(AND(ISNUMBER(CA46),ISNUMBER(CA44)),IFERROR(CA46/CA44,""),"") -> 0.079241813 | CB47: =CHOOSE(MATCH($CF$2,{"Bull","Base","Bear"},0),$CO$67,$CP$67,$CQ$67) -> 0.085 | CC47: =CHOOSE(MATCH($CF$2,{"Bull","Base","Bear"},0),$CO$68,$CP$68,$CQ$68) -> 0.09 | CD47: =CHOOSE(MATCH($CF$2,{"Bull","Base","Bear"},0),$CO$69,$CP$69,$CQ$69) -> 0.095 | CE47: =CHOOSE(MATCH($CF$2,{"Bull","Base","Bear"},0),$CO$70,$CP$70,$CQ$70) -> 0.1 | CF47: Q3/Q4-26E: margin before calibration + operating-income guidance calibration Δ (uniform). 2027E+: scenario lever. | CH47: =IFERROR(AVERAGE(CA47,CB47,CC47,CD47,CE47),"n/m") -> 0.089848363 | CI47: =IFERROR(AVERAGE(BB47,BG47,BL47,BQ47,BV47),"n/m") -> 0.03860907 | CJ47: =IFERROR(AVERAGE(AC47,AH47,AM47,AR47,AW47,BB47,BG47,BL47,BQ47,BV47),"n/m") -> 0.037857571 | CK47: =IFERROR(AVERAGE(C47,D47,E47,F47,G47,H47,I47,N47,S47,X47,AC47,AH47,AM47,AR47,AW47,BB47,BG47,BL47,BQ47,BV47),"n/m") -> 0.034962838 | CN47: 2027E | CO47: =CP47+$CO$46 -> 0.13 | CP47: 0.11 | CQ47: =CP47+$CQ$46 -> 0.08
B48: Q3/Q4-26E margin before calibration (prior-year quarter ex disclosed special charges + 1H-26 y/y drift) | BY48: =(BT46+BT62)/BT44+IFERROR(SUM(BW46:BX46)/SUM(BW44:BX44)-SUM(BR46:BS46)/SUM(BR44:BS44),0) -> 0.078293448 | BZ48: =(BU46+BU62)/BU44+IFERROR(SUM(BW46:BX46)/SUM(BW44:BX44)-SUM(BR46:BS46)/SUM(BR44:BS44),0) -> 0.099973782 | CN48: 2028E | CO48: =CP48+$CO$46 -> 0.12 | CP48: 0.1 | CQ48: =CP48+$CQ$46 -> 0.07
B49: Incremental segment margin (Δ OI / Δ net sales) | D49: =IFERROR((D46-C46)/(D44-C44),"") | E49: =IFERROR((E46-D46)/(E44-D44),"") | F49: =IFERROR((F46-E46)/(F44-E44),"") | G49: =IFERROR((G46-F46)/(G44-F44),"") | H49: =IFERROR((H46-G46)/(H44-G44),"") | I49: =IFERROR((I46-H46)/(I44-H44),"") | N49: =IFERROR((N46-I46)/(N44-I44),"") -> 0.02815745 | O49: =IFERROR((O46-J46)/(O44-J44),"") -> 0.026831976 | P49: =IFERROR((P46-K46)/(P44-K44),"") -> 0.029925414 | Q49: =IFERROR((Q46-L46)/(Q44-L44),"") -> -0.0051286435 | R49: =IFERROR((R46-M46)/(R44-M44),"") -> 0.042289275 | S49: =IFERROR((S46-N46)/(S44-N44),"") -> 0.013370119 | T49: =IFERROR((T46-O46)/(T44-O44),"") -> -0.013856813 | U49: =IFERROR((U46-P46)/(U44-P44),"") -> 0.0067808708 | ... CA49: =IFERROR((CA46-BV46)/(CA44-BV44),"") -> 0.17486613 | CB49: =IFERROR((CB46-CA46)/(CB44-CA44),"") -> 0.13908448 | CC49: =IFERROR((CC46-CB46)/(CC44-CB44),"") -> 0.1406378 | CD49: =IFERROR((CD46-CC46)/(CD44-CC44),"") -> 0.14913588 | CE49: =IFERROR((CE46-CD46)/(CE44-CD44),"") -> 0.15830484 | CN49: 2029E | CO49: =CP49+$CO$46 -> 0.115 | CP49: 0.095 | CQ49: =CP49+$CQ$46 -> 0.065
B50: International — segment net sales | N50: 29934 | O50: 7883 | P50: 7341 | Q50: 7711 | R50: 10575 | S50: 33510 | T50: 7745 | U50: 7565 | V50: 8267 | W50: 11841 | X50: 35418 | Y50: 9566 | Z50: 9844 | AA50: 10609 | AB50: 13965 | AC50: 43983 | AD50: 11061 | AE50: 11485 | AF50: 13714 | AG50: 18038 | AH50: 54297 | AI50: 14875 | AJ50: 14612 | AK50: 15549 | AL50: 20829 | AM50: 65866 | AN50: 16192 | AO50: 16370 | AP50: 18348 | AQ50: 23813 | AR50: 74723 | AS50: 19106 | AT50: 22668 | AU50: 25171 | AV50: 37467 | AW50: 104412 | AX50: 30649 | AY50: 30721 | AZ50: 29145 | BA50: 37272 | BB50: 127787 | BC50: 28759 | BD50: 27065 | BE50: 27720 | BF50: 34463 | BG50: 118007 | BH50: 29123 | BI50: 29697 | BJ50: 32137 | BK50: 40243 | BL50: 131200 | BM50: 31935 | BN50: 31663 | BO50: 35888 | BP50: 43420 | BQ50: 142906 | BR50: 33513 | BS50: 36761 | BT50: 40896 | BU50: 50724 | BV50: 161894 | BW50: 39789 | BX50: 42197 | BY50: =BY42-BY44 -> 43546.656 | BZ50: =BZ42-BZ44 -> 56520.182 | CA50: =SUM(BW50:BZ50) -> 182052.84 | CB50: =CB42-CB44 -> 201435.37 | CC50: =CC42-CC44 -> 221325.2 | CD50: =CD42-CD44 -> 241766.83 | CE50: =CE42-CE44 -> 262499.83 | CF50: Consumer-facing sales outside North America (UK, Germany, Japan, …). Forecast = retail groups − North America. | CH50: =IFERROR((CE50/BV50)^(1/5)-1,"n/m") -> 0.10148771 | CI50: =IFERROR((BV50/AW50)^(1/5)-1,"n/m") -> 0.091681794 | CJ50: =IFERROR((BV50/X50)^(1/10)-1,"n/m") -> 0.16412783 | CK50: =IFERROR((BV50/C50)^(1/19)-1,"n/m") -> n/m | CN50: 2030E | CO50: =CP50+$CO$46 -> 0.11 | CP50: 0.09 | CQ50: =CP50+$CQ$46 -> 0.06
B51: y/y % | D51: =IF(AND(ISNUMBER(D50),ISNUMBER(C50)),IFERROR(D50/C50-1,""),"") | E51: =IF(AND(ISNUMBER(E50),ISNUMBER(D50)),IFERROR(E50/D50-1,""),"") | F51: =IF(AND(ISNUMBER(F50),ISNUMBER(E50)),IFERROR(F50/E50-1,""),"") | G51: =IF(AND(ISNUMBER(G50),ISNUMBER(F50)),IFERROR(G50/F50-1,""),"") | H51: =IF(AND(ISNUMBER(H50),ISNUMBER(G50)),IFERROR(H50/G50-1,""),"") | I51: =IF(AND(ISNUMBER(I50),ISNUMBER(H50)),IFERROR(I50/H50-1,""),"") | N51: =IF(AND(ISNUMBER(N50),ISNUMBER(I50)),IFERROR(N50/I50-1,""),"") | O51: =IF(AND(ISNUMBER(O50),ISNUMBER(J50)),IFERROR(O50/J50-1,""),"") | P51: =IF(AND(ISNUMBER(P50),ISNUMBER(K50)),IFERROR(P50/K50-1,""),"") | Q51: =IF(AND(ISNUMBER(Q50),ISNUMBER(L50)),IFERROR(Q50/L50-1,""),"") | R51: =IF(AND(ISNUMBER(R50),ISNUMBER(M50)),IFERROR(R50/M50-1,""),"") | S51: =IF(AND(ISNUMBER(S50),ISNUMBER(N50)),IFERROR(S50/N50-1,""),"") -> 0.11946282 | T51: =IF(AND(ISNUMBER(T50),ISNUMBER(O50)),IFERROR(T50/O50-1,""),"") -> -0.017506026 | U51: =IF(AND(ISNUMBER(U50),ISNUMBER(P50)),IFERROR(U50/P50-1,""),"") -> 0.030513554 | ... CA51: =IF(AND(ISNUMBER(CA50),ISNUMBER(BV50)),IFERROR(CA50/BV50-1,""),"") -> 0.12451875 | CB51: =IF(AND(ISNUMBER(CB50),ISNUMBER(CA50)),IFERROR(CB50/CA50-1,""),"") -> 0.10646655 | CC51: =IF(AND(ISNUMBER(CC50),ISNUMBER(CB50)),IFERROR(CC50/CB50-1,""),"") -> 0.098740463 | CD51: =IF(AND(ISNUMBER(CD50),ISNUMBER(CC50)),IFERROR(CD50/CC50-1,""),"") -> 0.092360185 | CE51: =IF(AND(ISNUMBER(CE50),ISNUMBER(CD50)),IFERROR(CE50/CD50-1,""),"") -> 0.085756172 | CN51: ADS (Advertising services y/y) | CO51: 0.03 | CP51: Δ → | CQ51: -0.05 | CR51: FY2025 +22.1%; Q2-26 +26%; Prime Video ads, sponsored products.
B52: International — segment operating income | N52: 154 | O52: -33 | P52: -2 | Q52: -174 | R52: 65 | S52: -144 | T52: -194 | U52: -189 | V52: -208 | W52: -108 | X52: -699 | Y52: -121 | Z52: -135 | AA52: -541 | AB52: -487 | AC52: -1283 | AD52: -481 | AE52: -724 | AF52: -936 | AG52: -919 | AH52: -3062 | AI52: -622 | AJ52: -494 | AK52: -385 | AL52: -642 | AM52: -2142 | AN52: -90 | AO52: -601 | AP52: -386 | AQ52: -617 | AR52: -1693 | AS52: -398 | AT52: 345 | AU52: 407 | AV52: 363 | AW52: 717 | AX52: 1252 | AY52: 362 | AZ52: -911 | BA52: -1627 | BB52: -924 | BC52: -1281 | BD52: -1771 | BE52: -2466 | BF52: -2228 | BG52: -7746 | BH52: -1247 | BI52: -895 | BJ52: -95 | BK52: -419 | BL52: -2656 | BM52: 903 | BN52: 273 | BO52: 1301 | BP52: 1315 | BQ52: 3792 | BR52: 1017 | BS52: 1494 | BT52: 1199 | BU52: 1040 | BV52: 4750 | BW52: 1424 | BX52: 1717 | BY52: =BY50*BY53 -> 882.51608 | BZ52: =BZ50*BZ53 -> 728.82159 | CA52: =SUM(BW52:BZ52) -> 4752.3377 | CB52: =CB50*CB53 -> 9064.5919 | CC52: =CC50*CC53 -> 11066.26 | CD52: =CD50*CD53 -> 13297.176 | CE52: =CE50*CE53 -> 15749.99 | CH52: =IFERROR((CE52/BV52)^(1/5)-1,"n/m") -> 0.27091742 | CI52: =IFERROR((BV52/AW52)^(1/5)-1,"n/m") -> 0.45960348 | CJ52: =IFERROR((BV52/X52)^(1/10)-1,"n/m") -> n/m | CK52: =IFERROR((BV52/C52)^(1/19)-1,"n/m") -> n/m | CN52: 2027E | CO52: =CP52+$CO$51 -> 0.22 | CP52: 0.19 | CQ52: =CP52+$CQ$51 -> 0.14
B53: Segment operating margin % | C53: =IF(AND(ISNUMBER(C52),ISNUMBER(C50)),IFERROR(C52/C50,""),"") | D53: =IF(AND(ISNUMBER(D52),ISNUMBER(D50)),IFERROR(D52/D50,""),"") | E53: =IF(AND(ISNUMBER(E52),ISNUMBER(E50)),IFERROR(E52/E50,""),"") | F53: =IF(AND(ISNUMBER(F52),ISNUMBER(F50)),IFERROR(F52/F50,""),"") | G53: =IF(AND(ISNUMBER(G52),ISNUMBER(G50)),IFERROR(G52/G50,""),"") | H53: =IF(AND(ISNUMBER(H52),ISNUMBER(H50)),IFERROR(H52/H50,""),"") | I53: =IF(AND(ISNUMBER(I52),ISNUMBER(I50)),IFERROR(I52/I50,""),"") | J53: =IF(AND(ISNUMBER(J52),ISNUMBER(J50)),IFERROR(J52/J50,""),"") | ... BX53: =IF(AND(ISNUMBER(BX52),ISNUMBER(BX50)),IFERROR(BX52/BX50,""),"") -> 0.040690096 | BY53: =BY54+BY120 -> 0.02026599 | BZ53: =BZ54+BZ120 -> 0.012894891 | CA53: =IF(AND(ISNUMBER(CA52),ISNUMBER(CA50)),IFERROR(CA52/CA50,""),"") -> 0.026104167 | CB53: =CHOOSE(MATCH($CF$2,{"Bull","Base","Bear"},0),$CO$72,$CP$72,$CQ$72) -> 0.045 | CC53: =CHOOSE(MATCH($CF$2,{"Bull","Base","Bear"},0),$CO$73,$CP$73,$CQ$73) -> 0.05 | CD53: =CHOOSE(MATCH($CF$2,{"Bull","Base","Bear"},0),$CO$74,$CP$74,$CQ$74) -> 0.055 | CE53: =CHOOSE(MATCH($CF$2,{"Bull","Base","Bear"},0),$CO$75,$CP$75,$CQ$75) -> 0.06 | CH53: =IFERROR(AVERAGE(CA53,CB53,CC53,CD53,CE53),"n/m") -> 0.047220833 | CI53: =IFERROR(AVERAGE(BB53,BG53,BL53,BQ53,BV53),"n/m") -> -0.0074479496 | CJ53: =IFERROR(AVERAGE(AC53,AH53,AM53,AR53,AW53,BB53,BG53,BL53,BQ53,BV53),"n/m") -> -0.017111421 | CK53: =IFERROR(AVERAGE(C53,D53,E53,F53,G53,H53,I53,N53,S53,X53,AC53,AH53,AM53,AR53,AW53,BB53,BG53,BL53,BQ53,BV53),"n/m") -> -0.014615578 | CN53: 2028E | CO53: =CP53+$CO$51 -> 0.2 | CP53: 0.17 | CQ53: =CP53+$CQ$51 -> 0.12
B54: Q3/Q4-26E margin before calibration (prior-year quarter ex disclosed special charges + 1H-26 y/y drift) | BY54: =(BT52)/BT50+IFERROR(SUM(BW52:BX52)/SUM(BW50:BX50)-SUM(BR52:BS52)/SUM(BR50:BS50),0) -> 0.031898125 | BZ54: =(BU52)/BU50+IFERROR(SUM(BW52:BX52)/SUM(BW50:BX50)-SUM(BR52:BS52)/SUM(BR50:BS50),0) -> 0.023082969 | CN54: 2029E | CO54: =CP54+$CO$51 -> 0.18 | CP54: 0.15 | CQ54: =CP54+$CQ$51 -> 0.1
B55: Incremental segment margin (Δ OI / Δ net sales) | D55: =IFERROR((D52-C52)/(D50-C50),"") | E55: =IFERROR((E52-D52)/(E50-D50),"") | F55: =IFERROR((F52-E52)/(F50-E50),"") | G55: =IFERROR((G52-F52)/(G50-F50),"") | H55: =IFERROR((H52-G52)/(H50-G50),"") | I55: =IFERROR((I52-H52)/(I50-H50),"") | N55: =IFERROR((N52-I52)/(N50-I50),"") -> 0.0051446516 | O55: =IFERROR((O52-J52)/(O50-J50),"") -> -0.0041862235 | P55: =IFERROR((P52-K52)/(P50-K50),"") -> -0.00027244245 | Q55: =IFERROR((Q52-L52)/(Q50-L50),"") -> -0.022565167 | R55: =IFERROR((R52-M52)/(R50-M50),"") -> 0.0061465721 | S55: =IFERROR((S52-N52)/(S50-N50),"") -> -0.083333333 | T55: =IFERROR((T52-O52)/(T50-O50),"") -> 1.1666667 | U55: =IFERROR((U52-P52)/(U50-P50),"") -> -0.83482143 | ... CA55: =IFERROR((CA52-BV52)/(CA50-BV50),"") -> 0.00011596225 | CB55: =IFERROR((CB52-CA52)/(CB50-CA50),"") -> 0.22248141 | CC55: =IFERROR((CC52-CB52)/(CC50-CB50),"") -> 0.1006378 | CD55: =IFERROR((CD52-CC52)/(CD50-CC50),"") -> 0.10913588 | CE55: =IFERROR((CE52-CD52)/(CE50-CD50),"") -> 0.11830484 | CN55: 2030E | CO55: =CP55+$CO$51 -> 0.16 | CP55: 0.13 | CQ55: =CP55+$CQ$51 -> 0.08
B56: AWS — segment net sales | N56: 3108 | O56: 1050 | P56: 1005 | Q56: 1169 | R56: 1420 | S56: 4644 | T56: 1566 | U56: 1824 | V56: 2085 | W56: 2405 | X56: 7880 | Y56: 2566 | Z56: 2886 | AA56: 3231 | AB56: 3536 | AC56: 12219 | AD56: 3661 | AE56: 4100 | AF56: 4584 | AG56: 5113 | AH56: 17459 | AI56: 5442 | AJ56: 6105 | AK56: 6679 | AL56: 7430 | AM56: 25655 | AN56: 7696 | AO56: 8381 | AP56: 8995 | AQ56: 9954 | AR56: 35026 | AS56: 10219 | AT56: 10808 | AU56: 11601 | AV56: 12742 | AW56: 45370 | AX56: 13503 | AY56: 14809 | AZ56: 16110 | BA56: 17780 | BB56: 62202 | BC56: 18441 | BD56: 19739 | BE56: 20538 | BF56: 21378 | BG56: 80096 | BH56: 21354 | BI56: 22140 | BJ56: 23059 | BK56: 24204 | BL56: 90757 | BM56: 25037 | BN56: 26281 | BO56: 27452 | BP56: 28786 | BQ56: 107556 | BR56: 29267 | BS56: 30873 | BT56: 33006 | BU56: 35579 | BV56: 128725 | BW56: 37587 | BX56: 42232 | BY56: =BY26 -> 45149.788 | BZ56: =BZ26 -> 48669.463 | CA56: =SUM(BW56:BZ56) -> 173638.25 | CB56: =CB26 -> 222256.96 | CC56: =CC26 -> 275598.63 | CD56: =CD26 -> 330718.36 | CE56: =CE26 -> 386940.48 | CF56: Compute, storage, database, AI services. Forecast = AWS product group. | CH56: =IFERROR((CE56/BV56)^(1/5)-1,"n/m") -> 0.24622441 | CI56: =IFERROR((BV56/AW56)^(1/5)-1,"n/m") -> 0.23190956 | CJ56: =IFERROR((BV56/X56)^(1/10)-1,"n/m") -> 0.32225028 | CK56: =IFERROR((BV56/C56)^(1/19)-1,"n/m") -> n/m | CN56: AWS_G (AWS y/y) | CO56: 0.05 | CP56: Δ → | CQ56: -0.08 | CR56: FY2025 +19.7%; Q2-26 +36.8% (fastest in 18 quarters; AI and chips run-rates >$25bn each). Capacity-constrained growth as capex lands.
B57: y/y % | D57: =IF(AND(ISNUMBER(D56),ISNUMBER(C56)),IFERROR(D56/C56-1,""),"") | E57: =IF(AND(ISNUMBER(E56),ISNUMBER(D56)),IFERROR(E56/D56-1,""),"") | F57: =IF(AND(ISNUMBER(F56),ISNUMBER(E56)),IFERROR(F56/E56-1,""),"") | G57: =IF(AND(ISNUMBER(G56),ISNUMBER(F56)),IFERROR(G56/F56-1,""),"") | H57: =IF(AND(ISNUMBER(H56),ISNUMBER(G56)),IFERROR(H56/G56-1,""),"") | I57: =IF(AND(ISNUMBER(I56),ISNUMBER(H56)),IFERROR(I56/H56-1,""),"") | N57: =IF(AND(ISNUMBER(N56),ISNUMBER(I56)),IFERROR(N56/I56-1,""),"") | O57: =IF(AND(ISNUMBER(O56),ISNUMBER(J56)),IFERROR(O56/J56-1,""),"") | P57: =IF(AND(ISNUMBER(P56),ISNUMBER(K56)),IFERROR(P56/K56-1,""),"") | Q57: =IF(AND(ISNUMBER(Q56),ISNUMBER(L56)),IFERROR(Q56/L56-1,""),"") | R57: =IF(AND(ISNUMBER(R56),ISNUMBER(M56)),IFERROR(R56/M56-1,""),"") | S57: =IF(AND(ISNUMBER(S56),ISNUMBER(N56)),IFERROR(S56/N56-1,""),"") -> 0.49420849 | T57: =IF(AND(ISNUMBER(T56),ISNUMBER(O56)),IFERROR(T56/O56-1,""),"") -> 0.49142857 | U57: =IF(AND(ISNUMBER(U56),ISNUMBER(P56)),IFERROR(U56/P56-1,""),"") -> 0.81492537 | ... CA57: =IF(AND(ISNUMBER(CA56),ISNUMBER(BV56)),IFERROR(CA56/BV56-1,""),"") -> 0.34890853 | CB57: =IF(AND(ISNUMBER(CB56),ISNUMBER(CA56)),IFERROR(CB56/CA56-1,""),"") -> 0.28 | CC57: =IF(AND(ISNUMBER(CC56),ISNUMBER(CB56)),IFERROR(CC56/CB56-1,""),"") -> 0.24 | CD57: =IF(AND(ISNUMBER(CD56),ISNUMBER(CC56)),IFERROR(CD56/CC56-1,""),"") -> 0.2 | CE57: =IF(AND(ISNUMBER(CE56),ISNUMBER(CD56)),IFERROR(CE56/CD56-1,""),"") -> 0.17 | CN57: 2027E | CO57: =CP57+$CO$56 -> 0.33 | CP57: 0.28 | CQ57: =CP57+$CQ$56 -> 0.2
B58: AWS — segment operating income | N58: 673 | O58: 245 | P58: 77 | Q58: 98 | R58: 240 | S58: 660 | T58: 195 | U58: 305 | V58: 428 | W58: 580 | X58: 1507 | Y58: 604 | Z58: 718 | AA58: 861 | AB58: 926 | AC58: 3108 | AD58: 890 | AE58: 916 | AF58: 1171 | AG58: 1354 | AH58: 4331 | AI58: 1400 | AJ58: 1642 | AK58: 2077 | AL58: 2177 | AM58: 7296 | AN58: 2223 | AO58: 2121 | AP58: 2261 | AQ58: 2596 | AR58: 9201 | AS58: 3075 | AT58: 3357 | AU58: 3535 | AV58: 3564 | AW58: 13531 | AX58: 4163 | AY58: 4193 | AZ58: 4883 | BA58: 5293 | BB58: 18532 | BC58: 6518 | BD58: 5715 | BE58: 5403 | BF58: 5205 | BG58: 22841 | BH58: 5123 | BI58: 5365 | BJ58: 6976 | BK58: 7167 | BL58: 24631 | BM58: 9421 | BN58: 9334 | BO58: 10447 | BP58: 10632 | BQ58: 39834 | BR58: 11547 | BS58: 10160 | BT58: 11434 | BU58: 12465 | BV58: 45606 | BW58: 14161 | BX58: 16621 | BY58: =BY56*BY59 -> 16231.173 | BZ58: =BZ56*BZ59 -> 17757.804 | CA58: =SUM(BW58:BZ58) -> 64770.978 | CB58: =CB56*CB59 -> 80012.506 | CC58: =CC56*CC59 -> 97837.514 | CD58: =CD56*CD59 -> 115751.43 | CE58: =CE56*CE59 -> 135429.17 | CH58: =IFERROR((CE58/BV58)^(1/5)-1,"n/m") -> 0.24319154 | CI58: =IFERROR((BV58/AW58)^(1/5)-1,"n/m") -> 0.27508289 | CJ58: =IFERROR((BV58/X58)^(1/10)-1,"n/m") -> 0.40634176 | CK58: =IFERROR((BV58/C58)^(1/19)-1,"n/m") -> n/m | CN58: 2028E | CO58: =CP58+$CO$56 -> 0.29 | CP58: 0.24 | CQ58: =CP58+$CQ$56 -> 0.16
B59: Segment operating margin % | C59: =IF(AND(ISNUMBER(C58),ISNUMBER(C56)),IFERROR(C58/C56,""),"") | D59: =IF(AND(ISNUMBER(D58),ISNUMBER(D56)),IFERROR(D58/D56,""),"") | E59: =IF(AND(ISNUMBER(E58),ISNUMBER(E56)),IFERROR(E58/E56,""),"") | F59: =IF(AND(ISNUMBER(F58),ISNUMBER(F56)),IFERROR(F58/F56,""),"") | G59: =IF(AND(ISNUMBER(G58),ISNUMBER(G56)),IFERROR(G58/G56,""),"") | H59: =IF(AND(ISNUMBER(H58),ISNUMBER(H56)),IFERROR(H58/H56,""),"") | I59: =IF(AND(ISNUMBER(I58),ISNUMBER(I56)),IFERROR(I58/I56,""),"") | J59: =IF(AND(ISNUMBER(J58),ISNUMBER(J56)),IFERROR(J58/J56,""),"") | ... BX59: =IF(AND(ISNUMBER(BX58),ISNUMBER(BX56)),IFERROR(BX58/BX56,""),"") -> 0.39356412 | BY59: =BY60+BY120 -> 0.35949612 | BZ59: =BZ60+BZ120 -> 0.36486543 | CA59: =IF(AND(ISNUMBER(CA58),ISNUMBER(CA56)),IFERROR(CA58/CA56,""),"") -> 0.37302252 | CB59: =CHOOSE(MATCH($CF$2,{"Bull","Base","Bear"},0),$CO$77,$CP$77,$CQ$77) -> 0.36 | CC59: =CHOOSE(MATCH($CF$2,{"Bull","Base","Bear"},0),$CO$78,$CP$78,$CQ$78) -> 0.355 | CD59: =CHOOSE(MATCH($CF$2,{"Bull","Base","Bear"},0),$CO$79,$CP$79,$CQ$79) -> 0.35 | CE59: =CHOOSE(MATCH($CF$2,{"Bull","Base","Bear"},0),$CO$80,$CP$80,$CQ$80) -> 0.35 | CH59: =IFERROR(AVERAGE(CA59,CB59,CC59,CD59,CE59),"n/m") -> 0.3576045 | CI59: =IFERROR(AVERAGE(BB59,BG59,BL59,BQ59,BV59),"n/m") -> 0.31582879 | CJ59: =IFERROR(AVERAGE(AC59,AH59,AM59,AR59,AW59,BB59,BG59,BL59,BQ59,BV59),"n/m") -> 0.29268851 | CK59: =IFERROR(AVERAGE(C59,D59,E59,F59,G59,H59,I59,N59,S59,X59,AC59,AH59,AM59,AR59,AW59,BB59,BG59,BL59,BQ59,BV59),"n/m") -> 0.26744505 | CN59: 2029E | CO59: =CP59+$CO$56 -> 0.25 | CP59: 0.2 | CQ59: =CP59+$CQ$56 -> 0.12
B60: Q3/Q4-26E margin before calibration (prior-year quarter ex disclosed special charges + 1H-26 y/y drift) | BY60: =(BT58)/BT56+IFERROR(SUM(BW58:BX58)/SUM(BW56:BX56)-SUM(BR58:BS58)/SUM(BR56:BS56),0) -> 0.37112825 | BZ60: =(BU58)/BU56+IFERROR(SUM(BW58:BX58)/SUM(BW56:BX56)-SUM(BR58:BS58)/SUM(BR56:BS56),0) -> 0.37505351 | CN60: 2030E | CO60: =CP60+$CO$56 -> 0.22 | CP60: 0.17 | CQ60: =CP60+$CQ$56 -> 0.09
B61: Incremental segment margin (Δ OI / Δ net sales) | D61: =IFERROR((D58-C58)/(D56-C56),"") | E61: =IFERROR((E58-D58)/(E56-D56),"") | F61: =IFERROR((F58-E58)/(F56-E56),"") | G61: =IFERROR((G58-F58)/(G56-F56),"") | H61: =IFERROR((H58-G58)/(H56-G56),"") | I61: =IFERROR((I58-H58)/(I56-H56),"") | N61: =IFERROR((N58-I58)/(N56-I56),"") -> 0.21653797 | O61: =IFERROR((O58-J58)/(O56-J56),"") -> 0.23333333 | P61: =IFERROR((P58-K58)/(P56-K56),"") -> 0.076616915 | Q61: =IFERROR((Q58-L58)/(Q56-L56),"") -> 0.083832335 | R61: =IFERROR((R58-M58)/(R56-M56),"") -> 0.16901408 | S61: =IFERROR((S58-N58)/(S56-N56),"") -> -0.0084635417 | T61: =IFERROR((T58-O58)/(T56-O56),"") -> -0.096899225 | U61: =IFERROR((U58-P58)/(U56-P56),"") -> 0.27838828 | ... CA61: =IFERROR((CA58-BV58)/(CA56-BV56),"") -> 0.42671099 | CB61: =IFERROR((CB58-CA58)/(CB56-CA56),"") -> 0.313491 | CC61: =IFERROR((CC58-CB58)/(CC56-CB56),"") -> 0.33416667 | CD61: =IFERROR((CD58-CC58)/(CD56-CC56),"") -> 0.325 | CE61: =IFERROR((CE58-CD58)/(CE56-CD56),"") -> 0.35 | CN61: OTHER (Other net sales y/y) | CO61: 0.02 | CP61: Δ → | CQ61: -0.03 | CR61: FY2025 +9.4% (co-branded credit cards, licensing, shipping services).
B62: Memo: special charges disclosed by segment — North America (FTC legal settlement $2.5bn, Q3-25) | C62: 0 | D62: 0 | E62: 0 | F62: 0 | G62: 0 | H62: 0 | I62: 0 | J62: 0 | K62: 0 | L62: 0 | M62: 0 | N62: 0 | O62: 0 | P62: 0 | Q62: 0 | R62: 0 | S62: 0 | T62: 0 | U62: 0 | V62: 0 | W62: 0 | X62: 0 | Y62: 0 | Z62: 0 | AA62: 0 | AB62: 0 | AC62: 0 | AD62: 0 | AE62: 0 | AF62: 0 | AG62: 0 | AH62: 0 | AI62: 0 | AJ62: 0 | AK62: 0 | AL62: 0 | AM62: 0 | AN62: 0 | AO62: 0 | AP62: 0 | AQ62: 0 | AR62: 0 | AS62: 0 | AT62: 0 | AU62: 0 | AV62: 0 | AW62: 0 | AX62: 0 | AY62: 0 | AZ62: 0 | BA62: 0 | BB62: 0 | BC62: 0 | BD62: 0 | BE62: 0 | BF62: 0 | BG62: 0 | BH62: 0 | BI62: 0 | BJ62: 0 | BK62: 0 | BL62: 0 | BM62: 0 | BN62: 0 | BO62: 0 | BP62: 0 | BQ62: 0 | BR62: 0 | BS62: 0 | BT62: 2500 | BU62: 0 | BV62: 2500 | BW62: 0 | BX62: 0 | BY62: =0 -> 0 | BZ62: =0 -> 0 | CA62: =SUM(BW62:BZ62) -> 0 | CB62: =0 -> 0 | CC62: =0 -> 0 | CD62: =0 -> 0 | CE62: =0 -> 0 | CN62: 2027E | CO62: =CP62+$CO$61 -> 0.1 | CP62: 0.08 | CQ62: =CP62+$CQ$61 -> 0.05
B63: Unallocated stock-based compensation & other operating expense (not allocated to segments until 2015) | N63: -1248 | O63: -356 | P63: -419 | Q63: -408 | R63: -447 | S63: -1630 | T63: 0 | U63: 0 | V63: 0 | W63: 0 | X63: 0 | Y63: 0 | Z63: 0 | AA63: 0 | AB63: 0 | AC63: 0 | AD63: 0 | AE63: 0 | AF63: 0 | AG63: 0 | AH63: 0 | AI63: 0 | AJ63: 0 | AK63: 0 | AL63: 0 | AM63: 0 | AN63: 0 | AO63: 0 | AP63: 0 | AQ63: 0 | AR63: 0 | AS63: 0 | AT63: 0 | AU63: 0 | AV63: 0 | AW63: 0 | AX63: 0 | AY63: 0 | AZ63: 0 | BA63: 0 | BB63: 0 | BC63: 0 | BD63: 0 | BE63: 0 | BF63: 0 | BG63: 0 | BH63: 0 | BI63: 0 | BJ63: 0 | BK63: 0 | BL63: 0 | BM63: 0 | BN63: 0 | BO63: 0 | BP63: 0 | BQ63: 0 | BR63: 0 | BS63: 0 | BT63: 0 | BU63: 0 | BV63: 0 | BW63: 0 | BX63: 0 | BY63: =0 -> 0 | BZ63: =0 -> 0 | CA63: =SUM(BW63:BZ63) -> 0 | CB63: =0 -> 0 | CC63: =0 -> 0 | CD63: =0 -> 0 | CE63: =0 -> 0 | CN63: 2028E | CO63: =CP63+$CO$61 -> 0.09 | CP63: 0.07 | CQ63: =CP63+$CQ$61 -> 0.04
B64: Net sales not on the current segment basis (FY2006–12, Q1–Q4/13: AWS inside North America — legacy memo below) | C64: =IF(ISNUMBER(C44),0,C144) -> 10711 | D64: =IF(ISNUMBER(D44),0,D144) -> 14835 | E64: =IF(ISNUMBER(E44),0,E144) -> 19166 | F64: =IF(ISNUMBER(F44),0,F144) -> 24509 | G64: =IF(ISNUMBER(G44),0,G144) -> 34204 | H64: =IF(ISNUMBER(H44),0,H144) -> 48077 | I64: =IF(ISNUMBER(I44),0,I144) -> 61093 | J64: =IF(ISNUMBER(J44),0,J144) -> 16070 | ... BX64: =IF(ISNUMBER(BX44),0,BX144) -> 0 | CN64: 2029E | CO64: =CP64+$CO$61 -> 0.08 | CP64: 0.06 | CQ64: =CP64+$CQ$61 -> 0.03
B65: Operating income not on the current segment basis | C65: =IF(ISNUMBER(C46),0,C154) -> 389 | D65: =IF(ISNUMBER(D46),0,D154) -> 655 | E65: =IF(ISNUMBER(E46),0,E154) -> 842 | F65: =IF(ISNUMBER(F46),0,F154) -> 1129 | G65: =IF(ISNUMBER(G46),0,G154) -> 1406 | H65: =IF(ISNUMBER(H46),0,H154) -> 862 | I65: =IF(ISNUMBER(I46),0,I154) -> 676 | J65: =IF(ISNUMBER(J46),0,J154) -> 181 | ... BX65: =IF(ISNUMBER(BX46),0,BX154) -> 0 | CN65: 2030E | CO65: =CP65+$CO$61 -> 0.08 | CP65: 0.06 | CQ65: =CP65+$CQ$61 -> 0.03
B66: Check: segment net sales vs consolidated (should be 0) | C66: =IF(ABS(N(C44)+N(C50)+N(C56)+C64-C144)<=1.01,0,ROUND(N(C44)+N(C50)+N(C56)+C64-C144,0)) -> 0 | D66: =IF(ABS(N(D44)+N(D50)+N(D56)+D64-D144)<=1.01,0,ROUND(N(D44)+N(D50)+N(D56)+D64-D144,0)) -> 0 | E66: =IF(ABS(N(E44)+N(E50)+N(E56)+E64-E144)<=1.01,0,ROUND(N(E44)+N(E50)+N(E56)+E64-E144,0)) -> 0 | F66: =IF(ABS(N(F44)+N(F50)+N(F56)+F64-F144)<=1.01,0,ROUND(N(F44)+N(F50)+N(F56)+F64-F144,0)) -> 0 | G66: =IF(ABS(N(G44)+N(G50)+N(G56)+G64-G144)<=1.01,0,ROUND(N(G44)+N(G50)+N(G56)+G64-G144,0)) -> 0 | H66: =IF(ABS(N(H44)+N(H50)+N(H56)+H64-H144)<=1.01,0,ROUND(N(H44)+N(H50)+N(H56)+H64-H144,0)) -> 0 | I66: =IF(ABS(N(I44)+N(I50)+N(I56)+I64-I144)<=1.01,0,ROUND(N(I44)+N(I50)+N(I56)+I64-I144,0)) -> 0 | J66: =IF(ABS(N(J44)+N(J50)+N(J56)+J64-J144)<=1.01,0,ROUND(N(J44)+N(J50)+N(J56)+J64-J144,0)) -> 0 | ... BX66: =IF(ABS(N(BX44)+N(BX50)+N(BX56)+BX64-BX144)<=1.01,0,ROUND(N(BX44)+N(BX50)+N(BX56)+BX64-BX144,0)) -> 0 | CN66: NA_M (North America segment margin) | CO66: 0.01 | CP66: Δ → | CQ66: -0.015 | CR66: FY2025 6.9% (7.5% ex the $2.5bn FTC charge); 1H-26 7.9%. Regionalised fulfilment, advertising mix vs quick-commerce and Leo investment.
B67: Check: Σ segment OI + unallocated vs consolidated operating income (should be 0) | C67: =IF(ABS(N(C46)+N(C52)+N(C58)+N(C63)+C65-C154)<=1.01,0,ROUND(N(C46)+N(C52)+N(C58)+N(C63)+C65-C154,0)) -> 0 | D67: =IF(ABS(N(D46)+N(D52)+N(D58)+N(D63)+D65-D154)<=1.01,0,ROUND(N(D46)+N(D52)+N(D58)+N(D63)+D65-D154,0)) -> 0 | E67: =IF(ABS(N(E46)+N(E52)+N(E58)+N(E63)+E65-E154)<=1.01,0,ROUND(N(E46)+N(E52)+N(E58)+N(E63)+E65-E154,0)) -> 0 | F67: =IF(ABS(N(F46)+N(F52)+N(F58)+N(F63)+F65-F154)<=1.01,0,ROUND(N(F46)+N(F52)+N(F58)+N(F63)+F65-F154,0)) -> 0 | G67: =IF(ABS(N(G46)+N(G52)+N(G58)+N(G63)+G65-G154)<=1.01,0,ROUND(N(G46)+N(G52)+N(G58)+N(G63)+G65-G154,0)) -> 0 | H67: =IF(ABS(N(H46)+N(H52)+N(H58)+N(H63)+H65-H154)<=1.01,0,ROUND(N(H46)+N(H52)+N(H58)+N(H63)+H65-H154,0)) -> 0 | I67: =IF(ABS(N(I46)+N(I52)+N(I58)+N(I63)+I65-I154)<=1.01,0,ROUND(N(I46)+N(I52)+N(I58)+N(I63)+I65-I154,0)) -> 0 | J67: =IF(ABS(N(J46)+N(J52)+N(J58)+N(J63)+J65-J154)<=1.01,0,ROUND(N(J46)+N(J52)+N(J58)+N(J63)+J65-J154,0)) -> 0 | ... BX67: =IF(ABS(N(BX46)+N(BX52)+N(BX58)+N(BX63)+BX65-BX154)<=1.01,0,ROUND(N(BX46)+N(BX52)+N(BX58)+N(BX63)+BX65-BX154,0)) -> 0 | CN67: 2027E | CO67: =CP67+$CO$66 -> 0.095 | CP67: 0.085 | CQ67: =CP67+$CQ$66 -> 0.07
B68: Check: AWS segment vs AWS product group (should be 0; ±2, FY = Σ quarters) | C68: =IF(AND(ISNUMBER(C56),ISNUMBER(C26)),IF(ABS(C56-C26)<=2.01,0,ROUND(C56-C26,0)),"") | D68: =IF(AND(ISNUMBER(D56),ISNUMBER(D26)),IF(ABS(D56-D26)<=2.01,0,ROUND(D56-D26,0)),"") | E68: =IF(AND(ISNUMBER(E56),ISNUMBER(E26)),IF(ABS(E56-E26)<=2.01,0,ROUND(E56-E26,0)),"") | F68: =IF(AND(ISNUMBER(F56),ISNUMBER(F26)),IF(ABS(F56-F26)<=2.01,0,ROUND(F56-F26,0)),"") | G68: =IF(AND(ISNUMBER(G56),ISNUMBER(G26)),IF(ABS(G56-G26)<=2.01,0,ROUND(G56-G26,0)),"") | H68: =IF(AND(ISNUMBER(H56),ISNUMBER(H26)),IF(ABS(H56-H26)<=2.01,0,ROUND(H56-H26,0)),"") | I68: =IF(AND(ISNUMBER(I56),ISNUMBER(I26)),IF(ABS(I56-I26)<=2.01,0,ROUND(I56-I26,0)),"") | J68: =IF(AND(ISNUMBER(J56),ISNUMBER(J26)),IF(ABS(J56-J26)<=2.01,0,ROUND(J56-J26,0)),"") | ... BX68: =IF(AND(ISNUMBER(BX56),ISNUMBER(BX26)),IF(ABS(BX56-BX26)<=2.01,0,ROUND(BX56-BX26,0)),"") -> 0 | CN68: 2028E | CO68: =CP68+$CO$66 -> 0.1 | CP68: 0.09 | CQ68: =CP68+$CQ$66 -> 0.075
B69: Legacy segment basis — as originally reported (North America incl. AWS, International; segment OI before SBC & other operating expense): | CN69: 2029E | CO69: =CP69+$CO$66 -> 0.105 | CP69: 0.095 | CQ69: =CP69+$CQ$66 -> 0.08
B70: North America net sales (incl. AWS) | C70: 5869 | D70: 8095 | E70: 10228 | F70: 12828 | G70: 18707 | H70: 26705 | I70: 34813 | J70: 9391 | K70: 9495 | L70: 10301 | M70: 15331 | N70: 44517 | O70: 11858 | P70: 11998 | Q70: 12867 | R70: 18747 | S70: 55469 | CN70: 2030E | CO70: =CP70+$CO$66 -> 0.11 | CP70: 0.1 | CQ70: =CP70+$CQ$66 -> 0.085
B71: North America segment operating income | C71: 230 | D71: 400 | E71: 445 | F71: 709 | G71: 955 | H71: 933 | I71: 1592 | J71: 457 | K71: 409 | L71: 295 | M71: 725 | N71: 1886 | O71: 562 | P71: 438 | Q71: 88 | R71: 1018 | S71: 2105 | CN71: INTL_M (International segment margin) | CO71: 0.01 | CP71: Δ → | CQ71: -0.015 | CR71: FY2025 2.9%; 1H-26 3.9%; scale in emerging markets offsets price investment.
B72: International net sales | C72: 4842 | D72: 6740 | E72: 8938 | F72: 11681 | G72: 15497 | H72: 21372 | I72: 26280 | J72: 6679 | K72: 6209 | L72: 6791 | M72: 10256 | N72: 29935 | O72: 7883 | P72: 7342 | Q72: 7712 | R72: 10581 | S72: 33519 | CN72: 2027E | CO72: =CP72+$CO$71 -> 0.055 | CP72: 0.045 | CQ72: =CP72+$CQ$71 -> 0.03
B73: International segment operating income | C73: 270 | D73: 449 | E73: 648 | F73: 863 | G73: 981 | H73: 640 | I73: 76 | J73: -16 | K73: 0 | L73: -28 | M73: 151 | N73: 107 | O73: -60 | P73: -34 | Q73: -224 | R73: 20 | S73: -297 | CN73: 2028E | CO73: =CP73+$CO$71 -> 0.06 | CP73: 0.05 | CQ73: =CP73+$CQ$71 -> 0.035
B74: Unallocated stock-based compensation & other operating expense | C74: -111 | D74: -194 | E74: -251 | F74: -443 | G74: -530 | H74: -711 | I74: -992 | J74: -260 | K74: -330 | L74: -292 | M74: -366 | N74: -1248 | O74: -356 | P74: -419 | Q74: -408 | R74: -447 | S74: -1630 | CN74: 2029E | CO74: =CP74+$CO$71 -> 0.065 | CP74: 0.055 | CQ74: =CP74+$CQ$71 -> 0.04
B75: Check: legacy segments + unallocated vs consolidated operating income (should be 0) | C75: =IF(ISNUMBER(C71),IF(ABS(C71+C73+C74-C154)<=1.01,0,ROUND(C71+C73+C74-C154,0)),"") -> 0 | D75: =IF(ISNUMBER(D71),IF(ABS(D71+D73+D74-D154)<=1.01,0,ROUND(D71+D73+D74-D154,0)),"") -> 0 | E75: =IF(ISNUMBER(E71),IF(ABS(E71+E73+E74-E154)<=1.01,0,ROUND(E71+E73+E74-E154,0)),"") -> 0 | F75: =IF(ISNUMBER(F71),IF(ABS(F71+F73+F74-F154)<=1.01,0,ROUND(F71+F73+F74-F154,0)),"") -> 0 | G75: =IF(ISNUMBER(G71),IF(ABS(G71+G73+G74-G154)<=1.01,0,ROUND(G71+G73+G74-G154,0)),"") -> 0 | H75: =IF(ISNUMBER(H71),IF(ABS(H71+H73+H74-H154)<=1.01,0,ROUND(H71+H73+H74-H154,0)),"") -> 0 | I75: =IF(ISNUMBER(I71),IF(ABS(I71+I73+I74-I154)<=1.01,0,ROUND(I71+I73+I74-I154,0)),"") -> 0 | J75: =IF(ISNUMBER(J71),IF(ABS(J71+J73+J74-J154)<=1.01,0,ROUND(J71+J73+J74-J154,0)),"") -> 0 | ... BX75: =IF(ISNUMBER(BX71),IF(ABS(BX71+BX73+BX74-BX154)<=1.01,0,ROUND(BX71+BX73+BX74-BX154,0)),"") | CN75: 2030E | CO75: =CP75+$CO$71 -> 0.07 | CP75: 0.06 | CQ75: =CP75+$CQ$71 -> 0.045
B76: 2015 as originally reported (before the 2016 restatement allocating SBC to segments): | CN76: AWS_M (AWS segment margin) | CO76: 0.02 | CP76: Δ → | CQ76: -0.03 | CR76: FY2025 35.4%; 1H-26 38.6% (incl. $0.6bn energy-contract gains). Rising depreciation from the AI build-out caps the margin.
B77: North America | T77: 517 | U77: 703 | V77: 528 | W77: 1003 | X77: 2751 | CN77: 2027E | CO77: =CP77+$CO$76 -> 0.38 | CP77: 0.36 | CQ77: =CP77+$CQ$76 -> 0.33
B78: International | T78: -76 | U78: -19 | V78: -56 | W78: 60 | X78: -91 | CN78: 2028E | CO78: =CP78+$CO$76 -> 0.375 | CP78: 0.355 | CQ78: =CP78+$CQ$76 -> 0.325
B79: AWS | T79: 265 | U79: 391 | V79: 521 | W79: 687 | X79: 1863 | CN79: 2029E | CO79: =CP79+$CO$76 -> 0.37 | CP79: 0.35 | CQ79: =CP79+$CQ$76 -> 0.32
B80: Unallocated SBC & other operating expense | T80: -451 | U80: -611 | V80: -587 | W80: -642 | X80: -2290 | CN80: 2030E | CO80: =CP80+$CO$76 -> 0.37 | CP80: 0.35 | CQ80: =CP80+$CQ$76 -> 0.32
B81: Legacy supplemental net sales (Media / Electronics & other general merchandise / Other; NA + International; 2006–2016): | CN81: CAPEX (gross capex % of net sales) | CO81: -0.01 | CP81: Δ → | CQ81: 0.015 | CR81: FY2025 18.4%; 1H-26 25.8%. AI / data-centre build-out peaking in 2026–27, then normalising (assumption).
B82: Media | C82: 7067 | D82: 9242 | E82: 11084 | F82: 12774 | G82: 14888 | H82: 17779 | I82: 19942 | J82: 5058 | K82: 4397 | L82: 5033 | M82: 7227 | N82: 21716 | O82: 5467 | P82: 4844 | Q82: 5244 | R82: 6950 | S82: 22505 | T82: 5289 | U82: 4714 | V82: 5283 | W82: 7223 | X82: 22509 | Y82: 5688 | Z82: 5211 | AA82: 5728 | AB82: 7585 | AC82: 24211 | CN82: 2027E | CO82: =CP82+$CO$81 -> 0.22 | CP82: 0.23 | CQ82: =CP82+$CQ$81 -> 0.245
B83: Electronics and other general merchandise | C83: 3361 | D83: 5210 | E83: 7540 | F83: 11082 | G83: 18363 | H83: 28712 | I83: 38628 | J83: 10214 | K83: 10415 | L83: 11048 | M83: 17126 | N83: 48802 | O83: 13017 | P83: 13278 | Q83: 13953 | R83: 20638 | S83: 60886 | T83: 15628 | U83: 16412 | V83: 17741 | W83: 25816 | X83: 75597 | Y83: 20545 | Z83: 21963 | AA83: 23383 | AB83: 32104 | AC83: 97994 | CN83: 2028E | CO83: =CP83+$CO$81 -> 0.2 | CP83: 0.21 | CQ83: =CP83+$CQ$81 -> 0.225
B84: Other (incl. AWS to 2014) | C84: 283 | D84: 383 | E84: 542 | F84: 653 | G84: 953 | H84: 1586 | I84: 2523 | J84: 798 | K84: 892 | L84: 1011 | M84: 1234 | N84: 3934 | O84: 1257 | P84: 1218 | Q84: 1382 | R84: 1740 | S84: 5597 | T84: 234 | U84: 235 | V84: 249 | W84: 303 | X84: 1020 | Y84: 329 | Z84: 344 | AA84: 372 | AB84: 516 | AC84: 1563 | CN84: 2029E | CO84: =CP84+$CO$81 -> 0.18 | CP84: 0.19 | CQ84: =CP84+$CQ$81 -> 0.205
B85: Contribution to net sales growth — North America (pp) | D85: =IF(AND(ISNUMBER(D44),ISNUMBER(C44)),IFERROR((D44-C44)/C144,""),"") | E85: =IF(AND(ISNUMBER(E44),ISNUMBER(D44)),IFERROR((E44-D44)/D144,""),"") | F85: =IF(AND(ISNUMBER(F44),ISNUMBER(E44)),IFERROR((F44-E44)/E144,""),"") | G85: =IF(AND(ISNUMBER(G44),ISNUMBER(F44)),IFERROR((G44-F44)/F144,""),"") | H85: =IF(AND(ISNUMBER(H44),ISNUMBER(G44)),IFERROR((H44-G44)/G144,""),"") | I85: =IF(AND(ISNUMBER(I44),ISNUMBER(H44)),IFERROR((I44-H44)/H144,""),"") | N85: =IF(AND(ISNUMBER(N44),ISNUMBER(I44)),IFERROR((N44-I44)/I144,""),"") | O85: =IF(AND(ISNUMBER(O44),ISNUMBER(J44)),IFERROR((O44-J44)/J144,""),"") | P85: =IF(AND(ISNUMBER(P44),ISNUMBER(K44)),IFERROR((P44-K44)/K144,""),"") | Q85: =IF(AND(ISNUMBER(Q44),ISNUMBER(L44)),IFERROR((Q44-L44)/L144,""),"") | R85: =IF(AND(ISNUMBER(R44),ISNUMBER(M44)),IFERROR((R44-M44)/M144,""),"") | S85: =IF(AND(ISNUMBER(S44),ISNUMBER(N44)),IFERROR((S44-N44)/N144,""),"") -> 0.1265782 | T85: =IF(AND(ISNUMBER(T44),ISNUMBER(O44)),IFERROR((T44-O44)/O144,""),"") -> 0.13160428 | U85: =IF(AND(ISNUMBER(U44),ISNUMBER(P44)),IFERROR((U44-P44)/P144,""),"") -> 0.14488108 | ... CA85: =IF(AND(ISNUMBER(CA44),ISNUMBER(BV44)),IFERROR((CA44-BV44)/BV144,""),"") -> 0.060712691 | CB85: =IF(AND(ISNUMBER(CB44),ISNUMBER(CA44)),IFERROR((CB44-CA44)/CA144,""),"") -> 0.060593535 | CC85: =IF(AND(ISNUMBER(CC44),ISNUMBER(CB44)),IFERROR((CC44-CB44)/CB144,""),"") -> 0.054377732 | CD85: =IF(AND(ISNUMBER(CD44),ISNUMBER(CC44)),IFERROR((CD44-CC44)/CC144,""),"") -> 0.049329921 | CE85: =IF(AND(ISNUMBER(CE44),ISNUMBER(CD44)),IFERROR((CE44-CD44)/CD144,""),"") -> 0.044636687 | CN85: 2030E | CO85: =CP85+$CO$81 -> 0.16 | CP85: 0.17 | CQ85: =CP85+$CQ$81 -> 0.185
B86: Contribution to net sales growth — International (pp) | D86: =IF(AND(ISNUMBER(D50),ISNUMBER(C50)),IFERROR((D50-C50)/C144,""),"") | E86: =IF(AND(ISNUMBER(E50),ISNUMBER(D50)),IFERROR((E50-D50)/D144,""),"") | F86: =IF(AND(ISNUMBER(F50),ISNUMBER(E50)),IFERROR((F50-E50)/E144,""),"") | G86: =IF(AND(ISNUMBER(G50),ISNUMBER(F50)),IFERROR((G50-F50)/F144,""),"") | H86: =IF(AND(ISNUMBER(H50),ISNUMBER(G50)),IFERROR((H50-G50)/G144,""),"") | I86: =IF(AND(ISNUMBER(I50),ISNUMBER(H50)),IFERROR((I50-H50)/H144,""),"") | N86: =IF(AND(ISNUMBER(N50),ISNUMBER(I50)),IFERROR((N50-I50)/I144,""),"") | O86: =IF(AND(ISNUMBER(O50),ISNUMBER(J50)),IFERROR((O50-J50)/J144,""),"") | P86: =IF(AND(ISNUMBER(P50),ISNUMBER(K50)),IFERROR((P50-K50)/K144,""),"") | Q86: =IF(AND(ISNUMBER(Q50),ISNUMBER(L50)),IFERROR((Q50-L50)/L144,""),"") | R86: =IF(AND(ISNUMBER(R50),ISNUMBER(M50)),IFERROR((R50-M50)/M144,""),"") | S86: =IF(AND(ISNUMBER(S50),ISNUMBER(N50)),IFERROR((S50-N50)/N144,""),"") -> 0.048030946 | T86: =IF(AND(ISNUMBER(T50),ISNUMBER(O50)),IFERROR((T50-O50)/O144,""),"") -> -0.0069905273 | U86: =IF(AND(ISNUMBER(U50),ISNUMBER(P50)),IFERROR((U50-P50)/P144,""),"") -> 0.011582213 | ... CA86: =IF(AND(ISNUMBER(CA50),ISNUMBER(BV50)),IFERROR((CA50-BV50)/BV144,""),"") -> 0.028118515 | CB86: =IF(AND(ISNUMBER(CB50),ISNUMBER(CA50)),IFERROR((CB50-CA50)/CA144,""),"") -> 0.023479115 | CC86: =IF(AND(ISNUMBER(CC50),ISNUMBER(CB50)),IFERROR((CC50-CB50)/CB144,""),"") -> 0.021070582 | CD86: =IF(AND(ISNUMBER(CD50),ISNUMBER(CC50)),IFERROR((CD50-CC50)/CC144,""),"") -> 0.019114628 | CE86: =IF(AND(ISNUMBER(CE50),ISNUMBER(CD50)),IFERROR((CE50-CD50)/CD144,""),"") -> 0.017296068 | CN86: M&A_spend (acquisitions & strategic investments, $m) | CO86: 3000 | CP86: Δ → | CQ86: -3000 | CR86: Cash-flow line incl. non-marketable investments (Anthropic): FY2024 $7.1bn, FY2025 and 1H-26 per the cash-flow statement. Base $5bn p.a. (assumption).
B87: Contribution to net sales growth — AWS (pp) | D87: =IF(AND(ISNUMBER(D56),ISNUMBER(C56)),IFERROR((D56-C56)/C144,""),"") | E87: =IF(AND(ISNUMBER(E56),ISNUMBER(D56)),IFERROR((E56-D56)/D144,""),"") | F87: =IF(AND(ISNUMBER(F56),ISNUMBER(E56)),IFERROR((F56-E56)/E144,""),"") | G87: =IF(AND(ISNUMBER(G56),ISNUMBER(F56)),IFERROR((G56-F56)/F144,""),"") | H87: =IF(AND(ISNUMBER(H56),ISNUMBER(G56)),IFERROR((H56-G56)/G144,""),"") | I87: =IF(AND(ISNUMBER(I56),ISNUMBER(H56)),IFERROR((I56-H56)/H144,""),"") | N87: =IF(AND(ISNUMBER(N56),ISNUMBER(I56)),IFERROR((N56-I56)/I144,""),"") | O87: =IF(AND(ISNUMBER(O56),ISNUMBER(J56)),IFERROR((O56-J56)/J144,""),"") | P87: =IF(AND(ISNUMBER(P56),ISNUMBER(K56)),IFERROR((P56-K56)/K144,""),"") | Q87: =IF(AND(ISNUMBER(Q56),ISNUMBER(L56)),IFERROR((Q56-L56)/L144,""),"") | R87: =IF(AND(ISNUMBER(R56),ISNUMBER(M56)),IFERROR((R56-M56)/M144,""),"") | S87: =IF(AND(ISNUMBER(S56),ISNUMBER(N56)),IFERROR((S56-N56)/N144,""),"") -> 0.020630742 | T87: =IF(AND(ISNUMBER(T56),ISNUMBER(O56)),IFERROR((T56-O56)/O144,""),"") -> 0.026138493 | U87: =IF(AND(ISNUMBER(U56),ISNUMBER(P56)),IFERROR((U56-P56)/P144,""),"") -> 0.042347466 | ... CA87: =IF(AND(ISNUMBER(CA56),ISNUMBER(BV56)),IFERROR((CA56-BV56)/BV144,""),"") -> 0.062647157 | CB87: =IF(AND(ISNUMBER(CB56),ISNUMBER(CA56)),IFERROR((CB56-CA56)/CA144,""),"") -> 0.058894472 | CC87: =IF(AND(ISNUMBER(CC56),ISNUMBER(CB56)),IFERROR((CC56-CB56)/CB144,""),"") -> 0.056508299 | CD87: =IF(AND(ISNUMBER(CD56),ISNUMBER(CC56)),IFERROR((CD56-CC56)/CC144,""),"") -> 0.051541523 | CE87: =IF(AND(ISNUMBER(CE56),ISNUMBER(CD56)),IFERROR((CE56-CD56)/CD144,""),"") -> 0.046902123 | CN87: 2027E | CO87: =MAX(0,CP87+$CO$86) -> 8000 | CP87: 5000 | CQ87: =MAX(0,CP87+$CQ$86) -> 2000
CN88: 2028E | CO88: =MAX(0,CP88+$CO$86) -> 8000 | CP88: 5000 | CQ88: =MAX(0,CP88+$CQ$86) -> 2000
B89: Future acquisitions & strategic investments (M&A lever — unallocated; from 2027E) | CF89: M&A LEVER — acquired revenue = spend × acquisition share ÷ EV/sales; mid-year convention | CN89: 2029E | CO89: =MAX(0,CP89+$CO$86) -> 8000 | CP89: 5000 | CQ89: =MAX(0,CP89+$CQ$86) -> 2000
B90: Acquisitions & strategic investments spend (USDm, scenario) | CA90: 0 | CB90: =MAX(0,CHOOSE(MATCH($CF$2,{"Bull","Base","Bear"},0),$CO$87,$CP$87,$CQ$87)) -> 5000 | CC90: =MAX(0,CHOOSE(MATCH($CF$2,{"Bull","Base","Bear"},0),$CO$88,$CP$88,$CQ$88)) -> 5000 | CD90: =MAX(0,CHOOSE(MATCH($CF$2,{"Bull","Base","Bear"},0),$CO$89,$CP$89,$CQ$89)) -> 5000 | CE90: =MAX(0,CHOOSE(MATCH($CF$2,{"Bull","Base","Bear"},0),$CO$90,$CP$90,$CQ$90)) -> 5000 | CF90: Scenario lever M&A_spend (Base $5bn p.a.; half assumed to buy operating businesses at 3.0x sales, half strategic investments with no revenue). | CN90: 2030E | CO90: =MAX(0,CP90+$CO$86) -> 8000 | CP90: 5000 | CQ90: =MAX(0,CP90+$CQ$86) -> 2000
B91: Share of spend on acquisitions of operating businesses (rest = minority / strategic investments, no revenue) | CA91: 0 | CB91: 0.5 | CC91: 0.5 | CD91: 0.5 | CE91: 0.5
B92: Purchase multiple — EV / sales (x) | CA92: 0 | CB92: 3 | CC92: 3 | CD92: 3 | CE92: 3 | CF92: Assumption (3.0x input). Precedents: MGM (17-Mar-2022, $6.1bn net of cash + $2.5bn debt assumed; Q1-22 10-Q), One Medical (22-Feb-2023, $3.5bn; Q1-23 10-Q), Whole Foods (28-Aug-2017, $13.2bn; FY2017 10-K).
B93: Annualised revenue acquired in the year | CA93: 0 | CB93: =IFERROR(CB90*CB91/CB92,0) -> 833.33333 | CC93: =IFERROR(CC90*CC91/CC92,0) -> 833.33333 | CD93: =IFERROR(CD90*CD91/CD92,0) -> 833.33333 | CE93: =IFERROR(CE90*CE91/CE92,0) -> 833.33333
B94: Growth of acquired businesses after acquisition % | CA94: 0 | CB94: 0.08 | CC94: 0.08 | CD94: 0.08 | CE94: 0.08
B95: Run-rate revenue of businesses acquired (year end) | CA95: 0 | CB95: =CA95*(1+CB94)+CB93 -> 833.33333 | CC95: =CB95*(1+CC94)+CC93 -> 1733.3333 | CD95: =CC95*(1+CD94)+CD93 -> 2705.3333 | CE95: =CD95*(1+CE94)+CE93 -> 3755.0933
B96: Revenue from future acquisitions | CA96: 0 | CB96: =CA95*(1+CB94)+0.5*CB93 -> 416.66667 | CC96: =CB95*(1+CC94)+0.5*CC93 -> 1316.6667 | CD96: =CC95*(1+CD94)+0.5*CD93 -> 2288.6667 | CE96: =CD95*(1+CE94)+0.5*CE93 -> 3338.4267 | CF96: Mid-year convention.
B97: Operating margin of acquired businesses % | CA97: 0 | CB97: 0.05 | CC97: 0.05 | CD97: 0.05 | CE97: 0.05
B98: Operating income from future acquisitions | CA98: 0 | CB98: =CB96*CB97 -> 20.833333 | CC98: =CC96*CC97 -> 65.833333 | CD98: =CD96*CD97 -> 114.43333 | CE98: =CE96*CE97 -> 166.92133
B99: Acquired intangibles % of acquisition spend | CA99: 0 | CB99: 0.3 | CC99: 0.3 | CD99: 0.3 | CE99: 0.3 | CF99: One Medical: $1.3bn intangibles / $3.5bn consideration (37%); 30% input (assumption).
B100: Intangible amortization life (years) | CA100: 0 | CB100: 10 | CC100: 10 | CD100: 10 | CE100: 10
...

Sheet Bull-Base-Bear
B2: Amazon.com, Inc. (AMZN) — Bull / Base / Bear Case P&L Summary | J2: Share price ($): | K2: =Model!$CA$416 -> 260
B3: Model definitions (Amazon publishes no adjusted measures besides free cash flow): adjusted operating income / EBITDA add back only the special charges Amazon quantified and energy-contract remeasurements; adjusted EPS also excludes other income (expense) — investment marks (Anthropic, Rivian) — and equity-method activity. USD millions · Live panel linked to Model — toggle the scenario with the switch on the Model sheet (cell CF2). Bull and Bear panels are value snapshots generated from the Model with the switch set to each case. 2026E = 1H actual + Q3 calibrated to the Q3-26 guidance + Q4 carrying the Q3 Δs. | J3: As of: | K3: =TODAY() -> 2026-10-12 00:00:00
B5: Scenario: | C5: =Model!$CF$2 -> Base | N5: Scenario: | O5: Bull | P5: Snapshot (values) — Model run with switch = Bull | Z5: Scenario: | AA5: Bear | AB5: Snapshot (values) — Model run with switch = Bear
B7: (USDm, except EPS and shares) | C7: 2025A | D7: 2026E | E7: 2027E | F7: 2028E | G7: 2029E | H7: 2030E | I7: 25-'30 CAGR | J7: LT Hist Avg | K7: LT Hist Min | L7: LT Hist Max | N7: (USDm, except EPS and shares) | O7: 2025A | P7: 2026E | Q7: 2027E | R7: 2028E | S7: 2029E | T7: 2030E | U7: 25-'30 CAGR | V7: LT Hist Avg | W7: LT Hist Min | X7: LT Hist Max | Z7: (USDm, except EPS and shares) | AA7: 2025A | AB7: 2026E | AC7: 2027E | AD7: 2028E | AE7: 2029E | AF7: 2030E | AG7: 25-'30 CAGR | AH7: LT Hist Avg | AI7: LT Hist Min | AJ7: LT Hist Max
B9: Net sales | C9: =Model!BV144 -> 716924 | D9: =Model!CA144 -> 825522.47 | E9: =Model!CB144 -> 943961.71 | F9: =Model!CC144 -> 1069423.7 | G9: =Model!CD144 -> 1198711.7 | H9: =Model!CE144 -> 1330223 | I9: =IFERROR((H9/C9)^(1/5)-1,"n/m") -> 0.13159305 | N9: Net sales | O9: 716924 | P9: 831043.05 | Q9: 972979.46 | R9: 1130482.8 | S9: 1301136.4 | T9: 1484139.7 | U9: 0.15664567 | Z9: Net sales | AA9: 716924 | AB9: 820001.89 | AC9: 902684.54 | AD9: 982133.81 | AE9: 1055392.4 | AF9: 1121336.6 | AG9: 0.093585071
B10: Net sales y/y % | D10: =IFERROR(D9/C9-1,"") -> 0.15147836 | E10: =IFERROR(E9/D9-1,"") -> 0.14347185 | F10: =IFERROR(F9/E9-1,"") -> 0.13291004 | G10: =IFERROR(G9/F9-1,"") -> 0.12089497 | H10: =IFERROR(H9/G9-1,"") -> 0.10971062 | N10: Net sales y/y % | P10: 0.15917873 | Q10: 0.17079308 | R10: 0.16187733 | S10: 0.15095645 | T10: 0.14064882 | Z10: Net sales y/y % | AB10: 0.14377799 | AC10: 0.10083226 | AD10: 0.088014443 | AE10: 0.074591281 | AF10: 0.062483043
B11: AWS segment net sales y/y % | C11: =Model!BV232 -> 0.1968184 | D11: =Model!CA232 -> 0.34890853 | E11: =Model!CB232 -> 0.28 | F11: =Model!CC232 -> 0.24 | G11: =Model!CD232 -> 0.2 | H11: =Model!CE232 -> 0.17 | N11: AWS segment net sales y/y % | O11: 0.1968184 | P11: 0.34890853 | Q11: 0.33 | R11: 0.29 | S11: 0.25 | T11: 0.22 | Z11: AWS segment net sales y/y % | AA11: 0.1968184 | AB11: 0.34890853 | AC11: 0.2 | AD11: 0.16 | AE11: 0.12 | AF11: 0.09
B12: Adjusted EBITDA (model definition) | C12: =Model!BV202 -> 152471 | D12: =Model!CA202 -> 191718.14 | E12: =Model!CB202 -> 248439.41 | F12: =Model!CC202 -> 297699.81 | G12: =Model!CD202 -> 346306.16 | H12: =Model!CE202 -> 395464.06 | I12: =IFERROR((H12/C12)^(1/5)-1,"n/m") -> 0.20999605 | N12: Adjusted EBITDA (model definition) | O12: 152471 | P12: 196379.81 | Q12: 265817.55 | R12: 324590.57 | S12: 386199.23 | T12: 452333.43 | U12: 0.2429518 | Z12: Adjusted EBITDA (model definition) | AA12: 152471 | AB12: 187055.79 | AC12: 223707.88 | AD12: 260600.95 | AE12: 293137.12 | AF12: 322431.63 | AG12: 0.16158255
B13: Adjusted EBITDA margin % | C13: =IFERROR(C12/C9,"") -> 0.21267387 | D13: =IFERROR(D12/D9,"") -> 0.23223854 | E13: =IFERROR(E12/E9,"") -> 0.26318801 | F13: =IFERROR(F12/F9,"") -> 0.27837405 | G13: =IFERROR(G12/G9,"") -> 0.28889864 | H13: =IFERROR(H12/H9,"") -> 0.29729154 | J13: =IFERROR(AVERAGE(Model!C203,Model!D203,Model!E203,Model!F203,Model!G203,Model!H203,Model!I203,Model!N203,Model!S203,Model!X203,Model!AC203,Model!AH203,Model!AM203,Model!AR203,Model!AW203,Model!BB203,Model!BG203,Model!BL203,Model!BQ203,Model!BV203),"") -> 0.095523357 | K13: =IFERROR(MIN(Model!C203,Model!D203,Model!E203,Model!F203,Model!G203,Model!H203,Model!I203,Model!N203,Model!S203,Model!X203,Model!AC203,Model!AH203,Model!AM203,Model!AR203,Model!AW203,Model!BB203,Model!BG203,Model!BL203,Model!BQ203,Model!BV203),"") -> 0.040455935 | L13: =IFERROR(MAX(Model!C203,Model!D203,Model!E203,Model!F203,Model!G203,Model!H203,Model!I203,Model!N203,Model!S203,Model!X203,Model!AC203,Model!AH203,Model!AM203,Model!AR203,Model!AW203,Model!BB203,Model!BG203,Model!BL203,Model!BQ203,Model!BV203),"") -> 0.21267387 | N13: Adjusted EBITDA margin % | O13: 0.21267387 | P13: 0.23630522 | Q13: 0.27319955 | R13: 0.28712563 | S13: 0.29681686 | T13: 0.3047782 | V13: 0.095523357 | W13: 0.040455935 | X13: 0.21267387 | Z13: Adjusted EBITDA margin % | AA13: 0.21267387 | AB13: 0.22811629 | AC13: 0.24782509 | AD13: 0.26534159 | AE13: 0.27775178 | AF13: 0.28754225 | AH13: 0.095523357 | AI13: 0.040455935 | AJ13: 0.21267387
B15: Operating Income (GAAP) | C15: =Model!BV154 -> 79975 | D15: =Model!CA154 -> 106753.61 | E15: =Model!CB154 -> 133285.41 | F15: =Model!CC154 -> 160376.1 | G15: =Model!CD154 -> 188437.12 | H15: =Model!CE154 -> 219090.51 | I15: =IFERROR((H15/C15)^(1/5)-1,"n/m") -> 0.2233025 | N15: Operating Income (GAAP) | O15: 79975 | P15: 111238.59 | Q15: 149937.12 | R15: 185589.57 | S15: 224764.84 | T15: 269609.91 | U15: 0.27513545 | Z15: Operating Income (GAAP) | AA15: 79975 | AB15: 102267.95 | AC15: 109607.07 | AD15: 125809.37 | AE15: 140620.56 | AF15: 155395.75 | AG15: 0.14208119
B16: Operating income y/y % | D16: =IFERROR(D15/C15-1,"") -> 0.33483721 | E16: =IFERROR(E15/D15-1,"") -> 0.24853311 | F16: =IFERROR(F15/E15-1,"") -> 0.20325319 | G16: =IFERROR(G15/F15-1,"") -> 0.17497015 | H16: =IFERROR(H15/G15-1,"") -> 0.16267169 | N16: Operating income y/y % | P16: 0.39091708 | Q16: 0.34788759 | R16: 0.23778269 | S16: 0.2110855 | T16: 0.19951994 | Z16: Operating income y/y % | AB16: 0.27874898 | AC16: 0.071763668 | AD16: 0.14782161 | AE16: 0.11772728 | AF16: 0.10507132
B17: Operating margin (GAAP) % | C17: =IFERROR(C15/C9,"") -> 0.11155297 | D17: =IFERROR(D15/D9,"") -> 0.12931641 | E17: =IFERROR(E15/E9,"") -> 0.1411979 | F17: =IFERROR(F15/F9,"") -> 0.14996497 | G17: =IFERROR(G15/G9,"") -> 0.15719971 | H17: =IFERROR(H15/H9,"") -> 0.16470209 | J17: =IFERROR(AVERAGE(Model!C243,Model!D243,Model!E243,Model!F243,Model!G243,Model!H243,Model!I243,Model!N243,Model!S243,Model!X243,Model!AC243,Model!AH243,Model!AM243,Model!AR243,Model!AW243,Model!BB243,Model!BG243,Model!BL243,Model!BQ243,Model!BV243),"") -> 0.042588227 | K17: =IFERROR(MIN(Model!C243,Model!D243,Model!E243,Model!F243,Model!G243,Model!H243,Model!I243,Model!N243,Model!S243,Model!X243,Model!AC243,Model!AH243,Model!AM243,Model!AR243,Model!AW243,Model!BB243,Model!BG243,Model!BL243,Model!BQ243,Model!BV243),"") -> 0.0020002697 | L17: =IFERROR(MAX(Model!C243,Model!D243,Model!E243,Model!F243,Model!G243,Model!H243,Model!I243,Model!N243,Model!S243,Model!X243,Model!AC243,Model!AH243,Model!AM243,Model!AR243,Model!AW243,Model!BB243,Model!BG243,Model!BL243,Model!BQ243,Model!BV243),"") -> 0.11155297 | N17: Operating margin (GAAP) % | O17: 0.11155297 | P17: 0.13385419 | Q17: 0.15410101 | R17: 0.16416842 | S17: 0.17274502 | T17: 0.18166073 | V17: 0.042588227 | W17: 0.0020002697 | X17: 0.11155297 | Z17: Operating margin (GAAP) % | AA17: 0.11155297 | AB17: 0.12471672 | AC17: 0.12142345 | AD17: 0.12809799 | AE17: 0.13324007 | AF17: 0.13858083 | AH17: 0.042588227 | AI17: 0.0020002697 | AJ17: 0.11155297
B19: Adjusted Net Income (model definition) | C19: =Model!BV220 -> 71517.69 | D19: =Model!CA220 -> 81602.866 | E19: =Model!CB220 -> 105559.4 | F19: =Model!CC220 -> 127702.65 | G19: =Model!CD220 -> 150300.09 | H19: =Model!CE220 -> 175129.33 | I19: =IFERROR((H19/C19)^(1/5)-1,"n/m") -> 0.19615947 | N19: Adjusted Net Income (model definition) | O19: 71517.69 | P19: 85235.706 | Q19: 119143.58 | R19: 146349.24 | S19: 177430.48 | T19: 213193.57 | U19: 0.24414823 | Z19: Adjusted Net Income (model definition) | AA19: 71517.69 | AB19: 77969.484 | AC19: 86283.648 | AD19: 99041.49 | AE19: 111534.77 | AF19: 125038.23 | AG19: 0.11821642
B21: FDSO (m) | C21: =Model!BV170 -> 10827 | D21: =Model!CA170 -> 10917.75 | E21: =Model!CB170 -> 11034.771 | F21: =Model!CC170 -> 11063.533 | G21: =Model!CD170 -> 10952.724 | H21: =Model!CE170 -> 10735.617 | I21: =IFERROR((H21/C21)^(1/5)-1,"n/m") -> -0.0016937926 | N21: FDSO (m) | O21: 10827 | P21: 10917.75 | Q21: 10882.428 | R21: 10702.914 | S21: 10473.543 | T21: 10120.458 | U21: -0.013406148 | Z21: FDSO (m) | AA21: 10827 | AB21: 10917.75 | AC21: 11038 | AD21: 11158 | AE21: 11278 | AF21: 11301.795 | AG21: 0.0086206563
B23: Adjusted EPS — Diluted ($) | C23: =Model!BV222 -> 6.6054946 | D23: =Model!CA222 -> 7.47433 | E23: =Model!CB222 -> 9.5660715 | F23: =Model!CC222 -> 11.542665 | G23: =Model!CD222 -> 13.722622 | H23: =Model!CE222 -> 16.312927 | I23: =IFERROR((H23/C23)^(1/5)-1,"n/m") -> 0.19818895 | N23: Adjusted EPS — Diluted ($) | O23: 6.6054946 | P23: 7.8070761 | Q23: 10.948253 | R23: 13.673775 | S23: 16.940826 | T23: 21.065605 | U23: 0.26105411 | Z23: Adjusted EPS — Diluted ($) | AA23: 6.6054946 | AB23: 7.1415341 | AC23: 7.8169639 | AD23: 8.8762762 | AE23: 9.8895878 | AF23: 11.063572 | AG23: 0.10865905
B24: EPS y/y % | D24: =IFERROR(D23/C23-1,"") -> 0.13153222 | E24: =IFERROR(E23/D23-1,"") -> 0.27985673 | F24: =IFERROR(F23/E23-1,"") -> 0.20662541 | G24: =IFERROR(G23/F23-1,"") -> 0.18886082 | H24: =IFERROR(H23/G23-1,"") -> 0.18876165 | N24: EPS y/y % | P24: 0.18190637 | Q24: 0.40234996 | R24: 0.24894589 | S24: 0.23892823 | T24: 0.24348157 | Z24: EPS y/y % | AB24: 0.081150549 | AC24: 0.09457769 | AD24: 0.13551454 | AE24: 0.11415954 | AF24: 0.11870916
B26: P / E (x) — assumed (adjusted EPS) | G26: 28 | H26: 28 | N26: P / E (x) — assumed (adjusted EPS) | S26: 32 | T26: 32 | Z26: P / E (x) — assumed (adjusted EPS) | AE26: 22 | AF26: 22
B27: Price Target ($) | G27: =G26*G23 -> 384.23342 | H27: =H26*H23 -> 456.76195 | N27: Price Target ($) | S27: =S26*S23 -> 542.10645 | T27: =T26*T23 -> 674.09937 | Z27: Price Target ($) | AD27: =AD26*AD23 -> 0 | AE27: =AE26*AE23 -> 217.57093 | AF27: =AF26*AF23 -> 243.39859
B28: Upside / (Downside) vs current | G28: =IFERROR(G27/$K$2-1,"") -> 0.47782085 | H28: =IFERROR(H27/$K$2-1,"") -> 0.75677674 | N28: Upside / (Downside) vs current | S28: =IFERROR(S27/$K$2-1,"") -> 1.0850248 | T28: =IFERROR(T27/$K$2-1,"") -> 1.5926899 | Z28: Upside / (Downside) vs current | AD28: =IFERROR(AD27/$K$2-1,"") -> -1 | AE28: =IFERROR(AE27/$K$2-1,"") -> -0.16318872 | AF28: =IFERROR(AF27/$K$2-1,"") -> -0.063851564
B29: IRR (to Dec-Y-1) | G29: =IFERROR((G27/$K$2)^(1/((DATE(2029-1,12,31)-$K$3)/365.25))-1,"") -> 0.19231923 | H29: =IFERROR((H27/$K$2)^(1/((DATE(2030-1,12,31)-$K$3)/365.25))-1,"") -> 0.1912577 | N29: IRR (to Dec-Y-1) | S29: =IFERROR((S27/$K$2)^(1/((DATE(2029-1,12,31)-$K$3)/365.25))-1,"") -> 0.39225278 | T29: =IFERROR((T27/$K$2)^(1/((DATE(2030-1,12,31)-$K$3)/365.25))-1,"") -> 0.34432861 | Z29: IRR (to Dec-Y-1) | AD29: =IFERROR((AD27/$K$2)^(1/((DATE(2028-1,12,31)-$K$3)/365.25))-1,"") -> -1 | AE29: =IFERROR((AE27/$K$2)^(1/((DATE(2029-1,12,31)-$K$3)/365.25))-1,"") -> -0.077101873 | AF29: =IFERROR((AF27/$K$2)^(1/((DATE(2030-1,12,31)-$K$3)/365.25))-1,"") -> -0.020284342
B31: Free Cash Flow | C31: =Model!BV277 -> 11194 | D31: =Model!CA277 -> -26742.759 | E31: =Model!CB277 -> 21226.413 | F31: =Model!CC277 -> 60379.489 | G31: =Model!CD277 -> 100541.79 | H31: =Model!CE277 -> 144462.64 | I31: =IFERROR((H31/C31)^(1/5)-1,"n/m") -> 0.66783871 | N31: Free Cash Flow | O31: 11194 | P31: -23140.363 | Q31: 39724.941 | R31: 82612.248 | S31: 129163.3 | T31: 182821.92 | U31: 0.74827035 | Z31: Free Cash Flow | AA31: 11194 | AB31: -30345.54 | AC31: -4754.8732 | AD31: 27502.165 | AE31: 61446.84 | AF31: 96489.918 | AG31: 0.53850647
B32: FCF % | C32: =IFERROR(C31/C9,"") -> 0.015613928 | D32: =IFERROR(D31/D9,"") -> -0.03239495 | E32: =IFERROR(E31/E9,"") -> 0.022486519 | F32: =IFERROR(F31/F9,"") -> 0.056459838 | G32: =IFERROR(G31/G9,"") -> 0.083874872 | H32: =IFERROR(H31/H9,"") -> 0.10860031 | J32: =IFERROR(AVERAGE(Model!C290,Model!D290,Model!E290,Model!F290,Model!G290,Model!H290,Model!I290,Model!N290,Model!S290,Model!X290,Model!AC290,Model!AH290,Model!AM290,Model!AR290,Model!AW290,Model!BB290,Model!BG290,Model!BL290,Model!BQ290,Model!BV290),"") -> 0.051422747 | K32: =IFERROR(MIN(Model!C290,Model!D290,Model!E290,Model!F290,Model!G290,Model!H290,Model!I290,Model!N290,Model!S290,Model!X290,Model!AC290,Model!AH290,Model!AM290,Model!AR290,Model!AW290,Model!BB290,Model!BG290,Model!BL290,Model!BQ290,Model!BV290),"") -> -0.022508527 | L32: =IFERROR(MAX(Model!C290,Model!D290,Model!E290,Model!F290,Model!G290,Model!H290,Model!I290,Model!N290,Model!S290,Model!X290,Model!AC290,Model!AH290,Model!AM290,Model!AR290,Model!AW290,Model!BB290,Model!BG290,Model!BL290,Model!BQ290,Model!BV290),"") -> 0.11913991 | N32: FCF % | O32: 0.015613928 | P32: -0.027844963 | Q32: 0.040828139 | R32: 0.073076963 | S32: 0.099269602 | T32: 0.12318376 | V32: 0.051422747 | W32: -0.022508527 | X32: 0.11913991 | Z32: FCF % | AA32: 0.015613928 | AB32: -0.03700667 | AC32: -0.0052674805 | AD32: 0.028002462 | AE32: 0.058221793 | AF32: 0.086049025 | AH32: 0.051422747 | AI32: -0.022508527 | AJ32: 0.11913991
B33: FCF / share ($) | C33: =IFERROR(C31/C21,"") -> 1.0338967 | D33: =IFERROR(D31/D21,"") -> -2.4494753 | E33: =IFERROR(E31/E21,"") -> 1.9235935 | F33: =IFERROR(F31/F21,"") -> 5.4575233 | G33: =IFERROR(G31/G21,"") -> 9.1796151 | H33: =IFERROR(H31/H21,"") -> 13.45639 | N33: FCF / share ($) | O33: 1.0338967 | P33: -2.1195176 | Q33: 3.6503746 | R33: 7.7186688 | S33: 12.33234 | T33: 18.06459 | Z33: FCF / share ($) | AA33: 1.0338967 | AB33: -2.7794683 | AC33: -0.43077308 | AD33: 2.4647934 | AE33: 5.4483809 | AF33: 8.5375745
B34: FCF Yield (on PT) | F34: =IFERROR(F33/F$27,"") | G34: =IFERROR(G33/G$27,"") -> 0.023890725 | H34: =IFERROR(H33/H$27,"") -> 0.0294604 | N34: FCF Yield (on PT) | R34: =IFERROR(R33/R$27,"") | S34: =IFERROR(S33/S$27,"") -> 0.022748927 | T34: =IFERROR(T33/T$27,"") -> 0.026798111 | Z34: FCF Yield (on PT) | AD34: =IFERROR(AD33/AD$27,"") | AE34: =IFERROR(AE33/AE$27,"") -> 0.02504186 | AF34: =IFERROR(AF33/AF$27,"") -> 0.035076515
B35: Adjusted EBITDA (leverage basis) | C35: =Model!BV202 -> 152471 | D35: =Model!CA202 -> 191718.14 | E35: =Model!CB202 -> 248439.41 | F35: =Model!CC202 -> 297699.81 | G35: =Model!CD202 -> 346306.16 | H35: =Model!CE202 -> 395464.06 | I35: =IFERROR((H35/C35)^(1/5)-1,"n/m") -> 0.20999605 | N35: Adjusted EBITDA (leverage basis) | O35: 152471 | P35: 196379.81 | Q35: 265817.55 | R35: 324590.57 | S35: 386199.23 | T35: 452333.43 | U35: 0.2429518 | Z35: Adjusted EBITDA (leverage basis) | AA35: 152471 | AB35: 187055.79 | AC35: 223707.88 | AD35: 260600.95 | AE35: 293137.12 | AF35: 322431.63 | AG35: 0.16158255
B36: Adjusted EBITDA % of net sales | C36: =IFERROR(C35/C9,"") -> 0.21267387 | D36: =IFERROR(D35/D9,"") -> 0.23223854 | E36: =IFERROR(E35/E9,"") -> 0.26318801 | F36: =IFERROR(F35/F9,"") -> 0.27837405 | G36: =IFERROR(G35/G9,"") -> 0.28889864 | H36: =IFERROR(H35/H9,"") -> 0.29729154 | J36: =IFERROR(AVERAGE(Model!C242,Model!D242,Model!E242,Model!F242,Model!G242,Model!H242,Model!I242,Model!N242,Model!S242,Model!X242,Model!AC242,Model!AH242,Model!AM242,Model!AR242,Model!AW242,Model!BB242,Model!BG242,Model!BL242,Model!BQ242,Model!BV242),"") -> 0.095523357 | K36: =IFERROR(MIN(Model!C242,Model!D242,Model!E242,Model!F242,Model!G242,Model!H242,Model!I242,Model!N242,Model!S242,Model!X242,Model!AC242,Model!AH242,Model!AM242,Model!AR242,Model!AW242,Model!BB242,Model!BG242,Model!BL242,Model!BQ242,Model!BV242),"") -> 0.040455935 | L36: =IFERROR(MAX(Model!C242,Model!D242,Model!E242,Model!F242,Model!G242,Model!H242,Model!I242,Model!N242,Model!S242,Model!X242,Model!AC242,Model!AH242,Model!AM242,Model!AR242,Model!AW242,Model!BB242,Model!BG242,Model!BL242,Model!BQ242,Model!BV242),"") -> 0.21267387 | N36: Adjusted EBITDA % of net sales | O36: 0.21267387 | P36: 0.23630522 | Q36: 0.27319955 | R36: 0.28712563 | S36: 0.29681686 | T36: 0.3047782 | V36: 0.095523357 | W36: 0.040455935 | X36: 0.21267387 | Z36: Adjusted EBITDA % of net sales | AA36: 0.21267387 | AB36: 0.22811629 | AC36: 0.24782509 | AD36: 0.26534159 | AE36: 0.27775178 | AF36: 0.28754225 | AH36: 0.095523357 | AI36: 0.040455935 | AJ36: 0.21267387
B38: Net Debt | C38: =Model!BV410 -> -54178 | D38: =Model!CA410 -> 12412.759 | E38: =Model!CB410 -> 0 | F38: =Model!CC410 -> 0 | G38: =Model!CD410 -> 0 | H38: =Model!CE410 -> 0 | N38: Net Debt | O38: -54178 | P38: 8810.3634 | Q38: 66454.387 | R38: 81147.644 | S38: 96549.807 | T38: 113083.36 | Z38: Net Debt | AA38: -54178 | AB38: 16015.54 | AC38: 24770.413 | AD38: 1268.2483 | AE38: -56178.592 | AF38: -80607.908
B39: Net Debt / Adjusted EBITDA (x) | C39: =IFERROR(C38/C35,"") -> -0.35533315 | D39: =IFERROR(D38/D35,"") -> 0.064744836 | E39: =IFERROR(E38/E35,"") -> 0 | F39: =IFERROR(F38/F35,"") -> 0 | G39: =IFERROR(G38/G35,"") -> 0 | H39: =IFERROR(H38/H35,"") -> 0 | N39: Net Debt / Adjusted EBITDA (x) | O39: -0.35533315 | P39: 0.044863896 | Q39: 0.25 | R39: 0.25 | S39: 0.25 | T39: 0.25 | Z39: Net Debt / Adjusted EBITDA (x) | AA39: -0.35533315 | AB39: 0.085619053 | AC39: 0.1107266 | AD39: 0.0048666294 | AE39: -0.19164612 | AF39: -0.25
B40: Share repurchases ($m; 2026E = 2H) | D40: =Model!CA301 -> 0 | E40: =Model!CB301 -> 1813.6534 | F40: =Model!CC301 -> 53379.489 | G40: =Model!CD301 -> 93541.787 | H40: =Model!CE301 -> 137462.64 | N40: Share repurchases ($m; 2026E = 2H) | P40: 0 | Q40: 87368.964 | R40: 87305.505 | S40: 134565.46 | T40: 189355.47 | AB40: 0 | AC40: 0 | AD40: 0 | AE40: 0 | AF40: 68060.601
B41: Implied avg buyback price ($) | D41: =Model!CA300 -> 260 | E41: =Model!CB300 -> 280.8 | F41: =Model!CC300 -> 303.264 | G41: =Model!CD300 -> 327.52512 | H41: =Model!CE300 -> 353.72713 | N41: Implied avg buyback price ($) | P41: 260 | Q41: 280.8 | R41: 303.264 | S41: 327.52512 | T41: 353.72713 | AB41: 260 | AC41: 280.8 | AD41: 303.264 | AE41: 327.52512 | AF41: 353.72713
B42: Shares repurchased (m) | D42: =Model!CA302 -> 0 | E42: =Model!CB302 -> 6.4588796 | F42: =Model!CC302 -> 176.01657 | G42: =Model!CD302 -> 285.60187 | H42: =Model!CE302 -> 388.6121 | N42: Shares repurchased (m) | P42: 0 | Q42: 311.14304 | R42: 287.88615 | S42: 410.85539 | T42: 535.31509 | AB42: 0 | AC42: 0 | AD42: 0 | AE42: 0 | AF42: 192.4099
B44: ROIC | C44: =Model!BV392 -> 0.19563945 | D44: =Model!CA392 -> 0.13376607 | E44: =Model!CB392 -> 0.14734354 | F44: =Model!CC392 -> 0.15560318 | G44: =Model!CD392 -> 0.1654085 | H44: =Model!CE392 -> 0.17835098 | J44: =IFERROR(AVERAGE(Model!C392,Model!D392,Model!E392,Model!F392,Model!G392,Model!H392,Model!I392,Model!N392,Model!S392,Model!X392,Model!AC392,Model!AH392,Model!AM392,Model!AR392,Model!AW392,Model!BB392,Model!BG392,Model!BL392,Model!BQ392,Model!BV392),"") -> 0.41136477 | K44: =IFERROR(MIN(Model!C392,Model!D392,Model!E392,Model!F392,Model!G392,Model!H392,Model!I392,Model!N392,Model!S392,Model!X392,Model!AC392,Model!AH392,Model!AM392,Model!AR392,Model!AW392,Model!BB392,Model!BG392,Model!BL392,Model!BQ392,Model!BV392),"") -> 0.034340836 | L44: =IFERROR(MAX(Model!C392,Model!D392,Model!E392,Model!F392,Model!G392,Model!H392,Model!I392,Model!N392,Model!S392,Model!X392,Model!AC392,Model!AH392,Model!AM392,Model!AR392,Model!AW392,Model!BB392,Model!BG392,Model!BL392,Model!BQ392,Model!BV392),"") -> 1.291021 | N44: ROIC | O44: 0.19563945 | P44: 0.13965114 | Q44: 0.16600746 | R44: 0.18009391 | S44: 0.19643581 | T44: 0.2171304 | V44: 0.41136477 | W44: 0.034340836 | X44: 1.291021 | Z44: ROIC | AA44: 0.19563945 | AB44: 0.12787934 | AC44: 0.12073904 | AD44: 0.12183922 | AE44: 0.12408749 | AF44: 0.12848849 | AH44: 0.41136477 | AI44: 0.034340836 | AJ44: 1.291021
B45: RONTA | C45: =Model!BV404 -> 0.1528023 | D45: =Model!CA404 -> 0.10691764 | E45: =Model!CB404 -> 0.12091553 | F45: =Model!CC404 -> 0.12987312 | G45: =Model!CD404 -> 0.13959359 | H45: =Model!CE404 -> 0.15155888 | J45: =IFERROR(AVERAGE(Model!C404,Model!D404,Model!E404,Model!F404,Model!G404,Model!H404,Model!I404,Model!N404,Model!S404,Model!X404,Model!AC404,Model!AH404,Model!AM404,Model!AR404,Model!AW404,Model!BB404,Model!BG404,Model!BL404,Model!BQ404,Model!BV404),"") -> 0.36434569 | K45: =IFERROR(MIN(Model!C404,Model!D404,Model!E404,Model!F404,Model!G404,Model!H404,Model!I404,Model!N404,Model!S404,Model!X404,Model!AC404,Model!AH404,Model!AM404,Model!AR404,Model!AW404,Model!BB404,Model!BG404,Model!BL404,Model!BQ404,Model!BV404),"") -> 0.014831273 | L45: =IFERROR(MAX(Model!C404,Model!D404,Model!E404,Model!F404,Model!G404,Model!H404,Model!I404,Model!N404,Model!S404,Model!X404,Model!AC404,Model!AH404,Model!AM404,Model!AR404,Model!AW404,Model!BB404,Model!BG404,Model!BL404,Model!BQ404,Model!BV404),"") -> 3.0727273 | N45: RONTA | O45: 0.1528023 | P45: 0.11162262 | Q45: 0.13635468 | R45: 0.15062661 | S45: 0.16636904 | T45: 0.18546877 | V45: 0.36434569 | W45: 0.014831273 | X45: 3.0727273 | Z45: RONTA | AA45: 0.1528023 | AB45: 0.10221143 | AC45: 0.0990297 | AD45: 0.10151061 | AE45: 0.1043333 | AF45: 0.1085351 | AH45: 0.36434569 | AI45: 0.014831273 | AJ45: 3.0727273
B47: Implied Market Cap (USDm) | F47: =F27*F21 -> 0 | G47: =G27*G21 -> 4208402.5 | H47: =H27*H21 -> 4903621.2 | N47: Implied Market Cap (USDm) | R47: =R27*R21 -> 0 | S47: =S27*S21 -> 5677775.2 | T47: =T27*T21 -> 6822194.3 | Z47: Implied Market Cap (USDm) | AD47: =AD27*AD21 -> 0 | AE47: =AE27*AE21 -> 2453765 | AF47: =AF27*AF21 -> 2750841
B48: (+) Net Debt & NCI | F48: =F38+Model!CC333 -> 0 | G48: =G38+Model!CD333 -> 0 | H48: =H38+Model!CE333 -> 0 | N48: (+) Net Debt & NCI | R48: =R38+Model!CC333 -> 81147.644 | S48: =S38+Model!CD333 -> 96549.807 | T48: =T38+Model!CE333 -> 113083.36 | Z48: (+) Net Debt & NCI | AD48: =AD38+Model!CC333 -> 1268.2483 | AE48: =AE38+Model!CD333 -> -56178.592 | AF48: =AF38+Model!CE333 -> -80607.908
B49: Implied Enterprise Value (USDm) | F49: =F47+F48 -> 0 | G49: =G47+G48 -> 4208402.5 | H49: =H47+H48 -> 4903621.2 | N49: Implied Enterprise Value (USDm) | R49: =R47+R48 -> 81147.644 | S49: =S47+S48 -> 5774325 | T49: =T47+T48 -> 6935277.7 | Z49: Implied Enterprise Value (USDm) | AD49: =AD47+AD48 -> 1268.2483 | AE49: =AE47+AE48 -> 2397586.4 | AF49: =AF47+AF48 -> 2670233.1
B50: Implied EV / Adjusted EBITDA (x) | F50: =IFERROR(F49/F35,"") -> 0 | G50: =IFERROR(G49/G35,"") -> 12.15226 | H50: =IFERROR(H49/H35,"") -> 12.399663 | N50: Implied EV / Adjusted EBITDA (x) | R50: =IFERROR(R49/R35,"") -> 0.25 | S50: =IFERROR(S49/S35,"") -> 14.951674 | T50: =IFERROR(T49/T35,"") -> 15.332224 | Z50: Implied EV / Adjusted EBITDA (x) | AD50: =IFERROR(AD49/AD35,"") -> 0.0048666294 | AE50: =IFERROR(AE49/AE35,"") -> 8.1790609 | AF50: =IFERROR(AF49/AF35,"") -> 8.2815482

Sheet DCF
B2: DCF VALUATION — AMAZON.COM, INC. (AMZN)
B4: 1. WACC BUILD
B5: Risk-free rate (US 10Y govt) | C5: 0.0425 | D5: Assumption (~US 10Y Treasury yield, Oct-2026; government rate sources not reachable from the build environment); update to market
B6: Equity risk premium | C6: 0.05 | D6: Assumption: US implied ERP ~4.5–5.5%
B7: Levered beta | C7: 1.1 | D7: Assumption: mega-cap internet / cloud peers (MSFT, GOOGL, META, ORCL) ~1.0–1.3; Amazon's retail cyclicality offset by AWS / advertising contract revenue; heavy AI capex raises operating leverage
B8: Cost of equity | C8: =C5+C7*C6 -> 0.0975
B9: Pre-tax cost of debt | C9: 0.053 | D9: AA / A1 issuer; 2026 issues priced at 3.85–6.25% (USD, 8-Ks 13-Mar and 9-Jul-2026); marginal long-dated cost ~5.3%
B10: Tax rate | C10: 0.19 | D10: Model 2027E+ effective tax rate (FY2025 19.6%)
B11: After-tax cost of debt | C11: =C9*(1-C10) -> 0.04293
B12: Target D/V | C12: 0.05 | D12: Gross debt ~$165bn after the Jul/Sep-2026 notes vs ~$2.8tn market cap ($260 × ~10.9bn shares) → ~5% D/V; net debt near zero
B13: WACC | C13: =C8*(1-C12)+C11*C12 -> 0.0947715
B15: Valuation date (live) | C15: =TODAY() -> 2026-10-12 00:00:00 | D15: Periods = (Dec-31-Year − today) / 365.25; cash flows assumed at year-end. 2026E UFCF is excluded (row 24) because valuation net debt is taken at YE2026E
B16: 2. UNLEVERED FREE CASH FLOW BUILD (USDm)
D17: 2026E | E17: 2027E | F17: 2028E | G17: 2029E | H17: 2030E | I17: 2031E | J17: 2032E | K17: 2033E | L17: 2034E | M17: 2035E | N17: Terminal | P17: CAGR 26–30E | Q17: CAGR 26–35E
B18: Adjusted operating income (full-cost: after SBC and all D&A) less cash special charges | D18: =Model!CA209-Model!CA211 -> 106154.61 | E18: =Model!CB209-Model!CB211 -> 133285.41 | F18: =Model!CC209-Model!CC211 -> 160376.1 | G18: =Model!CD209-Model!CD211 -> 188437.12 | H18: =Model!CE209-Model!CE211 -> 219090.51 | I18: =H18*(1+I$26) -> 238808.66 | J18: =I18*(1+J$26) -> 257913.35 | K18: =J18*(1+K$26) -> 275967.28 | L18: =K18*(1+L$26) -> 292525.32 | M18: =L18*(1+M$26) -> 307151.59 | P18: =(H18/D18)^(1/(COLUMNS(D18:H18)-1))-1 -> 0.19859146 | Q18: =(M18/D18)^(1/(COLUMNS(D18:M18)-1))-1 -> 0.12529973
B19: × (1 − tax rate) | D19: =1-$C$10 -> 0.81 | E19: =1-$C$10 -> 0.81 | F19: =1-$C$10 -> 0.81 | G19: =1-$C$10 -> 0.81 | H19: =1-$C$10 -> 0.81 | I19: =1-$C$10 -> 0.81 | J19: =1-$C$10 -> 0.81 | K19: =1-$C$10 -> 0.81 | ... M19: =1-$C$10 -> 0.81
B20: NOPAT | D20: =D18*D19 -> 85985.231 | E20: =E18*E19 -> 107961.18 | F20: =F18*F19 -> 129904.64 | G20: =G18*G19 -> 152634.07 | H20: =H18*H19 -> 177463.31 | I20: =I18*I19 -> 193435.01 | J20: =J18*J19 -> 208909.81 | K20: =K18*K19 -> 223533.5 | ... M20: =M18*M19 -> 248792.78
B21: plus depreciation of property & equipment (operating-lease, content and other amortization is reinvested — see Model cash-flow offset line) | D21: =Model!CA127 -> 59142.491 | E21: =Model!CB127 -> 84947.221 | F21: =Model!CC127 -> 103102.15 | G21: =Model!CD127 -> 119510.27 | H21: =Model!CE127 -> 133806.41 | I21: =H21*(1+I$26) -> 145848.99 | J21: =I21*(1+J$26) -> 157516.91 | K21: =J21*(1+K$26) -> 168543.09 | L21: =K21*(1+L$26) -> 178655.68 | M21: =L21*(1+M$26) -> 187588.46
B22: − Capex net of proceeds, acquisitions & investments (M&A lever 2027E–30E) and finance-lease principal | D22: =Model!CA258+Model!CA259+Model!CA260+Model!CA266 -> -244361.68 | E22: =Model!CB258+Model!CB259+Model!CB260+Model!CB266 -> -219768.97 | F22: =Model!CC258+Model!CC259+Model!CC260+Model!CC266 -> -227087.4 | G22: =Model!CD258+Model!CD259+Model!CD260+Model!CD266 -> -230200.11 | H22: =Model!CE258+Model!CE259+Model!CE260+Model!CE266 -> -228615.16 | I22: =H22*(1+I$26) -> -249190.52 | J22: =I22*(1+J$26) -> -269125.77 | K22: =J22*(1+K$26) -> -287964.57 | L22: =K22*(1+L$26) -> -305242.44 | M22: =L22*(1+M$26) -> -320504.57
B23: − Δ Working capital (CF statement) | D23: =Model!CA256 -> -16814.278 | E23: =Model!CB256 -> 12945.753 | F23: =Model!CC256 -> 15857.066 | G23: =Model!CD256 -> 16765.038 | H23: =Model!CE256 -> 16556.26 | I23: =H23*(1+I$26) -> 18046.324 | J23: =I23*(1+J$26) -> 19490.029 | K23: =J23*(1+K$26) -> 20854.332 | L23: =K23*(1+L$26) -> 22105.591 | M23: =L23*(1+M$26) -> 23210.871
B24: Unlevered FCF | D24: =0*(D20+D21+D22+D23) -> 0 | E24: =E20+E21+E22+E23 -> -13914.813 | F24: =F20+F21+F22+F23 -> 21776.457 | G24: =G20+G21+G22+G23 -> 58709.267 | H24: =H20+H21+H22+H23 -> 99210.825 | I24: =I20+I21+I22+I23 -> 108139.8 | J24: =J20+J21+J22+J23 -> 116790.98 | K24: =K20+K21+K22+K23 -> 124966.35 | L24: =L20+L21+L22+L23 -> 132464.33 | M24: =M20+M21+M22+M23 -> 139087.55 | N24: =M24*(1+$C$27) -> 143955.61 | P24: =IFERROR((H24/E24)^(1/(COLUMNS(E24:H24)-1))-1,"n/m") -> -2.924689 | Q24: =IFERROR((M24/E24)^(1/(COLUMNS(E24:M24)-1))-1,"n/m") -> n/m
B25: Terminal Value (Gordon Growth) | N25: =N24/($C$13-$C$27) -> 2408432.4
B26: Fade-period growth (2031E–35E; 9% → 5% linear) | I26: 0.09 | J26: =I26+($M$26-$I$26)/4 -> 0.08 | K26: =J26+($M$26-$I$26)/4 -> 0.07 | L26: =K26+($M$26-$I$26)/4 -> 0.06 | M26: 0.05
B27: Terminal growth rate | C27: 0.035
B29: Discount period (years) | D29: =(DATE(2026,12,31)-$C$15)/365.25 -> 0.21902806 | E29: =(DATE(2027,12,31)-$C$15)/365.25 -> 1.2183436 | F29: =(DATE(2028,12,31)-$C$15)/365.25 -> 2.220397 | G29: =(DATE(2029,12,31)-$C$15)/365.25 -> 3.2197125 | H29: =(DATE(2030,12,31)-$C$15)/365.25 -> 4.2190281 | I29: =(DATE(2031,12,31)-$C$15)/365.25 -> 5.2183436 | J29: =(DATE(2032,12,31)-$C$15)/365.25 -> 6.220397 | K29: =(DATE(2033,12,31)-$C$15)/365.25 -> 7.2197125 | L29: =(DATE(2034,12,31)-$C$15)/365.25 -> 8.2190281 | M29: =(DATE(2035,12,31)-$C$15)/365.25 -> 9.2183436 | N29: =M29 -> 9.2183436
B30: Discount factor | D30: =1/(1+$C$13)^D29 -> 0.98036332 | E30: =1/(1+$C$13)^E29 -> 0.89555134 | F30: =1/(1+$C$13)^F29 -> 0.81787373 | G30: =1/(1+$C$13)^G29 -> 0.74711884 | H30: =1/(1+$C$13)^H29 -> 0.68248502 | I30: =1/(1+$C$13)^I29 -> 0.62344271 | J30: =1/(1+$C$13)^J29 -> 0.56936704 | K30: =1/(1+$C$13)^K29 -> 0.52011066 | ... N30: =1/(1+$C$13)^N29 -> 0.43401288
B31: PV of UFCF | D31: =D24*D30 -> 0 | E31: =E24*E30 -> -12461.429 | F31: =F24*F30 -> 17810.392 | G31: =G24*G30 -> 43862.8 | H31: =H24*H30 -> 67709.902 | I31: =I24*I30 -> 67418.97 | J31: =J24*J30 -> 66496.937 | K31: =K24*K30 -> 64996.332 | ... M31: =M24*M30 -> 60365.789 | N31: =N25*N30 -> 1045290.7
D32: Amazon's operating income expenses stock-based compensation (not adjusted out) and all D&A, so NOPAT is taxed on full-cost adjusted operating income less cash special charges (settlements, severance). Only P&E depreciation is added back: operating-lease and content amortization is matched by lease payments / content spend (held flat in the Model). Finance-lease and financing-obligation principal is deducted with capex because leases are excluded from net debt. Non-marketable equity investments (Anthropic) are neither in UFCF nor added to EV (conservative; their marks sit in other income). 2026E UFCF is set to zero (cash flows already in YE2026E net debt).
B33: IMPLIED ROIC — invested capital roll-forward (USDm)
B34: Opening invested capital | D34: =Model!BV389 -> 356887 | E34: =D38 -> 558920.47 | F34: =E38 -> 680796.46 | G34: =F38 -> 788924.64 | H34: =G38 -> 882849.45 | I34: =H38 -> 961101.94 | J34: =I38 -> 1046397.1 | K34: =J38 -> 1138516 | L34: =K38 -> 1237083.1 | M34: =L38 -> 1341564.3
B35: plus Capex and acquisitions | D35: =-D22 -> 244361.68 | E35: =-E22 -> 219768.97 | F35: =-F22 -> 227087.4 | G35: =-G22 -> 230200.11 | H35: =-H22 -> 228615.16 | I35: =-I22 -> 249190.52 | J35: =-J22 -> 269125.77 | K35: =-K22 -> 287964.57 | ... M35: =-M22 -> 320504.57
B36: less P&E depreciation | D36: =-D21 -> -59142.491 | E36: =-E21 -> -84947.221 | F36: =-F21 -> -103102.15 | G36: =-G21 -> -119510.27 | H36: =-H21 -> -133806.41 | I36: =-I21 -> -145848.99 | J36: =-J21 -> -157516.91 | K36: =-K21 -> -168543.09 | ... M36: =-M21 -> -187588.46
B37: plus Δ Working capital investment | D37: =-D23 -> 16814.278 | E37: =-E23 -> -12945.753 | F37: =-F23 -> -15857.066 | G37: =-G23 -> -16765.038 | H37: =-H23 -> -16556.26 | I37: =-I23 -> -18046.324 | J37: =-J23 -> -19490.029 | K37: =-K23 -> -20854.332 | ... M37: =-M23 -> -23210.871
B38: Closing invested capital | D38: =SUM(D34:D37) -> 558920.47 | E38: =SUM(E34:E37) -> 680796.46 | F38: =SUM(F34:F37) -> 788924.64 | G38: =SUM(G34:G37) -> 882849.45 | H38: =SUM(H34:H37) -> 961101.94 | I38: =SUM(I34:I37) -> 1046397.1 | J38: =SUM(J34:J37) -> 1138516 | K38: =SUM(K34:K37) -> 1237083.1 | ... M38: =SUM(M34:M37) -> 1451269.5
B39: NOPAT (row 20) | D39: =D20 -> 85985.231 | E39: =E20 -> 107961.18 | F39: =F20 -> 129904.64 | G39: =G20 -> 152634.07 | H39: =H20 -> 177463.31 | I39: =I20 -> 193435.01 | J39: =J20 -> 208909.81 | K39: =K20 -> 223533.5 | ... M39: =M20 -> 248792.78
B40: Implied ROIC (NOPAT / avg. invested capital) | D40: =IFERROR(D39/AVERAGE(D34,D38),"") -> 0.18778015 | E40: =IFERROR(E39/AVERAGE(E34,E38),"") -> 0.1741707 | F40: =IFERROR(F39/AVERAGE(F34,F38),"") -> 0.17677454 | G40: =IFERROR(G39/AVERAGE(G34,G38),"") -> 0.18260131 | H40: =IFERROR(H39/AVERAGE(H34,H38),"") -> 0.19248155 | I40: =IFERROR(I39/AVERAGE(I34,I38),"") -> 0.19271243 | J40: =IFERROR(J39/AVERAGE(J34,J38),"") -> 0.1912294 | K40: =IFERROR(K39/AVERAGE(K34,K38),"") -> 0.18819126 | ... M40: =IFERROR(M39/AVERAGE(M34,M38),"") -> 0.17816512
B41: Reinvestment rate (net investment / NOPAT) | D41: =IFERROR(SUM(D35:D37)/D39,"") -> 2.3496299 | E41: =IFERROR(SUM(E35:E37)/E39,"") -> 1.1288872 | F41: =IFERROR(SUM(F35:F37)/F39,"") -> 0.83236582 | G41: =IFERROR(SUM(G35:G37)/G39,"") -> 0.61535936 | H41: =IFERROR(SUM(H35:H37)/H39,"") -> 0.44095022 | I41: =IFERROR(SUM(I35:I37)/I39,"") -> 0.44095022 | J41: =IFERROR(SUM(J35:J37)/J39,"") -> 0.44095022 | K41: =IFERROR(SUM(K35:K37)/K39,"") -> 0.44095022 | ... M41: =IFERROR(SUM(M35:M37)/M39,"") -> 0.44095022
B42: Implied terminal RONIC (g / reinvestment rate) | N42: =IFERROR($C$27/M41,"") -> 0.079374038
D43: Opening IC = Model 2025A book invested capital (equity + net debt; includes the non-marketable investments in other assets), rolled forward with DCF net investment (net capex + M&A + lease principal − P&E depreciation − ΔWC).
B44: 3. VALUATION SUMMARY
B45: Sum of PV (explicit + fade) | C45: =SUM(D31:M31) -> 439135.55
B46: PV of Terminal Value | C46: =N31 -> 1045290.7
B47: Enterprise Value | C47: =C45+C46 -> 1484426.2
B48: Less: Net debt + NCI (Model 2026E year end) | C48: =Model!CA410+Model!CA333 -> 12412.759 | D48: AMZN: no noncontrolling interests; net debt = debt (incl. Jul/Sep-2026 notes) − cash − marketable securities; finance-lease liabilities excluded (principal deducted in UFCF).
B49: Equity Value | C49: =C47-C48 -> 1472013.5
B50: Diluted shares (m, Model 2026E period end) | C50: =Model!CA417 -> 10977
B51: Implied share price ($) | C51: =C49/C50 -> 134.0998
B52: Current share price ($) | C52: =Model!CA416 -> 260
B53: Implied upside / (downside) | C53: =C51/C52-1 -> -0.48423155
B54: Required discount to DCF value for target IRR | C54: =1-((1+C13)/(1+H54))^H55 -> 0.13726597 | D54: vs. current | E54: Target IRR | H54: 0.15
B55: Max entry price for target IRR ($) | C55: =C51*(1-C54) -> 115.69246 | D55: =C55/C52-1 -> -0.55502901 | E55: Years for discount to close | H55: 3
B58: 4. SENSITIVITY: IMPLIED PRICE ($) — WACC × Terminal Growth
D60: WACC →
B61: Terminal growth ↓ | D61: =F61-0.01 -> 0.0847715 | E61: =F61-0.005 -> 0.0897715 | F61: =$C$13 -> 0.0947715 | G61: =F61+0.005 -> 0.0997715 | H61: =F61+0.01 -> 0.1047715
B62: =B64-0.01 -> 0.025 | D62: {=IFERROR((SUMPRODUCT($D$24:$M$24/(1+D$61)^$D$29:$M$29)+($M$24*(1+$B62)/(D$61-$B62))/(1+D$61)^$M$29-$C$48)/$C$50,"")} -> 143.88537 | E62: {=IFERROR((SUMPRODUCT($D$24:$M$24/(1+E$61)^$D$29:$M$29)+($M$24*(1+$B62)/(E$61-$B62))/(1+E$61)^$M$29-$C$48)/$C$50,"")} -> 130.81989 | F62: {=IFERROR((SUMPRODUCT($D$24:$M$24/(1+F$61)^$D$29:$M$29)+($M$24*(1+$B62)/(F$61-$B62))/(1+F$61)^$M$29-$C$48)/$C$50,"")} -> 119.66341 | G62: {=IFERROR((SUMPRODUCT($D$24:$M$24/(1+G$61)^$D$29:$M$29)+($M$24*(1+$B62)/(G$61-$B62))/(1+G$61)^$M$29-$C$48)/$C$50,"")} -> 110.03199 | H62: {=IFERROR((SUMPRODUCT($D$24:$M$24/(1+H$61)^$D$29:$M$29)+($M$24*(1+$B62)/(H$61-$B62))/(1+H$61)^$M$29-$C$48)/$C$50,"")} -> 101.63797
B63: =B64-0.005 -> 0.03 | D63: {=IFERROR((SUMPRODUCT($D$24:$M$24/(1+D$61)^$D$29:$M$29)+($M$24*(1+$B63)/(D$61-$B63))/(1+D$61)^$M$29-$C$48)/$C$50,"")} -> 153.80062 | E63: {=IFERROR((SUMPRODUCT($D$24:$M$24/(1+E$61)^$D$29:$M$29)+($M$24*(1+$B63)/(E$61-$B63))/(1+E$61)^$M$29-$C$48)/$C$50,"")} -> 138.89337 | F63: {=IFERROR((SUMPRODUCT($D$24:$M$24/(1+F$61)^$D$29:$M$29)+($M$24*(1+$B63)/(F$61-$B63))/(1+F$61)^$M$29-$C$48)/$C$50,"")} -> 126.3244 | G63: {=IFERROR((SUMPRODUCT($D$24:$M$24/(1+G$61)^$D$29:$M$29)+($M$24*(1+$B63)/(G$61-$B63))/(1+G$61)^$M$29-$C$48)/$C$50,"")} -> 115.59004 | H63: {=IFERROR((SUMPRODUCT($D$24:$M$24/(1+H$61)^$D$29:$M$29)+($M$24*(1+$B63)/(H$61-$B63))/(1+H$61)^$M$29-$C$48)/$C$50,"")} -> 106.32139
B64: =$C$27 -> 0.035 | D64: {=IFERROR((SUMPRODUCT($D$24:$M$24/(1+D$61)^$D$29:$M$29)+($M$24*(1+$B64)/(D$61-$B64))/(1+D$61)^$M$29-$C$48)/$C$50,"")} -> 165.70803 | E64: {=IFERROR((SUMPRODUCT($D$24:$M$24/(1+E$61)^$D$29:$M$29)+($M$24*(1+$B64)/(E$61-$B64))/(1+E$61)^$M$29-$C$48)/$C$50,"")} -> 148.44089 | F64: {=IFERROR((SUMPRODUCT($D$24:$M$24/(1+F$61)^$D$29:$M$29)+($M$24*(1+$B64)/(F$61-$B64))/(1+F$61)^$M$29-$C$48)/$C$50,"")} -> 134.0998 | G64: {=IFERROR((SUMPRODUCT($D$24:$M$24/(1+G$61)^$D$29:$M$29)+($M$24*(1+$B64)/(G$61-$B64))/(1+G$61)^$M$29-$C$48)/$C$50,"")} -> 122.00619 | H64: {=IFERROR((SUMPRODUCT($D$24:$M$24/(1+H$61)^$D$29:$M$29)+($M$24*(1+$B64)/(H$61-$B64))/(1+H$61)^$M$29-$C$48)/$C$50,"")} -> 111.67606
B65: =B64+0.005 -> 0.04 | D65: {=IFERROR((SUMPRODUCT($D$24:$M$24/(1+D$61)^$D$29:$M$29)+($M$24*(1+$B65)/(D$61-$B65))/(1+D$61)^$M$29-$C$48)/$C$50,"")} -> 180.27503 | E65: {=IFERROR((SUMPRODUCT($D$24:$M$24/(1+E$61)^$D$29:$M$29)+($M$24*(1+$B65)/(E$61-$B65))/(1+E$61)^$M$29-$C$48)/$C$50,"")} -> 159.90667 | F65: {=IFERROR((SUMPRODUCT($D$24:$M$24/(1+F$61)^$D$29:$M$29)+($M$24*(1+$B65)/(F$61-$B65))/(1+F$61)^$M$29-$C$48)/$C$50,"")} -> 143.2948 | G65: {=IFERROR((SUMPRODUCT($D$24:$M$24/(1+G$61)^$D$29:$M$29)+($M$24*(1+$B65)/(G$61-$B65))/(1+G$61)^$M$29-$C$48)/$C$50,"")} -> 129.4958 | H65: {=IFERROR((SUMPRODUCT($D$24:$M$24/(1+H$61)^$D$29:$M$29)+($M$24*(1+$B65)/(H$61-$B65))/(1+H$61)^$M$29-$C$48)/$C$50,"")} -> 117.85742
B66: =B64+0.01 -> 0.045 | D66: {=IFERROR((SUMPRODUCT($D$24:$M$24/(1+D$61)^$D$29:$M$29)+($M$24*(1+$B66)/(D$61-$B66))/(1+D$61)^$M$29-$C$48)/$C$50,"")} -> 198.50471 | E66: {=IFERROR((SUMPRODUCT($D$24:$M$24/(1+E$61)^$D$29:$M$29)+($M$24*(1+$B66)/(E$61-$B66))/(1+E$61)^$M$29-$C$48)/$C$50,"")} -> 173.93341 | F66: {=IFERROR((SUMPRODUCT($D$24:$M$24/(1+F$61)^$D$29:$M$29)+($M$24*(1+$B66)/(F$61-$B66))/(1+F$61)^$M$29-$C$48)/$C$50,"")} -> 154.33725 | G66: {=IFERROR((SUMPRODUCT($D$24:$M$24/(1+G$61)^$D$29:$M$29)+($M$24*(1+$B66)/(G$61-$B66))/(1+G$61)^$M$29-$C$48)/$C$50,"")} -> 138.35282 | H66: {=IFERROR((SUMPRODUCT($D$24:$M$24/(1+H$61)^$D$29:$M$29)+($M$24*(1+$B66)/(H$61-$B66))/(1+H$61)^$M$29-$C$48)/$C$50,"")} -> 125.07296
B69: 5. REVERSE DCF
B70: To solve for the market-implied path: Data ▸ What-If Analysis ▸ Goal Seek — set C51 to the current price (C52) by changing C27 (terminal growth) or the fade-period growth inputs (I26:M26).
B72: 6. MAUBOUSSIN EV / NOPAT — TWO-STAGE FRAMEWORK
B73: EV/NOPAT = 1/r + [g × (1 − r/ROIIC) / (r × (r − g))] × [1 − ((1+g)/(1+r))^N]
B74: Formula source: Mauboussin & Rappaport, "Expectations Investing" (2021); Counterpoint Global, "What Does a Price-Earnings Multiple Mean?" (2020).
B76: Input | C76: Value | D76: Rationale (Amazon characteristics)
B77: r (Cost of capital / WACC) | C77: =$C$13 -> 0.0947715 | D77: Linked from Section 1 WACC build
B78: g (NOPAT growth, Stage 1) | C78: 0.12 | D78: Model adjusted operating income CAGR 2025–30E (~15%): AWS growth on the AI build-out, advertising mix and retail margin expansion, partly offset by rising depreciation
B79: ROIIC (Return on incremental invested capital) | C79: 0.2 | D79: Advertising, AWS and third-party services earn high incremental returns on a shared logistics / data-centre base; the 2025–27 AI capex wave lowers near-term returns until utilisation catches up
B80: N (Years of value creation / CAP) | C80: 15 | D80: Scale in fulfilment, Prime ecosystem, AWS installed base and switching costs sustain a long competitive-advantage period; capital intensity and regulatory risk cap it
B82: Calculation | C82: Value
B83: Steady-state component: 1 / r | C83: =1/C77 -> 10.551695
B84: Value-creation factor: 1 − r / ROIIC | C84: =1-C77/C79 -> 0.5261425
B85: Growth multiplier: g × (1 − r/ROIIC) / (r × (r − g)) | C85: =C78*C84/(C77*(C77-C78)) -> -26.40678
B86: Time decay: 1 − ((1+g)/(1+r))^N | C86: =1-((1+C78)/(1+C77))^C80 -> -0.40740178
B87: PVGO component (growth value) | C87: =C85*C86 -> 10.758169
B88: Mauboussin EV / NOPAT (steady-state + PVGO) | C88: =C83+C87 -> 21.309864
B90: VALUATION — Applied to 2028E NOPAT | C90: USDm
B91: 2028E adjusted operating income less cash special charges | C91: =Model!CC209-Model!CC211 -> 160376.1
B92: Tax rate (from WACC build) | C92: =$C$10 -> 0.19
B93: 2028E NOPAT | C93: =C91*(1-C92) -> 129904.64
B94: × Mauboussin EV/NOPAT multiple | C94: =C88 -> 21.309864
B95: Implied Enterprise Value (2028E basis) | C95: =C93*C94 -> 2768250.2
B96: Less: YE2027 net debt + NCI (Model) | C96: =Model!CB410+Model!CB333 -> 0
B97: Implied Equity Value | C97: =C95-C96 -> 2768250.2
B98: Diluted shares 2028E (m, Model) | C98: =Model!CC417 -> 11035.525
B99: Implied share price 2028 ($) | C99: =C97/C98 -> 250.84899
B101: Current share price ($) | C101: =C52 -> 260
B102: Implied upside / (downside) | C102: =C99/C101-1 -> -0.035196179
B104: MARKET-IMPLIED EV/NOPAT TODAY | C104: USDm
B105: Current market cap (spot × diluted shares) | C105: =C52*C50 -> 2854020
B106: Plus: YE2026 net debt + NCI | C106: =C48 -> 12412.759
B107: Implied Enterprise Value (today) | C107: =C105+C106 -> 2866432.8
B108: AMZN market-implied EV/NOPAT (on 2028E NOPAT) | C108: =C107/C93 -> 22.065669
B110: Multiple gap (Mauboussin − Market) | C110: =C88-C108 -> -0.75580467
B111: Implied re-rating headroom | C111: =C88/C108-1 -> -0.034252515

Sheet Charts
B2: Amazon.com, Inc. — Historical Operating Performance (2006–2025)
B3: All historicals · USDm · Linked to Model. Bars = contribution to net-sales growth of North America + International vs AWS (pp; stacked = total growth; AWS a segment from 2015, recast 2013–14, so 2006–13 bars show total growth). Adjusted EBITDA = model definition (operating income + total D&A + Amazon-quantified special items). ROIC / RONTA on adjusted operating income (full-cost); blank (plotted at zero) where invested capital is negative (2006–11, n/m).
C7: 2006 | D7: 2007 | E7: 2008 | F7: 2009 | G7: 2010 | H7: 2011 | I7: 2012 | J7: 2013 | K7: 2014 | L7: 2015 | M7: 2016 | N7: 2017 | O7: 2018 | P7: 2019 | Q7: 2020 | R7: 2021 | S7: 2022 | T7: 2023 | U7: 2024 | V7: 2025
B8: North America + International contribution (pp; total growth before 2014) | C8: =IFERROR(Model!C85+Model!C86,IFERROR(Model!C231+0,0)) -> 0 | D8: =IFERROR(Model!D85+Model!D86,IFERROR(Model!D231+0,0)) -> 0.38502474 | E8: =IFERROR(Model!E85+Model!E86,IFERROR(Model!E231+0,0)) -> 0.29194473 | F8: =IFERROR(Model!F85+Model!F86,IFERROR(Model!F231+0,0)) -> 0.27877491 | G8: =IFERROR(Model!G85+Model!G86,IFERROR(Model!G231+0,0)) -> 0.39556897 | H8: =IFERROR(Model!H85+Model!H86,IFERROR(Model!H231+0,0)) -> 0.40559584 | I8: =IFERROR(Model!I85+Model!I86,IFERROR(Model!I231+0,0)) -> 0.27073237 | J8: =IFERROR(Model!N85+Model!N86,IFERROR(Model!N231+0,0)) -> 0.21866662 | K8: =IFERROR(Model!S85+Model!S86,IFERROR(Model!S231+0,0)) -> 0.17460914 | L8: =IFERROR(Model!X85+Model!X86,IFERROR(Model!X231+0,0)) -> 0.16611228 | M8: =IFERROR(Model!AC85+Model!AC86,IFERROR(Model!AC231+0,0)) -> 0.23028615 | N8: =IFERROR(Model!AH85+Model!AH86,IFERROR(Model!AH231+0,0)) -> 0.26943017 | O8: =IFERROR(Model!AM85+Model!AM86,IFERROR(Model!AM231+0,0)) -> 0.26325998 | P8: =IFERROR(Model!AR85+Model!AR86,IFERROR(Model!AR231+0,0)) -> 0.16430286 | Q8: =IFERROR(Model!AW85+Model!AW86,IFERROR(Model!AW231+0,0)) -> 0.33936019 | R8: =IFERROR(Model!BB85+Model!BB86,IFERROR(Model!BB231+0,0)) -> 0.17335468 | S8: =IFERROR(Model!BG85+Model!BG86,IFERROR(Model!BG231+0,0)) -> 0.055908408 | T8: =IFERROR(Model!BL85+Model!BL86,IFERROR(Model!BL231+0,0)) -> 0.09755381 | U8: =IFERROR(Model!BQ85+Model!BQ86,IFERROR(Model!BQ231+0,0)) -> 0.080682342 | V8: =IFERROR(Model!BV85+Model!BV86,IFERROR(Model!BV231+0,0)) -> 0.090595164
B9: AWS contribution (pp) | C9: =IFERROR(Model!C87+0,0) -> 0 | D9: =IFERROR(Model!D87+0,0) -> 0 | E9: =IFERROR(Model!E87+0,0) -> 0 | F9: =IFERROR(Model!F87+0,0) -> 0 | G9: =IFERROR(Model!G87+0,0) -> 0 | H9: =IFERROR(Model!H87+0,0) -> 0 | I9: =IFERROR(Model!I87+0,0) -> 0 | J9: =IFERROR(Model!N87+0,0) -> 0 | K9: =IFERROR(Model!S87+0,0) -> 0.020630742 | L9: =IFERROR(Model!X87+0,0) -> 0.036364454 | M9: =IFERROR(Model!AC87+0,0) -> 0.040549128 | N9: =IFERROR(Model!AH87+0,0) -> 0.038533095 | O9: =IFERROR(Model!AM87+0,0) -> 0.046079633 | P9: =IFERROR(Model!AR87+0,0) -> 0.040238399 | Q9: =IFERROR(Model!AW87+0,0) -> 0.036874113 | R9: =IFERROR(Model!BB87+0,0) -> 0.043598989 | S9: =IFERROR(Model!BG87+0,0) -> 0.038086765 | T9: =IFERROR(Model!BL87+0,0) -> 0.020741931 | U9: =IFERROR(Model!BQ87+0,0) -> 0.02922658 | V9: =IFERROR(Model!BV87+0,0) -> 0.033182383
C11: =C7 -> 2006 | D11: =D7 -> 2007 | E11: =E7 -> 2008 | F11: =F7 -> 2009 | G11: =G7 -> 2010 | H11: =H7 -> 2011 | I11: =I7 -> 2012 | J11: =J7 -> 2013 | ... V11: =V7 -> 2025
B12: Adjusted EBITDA (model) | C12: =Model!C202 -> 594 | D12: =Model!D202 -> 901 | E12: =Model!E202 -> 1129 | F12: =Model!F202 -> 1507 | G12: =Model!G202 -> 1974 | H12: =Model!H202 -> 1945 | I12: =Model!I202 -> 2835 | J12: =Model!N202 -> 3998 | K12: =Model!S202 -> 4924 | L12: =Model!X202 -> 8514 | M12: =Model!AC202 -> 12302 | N12: =Model!AH202 -> 15584 | O12: =Model!AM202 -> 27762 | P12: =Model!AR202 -> 36330 | Q12: =Model!AW202 -> 48150 | R12: =Model!BB202 -> 59175 | S12: =Model!BG202 -> 56869 | T12: =Model!BL202 -> 86015 | U12: =Model!BQ202 -> 121388 | V12: =Model!BV202 -> 152471
B13: Operating Income (GAAP) | C13: =Model!C154 -> 389 | D13: =Model!D154 -> 655 | E13: =Model!E154 -> 842 | F13: =Model!F154 -> 1129 | G13: =Model!G154 -> 1406 | H13: =Model!H154 -> 862 | I13: =Model!I154 -> 676 | J13: =Model!N154 -> 745 | K13: =Model!S154 -> 178 | L13: =Model!X154 -> 2233 | M13: =Model!AC154 -> 4186 | N13: =Model!AH154 -> 4106 | O13: =Model!AM154 -> 12421 | P13: =Model!AR154 -> 14541 | Q13: =Model!AW154 -> 22899 | R13: =Model!BB154 -> 24879 | S13: =Model!BG154 -> 12248 | T13: =Model!BL154 -> 36852 | U13: =Model!BQ154 -> 68593 | V13: =Model!BV154 -> 79975
B14: Adj. EBITDA Margin % | C14: =Model!C242 -> 0.055457007 | D14: =Model!D242 -> 0.060734749 | E14: =Model!E242 -> 0.058906397 | F14: =Model!F242 -> 0.061487617 | G14: =Model!G242 -> 0.057712548 | H14: =Model!H242 -> 0.040455935 | I14: =Model!I242 -> 0.046404662 | J14: =Model!N242 -> 0.053699028 | K14: =Model!S242 -> 0.055333303 | L14: =Model!X242 -> 0.079565632 | M14: =Model!AC242 -> 0.09046453 | N14: =Model!AH242 -> 0.08761652 | O14: =Model!AM242 -> 0.11920803 | P14: =Model!AR242 -> 0.12950856 | Q14: =Model!AW242 -> 0.12472025 | R14: =Model!BB242 -> 0.12595196 | S14: =Model!BG242 -> 0.11064374 | T14: =Model!BL242 -> 0.14964726 | U14: =Model!BQ242 -> 0.19027555 | V14: =Model!BV242 -> 0.21267387
B15: GAAP Op. Margin % | C15: =Model!C243 -> 0.036317804 | D15: =Model!D243 -> 0.044152342 | E15: =Model!E243 -> 0.043931963 | F15: =Model!F243 -> 0.046064711 | G15: =Model!G243 -> 0.041106303 | H15: =Model!H243 -> 0.017929571 | I15: =Model!I243 -> 0.011065097 | J15: =Model!N243 -> 0.010006447 | K15: =Model!S243 -> 0.0020002697 | L15: =Model!X243 -> 0.020867989 | M15: =Model!AC243 -> 0.030782354 | N15: =Model!AH243 -> 0.023084794 | O15: =Model!AM243 -> 0.053334879 | P15: =Model!AR243 -> 0.051835507 | Q15: =Model!AW243 -> 0.059314 | R15: =Model!BB243 -> 0.052954098 | S15: =Model!BG243 -> 0.023829582 | T15: =Model!BL243 -> 0.064114408 | U15: =Model!BQ243 -> 0.10751945 | V15: =Model!BV243 -> 0.11155297
C17: =C7 -> 2006 | D17: =D7 -> 2007 | E17: =E7 -> 2008 | F17: =F7 -> 2009 | G17: =G7 -> 2010 | H17: =H7 -> 2011 | I17: =I7 -> 2012 | J17: =J7 -> 2013 | ... V17: =V7 -> 2025
B18: ROIC | C18: =IFERROR(Model!C392+0,"") | D18: =IFERROR(Model!D392+0,"") | E18: =IFERROR(Model!E392+0,"") | F18: =IFERROR(Model!F392+0,"") | G18: =IFERROR(Model!G392+0,"") | H18: =IFERROR(Model!H392+0,"") | I18: =IFERROR(Model!I392+0,"") -> 0.9965602 | J18: =IFERROR(Model!N392+0,"") -> 0.40461225 | K18: =IFERROR(Model!S392+0,"") -> 0.034340836 | L18: =IFERROR(Model!X392+0,"") -> 0.65387994 | M18: =IFERROR(Model!AC392+0,"") -> 1.291021 | N18: =IFERROR(Model!AH392+0,"") -> 0.1547405 | O18: =IFERROR(Model!AM392+0,"") -> 0.40788141 | P18: =IFERROR(Model!AR392+0,"") -> 0.38034099 | Q18: =IFERROR(Model!AW392+0,"") -> 0.48632594 | R18: =IFERROR(Model!BB392+0,"") -> 0.24864424 | S18: =IFERROR(Model!BG392+0,"") -> 0.094862135 | T18: =IFERROR(Model!BL392+0,"") -> 0.16632719 | U18: =IFERROR(Model!BQ392+0,"") -> 0.24393059 | V18: =IFERROR(Model!BV392+0,"") -> 0.19563945
B19: RONTA | C19: =IFERROR(Model!C404+0,"") | D19: =IFERROR(Model!D404+0,"") | E19: =IFERROR(Model!E404+0,"") | F19: =IFERROR(Model!F404+0,"") | G19: =IFERROR(Model!G404+0,"") | H19: =IFERROR(Model!H404+0,"") | I19: =IFERROR(Model!I404+0,"") -> 3.0727273 | J19: =IFERROR(Model!N404+0,"") -> 0.17771485 | K19: =IFERROR(Model!S404+0,"") -> 0.014831273 | L19: =IFERROR(Model!X404+0,"") -> 0.16307205 | M19: =IFERROR(Model!AC404+0,"") -> 0.24379491 | N19: =IFERROR(Model!AH404+0,"") -> 0.11432064 | O19: =IFERROR(Model!AM404+0,"") -> 0.27818475 | P19: =IFERROR(Model!AR404+0,"") -> 0.17514833 | Q19: =IFERROR(Model!AW404+0,"") -> 0.2114454 | R19: =IFERROR(Model!BB404+0,"") -> 0.13672396 | S19: =IFERROR(Model!BG404+0,"") -> 0.063207682 | T19: =IFERROR(Model!BL404+0,"") -> 0.11556803 | U19: =IFERROR(Model!BQ404+0,"") -> 0.18129816 | V19: =IFERROR(Model!BV404+0,"") -> 0.1528023
B20: Adj. EBITDA margin % | C20: =IFERROR(Model!C242+0,NA()) -> 0.055457007 | D20: =IFERROR(Model!D242+0,NA()) -> 0.060734749 | E20: =IFERROR(Model!E242+0,NA()) -> 0.058906397 | F20: =IFERROR(Model!F242+0,NA()) -> 0.061487617 | G20: =IFERROR(Model!G242+0,NA()) -> 0.057712548 | H20: =IFERROR(Model!H242+0,NA()) -> 0.040455935 | I20: =IFERROR(Model!I242+0,NA()) -> 0.046404662 | J20: =IFERROR(Model!N242+0,NA()) -> 0.053699028 | K20: =IFERROR(Model!S242+0,NA()) -> 0.055333303 | L20: =IFERROR(Model!X242+0,NA()) -> 0.079565632 | M20: =IFERROR(Model!AC242+0,NA()) -> 0.09046453 | N20: =IFERROR(Model!AH242+0,NA()) -> 0.08761652 | O20: =IFERROR(Model!AM242+0,NA()) -> 0.11920803 | P20: =IFERROR(Model!AR242+0,NA()) -> 0.12950856 | Q20: =IFERROR(Model!AW242+0,NA()) -> 0.12472025 | R20: =IFERROR(Model!BB242+0,NA()) -> 0.12595196 | S20: =IFERROR(Model!BG242+0,NA()) -> 0.11064374 | T20: =IFERROR(Model!BL242+0,NA()) -> 0.14964726 | U20: =IFERROR(Model!BQ242+0,NA()) -> 0.19027555 | V20: =IFERROR(Model!BV242+0,NA()) -> 0.21267387
B21: FCF margin % | C21: =IFERROR(Model!C290+0,NA()) -> 0.045373915 | D21: =IFERROR(Model!D290+0,NA()) -> 0.079609033 | E21: =IFERROR(Model!E290+0,NA()) -> 0.071167693 | F21: =IFERROR(Model!F290+0,NA()) -> 0.11913991 | G21: =IFERROR(Model!G290+0,NA()) -> 0.073558648 | H21: =IFERROR(Model!H290+0,NA()) -> 0.04351353 | I21: =IFERROR(Model!I290+0,NA()) -> 0.0064655525 | J21: =IFERROR(Model!N290+0,NA()) -> 0.027279321 | K21: =IFERROR(Model!S290+0,NA()) -> 0.021901829 | L21: =IFERROR(Model!X290+0,NA()) -> 0.068510177 | M21: =IFERROR(Model!AC290+0,NA()) -> 0.07137447 | N21: =IFERROR(Model!AH290+0,NA()) -> 0.047091631 | O21: =IFERROR(Model!AM290+0,NA()) -> 0.083302202 | P21: =IFERROR(Model!AR290+0,NA()) -> 0.092060516 | Q21: =IFERROR(Model!AW290+0,NA()) -> 0.080349372 | R21: =IFERROR(Model!BB290+0,NA()) -> -0.019303055 | S21: =IFERROR(Model!BG290+0,NA()) -> -0.022508527 | T21: =IFERROR(Model!BL290+0,NA()) -> 0.064046557 | U21: =IFERROR(Model!BQ290+0,NA()) -> 0.059908239 | V21: =IFERROR(Model!BV290+0,NA()) -> 0.015613928
