Workbook

Sheet Model
AU1: SCENARIO SWITCH ▼ (Bull / Base / Bear) — drives all scenario-linked forecast drivers
B2: Booz Allen Hamilton Holding Corporation (NYSE: BAH) — 3-Statement Financial Model | AU2: Base
B3: US GAAP as reported · USD millions (per-share data in USD; shares in millions) · Fiscal years ended 31 March (2027 = Apr-2026 – Mar-2027) · Source: Booz Allen Forms 10-K / 10-Q, Form 8-K earnings releases (Ex. 99.1), deal and financing 8-Ks and the Jul-2026 424B2, SEC EDGAR (CIK 1443646); XBRL company facts; investor-relations releases are the same documents as filed on EDGAR
B4: Basis notes: as originally reported in each period's release; one reportable segment (revenue by customer type: Defense / Intelligence / Civil / Global Commercial to FY2026, National Security / Civil & Commercial from Q1 FY2027); USD thousands to Q3 FY2025, millions from Q4 FY2025. Acquisitions: Liberty Jun-21, EverWatch Oct-22, PGSC FY25, Defy Apr-26, Ultra Mission Solutions 24-Aug-26 ($720m). Q2–Q4/27E calibrated to FY27 revenue and adjusted EBITDA guidance (22-May-2026, reiterated 24-Jul-2026; assumed to exclude Ultra).
AW5: Forecast | AX5: Historical | AY5: Historical | AZ5: Historical
B6: (USDm) | C6: 2012 | D6: 2013 | E6: 2014 | F6: 2015 | G6: 2016 | H6: 2017 | I6: 2018 | J6: 2019 | K6: 2020 | L6: 2021 | M6: Q1/22 | N6: Q2/22 | O6: Q3/22 | P6: Q4/22 | Q6: 2022 | R6: Q1/23 | S6: Q2/23 | T6: Q3/23 | U6: Q4/23 | V6: 2023 | W6: Q1/24 | X6: Q2/24 | Y6: Q3/24 | Z6: Q4/24 | AA6: 2024 | AB6: Q1/25 | AC6: Q2/25 | AD6: Q3/25 | AE6: Q4/25 | AF6: 2025 | AG6: Q1/26 | AH6: Q2/26 | AI6: Q3/26 | AJ6: Q4/26 | AK6: 2026 | AL6: Q1/27 | AM6: Q2/27E | AN6: Q3/27E | AO6: Q4/27E | AP6: 2027E | AQ6: 2028E | AR6: 2029E | AS6: 2030E | AT6: 2031E | AU6: Modelling Notes | AW6: 5Y CAGR | AX6: 5Y CAGR | AY6: 10Y CAGR | AZ6: 14Y CAGR
AW7: 26-'31 | AX7: 21-'26 | AY7: 16-'26 | AZ7: 12-'26
B8: REVENUE BUILD — CUSTOMER TYPE (NATIONAL SECURITY · CIVIL & COMMERCIAL) · ULTRA MISSION SOLUTIONS · BACKLOG | AU8: REVENUE BUILD — modelling logic (one reportable segment: revenue by customer type → + Ultra Mission Solutions (closed 24-Aug-2026) + future M&A = revenue; adjusted EBITDA = revenue × margin → GAAP P&L)
BC9: SCENARIO INPUT TABLE — driver assumptions per Bull / Base / Bear | BD9: Bull | BE9: Base | BF9: Bear | BG9: Bull / Bear = Base + Δ (Δ inputs on each block header). Outlook block = high / mid / low end of the FY27 guidance ranges.
B10: National Security (Defense + Intelligence customers; one customer type from Q1 FY2027) | AU10: NATIONAL SECURITY — modelling logic
B11: National Security revenue (Defense + Intelligence) | H11: 4044.19 | I11: 4324.591 | J11: 4681.441 | K11: 5182.974 | L11: 5470.213 | M11: 1352.682 | N11: 1392.743 | O11: 1315.148 | P11: 1467.936 | Q11: 5528.51 | R11: 1428.874 | S11: 1451.651 | T11: 1462.762 | U11: 1561.085 | V11: 5904.372 | W11: 1700.814 | X11: 1715.117 | Y11: 1633.019 | Z11: 1781.234 | AA11: 6830.184 | AB11: 1877.909 | AC11: 2040.528 | AD11: 1905.873 | AE11: 1985.69 | AF11: 7810 | AG11: 2001 | AH11: 2063 | AI11: 1888 | AJ11: 2017 | AK11: 7969 | AL11: 2028 | AM11: =AH11*(1+AM12) -> 2254.2335 | AN11: =AI11*(1+AN12) -> 2063.0116 | AO11: =AJ11*(1+AO12) -> 2203.9695 | AP11: =SUM(AL11,AM11,AN11,AO11) -> 8549.2146 | AQ11: =AP11*(1+AQ12) -> 8891.1832 | AR11: =AQ11*(1+AR12) -> 9335.7424 | AS11: =AR11*(1+AS12) -> 9802.5295 | AT11: =AS11*(1+AT12) -> 10292.656 | AU11: Revenue by customer type (10-Q / 10-K revenue note; FY2017–18 from the FY2019 10-K comparatives; Q4 = fiscal year − nine months). Q2–Q4/27E: prior-year quarter × (1 + growth). 2028E+: prior year × (1 + scenario lever). Excludes Ultra (own block below). | AW11: =IFERROR((AT11/AK11)^(1/5)-1,"n/m") -> 0.052506353 | AX11: =IFERROR((AK11/L11)^(1/5)-1,"n/m") -> 0.078151814 | AY11: =IFERROR((AK11/G11)^(1/10)-1,"n/m") -> n/m | AZ11: =IFERROR((AK11/C11)^(1/14)-1,"n/m") -> n/m | BC11: FY27 guidance — Q4 FY26 release (22-May-2026), reiterated in the Q1 FY27 release (24-Jul-2026) | BD11: High | BE11: Mid | BF11: Low | BG11: Revenue $11.2–11.7bn (0–4% growth), adjusted EBITDA $1,240–1,290m (~11% margin), adjusted diluted EPS $6.00–6.35, free cash flow $825–925m; effective tax rate 20–23%, average diluted shares 118–120m, capex ~$220m ($105m new headquarters). Assumed to exclude Ultra (see the Ultra block).
B12: y/y % | D12: =IF(AND(ISNUMBER(D11),ISNUMBER(C11)),IFERROR(D11/C11-1,""),"") | E12: =IF(AND(ISNUMBER(E11),ISNUMBER(D11)),IFERROR(E11/D11-1,""),"") | F12: =IF(AND(ISNUMBER(F11),ISNUMBER(E11)),IFERROR(F11/E11-1,""),"") | G12: =IF(AND(ISNUMBER(G11),ISNUMBER(F11)),IFERROR(G11/F11-1,""),"") | H12: =IF(AND(ISNUMBER(H11),ISNUMBER(G11)),IFERROR(H11/G11-1,""),"") | I12: =IF(AND(ISNUMBER(I11),ISNUMBER(H11)),IFERROR(I11/H11-1,""),"") -> 0.06933428 | J12: =IF(AND(ISNUMBER(J11),ISNUMBER(I11)),IFERROR(J11/I11-1,""),"") -> 0.082516474 | K12: =IF(AND(ISNUMBER(K11),ISNUMBER(J11)),IFERROR(K11/J11-1,""),"") -> 0.10713218 | L12: =IF(AND(ISNUMBER(L11),ISNUMBER(K11)),IFERROR(L11/K11-1,""),"") -> 0.055419726 | Q12: =IF(AND(ISNUMBER(Q11),ISNUMBER(L11)),IFERROR(Q11/L11-1,""),"") -> 0.010657172 | R12: =IF(AND(ISNUMBER(R11),ISNUMBER(M11)),IFERROR(R11/M11-1,""),"") -> 0.056326616 | S12: =IF(AND(ISNUMBER(S11),ISNUMBER(N11)),IFERROR(S11/N11-1,""),"") -> 0.042296389 | T12: =IF(AND(ISNUMBER(T11),ISNUMBER(O11)),IFERROR(T11/O11-1,""),"") -> 0.11224136 | U12: =IF(AND(ISNUMBER(U11),ISNUMBER(P11)),IFERROR(U11/P11-1,""),"") -> 0.063455764 | V12: =IF(AND(ISNUMBER(V11),ISNUMBER(Q11)),IFERROR(V11/Q11-1,""),"") -> 0.06798613 | W12: =IF(AND(ISNUMBER(W11),ISNUMBER(R11)),IFERROR(W11/R11-1,""),"") -> 0.19031769 | X12: =IF(AND(ISNUMBER(X11),ISNUMBER(S11)),IFERROR(X11/S11-1,""),"") -> 0.18149404 | ... AL12: =IF(AND(ISNUMBER(AL11),ISNUMBER(AG11)),IFERROR(AL11/AG11-1,""),"") -> 0.013493253 | AM12: =AM13+$AM$87 -> 0.092696824 | AN12: =AN13+$AM$87 -> 0.092696824 | AO12: =AO13+$AM$87 -> 0.092696824 | AP12: =IF(AND(ISNUMBER(AP11),ISNUMBER(AK11)),IFERROR(AP11/AK11-1,""),"") -> 0.072808965 | AQ12: =CHOOSE(MATCH($AU$2,{"Bull","Base","Bear"},0),$BD$35,$BE$35,$BF$35) -> 0.04 | AR12: =CHOOSE(MATCH($AU$2,{"Bull","Base","Bear"},0),$BD$36,$BE$36,$BF$36) -> 0.05 | AS12: =CHOOSE(MATCH($AU$2,{"Bull","Base","Bear"},0),$BD$37,$BE$37,$BF$37) -> 0.05 | AT12: =CHOOSE(MATCH($AU$2,{"Bull","Base","Bear"},0),$BD$38,$BE$38,$BF$38) -> 0.05 | AU12: Q2–Q4/27E: Q1/27 y/y growth + guidance-calibration Δ (Group block). 2028E–2031E: scenario lever (Bull/Base/Bear table →). | BC12: FY27 revenue ($m; legacy basis, excl. Ultra) | BD12: 11700 | BE12: 11450 | BF12: 11200 | BG12: Guided $11.2–11.7bn. Drives the Q2–Q4/27E revenue calibration.
B13: Q2–Q4/27E growth before calibration (Q1/27 y/y) | AM13: =IFERROR(AL11/AG11-1,0) -> 0.013493253 | AN13: =IFERROR(AL11/AG11-1,0) -> 0.013493253 | AO13: =IFERROR(AL11/AG11-1,0) -> 0.013493253 | BC13: FY27 adjusted EBITDA ($m; legacy basis) | BD13: 1290 | BE13: 1265 | BF13: 1240 | BG13: Guided $1,240–1,290m. Drives the Q2–Q4/27E adjusted EBITDA margin calibration.
B14: National Security % of revenue | C14: =IF(AND(ISNUMBER(C11),ISNUMBER(C120)),IFERROR(C11/C120,""),"") | D14: =IF(AND(ISNUMBER(D11),ISNUMBER(D120)),IFERROR(D11/D120,""),"") | E14: =IF(AND(ISNUMBER(E11),ISNUMBER(E120)),IFERROR(E11/E120,""),"") | F14: =IF(AND(ISNUMBER(F11),ISNUMBER(F120)),IFERROR(F11/F120,""),"") | G14: =IF(AND(ISNUMBER(G11),ISNUMBER(G120)),IFERROR(G11/G120,""),"") | H14: =IF(AND(ISNUMBER(H11),ISNUMBER(H120)),IFERROR(H11/H120,""),"") -> 0.6967595 | I14: =IF(AND(ISNUMBER(I11),ISNUMBER(I120)),IFERROR(I11/I120,""),"") -> 0.70069572 | J14: =IF(AND(ISNUMBER(J11),ISNUMBER(J120)),IFERROR(J11/J120,""),"") -> 0.69830178 | ... AT14: =IF(AND(ISNUMBER(AT11),ISNUMBER(AT120)),IFERROR(AT11/AT120,""),"") -> 0.74598759 | AW14: =IFERROR(AVERAGE(AP14,AQ14,AR14,AS14,AT14),"n/m") -> 0.74553193 | AX14: =IFERROR(AVERAGE(Q14,V14,AA14,AF14,AK14),"n/m") -> 0.66033686 | AY14: =IFERROR(AVERAGE(H14,I14,J14,K14,L14,Q14,V14,AA14,AF14,AK14),"n/m") -> 0.67879023 | AZ14: =IFERROR(AVERAGE(C14,D14,E14,F14,G14,H14,I14,J14,K14,L14,Q14,V14,AA14,AF14,AK14),"n/m") -> 0.67879023 | BC14: FY27 adjusted diluted EPS ($) — memo | BD14: 6.35 | BE14: 6.175 | BF14: 6 | BG14: Guided $6.00–6.35 (information row; not forced).
B15: Civil & Commercial (Civil customers + Global Commercial) | AU15: CIVIL & COMMERCIAL — modelling logic | BC15: FY27 free cash flow ($m) | BD15: 925 | BE15: 875 | BF15: 825 | BG15: Guided $825–925m. Drives the FY2027E payables & accrued calibration (working-capital block).
B16: Civil & Commercial revenue | H16: 1765.301 | I16: 1843.009 | J16: 2022.596 | K16: 2280.867 | L16: 2388.725 | M16: 636.384 | N16: 713.295 | O16: 715.372 | P16: 770.14 | Q16: 2835.19 | R16: 820.726 | S16: 847.325 | T16: 814.312 | U16: 872.176 | V16: 3354.539 | W16: 953.672 | X16: 951.165 | Y16: 936.782 | Z16: 990.093 | AA16: 3831.712 | AB16: 1063.888 | AC16: 1105.858 | AD16: 1011.317 | AE16: 988.937 | AF16: 4170 | AG16: 923 | AH16: 827 | AI16: 732 | AJ16: 766 | AK16: 3248 | AL16: 772 | AM16: =AH16*(1+AM17) -> 757.20666 | AN16: =AI16*(1+AN17) -> 670.22403 | AO16: =AJ16*(1+AO17) -> 701.35466 | AP16: =SUM(AL16,AM16,AN16,AO16) -> 2900.7854 | AQ16: =AP16*(1+AQ17) -> 2784.7539 | AR16: =AQ16*(1+AR17) -> 2784.7539 | AS16: =AR16*(1+AS17) -> 2840.449 | AT16: =AS16*(1+AT17) -> 2925.6625 | AU16: Civil customers + Global Commercial (reported separately to FY2024, inside Civil from FY2025). Same forecast logic as National Security. | AW16: =IFERROR((AT16/AK16)^(1/5)-1,"n/m") -> -0.020686727 | AX16: =IFERROR((AK16/L16)^(1/5)-1,"n/m") -> 0.063383637 | AY16: =IFERROR((AK16/G16)^(1/10)-1,"n/m") -> n/m | AZ16: =IFERROR((AK16/C16)^(1/14)-1,"n/m") -> n/m | BC16: Q2–Q4/27E share repurchases ($m) | BD16: 300 | BE16: 150 | BF16: 50 | BG16: Assumption. Q1/27 $72m (incl. shares withheld for taxes); $634m left on the $4,085m program at 30-Jun-2026; Ultra ($720m) funded in Q2.
B17: y/y % | D17: =IF(AND(ISNUMBER(D16),ISNUMBER(C16)),IFERROR(D16/C16-1,""),"") | E17: =IF(AND(ISNUMBER(E16),ISNUMBER(D16)),IFERROR(E16/D16-1,""),"") | F17: =IF(AND(ISNUMBER(F16),ISNUMBER(E16)),IFERROR(F16/E16-1,""),"") | G17: =IF(AND(ISNUMBER(G16),ISNUMBER(F16)),IFERROR(G16/F16-1,""),"") | H17: =IF(AND(ISNUMBER(H16),ISNUMBER(G16)),IFERROR(H16/G16-1,""),"") | I17: =IF(AND(ISNUMBER(I16),ISNUMBER(H16)),IFERROR(I16/H16-1,""),"") -> 0.044019688 | J17: =IF(AND(ISNUMBER(J16),ISNUMBER(I16)),IFERROR(J16/I16-1,""),"") -> 0.097442281 | K17: =IF(AND(ISNUMBER(K16),ISNUMBER(J16)),IFERROR(K16/J16-1,""),"") -> 0.12769283 | L17: =IF(AND(ISNUMBER(L16),ISNUMBER(K16)),IFERROR(L16/K16-1,""),"") -> 0.047288158 | Q17: =IF(AND(ISNUMBER(Q16),ISNUMBER(L16)),IFERROR(Q16/L16-1,""),"") -> 0.18690515 | R17: =IF(AND(ISNUMBER(R16),ISNUMBER(M16)),IFERROR(R16/M16-1,""),"") -> 0.28967102 | S17: =IF(AND(ISNUMBER(S16),ISNUMBER(N16)),IFERROR(S16/N16-1,""),"") -> 0.18790262 | T17: =IF(AND(ISNUMBER(T16),ISNUMBER(O16)),IFERROR(T16/O16-1,""),"") -> 0.13830566 | U17: =IF(AND(ISNUMBER(U16),ISNUMBER(P16)),IFERROR(U16/P16-1,""),"") -> 0.1324902 | V17: =IF(AND(ISNUMBER(V16),ISNUMBER(Q16)),IFERROR(V16/Q16-1,""),"") -> 0.18317961 | W17: =IF(AND(ISNUMBER(W16),ISNUMBER(R16)),IFERROR(W16/R16-1,""),"") -> 0.16198585 | X17: =IF(AND(ISNUMBER(X16),ISNUMBER(S16)),IFERROR(X16/S16-1,""),"") -> 0.12255038 | ... AL17: =IF(AND(ISNUMBER(AL16),ISNUMBER(AG16)),IFERROR(AL16/AG16-1,""),"") -> -0.16359697 | AM17: =AM18+$AM$87 -> -0.084393396 | AN17: =AN18+$AM$87 -> -0.084393396 | AO17: =AO18+$AM$87 -> -0.084393396 | AP17: =IF(AND(ISNUMBER(AP16),ISNUMBER(AK16)),IFERROR(AP16/AK16-1,""),"") -> -0.10690106 | AQ17: =CHOOSE(MATCH($AU$2,{"Bull","Base","Bear"},0),$BD$40,$BE$40,$BF$40) -> -0.04 | AR17: =CHOOSE(MATCH($AU$2,{"Bull","Base","Bear"},0),$BD$41,$BE$41,$BF$41) -> 0 | AS17: =CHOOSE(MATCH($AU$2,{"Bull","Base","Bear"},0),$BD$42,$BE$42,$BF$42) -> 0.02 | AT17: =CHOOSE(MATCH($AU$2,{"Bull","Base","Bear"},0),$BD$43,$BE$43,$BF$43) -> 0.03
B18: Q2–Q4/27E growth before calibration (Q1/27 y/y) | AM18: =IFERROR(AL16/AG16-1,0) -> -0.16359697 | AN18: =IFERROR(AL16/AG16-1,0) -> -0.16359697 | AO18: =IFERROR(AL16/AG16-1,0) -> -0.16359697 | BC18: FY27 point estimates (all cases)
B19: Civil & Commercial % of revenue | C19: =IF(AND(ISNUMBER(C16),ISNUMBER(C120)),IFERROR(C16/C120,""),"") | D19: =IF(AND(ISNUMBER(D16),ISNUMBER(D120)),IFERROR(D16/D120,""),"") | E19: =IF(AND(ISNUMBER(E16),ISNUMBER(E120)),IFERROR(E16/E120,""),"") | F19: =IF(AND(ISNUMBER(F16),ISNUMBER(F120)),IFERROR(F16/F120,""),"") | G19: =IF(AND(ISNUMBER(G16),ISNUMBER(G120)),IFERROR(G16/G120,""),"") | H19: =IF(AND(ISNUMBER(H16),ISNUMBER(H120)),IFERROR(H16/H120,""),"") -> 0.3041376 | I19: =IF(AND(ISNUMBER(I16),ISNUMBER(I120)),IFERROR(I16/I120,""),"") -> 0.29861518 | J19: =IF(AND(ISNUMBER(J16),ISNUMBER(J120)),IFERROR(J16/J120,""),"") -> 0.30169822 | ... AT19: =IF(AND(ISNUMBER(AT16),ISNUMBER(AT120)),IFERROR(AT16/AT120,""),"") -> 0.21204516 | AW19: =IFERROR(AVERAGE(AP19,AQ19,AR19,AS19,AT19),"n/m") -> 0.22730672 | AX19: =IFERROR(AVERAGE(Q19,V19,AA19,AF19,AK19),"n/m") -> 0.33966314 | AY19: =IFERROR(AVERAGE(H19,I19,J19,K19,L19,Q19,V19,AA19,AF19,AK19),"n/m") -> 0.32123057 | AZ19: =IFERROR(AVERAGE(C19,D19,E19,F19,G19,H19,I19,J19,K19,L19,Q19,V19,AA19,AF19,AK19),"n/m") -> 0.32123057 | BC19: FY27 interest expense, net ($m) | BE19: 216 | BG19: Not guided (assumption): Q1 $48m; $1.2bn notes at 5.375% / 5.900% from 4-Aug-2026, Term Loan A-1 ($714m, ~5.0%) repaid, lower interest income after the Ultra payment.
B20: Revenue outside the customer split (FY2012–16 not split; FY2017–18 ASC 606 recast basis difference; rounding) — derived | C20: =IF(ISNUMBER(C11),C120-C11-C16,C120) -> 5859.218 | D20: =IF(ISNUMBER(D11),D120-D11-D16,D120) -> 5758.059 | E20: =IF(ISNUMBER(E11),E120-E11-E16,E120) -> 5478.693 | F20: =IF(ISNUMBER(F11),F120-F11-F16,F120) -> 5274.77 | G20: =IF(ISNUMBER(G11),G120-G11-G16,G120) -> 5405.738 | H20: =IF(ISNUMBER(H11),H120-H11-H16,H120) -> -5.207 | I20: =IF(ISNUMBER(I11),I120-I11-I16,I120) -> 4.253 | J20: =IF(ISNUMBER(J11),J120-J11-J16,J120) -> 0 | ... AL20: =IF(ISNUMBER(AL11),AL120-AL11-AL16,AL120) -> 0 | AM20: =0 -> 0 | AN20: =0 -> 0 | AO20: =0 -> 0 | AP20: =SUM(AL20,AM20,AN20,AO20) -> 0 | AQ20: =0 -> 0 | AR20: =0 -> 0 | AS20: =0 -> 0 | AT20: =0 -> 0 | AU20: Derived = revenue − Σ customer types, so the build ties in every period. FY2012–16: no customer split published (whole revenue). FY2017–18: the split comes from the FY2019 10-K (ASC 606 full-retrospective recast: $5,809.5m / $6,167.6m vs $5,804.3m / $6,171.9m as originally reported). From FY2025 the 10-Q tables are in whole $m (±1 rounding). | BC20: FY27 other income (expense) ($m) | BE20: 26 | BG20: Q1 $20m (incl. $18m net gains on investments and dispositions); ~$2m a quarter after (assumption).
B21: Legacy customer types (as reported; replaced by National Security / Civil & Commercial): | BC21: FY27 acquisition amortization excl. Ultra ($m) | BE21: 60 | BG21: Q1 $15m (incl. Defy, $86m over 8 years) × 4.
B22: Defense | H22: 2699.284 | I22: 2830.102 | J22: 3114.571 | K22: 3568.659 | L22: 3898.802 | M22: 975.926 | N22: 999.174 | O22: 946.161 | P22: 1034.211 | Q22: 3955.473 | R22: 1019.991 | S22: 1019.108 | T22: 1043.535 | U22: 1127.796 | V22: 4210.43 | W22: 1224.317 | X22: 1270.135 | Y22: 1224.561 | Z22: 1336.766 | AA22: 5055.779 | AB22: 1416.87 | AC22: 1544.108 | AD22: 1454.686 | AE22: 1527.336 | AF22: 5943 | AG22: 1517 | AH22: 1580 | AI22: 1454 | AJ22: 1518 | AK22: 6069 | BC22: FY27 depreciation & other amortization ($m) | BE22: 120 | BG22: Q1 $30m (D&A $45m − acquisition amortization $15m) × 4.
B23: Intelligence | H23: 1344.906 | I23: 1494.489 | J23: 1566.87 | K23: 1614.315 | L23: 1571.411 | M23: 376.756 | N23: 393.569 | O23: 368.987 | P23: 433.725 | Q23: 1573.037 | R23: 408.883 | S23: 432.543 | T23: 419.227 | U23: 433.289 | V23: 1693.942 | W23: 476.497 | X23: 444.982 | Y23: 408.458 | Z23: 444.468 | AA23: 1774.405 | AB23: 461.039 | AC23: 496.42 | AD23: 451.187 | AE23: 458.354 | AF23: 1867 | AG23: 484 | AH23: 483 | AI23: 434 | AJ23: 499 | AK23: 1900 | BC23: FY27 stock-based compensation ($m) | BE23: 84 | BG23: Q1 $21m × 4 (FY26 $69m).
B24: Civil (incl. Global Commercial from FY2025) | H24: 1611.309 | I24: 1644.86 | J24: 1760.996 | K24: 2019.245 | L24: 2185.03 | M24: 592.896 | N24: 662.261 | O24: 651.372 | P24: 712.386 | Q24: 2618.914 | R24: 757.714 | S24: 783.782 | T24: 758.473 | U24: 824.92 | V24: 3124.889 | W24: 904.96 | X24: 916.069 | Y24: 893.202 | Z24: 944.234 | AA24: 3658.465 | AB24: 1063.888 | AC24: 1105.858 | AD24: 1011.317 | AE24: 988.937 | AF24: 4170 | AG24: 923 | AH24: 827 | AI24: 732 | AJ24: 766 | AK24: 3248 | BC24: Q2–Q4/27E effective tax rate | BE24: 0.215 | BG24: FY27 guidance 20–23% (Q1/27 21.1%).
B25: Global Commercial (to FY2024) | H25: 153.992 | I25: 198.149 | J25: 261.6 | K25: 261.622 | L25: 203.695 | M25: 43.488 | N25: 51.034 | O25: 64 | P25: 57.754 | Q25: 216.276 | R25: 63.012 | S25: 63.543 | T25: 55.839 | U25: 47.256 | V25: 229.65 | W25: 48.712 | X25: 35.096 | Y25: 43.58 | Z25: 45.859 | AA25: 173.247 | BC25: FY27 capital expenditures ($m) | BE25: 220 | BG25: Guided ~$220m, of which ~$105m for the new headquarters (Q1 $20m).
B26: Check: legacy customer types vs National Security + Civil & Commercial (should be 0; ±0.15, ±0.6 from Q4 FY25) | C26: =IF(ISNUMBER(C22),IF(ABS(C22+C23+C24+N(C25)-C11-C16)<=1,0,ROUND(C22+C23+C24+N(C25)-C11-C16,1)),"") | D26: =IF(ISNUMBER(D22),IF(ABS(D22+D23+D24+N(D25)-D11-D16)<=1,0,ROUND(D22+D23+D24+N(D25)-D11-D16,1)),"") | E26: =IF(ISNUMBER(E22),IF(ABS(E22+E23+E24+N(E25)-E11-E16)<=1,0,ROUND(E22+E23+E24+N(E25)-E11-E16,1)),"") | F26: =IF(ISNUMBER(F22),IF(ABS(F22+F23+F24+N(F25)-F11-F16)<=1,0,ROUND(F22+F23+F24+N(F25)-F11-F16,1)),"") | G26: =IF(ISNUMBER(G22),IF(ABS(G22+G23+G24+N(G25)-G11-G16)<=1,0,ROUND(G22+G23+G24+N(G25)-G11-G16,1)),"") | H26: =IF(ISNUMBER(H22),IF(ABS(H22+H23+H24+N(H25)-H11-H16)<=1,0,ROUND(H22+H23+H24+N(H25)-H11-H16,1)),"") -> 0 | I26: =IF(ISNUMBER(I22),IF(ABS(I22+I23+I24+N(I25)-I11-I16)<=1,0,ROUND(I22+I23+I24+N(I25)-I11-I16,1)),"") -> 0 | J26: =IF(ISNUMBER(J22),IF(ABS(J22+J23+J24+N(J25)-J11-J16)<=1,0,ROUND(J22+J23+J24+N(J25)-J11-J16,1)),"") -> 0 | ... AL26: =IF(ISNUMBER(AL22),IF(ABS(AL22+AL23+AL24+N(AL25)-AL11-AL16)<=1,0,ROUND(AL22+AL23+AL24+N(AL25)-AL11-AL16,1)),"") | BC26: FY27 other corporate (acquisition) expenses, adjusted out ($m) | BE26: 25 | BG26: Q1 $10m (Defy; Ultra agreement). Ultra closing and integration costs (assumption).
BC27: FY27 non-operating adjusting items ($m) | BE27: 0 | BG27: None in Q1/27 (debt-cost amortization no longer adjusted out since FY2026).
B28: Ultra I&C Mission Solutions — acquired 24-Aug-2026 for $720m (National Security defense technology; revenue not disclosed) | AU28: ULTRA MISSION SOLUTIONS — modelling logic (closed after the FY27 guidance; added on top of the calibrated legacy business) | BC28: Two-class allocation to participating securities (% of net income) | BE28: 0.008 | BG28: FY2026 0.7%, Q1/27 1.0%, FY2025 0.5%.
B29: Annualised revenue run-rate (USDm; FY2027E = assumption, then × (1 + growth)) | AP29: 180 | AQ29: =AP29*(1+AQ30) -> 207 | AR29: =AQ29*(1+AR30) -> 238.05 | AS29: =AR29*(1+AS30) -> 266.616 | AT29: =AS29*(1+AT30) -> 293.2776 | AU29: Ultra I&C Mission Solutions (Ultra Electronics Advanced Tactical Systems, Inc.): stock purchase agreement 19-Jun-2026 for $720m subject to adjustments (8-K Item 1.01, 22-Jun-2026); closed 24-Aug-2026 (8-K 24-Aug-2026, Ex. 99.1). Revenue and EBITDA not disclosed; the announcement (Ex. 99.1, 22-Jun-2026) says BAH 'expects revenue from this acquisition to grow at a strong double-digit rate for the next several years with EBITDA margins well above 20%'. Run-rate $180m is an ASSUMPTION (~4x EV / sales); replace with the Q2 FY27 10-Q disclosure. | BC29: Tax rate on adjusting items (company assumed rate) | BE29: 0.26 | BG29: Release footnote: "assumed effective tax rate of 26%, which approximates the blended federal and state tax rates".
B30: Growth % (scenario lever from 2028E; company: "strong double-digit rate for the next several years") | AQ30: =CHOOSE(MATCH($AU$2,{"Bull","Base","Bear"},0),$BD$45,$BE$45,$BF$45) -> 0.15 | AR30: =CHOOSE(MATCH($AU$2,{"Bull","Base","Bear"},0),$BD$46,$BE$46,$BF$46) -> 0.15 | AS30: =CHOOSE(MATCH($AU$2,{"Bull","Base","Bear"},0),$BD$47,$BE$47,$BF$47) -> 0.12 | AT30: =CHOOSE(MATCH($AU$2,{"Bull","Base","Bear"},0),$BD$48,$BE$48,$BF$48) -> 0.1 | BC30: FY27 Ultra adjusted EBITDA margin | BE30: 0.25 | BG30: Company: "EBITDA margins well above 20%" (8-K Ex. 99.1, 22-Jun-2026). 25% is an assumption.
B31: Share of the quarter consolidated (closed 24-Aug-2026: 38 of 91 days in Q2/27) | AM31: 0.41758242 | AN31: 1 | AO31: 1
B32: Ultra revenue | AM32: =$AP$29/4*AM31 -> 18.791209 | AN32: =$AP$29/4*AN31 -> 45 | AO32: =$AP$29/4*AO31 -> 45 | AP32: =SUM(AL32,AM32,AN32,AO32) -> 108.79121 | AQ32: =AQ29 -> 207 | AR32: =AR29 -> 238.05 | AS32: =AS29 -> 266.616 | AT32: =AT29 -> 293.2776 | BC32: Maximum net debt / adjusted EBITDA before buybacks (x) — buyback floor 2028E+ | BD32: 3.25 | BE32: 3 | BF32: 2.5 | BG32: Assumption (no leverage target in the SEC filings). Net leverage ratio (net debt / LTM adjusted EBITDA, company definition) 2.6x at 31-Mar-2026, 2.7x at 30-Jun-2026; ~3.2x pro forma for Ultra. Target = leverage up to which surplus cash is returned via buybacks; below it free cash flow repays debt / builds cash.
B33: Adjusted EBITDA margin % (company: "EBITDA margins well above 20%") | AM33: =$BE$30 -> 0.25 | AN33: =$BE$30 -> 0.25 | AO33: =$BE$30 -> 0.25 | AP33: =$BE$30 -> 0.25 | AQ33: =CHOOSE(MATCH($AU$2,{"Bull","Base","Bear"},0),$BD$55,$BE$55,$BF$55) -> 0.25 | AR33: =CHOOSE(MATCH($AU$2,{"Bull","Base","Bear"},0),$BD$56,$BE$56,$BF$56) -> 0.25 | AS33: =CHOOSE(MATCH($AU$2,{"Bull","Base","Bear"},0),$BD$57,$BE$57,$BF$57) -> 0.25 | AT33: =CHOOSE(MATCH($AU$2,{"Bull","Base","Bear"},0),$BD$58,$BE$58,$BF$58) -> 0.25
B34: Ultra adjusted EBITDA | AM34: =AM32*AM33 -> 4.6978022 | AN34: =AN32*AN33 -> 11.25 | AO34: =AO32*AO33 -> 11.25 | AP34: =SUM(AL34,AM34,AN34,AO34) -> 27.197802 | AQ34: =AQ32*AQ33 -> 51.75 | AR34: =AR32*AR33 -> 59.5125 | AS34: =AS32*AS33 -> 66.654 | AT34: =AT32*AT33 -> 73.3194 | BC34: NS_G (National Security revenue y/y, ex-Ultra) | BD34: 0.02 | BE34: Δ → | BF34: -0.03 | BG34: FY26 +2.0%, Q1/27 +1.3% (incl. Defy); FY2022–25 CAGR +9%. Record $39.5bn backlog, Q1/27 book-to-bill 1.5x; defense / intelligence budget growth (FY26 NDAA). Assumption.
B35: Consideration (USDm; 8-K 22-Jun-2026, subject to adjustments) | AP35: 720 | BC35: 2028E | BD35: =BE35+$BD$34 -> 0.06 | BE35: 0.04 | BF35: =BE35+$BF$34 -> 0.01
B36: Acquired intangibles % of consideration (assumption; Defy 37%) | AP36: 0.4 | BC36: 2029E | BD36: =BE36+$BD$34 -> 0.07 | BE36: 0.05 | BF36: =BE36+$BF$34 -> 0.02
B37: Intangible amortization life (years; assumption) | AP37: 10 | BC37: 2030E | BD37: =BE37+$BD$34 -> 0.07 | BE37: 0.05 | BF37: =BE37+$BF$34 -> 0.02
B38: Ultra acquisition amortization (adjusted out by the company) | AM38: =$AP$35*$AP$36/$AP$37/4*AM31 -> 3.0065934 | AN38: =$AP$35*$AP$36/$AP$37/4*AN31 -> 7.2 | AO38: =$AP$35*$AP$36/$AP$37/4*AO31 -> 7.2 | AP38: =SUM(AL38,AM38,AN38,AO38) -> 17.406593 | AQ38: =AP35*AP36/AP37 -> 28.8 | AR38: =AP35*AP36/AP37 -> 28.8 | AS38: =AP35*AP36/AP37 -> 28.8 | AT38: =AP35*AP36/AP37 -> 28.8 | BC38: 2031E | BD38: =BE38+$BD$34 -> 0.07 | BE38: 0.05 | BF38: =BE38+$BF$34 -> 0.02
BC39: CC_G (Civil & Commercial revenue y/y) | BD39: 0.04 | BE39: Δ → | BF39: -0.04 | BG39: FY26 −22% (civil agency contract cuts and cancellations, contract sale Nov-2025), Q1/27 −16%. Assumed to trough in FY28. Assumption.
B40: Backlog, book-to-bill & headcount (operating data, release Exhibit 5) | AU40: BACKLOG — roll-forward: closing = opening + net bookings − revenue; net bookings = revenue × book-to-bill (company definition) | BC40: 2028E | BD40: =BE40+$BD$39 -> 0 | BE40: -0.04 | BF40: =BE40+$BF$39 -> -0.08
B41: Funded backlog | C41: 2898 | D41: 2509 | E41: 2290 | F41: 2691 | G41: 2673 | H41: 2815 | I41: 2685 | J41: 3436 | K41: 3415 | L41: 3510 | M41: 3493 | N41: 4917 | O41: 4044 | P41: 3710 | Q41: 3710 | R41: 4020 | S41: 5475 | T41: 4544 | U41: 4619 | V41: 4619 | W41: 4903 | X41: 6282 | Y41: 5246 | Z41: 4822 | AA41: 4822 | AB41: 5136 | AC41: 6612 | AD41: 5330 | AE41: 4421 | AF41: 4421 | AG41: 4047 | AH41: 5440 | AI41: 4206 | AJ41: 4319 | AK41: 4319 | AL41: 4664 | BC41: 2029E | BD41: =BE41+$BD$39 -> 0.04 | BE41: 0 | BF41: =BE41+$BF$39 -> -0.04
B42: Unfunded backlog | C42: 2681 | D42: 3056 | E42: 2343 | F42: 2121 | G42: 2546 | H42: 3098 | I42: 4161 | J42: 3687 | K42: 4518 | L42: 6086 | M42: 9029 | N42: 9528 | O42: 9415 | P42: 9925 | Q42: 9925 | R42: 9991 | S42: 10380 | T42: 10131 | U42: 9519 | V42: 9519 | W42: 9045 | X42: 10128 | Y42: 9195 | Z42: 9463 | AA42: 9463 | AB42: 10119 | AC42: 10317 | AD42: 9340 | AE42: 8804 | AF42: 8804 | AG42: 10441 | AH42: 10668 | AI42: 10059 | AJ42: 10183 | AK42: 10183 | AL42: 10218 | BC42: 2030E | BD42: =BE42+$BD$39 -> 0.06 | BE42: 0.02 | BF42: =BE42+$BF$39 -> -0.02
B43: Priced options | C43: 5225 | D43: 6265 | E43: 5205 | F43: 4548 | G43: 6595 | H43: 7679 | I43: 9174 | J43: 12198 | K43: 12796 | L43: 14436 | M43: 14295 | N43: 14550 | O43: 14302 | P43: 15612 | Q43: 15612 | R43: 14617 | S43: 15981 | T43: 15373 | U43: 17064 | V43: 17064 | W43: 17329 | X43: 18630 | Y43: 19880 | Z43: 19533 | AA43: 19533 | AB43: 20923 | AC43: 24325 | AD43: 24743 | AE43: 23802 | AF43: 23802 | AG43: 23777 | AH43: 24080 | AI43: 24191 | AJ43: 23685 | AK43: 23685 | AL43: 24601 | BC43: 2031E | BD43: =BE43+$BD$39 -> 0.07 | BE43: 0.03 | BF43: =BE43+$BF$39 -> -0.01
B44: Total backlog (period end) | C44: 10804 | D44: 11830 | E44: 9838 | F44: 9360 | G44: 11814 | H44: 13592 | I44: 16020 | J44: 19321 | K44: 20729 | L44: 24032 | M44: 26817 | N44: 28995 | O44: 27761 | P44: 29247 | Q44: 29247 | R44: 28628 | S44: 31836 | T44: 30048 | U44: 31202 | V44: 31202 | W44: 31277 | X44: 35040 | Y44: 34321 | Z44: 33818 | AA44: 33818 | AB44: 36178 | AC44: 41254 | AD44: 39413 | AE44: 37027 | AF44: 37027 | AG44: 38265 | AH44: 40188 | AI44: 38456 | AJ44: 38187 | AK44: 38187 | AL44: 39483 | AM44: =AL44+AM45-AM120 -> 39483 | AN44: =AM44+AN45-AN120 -> 39483 | AO44: =AN44+AO45-AO120 -> 39483 | AP44: =AO44 -> 39483 | AQ44: =AP44+AQ45-AQ120 -> 40079.022 | AR44: =AQ44+AR45-AR120 -> 40702.762 | AS44: =AR44+AS45-AS120 -> 41358.188 | AT44: =AS44+AT45-AT120 -> 42048.056 | AU44: Company definition: funded + unfunded + priced options (100% of unexercised option value). Acquired backlog (EverWatch, Liberty, Defy, Ultra) enters through net bookings. | AW44: =IFERROR((AT44/AK44)^(1/5)-1,"n/m") -> 0.019450343 | AX44: =IFERROR((AK44/L44)^(1/5)-1,"n/m") -> 0.097046725 | AY44: =IFERROR((AK44/G44)^(1/10)-1,"n/m") -> 0.12448032 | AZ44: =IFERROR((AK44/C44)^(1/14)-1,"n/m") -> 0.094375842 | BC44: ULTRA_G (Ultra Mission Solutions revenue y/y) | BD44: 0.05 | BE44: Δ → | BF44: -0.08 | BG44: Company: "expects revenue from this acquisition to grow at a strong double-digit rate for the next several years" (22-Jun-2026). Base = 15% fading to 10%.
B45: Net bookings (Δ total backlog + revenue; incl. acquired backlog) | D45: =IF(AND(ISNUMBER(D44),ISNUMBER(C44)),D44-C44+D120,"") -> 6784.059 | E45: =IF(AND(ISNUMBER(E44),ISNUMBER(D44)),E44-D44+E120,"") -> 3486.693 | F45: =IF(AND(ISNUMBER(F44),ISNUMBER(E44)),F44-E44+F120,"") -> 4796.77 | G45: =IF(AND(ISNUMBER(G44),ISNUMBER(F44)),G44-F44+G120,"") -> 7859.738 | H45: =IF(AND(ISNUMBER(H44),ISNUMBER(G44)),H44-G44+H120,"") -> 7582.284 | I45: =IF(AND(ISNUMBER(I44),ISNUMBER(H44)),I44-H44+I120,"") -> 8599.853 | J45: =IF(AND(ISNUMBER(J44),ISNUMBER(I44)),J44-I44+J120,"") -> 10005.037 | K45: =IF(AND(ISNUMBER(K44),ISNUMBER(J44)),K44-J44+K120,"") -> 8871.841 | L45: =IF(AND(ISNUMBER(L44),ISNUMBER(K44)),L44-K44+L120,"") -> 11161.938 | N45: =IF(AND(ISNUMBER(N44),ISNUMBER(M44)),N44-M44+N120,"") -> 4284.038 | O45: =IF(AND(ISNUMBER(O44),ISNUMBER(N44)),O44-N44+O120,"") -> 796.52 | P45: =IF(AND(ISNUMBER(P44),ISNUMBER(O44)),P44-O44+P120,"") -> 3724.076 | Q45: =IF(AND(ISNUMBER(Q44),ISNUMBER(L44)),Q44-L44+Q120,"") -> 13578.7 | R45: =IF(AND(ISNUMBER(R44),ISNUMBER(P44)),R44-P44+R120,"") -> 1630.6 | S45: =IF(AND(ISNUMBER(S44),ISNUMBER(R44)),S44-R44+S120,"") -> 5506.976 | T45: =IF(AND(ISNUMBER(T44),ISNUMBER(S44)),T44-S44+T120,"") -> 489.074 | U45: =IF(AND(ISNUMBER(U44),ISNUMBER(T44)),U44-T44+U120,"") -> 3587.261 | V45: =IF(AND(ISNUMBER(V44),ISNUMBER(Q44)),V44-Q44+V120,"") -> 11213.911 | W45: =IF(AND(ISNUMBER(W44),ISNUMBER(U44)),W44-U44+W120,"") -> 2729.486 | X45: =IF(AND(ISNUMBER(X44),ISNUMBER(W44)),X44-W44+X120,"") -> 6429.282 | Y45: =IF(AND(ISNUMBER(Y44),ISNUMBER(X44)),Y44-X44+Y120,"") -> 1850.801 | Z45: =IF(AND(ISNUMBER(Z44),ISNUMBER(Y44)),Z44-Y44+Z120,"") -> 2268.327 | AA45: =IF(AND(ISNUMBER(AA44),ISNUMBER(V44)),AA44-V44+AA120,"") -> 13277.896 | AB45: =IF(AND(ISNUMBER(AB44),ISNUMBER(Z44)),AB44-Z44+AB120,"") -> 5301.797 | AC45: =IF(AND(ISNUMBER(AC44),ISNUMBER(AB44)),AC44-AB44+AC120,"") -> 8222.386 | AD45: =IF(AND(ISNUMBER(AD44),ISNUMBER(AC44)),AD44-AC44+AD120,"") -> 1076.19 | AE45: =IF(AND(ISNUMBER(AE44),ISNUMBER(AD44)),AE44-AD44+AE120,"") -> 588 | AF45: =IF(AND(ISNUMBER(AF44),ISNUMBER(AA44)),AF44-AA44+AF120,"") -> 15189 | AG45: =IF(AND(ISNUMBER(AG44),ISNUMBER(AE44)),AG44-AE44+AG120,"") -> 4162 | AH45: =IF(AND(ISNUMBER(AH44),ISNUMBER(AG44)),AH44-AG44+AH120,"") -> 4813 | AI45: =IF(AND(ISNUMBER(AI44),ISNUMBER(AH44)),AI44-AH44+AI120,"") -> 888 | AJ45: =IF(AND(ISNUMBER(AJ44),ISNUMBER(AI44)),AJ44-AI44+AJ120,"") -> 2514 | AK45: =IF(AND(ISNUMBER(AK44),ISNUMBER(AF44)),AK44-AF44+AK120,"") -> 12377 | AL45: =IF(AND(ISNUMBER(AL44),ISNUMBER(AJ44)),AL44-AJ44+AL120,"") -> 4096 | AM45: =AM120*AM46 -> 3030.2314 | AN45: =AN120*AN46 -> 2778.2356 | AO45: =AO120*AO46 -> 2950.3242 | AP45: =SUM(AL45,AM45,AN45,AO45) -> 12854.791 | AQ45: =AQ120*AQ46 -> 12516.459 | AR45: =AR120*AR46 -> 13098.536 | AS45: =AS120*AS46 -> 13763.959 | AT45: =AT120*AT46 -> 14487.223 | BC45: 2028E | BD45: =BE45+$BD$44 -> 0.2 | BE45: 0.15 | BF45: =BE45+$BF$44 -> 0.07
B46: Book-to-bill (x) | C46: =IF(ISNUMBER(C45),IFERROR(C45/C120,""),"") | D46: =IF(ISNUMBER(D45),IFERROR(D45/D120,""),"") -> 1.178185 | E46: =IF(ISNUMBER(E45),IFERROR(E45/E120,""),"") -> 0.63640963 | F46: =IF(ISNUMBER(F45),IFERROR(F45/F120,""),"") -> 0.90937994 | G46: =IF(ISNUMBER(G45),IFERROR(G45/G120,""),"") -> 1.4539621 | H46: =IF(ISNUMBER(H45),IFERROR(H45/H120,""),"") -> 1.3063255 | I46: =IF(ISNUMBER(I45),IFERROR(I45/I120,""),"") -> 1.3933989 | J46: =IF(ISNUMBER(J45),IFERROR(J45/J120,""),"") -> 1.4923899 | ... AL46: =IF(ISNUMBER(AL45),IFERROR(AL45/AL120,""),"") -> 1.4628571 | AM46: 1 | AN46: 1 | AO46: 1 | AP46: =IFERROR(AP45/AP120,"") -> 1.1121225 | AQ46: =CHOOSE(MATCH($AU$2,{"Bull","Base","Bear"},0),$BD$60,$BE$60,$BF$60) -> 1.05 | AR46: =CHOOSE(MATCH($AU$2,{"Bull","Base","Bear"},0),$BD$61,$BE$61,$BF$61) -> 1.05 | AS46: =CHOOSE(MATCH($AU$2,{"Bull","Base","Bear"},0),$BD$62,$BE$62,$BF$62) -> 1.05 | AT46: =CHOOSE(MATCH($AU$2,{"Bull","Base","Bear"},0),$BD$63,$BE$63,$BF$63) -> 1.05 | AU46: Q2–Q4/27E 1.0x (government awards are lumpy; Q1/27 1.5x, TTM 1.1x). 2028E+: scenario lever. | AW46: =IFERROR(AVERAGE(AP46,AQ46,AR46,AS46,AT46),"n/m") -> 1.0624245 | AX46: =IFERROR(AVERAGE(Q46,V46,AA46,AF46,AK46),"n/m") -> 1.2902626 | AY46: =IFERROR(AVERAGE(H46,I46,J46,K46,L46,Q46,V46,AA46,AF46,AK46),"n/m") -> 1.3252356 | AZ46: =IFERROR(AVERAGE(C46,D46,E46,F46,G46,H46,I46,J46,K46,L46,Q46,V46,AA46,AF46,AK46),"n/m") -> 1.2450209 | BC46: 2029E | BD46: =BE46+$BD$44 -> 0.2 | BE46: 0.15 | BF46: =BE46+$BF$44 -> 0.07
B47: Memo: book-to-bill as published (quarter / fiscal year) | I47: 1.39 | J47: 1.49 | K47: 1.19 | L47: 1.42 | M47: 1.3 | N47: 2.03 | O47: 0.39 | P47: 1.66 | Q47: 1.36 | R47: 0.72 | S47: 2.4 | T47: 0.09 | U47: 1.47 | V47: 1.18 | W47: 1.03 | X47: 2.41 | Y47: 0.72 | Z47: 0.82 | AA47: 1.25 | AB47: 1.72 | AC47: 2.61 | AD47: 0.37 | AE47: 0.71 | AF47: 1.39 | AG47: 1.42 | AH47: 1.7 | AI47: 0.3 | AJ47: 0.9 | AK47: 1.1 | AL47: 1.5 | BC47: 2030E | BD47: =BE47+$BD$44 -> 0.17 | BE47: 0.12 | BF47: =BE47+$BF$44 -> 0.04
B48: Total backlog / revenue (x, annualised) | C48: =IF(ISNUMBER(C44),IFERROR(C44/(C120*1),""),"") -> 1.8439321 | D48: =IF(ISNUMBER(D44),IFERROR(D44/(D120*1),""),"") -> 2.0545118 | E48: =IF(ISNUMBER(E44),IFERROR(E44/(E120*1),""),"") -> 1.7956838 | F48: =IF(ISNUMBER(F44),IFERROR(F44/(F120*1),""),"") -> 1.774485 | G48: =IF(ISNUMBER(G44),IFERROR(G44/(G120*1),""),"") -> 2.1854555 | H48: =IF(ISNUMBER(H44),IFERROR(H44/(H120*1),""),"") -> 2.3417186 | I48: =IF(ISNUMBER(I44),IFERROR(I44/(I120*1),""),"") -> 2.5956548 | J48: =IF(ISNUMBER(J44),IFERROR(J44/(J120*1),""),"") -> 2.8819948 | ... L48: =IF(ISNUMBER(L44),IFERROR(L44/(L120*1),""),"") -> 3.0579195 | M48: =IF(ISNUMBER(M44),IFERROR(M44/(M120*4),""),"") -> 3.3705518 | N48: =IF(ISNUMBER(N44),IFERROR(N44/(N120*4),""),"") -> 3.4418895 | O48: =IF(ISNUMBER(O44),IFERROR(O44/(O120*4),""),"") -> 3.4179668 | P48: =IF(ISNUMBER(P44),IFERROR(P44/(P120*4),""),"") -> 3.2669802 | Q48: =IF(ISNUMBER(Q44),IFERROR(Q44/(Q120*1),""),"") -> 3.4968973 | R48: =IF(ISNUMBER(R44),IFERROR(R44/(R120*4),""),"") -> 3.1814545 | S48: =IF(ISNUMBER(S44),IFERROR(S44/(S120*4),""),"") -> 3.4619761 | T48: =IF(ISNUMBER(T44),IFERROR(T44/(T120*4),""),"") -> 3.2989705 | U48: =IF(ISNUMBER(U44),IFERROR(U44/(U120*4),""),"") -> 3.2057802 | V48: =IF(ISNUMBER(V44),IFERROR(V44/(V120*1),""),"") -> 3.3699428 | W48: =IF(ISNUMBER(W44),IFERROR(W44/(W120*4),""),"") -> 2.9456739 | X48: =IF(ISNUMBER(X44),IFERROR(X44/(X120*4),""),"") -> 3.2854739 | Y48: =IF(ISNUMBER(Y44),IFERROR(Y44/(Y120*4),""),"") -> 3.3388772 | Z48: =IF(ISNUMBER(Z44),IFERROR(Z44/(Z120*4),""),"") -> 3.0507046 | AA48: =IF(ISNUMBER(AA44),IFERROR(AA44/(AA120*1),""),"") -> 3.1718561 | AB48: =IF(ISNUMBER(AB44),IFERROR(AB44/(AB120*4),""),"") -> 3.0744813 | AC48: =IF(ISNUMBER(AC44),IFERROR(AC44/(AC120*4),""),"") -> 3.2778877 | AD48: =IF(ISNUMBER(AD44),IFERROR(AD44/(AD120*4),""),"") -> 3.3776511 | AE48: =IF(ISNUMBER(AE44),IFERROR(AE44/(AE120*4),""),"") -> 3.1125588 | AF48: =IF(ISNUMBER(AF44),IFERROR(AF44/(AF120*1),""),"") -> 3.0907346 | AG48: =IF(ISNUMBER(AG44),IFERROR(AG44/(AG120*4),""),"") -> 3.2716313 | AH48: =IF(ISNUMBER(AH44),IFERROR(AH44/(AH120*4),""),"") -> 3.4764706 | AI48: =IF(ISNUMBER(AI44),IFERROR(AI44/(AI120*4),""),"") -> 3.6694656 | AJ48: =IF(ISNUMBER(AJ44),IFERROR(AJ44/(AJ120*4),""),"") -> 3.4303809 | AK48: =IF(ISNUMBER(AK44),IFERROR(AK44/(AK120*1),""),"") -> 3.4043862 | AL48: =IF(ISNUMBER(AL44),IFERROR(AL44/(AL120*4),""),"") -> 3.5252679 | AM48: =IF(ISNUMBER(AM44),IFERROR(AM44/(AM120*4),""),"") -> 3.2574245 | AN48: =IF(ISNUMBER(AN44),IFERROR(AN44/(AN120*4),""),"") -> 3.5528844 | AO48: =IF(ISNUMBER(AO44),IFERROR(AO44/(AO120*4),""),"") -> 3.3456493 | AP48: =IF(ISNUMBER(AP44),IFERROR(AP44/(AP120*1),""),"") -> 3.4158416 | AQ48: =IF(ISNUMBER(AQ44),IFERROR(AQ44/(AQ120*1),""),"") -> 3.3622107 | AR48: =IF(ISNUMBER(AR44),IFERROR(AR44/(AR120*1),""),"") -> 3.2627997 | AS48: =IF(ISNUMBER(AS44),IFERROR(AS44/(AS120*1),""),"") -> 3.1550587 | AT48: =IF(ISNUMBER(AT44),IFERROR(AT44/(AT120*1),""),"") -> 3.0475446 | BC48: 2031E | BD48: =BE48+$BD$44 -> 0.15 | BE48: 0.1 | BF48: =BE48+$BF$44 -> 0.02
B49: Funded backlog % of total | C49: =IF(ISNUMBER(C41),IFERROR(C41/C44,""),"") -> 0.26823399 | D49: =IF(ISNUMBER(D41),IFERROR(D41/D44,""),"") -> 0.21208791 | E49: =IF(ISNUMBER(E41),IFERROR(E41/E44,""),"") -> 0.23277089 | F49: =IF(ISNUMBER(F41),IFERROR(F41/F44,""),"") -> 0.2875 | G49: =IF(ISNUMBER(G41),IFERROR(G41/G44,""),"") -> 0.22625698 | H49: =IF(ISNUMBER(H41),IFERROR(H41/H44,""),"") -> 0.20710712 | I49: =IF(ISNUMBER(I41),IFERROR(I41/I44,""),"") -> 0.167603 | J49: =IF(ISNUMBER(J41),IFERROR(J41/J44,""),"") -> 0.17783759 | ... AT49: =IF(ISNUMBER(AT41),IFERROR(AT41/AT44,""),"") | BC49: ADJ_M (legacy adjusted EBITDA margin on revenue) | BD49: 0.005 | BE49: Δ → | BF49: -0.01 | BG49: FY26 11.0%, FY25 11.0%, FY24 11.0%; FY27 guided ~11% (calibrated). Mix shift to National Security and fixed-price / product work vs pricing pressure (outcomes-based contracts).
B50: Total headcount (period end) | C50: 24950 | D50: 24455 | E50: 22664 | F50: 22540 | G50: 22583 | H50: 23300 | I50: 24639 | J50: 26069 | K50: 27173 | L50: 27727 | M50: 28558 | N50: 29228 | O50: 29453 | P50: 29317 | Q50: 29317 | R50: 29291 | S50: 30012 | T50: 31130 | U50: 31925 | V50: 31925 | W50: 32574 | X50: 33117 | Y50: 33798 | Z50: 34234 | AA50: 34234 | AB50: 35100 | AC50: 35800 | AD50: 35900 | AE50: 35800 | AF50: 35800 | AG50: 33400 | AH50: 32500 | AI50: 31600 | AJ50: 31500 | AK50: 31500 | AL50: 30900 | AW50: =IFERROR((AT50/AK50)^(1/5)-1,"n/m") -> -1 | AX50: =IFERROR((AK50/L50)^(1/5)-1,"n/m") -> 0.0258445 | AY50: =IFERROR((AK50/G50)^(1/10)-1,"n/m") -> 0.033838954 | AZ50: =IFERROR((AK50/C50)^(1/14)-1,"n/m") -> 0.01679038 | BC50: 2028E | BD50: =BE50+$BD$49 -> 0.117 | BE50: 0.112 | BF50: =BE50+$BF$49 -> 0.102
B51: Client / customer staff headcount (period end) | C51: 22447 | D51: 21996 | E51: 20572 | F51: 20454 | G51: 20329 | H51: 21032 | I51: 22145 | J51: 23379 | K51: 24218 | L51: 24823 | M51: 25466 | N51: 26120 | O51: 26294 | P51: 26289 | Q51: 26289 | R51: 26438 | S51: 27208 | T51: 28269 | U51: 29070 | V51: 29070 | W51: 29747 | X51: 30249 | Y51: 30864 | Z51: 31228 | AA51: 31228 | AB51: 32000 | AC51: 32700 | AD51: 32700 | AE51: 32700 | AF51: 32700 | AG51: 30400 | AH51: 29600 | AI51: 29000 | AJ51: 28800 | AK51: 28800 | AL51: 28200 | BC51: 2029E | BD51: =BE51+$BD$49 -> 0.118 | BE51: 0.113 | BF51: =BE51+$BF$49 -> 0.103
B52: Revenue ex-billable expenses per average customer-staff head ($000, annualised) | D52: =IFERROR(D186*1/AVERAGE(D51,C51)*1000,"") -> 190.15228 | E52: =IFERROR(E186*1/AVERAGE(E51,D51)*1000,"") -> 187.5389 | F52: =IFERROR(F186*1/AVERAGE(F51,E51)*1000,"") -> 188.5752 | G52: =IFERROR(G186*1/AVERAGE(G51,F51)*1000,"") -> 190.89596 | H52: =IFERROR(H186*1/AVERAGE(H51,G51)*1000,"") -> 195.99173 | I52: =IFERROR(I186*1/AVERAGE(I51,H51)*1000,"") -> 199.66839 | J52: =IFERROR(J186*1/AVERAGE(J51,I51)*1000,"") -> 206.45695 | K52: =IFERROR(K186*1/AVERAGE(K51,J51)*1000,"") -> 217.04847 | L52: =IFERROR(L186*1/AVERAGE(L51,K51)*1000,"") -> 225.64997 | N52: =IFERROR(N186*4/AVERAGE(N51,M51)*1000,"") -> 227.33579 | O52: =IFERROR(O186*4/AVERAGE(O51,N51)*1000,"") -> 215.05247 | P52: =IFERROR(P186*4/AVERAGE(P51,O51)*1000,"") -> 240.55349 | Q52: =IFERROR(Q186*1/AVERAGE(Q51,L51)*1000,"") -> 230.45614 | R52: =IFERROR(R186*4/AVERAGE(R51,P51)*1000,"") -> 239.01743 | S52: =IFERROR(S186*4/AVERAGE(S51,R51)*1000,"") -> 240.69418 | T52: =IFERROR(T186*4/AVERAGE(T51,S51)*1000,"") -> 225.90234 | U52: =IFERROR(U186*4/AVERAGE(U51,T51)*1000,"") -> 236.36785 | V52: =IFERROR(V186*1/AVERAGE(V51,Q51)*1000,"") -> 233.02639 | W52: =IFERROR(W186*4/AVERAGE(W51,U51)*1000,"") -> 250.56456 | X52: =IFERROR(X186*4/AVERAGE(X51,W51)*1000,"") -> 245.5489 | Y52: =IFERROR(Y186*4/AVERAGE(Y51,X51)*1000,"") -> 231.68949 | Z52: =IFERROR(Z186*4/AVERAGE(Z51,Y51)*1000,"") -> 248.21735 | AA52: =IFERROR(AA186*1/AVERAGE(AA51,V51)*1000,"") -> 244.78822 | AB52: =IFERROR(AB186*4/AVERAGE(AB51,Z51)*1000,"") -> 252.64959 | AC52: =IFERROR(AC186*4/AVERAGE(AC51,AB51)*1000,"") -> 269.34949 | AD52: =IFERROR(AD186*4/AVERAGE(AD51,AC51)*1000,"") -> 242.03743 | AE52: =IFERROR(AE186*4/AVERAGE(AE51,AD51)*1000,"") -> 250.27523 | AF52: =IFERROR(AF186*1/AVERAGE(AF51,AA51)*1000,"") -> 256.53861 | AG52: =IFERROR(AG186*4/AVERAGE(AG51,AE51)*1000,"") -> 259.01743 | AH52: =IFERROR(AH186*4/AVERAGE(AH51,AG51)*1000,"") -> 262.93333 | AI52: =IFERROR(AI186*4/AVERAGE(AI51,AH51)*1000,"") -> 252.01365 | AJ52: =IFERROR(AJ186*4/AVERAGE(AJ51,AI51)*1000,"") -> 263.80623 | AK52: =IFERROR(AK186*1/AVERAGE(AK51,AF51)*1000,"") -> 252.58537 | AL52: =IFERROR(AL186*4/AVERAGE(AL51,AJ51)*1000,"") -> 275.78947 | BC52: 2030E | BD52: =BE52+$BD$49 -> 0.119 | BE52: 0.114 | BF52: =BE52+$BF$49 -> 0.104
B53: Revenue by contract type (% of revenue): | BC53: 2031E | BD53: =BE53+$BD$49 -> 0.12 | BE53: 0.115 | BF53: =BE53+$BF$49 -> 0.105
B54: Cost-reimbursable | C54: 0.54 | D54: 0.57 | E54: 0.55 | F54: 0.55 | G54: 0.51 | H54: 0.5 | I54: 0.51 | J54: 0.53 | K54: 0.57 | L54: 0.56 | M54: 0.56 | N54: 0.53 | O54: 0.53 | P54: 0.53 | Q54: 0.54 | R54: 0.53 | S54: 0.52 | T54: 0.53 | U54: 0.54 | V54: 0.53 | W54: 0.55 | X54: 0.55 | Y54: 0.55 | Z54: 0.56 | AA54: 0.55 | AB54: 0.56 | AC54: 0.57 | AD54: 0.57 | AE54: 0.59 | AF54: 0.57 | AG54: 0.6 | AH54: 0.59 | AI54: 0.58 | AJ54: 0.58 | AK54: 0.59 | AL54: 0.57 | AW54: =IFERROR(AVERAGE(AP54,AQ54,AR54,AS54,AT54),"n/m") -> n/m | AX54: =IFERROR(AVERAGE(Q54,V54,AA54,AF54,AK54),"n/m") -> 0.556 | AY54: =IFERROR(AVERAGE(H54,I54,J54,K54,L54,Q54,V54,AA54,AF54,AK54),"n/m") -> 0.545 | AZ54: =IFERROR(AVERAGE(C54,D54,E54,F54,G54,H54,I54,J54,K54,L54,Q54,V54,AA54,AF54,AK54),"n/m") -> 0.54466667 | BC54: ULTRA_M (Ultra adjusted EBITDA margin) | BD54: 0.03 | BE54: Δ → | BF54: -0.03 | BG54: Company: "EBITDA margins well above 20%". Assumption.
B55: Time-and-materials | C55: 0.31 | D55: 0.28 | E55: 0.28 | F55: 0.25 | G55: 0.26 | H55: 0.26 | I55: 0.25 | J55: 0.24 | K55: 0.23 | L55: 0.25 | M55: 0.25 | N55: 0.24 | O55: 0.24 | P55: 0.24 | Q55: 0.24 | R55: 0.24 | S55: 0.25 | T55: 0.25 | U55: 0.25 | V55: 0.25 | W55: 0.24 | X55: 0.24 | Y55: 0.24 | Z55: 0.23 | AA55: 0.24 | AB55: 0.23 | AC55: 0.23 | AD55: 0.23 | AE55: 0.22 | AF55: 0.23 | AG55: 0.22 | AH55: 0.22 | AI55: 0.22 | AJ55: 0.23 | AK55: 0.22 | AL55: 0.22 | AW55: =IFERROR(AVERAGE(AP55,AQ55,AR55,AS55,AT55),"n/m") -> n/m | AX55: =IFERROR(AVERAGE(Q55,V55,AA55,AF55,AK55),"n/m") -> 0.236 | AY55: =IFERROR(AVERAGE(H55,I55,J55,K55,L55,Q55,V55,AA55,AF55,AK55),"n/m") -> 0.241 | AZ55: =IFERROR(AVERAGE(C55,D55,E55,F55,G55,H55,I55,J55,K55,L55,Q55,V55,AA55,AF55,AK55),"n/m") -> 0.25266667 | BC55: 2028E | BD55: =BE55+$BD$54 -> 0.28 | BE55: 0.25 | BF55: =BE55+$BF$54 -> 0.22
B56: Fixed-price | C56: 0.15 | D56: 0.15 | E56: 0.17 | F56: 0.2 | G56: 0.23 | H56: 0.24 | I56: 0.24 | J56: 0.23 | K56: 0.2 | L56: 0.19 | M56: 0.19 | N56: 0.23 | O56: 0.23 | P56: 0.23 | Q56: 0.22 | R56: 0.23 | S56: 0.23 | T56: 0.22 | U56: 0.21 | V56: 0.22 | W56: 0.21 | X56: 0.21 | Y56: 0.21 | Z56: 0.21 | AA56: 0.21 | AB56: 0.21 | AC56: 0.2 | AD56: 0.2 | AE56: 0.19 | AF56: 0.2 | AG56: 0.18 | AH56: 0.19 | AI56: 0.2 | AJ56: 0.19 | AK56: 0.19 | AL56: 0.21 | AW56: =IFERROR(AVERAGE(AP56,AQ56,AR56,AS56,AT56),"n/m") -> n/m | AX56: =IFERROR(AVERAGE(Q56,V56,AA56,AF56,AK56),"n/m") -> 0.208 | AY56: =IFERROR(AVERAGE(H56,I56,J56,K56,L56,Q56,V56,AA56,AF56,AK56),"n/m") -> 0.214 | AZ56: =IFERROR(AVERAGE(C56,D56,E56,F56,G56,H56,I56,J56,K56,L56,Q56,V56,AA56,AF56,AK56),"n/m") -> 0.20266667 | BC56: 2029E | BD56: =BE56+$BD$54 -> 0.28 | BE56: 0.25 | BF56: =BE56+$BF$54 -> 0.22
BC57: 2030E | BD57: =BE57+$BD$54 -> 0.28 | BE57: 0.25 | BF57: =BE57+$BF$54 -> 0.22
B58: Future acquisitions (M&A lever — bolt-ons from 2028E) | AU58: M&A LEVER — acquired revenue = spend ÷ EV/sales; mid-year convention | BC58: 2031E | BD58: =BE58+$BD$54 -> 0.28 | BE58: 0.25 | BF58: =BE58+$BF$54 -> 0.22
B59: Acquisition spend (USDm, scenario) | AP59: 0 | AQ59: =MAX(0,CHOOSE(MATCH($AU$2,{"Bull","Base","Bear"},0),$BD$65,$BE$65,$BF$65)) -> 150 | AR59: =MAX(0,CHOOSE(MATCH($AU$2,{"Bull","Base","Bear"},0),$BD$66,$BE$66,$BF$66)) -> 150 | AS59: =MAX(0,CHOOSE(MATCH($AU$2,{"Bull","Base","Bear"},0),$BD$67,$BE$67,$BF$67)) -> 150 | AT59: =MAX(0,CHOOSE(MATCH($AU$2,{"Bull","Base","Bear"},0),$BD$68,$BE$68,$BF$68)) -> 150 | AU59: Scenario lever M&A_spend (Base $150m p.a. of bolt-ons from 2028E). Funded from cash / revolver (debt schedule). | BC59: B2B (annual book-to-bill, x) | BD59: 0.1 | BE59: Δ → | BF59: -0.15 | BG59: FY2022–26 1.1–1.4x (FY26 TTM 1.1x); Q1/27 1.5x.
B60: Purchase multiple — EV / sales (x) | AP60: 0 | AQ60: 2 | AR60: 2 | AS60: 2 | AT60: 2 | AU60: Assumption: technology-services bolt-ons ~1.5–2.5x sales (Liberty IT Solutions $725m, Q2 FY22; EverWatch $440m, Q3 FY23; Defy $235m, Q1 FY27 — target revenue not disclosed). | BC60: 2028E | BD60: =BE60+$BD$59 -> 1.15 | BE60: 1.05 | BF60: =BE60+$BF$59 -> 0.9
B61: Annualised revenue acquired in the year | AP61: 0 | AQ61: =IFERROR(AQ59/AQ60,0) -> 75 | AR61: =IFERROR(AR59/AR60,0) -> 75 | AS61: =IFERROR(AS59/AS60,0) -> 75 | AT61: =IFERROR(AT59/AT60,0) -> 75 | BC61: 2029E | BD61: =BE61+$BD$59 -> 1.15 | BE61: 1.05 | BF61: =BE61+$BF$59 -> 0.9
B62: Growth of acquired businesses after acquisition % | AP62: 0 | AQ62: 0.05 | AR62: 0.05 | AS62: 0.05 | AT62: 0.05 | BC62: 2030E | BD62: =BE62+$BD$59 -> 1.15 | BE62: 1.05 | BF62: =BE62+$BF$59 -> 0.9
B63: Run-rate revenue of businesses acquired (year end) | AP63: 0 | AQ63: =AP63*(1+AQ62)+AQ61 -> 75 | AR63: =AQ63*(1+AR62)+AR61 -> 153.75 | AS63: =AR63*(1+AS62)+AS61 -> 236.4375 | AT63: =AS63*(1+AT62)+AT61 -> 323.25937 | BC63: 2031E | BD63: =BE63+$BD$59 -> 1.15 | BE63: 1.05 | BF63: =BE63+$BF$59 -> 0.9
B64: Revenue from future acquisitions | AP64: 0 | AQ64: =AP63*(1+AQ62)+0.5*AQ61 -> 37.5 | AR64: =AQ63*(1+AR62)+0.5*AR61 -> 116.25 | AS64: =AR63*(1+AS62)+0.5*AS61 -> 198.9375 | AT64: =AS63*(1+AT62)+0.5*AT61 -> 285.75937 | AU64: Mid-year convention. | BC64: M&A_spend (bolt-on acquisitions, $m) | BD64: 150 | BE64: Δ → | BF64: -150 | BG64: Booz Allen bought Liberty IT ($725m, FY22), EverWatch ($440m, FY23), PGSC (FY25), Defy ($235m, Q1/27) and Ultra ($720m, Q2/27). Base $150m p.a. (assumption).
B65: Adjusted EBITDA margin of acquired businesses % | AP65: 0 | AQ65: 0.12 | AR65: 0.12 | AS65: 0.12 | AT65: 0.12 | BC65: 2028E | BD65: =MAX(0,BE65+$BD$64) -> 300 | BE65: 150 | BF65: =MAX(0,BE65+$BF$64) -> 0
B66: Adjusted EBITDA from future acquisitions | AP66: 0 | AQ66: =AQ64*AQ65 -> 4.5 | AR66: =AR64*AR65 -> 13.95 | AS66: =AS64*AS65 -> 23.8725 | AT66: =AT64*AT65 -> 34.291125 | BC66: 2029E | BD66: =MAX(0,BE66+$BD$64) -> 300 | BE66: 150 | BF66: =MAX(0,BE66+$BF$64) -> 0
B67: PP&E % of spend | AP67: 0 | AQ67: 0.02 | AR67: 0.02 | AS67: 0.02 | AT67: 0.02 | BC67: 2030E | BD67: =MAX(0,BE67+$BD$64) -> 300 | BE67: 150 | BF67: =MAX(0,BE67+$BF$64) -> 0
B68: Acquired intangibles % of spend | AP68: 0 | AQ68: 0.35 | AR68: 0.35 | AS68: 0.35 | AT68: 0.35 | AU68: Defy Security (Apr-2026): intangibles $86m of $235m (37%), goodwill $129m (Q1 FY27 10-Q Note 5). | BC68: 2031E | BD68: =MAX(0,BE68+$BD$64) -> 300 | BE68: 150 | BF68: =MAX(0,BE68+$BF$64) -> 0
B69: Intangible amortization life (years) | AP69: 0 | AQ69: 8 | AR69: 8 | AS69: 8 | AT69: 8
B70: Cumulative acquired intangibles (gross) | AP70: 0 | AQ70: =AP70+AQ59*AQ68 -> 52.5 | AR70: =AQ70+AR59*AR68 -> 105 | AS70: =AR70+AS59*AS68 -> 157.5 | AT70: =AS70+AT59*AT68 -> 210
B71: Amortization of future-acquisition intangibles (adjusted out as acquisition amortization) | AP71: 0 | AQ71: =IFERROR((AP70+0.5*AQ59*AQ68)/AQ69,0) -> 3.28125 | AR71: =IFERROR((AQ70+0.5*AR59*AR68)/AR69,0) -> 9.84375 | AS71: =IFERROR((AR70+0.5*AS59*AS68)/AS69,0) -> 16.40625 | AT71: =IFERROR((AS70+0.5*AT59*AT68)/AT69,0) -> 22.96875
B73: Group Total — revenue & adjusted EBITDA (build) → FY27 guidance calibration | AU73: GROUP TOTAL (CONSOLIDATED) — modelling logic
B74: Legacy revenue (excl. Ultra and future M&A; FY27 guidance basis) | C74: =IF(ISNUMBER(C120),C11*N(ISNUMBER(C11))+N(C16)+N(C20),"") -> 5859.218 | D74: =IF(ISNUMBER(D120),D11*N(ISNUMBER(D11))+N(D16)+N(D20),"") -> 5758.059 | E74: =IF(ISNUMBER(E120),E11*N(ISNUMBER(E11))+N(E16)+N(E20),"") -> 5478.693 | F74: =IF(ISNUMBER(F120),F11*N(ISNUMBER(F11))+N(F16)+N(F20),"") -> 5274.77 | G74: =IF(ISNUMBER(G120),G11*N(ISNUMBER(G11))+N(G16)+N(G20),"") -> 5405.738 | H74: =IF(ISNUMBER(H120),H11*N(ISNUMBER(H11))+N(H16)+N(H20),"") -> 5804.284 | I74: =IF(ISNUMBER(I120),I11*N(ISNUMBER(I11))+N(I16)+N(I20),"") -> 6171.853 | J74: =IF(ISNUMBER(J120),J11*N(ISNUMBER(J11))+N(J16)+N(J20),"") -> 6704.037 | ... AL74: =IF(ISNUMBER(AL120),AL11*N(ISNUMBER(AL11))+N(AL16)+N(AL20),"") -> 2800 | AM74: =AM11+AM16+AM20 -> 3011.4402 | AN74: =AN11+AN16+AN20 -> 2733.2356 | AO74: =AO11+AO16+AO20 -> 2905.3242 | AP74: =SUM(AL74,AM74,AN74,AO74) -> 11450 | AQ74: =AQ11+AQ16+AQ20 -> 11675.937 | AR74: =AR11+AR16+AR20 -> 12120.496 | AS74: =AS11+AS16+AS20 -> 12642.979 | AT74: =AT11+AT16+AT20 -> 13218.318
B75: Revenue (build) | C75: =C74 -> 5859.218 | D75: =D74 -> 5758.059 | E75: =E74 -> 5478.693 | F75: =F74 -> 5274.77 | G75: =G74 -> 5405.738 | H75: =H74 -> 5804.284 | I75: =I74 -> 6171.853 | J75: =J74 -> 6704.037 | ... AL75: =AL74 -> 2800 | AM75: =AM74+AM32+N(AM64) -> 3030.2314 | AN75: =AN74+AN32+N(AN64) -> 2778.2356 | AO75: =AO74+AO32+N(AO64) -> 2950.3242 | AP75: =AP74+AP32+N(AP64) -> 11558.791 | AQ75: =AQ74+AQ32+N(AQ64) -> 11920.437 | AR75: =AR74+AR32+N(AR64) -> 12474.796 | AS75: =AS74+AS32+N(AS64) -> 13108.532 | AT75: =AT74+AT32+N(AT64) -> 13797.355 | AU75: Σ customer types + Ultra + future acquisitions. | AW75: =IFERROR((AT75/AK75)^(1/5)-1,"n/m") -> 0.042278614 | AX75: =IFERROR((AK75/L75)^(1/5)-1,"n/m") -> 0.073748503 | AY75: =IFERROR((AK75/G75)^(1/10)-1,"n/m") -> 0.075727256 | AZ75: =IFERROR((AK75/C75)^(1/14)-1,"n/m") -> 0.047479433
B76: Revenue y/y % | D76: =IF(AND(ISNUMBER(D75),ISNUMBER(C75)),IFERROR(D75/C75-1,""),"") -> -0.017264932 | E76: =IF(AND(ISNUMBER(E75),ISNUMBER(D75)),IFERROR(E75/D75-1,""),"") -> -0.048517391 | F76: =IF(AND(ISNUMBER(F75),ISNUMBER(E75)),IFERROR(F75/E75-1,""),"") -> -0.037221104 | G76: =IF(AND(ISNUMBER(G75),ISNUMBER(F75)),IFERROR(G75/F75-1,""),"") -> 0.024829139 | H76: =IF(AND(ISNUMBER(H75),ISNUMBER(G75)),IFERROR(H75/G75-1,""),"") -> 0.073726474 | I76: =IF(AND(ISNUMBER(I75),ISNUMBER(H75)),IFERROR(I75/H75-1,""),"") -> 0.063327191 | J76: =IF(AND(ISNUMBER(J75),ISNUMBER(I75)),IFERROR(J75/I75-1,""),"") -> 0.086227588 | K76: =IF(AND(ISNUMBER(K75),ISNUMBER(J75)),IFERROR(K75/J75-1,""),"") -> 0.11333529 | L76: =IF(AND(ISNUMBER(L75),ISNUMBER(K75)),IFERROR(L75/K75-1,""),"") -> 0.052934809 | Q76: =IF(AND(ISNUMBER(Q75),ISNUMBER(L75)),IFERROR(Q75/L75-1,""),"") -> 0.064227762 | R76: =IF(AND(ISNUMBER(R75),ISNUMBER(M75)),IFERROR(R75/M75-1,""),"") -> 0.13098308 | S76: =IF(AND(ISNUMBER(S75),ISNUMBER(N75)),IFERROR(S75/N75-1,""),"") -> 0.091611832 | T76: =IF(AND(ISNUMBER(T75),ISNUMBER(O75)),IFERROR(T75/O75-1,""),"") -> 0.12142407 | U76: =IF(AND(ISNUMBER(U75),ISNUMBER(P75)),IFERROR(U75/P75-1,""),"") -> 0.087211069 | V76: =IF(AND(ISNUMBER(V75),ISNUMBER(Q75)),IFERROR(V75/Q75-1,""),"") -> 0.10703528 | W76: =IF(AND(ISNUMBER(W75),ISNUMBER(R75)),IFERROR(W75/R75-1,""),"") -> 0.17998133 | X76: =IF(AND(ISNUMBER(X75),ISNUMBER(S75)),IFERROR(X75/S75-1,""),"") -> 0.15976939 | ... AP76: =IF(AND(ISNUMBER(AP75),ISNUMBER(AK75)),IFERROR(AP75/AK75-1,""),"") -> 0.030470822 | AQ76: =IF(AND(ISNUMBER(AQ75),ISNUMBER(AP75)),IFERROR(AQ75/AP75-1,""),"") -> 0.031287524 | AR76: =IF(AND(ISNUMBER(AR75),ISNUMBER(AQ75)),IFERROR(AR75/AQ75-1,""),"") -> 0.046504935 | AS76: =IF(AND(ISNUMBER(AS75),ISNUMBER(AR75)),IFERROR(AS75/AR75-1,""),"") -> 0.050801286 | AT76: =IF(AND(ISNUMBER(AT75),ISNUMBER(AS75)),IFERROR(AT75/AS75-1,""),"") -> 0.052547716
B77: Check: build vs consolidated revenue (should be 0; ±0.15, ±0.6 from Q4 FY25) | C77: =IF(ISNUMBER(C75),IF(ABS(C75-C120)<=0.15,0,ROUND(C75-C120,1)),"") -> 0 | D77: =IF(ISNUMBER(D75),IF(ABS(D75-D120)<=0.15,0,ROUND(D75-D120,1)),"") -> 0 | E77: =IF(ISNUMBER(E75),IF(ABS(E75-E120)<=0.15,0,ROUND(E75-E120,1)),"") -> 0 | F77: =IF(ISNUMBER(F75),IF(ABS(F75-F120)<=0.15,0,ROUND(F75-F120,1)),"") -> 0 | G77: =IF(ISNUMBER(G75),IF(ABS(G75-G120)<=0.15,0,ROUND(G75-G120,1)),"") -> 0 | H77: =IF(ISNUMBER(H75),IF(ABS(H75-H120)<=0.15,0,ROUND(H75-H120,1)),"") -> 0 | I77: =IF(ISNUMBER(I75),IF(ABS(I75-I120)<=0.15,0,ROUND(I75-I120,1)),"") -> 0 | J77: =IF(ISNUMBER(J75),IF(ABS(J75-J120)<=0.15,0,ROUND(J75-J120,1)),"") -> 0 | ... AD77: =IF(ISNUMBER(AD75),IF(ABS(AD75-AD120)<=0.15,0,ROUND(AD75-AD120,1)),"") -> 0 | AE77: =IF(ISNUMBER(AE75),IF(ABS(AE75-AE120)<=0.6,0,ROUND(AE75-AE120,1)),"") -> 0 | AF77: =IF(ISNUMBER(AF75),IF(ABS(AF75-AF120)<=0.6,0,ROUND(AF75-AF120,1)),"") -> 0 | AG77: =IF(ISNUMBER(AG75),IF(ABS(AG75-AG120)<=0.6,0,ROUND(AG75-AG120,1)),"") -> 0 | AH77: =IF(ISNUMBER(AH75),IF(ABS(AH75-AH120)<=0.6,0,ROUND(AH75-AH120,1)),"") -> 0 | AI77: =IF(ISNUMBER(AI75),IF(ABS(AI75-AI120)<=0.6,0,ROUND(AI75-AI120,1)),"") -> 0 | AJ77: =IF(ISNUMBER(AJ75),IF(ABS(AJ75-AJ120)<=0.6,0,ROUND(AJ75-AJ120,1)),"") -> 0 | AK77: =IF(ISNUMBER(AK75),IF(ABS(AK75-AK120)<=0.6,0,ROUND(AK75-AK120,1)),"") -> 0 | AL77: =IF(ISNUMBER(AL75),IF(ABS(AL75-AL120)<=0.6,0,ROUND(AL75-AL120,1)),"") -> 0 | ... AT77: =IF(ISNUMBER(AT75),IF(ABS(AT75-AT120)<=0.6,0,ROUND(AT75-AT120,1)),"") -> 0
B78: Legacy adjusted EBITDA margin on revenue % | C78: =IF(ISNUMBER(C174),IFERROR(C174/C120,""),"") -> 0.083297805 | D78: =IF(ISNUMBER(D174),IFERROR(D174/D120,""),"") -> 0.091842755 | E78: =IF(ISNUMBER(E174),IFERROR(E174/E120,""),"") -> 0.097474343 | F78: =IF(ISNUMBER(F174),IFERROR(F174/F120,""),"") -> 0.099250015 | G78: =IF(ISNUMBER(G174),IFERROR(G174/G120,""),"") -> 0.093626439 | H78: =IF(ISNUMBER(H174),IFERROR(H174/H120,""),"") -> 0.094265718 | I78: =IF(ISNUMBER(I174),IFERROR(I174/I120,""),"") -> 0.094759386 | J78: =IF(ISNUMBER(J174),IFERROR(J174/J120,""),"") -> 0.10063026 | ... AL78: =IF(ISNUMBER(AL174),IFERROR(AL174/AL120,""),"") -> 0.11928571 | AM78: =AM79+$AM$91 -> 0.1090455 | AN78: =AN79+$AM$91 -> 0.1057134 | AO78: =AO79+$AM$91 -> 0.10796604 | AP78: =IFERROR(AP80/AP74,"") -> 0.11048035 | AQ78: =CHOOSE(MATCH($AU$2,{"Bull","Base","Bear"},0),$BD$50,$BE$50,$BF$50) -> 0.112 | AR78: =CHOOSE(MATCH($AU$2,{"Bull","Base","Bear"},0),$BD$51,$BE$51,$BF$51) -> 0.113 | AS78: =CHOOSE(MATCH($AU$2,{"Bull","Base","Bear"},0),$BD$52,$BE$52,$BF$52) -> 0.114 | AT78: =CHOOSE(MATCH($AU$2,{"Bull","Base","Bear"},0),$BD$53,$BE$53,$BF$53) -> 0.115 | AU78: History = company adjusted EBITDA margin on revenue. Q2–Q4/27E: prior-year quarter margin + Q1/27 y/y drift + calibration Δ. 2028E+: scenario lever on legacy revenue. | AW78: =IFERROR(AVERAGE(AP78,AQ78,AR78,AS78,AT78),"n/m") -> 0.11289607 | AX78: =IFERROR(AVERAGE(Q78,V78,AA78,AF78,AK78),"n/m") -> 0.11017009 | AY78: =IFERROR(AVERAGE(H78,I78,J78,K78,L78,Q78,V78,AA78,AF78,AK78),"n/m") -> 0.10483793 | AZ78: =IFERROR(AVERAGE(C78,D78,E78,F78,G78,H78,I78,J78,K78,L78,Q78,V78,AA78,AF78,AK78),"n/m") -> 0.10092471
B79: Q2–Q4/27E margin before calibration (prior-year quarter + Q1/27 y/y drift) | AM79: =AH78+IFERROR(AL78-AG78,0) -> 0.12503529 | AN79: =AI78+IFERROR(AL78-AG78,0) -> 0.12170319 | AO79: =AJ78+IFERROR(AL78-AG78,0) -> 0.12395583
B80: Legacy adjusted EBITDA | C80: =C174 -> 488.06 | D80: =D174 -> 528.836 | E80: =E174 -> 534.032 | F80: =F174 -> 523.521 | G80: =G174 -> 506.12 | H80: =H174 -> 547.145 | I80: =I174 -> 584.841 | J80: =J174 -> 674.629 | ... AL80: =AL174 -> 334 | AM80: =AM74*AM78 -> 328.38402 | AN80: =AN74*AN78 -> 288.93964 | AO80: =AO74*AO78 -> 313.67634 | AP80: =SUM(AL80,AM80,AN80,AO80) -> 1265 | AQ80: =AQ74*AQ78 -> 1307.705 | AR80: =AR74*AR78 -> 1369.6161 | AS80: =AS74*AS78 -> 1441.2996 | AT80: =AT74*AT78 -> 1520.1066
B81: Adjusted EBITDA (build) | C81: =C80 -> 488.06 | D81: =D80 -> 528.836 | E81: =E80 -> 534.032 | F81: =F80 -> 523.521 | G81: =G80 -> 506.12 | H81: =H80 -> 547.145 | I81: =I80 -> 584.841 | J81: =J80 -> 674.629 | ... AL81: =AL80 -> 334 | AM81: =AM80+AM34+N(AM66) -> 333.08182 | AN81: =AN80+AN34+N(AN66) -> 300.18964 | AO81: =AO80+AO34+N(AO66) -> 324.92634 | AP81: =AP80+AP34+N(AP66) -> 1292.1978 | AQ81: =AQ80+AQ34+N(AQ66) -> 1363.955 | AR81: =AR80+AR34+N(AR66) -> 1443.0786 | AS81: =AS80+AS34+N(AS66) -> 1531.8261 | AT81: =AT80+AT34+N(AT66) -> 1627.7171 | AU81: Legacy + Ultra + future acquisitions. Company definition; drives the GAAP P&L below (operating income = adjusted EBITDA − D&A − operating adjusting items). | AW81: =IFERROR((AT81/AK81)^(1/5)-1,"n/m") -> 0.057804503 | AX81: =IFERROR((AK81/L81)^(1/5)-1,"n/m") -> 0.079165954 | AY81: =IFERROR((AK81/G81)^(1/10)-1,"n/m") -> 0.092772704 | AZ81: =IFERROR((AK81/C81)^(1/14)-1,"n/m") -> 0.068189922
B82: Adjusted EBITDA margin on revenue % | C82: =IF(AND(ISNUMBER(C81),ISNUMBER(C120)),IFERROR(C81/C120,""),"") -> 0.083297805 | D82: =IF(AND(ISNUMBER(D81),ISNUMBER(D120)),IFERROR(D81/D120,""),"") -> 0.091842755 | E82: =IF(AND(ISNUMBER(E81),ISNUMBER(E120)),IFERROR(E81/E120,""),"") -> 0.097474343 | F82: =IF(AND(ISNUMBER(F81),ISNUMBER(F120)),IFERROR(F81/F120,""),"") -> 0.099250015 | G82: =IF(AND(ISNUMBER(G81),ISNUMBER(G120)),IFERROR(G81/G120,""),"") -> 0.093626439 | H82: =IF(AND(ISNUMBER(H81),ISNUMBER(H120)),IFERROR(H81/H120,""),"") -> 0.094265718 | I82: =IF(AND(ISNUMBER(I81),ISNUMBER(I120)),IFERROR(I81/I120,""),"") -> 0.094759386 | J82: =IF(AND(ISNUMBER(J81),ISNUMBER(J120)),IFERROR(J81/J120,""),"") -> 0.10063026 | ... AT82: =IF(AND(ISNUMBER(AT81),ISNUMBER(AT120)),IFERROR(AT81/AT120,""),"") -> 0.11797313 | AW82: =IFERROR(AVERAGE(AP82,AQ82,AR82,AS82,AT82),"n/m") -> 0.11534498 | AX82: =IFERROR(AVERAGE(Q82,V82,AA82,AF82,AK82),"n/m") -> 0.11017009 | AY82: =IFERROR(AVERAGE(H82,I82,J82,K82,L82,Q82,V82,AA82,AF82,AK82),"n/m") -> 0.10483793 | AZ82: =IFERROR(AVERAGE(C82,D82,E82,F82,G82,H82,I82,J82,K82,L82,Q82,V82,AA82,AF82,AK82),"n/m") -> 0.10092471
B83: Check: build vs adjusted EBITDA bridge (should be 0; ±0.15, ±0.6 from Q4 FY25) | C83: =IF(AND(ISNUMBER(C81),ISNUMBER(C174)),IF(ABS(C81-C174)<=0.15,0,ROUND(C81-C174,1)),"") -> 0 | D83: =IF(AND(ISNUMBER(D81),ISNUMBER(D174)),IF(ABS(D81-D174)<=0.15,0,ROUND(D81-D174,1)),"") -> 0 | E83: =IF(AND(ISNUMBER(E81),ISNUMBER(E174)),IF(ABS(E81-E174)<=0.15,0,ROUND(E81-E174,1)),"") -> 0 | F83: =IF(AND(ISNUMBER(F81),ISNUMBER(F174)),IF(ABS(F81-F174)<=0.15,0,ROUND(F81-F174,1)),"") -> 0 | G83: =IF(AND(ISNUMBER(G81),ISNUMBER(G174)),IF(ABS(G81-G174)<=0.15,0,ROUND(G81-G174,1)),"") -> 0 | H83: =IF(AND(ISNUMBER(H81),ISNUMBER(H174)),IF(ABS(H81-H174)<=0.15,0,ROUND(H81-H174,1)),"") -> 0 | I83: =IF(AND(ISNUMBER(I81),ISNUMBER(I174)),IF(ABS(I81-I174)<=0.15,0,ROUND(I81-I174,1)),"") -> 0 | J83: =IF(AND(ISNUMBER(J81),ISNUMBER(J174)),IF(ABS(J81-J174)<=0.15,0,ROUND(J81-J174,1)),"") -> 0 | ... AD83: =IF(AND(ISNUMBER(AD81),ISNUMBER(AD174)),IF(ABS(AD81-AD174)<=0.15,0,ROUND(AD81-AD174,1)),"") -> 0 | AE83: =IF(AND(ISNUMBER(AE81),ISNUMBER(AE174)),IF(ABS(AE81-AE174)<=0.6,0,ROUND(AE81-AE174,1)),"") -> 0 | AF83: =IF(AND(ISNUMBER(AF81),ISNUMBER(AF174)),IF(ABS(AF81-AF174)<=0.6,0,ROUND(AF81-AF174,1)),"") -> 0 | AG83: =IF(AND(ISNUMBER(AG81),ISNUMBER(AG174)),IF(ABS(AG81-AG174)<=0.6,0,ROUND(AG81-AG174,1)),"") -> 0 | AH83: =IF(AND(ISNUMBER(AH81),ISNUMBER(AH174)),IF(ABS(AH81-AH174)<=0.6,0,ROUND(AH81-AH174,1)),"") -> 0 | AI83: =IF(AND(ISNUMBER(AI81),ISNUMBER(AI174)),IF(ABS(AI81-AI174)<=0.6,0,ROUND(AI81-AI174,1)),"") -> 0 | AJ83: =IF(AND(ISNUMBER(AJ81),ISNUMBER(AJ174)),IF(ABS(AJ81-AJ174)<=0.6,0,ROUND(AJ81-AJ174,1)),"") -> 0 | AK83: =IF(AND(ISNUMBER(AK81),ISNUMBER(AK174)),IF(ABS(AK81-AK174)<=0.6,0,ROUND(AK81-AK174,1)),"") -> 0 | AL83: =IF(AND(ISNUMBER(AL81),ISNUMBER(AL174)),IF(ABS(AL81-AL174)<=0.6,0,ROUND(AL81-AL174,1)),"") -> 0 | ... AT83: =IF(AND(ISNUMBER(AT81),ISNUMBER(AT174)),IF(ABS(AT81-AT174)<=0.6,0,ROUND(AT81-AT174,1)),"") -> 0
B84: Memo: FY27 revenue guidance (scenario end-point; legacy basis, excl. Ultra — assumption) | AP84: =CHOOSE(MATCH($AU$2,{"Bull","Base","Bear"},0),$BD$12,$BE$12,$BF$12) -> 11450 | AU84: Company FY27 revenue guidance $11.2–11.7bn (22-May-2026; reiterated 24-Jul-2026). The releases do not say whether the FY27 guidance includes Ultra Mission Solutions. The guidance was issued on 22-May-2026, before the 19-Jun-2026 agreement, and reiterated unchanged on 24-Jul-2026, before the 24-Aug-2026 close. The model therefore treats it as excluding Ultra (assumption) and calibrates the legacy business, with Ultra added in its own block. Defy Security (closed 6-Apr-2026, within Q1 actuals) is inside the guidance and the Q1 y/y trend.
B85: Legacy revenue before calibration (Q2–Q4/27E helper) | AM85: =AH11*(1+AM13)+AH16*(1+AM18) -> 2782.5419 | AN85: =AI11*(1+AN13)+AI16*(1+AN18) -> 2525.7223 | AO85: =AJ11*(1+AO13)+AJ16*(1+AO18) -> 2684.9006
B86: Revenue sensitivity to +1.00 of growth (Q2–Q4/27E helper) | AM86: =AH11+AH16 -> 2890 | AN86: =AI11+AI16 -> 2620 | AO86: =AJ11+AJ16 -> 2783
B87: Guidance calibration: Δ y/y growth applied to both customer types (Q2–Q4/27E) | AM87: =(AP84-AL74-((AM85+AN85+AO85)))/((AM86+AN86+AO86)) -> 0.079203571 | AN87: =$AM$87 -> 0.079203571 | AO87: =$AM$87 -> 0.079203571 | AU87: Solves the uniform growth shift (vs Q1/27 y/y rates) so that FY27 legacy revenue = the guidance end-point for the active scenario (closed form; no circularity).
B88: Check: FY27 legacy revenue vs guidance end-point (should be 0; ±0.15, ±0.6 from Q4 FY25) | AP88: =ROUND(AP74-AP84,1) -> 0
B89: Memo: FY27 adjusted EBITDA guidance (scenario end-point; legacy basis) | AP89: =CHOOSE(MATCH($AU$2,{"Bull","Base","Bear"},0),$BD$13,$BE$13,$BF$13) -> 1265 | AU89: Company FY27 adjusted EBITDA guidance $1,240–1,290m (~11% margin on revenue). Drives the adjusted EBITDA margin calibration (legacy basis).
B90: Legacy adjusted EBITDA before margin calibration (Q2–Q4/27E helper) | AM90: =AM74*AM79 -> 376.53631 | AN90: =AN74*AN79 -> 332.6435 | AO90: =AO74*AO79 -> 360.13186
B91: Guidance calibration: Δ adjusted EBITDA margin (Q2–Q4/27E) | AM91: =(AP89-AL80-((AM90+AN90+AO90)))/((AM74+AN74+AO74)) -> -0.015989787 | AN91: =$AM$91 -> -0.015989787 | AO91: =$AM$91 -> -0.015989787 | AU91: Solves the uniform margin shift so that FY27 legacy adjusted EBITDA = the guidance end-point for the active scenario.
B92: Check: FY27 legacy adjusted EBITDA vs guidance end-point (should be 0; ±0.15, ±0.6 from Q4 FY25) | AP92: =ROUND(AP80-AP89,1) -> 0
B93: Memo: FY27 adjusted diluted EPS guidance (scenario end-point, $) — information, not forced | AP93: =CHOOSE(MATCH($AU$2,{"Bull","Base","Bear"},0),$BD$14,$BE$14,$BF$14) -> 6.175
B94: Model FY27 adjusted EPS − guidance ($; incl. Ultra, which the guidance is assumed to exclude) | AP94: =AP203-AP93 -> 0.22938573
B95: Memo: FY27 free cash flow guidance (scenario end-point) — solved via payables & accrued % (working-capital block) | AP95: =CHOOSE(MATCH($AU$2,{"Bull","Base","Bear"},0),$BD$15,$BE$15,$BF$15) -> 875
B96: Model FY27 diluted shares − guidance mid-point (119m) | AP96: =AP146-119 -> 0.8993955
B98: Cost drivers, D&A & adjusting items | AU98: COST DRIVERS — inputs that drive forecast cost lines (Q2–Q4/27E: point estimates / drift; 2028E+: % of revenue or schedules)
B99: Billable expenses % of revenue | C99: =IF(AND(ISNUMBER(C122),ISNUMBER(C120)),IFERROR(C122/C120,""),"") -> 0.26331534 | D99: =IF(AND(ISNUMBER(D122),ISNUMBER(D120)),IFERROR(D122/D120,""),"") -> 0.26616434 | E99: =IF(AND(ISNUMBER(E122),ISNUMBER(E120)),IFERROR(E122/E120,""),"") -> 0.27143609 | F99: =IF(AND(ISNUMBER(F122),ISNUMBER(F120)),IFERROR(F122/F120,""),"") -> 0.26665182 | G99: =IF(AND(ISNUMBER(G122),ISNUMBER(G120)),IFERROR(G122/G120,""),"") -> 0.27990313 | H99: =IF(AND(ISNUMBER(H122),ISNUMBER(H120)),IFERROR(H122/H120,""),"") -> 0.301687 | I99: =IF(AND(ISNUMBER(I122),ISNUMBER(I120)),IFERROR(I122/I120,""),"") -> 0.30158074 | J99: =IF(AND(ISNUMBER(J122),ISNUMBER(J120)),IFERROR(J122/J120,""),"") -> 0.29902341 | ... AL99: =IF(AND(ISNUMBER(AL122),ISNUMBER(AL120)),IFERROR(AL122/AL120,""),"") -> 0.29821429 | AM99: =AH99+IFERROR(AL99-AG99,0) -> 0.31456175 | AN99: =AI99+IFERROR(AL99-AG99,0) -> 0.29233454 | AO99: =AJ99+IFERROR(AL99-AG99,0) -> 0.31204226 | AP99: =IF(AND(ISNUMBER(AP122),ISNUMBER(AP120)),IFERROR(AP122/AP120,""),"") -> 0.30461619 | AQ99: 0.305 | AR99: 0.305 | AS99: 0.305 | AT99: 0.305 | AU99: Subcontractor, travel and other direct non-labor costs (pass-through, low margin). Q2–Q4/27E: prior-year quarter + Q1/27 y/y drift; 2028E+ input. | AW99: =IFERROR(AVERAGE(AP99,AQ99,AR99,AS99,AT99),"n/m") -> 0.30492324 | AX99: =IFERROR(AVERAGE(Q99,V99,AA99,AF99,AK99),"n/m") -> 0.30601769 | AY99: =IFERROR(AVERAGE(H99,I99,J99,K99,L99,Q99,V99,AA99,AF99,AK99),"n/m") -> 0.30362738 | AZ99: =IFERROR(AVERAGE(C99,D99,E99,F99,G99,H99,I99,J99,K99,L99,Q99,V99,AA99,AF99,AK99),"n/m") -> 0.29224964
B100: Cost of revenue (direct labor & related) % of revenue | C100: =IF(AND(ISNUMBER(C121),ISNUMBER(C120)),IFERROR(C121/C120,""),"") -> 0.50081393 | D100: =IF(AND(ISNUMBER(D121),ISNUMBER(D120)),IFERROR(D121/D120,""),"") -> 0.4986472 | E100: =IF(AND(ISNUMBER(E121),ISNUMBER(E120)),IFERROR(E121/E120,""),"") -> 0.4957593 | F100: =IF(AND(ISNUMBER(F121),ISNUMBER(F120)),IFERROR(F121/F120,""),"") -> 0.49174637 | G100: =IF(AND(ISNUMBER(G121),ISNUMBER(G120)),IFERROR(G121/G120,""),"") -> 0.47727544 | H100: =IF(AND(ISNUMBER(H121),ISNUMBER(H120)),IFERROR(H121/H120,""),"") -> 0.46379226 | I100: =IF(AND(ISNUMBER(I121),ISNUMBER(I120)),IFERROR(I121/I120,""),"") -> 0.46454493 | J100: =IF(AND(ISNUMBER(J121),ISNUMBER(J120)),IFERROR(J121/J120,""),"") -> 0.46247746 | ... AL100: =IF(AND(ISNUMBER(AL121),ISNUMBER(AL120)),IFERROR(AL121/AL120,""),"") -> 0.47714286 | AM100: =AH100+IFERROR(AL100-AG100,0) -> 0.45414857 | AN100: =AI100+IFERROR(AL100-AG100,0) -> 0.4710151 | AO100: =AJ100+IFERROR(AL100-AG100,0) -> 0.45149405 | AP100: =IF(AND(ISNUMBER(AP121),ISNUMBER(AP120)),IFERROR(AP121/AP120,""),"") -> 0.46309514 | AQ100: 0.475 | AR100: 0.475 | AS100: 0.475 | AT100: 0.475 | AU100: G&A is the implied balancing line: revenue − cost of revenue − billable expenses − D&A − operating income (from the adjusted EBITDA build). | AW100: =IFERROR(AVERAGE(AP100,AQ100,AR100,AS100,AT100),"n/m") -> 0.47261903 | AX100: =IFERROR(AVERAGE(Q100,V100,AA100,AF100,AK100),"n/m") -> 0.4636059 | AY100: =IFERROR(AVERAGE(H100,I100,J100,K100,L100,Q100,V100,AA100,AF100,AK100),"n/m") -> 0.46269817 | AZ100: =IFERROR(AVERAGE(C100,D100,E100,F100,G100,H100,I100,J100,K100,L100,Q100,V100,AA100,AF100,AK100),"n/m") -> 0.47274826
B101: Depreciation & amortization (total, income statement) | C101: =IF(AND(ISNUMBER(C104),ISNUMBER(C102)),C104+C102,"") -> 75.205 | D101: =IF(AND(ISNUMBER(D104),ISNUMBER(D102)),D104+D102,"") -> 74.009 | E101: =IF(AND(ISNUMBER(E104),ISNUMBER(E102)),E104+E102,"") -> 72.327 | F101: =IF(AND(ISNUMBER(F104),ISNUMBER(F102)),F104+F102,"") -> 62.66 | G101: =IF(AND(ISNUMBER(G104),ISNUMBER(G102)),G104+G102,"") -> 61.536 | H101: =IF(AND(ISNUMBER(H104),ISNUMBER(H102)),H104+H102,"") -> 59.544 | I101: =IF(AND(ISNUMBER(I104),ISNUMBER(I102)),I104+I102,"") -> 64.756 | J101: =IF(AND(ISNUMBER(J104),ISNUMBER(J102)),J104+J102,"") -> 68.575 | ... AT101: =IF(AND(ISNUMBER(AT104),ISNUMBER(AT102)),AT104+AT102,"") -> 221.7423
B102: Acquisition amortization (adjusted out of adjusted net income / operating income where the company did so) | C102: 16.364 | D102: 12.51 | E102: 8.45 | F102: 4.225 | G102: 4.225 | H102: 4.225 | I102: 0 | J102: 0 | K102: 0 | L102: 0 | M102: 2.658 | N102: 11.868 | O102: 11.884 | P102: 11.885 | Q102: 38.295 | R102: 11.087 | S102: 11.087 | T102: 14.101 | U102: 15.278 | V102: 51.553 | W102: 13.108 | X102: 13.596 | Y102: 13.597 | Z102: 13.596 | AA102: 53.897 | AB102: 12.684 | AC102: 13.326 | AD102: 13.386 | AE102: 13 | AF102: 54 | AG102: 12 | AH102: 12 | AI102: 12 | AJ102: 12 | AK102: 48 | AL102: 15 | AM102: =($BE$21-AL102)/3+AM38 -> 18.006593 | AN102: =($BE$21-AL102)/3+AN38 -> 22.2 | AO102: =($BE$21-AL102)/3+AO38 -> 22.2 | AP102: =SUM(AL102,AM102,AN102,AO102) -> 77.406593 | AQ102: =AQ103+AQ38+N(AQ71) -> 82.38125 | AR102: =AR103+AR38+N(AR71) -> 81.64375 | AS102: =AS103+AS38+N(AS71) -> 81.50625 | AT102: =AT103+AT38+N(AT71) -> 83.76875 | AU102: Carlyle-acquisition intangibles to FY2017; none adjusted FY2018–21; "significant acquisition amortization" (Liberty, EverWatch, PGSC, Defy) from FY2022. Q2–Q4/27E: FY27 point estimate (excl. Ultra) + Ultra. 2028E+: schedule + Ultra + future M&A.
...

Sheet Bull-Base-Bear
B2: Booz Allen Hamilton Holding Corporation (BAH) — Bull / Base / Bear Case P&L Summary | J2: Share price ($): | K2: =Model!$AP$385 -> 75
B3: Adjusted figures (company definitions: adjusted EBITDA, adjusted net income, adjusted diluted EPS) · USD millions · fiscal years ended 31 March · Live panel linked to Model — toggle scenario via Model!AU2. Bull and Bear panels are value snapshots generated from the Model with the switch set to each case. FY2027E = Q1 actual + Q2–Q4 calibrated to FY27 guidance (revenue $11.2–11.7bn, adjusted EBITDA $1,240–1,290m), plus Ultra Mission Solutions from 24-Aug-2026. | J3: As of: | K3: =TODAY() -> 2026-10-12 00:00:00
B5: Scenario: | C5: =Model!$AU$2 -> Base | N5: Scenario: | O5: Bull | P5: Snapshot (values) — Model run with switch = Bull | Z5: Scenario: | AA5: Bear | AB5: Snapshot (values) — Model run with switch = Bear
B7: (USDm, except EPS and shares) | C7: 2026A | D7: 2027E | E7: 2028E | F7: 2029E | G7: 2030E | H7: 2031E | I7: 26-'31 CAGR | J7: LT Hist Avg | K7: LT Hist Min | L7: LT Hist Max | N7: (USDm, except EPS and shares) | O7: 2026A | P7: 2027E | Q7: 2028E | R7: 2029E | S7: 2030E | T7: 2031E | U7: 26-'31 CAGR | V7: LT Hist Avg | W7: LT Hist Min | X7: LT Hist Max | Z7: (USDm, except EPS and shares) | AA7: 2026A | AB7: 2027E | AC7: 2028E | AD7: 2029E | AE7: 2030E | AF7: 2031E | AG7: 26-'31 CAGR | AH7: LT Hist Avg | AI7: LT Hist Min | AJ7: LT Hist Max
B9: Revenue | C9: =Model!AK120 -> 11217 | D9: =Model!AP120 -> 11558.791 | E9: =Model!AQ120 -> 11920.437 | F9: =Model!AR120 -> 12474.796 | G9: =Model!AS120 -> 13108.532 | H9: =Model!AT120 -> 13797.355 | I9: =IFERROR((H9/C9)^(1/5)-1,"n/m") -> 0.042278614 | N9: Revenue | O9: 11217 | P9: 11808.791 | Q9: 12514.748 | R9: 13481.984 | S9: 14569.845 | T9: 15759.788 | U9: 0.070371979 | Z9: Revenue | AA9: 11217 | AB9: 11308.791 | AC9: 11249.837 | AD9: 11328.21 | AE9: 11458.893 | AF9: 11614.568 | AG9: 0.0069902638
B10: Revenue y/y % | D10: =IFERROR(D9/C9-1,"") -> 0.030470822 | E10: =IFERROR(E9/D9-1,"") -> 0.031287524 | F10: =IFERROR(F9/E9-1,"") -> 0.046504935 | G10: =IFERROR(G9/F9-1,"") -> 0.050801286 | H10: =IFERROR(H9/G9-1,"") -> 0.052547716 | N10: Revenue y/y % | P10: 0.052758421 | Q10: 0.059782268 | R10: 0.077287703 | S10: 0.080690037 | T10: 0.081671615 | Z10: Revenue y/y % | AB10: 0.0081832227 | AC10: -0.0052131 | AD10: 0.0069665293 | AE10: 0.011536068 | AF10: 0.013585586
B11: National Security revenue y/y % | C11: =Model!AK214 -> 0.020358515 | D11: =Model!AP214 -> 0.072808965 | E11: =Model!AQ214 -> 0.04 | F11: =Model!AR214 -> 0.05 | G11: =Model!AS214 -> 0.05 | H11: =Model!AT214 -> 0.05 | N11: National Security revenue y/y % | O11: 0.020358515 | P11: 0.095385295 | Q11: 0.06 | R11: 0.07 | S11: 0.07 | T11: 0.07 | Z11: National Security revenue y/y % | AA11: 0.020358515 | AB11: 0.050232636 | AC11: 0.01 | AD11: 0.02 | AE11: 0.02 | AF11: 0.02
B12: Adjusted EBITDA | C12: =Model!AK174 -> 1229 | D12: =Model!AP174 -> 1292.1978 | E12: =Model!AQ174 -> 1363.955 | F12: =Model!AR174 -> 1443.0786 | G12: =Model!AS174 -> 1531.8261 | H12: =Model!AT174 -> 1627.7171 | I12: =IFERROR((H12/C12)^(1/5)-1,"n/m") -> 0.057804503 | N12: Adjusted EBITDA | O12: 1229 | P12: 1317.1978 | Q12: 1499.6585 | R12: 1633.3295 | S12: 1783.035 | T12: 1946.9752 | U12: 0.096381517 | Z12: Adjusted EBITDA | AA12: 1229 | AB12: 1267.1978 | AC12: 1170.2102 | AD12: 1190.9172 | AE12: 1216.5866 | AF12: 1244.67 | AG12: 0.0025371406
B13: Adjusted EBITDA margin % | C13: =IFERROR(C12/C9,"") -> 0.10956584 | D13: =IFERROR(D12/D9,"") -> 0.11179351 | E13: =IFERROR(E12/E9,"") -> 0.11442156 | F13: =IFERROR(F12/F9,"") -> 0.11567953 | G13: =IFERROR(G12/G9,"") -> 0.11685718 | H13: =IFERROR(H12/H9,"") -> 0.11797313 | J13: =IFERROR(AVERAGE(Model!C175,Model!D175,Model!E175,Model!F175,Model!G175,Model!H175,Model!I175,Model!J175,Model!K175,Model!L175,Model!Q175,Model!V175,Model!AA175,Model!AF175,Model!AK175),"") -> 0.10092471 | K13: =IFERROR(MIN(Model!C175,Model!D175,Model!E175,Model!F175,Model!G175,Model!H175,Model!I175,Model!J175,Model!K175,Model!L175,Model!Q175,Model!V175,Model!AA175,Model!AF175,Model!AK175),"") -> 0.083297805 | L13: =IFERROR(MAX(Model!C175,Model!D175,Model!E175,Model!F175,Model!G175,Model!H175,Model!I175,Model!J175,Model!K175,Model!L175,Model!Q175,Model!V175,Model!AA175,Model!AF175,Model!AK175),"") -> 0.11178366 | N13: Adjusted EBITDA margin % | O13: 0.10956584 | P13: 0.11154383 | Q13: 0.1198313 | R13: 0.12114905 | S13: 0.12237844 | T13: 0.12354069 | V13: 0.10092471 | W13: 0.083297805 | X13: 0.11178366 | Z13: Adjusted EBITDA margin % | AA13: 0.10956584 | AB13: 0.11205422 | AC13: 0.10402019 | AD13: 0.10512846 | AE13: 0.10616965 | AF13: 0.10716455 | AH13: 0.10092471 | AI13: 0.083297805 | AJ13: 0.11178366
B15: Operating Income (GAAP) | C15: =Model!AK127 -> 1033 | D15: =Model!AP127 -> 1069.7912 | E15: =Model!AQ127 -> 1157.8693 | F15: =Model!AR127 -> 1232.1869 | G15: =Model!AS127 -> 1314.7345 | H15: =Model!AT127 -> 1401.4748 | I15: =IFERROR((H15/C15)^(1/5)-1,"n/m") -> 0.062911234 | N15: Operating Income (GAAP) | O15: 1033 | P15: 1094.7912 | Q15: 1279.8485 | R15: 1398.0221 | S15: 1530.424 | T15: 1673.6398 | U15: 0.10131698 | Z15: Operating Income (GAAP) | AA15: 1033 | AB15: 1044.7912 | AC15: 978.61184 | AD15: 1005.8351 | AE15: 1036.8976 | AF15: 1067.7244 | AG15: 0.0066343957
B16: Operating income y/y % | D16: =IFERROR(D15/C15-1,"") -> 0.035615885 | E16: =IFERROR(E15/D15-1,"") -> 0.082332078 | F16: =IFERROR(F15/E15-1,"") -> 0.06418473 | G16: =IFERROR(G15/F15-1,"") -> 0.066992769 | H16: =IFERROR(H15/G15-1,"") -> 0.065975575 | N16: Operating income y/y % | P16: 0.05981724 | Q16: 0.16903431 | R16: 0.09233409 | S16: 0.09470658 | T16: 0.093579131 | Z16: Operating income y/y % | AB16: 0.011414529 | AC16: -0.063342199 | AD16: 0.027818238 | AE16: 0.030882349 | AF16: 0.029729756
B17: Operating margin (GAAP) % | C17: =IFERROR(C15/C9,"") -> 0.09209236 | D17: =IFERROR(D15/D9,"") -> 0.09255217 | E17: =IFERROR(E15/E9,"") -> 0.097133127 | F17: =IFERROR(F15/F9,"") -> 0.098774107 | G17: =IFERROR(G15/G9,"") -> 0.10029609 | H17: =IFERROR(H15/H9,"") -> 0.10157561 | J17: =IFERROR(AVERAGE(Model!C223,Model!D223,Model!E223,Model!F223,Model!G223,Model!H223,Model!I223,Model!J223,Model!K223,Model!L223,Model!Q223,Model!V223,Model!AA223,Model!AF223,Model!AK223),"") -> 0.084786964 | K17: =IFERROR(MIN(Model!C223,Model!D223,Model!E223,Model!F223,Model!G223,Model!H223,Model!I223,Model!J223,Model!K223,Model!L223,Model!Q223,Model!V223,Model!AA223,Model!AF223,Model!AK223),"") -> 0.048261399 | L17: =IFERROR(MAX(Model!C223,Model!D223,Model!E223,Model!F223,Model!G223,Model!H223,Model!I223,Model!J223,Model!K223,Model!L223,Model!Q223,Model!V223,Model!AA223,Model!AF223,Model!AK223),"") -> 0.11435726 | N17: Operating margin (GAAP) % | O17: 0.09209236 | P17: 0.092709846 | Q17: 0.10226722 | R17: 0.10369558 | S17: 0.10504051 | T17: 0.10619684 | V17: 0.084786964 | W17: 0.048261399 | X17: 0.11435726 | Z17: Operating margin (GAAP) % | AA17: 0.09209236 | AB17: 0.092387523 | AC17: 0.086988976 | AD17: 0.088790296 | AE17: 0.090488468 | AF17: 0.091929749 | AH17: 0.084786964 | AI17: 0.048261399 | AJ17: 0.11435726
B19: Adjusted Net Income | C19: =Model!AK199 -> 797 | D19: =Model!AP199 -> 767.88198 | E19: =Model!AQ199 -> 800.61154 | F19: =Model!AR199 -> 846.57043 | G19: =Model!AS199 -> 893.51464 | H19: =Model!AT199 -> 946.03976 | I19: =IFERROR((H19/C19)^(1/5)-1,"n/m") -> 0.034880524 | N19: Adjusted Net Income | O19: 797 | P19: 787.50698 | Q19: 898.61965 | R19: 952.37331 | S19: 1034.4112 | T19: 1126.1706 | U19: 0.071591294 | Z19: Adjusted Net Income | AA19: 797 | AB19: 748.25698 | AC19: 657.06391 | AD19: 681.82032 | AE19: 701.55895 | AF19: 716.47786 | AG19: -0.021076193
B21: FDSO (m) | C21: =Model!AK146 -> 122.37515 | D21: =Model!AP146 -> 119.8994 | E21: =Model!AQ146 -> 115.01146 | F21: =Model!AR146 -> 106.93131 | G21: =Model!AS146 -> 98.87022 | H21: =Model!AT146 -> 90.541097 | I21: =IFERROR((H21/C21)^(1/5)-1,"n/m") -> -0.058477935 | N21: FDSO (m) | O21: 122.37515 | P21: 119.1494 | Q21: 109.11035 | R21: 96.134078 | S21: 85.771397 | T21: 74.519962 | U21: -0.094442824 | Z21: FDSO (m) | AA21: 122.37515 | AB21: 120.3994 | AC21: 121.06759 | AD21: 120.94998 | AE21: 117.67531 | AF21: 112.69234 | AG21: -0.016350823
B23: Adjusted EPS — Diluted ($) | C23: =Model!AK203 -> 6.5127601 | D23: =Model!AP203 -> 6.4043857 | E23: =Model!AQ203 -> 6.961146 | F23: =Model!AR203 -> 7.9169555 | G23: =Model!AS203 -> 9.0372474 | H23: =Model!AT203 -> 10.448733 | I23: =IFERROR((H23/C23)^(1/5)-1,"n/m") -> 0.099156953 | N23: Adjusted EPS — Diluted ($) | O23: 6.5127601 | P23: 6.6094081 | Q23: 8.235879 | R23: 9.9067191 | S23: 12.060095 | T23: 15.112335 | U23: 0.18335023 | Z23: Adjusted EPS — Diluted ($) | AA23: 6.5127601 | AB23: 6.2147902 | AC23: 5.4272486 | AD23: 5.6372089 | AE23: 5.9618197 | AF23: 6.357822 | AG23: -0.0048039188
B24: EPS y/y % | D24: =IFERROR(D23/C23-1,"") -> -0.016640312 | E24: =IFERROR(E23/D23-1,"") -> 0.086934221 | F24: =IFERROR(F23/E23-1,"") -> 0.13730634 | G24: =IFERROR(G23/F23-1,"") -> 0.14150539 | H24: =IFERROR(H23/G23-1,"") -> 0.15618536 | N24: EPS y/y % | P24: 0.01483979 | Q24: 0.2460842 | R24: 0.20287332 | S24: 0.21736514 | T24: 0.25308597 | Z24: EPS y/y % | AB24: -0.045751714 | AC24: -0.12672053 | AD24: 0.038686314 | AE24: 0.057583601 | AF24: 0.066423072
B26: P / E (x) — assumed (adjusted EPS) | G26: 13 | H26: 13 | N26: P / E (x) — assumed (adjusted EPS) | S26: 15 | T26: 15 | Z26: P / E (x) — assumed (adjusted EPS) | AD26: 10 | AE26: 10 | AF26: 10
B27: Price Target ($) | G27: =G26*G23 -> 117.48422 | H27: =H26*H23 -> 135.83353 | N27: Price Target ($) | S27: =S26*S23 -> 180.90142 | T27: =T26*T23 -> 226.68503 | Z27: Price Target ($) | AD27: =AD26*AD23 -> 56.372089 | AE27: =AE26*AE23 -> 59.618197 | AF27: =AF26*AF23 -> 63.57822
B28: Upside / (Downside) vs current | G28: =IFERROR(G27/$K$2-1,"") -> 0.56645621 | H28: =IFERROR(H27/$K$2-1,"") -> 0.81111374 | N28: Upside / (Downside) vs current | S28: =IFERROR(S27/$K$2-1,"") -> 1.4120189 | T28: =IFERROR(T27/$K$2-1,"") -> 2.0224671 | Z28: Upside / (Downside) vs current | AD28: =IFERROR(AD27/$K$2-1,"") -> -0.24837215 | AE28: =IFERROR(AE27/$K$2-1,"") -> -0.20509071 | AF28: =IFERROR(AF27/$K$2-1,"") -> -0.1522904
B29: IRR (to 31-Mar of Y-1) | G29: =IFERROR((G27/$K$2)^(1/((DATE(2030-1,3,31)-$K$3)/365.25))-1,"") -> 0.19954496 | H29: =IFERROR((H27/$K$2)^(1/((DATE(2031-1,3,31)-$K$3)/365.25))-1,"") -> 0.18691379 | N29: IRR (to 31-Mar of Y-1) | S29: =IFERROR((S27/$K$2)^(1/((DATE(2030-1,3,31)-$K$3)/365.25))-1,"") -> 0.42892884 | T29: =IFERROR((T27/$K$2)^(1/((DATE(2031-1,3,31)-$K$3)/365.25))-1,"") -> 0.37590272 | Z29: IRR (to 31-Mar of Y-1) | AD29: =IFERROR((AD27/$K$2)^(1/((DATE(2029-1,3,31)-$K$3)/365.25))-1,"") -> -0.17680293 | AE29: =IFERROR((AE27/$K$2)^(1/((DATE(2030-1,3,31)-$K$3)/365.25))-1,"") -> -0.088848809 | AF29: =IFERROR((AF27/$K$2)^(1/((DATE(2031-1,3,31)-$K$3)/365.25))-1,"") -> -0.04654812
B31: Free Cash Flow | C31: =Model!AK252 -> 951 | D31: =Model!AP252 -> 875 | E31: =Model!AQ252 -> 902.20964 | F31: =Model!AR252 -> 943.66475 | G31: =Model!AS252 -> 991.83763 | H31: =Model!AT252 -> 1047.6961 | I31: =IFERROR((H31/C31)^(1/5)-1,"n/m") -> 0.019555709 | N31: Free Cash Flow | O31: 951 | P31: 925 | Q31: 989.53854 | R31: 1041.4929 | S31: 1128.4813 | T31: 1227.3309 | U31: 0.052340375 | Z31: Free Cash Flow | AA31: 951 | AB31: 825 | AC31: 774.81034 | AD31: 791.71879 | AE31: 808.20516 | AF31: 821.98379 | AG31: -0.028737664
B32: FCF % | C32: =IFERROR(C31/C9,"") -> 0.084782027 | D32: =IFERROR(D31/D9,"") -> 0.075699957 | E32: =IFERROR(E31/E9,"") -> 0.075685952 | F32: =IFERROR(F31/F9,"") -> 0.075645704 | G32: =IFERROR(G31/G9,"") -> 0.075663517 | H32: =IFERROR(H31/H9,"") -> 0.075934558 | J32: =IFERROR(AVERAGE(Model!C256,Model!D256,Model!E256,Model!F256,Model!G256,Model!H256,Model!I256,Model!J256,Model!K256,Model!L256,Model!Q256,Model!V256,Model!AA256,Model!AF256,Model!AK256),"") -> 0.0587511 | K32: =IFERROR(MIN(Model!C256,Model!D256,Model!E256,Model!F256,Model!G256,Model!H256,Model!I256,Model!J256,Model!K256,Model!L256,Model!Q256,Model!V256,Model!AA256,Model!AF256,Model!AK256),"") -> 0.018021091 | L32: =IFERROR(MAX(Model!C256,Model!D256,Model!E256,Model!F256,Model!G256,Model!H256,Model!I256,Model!J256,Model!K256,Model!L256,Model!Q256,Model!V256,Model!AA256,Model!AF256,Model!AK256),"") -> 0.084782027 | N32: FCF % | O32: 0.084782027 | P32: 0.078331472 | Q32: 0.079069797 | R32: 0.077250719 | S32: 0.077453209 | T32: 0.077877375 | V32: 0.0587511 | W32: 0.018021091 | X32: 0.084782027 | Z32: FCF % | AA32: 0.084782027 | AB32: 0.072952094 | AC32: 0.068873026 | AD32: 0.069889136 | AE32: 0.070530826 | AF32: 0.07077179 | AH32: 0.0587511 | AI32: 0.018021091 | AJ32: 0.084782027
B33: FCF / share ($) | C33: =IFERROR(C31/C21,"") -> 7.7711855 | D33: =IFERROR(D31/D21,"") -> 7.2977849 | E33: =IFERROR(E31/E21,"") -> 7.8445198 | F33: =IFERROR(F31/F21,"") -> 8.8249619 | G33: =IFERROR(G31/G21,"") -> 10.031713 | H33: =IFERROR(H31/H21,"") -> 11.571498 | N33: FCF / share ($) | O33: 7.7711855 | P33: 7.7633629 | Q33: 9.0691536 | R33: 10.833754 | S33: 13.156848 | T33: 16.469828 | Z33: FCF / share ($) | AA33: 7.7711855 | AB33: 6.8521939 | AC33: 6.3998163 | AD33: 6.5458362 | AE33: 6.8680949 | AF33: 7.2940519
B34: FCF Yield (on PT) | F34: =IFERROR(F33/F$27,"") | G34: =IFERROR(G33/G$27,"") -> 0.085387748 | H34: =IFERROR(H33/H$27,"") -> 0.085188815 | N34: FCF Yield (on PT) | R34: =IFERROR(R33/R$27,"") | S34: =IFERROR(S33/S$27,"") -> 0.072729383 | T34: =IFERROR(T33/T$27,"") -> 0.072655119 | Z34: FCF Yield (on PT) | AD34: =IFERROR(AD33/AD$27,"") -> 0.11611839 | AE34: =IFERROR(AE33/AE$27,"") -> 0.11520132 | AF34: =IFERROR(AF33/AF$27,"") -> 0.11472564
B35: Adjusted EBITDA (leverage basis) | C35: =Model!AK174 -> 1229 | D35: =Model!AP174 -> 1292.1978 | E35: =Model!AQ174 -> 1363.955 | F35: =Model!AR174 -> 1443.0786 | G35: =Model!AS174 -> 1531.8261 | H35: =Model!AT174 -> 1627.7171 | I35: =IFERROR((H35/C35)^(1/5)-1,"n/m") -> 0.057804503 | N35: Adjusted EBITDA (leverage basis) | O35: 1229 | P35: 1317.1978 | Q35: 1499.6585 | R35: 1633.3295 | S35: 1783.035 | T35: 1946.9752 | U35: 0.096381517 | Z35: Adjusted EBITDA (leverage basis) | AA35: 1229 | AB35: 1267.1978 | AC35: 1170.2102 | AD35: 1190.9172 | AE35: 1216.5866 | AF35: 1244.67 | AG35: 0.0025371406
B36: Adjusted EBITDA % of revenue | C36: =IFERROR(C35/C9,"") -> 0.10956584 | D36: =IFERROR(D35/D9,"") -> 0.11179351 | E36: =IFERROR(E35/E9,"") -> 0.11442156 | F36: =IFERROR(F35/F9,"") -> 0.11567953 | G36: =IFERROR(G35/G9,"") -> 0.11685718 | H36: =IFERROR(H35/H9,"") -> 0.11797313 | J36: =IFERROR(AVERAGE(Model!C221,Model!D221,Model!E221,Model!F221,Model!G221,Model!H221,Model!I221,Model!J221,Model!K221,Model!L221,Model!Q221,Model!V221,Model!AA221,Model!AF221,Model!AK221),"") -> 0.10092471 | K36: =IFERROR(MIN(Model!C221,Model!D221,Model!E221,Model!F221,Model!G221,Model!H221,Model!I221,Model!J221,Model!K221,Model!L221,Model!Q221,Model!V221,Model!AA221,Model!AF221,Model!AK221),"") -> 0.083297805 | L36: =IFERROR(MAX(Model!C221,Model!D221,Model!E221,Model!F221,Model!G221,Model!H221,Model!I221,Model!J221,Model!K221,Model!L221,Model!Q221,Model!V221,Model!AA221,Model!AF221,Model!AK221),"") -> 0.11178366 | N36: Adjusted EBITDA % of revenue | O36: 0.10956584 | P36: 0.11154383 | Q36: 0.1198313 | R36: 0.12114905 | S36: 0.12237844 | T36: 0.12354069 | V36: 0.10092471 | W36: 0.083297805 | X36: 0.11178366 | Z36: Adjusted EBITDA % of revenue | AA36: 0.10956584 | AB36: 0.11205422 | AC36: 0.10402019 | AD36: 0.10512846 | AE36: 0.10616965 | AF36: 0.10716455 | AH36: 0.10092471 | AI36: 0.083297805 | AJ36: 0.11178366
B38: Net Debt | C38: =Model!AK380 -> 3212 | D38: =Model!AP380 -> 3833.6641 | E38: =Model!AQ380 -> 4091.8649 | F38: =Model!AR380 -> 4329.2358 | G38: =Model!AS380 -> 4595.4782 | H38: =Model!AT380 -> 4883.1514 | N38: Net Debt | O38: 3212 | P38: 3931.8941 | Q38: 4873.89 | R38: 5308.3208 | S38: 5794.8637 | T38: 6327.6693 | Z38: Net Debt | AA38: 3212 | AB38: 3784.8441 | AC38: 3265.7701 | AD38: 2977.293 | AE38: 3041.4664 | AF38: 3111.6751
B39: Net Debt / Adjusted EBITDA (x) | C39: =IFERROR(C38/C35,"") -> 2.6135069 | D39: =IFERROR(D38/D35,"") -> 2.9667781 | E39: =IFERROR(E38/E35,"") -> 3 | F39: =IFERROR(F38/F35,"") -> 3 | G39: =IFERROR(G38/G35,"") -> 3 | H39: =IFERROR(H38/H35,"") -> 3 | N39: Net Debt / Adjusted EBITDA (x) | O39: 2.6135069 | P39: 2.9850446 | Q39: 3.25 | R39: 3.25 | S39: 3.25 | T39: 3.25 | Z39: Net Debt / Adjusted EBITDA (x) | AA39: 2.6135069 | AB39: 2.9867824 | AC39: 2.7907551 | AD39: 2.5 | AE39: 2.5 | AF39: 2.5
B40: Share repurchases ($m; FY2027E = Q2–Q4) | D40: =Model!AP266 -> 150 | E40: =Model!AQ266 -> 758.00954 | F40: =Model!AR266 -> 782.65554 | G40: =Model!AS266 -> 864.34374 | H40: =Model!AT266 -> 948.76268 | N40: Share repurchases ($m; FY2027E = Q2–Q4) | P40: 300 | Q40: 1384.1367 | R40: 953.5361 | S40: 1104.4335 | T40: 1266.4499 | AB40: 50 | AC40: 0 | AD40: 226.2791 | AE40: 580.13241 | AF40: 594.94882
B41: Implied avg buyback price ($) | D41: =Model!AP265 -> 75 | E41: =Model!AQ265 -> 80.25 | F41: =Model!AR265 -> 85.8675 | G41: =Model!AS265 -> 91.878225 | H41: =Model!AT265 -> 98.309701 | N41: Implied avg buyback price ($) | P41: 75 | Q41: 80.25 | R41: 85.8675 | S41: 91.878225 | T41: 98.309701 | AB41: 75 | AC41: 80.25 | AD41: 85.8675 | AE41: 91.878225 | AF41: 98.309701
B42: Shares repurchased (m) | D42: =Model!AP267 -> 2 | E42: =Model!AQ267 -> 9.4456017 | F42: =Model!AR267 -> 9.1146887 | G42: =Model!AS267 -> 9.4074928 | H42: =Model!AT267 -> 9.6507534 | N42: Shares repurchased (m) | P42: 4 | Q42: 17.24781 | R42: 11.104738 | S42: 12.020623 | T42: 12.882247 | AB42: 0.66666667 | AC42: 0 | AD42: 2.6352124 | AE42: 6.3141447 | AF42: 6.0517814
B44: ROIC | C44: =Model!AK363 -> 0.21026047 | D44: =Model!AP363 -> 0.16270146 | E44: =Model!AQ363 -> 0.16861988 | F44: =Model!AR363 -> 0.17710557 | G44: =Model!AS363 -> 0.1864314 | H44: =Model!AT363 -> 0.19610118 | J44: =IFERROR(AVERAGE(Model!C363,Model!D363,Model!E363,Model!F363,Model!G363,Model!H363,Model!I363,Model!J363,Model!K363,Model!L363,Model!Q363,Model!V363,Model!AA363,Model!AF363,Model!AK363),"") -> 0.18929918 | K44: =IFERROR(MIN(Model!C363,Model!D363,Model!E363,Model!F363,Model!G363,Model!H363,Model!I363,Model!J363,Model!K363,Model!L363,Model!Q363,Model!V363,Model!AA363,Model!AF363,Model!AK363),"") -> 0.1463063 | L44: =IFERROR(MAX(Model!C363,Model!D363,Model!E363,Model!F363,Model!G363,Model!H363,Model!I363,Model!J363,Model!K363,Model!L363,Model!Q363,Model!V363,Model!AA363,Model!AF363,Model!AK363),"") -> 0.24719915 | N44: ROIC | O44: 0.21026047 | P44: 0.1674003 | Q44: 0.18258317 | R44: 0.19144967 | S44: 0.20161094 | T44: 0.21259684 | V44: 0.18929918 | W44: 0.1463063 | X44: 0.24719915 | Z44: ROIC | AA44: 0.21026047 | AB44: 0.15805648 | AC44: 0.14557985 | AD44: 0.15233332 | AE44: 0.15962149 | AF44: 0.1669072 | AH44: 0.18929918 | AI44: 0.1463063 | AJ44: 0.24719915
B45: RONTA | C45: =Model!AK374 -> 0.35373907 | D45: =Model!AP374 -> 0.32454624 | E45: =Model!AQ374 -> 0.36333375 | F45: =Model!AR374 -> 0.3843383 | G45: =Model!AS374 -> 0.40716366 | H45: =Model!AT374 -> 0.43062826 | J45: =IFERROR(AVERAGE(Model!C374,Model!D374,Model!E374,Model!F374,Model!G374,Model!H374,Model!I374,Model!J374,Model!K374,Model!L374,Model!Q374,Model!V374,Model!AA374,Model!AF374,Model!AK374),"") -> 0.39003852 | K45: =IFERROR(MIN(Model!C374,Model!D374,Model!E374,Model!F374,Model!G374,Model!H374,Model!I374,Model!J374,Model!K374,Model!L374,Model!Q374,Model!V374,Model!AA374,Model!AF374,Model!AK374),"") -> 0.23645009 | L45: =IFERROR(MAX(Model!C374,Model!D374,Model!E374,Model!F374,Model!G374,Model!H374,Model!I374,Model!J374,Model!K374,Model!L374,Model!Q374,Model!V374,Model!AA374,Model!AF374,Model!AK374),"") -> 0.54451307 | N45: RONTA | O45: 0.35373907 | P45: 0.34901059 | Q45: 0.40542622 | R45: 0.43696449 | S45: 0.47140146 | T45: 0.50754476 | V45: 0.39003852 | W45: 0.23645009 | X45: 0.54451307 | Z45: RONTA | AA45: 0.35373907 | AB45: 0.30785642 | AC45: 0.23615659 | AD45: 0.22567894 | AE45: 0.24021237 | AF45: 0.25526997 | AH45: 0.39003852 | AI45: 0.23645009 | AJ45: 0.54451307
B47: Implied Market Cap (USDm) | F47: =F27*F21 -> 0 | G47: =G27*G21 -> 11615.69 | H47: =H27*H21 -> 12298.517 | N47: Implied Market Cap (USDm) | R47: =R27*R21 -> 0 | S47: =S27*S21 -> 15516.167 | T47: =T27*T21 -> 16892.56 | Z47: Implied Market Cap (USDm) | AD47: =AD27*AD21 -> 6818.2032 | AE47: =AE27*AE21 -> 7015.5895 | AF47: =AF27*AF21 -> 7164.7786
B48: (+) Net Debt & NCI | F48: =F38+Model!AR297 -> 4329.2358 | G48: =G38+Model!AS297 -> 4595.4782 | H48: =H38+Model!AT297 -> 4883.1514 | N48: (+) Net Debt & NCI | R48: =R38+Model!AR297 -> 5308.3208 | S48: =S38+Model!AS297 -> 5794.8637 | T48: =T38+Model!AT297 -> 6327.6693 | Z48: (+) Net Debt & NCI | AD48: =AD38+Model!AR297 -> 2977.293 | AE48: =AE38+Model!AS297 -> 3041.4664 | AF48: =AF38+Model!AT297 -> 3111.6751
B49: Implied Enterprise Value (USDm) | F49: =F47+F48 -> 4329.2358 | G49: =G47+G48 -> 16211.168 | H49: =H47+H48 -> 17181.668 | N49: Implied Enterprise Value (USDm) | R49: =R47+R48 -> 5308.3208 | S49: =S47+S48 -> 21311.031 | T49: =T47+T48 -> 23220.229 | Z49: Implied Enterprise Value (USDm) | AD49: =AD47+AD48 -> 9795.4962 | AE49: =AE47+AE48 -> 10057.056 | AF49: =AF47+AF48 -> 10276.454
B50: Implied EV / Adjusted EBITDA (x) | F50: =IFERROR(F49/F35,"") -> 3 | G50: =IFERROR(G49/G35,"") -> 10.582904 | H50: =IFERROR(H49/H35,"") -> 10.555684 | N50: Implied EV / Adjusted EBITDA (x) | R50: =IFERROR(R49/R35,"") -> 3.25 | S50: =IFERROR(S49/S35,"") -> 11.95211 | T50: =IFERROR(T49/T35,"") -> 11.92631 | Z50: Implied EV / Adjusted EBITDA (x) | AD50: =IFERROR(AD49/AD35,"") -> 8.2251699 | AE50: =IFERROR(AE49/AE35,"") -> 8.2666176 | AF50: =IFERROR(AF49/AF35,"") -> 8.2563678

Sheet DCF
B2: DCF VALUATION — BOOZ ALLEN HAMILTON HOLDING CORPORATION (BAH)
B4: 1. WACC BUILD
B5: Risk-free rate (US 10Y govt) | C5: 0.0425 | D5: Assumption (~US 10Y Treasury yield, Oct-2026; government rate sources not reachable from the build environment); update to market
B6: Equity risk premium | C6: 0.05 | D6: Assumption: US implied ERP ~4.5–5.5%
B7: Levered beta | C7: 1 | D7: Assumption: government IT / consulting services peers (CACI, SAIC, Leidos, Parsons) ~0.6–1.0; ~98% U.S. government revenue on cost-reimbursable contracts, but Civil budget and procurement-policy risk (FY26 Civil −22%) and the 2025–26 de-rating argue for the top of the range
B8: Cost of equity | C8: =C5+C7*C6 -> 0.0925
B9: Pre-tax cost of debt | C9: 0.0575 | D9: Aug-2026 notes at 5.375% (2030) and 5.900% (2034) (8-K 4-Aug-2026); 2033 / 2035 notes 5.950%; marginal cost ~5.75%
B10: Tax rate | C10: 0.225 | D10: Model FY2028E+ effective tax rate (FY27 guidance 20–23%)
B11: After-tax cost of debt | C11: =C9*(1-C10) -> 0.0445625
B12: Target D/V | C12: 0.3 | D12: Net debt ~$3.9bn at FY2027E YE (post-Ultra) vs ~$9.0bn market cap ($75.00 × ~120m diluted shares); net leverage ~3.0x
B13: WACC | C13: =C8*(1-C12)+C11*C12 -> 0.07811875
B15: Valuation date (live) | C15: =TODAY() -> 2026-10-12 00:00:00 | D15: Periods = (31-Mar of fiscal year − today) / 365.25; cash flows assumed at fiscal year-end (31 March). FY2027E UFCF is excluded from the PV (its cash flows, incl. the $720m Ultra payment, are in the FY2027E year-end net debt deducted below); explicit years FY2028E–31E.
B16: 2. UNLEVERED FREE CASH FLOW BUILD (USDm)
D17: 2027E | E17: 2028E | F17: 2029E | G17: 2030E | H17: 2031E | I17: 2032E | J17: 2033E | K17: 2034E | L17: 2035E | M17: 2036E | N17: Terminal | P17: CAGR 28–31E | Q17: CAGR 28–36E
B18: Adj. EBITA (before acquisition amortization) less acquisition, restructuring, legal & financing costs | D18: =Model!AP181-Model!AP184 -> 1147.1978 | E18: =Model!AQ181-Model!AQ184 -> 1240.2506 | F18: =Model!AR181-Model!AR184 -> 1313.8306 | G18: =Model!AS181-Model!AS184 -> 1396.2407 | H18: =Model!AT181-Model!AT184 -> 1485.2436 | I18: =H18*(1+I$26) -> 1552.0796 | J18: =I18*(1+J$26) -> 1616.1028 | K18: =J18*(1+K$26) -> 1676.7067 | L18: =K18*(1+L$26) -> 1733.2955 | M18: =L18*(1+M$26) -> 1785.2944 | P18: =(H18/D18)^(1/(COLUMNS(D18:H18)-1))-1 -> 0.066693983 | Q18: =(M18/D18)^(1/(COLUMNS(D18:M18)-1))-1 -> 0.050367516
B19: × (1 − tax rate) | D19: =1-$C$10 -> 0.775 | E19: =1-$C$10 -> 0.775 | F19: =1-$C$10 -> 0.775 | G19: =1-$C$10 -> 0.775 | H19: =1-$C$10 -> 0.775 | I19: =1-$C$10 -> 0.775 | J19: =1-$C$10 -> 0.775 | K19: =1-$C$10 -> 0.775 | ... M19: =1-$C$10 -> 0.775
B20: NOPAT | D20: =D18*D19 -> 889.0783 | E20: =E18*E19 -> 961.19421 | F20: =F18*F19 -> 1018.2187 | G20: =G18*G19 -> 1082.0866 | H20: =H18*H19 -> 1151.0638 | I20: =I18*I19 -> 1202.8617 | J20: =J18*J19 -> 1252.4797 | K20: =K18*K19 -> 1299.4477 | ... M20: =M18*M19 -> 1383.6032
B21: plus depreciation & other amortization (acquisition amortization is outside the NOPAT basis) | D21: =Model!AP104 -> 120 | E21: =Model!AQ104 -> 119.20437 | F21: =Model!AR104 -> 124.74796 | G21: =Model!AS104 -> 131.08532 | H21: =Model!AT104 -> 137.97355 | I21: =H21*(1+I$26) -> 144.18236 | J21: =I21*(1+J$26) -> 150.12989 | K21: =J21*(1+K$26) -> 155.75976 | L21: =K21*(1+L$26) -> 161.01665 | M21: =L21*(1+M$26) -> 165.84715
B22: − Capex and acquisitions (Ultra in FY2027E; M&A lever 2028E–31E) | D22: =Model!AP236+Model!AP237 -> -1160 | E22: =Model!AQ236+Model!AQ237 -> -257.28393 | F22: =Model!AR236+Model!AR237 -> -262.27317 | G22: =Model!AS236+Model!AS237 -> -267.97679 | H22: =Model!AT236+Model!AT237 -> -274.1762 | I22: =Model!AT236*(1+I$26) -> -129.76413 | J22: =I22*(1+J$26) -> -135.1169 | K22: =J22*(1+K$26) -> -140.18378 | L22: =K22*(1+L$26) -> -144.91498 | M22: =L22*(1+M$26) -> -149.26243
B23: − Δ Working capital (CF statement) | D23: =Model!AP234 -> 121.99231 | E23: =Model!AQ234 -> -15.894303 | F23: =Model!AR234 -> -24.364028 | G23: =Model!AS234 -> -27.852619 | H23: =Model!AT234 -> -30.273719 | I23: =H23*(1+I$26) -> -31.636036 | J23: =I23*(1+J$26) -> -32.941023 | K23: =J23*(1+K$26) -> -34.176311 | L23: =K23*(1+L$26) -> -35.329762 | M23: =L23*(1+M$26) -> -36.389655
B24: Unlevered FCF | D24: =D20+D21+D22+D23 -> -28.929396 | E24: =E20+E21+E22+E23 -> 807.22034 | F24: =F20+F21+F22+F23 -> 856.3295 | G24: =G20+G21+G22+G23 -> 917.34248 | H24: =H20+H21+H22+H23 -> 984.58742 | I24: =I20+I21+I22+I23 -> 1185.6439 | J24: =J20+J21+J22+J23 -> 1234.5517 | K24: =K20+K21+K22+K23 -> 1280.8474 | ... M24: =M20+M21+M22+M23 -> 1363.7982 | N24: =M24*(1+$C$27) -> 1397.8932 | P24: =IFERROR((H24/E24)^(1/(COLUMNS(E24:H24)-1))-1,"n/m") -> 0.068449652 | Q24: =IFERROR((M24/E24)^(1/(COLUMNS(E24:M24)-1))-1,"n/m") -> 0.067750425
B25: Terminal Value (Gordon Growth) | N25: =N24/($C$13-$C$27) -> 26316.38
B26: Fade-period growth (2032E–36E; 4.5% → 3.0% linear) | I26: 0.045 | J26: =I26+($M$26-$I$26)/4 -> 0.04125 | K26: =J26+($M$26-$I$26)/4 -> 0.0375 | L26: =K26+($M$26-$I$26)/4 -> 0.03375 | M26: 0.03
B27: Terminal growth rate | C27: 0.025
B29: Discount period (years) | D29: =(DATE(2027,3,31)-$C$15)/365.25 -> 0.46543463 | E29: =(DATE(2028,3,31)-$C$15)/365.25 -> 1.467488 | F29: =(DATE(2029,3,31)-$C$15)/365.25 -> 2.4668036 | G29: =(DATE(2030,3,31)-$C$15)/365.25 -> 3.4661191 | H29: =(DATE(2031,3,31)-$C$15)/365.25 -> 4.4654346 | I29: =(DATE(2032,3,31)-$C$15)/365.25 -> 5.467488 | J29: =(DATE(2033,3,31)-$C$15)/365.25 -> 6.4668036 | K29: =(DATE(2034,3,31)-$C$15)/365.25 -> 7.4661191 | L29: =(DATE(2035,3,31)-$C$15)/365.25 -> 8.4654346 | M29: =(DATE(2036,3,31)-$C$15)/365.25 -> 9.467488 | N29: =M29 -> 9.467488
B30: Discount factor | D30: =1/(1+$C$13)^D29 -> 0.96559683 | E30: =1/(1+$C$13)^E29 -> 0.89549292 | F30: =1/(1+$C$13)^F29 -> 0.83064971 | G30: =1/(1+$C$13)^G29 -> 0.77050183 | H30: =1/(1+$C$13)^H29 -> 0.71470931 | I30: =1/(1+$C$13)^I29 -> 0.66282024 | J30: =1/(1+$C$13)^J29 -> 0.614825 | K30: =1/(1+$C$13)^K29 -> 0.57030513 | ... N30: =1/(1+$C$13)^N29 -> 0.49060206
B31: PV of UFCF | D31: =0*D24*D30 -> 0 | E31: =E24*E30 -> 722.8601 | F31: =F24*F30 -> 711.30985 | G31: =G24*G30 -> 706.81406 | H31: =H24*H30 -> 703.69379 | I31: =I24*I30 -> 785.86874 | J31: =J24*J30 -> 759.03323 | K31: =K24*K30 -> 730.47382 | L31: =L24*L30 -> 700.44806 | M31: =M24*M30 -> 669.08222 | N31: =N25*N30 -> 12910.87
D32: Booz Allen's adjusted EBITDA expenses stock-based compensation (not adjusted out since FY2016). NOPAT is taxed on adjusted EBITA (before acquisition amortization, which is non-cash and excluded) less the cash items the company adjusts out (other corporate / acquisition costs, restructuring, legal matters, financing costs); row 21 adds back depreciation & other amortization only. FY2027E (column D) is shown but not discounted: its cash flows, including the $720m Ultra acquisition, are already in the FY2027E year-end net debt. Row 22 includes bolt-on acquisitions in FY2028E–31E; the fade period and terminal value assume no new acquisitions. Operating leases are treated as operating costs (not in net debt).
B33: IMPLIED ROIC — invested capital roll-forward (USDm)
B34: Opening invested capital | D34: =Model!AK360 -> 4317 | E34: =D38 -> 5235.0077 | F34: =E38 -> 5388.9816 | G34: =F38 -> 5550.8708 | H34: =G38 -> 5715.6149 | I34: =H38 -> 5882.0912 | J34: =I38 -> 5899.309 | K34: =J38 -> 5917.2371 | L34: =K38 -> 5935.8374 | M34: =L38 -> 5955.0655
B35: plus Capex and acquisitions | D35: =-D22 -> 1160 | E35: =-E22 -> 257.28393 | F35: =-F22 -> 262.27317 | G35: =-G22 -> 267.97679 | H35: =-H22 -> 274.1762 | I35: =-I22 -> 129.76413 | J35: =-J22 -> 135.1169 | K35: =-K22 -> 140.18378 | ... M35: =-M22 -> 149.26243
B36: less DD&A | D36: =-D21 -> -120 | E36: =-E21 -> -119.20437 | F36: =-F21 -> -124.74796 | G36: =-G21 -> -131.08532 | H36: =-H21 -> -137.97355 | I36: =-I21 -> -144.18236 | J36: =-J21 -> -150.12989 | K36: =-K21 -> -155.75976 | ... M36: =-M21 -> -165.84715
B37: plus Δ Working capital investment | D37: =-D23 -> -121.99231 | E37: =-E23 -> 15.894303 | F37: =-F23 -> 24.364028 | G37: =-G23 -> 27.852619 | H37: =-H23 -> 30.273719 | I37: =-I23 -> 31.636036 | J37: =-J23 -> 32.941023 | K37: =-K23 -> 34.176311 | ... M37: =-M23 -> 36.389655
B38: Closing invested capital | D38: =SUM(D34:D37) -> 5235.0077 | E38: =SUM(E34:E37) -> 5388.9816 | F38: =SUM(F34:F37) -> 5550.8708 | G38: =SUM(G34:G37) -> 5715.6149 | H38: =SUM(H34:H37) -> 5882.0912 | I38: =SUM(I34:I37) -> 5899.309 | J38: =SUM(J34:J37) -> 5917.2371 | K38: =SUM(K34:K37) -> 5935.8374 | ... M38: =SUM(M34:M37) -> 5974.8704
B39: NOPAT (row 20) | D39: =D20 -> 889.0783 | E39: =E20 -> 961.19421 | F39: =F20 -> 1018.2187 | G39: =G20 -> 1082.0866 | H39: =H20 -> 1151.0638 | I39: =I20 -> 1202.8617 | J39: =J20 -> 1252.4797 | K39: =K20 -> 1299.4477 | ... M39: =M20 -> 1383.6032
B40: Implied ROIC (NOPAT / avg. invested capital) | D40: =IFERROR(D39/AVERAGE(D34,D38),"") -> 0.18615527 | E40: =IFERROR(E39/AVERAGE(E34,E38),"") -> 0.18094789 | F40: =IFERROR(F39/AVERAGE(F34,F38),"") -> 0.18614853 | G40: =IFERROR(G39/AVERAGE(G34,G38),"") -> 0.19208946 | H40: =IFERROR(H39/AVERAGE(H34,H38),"") -> 0.19849853 | I40: =IFERROR(I39/AVERAGE(I34,I38),"") -> 0.20419672 | J40: =IFERROR(J39/AVERAGE(J34,J38),"") -> 0.21198744 | K40: =IFERROR(K39/AVERAGE(K34,K38),"") -> 0.21925918 | ... M40: =IFERROR(M39/AVERAGE(M34,M38),"") -> 0.23195484
B41: Reinvestment rate (net investment / NOPAT) | D41: =IFERROR(SUM(D35:D37)/D39,"") -> 1.0325386 | E41: =IFERROR(SUM(E35:E37)/E39,"") -> 0.16019017 | F41: =IFERROR(SUM(F35:F37)/F39,"") -> 0.15899259 | G41: =IFERROR(SUM(G35:G37)/G39,"") -> 0.15224668 | H41: =IFERROR(SUM(H35:H37)/H39,"") -> 0.14462827 | I41: =IFERROR(SUM(I35:I37)/I39,"") -> 0.014314032 | J41: =IFERROR(SUM(J35:J37)/J39,"") -> 0.014314032 | K41: =IFERROR(SUM(K35:K37)/K39,"") -> 0.014314032 | ... M41: =IFERROR(SUM(M35:M37)/M39,"") -> 0.014314032
B42: Implied terminal RONIC (g / reinvestment rate) | N42: =IFERROR($C$27/M41,"") -> 1.746538
D43: Opening IC = Model FY2026A book IC (equity + net debt), rolled forward with capex + acquisitions (incl. Ultra in FY2027E) − depreciation + ΔWC.
B44: 3. VALUATION SUMMARY
B45: Sum of PV (explicit + fade) | C45: =SUM(D31:M31) -> 6489.5839
B46: PV of Terminal Value | C46: =N31 -> 12910.87
B47: Enterprise Value | C47: =C45+C46 -> 19400.454
B48: Less: Net debt + NCI (Model FY2027E year end, 31-Mar-2027, after the Ultra payment) | C48: =Model!AP380+Model!AP297 -> 3833.6641 | D48: BAH: no non-controlling interests after FY2025; net debt taken at the FY2027E year end, so the FY2027E UFCF (column D) is excluded from the PV.
B49: Equity Value | C49: =C47-C48 -> 15566.79
B50: Diluted shares (m, Model FY2027E period end) | C50: =Model!AP386 -> 119.10415
B51: Implied share price ($) | C51: =C49/C50 -> 130.69898
B52: Current share price ($) | C52: =Model!AP385 -> 75
B53: Implied upside / (downside) | C53: =C51/C52-1 -> 0.742653
B54: Required discount to DCF value for target IRR | C54: =1-((1+C13)/(1+H54))^H55 -> 0.17603972 | D54: vs. current | E54: Target IRR | H54: 0.15
B55: Max entry price for target IRR ($) | C55: =C51*(1-C54) -> 107.69076 | D55: =C55/C52-1 -> 0.43587685 | E55: Years for discount to close | H55: 3
B58: 4. SENSITIVITY: IMPLIED PRICE ($) — WACC × Terminal Growth
D60: WACC →
B61: Terminal growth ↓ | D61: =F61-0.01 -> 0.06811875 | E61: =F61-0.005 -> 0.07311875 | F61: =$C$13 -> 0.07811875 | G61: =F61+0.005 -> 0.08311875 | H61: =F61+0.01 -> 0.08811875
B62: =B64-0.01 -> 0.015 | D62: {=IFERROR((SUMPRODUCT($D$24:$M$24/(1+D$61)^$D$29:$M$29)+($M$24*(1+$B62)/(D$61-$B62))/(1+D$61)^$M$29-$C$48)/$C$50,"")} -> 142.1582 | E62: {=IFERROR((SUMPRODUCT($D$24:$M$24/(1+E$61)^$D$29:$M$29)+($M$24*(1+$B62)/(E$61-$B62))/(1+E$61)^$M$29-$C$48)/$C$50,"")} -> 125.98617 | F62: {=IFERROR((SUMPRODUCT($D$24:$M$24/(1+F$61)^$D$29:$M$29)+($M$24*(1+$B62)/(F$61-$B62))/(1+F$61)^$M$29-$C$48)/$C$50,"")} -> 112.40048 | G62: {=IFERROR((SUMPRODUCT($D$24:$M$24/(1+G$61)^$D$29:$M$29)+($M$24*(1+$B62)/(G$61-$B62))/(1+G$61)^$M$29-$C$48)/$C$50,"")} -> 100.83089 | H62: {=IFERROR((SUMPRODUCT($D$24:$M$24/(1+H$61)^$D$29:$M$29)+($M$24*(1+$B62)/(H$61-$B62))/(1+H$61)^$M$29-$C$48)/$C$50,"")} -> 90.863163
B63: =B64-0.005 -> 0.02 | D63: {=IFERROR((SUMPRODUCT($D$24:$M$24/(1+D$61)^$D$29:$M$29)+($M$24*(1+$B63)/(D$61-$B63))/(1+D$61)^$M$29-$C$48)/$C$50,"")} -> 154.97842 | E63: {=IFERROR((SUMPRODUCT($D$24:$M$24/(1+E$61)^$D$29:$M$29)+($M$24*(1+$B63)/(E$61-$B63))/(1+E$61)^$M$29-$C$48)/$C$50,"")} -> 136.18897 | F63: {=IFERROR((SUMPRODUCT($D$24:$M$24/(1+F$61)^$D$29:$M$29)+($M$24*(1+$B63)/(F$61-$B63))/(1+F$61)^$M$29-$C$48)/$C$50,"")} -> 120.65543 | G63: {=IFERROR((SUMPRODUCT($D$24:$M$24/(1+G$61)^$D$29:$M$29)+($M$24*(1+$B63)/(G$61-$B63))/(1+G$61)^$M$29-$C$48)/$C$50,"")} -> 107.60339 | H63: {=IFERROR((SUMPRODUCT($D$24:$M$24/(1+H$61)^$D$29:$M$29)+($M$24*(1+$B63)/(H$61-$B63))/(1+H$61)^$M$29-$C$48)/$C$50,"")} -> 96.485822
B64: =$C$27 -> 0.025 | D64: {=IFERROR((SUMPRODUCT($D$24:$M$24/(1+D$61)^$D$29:$M$29)+($M$24*(1+$B64)/(D$61-$B64))/(1+D$61)^$M$29-$C$48)/$C$50,"")} -> 170.77187 | E64: {=IFERROR((SUMPRODUCT($D$24:$M$24/(1+E$61)^$D$29:$M$29)+($M$24*(1+$B64)/(E$61-$B64))/(1+E$61)^$M$29-$C$48)/$C$50,"")} -> 148.51211 | F64: {=IFERROR((SUMPRODUCT($D$24:$M$24/(1+F$61)^$D$29:$M$29)+($M$24*(1+$B64)/(F$61-$B64))/(1+F$61)^$M$29-$C$48)/$C$50,"")} -> 130.46444 | G64: {=IFERROR((SUMPRODUCT($D$24:$M$24/(1+G$61)^$D$29:$M$29)+($M$24*(1+$B64)/(G$61-$B64))/(1+G$61)^$M$29-$C$48)/$C$50,"")} -> 115.54118 | H64: {=IFERROR((SUMPRODUCT($D$24:$M$24/(1+H$61)^$D$29:$M$29)+($M$24*(1+$B64)/(H$61-$B64))/(1+H$61)^$M$29-$C$48)/$C$50,"")} -> 102.99929
B65: =B64+0.005 -> 0.03 | D65: {=IFERROR((SUMPRODUCT($D$24:$M$24/(1+D$61)^$D$29:$M$29)+($M$24*(1+$B65)/(D$61-$B65))/(1+D$61)^$M$29-$C$48)/$C$50,"")} -> 190.70855 | E65: {=IFERROR((SUMPRODUCT($D$24:$M$24/(1+E$61)^$D$29:$M$29)+($M$24*(1+$B65)/(E$61-$B65))/(1+E$61)^$M$29-$C$48)/$C$50,"")} -> 163.6932 | F65: {=IFERROR((SUMPRODUCT($D$24:$M$24/(1+F$61)^$D$29:$M$29)+($M$24*(1+$B65)/(F$61-$B65))/(1+F$61)^$M$29-$C$48)/$C$50,"")} -> 142.31195 | G65: {=IFERROR((SUMPRODUCT($D$24:$M$24/(1+G$61)^$D$29:$M$29)+($M$24*(1+$B65)/(G$61-$B65))/(1+G$61)^$M$29-$C$48)/$C$50,"")} -> 124.97331 | H65: {=IFERROR((SUMPRODUCT($D$24:$M$24/(1+H$61)^$D$29:$M$29)+($M$24*(1+$B65)/(H$61-$B65))/(1+H$61)^$M$29-$C$48)/$C$50,"")} -> 110.63347
B66: =B64+0.01 -> 0.035 | D66: {=IFERROR((SUMPRODUCT($D$24:$M$24/(1+D$61)^$D$29:$M$29)+($M$24*(1+$B66)/(D$61-$B66))/(1+D$61)^$M$29-$C$48)/$C$50,"")} -> 216.66499 | E66: {=IFERROR((SUMPRODUCT($D$24:$M$24/(1+E$61)^$D$29:$M$29)+($M$24*(1+$B66)/(E$61-$B66))/(1+E$61)^$M$29-$C$48)/$C$50,"")} -> 182.85687 | F66: {=IFERROR((SUMPRODUCT($D$24:$M$24/(1+F$61)^$D$29:$M$29)+($M$24*(1+$B66)/(F$61-$B66))/(1+F$61)^$M$29-$C$48)/$C$50,"")} -> 156.9071 | G66: {=IFERROR((SUMPRODUCT($D$24:$M$24/(1+G$61)^$D$29:$M$29)+($M$24*(1+$B66)/(G$61-$B66))/(1+G$61)^$M$29-$C$48)/$C$50,"")} -> 136.36562 | H66: {=IFERROR((SUMPRODUCT($D$24:$M$24/(1+H$61)^$D$29:$M$29)+($M$24*(1+$B66)/(H$61-$B66))/(1+H$61)^$M$29-$C$48)/$C$50,"")} -> 119.70484
B69: 5. REVERSE DCF
B70: To solve for the market-implied path: Data ▸ What-If Analysis ▸ Goal Seek — set C51 to the current price (C52) by changing C27 (terminal growth) or the fade-period growth inputs (I26:M26).
B72: 6. MAUBOUSSIN EV / NOPAT — TWO-STAGE FRAMEWORK
B73: EV/NOPAT = 1/r + [g × (1 − r/ROIIC) / (r × (r − g))] × [1 − ((1+g)/(1+r))^N]
B74: Formula source: Mauboussin & Rappaport, "Expectations Investing" (2021); Counterpoint Global, "What Does a Price-Earnings Multiple Mean?" (2020).
B76: Input | C76: Value | D76: Rationale (Booz Allen characteristics)
B77: r (Cost of capital / WACC) | C77: =$C$13 -> 0.07811875 | D77: Linked from Section 1 WACC build
B78: g (NOPAT growth, Stage 1) | C78: 0.06 | D78: Model adjusted EBITA CAGR FY2027–31E: low-to-mid single-digit National Security growth, Civil trough, Ultra double-digit growth and slight margin expansion → ~6% NOPAT growth
B79: ROIIC (Return on incremental invested capital) | C79: 0.25 | D79: Asset-light services model: invested capital is mostly acquisition goodwill and receivables; organic growth needs little capital (capex ~1% of revenue), so incremental returns are high; acquisitions (Liberty, EverWatch, Ultra) earn high-single-digit returns on price paid
B80: N (Years of value creation / CAP) | C80: 12 | D80: Cleared workforce, incumbent positions on multi-year IDIQ vehicles and a $39bn backlog sustain the advantage; exposure to U.S. budget priorities, procurement reform and outcome-based pricing shortens it
B82: Calculation | C82: Value
B83: Steady-state component: 1 / r | C83: =1/C77 -> 12.801024
B84: Value-creation factor: 1 − r / ROIIC | C84: =1-C77/C79 -> 0.687525
B85: Growth multiplier: g × (1 − r/ROIIC) / (r × (r − g)) | C85: =C78*C84/(C77*(C77-C78)) -> 29.144474
B86: Time decay: 1 − ((1+g)/(1+r))^N | C86: =1-((1+C78)/(1+C77))^C80 -> 0.18403563
B87: PVGO component (growth value) | C87: =C85*C86 -> 5.3636218
B88: Mauboussin EV / NOPAT (steady-state + PVGO) | C88: =C83+C87 -> 18.164646
B90: VALUATION — Applied to FY2029E NOPAT | C90: USDm
B91: FY2029E Adj. EBITA less acquisition, restructuring, legal & financing costs | C91: =Model!AR181-Model!AR184 -> 1313.8306
B92: Tax rate (from WACC build) | C92: =$C$10 -> 0.225
B93: FY2029E NOPAT | C93: =C91*(1-C92) -> 1018.2187
B94: × Mauboussin EV/NOPAT multiple | C94: =C88 -> 18.164646
B95: Implied Enterprise Value (FY2029E basis) | C95: =C93*C94 -> 18495.583
B96: Less: FY2028E year-end net debt + NCI (Model) | C96: =Model!AQ380+Model!AQ297 -> 4091.8649
B97: Implied Equity Value | C97: =C95-C96 -> 14403.718
B98: Diluted shares FY2029E (m, Model) | C98: =Model!AR386 -> 102.97397
B99: Implied share price FY2029 ($) | C99: =C97/C98 -> 139.87727
B101: Current share price ($) | C101: =C52 -> 75
B102: Implied upside / (downside) | C102: =C99/C101-1 -> 0.86503033
B104: MARKET-IMPLIED EV/NOPAT TODAY | C104: USDm
B105: Current market cap (spot × diluted shares) | C105: =C52*C50 -> 8932.8109
B106: Plus: FY2027E year-end net debt + NCI | C106: =C48 -> 3833.6641
B107: Implied Enterprise Value (today) | C107: =C105+C106 -> 12766.475
B108: BAH market-implied EV/NOPAT (on FY2029E NOPAT) | C108: =C107/C93 -> 12.538048
B110: Multiple gap (Mauboussin − Market) | C110: =C88-C108 -> 5.6265982
B111: Implied re-rating headroom | C111: =C88/C108-1 -> 0.44876191

Sheet Charts
B2: Booz Allen Hamilton — Operating Performance (FY2012–FY2026) and Model Forecast (FY2027E–FY2031E)
B3: USDm · fiscal years ended 31 March · Linked to Model. Bars = contribution to revenue growth (pp): National Security (Defense + Intelligence) vs Civil & Commercial, Ultra and other (customer split published from FY2017; earlier years shown as other). Adjusted EBITDA = company definition. ROIC / RONTA on adjusted EBIT (full-cost).
C7: 2012 | D7: 2013 | E7: 2014 | F7: 2015 | G7: 2016 | H7: 2017 | I7: 2018 | J7: 2019 | K7: 2020 | L7: 2021 | M7: 2022 | N7: 2023 | O7: 2024 | P7: 2025 | Q7: 2026 | R7: 2027E | S7: 2028E | T7: 2029E | U7: 2030E | V7: 2031E
B8: National Security contribution (pp) | C8: 0 | D8: =IF(AND(ISNUMBER(Model!D11),ISNUMBER(Model!C11)),IFERROR((Model!D11-Model!C11)/Model!C120,0),0) -> 0 | E8: =IF(AND(ISNUMBER(Model!E11),ISNUMBER(Model!D11)),IFERROR((Model!E11-Model!D11)/Model!D120,0),0) -> 0 | F8: =IF(AND(ISNUMBER(Model!F11),ISNUMBER(Model!E11)),IFERROR((Model!F11-Model!E11)/Model!E120,0),0) -> 0 | G8: =IF(AND(ISNUMBER(Model!G11),ISNUMBER(Model!F11)),IFERROR((Model!G11-Model!F11)/Model!F120,0),0) -> 0 | H8: =IF(AND(ISNUMBER(Model!H11),ISNUMBER(Model!G11)),IFERROR((Model!H11-Model!G11)/Model!G120,0),0) -> 0 | I8: =IF(AND(ISNUMBER(Model!I11),ISNUMBER(Model!H11)),IFERROR((Model!I11-Model!H11)/Model!H120,0),0) -> 0.048309318 | J8: =IF(AND(ISNUMBER(Model!J11),ISNUMBER(Model!I11)),IFERROR((Model!J11-Model!I11)/Model!I120,0),0) -> 0.05781894 | K8: =IF(AND(ISNUMBER(Model!K11),ISNUMBER(Model!J11)),IFERROR((Model!K11-Model!J11)/Model!J120,0),0) -> 0.074810595 | L8: =IF(AND(ISNUMBER(Model!L11),ISNUMBER(Model!K11)),IFERROR((Model!L11-Model!K11)/Model!K120,0),0) -> 0.038484073 | M8: =IF(AND(ISNUMBER(Model!Q11),ISNUMBER(Model!L11)),IFERROR((Model!Q11-Model!L11)/Model!L120,0),0) -> 0.0074179234 | N8: =IF(AND(ISNUMBER(Model!V11),ISNUMBER(Model!Q11)),IFERROR((Model!V11-Model!Q11)/Model!Q120,0),0) -> 0.04493968 | O8: =IF(AND(ISNUMBER(Model!AA11),ISNUMBER(Model!V11)),IFERROR((Model!AA11-Model!V11)/Model!V120,0),0) -> 0.099991457 | P8: =IF(AND(ISNUMBER(Model!AF11),ISNUMBER(Model!AA11)),IFERROR((Model!AF11-Model!AA11)/Model!AA120,0),0) -> 0.091898852 | Q8: =IF(AND(ISNUMBER(Model!AK11),ISNUMBER(Model!AF11)),IFERROR((Model!AK11-Model!AF11)/Model!AF120,0),0) -> 0.01327212 | R8: =IF(AND(ISNUMBER(Model!AP11),ISNUMBER(Model!AK11)),IFERROR((Model!AP11-Model!AK11)/Model!AK120,0),0) -> 0.051726366 | S8: =IF(AND(ISNUMBER(Model!AQ11),ISNUMBER(Model!AP11)),IFERROR((Model!AQ11-Model!AP11)/Model!AP120,0),0) -> 0.029585151 | T8: =IF(AND(ISNUMBER(Model!AR11),ISNUMBER(Model!AQ11)),IFERROR((Model!AR11-Model!AQ11)/Model!AQ120,0),0) -> 0.037293864 | U8: =IF(AND(ISNUMBER(Model!AS11),ISNUMBER(Model!AR11)),IFERROR((Model!AS11-Model!AR11)/Model!AR120,0),0) -> 0.037418416 | V8: =IF(AND(ISNUMBER(Model!AT11),ISNUMBER(Model!AS11)),IFERROR((Model!AT11-Model!AS11)/Model!AS120,0),0) -> 0.037389883
B9: Civil & Commercial, Ultra & other (pp) | C9: 0 | D9: =IFERROR(Model!D213-D8,0) -> -0.017264932 | E9: =IFERROR(Model!E213-E8,0) -> -0.048517391 | F9: =IFERROR(Model!F213-F8,0) -> -0.037221104 | G9: =IFERROR(Model!G213-G8,0) -> 0.024829139 | H9: =IFERROR(Model!H213-H8,0) -> 0.073726474 | I9: =IFERROR(Model!I213-I8,0) -> 0.015017873 | J9: =IFERROR(Model!J213-J8,0) -> 0.028408648 | K9: =IFERROR(Model!K213-K8,0) -> 0.038524698 | L9: =IFERROR(Model!L213-L8,0) -> 0.014450737 | M9: =IFERROR(Model!Q213-M8,0) -> 0.056809839 | N9: =IFERROR(Model!V213-N8,0) -> 0.062095604 | O9: =IFERROR(Model!AA213-O8,0) -> 0.051536622 | P9: =IFERROR(Model!AF213-P8,0) -> 0.031728691 | Q9: =IFERROR(Model!AK213-Q8,0) -> -0.076961603 | R9: =IFERROR(Model!AP213-R8,0) -> -0.021255544 | S9: =IFERROR(Model!AQ213-S8,0) -> 0.0017023733 | T9: =IFERROR(Model!AR213-T8,0) -> 0.0092110716 | U9: =IFERROR(Model!AS213-U8,0) -> 0.01338287 | V9: =IFERROR(Model!AT213-V8,0) -> 0.015157833
C11: =C7 -> 2012 | D11: =D7 -> 2013 | E11: =E7 -> 2014 | F11: =F7 -> 2015 | G11: =G7 -> 2016 | H11: =H7 -> 2017 | I11: =I7 -> 2018 | J11: =J7 -> 2019 | ... V11: =V7 -> 2031E
B12: Adjusted EBITDA | C12: =Model!C174 -> 488.06 | D12: =Model!D174 -> 528.836 | E12: =Model!E174 -> 534.032 | F12: =Model!F174 -> 523.521 | G12: =Model!G174 -> 506.12 | H12: =Model!H174 -> 547.145 | I12: =Model!I174 -> 584.841 | J12: =Model!J174 -> 674.629 | ... L12: =Model!L174 -> 839.674 | M12: =Model!Q174 -> 934.925 | N12: =Model!V174 -> 1014.065 | O12: =Model!AA174 -> 1175.064 | P12: =Model!AF174 -> 1315 | Q12: =Model!AK174 -> 1229 | R12: =Model!AP174 -> 1292.1978 | S12: =Model!AQ174 -> 1363.955 | T12: =Model!AR174 -> 1443.0786 | U12: =Model!AS174 -> 1531.8261 | V12: =Model!AT174 -> 1627.7171
B13: Operating income (GAAP) | C13: =Model!C127 -> 387.432 | D13: =Model!D127 -> 446.234 | E13: =Model!E127 -> 460.611 | F13: =Model!F127 -> 458.822 | G13: =Model!G127 -> 444.584 | H13: =Model!H127 -> 484.247 | I13: =Model!I127 -> 520.085 | J13: =Model!J127 -> 602.394 | ... L13: =Model!L127 -> 754.371 | M13: =Model!Q127 -> 685.181 | N13: =Model!V127 -> 446.848 | O13: =Model!AA127 -> 1013.403 | P13: =Model!AF127 -> 1370 | Q13: =Model!AK127 -> 1033 | R13: =Model!AP127 -> 1069.7912 | S13: =Model!AQ127 -> 1157.8693 | T13: =Model!AR127 -> 1232.1869 | U13: =Model!AS127 -> 1314.7345 | V13: =Model!AT127 -> 1401.4748
B14: Adj. EBITDA Margin % | C14: =Model!C221 -> 0.083297805 | D14: =Model!D221 -> 0.091842755 | E14: =Model!E221 -> 0.097474343 | F14: =Model!F221 -> 0.099250015 | G14: =Model!G221 -> 0.093626439 | H14: =Model!H221 -> 0.094265718 | I14: =Model!I221 -> 0.094759386 | J14: =Model!J221 -> 0.10063026 | ... L14: =Model!L221 -> 0.10684319 | M14: =Model!Q221 -> 0.11178366 | N14: =Model!V221 -> 0.10952314 | O14: =Model!AA221 -> 0.11021154 | P14: =Model!AF221 -> 0.10976628 | Q14: =Model!AK221 -> 0.10956584 | R14: =Model!AP221 -> 0.11179351 | S14: =Model!AQ221 -> 0.11442156 | T14: =Model!AR221 -> 0.11567953 | U14: =Model!AS221 -> 0.11685718 | V14: =Model!AT221 -> 0.11797313
B15: Operating Margin % | C15: =Model!C223 -> 0.0661235 | D15: =Model!D223 -> 0.077497296 | E15: =Model!E223 -> 0.084073154 | F15: =Model!F223 -> 0.086984267 | G15: =Model!G223 -> 0.08224298 | H15: =Model!H223 -> 0.08342924 | I15: =Model!I223 -> 0.084267237 | J15: =Model!J223 -> 0.089855411 | ... L15: =Model!L223 -> 0.095988924 | M15: =Model!Q223 -> 0.081923192 | N15: =Model!V223 -> 0.048261399 | O15: =Model!AA223 -> 0.095049042 | P15: =Model!AF223 -> 0.11435726 | Q15: =Model!AK223 -> 0.09209236 | R15: =Model!AP223 -> 0.09255217 | S15: =Model!AQ223 -> 0.097133127 | T15: =Model!AR223 -> 0.098774107 | U15: =Model!AS223 -> 0.10029609 | V15: =Model!AT223 -> 0.10157561
C17: =C7 -> 2012 | D17: =D7 -> 2013 | E17: =E7 -> 2014 | F17: =F7 -> 2015 | G17: =G7 -> 2016 | H17: =H7 -> 2017 | I17: =I7 -> 2018 | J17: =J7 -> 2019 | ... V17: =V7 -> 2031E
B18: ROIC | C18: =IFERROR(Model!C363+0,NA()) -> 0.1463063 | D18: =IFERROR(Model!D363+0,NA()) -> 0.17009229 | E18: =IFERROR(Model!E363+0,NA()) -> 0.17913606 | F18: =IFERROR(Model!F363+0,NA()) -> 0.17295107 | G18: =IFERROR(Model!G363+0,NA()) -> 0.15495654 | H18: =IFERROR(Model!H363+0,NA()) -> 0.14788363 | I18: =IFERROR(Model!I363+0,NA()) -> 0.16841074 | J18: =IFERROR(Model!J363+0,NA()) -> 0.21321354 | ... L18: =IFERROR(Model!L363+0,NA()) -> 0.24719915 | M18: =IFERROR(Model!Q363+0,NA()) -> 0.19306862 | N18: =IFERROR(Model!V363+0,NA()) -> 0.19281577 | O18: =IFERROR(Model!AA363+0,NA()) -> 0.20359084 | P18: =IFERROR(Model!AF363+0,NA()) -> 0.21542946 | Q18: =IFERROR(Model!AK363+0,NA()) -> 0.21026047 | R18: =IFERROR(Model!AP363+0,NA()) -> 0.16270146 | S18: =IFERROR(Model!AQ363+0,NA()) -> 0.16861988 | T18: =IFERROR(Model!AR363+0,NA()) -> 0.17710557 | U18: =IFERROR(Model!AS363+0,NA()) -> 0.1864314 | V18: =IFERROR(Model!AT363+0,NA()) -> 0.19610118
B19: RONTA | C19: =IFERROR(Model!C374+0,NA()) -> 0.23645009 | D19: =IFERROR(Model!D374+0,NA()) -> 0.35863288 | E19: =IFERROR(Model!E374+0,NA()) -> 0.46678608 | F19: =IFERROR(Model!F374+0,NA()) -> 0.49416051 | G19: =IFERROR(Model!G374+0,NA()) -> 0.46918415 | H19: =IFERROR(Model!H374+0,NA()) -> 0.48031262 | I19: =IFERROR(Model!I374+0,NA()) -> 0.44576854 | J19: =IFERROR(Model!J374+0,NA()) -> 0.54451307 | ... L19: =IFERROR(Model!L374+0,NA()) -> 0.25119297 | M19: =IFERROR(Model!Q374+0,NA()) -> 0.32163519 | N19: =IFERROR(Model!V374+0,NA()) -> 0.3922806 | O19: =IFERROR(Model!AA374+0,NA()) -> 0.39971178 | P19: =IFERROR(Model!AF374+0,NA()) -> 0.34355198 | Q19: =IFERROR(Model!AK374+0,NA()) -> 0.35373907 | R19: =IFERROR(Model!AP374+0,NA()) -> 0.32454624 | S19: =IFERROR(Model!AQ374+0,NA()) -> 0.36333375 | T19: =IFERROR(Model!AR374+0,NA()) -> 0.3843383 | U19: =IFERROR(Model!AS374+0,NA()) -> 0.40716366 | V19: =IFERROR(Model!AT374+0,NA()) -> 0.43062826
B20: Adj. EBITDA margin % | C20: =IFERROR(Model!C221+0,NA()) -> 0.083297805 | D20: =IFERROR(Model!D221+0,NA()) -> 0.091842755 | E20: =IFERROR(Model!E221+0,NA()) -> 0.097474343 | F20: =IFERROR(Model!F221+0,NA()) -> 0.099250015 | G20: =IFERROR(Model!G221+0,NA()) -> 0.093626439 | H20: =IFERROR(Model!H221+0,NA()) -> 0.094265718 | I20: =IFERROR(Model!I221+0,NA()) -> 0.094759386 | J20: =IFERROR(Model!J221+0,NA()) -> 0.10063026 | ... L20: =IFERROR(Model!L221+0,NA()) -> 0.10684319 | M20: =IFERROR(Model!Q221+0,NA()) -> 0.11178366 | N20: =IFERROR(Model!V221+0,NA()) -> 0.10952314 | O20: =IFERROR(Model!AA221+0,NA()) -> 0.11021154 | P20: =IFERROR(Model!AF221+0,NA()) -> 0.10976628 | Q20: =IFERROR(Model!AK221+0,NA()) -> 0.10956584 | R20: =IFERROR(Model!AP221+0,NA()) -> 0.11179351 | S20: =IFERROR(Model!AQ221+0,NA()) -> 0.11442156 | T20: =IFERROR(Model!AR221+0,NA()) -> 0.11567953 | U20: =IFERROR(Model!AS221+0,NA()) -> 0.11685718 | V20: =IFERROR(Model!AT221+0,NA()) -> 0.11797313
B21: FCF margin % | C21: =IFERROR(Model!C256+0,NA()) -> 0.048320612 | D21: =IFERROR(Model!D256+0,NA()) -> 0.074945568 | E21: =IFERROR(Model!E256+0,NA()) -> 0.056913757 | F21: =IFERROR(Model!F256+0,NA()) -> 0.051929658 | G21: =IFERROR(Model!G256+0,NA()) -> 0.033778737 | H21: =IFERROR(Model!H256+0,NA()) -> 0.056571663 | I21: =IFERROR(Model!I256+0,NA()) -> 0.0471019 | J21: =IFERROR(Model!J256+0,NA()) -> 0.06040077 | ... L21: =IFERROR(Model!L256+0,NA()) -> 0.08035106 | M21: =IFERROR(Model!Q256+0,NA()) -> 0.078501381 | N21: =IFERROR(Model!V256+0,NA()) -> 0.056884876 | O21: =IFERROR(Model!AA256+0,NA()) -> 0.018021091 | P21: =IFERROR(Model!AF256+0,NA()) -> 0.076043406 | Q21: =IFERROR(Model!AK256+0,NA()) -> 0.084782027 | R21: =IFERROR(Model!AP256+0,NA()) -> 0.075699957 | S21: =IFERROR(Model!AQ256+0,NA()) -> 0.075685952 | T21: =IFERROR(Model!AR256+0,NA()) -> 0.075645704 | U21: =IFERROR(Model!AS256+0,NA()) -> 0.075663517 | V21: =IFERROR(Model!AT256+0,NA()) -> 0.075934558
