Workbook

Sheet Model
BC1: SCENARIO SWITCH ▼ (Bull / Base / Bear) — drives all scenario-linked forecast drivers
B2: Brunello Cucinelli S.p.A. (Euronext Milan: BC) — 3-Statement Financial Model | BC2: Base
B3: IFRS as reported · EUR millions (per-share data in EUR; store counts in units) · Source: Brunello Cucinelli annual financial reports (consolidated financial statements) and half-year financial reports 2011–H1/26, Q1 / nine-month interim reports (2012–15) and revenue press releases (2016–26), investor.brunellocucinelli.com (regulated information also filed via eMarket Storage / Borsa Italiana; BC is not an SEC registrant — no EDGAR filings)
B4: Basis notes: calendar fiscal year; full statements published for H1 and FY only (H2 = FY − H1; Q1/Q3 revenue memo). Revenues = net revenues (other operating income shown separately; "revenues from sales and services" to 2016 included it). IPO Apr-2012 (60.0m → 68.0m shares). IFRS 15 from 2018 (2017 as originally reported); IFRS 16 from 1-Jan-2019 (modified retrospective, 2018 not restated) — pre-IFRS 16 bridge provided. Channels: retail / mono-brand wholesale / multi-brand wholesale to 2020, retail / wholesale from 2021. Regions: Italy, Europe, North America, Greater China, RoW to 2020; Italy, Europe, Americas, Asia 2021–24; Europe (incl. Italy), Americas, Asia from 2025.
BE5: Forecast | BF5: Historical | BG5: Historical | BH5: Historical
B6: (EURm) | C6: H1/11 | D6: H2/11 | E6: 2011 | F6: H1/12 | G6: H2/12 | H6: 2012 | I6: H1/13 | J6: H2/13 | K6: 2013 | L6: H1/14 | M6: H2/14 | N6: 2014 | O6: H1/15 | P6: H2/15 | Q6: 2015 | R6: H1/16 | S6: H2/16 | T6: 2016 | U6: H1/17 | V6: H2/17 | W6: 2017 | X6: H1/18 | Y6: H2/18 | Z6: 2018 | AA6: H1/19 | AB6: H2/19 | AC6: 2019 | AD6: H1/20 | AE6: H2/20 | AF6: 2020 | AG6: H1/21 | AH6: H2/21 | AI6: 2021 | AJ6: H1/22 | AK6: H2/22 | AL6: 2022 | AM6: H1/23 | AN6: H2/23 | AO6: 2023 | AP6: H1/24 | AQ6: H2/24 | AR6: 2024 | AS6: H1/25 | AT6: H2/25 | AU6: 2025 | AV6: H1/26 | AW6: H2/26E | AX6: 2026E | AY6: 2027E | AZ6: 2028E | BA6: 2029E | BB6: 2030E | BC6: Modelling Notes | BE6: 5Y CAGR | BF6: 5Y CAGR | BG6: 10Y CAGR | BH6: 14Y CAGR
BE7: 25-'30 | BF7: 20-'25 | BG7: 15-'25 | BH7: 11-'25
B8: REVENUE BUILD — DISTRIBUTION CHANNEL (RETAIL · WHOLESALE) × GEOGRAPHY (EUROPE · AMERICAS · ASIA) | BC8: REVENUE BUILD — modelling logic
BK9: SCENARIO INPUT TABLE — driver assumptions per Bull / Base / Bear | BL9: Bull | BM9: Base | BN9: Bear | BO9: Bull / Bear = Base + Δ (Δ inputs on each block header). Outlook block = company guidance end-points.
B10: Retail channel (directly operated boutiques, concessions / hard shops in luxury department stores, e-commerce) | BC10: RETAIL — modelling logic
B11: Directly operated boutiques (DOS), period end (#) | C11: 21 | D11: =E11 -> 20 | E11: 20 | F11: 30 | G11: =H11 -> 46 | H11: 46 | I11: 54 | J11: =K11 -> 61 | K11: 61 | L11: 65 | M11: =N11 -> 71 | N11: 71 | O11: 79 | P11: =Q11 -> 81 | Q11: 81 | R11: 86 | S11: =T11 -> 86 | T11: 86 | U11: 91 | V11: =W11 -> 94 | W11: 94 | X11: 97 | Y11: =Z11 -> 100 | Z11: 100 | AA11: 102 | AB11: =AC11 -> 106 | AC11: 106 | AD11: 107 | AE11: =AF11 -> 107 | AF11: 107 | AG11: 112 | AH11: =AI11 -> 114 | AI11: 114 | AJ11: 117 | AK11: =AL11 -> 119 | AL11: 119 | AM11: 124 | AN11: =AO11 -> 125 | AO11: 125 | AP11: 126 | AQ11: =AR11 -> 130 | AR11: 130 | AS11: 130 | AT11: =AU11 -> 136 | AU11: 136 | AV11: 141 | AW11: =AX11 -> 143 | AX11: =AU11+AX12 -> 143 | AY11: =AX11+AY12 -> 148 | AZ11: =AY11+AZ12 -> 153 | BA11: =AZ11+BA12 -> 158 | BB11: =BA11+BB12 -> 163 | BC11: 2026E+: prior year-end + net openings (row below). H2/26E column = 31-Dec-26 count. | BK11: FY26 outlook — H1-26 release (30-Jul-26) | BL11: High | BM11: Mid | BN11: Low | BO11: Revenue growth guidance is at constant exchange rates.
B12: Net DOS openings in period (#) | D12: =D11-C11 -> -1 | F12: =F11-E11 -> 10 | G12: =G11-F11 -> 16 | H12: =H11-E11 -> 26 | I12: =I11-H11 -> 8 | J12: =J11-I11 -> 7 | K12: =K11-H11 -> 15 | L12: =L11-K11 -> 4 | M12: =M11-L11 -> 6 | N12: =N11-K11 -> 10 | O12: =O11-N11 -> 8 | P12: =P11-O11 -> 2 | Q12: =Q11-N11 -> 10 | R12: =R11-Q11 -> 5 | S12: =S11-R11 -> 0 | T12: =T11-Q11 -> 5 | U12: =U11-T11 -> 5 | V12: =V11-U11 -> 3 | W12: =W11-T11 -> 8 | X12: =X11-W11 -> 3 | Y12: =Y11-X11 -> 3 | Z12: =Z11-W11 -> 6 | AA12: =AA11-Z11 -> 2 | AB12: =AB11-AA11 -> 4 | AC12: =AC11-Z11 -> 6 | AD12: =AD11-AC11 -> 1 | AE12: =AE11-AD11 -> 0 | AF12: =AF11-AC11 -> 1 | AG12: =AG11-AF11 -> 5 | AH12: =AH11-AG11 -> 2 | AI12: =AI11-AF11 -> 7 | AJ12: =AJ11-AI11 -> 3 | AK12: =AK11-AJ11 -> 2 | AL12: =AL11-AI11 -> 5 | AM12: =AM11-AL11 -> 5 | AN12: =AN11-AM11 -> 1 | AO12: =AO11-AL11 -> 6 | AP12: =AP11-AO11 -> 1 | AQ12: =AQ11-AP11 -> 4 | AR12: =AR11-AO11 -> 5 | AS12: =AS11-AR11 -> 0 | AT12: =AT11-AS11 -> 6 | AU12: =AU11-AR11 -> 6 | AV12: =AV11-AU11 -> 5 | AW12: =AW11-AV11 -> 2 | AX12: 7 | AY12: 5 | AZ12: 5 | BA12: 5 | BB12: 5 | BC12: Net DOS openings: 2025 +6 (130→136), H1/26 +5 (141). 2026E +7 for the year; 2027E–30E +5 p.a. (selective openings and enlargements; Base, scenario-neutral input). | BK12: FY26 revenue growth at constant FX | BL12: 0.11 | BM12: 0.105 | BN12: 0.1 | BO12: Raised to +10% to +11% (from ~+10%) on 30-Jul-26.
B13: Average DOS in period (#) | D13: =IFERROR(AVERAGE(C11,D11),"") -> 20.5 | F13: =IFERROR(AVERAGE(E11,F11),"") -> 25 | G13: =IFERROR(AVERAGE(F11,G11),"") -> 38 | H13: =IFERROR(AVERAGE(E11,H11),"") -> 33 | I13: =IFERROR(AVERAGE(H11,I11),"") -> 50 | J13: =IFERROR(AVERAGE(I11,J11),"") -> 57.5 | K13: =IFERROR(AVERAGE(H11,K11),"") -> 53.5 | L13: =IFERROR(AVERAGE(K11,L11),"") -> 63 | M13: =IFERROR(AVERAGE(L11,M11),"") -> 68 | N13: =IFERROR(AVERAGE(K11,N11),"") -> 66 | O13: =IFERROR(AVERAGE(N11,O11),"") -> 75 | P13: =IFERROR(AVERAGE(O11,P11),"") -> 80 | Q13: =IFERROR(AVERAGE(N11,Q11),"") -> 76 | R13: =IFERROR(AVERAGE(Q11,R11),"") -> 83.5 | S13: =IFERROR(AVERAGE(R11,S11),"") -> 86 | T13: =IFERROR(AVERAGE(Q11,T11),"") -> 83.5 | U13: =IFERROR(AVERAGE(T11,U11),"") -> 88.5 | V13: =IFERROR(AVERAGE(U11,V11),"") -> 92.5 | W13: =IFERROR(AVERAGE(T11,W11),"") -> 90 | X13: =IFERROR(AVERAGE(W11,X11),"") -> 95.5 | Y13: =IFERROR(AVERAGE(X11,Y11),"") -> 98.5 | Z13: =IFERROR(AVERAGE(W11,Z11),"") -> 97 | AA13: =IFERROR(AVERAGE(Z11,AA11),"") -> 101 | AB13: =IFERROR(AVERAGE(AA11,AB11),"") -> 104 | AC13: =IFERROR(AVERAGE(Z11,AC11),"") -> 103 | AD13: =IFERROR(AVERAGE(AC11,AD11),"") -> 106.5 | AE13: =IFERROR(AVERAGE(AD11,AE11),"") -> 107 | AF13: =IFERROR(AVERAGE(AC11,AF11),"") -> 106.5 | AG13: =IFERROR(AVERAGE(AF11,AG11),"") -> 109.5 | AH13: =IFERROR(AVERAGE(AG11,AH11),"") -> 113 | AI13: =IFERROR(AVERAGE(AF11,AI11),"") -> 110.5 | AJ13: =IFERROR(AVERAGE(AI11,AJ11),"") -> 115.5 | AK13: =IFERROR(AVERAGE(AJ11,AK11),"") -> 118 | AL13: =IFERROR(AVERAGE(AI11,AL11),"") -> 116.5 | AM13: =IFERROR(AVERAGE(AL11,AM11),"") -> 121.5 | AN13: =IFERROR(AVERAGE(AM11,AN11),"") -> 124.5 | AO13: =IFERROR(AVERAGE(AL11,AO11),"") -> 122 | AP13: =IFERROR(AVERAGE(AO11,AP11),"") -> 125.5 | AQ13: =IFERROR(AVERAGE(AP11,AQ11),"") -> 128 | AR13: =IFERROR(AVERAGE(AO11,AR11),"") -> 127.5 | AS13: =IFERROR(AVERAGE(AR11,AS11),"") -> 130 | AT13: =IFERROR(AVERAGE(AS11,AT11),"") -> 133 | AU13: =IFERROR(AVERAGE(AR11,AU11),"") -> 133 | AV13: =IFERROR(AVERAGE(AU11,AV11),"") -> 138.5 | AW13: =IFERROR(AVERAGE(AV11,AW11),"") -> 142 | AX13: =IFERROR(AVERAGE(AU11,AX11),"") -> 139.5 | AY13: =IFERROR(AVERAGE(AX11,AY11),"") -> 145.5 | AZ13: =IFERROR(AVERAGE(AY11,AZ11),"") -> 150.5 | BA13: =IFERROR(AVERAGE(AZ11,BA11),"") -> 155.5 | BB13: =IFERROR(AVERAGE(BA11,BB11),"") -> 160.5 | BK13: 2028 revenue target (EURm; 2024–28 plan, Jan-26) — memo | BL13: 1800 | BM13: 1800 | BN13: 1800 | BO13: "Turnover of approximately €1.8 billion in 2028" (12-Jan-26 / 18-Feb-26 releases).
B14: Retail revenues per average DOS (EURm; half-years not annualised) | C14: =IFERROR(C16/C13,"") | D14: =IFERROR(D16/D13,"") -> 1.6346829 | E14: =IFERROR(E16/E13,"") | F14: =IFERROR(F16/F13,"") -> 1.21576 | G14: =IFERROR(G16/G13,"") -> 1.2251316 | H14: =IFERROR(H16/H13,"") -> 2.3317879 | I14: =IFERROR(I16/I13,"") -> 1.01494 | J14: =IFERROR(J16/J13,"") -> 1.1250957 | ... AX14: =IFERROR(AX16/AX13,"") -> 7.6131936 | AY14: =AX14*(1+AY15) -> 8.1841832 | AZ14: =AY14*(1+AZ15) -> 8.6752341 | BA14: =AZ14*(1+BA15) -> 9.152372 | BB14: =BA14*(1+BB15) -> 9.6099906 | BC14: Sales density incl. e-commerce and hard shops (not separately disclosed). 2027E+: prior year × (1 + scenario lever RET_density: like-for-like + pricing).
B15: Sales density y/y % (like-for-like + price/mix + non-DOS formats) | F15: =IF(AND(ISNUMBER(F14),ISNUMBER(C14)),IFERROR(F14/C14-1,""),"") | G15: =IF(AND(ISNUMBER(G14),ISNUMBER(D14)),IFERROR(G14/D14-1,""),"") -> -0.25053871 | H15: =IF(AND(ISNUMBER(H14),ISNUMBER(E14)),IFERROR(H14/E14-1,""),"") | I15: =IF(AND(ISNUMBER(I14),ISNUMBER(F14)),IFERROR(I14/F14-1,""),"") -> -0.16518063 | J15: =IF(AND(ISNUMBER(J14),ISNUMBER(G14)),IFERROR(J14/G14-1,""),"") -> -0.081653211 | K15: =IF(AND(ISNUMBER(K14),ISNUMBER(H14)),IFERROR(K14/H14-1,""),"") -> -0.074634091 | L15: =IF(AND(ISNUMBER(L14),ISNUMBER(I14)),IFERROR(L14/I14-1,""),"") -> -0.024885668 | M15: =IF(AND(ISNUMBER(M14),ISNUMBER(J14)),IFERROR(M14/J14-1,""),"") -> 0.12586506 | ... AX15: =IF(AND(ISNUMBER(AX14),ISNUMBER(AU14)),IFERROR(AX14/AU14-1,""),"") -> 0.069213443 | AY15: =CHOOSE(MATCH($BC$2,{"Bull","Base","Bear"},0),$BL$16,$BM$16,$BN$16) -> 0.075 | AZ15: =CHOOSE(MATCH($BC$2,{"Bull","Base","Bear"},0),$BL$17,$BM$17,$BN$17) -> 0.06 | BA15: =CHOOSE(MATCH($BC$2,{"Bull","Base","Bear"},0),$BL$18,$BM$18,$BN$18) -> 0.055 | BB15: =CHOOSE(MATCH($BC$2,{"Bull","Base","Bear"},0),$BL$19,$BM$19,$BN$19) -> 0.05 | BC15: 2027E–2030E: scenario lever RET_density (Bull / Base / Bear table →). | BK15: RET_density (retail sales per average DOS y/y) | BL15: 0.02 | BM15: Δ → | BN15: -0.03 | BO15: LFL + pricing + enlargements/e-commerce: 2023 +17%, 2024 +11%, 2025 +6% (per avg DOS); H1/26 retail +19.3% cFX.
B16: Retail revenues | C16: 20.35 | D16: =E16-C16 -> 33.511 | E16: 53.861 | F16: 30.394 | G16: =H16-F16 -> 46.555 | H16: 76.949 | I16: 50.747 | J16: =K16-I16 -> 64.693 | K16: 115.44 | L16: 62.35 | M16: =N16-L16 -> 86.136 | N16: 148.486 | O16: 84.768 | P16: =Q16-O16 -> 108.406 | Q16: 193.174 | R16: 99.555 | S16: =T16-R16 -> 126.665 | T16: 226.22 | U16: 121.121 | V16: =W16-U16 -> 149.433 | W16: 270.554 | X16: 133.92 | Y16: =Z16-X16 -> 162.345 | Z16: 296.265 | AA16: 149.946 | AB16: =AC16-AA16 -> 189.489 | AC16: 339.435 | AD16: 102.517 | AE16: =AF16-AD16 -> 166.256 | AF16: 268.773 | AG16: 165.468 | AH16: =AI16-AG16 -> 254.349 | AI16: 419.817 | AJ16: 243.325 | AK16: =AL16-AJ16 -> 329.995 | AL16: 573.32 | AM16: 344.648 | AN16: =AO16-AM16 -> 402.168 | AO16: 746.816 | AP16: 395.184 | AQ16: =AR16-AP16 -> 456.059 | AR16: 851.243 | AS16: 435.837 | AT16: =AU16-AS16 -> 511.172 | AU16: 947.009 | AV16: 499.765 | AW16: =AT16*(1+AW18+AW66) -> 562.27551 | AX16: =AV16+AW16 -> 1062.0405 | AY16: =AY13*AY14 -> 1190.7986 | AZ16: =AZ13*AZ14 -> 1305.6227 | BA16: =BA13*BA14 -> 1423.1938 | BB16: =BB13*BB14 -> 1542.4035 | BC16: H2/26E: H2/25 × (1 + calibrated constant-FX growth + FX effect). 2027E+: average DOS × sales density. | BE16: =IFERROR(IF(AND(BB16>0,AU16>0),(BB16/AU16)^(1/5)-1,"n/m"),"n/m") -> 0.10247507 | BF16: =IFERROR(IF(AND(AU16>0,AF16>0),(AU16/AF16)^(1/5)-1,"n/m"),"n/m") -> 0.28645232 | BG16: =IFERROR(IF(AND(AU16>0,Q16>0),(AU16/Q16)^(1/10)-1,"n/m"),"n/m") -> 0.1723048 | BH16: =IFERROR(IF(AND(AU16>0,E16>0),(AU16/E16)^(1/14)-1,"n/m"),"n/m") -> 0.22725346 | BK16: 2027E | BL16: =BM16+$BL$15 -> 0.095 | BM16: 0.075 | BN16: =BM16+$BN$15 -> 0.045
B17: Retail revenues y/y % | F17: =IF(AND(ISNUMBER(F16),ISNUMBER(C16)),IFERROR(F16/C16-1,""),"") -> 0.49356265 | G17: =IF(AND(ISNUMBER(G16),ISNUMBER(D16)),IFERROR(G16/D16-1,""),"") -> 0.38924532 | H17: =IF(AND(ISNUMBER(H16),ISNUMBER(E16)),IFERROR(H16/E16-1,""),"") -> 0.42865896 | I17: =IF(AND(ISNUMBER(I16),ISNUMBER(F16)),IFERROR(I16/F16-1,""),"") -> 0.66963874 | J17: =IF(AND(ISNUMBER(J16),ISNUMBER(G16)),IFERROR(J16/G16-1,""),"") -> 0.38960369 | K17: =IF(AND(ISNUMBER(K16),ISNUMBER(H16)),IFERROR(K16/H16-1,""),"") -> 0.50021443 | L17: =IF(AND(ISNUMBER(L16),ISNUMBER(I16)),IFERROR(L16/I16-1,""),"") -> 0.22864406 | M17: =IF(AND(ISNUMBER(M16),ISNUMBER(J16)),IFERROR(M16/J16-1,""),"") -> 0.33145781 | ... AX17: =IF(AND(ISNUMBER(AX16),ISNUMBER(AU16)),IFERROR(AX16/AU16-1,""),"") -> 0.12146824 | AY17: =IF(AND(ISNUMBER(AY16),ISNUMBER(AX16)),IFERROR(AY16/AX16-1,""),"") -> 0.12123656 | AZ17: =IF(AND(ISNUMBER(AZ16),ISNUMBER(AY16)),IFERROR(AZ16/AY16-1,""),"") -> 0.096426117 | BA17: =IF(AND(ISNUMBER(BA16),ISNUMBER(AZ16)),IFERROR(BA16/AZ16-1,""),"") -> 0.090049834 | BB17: =IF(AND(ISNUMBER(BB16),ISNUMBER(BA16)),IFERROR(BB16/BA16-1,""),"") -> 0.083762058 | BK17: 2028E | BL17: =BM17+$BL$15 -> 0.08 | BM17: 0.06 | BN17: =BM17+$BN$15 -> 0.03
B18: Retail growth at constant FX (company) % | AU18: 0.129 | AV18: 0.193 | AW18: =AW69+AW71 -> 0.099973222 | AX18: =IFERROR((AS16*(1+AV18)+AT16*(1+AW18))/AU16-1,"") -> 0.14278645 | BC18: Company-reported constant-currency growth (H1 and FY). H2/26E retail: H1/26 trend + outlook calibration Δ; wholesale: H1/26 trend. | BK18: 2029E | BL18: =BM18+$BL$15 -> 0.075 | BM18: 0.055 | BN18: =BM18+$BN$15 -> 0.025
B19: Memo: retail like-for-like growth (company, where disclosed) % | F19: 0.197 | H19: 0.093 | I19: 0.106 | K19: 0.073 | L19: 0.056 | N19: 0.055 | O19: 0.051 | Q19: 0.054 | R19: 0.037 | T19: 0.039 | U19: 0.04 | W19: 0.044 | X19: 0.038 | Z19: 0.035 | AA19: 0.037 | AC19: 0.042 | BK19: 2030E | BL19: =BM19+$BL$15 -> 0.07 | BM19: 0.05 | BN19: =BM19+$BN$15 -> 0.02
B20: Retail % of revenues | C20: =IF(AND(ISNUMBER(C16),ISNUMBER(C111)),IFERROR(C16/C111,""),"") -> 0.17474261 | D20: =IF(AND(ISNUMBER(D16),ISNUMBER(D111)),IFERROR(D16/D111,""),"") -> 0.26558513 | E20: =IF(AND(ISNUMBER(E16),ISNUMBER(E111)),IFERROR(E16/E111,""),"") -> 0.22198364 | F20: =IF(AND(ISNUMBER(F16),ISNUMBER(F111)),IFERROR(F16/F111,""),"") -> 0.2248027 | G20: =IF(AND(ISNUMBER(G16),ISNUMBER(G111)),IFERROR(G16/G111,""),"") -> 0.3230339 | H20: =IF(AND(ISNUMBER(H16),ISNUMBER(H111)),IFERROR(H16/H111,""),"") -> 0.27548591 | I20: =IF(AND(ISNUMBER(I16),ISNUMBER(I111)),IFERROR(I16/I111,""),"") -> 0.32205186 | J20: =IF(AND(ISNUMBER(J16),ISNUMBER(J111)),IFERROR(J16/J111,""),"") -> 0.39230228 | ... BB20: =IF(AND(ISNUMBER(BB16),ISNUMBER(BB111)),IFERROR(BB16/BB111,""),"") -> 0.7315037
B21: Memo: hard shops in luxury department stores, period end (#) | AE21: =AF21 -> 31 | AF21: 31 | AG21: 41 | AH21: =AI21 -> 43 | AI21: 43 | AJ21: 42 | AK21: =AL21 -> 42 | AL21: 42 | AM21: 42 | AN21: =AO21 -> 49 | AO21: 49 | AP21: 49 | AQ21: =AR21 -> 50 | AR21: 50 | AS21: 51 | AT21: =AU21 -> 57 | AU21: 57 | AV21: 59 | BK21: WHS_growth (wholesale revenues y/y) | BL21: 0.02 | BM21: Δ → | BN21: -0.03 | BO21: Selective multi-brand & department stores: FY25 +7.9%, H1/26 +2.7% cFX; SS27 order intake "extremely positive".
BK22: 2027E | BL22: =BM22+$BL$21 -> 0.08 | BM22: 0.06 | BN22: =BM22+$BN$21 -> 0.03
B23: Wholesale channel (mono-brand franchised boutiques, multi-brand specialty stores & department stores, e-tailers) | BC23: WHOLESALE — modelling logic | BK23: 2028E | BL23: =BM23+$BL$21 -> 0.07 | BM23: 0.05 | BN23: =BM23+$BN$21 -> 0.02
B24: Mono-brand wholesale boutiques, period end (#) | C24: 34 | D24: =E24 -> 39 | E24: 39 | F24: 40 | G24: =H24 -> 35 | H24: 35 | I24: 38 | J24: =K24 -> 37 | K24: 37 | L24: 37 | M24: =N24 -> 34 | N24: 34 | O24: 36 | P24: =Q24 -> 36 | Q24: 36 | R24: 36 | S24: =T24 -> 36 | T24: 36 | U24: 32 | V24: =W24 -> 30 | W24: 30 | X24: 29 | Y24: =Z24 -> 27 | Z24: 27 | AA24: 28 | AB24: =AC24 -> 30 | AC24: 30 | AD24: 30 | AE24: =AF24 -> 31 | AF24: 31 | AG24: 31 | AH24: =AI24 -> 30 | AI24: 30 | AJ24: 30 | AK24: =AL24 -> 30 | AL24: 30 | AM24: 27 | AN24: =AO24 -> 27 | AO24: 27 | AP24: 27 | AQ24: =AR24 -> 27 | AR24: 27 | AS24: 27 | AT24: =AU24 -> 28 | AU24: 28 | AV24: 28 | BK24: 2029E | BL24: =BM24+$BL$21 -> 0.065 | BM24: 0.045 | BN24: =BM24+$BN$21 -> 0.015
B25: Wholesale revenues | C25: 96.107 | D25: =E25-C25 -> 92.667 | E25: 188.774 | F25: 104.809 | G25: =H25-F25 -> 97.563 | H25: 202.372 | I25: 106.827 | J25: =K25-I25 -> 100.213 | K25: 207.04 | L25: 113.461 | M25: =N25-L25 -> 93.962 | N25: 207.423 | O25: 115.564 | P25: =Q25-O25 -> 105.413 | Q25: 220.977 | R25: 120.285 | S25: =T25-R25 -> 109.466 | T25: 229.751 | U25: 122.206 | V25: =W25-U25 -> 110.811 | W25: 233.017 | X25: 135.566 | Y25: =Z25-X25 -> 121.165 | Z25: 256.731 | AA25: 141.467 | AB25: =AC25-AA25 -> 126.859 | AC25: 268.326 | AD25: 102.626 | AE25: =AF25-AD25 -> 172.614 | AF25: 275.24 | AG25: 148.296 | AH25: =AI25-AG25 -> 144.066 | AI25: 292.362 | AJ25: 172.032 | AK25: =AL25-AJ25 -> 174.356 | AL25: 346.388 | AM25: 199.294 | AN25: =AO25-AM25 -> 193.31 | AO25: 392.604 | AP25: 225.478 | AQ25: =AR25-AP25 -> 201.819 | AR25: 427.297 | AS25: 248.298 | AT25: =AU25-AS25 -> 212.644 | AU25: 460.942 | AV25: 249.646 | AW25: =AT25*(1+AW27+AW66) -> 218.38539 | AX25: =AV25+AW25 -> 468.03139 | AY25: =AX25*(1+AY26) -> 496.11327 | AZ25: =AY25*(1+AZ26) -> 520.91893 | BA25: =AZ25*(1+BA26) -> 544.36029 | BB25: =BA25*(1+BB26) -> 566.1347 | BC25: H2/26E: H2/25 × (1 + calibrated constant-FX growth + FX effect). 2027E+: prior year × (1 + scenario lever WHS_growth). | BE25: =IFERROR(IF(AND(BB25>0,AU25>0),(BB25/AU25)^(1/5)-1,"n/m"),"n/m") -> 0.04196876 | BF25: =IFERROR(IF(AND(AU25>0,AF25>0),(AU25/AF25)^(1/5)-1,"n/m"),"n/m") -> 0.10863082 | BG25: =IFERROR(IF(AND(AU25>0,Q25>0),(AU25/Q25)^(1/10)-1,"n/m"),"n/m") -> 0.076291526 | BH25: =IFERROR(IF(AND(AU25>0,E25>0),(AU25/E25)^(1/14)-1,"n/m"),"n/m") -> 0.065842786 | BK25: 2030E | BL25: =BM25+$BL$21 -> 0.06 | BM25: 0.04 | BN25: =BM25+$BN$21 -> 0.01
B26: Wholesale revenues y/y % | F26: =IF(AND(ISNUMBER(F25),ISNUMBER(C25)),IFERROR(F25/C25-1,""),"") -> 0.090544913 | G26: =IF(AND(ISNUMBER(G25),ISNUMBER(D25)),IFERROR(G25/D25-1,""),"") -> 0.052834342 | H26: =IF(AND(ISNUMBER(H25),ISNUMBER(E25)),IFERROR(H25/E25-1,""),"") -> 0.072033225 | I26: =IF(AND(ISNUMBER(I25),ISNUMBER(F25)),IFERROR(I25/F25-1,""),"") -> 0.019254072 | J26: =IF(AND(ISNUMBER(J25),ISNUMBER(G25)),IFERROR(J25/G25-1,""),"") -> 0.027161936 | K26: =IF(AND(ISNUMBER(K25),ISNUMBER(H25)),IFERROR(K25/H25-1,""),"") -> 0.023066432 | L26: =IF(AND(ISNUMBER(L25),ISNUMBER(I25)),IFERROR(L25/I25-1,""),"") -> 0.062100405 | M26: =IF(AND(ISNUMBER(M25),ISNUMBER(J25)),IFERROR(M25/J25-1,""),"") -> -0.062377137 | ... AX26: =IF(AND(ISNUMBER(AX25),ISNUMBER(AU25)),IFERROR(AX25/AU25-1,""),"") -> 0.015380217 | AY26: =CHOOSE(MATCH($BC$2,{"Bull","Base","Bear"},0),$BL$22,$BM$22,$BN$22) -> 0.06 | AZ26: =CHOOSE(MATCH($BC$2,{"Bull","Base","Bear"},0),$BL$23,$BM$23,$BN$23) -> 0.05 | BA26: =CHOOSE(MATCH($BC$2,{"Bull","Base","Bear"},0),$BL$24,$BM$24,$BN$24) -> 0.045 | BB26: =CHOOSE(MATCH($BC$2,{"Bull","Base","Bear"},0),$BL$25,$BM$25,$BN$25) -> 0.04 | BC26: 2027E–2030E: scenario lever WHS_growth (selective distribution: SS/FW order books, department-store exposure).
B27: Wholesale growth at constant FX (company) % | AU27: 0.087 | AV27: 0.027 | AW27: =AW70 -> 0.027 | AX27: =IFERROR((AS25*(1+AV27)+AT25*(1+AW27))/AU25-1,"") -> 0.027 | BK27: FM_margin (first margin %) | BL27: 0.007 | BM27: Δ → | BN27: -0.01 | BO27: FY23 72.5%, FY24 74.5%, FY25 75.2%, H1/26 75.0%: retail mix and pricing.
B28: Memo: mono-brand wholesale revenues (reported separately to 2016) | C28: 14.864 | D28: =E28-C28 -> 12.292 | E28: 27.156 | F28: 21.809 | G28: =H28-F28 -> 10.873 | H28: 32.682 | I28: 20.6 | J28: =K28-I28 -> 12.48 | K28: 33.08 | L28: 21.833 | M28: =N28-L28 -> 9.04 | N28: 30.873 | O28: 21.96 | P28: =Q28-O28 -> 11.428 | Q28: 33.388 | R28: 22.221 | S28: =T28-R28 -> 11.955 | T28: 34.176 | U28: 17.6 | V28: =W28-U28 -> 7.705 | W28: 25.305 | X28: 19.778 | Y28: =Z28-X28 -> 10.427 | Z28: 30.205 | AA28: 18.209 | AB28: =AC28-AA28 -> 14.408 | AC28: 32.617 | AD28: 13.604 | AE28: =AF28-AD28 -> 21.972 | AF28: 35.576 | BK28: 2027E | BL28: =BM28+$BL$27 -> 0.765 | BM28: 0.758 | BN28: =BM28+$BN$27 -> 0.748
B29: Memo: multi-brand wholesale revenues (reported separately to 2016) | C29: 81.243 | D29: =E29-C29 -> 80.375 | E29: 161.618 | F29: 83 | G29: =H29-F29 -> 86.69 | H29: 169.69 | I29: 86.227 | J29: =K29-I29 -> 87.733 | K29: 173.96 | L29: 91.628 | M29: =N29-L29 -> 84.922 | N29: 176.55 | O29: 93.604 | P29: =Q29-O29 -> 93.985 | Q29: 187.589 | R29: 98.064 | S29: =T29-R29 -> 97.511 | T29: 195.575 | U29: 104.606 | V29: =W29-U29 -> 103.106 | W29: 207.712 | X29: 115.788 | Y29: =Z29-X29 -> 110.738 | Z29: 226.526 | AA29: 123.258 | AB29: =AC29-AA29 -> 112.451 | AC29: 235.709 | AD29: 89.022 | AE29: =AF29-AD29 -> 150.642 | AF29: 239.664 | BK29: 2028E | BL29: =BM29+$BL$27 -> 0.766 | BM29: 0.759 | BN29: =BM29+$BN$27 -> 0.749
B30: Wholesale % of revenues | C30: =IF(AND(ISNUMBER(C25),ISNUMBER(C111)),IFERROR(C25/C111,""),"") -> 0.82525739 | D30: =IF(AND(ISNUMBER(D25),ISNUMBER(D111)),IFERROR(D25/D111,""),"") -> 0.73441487 | E30: =IF(AND(ISNUMBER(E25),ISNUMBER(E111)),IFERROR(E25/E111,""),"") -> 0.77801636 | F30: =IF(AND(ISNUMBER(F25),ISNUMBER(F111)),IFERROR(F25/F111,""),"") -> 0.7751973 | G30: =IF(AND(ISNUMBER(G25),ISNUMBER(G111)),IFERROR(G25/G111,""),"") -> 0.6769661 | H30: =IF(AND(ISNUMBER(H25),ISNUMBER(H111)),IFERROR(H25/H111,""),"") -> 0.72451409 | I30: =IF(AND(ISNUMBER(I25),ISNUMBER(I111)),IFERROR(I25/I111,""),"") -> 0.67794814 | J30: =IF(AND(ISNUMBER(J25),ISNUMBER(J111)),IFERROR(J25/J111,""),"") -> 0.60769772 | ... BB30: =IF(AND(ISNUMBER(BB25),ISNUMBER(BB111)),IFERROR(BB25/BB111,""),"") -> 0.2684963 | BK30: 2029E | BL30: =BM30+$BL$27 -> 0.767 | BM30: 0.76 | BN30: =BM30+$BN$27 -> 0.75
BK31: 2030E | BL31: =BM31+$BL$27 -> 0.767 | BM31: 0.76 | BN31: =BM31+$BN$27 -> 0.75
B32: Geography (Europe incl. Italy · Americas · Asia incl. Middle East & rest of world) — reconciled to the channel build | BC32: GEOGRAPHY — modelling logic
B33: Europe (incl. Italy) | C33: 75.172 | D33: =E33-C33 -> 74.348 | E33: 149.52 | F33: 80.638 | G33: =H33-F33 -> 77.948 | H33: 158.586 | I33: 91.017 | J33: =K33-I33 -> 83.544 | K33: 174.561 | L33: 96.308 | M33: =N33-L33 -> 88.885 | N33: 185.193 | O33: 100.119 | P33: =Q33-O33 -> 99.853 | Q33: 199.972 | R33: 107.908 | S33: =T33-R33 -> 104.692 | T33: 212.6 | U33: 117.048 | V33: =W33-U33 -> 118.507 | W33: 235.555 | X33: 128.077 | Y33: =Z33-X33 -> 123.85 | Z33: 251.927 | AA33: 136.705 | AB33: =AC33-AA33 -> 137.766 | AC33: 274.471 | AD33: 99.031 | AE33: =AF33-AD33 -> 150.764 | AF33: 249.795 | AG33: 136.932 | AH33: =AI33-AG33 -> 166.441 | AI33: 303.373 | AJ33: 164.955 | AK33: =AL33-AJ33 -> 201.612 | AL33: 366.567 | AM33: 202.769 | AN33: =AO33-AM33 -> 225.463 | AO33: 428.232 | AP33: 221.052 | AQ33: =AR33-AP33 -> 235.535 | AR33: 456.587 | AS33: 243.213 | AT33: =AU33-AS33 -> 251.707 | AU33: 494.92 | AV33: 255.582 | AW33: =AW47*AW52 -> 265.61866 | AX33: =AV33+AW33 -> 521.20066 | AY33: =AY47*AY52 -> 560.80307 | AZ33: =AZ47*AZ52 -> 595.23614 | BA33: =BA47*BA52 -> 628.34989 | BB33: =BB47*BB52 -> 661.8416 | BE33: =IFERROR(IF(AND(BB33>0,AU33>0),(BB33/AU33)^(1/5)-1,"n/m"),"n/m") -> 0.059848552 | BF33: =IFERROR(IF(AND(AU33>0,AF33>0),(AU33/AF33)^(1/5)-1,"n/m"),"n/m") -> 0.14654275 | BG33: =IFERROR(IF(AND(AU33>0,Q33>0),(AU33/Q33)^(1/10)-1,"n/m"),"n/m") -> 0.094854938 | BH33: =IFERROR(IF(AND(AU33>0,E33>0),(AU33/E33)^(1/14)-1,"n/m"),"n/m") -> 0.089258914 | BK33: SVC_ratio (services ex-outsourced % revenues) | BL33: -0.005 | BM33: Δ → | BN33: 0.008 | BO33: Variable rents, communication, transport & duties (US tariffs from FW25), cards: FY24 26.3%, FY25 26.1%.
B34: Europe y/y % | F34: =IF(AND(ISNUMBER(F33),ISNUMBER(C33)),IFERROR(F33/C33-1,""),"") -> 0.072713244 | G34: =IF(AND(ISNUMBER(G33),ISNUMBER(D33)),IFERROR(G33/D33-1,""),"") -> 0.048420939 | H34: =IF(AND(ISNUMBER(H33),ISNUMBER(E33)),IFERROR(H33/E33-1,""),"") -> 0.060634029 | I34: =IF(AND(ISNUMBER(I33),ISNUMBER(F33)),IFERROR(I33/F33-1,""),"") -> 0.12871103 | J34: =IF(AND(ISNUMBER(J33),ISNUMBER(G33)),IFERROR(J33/G33-1,""),"") -> 0.071791451 | K34: =IF(AND(ISNUMBER(K33),ISNUMBER(H33)),IFERROR(K33/H33-1,""),"") -> 0.10073399 | L34: =IF(AND(ISNUMBER(L33),ISNUMBER(I33)),IFERROR(L33/I33-1,""),"") -> 0.058131997 | M34: =IF(AND(ISNUMBER(M33),ISNUMBER(J33)),IFERROR(M33/J33-1,""),"") -> 0.063930384 | ... AX34: =IF(AND(ISNUMBER(AX33),ISNUMBER(AU33)),IFERROR(AX33/AU33-1,""),"") -> 0.053100823 | AY34: =IF(AND(ISNUMBER(AY33),ISNUMBER(AX33)),IFERROR(AY33/AX33-1,""),"") -> 0.075983045 | AZ34: =IF(AND(ISNUMBER(AZ33),ISNUMBER(AY33)),IFERROR(AZ33/AY33-1,""),"") -> 0.061399578 | BA34: =IF(AND(ISNUMBER(BA33),ISNUMBER(AZ33)),IFERROR(BA33/AZ33-1,""),"") -> 0.05563127 | BB34: =IF(AND(ISNUMBER(BB33),ISNUMBER(BA33)),IFERROR(BB33/BA33-1,""),"") -> 0.053301051 | BK34: 2027E | BL34: =BM34+$BL$33 -> 0.253 | BM34: 0.258 | BN34: =BM34+$BN$33 -> 0.266
B35: Europe growth at constant FX (company) % | AS35: 0.097 | AU35: 0.081 | AV35: 0.053 | BK35: 2028E | BL35: =BM35+$BL$33 -> 0.252 | BM35: 0.257 | BN35: =BM35+$BN$33 -> 0.265
B36: Americas (North America to 2023) | C36: 28.744 | D36: =E36-C36 -> 40.217 | E36: 68.961 | F36: 35.445 | G36: =H36-F36 -> 53.109 | H36: 88.554 | I36: 46.892 | J36: =K36-I36 -> 62.176 | K36: 109.068 | L36: 55.416 | M36: =N36-L36 -> 67.467 | N36: 122.883 | O36: 69.692 | P36: =Q36-O36 -> 86.903 | Q36: 156.595 | R36: 76.445 | S36: =T36-R36 -> 91.212 | T36: 167.657 | U36: 83.584 | V36: =W36-U36 -> 95.072 | W36: 178.656 | X36: 86.323 | Y36: =Z36-X36 -> 100.913 | Z36: 187.236 | AA36: 94.077 | AB36: =AC36-AA36 -> 110.032 | AC36: 204.109 | AD36: 57.484 | AE36: =AF36-AD36 -> 115.294 | AF36: 172.778 | AG36: 99.983 | AH36: =AI36-AG36 -> 138.255 | AI36: 238.238 | AJ36: 152.613 | AK36: =AL36-AJ36 -> 182.08 | AL36: 334.693 | AM36: 189.007 | AN36: =AO36-AM36 -> 215.446 | AO36: 404.453 | AP36: 225.616 | AQ36: =AR36-AP36 -> 250.943 | AR36: 476.559 | AS36: 245.253 | AT36: =AU36-AS36 -> 275.235 | AU36: 520.488 | AV36: 278.671 | AW36: =AW49*AW52 -> 301.4073 | AX36: =AV36+AW36 -> 580.0783 | AY36: =AY49*AY52 -> 647.48729 | AZ36: =AZ49*AZ52 -> 706.60169 | BA36: =BA49*BA52 -> 767.02152 | BB36: =BB49*BB52 -> 826.95893 | BE36: =IFERROR(IF(AND(BB36>0,AU36>0),(BB36/AU36)^(1/5)-1,"n/m"),"n/m") -> 0.097020249 | BF36: =IFERROR(IF(AND(AU36>0,AF36>0),(AU36/AF36)^(1/5)-1,"n/m"),"n/m") -> 0.24676458 | BG36: =IFERROR(IF(AND(AU36>0,Q36>0),(AU36/Q36)^(1/10)-1,"n/m"),"n/m") -> 0.12762133 | BH36: =IFERROR(IF(AND(AU36>0,E36>0),(AU36/E36)^(1/14)-1,"n/m"),"n/m") -> 0.15531527 | BK36: 2029E | BL36: =BM36+$BL$33 -> 0.251 | BM36: 0.256 | BN36: =BM36+$BN$33 -> 0.264
B37: Americas y/y % | F37: =IF(AND(ISNUMBER(F36),ISNUMBER(C36)),IFERROR(F36/C36-1,""),"") -> 0.23312691 | G37: =IF(AND(ISNUMBER(G36),ISNUMBER(D36)),IFERROR(G36/D36-1,""),"") -> 0.32056096 | H37: =IF(AND(ISNUMBER(H36),ISNUMBER(E36)),IFERROR(H36/E36-1,""),"") -> 0.28411711 | I37: =IF(AND(ISNUMBER(I36),ISNUMBER(F36)),IFERROR(I36/F36-1,""),"") -> 0.32295105 | J37: =IF(AND(ISNUMBER(J36),ISNUMBER(G36)),IFERROR(J36/G36-1,""),"") -> 0.17072436 | K37: =IF(AND(ISNUMBER(K36),ISNUMBER(H36)),IFERROR(K36/H36-1,""),"") -> 0.23165526 | L37: =IF(AND(ISNUMBER(L36),ISNUMBER(I36)),IFERROR(L36/I36-1,""),"") -> 0.18177941 | M37: =IF(AND(ISNUMBER(M36),ISNUMBER(J36)),IFERROR(M36/J36-1,""),"") -> 0.085097144 | ... AX37: =IF(AND(ISNUMBER(AX36),ISNUMBER(AU36)),IFERROR(AX36/AU36-1,""),"") -> 0.11448929 | AY37: =IF(AND(ISNUMBER(AY36),ISNUMBER(AX36)),IFERROR(AY36/AX36-1,""),"") -> 0.11620671 | AZ37: =IF(AND(ISNUMBER(AZ36),ISNUMBER(AY36)),IFERROR(AZ36/AY36-1,""),"") -> 0.091298158 | BA37: =IF(AND(ISNUMBER(BA36),ISNUMBER(AZ36)),IFERROR(BA36/AZ36-1,""),"") -> 0.085507627 | BB37: =IF(AND(ISNUMBER(BB36),ISNUMBER(BA36)),IFERROR(BB36/BA36-1,""),"") -> 0.078143057 | BK37: 2030E | BL37: =BM37+$BL$33 -> 0.25 | BM37: 0.255 | BN37: =BM37+$BN$33 -> 0.263
B38: Americas growth at constant FX (company) % | AS38: 0.1 | AU38: 0.119 | AV38: 0.206
B39: Asia (Greater China + rest of world / rest of Asia) | C39: 12.541 | D39: =E39-C39 -> 11.613 | E39: 24.154 | F39: 19.12 | G39: =H39-F39 -> 13.061 | H39: 32.181 | I39: 19.665 | J39: =K39-I39 -> 19.186 | K39: 38.851 | L39: 24.087 | M39: =N39-L39 -> 23.746 | N39: 47.833 | O39: 30.521 | P39: =Q39-O39 -> 27.063 | Q39: 57.584 | R39: 35.487 | S39: =T39-R39 -> 40.227 | T39: 75.714 | U39: 42.695 | V39: =W39-U39 -> 46.665 | W39: 89.36 | X39: 55.086 | Y39: =Z39-X39 -> 58.747 | Z39: 113.833 | AA39: 60.631 | AB39: =AC39-AA39 -> 68.55 | AC39: 129.181 | AD39: 48.628 | AE39: =AF39-AD39 -> 72.812 | AF39: 121.44 | AG39: 76.849 | AH39: =AI39-AG39 -> 93.719 | AI39: 170.568 | AJ39: 97.789 | AK39: =AL39-AJ39 -> 120.659 | AL39: 218.448 | AM39: 152.166 | AN39: =AO39-AM39 -> 154.569 | AO39: 306.735 | AP39: 173.994 | AQ39: =AR39-AP39 -> 171.4 | AR39: 345.394 | AS39: 195.669 | AT39: =AU39-AS39 -> 196.874 | AU39: 392.543 | AV39: 215.158 | AW39: =AW51*AW52 -> 213.63494 | AX39: =AV39+AW39 -> 428.79294 | AY39: =AY51*AY52 -> 478.62156 | AZ39: =AZ51*AZ52 -> 524.70384 | BA39: =BA51*BA52 -> 572.18273 | BB39: =BB51*BB52 -> 619.73767 | BE39: =IFERROR(IF(AND(BB39>0,AU39>0),(BB39/AU39)^(1/5)-1,"n/m"),"n/m") -> 0.095630545 | BF39: =IFERROR(IF(AND(AU39>0,AF39>0),(AU39/AF39)^(1/5)-1,"n/m"),"n/m") -> 0.26446 | BG39: =IFERROR(IF(AND(AU39>0,Q39>0),(AU39/Q39)^(1/10)-1,"n/m"),"n/m") -> 0.21159798 | BH39: =IFERROR(IF(AND(AU39>0,E39>0),(AU39/E39)^(1/14)-1,"n/m"),"n/m") -> 0.22037338 | BK39: PAY_ratio (payroll % revenues) | BL39: -0.003 | BM39: Δ → | BN39: 0.005 | BO39: FY24 18.3%, FY25 18.1%, H1/26 18.5% (artisans in boutiques, stock-grant plan).
B40: Asia y/y % | F40: =IF(AND(ISNUMBER(F39),ISNUMBER(C39)),IFERROR(F39/C39-1,""),"") -> 0.52459931 | G40: =IF(AND(ISNUMBER(G39),ISNUMBER(D39)),IFERROR(G39/D39-1,""),"") -> 0.12468785 | H40: =IF(AND(ISNUMBER(H39),ISNUMBER(E39)),IFERROR(H39/E39-1,""),"") -> 0.33232591 | I40: =IF(AND(ISNUMBER(I39),ISNUMBER(F39)),IFERROR(I39/F39-1,""),"") -> 0.028504184 | J40: =IF(AND(ISNUMBER(J39),ISNUMBER(G39)),IFERROR(J39/G39-1,""),"") -> 0.46895337 | K40: =IF(AND(ISNUMBER(K39),ISNUMBER(H39)),IFERROR(K39/H39-1,""),"") -> 0.20726516 | L40: =IF(AND(ISNUMBER(L39),ISNUMBER(I39)),IFERROR(L39/I39-1,""),"") -> 0.22486651 | M40: =IF(AND(ISNUMBER(M39),ISNUMBER(J39)),IFERROR(M39/J39-1,""),"") -> 0.2376733 | ... AX40: =IF(AND(ISNUMBER(AX39),ISNUMBER(AU39)),IFERROR(AX39/AU39-1,""),"") -> 0.09234642 | AY40: =IF(AND(ISNUMBER(AY39),ISNUMBER(AX39)),IFERROR(AY39/AX39-1,""),"") -> 0.11620671 | AZ40: =IF(AND(ISNUMBER(AZ39),ISNUMBER(AY39)),IFERROR(AZ39/AY39-1,""),"") -> 0.096281255 | BA40: =IF(AND(ISNUMBER(BA39),ISNUMBER(AZ39)),IFERROR(BA39/AZ39-1,""),"") -> 0.09048702 | BB40: =IF(AND(ISNUMBER(BB39),ISNUMBER(BA39)),IFERROR(BB39/BA39-1,""),"") -> 0.083111458 | BK40: 2027E | BL40: =BM40+$BL$39 -> 0.178 | BM40: 0.181 | BN40: =BM40+$BN$39 -> 0.186
B41: Asia growth at constant FX (company) % | AS41: 0.13 | AU41: 0.153 | AV41: 0.141 | BK41: 2028E | BL41: =BM41+$BL$39 -> 0.177 | BM41: 0.18 | BN41: =BM41+$BN$39 -> 0.185
B42: Memo: of which Italy | C42: 37.642 | D42: =E42-C42 -> 37.162 | E42: 74.804 | F42: 36.605 | G42: =H42-F42 -> 32.057 | H42: 68.662 | I42: 36.174 | J42: =K42-I42 -> 30.49 | K42: 66.664 | L42: 36.26 | M42: =N42-L42 -> 32.234 | N42: 68.494 | O42: 36.906 | P42: =Q42-O42 -> 34.088 | Q42: 70.994 | R42: 39.464 | S42: =T42-R42 -> 36.734 | T42: 76.198 | U42: 41.814 | V42: =W42-U42 -> 42.883 | W42: 84.697 | X42: 43.826 | Y42: =Z42-X42 -> 44.394 | Z42: 88.22 | AA42: 44.308 | AB42: =AC42-AA42 -> 45.412 | AC42: 89.72 | AD42: 28.943 | AE42: =AF42-AD42 -> 39.38 | AF42: 68.323 | AG42: 41.038 | AH42: =AI42-AG42 -> 43.185 | AI42: 84.223 | AJ42: 49.187 | AK42: =AL42-AJ42 -> 53.566 | AL42: 102.753 | AM42: 60.888 | AN42: =AO42-AM42 -> 67.964 | AO42: 128.852 | AP42: 68.093 | AQ42: =AR42-AP42 -> 72.828 | AR42: 140.921 | AS42: 78.828 | AT42: =AU42-AS42 -> 79.872 | AU42: 158.7 | BK42: 2029E | BL42: =BM42+$BL$39 -> 0.177 | BM42: 0.18 | BN42: =BM42+$BN$39 -> 0.185
B43: Memo: Europe excluding Italy (legacy disclosure) | C43: 37.53 | D43: =E43-C43 -> 37.186 | E43: 74.716 | F43: 44.033 | G43: =H43-F43 -> 45.891 | H43: 89.924 | I43: 54.843 | J43: =K43-I43 -> 53.054 | K43: 107.897 | L43: 60.048 | M43: =N43-L43 -> 56.651 | N43: 116.699 | O43: 63.213 | P43: =Q43-O43 -> 65.765 | Q43: 128.978 | R43: 68.444 | S43: =T43-R43 -> 67.958 | T43: 136.402 | U43: 75.234 | V43: =W43-U43 -> 75.624 | W43: 150.858 | X43: 84.251 | Y43: =Z43-X43 -> 79.456 | Z43: 163.707 | AA43: 92.397 | AB43: =AC43-AA43 -> 92.354 | AC43: 184.751 | AD43: 70.088 | AE43: =AF43-AD43 -> 111.384 | AF43: 181.472 | AG43: 95.894 | AH43: =AI43-AG43 -> 123.256 | AI43: 219.15 | AJ43: 115.768 | AK43: =AL43-AJ43 -> 148.046 | AL43: 263.814 | AM43: 141.881 | AN43: =AO43-AM43 -> 157.499 | AO43: 299.38 | AP43: 152.959 | AQ43: =AR43-AP43 -> 162.707 | AR43: 315.666 | BK43: 2030E | BL43: =BM43+$BL$39 -> 0.176 | BM43: 0.179 | BN43: =BM43+$BN$39 -> 0.184
B44: Memo: Greater China / China (legacy disclosure) | C44: 4.08 | D44: =E44-C44 -> 4.449 | E44: 8.529 | F44: 6.184 | G44: =H44-F44 -> 4.131 | H44: 10.315 | I44: 7.226 | J44: =K44-I44 -> 8.502 | K44: 15.728 | L44: 10.367 | M44: =N44-L44 -> 10.505 | N44: 20.872 | O44: 11.867 | P44: =Q44-O44 -> 13.871 | Q44: 25.738 | R44: 13.651 | S44: =T44-R44 -> 17.697 | T44: 31.348 | U44: 18.371 | V44: =W44-U44 -> 24.325 | W44: 42.696 | X44: 24.858 | Y44: =Z44-X44 -> 30.029 | Z44: 54.887 | AA44: 28.8 | AB44: =AC44-AA44 -> 34.098 | AC44: 62.898 | AD44: 22.863 | AE44: =AF44-AD44 -> 38.863 | AF44: 61.726
B45: Memo: Rest of the world / rest of Asia (legacy disclosure) | C45: 8.461 | D45: =E45-C45 -> 7.164 | E45: 15.625 | F45: 12.936 | G45: =H45-F45 -> 8.93 | H45: 21.866 | I45: 12.439 | J45: =K45-I45 -> 10.684 | K45: 23.123 | L45: 13.72 | M45: =N45-L45 -> 13.241 | N45: 26.961 | O45: 18.654 | P45: =Q45-O45 -> 13.192 | Q45: 31.846 | R45: 21.836 | S45: =T45-R45 -> 22.53 | T45: 44.366 | U45: 24.324 | V45: =W45-U45 -> 22.34 | W45: 46.664 | X45: 30.228 | Y45: =Z45-X45 -> 28.718 | Z45: 58.946 | AA45: 31.831 | AB45: =AC45-AA45 -> 34.452 | AC45: 66.283 | AD45: 25.765 | AE45: =AF45-AD45 -> 33.949 | AF45: 59.714 | BK45: CAPEX_pct (capex % revenues) | BL45: 0 | BM45: Δ → | BN45: 0 | BO45: Ordinary investment level after the 2024–25 extraordinary programme (FY23 6.7%, FY24 7.8%, FY25 10.1%, H1/26 7.6%).
B46: Europe growth input before reconciliation (forecast) % | AW46: 0.06 | AY46: 0.07 | AZ46: 0.065 | BA46: 0.06 | BB46: 0.06 | BC46: Regional growth inputs (reconciled pro rata to the channel build). Europe: FY25 +7.8%, H1/26 +5.3% cFX. | BK46: 2027E | BL46: =BM46+$BL$45 -> 0.065 | BM46: 0.065 | BN46: =BM46+$BN$45 -> 0.065
B47: Europe before reconciliation (forecast helper) | AW47: =AT33*(1+AW46+AW66) -> 266.80942 | AY47: =AX33*(1+AY46) -> 557.68471 | AZ47: =AY33*(1+AZ46) -> 597.25527 | BA47: =AZ33*(1+BA46) -> 630.95031 | BB47: =BA33*(1+BB46) -> 666.05088 | BK47: 2028E | BL47: =BM47+$BL$45 -> 0.065 | BM47: 0.065 | BN47: =BM47+$BN$45 -> 0.065
B48: Americas growth input before reconciliation (forecast) % | AW48: 0.1 | AY48: 0.11 | AZ48: 0.095 | BA48: 0.09 | BB48: 0.085 | BC48: Americas: FY25 +9.2%, H1/26 +20.6% cFX (Exemplar Luxury Group / ex-Saks wholesale normalising). | BK48: 2029E | BL48: =BM48+$BL$45 -> 0.065 | BM48: 0.065 | BN48: =BM48+$BN$45 -> 0.065
B49: Americas before reconciliation (forecast helper) | AW49: =AT36*(1+AW48+AW66) -> 302.7585 | AY49: =AX36*(1+AY48) -> 643.88691 | AZ49: =AY36*(1+AZ48) -> 708.99858 | BA49: =AZ36*(1+BA48) -> 770.19584 | BB49: =BA36*(1+BB48) -> 832.21835 | BK49: 2030E | BL49: =BM49+$BL$45 -> 0.065 | BM49: 0.065 | BN49: =BM49+$BN$45 -> 0.065
B50: Asia growth input before reconciliation (forecast) % | AW50: 0.09 | AY50: 0.11 | AZ50: 0.1 | BA50: 0.095 | BB50: 0.09 | BC50: Asia: FY25 +13.7%, H1/26 +14.1% cFX (China driving).
B51: Asia before reconciliation (forecast helper) | AW51: =AT39*(1+AW50+AW66) -> 214.59266 | AY51: =AX39*(1+AY50) -> 475.96016 | AZ51: =AY39*(1+AZ50) -> 526.48371 | BA51: =AZ39*(1+BA50) -> 574.55071 | BB51: =BA39*(1+BB50) -> 623.67917
B52: Reconciliation factor: channel-build revenues ÷ Σ regional inputs (x) | AW52: =IFERROR(AW62/(AW47+AW49+AW51),"") -> 0.99553704 | AY52: =IFERROR(AY62/(AY47+AY49+AY51),"") -> 1.0055916 | AZ52: =IFERROR(AZ62/(AZ47+AZ49+AZ51),"") -> 0.99661932 | BA52: =IFERROR(BA62/(BA47+BA49+BA51),"") -> 0.99587856 | BB52: =IFERROR(BB62/(BB47+BB49+BB51),"") -> 0.99368024 | BC52: Regional growth inputs are scaled pro rata so that Σ regions = channel build (channel build is the driver).
B53: Check: Σ regions vs consolidated revenues (should be 0) | C53: =IF(ISNUMBER(C33),ROUND(C33+C36+C39-C111,1),"") -> 0 | D53: =IF(ISNUMBER(D33),ROUND(D33+D36+D39-D111,1),"") -> 0 | E53: =IF(ISNUMBER(E33),ROUND(E33+E36+E39-E111,1),"") -> 0 | F53: =IF(ISNUMBER(F33),ROUND(F33+F36+F39-F111,1),"") -> 0 | G53: =IF(ISNUMBER(G33),ROUND(G33+G36+G39-G111,1),"") -> 0 | H53: =IF(ISNUMBER(H33),ROUND(H33+H36+H39-H111,1),"") -> 0 | I53: =IF(ISNUMBER(I33),ROUND(I33+I36+I39-I111,1),"") -> 0 | J53: =IF(ISNUMBER(J33),ROUND(J33+J36+J39-J111,1),"") -> 0 | ... BB53: =IF(ISNUMBER(BB33),ROUND(BB33+BB36+BB39-BB111,1),"") -> 0
B55: Quarterly revenues (memo; Q1/Q3 revenue-only releases) | BC55: QUARTERS — modelling logic
B56: First quarter of the half: Q1 (H1 columns) / Q3 (H2 columns) | F56: 77.636 | G56: =220.165-F111 -> 84.962 | I56: 88.835 | J56: =251.685-I111 -> 94.111 | L56: 99.643 | M56: =277.346-L111 -> 101.535 | O56: 111.701 | P56: =317.558-O111 -> 117.226 | R56: 121.8 | S56: =348.4-R111 -> 128.56 | U56: 134.1 | V56: =384.2-U111 -> 140.873 | X56: 148.3 | Y56: =422.1-X111 -> 152.614 | AA56: 160.4 | AB56: =459.2-AA111 -> 167.787 | AD56: 156.7 | AE56: =378.7-AD111 -> 173.557 | AG56: 164.6 | AH56: =502.59-AG111 -> 188.826 | AJ56: 196.936 | AK56: =642.026-AJ111 -> 226.669 | AM56: 265.331 | AN56: =818.379-AM111 -> 274.437 | AP56: 309.092 | AQ56: =920.238-AP111 -> 299.576 | AS56: 341.473 | AT56: =1019.171-AS111 -> 335.036 | AV56: 369.052 | BC56: Q1 from the Q1 sales release; Q3 = nine-month revenues − H1.
B57: Second quarter of the half: Q2 / Q4 (half − first quarter) | C57: =IF(ISNUMBER(C56),C111-C56,"") | D57: =IF(ISNUMBER(D56),D111-D56,"") | F57: =IF(ISNUMBER(F56),F111-F56,"") -> 57.567 | G57: =IF(ISNUMBER(G56),G111-G56,"") -> 59.156 | I57: =IF(ISNUMBER(I56),I111-I56,"") -> 68.739 | J57: =IF(ISNUMBER(J56),J111-J56,"") -> 70.795 | L57: =IF(ISNUMBER(L56),L111-L56,"") -> 76.168 | M57: =IF(ISNUMBER(M56),M111-M56,"") -> 78.563 | O57: =IF(ISNUMBER(O56),O111-O56,"") -> 88.631 | P57: =IF(ISNUMBER(P56),P111-P56,"") -> 96.593 | R57: =IF(ISNUMBER(R56),R111-R56,"") -> 98.04 | S57: =IF(ISNUMBER(S56),S111-S56,"") -> 107.571 | U57: =IF(ISNUMBER(U56),U111-U56,"") -> 109.227 | V57: =IF(ISNUMBER(V56),V111-V56,"") -> 119.371 | X57: =IF(ISNUMBER(X56),X111-X56,"") -> 121.186 | Y57: =IF(ISNUMBER(Y56),Y111-Y56,"") -> 130.896 | AA57: =IF(ISNUMBER(AA56),AA111-AA56,"") -> 131.013 | AB57: =IF(ISNUMBER(AB56),AB111-AB56,"") -> 148.561 | AD57: =IF(ISNUMBER(AD56),AD111-AD56,"") -> 48.443 | AE57: =IF(ISNUMBER(AE56),AE111-AE56,"") -> 165.313 | AG57: =IF(ISNUMBER(AG56),AG111-AG56,"") -> 149.164 | AH57: =IF(ISNUMBER(AH56),AH111-AH56,"") -> 209.589 | AJ57: =IF(ISNUMBER(AJ56),AJ111-AJ56,"") -> 218.421 | AK57: =IF(ISNUMBER(AK56),AK111-AK56,"") -> 277.682 | AM57: =IF(ISNUMBER(AM56),AM111-AM56,"") -> 278.611 | AN57: =IF(ISNUMBER(AN56),AN111-AN56,"") -> 321.041 | AP57: =IF(ISNUMBER(AP56),AP111-AP56,"") -> 311.57 | AQ57: =IF(ISNUMBER(AQ56),AQ111-AQ56,"") -> 358.302 | AS57: =IF(ISNUMBER(AS56),AS111-AS56,"") -> 342.662 | AT57: =IF(ISNUMBER(AT56),AT111-AT56,"") -> 388.78 | AV57: =IF(ISNUMBER(AV56),AV111-AV56,"") -> 380.359
B58: Q1 / Q3 revenues y/y % | F58: =IF(AND(ISNUMBER(F56),ISNUMBER(C56)),IFERROR(F56/C56-1,""),"") | G58: =IF(AND(ISNUMBER(G56),ISNUMBER(D56)),IFERROR(G56/D56-1,""),"") | H58: =IF(AND(ISNUMBER(H56),ISNUMBER(E56)),IFERROR(H56/E56-1,""),"") | I58: =IF(AND(ISNUMBER(I56),ISNUMBER(F56)),IFERROR(I56/F56-1,""),"") -> 0.14425009 | J58: =IF(AND(ISNUMBER(J56),ISNUMBER(G56)),IFERROR(J56/G56-1,""),"") -> 0.10768343 | K58: =IF(AND(ISNUMBER(K56),ISNUMBER(H56)),IFERROR(K56/H56-1,""),"") | L58: =IF(AND(ISNUMBER(L56),ISNUMBER(I56)),IFERROR(L56/I56-1,""),"") -> 0.12166376 | M58: =IF(AND(ISNUMBER(M56),ISNUMBER(J56)),IFERROR(M56/J56-1,""),"") -> 0.078885571 | ... AX58: =IF(AND(ISNUMBER(AX56),ISNUMBER(AU56)),IFERROR(AX56/AU56-1,""),"") | AY58: =IF(AND(ISNUMBER(AY56),ISNUMBER(AX56)),IFERROR(AY56/AX56-1,""),"") | AZ58: =IF(AND(ISNUMBER(AZ56),ISNUMBER(AY56)),IFERROR(AZ56/AY56-1,""),"") | BA58: =IF(AND(ISNUMBER(BA56),ISNUMBER(AZ56)),IFERROR(BA56/AZ56-1,""),"") | BB58: =IF(AND(ISNUMBER(BB56),ISNUMBER(BA56)),IFERROR(BB56/BA56-1,""),"")
B59: Q2 / Q4 revenues y/y % | F59: =IF(AND(ISNUMBER(F57),ISNUMBER(C57)),IFERROR(F57/C57-1,""),"") | G59: =IF(AND(ISNUMBER(G57),ISNUMBER(D57)),IFERROR(G57/D57-1,""),"") | H59: =IF(AND(ISNUMBER(H57),ISNUMBER(E57)),IFERROR(H57/E57-1,""),"") | I59: =IF(AND(ISNUMBER(I57),ISNUMBER(F57)),IFERROR(I57/F57-1,""),"") -> 0.19406952 | J59: =IF(AND(ISNUMBER(J57),ISNUMBER(G57)),IFERROR(J57/G57-1,""),"") -> 0.19675096 | K59: =IF(AND(ISNUMBER(K57),ISNUMBER(H57)),IFERROR(K57/H57-1,""),"") | L59: =IF(AND(ISNUMBER(L57),ISNUMBER(I57)),IFERROR(L57/I57-1,""),"") -> 0.10807547 | M59: =IF(AND(ISNUMBER(M57),ISNUMBER(J57)),IFERROR(M57/J57-1,""),"") -> 0.10972526 | ... AX59: =IF(AND(ISNUMBER(AX57),ISNUMBER(AU57)),IFERROR(AX57/AU57-1,""),"") | AY59: =IF(AND(ISNUMBER(AY57),ISNUMBER(AX57)),IFERROR(AY57/AX57-1,""),"") | AZ59: =IF(AND(ISNUMBER(AZ57),ISNUMBER(AY57)),IFERROR(AZ57/AY57-1,""),"") | BA59: =IF(AND(ISNUMBER(BA57),ISNUMBER(AZ57)),IFERROR(BA57/AZ57-1,""),"") | BB59: =IF(AND(ISNUMBER(BB57),ISNUMBER(BA57)),IFERROR(BB57/BA57-1,""),"")
B61: Group revenues, FX and FY26 outlook calibration | BC61: GROUP TOTAL — modelling logic
B62: Revenues (channel build) | C62: =N(C16)+N(C25) -> 116.457 | D62: =N(D16)+N(D25) -> 126.178 | E62: =N(E16)+N(E25) -> 242.635 | F62: =N(F16)+N(F25) -> 135.203 | G62: =N(G16)+N(G25) -> 144.118 | H62: =N(H16)+N(H25) -> 279.321 | I62: =N(I16)+N(I25) -> 157.574 | J62: =N(J16)+N(J25) -> 164.906 | ... BB62: =N(BB16)+N(BB25) -> 2108.5382 | BE62: =IFERROR(IF(AND(BB62>0,AU62>0),(BB62/AU62)^(1/5)-1,"n/m"),"n/m") -> 0.084123569 | BF62: =IFERROR(IF(AND(AU62>0,AF62>0),(AU62/AF62)^(1/5)-1,"n/m"),"n/m") -> 0.20947154 | BG62: =IFERROR(IF(AND(AU62>0,Q62>0),(AU62/Q62)^(1/10)-1,"n/m"),"n/m") -> 0.13016768 | BH62: =IFERROR(IF(AND(AU62>0,E62>0),(AU62/E62)^(1/14)-1,"n/m"),"n/m") -> 0.13382308
B63: Revenues y/y % | F63: =IF(AND(ISNUMBER(F62),ISNUMBER(C62)),IFERROR(F62/C62-1,""),"") -> 0.16096928 | G63: =IF(AND(ISNUMBER(G62),ISNUMBER(D62)),IFERROR(G62/D62-1,""),"") -> 0.14218009 | H63: =IF(AND(ISNUMBER(H62),ISNUMBER(E62)),IFERROR(H62/E62-1,""),"") -> 0.1511983 | I63: =IF(AND(ISNUMBER(I62),ISNUMBER(F62)),IFERROR(I62/F62-1,""),"") -> 0.1654623 | J63: =IF(AND(ISNUMBER(J62),ISNUMBER(G62)),IFERROR(J62/G62-1,""),"") -> 0.14424291 | K63: =IF(AND(ISNUMBER(K62),ISNUMBER(H62)),IFERROR(K62/H62-1,""),"") -> 0.15451398 | L63: =IF(AND(ISNUMBER(L62),ISNUMBER(I62)),IFERROR(L62/I62-1,""),"") -> 0.1157361 | M63: =IF(AND(ISNUMBER(M62),ISNUMBER(J62)),IFERROR(M62/J62-1,""),"") -> 0.092125211 | ... AX63: =IF(AND(ISNUMBER(AX62),ISNUMBER(AU62)),IFERROR(AX62/AU62-1,""),"") -> 0.086736612 | AY63: =IF(AND(ISNUMBER(AY62),ISNUMBER(AX62)),IFERROR(AY62/AX62-1,""),"") -> 0.102505 | AZ63: =IF(AND(ISNUMBER(AZ62),ISNUMBER(AY62)),IFERROR(AZ62/AY62-1,""),"") -> 0.082772403 | BA63: =IF(AND(ISNUMBER(BA62),ISNUMBER(AZ62)),IFERROR(BA62/AZ62-1,""),"") -> 0.077201886 | BB63: =IF(AND(ISNUMBER(BB62),ISNUMBER(BA62)),IFERROR(BB62/BA62-1,""),"") -> 0.071654474
B64: Check: channel build vs consolidated revenues (should be 0) | C64: =ROUND(C62-C111,1) -> 0 | D64: =ROUND(D62-D111,1) -> 0 | E64: =ROUND(E62-E111,1) -> 0 | F64: =ROUND(F62-F111,1) -> 0 | G64: =ROUND(G62-G111,1) -> 0 | H64: =ROUND(H62-H111,1) -> 0 | I64: =ROUND(I62-I111,1) -> 0 | J64: =ROUND(J62-J111,1) -> 0 | ... BB64: =ROUND(BB62-BB111,1) -> 0
B65: Revenue growth at constant FX (company) % | H65: 0.133 | I65: 0.172 | K65: 0.171 | L65: 0.129 | N65: 0.105 | O65: 0.093 | Q65: 0.095 | R65: 0.103 | T65: 0.104 | U65: 0.097 | W65: 0.109 | X65: 0.119 | Z65: 0.107 | AA65: 0.072 | AC65: 0.086 | AD65: -0.298 | AF65: -0.099 | AJ65: 0.283 | AL65: 0.248 | AM65: 0.305 | AO65: 0.26 | AP65: 0.147 | AR65: 0.124 | AS65: 0.107 | AU65: 0.115 | AV65: 0.133 | AW65: =AW68 -> 0.078535014 | AX65: =IFERROR((AS111*(1+AV65)+AT111*(1+AW65))/AU111-1,"") -> 0.105 | AY65: =AY63-AY66 -> 0.102505 | AZ65: =AZ63-AZ66 -> 0.082772403 | BA65: =BA63-BA66 -> 0.077201886 | BB65: =BB63-BB66 -> 0.071654474 | BC65: Company-reported constant-exchange-rate growth. FY26E = H1/26 actual and H2/26E constant-FX growth on the 2025 base.
B66: FX translation effect (reported − constant-FX growth), pp | H66: =IFERROR(H63-H65,"") -> 0.018198302 | I66: =IFERROR(I63-I65,"") -> -0.0065376952 | K66: =IFERROR(K63-K65,"") -> -0.016486018 | L66: =IFERROR(L63-L65,"") -> -0.013263901 | N66: =IFERROR(N63-N65,"") -> -0.0013377574 | O66: =IFERROR(O63-O65,"") -> 0.046473639 | Q66: =IFERROR(Q63-Q65,"") -> 0.068642954 | R66: =IFERROR(R63-R65,"") -> -0.0056216481 | T66: =IFERROR(T63-T65,"") -> -0.0030223373 | U66: =IFERROR(U63-U65,"") -> 0.0098367904 | W66: =IFERROR(W63-W65,"") -> -0.0046073961 | X66: =IFERROR(X63-X65,"") -> -0.011494462 | Z66: =IFERROR(Z63-Z65,"") -> -0.0088509803 | AA66: =IFERROR(AA63-AA65,"") -> 0.0093660079 | AC66: =IFERROR(AC63-AC65,"") -> 0.013033266 | AD66: =IFERROR(AD63-AD65,"") -> 0.0019596724 | AF66: =IFERROR(AF63-AF65,"") -> -0.0058899156 | AJ66: =IFERROR(AJ63-AJ65,"") -> 0.040787943 | AL66: =IFERROR(AL63-AL65,"") -> 0.043400055 | AM66: =IFERROR(AM63-AM65,"") -> 0.0045770626 | AO66: =IFERROR(AO63-AO65,"") -> -0.021106786 | AP66: =IFERROR(AP63-AP65,"") -> -0.0059555504 | AR66: =IFERROR(AR63-AR65,"") -> -0.0019027926 | AS66: =IFERROR(AS63-AS65,"") -> -0.0047333879 | AU66: =IFERROR(AU63-AU65,"") -> -0.013782205 | AV66: =IFERROR(AV63-AV65,"") -> -0.037586083 | AW66: 0 | AX66: =IFERROR(AX63-AX65,"") -> -0.018263388 | AY66: 0 | AZ66: 0 | BA66: 0 | BB66: 0 | BC66: H2/26E: neutral FX input (EUR/USD ~1.12 on 5-Oct-26 vs ~1.16–1.17 in H2/25 would be a tailwind in Q4; H1/26 FX drag was −3.8pp). 2027E+: constant FX. Update as required.
B67: Memo: FY26 revenue growth guidance at constant FX (scenario end-point) | AX67: =CHOOSE(MATCH($BC$2,{"Bull","Base","Bear"},0),$BL$12,$BM$12,$BN$12) -> 0.105 | BC67: FY26 guidance raised to +10% to +11% at constant FX in the H1-26 release (30-Jul-26), from ~+10% (Jan/Feb-26). Bull 11% / Base 10.5% / Bear 10%.
B68: Required H2/26E constant-FX growth to meet the FY26 guidance end-point | AW68: =(AU111*(1+AX67)-AS111*(1+AV65))/AT111-1 -> 0.078535014 | BC68: Formula: (FY25 revenues × (1 + guidance) − H1/25 × (1 + H1/26 constant-FX growth)) ÷ H2/25 − 1.
B69: Retail H2/26E growth before calibration (H1/26 constant-FX trend) % | AW69: =AV18 -> 0.193
B70: Wholesale H2/26E growth before calibration (H1/26 constant-FX trend) % | AW70: =AV27 -> 0.027
B71: Outlook calibration: Δ constant-FX growth applied to retail (H2/26E) | AW71: =(AW68*(AT16+AT25)-AT25*AW70)/AT16-AW69 -> -0.093026778 | BC71: Solves the shift to retail H2/26E growth (vs the H1/26 trend) so that FY26 constant-FX growth = guidance end-point for the active scenario; wholesale held at the H1/26 order-book trend (SS26/FW26 orders already collected).
B72: Check: FY26E constant-FX growth vs guidance end-point (should be 0) | AX72: =ROUND(AX65-AX67,4) -> 0
B73: Memo: 2028 revenue target, 2024–28 plan (~EUR 1.8bn, Jan-26) | AZ73: =$BM$13 -> 1800
B74: Model 2028E revenues vs plan target % | AZ74: =IFERROR(AZ111/AZ73-1,"") -> 0.014745374
B76: COST BUILD — FIRST MARGIN · OPERATING COSTS BY NATURE · D&A (IFRS 16 right-of-use vs other) | BC76: COST BUILD — modelling logic
B78: First margin (revenues − production costs: raw materials net of inventory change + outsourced work) | BC78: FIRST MARGIN — modelling logic
B79: First margin % | C79: =IFERROR(C83/C111,"") -> 0.52036374 | D79: =IFERROR(D83/D111,"") -> 0.57501308 | E79: =IFERROR(E83/E111,"") -> 0.54878315 | F79: =IFERROR(F83/F111,"") -> 0.54107527 | G79: =IFERROR(G83/G111,"") -> 0.60606586 | H79: =IFERROR(H83/H111,"") -> 0.57460771 | I79: =IFERROR(I83/I111,"") -> 0.57822991 | J79: =IFERROR(J83/J111,"") -> 0.61328272 | ... AV79: =IFERROR(AV83/AV111,"") -> 0.7502532 | AW79: =AT79+(AV79-AS79) -> 0.76419541 | AX79: =IFERROR(AX83/AX111,"") -> 0.75736668 | AY79: =CHOOSE(MATCH($BC$2,{"Bull","Base","Bear"},0),$BL$28,$BM$28,$BN$28) -> 0.758 | AZ79: =CHOOSE(MATCH($BC$2,{"Bull","Base","Bear"},0),$BL$29,$BM$29,$BN$29) -> 0.759 | BA79: =CHOOSE(MATCH($BC$2,{"Bull","Base","Bear"},0),$BL$30,$BM$30,$BN$30) -> 0.76 | BB79: =CHOOSE(MATCH($BC$2,{"Bull","Base","Bear"},0),$BL$31,$BM$31,$BN$31) -> 0.76 | BC79: H2/26E: H2/25 margin + H1/26 y/y drift. 2027E–2030E: scenario lever FM_margin.
B80: Production costs (raw materials net of inventory change + outsourced work) | C80: =IF(ISNUMBER(C81),C113+C81,"") -> -55.857 | D80: =IF(ISNUMBER(D81),D113+D81,"") -> -53.624 | E80: =IF(ISNUMBER(E81),E113+E81,"") -> -109.481 | F80: =IF(ISNUMBER(F81),F113+F81,"") -> -62.048 | G80: =IF(ISNUMBER(G81),G113+G81,"") -> -56.773 | H80: =IF(ISNUMBER(H81),H113+H81,"") -> -118.821 | I80: =IF(ISNUMBER(I81),I113+I81,"") -> -66.46 | J80: =IF(ISNUMBER(J81),J113+J81,"") -> -63.772 | ... AV80: =IF(ISNUMBER(AV81),AV113+AV81,"") -> -187.163 | AW80: =-AW111*(1-AW79) -> -184.08342 | AX80: =IF(ISNUMBER(AX81),AX113+AX81,"") -> -371.24642 | AY80: =-AY111*(1-AY79) -> -408.23268 | AZ80: =-AZ111*(1-AZ79) -> -440.19654 | BA80: =-BA111*(1-BA79) -> -472.21299 | BB80: =-BB111*(1-BB79) -> -506.04917
B81: of which outsourced work (within costs for services) | C81: -38.275 | D81: =E81-C81 -> -24.145 | E81: -62.42 | F81: -41.261 | G81: =H81-F81 -> -33.099 | H81: -74.36 | I81: -38.573 | J81: =K81-I81 -> -37.174 | K81: -75.747 | L81: -42.526 | M81: =N81-L81 -> -38.861 | N81: -81.387 | O81: -43.253 | P81: =Q81-O81 -> -39.085 | Q81: -82.338 | R81: -44.834 | S81: =T81-R81 -> -42.171 | T81: -87.005 | U81: -47.912 | V81: =W81-U81 -> -44.899 | W81: -92.811 | X81: -52.057 | Y81: =Z81-X81 -> -49.038 | Z81: -101.095 | AA81: -58.033 | AB81: =AC81-AA81 -> -61.33 | AC81: -119.363 | AD81: -57.277 | AE81: =AF81-AD81 -> -63.731 | AF81: -121.008 | AG81: -57.393 | AH81: =AI81-AG81 -> -62.213 | AI81: -119.606 | AJ81: -83.901 | AK81: =AL81-AJ81 -> -82.291 | AL81: -166.192 | AM81: -100.902 | AN81: =AO81-AM81 -> -98.423 | AO81: -199.325 | AP81: -119.177 | AQ81: =AR81-AP81 -> -104.547 | AR81: -223.724 | AS81: -116.397 | AT81: =AU81-AS81 -> -112.112 | AU81: -228.509 | AV81: -118.596 | AW81: =AW80-AW113 -> -118.0479 | AX81: =AV81+AW81 -> -236.6439 | AY81: =AY80-AY113 -> -260.22009 | AZ81: =AZ80-AZ113 -> -280.59483 | BA81: =BA80-BA113 -> -301.0031 | BB81: =BB80-BB113 -> -322.57132
B82: Raw materials share of production costs % | C82: =IFERROR(C113/C80,"") -> 0.31476807 | D82: =IFERROR(D113/D80,"") -> 0.54973519 | E82: =IFERROR(E113/E80,"") -> 0.42985541 | F82: =IFERROR(F113/F80,"") -> 0.33501483 | G82: =IFERROR(G113/G80,"") -> 0.41699399 | H82: =IFERROR(H113/H80,"") -> 0.3741847 | I82: =IFERROR(I113/I80,"") -> 0.41960578 | J82: =IFERROR(J113/J80,"") -> 0.4170796 | ... AV82: =IFERROR(AV113/AV80,"") -> 0.36634912 | AW82: =AT82 -> 0.35872605 | AX82: =IFERROR(AX113/AX80,"") -> 0.3625692 | AY82: =AX82 -> 0.3625692 | AZ82: =AY82 -> 0.3625692 | BA82: =AZ82 -> 0.3625692 | BB82: =BA82 -> 0.3625692 | BC82: Forecast: prior-year mix (make vs buy).
B83: First margin | C83: =IF(ISNUMBER(C80),C111+C80,"") -> 60.6 | D83: =IF(ISNUMBER(D80),D111+D80,"") -> 72.554 | E83: =IF(ISNUMBER(E80),E111+E80,"") -> 133.154 | F83: =IF(ISNUMBER(F80),F111+F80,"") -> 73.155 | G83: =IF(ISNUMBER(G80),G111+G80,"") -> 87.345 | H83: =IF(ISNUMBER(H80),H111+H80,"") -> 160.5 | I83: =IF(ISNUMBER(I80),I111+I80,"") -> 91.114 | J83: =IF(ISNUMBER(J80),J111+J80,"") -> 101.134 | ... BB83: =IF(ISNUMBER(BB80),BB111+BB80,"") -> 1602.489 | BE83: =IFERROR(IF(AND(BB83>0,AU83>0),(BB83/AU83)^(1/5)-1,"n/m"),"n/m") -> 0.086509992 | BF83: =IFERROR(IF(AND(AU83>0,AF83>0),(AU83/AF83)^(1/5)-1,"n/m"),"n/m") -> 0.23439493 | BG83: =IFERROR(IF(AND(AU83>0,Q83>0),(AU83/Q83)^(1/10)-1,"n/m"),"n/m") -> 0.14796581 | BH83: =IFERROR(IF(AND(AU83>0,E83>0),(AU83/E83)^(1/14)-1,"n/m"),"n/m") -> 0.15959186
B84: Memo: first margin as reported by the company | AM84: 389.04 | AN84: =AO84-AM84 -> 436.712 | AO84: 825.752 | AP84: 462.209 | AQ84: =AR84-AP84 -> 490.807 | AR84: 953.016 | AS84: 509.354 | AT84: =AU84-AS84 -> 548.989 | AU84: 1058.343 | AV84: 562.248
B86: Operating costs by nature (% of revenues) | BC86: OPERATING COSTS — modelling logic
B87: Costs for services excluding outsourced work | C87: =IF(ISNUMBER(C81),C114-C81,"") -> -24.971 | D87: =IF(ISNUMBER(D81),D114-D81,"") -> -28.643 | E87: =IF(ISNUMBER(E81),E114-E81,"") -> -53.614 | F87: =IF(ISNUMBER(F81),F114-F81,"") -> -36.561 | G87: =IF(ISNUMBER(G81),G114-G81,"") -> -38.035 | H87: =IF(ISNUMBER(H81),H114-H81,"") -> -74.596 | I87: =IF(ISNUMBER(I81),I114-I81,"") -> -39.176 | J87: =IF(ISNUMBER(J81),J114-J81,"") -> -41.696 | ... AV87: =IF(ISNUMBER(AV81),AV114-AV81,"") -> -184.645 | AW87: =-AW111*AW88 -> -207.28149 | AX87: =IF(ISNUMBER(AX81),AX114-AX81,"") -> -391.92649 | AY87: =-AY111*AY88 -> -435.22328 | AZ87: =-AZ111*AZ88 -> -469.42121 | BA87: =-BA111*BA88 -> -503.69386 | BB87: =-BB111*BB88 -> -537.67724 | BC87: Rents not in IFRS 16 scope (variable), advertising & commercial, transport & duties, commissions, credit-card fees, other services.
B88: Services ex-outsourced % of revenues | C88: =IFERROR(-C87/C111,"") -> 0.21442249 | D88: =IFERROR(-D87/D111,"") -> 0.22700471 | E88: =IFERROR(-E87/E111,"") -> 0.22096565 | F88: =IFERROR(-F87/F111,"") -> 0.2704156 | G88: =IFERROR(-G87/G111,"") -> 0.26391568 | H88: =IFERROR(-H87/H111,"") -> 0.26706191 | I88: =IFERROR(-I87/I111,"") -> 0.2486197 | J88: =IFERROR(-J87/J111,"") -> 0.25284708 | ... AV88: =IFERROR(-AV87/AV111,"") -> 0.24638683 | AW88: =AT88 -> 0.26552052 | AX88: =IFERROR(-AX87/AX111,"") -> 0.25614907 | AY88: =CHOOSE(MATCH($BC$2,{"Bull","Base","Bear"},0),$BL$34,$BM$34,$BN$34) -> 0.258 | AZ88: =CHOOSE(MATCH($BC$2,{"Bull","Base","Bear"},0),$BL$35,$BM$35,$BN$35) -> 0.257 | BA88: =CHOOSE(MATCH($BC$2,{"Bull","Base","Bear"},0),$BL$36,$BM$36,$BN$36) -> 0.256 | BB88: =CHOOSE(MATCH($BC$2,{"Bull","Base","Bear"},0),$BL$37,$BM$37,$BN$37) -> 0.255 | BC88: H2/26E: H2/25 ratio (no H1 drift: communication spend shifted into H2 per the H1-26 release). 2027E–2030E: scenario lever SVC_ratio.
B89: Memo: Rents in P&L (variable / short-term; outside IFRS 16 from 2019) | C89: 3.461 | D89: =E89-C89 -> 4.637 | E89: 8.098 | F89: 5.509 | G89: =H89-F89 -> 7.486 | H89: 12.995 | I89: 9.164 | J89: =K89-I89 -> 11.349 | K89: 20.513 | L89: 12.629 | M89: =N89-L89 -> 16.426 | N89: 29.055 | O89: 21.996 | P89: =Q89-O89 -> 21.519 | Q89: 43.515 | R89: 26.526 | S89: =T89-R89 -> 28.471 | T89: 54.997 | U89: 28.813 | V89: =W89-U89 -> 30.256 | W89: 59.069 | X89: 34.165 | Y89: =Z89-X89 -> 36.886 | Z89: 71.051 | AA89: 10.31 | AB89: =AC89-AA89 -> 11.5 | AC89: 21.81 | AD89: 4.703 | AE89: =AF89-AD89 -> 13.209 | AF89: 17.912 | AG89: 12.892 | AH89: =AI89-AG89 -> 17.67 | AI89: 30.562 | AJ89: 16.107 | AK89: =AL89-AJ89 -> 22.454 | AL89: 38.561 | AM89: 22.807 | AN89: =AO89-AM89 -> 27.791 | AO89: 50.598 | AP89: 29.213 | AQ89: =AR89-AP89 -> 32.369 | AR89: 61.582 | AS89: 31.801 | AT89: =AU89-AS89 -> 36.481 | AU89: 68.282 | AV89: 36.362
B90: Memo: Rents within IFRS 16 scope (memo — excluded from P&L from 2019) | AA90: 29.362 | AB90: =AC90-AA90 -> 34.206 | AC90: 63.568 | AD90: 39.982 | AE90: =AF90-AD90 -> 38.505 | AF90: 78.487 | AG90: 41.491 | AH90: =AI90-AG90 -> 43.199 | AI90: 84.69 | AJ90: 45.197 | AK90: =AL90-AJ90 -> 49.816 | AL90: 95.013 | AM90: 50.62 | AN90: =AO90-AM90 -> 53.794 | AO90: 104.414 | AP90: 57.995 | AQ90: =AR90-AP90 -> 63.657 | AR90: 121.652 | AS90: 72.862 | AT90: =AU90-AS90 -> 77.804 | AU90: 150.666 | AV90: 80.947
B91: Memo: Advertising & other commercial expenses | C91: 4.664 | D91: =E91-C91 -> 8.088 | E91: 12.752 | F91: 6.477 | G91: =H91-F91 -> 8.906 | H91: 15.383 | I91: 8.085 | J91: =K91-I91 -> 9.722 | K91: 17.807 | L91: 9.046 | M91: =N91-L91 -> 10.516 | N91: 19.562 | O91: 9.641 | P91: =Q91-O91 -> 13.644 | Q91: 23.285 | R91: 11.223 | S91: =T91-R91 -> 13.434 | T91: 24.657 | U91: 12.528 | V91: =W91-U91 -> 16.146 | W91: 28.674 | X91: 14.732 | Y91: =Z91-X91 -> 17.541 | Z91: 32.273 | AA91: 16.223 | AB91: =AC91-AA91 -> 19.247 | AC91: 35.47 | AD91: 13.335 | AE91: =AF91-AD91 -> 18.734 | AF91: 32.069 | AG91: 14.423 | AH91: =AI91-AG91 -> 21.635 | AI91: 36.058 | AJ91: 20.406 | AK91: =AL91-AJ91 -> 31.795 | AL91: 52.201 | AM91: 36.256 | AN91: =AO91-AM91 -> 42.682 | AO91: 78.938 | AP91: 44.633 | AQ91: =AR91-AP91 -> 47.715 | AR91: 92.348 | AS91: 44.421 | AT91: =AU91-AS91 -> 52.432 | AU91: 96.853 | AV91: 45.778
B92: Memo: Transport & duties | C92: 4.533 | D92: =E92-C92 -> 4.833 | E92: 9.366 | F92: 5.512 | G92: =H92-F92 -> 6.538 | H92: 12.05 | I92: 7.222 | J92: =K92-I92 -> 6.536 | K92: 13.758 | L92: 7.908 | M92: =N92-L92 -> 7.2 | N92: 15.108 | O92: 7.457 | P92: =Q92-O92 -> 7.701 | Q92: 15.158 | R92: 7.956 | S92: =T92-R92 -> 8.078 | T92: 16.034 | U92: 8.595 | V92: =W92-U92 -> 8.875 | W92: 17.47 | X92: 9.391 | Y92: =Z92-X92 -> 9.348 | Z92: 18.739 | AA92: 10.409 | AB92: =AC92-AA92 -> 11.741 | AC92: 22.15 | AD92: 9.005 | AE92: =AF92-AD92 -> 14.4 | AF92: 23.405 | AG92: 12.999 | AH92: =AI92-AG92 -> 16.116 | AI92: 29.115 | AJ92: 18.223 | AK92: =AL92-AJ92 -> 24.474 | AL92: 42.697 | AM92: 23.446 | AN92: =AO92-AM92 -> 23.409 | AO92: 46.855 | AP92: 27.884 | AQ92: =AR92-AP92 -> 27.278 | AR92: 55.162 | AS92: 33.905 | AT92: =AU92-AS92 -> 28.512 | AU92: 62.417 | AV92: 30.13
B93: Memo: Commissions & accessory charges | C93: 6.785 | D93: =E93-C93 -> 5.832 | E93: 12.617 | F93: 6.042 | G93: =H93-F93 -> 6.722 | H93: 12.764 | I93: 6.059 | J93: =K93-I93 -> 5.761 | K93: 11.82 | L93: 5.77 | M93: =N93-L93 -> 5.818 | N93: 11.588 | O93: 6.616 | P93: =Q93-O93 -> 6.592 | Q93: 13.208 | R93: 6.061 | S93: =T93-R93 -> 6.737 | T93: 12.798 | U93: 6.205 | V93: =W93-U93 -> 6.496 | W93: 12.701 | X93: 6.584 | Y93: =Z93-X93 -> 5.523 | Z93: 12.107 | AA93: 4.867 | AB93: =AC93-AA93 -> 4.389 | AC93: 9.256 | AD93: 5.912 | AE93: =AF93-AD93 -> 4.723 | AF93: 10.635 | AG93: 4.019 | AH93: =AI93-AG93 -> 3.791 | AI93: 7.81 | AJ93: 3.184 | AK93: =AL93-AJ93 -> 4.06 | AL93: 7.244 | AM93: 4.408 | AN93: =AO93-AM93 -> 5.594 | AO93: 10.002 | AP93: 5.596 | AQ93: =AR93-AP93 -> 5.531 | AR93: 11.127 | AS93: 6.191 | AT93: =AU93-AS93 -> 5.622 | AU93: 11.813 | AV93: 6.124
B94: Memo: Credit-card charges | E94: 1.096 | H94: 1.634 | I94: 0.997 | J94: =K94-I94 -> 1.299 | K94: 2.296 | L94: 1.196 | M94: =N94-L94 -> 1.565 | N94: 2.761 | O94: 1.573 | P94: =Q94-O94 -> 2.066 | Q94: 3.639 | R94: 1.798 | S94: =T94-R94 -> 2.187 | T94: 3.985 | U94: 2.253 | V94: =W94-U94 -> 2.646 | W94: 4.899 | X94: 2.264 | Y94: =Z94-X94 -> 2.737 | Z94: 5.001 | AA94: 2.735 | AB94: =AC94-AA94 -> 3.626 | AC94: 6.361 | AD94: 2.017 | AE94: =AF94-AD94 -> 2.954 | AF94: 4.971 | AG94: 3.075 | AH94: =AI94-AG94 -> 4.902 | AI94: 7.977 | AJ94: 5.074 | AK94: =AL94-AJ94 -> 6.901 | AL94: 11.975 | AM94: 7.557 | AN94: =AO94-AM94 -> 8.135 | AO94: 15.692 | AP94: 8.724 | AQ94: =AR94-AP94 -> 9.574 | AR94: 18.298 | AS94: 9.607 | AT94: =AU94-AS94 -> 10.598 | AU94: 20.205 | AV94: 10.769
B95: Payroll costs | C95: =C115 -> -17.024 | D95: =D115 -> -20.686 | E95: =E115 -> -37.71 | F95: =F115 -> -20.526 | G95: =G115 -> -22.095 | H95: =H115 -> -42.621 | I95: =I115 -> -24.577 | J95: =J115 -> -26.535 | ... AV95: =AV115 -> -138.367 | AW95: =-AW111*AW96 -> -140.74284 | AX95: =AX115 -> -279.10984 | AY95: =-AY111*AY96 -> -305.33106 | AZ95: =-AZ111*AZ96 -> -328.7775 | BA95: =-BA111*BA96 -> -354.15974 | BB95: =-BB111*BB96 -> -377.42834
B96: Payroll % of revenues | C96: =IFERROR(-C95/C111,"") -> 0.14618271 | D96: =IFERROR(-D95/D111,"") -> 0.163943 | E96: =IFERROR(-E95/E111,"") -> 0.15541863 | F96: =IFERROR(-F95/F111,"") -> 0.15181616 | G96: =IFERROR(-G95/G111,"") -> 0.15331187 | H96: =IFERROR(-H95/H111,"") -> 0.15258788 | I96: =IFERROR(-I95/I111,"") -> 0.15597116 | J96: =IFERROR(-J95/J111,"") -> 0.16090985 | ... AV96: =IFERROR(-AV95/AV111,"") -> 0.18463433 | AW96: =AT96+(AV96-AS96) -> 0.18028678 | AX96: =IFERROR(-AX95/AX111,"") -> 0.18241616 | AY96: =CHOOSE(MATCH($BC$2,{"Bull","Base","Bear"},0),$BL$40,$BM$40,$BN$40) -> 0.181 | AZ96: =CHOOSE(MATCH($BC$2,{"Bull","Base","Bear"},0),$BL$41,$BM$41,$BN$41) -> 0.18 | BA96: =CHOOSE(MATCH($BC$2,{"Bull","Base","Bear"},0),$BL$42,$BM$42,$BN$42) -> 0.18 | BB96: =CHOOSE(MATCH($BC$2,{"Bull","Base","Bear"},0),$BL$43,$BM$43,$BN$43) -> 0.179 | BC96: 2027E–2030E: scenario lever PAY_ratio (artisans in boutiques, network growth).
B97: Memo: workforce, period end (FTE / headcount) | C97: 685 | D97: =E97 -> 715.8 | E97: 715.8 | F97: 762 | G97: =H97 -> 804.1 | H97: 804.1 | I97: 974.3 | J97: =K97 -> 1006.6 | K97: 1006.6 | L97: 1170.7 | M97: =N97 -> 1240.8 | N97: 1240.8 | O97: 1352 | P97: =Q97 -> 1364.8 | Q97: 1364.8 | R97: 1423.1 | S97: =T97 -> 1440.2 | T97: 1440.2 | U97: 1570.1 | V97: =W97 -> 1605.4 | W97: 1605.4 | X97: 1693.2 | Y97: =Z97 -> 1735.9 | Z97: 1735.9 | AA97: 1842.1 | AB97: =AC97 -> 1889.8 | AC97: 1889.8 | AD97: 2026.3 | AE97: =AF97 -> 2044.7 | AF97: 2044.7 | AG97: 2127.4 | AH97: =AI97 -> 2160.1 | AI97: 2160.1 | AJ97: 2254.5 | AK97: =AL97 -> 2308.3 | AL97: 2308.3 | AM97: 2531.1 | AN97: =AO97 -> 2623.3 | AO97: 2623.3 | AP97: 3021.1 | AQ97: =AR97 -> 3101.4 | AR97: 3101.4 | AS97: 3283.1 | AT97: =AU97 -> 3327.5 | AU97: 3327.5 | AV97: 3542.9
B98: Other operating (costs) / income, net (other opex + other income + capitalised costs + impairment & accruals) | C98: =C112+C116+C117+N(C119) -> -0.254 | D98: =D112+D116+D117+N(D119) -> -1.416 | E98: =E112+E116+E117+N(E119) -> -1.67 | F98: =F112+F116+F117+N(F119) -> 0.35 | G98: =G112+G116+G117+N(G119) -> -0.764 | H98: =H112+H116+H117+N(H119) -> -0.414 | I98: =I112+I116+I117+N(I119) -> -0.232 | J98: =J112+J116+J117+N(J119) -> -1.851 | ... AV98: =AV112+AV116+AV117+N(AV119) -> -12.694 | AW98: =-AW111*AW99 -> -12.079592 | AX98: =AX112+AX116+AX117+N(AX119) -> -24.773592 | AY98: =-AY111*AY99 -> -25.303679 | AZ98: =-AZ111*AZ99 -> -27.398125 | BA98: =-BA111*BA99 -> -29.513312 | BB98: =-BB111*BB99 -> -31.628073
B99: Other operating costs, net % of revenues | C99: =IFERROR(-C98/C111,"") -> 0.0021810625 | D99: =IFERROR(-D98/D111,"") -> 0.011222242 | E99: =IFERROR(-E98/E111,"") -> 0.0068827663 | F99: =IFERROR(-F98/F111,"") -> -0.0025887 | G99: =IFERROR(-G98/G111,"") -> 0.0053012115 | H99: =IFERROR(-H98/H111,"") -> 0.0014821657 | I99: =IFERROR(-I98/I111,"") -> 0.0014723241 | J99: =IFERROR(-J98/J111,"") -> 0.011224576 | ... AV99: =IFERROR(-AV98/AV111,"") -> 0.016938636 | AW99: =-(AT98+N(AT157))/AT111 -> 0.015473546 | AX99: =IFERROR(-AX98/AX111,"") -> 0.016191129 | AY99: 0.015 | AZ99: 0.015 | BA99: 0.015 | BB99: 0.015 | BC99: Other operating costs net (taxes & duties, donations, bad-debt provisions, net of other income): FY25 1.9% incl. the €8.1m Saks provision (1.4% normalised); 2027E+ 1.5% input.
B100: EBITDA (cost build) | C100: =IF(ISNUMBER(C83),C83+C87+C95+C98,"") -> 18.351 | D100: =IF(ISNUMBER(D83),D83+D87+D95+D98,"") -> 21.809 | E100: =IF(ISNUMBER(E83),E83+E87+E95+E98,"") -> 40.16 | F100: =IF(ISNUMBER(F83),F83+F87+F95+F98,"") -> 16.418 | G100: =IF(ISNUMBER(G83),G83+G87+G95+G98,"") -> 26.451 | H100: =IF(ISNUMBER(H83),H83+H87+H95+H98,"") -> 42.869 | I100: =IF(ISNUMBER(I83),I83+I87+I95+I98,"") -> 27.129 | J100: =IF(ISNUMBER(J83),J83+J87+J95+J98,"") -> 31.052 | ... BB100: =IF(ISNUMBER(BB83),BB83+BB87+BB95+BB98,"") -> 655.75538 | BE100: =IFERROR(IF(AND(BB100>0,AU100>0),(BB100/AU100)^(1/5)-1,"n/m"),"n/m") -> 0.099340116 | BF100: =IFERROR(IF(AND(AU100>0,AF100>0),(AU100/AF100)^(1/5)-1,"n/m"),"n/m") -> 0.35482965 | BG100: =IFERROR(IF(AND(AU100>0,Q100>0),(AU100/Q100)^(1/10)-1,"n/m"),"n/m") -> 0.19438753 | BH100: =IFERROR(IF(AND(AU100>0,E100>0),(AU100/E100)^(1/14)-1,"n/m"),"n/m") -> 0.18018238
B101: Check: cost build vs income-statement EBITDA (should be 0) | C101: =IF(ISNUMBER(C100),ROUND(C100-C136,1),"n/a") -> 0 | D101: =IF(ISNUMBER(D100),ROUND(D100-D136,1),"n/a") -> 0 | E101: =IF(ISNUMBER(E100),ROUND(E100-E136,1),"n/a") -> 0 | F101: =IF(ISNUMBER(F100),ROUND(F100-F136,1),"n/a") -> 0 | G101: =IF(ISNUMBER(G100),ROUND(G100-G136,1),"n/a") -> 0 | H101: =IF(ISNUMBER(H100),ROUND(H100-H136,1),"n/a") -> 0 | I101: =IF(ISNUMBER(I100),ROUND(I100-I136,1),"n/a") -> 0 | J101: =IF(ISNUMBER(J100),ROUND(J100-J136,1),"n/a") -> 0 | ... BB101: =IF(ISNUMBER(BB100),ROUND(BB100-BB136,1),"n/a") -> 0
B103: Depreciation & amortisation (IFRS 16 right-of-use vs property, plant, equipment & intangibles) | BC103: D&A — modelling logic
B104: Depreciation of right-of-use assets (IFRS 16 lease contracts) | AA104: -26.146 | AB104: =AC104-AA104 -> -30.859 | AC104: -57.005 | AD104: -34.126 | AE104: =AF104-AD104 -> -35.326 | AF104: -69.452 | AG104: -39.138 | AH104: =AI104-AG104 -> -42.182 | AI104: -81.32 | AJ104: -43.619 | AK104: =AL104-AJ104 -> -47.383 | AL104: -91.002 | AM104: -44.386 | AN104: =AO104-AM104 -> -47.04 | AO104: -91.426 | AP104: -49.843 | AQ104: =AR104-AP104 -> -54.142 | AR104: -103.985 | AS104: -60.635 | AT104: =AU104-AS104 -> -64.336 | AU104: -124.971 | AV104: -67.449 | AW104: =-AW105*AV262 -> -69.870639 | AX104: =AV104+AW104 -> -137.31964 | AY104: =-AY105*AX262 -> -155.39104 | AZ104: =-AZ105*AY262 -> -163.30482 | BA104: =-BA105*AZ262 -> -171.01585 | BB104: =-BB105*BA262 -> -180.32595 | BC104: Historical: company "exclusion of IFRS 16 effects" on D&A (2019+). Forecast: depreciation rate × opening right-of-use asset.
B105: Right-of-use depreciation rate (% of opening right-of-use asset) | AD105: =IFERROR(-AD104/AC262,"") -> 0.078700063 | AF105: =IFERROR(-AF104/AD262,"") -> 0.15045699 | AG105: =IFERROR(-AG104/AF262,"") -> 0.083237452 | AI105: =IFERROR(-AI104/AG262,"") -> 0.1625558 | AJ105: =IFERROR(-AJ104/AI262,"") -> 0.086379731 | AL105: =IFERROR(-AL104/AJ262,"") -> 0.16054124 | AM105: =IFERROR(-AM104/AL262,"") -> 0.08534686 | AO105: =IFERROR(-AO104/AM262,"") -> 0.18471877 | AP105: =IFERROR(-AP104/AO262,"") -> 0.0994769 | AR105: =IFERROR(-AR104/AP262,"") -> 0.17852054 | AS105: =IFERROR(-AS104/AR262,"") -> 0.09913495 | AU105: =IFERROR(-AU104/AS262,"") -> 0.17154093 | AV105: =IFERROR(-AV104/AU262,"") -> 0.094164901 | AW105: =AV105 -> 0.094164901 | AY105: 0.205 | AZ105: 0.205 | BA105: 0.205 | BB105: 0.205 | BC105: Right-of-use depreciation ≈ 20–21% of the opening right-of-use asset (2024–25 actual: 20.8%, 20.4%); H2/26E: H1/26 half-year rate × 30-Jun-26 asset.
B106: D&A of property, plant & equipment, intangibles & investment property | C106: =C118-N(C104) -> -2.389 | D106: =D118-N(D104) -> -2.864 | E106: =E118-N(E104) -> -5.253 | F106: =F118-N(F104) -> -2.963 | G106: =G118-N(G104) -> -4.162 | H106: =H118-N(H104) -> -7.125 | I106: =I118-N(I104) -> -5.325 | J106: =J118-N(J104) -> -5.9 | ... AV106: =AV118-N(AV104) -> -30.894 | AW106: =-AW111*AV107 -> -32.182258 | AX106: =AX118-N(AX104) -> -63.076258 | AY106: =-AY111*AY107 -> -69.163389 | AZ106: =-AZ111*AZ107 -> -74.888209 | BA106: =-BA111*BA107 -> -78.702165 | BB106: =-BB111*BB107 -> -84.341528
...

Sheet Bull-Base-Bear
B2: Brunello Cucinelli (BC) — Bull / Base / Bear Case P&L Summary | J2: Share price (EUR): | K2: =Model!$AX$384 -> 80.18
B3: Adjusted figures (company-normalised; IFRS 16 basis unless stated) · EUR millions · Live panel linked to Model — toggle scenario on Model!BC2. Bull / Bear panels are value snapshots of the Model run with the switch set to Bull / Bear. | J3: As of: | K3: =TODAY() -> 46301
B5: Scenario: | C5: =Model!$BC$2 -> Base | N5: Scenario: | O5: Bull | P5: Snapshot (values) — Model run with switch = Bull | Z5: Scenario: | AA5: Bear | AB5: Snapshot (values) — Model run with switch = Bear
B7: (EURm, except EPS and shares) | C7: 2025A | D7: 2026E | E7: 2027E | F7: 2028E | G7: 2029E | H7: 2030E | I7: 25-'30 CAGR | J7: LT Hist Avg | K7: LT Hist Min | L7: LT Hist Max | N7: (EURm, except EPS and shares) | O7: 2025A | P7: 2026E | Q7: 2027E | R7: 2028E | S7: 2029E | T7: 2030E | U7: 25-'30 CAGR | V7: LT Hist Avg | W7: LT Hist Min | X7: LT Hist Max | Z7: (EURm, except EPS and shares) | AA7: 2025A | AB7: 2026E | AC7: 2027E | AD7: 2028E | AE7: 2029E | AF7: 2030E | AG7: 25-'30 CAGR | AH7: LT Hist Avg | AI7: LT Hist Min | AJ7: LT Hist Max
B9: Revenues | C9: =Model!AU111 -> 1407.951 | D9: =Model!AX111 -> 1530.0719 | E9: =Model!AY111 -> 1686.9119 | F9: =Model!AZ111 -> 1826.5417 | G9: =Model!BA111 -> 1967.5541 | H9: =Model!BB111 -> 2108.5382 | I9: =IFERROR(IF(AND(H9>0,C9>0),(H9/C9)^(1/5)-1,"n/m"),"n/m") -> 0.084123569 | N9: Revenues | O9: 1407.951 | P9: 1537.1117 | Q9: 1726.467 | R9: 1904.8449 | S9: 2091.0135 | T9: 2283.7481 | U9: 0.10157008 | Z9: Revenues | AA9: 1407.951 | AB9: 1523.0321 | AC9: 1631.9664 | AD9: 1716.8054 | AE9: 1796.5267 | AF9: 1870.0189 | AG9: 0.058404532
B10: Revenues y/y % | D10: =IFERROR(D9/C9-1,"") -> 0.086736612 | E10: =IFERROR(E9/D9-1,"") -> 0.102505 | F10: =IFERROR(F9/E9-1,"") -> 0.082772403 | G10: =IFERROR(G9/F9-1,"") -> 0.077201886 | H10: =IFERROR(H9/G9-1,"") -> 0.071654474 | N10: Revenues y/y % | P10: 0.091736612 | Q10: 0.12318908 | R10: 0.10331957 | S10: 0.097734281 | T10: 0.092172832 | Z10: Revenues y/y % | AB10: 0.081736612 | AC10: 0.071524616 | AD10: 0.051985744 | AE10: 0.046435801 | AF10: 0.04090796
B11: Retail revenues y/y % | C11: =Model!AU17 -> 0.11250137 | D11: =Model!AX17 -> 0.12146824 | E11: =Model!AY17 -> 0.12123656 | F11: =Model!AZ17 -> 0.096426117 | G11: =Model!BA17 -> 0.090049834 | H11: =Model!BB17 -> 0.083762058 | N11: Retail revenues y/y % | O11: 0.11250137 | P11: 0.12890191 | Q11: 0.14209677 | R11: 0.1171134 | S11: 0.11071429 | T11: 0.10440514 | Z11: Retail revenues y/y % | AA11: 0.11250137 | AB11: 0.11403456 | AC11: 0.089946237 | AD11: 0.065395189 | AE11: 0.059053156 | AF11: 0.052797428
B12: Adjusted EBITDA (normalised, IFRS 16) | C12: =Model!AU158 -> 416.463 | D12: =Model!AX158 -> 463.01556 | E12: =Model!AY158 -> 512.82122 | F12: =Model!AZ158 -> 560.74829 | G12: =Model!BA158 -> 607.97423 | H12: =Model!BB158 -> 655.75538 | I12: =IFERROR(IF(AND(H12>0,C12>0),(H12/C12)^(1/5)-1,"n/m"),"n/m") -> 0.095047827 | N12: Adjusted EBITDA (normalised, IFRS 16) | O12: 416.463 | P12: 465.148 | Q12: 550.74298 | R12: 613.36004 | S12: 677.48837 | T12: 744.50189 | U12: 0.12320202 | Z12: Adjusted EBITDA (normalised, IFRS 16) | AA12: 416.463 | AB12: 460.88311 | AC12: 458.58257 | AD12: 487.57274 | AE12: 513.80662 | AF12: 538.56544 | AG12: 0.052767361
B13: Adjusted EBITDA margin % | C13: =IFERROR(C12/C9,"") -> 0.29579367 | D13: =IFERROR(D12/D9,"") -> 0.30261033 | E13: =IFERROR(E12/E9,"") -> 0.304 | F13: =IFERROR(F12/F9,"") -> 0.307 | G13: =IFERROR(G12/G9,"") -> 0.309 | H13: =IFERROR(H12/H9,"") -> 0.311 | J13: =IFERROR(AVERAGE(Model!E159,Model!H159,Model!K159,Model!N159,Model!Q159,Model!T159,Model!W159,Model!Z159,Model!AC159,Model!AF159,Model!AI159,Model!AL159,Model!AO159,Model!AR159,Model!AU159),"") -> 0.22089036 | K13: =IFERROR(MIN(Model!E159,Model!H159,Model!K159,Model!N159,Model!Q159,Model!T159,Model!W159,Model!Z159,Model!AC159,Model!AF159,Model!AI159,Model!AL159,Model!AO159,Model!AR159,Model!AU159),"") -> 0.1655161 | L13: =IFERROR(MAX(Model!E159,Model!H159,Model!K159,Model!N159,Model!Q159,Model!T159,Model!W159,Model!Z159,Model!AC159,Model!AF159,Model!AI159,Model!AL159,Model!AO159,Model!AR159,Model!AU159),"") -> 0.29579367 | N13: Adjusted EBITDA margin % | O13: 0.29579367 | P13: 0.30261172 | Q13: 0.319 | R13: 0.322 | S13: 0.324 | T13: 0.326 | V13: 0.22089036 | W13: 0.1655161 | X13: 0.29579367 | Z13: Adjusted EBITDA margin % | AA13: 0.29579367 | AB13: 0.30260892 | AC13: 0.281 | AD13: 0.284 | AE13: 0.286 | AF13: 0.288 | AH13: 0.22089036 | AI13: 0.1655161 | AJ13: 0.29579367
B15: Operating Income — EBIT (IFRS) | C15: =Model!AU120 -> 227.784 | D15: =Model!AX120 -> 262.61966 | E15: =Model!AY120 -> 288.2668 | F15: =Model!AZ120 -> 322.55526 | G15: =Model!BA120 -> 358.25621 | H15: =Model!BB120 -> 391.0879 | I15: =IFERROR(IF(AND(H15>0,C15>0),(H15/C15)^(1/5)-1,"n/m"),"n/m") -> 0.11416685 | N15: Operating Income — EBIT (IFRS) | O15: 227.784 | P15: 264.4619 | Q15: 324.40805 | R15: 370.89787 | S15: 420.22457 | T15: 467.96912 | U15: 0.15488515 | Z15: Operating Income — EBIT (IFRS) | AA15: 227.784 | AB15: 260.77743 | AC15: 236.43965 | AD15: 255.30044 | AE15: 274.53439 | AF15: 290.16113 | AG15: 0.049598506
B16: EBIT y/y % | D16: =IFERROR(D15/C15-1,"") -> 0.15293287 | E16: =IFERROR(E15/D15-1,"") -> 0.097658862 | F16: =IFERROR(F15/E15-1,"") -> 0.11894698 | G16: =IFERROR(G15/F15-1,"") -> 0.11068166 | H16: =IFERROR(H15/G15-1,"") -> 0.091643047 | N16: EBIT y/y % | P16: 0.16102051 | Q16: 0.22667218 | R16: 0.14330661 | S16: 0.13299268 | T16: 0.11361674 | Z16: EBIT y/y % | AB16: 0.14484523 | AC16: -0.093327758 | AD16: 0.079769972 | AE16: 0.075338493 | AF16: 0.056920893
B17: Operating margin (IFRS) % | C17: =IFERROR(C15/C9,"") -> 0.16178404 | D17: =IFERROR(D15/D9,"") -> 0.17163877 | E17: =IFERROR(E15/E9,"") -> 0.17088432 | F17: =IFERROR(F15/F9,"") -> 0.17659343 | G17: =IFERROR(G15/G9,"") -> 0.18208201 | H17: =IFERROR(H15/H9,"") -> 0.18547822 | J17: =IFERROR(AVERAGE(Model!E121,Model!H121,Model!K121,Model!N121,Model!Q121,Model!T121,Model!W121,Model!Z121,Model!AC121,Model!AF121,Model!AI121,Model!AL121,Model!AO121,Model!AR121,Model!AU121),"") -> 0.1275804 | K17: =IFERROR(MIN(Model!E121,Model!H121,Model!K121,Model!N121,Model!Q121,Model!T121,Model!W121,Model!Z121,Model!AC121,Model!AF121,Model!AI121,Model!AL121,Model!AO121,Model!AR121,Model!AU121),"") -> -0.02723832 | L17: =IFERROR(MAX(Model!E121,Model!H121,Model!K121,Model!N121,Model!Q121,Model!T121,Model!W121,Model!Z121,Model!AC121,Model!AF121,Model!AI121,Model!AL121,Model!AO121,Model!AR121,Model!AU121),"") -> 0.16555681 | N17: Operating margin (IFRS) % | O17: 0.16178404 | P17: 0.17205119 | Q17: 0.18790284 | R17: 0.1947129 | S17: 0.20096693 | T17: 0.20491275 | V17: 0.1275804 | W17: -0.02723832 | X17: 0.16555681 | Z17: Operating margin (IFRS) % | AA17: 0.16178404 | AB17: 0.17122254 | AC17: 0.14488022 | AD17: 0.14870668 | AE17: 0.15281398 | AF17: 0.15516481 | AH17: 0.1275804 | AI17: -0.02723832 | AJ17: 0.16555681
B19: Adjusted Net Profit (attributable to BC shareholders) | C19: =Model!AU184 -> 140.79871 | D19: =Model!AX184 -> 155.41683 | E19: =Model!AY184 -> 169.57534 | F19: =Model!AZ184 -> 192.34758 | G19: =Model!BA184 -> 216.48774 | H19: =Model!BB184 -> 238.64752 | I19: =IFERROR(IF(AND(H19>0,C19>0),(H19/C19)^(1/5)-1,"n/m"),"n/m") -> 0.11130085 | N19: Adjusted Net Profit (attributable to BC shareholders) | O19: 140.79871 | P19: 156.67602 | Q19: 194.36404 | R19: 225.6711 | S19: 259.22548 | T19: 291.6446 | U19: 0.15678075 | Z19: Adjusted Net Profit (attributable to BC shareholders) | AA19: 140.79871 | AB19: 154.15764 | AC19: 134.01986 | AD19: 145.96631 | AE19: 158.73363 | AF19: 169.06124 | AG19: 0.037263442
B21: Shares outstanding (m, weighted average) | C21: =Model!AU138 -> 67.975949 | D21: =Model!AX138 -> 68 | E21: =Model!AY138 -> 68 | F21: =Model!AZ138 -> 68 | G21: =Model!BA138 -> 68 | H21: =Model!BB138 -> 68 | I21: =IFERROR(IF(AND(H21>0,C21>0),(H21/C21)^(1/5)-1,"n/m"),"n/m") -> 7.0753251e-05 | N21: Shares outstanding (m, weighted average) | O21: 67.975949 | P21: 68 | Q21: 68 | R21: 68 | S21: 68 | T21: 68 | U21: 7.0753251e-05 | Z21: Shares outstanding (m, weighted average) | AA21: 67.975949 | AB21: 68 | AC21: 68 | AD21: 68 | AE21: 68 | AF21: 68 | AG21: 7.0753251e-05
B23: Adjusted EPS — basic & diluted (EUR) | C23: =Model!AU188 -> 2.0713019 | D23: =Model!AX188 -> 2.2855416 | E23: =Model!AY188 -> 2.4937551 | F23: =Model!AZ188 -> 2.8286409 | G23: =Model!BA188 -> 3.1836433 | H23: =Model!BB188 -> 3.5095223 | I23: =IFERROR(IF(AND(H23>0,C23>0),(H23/C23)^(1/5)-1,"n/m"),"n/m") -> 0.11122223 | N23: Adjusted EPS — basic & diluted (EUR) | O23: 2.0713019 | P23: 2.3040591 | Q23: 2.8582946 | R23: 3.3186927 | S23: 3.8121394 | T23: 4.2888912 | U23: 0.15669891 | Z23: Adjusted EPS — basic & diluted (EUR) | AA23: 2.0713019 | AB23: 2.2670241 | AC23: 1.9708803 | AD23: 2.1465634 | AE23: 2.334318 | AF23: 2.4861947 | AG23: 0.037190057
B24: EPS y/y % | D24: =IFERROR(D23/C23-1,"") -> 0.10343238 | E24: =IFERROR(E23/D23-1,"") -> 0.091100284 | F24: =IFERROR(F23/E23-1,"") -> 0.13428978 | G24: =IFERROR(G23/F23-1,"") -> 0.12550281 | H24: =IFERROR(H23/G23-1,"") -> 0.10236042 | N24: EPS y/y % | P24: 0.11237242 | Q24: 0.24054744 | R24: 0.16107437 | S24: 0.14868709 | T24: 0.12506148 | Z24: EPS y/y % | AB24: 0.094492337 | AC24: -0.13063108 | AD24: 0.08913942 | AE24: 0.08746756 | AF24: 0.065062521
B26: P / E (x) — assumed (adjusted EPS) | G26: 35 | H26: 35 | N26: P / E (x) — assumed (adjusted EPS) | S26: 40 | T26: 40 | Z26: P / E (x) — assumed (adjusted EPS) | AE26: 28 | AF26: 28
B27: Price Target (EUR) | G27: =G26*G23 -> 111.42752 | H27: =H26*H23 -> 122.83328 | N27: Price Target (EUR) | S27: =S26*S23 -> 152.48558 | T27: =T26*T23 -> 171.55565 | Z27: Price Target (EUR) | AE27: =AE26*AE23 -> 65.360905 | AF27: =AF26*AF23 -> 69.61345
B28: Upside / (Downside) vs current | G28: =IFERROR(G27/$K$2-1,"") -> 0.38971707 | H28: =IFERROR(H27/$K$2-1,"") -> 0.5319691 | N28: Upside / (Downside) vs current | S28: =IFERROR(S27/$K$2-1,"") -> 0.90179068 | T28: =IFERROR(T27/$K$2-1,"") -> 1.1396314 | Z28: Upside / (Downside) vs current | AE28: =IFERROR(AE27/$K$2-1,"") -> -0.18482284 | AF28: =IFERROR(AF27/$K$2-1,"") -> -0.13178536
B29: IRR (to Dec-Y-1) | G29: =IFERROR((G27/$K$2)^(1/((DATE(2029-1,12,31)-$K$3)/365.25))-1,"") -> 0.15850262 | H29: =IFERROR((H27/$K$2)^(1/((DATE(2030-1,12,31)-$K$3)/365.25))-1,"") -> 0.14089094 | N29: IRR (to Dec-Y-1) | S29: =IFERROR((S27/$K$2)^(1/((DATE(2029-1,12,31)-$K$3)/365.25))-1,"") -> 0.33291716 | T29: =IFERROR((T27/$K$2)^(1/((DATE(2030-1,12,31)-$K$3)/365.25))-1,"") -> 0.2649638 | Z29: IRR (to Dec-Y-1) | AE29: =IFERROR((AE27/$K$2)^(1/((DATE(2029-1,12,31)-$K$3)/365.25))-1,"") -> -0.087308289 | AF29: =IFERROR((AF27/$K$2)^(1/((DATE(2030-1,12,31)-$K$3)/365.25))-1,"") -> -0.042728448
B31: Free Cash Flow after lease payments | C31: =Model!AU240 -> -12.982 | D31: =Model!AX240 -> 120.86336 | E31: =Model!AY240 -> 100.86355 | F31: =Model!AZ240 -> 123.79637 | G31: =Model!BA240 -> 143.13626 | H31: =Model!BB240 -> 163.08211 | I31: =IFERROR(IF(AND(H31>0,C31>0),(H31/C31)^(1/5)-1,"n/m"),"n/m") -> n/m | N31: Free Cash Flow after lease payments | O31: -12.982 | P31: 120.10256 | Q31: 113.21331 | R31: 147.23024 | S31: 173.64111 | T31: 201.44633 | U31: n/m | Z31: Free Cash Flow after lease payments | AA31: -12.982 | AB31: 121.62417 | AC31: 83.310703 | AD31: 91.03617 | AE31: 101.69085 | AF31: 112.39538 | AG31: n/m
B32: FCF % | C32: =IFERROR(C31/C9,"") -> -0.0092204913 | D32: =IFERROR(D31/D9,"") -> 0.078991951 | E32: =IFERROR(E31/E9,"") -> 0.059791828 | F32: =IFERROR(F31/F9,"") -> 0.067776373 | G32: =IFERROR(G31/G9,"") -> 0.072748319 | H32: =IFERROR(H31/H9,"") -> 0.077343681 | J32: =IFERROR(AVERAGE(Model!E242,Model!H242,Model!K242,Model!N242,Model!Q242,Model!T242,Model!W242,Model!Z242,Model!AC242,Model!AF242,Model!AI242,Model!AL242,Model!AO242,Model!AR242,Model!AU242),"") -> 0.01037891 | K32: =IFERROR(MIN(Model!E242,Model!H242,Model!K242,Model!N242,Model!Q242,Model!T242,Model!W242,Model!Z242,Model!AC242,Model!AF242,Model!AI242,Model!AL242,Model!AO242,Model!AR242,Model!AU242),"") -> -0.11541636 | L32: =IFERROR(MAX(Model!E242,Model!H242,Model!K242,Model!N242,Model!Q242,Model!T242,Model!W242,Model!Z242,Model!AC242,Model!AF242,Model!AI242,Model!AL242,Model!AO242,Model!AR242,Model!AU242),"") -> 0.11571357 | N32: FCF % | O32: -0.0092204913 | P32: 0.078135222 | Q32: 0.065575136 | R32: 0.077292508 | S32: 0.0830416 | T32: 0.088208645 | V32: 0.01037891 | W32: -0.11541636 | X32: 0.11571357 | Z32: FCF % | AA32: -0.0092204913 | AB32: 0.0798566 | AC32: 0.051049275 | AD32: 0.053026493 | AE32: 0.05660414 | AF32: 0.060103872 | AH32: 0.01037891 | AI32: -0.11541636 | AJ32: 0.11571357
B33: FCF / share (EUR) | C33: =IFERROR(C31/C21,"") -> -0.19097931 | D33: =IFERROR(D31/D21,"") -> 1.7774024 | E33: =IFERROR(E31/E21,"") -> 1.4832875 | F33: =IFERROR(F31/F21,"") -> 1.8205349 | G33: =IFERROR(G31/G21,"") -> 2.104945 | H33: =IFERROR(H31/H21,"") -> 2.3982663 | N33: FCF / share (EUR) | O33: -0.19097931 | P33: 1.7662141 | Q33: 1.6649016 | R33: 2.1651505 | S33: 2.5535457 | T33: 2.962446 | Z33: FCF / share (EUR) | AA33: -0.19097931 | AB33: 1.7885907 | AC33: 1.2251574 | AD33: 1.3387672 | AE33: 1.4954536 | AF33: 1.6528732
B34: FCF Yield (on PT) | G34: =IFERROR(G33/G$27,"") -> 0.018890711 | H34: =IFERROR(H33/H$27,"") -> 0.019524564 | N34: FCF Yield (on PT) | S34: =IFERROR(S33/S$27,"") -> 0.016746146 | T34: =IFERROR(T33/T$27,"") -> 0.017268134 | Z34: FCF Yield (on PT) | AE34: =IFERROR(AE33/AE$27,"") -> 0.022879941 | AF34: =IFERROR(AF33/AF$27,"") -> 0.02374359
B35: Adjusted EBITDA pre-IFRS 16 (comparable with 2011–18) | C35: =Model!AU162 -> 265.797 | D35: =Model!AX162 -> 297.75718 | E35: =Model!AY162 -> 323.93009 | F35: =Model!AZ162 -> 362.39922 | G35: =Model!BA162 -> 400.40954 | H35: =Model!BB162 -> 437.06399 | I35: =IFERROR(IF(AND(H35>0,C35>0),(H35/C35)^(1/5)-1,"n/m"),"n/m") -> 0.10458462 | N35: Adjusted EBITDA pre-IFRS 16 (comparable with 2011–18) | O35: 265.797 | P35: 299.12933 | Q35: 361.69254 | R35: 413.77609 | S35: 466.83792 | T35: 520.03632 | U35: 0.14365945 | Z35: Adjusted EBITDA pre-IFRS 16 (comparable with 2011–18) | AA35: 265.797 | AB35: 296.38503 | AC35: 269.85075 | AD35: 290.89218 | AE35: 310.51956 | AF35: 327.87772 | AG35: 0.042875263
B36: Adjusted EBITDA pre-IFRS 16 % of revenues | C36: =IFERROR(C35/C9,"") -> 0.18878285 | D36: =IFERROR(D35/D9,"") -> 0.19460339 | E36: =IFERROR(E35/E9,"") -> 0.19202549 | F36: =IFERROR(F35/F9,"") -> 0.19840731 | G36: =IFERROR(G35/G9,"") -> 0.20350624 | H36: =IFERROR(H35/H9,"") -> 0.20728294 | J36: =IFERROR(AVERAGE(Model!E163,Model!H163,Model!K163,Model!N163,Model!Q163,Model!T163,Model!W163,Model!Z163,Model!AC163,Model!AF163,Model!AI163,Model!AL163,Model!AO163,Model!AR163,Model!AU163),"") -> 0.17048322 | K36: =IFERROR(MIN(Model!E163,Model!H163,Model!K163,Model!N163,Model!Q163,Model!T163,Model!W163,Model!Z163,Model!AC163,Model!AF163,Model!AI163,Model!AL163,Model!AO163,Model!AR163,Model!AU163),"") -> 0.076761033 | L36: =IFERROR(MAX(Model!E163,Model!H163,Model!K163,Model!N163,Model!Q163,Model!T163,Model!W163,Model!Z163,Model!AC163,Model!AF163,Model!AI163,Model!AL163,Model!AO163,Model!AR163,Model!AU163),"") -> 0.20210195 | N36: Adjusted EBITDA pre-IFRS 16 % of revenues | O36: 0.18878285 | P36: 0.19460482 | Q36: 0.20949867 | R36: 0.21722299 | S36: 0.22325916 | T36: 0.22771177 | V36: 0.17048322 | W36: 0.076761033 | X36: 0.20210195 | Z36: Adjusted EBITDA pre-IFRS 16 % of revenues | AA36: 0.18878285 | AB36: 0.19460195 | AC36: 0.16535312 | AD36: 0.16943806 | AE36: 0.17284439 | AF36: 0.17533391 | AH36: 0.17048322 | AI36: 0.076761033 | AJ36: 0.20210195
B38: Net Financial Debt (core, excl. leases) | C38: =Model!AU300 -> 198.365 | D38: =Model!AX300 -> 139.85164 | E38: =Model!AY300 -> 127.50809 | F38: =Model!AZ300 -> 99.711718 | G38: =Model!BA300 -> 63.455461 | H38: =Model!BB300 -> 19.493356 | I38: =IFERROR(IF(AND(H38>0,C38>0),(H38/C38)^(1/5)-1,"n/m"),"n/m") -> -0.37124086 | N38: Net Financial Debt (core, excl. leases) | O38: 198.365 | P38: 140.61244 | Q38: 116.59913 | R38: 77.608893 | S38: 27.847788 | T38: -32.718541 | U38: n/m | Z38: Net Financial Debt (core, excl. leases) | AA38: 198.365 | AB38: 139.09083 | AC38: 143.62013 | AD38: 130.90396 | AE38: 112.97311 | AF38: 91.137736 | AG38: -0.14405347
B39: Net financial debt / Adjusted EBITDA pre-IFRS 16 (x) | C39: =IFERROR(C38/C35,"") -> 0.74630263 | D39: =IFERROR(D38/D35,"") -> 0.4696835 | E39: =IFERROR(E38/E35,"") -> 0.39362841 | F39: =IFERROR(F38/F35,"") -> 0.2751433 | G39: =IFERROR(G38/G35,"") -> 0.15847639 | H39: =IFERROR(H38/H35,"") -> 0.04460069 | N39: Net financial debt / Adjusted EBITDA pre-IFRS 16 (x) | O39: 0.74630263 | P39: 0.47007239 | Q39: 0.32237085 | R39: 0.18756254 | S39: 0.059651941 | T39: -0.062915876 | Z39: Net financial debt / Adjusted EBITDA pre-IFRS 16 (x) | AA39: 0.74630263 | AB39: 0.46929102 | AC39: 0.53222061 | AD39: 0.45000852 | AE39: 0.36381964 | AF39: 0.27796258
B41: ROIC | C41: =Model!AU361 -> 0.10876679 | D41: =Model!AX361 -> 0.11504936 | E41: =Model!AY361 -> 0.11847993 | F41: =Model!AZ361 -> 0.12440728 | G41: =Model!BA361 -> 0.12926627 | H41: =Model!BB361 -> 0.1326399 | J41: =IFERROR(AVERAGE(Model!E361,Model!H361,Model!K361,Model!N361,Model!Q361,Model!T361,Model!W361,Model!Z361,Model!AC361,Model!AF361,Model!AI361,Model!AL361,Model!AO361,Model!AR361,Model!AU361),"") -> 0.14327853 | K41: =IFERROR(MIN(Model!E361,Model!H361,Model!K361,Model!N361,Model!Q361,Model!T361,Model!W361,Model!Z361,Model!AC361,Model!AF361,Model!AI361,Model!AL361,Model!AO361,Model!AR361,Model!AU361),"") -> 0.018513493 | L41: =IFERROR(MAX(Model!E361,Model!H361,Model!K361,Model!N361,Model!Q361,Model!T361,Model!W361,Model!Z361,Model!AC361,Model!AF361,Model!AI361,Model!AL361,Model!AO361,Model!AR361,Model!AU361),"") -> 0.26386811 | N41: ROIC | O41: 0.10876679 | P41: 0.11570786 | Q41: 0.13182264 | R41: 0.14012137 | S41: 0.14689853 | T41: 0.1519296 | V41: 0.14327853 | W41: 0.018513493 | X41: 0.26386811 | Z41: ROIC | AA41: 0.10876679 | AB41: 0.11438916 | AC41: 0.098752737 | AD41: 0.10141818 | AE41: 0.10365334 | AF41: 0.10477011 | AH41: 0.14327853 | AI41: 0.018513493 | AJ41: 0.26386811
B42: RONTA | C42: =Model!AU372 -> 0.096346132 | D42: =Model!AX372 -> 0.10523115 | E42: =Model!AY372 -> 0.10901119 | F42: =Model!AZ372 -> 0.1150642 | G42: =Model!BA372 -> 0.12019182 | H42: =Model!BB372 -> 0.12390457 | J42: =IFERROR(AVERAGE(Model!E372,Model!H372,Model!K372,Model!N372,Model!Q372,Model!T372,Model!W372,Model!Z372,Model!AC372,Model!AF372,Model!AI372,Model!AL372,Model!AO372,Model!AR372,Model!AU372),"") -> 0.12564941 | K42: =IFERROR(MIN(Model!E372,Model!H372,Model!K372,Model!N372,Model!Q372,Model!T372,Model!W372,Model!Z372,Model!AC372,Model!AF372,Model!AI372,Model!AL372,Model!AO372,Model!AR372,Model!AU372),"") -> 0.017232995 | L42: =IFERROR(MAX(Model!E372,Model!H372,Model!K372,Model!N372,Model!Q372,Model!T372,Model!W372,Model!Z372,Model!AC372,Model!AF372,Model!AI372,Model!AL372,Model!AO372,Model!AR372,Model!AU372),"") -> 0.25139736 | N42: RONTA | O42: 0.096346132 | P42: 0.10584244 | Q42: 0.1213956 | R42: 0.1297975 | S42: 0.13688908 | T42: 0.14233265 | V42: 0.12564941 | W42: 0.017232995 | X42: 0.25139736 | Z42: RONTA | AA42: 0.096346132 | AB42: 0.10461838 | AC42: 0.090744366 | AD42: 0.093590568 | AE42: 0.096059896 | AF42: 0.097446286 | AH42: 0.12564941 | AI42: 0.017232995 | AJ42: 0.25139736
B44: Implied Market Cap (EURm) | G44: =G27*G21 -> 7577.071 | H44: =H27*H21 -> 8352.6632 | N44: Implied Market Cap (EURm) | S44: =S27*S21 -> 10369.019 | T44: =T27*T21 -> 11665.784 | Z44: Implied Market Cap (EURm) | AE44: =AE27*AE21 -> 4444.5415 | AF44: =AF27*AF21 -> 4733.7146
B45: (+) Net financial debt, lease liabilities & NCI | G45: =G38+Model!BA304+Model!BA278 -> 1058.3339 | H45: =H38+Model!BB304+Model!BB278 -> 1062.386 | N45: (+) Net financial debt, lease liabilities & NCI | S45: 1049.9127 | T45: 1053.1089 | Z45: (+) Net financial debt, lease liabilities & NCI | AE45: 1069.9468 | AF45: 1074.904
B46: Implied Enterprise Value (EURm; IFRS 16 basis) | G46: =G44+G45 -> 8635.4049 | H46: =H44+H45 -> 9415.0492 | N46: Implied Enterprise Value (EURm; IFRS 16 basis) | S46: =S44+S45 -> 11418.932 | T46: =T44+T45 -> 12718.893 | Z46: Implied Enterprise Value (EURm; IFRS 16 basis) | AE46: =AE44+AE45 -> 5514.4883 | AF46: =AF44+AF45 -> 5808.6186
B47: Implied EV / Adjusted EBITDA (x) | G47: =IFERROR(G46/G12,"") -> 14.203571 | H47: =IFERROR(H46/H12,"") -> 14.357563 | N47: Implied EV / Adjusted EBITDA (x) | S47: =IFERROR(S46/S12,"") -> 16.854801 | T47: =IFERROR(T46/T12,"") -> 17.083762 | Z47: Implied EV / Adjusted EBITDA (x) | AE47: =IFERROR(AE46/AE12,"") -> 10.732614 | AF47: =IFERROR(AF46/AF12,"") -> 10.785353

Sheet DCF
B2: DCF VALUATION — BRUNELLO CUCINELLI (BC)
B4: 1. WACC BUILD (EUR)
B5: Risk-free rate (EUR 10Y) | C5: 0.0325 | D5: EUR 10Y swap / Bund-BTP blend ~3.0–3.5%; update to market
B6: Equity risk premium | C6: 0.055 | D6: Mature-market ERP ~4.5% + Italy country premium ~1.0% (Damodaran)
B7: Levered beta | C7: 1.05 | D7: European luxury peers (Hermès, Moncler, Prada, Zegna, Kering) ~0.9–1.2; high-end positioning and low leverage
B8: Cost of equity | C8: =C5+C7*C6 -> 0.09025
B9: Pre-tax cost of debt | C9: 0.04 | D9: Unrated; bank loans at Euribor + spread (FY25 loan interest ~3.1% of average bank debt)
B10: Tax rate | C10: 0.285 | D10: Model 2027E+ effective tax rate (IRES 24% + IRAP 3.9%)
B11: After-tax cost of debt | C11: =C9*(1-C10) -> 0.0286
B12: Target D/V | C12: 0.03 | D12: Core net financial debt ~€140m at YE2026E vs ~€5.5bn market cap; leases treated as operating costs (pre-IFRS 16 DCF)
B13: WACC | C13: =C8*(1-C12)+C11*C12 -> 0.0884005
B15: Valuation date (live) | C15: =TODAY() -> 46301 | D15: Periods = (Dec-31-Year − today) / 365.25; cash flows assumed at period end. Valuation from the 30-Jun-26 balance sheet: H2/26E is the first explicit period.
B16: 2. UNLEVERED FREE CASH FLOW BUILD — pre-IFRS 16 basis (rents as operating costs; EURm)
D17: H2/26E | E17: 2027E | F17: 2028E | G17: 2029E | H17: 2030E | I17: 2031E | J17: 2032E | K17: 2033E | L17: 2034E | M17: 2035E | N17: Terminal
B18: Adjusted EBIT pre-IFRS 16 | D18: =Model!AW173 -> 119.97992 | E18: =Model!AY173 -> 254.7667 | F18: =Model!AZ173 -> 287.51102 | G18: =Model!BA173 -> 321.70738 | H18: =Model!BB173 -> 352.72246 | I18: =H18*(1+I$26) -> 377.41304 | J18: =I18*(1+J$26) -> 401.47312 | K18: =J18*(1+K$26) -> 424.55782 | L18: =K18*(1+L$26) -> 446.31641 | M18: =L18*(1+M$26) -> 466.40065
B19: × (1 − tax rate) | D19: =1-$C$10 -> 0.715 | E19: =1-$C$10 -> 0.715 | F19: =1-$C$10 -> 0.715 | G19: =1-$C$10 -> 0.715 | H19: =1-$C$10 -> 0.715 | I19: =1-$C$10 -> 0.715 | J19: =1-$C$10 -> 0.715 | K19: =1-$C$10 -> 0.715 | ... M19: =1-$C$10 -> 0.715
B20: NOPAT | D20: =D18*D19 -> 85.785644 | E20: =E18*E19 -> 182.15819 | F20: =F18*F19 -> 205.57038 | G20: =G18*G19 -> 230.02077 | H20: =H18*H19 -> 252.19656 | I20: =I18*I19 -> 269.85032 | J20: =J18*J19 -> 287.05328 | K20: =K18*K19 -> 303.55884 | ... M20: =M18*M19 -> 333.47646
B21: plus D&A excl. right-of-use | D21: =-Model!AW106 -> 32.182258 | E21: =-Model!AY106 -> 69.163389 | F21: =-Model!AZ106 -> 74.888209 | G21: =-Model!BA106 -> 78.702165 | H21: =-Model!BB106 -> 84.341528 | I21: =H21*(1+I$26) -> 90.245435 | J21: =I21*(1+J$26) -> 95.998581 | K21: =J21*(1+K$26) -> 101.5185 | L21: =K21*(1+L$26) -> 106.72132 | M21: =L21*(1+M$26) -> 111.52378
B22: − Capex (PP&E + intangibles) | D22: =Model!AW221+Model!AW222 -> -39.946 | E22: =Model!AY221+Model!AY222 -> -109.64927 | F22: =Model!AZ221+Model!AZ222 -> -118.72521 | G22: =Model!BA221+Model!BA222 -> -127.89102 | H22: =Model!BB221+Model!BB222 -> -137.05498 | I22: =H22*(1+I$26) -> -146.64883 | J22: =I22*(1+J$26) -> -155.99769 | K22: =J22*(1+K$26) -> -164.96756 | L22: =K22*(1+L$26) -> -173.42215 | M22: =L22*(1+M$26) -> -181.22615
B23: − Δ Working capital (CF statement) | D23: =Model!AW216+Model!AW217+Model!AW218 -> 10.826066 | E23: =Model!AY216+Model!AY217+Model!AY218 -> -35.291551 | F23: =Model!AZ216+Model!AZ217+Model!AZ218 -> -32.728693 | G23: =Model!BA216+Model!BA217+Model!BA218 -> -33.182956 | H23: =Model!BB216+Model!BB217+Model!BB218 -> -32.795606 | I23: =H23*(1+I$26) -> -35.091299 | J23: =I23*(1+J$26) -> -37.328369 | K23: =J23*(1+K$26) -> -39.47475 | L23: =K23*(1+L$26) -> -41.497831 | M23: =L23*(1+M$26) -> -43.365233
B24: Unlevered FCF | D24: =D20+D21+D22+D23 -> 88.847968 | E24: =E20+E21+E22+E23 -> 106.38076 | F24: =F20+F21+F22+F23 -> 129.00468 | G24: =G20+G21+G22+G23 -> 147.64897 | H24: =H20+H21+H22+H23 -> 166.6875 | I24: =I20+I21+I22+I23 -> 178.35563 | J24: =J20+J21+J22+J23 -> 189.7258 | K24: =K20+K21+K22+K23 -> 200.63503 | ... M24: =M20+M21+M22+M23 -> 220.40887 | N24: =M24*(1+$C$27) -> 227.02113
B25: Terminal Value (Gordon Growth) | N25: =N24/($C$13-$C$27) -> 3887.3149
B26: Fade-period growth (2031E–35E; 7% → 4.5% linear) | I26: 0.07 | J26: =I26+($M$26-$I$26)/4 -> 0.06375 | K26: =J26+($M$26-$I$26)/4 -> 0.0575 | L26: =K26+($M$26-$I$26)/4 -> 0.05125 | M26: 0.045
B27: Terminal growth rate | C27: 0.03
B29: Discount period (years) | D29: =MAX(0,(DATE(2026,12,31)-$C$15)/365.25) -> 0.23545517 | E29: =MAX(0,(DATE(2027,12,31)-$C$15)/365.25) -> 1.2347707 | F29: =MAX(0,(DATE(2028,12,31)-$C$15)/365.25) -> 2.2368241 | G29: =MAX(0,(DATE(2029,12,31)-$C$15)/365.25) -> 3.2361396 | H29: =MAX(0,(DATE(2030,12,31)-$C$15)/365.25) -> 4.2354552 | I29: =MAX(0,(DATE(2031,12,31)-$C$15)/365.25) -> 5.2347707 | J29: =MAX(0,(DATE(2032,12,31)-$C$15)/365.25) -> 6.2368241 | K29: =MAX(0,(DATE(2033,12,31)-$C$15)/365.25) -> 7.2361396 | L29: =MAX(0,(DATE(2034,12,31)-$C$15)/365.25) -> 8.2354552 | M29: =MAX(0,(DATE(2035,12,31)-$C$15)/365.25) -> 9.2347707 | N29: =M29 -> 9.2347707
B30: Discount factor | D30: =1/(1+$C$13)^D29 -> 0.98025237 | E30: =1/(1+$C$13)^E29 -> 0.90068795 | F30: =1/(1+$C$13)^F29 -> 0.82738964 | G30: =1/(1+$C$13)^G29 -> 0.76023266 | H30: =1/(1+$C$13)^H29 -> 0.69852664 | I30: =1/(1+$C$13)^I29 -> 0.64182912 | J30: =1/(1+$C$13)^J29 -> 0.58959684 | K30: =1/(1+$C$13)^K29 -> 0.54174086 | ... N30: =1/(1+$C$13)^N29 -> 0.45736665
B31: PV of UFCF | D31: =D24*D30 -> 87.093432 | E31: =E24*E30 -> 95.815866 | F31: =F24*F30 -> 106.73714 | G31: =G24*G30 -> 112.24757 | H31: =H24*H30 -> 116.43566 | I31: =I24*I30 -> 114.47384 | J31: =J24*J30 -> 111.86173 | K31: =K24*K30 -> 108.69219 | ... M31: =M24*M30 -> 100.80766 | N31: =N25*N30 -> 1777.9282
D32: DCF on a pre-IFRS 16 basis: Adjusted EBIT pre-IFRS 16 deducts all rents (fixed & variable) as operating costs, so lease liabilities are NOT deducted from EV (consistent treatment). H2/26E UFCF is valued against the 30-Jun-26 net financial debt.
B33: IMPLIED ROIC — invested capital roll-forward (EURm; pre-IFRS 16, excl. right-of-use / lease liabilities)
B34: Opening invested capital | D34: =Model!AV279+Model!AV300-Model!AV262+Model!AV304 -> 870.302 | E34: =D38 -> 867.23968 | F34: =E38 -> 943.01711 | G34: =F38 -> 1019.5828 | H34: =G38 -> 1101.9546 | I34: =H38 -> 1187.4637 | J34: =I38 -> 1278.9584 | K34: =J38 -> 1376.2859 | L34: =K38 -> 1479.2097 | M34: =L38 -> 1587.4083
B35: plus Capex | D35: =-D22 -> 39.946 | E35: =-E22 -> 109.64927 | F35: =-F22 -> 118.72521 | G35: =-G22 -> 127.89102 | H35: =-H22 -> 137.05498 | I35: =-I22 -> 146.64883 | J35: =-J22 -> 155.99769 | K35: =-K22 -> 164.96756 | ... M35: =-M22 -> 181.22615
B36: less D&A excl. right-of-use | D36: =-D21 -> -32.182258 | E36: =-E21 -> -69.163389 | F36: =-F21 -> -74.888209 | G36: =-G21 -> -78.702165 | H36: =-H21 -> -84.341528 | I36: =-I21 -> -90.245435 | J36: =-J21 -> -95.998581 | K36: =-K21 -> -101.5185 | ... M36: =-M21 -> -111.52378
B37: plus Δ Working capital investment | D37: =-D23 -> -10.826066 | E37: =-E23 -> 35.291551 | F37: =-F23 -> 32.728693 | G37: =-G23 -> 33.182956 | H37: =-H23 -> 32.795606 | I37: =-I23 -> 35.091299 | J37: =-J23 -> 37.328369 | K37: =-K23 -> 39.47475 | ... M37: =-M23 -> 43.365233
B38: Closing invested capital | D38: =SUM(D34:D37) -> 867.23968 | E38: =SUM(E34:E37) -> 943.01711 | F38: =SUM(F34:F37) -> 1019.5828 | G38: =SUM(G34:G37) -> 1101.9546 | H38: =SUM(H34:H37) -> 1187.4637 | I38: =SUM(I34:I37) -> 1278.9584 | J38: =SUM(J34:J37) -> 1376.2859 | K38: =SUM(K34:K37) -> 1479.2097 | ... M38: =SUM(M34:M37) -> 1700.4759
B39: NOPAT (row 20) | D39: =D20 -> 85.785644 | E39: =E20 -> 182.15819 | F39: =F20 -> 205.57038 | G39: =G20 -> 230.02077 | H39: =H20 -> 252.19656 | I39: =I20 -> 269.85032 | J39: =J20 -> 287.05328 | K39: =K20 -> 303.55884 | ... M39: =M20 -> 333.47646
B40: Implied ROIC (NOPAT / avg. invested capital; H2/26E annualised) | D40: =IFERROR(D39/AVERAGE(D34,D38)*2,"") -> 0.19748739 | E40: =IFERROR(E39/AVERAGE(E34,E38)*1,"") -> 0.20125122 | F40: =IFERROR(F39/AVERAGE(F34,F38)*1,"") -> 0.20948781 | G40: =IFERROR(G39/AVERAGE(G34,G38)*1,"") -> 0.21684348 | H40: =IFERROR(H39/AVERAGE(H34,H38)*1,"") -> 0.22031497 | I40: =IFERROR(I39/AVERAGE(I34,I38)*1,"") -> 0.21881926 | J40: =IFERROR(J39/AVERAGE(J34,J38)*1,"") -> 0.2162161 | K40: =IFERROR(K39/AVERAGE(K34,K38)*1,"") -> 0.21261378 | L40: =IFERROR(L39/AVERAGE(L34,L38)*1,"") -> 0.20812259 | M40: =IFERROR(M39/AVERAGE(M34,M38)*1,"") -> 0.20285171
B41: Reinvestment rate (net investment / NOPAT) | D41: =IFERROR(SUM(D35:D37)/D39,"") -> -0.035697395 | E41: =IFERROR(SUM(E35:E37)/E39,"") -> 0.41599796 | F41: =IFERROR(SUM(F35:F37)/F39,"") -> 0.3724549 | G41: =IFERROR(SUM(G35:G37)/G39,"") -> 0.35810596 | H41: =IFERROR(SUM(H35:H37)/H39,"") -> 0.3390572 | I41: =IFERROR(SUM(I35:I37)/I39,"") -> 0.3390572 | J41: =IFERROR(SUM(J35:J37)/J39,"") -> 0.3390572 | K41: =IFERROR(SUM(K35:K37)/K39,"") -> 0.3390572 | ... M41: =IFERROR(SUM(M35:M37)/M39,"") -> 0.3390572
B42: Implied terminal RONIC (g / reinvestment rate) | M42: =IFERROR($C$27/M41,"") -> 0.088480645
D43: Opening IC = 30-Jun-26 equity + core net financial debt (pre-IFRS 16: right-of-use assets and lease liabilities excluded), rolled forward with capex − D&A + ΔWC.
B44: 3. VALUATION SUMMARY
B45: Sum of PV (explicit + fade) | C45: =SUM(D31:M31) -> 1059.1534
B46: PV of Terminal Value | C46: =N31 -> 1777.9282
B47: Enterprise Value (pre-IFRS 16) | C47: =C45+C46 -> 2837.0815
B48: Less: Net financial debt (core, 30-Jun-26) + NCI | C48: =Model!AV300+Model!AV278 -> 242.389 | D48: BC-specific: NCI (minority partners in Asian subsidiaries) deducted alongside core net financial debt; lease liabilities excluded (pre-IFRS 16 DCF).
B49: Equity Value | C49: =C47-C48 -> 2594.6925
B50: Shares outstanding (m, net of treasury shares) | C50: =Model!AX385 -> 68
B51: Implied share price (EUR) | C51: =C49/C50 -> 38.157243
B52: Current share price (EUR) | C52: =Model!AX384 -> 80.18
B53: Implied upside / (downside) | C53: =C51/C52-1 -> -0.52410523
B54: Required discount to DCF value for target IRR | C54: =1-((1+C13)/(1+H54))^H55 -> 0.082275914 | D54: vs. current | E54: Target IRR | H54: 0.12
B55: Max entry price for target IRR (EUR) | C55: =C51*(1-C54) -> 35.017821 | D55: =C55/C52-1 -> -0.5632599 | E55: Years for discount to close | H55: 3
B58: 4. SENSITIVITY: IMPLIED PRICE (EUR) — WACC × Terminal Growth
D60: WACC →
B61: Terminal growth ↓ | D61: =$F$61-0.01 -> 0.0784005 | E61: =$F$61-0.005 -> 0.0834005 | F61: =$C$13 -> 0.0884005 | G61: =$F$61+0.005 -> 0.0934005 | H61: =$F$61+0.01 -> 0.0984005
B62: =$B$64-0.01 -> 0.02 | D62: =IFERROR((SUMPRODUCT($D$24:$M$24,1/(1+D$61)^$D$29:$M$29)+($M$24*(1+$B62)/(D$61-$B62))/(1+D$61)^$M$29-$C$48)/$C$50,"") -> 40.922292 | E62: =IFERROR((SUMPRODUCT($D$24:$M$24,1/(1+E$61)^$D$29:$M$29)+($M$24*(1+$B62)/(E$61-$B62))/(1+E$61)^$M$29-$C$48)/$C$50,"") -> 37.24885 | F62: =IFERROR((SUMPRODUCT($D$24:$M$24,1/(1+F$61)^$D$29:$M$29)+($M$24*(1+$B62)/(F$61-$B62))/(1+F$61)^$M$29-$C$48)/$C$50,"") -> 34.118023 | G62: =IFERROR((SUMPRODUCT($D$24:$M$24,1/(1+G$61)^$D$29:$M$29)+($M$24*(1+$B62)/(G$61-$B62))/(1+G$61)^$M$29-$C$48)/$C$50,"") -> 31.418747 | H62: =IFERROR((SUMPRODUCT($D$24:$M$24,1/(1+H$61)^$D$29:$M$29)+($M$24*(1+$B62)/(H$61-$B62))/(1+H$61)^$M$29-$C$48)/$C$50,"") -> 29.068298
B63: =$B$64-0.005 -> 0.025 | D63: =IFERROR((SUMPRODUCT($D$24:$M$24,1/(1+D$61)^$D$29:$M$29)+($M$24*(1+$B63)/(D$61-$B63))/(1+D$61)^$M$29-$C$48)/$C$50,"") -> 43.713498 | E63: =IFERROR((SUMPRODUCT($D$24:$M$24,1/(1+E$61)^$D$29:$M$29)+($M$24*(1+$B63)/(E$61-$B63))/(1+E$61)^$M$29-$C$48)/$C$50,"") -> 39.511937 | F63: =IFERROR((SUMPRODUCT($D$24:$M$24,1/(1+F$61)^$D$29:$M$29)+($M$24*(1+$B63)/(F$61-$B63))/(1+F$61)^$M$29-$C$48)/$C$50,"") -> 35.978359 | G63: =IFERROR((SUMPRODUCT($D$24:$M$24,1/(1+G$61)^$D$29:$M$29)+($M$24*(1+$B63)/(G$61-$B63))/(1+G$61)^$M$29-$C$48)/$C$50,"") -> 32.966115 | H63: =IFERROR((SUMPRODUCT($D$24:$M$24,1/(1+H$61)^$D$29:$M$29)+($M$24*(1+$B63)/(H$61-$B63))/(1+H$61)^$M$29-$C$48)/$C$50,"") -> 30.368519
B64: =$C$27 -> 0.03 | D64: =IFERROR((SUMPRODUCT($D$24:$M$24,1/(1+D$61)^$D$29:$M$29)+($M$24*(1+$B64)/(D$61-$B64))/(1+D$61)^$M$29-$C$48)/$C$50,"") -> 47.081393 | E64: =IFERROR((SUMPRODUCT($D$24:$M$24,1/(1+E$61)^$D$29:$M$29)+($M$24*(1+$B64)/(E$61-$B64))/(1+E$61)^$M$29-$C$48)/$C$50,"") -> 42.198819 | F64: =IFERROR((SUMPRODUCT($D$24:$M$24,1/(1+F$61)^$D$29:$M$29)+($M$24*(1+$B64)/(F$61-$B64))/(1+F$61)^$M$29-$C$48)/$C$50,"") -> 38.157243 | G64: =IFERROR((SUMPRODUCT($D$24:$M$24,1/(1+G$61)^$D$29:$M$29)+($M$24*(1+$B64)/(G$61-$B64))/(1+G$61)^$M$29-$C$48)/$C$50,"") -> 34.757544 | H64: =IFERROR((SUMPRODUCT($D$24:$M$24,1/(1+H$61)^$D$29:$M$29)+($M$24*(1+$B64)/(H$61-$B64))/(1+H$61)^$M$29-$C$48)/$C$50,"") -> 31.858829
B65: =$B$64+0.005 -> 0.035 | D65: =IFERROR((SUMPRODUCT($D$24:$M$24,1/(1+D$61)^$D$29:$M$29)+($M$24*(1+$B65)/(D$61-$B65))/(1+D$61)^$M$29-$C$48)/$C$50,"") -> 51.225291 | E65: =IFERROR((SUMPRODUCT($D$24:$M$24,1/(1+E$61)^$D$29:$M$29)+($M$24*(1+$B65)/(E$61-$B65))/(1+E$61)^$M$29-$C$48)/$C$50,"") -> 45.440835 | F65: =IFERROR((SUMPRODUCT($D$24:$M$24,1/(1+F$61)^$D$29:$M$29)+($M$24*(1+$B65)/(F$61-$B65))/(1+F$61)^$M$29-$C$48)/$C$50,"") -> 40.744154 | G65: =IFERROR((SUMPRODUCT($D$24:$M$24,1/(1+G$61)^$D$29:$M$29)+($M$24*(1+$B65)/(G$61-$B65))/(1+G$61)^$M$29-$C$48)/$C$50,"") -> 36.855723 | H65: =IFERROR((SUMPRODUCT($D$24:$M$24,1/(1+H$61)^$D$29:$M$29)+($M$24*(1+$B65)/(H$61-$B65))/(1+H$61)^$M$29-$C$48)/$C$50,"") -> 33.584202
B66: =$B$64+0.01 -> 0.04 | D66: =IFERROR((SUMPRODUCT($D$24:$M$24,1/(1+D$61)^$D$29:$M$29)+($M$24*(1+$B66)/(D$61-$B66))/(1+D$61)^$M$29-$C$48)/$C$50,"") -> 56.448316 | E66: =IFERROR((SUMPRODUCT($D$24:$M$24,1/(1+E$61)^$D$29:$M$29)+($M$24*(1+$B66)/(E$61-$B66))/(1+E$61)^$M$29-$C$48)/$C$50,"") -> 49.429852 | F66: =IFERROR((SUMPRODUCT($D$24:$M$24,1/(1+F$61)^$D$29:$M$29)+($M$24*(1+$B66)/(F$61-$B66))/(1+F$61)^$M$29-$C$48)/$C$50,"") -> 43.865545 | G66: =IFERROR((SUMPRODUCT($D$24:$M$24,1/(1+G$61)^$D$29:$M$29)+($M$24*(1+$B66)/(G$61-$B66))/(1+G$61)^$M$29-$C$48)/$C$50,"") -> 39.346816 | H66: =IFERROR((SUMPRODUCT($D$24:$M$24,1/(1+H$61)^$D$29:$M$29)+($M$24*(1+$B66)/(H$61-$B66))/(1+H$61)^$M$29-$C$48)/$C$50,"") -> 35.605013
B69: 5. REVERSE DCF
B70: To solve for the market-implied path: Data ▸ What-If Analysis ▸ Goal Seek — set C51 to the current price (C52) by changing C27 (terminal growth) or the fade-period start growth (I26).
B72: 6. MAUBOUSSIN EV / NOPAT — TWO-STAGE FRAMEWORK
B73: EV/NOPAT = 1/r + [g × (1 − r/ROIIC) / (r × (r − g))] × [1 − ((1+g)/(1+r))^N]
B74: Formula source: Mauboussin & Rappaport, "Expectations Investing" (2021); Counterpoint Global, "What Does a Price-Earnings Multiple Mean?" (2020).
B76: Input | C76: Value | D76: Rationale (Brunello Cucinelli characteristics)
B77: r (Cost of capital / WACC) | C77: =$C$13 -> 0.0884005 | D77: Linked from Section 1 WACC build
B78: g (NOPAT growth, Stage 1) | C78: 0.09 | D78: Model Adjusted EBIT pre-IFRS 16 CAGR 2026–30E ~9–10%: high-single-digit revenue growth (retail density + selective openings) with modest operating leverage
B79: ROIIC (Return on incremental invested capital) | C79: 0.3 | D79: Asset-light luxury model: incremental capital = boutiques capex + working capital (~25% of sales) on ~15% pre-IFRS 16 EBIT margins → ~30% after tax
B80: N (Years of value creation / CAP) | C80: 15 | D80: Absolute-luxury positioning, founder-led brand, Made-in-Italy craftsmanship and pricing power; exposure to aspirational-demand cycles and key-person risk
B82: Calculation | C82: Value
B83: Steady-state component: 1 / r | C83: =1/C77 -> 11.312153
B84: Value-creation factor: 1 − r / ROIIC | C84: =1-C77/C79 -> 0.70533167
B85: Growth multiplier: g × (1 − r/ROIIC) / (r × (r − g)) | C85: =C78*C84/(C77*(C77-C78)) -> -448.94891
B86: Time decay: 1 − ((1+g)/(1+r))^N | C86: =1-((1+C78)/(1+C77))^C80 -> -0.022272033
B87: PVGO component (growth value) | C87: =C85*C86 -> 9.9990052
B88: Mauboussin EV / NOPAT (steady-state + PVGO) | C88: =C83+C87 -> 21.311158
B90: VALUATION — Applied to 2028E NOPAT | C90: EURm
B91: 2028E Adjusted EBIT pre-IFRS 16 | C91: =Model!AZ173 -> 287.51102
B92: Tax rate (from WACC build) | C92: =$C$10 -> 0.285
B93: 2028E NOPAT | C93: =C91*(1-C92) -> 205.57038
B94: × Mauboussin EV/NOPAT multiple | C94: =C88 -> 21.311158
B95: Implied Enterprise Value (2028E basis) | C95: =C93*C94 -> 4380.9429
B96: Less: YE2027 net financial debt + NCI (Model) | C96: =Model!AY300+Model!AY278 -> 152.21568
B97: Implied Equity Value | C97: =C95-C96 -> 4228.7272
B98: Shares outstanding 2028E (m, Model) | C98: =Model!AZ385 -> 68
B99: Implied share price 2028 (EUR) | C99: =C97/C98 -> 62.187164
B101: Current share price (EUR) | C101: =C52 -> 80.18
B102: Implied upside / (downside) | C102: =C99/C101-1 -> -0.22440553
B104: MARKET-IMPLIED EV/NOPAT TODAY | C104: EURm
B105: Current market cap (spot × shares outstanding) | C105: =C52*C50 -> 5452.24
B106: Plus: 30-Jun-26 net financial debt + NCI | C106: =C48 -> 242.389
B107: Implied Enterprise Value (today; pre-IFRS 16) | C107: =C105+C106 -> 5694.629
B108: BC market-implied EV/NOPAT (on 2028E NOPAT) | C108: =C107/C93 -> 27.701603
B110: Multiple gap (Mauboussin − Market) | C110: =C88-C108 -> -6.3904448
B111: Implied re-rating headroom | C111: =C88/C108-1 -> -0.23068863

Sheet Charts
B2: Brunello Cucinelli — Historical Operating Performance (2011–2025)
B3: All historicals · EURm · Linked to Model. Channel growth = retail and wholesale revenue y/y (reported currency). Adjusted EBITDA on the company basis in force (IFRS 16 from 2019 — see pre-IFRS 16 line for comparability). Returns on the IFRS 16 basis.
C7: 2011 | D7: 2012 | E7: 2013 | F7: 2014 | G7: 2015 | H7: 2016 | I7: 2017 | J7: 2018 | K7: 2019 | L7: 2020 | M7: 2021 | N7: 2022 | O7: 2023 | P7: 2024 | Q7: 2025
B8: Retail revenues y/y % | C8: =IFERROR(Model!E17+0,0) -> 0 | D8: =IFERROR(Model!H17+0,0) -> 0.42865896 | E8: =IFERROR(Model!K17+0,0) -> 0.50021443 | F8: =IFERROR(Model!N17+0,0) -> 0.28626126 | G8: =IFERROR(Model!Q17+0,0) -> 0.30095767 | H8: =IFERROR(Model!T17+0,0) -> 0.17106857 | I8: =IFERROR(Model!W17+0,0) -> 0.19597737 | J8: =IFERROR(Model!Z17+0,0) -> 0.095030937 | K8: =IFERROR(Model!AC17+0,0) -> 0.14571414 | L8: =IFERROR(Model!AF17+0,0) -> -0.20817535 | M8: =IFERROR(Model!AI17+0,0) -> 0.56197609 | N8: =IFERROR(Model!AL17+0,0) -> 0.36564265 | O8: =IFERROR(Model!AO17+0,0) -> 0.30261634 | P8: =IFERROR(Model!AR17+0,0) -> 0.13982962 | Q8: =IFERROR(Model!AU17+0,0) -> 0.11250137
B9: Wholesale revenues y/y % | C9: =IFERROR(Model!E26+0,0) -> 0 | D9: =IFERROR(Model!H26+0,0) -> 0.072033225 | E9: =IFERROR(Model!K26+0,0) -> 0.023066432 | F9: =IFERROR(Model!N26+0,0) -> 0.0018498841 | G9: =IFERROR(Model!Q26+0,0) -> 0.06534473 | H9: =IFERROR(Model!T26+0,0) -> 0.03970549 | I9: =IFERROR(Model!W26+0,0) -> 0.01421539 | J9: =IFERROR(Model!Z26+0,0) -> 0.1017694 | K9: =IFERROR(Model!AC26+0,0) -> 0.045164004 | L9: =IFERROR(Model!AF26+0,0) -> 0.025767164 | M9: =IFERROR(Model!AI26+0,0) -> 0.062207528 | N9: =IFERROR(Model!AL26+0,0) -> 0.18479146 | O9: =IFERROR(Model!AO26+0,0) -> 0.13342264 | P9: =IFERROR(Model!AR26+0,0) -> 0.088366395 | Q9: =IFERROR(Model!AU26+0,0) -> 0.078739144
B12: Adjusted EBITDA | C12: =IFERROR(Model!E158+0,0) -> 40.16 | D12: =IFERROR(Model!H158+0,0) -> 49.11 | E12: =IFERROR(Model!K158+0,0) -> 58.181 | F12: =IFERROR(Model!N158+0,0) -> 63.041 | G12: =IFERROR(Model!Q158+0,0) -> 69.124 | H12: =IFERROR(Model!T158+0,0) -> 78.215 | I12: =IFERROR(Model!W158+0,0) -> 87.476 | J12: =IFERROR(Model!Z158+0,0) -> 95.143 | K12: =IFERROR(Model!AC158+0,0) -> 169.626 | L12: =IFERROR(Model!AF158+0,0) -> 121.193 | M12: =IFERROR(Model!AI158+0,0) -> 193.311 | N12: =IFERROR(Model!AL158+0,0) -> 266.357 | O12: =IFERROR(Model!AO158+0,0) -> 326.251 | P12: =IFERROR(Model!AR158+0,0) -> 364.675 | Q12: =IFERROR(Model!AU158+0,0) -> 416.463
B13: Operating Income — EBIT (IFRS) | C13: =IFERROR(Model!E120+0,0) -> 34.907 | D13: =IFERROR(Model!H120+0,0) -> 35.744 | E13: =IFERROR(Model!K120+0,0) -> 46.956 | F13: =IFERROR(Model!N120+0,0) -> 49.329 | G13: =IFERROR(Model!Q120+0,0) -> 50.975 | H13: =IFERROR(Model!T120+0,0) -> 56.645 | I13: =IFERROR(Model!W120+0,0) -> 64.721 | J13: =IFERROR(Model!Z120+0,0) -> 69.538 | K13: =IFERROR(Model!AC120+0,0) -> 83.376 | L13: =IFERROR(Model!AF120+0,0) -> -14.818 | M13: =IFERROR(Model!AI120+0,0) -> 77.036 | N13: =IFERROR(Model!AL120+0,0) -> 134.412 | O13: =IFERROR(Model!AO120+0,0) -> 187.406 | P13: =IFERROR(Model!AR120+0,0) -> 211.671 | Q13: =IFERROR(Model!AU120+0,0) -> 227.784
B14: Adj. EBITDA Margin % | C14: =IFERROR(Model!E159+0,0) -> 0.1655161 | D14: =IFERROR(Model!H159+0,0) -> 0.17581922 | E14: =IFERROR(Model!K159+0,0) -> 0.18041739 | F14: =IFERROR(Model!N159+0,0) -> 0.17712674 | G14: =IFERROR(Model!Q159+0,0) -> 0.16690531 | H14: =IFERROR(Model!T159+0,0) -> 0.17153503 | I14: =IFERROR(Model!W159+0,0) -> 0.17371135 | J14: =IFERROR(Model!Z159+0,0) -> 0.17205007 | K14: =IFERROR(Model!AC159+0,0) -> 0.27909984 | L14: =IFERROR(Model!AF159+0,0) -> 0.22277593 | M14: =IFERROR(Model!AI159+0,0) -> 0.27143597 | N14: =IFERROR(Model!AL159+0,0) -> 0.2896104 | O14: =IFERROR(Model!AO159+0,0) -> 0.28633076 | P14: =IFERROR(Model!AR159+0,0) -> 0.28522768 | Q14: =IFERROR(Model!AU159+0,0) -> 0.29579367
B15: Adj. EBITDA pre-IFRS 16 Margin % | C15: =IFERROR(Model!E163+0,0) -> 0.1655161 | D15: =IFERROR(Model!H163+0,0) -> 0.17581922 | E15: =IFERROR(Model!K163+0,0) -> 0.18041739 | F15: =IFERROR(Model!N163+0,0) -> 0.17712674 | G15: =IFERROR(Model!Q163+0,0) -> 0.16690531 | H15: =IFERROR(Model!T163+0,0) -> 0.17153503 | I15: =IFERROR(Model!W163+0,0) -> 0.17371135 | J15: =IFERROR(Model!Z163+0,0) -> 0.17205007 | K15: =IFERROR(Model!AC163+0,0) -> 0.1745061 | L15: =IFERROR(Model!AF163+0,0) -> 0.076761033 | M15: =IFERROR(Model!AI163+0,0) -> 0.15447381 | N15: =IFERROR(Model!AL163+0,0) -> 0.18746276 | O15: =IFERROR(Model!AO163+0,0) -> 0.20210195 | P15: =IFERROR(Model!AR163+0,0) -> 0.19007853 | Q15: =IFERROR(Model!AU163+0,0) -> 0.18878285
B16: Operating Margin (IFRS) % | C16: =IFERROR(Model!E121+0,0) -> 0.1438663 | D16: =IFERROR(Model!H121+0,0) -> 0.12796746 | E16: =IFERROR(Model!K121+0,0) -> 0.14560903 | F16: =IFERROR(Model!N121+0,0) -> 0.13860004 | G16: =IFERROR(Model!Q121+0,0) -> 0.12308313 | H16: =IFERROR(Model!T121+0,0) -> 0.12422939 | I16: =IFERROR(Model!W121+0,0) -> 0.12852408 | J16: =IFERROR(Model!Z121+0,0) -> 0.12574775 | K16: =IFERROR(Model!AC121+0,0) -> 0.13718551 | L16: =IFERROR(Model!AF121+0,0) -> -0.02723832 | M16: =IFERROR(Model!AI121+0,0) -> 0.10816943 | N16: =IFERROR(Model!AL121+0,0) -> 0.14614639 | O16: =IFERROR(Model!AO121+0,0) -> 0.16447491 | P16: =IFERROR(Model!AR121+0,0) -> 0.16555681 | Q16: =IFERROR(Model!AU121+0,0) -> 0.16178404
B18: ROIC | C18: =IFERROR(Model!E361+0,0) -> 0.26386811 | D18: =IFERROR(Model!H361+0,0) -> 0.22962194 | E18: =IFERROR(Model!K361+0,0) -> 0.19037106 | F18: =IFERROR(Model!N361+0,0) -> 0.15859537 | G18: =IFERROR(Model!Q361+0,0) -> 0.14376299 | H18: =IFERROR(Model!T361+0,0) -> 0.14605399 | I18: =IFERROR(Model!W361+0,0) -> 0.20499934 | J18: =IFERROR(Model!Z361+0,0) -> 0.1800808 | K18: =IFERROR(Model!AC361+0,0) -> 0.081931977 | L18: =IFERROR(Model!AF361+0,0) -> 0.018513493 | M18: =IFERROR(Model!AI361+0,0) -> 0.075698118 | N18: =IFERROR(Model!AL361+0,0) -> 0.097969755 | O18: =IFERROR(Model!AO361+0,0) -> 0.13153286 | P18: =IFERROR(Model!AR361+0,0) -> 0.1174114 | Q18: =IFERROR(Model!AU361+0,0) -> 0.10876679
B19: RONTA | C19: =IFERROR(Model!E372+0,0) -> 0.25139736 | D19: =IFERROR(Model!H372+0,0) -> 0.18453084 | E19: =IFERROR(Model!K372+0,0) -> 0.1682226 | F19: =IFERROR(Model!N372+0,0) -> 0.13227523 | G19: =IFERROR(Model!Q372+0,0) -> 0.12675723 | H19: =IFERROR(Model!T372+0,0) -> 0.12854698 | I19: =IFERROR(Model!W372+0,0) -> 0.17448533 | J19: =IFERROR(Model!Z372+0,0) -> 0.15476961 | K19: =IFERROR(Model!AC372+0,0) -> 0.07516578 | L19: =IFERROR(Model!AF372+0,0) -> 0.017232995 | M19: =IFERROR(Model!AI372+0,0) -> 0.068123259 | N19: =IFERROR(Model!AL372+0,0) -> 0.086620315 | O19: =IFERROR(Model!AO372+0,0) -> 0.11847625 | P19: =IFERROR(Model!AR372+0,0) -> 0.10179126 | Q19: =IFERROR(Model!AU372+0,0) -> 0.096346132
B20: Adj. EBITDA pre-IFRS 16 margin % | C20: =IFERROR(Model!E163+0,0) -> 0.1655161 | D20: =IFERROR(Model!H163+0,0) -> 0.17581922 | E20: =IFERROR(Model!K163+0,0) -> 0.18041739 | F20: =IFERROR(Model!N163+0,0) -> 0.17712674 | G20: =IFERROR(Model!Q163+0,0) -> 0.16690531 | H20: =IFERROR(Model!T163+0,0) -> 0.17153503 | I20: =IFERROR(Model!W163+0,0) -> 0.17371135 | J20: =IFERROR(Model!Z163+0,0) -> 0.17205007 | K20: =IFERROR(Model!AC163+0,0) -> 0.1745061 | L20: =IFERROR(Model!AF163+0,0) -> 0.076761033 | M20: =IFERROR(Model!AI163+0,0) -> 0.15447381 | N20: =IFERROR(Model!AL163+0,0) -> 0.18746276 | O20: =IFERROR(Model!AO163+0,0) -> 0.20210195 | P20: =IFERROR(Model!AR163+0,0) -> 0.19007853 | Q20: =IFERROR(Model!AU163+0,0) -> 0.18878285
B21: FCF after leases margin % | C21: =IFERROR(Model!E242+0,0) -> 0.011259711 | D21: =IFERROR(Model!H242+0,0) -> -0.031444109 | E21: =IFERROR(Model!K242+0,0) -> -0.024599975 | F21: =IFERROR(Model!N242+0,0) -> -0.056702696 | G21: =IFERROR(Model!Q242+0,0) -> -0.010286103 | H21: =IFERROR(Model!T242+0,0) -> 0.032734538 | I21: =IFERROR(Model!W242+0,0) -> 0.11571357 | J21: =IFERROR(Model!Z242+0,0) -> 0.047588048 | K21: =IFERROR(Model!AC242+0,0) -> 0.016220192 | L21: =IFERROR(Model!AF242+0,0) -> -0.11541636 | M21: =IFERROR(Model!AI242+0,0) -> 0.095796141 | N21: =IFERROR(Model!AL242+0,0) -> 0.061984891 | O21: =IFERROR(Model!AO242+0,0) -> 0.032546383 | P21: =IFERROR(Model!AR242+0,0) -> -0.01049009 | Q21: =IFERROR(Model!AU242+0,0) -> -0.0092204913
