Workbook

Sheet Model
BV1: SCENARIO SWITCH ▼ (Bull / Base / Bear) — drives all scenario-linked forecast drivers
B2: BWX Technologies, Inc. (NYSE: BWXT) — 3-Statement Financial Model | BV2: Base
B3: US GAAP as reported · USD millions (per-share data in USD; shares in millions) · Source: BWXT Forms 10-K / 10-Q and Form 8-K earnings releases (Ex. 99.1), convertible-note 8-Ks (Nov-2025), SEC EDGAR CIK 0001486957 (investor-relations releases at investors.bwxt.com are the same documents as filed on EDGAR); Form 4 for the share price
B4: Basis notes: calendar fiscal year. Power Generation (Babcock & Wilcox Enterprises) spun off 30-Jun-2015 → discontinued operations; 2012–13 annual and Q1/14–Q1/15 on the recast continuing-operations basis (Q1/14 = 6M/14 − Q2/14; balance sheets from Dec-14 recast). Later periods as originally reported (2017 and earlier: pension MTM within operating income; ASU 2017-07 from 2018). Segments: Government / Commercial Operations from 2022 (2020 annual and 2021 quarters recast); legacy NOG/NSG/NPG memo. Kinectrics from 20-May-2025; A.O.T. 2025; PCG from 1-Jul-2026; medical business (BWXT Medical + Kinectrics isotopes) sale to Nordic Capital agreed 31-Jul-2026 — modelled to close 31-Mar-2027.
BX5: Forecast | BY5: Historical | BZ5: Historical | CA5: Historical
B6: (USDm) | C6: 2012 | D6: 2013 | E6: Q1/14 | F6: Q2/14 | G6: Q3/14 | H6: Q4/14 | I6: 2014 | J6: Q1/15 | K6: Q2/15 | L6: Q3/15 | M6: Q4/15 | N6: 2015 | O6: Q1/16 | P6: Q2/16 | Q6: Q3/16 | R6: Q4/16 | S6: 2016 | T6: Q1/17 | U6: Q2/17 | V6: Q3/17 | W6: Q4/17 | X6: 2017 | Y6: Q1/18 | Z6: Q2/18 | AA6: Q3/18 | AB6: Q4/18 | AC6: 2018 | AD6: Q1/19 | AE6: Q2/19 | AF6: Q3/19 | AG6: Q4/19 | AH6: 2019 | AI6: Q1/20 | AJ6: Q2/20 | AK6: Q3/20 | AL6: Q4/20 | AM6: 2020 | AN6: Q1/21 | AO6: Q2/21 | AP6: Q3/21 | AQ6: Q4/21 | AR6: 2021 | AS6: Q1/22 | AT6: Q2/22 | AU6: Q3/22 | AV6: Q4/22 | AW6: 2022 | AX6: Q1/23 | AY6: Q2/23 | AZ6: Q3/23 | BA6: Q4/23 | BB6: 2023 | BC6: Q1/24 | BD6: Q2/24 | BE6: Q3/24 | BF6: Q4/24 | BG6: 2024 | BH6: Q1/25 | BI6: Q2/25 | BJ6: Q3/25 | BK6: Q4/25 | BL6: 2025 | BM6: Q1/26 | BN6: Q2/26 | BO6: Q3/26E | BP6: Q4/26E | BQ6: 2026E | BR6: 2027E | BS6: 2028E | BT6: 2029E | BU6: 2030E | BV6: Modelling Notes | BX6: 5Y CAGR | BY6: 5Y CAGR | BZ6: 10Y CAGR | CA6: 12Y CAGR
BX7: 25-'30 | BY7: 20-'25 | BZ7: 15-'25 | CA7: 13-'25
B9: SEGMENT BUILD — GOVERNMENT OPERATIONS · COMMERCIAL OPERATIONS (backlog × book-to-bill → revenues → non-GAAP operating income → Adjusted EBITDA) | BV9: SEGMENT BUILD — modelling logic (bookings = revenues × book-to-bill; backlog roll-forward; non-GAAP margin → segment Adjusted EBITDA) | CD9: SCENARIO INPUT TABLE — driver assumptions per Bull / Base / Bear | CE9: Bull | CF9: Base | CG9: Bear | CH9: Bull / Bear = Base + Δ (Δ inputs on each block header). Outlook block: High / Mid / Low guidance end-points.
B11: Government Operations (naval nuclear reactors & fuel, special materials / HEU down-blending, advanced reactors, technical-services JVs) — reported from 2022 (2020–21 recast) | BV11: GOVERNMENT OPERATIONS — modelling logic | CD11: FY26 outlook — Q2-26 release (3-Aug-26); includes PCG from 1-Jul-26 | CE11: High | CF11: Mid | CG11: Low | CH11: Company does not give GAAP guidance. Medical business still consolidated in 2026.
B12: Opening backlog | AN12: =AM19 -> 3680.126 | AO12: =AN19 -> 4495.617 | AP12: =AO19 -> 4174.767 | AQ12: =AP19 -> 3813.289 | AR12: =AM19 -> 3680.126 | AS12: =AR19 -> 4532.17 | AT12: =AS19 -> 4158.335 | AU12: =AT19 -> 3989.3 | AV12: =AU19 -> 3686.469 | AW12: =AR19 -> 4532.17 | AX12: =AW19 -> 3515.377 | AY12: =AX19 -> 3108.628 | AZ12: =AY19 -> 3405.716 | BA12: =AZ19 -> 3258.877 | BB12: =AW19 -> 3515.377 | BC12: =BB19 -> 3216.673 | BD12: =BC19 -> 2908.986 | BE12: =BD19 -> 2865.193 | BF12: =BE19 -> 2745.333 | BG12: =BB19 -> 3216.673 | BH12: =BG19 -> 3912.58 | BI12: =BH19 -> 3583.69 | BJ12: =BI19 -> 4435.593 | BK12: =BJ19 -> 5905.02 | BL12: =BG19 -> 3912.58 | BM12: =BL19 -> 5541.291 | BN12: =BM19 -> 6931.111 | BO12: =BN19 -> 6797.627 | BP12: =BO19 -> 6797.627 | BQ12: =BL19 -> 5541.291 | BR12: =BQ19 -> 6797.627 | BS12: =BR19 -> 6928.9501 | BT12: =BS19 -> 7070.7791 | BU12: =BT19 -> 7222.5361 | BV12: Prior period-end backlog (Q1 = prior year-end). | CD12: FY26 revenues ($m) | CE12: 3850 | CF12: 3800 | CG12: 3750 | CH12: ~$3,800m (raised from >$3,750m in Q1, ~$3,750m in Feb-26).
B13: Bookings | AM13: 889.844 | AN13: 1236.546 | AO13: 82.751 | AP13: 53.989 | AQ13: 1196.527 | AR13: 2569.813 | AS13: 57.019 | AT13: 222.127 | AU13: 119.086 | AV13: 345.22 | AW13: 743.452 | AX13: 52.737 | AY13: 788.668 | AZ13: 330.801 | BA13: 559.412 | BB13: 1731.618 | BC13: 179.413 | BD13: 497.021 | BE13: 440.146 | BF13: 1762.228 | BG13: 2878.808 | BH13: 226.397 | BI13: 1412.286 | BJ13: 2086.092 | BK13: 225.397 | BL13: 3950.171 | BM13: 1967.644 | BN13: 467.619 | BO13: =BO15*BO14 -> 640.6692 | BP13: =BP15*BP14 -> 612.04828 | BQ13: =SUM(BM13:BP13) -> 3687.9805 | BR13: =BR15*BR14 -> 2757.7853 | BS13: =BS15*BS14 -> 2978.4082 | BT13: =BT15*BT14 -> 3186.8967 | BU13: =BU15*BU14 -> 3409.9795 | BV13: Forecast = revenues × book-to-bill. Naval awards are lumpy (multi-year Navy contract options), so quarterly book-to-bill is set at 1.0x. | BX13: =IFERROR((BU13/BL13)^(1/5)-1,"n/m") -> -0.028982237 | BY13: =IFERROR((BL13/AM13)^(1/5)-1,"n/m") -> 0.34728788 | BZ13: =IFERROR((BL13/N13)^(1/10)-1,"n/m") -> n/m | CA13: =IFERROR((BL13/D13)^(1/12)-1,"n/m") -> n/m | CD13: FY26 Adjusted EBITDA ($m) | CE13: 672 | CF13: 667 | CG13: 662 | CH13: $662–672m (raised from $650–665m). Drives the Q3/Q4-26E margin calibration.
B14: Book-to-bill (x) | C14: =IF(AND(ISNUMBER(C13),ISNUMBER(C15)),IFERROR(C13/C15,""),"") | D14: =IF(AND(ISNUMBER(D13),ISNUMBER(D15)),IFERROR(D13/D15,""),"") | E14: =IF(AND(ISNUMBER(E13),ISNUMBER(E15)),IFERROR(E13/E15,""),"") | F14: =IF(AND(ISNUMBER(F13),ISNUMBER(F15)),IFERROR(F13/F15,""),"") | G14: =IF(AND(ISNUMBER(G13),ISNUMBER(G15)),IFERROR(G13/G15,""),"") | H14: =IF(AND(ISNUMBER(H13),ISNUMBER(H15)),IFERROR(H13/H15,""),"") | I14: =IF(AND(ISNUMBER(I13),ISNUMBER(I15)),IFERROR(I13/I15,""),"") | J14: =IF(AND(ISNUMBER(J13),ISNUMBER(J15)),IFERROR(J13/J15,""),"") | ... BN14: =IF(AND(ISNUMBER(BN13),ISNUMBER(BN15)),IFERROR(BN13/BN15,""),"") -> 0.77769167 | BO14: 1 | BP14: 1 | BQ14: =IF(AND(ISNUMBER(BQ13),ISNUMBER(BQ15)),IFERROR(BQ13/BQ15,""),"") -> 1.5164958 | BR14: =CHOOSE(MATCH($BV$2,{"Bull","Base","Bear"},0),$CE$33,$CF$33,$CG$33) -> 1.05 | BS14: =CHOOSE(MATCH($BV$2,{"Bull","Base","Bear"},0),$CE$34,$CF$34,$CG$34) -> 1.05 | BT14: =CHOOSE(MATCH($BV$2,{"Bull","Base","Bear"},0),$CE$35,$CF$35,$CG$35) -> 1.05 | BU14: =CHOOSE(MATCH($BV$2,{"Bull","Base","Bear"},0),$CE$36,$CF$36,$CG$36) -> 1.05 | BV14: 2027E+: scenario lever GOV_btb (Bull / Base / Bear table →). 2021–25 average ~1.4x incl. the 2023/2025 naval awards. | CD14: FY26 non-GAAP EPS ($) | CE14: 4.8 | CF14: 4.75 | CG14: 4.7 | CH14: $4.70–4.80 (memo; compared with the model, not forced).
B15: Revenues | AM15: 1763.127 | AN15: 423.275 | AO15: 405.497 | AP15: 417.139 | AQ15: 479.186 | AR15: 1725.097 | AS15: 431.777 | AT15: 436.537 | AU15: 422.521 | AV15: 517.648 | AW15: 1808.483 | AX15: 459.886 | AY15: 491.967 | AZ15: 477.855 | BA15: 601.629 | BB15: 2031.337 | BC15: 487.121 | BD15: 540.846 | BE15: 560.073 | BF15: 595 | BG15: 2183.04 | BH15: 555.286 | BI15: 588.959 | BJ15: 616.697 | BK15: 589.147 | BL15: 2350.09 | BM15: 577.901 | BN15: 601.291 | BO15: =BJ15*(1+BO17) -> 640.6692 | BP15: =BK15*(1+BP17) -> 612.04828 | BQ15: =SUM(BM15:BP15) -> 2431.9095 | BR15: =BQ15*(1+BR17) -> 2626.4622 | BS15: =BR15*(1+BS17) -> 2836.5792 | BT15: =BS15*(1+BT17) -> 3035.1398 | BU15: =BT15*(1+BU17) -> 3247.5995 | BV15: Q3/26E–Q4/26E: prior-year quarter × (1 + 1H/26 y/y growth + revenue-outlook calibration Δ). 2027E+: prior year × (1 + GOV_growth). | BX15: =IFERROR((BU15/BL15)^(1/5)-1,"n/m") -> 0.066830922 | BY15: =IFERROR((BL15/AM15)^(1/5)-1,"n/m") -> 0.059156607 | BZ15: =IFERROR((BL15/N15)^(1/10)-1,"n/m") -> n/m | CA15: =IFERROR((BL15/D15)^(1/12)-1,"n/m") -> n/m | CD15: FY26 free cash flow ($m) | CE15: 360 | CF15: 352.5 | CG15: 345 | CH15: $345–360m (memo).
B16: Q3/Q4-26E growth input — 1H/26 y/y (before revenue calibration) | BO16: =SUM(BM15,BN15)/SUM(BH15,BI15)-1 -> 0.030541536 | BP16: =SUM(BM15,BN15)/SUM(BH15,BI15)-1 -> 0.030541536 | BV16: 1H/26 Government Operations revenue growth (+3.1% y/y; naval propulsion & special materials up, microreactor volumes down).
B17: Revenues y/y % | D17: =IF(AND(ISNUMBER(D15),ISNUMBER(C15)),IFERROR(D15/C15-1,""),"") | I17: =IF(AND(ISNUMBER(I15),ISNUMBER(D15)),IFERROR(I15/D15-1,""),"") | J17: =IF(AND(ISNUMBER(J15),ISNUMBER(E15)),IFERROR(J15/E15-1,""),"") | K17: =IF(AND(ISNUMBER(K15),ISNUMBER(F15)),IFERROR(K15/F15-1,""),"") | L17: =IF(AND(ISNUMBER(L15),ISNUMBER(G15)),IFERROR(L15/G15-1,""),"") | M17: =IF(AND(ISNUMBER(M15),ISNUMBER(H15)),IFERROR(M15/H15-1,""),"") | N17: =IF(AND(ISNUMBER(N15),ISNUMBER(I15)),IFERROR(N15/I15-1,""),"") | O17: =IF(AND(ISNUMBER(O15),ISNUMBER(J15)),IFERROR(O15/J15-1,""),"") | P17: =IF(AND(ISNUMBER(P15),ISNUMBER(K15)),IFERROR(P15/K15-1,""),"") | ... BN17: =IF(AND(ISNUMBER(BN15),ISNUMBER(BI15)),IFERROR(BN15/BI15-1,""),"") -> 0.020938639 | BO17: =BO16+BO118 -> 0.038871923 | BP17: =BP16+BP118 -> 0.038871923 | BQ17: =IF(AND(ISNUMBER(BQ15),ISNUMBER(BL15)),IFERROR(BQ15/BL15-1,""),"") -> 0.034815464 | BR17: =CHOOSE(MATCH($BV$2,{"Bull","Base","Bear"},0),$CE$23,$CF$23,$CG$23) -> 0.08 | BS17: =CHOOSE(MATCH($BV$2,{"Bull","Base","Bear"},0),$CE$24,$CF$24,$CG$24) -> 0.08 | BT17: =CHOOSE(MATCH($BV$2,{"Bull","Base","Bear"},0),$CE$25,$CF$25,$CG$25) -> 0.07 | BU17: =CHOOSE(MATCH($BV$2,{"Bull","Base","Bear"},0),$CE$26,$CF$26,$CG$26) -> 0.07 | BV17: 2027E–2030E: scenario lever GOV_growth (Columbia/Virginia-class build rates, naval fuel, special materials / DUECE, TRISO). | BX17: =IFERROR(AVERAGE(BQ17,BR17,BS17,BT17,BU17),"n/m") -> 0.066963093 | BY17: =IFERROR(AVERAGE(AR17,AW17,BB17,BG17,BL17),"n/m") -> 0.060239497 | BZ17: =IFERROR(AVERAGE(S17,X17,AC17,AH17,AM17,AR17,AW17,BB17,BG17,BL17),"n/m") -> 0.060239497 | CA17: =IFERROR(AVERAGE(D17,I17,N17,S17,X17,AC17,AH17,AM17,AR17,AW17,BB17,BG17,BL17),"n/m") -> 0.060239497 | CD17: Capital allocation & transactions | CE17: Bull | CF17: Base | CG17: Bear
B18: Backlog adjustments, FX & de-bookings (derived) | AN18: =AN19-AN12-AN13+AN15 -> 2.22 | AO18: =AO19-AO12-AO13+AO15 -> 1.896 | AP18: =AP19-AP12-AP13+AP15 -> 1.672 | AQ18: =AQ19-AQ12-AQ13+AQ15 -> 1.54 | AR18: =AR19-AR12-AR13+AR15 -> 7.328 | AS18: =AS19-AS12-AS13+AS15 -> 0.923 | AT18: =AT19-AT12-AT13+AT15 -> 45.375 | AU18: =AU19-AU12-AU13+AU15 -> 0.604 | ... BN18: =BN19-BN12-BN13+BN15 -> 0.188 | BO18: 0 | BP18: 0 | BQ18: =SUM(BM18:BP18) -> 0.265 | BR18: 0 | BS18: 0 | BT18: 0 | BU18: 0 | BV18: Historical = closing − opening − bookings + revenues (unfunded options, FX, scope changes). Forecast: nil. | CD18: 2H/26 share repurchases ($m) | CE18: 0 | CF18: 0 | CG18: 0 | CH18: No buybacks in 1H/26; PCG funded from cash.
B19: Closing backlog | AM19: 3680.126 | AN19: 4495.617 | AO19: 4174.767 | AP19: 3813.289 | AQ19: 4532.17 | AR19: 4532.17 | AS19: 4158.335 | AT19: 3989.3 | AU19: 3686.469 | AV19: 3515.377 | AW19: 3515.377 | AX19: 3108.628 | AY19: 3405.716 | AZ19: 3258.877 | BA19: 3216.673 | BB19: 3216.673 | BC19: 2908.986 | BD19: 2865.193 | BE19: 2745.333 | BF19: 3912.58 | BG19: 3912.58 | BH19: 3583.69 | BI19: 4435.593 | BJ19: 5905.02 | BK19: 5541.291 | BL19: 5541.291 | BM19: 6931.111 | BN19: 6797.627 | BO19: =BO12+BO13-BO15+BO18 -> 6797.627 | BP19: =BP12+BP13-BP15+BP18 -> 6797.627 | BQ19: =BP19 -> 6797.627 | BR19: =BR12+BR13-BR15+BR18 -> 6928.9501 | BS19: =BS12+BS13-BS15+BS18 -> 7070.7791 | BT19: =BT12+BT13-BT15+BT18 -> 7222.5361 | BU19: =BU12+BU13-BU15+BU18 -> 7384.916 | BV19: Backlog at 30-Jun-26: $6.80bn (Government) — c.2.9x LTM segment revenues. | BX19: =IFERROR((BU19/BL19)^(1/5)-1,"n/m") -> 0.059124272 | BY19: =IFERROR((BL19/AM19)^(1/5)-1,"n/m") -> 0.085299627 | BZ19: =IFERROR((BL19/N19)^(1/10)-1,"n/m") -> n/m | CA19: =IFERROR((BL19/D19)^(1/12)-1,"n/m") -> n/m | CD19: Medical sale cash consideration ($m) | CE19: 800 | CF19: 750 | CG19: 750 | CH19: $750m base; up to $800m with shared economics (Q2-26 call).
B20: Closing backlog ÷ annual revenues (years of coverage) | C20: =IF(AND(ISNUMBER(C19),ISNUMBER(C15)),IFERROR(C19/C15,""),"") | D20: =IF(AND(ISNUMBER(D19),ISNUMBER(D15)),IFERROR(D19/D15,""),"") | I20: =IF(AND(ISNUMBER(I19),ISNUMBER(I15)),IFERROR(I19/I15,""),"") | N20: =IF(AND(ISNUMBER(N19),ISNUMBER(N15)),IFERROR(N19/N15,""),"") | S20: =IF(AND(ISNUMBER(S19),ISNUMBER(S15)),IFERROR(S19/S15,""),"") | X20: =IF(AND(ISNUMBER(X19),ISNUMBER(X15)),IFERROR(X19/X15,""),"") | AC20: =IF(AND(ISNUMBER(AC19),ISNUMBER(AC15)),IFERROR(AC19/AC15,""),"") | AH20: =IF(AND(ISNUMBER(AH19),ISNUMBER(AH15)),IFERROR(AH19/AH15,""),"") | AM20: =IF(AND(ISNUMBER(AM19),ISNUMBER(AM15)),IFERROR(AM19/AM15,""),"") -> 2.0872722 | AR20: =IF(AND(ISNUMBER(AR19),ISNUMBER(AR15)),IFERROR(AR19/AR15,""),"") -> 2.6271972 | AW20: =IF(AND(ISNUMBER(AW19),ISNUMBER(AW15)),IFERROR(AW19/AW15,""),"") -> 1.9438264 | BB20: =IF(AND(ISNUMBER(BB19),ISNUMBER(BB15)),IFERROR(BB19/BB15,""),"") -> 1.583525 | BG20: =IF(AND(ISNUMBER(BG19),ISNUMBER(BG15)),IFERROR(BG19/BG15,""),"") -> 1.7922622 | BL20: =IF(AND(ISNUMBER(BL19),ISNUMBER(BL15)),IFERROR(BL19/BL15,""),"") -> 2.3579059 | BQ20: =IF(AND(ISNUMBER(BQ19),ISNUMBER(BQ15)),IFERROR(BQ19/BQ15,""),"") -> 2.7951809 | BR20: =IF(AND(ISNUMBER(BR19),ISNUMBER(BR15)),IFERROR(BR19/BR15,""),"") -> 2.6381305 | BS20: =IF(AND(ISNUMBER(BS19),ISNUMBER(BS15)),IFERROR(BS19/BS15,""),"") -> 2.4927134 | BT20: =IF(AND(ISNUMBER(BT19),ISNUMBER(BT15)),IFERROR(BT19/BT15,""),"") -> 2.3796387 | BU20: =IF(AND(ISNUMBER(BU19),ISNUMBER(BU15)),IFERROR(BU19/BU15,""),"") -> 2.2739614 | CD20: Minimum net debt / Adjusted EBITDA (x) — buyback floor 2027E+ | CE20: 2 | CF20: 1.5 | CG20: 1 | CH20: Buybacks resume once leverage falls to the floor.
B21: Operating income (GAAP; incl. equity income of technical-services JVs) | AM21: 345.25 | AN21: 78.245 | AO21: 72.871 | AP21: 87.542 | AQ21: 90.891 | AR21: 329.549 | AS21: 72.231 | AT21: 83.783 | AU21: 77.735 | AV21: 102.752 | AW21: 336.501 | AX21: 90.56 | AY21: 82.208 | AZ21: 85.632 | BA21: 116.282 | BB21: 374.682 | BC21: 85.686 | BD21: 92.52 | BE21: 101.609 | BF21: 98.059 | BG21: 377.875 | BH21: 97.746 | BI21: 109.417 | BJ21: 97.371 | BK21: 90.314 | BL21: 394.85 | BM21: 99.141 | BN21: 105.678 | BO21: =BO24-BO23 -> 107.21967 | BP21: =BP24-BP23 -> 98.818983 | BQ21: =SUM(BM21:BP21) -> 410.85766 | BR21: =BR24-BR23 -> 455.13089 | BS21: =BS24-BS23 -> 498.99281 | BT21: =BT24-BT23 -> 541.82516 | BU21: =BU24-BU23 -> 580.06792 | BV21: Forecast = non-GAAP operating income − non-GAAP adjustments allocated to the segment. | BX21: =IFERROR((BU21/BL21)^(1/5)-1,"n/m") -> 0.079964154 | BY21: =IFERROR((BL21/AM21)^(1/5)-1,"n/m") -> 0.02721107 | BZ21: =IFERROR((BL21/N21)^(1/10)-1,"n/m") -> n/m | CA21: =IFERROR((BL21/D21)^(1/12)-1,"n/m") -> n/m
B22: Operating margin (GAAP) % | C22: =IF(AND(ISNUMBER(C21),ISNUMBER(C15)),IFERROR(C21/C15,""),"") | D22: =IF(AND(ISNUMBER(D21),ISNUMBER(D15)),IFERROR(D21/D15,""),"") | E22: =IF(AND(ISNUMBER(E21),ISNUMBER(E15)),IFERROR(E21/E15,""),"") | F22: =IF(AND(ISNUMBER(F21),ISNUMBER(F15)),IFERROR(F21/F15,""),"") | G22: =IF(AND(ISNUMBER(G21),ISNUMBER(G15)),IFERROR(G21/G15,""),"") | H22: =IF(AND(ISNUMBER(H21),ISNUMBER(H15)),IFERROR(H21/H15,""),"") | I22: =IF(AND(ISNUMBER(I21),ISNUMBER(I15)),IFERROR(I21/I15,""),"") | J22: =IF(AND(ISNUMBER(J21),ISNUMBER(J15)),IFERROR(J21/J15,""),"") | ... BU22: =IF(AND(ISNUMBER(BU21),ISNUMBER(BU15)),IFERROR(BU21/BU15,""),"") -> 0.17861436 | BX22: =IFERROR(AVERAGE(BQ22,BR22,BS22,BT22,BU22),"n/m") -> 0.17505529 | BY22: =IFERROR(AVERAGE(AR22,AW22,BB22,BG22,BL22),"n/m") -> 0.18053236 | BZ22: =IFERROR(AVERAGE(S22,X22,AC22,AH22,AM22,AR22,AW22,BB22,BG22,BL22),"n/m") -> 0.18307978 | CA22: =IFERROR(AVERAGE(D22,I22,N22,S22,X22,AC22,AH22,AM22,AR22,AW22,BB22,BG22,BL22),"n/m") -> 0.18307978 | CD22: GOV_growth (Government Operations revenues y/y) | CE22: 0.02 | CF22: Δ → | CG22: -0.025 | CH22: Naval propulsion (Columbia 1+1 / Virginia 2/yr build rates), naval fuel, special materials & DUECE enrichment, TRISO / microreactors; FY21–25 CAGR 7.5%.
B23: Non-GAAP adjustments (restructuring, acquisition costs & amortization) | AM23: =AM24-AM21 -> 0.956 | AN23: =AN24-AN21 -> 0 | AO23: =AO24-AO21 -> 0 | AP23: =AP24-AP21 -> 0.165 | AQ23: =AQ24-AQ21 -> 0 | AR23: =AR24-AR21 -> 0.165 | AS23: =AS24-AS21 -> 1.3 | AT23: =AT24-AT21 -> 0 | ... BN23: =BN24-BN21 -> 1.1 | BO23: =BN23 -> 1.1 | BP23: =BN23 -> 1.1 | BQ23: =SUM(BM23:BP23) -> 4.3 | BR23: =BR147*BR148 -> 4.5 | BS23: =BS147*BS148 -> 4.5 | BT23: =BT147*BT148 -> 4.5 | BU23: =BU147*BU148 -> 4.5 | BV23: Q3/Q4-26E: Q2/26 run-rate. 2027E+: Government share of legacy acquisition amortization (A.O.T., Kinectrics). | CD23: 2027E | CE23: =CF23+$CE$22 -> 0.1 | CF23: 0.08 | CG23: =CF23+$CG$22 -> 0.055
B24: Non-GAAP operating income | AM24: 346.206 | AN24: 78.245 | AO24: 72.871 | AP24: 87.707 | AQ24: 90.891 | AR24: 329.714 | AS24: 73.531 | AT24: 83.783 | AU24: 78.235 | AV24: 103.052 | AW24: 338.601 | AX24: 90.76 | AY24: 82.408 | AZ24: 85.632 | BA24: 117.182 | BB24: 376.082 | BC24: 85.686 | BD24: 92.82 | BE24: 101.709 | BF24: 100.559 | BG24: 380.875 | BH24: 100.646 | BI24: 115.617 | BJ24: 101.371 | BK24: 93.414 | BL24: 410.95 | BM24: 100.141 | BN24: 106.778 | BO24: =BO15*BO26 -> 108.31967 | BP24: =BP15*BP26 -> 99.918983 | BQ24: =SUM(BM24:BP24) -> 415.15766 | BR24: =BR15*BR26 -> 459.63089 | BS24: =BS15*BS26 -> 503.49281 | BT24: =BT15*BT26 -> 546.32516 | BU24: =BU15*BU26 -> 584.56792 | BV24: Company non-GAAP segment operating income (reconciliation tables, Ex. 99.1). | BX24: =IFERROR((BU24/BL24)^(1/5)-1,"n/m") -> 0.073023413 | BY24: =IFERROR((BL24/AM24)^(1/5)-1,"n/m") -> 0.034882109 | BZ24: =IFERROR((BL24/N24)^(1/10)-1,"n/m") -> n/m | CA24: =IFERROR((BL24/D24)^(1/12)-1,"n/m") -> n/m | CD24: 2028E | CE24: =CF24+$CE$22 -> 0.1 | CF24: 0.08 | CG24: =CF24+$CG$22 -> 0.055
B25: Non-GAAP margin before outlook calibration % (Q3/Q4-26E helper) | BO25: =BJ26+(SUM(BM24,BN24)/SUM(BM15,BN15)-SUM(BH24,BI24)/SUM(BH15,BI15)) -> 0.15085195 | BP25: =BK26+(SUM(BM24,BN24)/SUM(BM15,BN15)-SUM(BH24,BI24)/SUM(BH15,BI15)) -> 0.14503268 | BV25: Prior-year quarter margin + (1H/26 − 1H/25 margin drift). | CD25: 2029E | CE25: =CF25+$CE$22 -> 0.09 | CF25: 0.07 | CG25: =CF25+$CG$22 -> 0.045
B26: Non-GAAP operating margin % | C26: =IF(AND(ISNUMBER(C24),ISNUMBER(C15)),IFERROR(C24/C15,""),"") | D26: =IF(AND(ISNUMBER(D24),ISNUMBER(D15)),IFERROR(D24/D15,""),"") | E26: =IF(AND(ISNUMBER(E24),ISNUMBER(E15)),IFERROR(E24/E15,""),"") | F26: =IF(AND(ISNUMBER(F24),ISNUMBER(F15)),IFERROR(F24/F15,""),"") | G26: =IF(AND(ISNUMBER(G24),ISNUMBER(G15)),IFERROR(G24/G15,""),"") | H26: =IF(AND(ISNUMBER(H24),ISNUMBER(H15)),IFERROR(H24/H15,""),"") | I26: =IF(AND(ISNUMBER(I24),ISNUMBER(I15)),IFERROR(I24/I15,""),"") | J26: =IF(AND(ISNUMBER(J24),ISNUMBER(J15)),IFERROR(J24/J15,""),"") | ... BN26: =IF(AND(ISNUMBER(BN24),ISNUMBER(BN15)),IFERROR(BN24/BN15,""),"") -> 0.17758124 | BO26: =BO25+BO121 -> 0.1690727 | BP26: =BP25+BP121 -> 0.16325343 | BQ26: =IF(AND(ISNUMBER(BQ24),ISNUMBER(BQ15)),IFERROR(BQ24/BQ15,""),"") -> 0.17071263 | BR26: =CHOOSE(MATCH($BV$2,{"Bull","Base","Bear"},0),$CE$28,$CF$28,$CG$28) -> 0.175 | BS26: =CHOOSE(MATCH($BV$2,{"Bull","Base","Bear"},0),$CE$29,$CF$29,$CG$29) -> 0.1775 | BT26: =CHOOSE(MATCH($BV$2,{"Bull","Base","Bear"},0),$CE$30,$CF$30,$CG$30) -> 0.18 | BU26: =CHOOSE(MATCH($BV$2,{"Bull","Base","Bear"},0),$CE$31,$CF$31,$CG$31) -> 0.18 | BV26: Q3/Q4-26E: margin before calibration + Adjusted EBITDA outlook calibration Δ. 2027E+: scenario lever GOV_margin. | BX26: =IFERROR(AVERAGE(BQ26,BR26,BS26,BT26,BU26),"n/m") -> 0.17664253 | BY26: =IFERROR(AVERAGE(AR26,AW26,BB26,BG26,BL26),"n/m") -> 0.18256658 | BZ26: =IFERROR(AVERAGE(S26,X26,AC26,AH26,AM26,AR26,AW26,BB26,BG26,BL26),"n/m") -> 0.18486533 | CA26: =IFERROR(AVERAGE(D26,I26,N26,S26,X26,AC26,AH26,AM26,AR26,AW26,BB26,BG26,BL26),"n/m") -> 0.18486533 | CD26: 2030E | CE26: =CF26+$CE$22 -> 0.09 | CF26: 0.07 | CG26: =CF26+$CG$22 -> 0.045
B27: D&A (excl. acquisition amortization) % of revenues | C27: =IF(AND(ISNUMBER(C28),ISNUMBER(C15)),IFERROR(C28/C15,""),"") | D27: =IF(AND(ISNUMBER(D28),ISNUMBER(D15)),IFERROR(D28/D15,""),"") | E27: =IF(AND(ISNUMBER(E28),ISNUMBER(E15)),IFERROR(E28/E15,""),"") | F27: =IF(AND(ISNUMBER(F28),ISNUMBER(F15)),IFERROR(F28/F15,""),"") | G27: =IF(AND(ISNUMBER(G28),ISNUMBER(G15)),IFERROR(G28/G15,""),"") | H27: =IF(AND(ISNUMBER(H28),ISNUMBER(H15)),IFERROR(H28/H15,""),"") | I27: =IF(AND(ISNUMBER(I28),ISNUMBER(I15)),IFERROR(I28/I15,""),"") | J27: =IF(AND(ISNUMBER(J28),ISNUMBER(J15)),IFERROR(J28/J15,""),"") | ... BN27: =IF(AND(ISNUMBER(BN28),ISNUMBER(BN15)),IFERROR(BN28/BN15,""),"") -> 0.032692989 | BO27: =SUM(BM28,BN28)/SUM(BM15,BN15) -> 0.031538545 | BP27: =SUM(BM28,BN28)/SUM(BM15,BN15) -> 0.031538545 | BQ27: =IF(AND(ISNUMBER(BQ28),ISNUMBER(BQ15)),IFERROR(BQ28/BQ15,""),"") -> 0.031538545 | BR27: 0.036 | BS27: 0.037 | BT27: 0.038 | BU27: 0.038 | BV27: 1H/26 3.4%. Rising with the 2021–26 capacity build-out (naval, special materials, Erwin/NFS, Lynchburg). | CD27: GOV_margin (Government non-GAAP operating margin) | CE27: 0.01 | CF27: Δ → | CG27: -0.01 | CH27: FY25 17.5%; 1H/26 17.6%. Includes technical-services JV equity income.
B28: D&A excl. acquisition-related amortization | AM28: 35.398 | AN28: 9.171 | AO28: 10.334 | AP28: 10.928 | AQ28: 12.052 | AR28: 42.485 | AS28: 11.208 | AT28: 11.913 | AU28: 12.137 | AV28: 12.724 | AW28: 47.982 | AX28: 12.795 | AY28: 13.141 | AZ28: 13.417 | BA28: 14.035 | BB28: 53.388 | BC28: 14.234 | BD28: 15.431 | BE28: 15.284 | BF28: 16.079 | BG28: 61.027 | BH28: 16.296 | BI28: 17.422 | BJ28: 16.962 | BK28: 17.522 | BL28: 68.202 | BM28: 17.532 | BN28: 19.658 | BO28: =BO15*BO27 -> 20.205774 | BP28: =BP15*BP27 -> 19.303112 | BQ28: =SUM(BM28:BP28) -> 76.698887 | BR28: =BR15*BR27 -> 94.55264 | BS28: =BS15*BS27 -> 104.95343 | BT28: =BT15*BT27 -> 115.33531 | BU28: =BU15*BU27 -> 123.40878 | CD28: 2027E | CE28: =CF28+$CE$27 -> 0.185 | CF28: 0.175 | CG28: =CF28+$CG$27 -> 0.165
B29: Segment Adjusted EBITDA (non-GAAP OI + D&A ex amortization) | C29: =IF(AND(ISNUMBER(C24),ISNUMBER(C28)),C24+C28,"") | D29: =IF(AND(ISNUMBER(D24),ISNUMBER(D28)),D24+D28,"") | E29: =IF(AND(ISNUMBER(E24),ISNUMBER(E28)),E24+E28,"") | F29: =IF(AND(ISNUMBER(F24),ISNUMBER(F28)),F24+F28,"") | G29: =IF(AND(ISNUMBER(G24),ISNUMBER(G28)),G24+G28,"") | H29: =IF(AND(ISNUMBER(H24),ISNUMBER(H28)),H24+H28,"") | I29: =IF(AND(ISNUMBER(I24),ISNUMBER(I28)),I24+I28,"") | J29: =IF(AND(ISNUMBER(J24),ISNUMBER(J28)),J24+J28,"") | ... BN29: =IF(AND(ISNUMBER(BN24),ISNUMBER(BN28)),BN24+BN28,"") -> 126.436 | BO29: =BO24+BO28 -> 128.52545 | BP29: =BP24+BP28 -> 119.22209 | BQ29: =BQ24+BQ28 -> 491.85654 | BR29: =BR24+BR28 -> 554.18353 | BS29: =BS24+BS28 -> 608.44624 | BT29: =BT24+BT28 -> 661.66047 | BU29: =BU24+BU28 -> 707.9767 | BX29: =IFERROR((BU29/BL29)^(1/5)-1,"n/m") -> 0.081207705 | BY29: =IFERROR((BL29/AM29)^(1/5)-1,"n/m") -> 0.046579147 | BZ29: =IFERROR((BL29/N29)^(1/10)-1,"n/m") -> n/m | CA29: =IFERROR((BL29/D29)^(1/12)-1,"n/m") -> n/m | CD29: 2028E | CE29: =CF29+$CE$27 -> 0.1875 | CF29: 0.1775 | CG29: =CF29+$CG$27 -> 0.1675
B30: Segment Adjusted EBITDA margin % | C30: =IF(AND(ISNUMBER(C29),ISNUMBER(C15)),IFERROR(C29/C15,""),"") | D30: =IF(AND(ISNUMBER(D29),ISNUMBER(D15)),IFERROR(D29/D15,""),"") | E30: =IF(AND(ISNUMBER(E29),ISNUMBER(E15)),IFERROR(E29/E15,""),"") | F30: =IF(AND(ISNUMBER(F29),ISNUMBER(F15)),IFERROR(F29/F15,""),"") | G30: =IF(AND(ISNUMBER(G29),ISNUMBER(G15)),IFERROR(G29/G15,""),"") | H30: =IF(AND(ISNUMBER(H29),ISNUMBER(H15)),IFERROR(H29/H15,""),"") | I30: =IF(AND(ISNUMBER(I29),ISNUMBER(I15)),IFERROR(I29/I15,""),"") | J30: =IF(AND(ISNUMBER(J29),ISNUMBER(J15)),IFERROR(J29/J15,""),"") | ... BU30: =IF(AND(ISNUMBER(BU29),ISNUMBER(BU15)),IFERROR(BU29/BU15,""),"") -> 0.218 | BX30: =IFERROR(AVERAGE(BQ30,BR30,BS30,BT30,BU30),"n/m") -> 0.21275023 | BY30: =IFERROR(AVERAGE(AR30,AW30,BB30,BG30,BL30),"n/m") -> 0.20945008 | BZ30: =IFERROR(AVERAGE(S30,X30,AC30,AH30,AM30,AR30,AW30,BB30,BG30,BL30),"n/m") -> 0.21061438 | CA30: =IFERROR(AVERAGE(D30,I30,N30,S30,X30,AC30,AH30,AM30,AR30,AW30,BB30,BG30,BL30),"n/m") -> 0.21061438 | CD30: 2029E | CE30: =CF30+$CE$27 -> 0.19 | CF30: 0.18 | CG30: =CF30+$CG$27 -> 0.17
B31: Memo: segment Adjusted EBITDA as published (2022+) | AU31: 90.4 | AV31: 115.8 | AW31: 386.5 | AX31: 103.6 | AY31: 95.5 | AZ31: 99 | BA31: 131.3 | BB31: 429.4 | BC31: 99.9 | BD31: 108.2 | BE31: 117 | BF31: 116.7 | BG31: 441.9 | BH31: 116.9 | BI31: 133 | BJ31: 118.3 | BK31: 110.9 | BL31: 479.1 | BM31: 117.7 | BN31: 126.5 | CD31: 2030E | CE31: =CF31+$CE$27 -> 0.19 | CF31: 0.18 | CG31: =CF31+$CG$27 -> 0.17
B32: Check: model vs published segment Adjusted EBITDA (should be 0) | C32: =IF(AND(ISNUMBER(C29),ISNUMBER(C31)),ROUND(C29-C31,1),"") | D32: =IF(AND(ISNUMBER(D29),ISNUMBER(D31)),ROUND(D29-D31,1),"") | E32: =IF(AND(ISNUMBER(E29),ISNUMBER(E31)),ROUND(E29-E31,1),"") | F32: =IF(AND(ISNUMBER(F29),ISNUMBER(F31)),ROUND(F29-F31,1),"") | G32: =IF(AND(ISNUMBER(G29),ISNUMBER(G31)),ROUND(G29-G31,1),"") | H32: =IF(AND(ISNUMBER(H29),ISNUMBER(H31)),ROUND(H29-H31,1),"") | I32: =IF(AND(ISNUMBER(I29),ISNUMBER(I31)),ROUND(I29-I31,1),"") | J32: =IF(AND(ISNUMBER(J29),ISNUMBER(J31)),ROUND(J29-J31,1),"") | ... BN32: =IF(AND(ISNUMBER(BN29),ISNUMBER(BN31)),ROUND(BN29-BN31,1),"") -> -0.1 | CD32: GOV_btb (Government book-to-bill, x) | CE32: 0.15 | CF32: Δ → | CG32: -0.15 | CH32: FY21–25 average ~1.4x (multi-year naval awards in 2023 and 2025).
B33: Memo: segment capital expenditures | AM33: 137.197 | AN33: 45.945 | AO33: 30.073 | AP33: 34.155 | AQ33: 36.878 | AR33: 147.051 | AS33: 27.581 | AT33: 19.488 | AU33: 19.126 | AV33: 36.898 | AW33: 103.093 | AX33: 15.268 | AY33: 23.223 | AZ33: 19.624 | BA33: 33.584 | BB33: 91.699 | BC33: 16.383 | BD33: 14.201 | BE33: 22.429 | BF33: 28.05 | BG33: 81.063 | BH33: 18.5 | BI33: 15.77 | BJ33: 25.703 | BK33: 38.472 | BL33: 98.445 | BM33: 27.096 | BN33: 15.546 | CD33: 2027E | CE33: =CF33+$CE$32 -> 1.2 | CF33: 1.05 | CG33: =CF33+$CG$32 -> 0.9
CD34: 2028E | CE34: =CF34+$CE$32 -> 1.2 | CF34: 1.05 | CG34: =CF34+$CG$32 -> 0.9
B35: Commercial Operations (CANDU & U.S. components, fuel & fuel handling, field services, Kinectrics from 20-May-2025, medical isotopes (sale pending), PCG from 1-Jul-2026) | BV35: COMMERCIAL OPERATIONS — modelling logic | CD35: 2029E | CE35: =CF35+$CE$32 -> 1.2 | CF35: 1.05 | CG35: =CF35+$CG$32 -> 0.9
B36: Opening backlog | AN36: =AM67 -> 725.702 | AO36: =AN67 -> 697.169 | AP36: =AO67 -> 674.287 | AQ36: =AP67 -> 687.806 | AR36: =AM67 -> 725.702 | AS36: =AR67 -> 643.866 | AT36: =AS67 -> 748.101 | AU36: =AT67 -> 731.42 | AV36: =AU67 -> 632.416 | AW36: =AR67 -> 643.866 | AX36: =AW67 -> 628.933 | AY36: =AX67 -> 665.745 | AZ36: =AY67 -> 709.254 | BA36: =AZ67 -> 721.967 | BB36: =AW67 -> 628.933 | BC36: =BB67 -> 780.974 | BD36: =BC67 -> 726.523 | BE36: =BD67 -> 669.054 | BF36: =BE67 -> 635.356 | BG36: =BB67 -> 780.974 | BH36: =BG67 -> 929.88 | BI36: =BH67 -> 1294.99 | BJ36: =BI67 -> 1579.598 | BK36: =BJ67 -> 1484.111 | BL36: =BG67 -> 929.88 | BM36: =BL67 -> 1719.401 | BN36: =BM67 -> 1719.725 | BO36: =BN67 -> 1600.454 | BP36: =BO67 -> 1600.454 | BQ36: =BL67 -> 1719.401 | BR36: =BQ67 -> 1600.454 | BS36: =BR67 -> 1600.454 | BT36: =BS67 -> 1600.454 | BU36: =BT67 -> 1600.454 | CD36: 2030E | CE36: =CF36+$CE$32 -> 1.2 | CF36: 1.05 | CG36: =CF36+$CG$32 -> 0.9
B37: Bookings | AM37: 239.104 | AN37: 78.685 | AO37: 78.616 | AP37: 96.78 | AQ37: 70.387 | AR37: 324.468 | AS37: 204.119 | AT37: 101.84 | AU37: 2.79 | AV37: 103.609 | AW37: 412.359 | AX37: 145.686 | AY37: 164.375 | AZ37: 125.061 | BA37: 182.907 | BB37: 618.029 | BC37: 62.414 | BD37: 83.183 | BE37: 78.252 | BF37: 446.438 | BG37: 670.288 | BH37: 493.42 | BI37: 228.195 | BJ37: 159.342 | BK37: 528.774 | BL37: 1409.732 | BM37: 282.716 | BN37: 181.251 | BO37: =BO39*BO38 -> 363.35299 | BP37: =BP39*BP38 -> 424.42454 | BQ37: =SUM(BM37:BP37) -> 1251.7445 | BR37: =BR39*BR38 -> 1542.5747 | BS37: =BS39*BS38 -> 1714.6442 | BT37: =BT39*BT38 -> 1935.7917 | BU37: =BU39*BU38 -> 2168.0868 | BX37: =IFERROR((BU37/BL37)^(1/5)-1,"n/m") -> 0.089903431 | BY37: =IFERROR((BL37/AM37)^(1/5)-1,"n/m") -> 0.42596854 | BZ37: =IFERROR((BL37/N37)^(1/10)-1,"n/m") -> n/m | CA37: =IFERROR((BL37/D37)^(1/12)-1,"n/m") -> n/m | CD37: COM_growth (core Commercial revenues y/y, ex PCG / medical) | CE37: 0.05 | CF37: Δ → | CG37: -0.05 | CH37: CANDU refurbishments (Bruce MCR, Darlington, Pickering), U.S. large components, SMR components (BWRX-300 Darlington), fuel & fuel handling, Kinectrics services.
B38: Book-to-bill (x) | C38: =IF(AND(ISNUMBER(C37),ISNUMBER(C39)),IFERROR(C37/C39,""),"") | D38: =IF(AND(ISNUMBER(D37),ISNUMBER(D39)),IFERROR(D37/D39,""),"") | E38: =IF(AND(ISNUMBER(E37),ISNUMBER(E39)),IFERROR(E37/E39,""),"") | F38: =IF(AND(ISNUMBER(F37),ISNUMBER(F39)),IFERROR(F37/F39,""),"") | G38: =IF(AND(ISNUMBER(G37),ISNUMBER(G39)),IFERROR(G37/G39,""),"") | H38: =IF(AND(ISNUMBER(H37),ISNUMBER(H39)),IFERROR(H37/H39,""),"") | I38: =IF(AND(ISNUMBER(I37),ISNUMBER(I39)),IFERROR(I37/I39,""),"") | J38: =IF(AND(ISNUMBER(J37),ISNUMBER(J39)),IFERROR(J37/J39,""),"") | ... BN38: =IF(AND(ISNUMBER(BN37),ISNUMBER(BN39)),IFERROR(BN37/BN39,""),"") -> 0.59915309 | BO38: 1 | BP38: 1 | BQ38: =IF(AND(ISNUMBER(BQ37),ISNUMBER(BQ39)),IFERROR(BQ37/BQ39,""),"") -> 0.91106563 | BR38: =CHOOSE(MATCH($BV$2,{"Bull","Base","Bear"},0),$CE$48,$CF$48,$CG$48) -> 1 | BS38: =CHOOSE(MATCH($BV$2,{"Bull","Base","Bear"},0),$CE$49,$CF$49,$CG$49) -> 1 | BT38: =CHOOSE(MATCH($BV$2,{"Bull","Base","Bear"},0),$CE$50,$CF$50,$CG$50) -> 1 | BU38: =CHOOSE(MATCH($BV$2,{"Bull","Base","Bear"},0),$CE$51,$CF$51,$CG$51) -> 1 | BV38: 2027E+: scenario lever COM_btb (CANDU refurbishments, U.S. large-component & SMR orders, fuel). | CD38: 2027E | CE38: =CF38+$CE$37 -> 0.2 | CF38: 0.15 | CG38: =CF38+$CG$37 -> 0.1
B39: Revenues | AM39: 371.269 | AN39: 107.398 | AO39: 101.842 | AP39: 83.382 | AQ39: 114.46 | AR39: 407.082 | AS39: 99.95 | AT39: 118.522 | AU39: 101.794 | AV39: 107.092 | AW39: 427.358 | AX39: 108.924 | AY39: 120.92 | AZ39: 112.359 | BA39: 124.141 | BB39: 466.344 | BC39: 117.038 | BD39: 141.491 | BE39: 113.112 | BF39: 152.331 | BG39: 523.972 | BH39: 128.31 | BI39: 176.139 | BJ39: 250.971 | BK39: 297.65 | BL39: 853.07 | BM39: 283.645 | BN39: 302.512 | BO39: =BJ39*(1+BO41)+BO47 -> 363.35299 | BP39: =BK39*(1+BP41)+BP47 -> 424.42454 | BQ39: =SUM(BM39:BP39) -> 1373.9345 | BR39: =BR42+BR47+BR48 -> 1542.5747 | BS39: =BS42+BS47+BS48 -> 1714.6442 | BT39: =BT42+BT47+BT48 -> 1935.7917 | BU39: =BU42+BU47+BU48 -> 2168.0868 | BV39: Q3/Q4-26E: prior-year quarter × (1 + organic growth + calibration Δ) + PCG. 2027E+: core (ex PCG, ex medical) + PCG + medical until closing. | BX39: =IFERROR((BU39/BL39)^(1/5)-1,"n/m") -> 0.20508699 | BY39: =IFERROR((BL39/AM39)^(1/5)-1,"n/m") -> 0.18102529 | BZ39: =IFERROR((BL39/N39)^(1/10)-1,"n/m") -> n/m | CA39: =IFERROR((BL39/D39)^(1/12)-1,"n/m") -> n/m | CD39: 2028E | CE39: =CF39+$CE$37 -> 0.19 | CF39: 0.14 | CG39: =CF39+$CG$37 -> 0.09
B40: Q3/Q4-26E organic growth input (before revenue calibration) | BO40: 0.3 | BP40: 0.3 | BV40: Input: 1H/26 Commercial +93% y/y is inflated by Kinectrics (closed 20-May-2025, in the base from Q3/25); Q1/26 organic ex-Kinectrics ~+39%. | CD40: 2029E | CE40: =CF40+$CE$37 -> 0.18 | CF40: 0.13 | CG40: =CF40+$CG$37 -> 0.08
B41: Revenues y/y % (Q3/Q4-26E: organic, incl. calibration) | D41: =IF(AND(ISNUMBER(D39),ISNUMBER(C39)),IFERROR(D39/C39-1,""),"") | I41: =IF(AND(ISNUMBER(I39),ISNUMBER(D39)),IFERROR(I39/D39-1,""),"") | J41: =IF(AND(ISNUMBER(J39),ISNUMBER(E39)),IFERROR(J39/E39-1,""),"") | K41: =IF(AND(ISNUMBER(K39),ISNUMBER(F39)),IFERROR(K39/F39-1,""),"") | L41: =IF(AND(ISNUMBER(L39),ISNUMBER(G39)),IFERROR(L39/G39-1,""),"") | M41: =IF(AND(ISNUMBER(M39),ISNUMBER(H39)),IFERROR(M39/H39-1,""),"") | N41: =IF(AND(ISNUMBER(N39),ISNUMBER(I39)),IFERROR(N39/I39-1,""),"") | O41: =IF(AND(ISNUMBER(O39),ISNUMBER(J39)),IFERROR(O39/J39-1,""),"") | P41: =IF(AND(ISNUMBER(P39),ISNUMBER(K39)),IFERROR(P39/K39-1,""),"") | ... BN41: =IF(AND(ISNUMBER(BN39),ISNUMBER(BI39)),IFERROR(BN39/BI39-1,""),"") -> 0.71746178 | BO41: =BO40+BO118 -> 0.30833039 | BP41: =BP40+BP118 -> 0.30833039 | BQ41: =IF(AND(ISNUMBER(BQ39),ISNUMBER(BL39)),IFERROR(BQ39/BL39-1,""),"") -> 0.61057654 | BR41: =IF(AND(ISNUMBER(BR39),ISNUMBER(BQ39)),IFERROR(BR39/BQ39-1,""),"") -> 0.12274251 | BS41: =IF(AND(ISNUMBER(BS39),ISNUMBER(BR39)),IFERROR(BS39/BR39-1,""),"") -> 0.11154692 | BT41: =IF(AND(ISNUMBER(BT39),ISNUMBER(BS39)),IFERROR(BT39/BS39-1,""),"") -> 0.12897579 | BU41: =IF(AND(ISNUMBER(BU39),ISNUMBER(BT39)),IFERROR(BU39/BT39-1,""),"") -> 0.12 | BX41: =IFERROR(AVERAGE(BQ41,BR41,BS41,BT41,BU41),"n/m") -> 0.21876835 | BY41: =IFERROR(AVERAGE(AR41,AW41,BB41,BG41,BL41),"n/m") -> 0.1978304 | BZ41: =IFERROR(AVERAGE(S41,X41,AC41,AH41,AM41,AR41,AW41,BB41,BG41,BL41),"n/m") -> 0.1978304 | CA41: =IFERROR(AVERAGE(D41,I41,N41,S41,X41,AC41,AH41,AM41,AR41,AW41,BB41,BG41,BL41),"n/m") -> 0.1978304 | CD41: 2030E | CE41: =CF41+$CE$37 -> 0.17 | CF41: 0.12 | CG41: =CF41+$CG$37 -> 0.07
B42: Core Commercial revenues (ex PCG, ex medical) | BQ42: =BQ39-BQ47-BQ48 -> 1173.9345 | BR42: =BQ42*(1+BR43) -> 1350.0247 | BS42: =BR42*(1+BS43) -> 1539.0282 | BT42: =BS42*(1+BT43) -> 1739.1018 | BU42: =BT42*(1+BU43) -> 1947.794 | BV42: 2026E = segment revenues − PCG − medical (2026E medical ~$130m per Q2-26 call). 2027E+: × (1 + COM_growth). | CD42: COM_margin (core + PCG non-GAAP operating margin) | CE42: 0.015 | CF42: Δ → | CG42: -0.015 | CH42: FY25 10.2%; 1H/26 9.9%. Operating leverage on Cambridge capacity.
B43: Core Commercial revenues y/y % | BR43: =CHOOSE(MATCH($BV$2,{"Bull","Base","Bear"},0),$CE$38,$CF$38,$CG$38) -> 0.15 | BS43: =CHOOSE(MATCH($BV$2,{"Bull","Base","Bear"},0),$CE$39,$CF$39,$CG$39) -> 0.14 | BT43: =CHOOSE(MATCH($BV$2,{"Bull","Base","Bear"},0),$CE$40,$CF$40,$CG$40) -> 0.13 | BU43: =CHOOSE(MATCH($BV$2,{"Bull","Base","Bear"},0),$CE$41,$CF$41,$CG$41) -> 0.12 | BV43: 2027E–2030E: scenario lever COM_growth (Bruce/Darlington/Pickering refurbishments, U.S. components incl. Mt. Vernon/PCG capacity, SMR (BWRX-300) components, fuel handling). | CD43: 2027E | CE43: =CF43+$CE$42 -> 0.135 | CF43: 0.12 | CG43: =CF43+$CG$42 -> 0.105
B44: PCG — FY2025 revenues (pre-acquisition; ~$125m) | BQ44: 125 | BV44: Precision Components Group (Precision Custom Components, DC Fabricators); FY2025 revenue ~$125m (press reports of the Apr-2026 announcement). Purchase price not disclosed. | CD44: 2028E | CE44: =CF44+$CE$42 -> 0.14 | CF44: 0.125 | CG44: =CF44+$CG$42 -> 0.11
B45: PCG — revenue growth % | BQ45: 0.12 | BR45: 0.12 | BS45: 0.12 | BT45: 0.12 | BU45: 0.12 | BV45: Input: heavy-walled / heat-transfer components; U.S. nuclear new-build demand. | CD45: 2029E | CE45: =CF45+$CE$42 -> 0.145 | CF45: 0.13 | CG45: =CF45+$CG$42 -> 0.115
B46: PCG — annual revenue run-rate | BQ46: =BQ44*(1+BQ45) -> 140 | BR46: =BQ46*(1+BR45) -> 156.8 | BS46: =BR46*(1+BS45) -> 175.616 | BT46: =BS46*(1+BT45) -> 196.68992 | BU46: =BT46*(1+BU45) -> 220.29271 | CD46: 2030E | CE46: =CF46+$CE$42 -> 0.15 | CF46: 0.135 | CG46: =CF46+$CG$42 -> 0.12
B47: PCG — revenues consolidated (from 1-Jul-2026) | BO47: =$BQ$46/4 -> 35 | BP47: =$BQ$46/4 -> 35 | BQ47: =SUM(BM47:BP47) -> 70 | BR47: =BR46 -> 156.8 | BS47: =BS46 -> 175.616 | BT47: =BT46 -> 196.68992 | BU47: =BU46 -> 220.29271 | BV47: Closed 1-Jul-2026 (Q2-26 10-Q note 2): Q3/26E and Q4/26E = one quarter of run-rate each. | CD47: COM_btb (Commercial book-to-bill, x) | CE47: 0.1 | CF47: Δ → | CG47: -0.1 | CH47: FY25 1.65x incl. Kinectrics; 1H/26 0.79x.
B48: Medical — revenues (BWXT Medical + Kinectrics stable isotopes; sale to Nordic Capital pending) | BM48: 32.5 | BN48: 32.5 | BO48: 32.5 | BP48: 32.5 | BQ48: =SUM(BM48:BP48) -> 130 | BR48: =BQ48*(1+BR49)*BR50 -> 35.75 | BS48: =BR48*(1+BS49)*BS50 -> 0 | BT48: =BS48*(1+BT49)*BT50 -> 0 | BU48: =BT48*(1+BU49)*BU50 -> 0 | BV48: Not separately reported: ~$130m 2026 revenue per Q2-26 call (spread evenly; estimate). Sale agreed 31-Jul-2026; closing expected 2026 or Q1-2027 → modelled 31-Mar-2027. | CD48: 2027E | CE48: =CF48+$CE$47 -> 1.1 | CF48: 1 | CG48: =CF48+$CG$47 -> 0.9
B49: Medical — revenue growth % | BR49: 0.1 | BS49: 0 | BT49: 0 | BU49: 0 | CD49: 2028E | CE49: =CF49+$CE$47 -> 1.1 | CF49: 1 | CG49: =CF49+$CG$47 -> 0.9
B50: Medical — share of year consolidated | BR50: 0.25 | BS50: 0 | BT50: 0 | BU50: 0 | BV50: Closing assumed 31-Mar-2027 (one quarter of 2027E consolidated). | CD50: 2029E | CE50: =CF50+$CE$47 -> 1.1 | CF50: 1 | CG50: =CF50+$CG$47 -> 0.9
B51: Medical — non-GAAP operating margin % | BR51: 0.12 | BS51: 0.12 | BT51: 0.12 | BU51: 0.12 | BV51: Company: margin "modestly accretive" to the Commercial segment average (Q2-26 call). Estimate. | CD51: 2030E | CE51: =CF51+$CE$47 -> 1.1 | CF51: 1 | CG51: =CF51+$CG$47 -> 0.9
B52: Operating income (GAAP) | AM52: 36.915 | AN52: 6.294 | AO52: 5.64 | AP52: 4.925 | AQ52: 18.384 | AR52: 35.243 | AS52: 3.962 | AT52: 12.864 | AU52: 6.847 | AV52: 3.745 | AW52: 27.418 | AX52: 1.513 | AY52: 11.017 | AZ52: 9.083 | BA52: 15.919 | BB52: 37.532 | BC52: 8.591 | BD52: 16.628 | BE52: 6.728 | BF52: 14.868 | BG52: 46.816 | BH52: 6.466 | BI52: 6.877 | BJ52: 23.959 | BK52: 20.427 | BL52: 57.728 | BM52: 24.029 | BN52: 24.332 | BO52: =BO55-BO54 -> 42.041856 | BP52: =BP55-BP54 -> 54.165988 | BQ52: =SUM(BM52:BP52) -> 144.56884 | BR52: =BR55-BR54 -> 170.60896 | BS52: =BS55-BS54 -> 199.83052 | BT52: =BT55-BT54 -> 237.15293 | BU52: =BU55-BU54 -> 278.19171 | BX52: =IFERROR((BU52/BL52)^(1/5)-1,"n/m") -> 0.36959302 | BY52: =IFERROR((BL52/AM52)^(1/5)-1,"n/m") -> 0.093545173 | BZ52: =IFERROR((BL52/N52)^(1/10)-1,"n/m") -> n/m | CA52: =IFERROR((BL52/D52)^(1/12)-1,"n/m") -> n/m | CD52: MA_spend (bolt-on acquisitions, $m) | CE52: 150 | CF52: Δ → | CG52: -150 | CH52: Base: digest PCG / medical exit in 2027E; bolt-ons resume 2028E.
B53: Operating margin (GAAP) % | C53: =IF(AND(ISNUMBER(C52),ISNUMBER(C39)),IFERROR(C52/C39,""),"") | D53: =IF(AND(ISNUMBER(D52),ISNUMBER(D39)),IFERROR(D52/D39,""),"") | E53: =IF(AND(ISNUMBER(E52),ISNUMBER(E39)),IFERROR(E52/E39,""),"") | F53: =IF(AND(ISNUMBER(F52),ISNUMBER(F39)),IFERROR(F52/F39,""),"") | G53: =IF(AND(ISNUMBER(G52),ISNUMBER(G39)),IFERROR(G52/G39,""),"") | H53: =IF(AND(ISNUMBER(H52),ISNUMBER(H39)),IFERROR(H52/H39,""),"") | I53: =IF(AND(ISNUMBER(I52),ISNUMBER(I39)),IFERROR(I52/I39,""),"") | J53: =IF(AND(ISNUMBER(J52),ISNUMBER(J39)),IFERROR(J52/J39,""),"") | ... BU53: =IF(AND(ISNUMBER(BU52),ISNUMBER(BU39)),IFERROR(BU52/BU39,""),"") -> 0.12831208 | BX53: =IFERROR(AVERAGE(BQ53,BR53,BS53,BT53,BU53),"n/m") -> 0.11663754 | BY53: =IFERROR(AVERAGE(AR53,AW53,BB53,BG53,BL53),"n/m") -> 0.077646442 | BZ53: =IFERROR(AVERAGE(S53,X53,AC53,AH53,AM53,AR53,AW53,BB53,BG53,BL53),"n/m") -> 0.08127691 | CA53: =IFERROR(AVERAGE(D53,I53,N53,S53,X53,AC53,AH53,AM53,AR53,AW53,BB53,BG53,BL53),"n/m") -> 0.08127691 | CD53: 2027E | CE53: =CF53+$CE$52 -> 150 | CF53: 0 | CG53: =MAX(0,CF53+$CG$52) -> 0
B54: Non-GAAP adjustments (restructuring, acquisition costs & amortization) | AM54: =AM55-AM52 -> 2.253 | AN54: =AN55-AN52 -> 0 | AO54: =AO55-AO52 -> 0 | AP54: =AP55-AP52 -> 0.319 | AQ54: =AQ55-AQ52 -> 0.59 | AR54: =AR55-AR52 -> 0.909 | AS54: =AS55-AS52 -> 1.9 | AT54: =AT55-AT52 -> 0.2 | ... BN54: =BN55-BN52 -> 4.4 | BO54: =BN54+BO153 -> 6.65 | BP54: =BN54+BP153 -> 6.65 | BQ54: =SUM(BM54:BP54) -> 22.9 | BR54: =BR147*(1-BR148)+BR153 -> 14.5 | BS54: =BS147*(1-BS148)+BS153 -> 14.5 | BT54: =BT147*(1-BT148)+BT153 -> 14.5 | BU54: =BU147*(1-BU148)+BU153 -> 14.5 | BV54: 2027E+: Commercial share of legacy amortization (Kinectrics) + PCG intangibles amortization. | CD54: 2028E | CE54: =CF54+$CE$52 -> 300 | CF54: 150 | CG54: =MAX(0,CF54+$CG$52) -> 0
B55: Non-GAAP operating income | AM55: 39.168 | AN55: 6.294 | AO55: 5.64 | AP55: 5.244 | AQ55: 18.974 | AR55: 36.152 | AS55: 5.862 | AT55: 13.064 | AU55: 6.847 | AV55: 9.345 | AW55: 35.118 | AX55: 4.613 | AY55: 11.517 | AZ55: 9.383 | BA55: 16.919 | BB55: 42.232 | BC55: 9.391 | BD55: 18.128 | BE55: 9.228 | BF55: 19.068 | BG55: 55.916 | BH55: 9.866 | BI55: 10.677 | BJ55: 29.059 | BK55: 37.227 | BL55: 86.828 | BM55: 29.229 | BN55: 28.732 | BO55: =BO39*BO57 -> 48.691856 | BP55: =BP39*BP57 -> 60.815988 | BQ55: =SUM(BM55:BP55) -> 167.46884 | BR55: =(BR42+BR47)*BR58+BR48*BR51 -> 185.10896 | BS55: =(BS42+BS47)*BS58+BS48*BS51 -> 214.33052 | BT55: =(BT42+BT47)*BT58+BT48*BT51 -> 251.65293 | BU55: =(BU42+BU47)*BU58+BU48*BU51 -> 292.69171 | BX55: =IFERROR((BU55/BL55)^(1/5)-1,"n/m") -> 0.27511726 | BY55: =IFERROR((BL55/AM55)^(1/5)-1,"n/m") -> 0.17258863 | BZ55: =IFERROR((BL55/N55)^(1/10)-1,"n/m") -> n/m | CA55: =IFERROR((BL55/D55)^(1/12)-1,"n/m") -> n/m | CD55: 2029E | CE55: =CF55+$CE$52 -> 300 | CF55: 150 | CG55: =MAX(0,CF55+$CG$52) -> 0
B56: Non-GAAP margin before outlook calibration % (Q3/Q4-26E helper) | BO56: =BJ57 -> 0.11578629 | BP56: =BK57 -> 0.12506971 | BV56: Prior-year quarter margin (already includes a full quarter of Kinectrics); no 1H drift applied (1H/25 base pre-dates Kinectrics). | CD56: 2030E | CE56: =CF56+$CE$52 -> 300 | CF56: 150 | CG56: =MAX(0,CF56+$CG$52) -> 0
B57: Non-GAAP operating margin % | C57: =IF(AND(ISNUMBER(C55),ISNUMBER(C39)),IFERROR(C55/C39,""),"") | D57: =IF(AND(ISNUMBER(D55),ISNUMBER(D39)),IFERROR(D55/D39,""),"") | E57: =IF(AND(ISNUMBER(E55),ISNUMBER(E39)),IFERROR(E55/E39,""),"") | F57: =IF(AND(ISNUMBER(F55),ISNUMBER(F39)),IFERROR(F55/F39,""),"") | G57: =IF(AND(ISNUMBER(G55),ISNUMBER(G39)),IFERROR(G55/G39,""),"") | H57: =IF(AND(ISNUMBER(H55),ISNUMBER(H39)),IFERROR(H55/H39,""),"") | I57: =IF(AND(ISNUMBER(I55),ISNUMBER(I39)),IFERROR(I55/I39,""),"") | J57: =IF(AND(ISNUMBER(J55),ISNUMBER(J39)),IFERROR(J55/J39,""),"") | ... BN57: =IF(AND(ISNUMBER(BN55),ISNUMBER(BN39)),IFERROR(BN55/BN39,""),"") -> 0.09497805 | BO57: =BO56+BO121 -> 0.13400704 | BP57: =BP56+BP121 -> 0.14329046 | BQ57: =IF(AND(ISNUMBER(BQ55),ISNUMBER(BQ39)),IFERROR(BQ55/BQ39,""),"") -> 0.12188997 | BR57: =IF(AND(ISNUMBER(BR55),ISNUMBER(BR39)),IFERROR(BR55/BR39,""),"") -> 0.12 | BS57: =IF(AND(ISNUMBER(BS55),ISNUMBER(BS39)),IFERROR(BS55/BS39,""),"") -> 0.125 | BT57: =IF(AND(ISNUMBER(BT55),ISNUMBER(BT39)),IFERROR(BT55/BT39,""),"") -> 0.13 | BU57: =IF(AND(ISNUMBER(BU55),ISNUMBER(BU39)),IFERROR(BU55/BU39,""),"") -> 0.135 | BX57: =IFERROR(AVERAGE(BQ57,BR57,BS57,BT57,BU57),"n/m") -> 0.12637799 | BY57: =IFERROR(AVERAGE(AR57,AW57,BB57,BG57,BL57),"n/m") -> 0.094008136 | BZ57: =IFERROR(AVERAGE(S57,X57,AC57,AH57,AM57,AR57,AW57,BB57,BG57,BL57),"n/m") -> 0.095923052 | CA57: =IFERROR(AVERAGE(D57,I57,N57,S57,X57,AC57,AH57,AM57,AR57,AW57,BB57,BG57,BL57),"n/m") -> 0.095923052
B58: Core + PCG non-GAAP operating margin % | BR58: =CHOOSE(MATCH($BV$2,{"Bull","Base","Bear"},0),$CE$43,$CF$43,$CG$43) -> 0.12 | BS58: =CHOOSE(MATCH($BV$2,{"Bull","Base","Bear"},0),$CE$44,$CF$44,$CG$44) -> 0.125 | BT58: =CHOOSE(MATCH($BV$2,{"Bull","Base","Bear"},0),$CE$45,$CF$45,$CG$45) -> 0.13 | BU58: =CHOOSE(MATCH($BV$2,{"Bull","Base","Bear"},0),$CE$46,$CF$46,$CG$46) -> 0.135 | BV58: 2027E–2030E: scenario lever COM_margin (FY25 10.2%; 1H/26 9.9% with growth SG&A, Kinectrics integration).
B59: D&A (excl. acquisition amortization) % of revenues | C59: =IF(AND(ISNUMBER(C60),ISNUMBER(C39)),IFERROR(C60/C39,""),"") | D59: =IF(AND(ISNUMBER(D60),ISNUMBER(D39)),IFERROR(D60/D39,""),"") | E59: =IF(AND(ISNUMBER(E60),ISNUMBER(E39)),IFERROR(E60/E39,""),"") | F59: =IF(AND(ISNUMBER(F60),ISNUMBER(F39)),IFERROR(F60/F39,""),"") | G59: =IF(AND(ISNUMBER(G60),ISNUMBER(G39)),IFERROR(G60/G39,""),"") | H59: =IF(AND(ISNUMBER(H60),ISNUMBER(H39)),IFERROR(H60/H39,""),"") | I59: =IF(AND(ISNUMBER(I60),ISNUMBER(I39)),IFERROR(I60/I39,""),"") | J59: =IF(AND(ISNUMBER(J60),ISNUMBER(J39)),IFERROR(J60/J39,""),"") | ... BN59: =IF(AND(ISNUMBER(BN60),ISNUMBER(BN39)),IFERROR(BN60/BN39,""),"") -> 0.024194082 | BO59: =SUM(BM60,BN60)/SUM(BM39,BN39) -> 0.024851704 | BP59: =SUM(BM60,BN60)/SUM(BM39,BN39) -> 0.024851704 | BQ59: =IF(AND(ISNUMBER(BQ60),ISNUMBER(BQ39)),IFERROR(BQ60/BQ39,""),"") -> 0.024851704 | BR59: 0.028 | BS59: 0.029 | BT59: 0.03 | BU59: 0.03 | BV59: 1H/26 2.5%; Cambridge expansion and PCG capacity raise the D&A run-rate.
B60: D&A excl. acquisition-related amortization | AM60: 18.431 | AN60: 4.917 | AO60: 5.037 | AP60: 4.985 | AQ60: 4.945 | AR60: 19.884 | AS60: 4.829 | AT60: 5.033 | AU60: 4.603 | AV60: 4.34 | AW60: 18.805 | AX60: 4.359 | AY60: 4.362 | AZ60: 4.557 | BA60: 4.467 | BB60: 17.745 | BC60: 4.444 | BD60: 4.397 | BE60: 4.313 | BF60: 4.554 | BG60: 17.708 | BH60: 4.019 | BI60: 5.543 | BJ60: 6.365 | BK60: 7.273 | BL60: 23.201 | BM60: 7.248 | BN60: 7.319 | BO60: =BO39*BO59 -> 9.0299407 | BP60: =BP39*BP59 -> 10.547673 | BQ60: =SUM(BM60:BP60) -> 34.144614 | BR60: =BR39*BR59 -> 43.192092 | BS60: =BS39*BS59 -> 49.724681 | BT60: =BT39*BT59 -> 58.073752 | BU60: =BU39*BU59 -> 65.042603
B61: Segment Adjusted EBITDA (non-GAAP OI + D&A ex amortization) | C61: =IF(AND(ISNUMBER(C55),ISNUMBER(C60)),C55+C60,"") | D61: =IF(AND(ISNUMBER(D55),ISNUMBER(D60)),D55+D60,"") | E61: =IF(AND(ISNUMBER(E55),ISNUMBER(E60)),E55+E60,"") | F61: =IF(AND(ISNUMBER(F55),ISNUMBER(F60)),F55+F60,"") | G61: =IF(AND(ISNUMBER(G55),ISNUMBER(G60)),G55+G60,"") | H61: =IF(AND(ISNUMBER(H55),ISNUMBER(H60)),H55+H60,"") | I61: =IF(AND(ISNUMBER(I55),ISNUMBER(I60)),I55+I60,"") | J61: =IF(AND(ISNUMBER(J55),ISNUMBER(J60)),J55+J60,"") | ... BN61: =IF(AND(ISNUMBER(BN55),ISNUMBER(BN60)),BN55+BN60,"") -> 36.051 | BO61: =BO55+BO60 -> 57.721797 | BP61: =BP55+BP60 -> 71.363661 | BQ61: =BQ55+BQ60 -> 201.61346 | BR61: =BR55+BR60 -> 228.30106 | BS61: =BS55+BS60 -> 264.0552 | BT61: =BT55+BT60 -> 309.72668 | BU61: =BU55+BU60 -> 357.73431 | BX61: =IFERROR((BU61/BL61)^(1/5)-1,"n/m") -> 0.2659329 | BY61: =IFERROR((BL61/AM61)^(1/5)-1,"n/m") -> 0.13819964 | BZ61: =IFERROR((BL61/N61)^(1/10)-1,"n/m") -> n/m | CA61: =IFERROR((BL61/D61)^(1/12)-1,"n/m") -> n/m
B62: Segment Adjusted EBITDA margin % | C62: =IF(AND(ISNUMBER(C61),ISNUMBER(C39)),IFERROR(C61/C39,""),"") | D62: =IF(AND(ISNUMBER(D61),ISNUMBER(D39)),IFERROR(D61/D39,""),"") | E62: =IF(AND(ISNUMBER(E61),ISNUMBER(E39)),IFERROR(E61/E39,""),"") | F62: =IF(AND(ISNUMBER(F61),ISNUMBER(F39)),IFERROR(F61/F39,""),"") | G62: =IF(AND(ISNUMBER(G61),ISNUMBER(G39)),IFERROR(G61/G39,""),"") | H62: =IF(AND(ISNUMBER(H61),ISNUMBER(H39)),IFERROR(H61/H39,""),"") | I62: =IF(AND(ISNUMBER(I61),ISNUMBER(I39)),IFERROR(I61/I39,""),"") | J62: =IF(AND(ISNUMBER(J61),ISNUMBER(J39)),IFERROR(J61/J39,""),"") | ... BU62: =IF(AND(ISNUMBER(BU61),ISNUMBER(BU39)),IFERROR(BU61/BU39,""),"") -> 0.165 | BX62: =IFERROR(AVERAGE(BQ62,BR62,BS62,BT62,BU62),"n/m") -> 0.15474834 | BY62: =IFERROR(AVERAGE(AR62,AW62,BB62,BG62,BL62),"n/m") -> 0.13238657 | BZ62: =IFERROR(AVERAGE(S62,X62,AC62,AH62,AM62,AR62,AW62,BB62,BG62,BL62),"n/m") -> 0.13617896 | CA62: =IFERROR(AVERAGE(D62,I62,N62,S62,X62,AC62,AH62,AM62,AR62,AW62,BB62,BG62,BL62),"n/m") -> 0.13617896
B63: Memo: segment Adjusted EBITDA as published (2022+) | AU63: 11.5 | AV63: 13.6 | AW63: 53.9 | AX63: 8.9 | AY63: 15.8 | AZ63: 13.9 | BA63: 21.3 | BB63: 60 | BC63: 13.9 | BD63: 22.5 | BE63: 13.5 | BF63: 23.7 | BG63: 73.6 | BH63: 14 | BI63: 16.2 | BJ63: 35.5 | BK63: 44.4 | BL63: 110.1 | BM63: 36.5 | BN63: 36.1
B64: Check: model vs published segment Adjusted EBITDA (should be 0) | C64: =IF(AND(ISNUMBER(C61),ISNUMBER(C63)),ROUND(C61-C63,1),"") | D64: =IF(AND(ISNUMBER(D61),ISNUMBER(D63)),ROUND(D61-D63,1),"") | E64: =IF(AND(ISNUMBER(E61),ISNUMBER(E63)),ROUND(E61-E63,1),"") | F64: =IF(AND(ISNUMBER(F61),ISNUMBER(F63)),ROUND(F61-F63,1),"") | G64: =IF(AND(ISNUMBER(G61),ISNUMBER(G63)),ROUND(G61-G63,1),"") | H64: =IF(AND(ISNUMBER(H61),ISNUMBER(H63)),ROUND(H61-H63,1),"") | I64: =IF(AND(ISNUMBER(I61),ISNUMBER(I63)),ROUND(I61-I63,1),"") | J64: =IF(AND(ISNUMBER(J61),ISNUMBER(J63)),ROUND(J61-J63,1),"") | ... BN64: =IF(AND(ISNUMBER(BN61),ISNUMBER(BN63)),ROUND(BN61-BN63,1),"") -> 0
B65: Memo: segment capital expenditures | AM65: 106.614 | AN65: 53.531 | AO65: 34.364 | AP65: 30.546 | AQ65: 35.13 | AR65: 153.571 | AS65: 24.1 | AT65: 21.644 | AU65: 17.815 | AV65: 25.294 | AW65: 88.853 | AX65: 13.951 | AY65: 15.777 | AZ65: 10.861 | BA65: 12.769 | BB65: 53.358 | BC65: 13.344 | BD65: 15.736 | BE65: 14.073 | BF65: 19.62 | BG65: 62.773 | BH65: 13.209 | BI65: 16.701 | BJ65: 21.368 | BK65: 25.803 | BL65: 77.081 | BM65: 14.286 | BN65: 24.011
B66: Backlog adjustments, FX & de-bookings (derived) | AN66: =AN67-AN36-AN37+AN39 -> 0.18 | AO66: =AO67-AO36-AO37+AO39 -> 0.344 | AP66: =AP67-AP36-AP37+AP39 -> 0.121 | AQ66: =AQ67-AQ36-AQ37+AQ39 -> 0.133 | AR66: =AR67-AR36-AR37+AR39 -> 0.778 | AS66: =AS67-AS36-AS37+AS39 -> 0.066 | AT66: =AT67-AT36-AT37+AT39 -> 0.001 | AU66: =AU67-AU36-AU37+AU39 -> 0 | ... BN66: =BN67-BN36-BN37+BN39 -> 1.99 | BO66: 0 | BP66: 0 | BQ66: =SUM(BM66:BP66) -> 3.243 | BR66: 0 | BS66: 0 | BT66: 0 | BU66: 0
B67: Closing backlog | AM67: 725.702 | AN67: 697.169 | AO67: 674.287 | AP67: 687.806 | AQ67: 643.866 | AR67: 643.866 | AS67: 748.101 | AT67: 731.42 | AU67: 632.416 | AV67: 628.933 | AW67: 628.933 | AX67: 665.745 | AY67: 709.254 | AZ67: 721.967 | BA67: 780.974 | BB67: 780.974 | BC67: 726.523 | BD67: 669.054 | BE67: 635.356 | BF67: 929.88 | BG67: 929.88 | BH67: 1294.99 | BI67: 1579.598 | BJ67: 1484.111 | BK67: 1719.401 | BL67: 1719.401 | BM67: 1719.725 | BN67: 1600.454 | BO67: =BO36+BO37-BO39+BO66 -> 1600.454 | BP67: =BP36+BP37-BP39+BP66 -> 1600.454 | BQ67: =BP67 -> 1600.454 | BR67: =BR36+BR37-BR39+BR66 -> 1600.454 | BS67: =BS36+BS37-BS39+BS66 -> 1600.454 | BT67: =BT36+BT37-BT39+BT66 -> 1600.454 | BU67: =BU36+BU37-BU39+BU66 -> 1600.454 | BV67: Backlog at 30-Jun-26: $1.60bn (Commercial). Medical backlog leaves with the divestiture (not separately disclosed; ignored). | BX67: =IFERROR((BU67/BL67)^(1/5)-1,"n/m") -> -0.014235431 | BY67: =IFERROR((BL67/AM67)^(1/5)-1,"n/m") -> 0.18829364 | BZ67: =IFERROR((BL67/N67)^(1/10)-1,"n/m") -> n/m | CA67: =IFERROR((BL67/D67)^(1/12)-1,"n/m") -> n/m
B68: Closing backlog ÷ annual revenues (years of coverage) | C68: =IF(AND(ISNUMBER(C67),ISNUMBER(C39)),IFERROR(C67/C39,""),"") | D68: =IF(AND(ISNUMBER(D67),ISNUMBER(D39)),IFERROR(D67/D39,""),"") | I68: =IF(AND(ISNUMBER(I67),ISNUMBER(I39)),IFERROR(I67/I39,""),"") | N68: =IF(AND(ISNUMBER(N67),ISNUMBER(N39)),IFERROR(N67/N39,""),"") | S68: =IF(AND(ISNUMBER(S67),ISNUMBER(S39)),IFERROR(S67/S39,""),"") | X68: =IF(AND(ISNUMBER(X67),ISNUMBER(X39)),IFERROR(X67/X39,""),"") | AC68: =IF(AND(ISNUMBER(AC67),ISNUMBER(AC39)),IFERROR(AC67/AC39,""),"") | AH68: =IF(AND(ISNUMBER(AH67),ISNUMBER(AH39)),IFERROR(AH67/AH39,""),"") | AM68: =IF(AND(ISNUMBER(AM67),ISNUMBER(AM39)),IFERROR(AM67/AM39,""),"") -> 1.9546528 | AR68: =IF(AND(ISNUMBER(AR67),ISNUMBER(AR39)),IFERROR(AR67/AR39,""),"") -> 1.5816617 | AW68: =IF(AND(ISNUMBER(AW67),ISNUMBER(AW39)),IFERROR(AW67/AW39,""),"") -> 1.4716771 | BB68: =IF(AND(ISNUMBER(BB67),ISNUMBER(BB39)),IFERROR(BB67/BB39,""),"") -> 1.6746736 | BG68: =IF(AND(ISNUMBER(BG67),ISNUMBER(BG39)),IFERROR(BG67/BG39,""),"") -> 1.774675 | BL68: =IF(AND(ISNUMBER(BL67),ISNUMBER(BL39)),IFERROR(BL67/BL39,""),"") -> 2.015545 | BQ68: =IF(AND(ISNUMBER(BQ67),ISNUMBER(BQ39)),IFERROR(BQ67/BQ39,""),"") -> 1.1648692 | BR68: =IF(AND(ISNUMBER(BR67),ISNUMBER(BR39)),IFERROR(BR67/BR39,""),"") -> 1.0375212 | BS68: =IF(AND(ISNUMBER(BS67),ISNUMBER(BS39)),IFERROR(BS67/BS39,""),"") -> 0.933403 | BT68: =IF(AND(ISNUMBER(BT67),ISNUMBER(BT39)),IFERROR(BT67/BT39,""),"") -> 0.82676972 | BU68: =IF(AND(ISNUMBER(BU67),ISNUMBER(BU39)),IFERROR(BU67/BU39,""),"") -> 0.73818725
B70: Eliminations & unallocated corporate | BV70: CORPORATE & ELIMINATIONS
B71: Eliminations (intersegment revenues) | AM71: -10.88 | AN71: -2.4 | AO71: -2.24 | AP71: -1.794 | AQ71: -1.671 | AR71: -8.105 | AS71: -0.989 | AT71: -0.851 | AU71: -0.604 | AV71: -0.563 | AW71: -3.007 | AX71: -0.45 | AY71: -0.442 | AZ71: -0.225 | BA71: -0.255 | BB71: -1.372 | BC71: -0.193 | BD71: -0.872 | BE71: -1.229 | BF71: -1.065 | BG71: -3.358 | BH71: -1.338 | BI71: -1.059 | BJ71: -1.382 | BK71: -0.955 | BL71: -4.735 | BM71: -1.329 | BN71: -2.178 | BO71: =BJ71 -> -1.382 | BP71: =BK71 -> -0.955 | BQ71: =SUM(BM71:BP71) -> -5.844 | BR71: =BQ71 -> -5.844 | BS71: =BR71 -> -5.844 | BT71: =BS71 -> -5.844 | BU71: =BT71 -> -5.844 | BV71: Forecast: prior-year quarter / prior year.
B72: Unallocated corporate — operating income (GAAP) | E72: -2.322 | F72: -5.961 | G72: -5.286 | H72: -12.68 | I72: -26.249 | J72: -5.375 | K72: -9.833 | L72: -4.847 | M72: -5.693 | N72: -25.747 | O72: -3.2 | P72: -5.757 | Q72: -3.94 | R72: -13.456 | S72: -26.353 | T72: -2.891 | U72: -3.577 | V72: -6.304 | W72: -9.56 | X72: -22.332 | Y72: -6.667 | Z72: -2.461 | AA72: -5.6 | AB72: -6.27 | AC72: -20.998 | AD72: -2.039 | AE72: -4.32 | AF72: -2.74 | AG72: -8.65 | AH72: -17.749 | AI72: -1.603 | AJ72: -3.162 | AK72: -10.732 | AL72: -8.116 | AM72: -23.613 | AN72: -2.125 | AO72: -4.76 | AP72: -4.999 | AQ72: -7.06 | AR72: -18.944 | AS72: -4.62 | AT72: -1.41 | AU72: -4.704 | AV72: -4.614 | AW72: -15.348 | AX72: -4.231 | AY72: -6.559 | AZ72: -9.357 | BA72: -9.008 | BB72: -29.155 | BC72: -1.316 | BD72: -10.342 | BE72: -11.759 | BF72: -20.666 | BG72: -44.084 | BH72: -7.582 | BI72: -13.87 | BJ72: -7.981 | BK72: -18.684 | BL72: -48.119 | BM72: -16.479 | BN72: -15.874 | BO72: =BO74-BO73 -> -16.1765 | BP72: =BP74-BP73 -> -16.1765 | BQ72: =SUM(BM72:BP72) -> -64.706 | BR72: =BR74-BR73 -> -60.1813 | BS72: =BS74-BS73 -> -51.940365 | BT72: =BT74-BT73 -> -48.787383 | BU72: =BU74-BU73 -> -50.726752
B73: Unallocated corporate — non-GAAP adjustments (restructuring, transformation & acquisition costs) | AM73: =AM74-AM72 -> 4.567 | AN73: =AN74-AN72 -> 0 | AO73: =AO74-AO72 -> 0 | AP73: =AP74-AP72 -> 0.3 | AQ73: =AQ74-AQ72 -> 1.8 | AR73: =AR74-AR72 -> 2 | AS73: =AS74-AS72 -> 2.1 | AT73: =AT74-AT72 -> 0.6 | ... BN73: =BN74-BN72 -> 7 | BO73: =AVERAGE(BM73,BN73) -> 7.8 | BP73: =AVERAGE(BM73,BN73) -> 7.8 | BQ73: =SUM(BM73:BP73) -> 31.2 | BR73: 25 | BS73: 15 | BT73: 10 | BU73: 10 | BV73: Q3/Q4-26E: 1H/26 run-rate (incl. PCG / medical-sale transaction costs). 2027E: $25m (medical separation, PCG integration); then $10–15m p.a.
B74: Unallocated corporate — non-GAAP operating income | AM74: -19.046 | AN74: -2.125 | AO74: -4.76 | AP74: -4.699 | AQ74: -5.26 | AR74: -16.944 | AS74: -2.52 | AT74: -0.81 | AU74: -3.504 | AV74: -1.314 | AW74: -8.148 | AX74: -3.731 | AY74: -6.159 | AZ74: -8.257 | BA74: -6.808 | BB74: -24.955 | BC74: -0.516 | BD74: -6.342 | BE74: -5.159 | BF74: -11.866 | BG74: -23.984 | BH74: -2.882 | BI74: -5.07 | BJ74: -4.581 | BK74: -9.484 | BL74: -22.119 | BM74: -7.879 | BN74: -8.874 | BO74: =AVERAGE(BM74,BN74) -> -8.3765 | BP74: =AVERAGE(BM74,BN74) -> -8.3765 | BQ74: =SUM(BM74:BP74) -> -33.506 | BR74: =BQ74*(1+BR75) -> -35.1813 | BS74: =BR74*(1+BS75) -> -36.940365 | BT74: =BS74*(1+BT75) -> -38.787383 | BU74: =BT74*(1+BU75) -> -40.726752 | BV74: Q3/Q4-26E: 1H/26 run-rate. 2027E+: prior year × (1 + corporate cost growth).
B75: Corporate cost growth % | BR75: 0.05 | BS75: 0.05 | BT75: 0.05 | BU75: 0.05
B76: Corporate D&A | AM76: 6.845 | AN76: 1.809 | AO76: 1.724 | AP76: 1.571 | AQ76: 1.607 | AR76: 6.711 | AS76: 1.583 | AT76: 1.65 | AU76: 1.852 | AV76: 1.97 | AW76: 7.055 | AX76: 1.866 | AY76: 1.881 | AZ76: 1.827 | BA76: 1.859 | BB76: 7.433 | BC76: 1.874 | BD76: 1.781 | BE76: 1.672 | BF76: 1.8 | BG76: 7.127 | BH76: 1.797 | BI76: 1.794 | BJ76: 1.831 | BK76: 1.761 | BL76: 7.183 | BM76: 1.733 | BN76: 1.785 | BO76: =AVERAGE(BM76,BN76) -> 1.759 | BP76: =AVERAGE(BM76,BN76) -> 1.759 | BQ76: =SUM(BM76:BP76) -> 7.036 | BR76: =BQ76 -> 7.036 | BS76: =BR76 -> 7.036 | BT76: =BS76 -> 7.036 | BU76: =BT76 -> 7.036
B77: Corporate Adjusted EBITDA | C77: =IF(AND(ISNUMBER(C74),ISNUMBER(C76)),C74+C76,"") | D77: =IF(AND(ISNUMBER(D74),ISNUMBER(D76)),D74+D76,"") | E77: =IF(AND(ISNUMBER(E74),ISNUMBER(E76)),E74+E76,"") | F77: =IF(AND(ISNUMBER(F74),ISNUMBER(F76)),F74+F76,"") | G77: =IF(AND(ISNUMBER(G74),ISNUMBER(G76)),G74+G76,"") | H77: =IF(AND(ISNUMBER(H74),ISNUMBER(H76)),H74+H76,"") | I77: =IF(AND(ISNUMBER(I74),ISNUMBER(I76)),I74+I76,"") | J77: =IF(AND(ISNUMBER(J74),ISNUMBER(J76)),J74+J76,"") | ... BN77: =IF(AND(ISNUMBER(BN74),ISNUMBER(BN76)),BN74+BN76,"") -> -7.089 | BO77: =BO74+BO76 -> -6.6175 | BP77: =BP74+BP76 -> -6.6175 | BQ77: =BQ74+BQ76 -> -26.47 | BR77: =BR74+BR76 -> -28.1453 | BS77: =BS74+BS76 -> -29.904365 | BT77: =BT74+BT76 -> -31.751383 | BU77: =BU74+BU76 -> -33.690752
B79: Medical business divestiture (agreement 31-Jul-2026 with Nordic Capital; ~80% sold, ~20% retained; closing assumed 31-Mar-2027) | BV79: MEDICAL SALE — modelling logic
B80: Cash consideration | BR80: =CHOOSE(MATCH($BV$2,{"Bull","Base","Bear"},0),$CE$19,$CF$19,$CG$19) -> 750 | BS80: 0 | BT80: 0 | BU80: 0 | BV80: $750m base consideration, up to $800m with shared economics (Q2-26 call). Scenario: Bull $800m / Base & Bear $750m.
B81: Carrying value of net assets sold (estimate) | BR81: 350 | BS81: 0 | BT81: 0 | BU81: 0 | BV81: Assumption (not disclosed): BWXT Medical Ottawa/Vancouver facilities, goodwill & intangibles. Update with held-for-sale disclosure in the Q3-26 10-Q.
B82: Fair value of retained ~20% stake (equity method) | BR82: =BR80*0.2/0.8 -> 187.5 | BS82: 0 | BT82: 0 | BU82: 0
B83: Pre-tax gain on sale (GAAP; excluded from non-GAAP) | BQ83: 0 | BR83: =BR80+BR82-BR81 -> 587.5 | BS83: =BS80+BS82-BS81 -> 0 | BT83: =BT80+BT82-BT81 -> 0 | BU83: =BU80+BU82-BU81 -> 0 | BV83: Booked in "(Gain) loss on asset disposals" (operating income); excluded from Adjusted EBITDA and non-GAAP EPS.
B85: Future acquisitions (M&A lever — bolt-ons, unallocated; deals closed from 2027E) | BV85: M&A LEVER — acquired sales = spend ÷ EV/sales; mid-year convention
B86: Acquisition spend (USDm, scenario) | BQ86: 0 | BR86: =CHOOSE(MATCH($BV$2,{"Bull","Base","Bear"},0),$CE$53,$CF$53,$CG$53) -> 0 | BS86: =CHOOSE(MATCH($BV$2,{"Bull","Base","Bear"},0),$CE$54,$CF$54,$CG$54) -> 150 | BT86: =CHOOSE(MATCH($BV$2,{"Bull","Base","Bear"},0),$CE$55,$CF$55,$CG$55) -> 150 | BU86: =CHOOSE(MATCH($BV$2,{"Bull","Base","Bear"},0),$CE$56,$CF$56,$CG$56) -> 150 | BV86: Scenario lever MA_spend. BWXT: NFS-era bolt-ons, Sotera isotopes (2018), Dynamic Controls / Cunico (2021), Kinectrics (2025), A.O.T. (2025), PCG (2026).
B87: Purchase multiple — EV / sales (x) | BR87: 2 | BS87: 2 | BT87: 2 | BU87: 2
B88: Annualised sales acquired in the year | BR88: =IFERROR(BR86/BR87,0) -> 0 | BS88: =IFERROR(BS86/BS87,0) -> 75 | BT88: =IFERROR(BT86/BT87,0) -> 75 | BU88: =IFERROR(BU86/BU87,0) -> 75
B89: Growth of acquired businesses after acquisition % | BR89: 0.08 | BS89: 0.08 | BT89: 0.08 | BU89: 0.08
B90: Run-rate sales of businesses acquired (year end) | BQ90: 0 | BR90: =BQ90*(1+BR89)+BR88 -> 0 | BS90: =BR90*(1+BS89)+BS88 -> 75 | BT90: =BS90*(1+BT89)+BT88 -> 156 | BU90: =BT90*(1+BU89)+BU88 -> 243.48
B91: Revenues from future acquisitions | BQ91: 0 | BR91: =BQ90*(1+BR89)+BR88*0.5 -> 0 | BS91: =BR90*(1+BS89)+BS88*0.5 -> 37.5 | BT91: =BS90*(1+BT89)+BT88*0.5 -> 118.5 | BU91: =BT90*(1+BU89)+BU88*0.5 -> 205.98 | BV91: Mid-year convention: deals close evenly through the year.
B92: Non-GAAP operating margin of acquired businesses % | BR92: 0.12 | BS92: 0.12 | BT92: 0.12 | BU92: 0.12
B93: Non-GAAP operating income from future acquisitions | BQ93: 0 | BR93: =BR91*BR92 -> 0 | BS93: =BS91*BS92 -> 4.5 | BT93: =BT91*BT92 -> 14.22 | BU93: =BU91*BU92 -> 24.7176
B94: D&A (ex amortization) of acquired businesses % of sales | BR94: 0.03 | BS94: 0.03 | BT94: 0.03 | BU94: 0.03
B95: D&A from future acquisitions | BQ95: 0 | BR95: =BR91*BR94 -> 0 | BS95: =BS91*BS94 -> 1.125 | BT95: =BT91*BT94 -> 3.555 | BU95: =BU91*BU94 -> 6.1794
B96: PP&E % of spend | BR96: 0.25 | BS96: 0.25 | BT96: 0.25 | BU96: 0.25
B97: Acquired intangibles % of spend | BR97: 0.35 | BS97: 0.35 | BT97: 0.35 | BU97: 0.35
B98: Intangible amortization life (years) | BR98: 12 | BS98: 12 | BT98: 12 | BU98: 12
B99: Cumulative acquired intangibles (gross) | BQ99: 0 | BR99: =BQ99+BR86*BR97 -> 0 | BS99: =BR99+BS86*BS97 -> 52.5 | BT99: =BS99+BT86*BT97 -> 105 | BU99: =BT99+BU86*BU97 -> 157.5
B100: Amortization of future-acquisition intangibles | BQ100: 0 | BR100: =IFERROR((BQ99+BR86*BR97*0.5)/BR98,0) -> 0 | BS100: =IFERROR((BR99+BS86*BS97*0.5)/BS98,0) -> 2.1875 | BT100: =IFERROR((BS99+BT86*BT97*0.5)/BT98,0) -> 6.5625 | BU100: =IFERROR((BT99+BU86*BU97*0.5)/BU98,0) -> 10.9375
B102: Group total — segment build → consolidated revenues, non-GAAP operating income & Adjusted EBITDA (BWXT primary KPIs) | BV102: GROUP TOTAL — modelling logic
B103: Revenues (segment build) | AM103: =IF(ISNUMBER(AM15),AM15+AM39+N(AM71),"") -> 2123.516 | AN103: =IF(ISNUMBER(AN15),AN15+AN39+N(AN71),"") -> 528.273 | AO103: =IF(ISNUMBER(AO15),AO15+AO39+N(AO71),"") -> 505.099 | AP103: =IF(ISNUMBER(AP15),AP15+AP39+N(AP71),"") -> 498.727 | AQ103: =IF(ISNUMBER(AQ15),AQ15+AQ39+N(AQ71),"") -> 591.975 | AR103: =IF(ISNUMBER(AR15),AR15+AR39+N(AR71),"") -> 2124.074 | AS103: =IF(ISNUMBER(AS15),AS15+AS39+N(AS71),"") -> 530.738 | AT103: =IF(ISNUMBER(AT15),AT15+AT39+N(AT71),"") -> 554.208 | ... BN103: =IF(ISNUMBER(BN15),BN15+BN39+N(BN71),"") -> 901.625 | BO103: =BO15+BO39+BO71 -> 1002.6402 | BP103: =BP15+BP39+BP71 -> 1035.5178 | BQ103: =BQ15+BQ39+BQ71+N(BQ91) -> 3800 | BR103: =BR15+BR39+BR71+BR91 -> 4163.1929 | BS103: =BS15+BS39+BS71+BS91 -> 4582.8794 | BT103: =BT15+BT39+BT71+BT91 -> 5083.5875 | BU103: =BU15+BU39+BU71+BU91 -> 5615.8223 | BX103: =IFERROR((BU103/BL103)^(1/5)-1,"n/m") -> 0.11916839 | BY103: =IFERROR((BL103/AM103)^(1/5)-1,"n/m") -> 0.085365785 | BZ103: =IFERROR((BL103/N103)^(1/10)-1,"n/m") -> n/m | CA103: =IFERROR((BL103/D103)^(1/12)-1,"n/m") -> n/m
B104: Non-GAAP operating income (segment build) | AM104: =IF(ISNUMBER(AM24),AM24+AM55+AM74,"") -> 366.328 | AN104: =IF(ISNUMBER(AN24),AN24+AN55+AN74,"") -> 82.414 | AO104: =IF(ISNUMBER(AO24),AO24+AO55+AO74,"") -> 73.751 | AP104: =IF(ISNUMBER(AP24),AP24+AP55+AP74,"") -> 88.252 | AQ104: =IF(ISNUMBER(AQ24),AQ24+AQ55+AQ74,"") -> 104.605 | AR104: =IF(ISNUMBER(AR24),AR24+AR55+AR74,"") -> 348.922 | AS104: =IF(ISNUMBER(AS24),AS24+AS55+AS74,"") -> 76.873 | AT104: =IF(ISNUMBER(AT24),AT24+AT55+AT74,"") -> 96.037 | ... BN104: =IF(ISNUMBER(BN24),BN24+BN55+BN74,"") -> 126.636 | BO104: =BO24+BO55+BO74 -> 148.63503 | BP104: =BP24+BP55+BP74 -> 152.35847 | BQ104: =BQ24+BQ55+BQ74+N(BQ93) -> 549.1205 | BR104: =BR24+BR55+BR74+BR93 -> 609.55856 | BS104: =BS24+BS55+BS74+BS93 -> 685.38297 | BT104: =BT24+BT55+BT74+BT93 -> 773.4107 | BU104: =BU24+BU55+BU74+BU93 -> 861.25048 | BX104: =IFERROR((BU104/BL104)^(1/5)-1,"n/m") -> 0.12607353 | BY104: =IFERROR((BL104/AM104)^(1/5)-1,"n/m") -> 0.053622705 | BZ104: =IFERROR((BL104/N104)^(1/10)-1,"n/m") -> n/m | CA104: =IFERROR((BL104/D104)^(1/12)-1,"n/m") -> n/m
B105: Non-GAAP adjustments in operating income (segments + corporate + future-M&A amortization) | AM105: =IF(ISNUMBER(AM23),AM23+AM54+AM73,"") -> 7.776 | AN105: =IF(ISNUMBER(AN23),AN23+AN54+AN73,"") -> 0 | AO105: =IF(ISNUMBER(AO23),AO23+AO54+AO73,"") -> 0 | AP105: =IF(ISNUMBER(AP23),AP23+AP54+AP73,"") -> 0.784 | AQ105: =IF(ISNUMBER(AQ23),AQ23+AQ54+AQ73,"") -> 2.39 | AR105: =IF(ISNUMBER(AR23),AR23+AR54+AR73,"") -> 3.074 | AS105: =IF(ISNUMBER(AS23),AS23+AS54+AS73,"") -> 5.3 | AT105: =IF(ISNUMBER(AT23),AT23+AT54+AT73,"") -> 0.8 | ... BN105: =IF(ISNUMBER(BN23),BN23+BN54+BN73,"") -> 12.5 | BO105: =BO23+BO54+BO73 -> 15.55 | BP105: =BP23+BP54+BP73 -> 15.55 | BQ105: =BQ23+BQ54+BQ73 -> 58.4 | BR105: =BR23+BR54+BR73+BR100 -> 44 | BS105: =BS23+BS54+BS73+BS100 -> 36.1875 | BT105: =BT23+BT54+BT73+BT100 -> 35.5625 | BU105: =BU23+BU54+BU73+BU100 -> 39.9375
B106: Operating income — GAAP (segment build) | AM106: =IF(ISNUMBER(AM104),AM104-AM105,"") -> 358.552 | AN106: =IF(ISNUMBER(AN104),AN104-AN105,"") -> 82.414 | AO106: =IF(ISNUMBER(AO104),AO104-AO105,"") -> 73.751 | AP106: =IF(ISNUMBER(AP104),AP104-AP105,"") -> 87.468 | AQ106: =IF(ISNUMBER(AQ104),AQ104-AQ105,"") -> 102.215 | AR106: =IF(ISNUMBER(AR104),AR104-AR105,"") -> 345.848 | AS106: =IF(ISNUMBER(AS104),AS104-AS105,"") -> 71.573 | AT106: =IF(ISNUMBER(AT104),AT104-AT105,"") -> 95.237 | ... BN106: =IF(ISNUMBER(BN104),BN104-BN105,"") -> 114.136 | BO106: =BO104-BO105 -> 133.08503 | BP106: =BP104-BP105 -> 136.80847 | BQ106: =BQ104-BQ105+N(BQ83) -> 490.7205 | BR106: =BR104-BR105+BR83 -> 1153.0586 | BS106: =BS104-BS105+BS83 -> 649.19547 | BT106: =BT104-BT105+BT83 -> 737.8482 | BU106: =BU104-BU105+BU83 -> 821.31298
...

Sheet Bull-Base-Bear
B2: BWX Technologies (BWXT) — Bull / Base / Bear Case P&L Summary | J2: Share price ($): | K2: =Model!$BQ$448 -> 152.29
B3: Adjusted figures (company definition: Adjusted EBITDA / non-GAAP EPS from continuing operations); GAAP operating income shown for reference. 2027E GAAP includes the medical-sale gain. | J3: As of: | K3: =TODAY() -> 46302
B5: Scenario: | C5: =Model!$BV$2 -> Base | N5: Scenario: | O5: Bull | P5: Snapshot (values) — Model run with switch = Bull; refresh by re-running the switch | Z5: Scenario: | AA5: Bear | AB5: Snapshot (values) — Model run with switch = Bear; refresh by re-running the switch
B7: (USDm, except EPS and shares) | C7: 2025A | D7: 2026E | E7: 2027E | F7: 2028E | G7: 2029E | H7: 2030E | I7: 25-'30 CAGR | J7: Hist. avg 16–25 | N7: (USDm, except EPS and shares) | O7: 2025A | P7: 2026E | Q7: 2027E | R7: 2028E | S7: 2029E | T7: 2030E | Z7: (USDm, except EPS and shares) | AA7: 2025A | AB7: 2026E | AC7: 2027E | AD7: 2028E | AE7: 2029E | AF7: 2030E
B9: Revenues | C9: =Model!BL157 -> 3198.425 | D9: =Model!BQ157 -> 3800 | E9: =Model!BR157 -> 4163.1929 | F9: =Model!BS157 -> 4582.8794 | G9: =Model!BT157 -> 5083.5875 | H9: =Model!BU157 -> 5615.8223 | I9: =IFERROR((H9/C9)^(1/5)-1,"n/m") -> 0.11916839 | N9: Revenues | O9: 3198.425 | P9: 3850 | Q9: 4364.5914 | R9: 5008.6694 | S9: 5772.5676 | T9: 6611.6383 | U9: =IFERROR((T9/O9)^(1/5)-1,"n/m") -> 0.1563108 | Z9: Revenues | AA9: 3198.425 | AB9: 3750 | AC9: 3990.2449 | AD9: 4227.1001 | AE9: 4479.3618 | AF9: 4733.4454 | AG9: =IFERROR((AF9/AA9)^(1/5)-1,"n/m") -> 0.081554082
B10: Revenues y/y % | D10: =IFERROR(D9/C9-1,"") -> 0.18808476 | E10: =IFERROR(E9/D9-1,"") -> 0.095577089 | F10: =IFERROR(F9/E9-1,"") -> 0.10080879 | G10: =IFERROR(G9/F9-1,"") -> 0.10925623 | H10: =IFERROR(H9/G9-1,"") -> 0.10469669 | N10: Revenues y/y % | P10: =IFERROR(P9/O9-1,"") -> 0.20371745 | Q10: =IFERROR(Q9/P9-1,"") -> 0.13366009 | R10: =IFERROR(R9/Q9-1,"") -> 0.14756892 | S10: =IFERROR(S9/R9-1,"") -> 0.15251519 | T10: =IFERROR(T9/S9-1,"") -> 0.14535485 | Z10: Revenues y/y % | AB10: =IFERROR(AB9/AA9-1,"") -> 0.17245207 | AC10: =IFERROR(AC9/AB9-1,"") -> 0.064065306 | AD10: =IFERROR(AD9/AC9-1,"") -> 0.059358555 | AE10: =IFERROR(AE9/AD9-1,"") -> 0.059677254 | AF10: =IFERROR(AF9/AE9-1,"") -> 0.056723178
B11: Government Operations revenues y/y % | C11: =Model!BL17 -> 0.076521731 | D11: =Model!BQ17 -> 0.034815464 | E11: =Model!BR17 -> 0.08 | F11: =Model!BS17 -> 0.08 | G11: =Model!BT17 -> 0.07 | H11: =Model!BU17 -> 0.07 | N11: Government Operations revenues y/y % | O11: 0.076521731 | P11: 0.049438311 | Q11: 0.1 | R11: 0.1 | S11: 0.09 | T11: 0.09 | Z11: Government Operations revenues y/y % | AA11: 0.076521731 | AB11: 0.020192618 | AC11: 0.055 | AD11: 0.055 | AE11: 0.045 | AF11: 0.045
B12: Adjusted EBITDA | C12: =Model!BL208 -> 574.245 | D12: =Model!BQ208 -> 667 | E12: =Model!BR208 -> 754.33929 | F12: =Model!BS208 -> 848.22208 | G12: =Model!BT208 -> 957.41076 | H12: =Model!BU208 -> 1062.9173 | I12: =IFERROR((H12/C12)^(1/5)-1,"n/m") -> 0.13104647 | N12: Adjusted EBITDA | O12: 574.245 | P12: 672 | Q12: 840.56022 | R12: 980.20706 | S12: 1143.7554 | T12: 1312.4478 | U12: =IFERROR((T12/O12)^(1/5)-1,"n/m") -> 0.17976895 | Z12: Adjusted EBITDA | AA12: 574.245 | AB12: 662 | AC12: 675.87061 | AD12: 733.26337 | AE12: 794.28593 | AF12: 846.22035 | AG12: =IFERROR((AF12/AA12)^(1/5)-1,"n/m") -> 0.080630569
B13: Adjusted EBITDA margin % | C13: =IFERROR(C12/C9,"") -> 0.17953993 | D13: =IFERROR(D12/D9,"") -> 0.17552632 | E13: =IFERROR(E12/E9,"") -> 0.18119249 | F13: =IFERROR(F12/F9,"") -> 0.18508497 | G13: =IFERROR(G12/G9,"") -> 0.18833368 | H13: =IFERROR(H12/H9,"") -> 0.18927188 | J13: =IFERROR(AVERAGE(Model!S209,Model!X209,Model!AC209,Model!AH209,Model!AM209,Model!AR209,Model!AW209,Model!BB209,Model!BG209,Model!BL209),"") -> 0.19920187 | N13: Adjusted EBITDA margin % | O13: =IFERROR(O12/O9,"") -> 0.17953993 | P13: =IFERROR(P12/P9,"") -> 0.17454545 | Q13: =IFERROR(Q12/Q9,"") -> 0.19258624 | R13: =IFERROR(R12/R9,"") -> 0.19570209 | S13: =IFERROR(S12/S9,"") -> 0.19813634 | T13: =IFERROR(T12/T9,"") -> 0.19850569 | Z13: Adjusted EBITDA margin % | AA13: =IFERROR(AA12/AA9,"") -> 0.17953993 | AB13: =IFERROR(AB12/AB9,"") -> 0.17653333 | AC13: =IFERROR(AC12/AC9,"") -> 0.16938073 | AD13: =IFERROR(AD12/AD9,"") -> 0.17346724 | AE13: =IFERROR(AE12/AE9,"") -> 0.17732123 | AF13: =IFERROR(AF12/AF9,"") -> 0.17877471
B15: Operating Income (GAAP) | C15: =Model!BL164 -> 404.459 | D15: =Model!BQ164 -> 490.7205 | E15: =Model!BR164 -> 1153.0586 | F15: =Model!BS164 -> 649.19547 | G15: =Model!BT164 -> 737.8482 | H15: =Model!BU164 -> 821.31298 | I15: =IFERROR((H15/C15)^(1/5)-1,"n/m") -> 0.15219725 | N15: Operating Income (GAAP) | O15: 404.459 | P15: 494.24812 | Q15: 1293.1863 | R15: 760.97064 | S15: 890.84492 | T15: 1023.2732 | U15: =IFERROR((T15/O15)^(1/5)-1,"n/m") -> 0.20399149 | Z15: Operating Income (GAAP) | AA15: 404.459 | AB15: 487.19288 | AC15: 1080.2088 | AD15: 548.12378 | AE15: 601.38487 | AF15: 644.69289 | AG15: =IFERROR((AF15/AA15)^(1/5)-1,"n/m") -> 0.097730358
B16: Operating income y/y % | D16: =IFERROR(D15/C15-1,"") -> 0.21327625 | E16: =IFERROR(E15/D15-1,"") -> 1.3497257 | F16: =IFERROR(F15/E15-1,"") -> -0.43697962 | G16: =IFERROR(G15/F15-1,"") -> 0.13655785 | H16: =IFERROR(H15/G15-1,"") -> 0.11311917 | N16: Operating income y/y % | P16: =IFERROR(P15/O15-1,"") -> 0.22199808 | Q16: =IFERROR(Q15/P15-1,"") -> 1.6164719 | R16: =IFERROR(R15/Q15-1,"") -> -0.41155375 | S16: =IFERROR(S15/R15-1,"") -> 0.17066924 | T16: =IFERROR(T15/S15-1,"") -> 0.14865468 | Z16: Operating income y/y % | AB16: =IFERROR(AB15/AA15-1,"") -> 0.20455443 | AC16: =IFERROR(AC15/AB15-1,"") -> 1.2172099 | AD16: =IFERROR(AD15/AC15-1,"") -> -0.49257611 | AE16: =IFERROR(AE15/AD15-1,"") -> 0.097169816 | AF16: =IFERROR(AF15/AE15-1,"") -> 0.072013812
B17: Operating margin (GAAP) % | C17: =IFERROR(C15/C9,"") -> 0.12645568 | D17: =IFERROR(D15/D9,"") -> 0.12913697 | E17: =IFERROR(E15/E9,"") -> 0.27696496 | F17: =IFERROR(F15/F9,"") -> 0.14165668 | G17: =IFERROR(G15/G9,"") -> 0.14514321 | H17: =IFERROR(H15/H9,"") -> 0.14624982 | J17: =IFERROR(AVERAGE(Model!S254,Model!X254,Model!AC254,Model!AH254,Model!AM254,Model!AR254,Model!AW254,Model!BB254,Model!BG254,Model!BL254),"") -> 0.15870152 | N17: Operating margin (GAAP) % | O17: =IFERROR(O15/O9,"") -> 0.12645568 | P17: =IFERROR(P15/P9,"") -> 0.12837614 | Q17: =IFERROR(Q15/Q9,"") -> 0.29629035 | R17: =IFERROR(R15/R9,"") -> 0.1519307 | S17: =IFERROR(S15/S9,"") -> 0.15432386 | T17: =IFERROR(T15/T9,"") -> 0.15476848 | Z17: Operating margin (GAAP) % | AA17: =IFERROR(AA15/AA9,"") -> 0.12645568 | AB17: =IFERROR(AB15/AB9,"") -> 0.1299181 | AC17: =IFERROR(AC15/AC9,"") -> 0.27071242 | AD17: =IFERROR(AD15/AD9,"") -> 0.12966899 | AE17: =IFERROR(AE15/AE9,"") -> 0.13425682 | AF17: =IFERROR(AF15/AF9,"") -> 0.1361995
B19: Non-GAAP Net Income (continuing ops, attributable to BWXT) | C19: =Model!BL234 -> 368.34256 | D19: =Model!BQ234 -> 436.00785 | E19: =Model!BR234 -> 481.21415 | F19: =Model!BS234 -> 540.78871 | G19: =Model!BT234 -> 600.71214 | H19: =Model!BU234 -> 659.76219 | I19: =IFERROR((H19/C19)^(1/5)-1,"n/m") -> 0.12363977 | N19: Non-GAAP Net Income (continuing ops, attributable to BWXT) | O19: 368.34256 | P19: 438.77703 | Q19: 544.61134 | R19: 617.95644 | S19: 708.38514 | T19: 799.48414 | U19: =IFERROR((T19/O19)^(1/5)-1,"n/m") -> 0.16764706 | Z19: Non-GAAP Net Income (continuing ops, attributable to BWXT) | AA19: 368.34256 | AB19: 433.23866 | AC19: 424.45634 | AD19: 468.41312 | AE19: 503.99984 | AF19: 531.20798 | AG19: =IFERROR((AF19/AA19)^(1/5)-1,"n/m") -> 0.075975885
B21: FDSO (m) | C21: =Model!BL185 -> 91.856 | D21: =Model!BQ185 -> 91.995125 | E21: =Model!BR185 -> 91.177622 | F21: =Model!BS185 -> 89.656385 | G21: =Model!BT185 -> 88.114487 | H21: =Model!BU185 -> 86.364543 | I21: =IFERROR((H21/C21)^(1/5)-1,"n/m") -> -0.012253293 | N21: FDSO (m) | O21: 91.856 | P21: 91.995125 | Q21: 89.730857 | R21: 86.643856 | S21: 84.733592 | T21: 82.399413 | U21: =IFERROR((T21/O21)^(1/5)-1,"n/m") -> -0.021494395 | Z21: FDSO (m) | AA21: 91.856 | AB21: 91.995125 | AC21: 92.1966 | AD21: 92.09913 | AE21: 91.027751 | AF21: 89.481149 | AG21: =IFERROR((AF21/AA21)^(1/5)-1,"n/m") -> -0.0052251334
B23: Non-GAAP EPS — Diluted ($) | C23: =Model!BL236 -> 4.01 | D23: =Model!BQ236 -> 4.7394669 | E23: =Model!BR236 -> 5.277766 | F23: =Model!BS236 -> 6.0317924 | G23: =Model!BT236 -> 6.8174049 | H23: =Model!BU236 -> 7.6392714 | I23: =IFERROR((H23/C23)^(1/5)-1,"n/m") -> 0.13757886 | N23: Non-GAAP EPS — Diluted ($) | O23: 4.01 | P23: 4.7695683 | Q23: 6.0693875 | R23: 7.1321439 | S23: 8.3601453 | T23: 9.7025465 | U23: =IFERROR((T23/O23)^(1/5)-1,"n/m") -> 0.19329624 | Z23: Non-GAAP EPS — Diluted ($) | AA23: 4.01 | AB23: 4.7093654 | AC23: 4.6038177 | AD23: 5.0859668 | AE23: 5.5367714 | AF23: 5.9365351 | AG23: =IFERROR((AF23/AA23)^(1/5)-1,"n/m") -> 0.081627533
B24: EPS y/y % | D24: =IFERROR(D23/C23-1,"") -> 0.18191193 | E24: =IFERROR(E23/D23-1,"") -> 0.11357799 | F24: =IFERROR(F23/E23-1,"") -> 0.14286849 | G24: =IFERROR(G23/F23-1,"") -> 0.13024528 | H24: =IFERROR(H23/G23-1,"") -> 0.12055416 | N24: EPS y/y % | P24: =IFERROR(P23/O23-1,"") -> 0.18941852 | Q24: =IFERROR(Q23/P23-1,"") -> 0.27252346 | R24: =IFERROR(R23/Q23-1,"") -> 0.17510109 | S24: =IFERROR(S23/R23-1,"") -> 0.17217844 | T24: =IFERROR(T23/S23-1,"") -> 0.16057152 | Z24: EPS y/y % | AB24: =IFERROR(AB23/AA23-1,"") -> 0.17440535 | AC24: =IFERROR(AC23/AB23-1,"") -> -0.022412307 | AD24: =IFERROR(AD23/AC23-1,"") -> 0.10472811 | AE24: =IFERROR(AE23/AD23-1,"") -> 0.088636938 | AF24: =IFERROR(AF23/AE23-1,"") -> 0.072201601
B26: P / E (x) — assumed (non-GAAP EPS) | F26: 30 | G26: 30 | H26: 30 | N26: P / E (x) — assumed (non-GAAP EPS) | R26: 35 | S26: 35 | T26: 35 | Z26: P / E (x) — assumed (non-GAAP EPS) | AD26: 22 | AE26: 22 | AF26: 22
B27: Price Target ($) | F27: =F26*F23 -> 180.95377 | G27: =G26*G23 -> 204.52215 | H27: =H26*H23 -> 229.17814 | N27: Price Target ($) | R27: =R26*R23 -> 249.62504 | S27: =S26*S23 -> 292.60509 | T27: =T26*T23 -> 339.58913 | Z27: Price Target ($) | AD27: =AD26*AD23 -> 111.89127 | AE27: =AE26*AE23 -> 121.80897 | AF27: =AF26*AF23 -> 130.60377
B28: Upside / (Downside) vs current | F28: =IFERROR(F27/$K$2-1,"") -> 0.18821835 | G28: =IFERROR(G27/$K$2-1,"") -> 0.34297818 | H28: =IFERROR(H27/$K$2-1,"") -> 0.50487978 | N28: Upside / (Downside) vs current | R28: =IFERROR(R27/$K$2-1,"") -> 0.63914266 | S28: =IFERROR(S27/$K$2-1,"") -> 0.92136769 | T28: =IFERROR(T27/$K$2-1,"") -> 1.2298846 | Z28: Upside / (Downside) vs current | AD28: =IFERROR(AD27/$K$2-1,"") -> -0.265275 | AE28: =IFERROR(AE27/$K$2-1,"") -> -0.20015123 | AF28: =IFERROR(AF27/$K$2-1,"") -> -0.14240086
B29: IRR (to Dec-Y-1) | F29: =IFERROR((F27/$K$2)^(1/((DATE(2028-1,12,31)-$K$3)/365.25))-1,"") -> 0.15024616 | G29: =IFERROR((G27/$K$2)^(1/((DATE(2029-1,12,31)-$K$3)/365.25))-1,"") -> 0.14110336 | H29: =IFERROR((H27/$K$2)^(1/((DATE(2030-1,12,31)-$K$3)/365.25))-1,"") -> 0.13473984 | N29: IRR (to Dec-Y-1) | R29: =IFERROR((R27/$K$2)^(1/((DATE(2028-1,12,31)-$K$3)/365.25))-1,"") -> 0.49347262 | S29: =IFERROR((S27/$K$2)^(1/((DATE(2029-1,12,31)-$K$3)/365.25))-1,"") -> 0.33951312 | T29: =IFERROR((T27/$K$2)^(1/((DATE(2030-1,12,31)-$K$3)/365.25))-1,"") -> 0.28148617 | Z29: IRR (to Dec-Y-1) | AD29: =IFERROR((AD27/$K$2)^(1/((DATE(2028-1,12,31)-$K$3)/365.25))-1,"") -> -0.22135773 | AE29: =IFERROR((AE27/$K$2)^(1/((DATE(2029-1,12,31)-$K$3)/365.25))-1,"") -> -0.095131791 | AF29: =IFERROR((AF27/$K$2)^(1/((DATE(2030-1,12,31)-$K$3)/365.25))-1,"") -> -0.046398938
B31: Free Cash Flow | C31: =Model!BL288 -> 295.291 | D31: =Model!BQ288 -> 368.23576 | E31: =Model!BR288 -> 152.65928 | F31: =Model!BS288 -> 451.36732 | G31: =Model!BT288 -> 531.75615 | H31: =Model!BU288 -> 584.86449 | I31: =IFERROR((H31/C31)^(1/5)-1,"n/m") -> 0.14646555 | N31: Free Cash Flow | O31: 295.291 | P31: 365.85621 | Q31: 181.33535 | R31: 501.52912 | S31: 609.8594 | T31: 689.16781 | U31: =IFERROR((T31/O31)^(1/5)-1,"n/m") -> 0.18471791 | Z31: Free Cash Flow | AA31: 295.291 | AB31: 370.6153 | AC31: 112.63 | AD31: 401.6589 | AE31: 463.17092 | AF31: 488.54399 | AG31: =IFERROR((AF31/AA31)^(1/5)-1,"n/m") -> 0.10593778
B32: FCF % | C32: =IFERROR(C31/C9,"") -> 0.092323878 | D32: =IFERROR(D31/D9,"") -> 0.096904146 | E32: =IFERROR(E31/E9,"") -> 0.036668797 | F32: =IFERROR(F31/F9,"") -> 0.098489898 | G32: =IFERROR(G31/G9,"") -> 0.10460254 | H32: =IFERROR(H31/H9,"") -> 0.10414583 | J32: =IFERROR(AVERAGE(Model!S290,Model!X290,Model!AC290,Model!AH290,Model!AM290,Model!AR290,Model!AW290,Model!BB290,Model!BG290,Model!BL290),"") -> 0.057972992 | N32: FCF % | O32: =IFERROR(O31/O9,"") -> 0.092323878 | P32: =IFERROR(P31/P9,"") -> 0.095027586 | Q32: =IFERROR(Q31/Q9,"") -> 0.041546925 | R32: =IFERROR(R31/R9,"") -> 0.10013221 | S32: =IFERROR(S31/S9,"") -> 0.10564786 | T32: =IFERROR(T31/T9,"") -> 0.10423556 | Z32: FCF % | AA32: =IFERROR(AA31/AA9,"") -> 0.092323878 | AB32: =IFERROR(AB31/AB9,"") -> 0.098830748 | AC32: =IFERROR(AC31/AC9,"") -> 0.028226338 | AD32: =IFERROR(AD31/AD9,"") -> 0.095019966 | AE32: =IFERROR(AE31/AE9,"") -> 0.1034011 | AF32: =IFERROR(AF31/AF9,"") -> 0.10321108
B33: FCF / share ($) | C33: =IFERROR(C31/C21,"") -> 3.2147165 | D33: =IFERROR(D31/D21,"") -> 4.0027747 | E33: =IFERROR(E31/E21,"") -> 1.6743064 | F33: =IFERROR(F31/F21,"") -> 5.0344136 | G33: =IFERROR(G31/G21,"") -> 6.0348322 | H33: =IFERROR(H31/H21,"") -> 6.772044 | N33: FCF / share ($) | O33: =IFERROR(O31/O21,"") -> 3.2147165 | P33: =IFERROR(P31/P21,"") -> 3.9769086 | Q33: =IFERROR(Q31/Q21,"") -> 2.0208806 | R33: =IFERROR(R31/R21,"") -> 5.788398 | S33: =IFERROR(S31/S21,"") -> 7.1973746 | T33: =IFERROR(T31/T21,"") -> 8.3637466 | Z33: FCF / share ($) | AA33: =IFERROR(AA31/AA21,"") -> 3.2147165 | AB33: =IFERROR(AB31/AB21,"") -> 4.0286407 | AC33: =IFERROR(AC31/AC21,"") -> 1.2216286 | AD33: =IFERROR(AD31/AD21,"") -> 4.3611585 | AE33: =IFERROR(AE31/AE21,"") -> 5.0882387 | AF33: =IFERROR(AF31/AF21,"") -> 5.4597421
B34: FCF Yield (on PT) | F34: =IFERROR(F33/F$27,"") -> 0.027821545 | G34: =IFERROR(G33/G$27,"") -> 0.029506986 | H34: =IFERROR(H33/H$27,"") -> 0.029549258 | N34: FCF Yield (on PT) | R34: =IFERROR(R33/R$27,"") -> 0.023188371 | S34: =IFERROR(S33/S$27,"") -> 0.024597572 | T34: =IFERROR(T33/T$27,"") -> 0.024629018 | Z34: FCF Yield (on PT) | AD34: =IFERROR(AD33/AD$27,"") -> 0.038976754 | AE34: =IFERROR(AE33/AE$27,"") -> 0.041772283 | AF34: =IFERROR(AF33/AF$27,"") -> 0.041803862
B35: Total backlog (year end) | C35: =Model!BL110 -> 7260.692 | D35: =Model!BQ110 -> 8398.081 | E35: =Model!BR110 -> 8529.4041 | F35: =Model!BS110 -> 8671.2331 | G35: =Model!BT110 -> 8822.9901 | H35: =Model!BU110 -> 8985.37 | I35: =IFERROR((H35/C35)^(1/5)-1,"n/m") -> 0.043545983 | N35: Total backlog (year end) | O35: 7260.692 | P35: 8398.081 | Q35: 9102.6647 | R35: 9886.9353 | S35: 10757.605 | T35: 11723.262 | U35: =IFERROR((T35/O35)^(1/5)-1,"n/m") -> 0.10056092 | Z35: Total backlog (year end) | AA35: 7260.692 | AB35: 8398.081 | AC35: 7998.4721 | AD35: 7575.1777 | AE35: 7126.6571 | AF35: 6652.7282 | AG35: =IFERROR((AF35/AA35)^(1/5)-1,"n/m") -> -0.017337568
B36: Book-to-bill (x) | C36: =Model!BL112 -> 1.6757945 | D36: =Model!BQ112 -> 1.2999276 | E36: =Model!BR112 -> 1.0329476 | F36: =Model!BS112 -> 1.0240401 | G36: =Model!BT112 -> 1.0076916 | H36: =Model!BU112 -> 0.99327685 | N36: Book-to-bill (x) | O36: 1.6757945 | P36: 1.2960325 | Q36: 1.1541789 | R36: 1.1266034 | S36: 1.0956306 | T36: 1.0703399 | Z36: Book-to-bill (x) | AA36: 1.6757945 | AB36: 1.3039267 | AC36: 0.90131811 | AD36: 0.90124426 | AE36: 0.90117419 | AF36: 0.90111116
B38: Net Debt | C38: =Model!BL443 -> 1508.779 | D38: =Model!BQ443 -> 1565.9949 | E38: =Model!BR443 -> 1131.5089 | F38: =Model!BS443 -> 1272.3331 | G38: =Model!BT443 -> 1436.1161 | H38: =Model!BU443 -> 1594.3759 | N38: Net Debt | O38: 1508.779 | P38: 1568.3745 | Q38: 1681.1204 | R38: 1960.4141 | S38: 2287.5108 | T38: 2624.8956 | Z38: Net Debt | AA38: 1508.779 | AB38: 1563.6154 | AC38: 833.96943 | AD38: 733.26337 | AE38: 794.28593 | AF38: 846.22035
B39: Net Debt / Adjusted EBITDA (x) | C39: =IFERROR(C38/C12,"") -> 2.6274134 | D39: =IFERROR(D38/D12,"") -> 2.3478185 | E39: =IFERROR(E38/E12,"") -> 1.5 | F39: =IFERROR(F38/F12,"") -> 1.5 | G39: =IFERROR(G38/G12,"") -> 1.5 | H39: =IFERROR(H38/H12,"") -> 1.5 | N39: Net Debt / Adjusted EBITDA (x) | O39: =IFERROR(O38/O12,"") -> 2.6274134 | P39: =IFERROR(P38/P12,"") -> 2.3338906 | Q39: =IFERROR(Q38/Q12,"") -> 2 | R39: =IFERROR(R38/R12,"") -> 2 | S39: =IFERROR(S38/S12,"") -> 2 | T39: =IFERROR(T38/T12,"") -> 2 | Z39: Net Debt / Adjusted EBITDA (x) | AA39: =IFERROR(AA38/AA12,"") -> 2.6274134 | AB39: =IFERROR(AB38/AB12,"") -> 2.3619567 | AC39: =IFERROR(AC38/AC12,"") -> 1.2339188 | AD39: =IFERROR(AD38/AD12,"") -> 1 | AE39: =IFERROR(AE38/AE12,"") -> 1 | AF39: =IFERROR(AF38/AF12,"") -> 1
B40: Share repurchases ($m) | D40: =Model!BQ299 -> 0 | E40: =Model!BR299 -> 335.18922 | F40: =Model!BS299 -> 302.77505 | G40: =Model!BT299 -> 398.8922 | H40: =Model!BU299 -> 439.36638 | N40: Share repurchases ($m) | P40: 0 | Q40: 811.09726 | R40: 345.05134 | S40: 494.56955 | T40: 578.12877 | Z40: Share repurchases ($m) | AB40: 0 | AC40: 0 | AD40: 158.96915 | AE40: 373.67247 | AF40: 382.34345
B41: Implied avg buyback price ($) | D41: =Model!BQ298 -> 152.29 | E41: =Model!BR298 -> 164.4732 | F41: =Model!BS298 -> 177.63106 | G41: =Model!BT298 -> 191.84154 | H41: =Model!BU298 -> 207.18886 | N41: Implied avg buyback price ($) | P41: 152.29 | Q41: 164.4732 | R41: 177.63106 | S41: 191.84154 | T41: 207.18886 | Z41: Implied avg buyback price ($) | AB41: 152.29 | AC41: 164.4732 | AD41: 177.63106 | AE41: 191.84154 | AF41: 207.18886
B42: Shares repurchased (m) | D42: =Model!BQ300 -> 0 | E42: =Model!BR300 -> 2.0379565 | F42: =Model!BS300 -> 1.7045164 | G42: =Model!BT300 -> 2.0792796 | H42: =Model!BU300 -> 2.1206081 | N42: Shares repurchased (m) | P42: 0 | Q42: 4.9314859 | R42: 1.942517 | S42: 2.5780107 | T42: 2.7903467 | Z42: Shares repurchased (m) | AB42: 0 | AC42: 0 | AD42: 0.89494005 | AE42: 1.9478183 | AF42: 1.8453861
B44: ROIC | C44: =Model!BL426 -> 0.14374023 | D44: =Model!BQ426 -> 0.14085705 | E44: =Model!BR426 -> 0.15064591 | F44: =Model!BS426 -> 0.1561988 | G44: =Model!BT426 -> 0.16418556 | H44: =Model!BU426 -> 0.170754 | J44: =IFERROR(AVERAGE(Model!S426,Model!X426,Model!AC426,Model!AH426,Model!AM426,Model!AR426,Model!AW426,Model!BB426,Model!BG426,Model!BL426),"") -> 0.2051783 | N44: ROIC | O44: 0.14374023 | P44: 0.14148447 | Q44: 0.16077454 | R44: 0.16552153 | S44: 0.17335056 | T44: 0.18045635 | Z44: ROIC | AA44: 0.14374023 | AB44: 0.14022735 | AC44: 0.13366953 | AD44: 0.14085612 | AE44: 0.14919125 | AF44: 0.15581351
B45: RONTA | C45: =Model!BL437 -> 0.14234019 | D45: =Model!BQ437 -> 0.1531374 | E45: =Model!BR437 -> 0.13561772 | F45: =Model!BS437 -> 0.15075449 | G45: =Model!BT437 -> 0.16978231 | H45: =Model!BU437 -> 0.18773961 | J45: =IFERROR(AVERAGE(Model!S437,Model!X437,Model!AC437,Model!AH437,Model!AM437,Model!AR437,Model!AW437,Model!BB437,Model!BG437,Model!BL437),"") -> 0.19833665 | N45: RONTA | O45: 0.14234019 | P45: 0.15392254 | Q45: 0.17720985 | R45: 0.20333255 | S45: 0.21989937 | T45: 0.23438101 | Z45: RONTA | AA45: 0.14234019 | AB45: 0.15235046 | AC45: 0.11077501 | AD45: 0.11361263 | AE45: 0.12192732 | AF45: 0.12871464
B47: Implied Market Cap (USDm) | F47: =F27*F21 -> 16223.661 | G47: =G27*G21 -> 18021.364 | H47: =H27*H21 -> 19792.866 | N47: Implied Market Cap (USDm) | R47: =R27*R21 -> 21628.476 | S47: =S27*S21 -> 24793.48 | T47: =T27*T21 -> 27981.945 | Z47: Implied Market Cap (USDm) | AD47: =AD27*AD21 -> 10305.089 | AE47: =AE27*AE21 -> 11087.997 | AF47: =AF27*AF21 -> 11686.576
B48: (+) Net Debt & NCI | F48: =F38+Model!BS354 -> 1274.0311 | G48: =G38+Model!BT354 -> 1438.2141 | H48: =H38+Model!BU354 -> 1596.8739 | N48: (+) Net Debt & NCI | R48: =R38+1.698 -> 1962.1121 | S48: =S38+2.098 -> 2289.6088 | T48: =T38+2.498 -> 2627.3936 | Z48: (+) Net Debt & NCI | AD48: =AD38+1.698 -> 734.96137 | AE48: =AE38+2.098 -> 796.38393 | AF48: =AF38+2.498 -> 848.71835
B49: Implied Enterprise Value (USDm) | F49: =F47+F48 -> 17497.692 | G49: =G47+G48 -> 19459.578 | H49: =H47+H48 -> 21389.739 | N49: Implied Enterprise Value (USDm) | R49: =R47+R48 -> 23590.588 | S49: =S47+S48 -> 27083.089 | T49: =T47+T48 -> 30609.338 | Z49: Implied Enterprise Value (USDm) | AD49: =AD47+AD48 -> 11040.05 | AE49: =AE47+AE48 -> 11884.38 | AF49: =AF47+AF48 -> 12535.294
B50: Implied EV / Adjusted EBITDA (x) | F50: =IFERROR(F49/F12,"") -> 20.628669 | G50: =IFERROR(G49/G12,"") -> 20.325214 | H50: =IFERROR(H49/H12,"") -> 20.123617 | N50: Implied EV / Adjusted EBITDA (x) | R50: =IFERROR(R49/R12,"") -> 24.066943 | S50: =IFERROR(S49/S12,"") -> 23.679091 | T50: =IFERROR(T49/T12,"") -> 23.322328 | Z50: Implied EV / Adjusted EBITDA (x) | AD50: =IFERROR(AD49/AD12,"") -> 15.05605 | AE50: =IFERROR(AE49/AE12,"") -> 14.962346 | AF50: =IFERROR(AF49/AF12,"") -> 14.813274

Sheet DCF
B2: DCF VALUATION — BWX TECHNOLOGIES (BWXT)
B4: 1. WACC BUILD
B5: Risk-free rate (US 10Y govt) | C5: 0.055 | D5: Assumption (kept consistent with the MLM model); update to the current US 10Y Treasury yield
B6: Equity risk premium | C6: 0.05 | D6: US implied ERP ~4.5–5.5% (Damodaran)
B7: Levered beta | C7: 0.85 | D7: Defense / nuclear peers (HII, GD, LHX, CW, CCJ) ~0.6–1.1; cost-plus naval reactor contracts (sole source) dampen cyclicality
B8: Cost of equity | C8: =C5+C7*C6 -> 0.0975
B9: Pre-tax cost of debt | C9: 0.06 | D9: BB-rated; 4.125% 2028/2029 notes trade ~5.5–6%; 0% 2030 converts carry an embedded equity option
B10: Tax rate | C10: 0.22 | D10: Model 2027E+ effective tax rate
B11: After-tax cost of debt | C11: =C9*(1-C10) -> 0.0468
B12: Target D/V | C12: 0.1 | D12: Net debt ~$1.7bn at YE2026E vs ~$14bn market cap ($152.29 × ~92m shares); 2.5x Adjusted EBITDA
B13: WACC | C13: =C8*(1-C12)+C11*C12 -> 0.09243
B15: Valuation date (live) | C15: =TODAY() -> 46302 | D15: Periods = (Dec-31-Year − today) / 365.25; cash flows assumed at year-end
B16: 2. UNLEVERED FREE CASH FLOW BUILD (USDm)
D17: 2026E | E17: 2027E | F17: 2028E | G17: 2029E | H17: 2030E | I17: 2031E | J17: 2032E | K17: 2033E | L17: 2034E | M17: 2035E | N17: Terminal
B18: Adj. EBITDA − total D&A − restructuring & acquisition costs | D18: =Model!BQ208-Model!BQ181-Model!BQ204 -> 499.4205 | E18: =Model!BR208-Model!BR181-Model!BR204 -> 565.55856 | F18: =Model!BS208-Model!BS181-Model!BS204 -> 649.19547 | G18: =Model!BT208-Model!BT181-Model!BT204 -> 737.8482 | H18: =Model!BU208-Model!BU181-Model!BU204 -> 821.31298 | I18: =H18*(1+I$26) -> 887.01801 | J18: =I18*(1+J$26) -> 951.32682 | K18: =J18*(1+K$26) -> 1013.1631 | L18: =K18*(1+L$26) -> 1071.4199 | M18: =L18*(1+M$26) -> 1124.9909
B19: × (1 − tax rate) | D19: =1-$C$10 -> 0.78 | E19: =1-$C$10 -> 0.78 | F19: =1-$C$10 -> 0.78 | G19: =1-$C$10 -> 0.78 | H19: =1-$C$10 -> 0.78 | I19: =1-$C$10 -> 0.78 | J19: =1-$C$10 -> 0.78 | K19: =1-$C$10 -> 0.78 | ... M19: =1-$C$10 -> 0.78
B20: NOPAT | D20: =D18*D19 -> 389.54799 | E20: =E18*E19 -> 441.13567 | F20: =F18*F19 -> 506.37246 | G20: =G18*G19 -> 575.5216 | H20: =H18*H19 -> 640.62412 | I20: =I18*I19 -> 691.87405 | J20: =J18*J19 -> 742.03492 | K20: =K18*K19 -> 790.26719 | ... M20: =M18*M19 -> 877.49293
B21: plus D&A (incl. acquisition amortization) | D21: =Model!BQ181 -> 132.4795 | E21: =Model!BR181 -> 163.78073 | F21: =Model!BS181 -> 184.02661 | G21: =Model!BT181 -> 209.56256 | H21: =Model!BU181 -> 231.60429 | I21: =H21*(1+I$26) -> 250.13263 | J21: =I21*(1+J$26) -> 268.26724 | K21: =J21*(1+K$26) -> 285.70461 | L21: =K21*(1+L$26) -> 302.13263 | M21: =L21*(1+M$26) -> 317.23926
B22: − Capex & acquisitions; + medical-sale proceeds after tax on gain (2027E) | D22: =Model!BQ269+Model!BQ270+Model!BQ271-Model!BQ83*$C$10 -> -506.22648 | E22: =Model!BR269+Model!BR270+Model!BR271-Model!BR83*$C$10 -> 370.95842 | F22: =Model!BS269+Model!BS270+Model!BS271-Model!BS83*$C$10 -> -402.05837 | G22: =Model!BT269+Model!BT270+Model!BT271-Model!BT83*$C$10 -> -404.17937 | H22: =Model!BU269+Model!BU270+Model!BU271-Model!BU83*$C$10 -> -430.79111 | I22: =(Model!BU269+Model!BU270)*(1+I$26) -> -465.2544 | J22: =I22*(1+J$26) -> -498.98535 | K22: =J22*(1+K$26) -> -531.4194 | L22: =K22*(1+L$26) -> -561.97601 | M22: =L22*(1+M$26) -> -590.07481
B23: − Δ Working capital (CF statement) | D23: =Model!BQ267 -> 5.895 | E23: =Model!BR267 -> -113.22728 | F23: =Model!BS267 -> -43.01786 | G23: =Model!BT267 -> -51.322583 | H23: =Model!BU267 -> -54.554066 | I23: =H23*(1+I$26) -> -58.918391 | J23: =I23*(1+J$26) -> -63.189975 | K23: =J23*(1+K$26) -> -67.297323 | L23: =K23*(1+L$26) -> -71.166919 | M23: =L23*(1+M$26) -> -74.725265
B24: Unlevered FCF | D24: =D20+D21+D22+D23 -> 21.69601 | E24: =E20+E21+E22+E23 -> 862.64755 | F24: =F20+F21+F22+F23 -> 245.32285 | G24: =G20+G21+G22+G23 -> 329.5822 | H24: =H20+H21+H22+H23 -> 386.88323 | I24: =I20+I21+I22+I23 -> 417.83388 | J24: =J20+J21+J22+J23 -> 448.12684 | K24: =K20+K21+K22+K23 -> 477.25509 | ... M24: =M20+M21+M22+M23 -> 529.93212 | N24: =M24*(1+$C$27) -> 551.1294
B25: Terminal Value (Gordon Growth) | N25: =N24/($C$13-$C$27) -> 10511.718
B26: Fade-period growth (2031E–35E; 8% → 5% linear) | I26: 0.08 | J26: =I26+($M$26-$I$26)/4 -> 0.0725 | K26: =J26+($M$26-$I$26)/4 -> 0.065 | L26: =K26+($M$26-$I$26)/4 -> 0.0575 | M26: 0.05
B27: Terminal growth rate | C27: 0.04
B28: Included in valuation (1 = yes) | D28: 0 | E28: 1 | F28: 1 | G28: 1 | H28: 1 | I28: 1 | J28: 1 | K28: 1 | L28: 1 | M28: 1
B29: Discount period (years) | D29: =(DATE(2026,12,31)-$C$15)/365.25 -> 0.23271732 | E29: =(DATE(2027,12,31)-$C$15)/365.25 -> 1.2320329 | F29: =(DATE(2028,12,31)-$C$15)/365.25 -> 2.2340862 | G29: =(DATE(2029,12,31)-$C$15)/365.25 -> 3.2334018 | H29: =(DATE(2030,12,31)-$C$15)/365.25 -> 4.2327173 | I29: =(DATE(2031,12,31)-$C$15)/365.25 -> 5.2320329 | J29: =(DATE(2032,12,31)-$C$15)/365.25 -> 6.2340862 | K29: =(DATE(2033,12,31)-$C$15)/365.25 -> 7.2334018 | L29: =(DATE(2034,12,31)-$C$15)/365.25 -> 8.2327173 | M29: =(DATE(2035,12,31)-$C$15)/365.25 -> 9.2320329 | N29: =M29 -> 9.2320329
B30: Discount factor | D30: =1/(1+$C$13)^D29 -> 0.97963691 | E30: =1/(1+$C$13)^E29 -> 0.89680455 | F30: =1/(1+$C$13)^F29 -> 0.82077732 | G30: =1/(1+$C$13)^G29 -> 0.75137719 | H30: =1/(1+$C$13)^H29 -> 0.68784513 | I30: =1/(1+$C$13)^I29 -> 0.62968497 | J30: =1/(1+$C$13)^J29 -> 0.57630299 | K30: =1/(1+$C$13)^K29 -> 0.52757418 | ... M30: =1/(1+$C$13)^M29 -> 0.44212885 | N30: =M30 -> 0.44212885
B31: PV of UFCF | D31: =D24*D30*D28 -> 0 | E31: =E24*E30*E28 -> 773.62625 | F31: =F24*F30*F28 -> 201.35543 | G31: =G24*G30*G28 -> 247.64055 | H31: =H24*H30*H28 -> 266.11574 | I31: =I24*I30*I28 -> 263.10372 | J31: =J24*J30*J28 -> 258.25684 | K31: =K24*K30*K28 -> 251.78746 | ... M31: =M24*M30*M28 -> 234.29828 | N31: =N25*N30 -> 4647.534
D32: BWXT Adjusted EBITDA expenses stock-based compensation; EBIT here deducts all D&A incl. acquisition amortization (added back in row 21). 2026E is shown but excluded (row 28 = 0): YE2026E net debt already reflects 2026 cash flows incl. the PCG purchase (avoids double counting).
B33: IMPLIED ROIC — invested capital roll-forward (USDm)
B34: Opening invested capital | D34: =Model!BL423 -> 2741.791 | E34: =D38 -> 3109.643 | F34: =E38 -> 2688.1311 | G34: =F38 -> 2949.1807 | H34: =G38 -> 3195.1201 | I34: =H38 -> 3448.861 | J34: =I38 -> 3722.9012 | K34: =J38 -> 4016.8093 | L34: =K38 -> 4329.8214 | M34: =L38 -> 4660.8317
B35: plus Capex and acquisitions | D35: =-D22 -> 506.22648 | E35: =-E22 -> -370.95842 | F35: =-F22 -> 402.05837 | G35: =-G22 -> 404.17937 | H35: =-H22 -> 430.79111 | I35: =-I22 -> 465.2544 | J35: =-J22 -> 498.98535 | K35: =-K22 -> 531.4194 | ... M35: =-M22 -> 590.07481
B36: less D&A | D36: =-D21 -> -132.4795 | E36: =-E21 -> -163.78073 | F36: =-F21 -> -184.02661 | G36: =-G21 -> -209.56256 | H36: =-H21 -> -231.60429 | I36: =-I21 -> -250.13263 | J36: =-J21 -> -268.26724 | K36: =-K21 -> -285.70461 | ... M36: =-M21 -> -317.23926
B37: plus Δ Working capital investment | D37: =-D23 -> -5.895 | E37: =-E23 -> 113.22728 | F37: =-F23 -> 43.01786 | G37: =-G23 -> 51.322583 | H37: =-H23 -> 54.554066 | I37: =-I23 -> 58.918391 | J37: =-J23 -> 63.189975 | K37: =-K23 -> 67.297323 | ... M37: =-M23 -> 74.725265
B38: Closing invested capital | D38: =SUM(D34:D37) -> 3109.643 | E38: =SUM(E34:E37) -> 2688.1311 | F38: =SUM(F34:F37) -> 2949.1807 | G38: =SUM(G34:G37) -> 3195.1201 | H38: =SUM(H34:H37) -> 3448.861 | I38: =SUM(I34:I37) -> 3722.9012 | J38: =SUM(J34:J37) -> 4016.8093 | K38: =SUM(K34:K37) -> 4329.8214 | ... M38: =SUM(M34:M37) -> 5008.3925
B39: NOPAT (row 20) | D39: =D20 -> 389.54799 | E39: =E20 -> 441.13567 | F39: =F20 -> 506.37246 | G39: =G20 -> 575.5216 | H39: =H20 -> 640.62412 | I39: =I20 -> 691.87405 | J39: =J20 -> 742.03492 | K39: =K20 -> 790.26719 | ... M39: =M20 -> 877.49293
B40: Implied ROIC (NOPAT / avg. invested capital) | D40: =IFERROR(D39/AVERAGE(D34,D38),"") -> 0.13314616 | E40: =IFERROR(E39/AVERAGE(E34,E38),"") -> 0.15217415 | F40: =IFERROR(F39/AVERAGE(F34,F38),"") -> 0.17965033 | G40: =IFERROR(G39/AVERAGE(G34,G38),"") -> 0.1873351 | H40: =IFERROR(H39/AVERAGE(H34,H38),"") -> 0.19284345 | I40: =IFERROR(I39/AVERAGE(I34,I38),"") -> 0.19294395 | J40: =IFERROR(J39/AVERAGE(J34,J38),"") -> 0.19174746 | K40: =IFERROR(K39/AVERAGE(K34,K38),"") -> 0.18936197 | ... M40: =IFERROR(M39/AVERAGE(M34,M38),"") -> 0.18150224
B41: Reinvestment rate (net investment / NOPAT) | D41: =IFERROR(SUM(D35:D37)/D39,"") -> 0.94430465 | E41: =IFERROR(SUM(E35:E37)/E39,"") -> -0.95551529 | F41: =IFERROR(SUM(F35:F37)/F39,"") -> 0.51552885 | G41: =IFERROR(SUM(G35:G37)/G39,"") -> 0.42733304 | H41: =IFERROR(SUM(H35:H37)/H39,"") -> 0.39608389 | I41: =IFERROR(SUM(I35:I37)/I39,"") -> 0.39608389 | J41: =IFERROR(SUM(J35:J37)/J39,"") -> 0.39608389 | K41: =IFERROR(SUM(K35:K37)/K39,"") -> 0.39608389 | ... M41: =IFERROR(SUM(M35:M37)/M39,"") -> 0.39608389
B42: Implied terminal RONIC (g / reinvestment rate) | N42: =IFERROR($C$27/M41,"") -> 0.10098871
D43: Opening IC = Model 2025A book IC (equity + net debt), rolled forward with capex + M&A (incl. PCG) − D&A + ΔWC; 2027E medical proceeds reduce IC.
B44: 3. VALUATION SUMMARY
B45: Sum of PV (explicit + fade, 2027E–2035E) | C45: =SUM(D31:M31) -> 2739.9357
B46: PV of Terminal Value | C46: =N31 -> 4647.534
B47: Enterprise Value | C47: =C45+C46 -> 7387.4697
B48: Less: Net debt + NCI (Model 2026E YE) | C48: =Model!BQ443+Model!BQ354 -> 1566.8929 | D48: Net debt incl. 0% 2030 convertible notes at face ($1.25bn); NCI ~$1m.
B49: Equity Value | C49: =C47-C48 -> 5820.5768
B50: Diluted shares (m, Model 2026E) | C50: =Model!BQ450 -> 92.0216
B51: Implied share price ($) | C51: =C49/C50 -> 63.252288
B52: Current share price ($) | C52: =Model!BQ448 -> 152.29
B53: Implied upside / (downside) | C53: =C51/C52-1 -> -0.58465895
B54: Required discount to DCF value for target IRR | C54: =1-((1+C13)/(1+H54))^H55 -> 0.14278979 | D54: vs. current | E54: Target IRR | H54: 0.15
B55: Max entry price for target IRR ($) | C55: =C51*(1-C54) -> 54.220507 | D55: =C55/C52-1 -> -0.64396541 | E55: Years for discount to close | H55: 3
B58: 4. SENSITIVITY: IMPLIED PRICE ($) — WACC × Terminal Growth
D60: WACC →
B61: Terminal growth ↓ | D61: =F61-0.01 -> 0.08243 | E61: =F61-0.005 -> 0.08743 | F61: =$C$13 -> 0.09243 | G61: =F61+0.005 -> 0.09743 | H61: =F61+0.01 -> 0.10243
B62: =B64-0.01 -> 0.03 | D62: =IFERROR((SUMPRODUCT($E$24:$M$24/(1+D$61)^$E$29:$M$29)+($M$24*(1+$B62)/(D$61-$B62))/(1+D$61)^$M$29-$C$48)/$C$50,"") -> 68.46455 | E62: =IFERROR((SUMPRODUCT($E$24:$M$24/(1+E$61)^$E$29:$M$29)+($M$24*(1+$B62)/(E$61-$B62))/(1+E$61)^$M$29-$C$48)/$C$50,"") -> 61.009766 | F62: =IFERROR((SUMPRODUCT($E$24:$M$24/(1+F$61)^$E$29:$M$29)+($M$24*(1+$B62)/(F$61-$B62))/(1+F$61)^$M$29-$C$48)/$C$50,"") -> 54.754621 | G62: =IFERROR((SUMPRODUCT($E$24:$M$24/(1+G$61)^$E$29:$M$29)+($M$24*(1+$B62)/(G$61-$B62))/(1+G$61)^$M$29-$C$48)/$C$50,"") -> 49.432009 | H62: =IFERROR((SUMPRODUCT($E$24:$M$24/(1+H$61)^$E$29:$M$29)+($M$24*(1+$B62)/(H$61-$B62))/(1+H$61)^$M$29-$C$48)/$C$50,"") -> 44.848591
B63: =B64-0.005 -> 0.035 | D63: =IFERROR((SUMPRODUCT($E$24:$M$24/(1+D$61)^$E$29:$M$29)+($M$24*(1+$B63)/(D$61-$B63))/(1+D$61)^$M$29-$C$48)/$C$50,"") -> 74.496907 | E63: =IFERROR((SUMPRODUCT($E$24:$M$24/(1+E$61)^$E$29:$M$29)+($M$24*(1+$B63)/(E$61-$B63))/(1+E$61)^$M$29-$C$48)/$C$50,"") -> 65.806273 | F63: =IFERROR((SUMPRODUCT($E$24:$M$24/(1+F$61)^$E$29:$M$29)+($M$24*(1+$B63)/(F$61-$B63))/(1+F$61)^$M$29-$C$48)/$C$50,"") -> 58.63354 | G63: =IFERROR((SUMPRODUCT($E$24:$M$24/(1+G$61)^$E$29:$M$29)+($M$24*(1+$B63)/(G$61-$B63))/(1+G$61)^$M$29-$C$48)/$C$50,"") -> 52.613792 | H63: =IFERROR((SUMPRODUCT($E$24:$M$24/(1+H$61)^$E$29:$M$29)+($M$24*(1+$B63)/(H$61-$B63))/(1+H$61)^$M$29-$C$48)/$C$50,"") -> 47.490354
B64: =$C$27 -> 0.04 | D64: =IFERROR((SUMPRODUCT($E$24:$M$24/(1+D$61)^$E$29:$M$29)+($M$24*(1+$B64)/(D$61-$B64))/(1+D$61)^$M$29-$C$48)/$C$50,"") -> 81.950984 | E64: =IFERROR((SUMPRODUCT($E$24:$M$24/(1+E$61)^$E$29:$M$29)+($M$24*(1+$B64)/(E$61-$B64))/(1+E$61)^$M$29-$C$48)/$C$50,"") -> 71.61406 | F64: =IFERROR((SUMPRODUCT($E$24:$M$24/(1+F$61)^$E$29:$M$29)+($M$24*(1+$B64)/(F$61-$B64))/(1+F$61)^$M$29-$C$48)/$C$50,"") -> 63.252288 | G64: =IFERROR((SUMPRODUCT($E$24:$M$24/(1+G$61)^$E$29:$M$29)+($M$24*(1+$B64)/(G$61-$B64))/(1+G$61)^$M$29-$C$48)/$C$50,"") -> 56.349603 | H64: =IFERROR((SUMPRODUCT($E$24:$M$24/(1+H$61)^$E$29:$M$29)+($M$24*(1+$B64)/(H$61-$B64))/(1+H$61)^$M$29-$C$48)/$C$50,"") -> 50.555272
B65: =B64+0.005 -> 0.045 | D65: =IFERROR((SUMPRODUCT($E$24:$M$24/(1+D$61)^$E$29:$M$29)+($M$24*(1+$B65)/(D$61-$B65))/(1+D$61)^$M$29-$C$48)/$C$50,"") -> 91.396532 | E65: =IFERROR((SUMPRODUCT($E$24:$M$24/(1+E$61)^$E$29:$M$29)+($M$24*(1+$B65)/(E$61-$B65))/(1+E$61)^$M$29-$C$48)/$C$50,"") -> 78.79064 | F65: =IFERROR((SUMPRODUCT($E$24:$M$24/(1+F$61)^$E$29:$M$29)+($M$24*(1+$B65)/(F$61-$B65))/(1+F$61)^$M$29-$C$48)/$C$50,"") -> 68.844839 | G65: =IFERROR((SUMPRODUCT($E$24:$M$24/(1+G$61)^$E$29:$M$29)+($M$24*(1+$B65)/(G$61-$B65))/(1+G$61)^$M$29-$C$48)/$C$50,"") -> 60.797948 | H65: =IFERROR((SUMPRODUCT($E$24:$M$24/(1+H$61)^$E$29:$M$29)+($M$24*(1+$B65)/(H$61-$B65))/(1+H$61)^$M$29-$C$48)/$C$50,"") -> 54.15387
B66: =B64+0.01 -> 0.05 | D66: =IFERROR((SUMPRODUCT($E$24:$M$24/(1+D$61)^$E$29:$M$29)+($M$24*(1+$B66)/(D$61-$B66))/(1+D$61)^$M$29-$C$48)/$C$50,"") -> 103.75468 | E66: =IFERROR((SUMPRODUCT($E$24:$M$24/(1+E$61)^$E$29:$M$29)+($M$24*(1+$B66)/(E$61-$B66))/(1+E$61)^$M$29-$C$48)/$C$50,"") -> 87.884553 | F66: =IFERROR((SUMPRODUCT($E$24:$M$24/(1+F$61)^$E$29:$M$29)+($M$24*(1+$B66)/(F$61-$B66))/(1+F$61)^$M$29-$C$48)/$C$50,"") -> 75.755456 | G66: =IFERROR((SUMPRODUCT($E$24:$M$24/(1+G$61)^$E$29:$M$29)+($M$24*(1+$B66)/(G$61-$B66))/(1+G$61)^$M$29-$C$48)/$C$50,"") -> 66.184168 | H66: =IFERROR((SUMPRODUCT($E$24:$M$24/(1+H$61)^$E$29:$M$29)+($M$24*(1+$B66)/(H$61-$B66))/(1+H$61)^$M$29-$C$48)/$C$50,"") -> 58.43883
B69: 5. REVERSE DCF
B70: To solve for the market-implied path: Data ▸ What-If Analysis ▸ Goal Seek — set C51 to the current price (C52) by changing C27 (terminal growth) or the fade-period growth inputs (I26:M26).
B72: 6. MAUBOUSSIN EV / NOPAT — TWO-STAGE FRAMEWORK
B73: EV/NOPAT = 1/r + [g × (1 − r/ROIIC) / (r × (r − g))] × [1 − ((1+g)/(1+r))^N]
B74: Formula source: Mauboussin & Rappaport, "Expectations Investing" (2021); Counterpoint Global, "What Does a Price-Earnings Multiple Mean?" (2020).
B76: Input | C76: Value | D76: Rationale (BWXT characteristics)
B77: r (Cost of capital / WACC) | C77: =$C$13 -> 0.09243 | D77: Linked from Section 1 WACC build
B78: g (NOPAT growth, Stage 1) | C78: 0.11 | D78: Model non-GAAP operating income CAGR 2026–30E ~11–12%: naval build rates, special materials, Commercial nuclear (CANDU refurbishments, SMR components)
B79: ROIIC (Return on incremental invested capital) | C79: 0.15 | D79: Sole-source naval reactor franchise (cost-plus-fee) and licensed nuclear facilities; heavy 2021–26 capacity capex (capex 6–15% of sales) dilutes incremental returns
B80: N (Years of value creation / CAP) | C80: 15 | D80: Unique Category 1 nuclear licences (NFS Erwin, Lynchburg), 60+ year Naval Nuclear Propulsion Program relationship; competitive advantage period long
B82: Calculation | C82: Value
B83: Steady-state component: 1 / r | C83: =1/C77 -> 10.818998
B84: Value-creation factor: 1 − r / ROIIC | C84: =1-C77/C79 -> 0.3838
B85: Growth multiplier: g × (1 − r/ROIIC) / (r × (r − g)) | C85: =C78*C84/(C77*(C77-C78)) -> -25.996384
B86: Time decay: 1 − ((1+g)/(1+r))^N | C86: =1-((1+C78)/(1+C77))^C80 -> -0.27039978
B87: PVGO component (growth value) | C87: =C85*C86 -> 7.0294165
B88: Mauboussin EV / NOPAT (steady-state + PVGO) | C88: =C83+C87 -> 17.848415
B90: VALUATION — Applied to 2028E NOPAT | C90: USDm
B91: 2028E Adj. EBITDA − D&A − restructuring & acquisition costs | C91: =Model!BS208-Model!BS181-Model!BS204 -> 649.19547
B92: Tax rate (from WACC build) | C92: =$C$10 -> 0.22
B93: 2028E NOPAT | C93: =C91*(1-C92) -> 506.37246
B94: × Mauboussin EV/NOPAT multiple | C94: =C88 -> 17.848415
B95: Implied Enterprise Value (2028E basis) | C95: =C93*C94 -> 9037.9457
B96: Less: YE2027 net debt + NCI (Model) | C96: =Model!BR443+Model!BR354 -> 1132.8069
B97: Implied Equity Value | C97: =C95-C96 -> 7905.1388
B98: Diluted shares 2028E (m, Model) | C98: =Model!BS450 -> 88.979127
B99: Implied share price 2028 ($) | C99: =C97/C98 -> 88.84262
B101: Current share price ($) | C101: =C52 -> 152.29
B102: Implied upside / (downside) | C102: =C99/C101-1 -> -0.4166221
B104: MARKET-IMPLIED EV/NOPAT TODAY | C104: USDm
B105: Current market cap (spot × diluted shares) | C105: =C52*C50 -> 14013.969
B106: Plus: YE2026 net debt + NCI | C106: =C48 -> 1566.8929
B107: Implied Enterprise Value (today) | C107: =C105+C106 -> 15580.862
B108: BWXT market-implied EV/NOPAT (on 2028E NOPAT) | C108: =C107/C93 -> 30.769569
B110: Multiple gap (Mauboussin − Market) | C110: =C88-C108 -> -12.921154
B111: Implied re-rating headroom | C111: =C88/C108-1 -> -0.4199329

Sheet Charts
B2: BWX Technologies — Historical Operating Performance (2014–2025)
B3: All historicals · USDm · Linked to Model. Backlog split: Government / Commercial Operations from 2021 (2020 recast); 2014–19 proxy = Nuclear Energy / NPG (Commercial) vs. remainder (Government). Adjusted EBITDA as reconciled in the Model bridge (company-published from 2020). 2014 returns not shown (balance sheet includes Power Generation pre-spin).
C7: 2014 | D7: 2015 | E7: 2016 | F7: 2017 | G7: 2018 | H7: 2019 | I7: 2020 | J7: 2021 | K7: 2022 | L7: 2023 | M7: 2024 | N7: 2025
B8: Government backlog | C8: =IF(ISNUMBER(Model!I19),Model!I19,IF(ISNUMBER(Model!I139),Model!I139,0)) -> 2780.734 | D8: =IF(ISNUMBER(Model!N19),Model!N19,IF(ISNUMBER(Model!N139),Model!N139,0)) -> 2314.955 | E8: =IF(ISNUMBER(Model!S19),Model!S19,IF(ISNUMBER(Model!S139),Model!S139,0)) -> 3489.987 | F8: =IF(ISNUMBER(Model!X19),Model!X19,IF(ISNUMBER(Model!X139),Model!X139,0)) -> 3333.701 | G8: =IF(ISNUMBER(Model!AC19),Model!AC19,IF(ISNUMBER(Model!AC139),Model!AC139,0)) -> 2674.966 | H8: =IF(ISNUMBER(Model!AH19),Model!AH19,IF(ISNUMBER(Model!AH139),Model!AH139,0)) -> 4558.718 | I8: =IF(ISNUMBER(Model!AM19),Model!AM19,IF(ISNUMBER(Model!AM139),Model!AM139,0)) -> 3680.126 | J8: =IF(ISNUMBER(Model!AR19),Model!AR19,IF(ISNUMBER(Model!AR139),Model!AR139,0)) -> 4532.17 | K8: =IF(ISNUMBER(Model!AW19),Model!AW19,IF(ISNUMBER(Model!AW139),Model!AW139,0)) -> 3515.377 | L8: =IF(ISNUMBER(Model!BB19),Model!BB19,IF(ISNUMBER(Model!BB139),Model!BB139,0)) -> 3216.673 | M8: =IF(ISNUMBER(Model!BG19),Model!BG19,IF(ISNUMBER(Model!BG139),Model!BG139,0)) -> 3912.58 | N8: =IF(ISNUMBER(Model!BL19),Model!BL19,IF(ISNUMBER(Model!BL139),Model!BL139,0)) -> 5541.291
B9: Commercial backlog | C9: =IF(ISNUMBER(Model!I67),Model!I67,IF(ISNUMBER(Model!I138),Model!I138,0)) -> 264.992 | D9: =IF(ISNUMBER(Model!N67),Model!N67,IF(ISNUMBER(Model!N138),Model!N138,0)) -> 335.333 | E9: =IF(ISNUMBER(Model!S67),Model!S67,IF(ISNUMBER(Model!S138),Model!S138,0)) -> 492.793 | F9: =IF(ISNUMBER(Model!X67),Model!X67,IF(ISNUMBER(Model!X138),Model!X138,0)) -> 637.053 | G9: =IF(ISNUMBER(Model!AC67),Model!AC67,IF(ISNUMBER(Model!AC138),Model!AC138,0)) -> 803.634 | H9: =IF(ISNUMBER(Model!AH67),Model!AH67,IF(ISNUMBER(Model!AH138),Model!AH138,0)) -> 729.748 | I9: =IF(ISNUMBER(Model!AM67),Model!AM67,IF(ISNUMBER(Model!AM138),Model!AM138,0)) -> 725.702 | J9: =IF(ISNUMBER(Model!AR67),Model!AR67,IF(ISNUMBER(Model!AR138),Model!AR138,0)) -> 643.866 | K9: =IF(ISNUMBER(Model!AW67),Model!AW67,IF(ISNUMBER(Model!AW138),Model!AW138,0)) -> 628.933 | L9: =IF(ISNUMBER(Model!BB67),Model!BB67,IF(ISNUMBER(Model!BB138),Model!BB138,0)) -> 780.974 | M9: =IF(ISNUMBER(Model!BG67),Model!BG67,IF(ISNUMBER(Model!BG138),Model!BG138,0)) -> 929.88 | N9: =IF(ISNUMBER(Model!BL67),Model!BL67,IF(ISNUMBER(Model!BL138),Model!BL138,0)) -> 1719.401
C11: =C7 -> 2014 | D11: =D7 -> 2015 | E11: =E7 -> 2016 | F11: =F7 -> 2017 | G11: =G7 -> 2018 | H11: =H7 -> 2019 | I11: =I7 -> 2020 | J11: =J7 -> 2021 | ... N11: =N7 -> 2025
B12: Adjusted EBITDA | C12: =Model!I208 -> 293.762 | D12: =Model!N208 -> 294.704 | E12: =Model!S208 -> 329.717 | F12: =Model!X208 -> 371.142 | G12: =Model!AC208 -> 367.574 | H12: =Model!AH208 -> 393.243 | I12: =Model!AM208 -> 427.026 | J12: =Model!AR208 -> 418.028 | K12: =Model!AW208 -> 439.413 | L12: =Model!BB208 -> 471.925 | M12: =Model!BG208 -> 498.669 | N12: =Model!BL208 -> 574.245
B13: Operating Income (GAAP) | C13: =Model!I164 -> 25.125 | D13: =Model!N164 -> 205.941 | E13: =Model!S164 -> 239.263 | F13: =Model!X164 -> 308.885 | G13: =Model!AC164 -> 304.977 | H13: =Model!AH164 -> 325.521 | I13: =Model!AM164 -> 358.552 | J13: =Model!AR164 -> 345.848 | K13: =Model!AW164 -> 348.571 | L13: =Model!BB164 -> 383.059 | M13: =Model!BG164 -> 380.607 | N13: =Model!BL164 -> 404.459
B14: Adj. EBITDA Margin % | C14: =Model!I209 -> 0.20250929 | D14: =Model!N209 -> 0.20819354 | E14: =Model!S209 -> 0.21264204 | F14: =Model!X209 -> 0.21990499 | G14: =Model!AC209 -> 0.20422037 | H14: =Model!AH209 -> 0.20752486 | I14: =Model!AM209 -> 0.20109385 | J14: =Model!AR209 -> 0.19680482 | K14: =Model!AW209 -> 0.19679609 | L14: =Model!BB209 -> 0.18904911 | M14: =Model!BG209 -> 0.18444261 | N14: =Model!BL209 -> 0.17953993
B15: GAAP Op. Margin % | C15: =Model!I254 -> 0.0173203 | D15: =Model!N254 -> 0.14548695 | E15: =Model!S254 -> 0.15430618 | F15: =Model!X254 -> 0.18301715 | G15: =Model!AC254 -> 0.16944212 | H15: =Model!AH254 -> 0.17178614 | I15: =Model!AM254 -> 0.16884827 | J15: =Model!AR254 -> 0.16282295 | K15: =Model!AW254 -> 0.15611147 | L15: =Model!BB254 -> 0.15345015 | M15: =Model!BG254 -> 0.14077504 | N15: =Model!BL254 -> 0.12645568
C17: =C7 -> 2014 | D17: =D7 -> 2015 | E17: =E7 -> 2016 | F17: =F7 -> 2017 | G17: =G7 -> 2018 | H17: =H7 -> 2019 | I17: =I7 -> 2020 | J17: =J7 -> 2021 | ... N17: =N7 -> 2025
B18: ROIC | C18: =IFERROR(Model!I426+0,NA()) -> 0 | D18: =IFERROR(Model!N426+0,NA()) -> 0.36902585 | E18: =IFERROR(Model!S426+0,NA()) -> 0.36642699 | F18: =IFERROR(Model!X426+0,NA()) -> 0.2713436 | G18: =IFERROR(Model!AC426+0,NA()) -> 0.25795904 | H18: =IFERROR(Model!AH426+0,NA()) -> 0.22761706 | I18: =IFERROR(Model!AM426+0,NA()) -> 0.1856922 | J18: =IFERROR(Model!AR426+0,NA()) -> 0.15116219 | K18: =IFERROR(Model!AW426+0,NA()) -> 0.13900015 | L18: =IFERROR(Model!BB426+0,NA()) -> 0.14624844 | M18: =IFERROR(Model!BG426+0,NA()) -> 0.16259311 | N18: =IFERROR(Model!BL426+0,NA()) -> 0.14374023
B19: RONTA | C19: =IFERROR(Model!I437+0,NA()) -> 0 | D19: =IFERROR(Model!N437+0,NA()) -> 0.18507487 | E19: =IFERROR(Model!S437+0,NA()) -> 0.23668904 | F19: =IFERROR(Model!X437+0,NA()) -> 0.17863614 | G19: =IFERROR(Model!AC437+0,NA()) -> 0.31611297 | H19: =IFERROR(Model!AH437+0,NA()) -> 0.24575769 | I19: =IFERROR(Model!AM437+0,NA()) -> 0.20524424 | J19: =IFERROR(Model!AR437+0,NA()) -> 0.17195461 | K19: =IFERROR(Model!AW437+0,NA()) -> 0.15671809 | L19: =IFERROR(Model!BB437+0,NA()) -> 0.15902526 | M19: =IFERROR(Model!BG437+0,NA()) -> 0.17088824 | N19: =IFERROR(Model!BL437+0,NA()) -> 0.14234019
B20: Adj. EBITDA margin % | C20: =IFERROR(Model!I209+0,NA()) -> 0.20250929 | D20: =IFERROR(Model!N209+0,NA()) -> 0.20819354 | E20: =IFERROR(Model!S209+0,NA()) -> 0.21264204 | F20: =IFERROR(Model!X209+0,NA()) -> 0.21990499 | G20: =IFERROR(Model!AC209+0,NA()) -> 0.20422037 | H20: =IFERROR(Model!AH209+0,NA()) -> 0.20752486 | I20: =IFERROR(Model!AM209+0,NA()) -> 0.20109385 | J20: =IFERROR(Model!AR209+0,NA()) -> 0.19680482 | K20: =IFERROR(Model!AW209+0,NA()) -> 0.19679609 | L20: =IFERROR(Model!BB209+0,NA()) -> 0.18904911 | M20: =IFERROR(Model!BG209+0,NA()) -> 0.18444261 | N20: =IFERROR(Model!BL209+0,NA()) -> 0.17953993
B21: FCF margin % | C21: =IFERROR(Model!I290+0,NA()) -> -0.00076105914 | D21: =IFERROR(Model!N290+0,NA()) -> 0.18496901 | E21: =IFERROR(Model!S290+0,NA()) -> 0.12073988 | F21: =IFERROR(Model!X290+0,NA()) -> 0.074225976 | G21: =IFERROR(Model!AC290+0,NA()) -> 0.033308721 | H21: =IFERROR(Model!AH290+0,NA()) -> 0.051318261 | I21: =IFERROR(Model!AM290+0,NA()) -> -0.027588678 | J21: =IFERROR(Model!AR290+0,NA()) -> 0.035297264 | K21: =IFERROR(Model!AW290+0,NA()) -> 0.020777183 | L21: =IFERROR(Model!BB290+0,NA()) -> 0.085091629 | M21: =IFERROR(Model!BG290+0,NA()) -> 0.094235801 | N21: =IFERROR(Model!BL290+0,NA()) -> 0.092323878
