Workbook

Sheet Model
CF1: SCENARIO SWITCH ▼ (Bull / Base / Bear) — drives all scenario-linked forecast drivers
B2: Clean Harbors, Inc. (NYSE: CLH) — 3-Statement Financial Model | CF2: Base
B3: US GAAP as reported · USD millions (per-share data in USD; shares in millions) · Source: Clean Harbors Forms 10-K / 10-Q and Form 8-K earnings releases (Ex. 99.1), deal & financing 8-Ks (Terra Nova May-26, ES&H Jul-26, EnviroServe Aug-26, $600m 6.25% notes Sep-26), Form 4 (share price), SEC EDGAR CIK 0000822818 (investor-relations releases are the same documents as filed on EDGAR)
B4: Basis notes: calendar fiscal year; each period as originally reported (quarters from 10-Qs, Q4 = FY − 9M; cash flows de-cumulated from YTD). Segments: Technical Services / Site Services 2006–08; Technical, Field, Industrial, Exploration (Eveready, Jul-09) / Oil & Gas Field Services 2009–12; Safety-Kleen acquired 28-Dec-2012 → 5–6 segments 2013–17; Environmental Services + Safety-Kleen from Q1/18 (2017 recast); Safety-Kleen renamed SKSS Q1/21. Adjusted EBITDA as published by period (SBC added back from Q1/21). Acquisitions: HydroChemPSC Oct-21, Thompson Industrial Mar-23, Noble Oil Mar-24, Depot Connect Mar-26, Terra Nova May-26, Western Oil Jul-26; ES&H ($305m) & EnviroServe ($470m) pending — excluded from FY26 guidance, modelled separately from Q3/26E.
CH5: Forecast | CI5: Historical | CJ5: Historical | CK5: Historical
B6: (USDm) | C6: 2006 | D6: 2007 | E6: 2008 | F6: 2009 | G6: 2010 | H6: 2011 | I6: 2012 | J6: Q1/13 | K6: Q2/13 | L6: Q3/13 | M6: Q4/13 | N6: 2013 | O6: Q1/14 | P6: Q2/14 | Q6: Q3/14 | R6: Q4/14 | S6: 2014 | T6: Q1/15 | U6: Q2/15 | V6: Q3/15 | W6: Q4/15 | X6: 2015 | Y6: Q1/16 | Z6: Q2/16 | AA6: Q3/16 | AB6: Q4/16 | AC6: 2016 | AD6: Q1/17 | AE6: Q2/17 | AF6: Q3/17 | AG6: Q4/17 | AH6: 2017 | AI6: Q1/18 | AJ6: Q2/18 | AK6: Q3/18 | AL6: Q4/18 | AM6: 2018 | AN6: Q1/19 | AO6: Q2/19 | AP6: Q3/19 | AQ6: Q4/19 | AR6: 2019 | AS6: Q1/20 | AT6: Q2/20 | AU6: Q3/20 | AV6: Q4/20 | AW6: 2020 | AX6: Q1/21 | AY6: Q2/21 | AZ6: Q3/21 | BA6: Q4/21 | BB6: 2021 | BC6: Q1/22 | BD6: Q2/22 | BE6: Q3/22 | BF6: Q4/22 | BG6: 2022 | BH6: Q1/23 | BI6: Q2/23 | BJ6: Q3/23 | BK6: Q4/23 | BL6: 2023 | BM6: Q1/24 | BN6: Q2/24 | BO6: Q3/24 | BP6: Q4/24 | BQ6: 2024 | BR6: Q1/25 | BS6: Q2/25 | BT6: Q3/25 | BU6: Q4/25 | BV6: 2025 | BW6: Q1/26 | BX6: Q2/26 | BY6: Q3/26E | BZ6: Q4/26E | CA6: 2026E | CB6: 2027E | CC6: 2028E | CD6: 2029E | CE6: 2030E | CF6: Modelling Notes | CH6: 5Y CAGR | CI6: 5Y CAGR | CJ6: 10Y CAGR | CK6: 19Y CAGR
CH7: 25-'30 | CI7: 20-'25 | CJ7: 15-'25 | CK7: 06-'25
B8: SEGMENT & SERVICE-LINE P&L — ENVIRONMENTAL SERVICES · SAFETY-KLEEN SUSTAINABILITY SOLUTIONS (service-line revenue × segment Adjusted EBITDA margin build) | CF8: SEGMENT BUILD — CLH reports segment profit as Adjusted EBITDA (no segment gross profit); revenues built by service line (third-party, ASC 606 disaggregation from 2018) + intersegment = segment direct revenues
CN9: SCENARIO INPUT TABLE — driver assumptions per Bull / Base / Bear | CO9: Bull | CP9: Base | CQ9: Bear | CR9: Bull / Bear = Base + Δ (Δ inputs on each block header). Outlook block = high / mid / low end of FY26 ranges.
B10: Environmental Services (ES) — Technical Services (incineration, landfill, TSDF network) · Field & Emergency Response · Industrial Services & Other · Safety-Kleen Environmental Services (ES portion from 2021) | CF10: ES — modelling logic: service lines = prior-year quarter × (1 + growth input) for Q3/Q4-26E; 2027E+ scenario levers. ES Adj. EBITDA = direct revenues × margin.
B11: Technical Services — third-party revenues | AI11: 236.306 | AJ11: 257.006 | AK11: 264.769 | AL11: 279.307 | AM11: 1037.388 | AN11: 251.919 | AO11: 275.908 | AP11: 292.506 | AQ11: 299.71 | AR11: 1120.043 | AS11: 275.273 | AT11: 241.929 | AU11: 257.612 | AV11: 287.9 | AW11: 1062.714 | AX11: 272.04 | AY11: 306.865 | AZ11: 308.158 | BA11: 322.561 | BB11: 1209.624 | BC11: 323.656 | BD11: 387.019 | BE11: 398.664 | BF11: 385.925 | BG11: 1495.264 | BH11: 366.509 | BI11: 389.908 | BJ11: 403.889 | BK11: 403.541 | BL11: 1563.847 | BM11: 407.491 | BN11: 443.668 | BO11: 437.18 | BP11: 445.211 | BQ11: 1733.55 | BR11: 426.205 | BS11: 463.421 | BT11: 490.768 | BU11: 479.311 | BV11: 1859.705 | BW11: 448.313 | BX11: 544.91 | BY11: =BT11*(1+BY12) -> 549.66016 | BZ11: =BU11*(1+BZ12) -> 527.2421 | CA11: =SUM(BW11,BX11,BY11,BZ11) -> 2070.1253 | CB11: =CA11*(1+CB12) -> 2235.7353 | CC11: =CB11*(1+CC12) -> 2403.4154 | CD11: =CC11*(1+CD12) -> 2571.6545 | CE11: =CD11*(1+CE12) -> 2738.812 | CF11: Incineration, landfill, wastewater, TSDF/transfer network (Kimball, NE incinerator online 2025; Terra Nova from 13-May-26). Historical: 10-Q/10-K revenue disaggregation (third-party), Q4 = FY − 9M. | CH11: =IFERROR((CE11/BV11)^(1/5)-1,"n/m") -> 0.080497171 | CI11: =IFERROR((BV11/AW11)^(1/5)-1,"n/m") -> 0.11842156 | CJ11: =IFERROR((BV11/X11)^(1/10)-1,"n/m") -> n/m | CK11: =IFERROR((BV11/C11)^(1/19)-1,"n/m") -> n/m | CN11: FY26 outlook — Q2-26 release (29-Jul-26); excludes pending ES&H / EnviroServe | CO11: High | CP11: Mid | CQ11: Low | CR11: Company guidance excludes ES&H (signed 17-Jul-26) and EnviroServe (signed 12-Aug-26) — the model adds them separately.
B12: Technical Services y/y % | D12: =IF(AND(ISNUMBER(D11),ISNUMBER(C11)),IFERROR(D11/C11-1,""),"") | E12: =IF(AND(ISNUMBER(E11),ISNUMBER(D11)),IFERROR(E11/D11-1,""),"") | F12: =IF(AND(ISNUMBER(F11),ISNUMBER(E11)),IFERROR(F11/E11-1,""),"") | G12: =IF(AND(ISNUMBER(G11),ISNUMBER(F11)),IFERROR(G11/F11-1,""),"") | H12: =IF(AND(ISNUMBER(H11),ISNUMBER(G11)),IFERROR(H11/G11-1,""),"") | I12: =IF(AND(ISNUMBER(I11),ISNUMBER(H11)),IFERROR(I11/H11-1,""),"") | N12: =IF(AND(ISNUMBER(N11),ISNUMBER(I11)),IFERROR(N11/I11-1,""),"") | O12: =IF(AND(ISNUMBER(O11),ISNUMBER(J11)),IFERROR(O11/J11-1,""),"") | P12: =IF(AND(ISNUMBER(P11),ISNUMBER(K11)),IFERROR(P11/K11-1,""),"") | Q12: =IF(AND(ISNUMBER(Q11),ISNUMBER(L11)),IFERROR(Q11/L11-1,""),"") | R12: =IF(AND(ISNUMBER(R11),ISNUMBER(M11)),IFERROR(R11/M11-1,""),"") | S12: =IF(AND(ISNUMBER(S11),ISNUMBER(N11)),IFERROR(S11/N11-1,""),"") | T12: =IF(AND(ISNUMBER(T11),ISNUMBER(O11)),IFERROR(T11/O11-1,""),"") | U12: =IF(AND(ISNUMBER(U11),ISNUMBER(P11)),IFERROR(U11/P11-1,""),"") | ... BX12: =IF(AND(ISNUMBER(BX11),ISNUMBER(BS11)),IFERROR(BX11/BS11-1,""),"") -> 0.17584227 | BY12: =BY13 -> 0.12 | BZ12: =BZ13 -> 0.1 | CA12: =IFERROR(CA11/BV11-1,"") -> 0.11314712 | CB12: =CHOOSE(MATCH($CF$2,{"Bull","Base","Bear"},0),$CO$31,$CP$31,$CQ$31) -> 0.08 | CC12: =CHOOSE(MATCH($CF$2,{"Bull","Base","Bear"},0),$CO$32,$CP$32,$CQ$32) -> 0.075 | CD12: =CHOOSE(MATCH($CF$2,{"Bull","Base","Bear"},0),$CO$33,$CP$33,$CQ$33) -> 0.07 | CE12: =CHOOSE(MATCH($CF$2,{"Bull","Base","Bear"},0),$CO$34,$CP$34,$CQ$34) -> 0.065 | CF12: Q3/Q4-26E: growth input below. 2027E+: scenario lever TS_growth (pricing + volumes into the disposal network, PFAS, reshoring). | CN12: FY26 Adjusted EBITDA ($m) | CO12: 1410 | CP12: 1380 | CQ12: 1350 | CR12: Raised by $110m at the mid-point in the Q2-26 release (from $1,240–1,300m). Drives the Q3/Q4-26E margin calibration.
B13: Q3/Q4-26E growth input (incl. Terra Nova from May-26) | BY13: 0.12 | BZ13: 0.1 | CF13: Q2/26 +17.6% y/y (incl. Terra Nova ~$12m/qtr, Kimball ramp, large PFAS filtration project). H2 input +12% / +10% as Kimball and the PFAS project anniversary. | CN13: FY26 GAAP net income ($m) | CO13: 531 | CP13: 506 | CQ13: 481 | CR13: Q2-26 release guidance reconciliation (memo).
B14: Field & Emergency Response Services — third-party revenues | AI14: 69.935 | AJ14: 76.092 | AK14: 77.025 | AL14: 81.675 | AM14: 304.727 | AN14: 71.626 | AO14: 86.722 | AP14: 95.546 | AQ14: 87.012 | AR14: 340.906 | AS14: 105.912 | AT14: 127.353 | AU14: 115.989 | AV14: 111.782 | AW14: 461.036 | AX14: 105.168 | AY14: 106.986 | AZ14: 116.677 | BA14: 137.549 | BB14: 466.38 | BC14: 132.359 | BD14: 144.86 | BE14: 150.031 | BF14: 148.05 | BG14: 575.3 | BH14: 148.086 | BI14: 154.359 | BJ14: 155.046 | BK14: 152.422 | BL14: 609.913 | BM14: 163.469 | BN14: 252.893 | BO14: 260.2 | BP14: 218.558 | BQ14: 895.12 | BR14: 215.702 | BS14: 242.791 | BT14: 232.262 | BU14: 246.607 | BV14: 937.362 | BW14: 231.358 | BX14: 249.02 | BY14: =BT14*(1+BY15) -> 248.52034 | BZ14: =BU14*(1+BZ15) -> 258.93735 | CA14: =SUM(BW14,BX14,BY14,BZ14) -> 987.83569 | CB14: =CA14*(1+CB15) -> 1037.2275 | CC14: =CB14*(1+CC15) -> 1089.0888 | CD14: =CC14*(1+CD15) -> 1138.0978 | CE14: =CD14*(1+CE15) -> 1189.3122 | CH14: =IFERROR((CE14/BV14)^(1/5)-1,"n/m") -> 0.048763851 | CI14: =IFERROR((BV14/AW14)^(1/5)-1,"n/m") -> 0.15248293 | CJ14: =IFERROR((BV14/X14)^(1/10)-1,"n/m") -> n/m | CK14: =IFERROR((BV14/C14)^(1/19)-1,"n/m") -> n/m | CN14: FY26 net cash from operating activities ($m) | CO14: 1010 | CP14: 950 | CQ14: 890 | CR14: Q2-26 release (memo vs model CFO).
B15: Field & Emergency Response y/y % | D15: =IF(AND(ISNUMBER(D14),ISNUMBER(C14)),IFERROR(D14/C14-1,""),"") | E15: =IF(AND(ISNUMBER(E14),ISNUMBER(D14)),IFERROR(E14/D14-1,""),"") | F15: =IF(AND(ISNUMBER(F14),ISNUMBER(E14)),IFERROR(F14/E14-1,""),"") | G15: =IF(AND(ISNUMBER(G14),ISNUMBER(F14)),IFERROR(G14/F14-1,""),"") | H15: =IF(AND(ISNUMBER(H14),ISNUMBER(G14)),IFERROR(H14/G14-1,""),"") | I15: =IF(AND(ISNUMBER(I14),ISNUMBER(H14)),IFERROR(I14/H14-1,""),"") | N15: =IF(AND(ISNUMBER(N14),ISNUMBER(I14)),IFERROR(N14/I14-1,""),"") | O15: =IF(AND(ISNUMBER(O14),ISNUMBER(J14)),IFERROR(O14/J14-1,""),"") | P15: =IF(AND(ISNUMBER(P14),ISNUMBER(K14)),IFERROR(P14/K14-1,""),"") | Q15: =IF(AND(ISNUMBER(Q14),ISNUMBER(L14)),IFERROR(Q14/L14-1,""),"") | R15: =IF(AND(ISNUMBER(R14),ISNUMBER(M14)),IFERROR(R14/M14-1,""),"") | S15: =IF(AND(ISNUMBER(S14),ISNUMBER(N14)),IFERROR(S14/N14-1,""),"") | T15: =IF(AND(ISNUMBER(T14),ISNUMBER(O14)),IFERROR(T14/O14-1,""),"") | U15: =IF(AND(ISNUMBER(U14),ISNUMBER(P14)),IFERROR(U14/P14-1,""),"") | ... BX15: =IF(AND(ISNUMBER(BX14),ISNUMBER(BS14)),IFERROR(BX14/BS14-1,""),"") -> 0.025655811 | BY15: =BY16 -> 0.07 | BZ15: =BZ16 -> 0.05 | CA15: =IFERROR(CA14/BV14-1,"") -> 0.053846529 | CB15: =CHOOSE(MATCH($CF$2,{"Bull","Base","Bear"},0),$CO$36,$CP$36,$CQ$36) -> 0.05 | CC15: =CHOOSE(MATCH($CF$2,{"Bull","Base","Bear"},0),$CO$37,$CP$37,$CQ$37) -> 0.05 | CD15: =CHOOSE(MATCH($CF$2,{"Bull","Base","Bear"},0),$CO$38,$CP$38,$CQ$38) -> 0.045 | CE15: =CHOOSE(MATCH($CF$2,{"Bull","Base","Bear"},0),$CO$39,$CP$39,$CQ$39) -> 0.045 | CN15: FY26 additions to PP&E ($m) | CO15: 565 | CP15: 535 | CQ15: 505 | CR15: Q2-26 release adjusted-FCF reconciliation: ($505)–($565)m.
B16: Q3/Q4-26E growth input | BY16: 0.07 | BZ16: 0.05 | CF16: Q2/26 +2.6% y/y against large prior-year ER comps; company: "multiple large emergency response events that should support Q3 growth". ES&H (Gulf ER) modelled separately in the deal block. | CN16: FY26 adjusted free cash flow ($m) | CO16: 580 | CP16: 550 | CQ16: 520 | CR16: Raised by $30m at the mid-point.
B17: Industrial Services & Other — third-party revenues (incl. Oil, Gas & Lodging and other to 2019) | AI17: 133.447 | AJ17: 186.818 | AK17: 167.019 | AL17: 174.444 | AM17: 661.728 | AN17: 150.153 | AO17: 163.664 | AP17: 162.07 | AQ17: 155.527 | AR17: 631.414 | AS17: 146.919 | AT17: 95.072 | AU17: 124.582 | AV17: 113.758 | AW17: 480.331 | AX17: 119.81 | AY17: 150.367 | AZ17: 154.977 | BA17: 280.845 | BB17: 705.999 | BC17: 308.838 | BD17: 360.87 | BE17: 332.025 | BF17: 309.339 | BG17: 1311.072 | BH17: 336.379 | BI17: 399.545 | BJ17: 350.251 | BK17: 332.763 | BL17: 1418.938 | BM17: 359.397 | BN17: 359.471 | BO17: 345.573 | BP17: 313.061 | BQ17: 1377.502 | BR17: 322.358 | BS17: 361.58 | BT17: 332.102 | BU17: 311.843 | BV17: 1327.883 | BW17: 302.561 | BX17: 358.929 | BY17: =BT17*(1+BY18) -> 342.06506 | BZ17: =BU17*(1+BZ18) -> 324.31672 | CA17: =SUM(BW17,BX17,BY17,BZ17) -> 1327.8718 | CB17: =CA17*(1+CB18) -> 1367.7079 | CC17: =CB17*(1+CC18) -> 1415.5777 | CD17: =CC17*(1+CD18) -> 1465.1229 | CE17: =CD17*(1+CE18) -> 1516.4022 | CH17: =IFERROR((CE17/BV17)^(1/5)-1,"n/m") -> 0.026906543 | CI17: =IFERROR((BV17/AW17)^(1/5)-1,"n/m") -> 0.2255297 | CJ17: =IFERROR((BV17/X17)^(1/10)-1,"n/m") -> n/m | CK17: =IFERROR((BV17/C17)^(1/19)-1,"n/m") -> n/m | CN17: FY26 point estimates (guidance mid-points; all cases)
B18: Industrial Services & Other y/y % | D18: =IF(AND(ISNUMBER(D17),ISNUMBER(C17)),IFERROR(D17/C17-1,""),"") | E18: =IF(AND(ISNUMBER(E17),ISNUMBER(D17)),IFERROR(E17/D17-1,""),"") | F18: =IF(AND(ISNUMBER(F17),ISNUMBER(E17)),IFERROR(F17/E17-1,""),"") | G18: =IF(AND(ISNUMBER(G17),ISNUMBER(F17)),IFERROR(G17/F17-1,""),"") | H18: =IF(AND(ISNUMBER(H17),ISNUMBER(G17)),IFERROR(H17/G17-1,""),"") | I18: =IF(AND(ISNUMBER(I17),ISNUMBER(H17)),IFERROR(I17/H17-1,""),"") | N18: =IF(AND(ISNUMBER(N17),ISNUMBER(I17)),IFERROR(N17/I17-1,""),"") | O18: =IF(AND(ISNUMBER(O17),ISNUMBER(J17)),IFERROR(O17/J17-1,""),"") | P18: =IF(AND(ISNUMBER(P17),ISNUMBER(K17)),IFERROR(P17/K17-1,""),"") | Q18: =IF(AND(ISNUMBER(Q17),ISNUMBER(L17)),IFERROR(Q17/L17-1,""),"") | R18: =IF(AND(ISNUMBER(R17),ISNUMBER(M17)),IFERROR(R17/M17-1,""),"") | S18: =IF(AND(ISNUMBER(S17),ISNUMBER(N17)),IFERROR(S17/N17-1,""),"") | T18: =IF(AND(ISNUMBER(T17),ISNUMBER(O17)),IFERROR(T17/O17-1,""),"") | U18: =IF(AND(ISNUMBER(U17),ISNUMBER(P17)),IFERROR(U17/P17-1,""),"") | ... BX18: =IF(AND(ISNUMBER(BX17),ISNUMBER(BS17)),IFERROR(BX17/BS17-1,""),"") -> -0.0073317108 | BY18: =BY19 -> 0.03 | BZ18: =BZ19 -> 0.04 | CA18: =IFERROR(CA17/BV17-1,"") -> -8.4495396e-06 | CB18: =CHOOSE(MATCH($CF$2,{"Bull","Base","Bear"},0),$CO$41,$CP$41,$CQ$41) -> 0.03 | CC18: =CHOOSE(MATCH($CF$2,{"Bull","Base","Bear"},0),$CO$42,$CP$42,$CQ$42) -> 0.035 | CD18: =CHOOSE(MATCH($CF$2,{"Bull","Base","Bear"},0),$CO$43,$CP$43,$CQ$43) -> 0.035 | CE18: =CHOOSE(MATCH($CF$2,{"Bull","Base","Bear"},0),$CO$44,$CP$44,$CQ$44) -> 0.035 | CN18: Stock-based compensation ($m) | CP18: 49.5 | CR18: Guidance reconciliation $48–51m.
B19: Q3/Q4-26E growth input (incl. Depot Connect from 20-Mar-26) | BY19: 0.03 | BZ19: 0.04 | CF19: Q2/26 −0.7% y/y (refinery turnaround timing) despite Depot Connect International ($131m, Mar-26). New data-center offering expected to support growth. | CN19: Depreciation & amortization ($m) | CP19: 480 | CR19: Guidance reconciliation $475–485m.
B20: Safety-Kleen Environmental Services — ES portion (containerized waste, vacuum, branch services; from 2021) | AI20: 0 | AJ20: 0 | AK20: 0 | AL20: 0 | AM20: 0 | AN20: 0 | AO20: 0 | AP20: 0 | AQ20: 0 | AR20: 0 | AS20: 0 | AT20: 0 | AU20: 0 | AV20: 0 | AW20: 0 | AX20: 155.86 | AY20: 158.929 | AZ20: 164.019 | BA20: 165.096 | BB20: 643.904 | BC20: 175.945 | BD20: 191.757 | BE20: 199.312 | BF20: 196.323 | BG20: 763.337 | BH20: 210.008 | BI20: 217.67 | BJ20: 226.093 | BK20: 223.44 | BL20: 877.211 | BM20: 230.922 | BN20: 241.266 | BO20: 244.697 | BP20: 237.268 | BQ20: 954.153 | BR20: 242.773 | BS20: 262.267 | BT20: 263.448 | BU20: 252.916 | BV20: 1021.404 | BW20: 260.216 | BX20: 291.673 | BY20: =BT20*(1+BY21) -> 289.7928 | BZ20: =BU20*(1+BZ21) -> 275.67844 | CA20: =SUM(BW20,BX20,BY20,BZ20) -> 1117.3602 | CB20: =CA20*(1+CB21) -> 1195.5755 | CC20: =CB20*(1+CC21) -> 1273.2879 | CD20: =CC20*(1+CD21) -> 1349.6851 | CE20: =CD20*(1+CE21) -> 1430.6662 | CH20: =IFERROR((CE20/BV20)^(1/5)-1,"n/m") -> 0.069715171 | CI20: =IFERROR((BV20/AW20)^(1/5)-1,"n/m") -> n/m | CJ20: =IFERROR((BV20/X20)^(1/10)-1,"n/m") -> n/m | CK20: =IFERROR((BV20/C20)^(1/19)-1,"n/m") -> n/m | CN20: Accretion of environmental liabilities ($m) | CP20: 15.5 | CR20: Guidance reconciliation $15–16m.
B21: Safety-Kleen Environmental Services (ES) y/y % | D21: =IF(AND(ISNUMBER(D20),ISNUMBER(C20)),IFERROR(D20/C20-1,""),"") | E21: =IF(AND(ISNUMBER(E20),ISNUMBER(D20)),IFERROR(E20/D20-1,""),"") | F21: =IF(AND(ISNUMBER(F20),ISNUMBER(E20)),IFERROR(F20/E20-1,""),"") | G21: =IF(AND(ISNUMBER(G20),ISNUMBER(F20)),IFERROR(G20/F20-1,""),"") | H21: =IF(AND(ISNUMBER(H20),ISNUMBER(G20)),IFERROR(H20/G20-1,""),"") | I21: =IF(AND(ISNUMBER(I20),ISNUMBER(H20)),IFERROR(I20/H20-1,""),"") | N21: =IF(AND(ISNUMBER(N20),ISNUMBER(I20)),IFERROR(N20/I20-1,""),"") | O21: =IF(AND(ISNUMBER(O20),ISNUMBER(J20)),IFERROR(O20/J20-1,""),"") | P21: =IF(AND(ISNUMBER(P20),ISNUMBER(K20)),IFERROR(P20/K20-1,""),"") | Q21: =IF(AND(ISNUMBER(Q20),ISNUMBER(L20)),IFERROR(Q20/L20-1,""),"") | R21: =IF(AND(ISNUMBER(R20),ISNUMBER(M20)),IFERROR(R20/M20-1,""),"") | S21: =IF(AND(ISNUMBER(S20),ISNUMBER(N20)),IFERROR(S20/N20-1,""),"") | T21: =IF(AND(ISNUMBER(T20),ISNUMBER(O20)),IFERROR(T20/O20-1,""),"") | U21: =IF(AND(ISNUMBER(U20),ISNUMBER(P20)),IFERROR(U20/P20-1,""),"") | ... BX21: =IF(AND(ISNUMBER(BX20),ISNUMBER(BS20)),IFERROR(BX20/BS20-1,""),"") -> 0.11212238 | BY21: =BY22 -> 0.1 | BZ21: =BZ22 -> 0.09 | CA21: =IFERROR(CA20/BV20-1,"") -> 0.093945432 | CB21: =CHOOSE(MATCH($CF$2,{"Bull","Base","Bear"},0),$CO$46,$CP$46,$CQ$46) -> 0.07 | CC21: =CHOOSE(MATCH($CF$2,{"Bull","Base","Bear"},0),$CO$47,$CP$47,$CQ$47) -> 0.065 | CD21: =CHOOSE(MATCH($CF$2,{"Bull","Base","Bear"},0),$CO$48,$CP$48,$CQ$48) -> 0.06 | CE21: =CHOOSE(MATCH($CF$2,{"Bull","Base","Bear"},0),$CO$49,$CP$49,$CQ$49) -> 0.06 | CN21: Interest expense, net ($m) | CP21: 148.5 | CR21: Guidance reconciliation $146–151m (before the Oct-26 notes).
B22: Q3/Q4-26E growth input (SK Environmental Services, ES & SKSS portions) | BY22: 0.1 | BZ22: 0.09 | CF22: Q2/26 +11.2% (ES) / +21.1% (SKSS) y/y on pricing, containerized waste and vacuum services (Noble Oil / Western Oil branches). | CN22: Tax rate (GAAP) | CP22: =180.5/(506+180.5) -> 0.2629279 | CR22: Implied by the mid-point reconciliation: tax $180.5m / pre-tax $686.5m.
B23: ES third-party revenues (Σ service lines from 2018; as reported 2017) | AD23: 395.907 | AE23: 449.631 | AF23: 440.163 | AG23: 442.999 | AH23: 1728.7 | AI23: 439.688 | AJ23: 519.916 | AK23: 508.813 | AL23: 535.426 | AM23: 2003.843 | AN23: 473.698 | AO23: 526.294 | AP23: 550.122 | AQ23: 542.249 | AR23: 2092.363 | AS23: 528.104 | AT23: 464.354 | AU23: 498.183 | AV23: 513.44 | AW23: 2004.081 | AX23: 652.878 | AY23: 723.147 | AZ23: 743.831 | BA23: 906.051 | BB23: 3025.907 | BC23: 940.798 | BD23: 1084.506 | BE23: 1080.032 | BF23: 1039.637 | BG23: 4144.973 | BH23: 1060.982 | BI23: 1161.482 | BJ23: 1135.279 | BK23: 1112.166 | BL23: 4469.909 | BM23: 1161.279 | BN23: 1297.298 | BO23: 1287.65 | BP23: 1214.098 | BQ23: 4960.325 | BR23: 1207.038 | BS23: 1330.059 | BT23: 1318.58 | BU23: 1290.677 | BV23: 5146.354 | BW23: 1242.448 | BX23: 1444.532 | BY23: =BY11+BY14+BY17+BY20 -> 1430.0384 | BZ23: =BZ11+BZ14+BZ17+BZ20 -> 1386.1746 | CA23: =SUM(BW23,BX23,BY23,BZ23) -> 5503.193 | CB23: =CB11+CB14+CB17+CB20 -> 5836.2461 | CC23: =CC11+CC14+CC17+CC20 -> 6181.3698 | CD23: =CD11+CD14+CD17+CD20 -> 6524.5604 | CE23: =CE11+CE14+CE17+CE20 -> 6875.1928 | CN23: Strategic growth investments excluded from adjusted FCF ($m) | CP23: 120 | CR23: Guidance reconciliation.
B24: Check: Σ service lines vs ES third-party revenues (should be 0) | AI24: =IF(ISNUMBER(AI11),ROUND(AI11+AI14+AI17+N(AI20)-AI23,1),"") -> 0 | AJ24: =IF(ISNUMBER(AJ11),ROUND(AJ11+AJ14+AJ17+N(AJ20)-AJ23,1),"") -> 0 | AK24: =IF(ISNUMBER(AK11),ROUND(AK11+AK14+AK17+N(AK20)-AK23,1),"") -> 0 | AL24: =IF(ISNUMBER(AL11),ROUND(AL11+AL14+AL17+N(AL20)-AL23,1),"") -> 0 | AM24: =IF(ISNUMBER(AM11),ROUND(AM11+AM14+AM17+N(AM20)-AM23,1),"") -> 0 | AN24: =IF(ISNUMBER(AN11),ROUND(AN11+AN14+AN17+N(AN20)-AN23,1),"") -> 0 | AO24: =IF(ISNUMBER(AO11),ROUND(AO11+AO14+AO17+N(AO20)-AO23,1),"") -> 0 | AP24: =IF(ISNUMBER(AP11),ROUND(AP11+AP14+AP17+N(AP20)-AP23,1),"") -> 0 | ... BX24: =IF(ISNUMBER(BX11),ROUND(BX11+BX14+BX17+N(BX20)-BX23,1),"") -> 0 | CN24: Proceeds from sale & disposal of fixed assets ($m) | CP24: 15 | CR24: Guidance reconciliation.
B25: Intersegment revenues (expenses), net | AD25: 32.989 | AE25: 31.959 | AF25: 32.518 | AG25: 31.308 | AH25: 128.774 | AI25: 32.759 | AJ25: 34.898 | AK25: 34.167 | AL25: 35.527 | AM25: 137.351 | AN25: 35.324 | AO25: 36.782 | AP25: 36.75 | AQ25: 35.849 | AR25: 144.705 | AS25: 38.258 | AT25: 32.56 | AU25: 29.787 | AV25: 32.62 | AW25: 133.225 | AX25: 1.724 | AY25: 0.95 | AZ25: 1.802 | BA25: 2.071 | BB25: 6.547 | BC25: 6.647 | BD25: 6.237 | BE25: 6.452 | BF25: 7.397 | BG25: 26.733 | BH25: 9.759 | BI25: 10.554 | BJ25: 11.084 | BK25: 10.136 | BL25: 41.533 | BM25: 11.231 | BN25: 12.085 | BO25: 9.537 | BP25: 11.569 | BQ25: 44.422 | BR25: 2.075 | BS25: 21.976 | BT25: 12.72 | BU25: 10.165 | BV25: 46.936 | BW25: 10.078 | BX25: 12.031 | BY25: =AVERAGE(BW25,BX25) -> 11.0545 | BZ25: =AVERAGE(BW25,BX25) -> 11.0545 | CA25: =SUM(BW25,BX25,BY25,BZ25) -> 44.218 | CB25: =CB23*CB26 -> 46.894073 | CC25: =CC23*CC26 -> 49.667132 | CD25: =CD23*CD26 -> 52.424659 | CE25: =CE23*CE26 -> 55.24198 | CF25: Net revenue for disposal/recycling of SKSS-collected waste. Q3/Q4-26E: 1H/26 quarterly average; 2027E+: 2026E % of ES third-party revenues. | CN25: 2H/26 share repurchases ($m) | CO25: 100 | CP25: 50 | CQ25: 0 | CR25: Q2/26 $25m; 1H/26 $52m. Base: Q2 pace maintained alongside ~$0.8bn of deal funding.
B26: Intersegment % of ES third-party revenues | AD26: =IF(AND(ISNUMBER(AD25),ISNUMBER(AD23)),IFERROR(AD25/AD23,""),"") -> 0.083325124 | AE26: =IF(AND(ISNUMBER(AE25),ISNUMBER(AE23)),IFERROR(AE25/AE23,""),"") -> 0.071078284 | AF26: =IF(AND(ISNUMBER(AF25),ISNUMBER(AF23)),IFERROR(AF25/AF23,""),"") -> 0.073877177 | AG26: =IF(AND(ISNUMBER(AG25),ISNUMBER(AG23)),IFERROR(AG25/AG23,""),"") -> 0.070672846 | AH26: =IF(AND(ISNUMBER(AH25),ISNUMBER(AH23)),IFERROR(AH25/AH23,""),"") -> 0.074491815 | AI26: =IF(AND(ISNUMBER(AI25),ISNUMBER(AI23)),IFERROR(AI25/AI23,""),"") -> 0.074505104 | AJ26: =IF(AND(ISNUMBER(AJ25),ISNUMBER(AJ23)),IFERROR(AJ25/AJ23,""),"") -> 0.067122381 | AK26: =IF(AND(ISNUMBER(AK25),ISNUMBER(AK23)),IFERROR(AK25/AK23,""),"") -> 0.067150407 | ... CA26: =IF(AND(ISNUMBER(CA25),ISNUMBER(CA23)),IFERROR(CA25/CA23,""),"") -> 0.0080349717 | CB26: =$CA$26 -> 0.0080349717 | CC26: =$CA$26 -> 0.0080349717 | CD26: =$CA$26 -> 0.0080349717 | CE26: =$CA$26 -> 0.0080349717 | CN26: Pending-deal run-rate cost synergies ($m) | CP26: 30 | CR26: EnviroServe ~$25m (within two years) + ES&H ~$5m (after first full year).
B27: ES direct revenues (segment revenues) | AD27: 428.896 | AE27: 481.59 | AF27: 472.681 | AG27: 474.307 | AH27: 1857.474 | AI27: 472.447 | AJ27: 554.814 | AK27: 542.98 | AL27: 570.953 | AM27: 2141.194 | AN27: 509.022 | AO27: 563.076 | AP27: 586.872 | AQ27: 578.098 | AR27: 2237.068 | AS27: 566.362 | AT27: 496.914 | AU27: 527.97 | AV27: 546.06 | AW27: 2137.306 | AX27: 654.602 | AY27: 724.097 | AZ27: 745.633 | BA27: 908.122 | BB27: 3032.454 | BC27: 947.445 | BD27: 1090.743 | BE27: 1086.484 | BF27: 1047.034 | BG27: 4171.706 | BH27: 1070.741 | BI27: 1172.036 | BJ27: 1146.363 | BK27: 1122.302 | BL27: 4511.442 | BM27: 1172.51 | BN27: 1309.383 | BO27: 1297.187 | BP27: 1225.667 | BQ27: 5004.747 | BR27: 1209.113 | BS27: 1352.035 | BT27: 1331.3 | BU27: 1300.842 | BV27: 5193.29 | BW27: 1252.526 | BX27: 1456.563 | BY27: =BY23+BY25 -> 1441.0929 | BZ27: =BZ23+BZ25 -> 1397.2291 | CA27: =SUM(BW27,BX27,BY27,BZ27) -> 5547.411 | CB27: =CB23+CB25 -> 5883.1402 | CC27: =CC23+CC25 -> 6231.037 | CD27: =CD23+CD25 -> 6576.9851 | CE27: =CE23+CE25 -> 6930.4348 | CH27: =IFERROR((CE27/BV27)^(1/5)-1,"n/m") -> 0.059408812 | CI27: =IFERROR((BV27/AW27)^(1/5)-1,"n/m") -> 0.19430479 | CJ27: =IFERROR((BV27/X27)^(1/10)-1,"n/m") -> n/m | CK27: =IFERROR((BV27/C27)^(1/19)-1,"n/m") -> n/m | CN27: Minimum annual buyback programme 2027E+ ($m) | CP27: 150 | CR27: CLH repurchased $50–200m p.a. 2022–25; $549m authorisation remaining.
B28: ES direct revenues y/y % | AI28: =IF(AND(ISNUMBER(AI27),ISNUMBER(AD27)),IFERROR(AI27/AD27-1,""),"") -> 0.1015421 | AJ28: =IF(AND(ISNUMBER(AJ27),ISNUMBER(AE27)),IFERROR(AJ27/AE27-1,""),"") -> 0.15204635 | AK28: =IF(AND(ISNUMBER(AK27),ISNUMBER(AF27)),IFERROR(AK27/AF27-1,""),"") -> 0.14872398 | AL28: =IF(AND(ISNUMBER(AL27),ISNUMBER(AG27)),IFERROR(AL27/AG27-1,""),"") -> 0.20376254 | AM28: =IF(AND(ISNUMBER(AM27),ISNUMBER(AH27)),IFERROR(AM27/AH27-1,""),"") -> 0.15274507 | AN28: =IF(AND(ISNUMBER(AN27),ISNUMBER(AI27)),IFERROR(AN27/AI27-1,""),"") -> 0.077416091 | AO28: =IF(AND(ISNUMBER(AO27),ISNUMBER(AJ27)),IFERROR(AO27/AJ27-1,""),"") -> 0.014891477 | AP28: =IF(AND(ISNUMBER(AP27),ISNUMBER(AK27)),IFERROR(AP27/AK27-1,""),"") -> 0.08083539 | ... BX28: =IF(AND(ISNUMBER(BX27),ISNUMBER(BS27)),IFERROR(BX27/BS27-1,""),"") -> 0.077311608 | BY28: =IFERROR(BY27/BT27-1,"") -> 0.082470412 | BZ28: =IFERROR(BZ27/BU27-1,"") -> 0.074095939 | CA28: =IFERROR(CA27/BV27-1,"") -> 0.068188176 | CB28: =IFERROR(CB27/CA27-1,"") -> 0.060519989 | CC28: =IFERROR(CC27/CB27-1,"") -> 0.059134535 | CD28: =IFERROR(CD27/CC27-1,"") -> 0.055520148 | CE28: =IFERROR(CE27/CD27-1,"") -> 0.05374038 | CN28: Minimum net debt / Adjusted EBITDA (x) — buyback floor 2027E+ | CO28: 2 | CP28: 1.75 | CQ28: 1.5 | CR28: Surplus cash above the floor returned via buybacks.
B29: ES Adjusted EBITDA (segment profit measure) | AD29: 60.19 | AE29: 94.832 | AF29: 86.505 | AG29: 79.783 | AH29: 321.31 | AI29: 61.417 | AJ29: 109.199 | AK29: 102.419 | AL29: 107.821 | AM29: 380.856 | AN29: 89.51 | AO29: 117.868 | AP29: 121.658 | AQ29: 117.248 | AR29: 446.284 | AS29: 108.914 | AT29: 138.083 | AU29: 140.854 | AV29: 132.109 | AW29: 519.96 | AX29: 140.254 | AY29: 176.041 | AZ29: 166.471 | BA29: 176.952 | BB29: 659.718 | BC29: 183.602 | BD29: 269.341 | BE29: 260.687 | BF29: 239.423 | BG29: 953.053 | BH29: 228.345 | BI29: 305.622 | BJ29: 288.982 | BK29: 278.659 | BL29: 1101.608 | BM29: 264.475 | BN29: 359.915 | BO29: 332.502 | BP29: 310.57 | BQ29: 1267.462 | BR29: 274.591 | BS29: 376.194 | BT29: 357.229 | BU29: 335.762 | BV29: 1343.776 | BW29: 290.401 | BX29: 406.104 | BY29: =BY27*BY31 -> 404.90967 | BZ29: =BZ27*BZ31 -> 378.30588 | CA29: =SUM(BW29,BX29,BY29,BZ29) -> 1479.7206 | CB29: =CB27*CB31 -> 1623.7467 | CC29: =CC27*CC31 -> 1744.6904 | CD29: =CD27*CD31 -> 1867.8638 | CE29: =CE27*CE31 -> 1989.0348 | CH29: =IFERROR((CE29/BV29)^(1/5)-1,"n/m") -> 0.081591085 | CI29: =IFERROR((BV29/AW29)^(1/5)-1,"n/m") -> 0.20912552 | CJ29: =IFERROR((BV29/X29)^(1/10)-1,"n/m") -> n/m | CK29: =IFERROR((BV29/C29)^(1/19)-1,"n/m") -> n/m
B30: Adj. EBITDA margin before outlook calibration % (Q3/Q4-26E helper) | BY30: =BT31+(BW29+BX29)/(BW27+BX27)-(BR29+BS29)/(BR27+BS27) -> 0.27133135 | BZ30: =BU31+(BW29+BX29)/(BW27+BX27)-(BR29+BS29)/(BR27+BS27) -> 0.26111168 | CF30: Prior-year quarter margin + 1H/26 y/y margin drift (1H/26 25.7% vs 1H/25 25.4%). | CN30: TS_growth (Technical Services revenues y/y) | CO30: 0.02 | CP30: Δ → | CQ30: -0.02 | CR30: Incineration / landfill pricing + volumes (reshoring, PFAS, Kimball ramp); FY23–25 +11% / +11% / +7%.
B31: ES Adjusted EBITDA margin % (on direct revenues) | AD31: =IF(AND(ISNUMBER(AD29),ISNUMBER(AD27)),IFERROR(AD29/AD27,""),"") -> 0.14033705 | AE31: =IF(AND(ISNUMBER(AE29),ISNUMBER(AE27)),IFERROR(AE29/AE27,""),"") -> 0.19691439 | AF31: =IF(AND(ISNUMBER(AF29),ISNUMBER(AF27)),IFERROR(AF29/AF27,""),"") -> 0.18300926 | AG31: =IF(AND(ISNUMBER(AG29),ISNUMBER(AG27)),IFERROR(AG29/AG27,""),"") -> 0.16820962 | AH31: =IF(AND(ISNUMBER(AH29),ISNUMBER(AH27)),IFERROR(AH29/AH27,""),"") -> 0.17298223 | AI31: =IF(AND(ISNUMBER(AI29),ISNUMBER(AI27)),IFERROR(AI29/AI27,""),"") -> 0.12999765 | AJ31: =IF(AND(ISNUMBER(AJ29),ISNUMBER(AJ27)),IFERROR(AJ29/AJ27,""),"") -> 0.19682092 | AK31: =IF(AND(ISNUMBER(AK29),ISNUMBER(AK27)),IFERROR(AK29/AK27,""),"") -> 0.18862389 | ... BX31: =IF(AND(ISNUMBER(BX29),ISNUMBER(BX27)),IFERROR(BX29/BX27,""),"") -> 0.27880977 | BY31: =BY30+BY101 -> 0.28097403 | BZ31: =BZ30+BZ101 -> 0.27075436 | CA31: =IF(AND(ISNUMBER(CA29),ISNUMBER(CA27)),IFERROR(CA29/CA27,""),"") -> 0.26674075 | CB31: =CHOOSE(MATCH($CF$2,{"Bull","Base","Bear"},0),$CO$56,$CP$56,$CQ$56) -> 0.276 | CC31: =CHOOSE(MATCH($CF$2,{"Bull","Base","Bear"},0),$CO$57,$CP$57,$CQ$57) -> 0.28 | CD31: =CHOOSE(MATCH($CF$2,{"Bull","Base","Bear"},0),$CO$58,$CP$58,$CQ$58) -> 0.284 | CE31: =CHOOSE(MATCH($CF$2,{"Bull","Base","Bear"},0),$CO$59,$CP$59,$CQ$59) -> 0.287 | CF31: Q3/Q4-26E: pre-calibration margin + outlook calibration Δ (solves FY26 Adjusted EBITDA = guidance end-point). 2027E+: scenario lever ES_margin (17 consecutive quarters of y/y margin expansion to Q2/26). | CH31: =IFERROR(AVERAGE(CA31,CB31,CC31,CD31,CE31),"n/m") -> 0.27874815 | CI31: =IFERROR(AVERAGE(BB31,BG31,BL31,BQ31,BV31),"n/m") -> 0.24043883 | CJ31: =IFERROR(AVERAGE(AC31,AH31,AM31,AR31,AW31,BB31,BG31,BL31,BQ31,BV31),"n/m") -> 0.22175783 | CK31: =IFERROR(AVERAGE(C31,D31,E31,F31,G31,H31,I31,N31,S31,X31,AC31,AH31,AM31,AR31,AW31,BB31,BG31,BL31,BQ31,BV31),"n/m") -> 0.22175783 | CN31: 2027E | CO31: =CP31+$CO$30 -> 0.1 | CP31: 0.08 | CQ31: =CP31+$CQ$30 -> 0.06
B32: ES incremental margin (Δ Adj. EBITDA / Δ direct revenues, y/y) | AI32: =IFERROR((AI29-AD29)/(AI27-AD27),"") -> 0.028173865 | AJ32: =IFERROR((AJ29-AE29)/(AJ27-AE27),"") -> 0.19620616 | AK32: =IFERROR((AK29-AF29)/(AK27-AF27),"") -> 0.22637591 | AL32: =IFERROR((AL29-AG29)/(AL27-AG27),"") -> 0.2901103 | AM32: =IFERROR((AM29-AH29)/(AM27-AH27),"") -> 0.20987593 | AN32: =IFERROR((AN29-AI29)/(AN27-AI27),"") -> 0.76809296 | AO32: =IFERROR((AO29-AJ29)/(AO27-AJ27),"") -> 1.0492617 | AP32: =IFERROR((AP29-AK29)/(AP27-AK27),"") -> 0.43832589 | ... CA32: =IFERROR((CA29-BV29)/(CA27-BV27),"") -> 0.38389297 | CB32: =IFERROR((CB29-CA29)/(CB27-CA27),"") -> 0.42899494 | CC32: =IFERROR((CC29-CB29)/(CC27-CB27),"") -> 0.34764237 | CD32: =IFERROR((CD29-CC29)/(CD27-CC27),"") -> 0.35604592 | CE32: =IFERROR((CE29-CD29)/(CE27-CD27),"") -> 0.34282394 | CN32: 2028E | CO32: =CP32+$CO$30 -> 0.095 | CP32: 0.075 | CQ32: =CP32+$CQ$30 -> 0.055
B33: Memo: incineration utilization % (company; ex-Kimball Q1–Q4/25, incl. Kimball from Q1/26) | J33: 0.88 | K33: 0.923 | L33: 0.93 | M33: 0.91 | O33: 0.91 | P33: 0.95 | Q33: 0.9 | R33: 0.96 | T33: 0.91 | U33: 0.91 | V33: 0.92 | W33: 0.89 | Y33: 0.88 | Z33: 0.88 | AA33: 0.9 | AB33: 0.9 | AD33: 0.79 | AE33: 0.87 | AF33: 0.92 | AG33: 0.92 | AI33: 0.87 | AJ33: 0.9 | AK33: 0.84 | AL33: 0.86 | AN33: 0.77 | AO33: 0.82 | AP33: 0.92 | AQ33: 0.89 | AS33: 0.86 | AT33: 0.87 | AU33: 0.8 | AV33: 0.84 | AX33: 0.8 | AY33: 0.87 | AZ33: 0.82 | BA33: 0.92 | BC33: 0.85 | BF33: 0.84 | BH33: 0.8 | BI33: 0.84 | BJ33: 0.86 | BK33: 0.85 | BM33: 0.79 | BN33: 0.88 | BO33: 0.89 | BP33: 0.94 | BR33: 0.88 | BS33: 0.89 | BT33: 0.92 | BU33: 0.87 | BW33: 0.8 | BX33: 0.91 | CF33: Quoted in each earnings release (CEO commentary); quarterly only. | CN33: 2029E | CO33: =CP33+$CO$30 -> 0.09 | CP33: 0.07 | CQ33: =CP33+$CQ$30 -> 0.05
B34: Memo: landfill volumes y/y % (company, where disclosed) | K34: 0.17 | O34: 0.25 | R34: 0.37 | T34: 0.21 | U34: -0.29 | V34: -0.28 | W34: -0.5 | Y34: -0.33 | Z34: -0.21 | AA34: -0.49 | AB34: -0.28 | AD34: -0.25 | AE34: 0.23 | AF34: 0.4 | AG34: 0.18 | AI34: 0.58 | AP34: 0.06 | AQ34: 0.4 | AT34: -0.24 | AV34: -0.37 | AZ34: -0.05 | BA34: 0.15 | BC34: 0.14 | BD34: 0.36 | BE34: 0.38 | BF34: 0.28 | BH34: -0.08 | BN34: 0.04 | BT34: 0.4 | BU34: 0.56 | BW34: 0.34 | BX34: 0.07 | CN34: 2030E | CO34: =CP34+$CO$30 -> 0.085 | CP34: 0.065 | CQ34: =CP34+$CQ$30 -> 0.045
CN35: FER_growth (Field & Emergency Response y/y) | CO35: 0.03 | CP35: Δ → | CQ35: -0.03 | CR35: ER is event-driven (lumpy); base business + branch growth.
B36: Safety-Kleen Sustainability Solutions (SKSS; "Safety-Kleen" segment Q1/18–Q4/20) — Safety-Kleen Oil (re-refined base oil, blended lubricants, used-oil collection) · SK Environmental Services (SKSS portion) | CF36: SKSS — modelling logic: re-refining spread business (base-oil price vs. charge-for-oil on collection); Q2/26 margin spike on global refined-product supply disruption. | CN36: 2027E | CO36: =CP36+$CO$35 -> 0.08 | CP36: 0.05 | CQ36: =CP36+$CQ$35 -> 0.02
B37: Safety-Kleen Environmental Services — SKSS portion (all SK Environmental Services 2018–20) | AI37: 194.161 | AJ37: 200.034 | AK37: 200.681 | AL37: 200.201 | AM37: 795.077 | AN37: 207.083 | AO37: 216.434 | AP37: 217.439 | AQ37: 210.564 | AR37: 851.52 | AS37: 214.481 | AT37: 194.872 | AU37: 203.455 | AV37: 196.428 | AW37: 809.236 | AX37: 38.978 | AY37: 40.453 | AZ37: 39.551 | BA37: 42.605 | BB37: 161.587 | BC37: 44.388 | BD37: 49.381 | BE37: 52.072 | BF37: 53.519 | BG37: 199.36 | BH37: 49.559 | BI37: 62.452 | BJ37: 59.458 | BK37: 53.361 | BL37: 224.83 | BM37: 53.021 | BN37: 58.421 | BO37: 59.675 | BP37: 58.613 | BQ37: 229.73 | BR37: 64.901 | BS37: 72.463 | BT37: 76.601 | BU37: 76.458 | BV37: 290.423 | BW37: 77.973 | BX37: 87.738 | BY37: =BT37*(1+BY38) -> 84.2611 | BZ37: =BU37*(1+BZ38) -> 83.33922 | CA37: =SUM(BW37,BX37,BY37,BZ37) -> 333.31132 | CB37: =CA37*(1+CB38) -> 356.64311 | CC37: =CB37*(1+CC38) -> 379.82491 | CD37: =CC37*(1+CD38) -> 402.61441 | CE37: =CD37*(1+CE38) -> 426.77127 | CH37: =IFERROR((CE37/BV37)^(1/5)-1,"n/m") -> 0.080022578 | CI37: =IFERROR((BV37/AW37)^(1/5)-1,"n/m") -> -0.18531229 | CJ37: =IFERROR((BV37/X37)^(1/10)-1,"n/m") -> n/m | CK37: =IFERROR((BV37/C37)^(1/19)-1,"n/m") -> n/m | CN37: 2028E | CO37: =CP37+$CO$35 -> 0.08 | CP37: 0.05 | CQ37: =CP37+$CQ$35 -> 0.02
B38: SK Environmental Services (SKSS) y/y % | D38: =IF(AND(ISNUMBER(D37),ISNUMBER(C37)),IFERROR(D37/C37-1,""),"") | E38: =IF(AND(ISNUMBER(E37),ISNUMBER(D37)),IFERROR(E37/D37-1,""),"") | F38: =IF(AND(ISNUMBER(F37),ISNUMBER(E37)),IFERROR(F37/E37-1,""),"") | G38: =IF(AND(ISNUMBER(G37),ISNUMBER(F37)),IFERROR(G37/F37-1,""),"") | H38: =IF(AND(ISNUMBER(H37),ISNUMBER(G37)),IFERROR(H37/G37-1,""),"") | I38: =IF(AND(ISNUMBER(I37),ISNUMBER(H37)),IFERROR(I37/H37-1,""),"") | N38: =IF(AND(ISNUMBER(N37),ISNUMBER(I37)),IFERROR(N37/I37-1,""),"") | O38: =IF(AND(ISNUMBER(O37),ISNUMBER(J37)),IFERROR(O37/J37-1,""),"") | P38: =IF(AND(ISNUMBER(P37),ISNUMBER(K37)),IFERROR(P37/K37-1,""),"") | Q38: =IF(AND(ISNUMBER(Q37),ISNUMBER(L37)),IFERROR(Q37/L37-1,""),"") | R38: =IF(AND(ISNUMBER(R37),ISNUMBER(M37)),IFERROR(R37/M37-1,""),"") | S38: =IF(AND(ISNUMBER(S37),ISNUMBER(N37)),IFERROR(S37/N37-1,""),"") | T38: =IF(AND(ISNUMBER(T37),ISNUMBER(O37)),IFERROR(T37/O37-1,""),"") | U38: =IF(AND(ISNUMBER(U37),ISNUMBER(P37)),IFERROR(U37/P37-1,""),"") | ... BX38: =IF(AND(ISNUMBER(BX37),ISNUMBER(BS37)),IFERROR(BX37/BS37-1,""),"") -> 0.21079723 | BY38: =BY22 -> 0.1 | BZ38: =BZ22 -> 0.09 | CA38: =IFERROR(CA37/BV37-1,"") -> 0.14767536 | CB38: =CHOOSE(MATCH($CF$2,{"Bull","Base","Bear"},0),$CO$46,$CP$46,$CQ$46) -> 0.07 | CC38: =CHOOSE(MATCH($CF$2,{"Bull","Base","Bear"},0),$CO$47,$CP$47,$CQ$47) -> 0.065 | CD38: =CHOOSE(MATCH($CF$2,{"Bull","Base","Bear"},0),$CO$48,$CP$48,$CQ$48) -> 0.06 | CE38: =CHOOSE(MATCH($CF$2,{"Bull","Base","Bear"},0),$CO$49,$CP$49,$CQ$49) -> 0.06 | CN38: 2029E | CO38: =CP38+$CO$35 -> 0.075 | CP38: 0.045 | CQ38: =CP38+$CQ$35 -> 0.015
B39: Safety-Kleen Oil — base oil, blended lubricants & collection services (Kleen Performance Products 2018) | AI39: 115.757 | AJ39: 128.681 | AK39: 133.22 | AL39: 122.62 | AM39: 500.278 | AN39: 99.464 | AO39: 125.748 | AP39: 123.978 | AQ39: 117.981 | AR39: 467.171 | AS39: 115.888 | AT39: 50.718 | AU39: 77.634 | AV39: 86.25 | AW39: 330.49 | AX39: 116.213 | AY39: 162.779 | AZ39: 168.038 | BA39: 170.743 | BB39: 617.773 | BC39: 183.851 | BD39: 222.346 | BE39: 230.699 | BF39: 184.869 | BG39: 821.765 | BH39: 196.739 | BI39: 173.85 | BJ39: 170.847 | BK39: 172.53 | BL39: 713.966 | BM39: 162.293 | BN39: 196.901 | BO39: 182.001 | BP39: 158.295 | BQ39: 699.49 | BR39: 159.914 | BS39: 147.243 | BT39: 154.156 | BU39: 132.561 | BV39: 593.874 | BW39: 139.116 | BX39: 202.735 | BY39: =BT39*(1+BY40) -> 197.31968 | BZ39: =BU39*(1+BZ40) -> 145.8171 | CA39: =SUM(BW39,BX39,BY39,BZ39) -> 684.98778 | CB39: =CA39*(1+CB40) -> 630.18876 | CC39: =CB39*(1+CC40) -> 642.79253 | CD39: =CC39*(1+CD40) -> 655.64838 | CE39: =CD39*(1+CE40) -> 668.76135 | CH39: =IFERROR((CE39/BV39)^(1/5)-1,"n/m") -> 0.024036345 | CI39: =IFERROR((BV39/AW39)^(1/5)-1,"n/m") -> 0.12436469 | CJ39: =IFERROR((BV39/X39)^(1/10)-1,"n/m") -> n/m | CK39: =IFERROR((BV39/C39)^(1/19)-1,"n/m") -> n/m | CN39: 2030E | CO39: =CP39+$CO$35 -> 0.075 | CP39: 0.045 | CQ39: =CP39+$CQ$35 -> 0.015
B40: Safety-Kleen Oil y/y % | D40: =IF(AND(ISNUMBER(D39),ISNUMBER(C39)),IFERROR(D39/C39-1,""),"") | E40: =IF(AND(ISNUMBER(E39),ISNUMBER(D39)),IFERROR(E39/D39-1,""),"") | F40: =IF(AND(ISNUMBER(F39),ISNUMBER(E39)),IFERROR(F39/E39-1,""),"") | G40: =IF(AND(ISNUMBER(G39),ISNUMBER(F39)),IFERROR(G39/F39-1,""),"") | H40: =IF(AND(ISNUMBER(H39),ISNUMBER(G39)),IFERROR(H39/G39-1,""),"") | I40: =IF(AND(ISNUMBER(I39),ISNUMBER(H39)),IFERROR(I39/H39-1,""),"") | N40: =IF(AND(ISNUMBER(N39),ISNUMBER(I39)),IFERROR(N39/I39-1,""),"") | O40: =IF(AND(ISNUMBER(O39),ISNUMBER(J39)),IFERROR(O39/J39-1,""),"") | P40: =IF(AND(ISNUMBER(P39),ISNUMBER(K39)),IFERROR(P39/K39-1,""),"") | Q40: =IF(AND(ISNUMBER(Q39),ISNUMBER(L39)),IFERROR(Q39/L39-1,""),"") | R40: =IF(AND(ISNUMBER(R39),ISNUMBER(M39)),IFERROR(R39/M39-1,""),"") | S40: =IF(AND(ISNUMBER(S39),ISNUMBER(N39)),IFERROR(S39/N39-1,""),"") | T40: =IF(AND(ISNUMBER(T39),ISNUMBER(O39)),IFERROR(T39/O39-1,""),"") | U40: =IF(AND(ISNUMBER(U39),ISNUMBER(P39)),IFERROR(U39/P39-1,""),"") | ... BX40: =IF(AND(ISNUMBER(BX39),ISNUMBER(BS39)),IFERROR(BX39/BS39-1,""),"") -> 0.3768736 | BY40: =BY41 -> 0.28 | BZ40: =BZ41 -> 0.1 | CA40: =IFERROR(CA39/BV39-1,"") -> 0.15342275 | CB40: =CHOOSE(MATCH($CF$2,{"Bull","Base","Bear"},0),$CO$51,$CP$51,$CQ$51) -> -0.08 | CC40: =CHOOSE(MATCH($CF$2,{"Bull","Base","Bear"},0),$CO$52,$CP$52,$CQ$52) -> 0.02 | CD40: =CHOOSE(MATCH($CF$2,{"Bull","Base","Bear"},0),$CO$53,$CP$53,$CQ$53) -> 0.02 | CE40: =CHOOSE(MATCH($CF$2,{"Bull","Base","Bear"},0),$CO$54,$CP$54,$CQ$54) -> 0.02 | CF40: 2027E+: scenario lever SKOIL_growth (base-oil pricing normalisation after the 2026 supply-disruption spike, then volume/blended mix growth). | CN40: IS_growth (Industrial Services & Other y/y) | CO40: 0.02 | CP40: Δ → | CQ40: -0.02 | CR40: Refinery / chemical turnarounds; data-center offering; FY24–25 −3% / −4%.
B41: Q3/Q4-26E growth input (base-oil pricing) | BY41: 0.28 | BZ41: 0.1 | CF41: Q2/26 +37.7% y/y on refined-product supply disruption; company expects conditions to extend into Q3. Q4 input assumes partial normalisation. | CN41: 2027E | CO41: =CP41+$CO$40 -> 0.05 | CP41: 0.03 | CQ41: =CP41+$CQ$40 -> 0.01
B42: SKSS third-party revenues | AD42: 292.901 | AE42: 302.956 | AF42: 315.028 | AG42: 302.818 | AH42: 1213.703 | AI42: 309.918 | AJ42: 328.715 | AK42: 333.901 | AL42: 322.821 | AM42: 1295.355 | AN42: 306.547 | AO42: 342.182 | AP42: 341.417 | AQ42: 328.545 | AR42: 1318.691 | AS42: 330.369 | AT42: 245.59 | AU42: 281.089 | AV42: 282.678 | AW42: 1139.726 | AX42: 155.191 | AY42: 203.232 | AZ42: 207.589 | BA42: 213.348 | BB42: 779.36 | BC42: 228.239 | BD42: 271.727 | BE42: 282.771 | BF42: 238.388 | BG42: 1021.125 | BH42: 246.298 | BI42: 236.302 | BJ42: 230.305 | BK42: 225.891 | BL42: 938.796 | BM42: 215.314 | BN42: 255.322 | BO42: 241.676 | BP42: 216.908 | BQ42: 929.22 | BR42: 224.815 | BS42: 219.706 | BT42: 230.757 | BU42: 209.019 | BV42: 884.297 | BW42: 217.089 | BX42: 290.473 | BY42: =BY37+BY39 -> 281.58078 | BZ42: =BZ37+BZ39 -> 229.15632 | CA42: =SUM(BW42,BX42,BY42,BZ42) -> 1018.2991 | CB42: =CB37+CB39 -> 986.83187 | CC42: =CC37+CC39 -> 1022.6174 | CD42: =CD37+CD39 -> 1058.2628 | CE42: =CE37+CE39 -> 1095.5326 | CN42: 2028E | CO42: =CP42+$CO$40 -> 0.055 | CP42: 0.035 | CQ42: =CP42+$CQ$40 -> 0.015
B43: Intersegment revenues (expenses), net | AD43: -32.066 | AE43: -31.641 | AF43: -31.754 | AG43: -30.356 | AH43: -125.817 | AI43: -31.954 | AJ43: -34.28 | AK43: -33.016 | AL43: -34.823 | AM43: -134.073 | AN43: -34.07 | AO43: -36.198 | AP43: -35.272 | AQ43: -35.022 | AR43: -140.562 | AS43: -37.157 | AT43: -31.034 | AU43: -29.449 | AV43: -31.884 | AW43: -129.524 | AX43: -1.724 | AY43: -0.95 | AZ43: -1.802 | BA43: -2.071 | BB43: -6.547 | BC43: -6.647 | BD43: -6.237 | BE43: -6.452 | BF43: -7.397 | BG43: -26.733 | BH43: -9.759 | BI43: -10.554 | BJ43: -11.084 | BK43: -10.136 | BL43: -41.533 | BM43: -11.231 | BN43: -12.085 | BO43: -9.537 | BP43: -11.569 | BQ43: -44.422 | BR43: -2.075 | BS43: -21.976 | BT43: -12.72 | BU43: -10.165 | BV43: -46.936 | BW43: -10.078 | BX43: -12.031 | BY43: =-BY25 -> -11.0545 | BZ43: =-BZ25 -> -11.0545 | CA43: =SUM(BW43,BX43,BY43,BZ43) -> -44.218 | CB43: =-CB25 -> -46.894073 | CC43: =-CC25 -> -49.667132 | CD43: =-CD25 -> -52.424659 | CE43: =-CE25 -> -55.24198 | CN43: 2029E | CO43: =CP43+$CO$40 -> 0.055 | CP43: 0.035 | CQ43: =CP43+$CQ$40 -> 0.015
B44: SKSS direct revenues (segment revenues) | AD44: 260.835 | AE44: 271.315 | AF44: 283.274 | AG44: 272.462 | AH44: 1087.886 | AI44: 277.964 | AJ44: 294.435 | AK44: 300.885 | AL44: 287.998 | AM44: 1161.282 | AN44: 272.477 | AO44: 305.984 | AP44: 306.145 | AQ44: 293.523 | AR44: 1178.129 | AS44: 293.212 | AT44: 214.556 | AU44: 251.64 | AV44: 250.794 | AW44: 1010.202 | AX44: 153.467 | AY44: 202.282 | AZ44: 205.787 | BA44: 211.277 | BB44: 772.813 | BC44: 221.592 | BD44: 265.49 | BE44: 276.319 | BF44: 230.991 | BG44: 994.392 | BH44: 236.539 | BI44: 225.748 | BJ44: 219.221 | BK44: 215.755 | BL44: 897.263 | BM44: 204.083 | BN44: 243.237 | BO44: 232.139 | BP44: 205.339 | BQ44: 884.798 | BR44: 222.74 | BS44: 197.73 | BT44: 218.037 | BU44: 198.854 | BV44: 837.361 | BW44: 207.011 | BX44: 278.442 | BY44: =BY42+BY43 -> 270.52628 | BZ44: =BZ42+BZ43 -> 218.10182 | CA44: =SUM(BW44,BX44,BY44,BZ44) -> 974.0811 | CB44: =CB42+CB43 -> 939.9378 | CC44: =CC42+CC43 -> 972.95032 | CD44: =CD42+CD43 -> 1005.8381 | CE44: =CE42+CE43 -> 1040.2906 | CH44: =IFERROR((CE44/BV44)^(1/5)-1,"n/m") -> 0.044355583 | CI44: =IFERROR((BV44/AW44)^(1/5)-1,"n/m") -> -0.036834537 | CJ44: =IFERROR((BV44/X44)^(1/10)-1,"n/m") -> n/m | CK44: =IFERROR((BV44/C44)^(1/19)-1,"n/m") -> n/m | CN44: 2030E | CO44: =CP44+$CO$40 -> 0.055 | CP44: 0.035 | CQ44: =CP44+$CQ$40 -> 0.015
B45: SKSS direct revenues y/y % | AI45: =IF(AND(ISNUMBER(AI44),ISNUMBER(AD44)),IFERROR(AI44/AD44-1,""),"") -> 0.065669868 | AJ45: =IF(AND(ISNUMBER(AJ44),ISNUMBER(AE44)),IFERROR(AJ44/AE44-1,""),"") -> 0.085214603 | AK45: =IF(AND(ISNUMBER(AK44),ISNUMBER(AF44)),IFERROR(AK44/AF44-1,""),"") -> 0.06216949 | AL45: =IF(AND(ISNUMBER(AL44),ISNUMBER(AG44)),IFERROR(AL44/AG44-1,""),"") -> 0.057020796 | AM45: =IF(AND(ISNUMBER(AM44),ISNUMBER(AH44)),IFERROR(AM44/AH44-1,""),"") -> 0.067466628 | AN45: =IF(AND(ISNUMBER(AN44),ISNUMBER(AI44)),IFERROR(AN44/AI44-1,""),"") -> -0.019739966 | AO45: =IF(AND(ISNUMBER(AO44),ISNUMBER(AJ44)),IFERROR(AO44/AJ44-1,""),"") -> 0.039224277 | AP45: =IF(AND(ISNUMBER(AP44),ISNUMBER(AK44)),IFERROR(AP44/AK44-1,""),"") -> 0.017481762 | ... BX45: =IF(AND(ISNUMBER(BX44),ISNUMBER(BS44)),IFERROR(BX44/BS44-1,""),"") -> 0.40819299 | BY45: =IFERROR(BY44/BT44-1,"") -> 0.24073565 | BZ45: =IFERROR(BZ44/BU44-1,"") -> 0.096793728 | CA45: =IFERROR(CA44/BV44-1,"") -> 0.16327498 | CB45: =IFERROR(CB44/CA44-1,"") -> -0.035051807 | CC45: =IFERROR(CC44/CB44-1,"") -> 0.035122024 | CD45: =IFERROR(CD44/CC44-1,"") -> 0.033802157 | CE45: =IFERROR(CE44/CD44-1,"") -> 0.03425254 | CN45: SKES_growth (Safety-Kleen Environmental Services y/y) | CO45: 0.02 | CP45: Δ → | CQ45: -0.02 | CR45: Containerized waste, vacuum, parts washers; FY24–25 +8% / +9%.
B46: SKSS Adjusted EBITDA (segment profit measure) | AD46: 52.368 | AE46: 60.281 | AF46: 70.305 | AG46: 66.857 | AH46: 249.811 | AI46: 61.884 | AJ46: 73.069 | AK46: 79.502 | AL46: 67.574 | AM46: 282.029 | AN46: 54.793 | AO46: 79.459 | AP46: 81.326 | AQ46: 66.8 | AR46: 282.378 | AS46: 61.148 | AT46: 46.589 | AU46: 68.761 | AV46: 52.674 | AW46: 229.172 | AX46: 31.632 | AY46: 63.314 | AZ46: 70.81 | BA46: 61.598 | BB46: 227.354 | BC46: 51.877 | BD46: 97.01 | BE46: 103.156 | BF46: 54.284 | BG46: 306.327 | BH46: 41.463 | BI46: 53.415 | BJ46: 31.146 | BK46: 46.849 | BL46: 172.873 | BM46: 29.7 | BN46: 51.476 | BO46: 41.226 | BP46: 24.604 | BQ46: 147.006 | BR46: 28.252 | BS46: 38.313 | BT46: 40.937 | BU46: 29.952 | BV46: 137.454 | BW46: 32.981 | BX46: 92.993 | BY46: =BY44*BY48 -> 80.774307 | BZ46: =BZ44*BZ48 -> 45.988774 | CA46: =SUM(BW46,BX46,BY46,BZ46) -> 252.73708 | CB46: =CB44*CB48 -> 187.98756 | CC46: =CC44*CC48 -> 199.45481 | CD46: =CD44*CD48 -> 211.22601 | CE46: =CE44*CE48 -> 218.46104 | CH46: =IFERROR((CE46/BV46)^(1/5)-1,"n/m") -> 0.097092689 | CI46: =IFERROR((BV46/AW46)^(1/5)-1,"n/m") -> -0.09718417 | CJ46: =IFERROR((BV46/X46)^(1/10)-1,"n/m") -> n/m | CK46: =IFERROR((BV46/C46)^(1/19)-1,"n/m") -> n/m | CN46: 2027E | CO46: =CP46+$CO$45 -> 0.09 | CP46: 0.07 | CQ46: =CP46+$CQ$45 -> 0.05
B47: Adj. EBITDA margin before outlook calibration % (Q3/Q4-26E helper) | BY47: =BT48+((BW46+BX46)/(BW44+BX44)-(BR46+BS46)/(BR44+BS44)) -> 0.28893943 | BZ47: =BU48+0.5*((BW46+BX46)/(BW44+BX44)-(BR46+BS46)/(BR44+BS44)) -> 0.20121652 | CF47: Prior-year quarter + 1H/26 y/y margin drift (+10pt: 1H/26 26.0% vs 1H/25 15.8%); half the drift in Q4 (spread normalising). | CN47: 2028E | CO47: =CP47+$CO$45 -> 0.085 | CP47: 0.065 | CQ47: =CP47+$CQ$45 -> 0.045
B48: SKSS Adjusted EBITDA margin % (on direct revenues) | AD48: =IF(AND(ISNUMBER(AD46),ISNUMBER(AD44)),IFERROR(AD46/AD44,""),"") -> 0.2007706 | AE48: =IF(AND(ISNUMBER(AE46),ISNUMBER(AE44)),IFERROR(AE46/AE44,""),"") -> 0.22218086 | AF48: =IF(AND(ISNUMBER(AF46),ISNUMBER(AF44)),IFERROR(AF46/AF44,""),"") -> 0.24818727 | AG48: =IF(AND(ISNUMBER(AG46),ISNUMBER(AG44)),IFERROR(AG46/AG44,""),"") -> 0.24538101 | AH48: =IF(AND(ISNUMBER(AH46),ISNUMBER(AH44)),IFERROR(AH46/AH44,""),"") -> 0.22962976 | AI48: =IF(AND(ISNUMBER(AI46),ISNUMBER(AI44)),IFERROR(AI46/AI44,""),"") -> 0.22263315 | AJ48: =IF(AND(ISNUMBER(AJ46),ISNUMBER(AJ44)),IFERROR(AJ46/AJ44,""),"") -> 0.24816683 | AK48: =IF(AND(ISNUMBER(AK46),ISNUMBER(AK44)),IFERROR(AK46/AK44,""),"") -> 0.2642272 | ... BX48: =IF(AND(ISNUMBER(BX46),ISNUMBER(BX44)),IFERROR(BX46/BX44,""),"") -> 0.3339762 | BY48: =BY47+BY101 -> 0.29858211 | BZ48: =BZ47+BZ101 -> 0.2108592 | CA48: =IF(AND(ISNUMBER(CA46),ISNUMBER(CA44)),IFERROR(CA46/CA44,""),"") -> 0.25946205 | CB48: =CHOOSE(MATCH($CF$2,{"Bull","Base","Bear"},0),$CO$61,$CP$61,$CQ$61) -> 0.2 | CC48: =CHOOSE(MATCH($CF$2,{"Bull","Base","Bear"},0),$CO$62,$CP$62,$CQ$62) -> 0.205 | CD48: =CHOOSE(MATCH($CF$2,{"Bull","Base","Bear"},0),$CO$63,$CP$63,$CQ$63) -> 0.21 | CE48: =CHOOSE(MATCH($CF$2,{"Bull","Base","Bear"},0),$CO$64,$CP$64,$CQ$64) -> 0.21 | CF48: 2027E+: scenario lever SKSS_margin (FY24–25 16–17%; 2026 elevated by the base-oil spread). | CH48: =IFERROR(AVERAGE(CA48,CB48,CC48,CD48,CE48),"n/m") -> 0.21689241 | CI48: =IFERROR(AVERAGE(BB48,BG48,BL48,BQ48,BV48),"n/m") -> 0.22504192 | CJ48: =IFERROR(AVERAGE(AC48,AH48,AM48,AR48,AW48,BB48,BG48,BL48,BQ48,BV48),"n/m") -> 0.22936005 | CK48: =IFERROR(AVERAGE(C48,D48,E48,F48,G48,H48,I48,N48,S48,X48,AC48,AH48,AM48,AR48,AW48,BB48,BG48,BL48,BQ48,BV48),"n/m") -> 0.22936005 | CN48: 2029E | CO48: =CP48+$CO$45 -> 0.08 | CP48: 0.06 | CQ48: =CP48+$CQ$45 -> 0.04
B49: SKSS incremental margin (Δ Adj. EBITDA / Δ direct revenues, y/y) | AI49: =IFERROR((AI46-AD46)/(AI44-AD44),"") -> 0.55554907 | AJ49: =IFERROR((AJ46-AE46)/(AJ44-AE44),"") -> 0.55311419 | AK49: =IFERROR((AK46-AF46)/(AK44-AF44),"") -> 0.52223042 | AL49: =IFERROR((AL46-AG46)/(AL44-AG44),"") -> 0.046150875 | AM49: =IFERROR((AM46-AH46)/(AM44-AH44),"") -> 0.43896125 | AN49: =IFERROR((AN46-AI46)/(AN44-AI44),"") -> 1.2923273 | AO49: =IFERROR((AO46-AJ46)/(AO44-AJ44),"") -> 0.55329466 | AP49: =IFERROR((AP46-AK46)/(AP44-AK44),"") -> 0.34676806 | ... CA49: =IFERROR((CA46-BV46)/(CA44-BV44),"") -> 0.84320507 | CB49: =IFERROR((CB46-CA46)/(CB44-CA44),"") -> 1.8964048 | CC49: =IFERROR((CC46-CB46)/(CC44-CB44),"") -> 0.34736081 | CD49: =IFERROR((CD46-CC46)/(CD44-CC44),"") -> 0.35791956 | CE49: =IFERROR((CE46-CD46)/(CE44-CD44),"") -> 0.21 | CN49: 2030E | CO49: =CP49+$CO$45 -> 0.08 | CP49: 0.06 | CQ49: =CP49+$CQ$45 -> 0.04
B50: Memo: waste oil collected (million gallons; company, where disclosed) | AK50: 60 | AO50: 63 | AP50: 63 | AQ50: 55 | AS50: 55 | AU50: 50 | AV50: 49 | AX50: 47 | AY50: 57 | AZ50: 60 | BA50: 56 | BC50: 53 | BE50: 62 | BF50: 57 | BH50: 59 | BI50: 64 | BJ50: 59 | BK50: 53 | BM50: 55 | BN50: 67 | BS50: 64 | BT50: 64 | BU50: 56 | BW50: 53 | BX50: 61 | CN50: SKOIL_growth (Safety-Kleen Oil revenues y/y) | CO50: 0.05 | CP50: Δ → | CQ50: -0.05 | CR50: Base-oil price normalisation in 2027 after the 2026 supply-disruption spike; FY24–25 −2% / −15%.
CN51: 2027E | CO51: =CP51+$CO$50 -> -0.03 | CP51: -0.08 | CQ51: =CP51+$CQ$50 -> -0.13
B52: Corporate (unallocated corporate costs; "Corporate Items") | CF52: CORPORATE — modelling logic | CN52: 2028E | CO52: =CP52+$CO$50 -> 0.07 | CP52: 0.02 | CQ52: =CP52+$CQ$50 -> -0.03
B53: Corporate revenues (direct) | AD53: -0.79 | AE53: -0.117 | AF53: -0.109 | AG53: 0.634 | AH53: -0.382 | AI53: -0.633 | AJ53: -0.109 | AK53: -0.684 | AL53: -0.747 | AM53: -2.173 | AN53: -0.66 | AO53: -0.382 | AP53: -1.349 | AQ53: -0.616 | AR53: -3.007 | AS53: -1.011 | AT53: -1.47 | AU53: -0.266 | AV53: -0.664 | AW53: -3.411 | AX53: 0.079 | AY53: 0.079 | AZ53: 0.059 | BA53: 0.082 | BB53: 0.299 | BC53: 0.072 | BD53: 0.079 | BE53: 0.283 | BF53: 0.073 | BG53: 0.507 | BH53: 0.107 | BI53: 0.116 | BJ53: 0.112 | BK53: 0.112 | BL53: 0.447 | BM53: 0.102 | BN53: 0.099 | BO53: 0.096 | BP53: 0.11 | BQ53: 0.407 | BR53: 0.097 | BS53: 0.089 | BT53: 0 | BU53: 0 | BV53: 0.186 | BW53: 0 | BX53: 0 | BY53: 0 | BZ53: 0 | CA53: =SUM(BW53,BX53,BY53,BZ53) -> 0 | CB53: =0 -> 0 | CC53: =0 -> 0 | CD53: =0 -> 0 | CE53: =0 -> 0 | CN53: 2029E | CO53: =CP53+$CO$50 -> 0.07 | CP53: 0.02 | CQ53: =CP53+$CQ$50 -> -0.03
B54: Corporate Adjusted EBITDA (costs) | AD54: -32.423 | AE54: -34.422 | AF54: -33.811 | AG54: -44.808 | AH54: -145.464 | AI54: -35.036 | AJ54: -42.707 | AK54: -40.644 | AL54: -53.493 | AM54: -171.88 | AN54: -42.64 | AO54: -47.502 | AP54: -46.371 | AQ54: -51.832 | AR54: -188.345 | AS54: -47.472 | AT54: -49.192 | AU54: -48.444 | AV54: -48.722 | AW54: -193.83 | AX54: -42.435 | AY54: -51.584 | AZ54: -52.197 | BA54: -64.25 | BB54: -210.466 | BC54: -55.22 | BD54: -57.281 | BE54: -55.288 | BF54: -69.463 | BG54: -237.252 | BH54: -54.67 | BI54: -71.531 | BJ54: -65.111 | BK54: -70.599 | BL54: -261.911 | BM54: -64.08 | BN54: -83.575 | BO54: -71.914 | BP54: -77.965 | BQ54: -297.534 | BR54: -67.989 | BS54: -78.27 | BT54: -78.007 | BU54: -87.025 | BV54: -311.291 | BW54: -75.528 | BX54: -90.073 | BY54: =BT54*(BW54+BX54)/(BR54+BS54) -> -88.323024 | BZ54: =BU54*(BW54+BX54)/(BR54+BS54) -> -98.533608 | CA54: =SUM(BW54,BX54,BY54,BZ54) -> -352.45763 | CB54: =(CB138-N(CB63)-N(CB80))*CB55 -> -354.80006 | CC54: =(CC138-N(CC63)-N(CC80))*CC55 -> -374.60734 | CD54: =(CD138-N(CD63)-N(CD80))*CD55 -> -394.30681 | CE54: =(CE138-N(CE63)-N(CE80))*CE55 -> -414.47772 | CF54: Q3/Q4-26E: prior-year quarter × 1H/26 y/y growth (+13%, incl. higher incentive comp). 2027E+: legacy revenues × corporate cost %. | CN54: 2030E | CO54: =CP54+$CO$50 -> 0.07 | CP54: 0.02 | CQ54: =CP54+$CQ$50 -> -0.03
B55: Corporate costs % of revenues | AD55: =IF(AND(ISNUMBER(AD54),ISNUMBER(AD138)),IFERROR(AD54/AD138,""),"") -> -0.047062085 | AE55: =IF(AND(ISNUMBER(AE54),ISNUMBER(AE138)),IFERROR(AE54/AE138,""),"") -> -0.045726021 | AF55: =IF(AND(ISNUMBER(AF54),ISNUMBER(AF138)),IFERROR(AF54/AF138,""),"") -> -0.044732657 | AG55: =IF(AND(ISNUMBER(AG54),ISNUMBER(AG138)),IFERROR(AG54/AG138,""),"") -> -0.059951592 | AH55: =IF(AND(ISNUMBER(AH54),ISNUMBER(AH138)),IFERROR(AH54/AH138,""),"") -> -0.049393917 | AI55: =IF(AND(ISNUMBER(AI54),ISNUMBER(AI138)),IFERROR(AI54/AI138,""),"") -> -0.046728498 | AJ55: =IF(AND(ISNUMBER(AJ54),ISNUMBER(AJ138)),IFERROR(AJ54/AJ138,""),"") -> -0.050294416 | AK55: =IF(AND(ISNUMBER(AK54),ISNUMBER(AK138)),IFERROR(AK54/AK138,""),"") -> -0.048203173 | ... CA55: =IF(AND(ISNUMBER(CA54),ISNUMBER(CA138)),IFERROR(CA54/CA138,""),"") -> -0.053456492 | CB55: =-0.052 -> -0.052 | CC55: =-0.052 -> -0.052 | CD55: =-0.052 -> -0.052 | CE55: =-0.052 -> -0.052 | CF55: 2027E+: −5.2% input (FY25 −5.2%; 1H/26 −5.2%). | CN55: ES_margin (ES Adjusted EBITDA margin) | CO55: 0.01 | CP55: Δ → | CQ55: -0.01 | CR55: FY23–25 24.4% / 25.3% / 25.9%; 1H/26 25.7%. ~+40bp p.a. (pricing, network utilisation).
CN56: 2027E | CO56: =CP56+$CO$55 -> 0.286 | CP56: 0.276 | CQ56: =CP56+$CQ$55 -> 0.266
B57: Pending acquisitions — ES&H (Gulf ER / Field Services, $305m) & EnviroServe (national waste services, $470m); NOT in FY26 guidance; reported within ES | CF57: PENDING DEALS — modelling logic (8-K 29-Jul-26 & 12-Aug-26; notes 8-K 18-Sep-26). Closing dates are model assumptions. | CN57: 2028E | CO57: =CP57+$CO$55 -> 0.29 | CP57: 0.28 | CQ57: =CP57+$CQ$55 -> 0.27
B58: ES&H — days consolidated in period (assumed closing 1-Sep-2026) | BY58: 30 | BZ58: 92 | CA58: =SUM(BW58,BX58,BY58,BZ58) -> 122 | CB58: =365 -> 365 | CC58: =365 -> 365 | CD58: =365 -> 365 | CE58: =365 -> 365 | CF58: Signed 17-Jul-26; Sep-26 notes release refers to revolver borrowings incurred for ES&H → assumed closed 1-Sep-26. | CN58: 2029E | CO58: =CP58+$CO$55 -> 0.294 | CP58: 0.284 | CQ58: =CP58+$CQ$55 -> 0.274
B59: EnviroServe — days consolidated in period (assumed closing 1-Nov-2026) | BY59: 0 | BZ59: 61 | CA59: =SUM(BW59,BX59,BY59,BZ59) -> 61 | CB59: =365 -> 365 | CC59: =365 -> 365 | CD59: =365 -> 365 | CE59: =365 -> 365 | CF59: Signed 12-Aug-26, expected 2H/26 close (regulatory approval); funded by the $600m 6.25% notes due 2034 (closed ~1-Oct-26). | CN59: 2030E | CO59: =CP59+$CO$55 -> 0.297 | CP59: 0.287 | CQ59: =CP59+$CQ$55 -> 0.277
B60: ES&H annual revenue run-rate | BY60: =$CA$60 -> 90 | BZ60: =$CA$60 -> 90 | CA60: 90 | CB60: =CA60*(1+CB62) -> 95.446799 | CC60: =CB60*(1+CC62) -> 101.091 | CD60: =CC60*(1+CD62) -> 106.70359 | CE60: =CD60*(1+CE62) -> 112.43788 | CF60: Deal release: ~$90m annual base revenues, ~$30m Adjusted EBITDA. | CN60: SKSS_margin (SKSS Adjusted EBITDA margin) | CO60: 0.03 | CP60: Δ → | CQ60: -0.03 | CR60: FY23–25 19.3% / 16.6% / 16.4%; 1H/26 26.0% (spread spike). Base normalises to ~20%.
B61: EnviroServe annual revenue run-rate | BY61: =$CA$61 -> 250 | BZ61: =$CA$61 -> 250 | CA61: 250 | CB61: =CA61*(1+CB62) -> 265.13 | CC61: =CB61*(1+CC62) -> 280.80834 | CD61: =CC61*(1+CD62) -> 296.39886 | CE61: =CD61*(1+CE62) -> 312.32744 | CF61: Deal release: ~$250m revenues, ~$27m Adjusted EBITDA. | CN61: 2027E | CO61: =CP61+$CO$60 -> 0.23 | CP61: 0.2 | CQ61: =CP61+$CQ$60 -> 0.17
B62: Revenue growth of acquired businesses y/y % | CB62: =CB28 -> 0.060519989 | CC62: =CC28 -> 0.059134535 | CD62: =CD28 -> 0.055520148 | CE62: =CE28 -> 0.05374038 | CF62: 2027E+: grows with ES direct revenues. | CN62: 2028E | CO62: =CP62+$CO$60 -> 0.235 | CP62: 0.205 | CQ62: =CP62+$CQ$60 -> 0.175
B63: Revenues (consolidated from closing) | BY63: =(BY60*BY58+BY61*BY59)/365 -> 7.3972603 | BZ63: =(BZ60*BZ58+BZ61*BZ59)/365 -> 64.465753 | CA63: =SUM(BW63,BX63,BY63,BZ63) -> 71.863014 | CB63: =(CB60*CB58+CB61*CB59)/365 -> 360.5768 | CC63: =(CC60*CC58+CC61*CC59)/365 -> 381.89934 | CD63: =(CD60*CD58+CD61*CD59)/365 -> 403.10245 | CE63: =(CE60*CE58+CE61*CE59)/365 -> 424.76532 | CN63: 2029E | CO63: =CP63+$CO$60 -> 0.24 | CP63: 0.21 | CQ63: =CP63+$CQ$60 -> 0.18
B64: ES&H standalone Adjusted EBITDA margin % ($30m / $90m) | BY64: =$CA$64 -> 0.33333333 | BZ64: =$CA$64 -> 0.33333333 | CA64: =30/90 -> 0.33333333 | CB64: =CA64 -> 0.33333333 | CC64: =CB64 -> 0.33333333 | CD64: =CC64 -> 0.33333333 | CE64: =CD64 -> 0.33333333 | CN64: 2030E | CO64: =CP64+$CO$60 -> 0.24 | CP64: 0.21 | CQ64: =CP64+$CQ$60 -> 0.18
B65: EnviroServe standalone Adjusted EBITDA margin % ($27m / $250m) | BY65: =$CA$65 -> 0.108 | BZ65: =$CA$65 -> 0.108 | CA65: =27/250 -> 0.108 | CB65: =CA65 -> 0.108 | CC65: =CB65 -> 0.108 | CD65: =CC65 -> 0.108 | CE65: =CD65 -> 0.108 | CN65: DEAL_syn (synergy realisation % of $30m run-rate) | CO65: 0.25 | CP65: Δ → | CQ65: -0.25 | CR65: Company: EnviroServe synergies over the first two years.
B66: (+) Cost synergies realised (ES&H ~$5m + EnviroServe ~$25m run-rate) | BY66: 0 | BZ66: 0 | CA66: =SUM(BW66,BX66,BY66,BZ66) -> 0 | CB66: =$CP$26*CHOOSE(MATCH($CF$2,{"Bull","Base","Bear"},0),$CO$66,$CP$66,$CQ$66) -> 15 | CC66: =$CP$26*CHOOSE(MATCH($CF$2,{"Bull","Base","Bear"},0),$CO$67,$CP$67,$CQ$67) -> 30 | CD66: =$CP$26*CHOOSE(MATCH($CF$2,{"Bull","Base","Bear"},0),$CO$68,$CP$68,$CQ$68) -> 30 | CE66: =$CP$26*CHOOSE(MATCH($CF$2,{"Bull","Base","Bear"},0),$CO$69,$CP$69,$CQ$69) -> 30 | CF66: EnviroServe ~$25m over the first two years; ES&H ~$5m after the first full year. Realisation % per scenario lever DEAL_syn. | CN66: 2027E | CO66: =CP66+$CO$65 -> 0.75 | CP66: 0.5 | CQ66: =CP66+$CQ$65 -> 0.25
B67: Adjusted EBITDA contribution | BY67: =(BY60*BY64*BY58+BY61*BY65*BY59)/365+BY66 -> 2.4657534 | BZ67: =(BZ60*BZ64*BZ58+BZ61*BZ65*BZ59)/365+BZ66 -> 12.073973 | CA67: =SUM(BW67,BX67,BY67,BZ67) -> 14.539726 | CB67: =(CB60*CB64*CB58+CB61*CB65*CB59)/365+CB66 -> 75.449639 | CC67: =(CC60*CC64*CC58+CC61*CC65*CC59)/365+CC66 -> 94.024301 | CD67: =(CD60*CD64*CD58+CD61*CD65*CD59)/365+CD66 -> 97.578939 | CE67: =(CE60*CE64*CE58+CE61*CE65*CE59)/365+CE66 -> 101.21066 | CN67: 2028E | CO67: =CP67+$CO$65 -> 1.25 | CP67: 1 | CQ67: =CP67+$CQ$65 -> 0.75
B68: Adjusted EBITDA margin % | BY68: =IF(AND(ISNUMBER(BY67),ISNUMBER(BY63)),IFERROR(BY67/BY63,""),"") -> 0.33333333 | BZ68: =IF(AND(ISNUMBER(BZ67),ISNUMBER(BZ63)),IFERROR(BZ67/BZ63,""),"") -> 0.18729282 | CA68: =IF(AND(ISNUMBER(CA67),ISNUMBER(CA63)),IFERROR(CA67/CA63,""),"") -> 0.20232558 | CB68: =IF(AND(ISNUMBER(CB67),ISNUMBER(CB63)),IFERROR(CB67/CB63,""),"") -> 0.20924707 | CC68: =IF(AND(ISNUMBER(CC67),ISNUMBER(CC63)),IFERROR(CC67/CC63,""),"") -> 0.24620179 | CD68: =IF(AND(ISNUMBER(CD67),ISNUMBER(CD63)),IFERROR(CD67/CD63,""),"") -> 0.24206983 | CE68: =IF(AND(ISNUMBER(CE67),ISNUMBER(CE63)),IFERROR(CE67/CE63,""),"") -> 0.23827429 | CN68: 2029E | CO68: =CP68+$CO$65 -> 1.25 | CP68: 1 | CQ68: =CP68+$CQ$65 -> 0.75
B69: Third-party transaction costs (expensed in SG&A; added back in Adj. EBITDA, as in Q4/25) | BY69: 4 | BZ69: 6 | CA69: =SUM(BW69,BX69,BY69,BZ69) -> 10 | CB69: =0 -> 0 | CC69: =0 -> 0 | CD69: =0 -> 0 | CE69: =0 -> 0 | CF69: Q4/25 reconciliation added back third-party transaction-related costs; assumed ~$10m for ES&H / EnviroServe in 2H/26 (same treatment). | CN69: 2030E | CO69: =CP69+$CO$65 -> 1.25 | CP69: 1 | CQ69: =CP69+$CQ$65 -> 0.75
B70: Standalone depreciation % of revenues | BY70: =$CA$70 -> 0.06 | BZ70: =$CA$70 -> 0.06 | CA70: 0.06 | CB70: =CA70 -> 0.06 | CC70: =CB70 -> 0.06 | CD70: =CC70 -> 0.06 | CE70: =CD70 -> 0.06 | CF70: Assumption: asset-light service businesses (fleet, transfer facilities). | CN70: M&A_spend (bolt-on acquisitions, $m) | CO70: 250 | CP70: Δ → | CQ70: -250 | CR70: CLH averaged ~$0.3bn p.a. of bolt-ons 2022–25 (ex HydroChemPSC).
B71: Amortization of acquired intangibles (customer relationships, permits) | BY71: =$CA$355/$CA$359*(($CA$348+$CA$350)*BY58+$CA$349*BY59)/$CA$351/365 -> 0.68835616 | BZ71: =$CA$355/$CA$359*(($CA$348+$CA$350)*BZ58+$CA$349*BZ59)/$CA$351/365 -> 4.0746575 | CA71: =SUM(BW71,BX71,BY71,BZ71) -> 4.7630137 | CB71: =$CA$355/$CA$359*(($CA$348+$CA$350)*CB58+$CA$349*CB59)/$CA$351/365 -> 20.125 | CC71: =$CA$355/$CA$359*(($CA$348+$CA$350)*CC58+$CA$349*CC59)/$CA$351/365 -> 20.125 | CD71: =$CA$355/$CA$359*(($CA$348+$CA$350)*CD58+$CA$349*CD59)/$CA$351/365 -> 20.125 | CE71: =$CA$355/$CA$359*(($CA$348+$CA$350)*CE58+$CA$349*CE59)/$CA$351/365 -> 20.125 | CN71: 2027E | CO71: =CP71+$CO$70 -> 550 | CP71: 300 | CQ71: =CP71+$CQ$70 -> 50
B72: D&A — standalone depreciation + purchase-accounting amortization | BY72: =BY63*BY70+BY71 -> 1.1321918 | BZ72: =BZ63*BZ70+BZ71 -> 7.9426027 | CA72: =SUM(BW72,BX72,BY72,BZ72) -> 9.0747945 | CB72: =CB63*CB70+CB71 -> 41.759608 | CC72: =CC63*CC70+CC71 -> 43.03896 | CD72: =CD63*CD70+CD71 -> 44.311147 | CE72: =CE63*CE70+CE71 -> 45.610919 | CN72: 2028E | CO72: =CP72+$CO$70 -> 550 | CP72: 300 | CQ72: =CP72+$CQ$70 -> 50
CN73: 2029E | CO73: =CP73+$CO$70 -> 550 | CP73: 300 | CQ73: =CP73+$CQ$70 -> 50
B74: Future acquisitions (M&A lever — bolt-ons, unallocated; deals closed from 2027E) | CF74: M&A LEVER — acquired revenues = spend ÷ EV/revenues; mid-year convention | CN74: 2030E | CO74: =CP74+$CO$70 -> 550 | CP74: 300 | CQ74: =CP74+$CQ$70 -> 50
B75: Acquisition spend (USDm, scenario) | CA75: 0 | CB75: =MAX(0,CHOOSE(MATCH($CF$2,{"Bull","Base","Bear"},0),$CO$71,$CP$71,$CQ$71)) -> 300 | CC75: =MAX(0,CHOOSE(MATCH($CF$2,{"Bull","Base","Bear"},0),$CO$72,$CP$72,$CQ$72)) -> 300 | CD75: =MAX(0,CHOOSE(MATCH($CF$2,{"Bull","Base","Bear"},0),$CO$73,$CP$73,$CQ$73)) -> 300 | CE75: =MAX(0,CHOOSE(MATCH($CF$2,{"Bull","Base","Bear"},0),$CO$74,$CP$74,$CQ$74)) -> 300 | CF75: Scenario lever M&A_spend. CLH deployed ~$0.1–1.3bn p.a. on acquisitions 2017–26 (HydroChemPSC $1.25bn 2021; Thompson $110m 2023; Noble Oil 2024; DCI, Terra Nova, ES&H, EnviroServe 2026).
B76: Purchase multiple — EV / revenues (x) | CA76: 0 | CB76: =1.6 -> 1.6 | CC76: =1.6 -> 1.6 | CD76: =1.6 -> 1.6 | CE76: =1.6 -> 1.6 | CF76: CLH bolt-ons at ~9–12x Adj. EBITDA post-synergy on ~15–20% margins → ~1.6x revenues.
B77: Annualised revenues acquired in the year | CA77: 0 | CB77: =IFERROR(CB75/CB76,0) -> 187.5 | CC77: =IFERROR(CC75/CC76,0) -> 187.5 | CD77: =IFERROR(CD75/CD76,0) -> 187.5 | CE77: =IFERROR(CE75/CE76,0) -> 187.5
B78: Growth of acquired businesses after acquisition % | CA78: 0 | CB78: =0.05 -> 0.05 | CC78: =0.05 -> 0.05 | CD78: =0.05 -> 0.05 | CE78: =0.05 -> 0.05
B79: Run-rate revenues of businesses acquired (year end) | CA79: 0 | CB79: =CA79*(1+CB78)+CB77 -> 187.5 | CC79: =CB79*(1+CC78)+CC77 -> 384.375 | CD79: =CC79*(1+CD78)+CD77 -> 591.09375 | CE79: =CD79*(1+CE78)+CE77 -> 808.14844
B80: Revenues from future acquisitions | CA80: 0 | CB80: =CA79*(1+CB78)+0.5*CB77 -> 93.75 | CC80: =CB79*(1+CC78)+0.5*CC77 -> 290.625 | CD80: =CC79*(1+CD78)+0.5*CD77 -> 497.34375 | CE80: =CD79*(1+CE78)+0.5*CE77 -> 714.39844 | CF80: Mid-year convention: half a year of revenues in the year of acquisition.
B81: Adjusted EBITDA margin of acquired businesses % (incl. synergies) | CA81: 0 | CB81: =0.19 -> 0.19 | CC81: =0.19 -> 0.19 | CD81: =0.19 -> 0.19 | CE81: =0.19 -> 0.19
B82: Adjusted EBITDA from future acquisitions | CA82: 0 | CB82: =CB80*CB81 -> 17.8125 | CC82: =CC80*CC81 -> 55.21875 | CD82: =CD80*CD81 -> 94.495312 | CE82: =CE80*CE81 -> 135.7357
B83: D&A of acquired businesses % of revenues (incl. step-ups) | CA83: 0 | CB83: =0.09 -> 0.09 | CC83: =0.09 -> 0.09 | CD83: =0.09 -> 0.09 | CE83: =0.09 -> 0.09
B84: D&A from future acquisitions | CA84: 0 | CB84: =CB80*CB83 -> 8.4375 | CC84: =CC80*CC83 -> 26.15625 | CD84: =CD80*CD83 -> 44.760937 | CE84: =CE80*CE83 -> 64.295859
B85: PP&E % of spend | CA85: 0 | CB85: =0.35 -> 0.35 | CC85: =0.35 -> 0.35 | CD85: =0.35 -> 0.35 | CE85: =0.35 -> 0.35
B86: Acquired intangibles % of spend | CA86: 0 | CB86: =0.25 -> 0.25 | CC86: =0.25 -> 0.25 | CD86: =0.25 -> 0.25 | CE86: =0.25 -> 0.25
B87: Intangible amortization life (years) | CA87: 0 | CB87: =12 -> 12 | CC87: =12 -> 12 | CD87: =12 -> 12 | CE87: =12 -> 12
B88: Cumulative acquired intangibles (gross) | CA88: 0 | CB88: =CA88+CB75*CB86 -> 75 | CC88: =CB88+CC75*CC86 -> 150 | CD88: =CC88+CD75*CD86 -> 225 | CE88: =CD88+CE75*CE86 -> 300
B89: Amortization of future-acquisition intangibles (within D&A) | CA89: 0 | CB89: =(CA88+0.5*CB75*CB86)/CB87 -> 3.125 | CC89: =(CB88+0.5*CC75*CC86)/CC87 -> 9.375 | CD89: =(CC88+0.5*CD75*CD86)/CD87 -> 15.625 | CE89: =(CD88+0.5*CE75*CE86)/CE87 -> 21.875
B91: Group total — revenues & Adjusted EBITDA (segment build) → consolidated (Adjusted EBITDA is CLH's primary profit KPI and segment measure) | CF91: GROUP TOTAL (CONSOLIDATED) — modelling logic
B92: Revenues (segment build) | C92: =N(C106)+N(C107)+N(C108)+N(C109)+N(C110)+N(C111)+N(C112)+N(C113)+N(C114)+N(C115)+N(C116) -> 829.809 | D92: =N(D106)+N(D107)+N(D108)+N(D109)+N(D110)+N(D111)+N(D112)+N(D113)+N(D114)+N(D115)+N(D116) -> 946.917 | E92: =N(E106)+N(E107)+N(E108)+N(E109)+N(E110)+N(E111)+N(E112)+N(E113)+N(E114)+N(E115)+N(E116) -> 1030.713 | F92: =N(F106)+N(F107)+N(F108)+N(F109)+N(F110)+N(F111)+N(F112)+N(F113)+N(F114)+N(F115)+N(F116) -> 1074.22 | G92: =N(G106)+N(G107)+N(G108)+N(G109)+N(G110)+N(G111)+N(G112)+N(G113)+N(G114)+N(G115)+N(G116) -> 1731.244 | H92: =N(H106)+N(H107)+N(H108)+N(H109)+N(H110)+N(H111)+N(H112)+N(H113)+N(H114)+N(H115)+N(H116) -> 1984.136 | I92: =N(I106)+N(I107)+N(I108)+N(I109)+N(I110)+N(I111)+N(I112)+N(I113)+N(I114)+N(I115)+N(I116) -> 2187.908 | J92: =N(J106)+N(J107)+N(J108)+N(J109)+N(J110)+N(J111)+N(J112)+N(J113)+N(J114)+N(J115)+N(J116) -> 862.163 | ... AC92: =N(AC106)+N(AC107)+N(AC108)+N(AC109)+N(AC110)+N(AC111)+N(AC112)+N(AC113)+N(AC114)+N(AC115)+N(AC116) -> 2755.226 | AD92: =N(AD27)+N(AD44)+N(AD53) -> 688.941 | AE92: =N(AE27)+N(AE44)+N(AE53) -> 752.788 | AF92: =N(AF27)+N(AF44)+N(AF53) -> 755.846 | AG92: =N(AG27)+N(AG44)+N(AG53) -> 747.403 | AH92: =N(AH27)+N(AH44)+N(AH53) -> 2944.978 | AI92: =N(AI27)+N(AI44)+N(AI53) -> 749.778 | AJ92: =N(AJ27)+N(AJ44)+N(AJ53) -> 849.14 | AK92: =N(AK27)+N(AK44)+N(AK53) -> 843.181 | ... BX92: =N(BX27)+N(BX44)+N(BX53) -> 1735.005 | BY92: =N(BY27)+N(BY44)+N(BY53)+N(BY63)+N(BY80) -> 1719.0164 | BZ92: =N(BZ27)+N(BZ44)+N(BZ53)+N(BZ63)+N(BZ80) -> 1679.7967 | CA92: =N(CA27)+N(CA44)+N(CA53)+N(CA63)+N(CA80) -> 6593.3551 | CB92: =N(CB27)+N(CB44)+N(CB53)+N(CB63)+N(CB80) -> 7277.4048 | CC92: =N(CC27)+N(CC44)+N(CC53)+N(CC63)+N(CC80) -> 7876.5116 | CD92: =N(CD27)+N(CD44)+N(CD53)+N(CD63)+N(CD80) -> 8483.2694 | CE92: =N(CE27)+N(CE44)+N(CE53)+N(CE63)+N(CE80) -> 9109.8892 | CF92: Σ ES + SKSS + Corporate direct revenues (+ pending deals + future M&A); before 2017: Σ legacy segments as originally reported. | CH92: =IFERROR((CE92/BV92)^(1/5)-1,"n/m") -> 0.085993186 | CI92: =IFERROR((BV92/AW92)^(1/5)-1,"n/m") -> 0.13913798 | CJ92: =IFERROR((BV92/X92)^(1/10)-1,"n/m") -> 0.062954835 | CK92: =IFERROR((BV92/C92)^(1/19)-1,"n/m") -> 0.11003536
B93: Adjusted EBITDA (segment build) | C93: =N(C117)+N(C118)+N(C119)+N(C120)+N(C121)+N(C122)+N(C123)+N(C124)+N(C125)+N(C126)+N(C127) -> 119.935 | D93: =N(D117)+N(D118)+N(D119)+N(D120)+N(D121)+N(D122)+N(D123)+N(D124)+N(D125)+N(D126)+N(D127) -> 133.297 | E93: =N(E117)+N(E118)+N(E119)+N(E120)+N(E121)+N(E122)+N(E123)+N(E124)+N(E125)+N(E126)+N(E127) -> 163.219 | F93: =N(F117)+N(F118)+N(F119)+N(F120)+N(F121)+N(F122)+N(F123)+N(F124)+N(F125)+N(F126)+N(F127) -> 157.58 | G93: =N(G117)+N(G118)+N(G119)+N(G120)+N(G121)+N(G122)+N(G123)+N(G124)+N(G125)+N(G126)+N(G127) -> 314.692 | H93: =N(H117)+N(H118)+N(H119)+N(H120)+N(H121)+N(H122)+N(H123)+N(H124)+N(H125)+N(H126)+N(H127) -> 350.008 | I93: =N(I117)+N(I118)+N(I119)+N(I120)+N(I121)+N(I122)+N(I123)+N(I124)+N(I125)+N(I126)+N(I127) -> 373.767 | J93: =N(J117)+N(J118)+N(J119)+N(J120)+N(J121)+N(J122)+N(J123)+N(J124)+N(J125)+N(J126)+N(J127) -> 111.228 | ... AC93: =N(AC117)+N(AC118)+N(AC119)+N(AC120)+N(AC121)+N(AC122)+N(AC123)+N(AC124)+N(AC125)+N(AC126)+N(AC127) -> 400.354 | AD93: =N(AD29)+N(AD46)+N(AD54) -> 80.135 | AE93: =N(AE29)+N(AE46)+N(AE54) -> 120.691 | AF93: =N(AF29)+N(AF46)+N(AF54) -> 122.999 | AG93: =N(AG29)+N(AG46)+N(AG54) -> 101.832 | AH93: =N(AH29)+N(AH46)+N(AH54) -> 425.657 | AI93: =N(AI29)+N(AI46)+N(AI54) -> 88.265 | AJ93: =N(AJ29)+N(AJ46)+N(AJ54) -> 139.561 | AK93: =N(AK29)+N(AK46)+N(AK54) -> 141.277 | ... BX93: =N(BX29)+N(BX46)+N(BX54) -> 409.024 | BY93: =N(BY29)+N(BY46)+N(BY54)+N(BY67)+N(BY82) -> 399.82671 | BZ93: =N(BZ29)+N(BZ46)+N(BZ54)+N(BZ67)+N(BZ82) -> 337.83502 | CA93: =N(CA29)+N(CA46)+N(CA54)+N(CA67)+N(CA82) -> 1394.5397 | CB93: =N(CB29)+N(CB46)+N(CB54)+N(CB67)+N(CB82) -> 1550.1963 | CC93: =N(CC29)+N(CC46)+N(CC54)+N(CC67)+N(CC82) -> 1718.7809 | CD93: =N(CD29)+N(CD46)+N(CD54)+N(CD67)+N(CD82) -> 1876.8572 | CE93: =N(CE29)+N(CE46)+N(CE54)+N(CE67)+N(CE82) -> 2029.9644 | CH93: =IFERROR((CE93/BV93)^(1/5)-1,"n/m") -> 0.11651624 | CI93: =IFERROR((BV93/AW93)^(1/5)-1,"n/m") -> 0.16071821 | CJ93: =IFERROR((BV93/X93)^(1/10)-1,"n/m") -> 0.087824611 | CK93: =IFERROR((BV93/C93)^(1/19)-1,"n/m") -> 0.12736375
B94: Adjusted EBITDA margin % | C94: =IF(AND(ISNUMBER(C93),ISNUMBER(C92)),IFERROR(C93/C92,""),"") -> 0.14453326 | D94: =IF(AND(ISNUMBER(D93),ISNUMBER(D92)),IFERROR(D93/D92,""),"") -> 0.14076947 | E94: =IF(AND(ISNUMBER(E93),ISNUMBER(E92)),IFERROR(E93/E92,""),"") -> 0.15835543 | F94: =IF(AND(ISNUMBER(F93),ISNUMBER(F92)),IFERROR(F93/F92,""),"") -> 0.14669248 | G94: =IF(AND(ISNUMBER(G93),ISNUMBER(G92)),IFERROR(G93/G92,""),"") -> 0.18177218 | H94: =IF(AND(ISNUMBER(H93),ISNUMBER(H92)),IFERROR(H93/H92,""),"") -> 0.17640323 | I94: =IF(AND(ISNUMBER(I93),ISNUMBER(I92)),IFERROR(I93/I92,""),"") -> 0.17083305 | J94: =IF(AND(ISNUMBER(J93),ISNUMBER(J92)),IFERROR(J93/J92,""),"") -> 0.12901041 | ... CE94: =IF(AND(ISNUMBER(CE93),ISNUMBER(CE92)),IFERROR(CE93/CE92,""),"") -> 0.22283086 | CH94: =IFERROR(AVERAGE(CA94,CB94,CC94,CD94,CE94),"n/m") -> 0.21736218 | CI94: =IFERROR(AVERAGE(BB94,BG94,BL94,BQ94,BV94),"n/m") -> 0.18928994 | CJ94: =IFERROR(AVERAGE(AC94,AH94,AM94,AR94,AW94,BB94,BG94,BL94,BQ94,BV94),"n/m") -> 0.17200355 | CK94: =IFERROR(AVERAGE(C94,D94,E94,F94,G94,H94,I94,N94,S94,X94,AC94,AH94,AM94,AR94,AW94,BB94,BG94,BL94,BQ94,BV94),"n/m") -> 0.16460537
B95: Revenues y/y % | D95: =IF(AND(ISNUMBER(D92),ISNUMBER(C92)),IFERROR(D92/C92-1,""),"") -> 0.14112645 | E95: =IF(AND(ISNUMBER(E92),ISNUMBER(D92)),IFERROR(E92/D92-1,""),"") -> 0.0884935 | F95: =IF(AND(ISNUMBER(F92),ISNUMBER(E92)),IFERROR(F92/E92-1,""),"") -> 0.042210586 | G95: =IF(AND(ISNUMBER(G92),ISNUMBER(F92)),IFERROR(G92/F92-1,""),"") -> 0.6116289 | H95: =IF(AND(ISNUMBER(H92),ISNUMBER(G92)),IFERROR(H92/G92-1,""),"") -> 0.14607531 | I95: =IF(AND(ISNUMBER(I92),ISNUMBER(H92)),IFERROR(I92/H92-1,""),"") -> 0.10270062 | N95: =IF(AND(ISNUMBER(N92),ISNUMBER(I92)),IFERROR(N92/I92-1,""),"") -> 0.60411498 | O95: =IF(AND(ISNUMBER(O92),ISNUMBER(J92)),IFERROR(O92/J92-1,""),"") -> -0.017973399 | P95: =IF(AND(ISNUMBER(P92),ISNUMBER(K92)),IFERROR(P92/K92-1,""),"") -> -0.0023799342 | Q95: =IF(AND(ISNUMBER(Q92),ISNUMBER(L92)),IFERROR(Q92/L92-1,""),"") -> -0.061782741 | R95: =IF(AND(ISNUMBER(R92),ISNUMBER(M92)),IFERROR(R92/M92-1,""),"") -> -0.039123068 | S95: =IF(AND(ISNUMBER(S92),ISNUMBER(N92)),IFERROR(S92/N92-1,""),"") -> -0.030777945 | T95: =IF(AND(ISNUMBER(T92),ISNUMBER(O92)),IFERROR(T92/O92-1,""),"") -> -0.13484404 | U95: =IF(AND(ISNUMBER(U92),ISNUMBER(P92)),IFERROR(U92/P92-1,""),"") -> 0.090564719 | ... BX95: =IF(AND(ISNUMBER(BX92),ISNUMBER(BS92)),IFERROR(BX92/BS92-1,""),"") -> 0.11946351 | BY95: =IFERROR(BY92/BT92-1,"") -> 0.10951743 | BZ95: =IFERROR(BZ92/BU92-1,"") -> 0.12009146 | CA95: =IFERROR(CA92/BV92-1,"") -> 0.093273634 | CB95: =IFERROR(CB92/CA92-1,"") -> 0.10374835 | CC95: =IFERROR(CC92/CB92-1,"") -> 0.08232424 | CD95: =IFERROR(CD92/CC92-1,"") -> 0.077033819 | CE95: =IFERROR(CE92/CD92-1,"") -> 0.073865361
B96: Check: segment build vs consolidated revenues (should be 0) | C96: =ROUND(C92-C138,1) -> 0 | D96: =ROUND(D92-D138,1) -> 0 | E96: =ROUND(E92-E138,1) -> 0 | F96: =ROUND(F92-F138,1) -> 0 | G96: =ROUND(G92-G138,1) -> 0 | H96: =ROUND(H92-H138,1) -> 0 | I96: =ROUND(I92-I138,1) -> 0 | J96: =ROUND(J92-J138,1) -> 0 | ... CE96: =ROUND(CE92-CE138,1) -> 0
B97: Check: segment build vs Adjusted EBITDA bridge (should be 0) | C97: =ROUND(C93-C187,1) -> 0 | D97: =ROUND(D93-D187,1) -> 0 | E97: =ROUND(E93-E187,1) -> 0 | F97: =ROUND(F93-F187,1) -> 0 | G97: =ROUND(G93-G187,1) -> 0 | H97: =ROUND(H93-H187,1) -> 0 | I97: =ROUND(I93-I187,1) -> 0 | J97: =ROUND(J93-J187,1) -> 0 | ... CE97: =ROUND(CE93-CE187,1) -> 0
B98: Memo: Adjusted EBITDA — legacy CLH (ex pending acquisitions & future M&A) | BW98: =BW93 -> 247.854 | BX98: =BX93 -> 409.024 | BY98: =BY93-N(BY67)-N(BY82) -> 397.36096 | BZ98: =BZ93-N(BZ67)-N(BZ82) -> 325.76104 | CA98: =CA93-N(CA67)-N(CA82) -> 1380 | CB98: =CB93-N(CB67)-N(CB82) -> 1456.9342 | CC98: =CC93-N(CC67)-N(CC82) -> 1569.5378 | CD98: =CD93-N(CD67)-N(CD82) -> 1684.783 | CE98: =CE93-N(CE67)-N(CE82) -> 1793.0181
B99: Memo: FY26 Adjusted EBITDA guidance — ex pending ES&H / EnviroServe (scenario end-point) | CA99: =CHOOSE(MATCH($CF$2,{"Bull","Base","Bear"},0),$CO$12,$CP$12,$CQ$12) -> 1380 | CF99: Q2-26 release (29-Jul-26): raised to $1,350–1,410m (mid $1,380m, +$110m); excludes ES&H / EnviroServe. Drives the Q3/Q4-26E margin calibration.
B100: Legacy Adjusted EBITDA before margin calibration (Q3/Q4-26E helper) | BY100: =BY27*BY30+BY44*BY47+BY54 -> 380.85636 | BZ100: =BZ27*BZ30+BZ44*BZ47+BZ54 -> 310.18493
B101: Outlook calibration: Δ Adj. EBITDA margin applied to ES & SKSS (Q3/Q4-26E) | BY101: =(CA99-BW98-BX98-BY100-BZ100)/(BY27+BZ27+BY44+BZ44) -> 0.0096426793 | BZ101: =BY101 -> 0.0096426793 | CF101: Solves the uniform margin shift (vs. prior-year quarter + 1H drift) so legacy FY26 Adjusted EBITDA = guidance end-point for the active scenario (High / Mid / Low).
...

Sheet Bull-Base-Bear
B2: Clean Harbors (CLH) — Bull / Base / Bear Case P&L Summary | J2: Share price ($): | K2: =Model!$CA$424 -> 321.34
B3: Adjusted figures (company definitions: Adjusted EBITDA as published — SBC added back from Q1/21; adjusted EPS = GAAP excl. debt extinguishment, impairments, business-sale gains / losses, tax items) · USD millions · Live panel linked to Model — toggle scenario via Model!CF2. Bull and Bear panels are value snapshots generated from the Model with the switch set to each case. 2026E includes ES&H (from 1-Sep-26) and EnviroServe (from 1-Nov-26) — assumed closing dates. | J3: As of: | K3: =TODAY() -> 46299
B5: Scenario: | C5: =Model!$CF$2 -> Base | N5: Scenario: | O5: Bull | P5: Snapshot (values) — Model run with switch = Bull | Z5: Scenario: | AA5: Bear | AB5: Snapshot (values) — Model run with switch = Bear
B7: (USDm, except EPS and shares) | C7: 2025A | D7: 2026E | E7: 2027E | F7: 2028E | G7: 2029E | H7: 2030E | I7: 25-'30 CAGR | J7: LT Hist Avg | K7: LT Hist Min | L7: LT Hist Max | N7: (USDm, except EPS and shares) | O7: 2025A | P7: 2026E | Q7: 2027E | R7: 2028E | S7: 2029E | T7: 2030E | U7: 25-'30 CAGR | V7: LT Hist Avg | W7: LT Hist Min | X7: LT Hist Max | Z7: (USDm, except EPS and shares) | AA7: 2025A | AB7: 2026E | AC7: 2027E | AD7: 2028E | AE7: 2029E | AF7: 2030E | AG7: 25-'30 CAGR | AH7: LT Hist Avg | AI7: LT Hist Min | AJ7: LT Hist Max
B9: Revenues | C9: =Model!BV138 -> 6030.837 | D9: =Model!CA138 -> 6593.3551 | E9: =Model!CB138 -> 7277.4048 | F9: =Model!CC138 -> 7876.5116 | G9: =Model!CD138 -> 8483.2694 | H9: =Model!CE138 -> 9109.8892 | I9: =IFERROR((H9/C9)^(1/5)-1,"n/m") -> 0.085993186 | N9: Revenues | O9: 6030.837 | P9: 6593.3551 | Q9: 7523.798 | R9: 8473.7845 | S9: 9462.2496 | T9: 10503.272 | U9: 0.11735045 | Z9: Revenues | AA9: 6030.837 | AB9: 6593.3551 | AC9: 7031.0117 | AD9: 7288.6538 | AE9: 7533.4165 | AF9: 7776.9012 | AG9: 0.052169717
B10: Revenues y/y % | D10: =IFERROR(D9/C9-1,"") -> 0.093273634 | E10: =IFERROR(E9/D9-1,"") -> 0.10374835 | F10: =IFERROR(F9/E9-1,"") -> 0.08232424 | G10: =IFERROR(G9/F9-1,"") -> 0.077033819 | H10: =IFERROR(H9/G9-1,"") -> 0.073865361 | N10: Revenues y/y % | P10: 0.093273634 | Q10: 0.14111827 | R10: 0.12626423 | S10: 0.11664978 | T10: 0.11001851 | Z10: Revenues y/y % | AB10: 0.093273634 | AC10: 0.066378434 | AD10: 0.036643673 | AE10: 0.033581333 | AF10: 0.032320624
B11: ES direct revenues y/y % | C11: =Model!BV226 -> 0.037672833 | D11: =Model!CA226 -> 0.068188176 | E11: =Model!CB226 -> 0.060519989 | F11: =Model!CC226 -> 0.059134535 | G11: =Model!CD226 -> 0.055520148 | H11: =Model!CE226 -> 0.05374038 | N11: ES direct revenues y/y % | O11: 0.037672833 | P11: 0.068188176 | Q11: 0.082315011 | R11: 0.080904949 | S11: 0.07726624 | T11: 0.075472574 | Z11: ES direct revenues y/y % | AA11: 0.037672833 | AB11: 0.068188176 | AC11: 0.038724966 | AD11: 0.037393512 | AE11: 0.033832253 | AF11: 0.032094305
B12: Adjusted EBITDA | C12: =Model!BV187 -> 1169.939 | D12: =Model!CA187 -> 1394.5397 | E12: =Model!CB187 -> 1550.1963 | F12: =Model!CC187 -> 1718.7809 | G12: =Model!CD187 -> 1876.8572 | H12: =Model!CE187 -> 2029.9644 | I12: =IFERROR((H12/C12)^(1/5)-1,"n/m") -> 0.11651624 | N12: Adjusted EBITDA | O12: 1169.939 | P12: 1424.5397 | Q12: 1696.2154 | R12: 1942.7647 | S12: 2187.0327 | T12: 2433.9323 | U12: 0.15778803 | Z12: Adjusted EBITDA | AA12: 1169.939 | AB12: 1364.5397 | AC12: 1408.9925 | AD12: 1506.4891 | AE12: 1587.8483 | AF12: 1659.5181 | AG12: 0.072417157
B13: Adjusted EBITDA margin % | C13: =IFERROR(C12/C9,"") -> 0.19399281 | D13: =IFERROR(D12/D9,"") -> 0.21150684 | E13: =IFERROR(E12/E9,"") -> 0.21301499 | F13: =IFERROR(F12/F9,"") -> 0.218216 | G13: =IFERROR(G12/G9,"") -> 0.2212422 | H13: =IFERROR(H12/H9,"") -> 0.22283086 | J13: =IFERROR(AVERAGE(Model!C188,Model!D188,Model!E188,Model!F188,Model!G188,Model!H188,Model!I188,Model!N188,Model!S188,Model!X188,Model!AC188,Model!AH188,Model!AM188,Model!AR188,Model!AW188,Model!BB188,Model!BG188,Model!BL188,Model!BQ188,Model!BV188),"") -> 0.16460537 | K13: =IFERROR(MIN(Model!C188,Model!D188,Model!E188,Model!F188,Model!G188,Model!H188,Model!I188,Model!N188,Model!S188,Model!X188,Model!AC188,Model!AH188,Model!AM188,Model!AR188,Model!AW188,Model!BB188,Model!BG188,Model!BL188,Model!BQ188,Model!BV188),"") -> 0.14076947 | L13: =IFERROR(MAX(Model!C188,Model!D188,Model!E188,Model!F188,Model!G188,Model!H188,Model!I188,Model!N188,Model!S188,Model!X188,Model!AC188,Model!AH188,Model!AM188,Model!AR188,Model!AW188,Model!BB188,Model!BG188,Model!BL188,Model!BQ188,Model!BV188),"") -> 0.19783359 | N13: Adjusted EBITDA margin % | O13: 0.19399281 | P13: 0.21605688 | Q13: 0.22544669 | R13: 0.22926765 | S13: 0.23113243 | T13: 0.23173086 | V13: 0.16460537 | W13: 0.14076947 | X13: 0.19783359 | Z13: Adjusted EBITDA margin % | AA13: 0.19399281 | AB13: 0.20695681 | AC13: 0.20039684 | AD13: 0.20668962 | AE13: 0.21077399 | AF13: 0.21339066 | AH13: 0.16460537 | AI13: 0.14076947 | AJ13: 0.19783359
B15: Income from Operations (GAAP) | C15: =Model!BV147 -> 673.372 | D15: =Model!CA147 -> 830.46493 | E15: =Model!CB147 -> 930.59597 | F15: =Model!CC147 -> 1046.5048 | G15: =Model!CD147 -> 1151.103 | H15: =Model!CE147 -> 1248.9178 | I15: =IFERROR((H15/C15)^(1/5)-1,"n/m") -> 0.13150313 | N15: Income from Operations (GAAP) | O15: 673.372 | P15: 860.46493 | Q15: 1054.9819 | R15: 1217.1234 | S15: 1373.5033 | T15: 1527.8617 | U15: 0.17805563 | Z15: Income from Operations (GAAP) | AA15: 673.372 | AB15: 800.46493 | AC15: 811.02532 | AD15: 886.80298 | AE15: 947.47122 | AF15: 998.52354 | AG15: 0.081983532
B16: Income from operations y/y % | D16: =IFERROR(D15/C15-1,"") -> 0.23329294 | E16: =IFERROR(E15/D15-1,"") -> 0.12057227 | F16: =IFERROR(F15/E15-1,"") -> 0.12455331 | G16: =IFERROR(G15/F15-1,"") -> 0.099950057 | H16: =IFERROR(H15/G15-1,"") -> 0.084974852 | N16: Income from operations y/y % | P16: 0.27784483 | Q16: 0.22606026 | R16: 0.15369127 | S16: 0.12848324 | T16: 0.112383 | Z16: Income from operations y/y % | AB16: 0.18874104 | AC16: 0.013192815 | AD16: 0.093434402 | AE16: 0.068412305 | AF16: 0.053882713
B17: Operating margin (GAAP) % | C17: =IFERROR(C15/C9,"") -> 0.11165482 | D17: =IFERROR(D15/D9,"") -> 0.12595483 | E17: =IFERROR(E15/E9,"") -> 0.1278747 | F17: =IFERROR(F15/F9,"") -> 0.13286399 | G17: =IFERROR(G15/G9,"") -> 0.13569096 | H17: =IFERROR(H15/H9,"") -> 0.13709473 | J17: =IFERROR(AVERAGE(Model!C235,Model!D235,Model!E235,Model!F235,Model!G235,Model!H235,Model!I235,Model!N235,Model!S235,Model!X235,Model!AC235,Model!AH235,Model!AM235,Model!AR235,Model!AW235,Model!BB235,Model!BG235,Model!BL235,Model!BQ235,Model!BV235),"") -> 0.083113356 | K17: =IFERROR(MIN(Model!C235,Model!D235,Model!E235,Model!F235,Model!G235,Model!H235,Model!I235,Model!N235,Model!S235,Model!X235,Model!AC235,Model!AH235,Model!AM235,Model!AR235,Model!AW235,Model!BB235,Model!BG235,Model!BL235,Model!BQ235,Model!BV235),"") -> 0.025102115 | L17: =IFERROR(MAX(Model!C235,Model!D235,Model!E235,Model!F235,Model!G235,Model!H235,Model!I235,Model!N235,Model!S235,Model!X235,Model!AC235,Model!AH235,Model!AM235,Model!AR235,Model!AW235,Model!BB235,Model!BG235,Model!BL235,Model!BQ235,Model!BV235),"") -> 0.12285572 | N17: Operating margin (GAAP) % | O17: 0.11165482 | P17: 0.13050487 | Q17: 0.14021932 | R17: 0.14363398 | S17: 0.14515611 | T17: 0.14546531 | V17: 0.083113356 | W17: 0.025102115 | X17: 0.12285572 | Z17: Operating margin (GAAP) % | AA17: 0.11165482 | AB17: 0.1214048 | AC17: 0.11534973 | AD17: 0.12166897 | AE17: 0.12576913 | AF17: 0.12839607 | AH17: 0.083113356 | AI17: 0.025102115 | AJ17: 0.12285572
B19: Adjusted Net Income | C19: =Model!BV204 -> 396.5287 | D19: =Model!CA204 -> 495.87315 | E19: =Model!CB204 -> 560.42977 | F19: =Model!CC204 -> 643.58192 | G19: =Model!CD204 -> 713.11883 | H19: =Model!CE204 -> 773.62868 | I19: =IFERROR((H19/C19)^(1/5)-1,"n/m") -> 0.1430141 | N19: Adjusted Net Income | O19: 396.5287 | P19: 517.98531 | Q19: 650.95166 | R19: 745.4684 | S19: 840.02578 | T19: 933.28304 | U19: 0.1867186 | Z19: Adjusted Net Income | AA19: 396.5287 | AB19: 473.76099 | AC19: 473.47115 | AD19: 535.43905 | AE19: 582.24709 | AF19: 617.07945 | AG19: 0.092479491
B21: FDSO (m) | C21: =Model!BV165 -> 53.716 | D21: =Model!CA165 -> 52.92985 | E21: =Model!CB165 -> 52.507983 | F21: =Model!CC165 -> 51.399485 | G21: =Model!CD165 -> 49.817265 | H21: =Model!CE165 -> 48.202127 | I21: =IFERROR((H21/C21)^(1/5)-1,"n/m") -> -0.021428625 | N21: FDSO (m) | O21: 53.716 | P21: 52.890951 | Q21: 51.738292 | R21: 50.013207 | S21: 48.3746 | T21: 46.597446 | U21: -0.028032622 | Z21: FDSO (m) | AA21: 53.716 | AB21: 52.96875 | AC21: 52.847965 | AD21: 52.157958 | AE21: 50.799969 | AF21: 49.20737 | AG21: -0.017380684
B23: Adjusted EPS — Diluted ($) | C23: =Model!BV207 -> 7.3819476 | D23: =Model!CA207 -> 9.3684971 | E23: =Model!CB207 -> 10.67323 | F23: =Model!CC207 -> 12.521174 | G23: =Model!CD207 -> 14.314693 | H23: =Model!CE207 -> 16.049679 | I23: =IFERROR((H23/C23)^(1/5)-1,"n/m") -> 0.16804367 | N23: Adjusted EPS — Diluted ($) | O23: 7.3819476 | P23: 9.7934582 | Q23: 12.581623 | R23: 14.905431 | S23: 17.365017 | T23: 20.028631 | U23: 0.22094489 | Z23: Adjusted EPS — Diluted ($) | AA23: 7.3819476 | AB23: 8.9441602 | AC23: 8.9591178 | AD23: 10.265721 | AE23: 11.461564 | AF23: 12.540387 | AG23: 0.11180339
B24: EPS y/y % | D24: =IFERROR(D23/C23-1,"") -> 0.26910914 | E24: =IFERROR(E23/D23-1,"") -> 0.13926808 | F24: =IFERROR(F23/E23-1,"") -> 0.17313829 | G24: =IFERROR(G23/F23-1,"") -> 0.14323881 | H24: =IFERROR(H23/G23-1,"") -> 0.1212032 | N24: EPS y/y % | P24: 0.32667674 | Q24: 0.28469662 | R24: 0.18469863 | S24: 0.16501276 | T24: 0.15338962 | Z24: EPS y/y % | AB24: 0.21162609 | AC24: 0.0016723239 | AD24: 0.14584062 | AE24: 0.1164889 | AF24: 0.094125302
B26: P / E (x) — assumed (adjusted EPS) | G26: 28 | H26: 28 | N26: P / E (x) — assumed (adjusted EPS) | S26: 32 | T26: 32 | Z26: P / E (x) — assumed (adjusted EPS) | AD26: 22 | AE26: 22 | AF26: 22
B27: Price Target ($) | G27: =G26*G23 -> 400.81139 | H27: =H26*H23 -> 449.39102 | N27: Price Target ($) | S27: =S26*S23 -> 555.68056 | T27: =T26*T23 -> 640.91619 | Z27: Price Target ($) | AD27: =AD26*AD23 -> 225.84586 | AE27: =AE26*AE23 -> 252.1544 | AF27: =AF26*AF23 -> 275.88851
B28: Upside / (Downside) vs current | G28: =IFERROR(G27/$K$2-1,"") -> 0.24731249 | H28: =IFERROR(H27/$K$2-1,"") -> 0.39849075 | N28: Upside / (Downside) vs current | S28: =IFERROR(S27/$K$2-1,"") -> 0.72926047 | T28: =IFERROR(T27/$K$2-1,"") -> 0.99451108 | Z28: Upside / (Downside) vs current | AD28: =IFERROR(AD27/$K$2-1,"") -> -0.29717476 | AE28: =IFERROR(AE27/$K$2-1,"") -> -0.21530341 | AF28: =IFERROR(AF27/$K$2-1,"") -> -0.14144361
B29: IRR (to Dec-Y-1) | G29: =IFERROR((G27/$K$2)^(1/((DATE(2029-1,12,31)-$K$3)/365.25))-1,"") -> 0.10357577 | H29: =IFERROR((H27/$K$2)^(1/((DATE(2030-1,12,31)-$K$3)/365.25))-1,"") -> 0.10900694 | N29: IRR (to Dec-Y-1) | S29: =IFERROR((S27/$K$2)^(1/((DATE(2029-1,12,31)-$K$3)/365.25))-1,"") -> 0.27667036 | T29: =IFERROR((T27/$K$2)^(1/((DATE(2030-1,12,31)-$K$3)/365.25))-1,"") -> 0.23735979 | Z29: IRR (to Dec-Y-1) | AD29: =IFERROR((AD27/$K$2)^(1/((DATE(2028-1,12,31)-$K$3)/365.25))-1,"") -> -0.24748642 | AE29: =IFERROR((AE27/$K$2)^(1/((DATE(2029-1,12,31)-$K$3)/365.25))-1,"") -> -0.1024884 | AF29: =IFERROR((AF27/$K$2)^(1/((DATE(2030-1,12,31)-$K$3)/365.25))-1,"") -> -0.045955866
B31: Free Cash Flow | C31: =Model!BV271 -> 441.807 | D31: =Model!CA271 -> 406.42372 | E31: =Model!CB271 -> 569.26249 | F31: =Model!CC271 -> 629.81474 | G31: =Model!CD271 -> 708.23579 | H31: =Model!CE271 -> 775.89339 | I31: =IFERROR((H31/C31)^(1/5)-1,"n/m") -> 0.11921595 | N31: Free Cash Flow | O31: 441.807 | P31: 397.595 | Q31: 620.79597 | R31: 683.57433 | S31: 788.76271 | T31: 891.11926 | U31: 0.15064313 | Z31: Free Cash Flow | AA31: 441.807 | AB31: 415.25243 | AC31: 521.14716 | AD31: 568.18253 | AE31: 620.60553 | AF31: 659.02097 | AG31: 0.083261549
B32: FCF % | C32: =IFERROR(C31/C9,"") -> 0.073257991 | D32: =IFERROR(D31/D9,"") -> 0.061641412 | E32: =IFERROR(E31/E9,"") -> 0.078223282 | F32: =IFERROR(F31/F9,"") -> 0.079961127 | G32: =IFERROR(G31/G9,"") -> 0.083486184 | H32: =IFERROR(H31/H9,"") -> 0.085170453 | J32: =IFERROR(AVERAGE(Model!C273,Model!D273,Model!E273,Model!F273,Model!G273,Model!H273,Model!I273,Model!N273,Model!S273,Model!X273,Model!AC273,Model!AH273,Model!AM273,Model!AR273,Model!AW273,Model!BB273,Model!BG273,Model!BL273,Model!BQ273,Model!BV273),"") -> 0.047231357 | K32: =IFERROR(MIN(Model!C273,Model!D273,Model!E273,Model!F273,Model!G273,Model!H273,Model!I273,Model!N273,Model!S273,Model!X273,Model!AC273,Model!AH273,Model!AM273,Model!AR273,Model!AW273,Model!BB273,Model!BG273,Model!BL273,Model!BQ273,Model!BV273),"") -> 0.011686436 | L32: =IFERROR(MAX(Model!C273,Model!D273,Model!E273,Model!F273,Model!G273,Model!H273,Model!I273,Model!N273,Model!S273,Model!X273,Model!AC273,Model!AH273,Model!AM273,Model!AR273,Model!AW273,Model!BB273,Model!BG273,Model!BL273,Model!BQ273,Model!BV273),"") -> 0.079920043 | N32: FCF % | O32: 0.073257991 | P32: 0.06030238 | Q32: 0.082510984 | R32: 0.080669307 | S32: 0.083358899 | T32: 0.08484206 | V32: 0.047231357 | W32: 0.011686436 | X32: 0.079920043 | Z32: FCF % | AA32: 0.073257991 | AB32: 0.062980444 | AC32: 0.07412122 | AD32: 0.077954386 | AE32: 0.082380356 | AF32: 0.084740818 | AH32: 0.047231357 | AI32: 0.011686436 | AJ32: 0.079920043
B33: FCF / share ($) | C33: =IFERROR(C31/C21,"") -> 8.2248678 | D33: =IFERROR(D31/D21,"") -> 7.6785352 | E33: =IFERROR(E31/E21,"") -> 10.841446 | F33: =IFERROR(F31/F21,"") -> 12.253328 | G33: =IFERROR(G31/G21,"") -> 14.216674 | H33: =IFERROR(H31/H21,"") -> 16.096663 | N33: FCF / share ($) | O33: 8.2248678 | P33: 7.5172595 | Q33: 11.998772 | R33: 13.667876 | S33: 16.305307 | T33: 19.123779 | Z33: FCF / share ($) | AA33: 8.2248678 | AB33: 7.8395739 | AC33: 9.8612531 | AD33: 10.893496 | AE33: 12.216652 | AF33: 13.392729
B34: FCF Yield (on PT) | F34: =IFERROR(F33/F$27,"") | G34: =IFERROR(G33/G$27,"") -> 0.035469734 | H34: =IFERROR(H33/H$27,"") -> 0.035818835 | N34: FCF Yield (on PT) | R34: =IFERROR(R33/R$27,"") | S34: =IFERROR(S33/S$27,"") -> 0.02934295 | T34: =IFERROR(T33/T$27,"") -> 0.02983819 | Z34: FCF Yield (on PT) | AD34: =IFERROR(AD33/AD$27,"") -> 0.048234208 | AE34: =IFERROR(AE33/AE$27,"") -> 0.048449091 | AF34: =IFERROR(AF33/AF$27,"") -> 0.04854399
B35: Adjusted EBITDA — pro forma (2026E incl. ES&H / EnviroServe full year) | C35: =Model!BV196 -> 1169.939 | D35: =Model!CA196 -> 1437 | E35: =Model!CB196 -> 1550.1963 | F35: =Model!CC196 -> 1718.7809 | G35: =Model!CD196 -> 1876.8572 | H35: =Model!CE196 -> 2029.9644 | I35: =IFERROR((H35/C35)^(1/5)-1,"n/m") -> 0.11651624 | N35: Adjusted EBITDA — pro forma (2026E incl. ES&H / EnviroServe full year) | O35: 1169.939 | P35: 1467 | Q35: 1696.2154 | R35: 1942.7647 | S35: 2187.0327 | T35: 2433.9323 | U35: 0.15778803 | Z35: Adjusted EBITDA — pro forma (2026E incl. ES&H / EnviroServe full year) | AA35: 1169.939 | AB35: 1407 | AC35: 1408.9925 | AD35: 1506.4891 | AE35: 1587.8483 | AF35: 1659.5181 | AG35: 0.072417157
B36: Adjusted EBITDA (pro forma) % of revenues | C36: =IFERROR(C35/C9,"") -> 0.19399281 | D36: =IFERROR(D35/D9,"") -> 0.2179467 | E36: =IFERROR(E35/E9,"") -> 0.21301499 | F36: =IFERROR(F35/F9,"") -> 0.218216 | G36: =IFERROR(G35/G9,"") -> 0.2212422 | H36: =IFERROR(H35/H9,"") -> 0.22283086 | J36: =IFERROR(AVERAGE(Model!C233,Model!D233,Model!E233,Model!F233,Model!G233,Model!H233,Model!I233,Model!N233,Model!S233,Model!X233,Model!AC233,Model!AH233,Model!AM233,Model!AR233,Model!AW233,Model!BB233,Model!BG233,Model!BL233,Model!BQ233,Model!BV233),"") -> 0.16460537 | K36: =IFERROR(MIN(Model!C233,Model!D233,Model!E233,Model!F233,Model!G233,Model!H233,Model!I233,Model!N233,Model!S233,Model!X233,Model!AC233,Model!AH233,Model!AM233,Model!AR233,Model!AW233,Model!BB233,Model!BG233,Model!BL233,Model!BQ233,Model!BV233),"") -> 0.14076947 | L36: =IFERROR(MAX(Model!C233,Model!D233,Model!E233,Model!F233,Model!G233,Model!H233,Model!I233,Model!N233,Model!S233,Model!X233,Model!AC233,Model!AH233,Model!AM233,Model!AR233,Model!AW233,Model!BB233,Model!BG233,Model!BL233,Model!BQ233,Model!BV233),"") -> 0.19783359 | N36: Adjusted EBITDA (pro forma) % of revenues | O36: 0.19399281 | P36: 0.22249674 | Q36: 0.22544669 | R36: 0.22926765 | S36: 0.23113243 | T36: 0.23173086 | V36: 0.16460537 | W36: 0.14076947 | X36: 0.19783359 | Z36: Adjusted EBITDA (pro forma) % of revenues | AA36: 0.19399281 | AB36: 0.21339667 | AC36: 0.20039684 | AD36: 0.20668962 | AE36: 0.21077399 | AF36: 0.21339066 | AH36: 0.16460537 | AI36: 0.14076947 | AJ36: 0.19783359
B38: Net Debt | C38: =Model!BV419 -> 1822.485 | D38: =Model!CA419 -> 2710.3113 | E38: =Model!CB419 -> 2712.8436 | F38: =Model!CC419 -> 3007.8665 | G38: =Model!CD419 -> 3284.5001 | H38: =Model!CE419 -> 3552.4378 | N38: Net Debt | O38: 1822.485 | P38: 2769.14 | Q38: 3392.4307 | R38: 3885.5293 | S38: 4374.0654 | T38: 4867.8646 | Z38: Net Debt | AA38: 1822.485 | AB38: 2651.4826 | AC38: 2325.3354 | AD38: 2259.7337 | AE38: 2381.7724 | AF38: 2489.2771
B39: Net Debt / Adjusted EBITDA (x) | C39: =IFERROR(C38/C35,"") -> 1.5577607 | D39: =IFERROR(D38/D35,"") -> 1.88609 | E39: =IFERROR(E38/E35,"") -> 1.75 | F39: =IFERROR(F38/F35,"") -> 1.75 | G39: =IFERROR(G38/G35,"") -> 1.75 | H39: =IFERROR(H38/H35,"") -> 1.75 | N39: Net Debt / Adjusted EBITDA (x) | O39: 1.5577607 | P39: 1.887621 | Q39: 2 | R39: 2 | S39: 2 | T39: 2 | Z39: Net Debt / Adjusted EBITDA (x) | AA39: 1.5577607 | AB39: 1.8844937 | AC39: 1.6503532 | AD39: 1.5 | AE39: 1.5 | AF39: 1.5
B41: ROIC | C41: =Model!BV402 -> 0.11735446 | D41: =Model!CA402 -> 0.11361331 | E41: =Model!CB402 -> 0.11939476 | F41: =Model!CC402 -> 0.12661089 | G41: =Model!CD402 -> 0.13196332 | H41: =Model!CE402 -> 0.13617116 | J41: =IFERROR(AVERAGE(Model!C402,Model!D402,Model!E402,Model!F402,Model!G402,Model!H402,Model!I402,Model!N402,Model!S402,Model!X402,Model!AC402,Model!AH402,Model!AM402,Model!AR402,Model!AW402,Model!BB402,Model!BG402,Model!BL402,Model!BQ402,Model!BV402),"") -> 0.12472586 | K41: =IFERROR(MIN(Model!C402,Model!D402,Model!E402,Model!F402,Model!G402,Model!H402,Model!I402,Model!N402,Model!S402,Model!X402,Model!AC402,Model!AH402,Model!AM402,Model!AR402,Model!AW402,Model!BB402,Model!BG402,Model!BL402,Model!BQ402,Model!BV402),"") -> 0.028214374 | L41: =IFERROR(MAX(Model!C402,Model!D402,Model!E402,Model!F402,Model!G402,Model!H402,Model!I402,Model!N402,Model!S402,Model!X402,Model!AC402,Model!AH402,Model!AM402,Model!AR402,Model!AW402,Model!BB402,Model!BG402,Model!BL402,Model!BQ402,Model!BV402),"") -> 0.348056 | N41: ROIC | O41: 0.11735446 | P41: 0.11675899 | Q41: 0.12787876 | R41: 0.13377652 | S41: 0.13823142 | T41: 0.14188842 | V41: 0.12472586 | W41: 0.028214374 | X41: 0.348056 | Z41: ROIC | AA41: 0.11735446 | AB41: 0.11043445 | AC41: 0.11058591 | AD41: 0.11927362 | AE41: 0.12599745 | AF41: 0.13146393 | AH41: 0.12472586 | AI41: 0.028214374 | AJ41: 0.348056
B42: RONTA | C42: =Model!BV413 -> 0.12273926 | D42: =Model!CA413 -> 0.14381298 | E42: =Model!CB413 -> 0.1531507 | F42: =Model!CC413 -> 0.17302979 | G42: =Model!CD413 -> 0.18066215 | H42: =Model!CE413 -> 0.18647255 | J42: =IFERROR(AVERAGE(Model!C413,Model!D413,Model!E413,Model!F413,Model!G413,Model!H413,Model!I413,Model!N413,Model!S413,Model!X413,Model!AC413,Model!AH413,Model!AM413,Model!AR413,Model!AW413,Model!BB413,Model!BG413,Model!BL413,Model!BQ413,Model!BV413),"") -> 0.099873354 | K42: =IFERROR(MIN(Model!C413,Model!D413,Model!E413,Model!F413,Model!G413,Model!H413,Model!I413,Model!N413,Model!S413,Model!X413,Model!AC413,Model!AH413,Model!AM413,Model!AR413,Model!AW413,Model!BB413,Model!BG413,Model!BL413,Model!BQ413,Model!BV413),"") -> 0.030727346 | L42: =IFERROR(MAX(Model!C413,Model!D413,Model!E413,Model!F413,Model!G413,Model!H413,Model!I413,Model!N413,Model!S413,Model!X413,Model!AC413,Model!AH413,Model!AM413,Model!AR413,Model!AW413,Model!BB413,Model!BG413,Model!BL413,Model!BQ413,Model!BV413),"") -> 0.19140262 | N42: RONTA | O42: 0.12273926 | P42: 0.14947012 | Q42: 0.17689516 | R42: 0.18800765 | S42: 0.19642746 | T42: 0.20307544 | V42: 0.099873354 | W42: 0.030727346 | X42: 0.19140262 | Z42: RONTA | AA42: 0.12273926 | AB42: 0.13822348 | AC42: 0.12852533 | AD42: 0.13588886 | AE42: 0.14589328 | AF42: 0.15422849 | AH42: 0.099873354 | AI42: 0.030727346 | AJ42: 0.19140262
B44: Implied Market Cap (USDm) | F44: =F27*F21 -> 0 | G44: =G27*G21 -> 19967.327 | H44: =H27*H21 -> 21661.603 | N44: Implied Market Cap (USDm) | R44: =R27*R21 -> 0 | S44: =S27*S21 -> 26880.825 | T44: =T27*T21 -> 29865.057 | Z44: Implied Market Cap (USDm) | AD44: =AD27*AD21 -> 11779.659 | AE44: =AE27*AE21 -> 12809.436 | AF44: =AF27*AF21 -> 13575.748
B45: (+) Net Debt & NCI | F45: =F38+Model!CC325 -> 3007.8665 | G45: =G38+Model!CD325 -> 3284.5001 | H45: =H38+Model!CE325 -> 3552.4378 | N45: (+) Net Debt & NCI | R45: =R38+Model!CC325 -> 3885.5293 | S45: =S38+Model!CD325 -> 4374.0654 | T45: =T38+Model!CE325 -> 4867.8646 | Z45: (+) Net Debt & NCI | AD45: =AD38+Model!CC325 -> 2259.7337 | AE45: =AE38+Model!CD325 -> 2381.7724 | AF45: =AF38+Model!CE325 -> 2489.2771
B46: Implied Enterprise Value (USDm) | F46: =F44+F45 -> 3007.8665 | G46: =G44+G45 -> 23251.827 | H46: =H44+H45 -> 25214.041 | N46: Implied Enterprise Value (USDm) | R46: =R44+R45 -> 3885.5293 | S46: =S44+S45 -> 31254.89 | T46: =T44+T45 -> 34732.922 | Z46: Implied Enterprise Value (USDm) | AD46: =AD44+AD45 -> 14039.393 | AE46: =AE44+AE45 -> 15191.208 | AF46: =AF44+AF45 -> 16065.025
B47: Implied EV / Adjusted EBITDA (x) | F47: =IFERROR(F46/F35,"") -> 1.75 | G47: =IFERROR(G46/G35,"") -> 12.388703 | H47: =IFERROR(H46/H35,"") -> 12.420927 | N47: Implied EV / Adjusted EBITDA (x) | R47: =IFERROR(R46/R35,"") -> 2 | S47: =IFERROR(S46/S35,"") -> 14.291003 | T47: =IFERROR(T46/T35,"") -> 14.270291 | Z47: Implied EV / Adjusted EBITDA (x) | AD47: =IFERROR(AD46/AD35,"") -> 9.3192794 | AE47: =IFERROR(AE46/AE35,"") -> 9.5671662 | AF47: =IFERROR(AF46/AF35,"") -> 9.6805364

Sheet DCF
B2: DCF VALUATION — CLEAN HARBORS (CLH)
B4: 1. WACC BUILD
B5: Risk-free rate (US 10Y govt) | C5: 0.055 | D5: Assumption (~US 10Y Treasury yield), as in prior models; update to market
B6: Equity risk premium | C6: 0.05 | D6: US implied ERP ~4.5–5.5% (Damodaran)
B7: Levered beta | C7: 1.05 | D7: Environmental-services peers (Republic, Waste Management, Veolia, US Ecology pre-2022) ~0.8–1.2; CLH ~1.0–1.1 (industrial / energy exposure in SKSS & Industrial Services)
B8: Cost of equity | C8: =C5+C7*C6 -> 0.1075
B9: Pre-tax cost of debt | C9: 0.0625 | D9: BB+/Ba1-area credit; Sep-2026 $600m notes due 2034 priced at 6.25% (par); term loans SOFR + ~1.75%
B10: Tax rate | C10: 0.26 | D10: Model 2027E+ effective tax rate
B11: After-tax cost of debt | C11: =C9*(1-C10) -> 0.04625
B12: Target D/V | C12: 0.15 | D12: Net debt ~$2.9bn at YE2026E (post ES&H / EnviroServe) vs ~$17bn market cap ($321.34 × ~53m shares); ~2.0x pro forma leverage
B13: WACC | C13: =C8*(1-C12)+C11*C12 -> 0.0983125
B15: Valuation date (live) | C15: =TODAY() -> 46299 | D15: Periods = (Dec-31-Year − today) / 365.25; cash flows assumed at year-end
B16: 2. UNLEVERED FREE CASH FLOW BUILD (USDm)
D17: 2026E | E17: 2027E | F17: 2028E | G17: 2029E | H17: 2030E | I17: 2031E | J17: 2032E | K17: 2033E | L17: 2034E | M17: 2035E | N17: Terminal | P17: CAGR 26–30E | Q17: CAGR 26–35E
B18: Adjusted EBIT (Model; Adjusted EBITDA − DD&A) | D18: =Model!CA194 -> 905.46493 | E18: =Model!CB194 -> 1001.9145 | F18: =Model!CC194 -> 1123.6946 | G18: =Model!CD194 -> 1234.239 | H18: =Model!CE194 -> 1338.1947 | I18: =H18*(1+I$31) -> 1418.4864 | J18: =I18*(1+J$31) -> 1500.0494 | K18: =J18*(1+K$31) -> 1582.5521 | L18: =K18*(1+L$31) -> 1665.6361 | M18: =L18*(1+M$31) -> 1748.9179 | P18: =IFERROR(($H18/$D18)^(1/(VALUE(LEFT($H$17,4))-VALUE(LEFT($D$17,4))))-1,"n/m") -> 0.10258459 | Q18: =IFERROR(($M18/$D18)^(1/(VALUE(LEFT($M$17,4))-VALUE(LEFT($D$17,4))))-1,"n/m") -> 0.075886406
B19: y/y % | E19: =IFERROR(E18/D18-1,"") -> 0.10651943 | F19: =IFERROR(F18/E18-1,"") -> 0.12154735 | G19: =IFERROR(G18/F18-1,"") -> 0.098375874 | H19: =IFERROR(H18/G18-1,"") -> 0.084226537 | I19: =IFERROR(I18/H18-1,"") -> 0.06 | J19: =IFERROR(J18/I18-1,"") -> 0.0575 | K19: =IFERROR(K18/J18-1,"") -> 0.055 | L19: =IFERROR(L18/K18-1,"") -> 0.0525 | M19: =IFERROR(M18/L18-1,"") -> 0.05
B20: (−) Stock-based compensation & transaction costs (real costs added back in Adjusted EBITDA) | D20: =-(Model!CA162+N(Model!CA69)) -> -59.5 | E20: =-(Model!CB162+N(Model!CB69)) -> -54.580536 | F20: =-(Model!CC162+N(Model!CC69)) -> -59.073837 | G20: =-(Model!CD162+N(Model!CD69)) -> -63.624521 | H20: =-(Model!CE162+N(Model!CE69)) -> -68.324169 | I20: =H20*(1+I$31) -> -72.423619 | J20: =I20*(1+J$31) -> -76.587977 | K20: =J20*(1+K$31) -> -80.800316 | L20: =K20*(1+L$31) -> -85.042332 | M20: =L20*(1+M$31) -> -89.294449
B21: × (1 − tax rate) | D21: =1-$C$10 -> 0.74 | E21: =1-$C$10 -> 0.74 | F21: =1-$C$10 -> 0.74 | G21: =1-$C$10 -> 0.74 | H21: =1-$C$10 -> 0.74 | I21: =1-$C$10 -> 0.74 | J21: =1-$C$10 -> 0.74 | K21: =1-$C$10 -> 0.74 | ... M21: =1-$C$10 -> 0.74
B22: NOPAT = (Adjusted EBIT − SBC & transaction costs) × (1 − t) | D22: =(D18+D20)*D21 -> 626.01405 | E22: =(E18+E20)*E21 -> 701.02716 | F22: =(F18+F20)*F21 -> 787.81936 | G22: =(G18+G20)*G21 -> 866.25474 | H22: =(H18+H20)*H21 -> 939.70421 | I22: =(I18+I20)*I21 -> 996.08646 | J22: =(J18+J20)*J21 -> 1053.3614 | K22: =(K18+K20)*K21 -> 1111.2963 | ... M22: =(M18+M20)*M21 -> 1228.1213
B23: plus depreciation & amortization (total, incl. pending-deal purchase accounting) | D23: =Model!CA145 -> 489.07479 | E23: =Model!CB145 -> 548.2818 | F23: =Model!CC145 -> 595.08628 | G23: =Model!CD145 -> 642.61818 | H23: =Model!CE145 -> 691.76973 | I23: =H23*(1+I$31) -> 733.27592 | J23: =I23*(1+J$31) -> 775.43928 | K23: =J23*(1+K$31) -> 818.08844 | L23: =K23*(1+L$31) -> 861.03809 | M23: =L23*(1+M$31) -> 904.08999
B24: − Capex (PP&E) and acquisitions (M&A lever, 2027E+) | D24: =D29 -> -535 | E24: =E29+Model!CB253 -> -823.97315 | F24: =F29+Model!CC253 -> -867.10884 | G24: =G29+Model!CD253 -> -910.7954 | H24: =H29+Model!CE253 -> -955.91202 | I24: =I29 -> -695.26674 | J24: =J29 -> -735.24458 | K24: =K29 -> -775.68303 | L24: =L29 -> -816.40639 | M24: =M29 -> -857.22671
B25: − Δ Working capital (CF statement) | D25: =Model!CA249 -> -99.246227 | E25: =Model!CB249 -> -68.794501 | F25: =Model!CC249 -> -100.93444 | G25: =Model!CD249 -> -101.84186 | H25: =Model!CE249 -> -104.86992 | I25: =H25*(1+I$31) -> -111.16211 | J25: =I25*(1+J$31) -> -117.55393 | K25: =J25*(1+K$31) -> -124.0194 | L25: =K25*(1+L$31) -> -130.53042 | M25: =L25*(1+M$31) -> -137.05694
B26: Unlevered FCF | D26: =D22+D23+D24+D25 -> 480.84262 | E26: =E22+E23+E24+E25 -> 356.54132 | F26: =F22+F23+F24+F25 -> 414.86237 | G26: =G22+G23+G24+G25 -> 496.23566 | H26: =H22+H23+H24+H25 -> 570.692 | I26: =I22+I23+I24+I25 -> 922.93352 | J26: =J22+J23+J24+J25 -> 976.0022 | K26: =K22+K23+K24+K25 -> 1029.6823 | ... M26: =M22+M23+M24+M25 -> 1137.9277 | N26: =M26*(1+$C$32) -> 1183.4448 | P26: =IFERROR(($H26/$D26)^(1/(VALUE(LEFT($H$17,4))-VALUE(LEFT($D$17,4))))-1,"n/m") -> 0.043757739 | Q26: =IFERROR(($M26/$D26)^(1/(VALUE(LEFT($M$17,4))-VALUE(LEFT($D$17,4))))-1,"n/m") -> 0.10044405
B27: y/y % | E27: =IFERROR(E26/D26-1,"") -> -0.25850724 | F27: =IFERROR(F26/E26-1,"") -> 0.16357446 | G27: =IFERROR(G26/F26-1,"") -> 0.19614527 | H27: =IFERROR(H26/G26-1,"") -> 0.1500423 | I27: =IFERROR(I26/H26-1,"") -> 0.61721825 | J27: =IFERROR(J26/I26-1,"") -> 0.0575 | K27: =IFERROR(K26/J26-1,"") -> 0.055 | L27: =IFERROR(L26/K26-1,"") -> 0.0525 | M27: =IFERROR(M26/L26-1,"") -> 0.05
B28: Terminal Value (Gordon Growth) | N28: =N26/($C$13-$C$32) -> 20294.873
B29: memo: PP&E capex only (fade years carry no new acquisitions) | D29: =Model!CA251 -> -535 | E29: =Model!CB251 -> -523.97315 | F29: =Model!CC251 -> -567.10884 | G29: =Model!CD251 -> -610.7954 | H29: =Model!CE251 -> -655.91202 | I29: =H29*(1+I$31) -> -695.26674 | J29: =I29*(1+J$31) -> -735.24458 | K29: =J29*(1+K$31) -> -775.68303 | L29: =K29*(1+L$31) -> -816.40639 | M29: =L29*(1+M$31) -> -857.22671
B31: Fade-period growth (2031E–35E) | I31: 0.06 | J31: =I31+($M$31-$I$31)/(COLUMNS($I$31:$M$31)-1) -> 0.0575 | K31: =J31+($M$31-$I$31)/(COLUMNS($I$31:$M$31)-1) -> 0.055 | L31: =K31+($M$31-$I$31)/(COLUMNS($I$31:$M$31)-1) -> 0.0525 | M31: 0.05
B32: Terminal growth rate | C32: 0.04
B34: Discount period (years) | D34: =(DATE(2026,12,31)-$C$15)/365.25 -> 0.24093087 | E34: =(DATE(2027,12,31)-$C$15)/365.25 -> 1.2402464 | F34: =(DATE(2028,12,31)-$C$15)/365.25 -> 2.2422998 | G34: =(DATE(2029,12,31)-$C$15)/365.25 -> 3.2416153 | H34: =(DATE(2030,12,31)-$C$15)/365.25 -> 4.2409309 | I34: =(DATE(2031,12,31)-$C$15)/365.25 -> 5.2402464 | J34: =(DATE(2032,12,31)-$C$15)/365.25 -> 6.2422998 | K34: =(DATE(2033,12,31)-$C$15)/365.25 -> 7.2416153 | L34: =(DATE(2034,12,31)-$C$15)/365.25 -> 8.2409309 | M34: =(DATE(2035,12,31)-$C$15)/365.25 -> 9.2402464 | N34: =M34 -> 9.2402464
B35: Discount factor | D35: =1/(1+$C$13)^D34 -> 0.97766005 | E35: =1/(1+$C$13)^E34 -> 0.89020456 | F35: =1/(1+$C$13)^F34 -> 0.81036423 | G35: =1/(1+$C$13)^G34 -> 0.73787401 | H35: =1/(1+$C$13)^H34 -> 0.67186832 | I35: =1/(1+$C$13)^I34 -> 0.61176709 | J35: =1/(1+$C$13)^J34 -> 0.55689915 | K35: =1/(1+$C$13)^K34 -> 0.50708236 | ... N35: =1/(1+$C$13)^N34 -> 0.42041907
B36: PV of UFCF | D36: =D26*D35 -> 470.10061 | E36: =E26*E35 -> 317.39471 | F36: =F26*F35 -> 336.18963 | G36: =G26*G35 -> 366.1594 | H36: =H26*H35 -> 383.42987 | I36: =I26*I35 -> 564.62035 | J36: =J26*J35 -> 543.5348 | K36: =K26*K35 -> 522.13375 | ... M36: =M26*M35 -> 478.40649 | N36: =N28*N35 -> 8532.3516
D37: CLH's Adjusted EBITDA adds back stock-based compensation (from Q1/21) and transaction costs — both deducted here (row 20) to reach cash NOPAT. Adjusted EBIT deducts all D&A (row 23 adds it back). ES&H / EnviroServe cash consideration ($0.78bn) sits in 2026E acquisitions (row 24) and YE2026E net debt. Acquisition spend from the M&A lever is deducted in 2027E–30E; fade years carry no new acquisitions.
B39: Implied ROIC & incremental ROIC (USDm) | D39: =D17 -> 2026E | E39: =E17 -> 2027E | F39: =F17 -> 2028E | G39: =G17 -> 2029E | H39: =H17 -> 2030E | I39: =I17 -> 2031E | J39: =J17 -> 2032E | K39: =K17 -> 2033E | ... M39: =M17 -> 2035E | N39: Terminal
B40: NOPAT (row 22) | D40: =D22 -> 626.01405 | E40: =E22 -> 701.02716 | F40: =F22 -> 787.81936 | G40: =G22 -> 866.25474 | H40: =H22 -> 939.70421 | I40: =I22 -> 996.08646 | J40: =J22 -> 1053.3614 | K40: =K22 -> 1111.2963 | ... M40: =M22 -> 1228.1213 | N40: =M40*(1+$C$32) -> 1277.2462
B41: Net investment = NOPAT − UFCF | D41: =D40-D26 -> 145.17143 | E41: =E40-E26 -> 344.48584 | F41: =F40-F26 -> 372.95699 | G41: =G40-G26 -> 370.01908 | H41: =H40-H26 -> 369.0122 | I41: =I40-I26 -> 73.152937 | J41: =J40-J26 -> 77.359231 | K41: =K40-K26 -> 81.613988 | ... N41: =N40-N26 -> 93.801405
B42: Opening invested capital | D42: =Model!BV399-Model!CA253 -> 5730.738 | E42: =D43 -> 5875.9094 | F42: =E43 -> 6220.3953 | G42: =F43 -> 6593.3523 | H42: =G43 -> 6963.3714 | I42: =H43 -> 7332.3836 | J42: =I43 -> 7405.5365 | K42: =J43 -> 7482.8957 | L42: =K43 -> 7564.5097 | ... N42: =M43 -> 7740.6021
B43: Closing invested capital | D43: =D42+D41 -> 5875.9094 | E43: =E42+E41 -> 6220.3953 | F43: =F42+F41 -> 6593.3523 | G43: =G42+G41 -> 6963.3714 | H43: =H42+H41 -> 7332.3836 | I43: =I42+I41 -> 7405.5365 | J43: =J42+J41 -> 7482.8957 | K43: =K42+K41 -> 7564.5097 | ... M43: =M42+M41 -> 7740.6021
B44: Implied ROIC = NOPAT / opening IC | D44: =IFERROR(D40/D42,"") -> 0.10923795 | E44: =IFERROR(E40/E42,"") -> 0.1193053 | F44: =IFERROR(F40/F42,"") -> 0.12665101 | G44: =IFERROR(G40/G42,"") -> 0.13138305 | H44: =IFERROR(H40/H42,"") -> 0.1349496 | I44: =IFERROR(I40/I42,"") -> 0.13584757 | J44: =IFERROR(J40/J42,"") -> 0.14223972 | K44: =IFERROR(K40/K42,"") -> 0.14851153 | ... N44: =IFERROR(N40/N42,"") -> 0.16500605
B45: Reinvestment rate = net inv. / NOPAT | D45: =IFERROR(D41/D40,"") -> 0.23189804 | E45: =IFERROR(E41/E40,"") -> 0.49140157 | F45: =IFERROR(F41/F40,"") -> 0.4734042 | G45: =IFERROR(G41/G40,"") -> 0.42714812 | H45: =IFERROR(H41/H40,"") -> 0.39268974 | I45: =IFERROR(I41/I40,"") -> 0.073440349 | J45: =IFERROR(J41/J40,"") -> 0.073440349 | K45: =IFERROR(K41/K40,"") -> 0.073440349 | ... N45: =IFERROR(N41/N40,"") -> 0.073440349
B46: Incremental ROIC = Δ NOPAT / prior-yr net inv. | E46: =IFERROR((E40-D40)/D41,"") -> 0.5167209 | F46: =IFERROR((F40-E40)/E41,"") -> 0.25194707 | G46: =IFERROR((G40-F40)/F41,"") -> 0.21030677 | H46: =IFERROR((H40-G40)/G41,"") -> 0.19850183 | I46: =IFERROR((I40-H40)/H41,"") -> 0.15279238 | J46: =IFERROR((J40-I40)/I41,"") -> 0.78294835 | K46: =IFERROR((K40-J40)/J41,"") -> 0.74890712 | L46: =IFERROR((L40-K40)/K41,"") -> 0.71486589 | M46: =IFERROR((M40-L40)/L41,"") -> 0.68082465 | N46: =IFERROR($C$32/N45,"") -> 0.54465972
B47: Cumulative incremental ROIC 2026E–35E | C47: =IFERROR((M40-D40)/SUM(D41:L41),"") -> 0.31365138
D48: Opening IC = Model 2025A book IC (equity + net debt) + 2026E acquisitions (Depot Connect, Terra Nova, Western Oil, ES&H, EnviroServe), rolled forward with DCF net investment (capex + M&A − D&A + ΔWC). Terminal incremental ROIC = g ÷ reinvestment rate. Cumulative = (NOPAT 2035E − 2026E) / Σ net investment 2026E–34E.
B49: 3. VALUATION SUMMARY
B50: Sum of PV (explicit + fade) | C50: =SUM(D36:M36) -> 4482.3564
B51: PV of Terminal Value | C51: =N36 -> 8532.3516
B52: Enterprise Value | C52: =C50+C51 -> 13014.708
B53: Less: net debt (Model 2026E YE, post ES&H / EnviroServe; net of marketable securities) | C53: =Model!CA419 -> 2710.3113
B54: Less: non-controlling interests (Model 2026E) | C54: =Model!CA325 -> 0
B55: Equity Value | C55: =C52-C53-C54 -> 10304.397
B56: Diluted shares (m, Model 2026E period end) | C56: =Model!CA425 -> 52.840496
B57: Implied share price ($) | C57: =C55/C56 -> 195.00946
B58: Current share price ($) | C58: =Model!CA424 -> 321.34
B59: Implied upside / (downside) | C59: =C57/C58-1 -> -0.39313667
B60: Required discount to DCF value for target IRR (discount closes over horizon; value compounds at WACC) | C60: =1-((1+C13)/(1+F60))^F61 -> 0.12886742 | E60: Target IRR | F60: 0.15
B61: Max entry price for target IRR ($) — % vs. current share price shown right | C61: =C57*(1-C60) -> 169.8791 | D61: =C61/C58-1 -> -0.47134158 | E61: Years for discount to close | F61: 3
B64: 4. SENSITIVITY: IMPLIED PRICE ($) — WACC × Terminal Growth
B65: WACC step (across) | C65: 0.005
B66: Terminal growth step (down) | C66: 0.005
B67: g (down) / WACC | D67: =E67-$C$65 -> 0.0883125 | E67: =F67-$C$65 -> 0.0933125 | F67: =$C$13 -> 0.0983125 | G67: =F67+$C$65 -> 0.1033125 | H67: =G67+$C$65 -> 0.1083125
B68: =B69-$C$66 -> 0.03 | D68: =IFERROR((SUMPRODUCT($D$26:$M$26/(1+D$67)^$D$34:$M$34)+($M$26*(1+$B68)/(D$67-$B68))/(1+D$67)^$M$34-$C$53-$C$54)/$C$56,"") -> 211.62149 | E68: =IFERROR((SUMPRODUCT($D$26:$M$26/(1+E$67)^$D$34:$M$34)+($M$26*(1+$B68)/(E$67-$B68))/(1+E$67)^$M$34-$C$53-$C$54)/$C$56,"") -> 189.16497 | F68: =IFERROR((SUMPRODUCT($D$26:$M$26/(1+F$67)^$D$34:$M$34)+($M$26*(1+$B68)/(F$67-$B68))/(1+F$67)^$M$34-$C$53-$C$54)/$C$56,"") -> 170.04661 | G68: =IFERROR((SUMPRODUCT($D$26:$M$26/(1+G$67)^$D$34:$M$34)+($M$26*(1+$B68)/(G$67-$B68))/(1+G$67)^$M$34-$C$53-$C$54)/$C$56,"") -> 153.58193 | H68: =IFERROR((SUMPRODUCT($D$26:$M$26/(1+H$67)^$D$34:$M$34)+($M$26*(1+$B68)/(H$67-$B68))/(1+H$67)^$M$34-$C$53-$C$54)/$C$56,"") -> 139.26133
B69: =B70-$C$66 -> 0.035 | D69: =IFERROR((SUMPRODUCT($D$26:$M$26/(1+D$67)^$D$34:$M$34)+($M$26*(1+$B69)/(D$67-$B69))/(1+D$67)^$M$34-$C$53-$C$54)/$C$56,"") -> 228.86668 | E69: =IFERROR((SUMPRODUCT($D$26:$M$26/(1+E$67)^$D$34:$M$34)+($M$26*(1+$B69)/(E$67-$B69))/(1+E$67)^$M$34-$C$53-$C$54)/$C$56,"") -> 203.14809 | F69: =IFERROR((SUMPRODUCT($D$26:$M$26/(1+F$67)^$D$34:$M$34)+($M$26*(1+$B69)/(F$67-$B69))/(1+F$67)^$M$34-$C$53-$C$54)/$C$56,"") -> 181.54234 | G69: =IFERROR((SUMPRODUCT($D$26:$M$26/(1+G$67)^$D$34:$M$34)+($M$26*(1+$B69)/(G$67-$B69))/(1+G$67)^$M$34-$C$53-$C$54)/$C$56,"") -> 163.14491 | H69: =IFERROR((SUMPRODUCT($D$26:$M$26/(1+H$67)^$D$34:$M$34)+($M$26*(1+$B69)/(H$67-$B69))/(1+H$67)^$M$34-$C$53-$C$54)/$C$56,"") -> 147.29809
B70: =$C$32 -> 0.04 | D70: =IFERROR((SUMPRODUCT($D$26:$M$26/(1+D$67)^$D$34:$M$34)+($M$26*(1+$B70)/(D$67-$B70))/(1+D$67)^$M$34-$C$53-$C$54)/$C$56,"") -> 249.68139 | E70: =IFERROR((SUMPRODUCT($D$26:$M$26/(1+E$67)^$D$34:$M$34)+($M$26*(1+$B70)/(E$67-$B70))/(1+E$67)^$M$34-$C$53-$C$54)/$C$56,"") -> 219.75406 | F70: =IFERROR((SUMPRODUCT($D$26:$M$26/(1+F$67)^$D$34:$M$34)+($M$26*(1+$B70)/(F$67-$B70))/(1+F$67)^$M$34-$C$53-$C$54)/$C$56,"") -> 195.00946 | G70: =IFERROR((SUMPRODUCT($D$26:$M$26/(1+G$67)^$D$34:$M$34)+($M$26*(1+$B70)/(G$67-$B70))/(1+G$67)^$M$34-$C$53-$C$54)/$C$56,"") -> 174.21833 | H70: =IFERROR((SUMPRODUCT($D$26:$M$26/(1+H$67)^$D$34:$M$34)+($M$26*(1+$B70)/(H$67-$B70))/(1+H$67)^$M$34-$C$53-$C$54)/$C$56,"") -> 156.51132
B71: =B70+$C$66 -> 0.045 | D71: =IFERROR((SUMPRODUCT($D$26:$M$26/(1+D$67)^$D$34:$M$34)+($M$26*(1+$B71)/(D$67-$B71))/(1+D$67)^$M$34-$C$53-$C$54)/$C$56,"") -> 275.30181 | E71: =IFERROR((SUMPRODUCT($D$26:$M$26/(1+E$67)^$D$34:$M$34)+($M$26*(1+$B71)/(E$67-$B71))/(1+E$67)^$M$34-$C$53-$C$54)/$C$56,"") -> 239.79724 | F71: =IFERROR((SUMPRODUCT($D$26:$M$26/(1+F$67)^$D$34:$M$34)+($M$26*(1+$B71)/(F$67-$B71))/(1+F$67)^$M$34-$C$53-$C$54)/$C$56,"") -> 211.00266 | G71: =IFERROR((SUMPRODUCT($D$26:$M$26/(1+G$67)^$D$34:$M$34)+($M$26*(1+$B71)/(G$67-$B71))/(1+G$67)^$M$34-$C$53-$C$54)/$C$56,"") -> 187.19072 | H71: =IFERROR((SUMPRODUCT($D$26:$M$26/(1+H$67)^$D$34:$M$34)+($M$26*(1+$B71)/(H$67-$B71))/(1+H$67)^$M$34-$C$53-$C$54)/$C$56,"") -> 167.17974
B72: =B71+$C$66 -> 0.05 | D72: =IFERROR((SUMPRODUCT($D$26:$M$26/(1+D$67)^$D$34:$M$34)+($M$26*(1+$B72)/(D$67-$B72))/(1+D$67)^$M$34-$C$53-$C$54)/$C$56,"") -> 307.60944 | E72: =IFERROR((SUMPRODUCT($D$26:$M$26/(1+E$67)^$D$34:$M$34)+($M$26*(1+$B72)/(E$67-$B72))/(1+E$67)^$M$34-$C$53-$C$54)/$C$56,"") -> 264.46798 | F72: =IFERROR((SUMPRODUCT($D$26:$M$26/(1+F$67)^$D$34:$M$34)+($M$26*(1+$B72)/(F$67-$B72))/(1+F$67)^$M$34-$C$53-$C$54)/$C$56,"") -> 230.30623 | G72: =IFERROR((SUMPRODUCT($D$26:$M$26/(1+G$67)^$D$34:$M$34)+($M$26*(1+$B72)/(G$67-$B72))/(1+G$67)^$M$34-$C$53-$C$54)/$C$56,"") -> 202.59639 | H72: =IFERROR((SUMPRODUCT($D$26:$M$26/(1+H$67)^$D$34:$M$34)+($M$26*(1+$B72)/(H$67-$B72))/(1+H$67)^$M$34-$C$53-$C$54)/$C$56,"") -> 179.67769
B75: 5. REVERSE DCF
B76: To solve for the market-implied path: Data ▸ What-If Analysis ▸ Goal Seek — set C57 (implied price) to the current price (C58) by changing C32 (terminal growth) or the Model scenario levers (service-line growth, ES / SKSS margins, deal synergies, M&A spend).
B78: 6. MAUBOUSSIN EV / NOPAT — TWO-STAGE FRAMEWORK
B79: EV/NOPAT = 1/r + [g × (1 − r/ROIIC) / (r × (r − g))] × [1 − ((1+g)/(1+r))^N]
B80: Formula source: Mauboussin & Rappaport, "Expectations Investing" (2021); Counterpoint Global, "What Does a Price-Earnings Multiple Mean?" (2020).
B82: Input | C82: Value | D82: Rationale (Clean Harbors characteristics)
B83: r (Cost of capital / WACC) | C83: =$C$13 -> 0.0983125 | D83: Linked from Section 1 WACC build
B84: g (NOPAT growth, Stage 1) | C84: 0.08 | D84: Model Adjusted EBIT CAGR 2026–30E: mid/high-single-digit Technical Services pricing & volume, ES margin expansion, deal synergies; SKSS normalises after the 2026 base-oil spike → ~8% NOPAT growth
B85: ROIIC (Return on incremental invested capital) | C85: 0.14 | D85: Irreplaceable permitted disposal network (9 incinerators incl. Kimball, landfills, TSDFs) earns high returns on organic investment; bolt-on M&A at ~9–12x post-synergy EBITDA earns ~8–10% after tax
B86: N (Years of value creation / CAP) | C86: 12 | D86: RCRA permitting barriers (no new commercial hazardous-waste incinerator permitted in the U.S. in decades), national scale & route density, PFAS and reshoring tailwinds; SKSS re-refining is spread-exposed (commodity)
B88: Calculation | C88: Value
B89: Steady-state component: 1 / r | C89: =1/C83 -> 10.171647
B90: Value-creation factor: 1 − r / ROIIC | C90: =1-C83/C85 -> 0.29776786
B91: Growth multiplier: g × (1 − r/ROIIC) / (r × (r − g)) | C91: =C84*C90/(C83*(C83-C84)) -> 13.231571
B92: Time decay: 1 − ((1+g)/(1+r))^N | C92: =1-((1+C84)/(1+C83))^C86 -> 0.18271421
B93: PVGO component (growth value) | C93: =C91*C92 -> 2.4175961
B94: Mauboussin EV / NOPAT (steady-state + PVGO) | C94: =C89+C93 -> 12.589243
B96: VALUATION — Applied to 2028E NOPAT | C96: USDm
B97: 2028E Adjusted EBIT (Model) | C97: =Model!CC194 -> 1123.6946
B98: (−) 2028E stock-based compensation & transaction costs | C98: =-(Model!CC162+N(Model!CC69)) -> -59.073837
B99: Tax rate (from WACC build) | C99: =$C$10 -> 0.26
B100: 2028E NOPAT = (Adj. EBIT − SBC & transaction costs) × (1 − t) | C100: =(C97+C98)*(1-C99) -> 787.81936
B101: × Mauboussin EV/NOPAT multiple | C101: =C94 -> 12.589243
B102: Implied Enterprise Value (2028E basis) | C102: =C100*C101 -> 9918.0491
B103: Less: YE2027 net debt + NCI (Model) | C103: =Model!CB419+Model!CB325 -> 2712.8436
B104: Implied Equity Value | C104: =C102-C103 -> 7205.2055
B105: Diluted shares 2028E (m, Model) | C105: =Model!CC425 -> 50.7735
B106: Implied share price 2028 ($) | C106: =C104/C105 -> 141.90878
B108: Current share price ($) | C108: =C58 -> 321.34
B109: Implied upside / (downside) | C109: =C106/C108-1 -> -0.55838432
B111: MARKET-IMPLIED EV/NOPAT TODAY | C111: USDm
B112: Current market cap (spot × diluted shares) | C112: =C58*C56 -> 16979.765
B113: Plus: YE2026 net debt & NCI | C113: =C53+C54 -> 2710.3113
B114: Implied Enterprise Value (today) | C114: =C112+C113 -> 19690.076
B115: CLH's market-implied EV/NOPAT (on 2028E NOPAT) | C115: =C114/C100 -> 24.993136
B117: Multiple gap (Mauboussin − Market) | C117: =C94-C115 -> -12.403893
...

Sheet Charts
B2: Clean Harbors — Historical Operating Performance (2006–2025)
B3: All historicals · USDm · Linked to Model. Growth = revenues and Adjusted EBITDA y/y (as reported; Adjusted EBITDA as published by period — SBC added back from 2021). Returns on Adjusted EBIT (NOPAT) / book invested capital; net debt net of marketable securities.
C7: 2006 | D7: 2007 | E7: 2008 | F7: 2009 | G7: 2010 | H7: 2011 | I7: 2012 | J7: 2013 | K7: 2014 | L7: 2015 | M7: 2016 | N7: 2017 | O7: 2018 | P7: 2019 | Q7: 2020 | R7: 2021 | S7: 2022 | T7: 2023 | U7: 2024 | V7: 2025
B8: Revenues y/y % | C8: =IFERROR(Model!C225+0,0) -> 0 | D8: =IFERROR(Model!D225+0,0) -> 0.14112645 | E8: =IFERROR(Model!E225+0,0) -> 0.0884935 | F8: =IFERROR(Model!F225+0,0) -> 0.042210586 | G8: =IFERROR(Model!G225+0,0) -> 0.6116289 | H8: =IFERROR(Model!H225+0,0) -> 0.14607531 | I8: =IFERROR(Model!I225+0,0) -> 0.10270062 | J8: =IFERROR(Model!N225+0,0) -> 0.60411498 | K8: =IFERROR(Model!S225+0,0) -> -0.030777945 | L8: =IFERROR(Model!X225+0,0) -> -0.037187694 | M8: =IFERROR(Model!AC225+0,0) -> -0.15874481 | N8: =IFERROR(Model!AH225+0,0) -> 0.06886985 | O8: =IFERROR(Model!AM225+0,0) -> 0.12065455 | P8: =IFERROR(Model!AR225+0,0) -> 0.033902039 | Q8: =IFERROR(Model!AW225+0,0) -> -0.078569189 | R8: =IFERROR(Model!BB225+0,0) -> 0.21038441 | S8: =IFERROR(Model!BG225+0,0) -> 0.3576443 | T8: =IFERROR(Model!BL225+0,0) -> 0.046945141 | U8: =IFERROR(Model!BQ225+0,0) -> 0.088886391 | V8: =IFERROR(Model!BV225+0,0) -> 0.02391955
B9: Adjusted EBITDA y/y % | C9: =IFERROR(Model!C228+0,0) -> 0 | D9: =IFERROR(Model!D228+0,0) -> 0.11141035 | E9: =IFERROR(Model!E228+0,0) -> 0.22447617 | F9: =IFERROR(Model!F228+0,0) -> -0.034548674 | G9: =IFERROR(Model!G228+0,0) -> 0.99703008 | H9: =IFERROR(Model!H228+0,0) -> 0.11222402 | I9: =IFERROR(Model!I228+0,0) -> 0.067881306 | J9: =IFERROR(Model!N228+0,0) -> 0.36476736 | K9: =IFERROR(Model!S228+0,0) -> 0.023159938 | L9: =IFERROR(Model!X228+0,0) -> -0.034012941 | M9: =IFERROR(Model!AC228+0,0) -> -0.20590995 | N9: =IFERROR(Model!AH228+0,0) -> 0.063201567 | O9: =IFERROR(Model!AM228+0,0) -> 0.15352267 | P9: =IFERROR(Model!AR228+0,0) -> 0.10043075 | Q9: =IFERROR(Model!AW228+0,0) -> 0.027733719 | R9: =IFERROR(Model!BB228+0,0) -> 0.2184469 | S9: =IFERROR(Model!BG228+0,0) -> 0.51066943 | T9: =IFERROR(Model!BL228+0,0) -> -0.0093510793 | U9: =IFERROR(Model!BQ228+0,0) -> 0.10306843 | V9: =IFERROR(Model!BV228+0,0) -> 0.047455803
C11: =C7 -> 2006 | D11: =D7 -> 2007 | E11: =E7 -> 2008 | F11: =F7 -> 2009 | G11: =G7 -> 2010 | H11: =H7 -> 2011 | I11: =I7 -> 2012 | J11: =J7 -> 2013 | ... V11: =V7 -> 2025
B12: Adjusted EBITDA | C12: =Model!C187 -> 119.935 | D12: =Model!D187 -> 133.297 | E12: =Model!E187 -> 163.219 | F12: =Model!F187 -> 157.58 | G12: =Model!G187 -> 314.692 | H12: =Model!H187 -> 350.008 | I12: =Model!I187 -> 373.767 | J12: =Model!N187 -> 510.105 | K12: =Model!S187 -> 521.919 | L12: =Model!X187 -> 504.167 | M12: =Model!AC187 -> 400.354 | N12: =Model!AH187 -> 425.657 | O12: =Model!AM187 -> 491.005 | P12: =Model!AR187 -> 540.317 | Q12: =Model!AW187 -> 555.302 | R12: =Model!BB187 -> 676.606 | S12: =Model!BG187 -> 1022.128 | T12: =Model!BL187 -> 1012.57 | U12: =Model!BQ187 -> 1116.934 | V12: =Model!BV187 -> 1169.939
B13: Income from Operations (GAAP) | C13: =Model!C147 -> 74.376 | D13: =Model!D147 -> 85.26 | E13: =Model!E147 -> 107.972 | F13: =Model!F147 -> 82.065 | G13: =Model!G147 -> 211.912 | H13: =Model!H147 -> 217.665 | I13: =Model!I147 -> 202.204 | J13: =Model!N147 -> 220.556 | K13: =Model!S147 -> 111.81 | L13: =Model!X147 -> 187.579 | M13: =Model!AC147 -> 69.162 | N13: =Model!AH147 -> 127.775 | O13: =Model!AM147 -> 182.574 | P13: =Model!AR147 -> 229.456 | Q13: =Model!AW147 -> 251.336 | R13: =Model!BB147 -> 347.887 | S13: =Model!BG147 -> 634.747 | T13: =Model!BL147 -> 612.439 | U13: =Model!BQ147 -> 670.232 | V13: =Model!BV147 -> 673.372
B14: Adj. EBITDA Margin % | C14: =Model!C233 -> 0.14453326 | D14: =Model!D233 -> 0.14076947 | E14: =Model!E233 -> 0.15835543 | F14: =Model!F233 -> 0.14669248 | G14: =Model!G233 -> 0.18177218 | H14: =Model!H233 -> 0.17640323 | I14: =Model!I233 -> 0.17083305 | J14: =Model!N233 -> 0.1453433 | K14: =Model!S233 -> 0.15343176 | L14: =Model!X233 -> 0.15393768 | M14: =Model!AC233 -> 0.14530714 | N14: =Model!AH233 -> 0.14453656 | O14: =Model!AM233 -> 0.14877573 | P14: =Model!AR233 -> 0.15834904 | Q14: =Model!AW233 -> 0.17661732 | R14: =Model!BB233 -> 0.17779379 | S14: =Model!BG233 -> 0.19783359 | T14: =Model!BL233 -> 0.1871957 | U14: =Model!BQ233 -> 0.1896338 | V14: =Model!BV233 -> 0.19399281
B15: GAAP Op. Margin % | C15: =Model!C235 -> 0.089630264 | D15: =Model!D235 -> 0.090039571 | E15: =Model!E235 -> 0.10475467 | F15: =Model!F235 -> 0.076394966 | G15: =Model!G235 -> 0.12240447 | H15: =Model!H235 -> 0.10970266 | I15: =Model!I235 -> 0.092418877 | J15: =Model!N235 -> 0.062842626 | K15: =Model!S235 -> 0.032869478 | L15: =Model!X235 -> 0.057273635 | M15: =Model!AC235 -> 0.025102115 | N15: =Model!AH235 -> 0.043387421 | O15: =Model!AM235 -> 0.055320375 | P15: =Model!AR235 -> 0.067245962 | Q15: =Model!AW235 -> 0.07993901 | R15: =Model!BB235 -> 0.091415311 | S15: =Model!BG235 -> 0.12285572 | T15: =Model!BL235 -> 0.11322274 | U15: =Model!BQ235 -> 0.11379244 | V15: =Model!BV235 -> 0.11165482
C17: =C7 -> 2006 | D17: =D7 -> 2007 | E17: =E7 -> 2008 | F17: =F7 -> 2009 | G17: =G7 -> 2010 | H17: =H7 -> 2011 | I17: =I7 -> 2012 | J17: =J7 -> 2013 | ... V17: =V7 -> 2025
B18: ROIC | C18: =IFERROR(Model!C402+0,NA()) -> 0.348056 | D18: =IFERROR(Model!D402+0,NA()) -> 0.28426949 | E18: =IFERROR(Model!E402+0,NA()) -> 0.3117853 | F18: =IFERROR(Model!F402+0,NA()) -> 0.08184106 | G18: =IFERROR(Model!G402+0,NA()) -> 0.20398113 | H18: =IFERROR(Model!H402+0,NA()) -> 0.13286358 | I18: =IFERROR(Model!I402+0,NA()) -> 0.081634326 | J18: =IFERROR(Model!N402+0,NA()) -> 0.063836969 | K18: =IFERROR(Model!S402+0,NA()) -> 0.061165203 | L18: =IFERROR(Model!X402+0,NA()) -> 0.060146802 | M18: =IFERROR(Model!AC402+0,NA()) -> 0.028214374 | N18: =IFERROR(Model!AH402+0,NA()) -> 0.055782935 | O18: =IFERROR(Model!AM402+0,NA()) -> 0.054262216 | P18: =IFERROR(Model!AR402+0,NA()) -> 0.065357612 | Q18: =IFERROR(Model!AW402+0,NA()) -> 0.087074635 | R18: =IFERROR(Model!BB402+0,NA()) -> 0.081158073 | S18: =IFERROR(Model!BG402+0,NA()) -> 0.13612042 | T18: =IFERROR(Model!BL402+0,NA()) -> 0.12145201 | U18: =IFERROR(Model!BQ402+0,NA()) -> 0.11816053 | V18: =IFERROR(Model!BV402+0,NA()) -> 0.11735446
B19: RONTA | C19: =IFERROR(Model!C413+0,NA()) -> 0.19140262 | D19: =IFERROR(Model!D413+0,NA()) -> 0.12622679 | E19: =IFERROR(Model!E413+0,NA()) -> 0.11696436 | F19: =IFERROR(Model!F413+0,NA()) -> 0.055642697 | G19: =IFERROR(Model!G413+0,NA()) -> 0.13621274 | H19: =IFERROR(Model!H413+0,NA()) -> 0.10801064 | I19: =IFERROR(Model!I413+0,NA()) -> 0.10123861 | J19: =IFERROR(Model!N413+0,NA()) -> 0.075032611 | K19: =IFERROR(Model!S413+0,NA()) -> 0.068618353 | L19: =IFERROR(Model!X413+0,NA()) -> 0.070602159 | M19: =IFERROR(Model!AC413+0,NA()) -> 0.030727346 | N19: =IFERROR(Model!AH413+0,NA()) -> 0.060747589 | O19: =IFERROR(Model!AM413+0,NA()) -> 0.061094499 | P19: =IFERROR(Model!AR413+0,NA()) -> 0.064419249 | Q19: =IFERROR(Model!AW413+0,NA()) -> 0.078280701 | R19: =IFERROR(Model!BB413+0,NA()) -> 0.099236177 | S19: =IFERROR(Model!BG413+0,NA()) -> 0.15874725 | T19: =IFERROR(Model!BL413+0,NA()) -> 0.14015724 | U19: =IFERROR(Model!BQ413+0,NA()) -> 0.1313662 | V19: =IFERROR(Model!BV413+0,NA()) -> 0.12273926
B20: Adj. EBITDA margin % | C20: =IFERROR(Model!C233+0,NA()) -> 0.14453326 | D20: =IFERROR(Model!D233+0,NA()) -> 0.14076947 | E20: =IFERROR(Model!E233+0,NA()) -> 0.15835543 | F20: =IFERROR(Model!F233+0,NA()) -> 0.14669248 | G20: =IFERROR(Model!G233+0,NA()) -> 0.18177218 | H20: =IFERROR(Model!H233+0,NA()) -> 0.17640323 | I20: =IFERROR(Model!I233+0,NA()) -> 0.17083305 | J20: =IFERROR(Model!N233+0,NA()) -> 0.1453433 | K20: =IFERROR(Model!S233+0,NA()) -> 0.15343176 | L20: =IFERROR(Model!X233+0,NA()) -> 0.15393768 | M20: =IFERROR(Model!AC233+0,NA()) -> 0.14530714 | N20: =IFERROR(Model!AH233+0,NA()) -> 0.14453656 | O20: =IFERROR(Model!AM233+0,NA()) -> 0.14877573 | P20: =IFERROR(Model!AR233+0,NA()) -> 0.15834904 | Q20: =IFERROR(Model!AW233+0,NA()) -> 0.17661732 | R20: =IFERROR(Model!BB233+0,NA()) -> 0.17779379 | S20: =IFERROR(Model!BG233+0,NA()) -> 0.19783359 | T20: =IFERROR(Model!BL233+0,NA()) -> 0.1871957 | U20: =IFERROR(Model!BQ233+0,NA()) -> 0.1896338 | V20: =IFERROR(Model!BV233+0,NA()) -> 0.19399281
B21: FCF margin % | C21: =IFERROR(Model!C273+0,NA()) -> 0.024962371 | D21: =IFERROR(Model!D273+0,NA()) -> 0.045903706 | E21: =IFERROR(Model!E273+0,NA()) -> 0.050574699 | F21: =IFERROR(Model!F273+0,NA()) -> 0.028882352 | G21: =IFERROR(Model!G273+0,NA()) -> 0.062185342 | H21: =IFERROR(Model!H273+0,NA()) -> 0.015633001 | I21: =IFERROR(Model!I273+0,NA()) -> 0.058031691 | J21: =IFERROR(Model!N273+0,NA()) -> 0.038645383 | K21: =IFERROR(Model!S273+0,NA()) -> 0.011686436 | L21: =IFERROR(Model!X273+0,NA()) -> 0.04249807 | M21: =IFERROR(Model!AC273+0,NA()) -> 0.014604973 | N21: =IFERROR(Model!AH273+0,NA()) -> 0.040302848 | O21: =IFERROR(Model!AM273+0,NA()) -> 0.054499844 | P21: =IFERROR(Model!AR273+0,NA()) -> 0.057695498 | Q21: =IFERROR(Model!AW273+0,NA()) -> 0.074533642 | R21: =IFERROR(Model!BB273+0,NA()) -> 0.079920043 | S21: =IFERROR(Model!BG273+0,NA()) -> 0.054418327 | T21: =IFERROR(Model!BL273+0,NA()) -> 0.057726609 | U21: =IFERROR(Model!BQ273+0,NA()) -> 0.058664315 | V21: =IFERROR(Model!BV273+0,NA()) -> 0.073257991
