Workbook

Sheet Cover
B2: COPART, INC.
B3: SEC-Filings 3-Statement Financial Model — 15-Year History + 5-Year Forecast
B5: Ticker / Exchange | C5: CPRT · Nasdaq
B6: SEC CIK | C6: 0000900075
B7: Fiscal year end | C7: July 31
B8: Currency / units | C8: US$ millions (except per-share and share counts)
B9: Data source | C9: SEC EDGAR — Forms 10-K & 10-Q, XBRL (data.sec.gov). No non-SEC inputs except the manual valuation share price.
B10: Reported segments | C10: United States · International
B11: Historical coverage | C11: FY2011–FY2025 (fiscal-year ends + Q1–Q4)
B12: Forecast | C12: FY2026E–FY2030E (driver-based, scenario toggle)
B14: Worksheets
B15: Model | C15: Full model — segment P&L, income statement, cash flow, balance sheet, ratios, non-GAAP reconciliation (8-K), valuation; historicals (formulas) + FY26E–30E estimates.
B16: Bull / Base / Bear | C16: Scenario P&L summary linked to the Model scenario toggle.
B17: DCF | C17: Unlevered DCF built off the model's forecast free cash flow.
B19: Colour key: blue = as-reported figure taken directly from Copart's SEC filings; black = live Excel formula; pale-yellow columns = forecast years driven by the Assumptions / scenario table on the Model tab. Segment operating income is reported by Copart from ~FY2016 (two reportable segments); earlier years reflect geographic revenue disclosure as filed. For research/education only — not investment advice.

Sheet Model
B2: COPART, INC. (CPRT) — SEC-Filings 3-Statement Model | CE2: Scenario: | CF2: Base
B3: US GAAP as reported · US$ millions · FYE July 31 · Source: SEC EDGAR Forms 10-K & 10-Q (data.sec.gov XBRL), CIK 0000900075
B4: Blue = as-reported input from SEC filings · Black = formula · Yellow columns = forecast (driven by Assumptions / scenario toggle).
CK5: SCENARIO / ASSUMPTIONS TABLE
B6: (US$ in millions) | C6: Q1 11 | D6: Q2 11 | E6: Q3 11 | F6: Q4 11 | G6: FY2011 | H6: Q1 12 | I6: Q2 12 | J6: Q3 12 | K6: Q4 12 | L6: FY2012 | M6: Q1 13 | N6: Q2 13 | O6: Q3 13 | P6: Q4 13 | Q6: FY2013 | R6: Q1 14 | S6: Q2 14 | T6: Q3 14 | U6: Q4 14 | V6: FY2014 | W6: Q1 15 | X6: Q2 15 | Y6: Q3 15 | Z6: Q4 15 | AA6: FY2015 | AB6: Q1 16 | AC6: Q2 16 | AD6: Q3 16 | AE6: Q4 16 | AF6: FY2016 | AG6: Q1 17 | AH6: Q2 17 | AI6: Q3 17 | AJ6: Q4 17 | AK6: FY2017 | AL6: Q1 18 | AM6: Q2 18 | AN6: Q3 18 | AO6: Q4 18 | AP6: FY2018 | AQ6: Q1 19 | AR6: Q2 19 | AS6: Q3 19 | AT6: Q4 19 | AU6: FY2019 | AV6: Q1 20 | AW6: Q2 20 | AX6: Q3 20 | AY6: Q4 20 | AZ6: FY2020 | BA6: Q1 21 | BB6: Q2 21 | BC6: Q3 21 | BD6: Q4 21 | BE6: FY2021 | BF6: Q1 22 | BG6: Q2 22 | BH6: Q3 22 | BI6: Q4 22 | BJ6: FY2022 | BK6: Q1 23 | BL6: Q2 23 | BM6: Q3 23 | BN6: Q4 23 | BO6: FY2023 | BP6: Q1 24 | BQ6: Q2 24 | BR6: Q3 24 | BS6: Q4 24 | BT6: FY2024 | BU6: Q1 25 | BV6: Q2 25 | BW6: Q3 25 | BX6: Q4 25 | BY6: FY2025 | BZ6: FY2026E | CA6: FY2027E | CB6: FY2028E | CC6: FY2029E | CD6: FY2030E | CE6: Modelling Notes | CF6: 5Y CAGR (fwd) | CG6: 5Y CAGR (hist) | CH6: 10Y CAGR | CK6: Driver | CL6: Bull | CM6: Base | CN6: Bear
CK7: Revenue growth — US | CL7: 0.14 | CM7: 0.1 | CN7: 0.04
B8: SEGMENT P&L — BY REPORTABLE SEGMENT (US & INTERNATIONAL) | CK8: Revenue growth — International | CL8: 0.16 | CM8: 0.11 | CN8: 0.04
B9: United States | CK9: Operating margin — US | CL9: 0.4 | CM9: 0.385 | CN9: 0.35
B10: Revenue | L10: 724.869 | Q10: 826.03 | V10: 904 | AA10: 914.443 | AF10: 1016.036 | AG10: 285.062 | AH10: 286.911 | AI10: 307.12 | AJ10: 314.095 | AK10: 1193.188 | AL10: 351.105 | AM10: 385.135 | AN10: 385.281 | AO10: 369.501 | AP10: 1491.022 | AQ10: 371.209 | AR10: 390.072 | AS10: 448.199 | AT10: 447.089 | AU10: 1656.569 | AV10: 464.164 | AW10: 482.737 | AX10: 467.198 | AY10: 446.587 | AZ10: 1860.686 | BA10: 497.255 | BB10: 517.923 | BC10: 621.953 | BD10: 634.941 | BE10: 2272.072 | BF10: 678.461 | BG10: 727.386 | BH10: 790.25 | BI10: 749.053 | BJ10: 2945.15 | BK10: 748.849 | BL10: 787.929 | BM10: 833.758 | BN10: 819.112 | BO10: 3189.648 | BP10: 840.906 | BQ10: 830.726 | BR10: 918.916 | BS10: 874.187 | BT10: 3464.735 | BU10: 947.539 | BV10: 974.845 | BW10: 1006.457 | BX10: 926.263 | BY10: 3855.104 | BZ10: =BY10*(1+CHOOSE(MATCH($CF$2,{"Bull","Base","Bear"},0),$CL$7,$CM$7,$CN$7)) | CA10: =BZ10*(1+CHOOSE(MATCH($CF$2,{"Bull","Base","Bear"},0),$CL$7,$CM$7,$CN$7)) | CB10: =CA10*(1+CHOOSE(MATCH($CF$2,{"Bull","Base","Bear"},0),$CL$7,$CM$7,$CN$7)) | CC10: =CB10*(1+CHOOSE(MATCH($CF$2,{"Bull","Base","Bear"},0),$CL$7,$CM$7,$CN$7)) | CD10: =CC10*(1+CHOOSE(MATCH($CF$2,{"Bull","Base","Bear"},0),$CL$7,$CM$7,$CN$7)) | CF10: =IFERROR((CD10/BY10)^(1/5)-1,"n/m") | CG10: =IFERROR((BY10/AZ10)^(1/5)-1,"n/m") | CH10: =IFERROR((BY10/G10)^(1/14)-1,"n/m") | CK10: Operating margin — International | CL10: 0.3 | CM10: 0.27 | CN10: 0.22
B11: Operating income | AF11: 347.709 | AG11: 88.982 | AH11: 93.592 | AI11: 119.117 | AJ11: 94.669 | AK11: 396.36 | AL11: 106.019 | AM11: 133.01 | AN11: 150.888 | AO11: 124.97 | AP11: 514.887 | AQ11: 130.292 | AR11: 145.402 | AS11: 188.258 | AT11: 176.842 | AU11: 640.794 | AV11: 189.05 | AW11: 190.085 | AX11: 180.687 | AY11: 188.955 | AZ11: 748.777 | BA11: 223.239 | BB11: 229.452 | BC11: 296.726 | BD11: 274.138 | BE11: 1023.555 | BF11: 294.949 | BG11: 312.646 | BH11: 340.437 | BI11: 299.537 | BJ11: 1247.569 | BK11: 282.628 | BL11: 336.164 | BM11: 384.791 | BN11: 364.514 | BO11: 1368.097 | BP11: 362.291 | BQ11: 347.338 | BR11: 392.931 | BS11: 325.474 | BT11: 1428.034 | BU11: 355.059 | BV11: 375.893 | BW11: 392.465 | BX11: 357.469 | BY11: 1480.886 | BZ11: =BZ10*CHOOSE(MATCH($CF$2,{"Bull","Base","Bear"},0),$CL$9,$CM$9,$CN$9) | CA11: =CA10*CHOOSE(MATCH($CF$2,{"Bull","Base","Bear"},0),$CL$9,$CM$9,$CN$9) | CB11: =CB10*CHOOSE(MATCH($CF$2,{"Bull","Base","Bear"},0),$CL$9,$CM$9,$CN$9) | CC11: =CC10*CHOOSE(MATCH($CF$2,{"Bull","Base","Bear"},0),$CL$9,$CM$9,$CN$9) | CD11: =CD10*CHOOSE(MATCH($CF$2,{"Bull","Base","Bear"},0),$CL$9,$CM$9,$CN$9) | CF11: =IFERROR((CD11/BY11)^(1/5)-1,"n/m") | CG11: =IFERROR((BY11/AZ11)^(1/5)-1,"n/m") | CH11: =IFERROR((BY11/G11)^(1/14)-1,"n/m") | CK11: Other income % of revenue | CL11: 0.02 | CM11: 0.015 | CN11: 0.01
B12: Operating margin % | C12: =IFERROR(C11/C10,"") | D12: =IFERROR(D11/D10,"") | E12: =IFERROR(E11/E10,"") | F12: =IFERROR(F11/F10,"") | G12: =IFERROR(G11/G10,"") | H12: =IFERROR(H11/H10,"") | I12: =IFERROR(I11/I10,"") | J12: =IFERROR(J11/J10,"") | ... CD12: =IFERROR(CD11/CD10,"") | CK12: Effective tax rate | CL12: 0.22 | CM12: 0.23 | CN12: 0.25
B13: Revenue y/y % | L13: =IFERROR(L10/G10-1,"") | Q13: =IFERROR(Q10/L10-1,"") | V13: =IFERROR(V10/Q10-1,"") | AA13: =IFERROR(AA10/V10-1,"") | AF13: =IFERROR(AF10/AA10-1,"") | AK13: =IFERROR(AK10/AF10-1,"") | AP13: =IFERROR(AP10/AK10-1,"") | AU13: =IFERROR(AU10/AP10-1,"") | AZ13: =IFERROR(AZ10/AU10-1,"") | BE13: =IFERROR(BE10/AZ10-1,"") | BJ13: =IFERROR(BJ10/BE10-1,"") | BO13: =IFERROR(BO10/BJ10-1,"") | BT13: =IFERROR(BT10/BO10-1,"") | BY13: =IFERROR(BY10/BT10-1,"") | BZ13: =IFERROR(BZ10/BY10-1,"") | CA13: =IFERROR(CA10/BZ10-1,"") | CB13: =IFERROR(CB10/CA10-1,"") | CC13: =IFERROR(CC10/CB10-1,"") | CD13: =IFERROR(CD10/CC10-1,"") | CK13: D&A % of revenue | CL13: 0.045 | CM13: 0.05 | CN13: 0.055
B14: Depreciation & amortisation | AF14: 39.083 | AG14: 12.386 | AH14: 12.667 | AI14: 10.904 | AJ14: 11.55 | AK14: 47.507 | AL14: 13.529 | AM14: 14.054 | AN14: 14.189 | AO14: 26.007 | AP14: 67.779 | AQ14: 19.392 | AR14: 17.877 | AS14: 18.636 | AT14: 19.23 | AU14: 75.135 | AV14: 20.567 | AW14: 21.698 | AX14: 23.703 | AY14: 24.667 | AZ14: 90.635 | BA14: 26.105 | BB14: 27.745 | BC14: 28.161 | BD14: 25.754 | BE14: 107.765 | BF14: 27.725 | BG14: 29.316 | BH14: 31.609 | BI14: 31.985 | BJ14: 120.635 | BK14: 34.935 | BL14: 34.121 | BM14: 32.918 | BN14: 33.83 | BO14: 135.804 | BP14: 36.936 | BQ14: 38.344 | BR14: 43.477 | BS14: 42.928 | BT14: 161.685 | BU14: 45.915 | BV14: 46.455 | BW14: 46.461 | BX14: 45.195 | BY14: 184.026 | CK14: Stock-based comp % of revenue | CL14: 0.006 | CM14: 0.007 | CN14: 0.008
B15: Capital expenditures | AF15: 153.451 | AG15: 36.521 | AH15: 51.541 | AI15: 40.872 | AJ15: 188.712 | AK15: 317.646 | AL15: 38.905 | AM15: 56.804 | AN15: 57.028 | AO15: 103.131 | AP15: 255.868 | AQ15: 35.253 | AR15: 66.901 | AS15: 107.569 | AT15: 101.749 | AU15: 311.472 | AV15: 113.266 | AW15: 261.157 | AX15: 86.423 | AY15: 107.626 | AZ15: 568.472 | BA15: 122.459 | BB15: 121.595 | BC15: 59.006 | BD15: 87.646 | BE15: 390.706 | BF15: 54.272 | BG15: 86.788 | BH15: 64.397 | BI15: 92.175 | BJ15: 297.632 | BK15: 136.283 | BL15: 89.428 | BM15: 79.633 | BN15: 67.846 | BO15: 373.19 | BP15: 216.131 | BQ15: 83.861 | BR15: 72.186 | BS15: 119.319 | BT15: 491.497 | BU15: 211.917 | BV15: 153.212 | BW15: 62.906 | BX15: 62.93 | BY15: 490.965 | CK15: ΔNWC % of Δrevenue | CL15: 0.05 | CM15: 0.08 | CN15: 0.1
B16: Total assets | AE16: 1249.755 | AF16: 1249.755 | AG16: 1375.198 | AH16: 1422.145 | AI16: 1372.425 | AJ16: 1514.018 | AK16: 1514.018 | AL16: 1577.659 | AM16: 1659.901 | AN16: 1702.637 | AO16: 1856.058 | AP16: 1856.058 | AQ16: 1934.693 | AR16: 1848.216 | AS16: 1935.621 | AT16: 2094.592 | AU16: 2094.592 | AV16: 2322.493 | AW16: 2526.943 | AX16: 2666.911 | AY16: 2901.158 | AZ16: 2901.158 | BA16: 3161.943 | BB16: 3287.453 | BC16: 3604.803 | BD16: 3900.712 | BE16: 3900.712 | BF16: 4223.448 | BG16: 4447.523 | BH16: 4751.379 | BI16: 4615.788 | BJ16: 4615.788 | BK16: 4870.941 | BL16: 5136.744 | BM16: 5510.093 | BN16: 5825.064 | BO16: 5825.064 | BP16: 6410.493 | BQ16: 6626.492 | BR16: 7034.96 | BS16: 7386.103 | BT16: 7386.103 | BU16: 7756.673 | BV16: 8047.72 | BW16: 8413.365 | BX16: 8834.063 | BY16: 8834.063 | CK16: CapEx % of revenue | CL16: 0.1 | CM16: 0.12 | CN16: 0.14
B17: Goodwill | AE17: 179.906 | AF17: 179.906 | AG17: 179.906 | AH17: 179.906 | AI17: 180.063 | AJ17: 259.162 | AK17: 259.162 | AL17: 257.896 | AM17: 257.896 | AN17: 257.896 | AO17: 256.434 | AP17: 256.434 | AQ17: 256.434 | AR17: 256.434 | AS17: 256.997 | AT17: 256.998 | AU17: 256.998 | AV17: 256.998 | AW17: 256.998 | AX17: 260.67 | AY17: 262.423 | AZ17: 262.423 | BA17: 262.423 | BB17: 262.423 | BC17: 262.423 | BD17: 270.305 | BE17: 270.305 | BF17: 270.269 | BG17: 270.357 | BH17: 270.358 | BI17: 270.269 | BJ17: 270.269 | BK17: 270.269 | BL17: 270.269 | BM17: 270.269 | BN17: 270.269 | BO17: 270.269 | BP17: 383.329 | BQ17: 388.207 | BR17: 390.903 | BS17: 390.421 | BT17: 390.421 | BU17: 390.422 | BV17: 390.421 | BW17: 390.421 | BX17: 390.422 | BY17: 390.422 | CK17: Buyback (% shares retired / yr) | CL17: 0.01 | CM17: 0.005 | CN17: 0
B19: International
B20: Revenue | Q20: 228.945 | V20: 269.915 | AA20: 243.199 | AF20: 252.413 | AG20: 60.929 | AH20: 62.621 | AI20: 66.742 | AJ20: 64.501 | AK20: 254.793 | AL20: 68.063 | AM20: 73.971 | AN20: 92.917 | AO20: 79.722 | AP20: 314.673 | AQ20: 90.159 | AR20: 94.826 | AS20: 104.917 | AT20: 95.486 | AU20: 385.388 | AV20: 90.26 | AW20: 92.403 | AX20: 83.162 | AY20: 79.072 | AZ20: 344.897 | BA20: 95.685 | BB20: 99.108 | BC20: 111.957 | BD20: 113.689 | BE20: 420.439 | BF20: 131.671 | BG20: 140.074 | BH20: 149.691 | BI20: 134.335 | BJ20: 555.771 | BK20: 144.523 | BL20: 168.795 | BM20: 188.073 | BN20: 178.479 | BO20: 679.87 | BP20: 179.51 | BQ20: 189.423 | BR20: 208.343 | BS20: 194.812 | BT20: 772.088 | BU20: 199.29 | BV20: 188.471 | BW20: 205.259 | BX20: 198.834 | BY20: 791.854 | BZ20: =BY20*(1+CHOOSE(MATCH($CF$2,{"Bull","Base","Bear"},0),$CL$8,$CM$8,$CN$8)) | CA20: =BZ20*(1+CHOOSE(MATCH($CF$2,{"Bull","Base","Bear"},0),$CL$8,$CM$8,$CN$8)) | CB20: =CA20*(1+CHOOSE(MATCH($CF$2,{"Bull","Base","Bear"},0),$CL$8,$CM$8,$CN$8)) | CC20: =CB20*(1+CHOOSE(MATCH($CF$2,{"Bull","Base","Bear"},0),$CL$8,$CM$8,$CN$8)) | CD20: =CC20*(1+CHOOSE(MATCH($CF$2,{"Bull","Base","Bear"},0),$CL$8,$CM$8,$CN$8)) | CF20: =IFERROR((CD20/BY20)^(1/5)-1,"n/m") | CG20: =IFERROR((BY20/AZ20)^(1/5)-1,"n/m") | CH20: =IFERROR((BY20/G20)^(1/14)-1,"n/m")
B21: Operating income | AF21: 58.761 | AG21: 15.842 | AH21: 15.288 | AI21: 17.671 | AJ21: 16.138 | AK21: 64.939 | AL21: 17.923 | AM21: 17.937 | AN21: 23.731 | AO21: 9.867 | AP21: 69.458 | AQ21: 21.148 | AR21: 19.337 | AS21: 19.236 | AT21: 15.96 | AU21: 75.681 | AV21: 16.341 | AW21: 19.807 | AX21: 14.414 | AY21: 16.76 | AZ21: 67.322 | BA21: 25.355 | BB21: 28.769 | BC21: 31.385 | BD21: 27.362 | BE21: 112.871 | BF21: 35.172 | BG21: 34.682 | BH21: 32.318 | BI21: 25.256 | BJ21: 127.428 | BK21: 28.875 | BL21: 29.361 | BM21: 34.133 | BN21: 26.103 | BO21: 118.472 | BP21: 33.085 | BQ21: 32.562 | BR21: 44.272 | BS21: 34.07 | BT21: 143.989 | BU21: 51.308 | BV21: 50.318 | BW21: 59.08 | BX21: 55.122 | BY21: 215.828 | BZ21: =BZ20*CHOOSE(MATCH($CF$2,{"Bull","Base","Bear"},0),$CL$10,$CM$10,$CN$10) | CA21: =CA20*CHOOSE(MATCH($CF$2,{"Bull","Base","Bear"},0),$CL$10,$CM$10,$CN$10) | CB21: =CB20*CHOOSE(MATCH($CF$2,{"Bull","Base","Bear"},0),$CL$10,$CM$10,$CN$10) | CC21: =CC20*CHOOSE(MATCH($CF$2,{"Bull","Base","Bear"},0),$CL$10,$CM$10,$CN$10) | CD21: =CD20*CHOOSE(MATCH($CF$2,{"Bull","Base","Bear"},0),$CL$10,$CM$10,$CN$10) | CF21: =IFERROR((CD21/BY21)^(1/5)-1,"n/m") | CG21: =IFERROR((BY21/AZ21)^(1/5)-1,"n/m") | CH21: =IFERROR((BY21/G21)^(1/14)-1,"n/m")
B22: Operating margin % | C22: =IFERROR(C21/C20,"") | D22: =IFERROR(D21/D20,"") | E22: =IFERROR(E21/E20,"") | F22: =IFERROR(F21/F20,"") | G22: =IFERROR(G21/G20,"") | H22: =IFERROR(H21/H20,"") | I22: =IFERROR(I21/I20,"") | J22: =IFERROR(J21/J20,"") | ... CD22: =IFERROR(CD21/CD20,"")
B23: Revenue y/y % | L23: =IFERROR(L20/G20-1,"") | Q23: =IFERROR(Q20/L20-1,"") | V23: =IFERROR(V20/Q20-1,"") | AA23: =IFERROR(AA20/V20-1,"") | AF23: =IFERROR(AF20/AA20-1,"") | AK23: =IFERROR(AK20/AF20-1,"") | AP23: =IFERROR(AP20/AK20-1,"") | AU23: =IFERROR(AU20/AP20-1,"") | AZ23: =IFERROR(AZ20/AU20-1,"") | BE23: =IFERROR(BE20/AZ20-1,"") | BJ23: =IFERROR(BJ20/BE20-1,"") | BO23: =IFERROR(BO20/BJ20-1,"") | BT23: =IFERROR(BT20/BO20-1,"") | BY23: =IFERROR(BY20/BT20-1,"") | BZ23: =IFERROR(BZ20/BY20-1,"") | CA23: =IFERROR(CA20/BZ20-1,"") | CB23: =IFERROR(CB20/CA20-1,"") | CC23: =IFERROR(CC20/CB20-1,"") | CD23: =IFERROR(CD20/CC20-1,"")
B24: Depreciation & amortisation | AF24: 9.492 | AG24: 2.323 | AH24: 2.548 | AI24: 2.304 | AJ24: 2.318 | AK24: 9.493 | AL24: 2.373 | AM24: 3.817 | AN24: 2.384 | AO24: 2.245 | AP24: 10.819 | AQ24: 2.477 | AR24: 2.522 | AS24: 2.476 | AT24: 2.285 | AU24: 9.76 | AV24: 2.447 | AW24: 2.584 | AX24: 3.012 | AY24: 2.712 | AZ24: 10.755 | BA24: 2.844 | BB24: 3.647 | BC24: 3.805 | BD24: 3.91 | BE24: 14.206 | BF24: 4.035 | BG24: 3.987 | BH24: 4.97 | BI24: 4.358 | BJ24: 17.35 | BK24: 4.123 | BL24: 4.293 | BM24: 4.453 | BN24: 10.805 | BO24: 23.674 | BP24: 6.228 | BQ24: 6.918 | BR24: 7.256 | BS24: 7.674 | BT24: 28.076 | BU24: 7.712 | BV24: 7.744 | BW24: 7.955 | BX24: 8.412 | BY24: 31.823
B25: Capital expenditures | AF25: 20.466 | AG25: 1.688 | AH25: 2.662 | AI25: 1.426 | AJ25: 9.568 | AK25: 15.344 | AL25: 2.456 | AM25: 12.617 | AN25: 20.672 | AO25: 5.084 | AP25: 40.829 | AQ25: 27.083 | AR25: 7.49 | AS25: 15.785 | AT25: 12.798 | AU25: 63.156 | AV25: 18.527 | AW25: 7.402 | AX25: 4.223 | AY25: 5.05 | AZ25: 35.202 | BA25: 24.634 | BB25: 14.526 | BC25: 22.175 | BD25: 15.955 | BE25: 77.29 | BF25: 10.424 | BG25: 5.185 | BH25: 14.237 | BI25: 116.574 | BJ25: 146.42 | BK25: 16.372 | BL25: 14.636 | BM25: 10.172 | BN25: 102.266 | BO25: 143.446 | BP25: 40.542 | BQ25: 39.168 | BR25: 15.629 | BS25: 18.567 | BT25: 113.906 | BU25: 26.098 | BV25: 20.868 | BW25: 7.561 | BX25: 24.721 | BY25: 79.248
B26: Total assets | AE26: 400.065 | AF26: 400.065 | AG26: 395.198 | AH26: 419.096 | AI26: 439.261 | AJ26: 468.483 | AK26: 468.483 | AL26: 485.011 | AM26: 483.64 | AN26: 462.556 | AO26: 451.64 | AP26: 451.64 | AQ26: 447.095 | AR26: 448.689 | AS26: 456.142 | AT26: 453.025 | AU26: 453.025 | AV26: 533.446 | AW26: 521.662 | AX26: 494.672 | AY26: 554.103 | AZ26: 554.103 | BA26: 579.245 | BB26: 646.985 | BC26: 677.143 | BD26: 661.431 | BE26: 661.431 | BF26: 695.404 | BG26: 689.433 | BH26: 692.495 | BI26: 693.076 | BJ26: 693.076 | BK26: 722.736 | BL26: 795.664 | BM26: 839.712 | BN26: 912.815 | BO26: 912.815 | BP26: 923.293 | BQ26: 972.028 | BR26: 975.672 | BS26: 1041.661 | BT26: 1041.661 | BU26: 1112.814 | BV26: 1139.627 | BW26: 1258.857 | BX26: 1256.839 | BY26: 1256.839
B27: Goodwill | AE27: 80.292 | AF27: 80.292 | AG27: 75.187 | AH27: 76.961 | AI27: 78.571 | AJ27: 81.081 | AK27: 81.081 | AL27: 81.128 | AM27: 86.603 | AN27: 84.563 | AO27: 80.801 | AP27: 80.801 | AQ27: 78.686 | AR27: 81.611 | AS27: 80.728 | AT27: 76.323 | AU27: 76.323 | AV27: 80.181 | AW27: 81.264 | AX27: 77.369 | AY27: 81.199 | AZ27: 81.199 | BA27: 80.153 | BB27: 84.543 | BC27: 85.092 | BD27: 85.412 | BE27: 85.412 | BF27: 83.793 | BG27: 82.551 | BH27: 77.642 | BI27: 131.685 | BJ27: 131.685 | BK27: 124.575 | BL27: 133.777 | BM27: 136.371 | BN27: 124.02 | BO27: 124.02 | BP27: 117.597 | BQ27: 122.356 | BR27: 120.469 | BS27: 123.488 | BT27: 123.488 | BU27: 124.061 | BV27: 119.249 | BW27: 128.179 | BX27: 127.357 | BY27: 127.357
B29: Group total (consolidated segments)
B30: Revenue | C30: =C10+C20 | D30: =D10+D20 | E30: =E10+E20 | F30: =F10+F20 | G30: =G10+G20 | H30: =H10+H20 | I30: =I10+I20 | J30: =J10+J20 | ... CD30: =CD10+CD20 | CF30: =IFERROR((CD30/BY30)^(1/5)-1,"n/m") | CG30: =IFERROR((BY30/AZ30)^(1/5)-1,"n/m") | CH30: =IFERROR((BY30/G30)^(1/14)-1,"n/m")
B31: Operating income | C31: =C11+C21 | D31: =D11+D21 | E31: =E11+E21 | F31: =F11+F21 | G31: =G11+G21 | H31: =H11+H21 | I31: =I11+I21 | J31: =J11+J21 | ... CD31: =CD11+CD21 | CF31: =IFERROR((CD31/BY31)^(1/5)-1,"n/m") | CG31: =IFERROR((BY31/AZ31)^(1/5)-1,"n/m") | CH31: =IFERROR((BY31/G31)^(1/14)-1,"n/m")
B32: Operating margin % | C32: =IFERROR(C31/C30,"") | D32: =IFERROR(D31/D30,"") | E32: =IFERROR(E31/E30,"") | F32: =IFERROR(F31/F30,"") | G32: =IFERROR(G31/G30,"") | H32: =IFERROR(H31/H30,"") | I32: =IFERROR(I31/I30,"") | J32: =IFERROR(J31/J30,"") | ... CD32: =IFERROR(CD31/CD30,"")
B33: Revenue mix %
B34: United States | C34: =IFERROR(C10/C30,"") | D34: =IFERROR(D10/D30,"") | E34: =IFERROR(E10/E30,"") | F34: =IFERROR(F10/F30,"") | G34: =IFERROR(G10/G30,"") | H34: =IFERROR(H10/H30,"") | I34: =IFERROR(I10/I30,"") | J34: =IFERROR(J10/J30,"") | ... CD34: =IFERROR(CD10/CD30,"")
B35: International | C35: =IFERROR(C20/C30,"") | D35: =IFERROR(D20/D30,"") | E35: =IFERROR(E20/E30,"") | F35: =IFERROR(F20/F30,"") | G35: =IFERROR(G20/G30,"") | H35: =IFERROR(H20/H30,"") | I35: =IFERROR(I20/I30,"") | J35: =IFERROR(J20/J30,"") | ... CD35: =IFERROR(CD20/CD30,"")
B37: CONSOLIDATED INCOME STATEMENT
B38: Total revenues (service + vehicle sales) | C38: 212.667 | D38: 207.38 | E38: 236.755 | F38: 215.443 | G38: 872.246 | H38: 225.626 | I38: 227.904 | J38: 244.105 | K38: 226.556 | L38: 924.191 | M38: 238.866 | N38: 266.185 | O38: 277.638 | P38: 263.697 | Q38: 1046.386 | R38: 279.883 | S38: 286.434 | T38: 309.722 | U38: 287.45 | V38: 1163.489 | W38: 290.386 | X38: 276.258 | Y38: 297.142 | Z38: 282.293 | AA38: 1146.079 | AB38: 288.838 | AC38: 299.706 | AD38: 347.246 | AE38: 332.659 | AF38: 1268.449 | AG38: 345.991 | AH38: 349.532 | AI38: 373.862 | AJ38: 378.596 | AK38: 1447.981 | AL38: 419.168 | AM38: 459.106 | AN38: 478.198 | AO38: 449.223 | AP38: 1805.695 | AQ38: 461.368 | AR38: 484.898 | AS38: 553.116 | AT38: 542.575 | AU38: 2041.957 | AV38: 554.424 | AW38: 575.14 | AX38: 550.36 | AY38: 525.659 | AZ38: 2205.583 | BA38: 592.94 | BB38: 617.031 | BC38: 733.91 | BD38: 748.63 | BE38: 2692.511 | BF38: 810.132 | BG38: 867.46 | BH38: 939.941 | BI38: 883.388 | BJ38: 3500.921 | BK38: 893.372 | BL38: 956.724 | BM38: 1021.831 | BN38: 997.591 | BO38: 3869.518 | BP38: 1020.416 | BQ38: 1020.149 | BR38: 1127.259 | BS38: 1068.999 | BT38: 4236.823 | BU38: 1146.829 | BV38: 1163.316 | BW38: 1211.716 | BX38: 1125.097 | BY38: 4646.958 | BZ38: =BZ30 | CA38: =CA30 | CB38: =CB30 | CC38: =CC30 | CD38: =CD30 | CF38: =IFERROR((CD38/BY38)^(1/5)-1,"n/m") | CG38: =IFERROR((BY38/AZ38)^(1/5)-1,"n/m") | CH38: =IFERROR((BY38/G38)^(1/14)-1,"n/m")
B39: Yard operations expense | D39: 94.473 | E39: 92.996 | G39: 374.149 | H39: 96.207 | I39: 94.603 | J39: 92.578 | L39: 377.604 | M39: 97.119 | N39: 127.164 | O39: 116.41 | P39: 117.535 | Q39: 458.228 | R39: 125.956 | S39: 131.246 | T39: 131.207 | U39: 132.014 | V39: 520.423 | W39: 131.005 | X39: 129.273 | Y39: 135.222 | Z39: 130.791 | AA39: 526.291 | AB39: 135.909 | AC39: 140.965 | AD39: 151.855 | AE39: 154.175 | AF39: 582.904 | AG39: 167.611 | AH39: 169.081 | AI39: 166.572 | AJ39: 175.137 | AK39: 678.401 | AL39: 217.607 | AM39: 217.184 | AN39: 201.592 | AO39: 210.485 | AP39: 846.868 | AQ39: 207.694 | AR39: 215.46 | AS39: 230.553 | AT39: 234.404 | AU39: 888.111 | AV39: 240.791 | AW39: 257.351 | AX39: 253.76 | AY39: 220.585 | AZ39: 972.487 | BA39: 231.811 | BB39: 235.904 | BC39: 258.071 | BD39: 277.506 | BE39: 1003.292 | BF39: 298.694 | BG39: 323.814 | BH39: 346.428 | BI39: 340.561 | BJ39: 1309.497 | BK39: 372.777 | BL39: 375.497 | BM39: 378.958 | BN39: 390.797 | BO39: 1518.029 | BP39: 408.501 | BQ39: 409.178 | BR39: 438.873 | BS39: 453.532 | BT39: 1710.084 | BU39: 496.546 | BV39: 490.056 | BW39: 489.735 | BX39: 467.981 | BY39: 1944.318
B40: Cost of vehicle sales | D40: 27.002 | E40: 34.852 | G40: 125.202 | H40: 34.194 | I40: 33.605 | J40: 36.258 | L40: 136.971 | M40: 36.311 | N40: 42.204 | O40: 45.631 | P40: 43.09 | Q40: 167.236 | R40: 46.091 | S40: 43.642 | T40: 46.263 | U40: 38.497 | V40: 174.493 | W40: 37.073 | X40: 32.118 | Y40: 34.503 | Z40: 32.718 | AA40: 136.412 | AB40: 32.068 | AC40: 34.127 | AD40: 37.744 | AE40: 37.02 | AF40: 140.959 | AG40: 33.087 | AH40: 33.686 | AI40: 34.785 | AJ40: 35.994 | AK40: 137.552 | AL40: 38.297 | AM40: 50.313 | AN40: 57.538 | AO40: 50.313 | AP40: 196.461 | AS40: 70.984 | AU40: 255.504 | AV40: 58.764 | AW40: 57.9 | AX40: 53.987 | AY40: 54.643 | AZ40: 225.294 | BA40: 64.36 | BB40: 73.629 | BC40: 94.498 | BD40: 113.641 | BE40: 346.128 | BF40: 126.408 | BG40: 140.304 | BH40: 157.236 | BI40: 161.255 | BJ40: 585.203 | BK40: 151.112 | BL40: 154.727 | BM40: 159.443 | BN40: 149.216 | BO40: 614.498 | BP40: 147.896 | BQ40: 146.819 | BR40: 162.881 | BS40: 161.891 | BT40: 619.487 | BU40: 138.178 | BV40: 147.707 | BW40: 169.714 | BX40: 147.398 | BY40: 602.997
B41: Gross profit | D41: =D38-D39-D40 | E41: =E38-E39-E40 | G41: =G38-G39-G40 | H41: =H38-H39-H40 | I41: =I38-I39-I40 | J41: =J38-J39-J40 | L41: =L38-L39-L40 | M41: =M38-M39-M40 | N41: =N38-N39-N40 | O41: =O38-O39-O40 | P41: =P38-P39-P40 | Q41: =Q38-Q39-Q40 | R41: =R38-R39-R40 | S41: =S38-S39-S40 | ... AP41: =AP38-AP39-AP40 | AS41: =AS38-AS39-AS40 | AU41: =AU38-AU39-AU40 | AV41: =AV38-AV39-AV40 | AW41: =AW38-AW39-AW40 | AX41: =AX38-AX39-AX40 | AY41: =AY38-AY39-AY40 | AZ41: =AZ38-AZ39-AZ40 | BA41: =BA38-BA39-BA40 | BB41: =BB38-BB39-BB40 | ... BY41: =BY38-BY39-BY40
B42: General & administrative | D42: 25.71 | E42: 26.863 | G42: 107.605 | H42: 29.849 | I42: 27.386 | J42: 27.325 | L42: 114.492 | M42: 31.079 | N42: 34.047 | O42: 32.784 | P42: 40.02 | Q42: 137.93 | R42: 42.877 | S42: 40.062 | T42: 40.515 | U42: 41.081 | V42: 164.535 | W42: 39.907 | X42: 34.399 | Y42: 32.65 | Z42: 32.019 | AA42: 138.975 | AB42: 34.615 | AC42: 32.529 | AD42: 35.699 | AE42: 35.273 | AF42: 138.116 | AG42: 40.469 | AH42: 37.885 | AI42: 35.717 | AJ42: 37.293 | AK42: 151.364 | AL42: 39.322 | AM42: 40.662 | AN42: 44.449 | AO42: 52.457 | AP42: 176.89 | AQ42: 44.478 | AR42: 43.487 | AS42: 44.085 | AT42: 49.817 | AU42: 181.867 | AV42: 49.478 | AW42: 49.997 | AX42: 47.512 | AY42: 44.716 | AZ42: 191.703 | BA42: 48.175 | BB42: 49.277 | BC42: 53.23 | BD42: 55.983 | BE42: 206.665 | BF42: 54.909 | BG42: 56.014 | BH42: 63.522 | BI42: 56.779 | BJ42: 231.224 | BK42: 57.98 | BL42: 60.975 | BM42: 64.506 | BN42: 66.961 | BO42: 250.422 | BP42: 68.643 | BQ42: 84.252 | BR42: 88.302 | BS42: 94.032 | BT42: 335.229 | BU42: 105.738 | BV42: 99.342 | BW42: 100.722 | BX42: 97.127 | BY42: 402.929
B43: Operating income | D43: =D41-D42 | E43: =E41-E42 | G43: =G41-G42 | H43: =H41-H42 | I43: =I41-I42 | J43: =J41-J42 | L43: =L41-L42 | M43: =M41-M42 | N43: =N41-N42 | O43: =O41-O42 | P43: =P41-P42 | Q43: =Q41-Q42 | R43: =R41-R42 | S43: =S41-S42 | ... AP43: =AP41-AP42 | AS43: =AS41-AS42 | AU43: =AU41-AU42 | AV43: =AV41-AV42 | AW43: =AW41-AW42 | AX43: =AX41-AX42 | AY43: =AY41-AY42 | AZ43: =AZ41-AZ42 | BA43: =BA41-BA42 | BB43: =BB41-BB42 | ... BY43: =BY41-BY42 | BZ43: =BZ31 | CA43: =CA31 | CB43: =CB31 | CC43: =CC31 | CD43: =CD31 | CF43: =IFERROR((CD43/BY43)^(1/5)-1,"n/m") | CG43: =IFERROR((BY43/AZ43)^(1/5)-1,"n/m") | CH43: =IFERROR((BY43/G43)^(1/14)-1,"n/m")
B44: Interest & other income / (expense), net | C44: 0.569 | D44: 0.522 | E44: -1.694 | F44: -0.811 | G44: -1.413 | H44: -1.561 | I44: -1.323 | J44: -3.397 | L44: -8.297 | M44: -2.769 | N44: -1.653 | O44: -0.808 | P44: -0.89 | Q44: -6.12 | R44: -0.714 | S44: -0.896 | T44: -1.315 | U44: -1.974 | V44: -4.899 | W44: -0.178 | X44: -0.364 | Y44: -6.471 | Z44: -5.319 | AA44: -12.332 | AB44: -4.486 | AC44: -0.533 | AD44: -5.38 | AE44: -0.206 | AF44: -10.605 | AG44: -2.29 | AH44: -8.781 | AI44: -5.7 | AJ44: -4.428 | AK44: -21.199 | AL44: -9.814 | AM44: -6.509 | AN44: -3.403 | AO44: -2.108 | AP44: -21.834 | AQ44: -2.654 | AR44: 0.227 | AS44: -3.365 | AT44: -5.732 | AU44: -11.524 | AV44: -3.309 | AW44: -4.818 | AX44: -3.301 | AY44: -3.832 | AZ44: -15.26 | BA44: -1.779 | BB44: -5.769 | BC44: -4.576 | BD44: -2.456 | BE44: -14.58 | BF44: -4.295 | BG44: -5.273 | BH44: -3.15 | BI44: -21.325 | BJ44: -34.043 | BK44: 1.6 | BL44: 11.578 | BM44: 21.506 | BN44: 33.075 | BO44: 67.759 | BP44: 27.933 | BQ44: 30.853 | BR44: 34.909 | BS44: 48.883 | BT44: 142.578 | BU44: 44.951 | BV44: 36.84 | BW44: 51.259 | BX44: 65.817 | BY44: 198.867 | BZ44: =BZ38*CHOOSE(MATCH($CF$2,{"Bull","Base","Bear"},0),$CL$11,$CM$11,$CN$11) | CA44: =CA38*CHOOSE(MATCH($CF$2,{"Bull","Base","Bear"},0),$CL$11,$CM$11,$CN$11) | CB44: =CB38*CHOOSE(MATCH($CF$2,{"Bull","Base","Bear"},0),$CL$11,$CM$11,$CN$11) | CC44: =CC38*CHOOSE(MATCH($CF$2,{"Bull","Base","Bear"},0),$CL$11,$CM$11,$CN$11) | CD44: =CD38*CHOOSE(MATCH($CF$2,{"Bull","Base","Bear"},0),$CL$11,$CM$11,$CN$11)
B45: Income before income taxes | D45: =D43+D44 | E45: =E43+E44 | G45: =G43+G44 | H45: =H43+H44 | I45: =I43+I44 | J45: =J43+J44 | L45: =L43+L44 | M45: =M43+M44 | N45: =N43+N44 | O45: =O43+O44 | P45: =P43+P44 | Q45: =Q43+Q44 | R45: =R43+R44 | S45: =S43+S44 | ... AP45: =AP43+AP44 | AS45: =AS43+AS44 | AU45: =AU43+AU44 | AV45: =AV43+AV44 | AW45: =AW43+AW44 | AX45: =AX43+AX44 | AY45: =AY43+AY44 | AZ45: =AZ43+AZ44 | BA45: =BA43+BA44 | BB45: =BB43+BB44 | ... CD45: =CD43+CD44
B46: Income tax expense | D46: 22.824 | E46: 30.214 | G46: 97.502 | H46: 22.666 | I46: 21.613 | J46: 29.076 | L46: 95.937 | M46: 25.743 | N46: 21.477 | O46: 28.769 | P46: 20.858 | Q46: 96.847 | R46: 22.823 | S46: 25.243 | T46: 20.441 | U46: 22.841 | V46: 91.348 | W46: 29.608 | X46: 27.911 | Y46: 30.733 | Z46: 24.034 | AA46: 112.286 | AB46: 29.15 | AC46: 32.548 | AD46: 41.944 | AE46: 21.863 | AF46: 125.505 | AG46: -64.746 | AH46: 34.033 | AI46: 40.542 | AJ46: 36.01 | AK46: 45.839 | AL46: 36.568 | AM46: 41.137 | AN46: 43.811 | AO46: 22.988 | AP46: 144.504 | AQ46: 34.703 | AR46: 33.593 | AS46: 11.388 | AT46: 33.574 | AU46: 113.258 | AV46: -16.098 | AW46: 36.367 | AX46: 44.313 | AY46: 36.35 | AZ46: 100.932 | BA46: 46.53 | BB46: 59.012 | BC46: 36.739 | BD46: 43.07 | BE46: 185.351 | BF46: 65.463 | BG46: 54.643 | BH46: 90.985 | BI46: 39.733 | BJ46: 250.824 | BK46: 67.255 | BL46: 83.426 | BM46: 89.999 | BN46: 75.907 | BO46: 316.587 | BP46: 90.777 | BQ46: 85.226 | BR46: 90.002 | BS46: 86.249 | BT46: 352.254 | BU46: 90.142 | BV46: 76.51 | BW46: 97.466 | BX46: 83.1 | BY46: 347.218 | BZ46: =BZ45*BZ47 | CA46: =CA45*CA47 | CB46: =CB45*CB47 | CC46: =CC45*CC47 | CD46: =CD45*CD47
B47: Effective tax rate | C47: =IFERROR(C46/C45,"") | D47: =IFERROR(D46/D45,"") | E47: =IFERROR(E46/E45,"") | F47: =IFERROR(F46/F45,"") | G47: =IFERROR(G46/G45,"") | H47: =IFERROR(H46/H45,"") | I47: =IFERROR(I46/I45,"") | J47: =IFERROR(J46/J45,"") | ... BY47: =IFERROR(BY46/BY45,"") | BZ47: =CHOOSE(MATCH($CF$2,{"Bull","Base","Bear"},0),$CL$12,$CM$12,$CN$12) | CA47: =CHOOSE(MATCH($CF$2,{"Bull","Base","Bear"},0),$CL$12,$CM$12,$CN$12) | CB47: =CHOOSE(MATCH($CF$2,{"Bull","Base","Bear"},0),$CL$12,$CM$12,$CN$12) | CC47: =CHOOSE(MATCH($CF$2,{"Bull","Base","Bear"},0),$CL$12,$CM$12,$CN$12) | CD47: =CHOOSE(MATCH($CF$2,{"Bull","Base","Bear"},0),$CL$12,$CM$12,$CN$12)
B48: Net income (incl. noncontrolling interests) | D48: =D45-D46 | E48: =E45-E46 | G48: =G45-G46 | H48: =H45-H46 | I48: =I45-I46 | J48: =J45-J46 | L48: =L45-L46 | M48: =M45-M46 | N48: =N45-N46 | O48: =O45-O46 | P48: =P45-P46 | Q48: =Q45-Q46 | R48: =R45-R46 | S48: =S45-S46 | ... AP48: =AP45-AP46 | AS48: =AS45-AS46 | AU48: =AU45-AU46 | AV48: =AV45-AV46 | AW48: =AW45-AW46 | AX48: =AX45-AX46 | AY48: =AY45-AY46 | AZ48: =AZ45-AZ46 | BA48: =BA45-BA46 | BB48: =BB45-BB46 | ... CD48: =CD45-CD46
B49: Net income attributable to Copart, Inc. | C49: 37.823 | D49: 37.893 | E49: 50.136 | F49: 40.521 | G49: 166.375 | H49: 41.149 | I49: 40.603 | J49: 55.471 | L49: 182.119 | M49: 45.845 | N49: 39.64 | O49: 53.236 | P49: 41.304 | Q49: 180.025 | R49: 41.422 | S49: 45.345 | T49: 40.877 | U49: 51.043 | V49: 178.687 | W49: 52.615 | X49: 52.193 | Y49: 57.563 | Z49: 57.412 | AA49: 219.783 | AB49: 52.61 | AC49: 59.007 | AD49: 74.623 | AE49: 84.12 | AF49: 270.36 | AG49: 167.28 | AH49: 66.066 | AI49: 90.546 | AJ49: 70.335 | AK49: 394.227 | AL49: 77.515 | AM49: 103.256 | AN49: 127.348 | AO49: 109.748 | AP49: 417.867 | AQ49: 114.083 | AR49: 131.373 | AS49: 192.741 | AT49: 153.496 | AU49: 591.693 | AV49: 218.18 | AW49: 168.707 | AX49: 147.487 | AY49: 165.533 | AZ49: 699.907 | BA49: 200.285 | BB49: 193.44 | BC49: 286.796 | BD49: 255.974 | BE49: 936.495 | BF49: 260.363 | BG49: 287.412 | BH49: 278.62 | BI49: 263.735 | BJ49: 1090.13 | BK49: 245.848 | BL49: 293.677 | BM49: 350.431 | BN49: 347.785 | BO49: 1237.741 | BP49: 332.527 | BQ49: 325.635 | BR49: 382.291 | BS49: 322.567 | BT49: 1363.02 | BU49: 362.086 | BV49: 387.4 | BW49: 406.609 | BX49: 396.354 | BY49: 1552.449 | BZ49: =BZ48 | CA49: =CA48 | CB49: =CB48 | CC49: =CC48 | CD49: =CD48 | CF49: =IFERROR((CD49/BY49)^(1/5)-1,"n/m") | CG49: =IFERROR((BY49/AZ49)^(1/5)-1,"n/m") | CH49: =IFERROR((BY49/G49)^(1/14)-1,"n/m")
B50: Memo: net income attributable to noncontrolling interests | C50: =IFERROR(C48-C49,"") | D50: =IFERROR(D48-D49,"") | E50: =IFERROR(E48-E49,"") | F50: =IFERROR(F48-F49,"") | G50: =IFERROR(G48-G49,"") | H50: =IFERROR(H48-H49,"") | I50: =IFERROR(I48-I49,"") | J50: =IFERROR(J48-J49,"") | ... BY50: =IFERROR(BY48-BY49,"")
B51: Weighted-avg shares — diluted (m) | D51: 81.955 | E51: 142.065 | G51: 153.352 | H51: 133.802 | I51: 131.59 | J51: 130.451 | L51: 0.131428 | M51: 128.473 | N51: 129.52 | O51: 0.13053 | P51: -128.34253 | Q51: 129.781 | R51: 0.130706 | S51: 131.101 | T51: 131.486 | U51: -131.48771 | V51: 131.23 | W51: 131.517 | X51: 131.872 | Y51: 132.124 | Z51: -132.662 | AA51: 262.851 | AB51: 127.144 | AC51: 124.612 | AD51: 236.412 | AE51: -243.873 | AF51: 244.295 | AG51: 237.758 | AH51: 235.588 | AI51: 237.135 | AJ51: -473.462 | AK51: 237.019 | AL51: 238.791 | AM51: 241.36 | AN51: 242.96 | AO51: -481.234 | AP51: 241.877 | AQ51: 244.826 | AR51: 240.66 | AS51: 237.892 | AT51: -482.925 | AU51: 240.453 | AV51: 238.662 | AW51: 238.47 | AX51: 238.591 | AY51: -477.067 | AZ51: 238.656 | BA51: 239.968 | BB51: 240.28 | BC51: 240.208 | BD51: 240.704 | BE51: 961.16 | BF51: 482.442 | BG51: 482.374 | BH51: 481.448 | BI51: -481.66 | BJ51: 964.604 | BK51: 964.336 | BL51: 965.072 | BM51: 967.38 | BN51: -1930.141 | BO51: 966.647 | BP51: 971.682 | BQ51: 974.589 | BR51: 976.445 | BS51: -1947.918 | BT51: 974.798 | BU51: 976.506 | BV51: 977.91 | BW51: 978.089 | BX51: -1954.942 | BY51: 977.563 | BZ51: =BY51*(1-CHOOSE(MATCH($CF$2,{"Bull","Base","Bear"},0),$CL$17,$CM$17,$CN$17)) | CA51: =BZ51*(1-CHOOSE(MATCH($CF$2,{"Bull","Base","Bear"},0),$CL$17,$CM$17,$CN$17)) | CB51: =CA51*(1-CHOOSE(MATCH($CF$2,{"Bull","Base","Bear"},0),$CL$17,$CM$17,$CN$17)) | CC51: =CB51*(1-CHOOSE(MATCH($CF$2,{"Bull","Base","Bear"},0),$CL$17,$CM$17,$CN$17)) | CD51: =CC51*(1-CHOOSE(MATCH($CF$2,{"Bull","Base","Bear"},0),$CL$17,$CM$17,$CN$17))
B52: Weighted-avg shares — basic (m) | D52: 81.24 | E52: 139.613 | G52: 151.298 | H52: 131.432 | I52: 128.306 | J52: 126.596 | L52: 0.12812 | M52: 124.302 | N52: 124.709 | O52: 0.12527 | P52: -124.22427 | Q52: 124.912 | R52: 0.12546 | S52: 125.564 | T52: 125.794 | U52: -125.79046 | V52: 125.693 | W52: 126.217 | X52: 126.3 | Y52: 126.415 | Z52: -127.103 | AA52: 251.829 | AB52: 120.155 | AC52: 117.306 | AD52: 221.088 | AE52: -229.703 | AF52: 228.846 | AG52: 225.436 | AH52: 229.142 | AI52: 229.92 | AJ52: -455.812 | AK52: 228.686 | AL52: 230.694 | AM52: 231.478 | AN52: 232.01 | AO52: -462.389 | AP52: 231.793 | AQ52: 233.888 | AR52: 230.798 | AS52: 227.984 | AT52: -462.181 | AU52: 230.489 | AV52: 231.169 | AW52: 232.671 | AX52: 234.133 | AY52: -464.771 | AZ52: 233.202 | BA52: 235.791 | BB52: 236.152 | BC52: 236.396 | BD52: 236.669 | BE52: 945.008 | BF52: 474.136 | BG52: 474.372 | BH52: 475.01 | BI52: -473.842 | BJ52: 949.676 | BK52: 952.198 | BL52: 952.752 | BM52: 953.574 | BN52: -1904.95 | BO52: 953.574 | BP52: 958.127 | BQ52: 960.525 | BR52: 961.813 | BS52: -1919.726 | BT52: 960.739 | BU52: 963.176 | BV52: 964.746 | BW52: 966.234 | BX52: -1928.85 | BY52: 965.306 | BZ52: =BZ51 | CA52: =CA51 | CB52: =CB51 | CC52: =CC51 | CD52: =CD51
B53: EPS — basic ($) | C53: =IFERROR(C49/C52,"") | D53: =IFERROR(D49/D52,"") | E53: =IFERROR(E49/E52,"") | F53: =IFERROR(F49/F52,"") | G53: =IFERROR(G49/G52,"") | H53: =IFERROR(H49/H52,"") | I53: =IFERROR(I49/I52,"") | J53: =IFERROR(J49/J52,"") | ... CD53: =IFERROR(CD49/CD52,"")
B54: EPS — diluted ($) | C54: =IFERROR(C49/C51,"") | D54: =IFERROR(D49/D51,"") | E54: =IFERROR(E49/E51,"") | F54: =IFERROR(F49/F51,"") | G54: =IFERROR(G49/G51,"") | H54: =IFERROR(H49/H51,"") | I54: =IFERROR(I49/I51,"") | J54: =IFERROR(J49/J51,"") | ... CD54: =IFERROR(CD49/CD51,"") | CF54: =IFERROR((CD54/BY54)^(1/5)-1,"n/m") | CG54: =IFERROR((BY54/AZ54)^(1/5)-1,"n/m") | CH54: =IFERROR((BY54/G54)^(1/14)-1,"n/m")
B55: Note: EPS and share counts are as-reported each period and are NOT retroactively adjusted for Copart's stock splits, so they are not comparable across split dates.
B57: GROWTH & MARGINS
B58: Revenue y/y % | L58: =IFERROR(L38/G38-1,"") | Q58: =IFERROR(Q38/L38-1,"") | V58: =IFERROR(V38/Q38-1,"") | AA58: =IFERROR(AA38/V38-1,"") | AF58: =IFERROR(AF38/AA38-1,"") | AK58: =IFERROR(AK38/AF38-1,"") | AP58: =IFERROR(AP38/AK38-1,"") | AU58: =IFERROR(AU38/AP38-1,"") | AZ58: =IFERROR(AZ38/AU38-1,"") | BE58: =IFERROR(BE38/AZ38-1,"") | BJ58: =IFERROR(BJ38/BE38-1,"") | BO58: =IFERROR(BO38/BJ38-1,"") | BT58: =IFERROR(BT38/BO38-1,"") | BY58: =IFERROR(BY38/BT38-1,"") | BZ58: =IFERROR(BZ38/BY38-1,"") | CA58: =IFERROR(CA38/BZ38-1,"") | CB58: =IFERROR(CB38/CA38-1,"") | CC58: =IFERROR(CC38/CB38-1,"") | CD58: =IFERROR(CD38/CC38-1,"")
B59: Operating income y/y % | L59: =IFERROR(L43/G43-1,"") | Q59: =IFERROR(Q43/L43-1,"") | V59: =IFERROR(V43/Q43-1,"") | AA59: =IFERROR(AA43/V43-1,"") | AF59: =IFERROR(AF43/AA43-1,"") | AK59: =IFERROR(AK43/AF43-1,"") | AP59: =IFERROR(AP43/AK43-1,"") | AU59: =IFERROR(AU43/AP43-1,"") | AZ59: =IFERROR(AZ43/AU43-1,"") | BE59: =IFERROR(BE43/AZ43-1,"") | BJ59: =IFERROR(BJ43/BE43-1,"") | BO59: =IFERROR(BO43/BJ43-1,"") | BT59: =IFERROR(BT43/BO43-1,"") | BY59: =IFERROR(BY43/BT43-1,"") | BZ59: =IFERROR(BZ43/BY43-1,"") | CA59: =IFERROR(CA43/BZ43-1,"") | CB59: =IFERROR(CB43/CA43-1,"") | CC59: =IFERROR(CC43/CB43-1,"") | CD59: =IFERROR(CD43/CC43-1,"")
B60: EPS (diluted) y/y % | L60: =IFERROR(L54/G54-1,"") | Q60: =IFERROR(Q54/L54-1,"") | V60: =IFERROR(V54/Q54-1,"") | AA60: =IFERROR(AA54/V54-1,"") | AF60: =IFERROR(AF54/AA54-1,"") | AK60: =IFERROR(AK54/AF54-1,"") | AP60: =IFERROR(AP54/AK54-1,"") | AU60: =IFERROR(AU54/AP54-1,"") | AZ60: =IFERROR(AZ54/AU54-1,"") | BE60: =IFERROR(BE54/AZ54-1,"") | BJ60: =IFERROR(BJ54/BE54-1,"") | BO60: =IFERROR(BO54/BJ54-1,"") | BT60: =IFERROR(BT54/BO54-1,"") | BY60: =IFERROR(BY54/BT54-1,"") | BZ60: =IFERROR(BZ54/BY54-1,"") | CA60: =IFERROR(CA54/BZ54-1,"") | CB60: =IFERROR(CB54/CA54-1,"") | CC60: =IFERROR(CC54/CB54-1,"") | CD60: =IFERROR(CD54/CC54-1,"")
B61: Gross margin % | C61: =IFERROR(C41/C38,"") | D61: =IFERROR(D41/D38,"") | E61: =IFERROR(E41/E38,"") | F61: =IFERROR(F41/F38,"") | G61: =IFERROR(G41/G38,"") | H61: =IFERROR(H41/H38,"") | I61: =IFERROR(I41/I38,"") | J61: =IFERROR(J41/J38,"") | ... CD61: =IFERROR(CD41/CD38,"") | CF61: =IFERROR(AVERAGE(BZ61,CA61,CB61,CC61,CD61),"n/m") | CG61: =IFERROR(AVERAGE(BE61,BJ61,BO61,BT61,BY61),"n/m") | CH61: =IFERROR(AVERAGE(G61,L61,Q61,V61,AA61,AF61,AK61,AP61,AU61,AZ61,BE61,BJ61,BO61,BT61,BY61),"n/m")
B62: Operating margin % | C62: =IFERROR(C43/C38,"") | D62: =IFERROR(D43/D38,"") | E62: =IFERROR(E43/E38,"") | F62: =IFERROR(F43/F38,"") | G62: =IFERROR(G43/G38,"") | H62: =IFERROR(H43/H38,"") | I62: =IFERROR(I43/I38,"") | J62: =IFERROR(J43/J38,"") | ... CD62: =IFERROR(CD43/CD38,"") | CF62: =IFERROR(AVERAGE(BZ62,CA62,CB62,CC62,CD62),"n/m") | CG62: =IFERROR(AVERAGE(BE62,BJ62,BO62,BT62,BY62),"n/m") | CH62: =IFERROR(AVERAGE(G62,L62,Q62,V62,AA62,AF62,AK62,AP62,AU62,AZ62,BE62,BJ62,BO62,BT62,BY62),"n/m")
B63: Net margin % | C63: =IFERROR(C49/C38,"") | D63: =IFERROR(D49/D38,"") | E63: =IFERROR(E49/E38,"") | F63: =IFERROR(F49/F38,"") | G63: =IFERROR(G49/G38,"") | H63: =IFERROR(H49/H38,"") | I63: =IFERROR(I49/I38,"") | J63: =IFERROR(J49/J38,"") | ... CD63: =IFERROR(CD49/CD38,"") | CF63: =IFERROR(AVERAGE(BZ63,CA63,CB63,CC63,CD63),"n/m") | CG63: =IFERROR(AVERAGE(BE63,BJ63,BO63,BT63,BY63),"n/m") | CH63: =IFERROR(AVERAGE(G63,L63,Q63,V63,AA63,AF63,AK63,AP63,AU63,AZ63,BE63,BJ63,BO63,BT63,BY63),"n/m")
B65: CONSOLIDATED CASH FLOW (fiscal-year basis)
B66: Interim cash-flow statements are filed year-to-date; only fiscal-year figures are shown below.
B67: Cash from operations | G67: 242.932 | AK67: 492.058 | AP67: 535.069 | AU67: 646.646 | AZ67: 917.885 | BE67: 990.891 | BJ67: 1176.683 | BO67: 1364.21 | BT67: 1472.564 | BY67: 1799.75 | BZ67: =BZ48+BZ68+BZ69-BZ70 | CA67: =CA48+CA68+CA69-CA70 | CB67: =CB48+CB68+CB69-CB70 | CC67: =CC48+CC68+CC69-CC70 | CD67: =CD48+CD68+CD69-CD70
B68: Depreciation & amortisation | G68: 45.694 | L68: 48.167 | Q68: 56.728 | V68: 53.726 | AA68: 46.573 | AF68: 48.575 | AK68: 57 | AP68: 78.598 | AU68: 84.895 | AZ68: 101.39 | BE68: 121.971 | BJ68: 137.985 | BO68: 159.478 | BT68: 189.761 | BY68: 215.849 | BZ68: =BZ38*CHOOSE(MATCH($CF$2,{"Bull","Base","Bear"},0),$CL$13,$CM$13,$CN$13) | CA68: =CA38*CHOOSE(MATCH($CF$2,{"Bull","Base","Bear"},0),$CL$13,$CM$13,$CN$13) | CB68: =CB38*CHOOSE(MATCH($CF$2,{"Bull","Base","Bear"},0),$CL$13,$CM$13,$CN$13) | CC68: =CC38*CHOOSE(MATCH($CF$2,{"Bull","Base","Bear"},0),$CL$13,$CM$13,$CN$13) | CD68: =CD38*CHOOSE(MATCH($CF$2,{"Bull","Base","Bear"},0),$CL$13,$CM$13,$CN$13)
B69: Stock-based compensation | G69: 19.007 | L69: 21.791 | Q69: 19.557 | V69: 22.099 | AA69: 18.154 | AF69: 20.864 | AK69: 20.84 | AP69: 23.221 | AU69: 23.445 | AZ69: 23.322 | BE69: 40.922 | BJ69: 38.965 | BO69: 39.673 | BT69: 35.234 | BY69: 38.004 | BZ69: =BZ38*CHOOSE(MATCH($CF$2,{"Bull","Base","Bear"},0),$CL$14,$CM$14,$CN$14) | CA69: =CA38*CHOOSE(MATCH($CF$2,{"Bull","Base","Bear"},0),$CL$14,$CM$14,$CN$14) | CB69: =CB38*CHOOSE(MATCH($CF$2,{"Bull","Base","Bear"},0),$CL$14,$CM$14,$CN$14) | CC69: =CC38*CHOOSE(MATCH($CF$2,{"Bull","Base","Bear"},0),$CL$14,$CM$14,$CN$14) | CD69: =CD38*CHOOSE(MATCH($CF$2,{"Bull","Base","Bear"},0),$CL$14,$CM$14,$CN$14)
B70: Change in net working capital (est.) | BZ70: =(BZ38-BY38)*CHOOSE(MATCH($CF$2,{"Bull","Base","Bear"},0),$CL$15,$CM$15,$CN$15) | CA70: =(CA38-BZ38)*CHOOSE(MATCH($CF$2,{"Bull","Base","Bear"},0),$CL$15,$CM$15,$CN$15) | CB70: =(CB38-CA38)*CHOOSE(MATCH($CF$2,{"Bull","Base","Bear"},0),$CL$15,$CM$15,$CN$15) | CC70: =(CC38-CB38)*CHOOSE(MATCH($CF$2,{"Bull","Base","Bear"},0),$CL$15,$CM$15,$CN$15) | CD70: =(CD38-CC38)*CHOOSE(MATCH($CF$2,{"Bull","Base","Bear"},0),$CL$15,$CM$15,$CN$15)
B71: Capital expenditures | G71: 70.17 | L71: 54.832 | Q71: 130.265 | V71: 95.81 | AA71: 79.153 | AF71: 173.917 | AK71: 332.99 | AP71: 296.697 | AU71: 374.628 | AZ71: 603.674 | BE71: 467.996 | BJ71: 444.052 | BO71: 516.636 | BT71: 605.403 | BY71: 570.213 | BZ71: =-BZ38*CHOOSE(MATCH($CF$2,{"Bull","Base","Bear"},0),$CL$16,$CM$16,$CN$16) | CA71: =-CA38*CHOOSE(MATCH($CF$2,{"Bull","Base","Bear"},0),$CL$16,$CM$16,$CN$16) | CB71: =-CB38*CHOOSE(MATCH($CF$2,{"Bull","Base","Bear"},0),$CL$16,$CM$16,$CN$16) | CC71: =-CC38*CHOOSE(MATCH($CF$2,{"Bull","Base","Bear"},0),$CL$16,$CM$16,$CN$16) | CD71: =-CD38*CHOOSE(MATCH($CF$2,{"Bull","Base","Bear"},0),$CL$16,$CM$16,$CN$16)
B72: Cash from investing | G72: -84.48 | AK72: -335.791 | AP72: -288.476 | AU72: -356.267 | AZ72: -601.208 | BE72: -465.466 | BJ72: -442.31 | BO72: -1892.049 | BT72: -940.079 | BY72: -587.448
B73: Cash from financing | G73: -354.075 | AK73: -106.975 | AP73: -182.038 | AU73: -370.304 | AZ73: -27.414 | BE73: 40.922 | BJ73: -382.693 | BO73: 66.615 | BT73: 19.273 | BY73: 52.107
B74: Free cash flow (CFO − CapEx) | G74: =G67-G71 | AK74: =AK67-AK71 | AP74: =AP67-AP71 | AU74: =AU67-AU71 | AZ74: =AZ67-AZ71 | BE74: =BE67-BE71 | BJ74: =BJ67-BJ71 | BO74: =BO67-BO71 | BT74: =BT67-BT71 | BY74: =BY67-BY71 | BZ74: =BZ67+BZ71 | CA74: =CA67+CA71 | CB74: =CB67+CB71 | CC74: =CC67+CC71 | CD74: =CD67+CD71 | CF74: =IFERROR((CD74/BY74)^(1/5)-1,"n/m") | CG74: =IFERROR((BY74/AZ74)^(1/5)-1,"n/m") | CH74: =IFERROR((BY74/G74)^(1/14)-1,"n/m")
B75: FCF margin % | C75: =IFERROR(C74/C38,"") | D75: =IFERROR(D74/D38,"") | E75: =IFERROR(E74/E38,"") | F75: =IFERROR(F74/F38,"") | G75: =IFERROR(G74/G38,"") | H75: =IFERROR(H74/H38,"") | I75: =IFERROR(I74/I38,"") | J75: =IFERROR(J74/J38,"") | ... CD75: =IFERROR(CD74/CD38,"") | CF75: =IFERROR(AVERAGE(BZ75,CA75,CB75,CC75,CD75),"n/m") | CG75: =IFERROR(AVERAGE(BE75,BJ75,BO75,BT75,BY75),"n/m") | CH75: =IFERROR(AVERAGE(G75,L75,Q75,V75,AA75,AF75,AK75,AP75,AU75,AZ75,BE75,BJ75,BO75,BT75,BY75),"n/m")
B76: CapEx % of revenue | C76: =IFERROR(ABS(C71)/C38,"") | D76: =IFERROR(ABS(D71)/D38,"") | E76: =IFERROR(ABS(E71)/E38,"") | F76: =IFERROR(ABS(F71)/F38,"") | G76: =IFERROR(ABS(G71)/G38,"") | H76: =IFERROR(ABS(H71)/H38,"") | I76: =IFERROR(ABS(I71)/I38,"") | J76: =IFERROR(ABS(J71)/J38,"") | ... CD76: =IFERROR(ABS(CD71)/CD38,"")
B78: CONSOLIDATED BALANCE SHEET (period end)
B79: Cash & cash equivalents | D79: 203.954 | E79: 192.148 | F79: 74.009 | G79: 74.009 | H79: 212.677 | I79: 127.64 | J79: 207.134 | L79: 140.112 | M79: 131.43 | N79: 49.51 | O79: 139.331 | P79: 63.631 | Q79: 63.631 | R79: 77.052 | S79: 46.199 | T79: 132.832 | U79: 158.668 | V79: 158.668 | W79: 198.484 | X79: 590.366 | Y79: 678.742 | Z79: 456.012 | AA79: 456.012 | AB79: 472.916 | AC79: 141.416 | AD79: 137.653 | AE79: 155.849 | AF79: 155.849 | AG79: 168.421 | AH79: 174.952 | AI79: 189.621 | AJ79: 210.1 | AK79: 210.1 | AL79: 224.246 | AM79: 204.275 | AN79: 204.275 | AO79: 274.52 | AP79: 274.52 | AQ79: 320.309 | AR79: 108.174 | AS79: 102.826 | AT79: 186.319 | AU79: 186.319 | AV79: 181.102 | AW79: 93.511 | AX79: 306.387 | AY79: 477.718 | AZ79: 477.718 | BA79: 605.732 | BB79: 616.403 | BC79: 911.89 | BD79: 1048.26 | BE79: 1048.26 | BF79: 1298.373 | BG79: 971.651 | BH79: 1454.818 | BI79: 1384.236 | BJ79: 1384.236 | BK79: 1539.391 | BL79: 1660.952 | BM79: 2114.183 | BN79: 957.395 | BO79: 957.395 | BP79: 2581.567 | BQ79: 1256.948 | BR79: 1089.995 | BS79: 1514.111 | BT79: 1514.111 | BU79: 3698.118 | BV79: 3338.909 | BW79: 2366.499 | BX79: 2780.531 | BY79: 2780.531
B80: Total current assets | D80: 392.353 | E80: 353.366 | F80: 241.868 | G80: 241.868 | H80: 384.271 | I80: 328.212 | J80: 383.375 | L80: 321.227 | M80: 327.069 | N80: 311.905 | O80: 353.162 | P80: 306.452 | Q80: 306.452 | R80: 320.955 | S80: 332.929 | T80: 385.754 | U80: 412.291 | V80: 412.291 | W80: 457.766 | X80: 888.425 | Y80: 954.459 | Z80: 734.582 | AA80: 734.582 | AB80: 785.656 | AC80: 506.858 | AD80: 464.505 | AE80: 499.306 | AF80: 499.306 | AG80: 630.711 | AH80: 659.252 | AI80: 593.609 | AJ80: 587.261 | AK80: 587.261 | AL80: 654.371 | AM80: 666.476 | AN80: 630.902 | AO80: 709.116 | AP80: 709.116 | AQ80: 763.222 | AR80: 628.466 | AS80: 613.585 | AT80: 687.167 | AU80: 687.167 | AV80: 744.076 | AW80: 731.963 | AX80: 794.152 | AY80: 963.759 | AZ80: 963.759 | BA80: 1138.176 | BB80: 1225.467 | BC80: 1499.371 | BD80: 1702.611 | BE80: 1702.611 | BF80: 2039.78 | BG80: 2189.373 | BH80: 2457.426 | BI80: 2202.455 | BJ80: 2202.455 | BK80: 2364.605 | BL80: 2638.781 | BM80: 3001.03 | BN80: 3262.604 | BO80: 3262.604 | BP80: 3584.89 | BQ80: 3748.486 | BR80: 4149.129 | BS80: 4418.184 | BT80: 4418.184 | BU80: 4733.117 | BV80: 4966.783 | BW80: 5359.154 | BX80: 5754.628 | BY80: 5754.628
B81: Property & equipment, net | D81: 575.686 | E81: 598.968 | F81: 600.388 | G81: 600.388 | H81: 594.851 | I81: 568.816 | J81: 574.732 | L81: 587.163 | M81: 625.043 | N81: 657.424 | O81: 676.698 | P81: 677.517 | Q81: 677.517 | R81: 692.398 | S81: 707.379 | T81: 685.564 | U81: 692.383 | V81: 692.383 | W81: 691.981 | X81: 688.244 | Y81: 683.956 | Z81: 700.402 | AA81: 700.402 | AB81: 705.59 | AC81: 744.224 | AD81: 806.973 | AE81: 816.791 | AF81: 816.791 | AG81: 840.587 | AH81: 882.256 | AI81: 913.303 | AJ81: 944.056 | AK81: 944.056 | AL81: 959.716 | AM81: 1024.564 | AN81: 1087.91 | AO81: 1163.425 | AP81: 1163.425 | AQ81: 1188.088 | AR81: 1237.117 | AS81: 1340.692 | AT81: 1427.726 | AU81: 1427.726 | AV81: 1545.714 | AW81: 1789.326 | AX81: 1838.297 | AY81: 1941.719 | AZ81: 1941.719 | BA81: 2072.059 | BB81: 2175.346 | BC81: 2227.531 | BD81: 2296.624 | BE81: 2296.624 | BF81: 2318.701 | BG81: 2376.013 | BH81: 2402.809 | BI81: 2485.764 | BJ81: 2485.764 | BK81: 2582.481 | BL81: 2656.273 | BM81: 2710.933 | BN81: 2844.339 | BO81: 2844.339 | BP81: 2943.537 | BQ81: 3042.711 | BR81: 3073.09 | BS81: 3175.838 | BT81: 3175.838 | BU81: 3363.155 | BV81: 3462.768 | BW81: 3569.267 | BX81: 3598.093 | BY81: 3598.093
B82: Goodwill | D82: 177.882 | E82: 200.611 | F82: 198.62 | G82: 198.62 | H82: 197.129 | I82: 194.954 | J82: 197.808 | L82: 196.438 | M82: 198.558 | N82: 210.188 | O82: 208.58 | P82: 267.463 | Q82: 267.463 | R82: 281.447 | S82: 291.227 | T82: 288.402 | U82: 283.78 | V82: 283.78 | W82: 276.889 | X82: 270.492 | Y82: 271.484 | Z82: 271.85 | AA82: 271.85 | AB82: 270.62 | AC82: 264.128 | AD82: 267.367 | AE82: 260.198 | AF82: 260.198 | AG82: 255.093 | AH82: 256.867 | AI82: 258.634 | AJ82: 340.243 | AK82: 340.243 | AL82: 339.024 | AM82: 344.499 | AN82: 342.459 | AO82: 337.235 | AP82: 337.235 | AQ82: 335.12 | AR82: 338.045 | AS82: 337.725 | AT82: 333.321 | AU82: 333.321 | AV82: 337.179 | AW82: 338.262 | AX82: 338.039 | AY82: 343.622 | AZ82: 343.622 | BA82: 342.576 | BB82: 346.966 | BC82: 347.515 | BD82: 355.717 | BE82: 355.717 | BF82: 354.062 | BG82: 352.908 | BH82: 348 | BI82: 401.954 | BJ82: 401.954 | BK82: 394.844 | BL82: 404.046 | BM82: 406.64 | BN82: 394.289 | BO82: 394.289 | BP82: 500.926 | BQ82: 510.563 | BR82: 511.372 | BS82: 513.909 | BT82: 513.909 | BU82: 514.483 | BV82: 509.67 | BW82: 518.6 | BX82: 517.779 | BY82: 517.779
B83: Total assets | D83: 1188.411 | E83: 1191.312 | F83: 1084.436 | G83: 1084.436 | H83: 1225.884 | I83: 1139.658 | J83: 1204.763 | L83: 1154 | M83: 1214.526 | N83: 1253.946 | O83: 1298.682 | P83: 1334.481 | Q83: 1334.481 | R83: 1397.388 | S83: 1438.493 | T83: 1476.672 | U83: 1506.121 | V83: 1506.121 | W83: 1536.586 | X83: 1952.071 | Y83: 2002.977 | Z83: 1798.66 | AA83: 1798.66 | AB83: 1855.764 | AC83: 1604.364 | AD83: 1624.135 | AE83: 1649.82 | AF83: 1649.82 | AG83: 1770.396 | AH83: 1841.241 | AI83: 1811.686 | AJ83: 1982.501 | AK83: 1982.501 | AL83: 2062.67 | AM83: 2143.541 | AN83: 2165.193 | AO83: 2307.698 | AP83: 2307.698 | AQ83: 2381.788 | AR83: 2296.905 | AS83: 2391.763 | AT83: 2547.617 | AU83: 2547.617 | AV83: 2855.939 | AW83: 3048.605 | AX83: 3161.583 | AY83: 3455.261 | AZ83: 3455.261 | BA83: 3741.188 | BB83: 3934.438 | BC83: 4281.946 | BD83: 4562.143 | BE83: 4562.143 | BF83: 4918.852 | BG83: 5136.956 | BH83: 5443.874 | BI83: 5308.864 | BJ83: 5308.864 | BK83: 5593.677 | BL83: 5932.408 | BM83: 6349.805 | BN83: 6737.879 | BO83: 6737.879 | BP83: 7333.786 | BQ83: 7598.52 | BR83: 8010.632 | BS83: 8427.764 | BT83: 8427.764 | BU83: 8869.487 | BV83: 9187.347 | BW83: 9672.222 | BX83: 10090.902 | BY83: 10090.902
B84: Total current liabilities | D84: 160.893 | E84: 171.406 | F84: 166.626 | G84: 166.626 | H84: 208.635 | I84: 186.182 | J84: 198.771 | L84: 186.319 | M84: 217.215 | N84: 212.811 | O84: 218.377 | P84: 238.559 | Q84: 238.559 | R84: 257.907 | S84: 259.651 | T84: 256.742 | U84: 244.284 | V84: 244.284 | W84: 259.691 | X84: 234.724 | Y84: 229.448 | Z84: 213.126 | AA84: 213.126 | AB84: 223.926 | AC84: 265.117 | AD84: 203.581 | AE84: 278.783 | AF84: 278.783 | AG84: 357.678 | AH84: 345.947 | AI84: 221.488 | AJ84: 302.153 | AK84: 302.153 | AL84: 289.169 | AM84: 375.048 | AN84: 270.578 | AO84: 277.256 | AP84: 277.256 | AQ84: 254.808 | AR84: 372.033 | AS84: 296.906 | AT84: 282.004 | AU84: 282.004 | AV84: 323.318 | AW84: 342.837 | AX84: 286.568 | AY84: 356.044 | AZ84: 356.044 | BA84: 407.536 | BB84: 371.015 | BC84: 413.045 | BD84: 421.031 | BE84: 421.031 | BF84: 491.911 | BG84: 417.86 | BH84: 449.095 | BI84: 440.889 | BJ84: 440.889 | BK84: 504.477 | BL84: 487.623 | BM84: 506.564 | BN84: 492.769 | BO84: 492.769 | BP84: 624.417 | BQ84: 526.023 | BR84: 563.419 | BS84: 628.567 | BT84: 628.567 | BU84: 714.855 | BV84: 629.637 | BW84: 657.132 | BX84: 683.281 | BY84: 683.281
B85: Long-term debt | D85: 350.474 | E85: 337.952 | F85: 325.386 | G85: 325.386 | H85: 425.337 | I85: 406.536 | J85: 387.752 | L85: 368.95 | M85: 350.159 | N85: 333.068 | O85: 314.23 | P85: 296.41 | Q85: 296.41 | R85: 280.121 | S85: 261.182 | T85: 242.106 | U85: 223.227 | V85: 223.227 | W85: 203.868 | X85: 608.236 | Y85: 599.951 | Z85: 590.843 | AA85: 590.843 | AB85: 584.302 | AC85: 576.501 | AD85: 670.507 | AE85: 564.341 | AF85: 564.341 | AG85: 573.03 | AH85: 565.926 | AI85: 550.755 | AJ85: 550.883 | AK85: 550.883 | AL85: 550.704 | AM85: 400.646 | AN85: 398.914 | AO85: 398.747 | AP85: 398.747 | AQ85: 398.642 | AR85: 398.74 | AS85: 398.835 | AT85: 400.091 | AU85: 400.091 | AV85: 399.979 | AW85: 399.846 | AX85: 403.653 | AY85: 396.9 | AZ85: 396.9 | BA85: 411.845 | BB85: 402.703 | BC85: 397.633 | BD85: 397.636 | BE85: 397.636 | BF85: 408.94 | BG85: 403.829 | BH85: 402.733 | BI85: 1.996 | BJ85: 1.996 | BK85: 1.969 | BL85: 1.946 | BM85: 22.368 | BN85: 10.903 | BO85: 10.903 | BP85: 9.462 | BQ85: 0.453 | BR85: 0.427 | BS85: 0 | BT85: 0
B86: Total liabilities | D86: 547.077 | E86: 544.97 | F86: 529.264 | G86: 529.264 | H86: 671.039 | I86: 632.286 | J86: 626.031 | L86: 592.883 | M86: 605.655 | N86: 586.443 | O86: 574.288 | P86: 572.08 | Q86: 572.08 | R86: 574.741 | S86: 557.769 | T86: 536.911 | U86: 503.305 | V86: 503.305 | W86: 499.155 | X86: 878.834 | Y86: 867.009 | Z86: 834.196 | AA86: 834.196 | AB86: 839.219 | AC86: 872.964 | AD86: 907.608 | AE86: 875.364 | AF86: 875.364 | AG86: 962.989 | AH86: 945.538 | AI86: 805.357 | AJ86: 883.901 | AK86: 883.901 | AL86: 873.761 | AM86: 811.75 | AN86: 704.381 | AO86: 726.599 | AP86: 726.599 | AQ86: 710.028 | AR86: 836.952 | AS86: 772.911 | AT86: 769.236 | AU86: 769.236 | AV86: 929.34 | AW86: 923.876 | AX86: 880.572 | AY86: 965.745 | AZ86: 965.745 | BA86: 1030.355 | BB86: 991.846 | BC86: 1032.569 | BD86: 1032.942 | BE86: 1032.942 | BF86: 1125.031 | BG86: 1047.1 | BH86: 1090.82 | BI86: 683.265 | BJ86: 683.265 | BK86: 740.843 | BL86: 718.756 | BM86: 757.383 | BN86: 750.439 | BO86: 750.439 | BP86: 897.147 | BQ86: 785.806 | BR86: 814.446 | BS86: 879.209 | BT86: 879.209 | BU86: 949.541 | BV86: 863.315 | BW86: 869.525 | BX86: 883.411 | BY86: 883.411
B87: Total stockholders' equity | D87: 641.334 | E87: 646.342 | F87: 555.172 | G87: 555.172 | H87: 554.845 | I87: 507.372 | J87: 578.732 | L87: 561.117 | M87: 608.871 | N87: 667.503 | O87: 724.394 | P87: 762.401 | Q87: 762.401 | R87: 822.647 | S87: 880.724 | T87: 939.761 | U87: 1003.499 | V87: 1003.499 | W87: 1037.431 | X87: 1073.237 | Y87: 1135.968 | Z87: 964.464 | AA87: 964.464 | AB87: 1016.545 | AC87: 731.4 | AD87: 716.527 | AE87: 774.456 | AF87: 774.456 | AG87: 807.407 | AH87: 895.703 | AI87: 1006.329 | AJ87: 1098.6 | AK87: 1098.6 | AL87: 1188.909 | AM87: 1331.791 | AN87: 1460.812 | AO87: 1581.099 | AP87: 1581.099 | AQ87: 1671.758 | AR87: 1459.953 | AS87: 1618.852 | AT87: 1778.381 | AU87: 1778.381 | AV87: 1926.599 | AW87: 2124.729 | AX87: 2281.011 | AY87: 2489.516 | AZ87: 2489.516 | BA87: 2710.833 | BB87: 2942.592 | BC87: 3249.377 | BD87: 3529.201 | BE87: 3529.201 | BF87: 3793.821 | BG87: 4089.856 | BH87: 4353.054 | BI87: 4625.599 | BJ87: 4625.599 | BK87: 4852.834 | BL87: 5213.652 | BM87: 5592.422 | BN87: 5987.44 | BO87: 5987.44 | BP87: 6411.417 | BQ87: 6787.6 | BR87: 7171.253 | BS87: 7524.011 | BT87: 7524.011 | BU87: 7896.312 | BV87: 8301.257 | BW87: 8781.193 | BX87: 9187.033 | BY87: 9187.033 | BZ87: =BY87+BZ49 | CA87: =BZ87+CA49 | CB87: =CA87+CB49 | CC87: =CB87+CC49 | CD87: =CC87+CD49
B88: Current ratio (x) | C88: =IFERROR(C80/C84,"") | D88: =IFERROR(D80/D84,"") | E88: =IFERROR(E80/E84,"") | F88: =IFERROR(F80/F84,"") | G88: =IFERROR(G80/G84,"") | H88: =IFERROR(H80/H84,"") | I88: =IFERROR(I80/I84,"") | J88: =IFERROR(J80/J84,"") | ... BY88: =IFERROR(BY80/BY84,"")
B90: RATIO ANALYSIS
B91: EBITDA (Operating income + D&A) | C91: =IFERROR(C43+C68,"") | D91: =IFERROR(D43+D68,"") | E91: =IFERROR(E43+E68,"") | F91: =IFERROR(F43+F68,"") | G91: =IFERROR(G43+G68,"") | H91: =IFERROR(H43+H68,"") | I91: =IFERROR(I43+I68,"") | J91: =IFERROR(J43+J68,"") | ... BY91: =IFERROR(BY43+BY68,"") | BZ91: =BZ43+BZ68 | CA91: =CA43+CA68 | CB91: =CB43+CB68 | CC91: =CC43+CC68 | CD91: =CD43+CD68
B92: Return on assets (ROA) | C92: =IFERROR(C49/C83,"") | D92: =IFERROR(D49/D83,"") | E92: =IFERROR(E49/E83,"") | F92: =IFERROR(F49/F83,"") | G92: =IFERROR(G49/G83,"") | H92: =IFERROR(H49/H83,"") | I92: =IFERROR(I49/I83,"") | J92: =IFERROR(J49/J83,"") | ... BY92: =IFERROR(BY49/BY83,"")
B93: Return on equity (ROE) | C93: =IFERROR(C49/C87,"") | D93: =IFERROR(D49/D87,"") | E93: =IFERROR(E49/E87,"") | F93: =IFERROR(F49/F87,"") | G93: =IFERROR(G49/G87,"") | H93: =IFERROR(H49/H87,"") | I93: =IFERROR(I49/I87,"") | J93: =IFERROR(J49/J87,"") | ... CD93: =IFERROR(CD49/CD87,"")
B94: NOPAT = EBIT × (1 − tax) | C94: =IFERROR(C43*(1-C47),"") | D94: =IFERROR(D43*(1-D47),"") | E94: =IFERROR(E43*(1-E47),"") | F94: =IFERROR(F43*(1-F47),"") | G94: =IFERROR(G43*(1-G47),"") | H94: =IFERROR(H43*(1-H47),"") | I94: =IFERROR(I43*(1-I47),"") | J94: =IFERROR(J43*(1-J47),"") | ... BY94: =IFERROR(BY43*(1-BY47),"") | BZ94: =BZ43*(1-BZ47) | CA94: =CA43*(1-CA47) | CB94: =CB43*(1-CB47) | CC94: =CC43*(1-CC47) | CD94: =CD43*(1-CD47)
B95: ROIC = NOPAT / (Equity + Debt − Cash) | C95: =IFERROR(C94/(C87+C85-C79),"") | D95: =IFERROR(D94/(D87+D85-D79),"") | E95: =IFERROR(E94/(E87+E85-E79),"") | F95: =IFERROR(F94/(F87+F85-F79),"") | G95: =IFERROR(G94/(G87+G85-G79),"") | H95: =IFERROR(H94/(H87+H85-H79),"") | I95: =IFERROR(I94/(I87+I85-I79),"") | J95: =IFERROR(J94/(J87+J85-J79),"") | ... BY95: =IFERROR(BY94/(BY87+BY85-BY79),"")
B96: Net debt (Debt − Cash) | C96: =IFERROR(C85-C79,"") | D96: =IFERROR(D85-D79,"") | E96: =IFERROR(E85-E79,"") | F96: =IFERROR(F85-F79,"") | G96: =IFERROR(G85-G79,"") | H96: =IFERROR(H85-H79,"") | I96: =IFERROR(I85-I79,"") | J96: =IFERROR(J85-J79,"") | ... BY96: =IFERROR(BY85-BY79,"")
B97: Net debt / EBITDA (x) | C97: =IFERROR(C96/C91,"") | D97: =IFERROR(D96/D91,"") | E97: =IFERROR(E96/E91,"") | F97: =IFERROR(F96/F91,"") | G97: =IFERROR(G96/G91,"") | H97: =IFERROR(H96/H91,"") | I97: =IFERROR(I96/I91,"") | J97: =IFERROR(J96/J91,"") | ... BY97: =IFERROR(BY96/BY91,"")
B99: NON-GAAP RECONCILIATION — AS REPORTED IN 8-K EARNINGS RELEASES
B100: Copart disclosed non-GAAP net income and non-GAAP diluted EPS in its quarterly earnings press releases (Form 8-K, Item 2.02, Exhibit 99.1) for fiscal 2016–2023 (and a one-off in Q3 FY2014); it reverted to GAAP-only reporting from FY2024. Copart reports no adjusted EBITDA, constant-currency, or non-GAAP free-cash-flow measures.
B101: GAAP net income attributable to Copart, Inc. | T101: 40.877 | AE101: 84.122 | AF101: 270.36 | AG101: 167.28 | AH101: 66.066 | AI101: 90.546 | AJ101: 70.335 | AK101: 394.227 | AL101: 77.515 | AM101: 103.256 | AN101: 127.348 | AO101: 109.748 | AP101: 417.867 | AQ101: 114.083 | AR101: 131.373 | AS101: 192.741 | AT101: 153.496 | AU101: 591.693 | AV101: 218.18 | AW101: 168.707 | AX101: 147.487 | AY101: 165.533 | AZ101: 699.907 | BA101: 200.285 | BB101: 193.44 | BC101: 286.796 | BD101: 255.974 | BE101: 936.495 | BF101: 260.363 | BG101: 287.412 | BH101: 278.62 | BI101: 263.735 | BJ101: 1090.13 | BK101: 245.848 | BL101: 293.677 | BM101: 350.431 | BN101: 347.785 | BO101: 1237.741
B102: Deemed repatriation of foreign earnings, net of tax | AM102: 10 | AN102: 1 | AO102: -2.87 | AP102: 8.131
B103: Tax Cuts & Jobs Act / discrete tax items, net of tax
B104: Disposal of non-operating assets, net of tax | AL104: 2.994 | AP104: 2.994 | AR104: -1.598
B105: Impairment of long-lived assets, net of tax | T105: 19.402 | AJ105: 12.339 | AK105: 12.339 | AO105: 0.916 | AP105: 0.916 | AU105: -1.598
B106: Acquisition-related fees & integration charges, net of tax | AJ106: 1.241 | AK106: 1.241 | AO106: 1.521 | AP106: 1.521 | BD106: 2.713 | BE106: 2.713
B107: Reserve for legacy sales-tax liabilities, net of tax | AO107: 1.017 | AP107: 1.017 | AT107: 0.978 | AU107: 0.978
B108: Foreign currency-related (gains) losses, net of tax | AE108: -3.521 | AF108: -4.86 | AG108: -2.847 | AH108: 2.72 | AI108: -0.167 | AJ108: -0.585 | AK108: -0.88 | AL108: 0.308 | AM108: 0.768 | AN108: -0.261 | AO108: -0.415 | AP108: 0.452 | AQ108: -0.345 | AR108: -0.056 | AS108: 0.094 | AT108: 0.048 | AU108: -0.256 | AV108: -0.263 | AW108: -0.416 | AX108: -0.49 | AY108: -0.268 | AZ108: -1.436 | BA108: -0.19 | BB108: 0.238 | BC108: 0.303 | BD108: -0.422 | BE108: 0.073
B109: Stock-option tax effects (ASU 2016-09), net of tax | AE109: -11.594 | AF109: -12.44 | AG109: -101.395 | AH109: -1.347 | AI109: -4.007 | AJ109: -0.428 | AK109: -107.177 | AL109: -3.767 | AM109: -2.596 | AN109: -3.085 | AO109: -11.821 | AP109: -21.269 | AQ109: -0.175 | AR109: -4.847 | AS109: -29.074 | AT109: -12.007 | AU109: -46.103 | AV109: -62.365 | AW109: -14.829 | AX109: -8.768 | AY109: -6.586 | AZ109: -92.548 | BA109: -11.773 | BB109: -2.167 | BC109: -4.91 | BD109: -10.962 | BE109: -29.812 | BF109: -2.987 | BG109: -3.965 | BH109: -2.244 | BI109: -5.077 | BJ109: -14.274 | BK109: -0.625 | BL109: -0.115 | BM109: -4.37 | BN109: -15.911 | BO109: -21.021
...

Sheet Bull-Base-Bear
B2: COPART — Bull / Base / Bear P&L Summary
B3: Linked to Model — toggle scenario via the Model tab.
C5: FY2025A | D5: FY2026E | E5: FY2027E | F5: FY2028E | G5: FY2029E | H5: FY2030E
B6: Revenue | C6: =Model!BY38 | D6: =Model!BZ38 | E6: =Model!CA38 | F6: =Model!CB38 | G6: =Model!CC38 | H6: =Model!CD38
B7: Operating income | C7: =Model!BY43 | D7: =Model!BZ43 | E7: =Model!CA43 | F7: =Model!CB43 | G7: =Model!CC43 | H7: =Model!CD43
B8: Net income attrib. to Copart | C8: =Model!BY49 | D8: =Model!BZ49 | E8: =Model!CA49 | F8: =Model!CB49 | G8: =Model!CC49 | H8: =Model!CD49
B9: EPS — diluted ($) | C9: =Model!BY54 | D9: =Model!BZ54 | E9: =Model!CA54 | F9: =Model!CB54 | G9: =Model!CC54 | H9: =Model!CD54
B10: Free cash flow | C10: =Model!BY74 | D10: =Model!BZ74 | E10: =Model!CA74 | F10: =Model!CB74 | G10: =Model!CC74 | H10: =Model!CD74
B12: Active scenario: | C12: =Model!$CF$2

Sheet DCF
B2: COPART — Unlevered DCF (off model forecast FCF)
B3: Free cash flow linked from the Model forecast columns. Assumptions in blue are editable.
B5: WACC | C5: 0.09
B6: Terminal growth (g) | C6: 0.03
C8: FY2026E | D8: FY2027E | E8: FY2028E | F8: FY2029E | G8: FY2030E
B9: Free cash flow (US$m) | C9: =Model!BZ74 | D9: =Model!CA74 | E9: =Model!CB74 | F9: =Model!CC74 | G9: =Model!CD74
B10: Discount factor | C10: =1/(1+$C$5)^1 | D10: =1/(1+$C$5)^2 | E10: =1/(1+$C$5)^3 | F10: =1/(1+$C$5)^4 | G10: =1/(1+$C$5)^5
B11: PV of FCF | C11: =C9*C10 | D11: =D9*D10 | E11: =E9*E10 | F11: =F9*F10 | G11: =G9*G10
B13: Terminal value (Gordon) | C13: =G9*(1+$C$6)/($C$5-$C$6)
B14: PV of terminal value | C14: =C13*G10
B15: Enterprise value | C15: =SUM(C11:G11)+C14
B16: − Net debt (FY latest, Model) | C16: =Model!BY96
B17: Equity value | C17: =C15-C16
B18: ÷ Diluted shares (m, FY latest) | C18: =Model!BY51
B19: Implied value per share ($) | C19: =C17/C18
