Workbook

Sheet Model
CU1: SCENARIO SWITCH ▼ (Bull / Base / Bear) — drives all scenario-linked forecast drivers
B2: Copart, Inc. (NASDAQ: CPRT) — 3-Statement Financial Model | CU2: Base
B3: US GAAP as reported · fiscal year ends 31-July (FY2026 = Aug-2025 to Jul-2026) · USD millions (per-share data in USD; shares and per-share data restated for the 2-for-1 splits of Mar-2012, Apr-2017, Nov-2022 and Aug-2023) · Source: Copart Forms 10-K / 10-Q and Form 8-K earnings releases (Ex. 99.1), SEC EDGAR CIK 0000900075
B4: Basis notes: FY2006–12 annual; quarterly from FY2013 (Q4 = 10-K fiscal year less 10-Q nine-month YTD). ASC 606 adopted FY2019 (modified retrospective, no recast); ASC 842 leases from FY2020. Segments: US / International from the FY2016 10-K (FY2014+ recast). Copart issues no financial guidance: FY2027E–31E are model estimates. STANDALONE — the pending ACV Auctions acquisition (merger agreement 10-Sep-2026, $10.50/share cash tender) is excluded.
CW5: Forecast | CX5: Historical | CY5: Historical | CZ5: Historical
B6: (USDm; FY = Aug–Jul) | C6: 2006 | D6: 2007 | E6: 2008 | F6: 2009 | G6: 2010 | H6: 2011 | I6: 2012 | J6: Q1/13 | K6: Q2/13 | L6: 1H/13 | M6: Q3/13 | N6: Q4/13 | O6: 2013 | P6: Q1/14 | Q6: Q2/14 | R6: 1H/14 | S6: Q3/14 | T6: Q4/14 | U6: 2014 | V6: Q1/15 | W6: Q2/15 | X6: 1H/15 | Y6: Q3/15 | Z6: Q4/15 | AA6: 2015 | AB6: Q1/16 | AC6: Q2/16 | AD6: 1H/16 | AE6: Q3/16 | AF6: Q4/16 | AG6: 2016 | AH6: Q1/17 | AI6: Q2/17 | AJ6: 1H/17 | AK6: Q3/17 | AL6: Q4/17 | AM6: 2017 | AN6: Q1/18 | AO6: Q2/18 | AP6: 1H/18 | AQ6: Q3/18 | AR6: Q4/18 | AS6: 2018 | AT6: Q1/19 | AU6: Q2/19 | AV6: 1H/19 | AW6: Q3/19 | AX6: Q4/19 | AY6: 2019 | AZ6: Q1/20 | BA6: Q2/20 | BB6: 1H/20 | BC6: Q3/20 | BD6: Q4/20 | BE6: 2020 | BF6: Q1/21 | BG6: Q2/21 | BH6: 1H/21 | BI6: Q3/21 | BJ6: Q4/21 | BK6: 2021 | BL6: Q1/22 | BM6: Q2/22 | BN6: 1H/22 | BO6: Q3/22 | BP6: Q4/22 | BQ6: 2022 | BR6: Q1/23 | BS6: Q2/23 | BT6: 1H/23 | BU6: Q3/23 | BV6: Q4/23 | BW6: 2023 | BX6: Q1/24 | BY6: Q2/24 | BZ6: 1H/24 | CA6: Q3/24 | CB6: Q4/24 | CC6: 2024 | CD6: Q1/25 | CE6: Q2/25 | CF6: 1H/25 | CG6: Q3/25 | CH6: Q4/25 | CI6: 2025 | CJ6: Q1/26 | CK6: Q2/26 | CL6: 1H/26 | CM6: Q3/26 | CN6: Q4/26 | CO6: 2026 | CP6: 2027E | CQ6: 2028E | CR6: 2029E | CS6: 2030E | CT6: 2031E | CU6: Modelling Notes | CW6: 5Y CAGR | CX6: 5Y CAGR | CY6: 10Y CAGR | CZ6: 20Y CAGR
CW7: 26-'31 | CX7: 21-'26 | CY7: 16-'26 | CZ7: 06-'26
B9: REVENUE BUILD — US / INTERNATIONAL SEGMENTS × UNITS (service revenues + vehicle sales) | CU9: REVENUE BUILD — modelling logic (Copart reports two operating segments: United States and International; the build replaces RBA's GTV × take-rate build) | DC9: SCENARIO INPUT TABLE — driver assumptions per Bull / Base / Bear | DD9: Bull | DE9: Base | DF9: Bear | DG9: Bull / Bear = Base + Δ (Δ inputs on each block header). Copart issues no guidance — all cases are model assumptions.
B11: United States segment | CU11: UNITED STATES — modelling logic | DC11: US_unitGrowth (US units sold y/y) | DD11: 0.02 | DE11: Δ → | DF11: -0.03 | DG11: US: insurance total-loss frequency (vehicle age, repair cost inflation), insurer share gains, non-insurance (dealer, fleet, Blue Car) volumes.
B12: Service revenues (USDm) | AM12: 1128.99 | AN12: 331.391 | AO12: 355.542 | AP12: =AN12+AO12 -> 686.933 | AQ12: 356.252 | AR12: 342.053 | AS12: 1385.238 | AT12: 343.573 | AU12: 362.023 | AV12: =AT12+AU12 -> 705.596 | AW12: 416.874 | AX12: 414.961 | AY12: 1537.431 | AZ12: 430.803 | BA12: 447.345 | BB12: =AZ12+BA12 -> 878.148 | BC12: 431.875 | BD12: 404.701 | BE12: 1714.724 | BF12: 450.235 | BG12: 465.423 | BH12: =BF12+BG12 -> 915.658 | BI12: 550.338 | BJ12: 551.508 | BK12: 2017.504 | BL12: 590.758 | BM12: 630.707 | BN12: =BL12+BM12 -> 1221.465 | BO12: 678.865 | BP12: 632.835 | BQ12: 2533.165 | BR12: 651.657 | BS12: 705.733 | BT12: =BR12+BS12 -> 1357.39 | BU12: 752.077 | BV12: 732.174 | BW12: 2841.641 | BX12: 762.524 | BY12: 756.036 | BZ12: =BX12+BY12 -> 1518.56 | CA12: 830.68 | CB12: 776.861 | CC12: 3126.102 | CD12: 859.99 | CE12: 868.13 | CF12: =CD12+CE12 -> 1728.12 | CG12: 898.625 | CH12: 824.813 | CI12: 3451.558 | CJ12: 855.534 | CK12: 819.467 | CL12: =CJ12+CK12 -> 1675.001 | CM12: 895.464 | CN12: 817.822 | CO12: 3388.287 | CP12: =CO12*(1+CP13)*(1+CP14) -> 3524.835 | CQ12: =CP12*(1+CQ13)*(1+CQ14) -> 3721.3445 | CR12: =CQ12*(1+CR13)*(1+CR14) -> 3947.9744 | CS12: =CR12*(1+CS13)*(1+CS14) -> 4188.406 | CT12: =CS12*(1+CT13)*(1+CT14) -> 4443.48 | CU12: FY2027E+: prior year × (1 + units sold growth, scenario lever) × (1 + service revenue per unit growth). | CW12: =IFERROR((CT12/CO12)^(1/5)-1,"n/m") -> 0.055719655 | CX12: =IFERROR((CO12/BK12)^(1/5)-1,"n/m") -> 0.1092595 | CY12: =IFERROR((CO12/AG12)^(1/10)-1,"n/m") -> n/m | CZ12: =IFERROR((CO12/C12)^(1/20)-1,"n/m") -> n/m | DC12: 2027E | DD12: =DE12+$DD$11 -> 0.03 | DE12: 0.01 | DF12: =DE12+$DF$11 -> -0.02
B13: Units sold y/y % (disclosed in MD&A; forecast = scenario lever) | CP13: =CHOOSE(MATCH($CU$2,{"Bull","Base","Bear"},0),$DD$12,$DE$12,$DF$12) -> 0.01 | CQ13: =CHOOSE(MATCH($CU$2,{"Bull","Base","Bear"},0),$DD$13,$DE$13,$DF$13) -> 0.025 | CR13: =CHOOSE(MATCH($CU$2,{"Bull","Base","Bear"},0),$DD$14,$DE$14,$DF$14) -> 0.03 | CS13: =CHOOSE(MATCH($CU$2,{"Bull","Base","Bear"},0),$DD$15,$DE$15,$DF$15) -> 0.03 | CT13: =CHOOSE(MATCH($CU$2,{"Bull","Base","Bear"},0),$DD$16,$DE$16,$DF$16) -> 0.03 | CU13: 2027E–2031E: scenario lever (US_unitGrowth, Bull/Base/Bear table →). | DC13: 2028E | DD13: =DE13+$DD$11 -> 0.045 | DE13: 0.025 | DF13: =DE13+$DF$11 -> -0.005
B14: Service revenue per unit y/y % (implied price / mix; forecast input) | C14: =IF(ISNUMBER(C13),IFERROR((1+C15)/(1+C13)-1,""),"") | D14: =IF(ISNUMBER(D13),IFERROR((1+D15)/(1+D13)-1,""),"") | E14: =IF(ISNUMBER(E13),IFERROR((1+E15)/(1+E13)-1,""),"") | F14: =IF(ISNUMBER(F13),IFERROR((1+F15)/(1+F13)-1,""),"") | G14: =IF(ISNUMBER(G13),IFERROR((1+G15)/(1+G13)-1,""),"") | H14: =IF(ISNUMBER(H13),IFERROR((1+H15)/(1+H13)-1,""),"") | I14: =IF(ISNUMBER(I13),IFERROR((1+I15)/(1+I13)-1,""),"") | J14: =IF(ISNUMBER(J13),IFERROR((1+J15)/(1+J13)-1,""),"") | ... CO14: =IF(ISNUMBER(CO13),IFERROR((1+CO15)/(1+CO13)-1,""),"") | CP14: =CHOOSE(MATCH($CU$2,{"Bull","Base","Bear"},0),$DD$26,$DE$26,$DF$26) -> 0.03 | CQ14: =CHOOSE(MATCH($CU$2,{"Bull","Base","Bear"},0),$DD$27,$DE$27,$DF$27) -> 0.03 | CR14: =CHOOSE(MATCH($CU$2,{"Bull","Base","Bear"},0),$DD$28,$DE$28,$DF$28) -> 0.03 | CS14: =CHOOSE(MATCH($CU$2,{"Bull","Base","Bear"},0),$DD$29,$DE$29,$DF$29) -> 0.03 | CT14: =CHOOSE(MATCH($CU$2,{"Bull","Base","Bear"},0),$DD$30,$DE$30,$DF$30) -> 0.03 | CU14: 2027E–2031E: scenario lever (US_RPU) — buyer / seller fee pricing, ASP-linked fees, mix of purchase vs fee units. | DC14: 2029E | DD14: =DE14+$DD$11 -> 0.05 | DE14: 0.03 | DF14: =DE14+$DF$11 -> 0
B15: Service revenues y/y % | D15: =IFERROR(D12/C12-1,"") | E15: =IFERROR(E12/D12-1,"") | F15: =IFERROR(F12/E12-1,"") | G15: =IFERROR(G12/F12-1,"") | H15: =IFERROR(H12/G12-1,"") | I15: =IFERROR(I12/H12-1,"") | O15: =IFERROR(O12/I12-1,"") | P15: =IFERROR(P12/J12-1,"") | Q15: =IFERROR(Q12/K12-1,"") | R15: =IFERROR(R12/L12-1,"") | S15: =IFERROR(S12/M12-1,"") | T15: =IFERROR(T12/N12-1,"") | U15: =IFERROR(U12/O12-1,"") | V15: =IFERROR(V12/P12-1,"") | ... CO15: =IFERROR(CO12/CI12-1,"") -> -0.018331142 | CP15: =IFERROR(CP12/CO12-1,"") -> 0.0403 | CQ15: =IFERROR(CQ12/CP12-1,"") -> 0.05575 | CR15: =IFERROR(CR12/CQ12-1,"") -> 0.0609 | CS15: =IFERROR(CS12/CR12-1,"") -> 0.0609 | CT15: =IFERROR(CT12/CS12-1,"") -> 0.0609 | DC15: 2030E | DD15: =DE15+$DD$11 -> 0.05 | DE15: 0.03 | DF15: =DE15+$DF$11 -> 0
B16: Vehicle sales (USDm; purchase-model units) | AM16: 64.198 | AN16: 19.714 | AO16: 29.593 | AP16: =AN16+AO16 -> 49.307 | AQ16: 29.029 | AR16: 27.448 | AS16: 105.784 | AT16: 27.636 | AU16: 28.049 | AV16: =AT16+AU16 -> 55.685 | AW16: 31.325 | AX16: 32.128 | AY16: 119.138 | AZ16: 33.361 | BA16: 35.392 | BB16: =AZ16+BA16 -> 68.753 | BC16: 35.323 | BD16: 41.886 | BE16: 145.962 | BF16: 47.02 | BG16: 52.5 | BH16: =BF16+BG16 -> 99.52 | BI16: 71.615 | BJ16: 83.433 | BK16: 254.568 | BL16: 87.703 | BM16: 96.679 | BN16: =BL16+BM16 -> 184.382 | BO16: 111.385 | BP16: 116.218 | BQ16: 411.985 | BR16: 97.192 | BS16: 82.196 | BT16: =BR16+BS16 -> 179.388 | BU16: 81.681 | BV16: 86.938 | BW16: 348.007 | BX16: 78.382 | BY16: 74.69 | BZ16: =BX16+BY16 -> 153.072 | CA16: 88.236 | CB16: 97.326 | CC16: 338.633 | CD16: 87.549 | CE16: 106.715 | CF16: =CD16+CE16 -> 194.264 | CG16: 107.832 | CH16: 101.449 | CI16: 403.546 | CJ16: 97.08 | CK16: 102.153 | CL16: =CJ16+CK16 -> 199.233 | CM16: 107.398 | CN16: 112.512 | CO16: 419.143 | CP16: =CO16*(1+CP17) -> 435.90872 | CQ16: =CP16*(1+CQ17) -> 453.34507 | CR16: =CQ16*(1+CR17) -> 471.47887 | CS16: =CR16*(1+CS17) -> 490.33803 | CT16: =CS16*(1+CT17) -> 509.95155 | CU16: Vehicle sales = units sold under the purchase model (gross revenue); forecast grows with the input below. | DC16: 2031E | DD16: =DE16+$DD$11 -> 0.05 | DE16: 0.03 | DF16: =DE16+$DF$11 -> 0
B17: Vehicle sales y/y % (forecast input) | D17: =IFERROR(D16/C16-1,"") | E17: =IFERROR(E16/D16-1,"") | F17: =IFERROR(F16/E16-1,"") | G17: =IFERROR(G16/F16-1,"") | H17: =IFERROR(H16/G16-1,"") | I17: =IFERROR(I16/H16-1,"") | O17: =IFERROR(O16/I16-1,"") | P17: =IFERROR(P16/J16-1,"") | Q17: =IFERROR(Q16/K16-1,"") | R17: =IFERROR(R16/L16-1,"") | S17: =IFERROR(S16/M16-1,"") | T17: =IFERROR(T16/N16-1,"") | U17: =IFERROR(U16/O16-1,"") | V17: =IFERROR(V16/P16-1,"") | ... CO17: =IFERROR(CO16/CI16-1,"") -> 0.038649869 | CP17: 0.04 | CQ17: 0.04 | CR17: 0.04 | CS17: 0.04 | CT17: 0.04
B18: Total US revenue | C18: 526.456 | D18: 541.801 | E18: 591.6 | F18: 591.284 | G18: 602.794 | H18: 674.742 | I18: 724.869 | U18: 893.659 | AA18: 902.88 | AB18: 230.465 | AC18: 238.261 | AD18: =AB18+AC18 -> 468.726 | AE18: 279.21 | AF18: 268.1 | AG18: 1016.036 | AH18: 285.062 | AI18: 286.911 | AJ18: =AH18+AI18 -> 571.973 | AK18: 307.12 | AL18: 314.095 | AM18: =AM12+AM16 -> 1193.188 | AN18: =AN12+AN16 -> 351.105 | AO18: =AO12+AO16 -> 385.135 | AP18: =AP12+AP16 -> 736.24 | AQ18: =AQ12+AQ16 -> 385.281 | AR18: =AR12+AR16 -> 369.501 | AS18: =AS12+AS16 -> 1491.022 | AT18: =AT12+AT16 -> 371.209 | ... CT18: =CT12+CT16 -> 4953.4315 | CW18: =IFERROR((CT18/CO18)^(1/5)-1,"n/m") -> 0.054034551 | CX18: =IFERROR((CO18/BK18)^(1/5)-1,"n/m") -> 0.10877128 | CY18: =IFERROR((CO18/AG18)^(1/10)-1,"n/m") -> 0.14122764 | CZ18: =IFERROR((CO18/C18)^(1/20)-1,"n/m") -> 0.10398581 | DC18: INTL_unitGrowth (International units sold y/y) | DD18: 0.02 | DE18: Δ → | DF18: -0.03 | DG18: International: UK / Germany / Brazil market-share gains, total-loss adoption in continental Europe, new country entries.
B19: Total revenue y/y % | D19: =IFERROR(D18/C18-1,"") -> 0.029147735 | E19: =IFERROR(E18/D18-1,"") -> 0.091913821 | F19: =IFERROR(F18/E18-1,"") -> -0.00053414469 | G19: =IFERROR(G18/F18-1,"") -> 0.019466111 | H19: =IFERROR(H18/G18-1,"") -> 0.11935753 | I19: =IFERROR(I18/H18-1,"") -> 0.074290618 | O19: =IFERROR(O18/I18-1,"") -> -1 | P19: =IFERROR(P18/J18-1,"") | Q19: =IFERROR(Q18/K18-1,"") | R19: =IFERROR(R18/L18-1,"") | S19: =IFERROR(S18/M18-1,"") | T19: =IFERROR(T18/N18-1,"") | U19: =IFERROR(U18/O18-1,"") | V19: =IFERROR(V18/P18-1,"") | ... CO19: =IFERROR(CO18/CI18-1,"") -> -0.012366463 | CP19: =IFERROR(CP18/CO18-1,"") -> 0.040266974 | CQ19: =IFERROR(CQ18/CP18-1,"") -> 0.054016598 | CR19: =IFERROR(CR18/CQ18-1,"") -> 0.058630391 | CS19: =IFERROR(CS18/CR18-1,"") -> 0.058670333 | CT19: =IFERROR(CT18/CS18-1,"") -> 0.058709655 | DC19: 2027E | DD19: =DE19+$DD$18 -> 0.08 | DE19: 0.06 | DF19: =DE19+$DF$18 -> 0.03
B20: Segment operating income (historical disclosure) | U20: 223.384 | AA20: 289.991 | AB20: 72.939 | AC20: 79.053 | AD20: =AB20+AC20 -> 151.992 | AE20: 104.914 | AF20: 90.803 | AG20: 347.709 | AH20: 88.982 | AI20: 93.592 | AJ20: =AH20+AI20 -> 182.574 | AK20: 119.117 | AL20: 94.669 | AM20: 396.36 | AN20: 106.019 | AO20: 133.01 | AP20: =AN20+AO20 -> 239.029 | AQ20: 150.888 | AR20: 124.97 | AS20: 514.887 | AT20: 130.292 | AU20: 145.402 | AV20: =AT20+AU20 -> 275.694 | AW20: 188.258 | AX20: 173.516 | AY20: 637.468 | AZ20: 189.05 | BA20: 188.989 | BB20: =AZ20+BA20 -> 378.039 | BC20: 178.82 | BD20: 187.696 | BE20: 743.179 | BF20: 221.591 | BG20: 229.452 | BH20: =BF20+BG20 -> 451.043 | BI20: 296.726 | BJ20: 275.785 | BK20: 1023.555 | BL20: 294.949 | BM20: 312.646 | BN20: =BL20+BM20 -> 607.595 | BO20: 340.437 | BP20: 299.537 | BQ20: 1247.569 | BR20: 282.628 | BS20: 336.164 | BT20: =BR20+BS20 -> 618.792 | BU20: 384.791 | BV20: 364.515 | BW20: 1368.097 | BX20: 362.291 | BY20: 347.338 | BZ20: =BX20+BY20 -> 709.629 | CA20: 392.931 | CB20: 325.474 | CC20: 1428.034 | CD20: 355.059 | CE20: 375.893 | CF20: =CD20+CE20 -> 730.952 | CG20: 392.465 | CH20: 357.468 | CI20: 1480.886 | CJ20: 374.972 | CK20: 341.472 | CL20: =CJ20+CK20 -> 716.444 | CM20: 390.445 | CN20: 312.15 | CO20: 1419.04 | CU20: Segment profit is disclosed but not forecast (consolidated cost drivers below). | DC20: 2028E | DD20: =DE20+$DD$18 -> 0.08 | DE20: 0.06 | DF20: =DE20+$DF$18 -> 0.03
B21: Segment operating margin % | C21: =IF(ISNUMBER(C20),IFERROR(C20/C18,""),"") | D21: =IF(ISNUMBER(D20),IFERROR(D20/D18,""),"") | E21: =IF(ISNUMBER(E20),IFERROR(E20/E18,""),"") | F21: =IF(ISNUMBER(F20),IFERROR(F20/F18,""),"") | G21: =IF(ISNUMBER(G20),IFERROR(G20/G18,""),"") | H21: =IF(ISNUMBER(H20),IFERROR(H20/H18,""),"") | I21: =IF(ISNUMBER(I20),IFERROR(I20/I18,""),"") | J21: =IF(ISNUMBER(J20),IFERROR(J20/J18,""),"") | ... CO21: =IF(ISNUMBER(CO20),IFERROR(CO20/CO18,""),"") -> 0.37270285 | DC21: 2029E | DD21: =DE21+$DD$18 -> 0.075 | DE21: 0.055 | DF21: =DE21+$DF$18 -> 0.025
B22: Segment depreciation & amortization | U22: 44.516 | AA22: 36.238 | AB22: 9.049 | AC22: 9.286 | AD22: =AB22+AC22 -> 18.335 | AE22: 10.048 | AF22: 10.7 | AG22: 39.083 | AH22: 12.386 | AI22: 12.667 | AJ22: =AH22+AI22 -> 25.053 | AK22: 10.904 | AL22: 11.55 | AM22: 47.507 | AN22: 13.529 | AO22: 14.054 | AP22: =AN22+AO22 -> 27.583 | AQ22: 14.189 | AR22: 26.007 | AS22: 67.779 | AT22: 19.392 | AU22: 17.877 | AV22: =AT22+AU22 -> 37.269 | AW22: 18.636 | AX22: 19.36 | AY22: 75.265 | AZ22: 20.567 | BA22: 21.728 | BB22: =AZ22+BA22 -> 42.295 | BC22: 23.764 | BD22: 24.717 | BE22: 90.818 | BF22: 26.162 | BG22: 27.745 | BH22: =BF22+BG22 -> 53.907 | BI22: 28.161 | BJ22: 25.697 | BK22: 107.765 | BL22: 27.725 | BM22: 29.316 | BN22: =BL22+BM22 -> 57.041 | BO22: 31.609 | BP22: 31.98 | BQ22: 120.635 | BR22: 34.935 | BS22: 34.121 | BT22: =BR22+BS22 -> 69.056 | BU22: 32.918 | BV22: 33.83 | BW22: 135.804 | BX22: 36.936 | BY22: 38.344 | BZ22: =BX22+BY22 -> 75.28 | CA22: 43.477 | CB22: 42.929 | CC22: 161.685 | CD22: 45.915 | CE22: 46.455 | CF22: =CD22+CE22 -> 92.37 | CG22: 46.461 | CH22: 45.195 | CI22: 184.026 | CJ22: 45.409 | CK22: 46.829 | CL22: =CJ22+CK22 -> 92.238 | CM22: 50.259 | CN22: 52.252 | CO22: 194.749 | DC22: 2030E | DD22: =DE22+$DD$18 -> 0.07 | DE22: 0.05 | DF22: =DE22+$DF$18 -> 0.02
B23: Segment capital expenditures (incl. acquired productive assets) | U23: 59.724 | AA23: 64.769 | AB23: 19.321 | AC23: 56.997 | AD23: =AB23+AC23 -> 76.318 | AE23: 49.866 | AF23: 27.267 | AG23: 153.451 | AH23: 36.521 | AI23: 51.541 | AJ23: =AH23+AI23 -> 88.062 | AK23: 40.872 | AL23: 188.712 | AM23: 317.646 | AN23: 38.905 | AO23: 56.804 | AP23: =AN23+AO23 -> 95.709 | AQ23: 57.028 | AR23: 103.131 | AS23: 255.868 | AT23: 35.253 | AU23: 66.901 | AV23: =AT23+AU23 -> 102.154 | AW23: 107.569 | AX23: 102.104 | AY23: 311.827 | AZ23: 113.266 | BA23: 261.258 | BB23: =AZ23+BA23 -> 374.524 | BC23: 86.441 | BD23: 107.701 | BE23: 568.773 | BF23: 122.459 | BG23: 121.595 | BH23: =BF23+BG23 -> 244.054 | BI23: 59.006 | BJ23: 87.646 | BK23: 390.706 | BL23: 54.272 | BM23: 86.788 | BN23: =BL23+BM23 -> 141.06 | BO23: 64.397 | BP23: 92.175 | BQ23: 297.632 | BR23: 136.283 | BS23: 89.428 | BT23: =BR23+BS23 -> 225.711 | BU23: 79.633 | BV23: 67.846 | BW23: 373.19 | BX23: 216.131 | BY23: 83.861 | BZ23: =BX23+BY23 -> 299.992 | CA23: 72.186 | CB23: 119.319 | CC23: 491.497 | CD23: 211.917 | CE23: 153.212 | CF23: =CD23+CE23 -> 365.129 | CG23: 62.906 | CH23: 62.93 | CI23: 490.965 | CJ23: 71.458 | CK23: 58.875 | CL23: =CJ23+CK23 -> 130.333 | CM23: 75.213 | CN23: 51.419 | CO23: 256.965 | DC23: 2031E | DD23: =DE23+$DD$18 -> 0.07 | DE23: 0.05 | DF23: =DE23+$DF$18 -> 0.02
B25: International segment (UK, Canada, Germany, Brazil, Spain, Ireland, Finland, UAE, Oman, Bahrain) | CU25: INTERNATIONAL — modelling logic | DC25: US_RPU (US service revenue per unit y/y) | DD25: 0.01 | DE25: Δ → | DF25: -0.015 | DG25: Per-unit fees track used-vehicle / salvage ASPs (buyer fees are ASP-linked) plus pricing actions and purchase-vs-fee mix.
B26: Service revenues (USDm) | AM26: 157.262 | AN26: 42.734 | AO26: 46.412 | AP26: =AN26+AO26 -> 89.146 | AQ26: 54.51 | AR26: 49.608 | AS26: 193.264 | AT26: 51.233 | AU26: 54.784 | AV26: =AT26+AU26 -> 106.017 | AW26: 56.808 | AX26: 55.438 | AY26: 218.263 | AZ26: 57.053 | BA26: 62.689 | BB26: =AZ26+BA26 -> 119.742 | BC26: 59.707 | BD26: 52.967 | BE26: 232.416 | BF26: 65.137 | BG26: 67.178 | BH26: =BF26+BG26 -> 132.315 | BI26: 73.508 | BJ26: 68.54 | BK26: 274.363 | BL26: 77.06 | BM26: 80.383 | BN26: =BL26+BM26 -> 157.443 | BO26: 87.451 | BP26: 74.981 | BQ26: 319.875 | BR26: 75.183 | BS26: 84.064 | BT26: =BR26+BS26 -> 159.247 | BU26: 95.172 | BV26: 102.068 | BW26: 356.487 | BX26: 97.012 | BY26: 105.709 | BZ26: =BX26+BY26 -> 202.721 | CA26: 115.95 | CB26: 116.23 | CC26: 434.9 | CD26: 126.346 | CE26: 123.151 | CF26: =CD26+CE26 -> 249.497 | CG26: 136.211 | CH26: 131.396 | CI26: 517.104 | CJ26: 136.311 | CK26: 132.584 | CL26: =CJ26+CK26 -> 268.895 | CM26: 160.616 | CN26: 151.722 | CO26: 581.233 | CP26: =CO26*(1+CP27)*(1+CP28) -> 634.59019 | CQ26: =CP26*(1+CQ27)*(1+CQ28) -> 692.84557 | CR26: =CQ26*(1+CR27)*(1+CR28) -> 752.88064 | CS26: =CR26*(1+CS27)*(1+CS28) -> 814.24041 | CT26: =CS26*(1+CT27)*(1+CT28) -> 880.601 | CU26: FY2027E+: prior year × (1 + units sold growth, scenario lever) × (1 + service revenue per unit growth). | CW26: =IFERROR((CT26/CO26)^(1/5)-1,"n/m") -> 0.086640237 | CX26: =IFERROR((CO26/BK26)^(1/5)-1,"n/m") -> 0.16199683 | CY26: =IFERROR((CO26/AG26)^(1/10)-1,"n/m") -> n/m | CZ26: =IFERROR((CO26/C26)^(1/20)-1,"n/m") -> n/m | DC26: 2027E | DD26: =DE26+$DD$25 -> 0.04 | DE26: 0.03 | DF26: =DE26+$DF$25 -> 0.015
B27: Units sold y/y % (disclosed in MD&A; forecast = scenario lever) | CP27: =CHOOSE(MATCH($CU$2,{"Bull","Base","Bear"},0),$DD$19,$DE$19,$DF$19) -> 0.06 | CQ27: =CHOOSE(MATCH($CU$2,{"Bull","Base","Bear"},0),$DD$20,$DE$20,$DF$20) -> 0.06 | CR27: =CHOOSE(MATCH($CU$2,{"Bull","Base","Bear"},0),$DD$21,$DE$21,$DF$21) -> 0.055 | CS27: =CHOOSE(MATCH($CU$2,{"Bull","Base","Bear"},0),$DD$22,$DE$22,$DF$22) -> 0.05 | CT27: =CHOOSE(MATCH($CU$2,{"Bull","Base","Bear"},0),$DD$23,$DE$23,$DF$23) -> 0.05 | CU27: 2027E–2031E: scenario lever (INTL_unitGrowth, Bull/Base/Bear table →). | DC27: 2028E | DD27: =DE27+$DD$25 -> 0.04 | DE27: 0.03 | DF27: =DE27+$DF$25 -> 0.015
B28: Service revenue per unit y/y % (implied price / mix; forecast input) | C28: =IF(ISNUMBER(C27),IFERROR((1+C29)/(1+C27)-1,""),"") | D28: =IF(ISNUMBER(D27),IFERROR((1+D29)/(1+D27)-1,""),"") | E28: =IF(ISNUMBER(E27),IFERROR((1+E29)/(1+E27)-1,""),"") | F28: =IF(ISNUMBER(F27),IFERROR((1+F29)/(1+F27)-1,""),"") | G28: =IF(ISNUMBER(G27),IFERROR((1+G29)/(1+G27)-1,""),"") | H28: =IF(ISNUMBER(H27),IFERROR((1+H29)/(1+H27)-1,""),"") | I28: =IF(ISNUMBER(I27),IFERROR((1+I29)/(1+I27)-1,""),"") | J28: =IF(ISNUMBER(J27),IFERROR((1+J29)/(1+J27)-1,""),"") | ... CO28: =IF(ISNUMBER(CO27),IFERROR((1+CO29)/(1+CO27)-1,""),"") | CP28: 0.03 | CQ28: 0.03 | CR28: 0.03 | CS28: 0.03 | CT28: 0.03 | CU28: Input: fee pricing and mix (International units carry lower fees per unit than the US). | DC28: 2029E | DD28: =DE28+$DD$25 -> 0.04 | DE28: 0.03 | DF28: =DE28+$DF$25 -> 0.015
B29: Service revenues y/y % | D29: =IFERROR(D26/C26-1,"") | E29: =IFERROR(E26/D26-1,"") | F29: =IFERROR(F26/E26-1,"") | G29: =IFERROR(G26/F26-1,"") | H29: =IFERROR(H26/G26-1,"") | I29: =IFERROR(I26/H26-1,"") | O29: =IFERROR(O26/I26-1,"") | P29: =IFERROR(P26/J26-1,"") | Q29: =IFERROR(Q26/K26-1,"") | R29: =IFERROR(R26/L26-1,"") | S29: =IFERROR(S26/M26-1,"") | T29: =IFERROR(T26/N26-1,"") | U29: =IFERROR(U26/O26-1,"") | V29: =IFERROR(V26/P26-1,"") | ... CO29: =IFERROR(CO26/CI26-1,"") -> 0.12401567 | CP29: =IFERROR(CP26/CO26-1,"") -> 0.0918 | CQ29: =IFERROR(CQ26/CP26-1,"") -> 0.0918 | CR29: =IFERROR(CR26/CQ26-1,"") -> 0.08665 | CS29: =IFERROR(CS26/CR26-1,"") -> 0.0815 | CT29: =IFERROR(CT26/CS26-1,"") -> 0.0815 | DC29: 2030E | DD29: =DE29+$DD$25 -> 0.04 | DE29: 0.03 | DF29: =DE29+$DF$25 -> 0.015
B30: Vehicle sales (USDm; purchase-model units) | AM30: 97.531 | AN30: 25.329 | AO30: 27.559 | AP30: =AN30+AO30 -> 52.888 | AQ30: 38.407 | AR30: 30.114 | AS30: 121.409 | AT30: 38.926 | AU30: 40.042 | AV30: =AT30+AU30 -> 78.968 | AW30: 48.109 | AX30: 40.048 | AY30: 167.125 | AZ30: 33.207 | BA30: 29.714 | BB30: =AZ30+BA30 -> 62.921 | BC30: 23.455 | BD30: 26.105 | BE30: 112.481 | BF30: 30.548 | BG30: 31.93 | BH30: =BF30+BG30 -> 62.478 | BI30: 38.449 | BJ30: 45.149 | BK30: 146.076 | BL30: 54.611 | BM30: 59.691 | BN30: =BL30+BM30 -> 114.302 | BO30: 62.24 | BP30: 59.354 | BQ30: 235.896 | BR30: 69.34 | BS30: 84.731 | BT30: =BR30+BS30 -> 154.071 | BU30: 92.901 | BV30: 76.411 | BW30: 323.383 | BX30: 82.498 | BY30: 83.714 | BZ30: =BX30+BY30 -> 166.212 | CA30: 92.393 | CB30: 78.582 | CC30: 337.188 | CD30: 72.944 | CE30: 65.32 | CF30: =CD30+CE30 -> 138.264 | CG30: 69.048 | CH30: 67.439 | CI30: 274.75 | CJ30: 66.105 | CK30: 67.47 | CL30: =CJ30+CK30 -> 133.575 | CM30: 73.588 | CN30: 70.383 | CO30: 277.546 | CP30: =CO30*(1+CP31) -> 291.4233 | CQ30: =CP30*(1+CQ31) -> 305.99446 | CR30: =CQ30*(1+CR31) -> 321.29419 | CS30: =CR30*(1+CS31) -> 337.3589 | CT30: =CS30*(1+CT31) -> 354.22684 | CU30: Vehicle sales = units sold under the purchase model (gross revenue); forecast grows with the input below. | DC30: 2031E | DD30: =DE30+$DD$25 -> 0.04 | DE30: 0.03 | DF30: =DE30+$DF$25 -> 0.015
B31: Vehicle sales y/y % (forecast input) | D31: =IFERROR(D30/C30-1,"") | E31: =IFERROR(E30/D30-1,"") | F31: =IFERROR(F30/E30-1,"") | G31: =IFERROR(G30/F30-1,"") | H31: =IFERROR(H30/G30-1,"") | I31: =IFERROR(I30/H30-1,"") | O31: =IFERROR(O30/I30-1,"") | P31: =IFERROR(P30/J30-1,"") | Q31: =IFERROR(Q30/K30-1,"") | R31: =IFERROR(R30/L30-1,"") | S31: =IFERROR(S30/M30-1,"") | T31: =IFERROR(T30/N30-1,"") | U31: =IFERROR(U30/O30-1,"") | V31: =IFERROR(V30/P30-1,"") | ... CO31: =IFERROR(CO30/CI30-1,"") -> 0.010176524 | CP31: 0.05 | CQ31: 0.05 | CR31: 0.05 | CS31: 0.05 | CT31: 0.05
B32: Total International revenue | C32: 2.115 | D32: 18.879 | E32: 193.248 | F32: 151.798 | G32: 170.085 | H32: 197.504 | I32: 199.322 | O32: 228.945 | U32: 269.83 | AA32: 243.199 | AB32: 58.373 | AC32: 61.445 | AD32: =AB32+AC32 -> 119.818 | AE32: 68.036 | AF32: 64.559 | AG32: 252.413 | AH32: 60.929 | AI32: 62.621 | AJ32: =AH32+AI32 -> 123.55 | AK32: 66.742 | AL32: 64.501 | AM32: =AM26+AM30 -> 254.793 | AN32: =AN26+AN30 -> 68.063 | AO32: =AO26+AO30 -> 73.971 | AP32: =AP26+AP30 -> 142.034 | AQ32: =AQ26+AQ30 -> 92.917 | AR32: =AR26+AR30 -> 79.722 | AS32: =AS26+AS30 -> 314.673 | AT32: =AT26+AT30 -> 90.159 | ... CT32: =CT26+CT30 -> 1234.8278 | CW32: =IFERROR((CT32/CO32)^(1/5)-1,"n/m") -> 0.075338016 | CX32: =IFERROR((CO32/BK32)^(1/5)-1,"n/m") -> 0.15354804 | CY32: =IFERROR((CO32/AG32)^(1/10)-1,"n/m") -> 0.13025639 | CZ32: =IFERROR((CO32/C32)^(1/20)-1,"n/m") -> 0.35029467 | DC32: ADJ_EBITDA_margin (% of total revenues) | DD32: 0.015 | DE32: Δ → | DF32: -0.02 | DG32: FY2026 40.3%, FY2025 41.2%, FY2021 peak ~45%. Yard capacity absorption and fee pricing vs labour / towing inflation.
B33: Total revenue y/y % | D33: =IFERROR(D32/C32-1,"") -> 7.9262411 | E33: =IFERROR(E32/D32-1,"") -> 9.2361354 | F33: =IFERROR(F32/E32-1,"") -> -0.21449122 | G33: =IFERROR(G32/F32-1,"") -> 0.12046931 | H33: =IFERROR(H32/G32-1,"") -> 0.16120763 | I33: =IFERROR(I32/H32-1,"") -> 0.0092048769 | O33: =IFERROR(O32/I32-1,"") -> 0.14861882 | P33: =IFERROR(P32/J32-1,"") | Q33: =IFERROR(Q32/K32-1,"") | R33: =IFERROR(R32/L32-1,"") | S33: =IFERROR(S32/M32-1,"") | T33: =IFERROR(T32/N32-1,"") | U33: =IFERROR(U32/O32-1,"") -> 0.17858001 | V33: =IFERROR(V32/P32-1,"") | ... CO33: =IFERROR(CO32/CI32-1,"") -> 0.084516843 | CP33: =IFERROR(CP32/CO32-1,"") -> 0.078290794 | CQ33: =IFERROR(CQ32/CP32-1,"") -> 0.078645231 | CR33: =IFERROR(CR32/CQ32-1,"") -> 0.075422279 | CS33: =IFERROR(CS32/CR32-1,"") -> 0.072078101 | CT33: =IFERROR(CT32/CS32-1,"") -> 0.072272133 | DC33: 2027E | DD33: =DE33+$DD$32 -> 0.415 | DE33: 0.4 | DF33: =DE33+$DF$32 -> 0.38
B34: Segment operating income (historical disclosure) | U34: 51.55 | AA34: 54.41 | AB34: 13.307 | AC34: 13.032 | AD34: =AB34+AC34 -> 26.339 | AE34: 17.034 | AF34: 15.388 | AG34: 58.761 | AH34: 15.842 | AI34: 15.288 | AJ34: =AH34+AI34 -> 31.13 | AK34: 17.671 | AL34: 16.138 | AM34: 64.939 | AN34: 17.923 | AO34: 17.937 | AP34: =AN34+AO34 -> 35.86 | AQ34: 23.731 | AR34: 9.867 | AS34: 69.458 | AT34: 21.148 | AU34: 19.337 | AV34: =AT34+AU34 -> 40.485 | AW34: 19.236 | AX34: 19.286 | AY34: 79.007 | AZ34: 16.341 | BA34: 20.903 | BB34: =AZ34+BA34 -> 37.244 | BC34: 16.281 | BD34: 18.019 | BE34: 72.92 | BF34: 27.003 | BG34: 28.769 | BH34: =BF34+BG34 -> 55.772 | BI34: 31.385 | BJ34: 25.715 | BK34: 112.871 | BL34: 35.172 | BM34: 34.682 | BN34: =BL34+BM34 -> 69.854 | BO34: 32.318 | BP34: 25.256 | BQ34: 127.428 | BR34: 28.875 | BS34: 29.361 | BT34: =BR34+BS34 -> 58.236 | BU34: 34.133 | BV34: 26.102 | BW34: 118.472 | BX34: 33.085 | BY34: 32.562 | BZ34: =BX34+BY34 -> 65.647 | CA34: 44.272 | CB34: 34.07 | CC34: 143.989 | CD34: 51.308 | CE34: 50.318 | CF34: =CD34+CE34 -> 101.626 | CG34: 59.08 | CH34: 55.123 | CI34: 215.828 | CJ34: 55.722 | CK34: 47.238 | CL34: =CJ34+CK34 -> 102.96 | CM34: 73.837 | CN34: 56.754 | CO34: 233.55 | CU34: Segment profit is disclosed but not forecast (consolidated cost drivers below). | DC34: 2028E | DD34: =DE34+$DD$32 -> 0.42 | DE34: 0.405 | DF34: =DE34+$DF$32 -> 0.385
B35: Segment operating margin % | C35: =IF(ISNUMBER(C34),IFERROR(C34/C32,""),"") | D35: =IF(ISNUMBER(D34),IFERROR(D34/D32,""),"") | E35: =IF(ISNUMBER(E34),IFERROR(E34/E32,""),"") | F35: =IF(ISNUMBER(F34),IFERROR(F34/F32,""),"") | G35: =IF(ISNUMBER(G34),IFERROR(G34/G32,""),"") | H35: =IF(ISNUMBER(H34),IFERROR(H34/H32,""),"") | I35: =IF(ISNUMBER(I34),IFERROR(I34/I32,""),"") | J35: =IF(ISNUMBER(J34),IFERROR(J34/J32,""),"") | ... CO35: =IF(ISNUMBER(CO34),IFERROR(CO34/CO32,""),"") -> 0.27195588 | DC35: 2029E | DD35: =DE35+$DD$32 -> 0.425 | DE35: 0.41 | DF35: =DE35+$DF$32 -> 0.39
B36: Segment depreciation & amortization | U36: 9.21 | AA36: 10.335 | AB36: 2.472 | AC36: 2.405 | AD36: =AB36+AC36 -> 4.877 | AE36: 2.31 | AF36: 2.305 | AG36: 9.492 | AH36: 2.323 | AI36: 2.548 | AJ36: =AH36+AI36 -> 4.871 | AK36: 2.304 | AL36: 2.318 | AM36: 9.493 | AN36: 2.373 | AO36: 3.817 | AP36: =AN36+AO36 -> 6.19 | AQ36: 2.384 | AR36: 2.245 | AS36: 10.819 | AT36: 2.477 | AU36: 2.522 | AV36: =AT36+AU36 -> 4.999 | AW36: 2.476 | AX36: 2.155 | AY36: 9.63 | AZ36: 2.447 | BA36: 2.554 | BB36: =AZ36+BA36 -> 5.001 | BC36: 2.951 | BD36: 2.662 | BE36: 10.572 | BF36: 2.787 | BG36: 3.647 | BH36: =BF36+BG36 -> 6.434 | BI36: 3.805 | BJ36: 3.967 | BK36: 14.206 | BL36: 4.035 | BM36: 3.987 | BN36: =BL36+BM36 -> 8.022 | BO36: 4.97 | BP36: 4.353 | BQ36: 17.35 | BR36: 4.123 | BS36: 4.293 | BT36: =BR36+BS36 -> 8.416 | BU36: 4.453 | BV36: 10.805 | BW36: 23.674 | BX36: 6.228 | BY36: 6.918 | BZ36: =BX36+BY36 -> 13.146 | CA36: 7.256 | CB36: 7.674 | CC36: 28.076 | CD36: 7.712 | CE36: 7.744 | CF36: =CD36+CE36 -> 15.456 | CG36: 7.955 | CH36: 8.412 | CI36: 31.823 | CJ36: 8.633 | CK36: 8.558 | CL36: =CJ36+CK36 -> 17.191 | CM36: 8.724 | CN36: 8.709 | CO36: 34.624 | DC36: 2030E | DD36: =DE36+$DD$32 -> 0.43 | DE36: 0.415 | DF36: =DE36+$DF$32 -> 0.395
B37: Segment capital expenditures (incl. acquired productive assets) | U37: 36.086 | AA37: 14.384 | AB37: 0.846 | AC37: 0.599 | AD37: =AB37+AC37 -> 1.445 | AE37: 16.204 | AF37: 2.817 | AG37: 20.466 | AH37: 1.688 | AI37: 2.662 | AJ37: =AH37+AI37 -> 4.35 | AK37: 1.426 | AL37: 9.568 | AM37: 15.344 | AN37: 2.456 | AO37: 12.617 | AP37: =AN37+AO37 -> 15.073 | AQ37: 20.672 | AR37: 5.084 | AS37: 40.829 | AT37: 27.083 | AU37: 7.49 | AV37: =AT37+AU37 -> 34.573 | AW37: 15.785 | AX37: 12.443 | AY37: 62.801 | AZ37: 18.527 | BA37: 7.301 | BB37: =AZ37+BA37 -> 25.828 | BC37: 4.205 | BD37: 4.975 | BE37: 34.901 | BF37: 24.634 | BG37: 14.526 | BH37: =BF37+BG37 -> 39.16 | BI37: 22.175 | BJ37: 15.955 | BK37: 77.29 | BL37: 10.424 | BM37: 5.185 | BN37: =BL37+BM37 -> 15.609 | BO37: 14.237 | BP37: 116.574 | BQ37: 146.42 | BR37: 16.372 | BS37: 14.636 | BT37: =BR37+BS37 -> 31.008 | BU37: 10.172 | BV37: 102.266 | BW37: 143.446 | BX37: 40.542 | BY37: 39.168 | BZ37: =BX37+BY37 -> 79.71 | CA37: 15.629 | CB37: 18.567 | CC37: 113.906 | CD37: 26.098 | CE37: 20.868 | CF37: =CD37+CE37 -> 46.966 | CG37: 7.561 | CH37: 24.721 | CI37: 79.248 | CJ37: 41.283 | CK37: 10.738 | CL37: =CJ37+CK37 -> 52.021 | CM37: 5.733 | CN37: 27.648 | CO37: 85.402 | DC37: 2031E | DD37: =DE37+$DD$32 -> 0.435 | DE37: 0.42 | DF37: =DE37+$DF$32 -> 0.4
B39: Total — segment build, units & mix | CU39: TOTAL — modelling logic | DC39: Buybacks ($m) | DD39: 500 | DE39: Δ → | DF39: -700 | DG39: FY2026 repurchases $1,633m (first material buyback since FY2019). ACV deal funding (~$2bn cash) would displace buybacks (not modelled).
B40: Service revenues — segment build | C40: =IF(ISNUMBER(C12),C12+C26,"n/d") -> n/d | D40: =IF(ISNUMBER(D12),D12+D26,"n/d") -> n/d | E40: =IF(ISNUMBER(E12),E12+E26,"n/d") -> n/d | F40: =IF(ISNUMBER(F12),F12+F26,"n/d") -> n/d | G40: =IF(ISNUMBER(G12),G12+G26,"n/d") -> n/d | H40: =IF(ISNUMBER(H12),H12+H26,"n/d") -> n/d | I40: =IF(ISNUMBER(I12),I12+I26,"n/d") -> n/d | J40: =IF(ISNUMBER(J12),J12+J26,"n/d") -> n/d | ... CO40: =IF(ISNUMBER(CO12),CO12+CO26,"n/d") -> 3969.52 | CP40: =CP12+CP26 -> 4159.4252 | CQ40: =CQ12+CQ26 -> 4414.1901 | CR40: =CR12+CR26 -> 4700.855 | CS40: =CS12+CS26 -> 5002.6464 | CT40: =CT12+CT26 -> 5324.081 | CU40: Forecast service revenues = US + International build (links to the income statement). | DC40: 2027E | DD40: =MAX(0,DE40+$DD$39) -> 1500 | DE40: 1000 | DF40: =MAX(0,DE40+$DF$39) -> 300
B41: Vehicle sales — segment build | C41: =IF(ISNUMBER(C16),C16+C30,"n/d") -> n/d | D41: =IF(ISNUMBER(D16),D16+D30,"n/d") -> n/d | E41: =IF(ISNUMBER(E16),E16+E30,"n/d") -> n/d | F41: =IF(ISNUMBER(F16),F16+F30,"n/d") -> n/d | G41: =IF(ISNUMBER(G16),G16+G30,"n/d") -> n/d | H41: =IF(ISNUMBER(H16),H16+H30,"n/d") -> n/d | I41: =IF(ISNUMBER(I16),I16+I30,"n/d") -> n/d | J41: =IF(ISNUMBER(J16),J16+J30,"n/d") -> n/d | ... CO41: =IF(ISNUMBER(CO16),CO16+CO30,"n/d") -> 696.689 | CP41: =CP16+CP30 -> 727.33202 | CQ41: =CQ16+CQ30 -> 759.33953 | CR41: =CR16+CR30 -> 792.77306 | CS41: =CS16+CS30 -> 827.69692 | CT41: =CT16+CT30 -> 864.17839 | DC41: 2028E | DD41: =MAX(0,DE41+$DD$39) -> 1250 | DE41: 750 | DF41: =MAX(0,DE41+$DF$39) -> 50
B42: Total service revenues and vehicle sales (build) | C42: =IF(ISNUMBER(C40),C40+C41,C73) -> 528.571 | D42: =IF(ISNUMBER(D40),D40+D41,D73) -> 560.68 | E42: =IF(ISNUMBER(E40),E40+E41,E73) -> 784.848 | F42: =IF(ISNUMBER(F40),F40+F41,F73) -> 743.082 | G42: =IF(ISNUMBER(G40),G40+G41,G73) -> 772.879 | H42: =IF(ISNUMBER(H40),H40+H41,H73) -> 872.246 | I42: =IF(ISNUMBER(I40),I40+I41,I73) -> 924.191 | J42: =IF(ISNUMBER(J40),J40+J41,J73) -> 238.866 | ... CO42: =IF(ISNUMBER(CO40),CO40+CO41,CO73) -> 4666.209 | CP42: =CP40+CP41 -> 4886.7572 | CQ42: =CQ40+CQ41 -> 5173.5296 | CR42: =CR40+CR41 -> 5493.6281 | CS42: =CS40+CS41 -> 5830.3434 | CT42: =CT40+CT41 -> 6188.2594 | CU42: Group revenue = service revenues + vehicle sales (ties to the GAAP income statement). | CW42: =IFERROR((CT42/CO42)^(1/5)-1,"n/m") -> 0.058085747 | CX42: =IFERROR((CO42/BK42)^(1/5)-1,"n/m") -> 0.11624966 | CY42: =IFERROR((CO42/AG42)^(1/10)-1,"n/m") -> 0.13911906 | CZ42: =IFERROR((CO42/C42)^(1/20)-1,"n/m") -> 0.11504666 | DC42: 2029E | DD42: =MAX(0,DE42+$DD$39) -> 1250 | DE42: 750 | DF42: =MAX(0,DE42+$DF$39) -> 50
B43: Check: service / vehicle segment build vs income statement (should be 0) | C43: =IF(ISNUMBER(C40),ROUND(C42-C73,1),"n/d") -> n/d | D43: =IF(ISNUMBER(D40),ROUND(D42-D73,1),"n/d") -> n/d | E43: =IF(ISNUMBER(E40),ROUND(E42-E73,1),"n/d") -> n/d | F43: =IF(ISNUMBER(F40),ROUND(F42-F73,1),"n/d") -> n/d | G43: =IF(ISNUMBER(G40),ROUND(G42-G73,1),"n/d") -> n/d | H43: =IF(ISNUMBER(H40),ROUND(H42-H73,1),"n/d") -> n/d | I43: =IF(ISNUMBER(I40),ROUND(I42-I73,1),"n/d") -> n/d | J43: =IF(ISNUMBER(J40),ROUND(J42-J73,1),"n/d") -> n/d | ... CO43: =IF(ISNUMBER(CO40),ROUND(CO42-CO73,1),"n/d") -> 0 | CP43: =ROUND(CP42-CP73,1) -> 0 | CQ43: =ROUND(CQ42-CQ73,1) -> 0 | CR43: =ROUND(CR42-CR73,1) -> 0 | CS43: =ROUND(CS42-CS73,1) -> 0 | CT43: =ROUND(CT42-CT73,1) -> 0 | DC43: 2030E | DD43: =MAX(0,DE43+$DD$39) -> 1250 | DE43: 750 | DF43: =MAX(0,DE43+$DF$39) -> 50
B44: Check: US + International revenue vs income statement (should be 0) | C44: =IF(AND(ISNUMBER(C18),ISNUMBER(C32)),ROUND(C18+C32-C73,1),"n/d") -> 0 | D44: =IF(AND(ISNUMBER(D18),ISNUMBER(D32)),ROUND(D18+D32-D73,1),"n/d") -> 0 | E44: =IF(AND(ISNUMBER(E18),ISNUMBER(E32)),ROUND(E18+E32-E73,1),"n/d") -> 0 | F44: =IF(AND(ISNUMBER(F18),ISNUMBER(F32)),ROUND(F18+F32-F73,1),"n/d") -> 0 | G44: =IF(AND(ISNUMBER(G18),ISNUMBER(G32)),ROUND(G18+G32-G73,1),"n/d") -> 0 | H44: =IF(AND(ISNUMBER(H18),ISNUMBER(H32)),ROUND(H18+H32-H73,1),"n/d") -> 0 | I44: =IF(AND(ISNUMBER(I18),ISNUMBER(I32)),ROUND(I18+I32-I73,1),"n/d") -> 0 | J44: =IF(AND(ISNUMBER(J18),ISNUMBER(J32)),ROUND(J18+J32-J73,1),"n/d") -> n/d | ... CO44: =IF(AND(ISNUMBER(CO18),ISNUMBER(CO32)),ROUND(CO18+CO32-CO73,1),"n/d") -> 0 | CP44: =ROUND(CP18+CP32-CP73,1) -> 0 | CQ44: =ROUND(CQ18+CQ32-CQ73,1) -> 0 | CR44: =ROUND(CR18+CR32-CR73,1) -> 0 | CS44: =ROUND(CS18+CS32-CS73,1) -> 0 | CT44: =ROUND(CT18+CT32-CT73,1) -> 0 | DC44: 2031E | DD44: =MAX(0,DE44+$DD$39) -> 1250 | DE44: 750 | DF44: =MAX(0,DE44+$DF$39) -> 50
B45: Global units sold y/y % (disclosed; forecast = service-revenue-weighted) | G45: 0.01 | CP45: =IFERROR((CO12*CP13+CO26*CP27)/(CO12+CO26),"") -> 0.0173212 | CQ45: =IFERROR((CP12*CQ13+CP26*CQ27)/(CP12+CP26),"") -> 0.030339838 | CR45: =IFERROR((CQ12*CR13+CQ26*CR27)/(CQ12+CQ26),"") -> 0.033923968 | CS45: =IFERROR((CR12*CS13+CR26*CS27)/(CR12+CR26),"") -> 0.033203165 | CT45: =IFERROR((CS12*CT13+CS26*CT27)/(CS12+CS26),"") -> 0.033255239
B46: International % of service revenues | C46: =IF(ISNUMBER(C26),IFERROR(C26/C71,""),"") | D46: =IF(ISNUMBER(D26),IFERROR(D26/D71,""),"") | E46: =IF(ISNUMBER(E26),IFERROR(E26/E71,""),"") | F46: =IF(ISNUMBER(F26),IFERROR(F26/F71,""),"") | G46: =IF(ISNUMBER(G26),IFERROR(G26/G71,""),"") | H46: =IF(ISNUMBER(H26),IFERROR(H26/H71,""),"") | I46: =IF(ISNUMBER(I26),IFERROR(I26/I71,""),"") | J46: =IF(ISNUMBER(J26),IFERROR(J26/J71,""),"") | ... CO46: =IF(ISNUMBER(CO26),IFERROR(CO26/CO71,""),"") -> 0.146424 | CP46: =IFERROR(CP26/CP71,"") -> 0.1525668 | CQ46: =IFERROR(CQ26/CQ71,"") -> 0.15695871 | CR46: =IFERROR(CR26/CR71,"") -> 0.16015823 | CS46: =IFERROR(CS26/CS71,"") -> 0.16276193 | CT46: =IFERROR(CT26/CT71,"") -> 0.16539963 | DC46: Min. net debt / adj. EBITDA (x) | DD46: -1.5 | DE46: -2 | DG46: Net-cash cap: buybacks are stepped up so year-end net debt / adj. EBITDA never falls below this level (i.e. net cash ≤ |x| × EBITDA). Blank = no cap.
B47: Service revenues % of total revenues | C47: =IFERROR(C71/C73,"") -> 1 | D47: =IFERROR(D71/D73,"") -> 0.95561461 | E47: =IFERROR(E71/E73,"") -> 0.78961531 | F47: =IFERROR(F71/F73,"") -> 0.8281078 | G47: =IFERROR(G71/G73,"") -> 0.8210936 | H47: =IFERROR(H71/H73,"") -> 0.81753657 | I47: =IFERROR(I71/I73,"") -> 0.81938907 | J47: =IFERROR(J71/J73,"") -> 0.81710666 | ... CT47: =IFERROR(CT71/CT73,"") -> 0.86035194
B48: Vehicle sales gross margin % ((vehicle sales − cost of vehicle sales) / vehicle sales) | C48: =IFERROR((C72-C75)/C72,"") | D48: =IFERROR((D72-D75)/D72,"") -> 0.1009001 | E48: =IFERROR((E72-E75)/E72,"") -> 0.19046754 | F48: =IFERROR((F72-F75)/F72,"") -> 0.16989744 | G48: =IFERROR((G72-G75)/G72,"") -> 0.24299755 | H48: =IFERROR((H72-H75)/H72,"") -> 0.21332303 | I48: =IFERROR((I72-I75)/I72,"") -> 0.17941636 | J48: =IFERROR((J72-J75)/J72,"") -> 0.16883741 | ... CO48: =IFERROR((CO72-CO75)/CO72,"") -> 0.11515325 | CP48: 0.115 | CQ48: 0.115 | CR48: 0.115 | CS48: 0.115 | CT48: 0.115 | CU48: Input: FY2026 11.5%, FY2021–26 range ~10–16%. Drives cost of vehicle sales.
B50: Cost drivers (% of revenue) | CU50: % OF REVENUE drivers — hardcoded inputs that drive forecast cost lines
B51: Yard operations % of service revenues (incl. yard D&A and SBC) | C51: =IFERROR(C74/C71,"") -> 0.56382775 | D51: =IFERROR(D74/D71,"") -> 0.50676753 | E51: =IFERROR(E74/E71,"") -> 0.53074736 | F51: =IFERROR(F74/F71,"") -> 0.5278166 | G51: =IFERROR(G74/G71,"") -> 0.50458395 | H51: =IFERROR(H74/H71,"") -> 0.52468472 | I51: =IFERROR(I74/I71,"") -> 0.49863721 | J51: =IFERROR(J74/J71,"") -> 0.49758939 | ... CO51: =IFERROR(CO74/CO71,"") -> 0.49524577 | CP51: 0.495 | CQ51: 0.495 | CR51: 0.495 | CS51: 0.495 | CT51: 0.495 | CU51: Yard operations: towing, yard labour, facility costs, title processing; incl. facility D&A and SBC (Copart 10-K presentation). FY2026 49.5%.
B52: Depreciation & amortization % of revenue | C52: =IFERROR(C102/C73,"") -> 0.0595114 | D52: =IFERROR(D102/D73,"") -> 0.066150032 | E52: =IFERROR(E102/E73,"") -> 0.054537949 | F52: =IFERROR(F102/F73,"") -> 0.055652001 | G52: =IFERROR(G102/G73,"") -> 0.055949249 | H52: =IFERROR(H102/H73,"") -> 0.052386597 | I52: =IFERROR(I102/I73,"") -> 0.052118015 | J52: =IFERROR(J102/J73,"") -> 0.053749801 | ... CO52: =IFERROR(CO102/CO73,"") -> 0.049156178 | CP52: 0.05 | CQ52: 0.05 | CR52: 0.05 | CS52: 0.05 | CT52: 0.05 | CU52: FY2026 4.9% (yard expansion / land-heavy model: owned facilities). Input.
B53: Stock-based compensation % of revenue | C53: =IFERROR(C103/C73,"") -> 0.0066783838 | D53: =IFERROR(D103/D73,"") -> 0.0061068702 | E53: =IFERROR(E103/E73,"") -> 0.0080983834 | F53: =IFERROR(F103/F73,"") -> 0.012667512 | G53: =IFERROR(G103/G73,"") -> 0.023231321 | H53: =IFERROR(H103/H73,"") -> 0.021790871 | I53: =IFERROR(I103/I73,"") -> 0.023578459 | J53: =IFERROR(J103/J73,"") -> 0.02166068 | ... CO53: =IFERROR(CO103/CO73,"") -> 0.0083189587 | CP53: 0.008 | CQ53: 0.008 | CR53: 0.008 | CS53: 0.008 | CT53: 0.008
B54: G&A % of revenue (forecast = balancing-line output) | C54: =IFERROR(C78/C73,"") -> 0.11159523 | D54: =IFERROR(D78/D73,"") -> 0.11349968 | E54: =IFERROR(E78/E73,"") -> 0.10746285 | F54: =IFERROR(F78/F73,"") -> 0.11699247 | G54: =IFERROR(G78/G73,"") -> 0.1409328 | H54: =IFERROR(H78/H73,"") -> 0.12336543 | I54: =IFERROR(I78/I73,"") -> 0.12388348 | J54: =IFERROR(J78/J73,"") -> 0.13011061 | ... CT54: =IFERROR(CT78/CT73,"") -> 0.080537258 | CU54: Sanity check on the balancing line: FY2021–26 range ~6–9%.
B56: Group Total — adjusted EBITDA & adjusted EBIT (model KPIs; Copart publishes no EBITDA) | CU56: GROUP TOTAL (CONSOLIDATED) — modelling logic
B57: Total revenues | C57: =C73 -> 528.571 | D57: =D73 -> 560.68 | E57: =E73 -> 784.848 | F57: =F73 -> 743.082 | G57: =G73 -> 772.879 | H57: =H73 -> 872.246 | I57: =I73 -> 924.191 | J57: =J73 -> 238.866 | ... CT57: =CT73 -> 6188.2594 | CW57: =IFERROR((CT57/CO57)^(1/5)-1,"n/m") -> 0.058085747 | CX57: =IFERROR((CO57/BK57)^(1/5)-1,"n/m") -> 0.11624966 | CY57: =IFERROR((CO57/AG57)^(1/10)-1,"n/m") -> 0.13911906 | CZ57: =IFERROR((CO57/C57)^(1/20)-1,"n/m") -> 0.11504666
B58: Adjusted EBITDA (model; EBITDA + Copart non-GAAP items, pre-tax) | C58: =C126 -> 197.868 | D58: =D126 -> 240.866 | E58: =E126 -> 284.902 | F58: =F126 -> 267.668 | G58: =G126 -> 282.748 | H58: =H126 -> 313.156 | I58: =I126 -> 337.207 | J58: =J126 -> 86.903 | ... CO58: =CO126 -> 1882.427 | CP58: =CP73*CP59 -> 1954.7029 | CQ58: =CQ73*CQ59 -> 2095.2795 | CR58: =CR73*CR59 -> 2252.3875 | CS58: =CS73*CS59 -> 2419.5925 | CT58: =CT73*CT59 -> 2599.0689 | CU58: Historical = model bridge (Copart does not publish EBITDA). 2027E–2031E: revenue × adjusted EBITDA margin (scenario lever). | CW58: =IFERROR((CT58/CO58)^(1/5)-1,"n/m") -> 0.066645071 | CX58: =IFERROR((CO58/BK58)^(1/5)-1,"n/m") -> 0.082284926 | CY58: =IFERROR((CO58/AG58)^(1/10)-1,"n/m") -> 0.15161177 | CZ58: =IFERROR((CO58/C58)^(1/20)-1,"n/m") -> 0.1192243
B59: Adjusted EBITDA margin % (of total revenues) | C59: =IFERROR(C58/C73,"") -> 0.37434517 | D59: =IFERROR(D58/D73,"") -> 0.4295962 | E59: =IFERROR(E58/E73,"") -> 0.36300277 | F59: =IFERROR(F58/F73,"") -> 0.36021327 | G59: =IFERROR(G58/G73,"") -> 0.36583734 | H59: =IFERROR(H58/H73,"") -> 0.35902257 | I59: =IFERROR(I58/I73,"") -> 0.36486722 | J59: =IFERROR(J58/J73,"") -> 0.36381486 | ... CO59: =IFERROR(CO58/CO73,"") -> 0.40341678 | CP59: =CHOOSE(MATCH($CU$2,{"Bull","Base","Bear"},0),$DD$33,$DE$33,$DF$33) -> 0.4 | CQ59: =CHOOSE(MATCH($CU$2,{"Bull","Base","Bear"},0),$DD$34,$DE$34,$DF$34) -> 0.405 | CR59: =CHOOSE(MATCH($CU$2,{"Bull","Base","Bear"},0),$DD$35,$DE$35,$DF$35) -> 0.41 | CS59: =CHOOSE(MATCH($CU$2,{"Bull","Base","Bear"},0),$DD$36,$DE$36,$DF$36) -> 0.415 | CT59: =CHOOSE(MATCH($CU$2,{"Bull","Base","Bear"},0),$DD$37,$DE$37,$DF$37) -> 0.42 | CU59: 2027E–2031E: scenario lever (ADJ_EBITDA_margin). FY2026 40.3%, FY2025 41.2%. | CW59: =IFERROR(AVERAGE(CP59:CT59),"n/m") -> 0.41
B60: Adjusted EBITDA y/y % | D60: =IFERROR(D58/C58-1,"") -> 0.21730649 | E60: =IFERROR(E58/D58-1,"") -> 0.18282364 | F60: =IFERROR(F58/E58-1,"") -> -0.060490976 | G60: =IFERROR(G58/F58-1,"") -> 0.056338449 | H60: =IFERROR(H58/G58-1,"") -> 0.10754453 | I60: =IFERROR(I58/H58-1,"") -> 0.076801977 | O60: =IFERROR(O58/I58-1,"") -> 0.00079705995 | P60: =IFERROR(P58/J58-1,"") -> -0.069238116 | Q60: =IFERROR(Q58/K58-1,"") -> 0.097329954 | R60: =IFERROR(R58/L58-1,"") -> 0.0096164916 | S60: =IFERROR(S58/M58-1,"") -> 0.12590027 | T60: =IFERROR(T58/N58-1,"") -> 0.13056027 | U60: =IFERROR(U58/O58-1,"") -> 0.070127184 | V60: =IFERROR(V58/P58-1,"") -> 0.21109957 | ... CO60: =IFERROR(CO58/CI58-1,"") -> -0.025921581 | CP60: =IFERROR(CP58/CO58-1,"") -> 0.038395045 | CQ60: =IFERROR(CQ58/CP58-1,"") -> 0.071917132 | CR60: =IFERROR(CR58/CQ58-1,"") -> 0.074981893 | CS60: =IFERROR(CS58/CR58-1,"") -> 0.074234553 | CT60: =IFERROR(CT58/CS58-1,"") -> 0.074176305
B61: Incremental adjusted EBITDA margin (ΔAdj. EBITDA / ΔRevenue) | D61: =IFERROR((D58-C58)/(D73-C73),"") -> 1.3391261 | E61: =IFERROR((E58-D58)/(E73-D73),"") -> 0.19644195 | F61: =IFERROR((F58-E58)/(F73-E73),"") -> 0.41263228 | G61: =IFERROR((G58-F58)/(G73-F73),"") -> 0.50609122 | H61: =IFERROR((H58-G58)/(H73-G73),"") -> 0.30601709 | I61: =IFERROR((I58-H58)/(I73-H73),"") -> 0.46300895 | O61: =IFERROR((O58-I58)/(O73-I73),"") -> 0.0021995515 | P61: =IFERROR((P58-J58)/(P73-J73),"") -> -0.14669527 | Q61: =IFERROR((Q58-K58)/(Q73-K73),"") -> 0.37552472 | R61: =IFERROR((R58-L58)/(R73-L73),"") -> 0.025903437 | S61: =IFERROR((S58-M58)/(S73-M73),"") -> 0.36670072 | T61: =IFERROR((T58-N58)/(T73-N73),"") -> 0.43421884 | U61: =IFERROR((U58-O58)/(U73-O73),"") -> 0.20209752 | V61: =IFERROR((V58-P58)/(V73-P73),"") -> 1.625726 | ... CO61: =IFERROR((CO58-CI58)/(CO73-CI73),"") -> -2.6021505 | CP61: =IFERROR((CP58-CO58)/(CP73-CO73),"") -> 0.32771013 | CQ61: =IFERROR((CQ58-CP58)/(CQ73-CP73),"") -> 0.4902027 | CR61: =IFERROR((CR58-CQ58)/(CR73-CQ73),"") -> 0.49081153 | CS61: =IFERROR((CS58-CR58)/(CS73-CR73),"") -> 0.49657676 | CT61: =IFERROR((CT58-CS58)/(CT73-CS73),"") -> 0.50144849
B62: Depreciation and amortization | C62: =C102 -> 31.456 | D62: =D102 -> 37.089 | E62: =E102 -> 42.804 | F62: =F102 -> 41.354 | G62: =G102 -> 43.242 | H62: =H102 -> 45.694 | I62: =I102 -> 48.167 | J62: =J102 -> 12.839 | ... CT62: =CT102 -> 309.41297
B63: Adjusted EBIT (adjusted EBITDA − D&A) | C63: =C58-C62 -> 166.412 | D63: =D58-D62 -> 203.777 | E63: =E58-E62 -> 242.098 | F63: =F58-F62 -> 226.314 | G63: =G58-G62 -> 239.506 | H63: =H58-H62 -> 267.462 | I63: =I58-I62 -> 289.04 | J63: =J58-J62 -> 74.064 | ... CT63: =CT58-CT62 -> 2289.656 | CU63: Model measure: GAAP operating income + Copart's pre-tax non-GAAP operating items (Copart has negligible acquired-intangible amortization, so no separate add-back). | CW63: =IFERROR((CT63/CO63)^(1/5)-1,"n/m") -> 0.067324892 | CX63: =IFERROR((CO63/BK63)^(1/5)-1,"n/m") -> 0.076074753 | CY63: =IFERROR((CO63/AG63)^(1/10)-1,"n/m") -> 0.14953636 | CZ63: =IFERROR((CO63/C63)^(1/20)-1,"n/m") -> 0.12164421
B64: Adjusted EBIT margin % | C64: =IFERROR(C63/C73,"") -> 0.31483377 | D64: =IFERROR(D63/D73,"") -> 0.36344617 | E64: =IFERROR(E63/E73,"") -> 0.30846482 | F64: =IFERROR(F63/F73,"") -> 0.30456127 | G64: =IFERROR(G63/G73,"") -> 0.30988809 | H64: =IFERROR(H63/H73,"") -> 0.30663597 | I64: =IFERROR(I63/I73,"") -> 0.3127492 | J64: =IFERROR(J63/J73,"") -> 0.31006506 | ... CT64: =IFERROR(CT63/CT73,"") -> 0.37 | CW64: =IFERROR(AVERAGE(CP64:CT64),"n/m") -> 0.36
B65: Gross profit (Copart definition: revenue − yard operations − cost of vehicle sales) | C65: =C76 -> 230.548 | D65: =D76 -> 266.782 | E65: =E76 -> 322.259 | F65: =F76 -> 312.26 | G65: =G76 -> 347.994 | H65: =H76 -> 372.895 | I65: =I76 -> 409.616 | J65: =J76 -> 105.436 | ... CT65: =CT76 -> 2788.0414 | CW65: =IFERROR((CT65/CO65)^(1/5)-1,"n/m") -> 0.059952051 | CX65: =IFERROR((CO65/BK65)^(1/5)-1,"n/m") -> 0.091823749 | CY65: =IFERROR((CO65/AG65)^(1/10)-1,"n/m") -> 0.14361585 | CZ65: =IFERROR((CO65/C65)^(1/20)-1,"n/m") -> 0.11636275
B66: Gross margin % | C66: =IFERROR(C76/C73,"") -> 0.43617225 | D66: =IFERROR(D76/D73,"") -> 0.47581865 | E66: =IFERROR(E76/E73,"") -> 0.41060052 | F66: =IFERROR(F76/F73,"") -> 0.4202228 | G66: =IFERROR(G76/G73,"") -> 0.45025677 | H66: =IFERROR(H76/H73,"") -> 0.42751128 | I66: =IFERROR(I76/I73,"") -> 0.44321574 | J66: =IFERROR(J76/J73,"") -> 0.44140229 | ... CT66: =IFERROR(CT76/CT73,"") -> 0.45053726 | CW66: =IFERROR(AVERAGE(CP66:CT66),"n/m") -> 0.4487206
B67: EBITDA (GAAP-derived: net income + D&A + interest expense − interest income + tax) | C67: =C113 -> 197.868 | D67: =D113 -> 240.866 | E67: =E113 -> 284.902 | F67: =F113 -> 267.668 | G67: =G113 -> 282.748 | H67: =H113 -> 313.156 | I67: =I113 -> 337.207 | J67: =J113 -> 86.903 | ... CT67: =CT113 -> 2599.0689
B68: Check: adjusted EBITDA model bridge vs KPI (should be 0) | C68: =ROUND(C126-C58,1) -> 0 | D68: =ROUND(D126-D58,1) -> 0 | E68: =ROUND(E126-E58,1) -> 0 | F68: =ROUND(F126-F58,1) -> 0 | G68: =ROUND(G126-G58,1) -> 0 | H68: =ROUND(H126-H58,1) -> 0 | I68: =ROUND(I126-I58,1) -> 0 | J68: =ROUND(J126-J58,1) -> 0 | ... CT68: =ROUND(CT126-CT58,1) -> 0
B70: CONSOLIDATED INCOME STATEMENT (US GAAP) | CU70: CONSOLIDATED IS — forecast logic
B71: Service revenues | C71: 528.571 | D71: 535.794 | E71: 619.728 | F71: 615.352 | G71: 634.606 | H71: 713.093 | I71: 757.272 | J71: 195.179 | K71: 216.92 | L71: =J71+K71 -> 412.099 | M71: 223.977 | N71: 213.591 | O71: 849.667 | P71: 226.363 | Q71: 235.732 | R71: =P71+Q71 -> 462.095 | S71: 255.045 | T71: 241.273 | U71: 958.413 | V71: 246.597 | W71: 238.508 | X71: =V71+W71 -> 485.105 | Y71: 256.564 | Z71: 243.671 | AA71: 985.363 | AB71: 250.967 | AC71: 260.417 | AD71: =AB71+AC71 -> 511.384 | AE71: 303.507 | AF71: 289.488 | AG71: 1104.379 | AH71: 307.078 | AI71: 310.033 | AJ71: =AH71+AI71 -> 617.111 | AK71: 332.346 | AL71: 336.795 | AM71: 1286.252 | AN71: 374.125 | AO71: 401.954 | AP71: =AN71+AO71 -> 776.079 | AQ71: 410.762 | AR71: 391.661 | AS71: 1578.502 | AT71: 394.806 | AU71: 416.807 | AV71: =AT71+AU71 -> 811.613 | AW71: 473.682 | AX71: 470.399 | AY71: 1755.694 | AZ71: 487.856 | BA71: 510.034 | BB71: =AZ71+BA71 -> 997.89 | BC71: 491.582 | BD71: 457.668 | BE71: 1947.14 | BF71: 515.372 | BG71: 532.601 | BH71: =BF71+BG71 -> 1047.973 | BI71: 623.846 | BJ71: 620.048 | BK71: 2291.867 | BL71: 667.818 | BM71: 711.09 | BN71: =BL71+BM71 -> 1378.908 | BO71: 766.316 | BP71: 707.816 | BQ71: 2853.04 | BR71: 726.84 | BS71: 789.797 | BT71: =BR71+BS71 -> 1516.637 | BU71: 847.249 | BV71: 834.242 | BW71: 3198.128 | BX71: 859.536 | BY71: 861.745 | BZ71: =BX71+BY71 -> 1721.281 | CA71: 946.63 | CB71: 893.091 | CC71: 3561.002 | CD71: 986.336 | CE71: 991.281 | CF71: =CD71+CE71 -> 1977.617 | CG71: 1034.836 | CH71: 956.209 | CI71: 3968.662 | CJ71: 991.845 | CK71: 952.051 | CL71: =CJ71+CK71 -> 1943.896 | CM71: 1056.08 | CN71: 969.544 | CO71: 3969.52 | CP71: =CP40 -> 4159.4252 | CQ71: =CQ40 -> 4414.1901 | CR71: =CR40 -> 4700.855 | CS71: =CS40 -> 5002.6464 | CT71: =CT40 -> 5324.081 | CU71: Forecast linked to the segment build. | CW71: =IFERROR((CT71/CO71)^(1/5)-1,"n/m") -> 0.060477189 | CX71: =IFERROR((CO71/BK71)^(1/5)-1,"n/m") -> 0.11611698 | CY71: =IFERROR((CO71/AG71)^(1/10)-1,"n/m") -> 0.13648049 | CZ71: =IFERROR((CO71/C71)^(1/20)-1,"n/m") -> 0.10606776
B72: Vehicle sales | C72: 0 | D72: 24.886 | E72: 165.12 | F72: 127.73 | G72: 138.273 | H72: 159.153 | I72: 166.919 | J72: 43.687 | K72: 49.265 | L72: =J72+K72 -> 92.952 | M72: 53.661 | N72: 50.106 | O72: 196.719 | P72: 53.52 | Q72: 50.702 | R72: =P72+Q72 -> 104.222 | S72: 54.677 | T72: 46.177 | U72: 205.076 | V72: 43.789 | W72: 37.75 | X72: =V72+W72 -> 81.539 | Y72: 40.578 | Z72: 38.622 | AA72: 160.716 | AB72: 37.871 | AC72: 39.289 | AD72: =AB72+AC72 -> 77.16 | AE72: 43.739 | AF72: 43.171 | AG72: 164.07 | AH72: 38.913 | AI72: 39.499 | AJ72: =AH72+AI72 -> 78.412 | AK72: 41.516 | AL72: 41.801 | AM72: 161.729 | AN72: 45.043 | AO72: 57.152 | AP72: =AN72+AO72 -> 102.195 | AQ72: 67.436 | AR72: 57.562 | AS72: 227.193 | AT72: 66.562 | AU72: 68.091 | AV72: =AT72+AU72 -> 134.653 | AW72: 79.434 | AX72: 72.176 | AY72: 286.263 | AZ72: 66.568 | BA72: 65.106 | BB72: =AZ72+BA72 -> 131.674 | BC72: 58.778 | BD72: 67.991 | BE72: 258.443 | BF72: 77.568 | BG72: 84.43 | BH72: =BF72+BG72 -> 161.998 | BI72: 110.064 | BJ72: 128.582 | BK72: 400.644 | BL72: 142.314 | BM72: 156.37 | BN72: =BL72+BM72 -> 298.684 | BO72: 173.625 | BP72: 175.572 | BQ72: 647.881 | BR72: 166.532 | BS72: 166.927 | BT72: =BR72+BS72 -> 333.459 | BU72: 174.582 | BV72: 163.349 | BW72: 671.39 | BX72: 160.88 | BY72: 158.404 | BZ72: =BX72+BY72 -> 319.284 | CA72: 180.629 | CB72: 175.908 | CC72: 675.821 | CD72: 160.493 | CE72: 172.035 | CF72: =CD72+CE72 -> 332.528 | CG72: 176.88 | CH72: 168.888 | CI72: 678.296 | CJ72: 163.185 | CK72: 169.623 | CL72: =CJ72+CK72 -> 332.808 | CM72: 180.986 | CN72: 182.895 | CO72: 696.689 | CP72: =CP41 -> 727.33202 | CQ72: =CQ41 -> 759.33953 | CR72: =CR41 -> 792.77306 | CS72: =CS41 -> 827.69692 | CT72: =CT41 -> 864.17839 | CW72: =IFERROR((CT72/CO72)^(1/5)-1,"n/m") -> 0.044029787 | CX72: =IFERROR((CO72/BK72)^(1/5)-1,"n/m") -> 0.11700743 | CY72: =IFERROR((CO72/AG72)^(1/10)-1,"n/m") -> 0.15558256 | CZ72: =IFERROR((CO72/C72)^(1/20)-1,"n/m") -> n/m
B73: Total service revenues and vehicle sales | C73: =C71+C72 -> 528.571 | D73: =D71+D72 -> 560.68 | E73: =E71+E72 -> 784.848 | F73: =F71+F72 -> 743.082 | G73: =G71+G72 -> 772.879 | H73: =H71+H72 -> 872.246 | I73: =I71+I72 -> 924.191 | J73: =J71+J72 -> 238.866 | ... CT73: =CT71+CT72 -> 6188.2594 | CW73: =IFERROR((CT73/CO73)^(1/5)-1,"n/m") -> 0.058085747 | CX73: =IFERROR((CO73/BK73)^(1/5)-1,"n/m") -> 0.11624966 | CY73: =IFERROR((CO73/AG73)^(1/10)-1,"n/m") -> 0.13911906 | CZ73: =IFERROR((CO73/C73)^(1/20)-1,"n/m") -> 0.11504666
B74: Yard operations (incl. yard D&A and stock-based compensation) | C74: 298.023 | D74: 271.523 | E74: 328.919 | F74: 324.793 | G74: 320.212 | H74: 374.149 | I74: 377.604 | J74: 97.119 | K74: 127.164 | L74: =J74+K74 -> 224.283 | M74: 116.41 | N74: 117.535 | O74: 458.228 | P74: 125.956 | Q74: 131.246 | R74: =P74+Q74 -> 257.202 | S74: 131.207 | T74: 132.014 | U74: 520.423 | V74: 131.005 | W74: 129.273 | X74: =V74+W74 -> 260.278 | Y74: 135.222 | Z74: 130.791 | AA74: 526.291 | AB74: 135.909 | AC74: 140.965 | AD74: =AB74+AC74 -> 276.874 | AE74: 151.855 | AF74: 154.175 | AG74: 582.904 | AH74: 167.611 | AI74: 169.081 | AJ74: =AH74+AI74 -> 336.692 | AK74: 166.572 | AL74: 175.137 | AM74: 678.401 | AN74: 217.607 | AO74: 217.184 | AP74: =AN74+AO74 -> 434.791 | AQ74: 201.592 | AR74: 210.485 | AS74: 846.868 | AT74: 207.694 | AU74: 215.46 | AV74: =AT74+AU74 -> 423.154 | AW74: 230.553 | AX74: 234.404 | AY74: 888.111 | AZ74: 240.791 | BA74: 257.351 | BB74: =AZ74+BA74 -> 498.142 | BC74: 253.76 | BD74: 220.585 | BE74: 972.487 | BF74: 231.811 | BG74: 235.904 | BH74: =BF74+BG74 -> 467.715 | BI74: 258.071 | BJ74: 277.506 | BK74: 1003.292 | BL74: 298.694 | BM74: 323.814 | BN74: =BL74+BM74 -> 622.508 | BO74: 346.428 | BP74: 340.561 | BQ74: 1309.497 | BR74: 372.777 | BS74: 375.497 | BT74: =BR74+BS74 -> 748.274 | BU74: 378.958 | BV74: 390.797 | BW74: 1518.029 | BX74: 408.501 | BY74: 409.178 | BZ74: =BX74+BY74 -> 817.679 | CA74: 438.873 | CB74: 453.532 | CC74: 1710.084 | CD74: 496.546 | CE74: 490.056 | CF74: =CD74+CE74 -> 986.602 | CG74: 489.735 | CH74: 467.981 | CI74: 1944.318 | CJ74: 476.489 | CK74: 478.43 | CL74: =CJ74+CK74 -> 954.919 | CM74: 504.19 | CN74: 506.779 | CO74: 1965.888 | CP74: =CP71*CP51 -> 2058.9155 | CQ74: =CQ71*CQ51 -> 2185.0241 | CR74: =CR71*CR51 -> 2326.9232 | CS74: =CS71*CS51 -> 2476.31 | CT74: =CT71*CT51 -> 2635.4201 | CU74: Yard operations = service revenues × yard-operations % (driver block).
B75: Cost of vehicle sales | C75: 0 | D75: 22.375 | E75: 133.67 | F75: 106.029 | G75: 104.673 | H75: 125.202 | I75: 136.971 | J75: 36.311 | K75: 42.204 | L75: =J75+K75 -> 78.515 | M75: 45.631 | N75: 43.09 | O75: 167.236 | P75: 46.091 | Q75: 43.642 | R75: =P75+Q75 -> 89.733 | S75: 46.263 | T75: 38.497 | U75: 174.493 | V75: 37.073 | W75: 32.118 | X75: =V75+W75 -> 69.191 | Y75: 34.503 | Z75: 32.718 | AA75: 136.412 | AB75: 32.068 | AC75: 34.127 | AD75: =AB75+AC75 -> 66.195 | AE75: 37.744 | AF75: 37.02 | AG75: 140.959 | AH75: 33.087 | AI75: 33.686 | AJ75: =AH75+AI75 -> 66.773 | AK75: 34.785 | AL75: 35.994 | AM75: 137.552 | AN75: 38.297 | AO75: 50.313 | AP75: =AN75+AO75 -> 88.61 | AQ75: 57.538 | AR75: 50.313 | AS75: 196.461 | AT75: 57.756 | AU75: 61.212 | AV75: =AT75+AU75 -> 118.968 | AW75: 70.984 | AX75: 65.552 | AY75: 255.504 | AZ75: 58.764 | BA75: 57.9 | BB75: =AZ75+BA75 -> 116.664 | BC75: 53.987 | BD75: 54.643 | BE75: 225.294 | BF75: 64.36 | BG75: 73.629 | BH75: =BF75+BG75 -> 137.989 | BI75: 94.498 | BJ75: 113.641 | BK75: 346.128 | BL75: 126.408 | BM75: 140.304 | BN75: =BL75+BM75 -> 266.712 | BO75: 157.236 | BP75: 161.255 | BQ75: 585.203 | BR75: 151.112 | BS75: 154.727 | BT75: =BR75+BS75 -> 305.839 | BU75: 159.443 | BV75: 149.216 | BW75: 614.498 | BX75: 147.896 | BY75: 146.819 | BZ75: =BX75+BY75 -> 294.715 | CA75: 162.881 | CB75: 161.891 | CC75: 619.487 | CD75: 138.178 | CE75: 147.707 | CF75: =CD75+CE75 -> 285.885 | CG75: 169.714 | CH75: 147.398 | CI75: 602.997 | CJ75: 141.543 | CK75: 150.432 | CL75: =CJ75+CK75 -> 291.975 | CM75: 160.277 | CN75: 164.211 | CO75: 616.463 | CP75: =CP72*(1-CP48) -> 643.68884 | CQ75: =CQ72*(1-CQ48) -> 672.01549 | CR75: =CR72*(1-CR48) -> 701.60416 | CS75: =CS72*(1-CS48) -> 732.51178 | CT75: =CT72*(1-CT48) -> 764.79788 | CU75: Cost of vehicle sales = vehicle sales × (1 − vehicle sales gross margin).
B76: Gross profit | C76: =C73-C74-C75 -> 230.548 | D76: =D73-D74-D75 -> 266.782 | E76: =E73-E74-E75 -> 322.259 | F76: =F73-F74-F75 -> 312.26 | G76: =G73-G74-G75 -> 347.994 | H76: =H73-H74-H75 -> 372.895 | I76: =I73-I74-I75 -> 409.616 | J76: =J73-J74-J75 -> 105.436 | ... CT76: =CT73-CT74-CT75 -> 2788.0414 | CW76: =IFERROR((CT76/CO76)^(1/5)-1,"n/m") -> 0.059952051 | CX76: =IFERROR((CO76/BK76)^(1/5)-1,"n/m") -> 0.091823749 | CY76: =IFERROR((CO76/AG76)^(1/10)-1,"n/m") -> 0.14361585 | CZ76: =IFERROR((CO76/C76)^(1/20)-1,"n/m") -> 0.11636275
B77: Gross margin % | C77: =IFERROR(C76/C73,"") -> 0.43617225 | D77: =IFERROR(D76/D73,"") -> 0.47581865 | E77: =IFERROR(E76/E73,"") -> 0.41060052 | F77: =IFERROR(F76/F73,"") -> 0.4202228 | G77: =IFERROR(G76/G73,"") -> 0.45025677 | H77: =IFERROR(H76/H73,"") -> 0.42751128 | I77: =IFERROR(I76/I73,"") -> 0.44321574 | J77: =IFERROR(J76/J73,"") -> 0.44140229 | ... CT77: =IFERROR(CT76/CT73,"") -> 0.45053726
B78: General and administrative (incl. G&A D&A and stock-based compensation) | C78: 58.986 | D78: 63.637 | E78: 84.342 | F78: 86.935 | G78: 108.924 | H78: 107.605 | I78: 114.492 | J78: 31.079 | K78: 34.047 | L78: =J78+K78 -> 65.126 | M78: 32.784 | N78: 40.02 | O78: 137.93 | P78: 42.877 | Q78: 40.062 | R78: =P78+Q78 -> 82.939 | S78: 40.515 | T78: 41.081 | U78: 164.535 | V78: 39.907 | W78: 34.399 | X78: =V78+W78 -> 74.306 | Y78: 32.65 | Z78: 32.019 | AA78: 138.975 | AB78: 34.615 | AC78: 32.529 | AD78: =AB78+AC78 -> 67.144 | AE78: 35.699 | AF78: 35.273 | AG78: 138.116 | AH78: 40.469 | AI78: 37.885 | AJ78: =AH78+AI78 -> 78.354 | AK78: 35.717 | AL78: 37.293 | AM78: 151.364 | AN78: 39.322 | AO78: 40.662 | AP78: =AN78+AO78 -> 79.984 | AQ78: 44.449 | AR78: 52.457 | AS78: 176.89 | AT78: 44.478 | AU78: 43.487 | AV78: =AT78+AU78 -> 87.965 | AW78: 44.085 | AX78: 49.817 | AY78: 181.867 | AZ78: 49.478 | BA78: 49.997 | BB78: =AZ78+BA78 -> 99.475 | BC78: 47.512 | BD78: 44.716 | BE78: 191.703 | BF78: 48.175 | BG78: 49.277 | BH78: =BF78+BG78 -> 97.452 | BI78: 53.23 | BJ78: 55.983 | BK78: 206.665 | BL78: 54.909 | BM78: 56.014 | BN78: =BL78+BM78 -> 110.923 | BO78: 63.522 | BP78: 56.779 | BQ78: 231.224 | BR78: 57.98 | BS78: 60.975 | BT78: =BR78+BS78 -> 118.955 | BU78: 64.506 | BV78: 66.961 | BW78: 250.422 | BX78: 68.643 | BY78: 84.252 | BZ78: =BX78+BY78 -> 152.895 | CA78: 88.302 | CB78: 94.032 | CC78: 335.229 | CD78: 105.738 | CE78: 99.342 | CF78: =CD78+CE78 -> 205.08 | CG78: 100.722 | CH78: 97.127 | CI78: 402.929 | CJ78: 106.304 | CK78: 104.102 | CL78: =CJ78+CK78 -> 210.406 | CM78: 108.317 | CN78: 112.545 | CO78: 431.268 | CP78: =CP73-CP74-CP75-CP79-CP58+CP102+CP125+CP86+CP85 -> 473.78787 | CQ78: =CQ73-CQ74-CQ75-CQ79-CQ58+CQ102+CQ125+CQ86+CQ85 -> 479.88702 | CR78: =CR73-CR74-CR75-CR79-CR58+CR102+CR125+CR86+CR85 -> 487.39458 | CS78: =CS73-CS74-CS75-CS79-CS58+CS102+CS125+CS86+CS85 -> 493.44627 | CT78: =CT73-CT74-CT75-CT79-CT58+CT102+CT125+CT86+CT85 -> 498.38544 | CU78: Forecast G&A is the balancing line so that adjusted EBITDA equals the KPI driver (margin lever): G&A = revenue − yard operations − cost of vehicle sales − other operating items − adjusted EBITDA + D&A + pre-tax adjusting items + other income + debt-extinguishment result.
B79: Impairment of long-lived assets & other operating items | C79: 0 | D79: 0 | E79: 0 | F79: 0 | G79: 0 | H79: 0 | I79: 8.771 | J79: 0 | K79: 0 | L79: =J79+K79 -> 0 | M79: 0 | N79: 0 | O79: 0 | P79: 0 | Q79: 0 | R79: =P79+Q79 -> 0 | S79: 29.104 | T79: 0 | U79: 29.104 | V79: 0 | W79: 0 | X79: =V79+W79 -> 0 | Y79: 0 | Z79: 0 | AA79: 0 | AB79: 0 | AC79: 0 | AD79: =AB79+AC79 -> 0 | AE79: 0 | AF79: 0 | AG79: 0 | AH79: 0 | AI79: 0 | AJ79: =AH79+AI79 -> 0 | AK79: 0 | AL79: 19.365 | AM79: 19.365 | AN79: 0 | AO79: 0 | AP79: =AN79+AO79 -> 0 | AQ79: 0 | AR79: 1.131 | AS79: 1.131 | AT79: 0 | AU79: 0 | AV79: =AT79+AU79 -> 0 | AW79: 0 | AX79: 0 | AY79: 0 | AZ79: 0 | BA79: 0 | BB79: =AZ79+BA79 -> 0 | BC79: 0 | BD79: 0 | BE79: 0 | BF79: 0 | BG79: 0 | BH79: =BF79+BG79 -> 0 | BI79: 0 | BJ79: 0 | BK79: 0 | BL79: 0 | BM79: 0 | BN79: =BL79+BM79 -> 0 | BO79: 0 | BP79: 0 | BQ79: 0 | BR79: 0 | BS79: 0 | BT79: =BR79+BS79 -> 0 | BU79: 0 | BV79: 0 | BW79: 0 | BX79: 0 | BY79: 0 | BZ79: =BX79+BY79 -> 0 | CA79: 0 | CB79: 0 | CC79: 0 | CD79: 0 | CE79: 0 | CF79: =CD79+CE79 -> 0 | CG79: 0 | CH79: 0 | CI79: 0 | CJ79: 0 | CK79: 0 | CL79: =CJ79+CK79 -> 0 | CM79: 0 | CN79: 0 | CO79: 0 | CP79: 0 | CQ79: 0 | CR79: 0 | CS79: 0 | CT79: 0
B80: Total operating expenses | C80: =C74+C75+C78+C79 -> 357.009 | D80: =D74+D75+D78+D79 -> 357.535 | E80: =E74+E75+E78+E79 -> 546.931 | F80: =F74+F75+F78+F79 -> 517.757 | G80: =G74+G75+G78+G79 -> 533.809 | H80: =H74+H75+H78+H79 -> 606.956 | I80: =I74+I75+I78+I79 -> 637.838 | J80: =J74+J75+J78+J79 -> 164.509 | ... CT80: =CT74+CT75+CT78+CT79 -> 3898.6034
B81: Operating income | C81: =C73-C80 -> 171.562 | D81: =D73-D80 -> 203.145 | E81: =E73-E80 -> 237.917 | F81: =F73-F80 -> 225.325 | G81: =G73-G80 -> 239.07 | H81: =H73-H80 -> 265.29 | I81: =I73-I80 -> 286.353 | J81: =J73-J80 -> 74.357 | ... CT81: =CT73-CT80 -> 2289.656 | CW81: =IFERROR((CT81/CO81)^(1/5)-1,"n/m") -> 0.06738482 | CX81: =IFERROR((CO81/BK81)^(1/5)-1,"n/m") -> 0.077766777 | CY81: =IFERROR((CO81/AG81)^(1/10)-1,"n/m") -> 0.15057163 | CZ81: =IFERROR((CO81/C81)^(1/20)-1,"n/m") -> 0.11992052
B82: Operating margin % | C82: =IFERROR(C81/C73,"") -> 0.32457702 | D82: =IFERROR(D81/D73,"") -> 0.36231897 | E82: =IFERROR(E81/E73,"") -> 0.30313768 | F82: =IFERROR(F81/F73,"") -> 0.30323033 | G82: =IFERROR(G81/G73,"") -> 0.30932397 | H82: =IFERROR(H81/H73,"") -> 0.30414585 | I82: =IFERROR(I81/I73,"") -> 0.3098418 | J82: =IFERROR(J81/J73,"") -> 0.31129169 | ... CT82: =IFERROR(CT81/CT73,"") -> 0.37 | CW82: =IFERROR(AVERAGE(CP82:CT82),"n/m") -> 0.36
B83: Interest expense (FY2021+: presented net within interest income) | C83: 0.072 | D83: 0.083 | E83: 0.209 | F83: 0.274 | G83: 0.216 | H83: 4.078 | I83: 11.341 | J83: 2.632 | K83: 2.588 | L83: =J83+K83 -> 5.22 | M83: 2.538 | N83: 2.509 | O83: 10.267 | P83: 2.286 | Q83: 2.209 | R83: =P83+Q83 -> 4.495 | S83: 2.104 | T83: 2.169 | U83: 8.768 | V83: 1.91 | W83: 4.688 | X83: =V83+W83 -> 6.598 | Y83: 5.917 | Z83: 5.606 | AA83: 18.121 | AB83: 5.724 | AC83: 5.57 | AD83: =AB83+AC83 -> 11.294 | AE83: 5.702 | AF83: 6.61 | AG83: 23.606 | AH83: 5.959 | AI83: 6.144 | AJ83: =AH83+AI83 -> 12.103 | AK83: 5.869 | AL83: 5.807 | AM83: 23.779 | AN83: 5.595 | AO83: 5.758 | AP83: =AN83+AO83 -> 11.353 | AQ83: 4.416 | AR83: 4.599 | AS83: 20.368 | AT83: 4.651 | AU83: 5.233 | AV83: =AT83+AU83 -> 9.884 | AW83: 5.324 | AX83: 4.602 | AY83: 19.81 | AZ83: 4.611 | BA83: 4.914 | BB83: =AZ83+BA83 -> 9.525 | BC83: 5.803 | BD83: 4.902 | BE83: 20.23 | CP83: =CP304 -> 0 | CQ83: =CQ304 -> 0 | CR83: =CR304 -> 0 | CS83: =CS304 -> 0 | CT83: =CT304 -> 0 | CU83: No funded debt since the May-2022 redemption of the senior notes; forecast = rate × average debt (debt schedule).
B84: Interest income (FY2021+: interest income (expense), net) | C84: 8.182 | D84: 13.727 | E84: 7.761 | F84: 1.692 | G84: 0.205 | H84: 0.493 | I84: 0.357 | J84: 0.156 | K84: 0.191 | L84: =J84+K84 -> 0.347 | M84: 0.138 | N84: 0.153 | O84: 0.638 | P84: 0.149 | Q84: 0.143 | R84: =P84+Q84 -> 0.292 | S84: 0.081 | T84: 0.118 | U84: 0.491 | V84: 0.139 | W84: 0.183 | X84: =V84+W84 -> 0.322 | Y84: 0.261 | Z84: 0.234 | AA84: 0.817 | AB84: 0.211 | AC84: 0.602 | AD84: =AB84+AC84 -> 0.813 | AE84: 0.283 | AF84: 0.353 | AG84: 1.449 | AH84: 0.337 | AI84: 0.384 | AJ84: =AH84+AI84 -> 0.721 | AK84: 0.363 | AL84: 0.322 | AM84: 1.406 | AN84: 0.197 | AO84: 0.197 | AP84: =AN84+AO84 -> 0.394 | AQ84: 0.282 | AR84: 0.617 | AS84: 1.293 | AT84: 0.96 | AU84: 0.678 | AV84: =AT84+AU84 -> 1.638 | AW84: 0.24 | AX84: 0.347 | AY84: 2.225 | AZ84: 0.585 | BA84: 0.45 | BB84: =AZ84+BA84 -> 1.035 | BC84: 0.225 | BD84: 0.099 | BE84: 1.359 | BF84: -5.032 | BG84: -4.849 | BH84: =BF84+BG84 -> -9.881 | BI84: -5.346 | BJ84: -5.02 | BK84: -20.247 | BL84: -5.107 | BM84: -4.433 | BN84: =BL84+BM84 -> -9.54 | BO84: -4.492 | BP84: -2.656 | BQ84: -16.688 | BR84: 4.422 | BS84: 14.48 | BT84: =BR84+BS84 -> 18.902 | BU84: 17.878 | BV84: 29.148 | BW84: 65.928 | BX84: 32.005 | BY84: 33.956 | BZ84: =BX84+BY84 -> 65.961 | CA84: 36.218 | CB84: 43.494 | CC84: 145.673 | CD84: 45.547 | CE84: 40.747 | CF84: =CD84+CE84 -> 86.294 | CG84: 42.776 | CH84: 49.839 | CI84: 178.909 | CJ84: 53.505 | CK84: 49.987 | CL84: =CJ84+CK84 -> 103.492 | CM84: 38.813 | CN84: 39.618 | CO84: 181.923 | CP84: =CP305*(CO243+CO244) -> 157.14307 | CQ84: =CQ305*(CP243+CP244) -> 127.05569 | CR84: =CR305*(CQ243+CQ244) -> 136.19317 | CS84: =CS305*(CR243+CR244) -> 146.40519 | CT84: =CT305*(CS243+CS244) -> 157.27351 | CU84: Forecast = yield × prior year-end cash + held-to-maturity investments (avoids a circular reference).
B85: Gain (loss) on extinguishment of debt | C85: 0 | D85: 0 | E85: 0 | BE85: 0 | BK85: 0 | BP85: -16.759 | BQ85: -16.759 | BW85: 0 | CC85: 0 | CP85: 0 | CQ85: 0 | CR85: 0 | CS85: 0 | CT85: 0
B86: Other income (expense), net (incl. FX and equity-method results) | C86: -5.15 | D86: 0.632 | E86: 4.181 | F86: 0.989 | G86: 0.436 | H86: 2.172 | I86: 2.687 | J86: -0.293 | K86: 0.744 | L86: =J86+K86 -> 0.451 | M86: 1.592 | N86: 1.466 | O86: 3.509 | P86: 1.423 | Q86: 1.17 | R86: =P86+Q86 -> 2.593 | S86: 0.708 | T86: 0.077 | U86: 3.378 | V86: 1.593 | W86: 4.141 | X86: =V86+W86 -> 5.734 | Y86: -0.815 | Z86: 0.053 | AA86: 4.972 | AB86: 1.027 | AC86: 4.435 | AD86: =AB86+AC86 -> 5.462 | AE86: 0.039 | AF86: 6.051 | AG86: 11.552 | AH86: 3.332 | AI86: -3.021 | AJ86: =AH86+AI86 -> 0.311 | AK86: -0.194 | AL86: 1.057 | AM86: 1.174 | AN86: -4.416 | AO86: -0.948 | AP86: =AN86+AO86 -> -5.364 | AQ86: 0.731 | AR86: 1.874 | AS86: -2.759 | AT86: 1.037 | AU86: 4.782 | AV86: =AT86+AU86 -> 5.819 | AW86: 1.719 | AX86: -1.477 | AY86: 6.061 | AZ86: 0.717 | BA86: -0.354 | BB86: =AZ86+BA86 -> 0.363 | BC86: 2.277 | BD86: 0.971 | BE86: 3.611 | BF86: 3.253 | BG86: -0.92 | BH86: =BF86+BG86 -> 2.333 | BI86: 0.77 | BJ86: 2.564 | BK86: 5.667 | BL86: 0.812 | BM86: -0.84 | BN86: =BL86+BM86 -> -0.028 | BO86: 1.342 | BP86: -1.91 | BQ86: -0.596 | BR86: -2.822 | BS86: -2.902 | BT86: =BR86+BS86 -> -5.724 | BU86: 3.628 | BV86: 3.927 | BW86: 1.831 | BX86: -4.072 | BY86: -3.103 | BZ86: =BX86+BY86 -> -7.175 | CA86: -1.309 | CB86: 5.389 | CC86: -3.095 | CD86: -0.596 | CE86: -3.907 | CF86: =CD86+CE86 -> -4.503 | CG86: 8.483 | CH86: 15.978 | CI86: 19.958 | CJ86: 2.924 | CK86: 2.352 | CL86: =CJ86+CK86 -> 5.276 | CM86: -1.001 | CN86: -3.811 | CO86: 0.464 | CP86: 0 | CQ86: 0 | CR86: 0 | CS86: 0 | CT86: 0
B87: Income before income taxes | C87: =C81-C83+C84+C85+C86 -> 174.522 | D87: =D81-D83+D84+D85+D86 -> 217.421 | E87: =E81-E83+E84+E85+E86 -> 249.65 | F87: =F81-F83+F84+F85+F86 -> 227.732 | G87: =G81-G83+G84+G85+G86 -> 239.495 | H87: =H81-H83+H84+H85+H86 -> 263.877 | I87: =I81-I83+I84+I85+I86 -> 278.056 | J87: =J81-J83+J84+J85+J86 -> 71.588 | ... CT87: =CT81-CT83+CT84+CT85+CT86 -> 2446.9295 | CW87: =IFERROR((CT87/CO87)^(1/5)-1,"n/m") -> 0.059249251 | CX87: =IFERROR((CO87/BK87)^(1/5)-1,"n/m") -> 0.10341651 | CY87: =IFERROR((CO87/AG87)^(1/10)-1,"n/m") -> 0.16575786 | CZ87: =IFERROR((CO87/C87)^(1/20)-1,"n/m") -> 0.12483552
B88: Income tax expense | C88: 61.862 | D88: 81.083 | E88: 92.718 | F88: 88.186 | G88: 87.868 | H88: 97.502 | I88: 95.937 | J88: 25.743 | K88: 21.477 | L88: =J88+K88 -> 47.22 | M88: 28.769 | N88: 20.858 | O88: 96.847 | P88: 22.823 | Q88: 25.243 | R88: =P88+Q88 -> 48.066 | S88: 20.441 | T88: 22.841 | U88: 91.348 | V88: 29.608 | W88: 27.911 | X88: =V88+W88 -> 57.519 | Y88: 30.733 | Z88: 24.034 | AA88: 112.286 | AB88: 29.15 | AC88: 32.548 | AD88: =AB88+AC88 -> 61.698 | AE88: 41.944 | AF88: 21.863 | AG88: 125.505 | AH88: -64.746 | AI88: 34.033 | AJ88: =AH88+AI88 -> -30.713 | AK88: 40.542 | AL88: 36.01 | AM88: 45.839 | AN88: 36.568 | AO88: 41.137 | AP88: =AN88+AO88 -> 77.705 | AQ88: 43.811 | AR88: 22.988 | AS88: 144.504 | AT88: 34.703 | AU88: 33.593 | AV88: =AT88+AU88 -> 68.296 | AW88: 11.388 | AX88: 33.574 | AY88: 113.258 | AZ88: -16.098 | BA88: 36.367 | BB88: =AZ88+BA88 -> 20.269 | BC88: 44.313 | BD88: 36.35 | BE88: 100.932 | BF88: 46.53 | BG88: 59.012 | BH88: =BF88+BG88 -> 105.542 | BI88: 36.739 | BJ88: 43.07 | BK88: 185.351 | BL88: 65.463 | BM88: 54.643 | BN88: =BL88+BM88 -> 120.106 | BO88: 90.985 | BP88: 39.733 | BQ88: 250.824 | BR88: 67.255 | BS88: 83.426 | BT88: =BR88+BS88 -> 150.681 | BU88: 89.999 | BV88: 75.907 | BW88: 316.587 | BX88: 90.777 | BY88: 85.226 | BZ88: =BX88+BY88 -> 176.003 | CA88: 90.002 | CB88: 86.249 | CC88: 352.254 | CD88: 90.142 | CE88: 76.51 | CF88: =CD88+CE88 -> 166.652 | CG88: 97.466 | CH88: 83.1 | CI88: 347.218 | CJ88: 84.913 | CK88: 91.082 | CL88: =CJ88+CK88 -> 175.995 | CM88: 100.701 | CN88: 77.884 | CO88: 354.58 | CP88: =CP87*CP89 -> 382.83916 | CQ88: =CQ87*CQ89 -> 402.55003 | CR88: =CR87*CR89 -> 433.34935 | CS88: =CS87*CS89 -> 466.26851 | CT88: =CT87*CT89 -> 501.62054
B89: Effective tax rate | C89: =IFERROR(C88/C87,"") -> 0.35446534 | D89: =IFERROR(D88/D87,"") -> 0.37293086 | E89: =IFERROR(E88/E87,"") -> 0.37139195 | F89: =IFERROR(F88/F87,"") -> 0.38723587 | G89: =IFERROR(G88/G87,"") -> 0.36688866 | H89: =IFERROR(H88/H87,"") -> 0.36949791 | I89: =IFERROR(I88/I87,"") -> 0.34502762 | J89: =IFERROR(J88/J87,"") -> 0.35959937 | ... CO89: =IFERROR(CO88/CO87,"") -> 0.19323403 | CP89: 0.205 | CQ89: 0.205 | CR89: 0.205 | CS89: 0.205 | CT89: 0.205 | CU89: Input: FY2026 19.3%, FY2025 18.3% (excess tax benefits on option exercises lower the ETR). 20.5% assumed. | CW89: =IFERROR(AVERAGE(CP89:CT89),"n/m") -> 0.205
B90: Income (loss) from discontinued operations / other, net of tax | C90: -15.713 | D90: 0 | E90: 0 | F90: 1.557 | G90: 0 | H90: 0 | I90: 0 | J90: 0 | K90: 0 | L90: =J90+K90 -> 0 | M90: 0 | N90: 0 | O90: 0 | P90: 0 | Q90: 0 | R90: =P90+Q90 -> 0 | S90: 0 | T90: 0 | U90: 0 | V90: 0 | W90: 0 | X90: =V90+W90 -> 0 | Y90: 0 | Z90: 0 | AA90: 0 | AB90: 0 | AC90: 0.003 | AD90: =AB90+AC90 -> 0.003 | AE90: -0.001 | AF90: -0.002 | AG90: 0 | AH90: 0 | AI90: 0 | AJ90: =AH90+AI90 -> 0 | AK90: 0 | AL90: 0 | AM90: 0 | AN90: 0 | AO90: 0 | AP90: =AN90+AO90 -> 0 | AQ90: 0 | AR90: 0 | AS90: 0 | AT90: 0 | AU90: 0 | AV90: =AT90+AU90 -> 0 | AW90: 0 | AX90: 0 | AY90: 0 | AZ90: 0 | BA90: 0 | BB90: =AZ90+BA90 -> 0 | BC90: 0 | BD90: 0 | BE90: 0 | BF90: 0 | BG90: 0 | BH90: =BF90+BG90 -> 0 | BI90: 0 | BJ90: 0 | BK90: 0 | BL90: 0 | BM90: 0 | BN90: =BL90+BM90 -> 0 | BO90: 0 | BP90: 0 | BQ90: 0 | BR90: 0 | BS90: 0 | BT90: =BR90+BS90 -> 0 | BU90: 0 | BV90: 0 | BW90: 0 | BX90: 0 | BY90: 0 | BZ90: =BX90+BY90 -> 0 | CA90: 0 | CB90: 0 | CC90: 0 | CD90: 0 | CE90: 0 | CF90: =CD90+CE90 -> 0 | CG90: 0 | CH90: 0 | CI90: 0 | CJ90: 0 | CK90: 0 | CL90: =CJ90+CK90 -> 0 | CM90: 0 | CN90: 0 | CO90: 0 | CP90: 0 | CQ90: 0 | CR90: 0 | CS90: 0 | CT90: 0
B91: Net income | C91: =C87-C88+C90 -> 96.947 | D91: =D87-D88+D90 -> 136.338 | E91: =E87-E88+E90 -> 156.932 | F91: =F87-F88+F90 -> 141.103 | G91: =G87-G88+G90 -> 151.627 | H91: =H87-H88+H90 -> 166.375 | I91: =I87-I88+I90 -> 182.119 | J91: =J87-J88+J90 -> 45.845 | ... CT91: =CT87-CT88+CT90 -> 1945.3089 | CW91: =IFERROR((CT91/CO91)^(1/5)-1,"n/m") -> 0.056141424 | CX91: =IFERROR((CO91/BK91)^(1/5)-1,"n/m") -> 0.095909134 | CY91: =IFERROR((CO91/AG91)^(1/10)-1,"n/m") -> 0.18534174 | CZ91: =IFERROR((CO91/C91)^(1/20)-1,"n/m") -> 0.14601998
B92: Less: net income (loss) attributable to noncontrolling interests | C92: 0 | D92: 0 | E92: 0 | AA92: 0 | AG92: 0 | AH92: 0 | AI92: 0 | AJ92: =AH92+AI92 -> 0 | AK92: 0 | AL92: 0.034 | AM92: 0.034 | AN92: 0.045 | AO92: 0.045 | AP92: =AN92+AO92 -> 0.09 | AQ92: 0.057 | AR92: -0.007 | AS92: 0.14 | AT92: 0 | AU92: 0 | AV92: =AT92+AU92 -> 0 | AW92: 0 | AX92: 0 | AY92: 0 | BE92: 0 | BQ92: 0 | BR92: 0 | BS92: 0 | BT92: =BR92+BS92 -> 0 | BU92: 0 | BV92: 0 | BW92: 0 | BX92: 0.005 | BY92: -0.108 | BZ92: =BX92+BY92 -> -0.103 | CA92: -0.181 | CB92: -0.389 | CC92: -0.673 | CD92: -0.91 | CE92: -0.859 | CF92: =CD92+CE92 -> -1.769 | CG92: -1.271 | CH92: -1.046 | CI92: -4.086 | CJ92: -1.504 | CK92: -0.765 | CL92: =CJ92+CK92 -> -2.269 | CM92: -1.008 | CN92: -0.596 | CO92: -3.873 | CP92: 0 | CQ92: 0 | CR92: 0 | CS92: 0 | CT92: 0
B93: Net income attributable to Copart, Inc. | C93: =C91-C92 -> 96.947 | D93: =D91-D92 -> 136.338 | E93: =E91-E92 -> 156.932 | F93: =F91-F92 -> 141.103 | G93: =G91-G92 -> 151.627 | H93: =H91-H92 -> 166.375 | I93: =I91-I92 -> 182.119 | J93: =J91-J92 -> 45.845 | ... CT93: =CT91-CT92 -> 1945.3089 | CW93: =IFERROR((CT93/CO93)^(1/5)-1,"n/m") -> 0.055589677 | CX93: =IFERROR((CO93/BK93)^(1/5)-1,"n/m") -> 0.096481956 | CY93: =IFERROR((CO93/AG93)^(1/10)-1,"n/m") -> 0.18565148 | CZ93: =IFERROR((CO93/C93)^(1/20)-1,"n/m") -> 0.14616971
B94: Check: net income vs as reported (should be 0) | C94: =IF(ISNUMBER(C95),ROUND(C93-C95,1),"") -> 0 | D94: =IF(ISNUMBER(D95),ROUND(D93-D95,1),"") -> 0 | E94: =IF(ISNUMBER(E95),ROUND(E93-E95,1),"") -> 0 | F94: =IF(ISNUMBER(F95),ROUND(F93-F95,1),"") -> 0 | G94: =IF(ISNUMBER(G95),ROUND(G93-G95,1),"") -> 0 | H94: =IF(ISNUMBER(H95),ROUND(H93-H95,1),"") -> 0 | I94: =IF(ISNUMBER(I95),ROUND(I93-I95,1),"") -> 0 | J94: =IF(ISNUMBER(J95),ROUND(J93-J95,1),"") -> 0 | ... CO94: =IF(ISNUMBER(CO95),ROUND(CO93-CO95,1),"") -> 0
B95: Memo: net income attributable to Copart as reported | C95: 96.947 | D95: 136.338 | E95: 156.932 | F95: 141.103 | G95: 151.627 | H95: 166.375 | I95: 182.119 | J95: 45.845 | K95: 39.64 | L95: =J95+K95 -> 85.485 | M95: 53.236 | N95: 41.304 | O95: 180.025 | P95: 41.422 | Q95: 45.345 | R95: =P95+Q95 -> 86.767 | S95: 40.877 | T95: 51.043 | U95: 178.687 | V95: 52.615 | W95: 52.193 | X95: =V95+W95 -> 104.808 | Y95: 57.563 | Z95: 57.412 | AA95: 219.783 | AB95: 52.61 | AC95: 59.007 | AD95: =AB95+AC95 -> 111.617 | AE95: 74.623 | AF95: 84.12 | AG95: 270.36 | AH95: 167.28 | AI95: 66.066 | AJ95: =AH95+AI95 -> 233.346 | AK95: 90.546 | AL95: 70.335 | AM95: 394.227 | AN95: 77.515 | AO95: 103.256 | AP95: =AN95+AO95 -> 180.771 | AQ95: 127.348 | AR95: 109.748 | AS95: 417.867 | AT95: 114.083 | AU95: 131.373 | AV95: =AT95+AU95 -> 245.456 | AW95: 192.741 | AX95: 153.496 | AY95: 591.693 | AZ95: 218.18 | BA95: 168.707 | BB95: =AZ95+BA95 -> 386.887 | BC95: 147.487 | BD95: 165.533 | BE95: 699.907 | BF95: 200.285 | BG95: 193.44 | BH95: =BF95+BG95 -> 393.725 | BI95: 286.796 | BJ95: 255.974 | BK95: 936.495 | BL95: 260.363 | BM95: 287.412 | BN95: =BL95+BM95 -> 547.775 | BO95: 278.62 | BP95: 263.735 | BQ95: 1090.13 | BR95: 245.848 | BS95: 293.677 | BT95: =BR95+BS95 -> 539.525 | BU95: 350.431 | BV95: 347.785 | BW95: 1237.741 | BX95: 332.527 | BY95: 325.635 | BZ95: =BX95+BY95 -> 658.162 | CA95: 382.291 | CB95: 322.567 | CC95: 1363.02 | CD95: 362.086 | CE95: 387.4 | CF95: =CD95+CE95 -> 749.486 | CG95: 406.609 | CH95: 396.354 | CI95: 1552.449 | CJ95: 403.714 | CK95: 350.732 | CL95: =CJ95+CK95 -> 754.446 | CM95: 402.401 | CN95: 327.423 | CO95: 1484.27
B96: (Earnings per share — shares and per-share data restated to the current basis for 2-for-1 splits: Mar-2012, Apr-2017, Nov-2022, Aug-2023)
B97: Weighted-average basic shares (m) | C97: 1445.952 | D97: 1450.416 | E97: 1398.592 | F97: 1336.592 | G97: 1346.64 | H97: 1210.384 | I97: 1024.96 | J97: 994.416 | K97: 997.672 | L97: =AVERAGE(J97,K97) -> 996.044 | M97: 1002.16 | N97: 1003.04 | O97: 999.296 | P97: 1003.68 | Q97: 1004.512 | R97: =AVERAGE(P97,Q97) -> 1004.096 | S97: 1006.352 | T97: 1007.672 | U97: 1005.544 | V97: 1009.736 | W97: 1010.4 | X97: =AVERAGE(V97,W97) -> 1010.068 | Y97: 1011.32 | Z97: 997.944 | AA97: 1007.316 | AB97: 961.24 | AC97: 938.448 | AD97: =AVERAGE(AB97,AC97) -> 949.844 | AE97: 884.352 | AF97: 876.624 | AG97: 915.384 | AH97: 901.744 | AI97: 916.568 | AJ97: =AVERAGE(AH97,AI97) -> 909.156 | AK97: 919.68 | AL97: 921.144 | AM97: 914.744 | AN97: 922.776 | AO97: 925.912 | AP97: =AVERAGE(AN97,AO97) -> 924.344 | AQ97: 928.04 | AR97: 931.98 | AS97: 927.172 | AT97: 935.552 | AU97: 923.192 | AV97: =AVERAGE(AT97,AU97) -> 929.372 | AW97: 911.936 | AX97: 916.816 | AY97: 921.956 | AZ97: 924.676 | BA97: 930.684 | BB97: =AVERAGE(AZ97,BA97) -> 927.68 | BC97: 936.532 | BD97: 939.452 | BE97: 932.808 | BF97: 943.164 | BG97: 944.608 | BH97: =AVERAGE(BF97,BG97) -> 943.886 | BI97: 945.584 | BJ97: 946.716 | BK97: 945.008 | BL97: 948.272 | BM97: 948.744 | BN97: =AVERAGE(BL97,BM97) -> 948.508 | BO97: 950.02 | BP97: 951.364 | BQ97: 949.676 | BR97: 952.198 | BS97: 952.752 | BT97: =AVERAGE(BR97,BS97) -> 952.475 | BU97: 953.574 | BV97: 955.773 | BW97: 953.574 | BX97: 958.127 | BY97: 960.525 | BZ97: =AVERAGE(BX97,BY97) -> 959.326 | CA97: 961.813 | CB97: 962.515 | CC97: 960.739 | CD97: 963.176 | CE97: 964.746 | CF97: =AVERAGE(CD97,CE97) -> 963.961 | CG97: 966.234 | CH97: 967.1 | CI97: 965.306 | CJ97: 967.65 | CK97: 967.212 | CL97: =AVERAGE(CJ97,CK97) -> 967.431 | CM97: 936.293 | CN97: 927.067 | CO97: 949.64 | CP97: =AVERAGE(CP227,CP228) -> 894.61248 | CQ97: =AVERAGE(CQ227,CQ228) -> 846.54856 | CR97: =AVERAGE(CR227,CR228) -> 813.86581 | CS97: =AVERAGE(CS227,CS228) -> 781.09375 | CT97: =AVERAGE(CT227,CT228) -> 748.04046 | CU97: 2027E+ = average of beginning and ending shares (buyback schedule).
B98: Weighted-average diluted shares (m) | C98: 1486.8 | D98: 1495.28 | E98: 1437.728 | F98: 1358.88 | G98: 1360.432 | H98: 1226.816 | I98: 1051.424 | J98: 1027.784 | K98: 1036.16 | L98: =AVERAGE(J98,K98) -> 1031.972 | M98: 1044.24 | N98: 1044.904 | O98: 1038.248 | P98: 1045.648 | Q98: 1048.808 | R98: =AVERAGE(P98,Q98) -> 1047.228 | S98: 1051.888 | T98: 1053.032 | U98: 1049.84 | V98: 1052.136 | W98: 1054.976 | X98: =AVERAGE(V98,W98) -> 1053.556 | Y98: 1056.992 | Z98: 1041.64 | AA98: 1051.404 | AB98: 1017.152 | AC98: 996.896 | AD98: =AVERAGE(AB98,AC98) -> 1007.024 | AE98: 945.648 | AF98: 948.152 | AG98: 977.18 | AH98: 951.032 | AI98: 942.352 | AJ98: =AVERAGE(AH98,AI98) -> 946.692 | AK98: 948.54 | AL98: 950.536 | AM98: 948.076 | AN98: 955.164 | AO98: 965.44 | AP98: =AVERAGE(AN98,AO98) -> 960.302 | AQ98: 971.84 | AR98: 977.624 | AS98: 967.508 | AT98: 979.304 | AU98: 962.64 | AV98: =AVERAGE(AT98,AU98) -> 970.972 | AW98: 951.568 | AX98: 953.416 | AY98: 961.812 | AZ98: 954.648 | BA98: 953.88 | BB98: =AVERAGE(AZ98,BA98) -> 954.264 | BC98: 954.364 | BD98: 955.708 | BE98: 954.624 | BF98: 959.872 | BG98: 961.12 | BH98: =AVERAGE(BF98,BG98) -> 960.496 | BI98: 960.832 | BJ98: 962.856 | BK98: 961.16 | BL98: 964.884 | BM98: 964.748 | BN98: =AVERAGE(BL98,BM98) -> 964.816 | BO98: 962.896 | BP98: 962.944 | BQ98: 964.604 | BR98: 964.336 | BS98: 965.072 | BT98: =AVERAGE(BR98,BS98) -> 964.704 | BU98: 967.38 | BV98: 970.255 | BW98: 966.647 | BX98: 971.682 | BY98: 974.589 | BZ98: =AVERAGE(BX98,BY98) -> 973.1355 | CA98: 976.445 | CB98: 976.5 | CC98: 974.798 | CD98: 976.506 | CE98: 977.91 | CF98: =AVERAGE(CD98,CE98) -> 977.208 | CG98: 978.089 | CH98: 977.778 | CI98: 977.563 | CJ98: 977.1 | CK98: 975.089 | CL98: =AVERAGE(CJ98,CK98) -> 976.0945 | CM98: 942.77 | CN98: 932.14 | CO98: 956.86 | CP98: =CP97+CP299 -> 901.11248 | CQ98: =CQ97+CQ299 -> 853.04856 | CR98: =CR97+CR299 -> 820.36581 | CS98: =CS97+CS299 -> 787.59375 | CT98: =CT97+CT299 -> 754.54046 | CU98: Diluted = basic + dilutive options / RSUs (input).
B99: EPS – basic ($) | C99: =IFERROR(C93/C97,"") -> 0.067047177 | D99: =IFERROR(D93/D97,"") -> 0.093999239 | E99: =IFERROR(E93/E97,"") -> 0.11220713 | F99: =IFERROR(F93/F97,"") -> 0.10556924 | G99: =IFERROR(G93/G97,"") -> 0.11259654 | H99: =IFERROR(H93/H97,"") -> 0.13745638 | I99: =IFERROR(I93/I97,"") -> 0.17768401 | J99: =IFERROR(J93/J97,"") -> 0.046102436 | ... CT99: =IFERROR(CT93/CT97,"") -> 2.6005397 | CW99: =IFERROR((CT99/CO99)^(1/5)-1,"n/m") -> 0.10718939 | CX99: =IFERROR((CO99/BK99)^(1/5)-1,"n/m") -> 0.095410215 | CY99: =IFERROR((CO99/AG99)^(1/10)-1,"n/m") -> 0.18130347 | CZ99: =IFERROR((CO99/C99)^(1/20)-1,"n/m") -> 0.17051955
B100: EPS – diluted ($) | C100: =IFERROR(C93/C98,"") -> 0.065205139 | D100: =IFERROR(D93/D98,"") -> 0.09117891 | E100: =IFERROR(E93/E98,"") -> 0.10915277 | F100: =IFERROR(F93/F98,"") -> 0.10383772 | G100: =IFERROR(G93/G98,"") -> 0.11145504 | H100: =IFERROR(H93/H98,"") -> 0.13561528 | I100: =IFERROR(I93/I98,"") -> 0.17321176 | J100: =IFERROR(J93/J98,"") -> 0.044605676 | ... CT100: =IFERROR(CT93/CT98,"") -> 2.5781373 | CU100: EPS computed as net income attributable to Copart / weighted diluted shares (may differ by ±$0.01 vs reported). | CW100: =IFERROR((CT100/CO100)^(1/5)-1,"n/m") -> 0.10695077 | CX100: =IFERROR((CO100/BK100)^(1/5)-1,"n/m") -> 0.097465678 | CY100: =IFERROR((CO100/AG100)^(1/10)-1,"n/m") -> 0.1881456 | CZ100: =IFERROR((CO100/C100)^(1/20)-1,"n/m") -> 0.1717073
B101: Memo: EPS – diluted as reported ($, split-adjusted) | C101: 0.065 | D101: 0.09125 | E101: 0.109375 | F101: 0.10375 | G101: 0.11125 | H101: 0.135 | I101: 0.17375 | J101: 0.045 | K101: 0.03875 | L101: =J101+K101 -> 0.08375 | M101: 0.05125 | N101: 0.04 | O101: 0.17375 | P101: 0.04 | Q101: 0.04375 | R101: =P101+Q101 -> 0.08375 | S101: 0.03875 | T101: 0.04875 | U101: 0.17 | V101: 0.05 | W101: 0.05 | X101: =V101+W101 -> 0.1 | Y101: 0.055 | Z101: 0.055 | AA101: 0.21 | AB101: 0.0525 | AC101: 0.06 | AD101: =AB101+AC101 -> 0.1125 | AE101: 0.08 | AF101: 0.08875 | AG101: 0.2775 | AH101: 0.175 | AI101: 0.07 | AJ101: =AH101+AI101 -> 0.245 | AK101: 0.095 | AL101: 0.075 | AM101: 0.415 | AN101: 0.08 | AO101: 0.1075 | AP101: =AN101+AO101 -> 0.1875 | AQ101: 0.13 | AR101: 0.1125 | AS101: 0.4325 | AT101: 0.1175 | AU101: 0.1375 | AV101: =AT101+AU101 -> 0.255 | AW101: 0.2025 | AX101: 0.16 | AY101: 0.615 | AZ101: 0.2275 | BA101: 0.1775 | BB101: =AZ101+BA101 -> 0.405 | BC101: 0.155 | BD101: 0.1725 | BE101: 0.7325 | BF101: 0.2075 | BG101: 0.2025 | BH101: =BF101+BG101 -> 0.41 | BI101: 0.2975 | BJ101: 0.265 | BK101: 0.97 | BL101: 0.27 | BM101: 0.3 | BN101: =BL101+BM101 -> 0.57 | BO101: 0.29 | BP101: 0.275 | BQ101: 1.13 | BR101: 0.25 | BS101: 0.3 | BT101: =BR101+BS101 -> 0.55 | BU101: 0.36 | BV101: 0.36 | BW101: 1.28 | BX101: 0.34 | BY101: 0.33 | BZ101: =BX101+BY101 -> 0.67 | CA101: 0.39 | CB101: 0.33 | CC101: 1.4 | CD101: 0.37 | CE101: 0.4 | CF101: =CD101+CE101 -> 0.77 | CG101: 0.42 | CH101: 0.41 | CI101: 1.59 | CJ101: 0.41 | CK101: 0.36 | CL101: =CJ101+CK101 -> 0.77 | CM101: 0.43 | CN101: 0.35 | CO101: 1.55
B102: Memo: depreciation & amortization (within yard operations and G&A) | C102: 31.456 | D102: 37.089 | E102: 42.804 | F102: 41.354 | G102: 43.242 | H102: 45.694 | I102: 48.167 | J102: 12.839 | K102: 14.612 | L102: =J102+K102 -> 27.451 | M102: 14.797 | N102: 14.48 | O102: 56.728 | P102: 14.504 | Q102: 13.076 | R102: =P102+Q102 -> 27.58 | S102: 12.769 | T102: 13.377 | U102: 53.726 | V102: 13.967 | W102: 11.4 | X102: =V102+W102 -> 25.367 | Y102: 12.212 | Z102: 8.994 | AA102: 46.573 | AB102: 11.521 | AC102: 11.691 | AD102: =AB102+AC102 -> 23.212 | AE102: 12.358 | AF102: 13.005 | AG102: 48.575 | AH102: 14.709 | AI102: 15.215 | AJ102: =AH102+AI102 -> 29.924 | AK102: 13.208 | AL102: 13.868 | AM102: 57 | AN102: 15.902 | AO102: 17.871 | AP102: =AN102+AO102 -> 33.773 | AQ102: 16.573 | AR102: 28.252 | AS102: 78.598 | AT102: 21.869 | AU102: 20.399 | AV102: =AT102+AU102 -> 42.268 | AW102: 21.112 | AX102: 21.515 | AY102: 84.895 | AZ102: 23.014 | BA102: 24.282 | BB102: =AZ102+BA102 -> 47.296 | BC102: 26.715 | BD102: 27.379 | BE102: 101.39 | BF102: 28.949 | BG102: 31.392 | BH102: =BF102+BG102 -> 60.341 | BI102: 31.966 | BJ102: 29.664 | BK102: 121.971 | BL102: 31.76 | BM102: 33.303 | BN102: =BL102+BM102 -> 65.063 | BO102: 36.579 | BP102: 36.333 | BQ102: 137.985 | BR102: 39.058 | BS102: 38.414 | BT102: =BR102+BS102 -> 77.472 | BU102: 37.371 | BV102: 44.635 | BW102: 159.478 | BX102: 43.164 | BY102: 45.262 | BZ102: =BX102+BY102 -> 88.426 | CA102: 50.733 | CB102: 50.603 | CC102: 189.761 | CD102: 53.627 | CE102: 54.199 | CF102: =CD102+CE102 -> 107.826 | CG102: 54.416 | CH102: 53.607 | CI102: 215.849 | CJ102: 54.042 | CK102: 55.387 | CL102: =CJ102+CK102 -> 109.429 | CM102: 58.983 | CN102: 60.961 | CO102: 229.373 | CP102: =CP73*CP52 -> 244.33786 | CQ102: =CQ73*CQ52 -> 258.67648 | CR102: =CR73*CR52 -> 274.6814 | CS102: =CS73*CS52 -> 291.51717 | CT102: =CT73*CT52 -> 309.41297
B103: Memo: stock-based compensation (within yard operations and G&A) | C103: 3.53 | D103: 3.424 | E103: 6.356 | F103: 9.413 | G103: 17.955 | H103: 19.007 | I103: 21.791 | J103: 5.174 | K103: 4.746 | L103: =J103+K103 -> 9.92 | M103: 4.677 | N103: 4.886 | O103: 19.557 | P103: 4.867 | Q103: 5.772 | R103: =P103+Q103 -> 10.639 | S103: 6.623 | T103: 4.837 | U103: 22.099 | V103: 4.366 | W103: 4.504 | X103: =V103+W103 -> 8.87 | Y103: 4.42 | Z103: 4.864 | AA103: 18.154 | AB103: 5.414 | AC103: 5.386 | AD103: =AB103+AC103 -> 10.8 | AE103: 5.034 | AF103: 5.03 | AG103: 20.864 | AH103: 5.085 | AI103: 5.52 | AJ103: =AH103+AI103 -> 10.605 | AK103: 5.008 | AL103: 5.227 | AM103: 20.84 | AN103: 5.306 | AO103: 5.992 | AP103: =AN103+AO103 -> 11.298 | AQ103: 5.941 | AR103: 5.982 | AS103: 23.221 | AT103: 6.021 | AU103: 5.929 | AV103: =AT103+AU103 -> 11.95 | AW103: 5.65 | AX103: 5.845 | AY103: 23.445 | AZ103: 5.533 | BA103: 6.141 | BB103: =AZ103+BA103 -> 11.674 | BC103: 5.555 | BD103: 6.093 | BE103: 23.322 | BF103: 8.913 | BG103: 8.865 | BH103: =BF103+BG103 -> 17.778 | BI103: 9.367 | BJ103: 13.777 | BK103: 40.922 | BL103: 9.452 | BM103: 9.662 | BN103: =BL103+BM103 -> 19.114 | BO103: 9.818 | BP103: 10.033 | BQ103: 38.965 | BR103: 10.192 | BS103: 10.131 | BT103: =BR103+BS103 -> 20.323 | BU103: 10.081 | BV103: 9.269 | BW103: 39.673 | BX103: 8.317 | BY103: 9.169 | BZ103: =BX103+BY103 -> 17.486 | CA103: 9.018 | CB103: 8.54 | CC103: 35.234 | CD103: 10.415 | CE103: 9.317 | CF103: =CD103+CE103 -> 19.732 | CG103: 9.173 | CH103: 9.099 | CI103: 38.004 | CJ103: 9.319 | CK103: 10.231 | CL103: =CJ103+CK103 -> 19.55 | CM103: 9.463 | CN103: 9.805 | CO103: 38.818 | CP103: =CP73*CP53 -> 39.094057 | CQ103: =CQ73*CQ53 -> 41.388237 | CR103: =CR73*CR53 -> 43.949025 | CS103: =CS73*CS53 -> 46.642747 | CT103: =CT73*CT53 -> 49.506075
B104: Memo: amortization of intangible assets (within D&A) | C104: 0.7 | D104: 1.4 | E104: 5.8 | F104: 4.1 | G104: 3.9 | H104: 4.7 | I104: 4.5 | J104: 1.1 | K104: 1.1 | L104: =J104+K104 -> 2.2 | M104: 1 | N104: 1.6 | O104: 4.8 | P104: 1.1 | Q104: 1.2 | R104: =P104+Q104 -> 2.3 | S104: 1.5 | T104: 3.1 | U104: 6.9 | V104: 1.9 | W104: 1.7 | X104: =V104+W104 -> 3.6 | Y104: 1.5 | Z104: 1.7 | AA104: 6.8 | AB104: 1.5 | AC104: 1.5 | AD104: =AB104+AC104 -> 3 | AE104: 1.4 | AF104: 1.4 | AG104: 5.8 | AH104: 1.3 | AI104: 1.3 | AJ104: =AH104+AI104 -> 2.6 | AK104: 1.4 | AL104: 2.8 | AM104: 6.8 | AN104: 3.8 | AO104: 3.5 | AP104: =AN104+AO104 -> 7.3 | AQ104: 3.6 | AR104: 3.1 | AS104: 14 | AT104: 2.9 | AU104: 2.6 | AV104: =AT104+AU104 -> 5.5 | AW104: 2.5 | AX104: 2.5 | AY104: 10.5 | AZ104: 2.5 | BA104: 2.3 | BB104: =AZ104+BA104 -> 4.8 | BC104: 2.2 | BD104: 1.9 | BE104: 8.9 | BF104: 1.8 | BG104: 1.8 | BH104: =BF104+BG104 -> 3.6 | BI104: 1.8 | BJ104: 1.6 | BK104: 6.9 | BL104: 1.8 | BM104: 1.8 | BN104: =BL104+BM104 -> 3.6 | BO104: 1.9 | BP104: 1.9 | BQ104: 7.5 | BR104: 1.9 | BS104: 1.9 | BT104: =BR104+BS104 -> 3.8 | BU104: 1.9 | BV104: 6.8 | BW104: 12.4 | BX104: 3.1 | BY104: 3.5 | BZ104: =BX104+BY104 -> 6.6 | CA104: 3.3 | CB104: 3.4 | CC104: 13.4 | CD104: 3.6 | CE104: 3.4 | CF104: =CD104+CE104 -> 7 | CG104: 3.5 | CH104: 3.5 | CI104: 13.9 | CO104: 13 | CP104: =CP298 -> 12 | CQ104: =CQ298 -> 11 | CR104: =CR298 -> 9 | CS104: =CS298 -> 7 | CT104: =CT298 -> 5
B106: RECONCILIATION: GAAP NET INCOME → EBITDA → ADJUSTED EBITDA → ADJUSTED EBIT | CU106: ADJUSTED EBITDA RECONCILIATION — Copart publishes no EBITDA; adjusting items = Copart's own non-GAAP items (pre-tax), definition in force in each period
B107: Net income (GAAP, incl. noncontrolling interests) | C107: =C91 -> 96.947 | D107: =D91 -> 136.338 | E107: =E91 -> 156.932 | F107: =F91 -> 141.103 | G107: =G91 -> 151.627 | H107: =H91 -> 166.375 | I107: =I91 -> 182.119 | J107: =J91 -> 45.845 | ... CT107: =CT91 -> 1945.3089
B108: (+) Depreciation and amortization | C108: =C102 -> 31.456 | D108: =D102 -> 37.089 | E108: =E102 -> 42.804 | F108: =F102 -> 41.354 | G108: =G102 -> 43.242 | H108: =H102 -> 45.694 | I108: =I102 -> 48.167 | J108: =J102 -> 12.839 | ... CT108: =CT102 -> 309.41297
...

Sheet Bull-Base-Bear
B2: Copart, Inc. (CPRT) — Bull / Base / Bear Case P&L Summary | J2: Share price ($): | K2: =Model!$CO$344 -> 27
B3: Adjusted figures (Copart non-GAAP definition; adjusted = GAAP since Q1/24) · USD millions · fiscal years ending 31-July · Live panel linked to Model — toggle scenario via Model!CU2. Bull and Bear panels are value snapshots of the Model run with the switch set to Bull / Bear. Standalone (pending ACV Auctions acquisition excluded). | J3: As of: | K3: =TODAY() -> 46298
B5: Scenario: | C5: =Model!CU2 -> Base | N5: Scenario: | O5: Bull | P5: Snapshot (values) — Model run with switch = Bull | Z5: Scenario: | AA5: Bear | AB5: Snapshot (values) — Model run with switch = Bear
B7: (USDm, except EPS and shares) | C7: 2026A | D7: 2027E | E7: 2028E | F7: 2029E | G7: 2030E | H7: 2031E | I7: 26-'31 CAGR | J7: LT Hist Avg | K7: LT Hist Min | L7: LT Hist Max | N7: (USDm, except EPS and shares) | O7: 2026A | P7: 2027E | Q7: 2028E | R7: 2029E | S7: 2030E | T7: 2031E | U7: 26-'31 CAGR | V7: LT Hist Avg | W7: LT Hist Min | X7: LT Hist Max | Z7: (USDm, except EPS and shares) | AA7: 2026A | AB7: 2027E | AC7: 2028E | AD7: 2029E | AE7: 2030E | AF7: 2031E | AG7: 26-'31 CAGR | AH7: LT Hist Avg | AI7: LT Hist Min | AJ7: LT Hist Max
B9: Revenue | C9: =Model!CO73 -> 4666.209 | D9: =Model!CP73 -> 4886.7572 | E9: =Model!CQ73 -> 5173.5296 | F9: =Model!CR73 -> 5493.6281 | G9: =Model!CS73 -> 5830.3434 | H9: =Model!CT73 -> 6188.2594 | I9: =IFERROR((H9/C9)^(1/5)-1,"n/m") -> 0.058085747 | N9: Revenue | O9: 4666.209 | P9: 5003.4286 | Q9: 5423.1534 | R9: 5896.6261 | S9: 6409.1479 | T9: 6967.9875 | U9: 0.083499299 | Z9: Revenue | AA9: 4666.209 | AB9: 4714.2912 | AC9: 4817.302 | AD9: 4938.2629 | AE9: 5059.9564 | AF9: 5185.7531 | AG9: 0.021338093
B10: Revenue y/y % | D10: =IFERROR(D9/C9-1,"") -> 0.047264959 | E10: =IFERROR(E9/D9-1,"") -> 0.058683588 | F10: =IFERROR(F9/E9-1,"") -> 0.061872358 | G10: =IFERROR(G9/F9-1,"") -> 0.061291968 | H10: =IFERROR(H9/G9-1,"") -> 0.061388492 | N10: Revenue y/y % | P10: 0.07226844 | Q10: 0.083887422 | R10: 0.087305805 | S10: 0.086917795 | T10: 0.087194053 | Z10: Revenue y/y % | AB10: 0.010304337 | AC10: 0.021850751 | AD10: 0.025109681 | AE10: 0.024642973 | AF10: 0.02486123
B11: Service revenues | C11: =Model!CO71 -> 3969.52 | D11: =Model!CP71 -> 4159.4252 | E11: =Model!CQ71 -> 4414.1901 | F11: =Model!CR71 -> 4700.855 | G11: =Model!CS71 -> 5002.6464 | H11: =Model!CT71 -> 5324.081 | I11: =IFERROR((H11/C11)^(1/5)-1,"n/m") -> 0.060477189 | N11: Service revenues | O11: 3969.52 | P11: 4276.0966 | Q11: 4663.8138 | R11: 5103.8531 | S11: 5581.451 | T11: 6103.8091 | U11: 0.089864707 | Z11: Service revenues | AA11: 3969.52 | AB11: 3986.9592 | AC11: 4057.9625 | AD11: 4145.4898 | AE11: 4232.2595 | AF11: 4321.5747 | AG11: 0.017140171
B12: Adjusted EBIT (model) | C12: =Model!CO63 -> 1653.054 | D12: =Model!CP63 -> 1710.365 | E12: =Model!CQ63 -> 1836.603 | F12: =Model!CR63 -> 1977.7061 | G12: =Model!CS63 -> 2128.0753 | H12: =Model!CT63 -> 2289.656 | I12: =IFERROR((H12/C12)^(1/5)-1,"n/m") -> 0.067324892 | N12: Adjusted EBIT (model) | O12: 1653.054 | P12: 1826.2515 | Q12: 2006.5667 | R12: 2211.2348 | S12: 2435.4762 | T12: 2682.6752 | U12: 0.10168189 | Z12: Adjusted EBIT (model) | AA12: 1653.054 | AB12: 1555.7161 | AC12: 1613.7962 | AD12: 1679.0094 | AE12: 1745.685 | AF12: 1815.0136 | AG12: 0.018869515
B13: Adjusted EBIT margin % | C13: =IFERROR(C12/C9,"") -> 0.3542606 | D13: =IFERROR(D12/D9,"") -> 0.35 | E13: =IFERROR(E12/E9,"") -> 0.355 | F13: =IFERROR(F12/F9,"") -> 0.36 | G13: =IFERROR(G12/G9,"") -> 0.365 | H13: =IFERROR(H12/H9,"") -> 0.37 | J13: =IFERROR(AVERAGE(Model!C64,Model!D64,Model!E64,Model!F64,Model!G64,Model!H64,Model!I64,Model!O64,Model!U64,Model!AA64,Model!AG64,Model!AM64,Model!AS64,Model!AY64,Model!BE64,Model!BK64,Model!BQ64,Model!BW64,Model!CC64,Model!CI64,Model!CO64),"") -> 0.33690307 | K13: =IFERROR(MIN(Model!C64,Model!D64,Model!E64,Model!F64,Model!G64,Model!H64,Model!I64,Model!O64,Model!U64,Model!AA64,Model!AG64,Model!AM64,Model!AS64,Model!AY64,Model!BE64,Model!BK64,Model!BQ64,Model!BW64,Model!CC64,Model!CI64,Model!CO64),"") -> 0.26421909 | L13: =IFERROR(MAX(Model!C64,Model!D64,Model!E64,Model!F64,Model!G64,Model!H64,Model!I64,Model!O64,Model!U64,Model!AA64,Model!AG64,Model!AM64,Model!AS64,Model!AY64,Model!BE64,Model!BK64,Model!BQ64,Model!BW64,Model!CC64,Model!CI64,Model!CO64),"") -> 0.42551742 | N13: Adjusted EBIT margin % | O13: 0.3542606 | P13: 0.365 | Q13: 0.37 | R13: 0.375 | S13: 0.38 | T13: 0.385 | V13: 0.33690307 | W13: 0.26421909 | X13: 0.42551742 | Z13: Adjusted EBIT margin % | AA13: 0.3542606 | AB13: 0.33 | AC13: 0.335 | AD13: 0.34 | AE13: 0.345 | AF13: 0.35 | AH13: 0.33690307 | AI13: 0.26421909 | AJ13: 0.42551742
B15: Operating Income (GAAP) | C15: =Model!CO81 -> 1652.59 | D15: =Model!CP81 -> 1710.365 | E15: =Model!CQ81 -> 1836.603 | F15: =Model!CR81 -> 1977.7061 | G15: =Model!CS81 -> 2128.0753 | H15: =Model!CT81 -> 2289.656 | I15: =IFERROR((H15/C15)^(1/5)-1,"n/m") -> 0.06738482 | N15: Operating Income (GAAP) | O15: 1652.59 | P15: 1826.2515 | Q15: 2006.5667 | R15: 2211.2348 | S15: 2435.4762 | T15: 2682.6752 | U15: 0.10174375 | Z15: Operating Income (GAAP) | AA15: 1652.59 | AB15: 1555.7161 | AC15: 1613.7962 | AD15: 1679.0094 | AE15: 1745.685 | AF15: 1815.0136 | AG15: 0.018926723
B16: Operating income y/y % | D16: =IFERROR(D15/C15-1,"") -> 0.034960281 | E16: =IFERROR(E15/D15-1,"") -> 0.073807639 | F16: =IFERROR(F15/E15-1,"") -> 0.076828306 | G16: =IFERROR(G15/F15-1,"") -> 0.076032134 | H16: =IFERROR(H15/G15-1,"") -> 0.07592806 | N16: Operating income y/y % | P16: 0.10508442 | Q16: 0.098735195 | R16: 0.10199913 | S16: 0.10141003 | T16: 0.10149924 | Z16: Operating income y/y % | AB16: -0.058619444 | AC16: 0.037333338 | AD16: 0.040409825 | AE16: 0.039711252 | AF16: 0.039714291
B17: Operating margin (GAAP) % | C17: =IFERROR(C15/C9,"") -> 0.35416116 | D17: =IFERROR(D15/D9,"") -> 0.35 | E17: =IFERROR(E15/E9,"") -> 0.355 | F17: =IFERROR(F15/F9,"") -> 0.36 | G17: =IFERROR(G15/G9,"") -> 0.365 | H17: =IFERROR(H15/H9,"") -> 0.37 | J17: =IFERROR(AVERAGE(Model!C171,Model!D171,Model!E171,Model!F171,Model!G171,Model!H171,Model!I171,Model!O171,Model!U171,Model!AA171,Model!AG171,Model!AM171,Model!AS171,Model!AY171,Model!BE171,Model!BK171,Model!BQ171,Model!BW171,Model!CC171,Model!CI171,Model!CO171),"") -> 0.33317515 | K17: =IFERROR(MIN(Model!C171,Model!D171,Model!E171,Model!F171,Model!G171,Model!H171,Model!I171,Model!O171,Model!U171,Model!AA171,Model!AG171,Model!AM171,Model!AS171,Model!AY171,Model!BE171,Model!BK171,Model!BQ171,Model!BW171,Model!CC171,Model!CI171,Model!CO171),"") -> 0.23630133 | L17: =IFERROR(MAX(Model!C171,Model!D171,Model!E171,Model!F171,Model!G171,Model!H171,Model!I171,Model!O171,Model!U171,Model!AA171,Model!AG171,Model!AM171,Model!AS171,Model!AY171,Model!BE171,Model!BK171,Model!BQ171,Model!BW171,Model!CC171,Model!CI171,Model!CO171),"") -> 0.42206921 | N17: Operating margin (GAAP) % | O17: 0.35416116 | P17: 0.365 | Q17: 0.37 | R17: 0.375 | S17: 0.38 | T17: 0.385 | V17: 0.33317515 | W17: 0.23630133 | X17: 0.42206921 | Z17: Operating margin (GAAP) % | AA17: 0.35416116 | AB17: 0.33 | AC17: 0.335 | AD17: 0.34 | AE17: 0.345 | AF17: 0.35 | AH17: 0.33317515 | AI17: 0.23630133 | AJ17: 0.42206921
B19: Net Income (Adjusted, available to common) | C19: =Model!CO148 -> 1484.27 | D19: =Model!CP148 -> 1484.6689 | E19: =Model!CQ148 -> 1561.1087 | F19: =Model!CR148 -> 1680.5499 | G19: =Model!CS148 -> 1808.212 | H19: =Model!CT148 -> 1945.3089 | I19: =IFERROR((H19/C19)^(1/5)-1,"n/m") -> 0.055589677 | N19: Net Income (Adjusted, available to common) | O19: 1484.27 | P19: 1576.7986 | Q19: 1675.6949 | R19: 1844.4514 | S19: 2032.593 | T19: 2239.5364 | U19: 0.085748014 | Z19: Net Income (Adjusted, available to common) | AA19: 1484.27 | AB19: 1361.723 | AC19: 1423.0195 | AD19: 1506.4472 | AE19: 1593.0484 | AF19: 1683.8774 | AG19: 0.02555631
B21: FDSO (m) | C21: =Model!CO98 -> 956.86 | D21: =Model!CP98 -> 901.11248 | E21: =Model!CQ98 -> 853.04856 | F21: =Model!CR98 -> 820.36581 | G21: =Model!CS98 -> 787.59375 | H21: =Model!CT98 -> 754.54046 | I21: =IFERROR((H21/C21)^(1/5)-1,"n/m") -> -0.046398718 | N21: FDSO (m) | O21: 956.86 | P21: 885.95651 | Q21: 820.39624 | R21: 784.28197 | S21: 748.67086 | T21: 711.23182 | U21: -0.057605905 | Z21: FDSO (m) | AA21: 956.86 | AB21: 929.10619 | AC21: 926.10534 | AD21: 927.54077 | AE21: 929.07855 | AF21: 930.71199 | AG21: -0.005526117
B23: Adjusted EPS — Diluted ($) | C23: =Model!CO152 -> 1.5511883 | D23: =Model!CP152 -> 1.6475956 | E23: =Model!CQ152 -> 1.8300349 | F23: =Model!CR152 -> 2.0485373 | G23: =Model!CS152 -> 2.2958689 | H23: =Model!CT152 -> 2.5781373 | I23: =IFERROR((H23/C23)^(1/5)-1,"n/m") -> 0.10695077 | N23: Adjusted EPS — Diluted ($) | O23: 1.5511883 | P23: 1.7797698 | Q23: 2.0425434 | R23: 2.3517708 | S23: 2.7149354 | T23: 3.1488136 | U23: 0.15211674 | Z23: Adjusted EPS — Diluted ($) | AA23: 1.5511883 | AB23: 1.4656269 | AC23: 1.5365634 | AD23: 1.6241304 | AE23: 1.7146542 | AF23: 1.8092357 | AG23: 0.031255147
B24: EPS y/y % | D24: =IFERROR(D23/C23-1,"") -> 0.062150618 | E24: =IFERROR(E23/D23-1,"") -> 0.11073067 | F24: =IFERROR(F23/E23-1,"") -> 0.11939789 | G24: =IFERROR(G23/F23-1,"") -> 0.12073574 | H24: =IFERROR(H23/G23-1,"") -> 0.12294623 | N24: EPS y/y % | P24: 0.147359 | Q24: 0.14764471 | R24: 0.15139332 | S24: 0.15442177 | T24: 0.15981158 | Z24: EPS y/y % | AB24: -0.055158581 | AC24: 0.048400062 | AD24: 0.056988897 | AE24: 0.05573677 | AF24: 0.055160709
B26: P / E (x) — assumed (adjusted EPS) | G26: 20 | H26: 20 | N26: P / E (x) — assumed (adjusted EPS) | S26: 20 | T26: 20 | Z26: P / E (x) — assumed (adjusted EPS) | AE26: 20 | AF26: 20
B27: Price Target ($) | G27: =G26*G23 -> 45.917378 | H27: =H26*H23 -> 51.562747 | N27: Price Target ($) | S27: 54.298709 | T27: 62.976271 | Z27: Price Target ($) | AE27: 34.293084 | AF27: 36.184714
B28: Upside / (Downside) vs current | G28: =IFERROR(G27/$K$2-1,"") -> 0.70064364 | H28: =IFERROR(H27/$K$2-1,"") -> 0.90973137 | N28: Upside / (Downside) vs current | S28: 1.0110633 | T28: 1.3324545 | Z28: Upside / (Downside) vs current | AE28: 0.27011421 | AF28: 0.34017461
B29: IRR (to Jul of FY−1) | G29: =IFERROR((G27/$K$2)^(1/((DATE(2029,7,31)-$K$3)/365.25))-1,"") -> 0.20675661 | H29: =IFERROR((H27/$K$2)^(1/((DATE(2030,7,31)-$K$3)/365.25))-1,"") -> 0.18429822 | N29: IRR (to Jul of FY−1) | S29: 0.28053006 | T29: 0.24786011 | Z29: IRR (to Jul of FY−1) | AE29: 0.088309685 | AF29: 0.07955989
B31: Free Cash Flow | C31: =Model!CO213 -> 1279.704 | D31: =Model!CP213 -> 1312.0802 | E31: =Model!CQ213 -> 1361.4597 | F31: =Model!CR213 -> 1467.0347 | G31: =Model!CS213 -> 1581.1973 | H31: =Model!CT213 -> 1703.7374 | I31: =IFERROR((H31/C31)^(1/5)-1,"n/m") -> 0.058908973 | N31: Free Cash Flow | O31: 1279.704 | P31: 1393.0205 | Q31: 1458.9782 | R31: 1606.9907 | S31: 1773.8066 | T31: 1957.2795 | U31: 0.088701108 | Z31: Free Cash Flow | AA31: 1279.704 | AB31: 1205.6747 | AC31: 1247.3755 | AD31: 1325.2107 | AE31: 1407.2039 | AF31: 1493.0717 | AG31: 0.031321869
B32: FCF % | C32: =IFERROR(C31/C9,"") -> 0.27424918 | D32: =IFERROR(D31/D9,"") -> 0.26849712 | E32: =IFERROR(E31/E9,"") -> 0.26315876 | F32: =IFERROR(F31/F9,"") -> 0.26704295 | G32: =IFERROR(G31/G9,"") -> 0.2712014 | H32: =IFERROR(H31/H9,"") -> 0.27531772 | J32: =IFERROR(AVERAGE(Model!C215,Model!D215,Model!E215,Model!F215,Model!G215,Model!H215,Model!I215,Model!O215,Model!U215,Model!AA215,Model!AG215,Model!AM215,Model!AS215,Model!AY215,Model!BE215,Model!BK215,Model!BQ215,Model!BW215,Model!CC215,Model!CI215,Model!CO215),"") -> 0.18143094 | K32: =IFERROR(MIN(Model!C215,Model!D215,Model!E215,Model!F215,Model!G215,Model!H215,Model!I215,Model!O215,Model!U215,Model!AA215,Model!AG215,Model!AM215,Model!AS215,Model!AY215,Model!BE215,Model!BK215,Model!BQ215,Model!BW215,Model!CC215,Model!CI215,Model!CO215),"") -> 0.068940143 | L32: =IFERROR(MAX(Model!C215,Model!D215,Model!E215,Model!F215,Model!G215,Model!H215,Model!I215,Model!O215,Model!U215,Model!AA215,Model!AG215,Model!AM215,Model!AS215,Model!AY215,Model!BE215,Model!BK215,Model!BQ215,Model!BW215,Model!CC215,Model!CI215,Model!CO215),"") -> 0.27424918 | N32: FCF % | O32: 0.27424918 | P32: 0.27841319 | Q32: 0.26902766 | R32: 0.27252715 | S32: 0.27676169 | T32: 0.28089596 | V32: 0.18143094 | W32: 0.068940143 | X32: 0.27424918 | Z32: FCF % | AA32: 0.27424918 | AB32: 0.25574889 | AC32: 0.25893653 | AD32: 0.26835564 | AE32: 0.27810594 | AF32: 0.28791801 | AH32: 0.18143094 | AI32: 0.068940143 | AJ32: 0.27424918
B33: FCF / share ($) | C33: =IFERROR(C31/C21,"") -> 1.3373994 | D33: =IFERROR(D31/D21,"") -> 1.4560671 | E33: =IFERROR(E31/E21,"") -> 1.5959932 | F33: =IFERROR(F31/F21,"") -> 1.7882689 | G33: =IFERROR(G31/G21,"") -> 2.0076305 | H33: =IFERROR(H31/H21,"") -> 2.2579802 | N33: FCF / share ($) | O33: 1.3373994 | P33: 1.5723351 | Q33: 1.7783824 | R33: 2.0489961 | S33: 2.3692743 | T33: 2.7519572 | Z33: FCF / share ($) | AA33: 1.3373994 | AB33: 1.2976716 | AC33: 1.3469045 | AD33: 1.4287358 | AE33: 1.5146232 | AF33: 1.6042253
B34: FCF Yield (on PT) | E34: =IFERROR(E33/E$27,"") | F34: =IFERROR(F33/F$27,"") | G34: =IFERROR(G33/G$27,"") -> 0.043722674 | H34: =IFERROR(H33/H$27,"") -> 0.043790922 | N34: FCF Yield (on PT) | Q34: =IFERROR(Q33/Q$27,"") | R34: =IFERROR(R33/R$27,"") | S34: 0.043634081 | T34: 0.043698319 | Z34: FCF Yield (on PT) | AC34: =IFERROR(AC33/AC$27,"") | AD34: =IFERROR(AD33/AD$27,"") | AE34: 0.044167017 | AF34: 0.044334335
B35: Adjusted EBITDA | C35: =Model!CO58 -> 1882.427 | D35: =Model!CP58 -> 1954.7029 | E35: =Model!CQ58 -> 2095.2795 | F35: =Model!CR58 -> 2252.3875 | G35: =Model!CS58 -> 2419.5925 | H35: =Model!CT58 -> 2599.0689 | I35: =IFERROR((H35/C35)^(1/5)-1,"n/m") -> 0.066645071 | N35: Adjusted EBITDA | O35: 1882.427 | P35: 2076.4229 | Q35: 2277.7244 | R35: 2506.0661 | S35: 2755.9336 | T35: 3031.0745 | U35: 0.099956967 | Z35: Adjusted EBITDA | AA35: 1882.427 | AB35: 1791.4307 | AC35: 1854.6613 | AD35: 1925.9225 | AE35: 1998.6828 | AF35: 2074.3012 | AG35: 0.019602137
B36: Adjusted EBITDA margin % | C36: =IFERROR(C35/C9,"") -> 0.40341678 | D36: =IFERROR(D35/D9,"") -> 0.4 | E36: =IFERROR(E35/E9,"") -> 0.405 | F36: =IFERROR(F35/F9,"") -> 0.41 | G36: =IFERROR(G35/G9,"") -> 0.415 | H36: =IFERROR(H35/H9,"") -> 0.42 | J36: =IFERROR(AVERAGE(Model!C170,Model!D170,Model!E170,Model!F170,Model!G170,Model!H170,Model!I170,Model!O170,Model!U170,Model!AA170,Model!AG170,Model!AM170,Model!AS170,Model!AY170,Model!BE170,Model!BK170,Model!BQ170,Model!BW170,Model!CC170,Model!CI170,Model!CO170),"") -> 0.38511197 | K36: =IFERROR(MIN(Model!C170,Model!D170,Model!E170,Model!F170,Model!G170,Model!H170,Model!I170,Model!O170,Model!U170,Model!AA170,Model!AG170,Model!AM170,Model!AS170,Model!AY170,Model!BE170,Model!BK170,Model!BQ170,Model!BW170,Model!CC170,Model!CI170,Model!CO170),"") -> 0.31039571 | L36: =IFERROR(MAX(Model!C170,Model!D170,Model!E170,Model!F170,Model!G170,Model!H170,Model!I170,Model!O170,Model!U170,Model!AA170,Model!AG170,Model!AM170,Model!AS170,Model!AY170,Model!BE170,Model!BK170,Model!BQ170,Model!BW170,Model!CC170,Model!CI170,Model!CO170),"") -> 0.47081751 | N36: Adjusted EBITDA margin % | O36: 0.40341678 | P36: 0.415 | Q36: 0.42 | R36: 0.425 | S36: 0.43 | T36: 0.435 | V36: 0.38511197 | W36: 0.31039571 | X36: 0.47081751 | Z36: Adjusted EBITDA margin % | AA36: 0.40341678 | AB36: 0.38 | AC36: 0.385 | AD36: 0.39 | AE36: 0.395 | AF36: 0.4 | AH36: 0.38511197 | AI36: 0.31039571 | AJ36: 0.47081751
B38: Net Debt (negative = net cash) | C38: =Model!CO318 -> -4489.802 | D38: =Model!CP318 -> -3909.4057 | E38: =Model!CQ318 -> -4190.559 | F38: =Model!CR318 -> -4504.775 | G38: =Model!CS318 -> -4839.185 | H38: =Model!CT318 -> -5198.1379 | N38: Net Debt (negative = net cash) | O38: -4489.802 | P38: -3114.6343 | Q38: -3348.6126 | R38: -3730.6033 | S38: -4133.9004 | T38: -4546.6118 | Z38: Net Debt (negative = net cash) | AA38: -4489.802 | AB38: -5420.4767 | AC38: -6642.8522 | AD38: -7943.0629 | AE38: -9325.2668 | AF38: -10793.339
B39: Net Debt / Adjusted EBITDA (x) | C39: =IFERROR(C38/C35,"") -> -2.3851135 | D39: =IFERROR(D38/D35,"") -> -2 | E39: =IFERROR(E38/E35,"") -> -2 | F39: =IFERROR(F38/F35,"") -> -2 | G39: =IFERROR(G38/G35,"") -> -2 | H39: =IFERROR(H38/H35,"") -> -2 | N39: Net Debt / Adjusted EBITDA (x) | O39: -2.3851135 | P39: -1.5 | Q39: -1.470157 | R39: -1.4886292 | S39: -1.5 | T39: -1.5 | Z39: Net Debt / Adjusted EBITDA (x) | AA39: -2.3851135 | AB39: -3.0257809 | AC39: -3.5817064 | AD39: -4.1242899 | AE39: -4.6657063 | AF39: -5.2033611
B41: ROIC | C41: =Model!CO319 -> 0.28840943 | D41: =Model!CP319 -> 0.28118434 | E41: =Model!CQ319 -> 0.28760242 | F41: =Model!CR319 -> 0.29475048 | G41: =Model!CS319 -> 0.30168404 | H41: =Model!CT319 -> 0.30857388 | J41: =IFERROR(AVERAGE(Model!C319,Model!D319,Model!E319,Model!F319,Model!G319,Model!H319,Model!I319,Model!O319,Model!U319,Model!AA319,Model!AG319,Model!AM319,Model!AS319,Model!AY319,Model!BE319,Model!BK319,Model!BQ319,Model!BW319,Model!CC319,Model!CI319,Model!CO319),"") -> 0.24810352 | K41: =IFERROR(MIN(Model!C319,Model!D319,Model!E319,Model!F319,Model!G319,Model!H319,Model!I319,Model!O319,Model!U319,Model!AA319,Model!AG319,Model!AM319,Model!AS319,Model!AY319,Model!BE319,Model!BK319,Model!BQ319,Model!BW319,Model!CC319,Model!CI319,Model!CO319),"") -> 0.17040746 | L41: =IFERROR(MAX(Model!C319,Model!D319,Model!E319,Model!F319,Model!G319,Model!H319,Model!I319,Model!O319,Model!U319,Model!AA319,Model!AG319,Model!AM319,Model!AS319,Model!AY319,Model!BE319,Model!BK319,Model!BQ319,Model!BW319,Model!CC319,Model!CI319,Model!CO319),"") -> 0.3461967 | N41: ROIC | O41: 0.28840943 | P41: 0.29948531 | Q41: 0.31229935 | R41: 0.32598847 | S41: 0.33952527 | T41: 0.35306073 | V41: 0.24810352 | W41: 0.17040746 | X41: 0.3461967 | Z41: ROIC | AA41: 0.28840943 | AB41: 0.25671133 | AC41: 0.25496067 | AD41: 0.25411613 | AE41: 0.25329381 | AF41: 0.25264217 | AH41: 0.24810352 | AI41: 0.17040746 | AJ41: 0.3461967
B42: RONTA | C42: =Model!CO331 -> 0.15220073 | D42: =Model!CP331 -> 0.16157412 | E42: =Model!CQ331 -> 0.16297986 | F42: =Model!CR331 -> 0.16464571 | G42: =Model!CS331 -> 0.16628007 | H42: =Model!CT331 -> 0.16792915 | J42: =IFERROR(AVERAGE(Model!C331,Model!D331,Model!E331,Model!F331,Model!G331,Model!H331,Model!I331,Model!O331,Model!U331,Model!AA331,Model!AG331,Model!AM331,Model!AS331,Model!AY331,Model!BE331,Model!BK331,Model!BQ331,Model!BW331,Model!CC331,Model!CI331,Model!CO331),"") -> 0.21732716 | K42: =IFERROR(MIN(Model!C331,Model!D331,Model!E331,Model!F331,Model!G331,Model!H331,Model!I331,Model!O331,Model!U331,Model!AA331,Model!AG331,Model!AM331,Model!AS331,Model!AY331,Model!BE331,Model!BK331,Model!BQ331,Model!BW331,Model!CC331,Model!CI331,Model!CO331),"") -> 0.15220073 | L42: =IFERROR(MAX(Model!C331,Model!D331,Model!E331,Model!F331,Model!G331,Model!H331,Model!I331,Model!O331,Model!U331,Model!AA331,Model!AG331,Model!AM331,Model!AS331,Model!AY331,Model!BE331,Model!BK331,Model!BQ331,Model!BW331,Model!CC331,Model!CI331,Model!CO331),"") -> 0.32455213 | N42: RONTA | O42: 0.15220073 | P42: 0.19021128 | Q42: 0.19578032 | R42: 0.19900428 | S42: 0.20244717 | T42: 0.20646538 | V42: 0.21732716 | W42: 0.15220073 | X42: 0.32455213 | Z42: RONTA | AA42: 0.15220073 | AB42: 0.12481862 | AC42: 0.11287482 | AD42: 0.10342378 | AE42: 0.095502432 | AF42: 0.088811708 | AH42: 0.21732716 | AI42: 0.15220073 | AJ42: 0.32455213
B44: Implied Market Cap (USDm) | H44: =H27*H21 -> 38906.179 | N44: Implied Market Cap (USDm) | T44: 44790.728 | Z44: Implied Market Cap (USDm) | AF44: 33677.548
B45: (+) Net debt (net cash) & NCI | H45: =H38+Model!CT348 -> -5181.5529 | N45: (+) Net debt (net cash) & NCI | T45: -4530.0268 | Z45: (+) Net debt (net cash) & NCI | AF45: -10776.754
B46: Implied Enterprise Value (USDm) | H46: =H44+H45 -> 33724.626 | N46: Implied Enterprise Value (USDm) | T46: 40260.701 | Z46: Implied Enterprise Value (USDm) | AF46: 22900.794
B47: Implied EV / Adjusted EBITDA (x) | H47: =IFERROR(H46/H35,"") -> 12.975657 | N47: Implied EV / Adjusted EBITDA (x) | T47: 13.28265 | Z47: Implied EV / Adjusted EBITDA (x) | AF47: 11.040245
B49: 2031E Price Target — P/E Sensitivity | N49: 2031E Price Target — P/E Sensitivity | Z49: 2031E Price Target — P/E Sensitivity
B50: P/E step (x) | C50: 2 | N50: P/E step (x) | O50: 2 | Z50: P/E step (x) | AA50: 2
B51: P / E (x) | D51: =E51-$C$50 -> 16 | E51: =F51-$C$50 -> 18 | F51: =$H$26 -> 20 | G51: =F51+$C$50 -> 22 | H51: =G51+$C$50 -> 24 | N51: P / E (x) | P51: 16 | Q51: 18 | R51: 20 | S51: 22 | T51: 24 | Z51: P / E (x) | AB51: 16 | AC51: 18 | AD51: 20 | AE51: 22 | AF51: 24
B52: 2031E Price Target ($) | D52: =D51*$H$23 -> 41.250198 | E52: =E51*$H$23 -> 46.406472 | F52: =F51*$H$23 -> 51.562747 | G52: =G51*$H$23 -> 56.719022 | H52: =H51*$H$23 -> 61.875296 | N52: 2031E Price Target ($) | P52: 50.381017 | Q52: 56.678644 | R52: 62.976271 | S52: 69.273898 | T52: 75.571526 | Z52: 2031E Price Target ($) | AB52: 28.947772 | AC52: 32.566243 | AD52: 36.184714 | AE52: 39.803186 | AF52: 43.421657
B53: Upside / (Downside) vs current | D53: =IFERROR(D52/$K$2-1,"") -> 0.52778509 | E53: =IFERROR(E52/$K$2-1,"") -> 0.71875823 | F53: =IFERROR(F52/$K$2-1,"") -> 0.90973137 | G53: =IFERROR(G52/$K$2-1,"") -> 1.1007045 | H53: =IFERROR(H52/$K$2-1,"") -> 1.2916776 | N53: Upside / (Downside) vs current | P53: 0.86596359 | Q53: 1.099209 | R53: 1.3324545 | S53: 1.5656999 | T53: 1.7989454 | Z53: Upside / (Downside) vs current | AB53: 0.072139689 | AC53: 0.20615715 | AD53: 0.34017461 | AE53: 0.47419207 | AF53: 0.60820953
B54: IRR (to Jul-2030) | D54: =IFERROR((D52/$K$2)^(1/((DATE(2030,7,31)-$K$3)/365.25))-1,"") -> 0.11718129 | E54: =IFERROR((E52/$K$2)^(1/((DATE(2030,7,31)-$K$3)/365.25))-1,"") -> 0.1521198 | F54: =IFERROR((F52/$K$2)^(1/((DATE(2030,7,31)-$K$3)/365.25))-1,"") -> 0.18429822 | G54: =IFERROR((G52/$K$2)^(1/((DATE(2030,7,31)-$K$3)/365.25))-1,"") -> 0.2141807 | H54: =IFERROR((H52/$K$2)^(1/((DATE(2030,7,31)-$K$3)/365.25))-1,"") -> 0.24211916 | N54: IRR (to Jul-2030) | P54: 0.17714097 | Q54: 0.21395465 | R54: 0.24786011 | S54: 0.27934639 | T54: 0.30878432 | Z54: IRR (to Jul-2030) | AB54: 0.01837872 | AC54: 0.050227297 | AD54: 0.07955989 | AE54: 0.10679958 | AF54: 0.13226719

Sheet DCF
B2: DCF VALUATION — COPART, INC. (CPRT)
B4: 1. WACC BUILD
B5: Risk-free rate (US 10Y govt) | C5: 0.055 | D5: Assumption (~US 10Y Treasury yield); update to market
B6: Equity risk premium | C6: 0.055 | D6: Damodaran-style US ERP estimate
B7: Levered beta | C7: 1 | D7: Online salvage-auction duopoly (with RB Global / IAA); defensive insurance-driven volumes, net-cash balance sheet
B8: Cost of equity | C8: =C5+C7*C6 -> 0.11
B9: Pre-tax cost of debt | C9: 0.055 | D9: No funded debt since May-2022 (senior notes redeemed); undrawn revolver — notional cost if levered
B10: Tax rate | C10: 0.205 | D10: Model effective tax rate (FY2026 19.3%; FY2025 18.3%)
B11: After-tax cost of debt | C11: =C9*(1-C10) -> 0.043725
B12: Target D/V | C12: 0 | D12: Debt-free capital structure (net cash $4.5bn incl. HTM Treasuries at FY2026)
B13: WACC | C13: =C8*(1-C12)+C11*C12 -> 0.11
B15: Valuation date (live) | C15: =TODAY() -> 46298 | D15: Periods = (31-Jul-FY − today) / 365.25; cash flows assumed at fiscal year-end
B16: 2. UNLEVERED FREE CASH FLOW BUILD (USDm)
D17: 2027E | E17: 2028E | F17: 2029E | G17: 2030E | H17: 2031E | I17: 2032E | J17: 2033E | K17: 2034E | L17: 2035E | M17: 2036E | N17: Terminal
B18: Adjusted EBIT (Model) | D18: =Model!CP63 -> 1710.365 | E18: =Model!CQ63 -> 1836.603 | F18: =Model!CR63 -> 1977.7061 | G18: =Model!CS63 -> 2128.0753 | H18: =Model!CT63 -> 2289.656 | I18: =H18*(1+I$29) -> 2427.0353 | J18: =I18*(1+J$29) -> 2560.5223 | K18: =J18*(1+K$29) -> 2688.5484 | L18: =K18*(1+L$29) -> 2809.5331 | M18: =L18*(1+M$29) -> 2921.9144
B19: (−) Stock-based compensation (economic cost) | D19: =-Model!CP103 -> -39.094057 | E19: =-Model!CQ103 -> -41.388237 | F19: =-Model!CR103 -> -43.949025 | G19: =-Model!CS103 -> -46.642747 | H19: =-Model!CT103 -> -49.506075 | I19: =H19*(1+I$29) -> -52.476439 | J19: =I19*(1+J$29) -> -55.362644 | K19: =J19*(1+K$29) -> -58.130776 | L19: =K19*(1+L$29) -> -60.746661 | M19: =L19*(1+M$29) -> -63.176527
B20: × (1 − tax rate) | D20: =1-$C$10 -> 0.795 | E20: =1-$C$10 -> 0.795 | F20: =1-$C$10 -> 0.795 | G20: =1-$C$10 -> 0.795 | H20: =1-$C$10 -> 0.795 | I20: =1-$C$10 -> 0.795 | J20: =1-$C$10 -> 0.795 | K20: =1-$C$10 -> 0.795 | ... M20: =1-$C$10 -> 0.795
B21: NOPAT = (Adj. EBIT − SBC) × (1 − t) | D21: =(D18+D19)*D20 -> 1328.6604 | E21: =(E18+E19)*E20 -> 1427.1957 | F21: =(F18+F19)*F20 -> 1537.3369 | G21: =(G18+G19)*G20 -> 1654.7389 | H21: =(H18+H19)*H20 -> 1780.9192 | I21: =(I18+I19)*I20 -> 1887.7743 | J21: =(J18+J19)*J20 -> 1991.6019 | K21: =(K18+K19)*K20 -> 2091.182 | ... M21: =(M18+M19)*M20 -> 2272.6966
B22: plus D&A (owned-yard depreciation; minimal acquired-intangible amortization) | D22: =Model!CP102 -> 244.33786 | E22: =Model!CQ102 -> 258.67648 | F22: =Model!CR102 -> 274.6814 | G22: =Model!CS102 -> 291.51717 | H22: =Model!CT102 -> 309.41297 | I22: =H22*(1+I$29) -> 327.97775 | J22: =I22*(1+J$29) -> 346.01652 | K22: =J22*(1+K$29) -> 363.31735 | L22: =K22*(1+L$29) -> 379.66663 | M22: =L22*(1+M$29) -> 394.85329
B23: − Capex (purchases of property & equipment, net of disposal proceeds) | D23: =Model!CP190+0+Model!CP191 -> -464.24193 | E23: =Model!CQ190+0+Model!CQ191 -> -491.48531 | F23: =Model!CR190+0+Model!CR191 -> -521.89467 | G23: =Model!CS190+0+Model!CS191 -> -553.88262 | H23: =Model!CT190+0+Model!CT191 -> -587.88464 | I23: =H23*(1+I$29) -> -623.15772 | J23: =I23*(1+J$29) -> -657.43139 | K23: =J23*(1+K$29) -> -690.30296 | L23: =K23*(1+L$29) -> -721.36659 | M23: =L23*(1+M$29) -> -750.22126
B24: − Δ Working capital (CF statement) | D24: =Model!CP188 -> -1.7786899 | E24: =Model!CQ188 -> -18.228411 | F24: =Model!CR188 -> -20.251013 | G24: =Model!CS188 -> -21.292037 | H24: =Model!CT188 -> -22.605886 | I24: =H24*(1+I$29) -> -23.962239 | J24: =I24*(1+J$29) -> -25.280163 | K24: =J24*(1+K$29) -> -26.544171 | L24: =K24*(1+L$29) -> -27.738658 | M24: =L24*(1+M$29) -> -28.848205
B25: Unlevered FCF | D25: =D21+D22+D23+D24 -> 1106.9776 | E25: =E21+E22+E23+E24 -> 1176.1585 | F25: =F21+F22+F23+F24 -> 1269.8726 | G25: =G21+G22+G23+G24 -> 1371.0814 | H25: =H21+H22+H23+H24 -> 1479.8416 | I25: =I21+I22+I23+I24 -> 1568.6321 | J25: =J21+J22+J23+J24 -> 1654.9069 | K25: =K21+K22+K23+K24 -> 1737.6522 | ... M25: =M21+M22+M23+M24 -> 1888.4804 | N25: =M25*(1+$C$30) -> 1964.0196
B26: Terminal Value (Gordon Growth) | N26: =N25/($C$13-$C$30) -> 28057.423
B29: Fade-period growth (2032E–36E) | I29: 0.06 | J29: =I29+($M29-$I29)/(COLUMNS($I29:$M29)-1) -> 0.055 | K29: =J29+($M29-$I29)/(COLUMNS($I29:$M29)-1) -> 0.05 | L29: =K29+($M29-$I29)/(COLUMNS($I29:$M29)-1) -> 0.045 | M29: 0.04
B30: Terminal growth rate | C30: 0.04
B32: Discount period (years) | D32: =(DATE(2027,7,31)-$C$15)/365.25 -> 0.82409309 | E32: =(DATE(2028,7,31)-$C$15)/365.25 -> 1.8261465 | F32: =(DATE(2029,7,31)-$C$15)/365.25 -> 2.825462 | G32: =(DATE(2030,7,31)-$C$15)/365.25 -> 3.8247775 | H32: =(DATE(2031,7,31)-$C$15)/365.25 -> 4.8240931 | I32: =(DATE(2032,7,31)-$C$15)/365.25 -> 5.8261465 | J32: =(DATE(2033,7,31)-$C$15)/365.25 -> 6.825462 | K32: =(DATE(2034,7,31)-$C$15)/365.25 -> 7.8247775 | L32: =(DATE(2035,7,31)-$C$15)/365.25 -> 8.8240931 | M32: =(DATE(2036,7,31)-$C$15)/365.25 -> 9.8261465 | N32: =M32 -> 9.8261465
B33: Discount factor | D33: =1/(1+$C$13)^D32 -> 0.91759206 | E33: =1/(1+$C$13)^E32 -> 0.82648239 | F33: =1/(1+$C$13)^F32 -> 0.74463191 | G33: =1/(1+$C$13)^G32 -> 0.67088748 | H33: =1/(1+$C$13)^H32 -> 0.60444631 | I33: =1/(1+$C$13)^I32 -> 0.54442955 | J33: =1/(1+$C$13)^J32 -> 0.49051211 | K33: =1/(1+$C$13)^K32 -> 0.44193436 | ... N33: =1/(1+$C$13)^N32 -> 0.35863261
B34: PV of UFCF | D34: =D25*D33 -> 1015.7539 | E34: =E25*E33 -> 972.07429 | F34: =F25*F33 -> 945.58767 | G34: =G25*G33 -> 919.84136 | H34: =H25*H33 -> 894.4848 | I34: =I25*I33 -> 854.00966 | J34: =J25*J33 -> 811.75185 | K34: =K25*K33 -> 767.92822 | ... M34: =M25*M33 -> 677.27065 | N34: =N26*N33 -> 10062.307
D35: SBC is deducted as an economic cost. Copart's D&A is mostly owned-yard depreciation (no acquired-intangible add-back); operating-lease costs sit inside EBITDA (lease liabilities therefore not deducted as debt). Net cash includes HTM Treasury investments.
B37: 2b. IMPLIED ROIC (USDm)
D38: =D17 -> 2027E | E38: =E17 -> 2028E | F38: =F17 -> 2029E | G38: =G17 -> 2030E | H38: =H17 -> 2031E | I38: =I17 -> 2032E | J38: =J17 -> 2033E | K38: =K17 -> 2034E | ... M38: =M17 -> 2036E
B39: NOPAT = (Adj. EBIT − SBC) × (1 − t) | D39: =D21 -> 1328.6604 | E39: =E21 -> 1427.1957 | F39: =F21 -> 1537.3369 | G39: =G21 -> 1654.7389 | H39: =H21 -> 1780.9192 | I39: =I21 -> 1887.7743 | J39: =J21 -> 1991.6019 | K39: =K21 -> 2091.182 | ... M39: =M21 -> 2272.6966
B40: Capex (net of disposal proceeds) | D40: =-D23 -> 464.24193 | E40: =-E23 -> 491.48531 | F40: =-F23 -> 521.89467 | G40: =-G23 -> 553.88262 | H40: =-H23 -> 587.88464 | I40: =-I23 -> 623.15772 | J40: =-J23 -> 657.43139 | K40: =-K23 -> 690.30296 | ... M40: =-M23 -> 750.22126
B41: (−) D&A | D41: =-D22 -> -244.33786 | E41: =-E22 -> -258.67648 | F41: =-F22 -> -274.6814 | G41: =-G22 -> -291.51717 | H41: =-H22 -> -309.41297 | I41: =-I22 -> -327.97775 | J41: =-J22 -> -346.01652 | K41: =-K22 -> -363.31735 | ... M41: =-M22 -> -394.85329
B42: Net investment = Capex − D&A | D42: =D40+D41 -> 219.90407 | E42: =E40+E41 -> 232.80883 | F42: =F40+F41 -> 247.21326 | G42: =G40+G41 -> 262.36545 | H42: =H40+H41 -> 278.47167 | I42: =I40+I41 -> 295.17997 | J42: =J40+J41 -> 311.41487 | K42: =K40+K41 -> 326.98561 | ... M42: =M40+M41 -> 355.36796
B43: Invested capital (YE) | D43: =Model!CP316 -> 4835.7608 | E43: =Model!CQ316 -> 5076.798 | F43: =Model!CR316 -> 5334.2623 | G43: =Model!CS316 -> 5607.9198 | H43: =Model!CT316 -> 5898.9973 | I43: =H43+I42 -> 6194.1773 | J43: =I43+J42 -> 6505.5922 | K43: =J43+K42 -> 6832.5778 | L43: =K43+L42 -> 7174.2778 | M43: =L43+M42 -> 7529.6457
B44: Implied ROIC = NOPAT / IC | D44: =IFERROR(D39/D43,"n/a") -> 0.27475727 | E44: =IFERROR(E39/E43,"n/a") -> 0.28112124 | F44: =IFERROR(F39/F43,"n/a") -> 0.28820047 | G44: =IFERROR(G39/G43,"n/a") -> 0.29507179 | H44: =IFERROR(H39/H43,"n/a") -> 0.30190201 | I44: =IFERROR(I39/I43,"n/a") -> 0.30476595 | J44: =IFERROR(J39/J43,"n/a") -> 0.30613691 | K44: =IFERROR(K39/K43,"n/a") -> 0.30606047 | ... M44: =IFERROR(M39/M43,"n/a") -> 0.30183314
B45: Implied incremental ROIC = Δ NOPAT / prior-yr net investment | D45: n/a | E45: =IFERROR((E39-D39)/D42,"n/a") -> 0.44808329 | F45: =IFERROR((F39-E39)/E42,"n/a") -> 0.4730969 | G45: =IFERROR((G39-F39)/F42,"n/a") -> 0.47490178 | H45: =IFERROR((H39-G39)/G42,"n/a") -> 0.4809332 | I45: =IFERROR((I39-H39)/H42,"n/a") -> 0.38372 | J45: =IFERROR((J39-I39)/I42,"n/a") -> 0.35174333 | K45: =IFERROR((K39-J39)/J42,"n/a") -> 0.31976667 | L45: =IFERROR((L39-K39)/K42,"n/a") -> 0.28779 | M45: =IFERROR((M39-L39)/L42,"n/a") -> 0.25581333
B46: NOPAT links to DCF row 21 (after SBC, consistent with UFCF). 2027–31E IC links to the Model ROIC build. From 2032E, IC = prior IC + (capex − D&A); working-capital investment excluded. Incremental ROIC = (NOPAT t − NOPAT t−1) / net investment t−1; 2027E n/a.
B48: 3. VALUATION SUMMARY
B49: Sum of PV (explicit + fade) | C49: =SUM(D34:M34) -> 8581.7135
B50: PV of Terminal Value | C50: =N34 -> 10062.307
B51: Enterprise Value | C51: =C49+C50 -> 18644.02
B52: Less: net debt (negative = net cash; Model FY2026A YE) | C52: =Model!CO318 -> -4489.802
B53: Less: redeemable NCI & NCI (Model FY2026A) | C53: =Model!CO348 -> 16.585
B54: Equity Value | C54: =C51-C52-C53 -> 23117.237
B55: Diluted shares (m, Model FY2026A) | C55: =Model!CO98 -> 956.86
B56: Implied share price ($) | C56: =C54/C55 -> 24.159477
B57: Current share price ($) | C57: =Model!CO344 -> 27
B58: Implied upside / (downside) | C58: =C56/C57-1 -> -0.10520455
B61: 4. SENSITIVITY: IMPLIED PRICE ($) — WACC × Terminal Growth
B63: WACC (across): | J63: WACC step | K63: 0.005
B64: g (down) / WACC | C64: =D64-$K$63 -> 0.1 | D64: =E64-$K$63 -> 0.105 | E64: =$C$13 -> 0.11 | F64: =E64+$K$63 -> 0.115 | G64: =F64+$K$63 -> 0.12 | J64: g step | K64: 0.005
B65: =B66-$K$64 -> 0.03 | C65: =IFERROR((SUMPRODUCT($D$25:$M$25/(1+C$64)^$D$32:$M$32)+($M$25*(1+$B65)/(C$64-$B65))/(1+C$64)^$M$32-$C$52-$C$53)/$C$55,"") -> 25.442878 | D65: =IFERROR((SUMPRODUCT($D$25:$M$25/(1+D$64)^$D$32:$M$32)+($M$25*(1+$B65)/(D$64-$B65))/(1+D$64)^$M$32-$C$52-$C$53)/$C$55,"") -> 24.009358 | E65: =IFERROR((SUMPRODUCT($D$25:$M$25/(1+E$64)^$D$32:$M$32)+($M$25*(1+$B65)/(E$64-$B65))/(1+E$64)^$M$32-$C$52-$C$53)/$C$55,"") -> 22.756506 | F65: =IFERROR((SUMPRODUCT($D$25:$M$25/(1+F$64)^$D$32:$M$32)+($M$25*(1+$B65)/(F$64-$B65))/(1+F$64)^$M$32-$C$52-$C$53)/$C$55,"") -> 21.652391 | G65: =IFERROR((SUMPRODUCT($D$25:$M$25/(1+G$64)^$D$32:$M$32)+($M$25*(1+$B65)/(G$64-$B65))/(1+G$64)^$M$32-$C$52-$C$53)/$C$55,"") -> 20.672179
B66: =B67-$K$64 -> 0.035 | C66: =IFERROR((SUMPRODUCT($D$25:$M$25/(1+C$64)^$D$32:$M$32)+($M$25*(1+$B66)/(C$64-$B66))/(1+C$64)^$M$32-$C$52-$C$53)/$C$55,"") -> 26.378036 | D66: =IFERROR((SUMPRODUCT($D$25:$M$25/(1+D$64)^$D$32:$M$32)+($M$25*(1+$B66)/(D$64-$B66))/(1+D$64)^$M$32-$C$52-$C$53)/$C$55,"") -> 24.788027 | E66: =IFERROR((SUMPRODUCT($D$25:$M$25/(1+E$64)^$D$32:$M$32)+($M$25*(1+$B66)/(E$64-$B66))/(1+E$64)^$M$32-$C$52-$C$53)/$C$55,"") -> 23.411226 | F66: =IFERROR((SUMPRODUCT($D$25:$M$25/(1+F$64)^$D$32:$M$32)+($M$25*(1+$B66)/(F$64-$B66))/(1+F$64)^$M$32-$C$52-$C$53)/$C$55,"") -> 22.207617 | G66: =IFERROR((SUMPRODUCT($D$25:$M$25/(1+G$64)^$D$32:$M$32)+($M$25*(1+$B66)/(G$64-$B66))/(1+G$64)^$M$32-$C$52-$C$53)/$C$55,"") -> 21.146604
B67: =$C$30 -> 0.04 | C67: =IFERROR((SUMPRODUCT($D$25:$M$25/(1+C$64)^$D$32:$M$32)+($M$25*(1+$B67)/(C$64-$B67))/(1+C$64)^$M$32-$C$52-$C$53)/$C$55,"") -> 27.469053 | D67: =IFERROR((SUMPRODUCT($D$25:$M$25/(1+D$64)^$D$32:$M$32)+($M$25*(1+$B67)/(D$64-$B67))/(1+D$64)^$M$32-$C$52-$C$53)/$C$55,"") -> 25.686492 | E67: =IFERROR((SUMPRODUCT($D$25:$M$25/(1+E$64)^$D$32:$M$32)+($M$25*(1+$B67)/(E$64-$B67))/(1+E$64)^$M$32-$C$52-$C$53)/$C$55,"") -> 24.159477 | F67: =IFERROR((SUMPRODUCT($D$25:$M$25/(1+F$64)^$D$32:$M$32)+($M$25*(1+$B67)/(F$64-$B67))/(1+F$64)^$M$32-$C$52-$C$53)/$C$55,"") -> 22.836874 | G67: =IFERROR((SUMPRODUCT($D$25:$M$25/(1+G$64)^$D$32:$M$32)+($M$25*(1+$B67)/(G$64-$B67))/(1+G$64)^$M$32-$C$52-$C$53)/$C$55,"") -> 21.680331
B68: =B67+$K$64 -> 0.045 | C68: =IFERROR((SUMPRODUCT($D$25:$M$25/(1+C$64)^$D$32:$M$32)+($M$25*(1+$B68)/(C$64-$B68))/(1+C$64)^$M$32-$C$52-$C$53)/$C$55,"") -> 28.758437 | D68: =IFERROR((SUMPRODUCT($D$25:$M$25/(1+D$64)^$D$32:$M$32)+($M$25*(1+$B68)/(D$64-$B68))/(1+D$64)^$M$32-$C$52-$C$53)/$C$55,"") -> 26.7347 | E68: =IFERROR((SUMPRODUCT($D$25:$M$25/(1+E$64)^$D$32:$M$32)+($M$25*(1+$B68)/(E$64-$B68))/(1+E$64)^$M$32-$C$52-$C$53)/$C$55,"") -> 25.022844 | F68: =IFERROR((SUMPRODUCT($D$25:$M$25/(1+F$64)^$D$32:$M$32)+($M$25*(1+$B68)/(F$64-$B68))/(1+F$64)^$M$32-$C$52-$C$53)/$C$55,"") -> 23.556025 | G68: =IFERROR((SUMPRODUCT($D$25:$M$25/(1+G$64)^$D$32:$M$32)+($M$25*(1+$B68)/(G$64-$B68))/(1+G$64)^$M$32-$C$52-$C$53)/$C$55,"") -> 22.285223
B69: =B68+$K$64 -> 0.05 | C69: =IFERROR((SUMPRODUCT($D$25:$M$25/(1+C$64)^$D$32:$M$32)+($M$25*(1+$B69)/(C$64-$B69))/(1+C$64)^$M$32-$C$52-$C$53)/$C$55,"") -> 30.305698 | D69: =IFERROR((SUMPRODUCT($D$25:$M$25/(1+D$64)^$D$32:$M$32)+($M$25*(1+$B69)/(D$64-$B69))/(1+D$64)^$M$32-$C$52-$C$53)/$C$55,"") -> 27.973492 | E69: =IFERROR((SUMPRODUCT($D$25:$M$25/(1+E$64)^$D$32:$M$32)+($M$25*(1+$B69)/(E$64-$B69))/(1+E$64)^$M$32-$C$52-$C$53)/$C$55,"") -> 26.030106 | F69: =IFERROR((SUMPRODUCT($D$25:$M$25/(1+F$64)^$D$32:$M$32)+($M$25*(1+$B69)/(F$64-$B69))/(1+F$64)^$M$32-$C$52-$C$53)/$C$55,"") -> 24.385814 | G69: =IFERROR((SUMPRODUCT($D$25:$M$25/(1+G$64)^$D$32:$M$32)+($M$25*(1+$B69)/(G$64-$B69))/(1+G$64)^$M$32-$C$52-$C$53)/$C$55,"") -> 22.976527
B72: 5. REVERSE DCF
B73: To solve for the market-implied path: Data ▸ What-If Analysis ▸ Goal Seek — set C56 to the current price (C57) by changing C30 (terminal growth) or the Model scenario levers (unit growth, service revenue per unit, adjusted EBITDA margin).
B75: 6. MAUBOUSSIN EV / NOPAT — TWO-STAGE FRAMEWORK
B76: EV/NOPAT = 1/r + [g × (1 − r/ROIIC) / (r × (r − g))] × [1 − ((1+g)/(1+r))^N]
B77: Formula source: Mauboussin & Rappaport, "Expectations Investing" (2021); Counterpoint Global, "What Does a Price-Earnings Multiple Mean?" (2020).
B79: Input | C79: Value | D79: Rationale (Copart characteristics)
B80: r (Cost of capital / WACC) | C80: =$C$13 -> 0.11 | D80: Linked from Section 1 WACC build
B81: g (NOPAT growth, Stage 1) | C81: 0.07 | D81: Model adjusted EBIT CAGR FY2026–31E: low/mid-single-digit units + ~3% fee pricing, modest margin expansion
B82: ROIIC (Return on incremental invested capital) | C82: 0.35 | D82: Land-heavy but high-return yard network: reported ROIC ~30% (equity-funded, net cash); incremental yard capacity earns well above WACC
B83: N (Years of value creation / CAP) | C83: 12 | D83: Two-player US salvage market (Copart / IAA) with global buyer network (~1m members, 185+ countries) — long competitive advantage period
B85: Calculation | C85: Value
B86: Steady-state component: 1 / r | C86: =1/C80 -> 9.0909091
B87: Value-creation factor: 1 − r / ROIIC | C87: =1-C80/C82 -> 0.68571429
B88: Growth multiplier: g × (1 − r/ROIIC) / (r × (r − g)) | C88: =C81*C87/(C80*(C80-C81)) -> 10.909091
B89: Time decay: 1 − ((1+g)/(1+r))^N | C89: =1-((1+C81)/(1+C80))^C83 -> 0.3562317
B90: PVGO component (growth value) | C90: =C88*C89 -> 3.886164
B91: Mauboussin EV / NOPAT (steady-state + PVGO) | C91: =C86+C90 -> 12.977073
B93: VALUATION — Applied to 2029E NOPAT | C93: USDm
B94: 2029E Adjusted EBIT (Model) | C94: =Model!CR63 -> 1977.7061
B95: (−) 2029E stock-based compensation | C95: =-Model!CR103 -> -43.949025
B96: Tax rate (from WACC build) | C96: =$C$10 -> 0.205
B97: 2029E NOPAT = (EBIT − SBC) × (1 − t) | C97: =(C94+C95)*(1-C96) -> 1537.3369
B98: × Mauboussin EV/NOPAT multiple | C98: =C91 -> 12.977073
B99: Implied Enterprise Value (2029E basis) | C99: =C97*C98 -> 19950.133
B100: Less: FY2028E net debt (net cash) + NCI (Model) | C100: =Model!CQ318+Model!CQ348 -> -4173.974
B101: Implied Equity Value | C101: =C99-C100 -> 24124.107
B102: Diluted shares 2029E (m, Model) | C102: =Model!CR98 -> 820.36581
B103: Implied share price 2029 ($) | C103: =C101/C102 -> 29.406524
B105: Current share price ($) | C105: =C57 -> 27
B106: Implied upside / (downside) | C106: =C103/C105-1 -> 0.089130525
B108: MARKET-IMPLIED EV/NOPAT TODAY | C108: USDm
B109: Current market cap (spot × diluted shares) | C109: =C57*C55 -> 25835.22
B110: Plus: FY2026A net debt (net cash) & NCI | C110: =C52+C53 -> -4473.217
B111: Implied Enterprise Value (today) | C111: =C109+C110 -> 21362.003
B112: CPRT's market-implied EV/NOPAT (on 2029E NOPAT) | C112: =C111/C97 -> 13.89546
B114: Multiple gap (Mauboussin − Market) | C114: =C91-C112 -> -0.91838676
B115: Implied re-rating headroom | C115: =C91/C112-1 -> -0.066092578

Sheet Charts
B2: Copart — Historical Operating Performance (FY2006–FY2026)
B3: All historicals · USDm · fiscal years ending 31-July · Linked to Model. Copart does not disclose acquired revenue, so growth is shown in total (M&A series n/d). Adjusted EBITDA = model bridge on Copart's own non-GAAP items.
C7: 2006 | D7: 2007 | E7: 2008 | F7: 2009 | G7: 2010 | H7: 2011 | I7: 2012 | J7: 2013 | K7: 2014 | L7: 2015 | M7: 2016 | N7: 2017 | O7: 2018 | P7: 2019 | Q7: 2020 | R7: 2021 | S7: 2022 | T7: 2023 | U7: 2024 | V7: 2025 | W7: 2026
B8: Revenue growth % (total) | C8: =IFERROR(Model!C160+0,0) -> 0 | D8: =IFERROR(Model!D160+0,0) -> 0.060746806 | E8: =IFERROR(Model!E160+0,0) -> 0.39981451 | F8: =IFERROR(Model!F160+0,0) -> -0.0532154 | G8: =IFERROR(Model!G160+0,0) -> 0.040099208 | H8: =IFERROR(Model!H160+0,0) -> 0.12856734 | I8: =IFERROR(Model!I160+0,0) -> 0.059553154 | J8: =IFERROR(Model!O160+0,0) -> 0.13221834 | K8: =IFERROR(Model!U160+0,0) -> 0.11191186 | L8: =IFERROR(Model!AA160+0,0) -> -0.014963614 | M8: =IFERROR(Model!AG160+0,0) -> 0.10677274 | N8: =IFERROR(Model!AM160+0,0) -> 0.14153663 | O8: =IFERROR(Model!AS160+0,0) -> 0.2470433 | P8: =IFERROR(Model!AY160+0,0) -> 0.13084269 | Q8: =IFERROR(Model!BE160+0,0) -> 0.080131952 | R8: =IFERROR(Model!BK160+0,0) -> 0.22077065 | S8: =IFERROR(Model!BQ160+0,0) -> 0.3002439 | T8: =IFERROR(Model!BW160+0,0) -> 0.10528572 | U8: =IFERROR(Model!CC160+0,0) -> 0.094922675 | V8: =IFERROR(Model!CI160+0,0) -> 0.096802486 | W8: =IFERROR(Model!CO160+0,0) -> 0.0041427101
B9: M&A % (acquired revenue not disclosed) | C9: 0 | D9: 0 | E9: 0 | F9: 0 | G9: 0 | H9: 0 | I9: 0 | J9: 0 | K9: 0 | L9: 0 | M9: 0 | N9: 0 | O9: 0 | P9: 0 | Q9: 0 | R9: 0 | S9: 0 | T9: 0 | U9: 0 | V9: 0 | W9: 0
C11: =C7 -> 2006 | D11: =D7 -> 2007 | E11: =E7 -> 2008 | F11: =F7 -> 2009 | G11: =G7 -> 2010 | H11: =H7 -> 2011 | I11: =I7 -> 2012 | J11: =J7 -> 2013 | ... V11: =V7 -> 2025
B12: Adjusted EBITDA | C12: =IFERROR(Model!C58+0,0) -> 197.868 | D12: =IFERROR(Model!D58+0,0) -> 240.866 | E12: =IFERROR(Model!E58+0,0) -> 284.902 | F12: =IFERROR(Model!F58+0,0) -> 267.668 | G12: =IFERROR(Model!G58+0,0) -> 282.748 | H12: =IFERROR(Model!H58+0,0) -> 313.156 | I12: =IFERROR(Model!I58+0,0) -> 337.207 | J12: =IFERROR(Model!O58+0,0) -> 337.47577 | K12: =IFERROR(Model!U58+0,0) -> 361.142 | L12: =IFERROR(Model!AA58+0,0) -> 396.80729 | M12: =IFERROR(Model!AG58+0,0) -> 458.83571 | N12: =IFERROR(Model!AM58+0,0) -> 544.75413 | O12: =IFERROR(Model!AS58+0,0) -> 675.69582 | P12: =IFERROR(Model!AY58+0,0) -> 807.98967 | Q12: =IFERROR(Model!BE58+0,0) -> 923.008 | R12: =IFERROR(Model!BK58+0,0) -> 1267.6813 | S12: =IFERROR(Model!BQ58+0,0) -> 1519.1753 | T12: =IFERROR(Model!BW58+0,0) -> 1647.878 | U12: =IFERROR(Model!CC58+0,0) -> 1758.689 | V12: =IFERROR(Model!CI58+0,0) -> 1932.521 | W12: =IFERROR(Model!CO58+0,0) -> 1882.427
B13: Operating Income (GAAP) | C13: =IFERROR(Model!C81+0,0) -> 171.562 | D13: =IFERROR(Model!D81+0,0) -> 203.145 | E13: =IFERROR(Model!E81+0,0) -> 237.917 | F13: =IFERROR(Model!F81+0,0) -> 225.325 | G13: =IFERROR(Model!G81+0,0) -> 239.07 | H13: =IFERROR(Model!H81+0,0) -> 265.29 | I13: =IFERROR(Model!I81+0,0) -> 286.353 | J13: =IFERROR(Model!O81+0,0) -> 282.992 | K13: =IFERROR(Model!U81+0,0) -> 274.934 | L13: =IFERROR(Model!AA81+0,0) -> 344.401 | M13: =IFERROR(Model!AG81+0,0) -> 406.47 | N13: =IFERROR(Model!AM81+0,0) -> 461.299 | O13: =IFERROR(Model!AS81+0,0) -> 584.345 | P13: =IFERROR(Model!AY81+0,0) -> 716.475 | Q13: =IFERROR(Model!BE81+0,0) -> 816.099 | R13: =IFERROR(Model!BK81+0,0) -> 1136.426 | S13: =IFERROR(Model!BQ81+0,0) -> 1374.997 | T13: =IFERROR(Model!BW81+0,0) -> 1486.569 | U13: =IFERROR(Model!CC81+0,0) -> 1572.023 | V13: =IFERROR(Model!CI81+0,0) -> 1696.714 | W13: =IFERROR(Model!CO81+0,0) -> 1652.59
B14: Adj. EBITDA Margin % | C14: =IFERROR(Model!C170+0,0) -> 0.37434517 | D14: =IFERROR(Model!D170+0,0) -> 0.4295962 | E14: =IFERROR(Model!E170+0,0) -> 0.36300277 | F14: =IFERROR(Model!F170+0,0) -> 0.36021327 | G14: =IFERROR(Model!G170+0,0) -> 0.36583734 | H14: =IFERROR(Model!H170+0,0) -> 0.35902257 | I14: =IFERROR(Model!I170+0,0) -> 0.36486722 | J14: =IFERROR(Model!O170+0,0) -> 0.32251557 | K14: =IFERROR(Model!U170+0,0) -> 0.31039571 | L14: =IFERROR(Model!AA170+0,0) -> 0.34623031 | M14: =IFERROR(Model!AG170+0,0) -> 0.36172973 | N14: =IFERROR(Model!AM170+0,0) -> 0.37621635 | O14: =IFERROR(Model!AS170+0,0) -> 0.37420263 | P14: =IFERROR(Model!AY170+0,0) -> 0.39569377 | Q14: =IFERROR(Model!BE170+0,0) -> 0.41848708 | R14: =IFERROR(Model!BK170+0,0) -> 0.47081751 | S14: =IFERROR(Model!BQ170+0,0) -> 0.43393591 | T14: =IFERROR(Model!BW170+0,0) -> 0.42586131 | U14: =IFERROR(Model!CC170+0,0) -> 0.41509617 | V14: =IFERROR(Model!CI170+0,0) -> 0.41586797 | W14: =IFERROR(Model!CO170+0,0) -> 0.40341678
B15: GAAP Op. Margin % | C15: =IFERROR(Model!C171+0,0) -> 0.32457702 | D15: =IFERROR(Model!D171+0,0) -> 0.36231897 | E15: =IFERROR(Model!E171+0,0) -> 0.30313768 | F15: =IFERROR(Model!F171+0,0) -> 0.30323033 | G15: =IFERROR(Model!G171+0,0) -> 0.30932397 | H15: =IFERROR(Model!H171+0,0) -> 0.30414585 | I15: =IFERROR(Model!I171+0,0) -> 0.3098418 | J15: =IFERROR(Model!O171+0,0) -> 0.27044704 | K15: =IFERROR(Model!U171+0,0) -> 0.23630133 | L15: =IFERROR(Model!AA171+0,0) -> 0.30050372 | M15: =IFERROR(Model!AG171+0,0) -> 0.32044647 | N15: =IFERROR(Model!AM171+0,0) -> 0.31858084 | O15: =IFERROR(Model!AS171+0,0) -> 0.32361224 | P15: =IFERROR(Model!AY171+0,0) -> 0.35087663 | Q15: =IFERROR(Model!BE171+0,0) -> 0.37001509 | R15: =IFERROR(Model!BK171+0,0) -> 0.42206921 | S15: =IFERROR(Model!BQ171+0,0) -> 0.39275294 | T15: =IFERROR(Model!BW171+0,0) -> 0.3841742 | U15: =IFERROR(Model!CC171+0,0) -> 0.37103816 | V15: =IFERROR(Model!CI171+0,0) -> 0.36512359 | W15: =IFERROR(Model!CO171+0,0) -> 0.35416116
C17: =C7 -> 2006 | D17: =D7 -> 2007 | E17: =E7 -> 2008 | F17: =F7 -> 2009 | G17: =G7 -> 2010 | H17: =H7 -> 2011 | I17: =I7 -> 2012 | J17: =J7 -> 2013 | ... V17: =V7 -> 2025
B18: ROIC | C18: =IFERROR(Model!C319+0,0) -> 0.20264226 | D18: =IFERROR(Model!D319+0,0) -> 0.19054348 | E18: =IFERROR(Model!E319+0,0) -> 0.20023203 | F18: =IFERROR(Model!F319+0,0) -> 0.18276614 | G18: =IFERROR(Model!G319+0,0) -> 0.18499911 | H18: =IFERROR(Model!H319+0,0) -> 0.19679264 | I18: =IFERROR(Model!I319+0,0) -> 0.21882759 | J18: =IFERROR(Model!O319+0,0) -> 0.17040746 | K18: =IFERROR(Model!U319+0,0) -> 0.17723883 | L18: =IFERROR(Model!AA319+0,0) -> 0.20105178 | M18: =IFERROR(Model!AG319+0,0) -> 0.22253349 | N18: =IFERROR(Model!AM319+0,0) -> 0.28717763 | O18: =IFERROR(Model!AS319+0,0) -> 0.26001451 | P18: =IFERROR(Model!AY319+0,0) -> 0.30448223 | Q18: =IFERROR(Model!BE319+0,0) -> 0.29802132 | R18: =IFERROR(Model!BK319+0,0) -> 0.33225322 | S18: =IFERROR(Model!BQ319+0,0) -> 0.3461967 | T18: =IFERROR(Model!BW319+0,0) -> 0.32612113 | U18: =IFERROR(Model!CC319+0,0) -> 0.30210414 | V18: =IFERROR(Model!CI319+0,0) -> 0.31735889 | W18: =IFERROR(Model!CO319+0,0) -> 0.28840943
B19: RONTA | C19: =IFERROR(Model!C331+0,0) -> 0.15407865 | D19: =IFERROR(Model!D331+0,0) -> 0.18006252 | E19: =IFERROR(Model!E331+0,0) -> 0.24197407 | F19: =IFERROR(Model!F331+0,0) -> 0.17942229 | G19: =IFERROR(Model!G331+0,0) -> 0.16257493 | H19: =IFERROR(Model!H331+0,0) -> 0.2228233 | I19: =IFERROR(Model!I331+0,0) -> 0.22579544 | J19: =IFERROR(Model!O331+0,0) -> 0.20584694 | K19: =IFERROR(Model!U331+0,0) -> 0.19702164 | L19: =IFERROR(Model!AA331+0,0) -> 0.17177192 | M19: =IFERROR(Model!AG331+0,0) -> 0.23841455 | N19: =IFERROR(Model!AM331+0,0) -> 0.32455213 | O19: =IFERROR(Model!AS331+0,0) -> 0.27230318 | P19: =IFERROR(Model!AY331+0,0) -> 0.32312734 | Q19: =IFERROR(Model!BE331+0,0) -> 0.26510893 | R19: =IFERROR(Model!BK331+0,0) -> 0.25575902 | S19: =IFERROR(Model!BQ331+0,0) -> 0.25453488 | T19: =IFERROR(Model!BW331+0,0) -> 0.20477141 | U19: =IFERROR(Model!CC331+0,0) -> 0.1728702 | V19: =IFERROR(Model!CI331+0,0) -> 0.15885619 | W19: =IFERROR(Model!CO331+0,0) -> 0.15220073
B20: Adj. EBITDA margin % | C20: =IFERROR(Model!C170+0,0) -> 0.37434517 | D20: =IFERROR(Model!D170+0,0) -> 0.4295962 | E20: =IFERROR(Model!E170+0,0) -> 0.36300277 | F20: =IFERROR(Model!F170+0,0) -> 0.36021327 | G20: =IFERROR(Model!G170+0,0) -> 0.36583734 | H20: =IFERROR(Model!H170+0,0) -> 0.35902257 | I20: =IFERROR(Model!I170+0,0) -> 0.36486722 | J20: =IFERROR(Model!O170+0,0) -> 0.32251557 | K20: =IFERROR(Model!U170+0,0) -> 0.31039571 | L20: =IFERROR(Model!AA170+0,0) -> 0.34623031 | M20: =IFERROR(Model!AG170+0,0) -> 0.36172973 | N20: =IFERROR(Model!AM170+0,0) -> 0.37621635 | O20: =IFERROR(Model!AS170+0,0) -> 0.37420263 | P20: =IFERROR(Model!AY170+0,0) -> 0.39569377 | Q20: =IFERROR(Model!BE170+0,0) -> 0.41848708 | R20: =IFERROR(Model!BK170+0,0) -> 0.47081751 | S20: =IFERROR(Model!BQ170+0,0) -> 0.43393591 | T20: =IFERROR(Model!BW170+0,0) -> 0.42586131 | U20: =IFERROR(Model!CC170+0,0) -> 0.41509617 | V20: =IFERROR(Model!CI170+0,0) -> 0.41586797 | W20: =IFERROR(Model!CO170+0,0) -> 0.40341678
B21: Gross margin % | C21: =IFERROR(Model!C66+0,0) -> 0.43617225 | D21: =IFERROR(Model!D66+0,0) -> 0.47581865 | E21: =IFERROR(Model!E66+0,0) -> 0.41060052 | F21: =IFERROR(Model!F66+0,0) -> 0.4202228 | G21: =IFERROR(Model!G66+0,0) -> 0.45025677 | H21: =IFERROR(Model!H66+0,0) -> 0.42751128 | I21: =IFERROR(Model!I66+0,0) -> 0.44321574 | J21: =IFERROR(Model!O66+0,0) -> 0.40226264 | K21: =IFERROR(Model!U66+0,0) -> 0.40273092 | L21: =IFERROR(Model!AA66+0,0) -> 0.42176499 | M21: =IFERROR(Model!AG66+0,0) -> 0.4293322 | N21: =IFERROR(Model!AM66+0,0) -> 0.43648915 | O21: =IFERROR(Model!AS66+0,0) -> 0.42220087 | P21: =IFERROR(Model!AY66+0,0) -> 0.43994168 | Q21: =IFERROR(Model!BE66+0,0) -> 0.45693225 | R21: =IFERROR(Model!BK66+0,0) -> 0.4988247 | S21: =IFERROR(Model!BQ66+0,0) -> 0.45879956 | T21: =IFERROR(Model!BW66+0,0) -> 0.44889079 | U21: =IFERROR(Model!CC66+0,0) -> 0.45016089 | V21: =IFERROR(Model!CI66+0,0) -> 0.45183171 | W21: =IFERROR(Model!CO66+0,0) -> 0.4465848
