Workbook

Sheet Model
CF1: SCENARIO SWITCH ▼ (Bull / Base / Bear) — drives all scenario-linked forecast drivers
B2: CoStar Group, Inc. (NASDAQ: CSGP) — 3-Statement Financial Model | CF2: Base
B3: US GAAP as reported · USD millions (per-share data in USD; shares in millions, split-adjusted for the 10-for-1 split of June 2021) · Source: CoStar Group Forms 10-K / 10-Q (XBRL statements; 2006–2010 from 10-K HTML) and Form 8-K earnings releases (Ex. 99.1), deal 8-Ks (Zonda, May/Aug-2026), Form 4 (share price), SEC EDGAR CIK 0001057352 (investor-relations releases are the same documents as filed on EDGAR)
B4: Basis notes: calendar fiscal year. Q4 = FY (10-K) − 9M (Q3 10-Q); quarterly cash flows = YTD − prior YTD. Revenue lines: current basis (CoStar · LoopNet · Other CRE · Residential) recast from Q1/23 in the Q4-25 release; legacy product lines 2015–Q3/25 and North America / International segments 2007–Q3/25 kept as memo. Adjusted EBITDA / Adjusted Net Income per company definitions in force (EBITDA only to 2008; non-GAAP net income from FY2009). Acquisitions: LoopNet Apr-2012, Apartments.com Apr-2014, ForRent Feb-2018, STR Oct-2019, Ten-X Jun-2020, Homesnap Dec-2020, Homes.com May-2021, OnTheMarket Dec-2023, Matterport Feb-2025, Domain Aug-2025; Zonda closed 21-Aug-2026 — excluded from company FY26 guidance, modelled separately from Q3/26E.
CH5: Forecast | CI5: Historical | CJ5: Historical | CK5: Historical
B6: (USDm) | C6: 2006 | D6: 2007 | E6: 2008 | F6: 2009 | G6: 2010 | H6: 2011 | I6: 2012 | J6: Q1/13 | K6: Q2/13 | L6: Q3/13 | M6: Q4/13 | N6: 2013 | O6: Q1/14 | P6: Q2/14 | Q6: Q3/14 | R6: Q4/14 | S6: 2014 | T6: Q1/15 | U6: Q2/15 | V6: Q3/15 | W6: Q4/15 | X6: 2015 | Y6: Q1/16 | Z6: Q2/16 | AA6: Q3/16 | AB6: Q4/16 | AC6: 2016 | AD6: Q1/17 | AE6: Q2/17 | AF6: Q3/17 | AG6: Q4/17 | AH6: 2017 | AI6: Q1/18 | AJ6: Q2/18 | AK6: Q3/18 | AL6: Q4/18 | AM6: 2018 | AN6: Q1/19 | AO6: Q2/19 | AP6: Q3/19 | AQ6: Q4/19 | AR6: 2019 | AS6: Q1/20 | AT6: Q2/20 | AU6: Q3/20 | AV6: Q4/20 | AW6: 2020 | AX6: Q1/21 | AY6: Q2/21 | AZ6: Q3/21 | BA6: Q4/21 | BB6: 2021 | BC6: Q1/22 | BD6: Q2/22 | BE6: Q3/22 | BF6: Q4/22 | BG6: 2022 | BH6: Q1/23 | BI6: Q2/23 | BJ6: Q3/23 | BK6: Q4/23 | BL6: 2023 | BM6: Q1/24 | BN6: Q2/24 | BO6: Q3/24 | BP6: Q4/24 | BQ6: 2024 | BR6: Q1/25 | BS6: Q2/25 | BT6: Q3/25 | BU6: Q4/25 | BV6: 2025 | BW6: Q1/26 | BX6: Q2/26 | BY6: Q3/26E | BZ6: Q4/26E | CA6: 2026E | CB6: 2027E | CC6: 2028E | CD6: 2029E | CE6: 2030E | CF6: Modelling Notes | CH6: 5Y CAGR / avg | CI6: 5Y CAGR / avg | CJ6: 10Y CAGR / avg | CK6: 19Y CAGR / avg
CH7: 25-'30 | CI7: 20-'25 | CJ7: 15-'25 | CK7: 06-'25
B8: SEGMENT REVENUE BUILD — COMMERCIAL REAL ESTATE · RESIDENTIAL REAL ESTATE · ZONDA → SEGMENT ADJUSTED EBITDA | CF8: SEGMENT BUILD — modelling logic (product-line revenues → segment Adjusted EBITDA margin → consolidated Adjusted EBITDA → GAAP P&L)
CN9: SCENARIO INPUT TABLE — driver assumptions per Bull / Base / Bear | CO9: Bull | CP9: Base | CQ9: Bear | CR9: Bull / Bear = Base + Δ (Δ inputs on each lever header). Outlook block = high / mid / low end of the FY26 ranges.
B10: Commercial Real Estate (CoStar · LoopNet · Other CRE) — current reporting basis (Q4-25 recast, history from Q1/23) | CF10: COMMERCIAL REAL ESTATE — modelling logic
B11: CoStar (subscription data & analytics, incl. Information Services) | T11: =IF(ISNUMBER(T37),N(T37)+N(T38),"") -> 105.347 | U11: =IF(ISNUMBER(U37),N(U37)+N(U38),"") -> 107.523 | V11: =IF(ISNUMBER(V37),N(V37)+N(V38),"") -> 110.476 | W11: =IF(ISNUMBER(W37),N(W37)+N(W38),"") -> 112.884 | X11: =IF(ISNUMBER(X37),N(X37)+N(X38),"") -> 436.23 | Y11: =IF(ISNUMBER(Y37),N(Y37)+N(Y38),"") -> 117.059 | Z11: =IF(ISNUMBER(Z37),N(Z37)+N(Z38),"") -> 120.499 | AA11: =IF(ISNUMBER(AA37),N(AA37)+N(AA38),"") -> 122.747 | ... BG11: =IF(ISNUMBER(BG37),N(BG37)+N(BG38),"") -> 994.362 | BH11: 267 | BI11: 271 | BJ11: 278 | BK11: 280 | BL11: =IF(ISNUMBER(BL37),N(BL37)+N(BL38),"") -> 1096.1 | BM11: 283 | BN11: 286 | BO11: 290 | BP11: 297 | BQ11: 1156 | BR11: 305 | BS11: 310 | BT11: 318 | BU11: 325 | BV11: 1259 | BW11: 331 | BX11: 337 | BY11: =BX11*(1+BY13+BY92) -> 345.92134 | BZ11: =BX11*((1+BZ13)^2+2*BZ92) -> 354.95548 | CA11: =SUM(BW11,BX11,BY11,BZ11) -> 1368.8768 | CB11: =CA11*(1+CB12) -> 1492.0757 | CC11: =CB11*(1+CC12) -> 1626.3626 | CD11: =CC11*(1+CD12) -> 1764.6034 | CE11: =CD11*(1+CE12) -> 1905.7716 | CF11: Q3/26E = Q2/26 × (1 + 1H/26 average q/q + outlook calibration Δ); Q4/26E = Q2/26 × ((1+g)² + 2Δ). 2027E+: prior year × (1 + scenario lever COSTAR_growth). | CH11: =IFERROR((CE11/BV11)^(1/5)-1,"n/m") -> 0.086448203 | CI11: =IFERROR((BV11/AW11)^(1/5)-1,"n/m") -> 0.096359611 | CJ11: =IFERROR((BV11/X11)^(1/10)-1,"n/m") -> 0.11181114 | CK11: =IFERROR((BV11/C11)^(1/19)-1,"n/m") -> n/m | CN11: FY26 outlook — Q2-26 release (28-Jul-26); legacy CoStar, excludes Zonda | CO11: High | CP11: Mid | CQ11: Low | CR11: Company guidance pre-dates the Zonda closing (21-Aug-26) — the model adds Zonda separately.
B12: y/y % | D12: =IF(AND(ISNUMBER(D11),ISNUMBER(C11)),IFERROR(D11/C11-1,""),"") | E12: =IF(AND(ISNUMBER(E11),ISNUMBER(D11)),IFERROR(E11/D11-1,""),"") | F12: =IF(AND(ISNUMBER(F11),ISNUMBER(E11)),IFERROR(F11/E11-1,""),"") | G12: =IF(AND(ISNUMBER(G11),ISNUMBER(F11)),IFERROR(G11/F11-1,""),"") | H12: =IF(AND(ISNUMBER(H11),ISNUMBER(G11)),IFERROR(H11/G11-1,""),"") | I12: =IF(AND(ISNUMBER(I11),ISNUMBER(H11)),IFERROR(I11/H11-1,""),"") | N12: =IF(AND(ISNUMBER(N11),ISNUMBER(I11)),IFERROR(N11/I11-1,""),"") | O12: =IF(AND(ISNUMBER(O11),ISNUMBER(J11)),IFERROR(O11/J11-1,""),"") | P12: =IF(AND(ISNUMBER(P11),ISNUMBER(K11)),IFERROR(P11/K11-1,""),"") | Q12: =IF(AND(ISNUMBER(Q11),ISNUMBER(L11)),IFERROR(Q11/L11-1,""),"") | R12: =IF(AND(ISNUMBER(R11),ISNUMBER(M11)),IFERROR(R11/M11-1,""),"") | S12: =IF(AND(ISNUMBER(S11),ISNUMBER(N11)),IFERROR(S11/N11-1,""),"") | T12: =IF(AND(ISNUMBER(T11),ISNUMBER(O11)),IFERROR(T11/O11-1,""),"") | U12: =IF(AND(ISNUMBER(U11),ISNUMBER(P11)),IFERROR(U11/P11-1,""),"") | ... BZ12: =IF(AND(ISNUMBER(BZ11),ISNUMBER(BU11)),IFERROR(BZ11/BU11-1,""),"") -> 0.092170695 | CA12: =IFERROR(CA11/BV11-1,"") -> 0.08727309 | CB12: =CHOOSE(MATCH($CF$2,{"Bull","Base","Bear"},0),$CO$46,$CP$46,$CQ$46) -> 0.09 | CC12: =CHOOSE(MATCH($CF$2,{"Bull","Base","Bear"},0),$CO$47,$CP$47,$CQ$47) -> 0.09 | CD12: =CHOOSE(MATCH($CF$2,{"Bull","Base","Bear"},0),$CO$48,$CP$48,$CQ$48) -> 0.085 | CE12: =CHOOSE(MATCH($CF$2,{"Bull","Base","Bear"},0),$CO$49,$CP$49,$CQ$49) -> 0.08 | CF12: 2015–22 mapped from legacy lines (CoStar Suite + Information Services). | CN12: FY26 revenues ($m) | CO12: 3755 | CP12: 3735 | CQ12: 3715 | CR12: Revised to $3.715–3.755bn in the Q2-26 release (from $3.78–3.82bn on 7-Jan-26 / 24-Feb-26).
B13: Sequential q/q % (Q3/Q4-26E: 1H/26 average q/q before outlook calibration) | K13: =IF(AND(ISNUMBER(K11),ISNUMBER(J11)),IFERROR(K11/J11-1,""),"") | L13: =IF(AND(ISNUMBER(L11),ISNUMBER(K11)),IFERROR(L11/K11-1,""),"") | M13: =IF(AND(ISNUMBER(M11),ISNUMBER(L11)),IFERROR(M11/L11-1,""),"") | O13: =IF(AND(ISNUMBER(O11),ISNUMBER(M11)),IFERROR(O11/M11-1,""),"") | P13: =IF(AND(ISNUMBER(P11),ISNUMBER(O11)),IFERROR(P11/O11-1,""),"") | Q13: =IF(AND(ISNUMBER(Q11),ISNUMBER(P11)),IFERROR(Q11/P11-1,""),"") | R13: =IF(AND(ISNUMBER(R11),ISNUMBER(Q11)),IFERROR(R11/Q11-1,""),"") | T13: =IF(AND(ISNUMBER(T11),ISNUMBER(R11)),IFERROR(T11/R11-1,""),"") | U13: =IF(AND(ISNUMBER(U11),ISNUMBER(T11)),IFERROR(U11/T11-1,""),"") -> 0.020655548 | V13: =IF(AND(ISNUMBER(V11),ISNUMBER(U11)),IFERROR(V11/U11-1,""),"") -> 0.027463891 | W13: =IF(AND(ISNUMBER(W11),ISNUMBER(V11)),IFERROR(W11/V11-1,""),"") -> 0.021796589 | Y13: =IF(AND(ISNUMBER(Y11),ISNUMBER(W11)),IFERROR(Y11/W11-1,""),"") -> 0.036984869 | Z13: =IF(AND(ISNUMBER(Z11),ISNUMBER(Y11)),IFERROR(Z11/Y11-1,""),"") -> 0.02938689 | AA13: =IF(AND(ISNUMBER(AA11),ISNUMBER(Z11)),IFERROR(AA11/Z11-1,""),"") -> 0.018655756 | AB13: =IF(AND(ISNUMBER(AB11),ISNUMBER(AA11)),IFERROR(AB11/AA11-1,""),"") -> 0.021035137 | AD13: =IF(AND(ISNUMBER(AD11),ISNUMBER(AB11)),IFERROR(AD11/AB11-1,""),"") -> 0.023825292 | AE13: =IF(AND(ISNUMBER(AE11),ISNUMBER(AD11)),IFERROR(AE11/AD11-1,""),"") -> 0.02954448 | AF13: =IF(AND(ISNUMBER(AF11),ISNUMBER(AE11)),IFERROR(AF11/AE11-1,""),"") -> 0.02970342 | AG13: =IF(AND(ISNUMBER(AG11),ISNUMBER(AF11)),IFERROR(AG11/AF11-1,""),"") -> 0.024421084 | AI13: =IF(AND(ISNUMBER(AI11),ISNUMBER(AG11)),IFERROR(AI11/AG11-1,""),"") -> 0.043551582 | AJ13: =IF(AND(ISNUMBER(AJ11),ISNUMBER(AI11)),IFERROR(AJ11/AI11-1,""),"") -> 0.028001458 | AK13: =IF(AND(ISNUMBER(AK11),ISNUMBER(AJ11)),IFERROR(AK11/AJ11-1,""),"") -> 0.047667784 | AL13: =IF(AND(ISNUMBER(AL11),ISNUMBER(AK11)),IFERROR(AL11/AK11-1,""),"") -> 0.028847075 | AN13: =IF(AND(ISNUMBER(AN11),ISNUMBER(AL11)),IFERROR(AN11/AL11-1,""),"") -> 0.033598739 | AO13: =IF(AND(ISNUMBER(AO11),ISNUMBER(AN11)),IFERROR(AO11/AN11-1,""),"") -> 0.042335381 | AP13: =IF(AND(ISNUMBER(AP11),ISNUMBER(AO11)),IFERROR(AP11/AO11-1,""),"") -> 0.010840889 | AQ13: =IF(AND(ISNUMBER(AQ11),ISNUMBER(AP11)),IFERROR(AQ11/AP11-1,""),"") -> 0.086178797 | AS13: =IF(AND(ISNUMBER(AS11),ISNUMBER(AQ11)),IFERROR(AS11/AQ11-1,""),"") -> 0.035313498 | AT13: =IF(AND(ISNUMBER(AT11),ISNUMBER(AS11)),IFERROR(AT11/AS11-1,""),"") -> -0.0088629661 | AU13: =IF(AND(ISNUMBER(AU11),ISNUMBER(AT11)),IFERROR(AU11/AT11-1,""),"") -> 0.018267899 | AV13: =IF(AND(ISNUMBER(AV11),ISNUMBER(AU11)),IFERROR(AV11/AU11-1,""),"") -> 0.01784477 | AX13: =IF(AND(ISNUMBER(AX11),ISNUMBER(AV11)),IFERROR(AX11/AV11-1,""),"") -> 0.020541053 | AY13: =IF(AND(ISNUMBER(AY11),ISNUMBER(AX11)),IFERROR(AY11/AX11-1,""),"") -> 0.025406032 | AZ13: =IF(AND(ISNUMBER(AZ11),ISNUMBER(AY11)),IFERROR(AZ11/AY11-1,""),"") -> 0.033256967 | BA13: =IF(AND(ISNUMBER(BA11),ISNUMBER(AZ11)),IFERROR(BA11/AZ11-1,""),"") -> 0.032291472 | BC13: =IF(AND(ISNUMBER(BC11),ISNUMBER(BA11)),IFERROR(BC11/BA11-1,""),"") -> 0.042405279 | BD13: =IF(AND(ISNUMBER(BD11),ISNUMBER(BC11)),IFERROR(BD11/BC11-1,""),"") -> 0.039022488 | BE13: =IF(AND(ISNUMBER(BE11),ISNUMBER(BD11)),IFERROR(BE11/BD11-1,""),"") -> 0.035235118 | BF13: =IF(AND(ISNUMBER(BF11),ISNUMBER(BE11)),IFERROR(BF11/BE11-1,""),"") -> 0.023744299 | BH13: =IF(AND(ISNUMBER(BH11),ISNUMBER(BF11)),IFERROR(BH11/BF11-1,""),"") -> 0.02800248 | BI13: =IF(AND(ISNUMBER(BI11),ISNUMBER(BH11)),IFERROR(BI11/BH11-1,""),"") -> 0.014981273 | BJ13: =IF(AND(ISNUMBER(BJ11),ISNUMBER(BI11)),IFERROR(BJ11/BI11-1,""),"") -> 0.025830258 | BK13: =IF(AND(ISNUMBER(BK11),ISNUMBER(BJ11)),IFERROR(BK11/BJ11-1,""),"") -> 0.0071942446 | BM13: =IF(AND(ISNUMBER(BM11),ISNUMBER(BK11)),IFERROR(BM11/BK11-1,""),"") -> 0.010714286 | BN13: =IF(AND(ISNUMBER(BN11),ISNUMBER(BM11)),IFERROR(BN11/BM11-1,""),"") -> 0.010600707 | BO13: =IF(AND(ISNUMBER(BO11),ISNUMBER(BN11)),IFERROR(BO11/BN11-1,""),"") -> 0.013986014 | BP13: =IF(AND(ISNUMBER(BP11),ISNUMBER(BO11)),IFERROR(BP11/BO11-1,""),"") -> 0.024137931 | BR13: =IF(AND(ISNUMBER(BR11),ISNUMBER(BP11)),IFERROR(BR11/BP11-1,""),"") -> 0.026936027 | BS13: =IF(AND(ISNUMBER(BS11),ISNUMBER(BR11)),IFERROR(BS11/BR11-1,""),"") -> 0.016393443 | BT13: =IF(AND(ISNUMBER(BT11),ISNUMBER(BS11)),IFERROR(BT11/BS11-1,""),"") -> 0.025806452 | BU13: =IF(AND(ISNUMBER(BU11),ISNUMBER(BT11)),IFERROR(BU11/BT11-1,""),"") -> 0.022012579 | BW13: =IF(AND(ISNUMBER(BW11),ISNUMBER(BU11)),IFERROR(BW11/BU11-1,""),"") -> 0.018461538 | BX13: =IF(AND(ISNUMBER(BX11),ISNUMBER(BW11)),IFERROR(BX11/BW11-1,""),"") -> 0.018126888 | BY13: =((BW11/BU11-1)+(BX11/BW11-1))/2 -> 0.018294213 | BZ13: =BY13 -> 0.018294213 | CN13: FY26 Adjusted EBITDA ($m) | CO13: 820 | CP13: 800 | CQ13: 780 | CR13: Affirmed $780–820m (raised +$30m at the mid-point vs Feb-26). Check vs model (segment calibration below sums to this).
B14: LoopNet (commercial property marketplace) | AS14: =IF(ISNUMBER(AS42),AS42,"") -> 43.2 | AT14: =IF(ISNUMBER(AT42),AT42,"") -> 43.32 | AU14: =IF(ISNUMBER(AU42),AU42,"") -> 45.084 | AV14: =IF(ISNUMBER(AV42),AV42,"") -> 48.201 | AW14: =IF(ISNUMBER(AW42),AW42,"") -> 179.805 | AX14: =IF(ISNUMBER(AX42),AX42,"") -> 49.23 | AY14: =IF(ISNUMBER(AY42),AY42,"") -> 51.095 | AZ14: =IF(ISNUMBER(AZ42),AZ42,"") -> 52.527 | ... BG14: =IF(ISNUMBER(BG42),BG42,"") -> 230.941 | BH14: 63 | BI14: 66 | BJ14: 68 | BK14: 69 | BL14: =IF(ISNUMBER(BL42),BL42,"") -> 264.8 | BM14: 69 | BN14: 70 | BO14: 71 | BP14: 72 | BQ14: 282 | BR14: 73 | BS14: 76 | BT14: 79 | BU14: 84 | BV14: 312 | BW14: 85 | BX14: 87 | BY14: =BX14*(1+BY16+BY92) -> 89.252926 | BZ14: =BX14*((1+BZ16)^2+2*BZ92) -> 91.533162 | CA14: =SUM(BW14,BX14,BY14,BZ14) -> 352.78609 | CB14: =CA14*(1+CB15) -> 395.12042 | CC14: =CB14*(1+CC15) -> 438.58366 | CD14: =CC14*(1+CD15) -> 482.44203 | CE14: =CD14*(1+CE15) -> 525.86181 | CF14: As CoStar. 2027E+: scenario lever LOOPNET_growth. | CH14: =IFERROR((CE14/BV14)^(1/5)-1,"n/m") -> 0.11005222 | CI14: =IFERROR((BV14/AW14)^(1/5)-1,"n/m") -> 0.11653044 | CJ14: =IFERROR((BV14/X14)^(1/10)-1,"n/m") -> n/m | CK14: =IFERROR((BV14/C14)^(1/19)-1,"n/m") -> n/m | CN14: FY26 net income ($m, guidance reconciliation) | CO14: 247 | CP14: 232.5 | CQ14: 218 | CR14: Q2-26 release forward-looking reconciliation (memo only).
B15: y/y % | D15: =IF(AND(ISNUMBER(D14),ISNUMBER(C14)),IFERROR(D14/C14-1,""),"") | E15: =IF(AND(ISNUMBER(E14),ISNUMBER(D14)),IFERROR(E14/D14-1,""),"") | F15: =IF(AND(ISNUMBER(F14),ISNUMBER(E14)),IFERROR(F14/E14-1,""),"") | G15: =IF(AND(ISNUMBER(G14),ISNUMBER(F14)),IFERROR(G14/F14-1,""),"") | H15: =IF(AND(ISNUMBER(H14),ISNUMBER(G14)),IFERROR(H14/G14-1,""),"") | I15: =IF(AND(ISNUMBER(I14),ISNUMBER(H14)),IFERROR(I14/H14-1,""),"") | N15: =IF(AND(ISNUMBER(N14),ISNUMBER(I14)),IFERROR(N14/I14-1,""),"") | O15: =IF(AND(ISNUMBER(O14),ISNUMBER(J14)),IFERROR(O14/J14-1,""),"") | P15: =IF(AND(ISNUMBER(P14),ISNUMBER(K14)),IFERROR(P14/K14-1,""),"") | Q15: =IF(AND(ISNUMBER(Q14),ISNUMBER(L14)),IFERROR(Q14/L14-1,""),"") | R15: =IF(AND(ISNUMBER(R14),ISNUMBER(M14)),IFERROR(R14/M14-1,""),"") | S15: =IF(AND(ISNUMBER(S14),ISNUMBER(N14)),IFERROR(S14/N14-1,""),"") | T15: =IF(AND(ISNUMBER(T14),ISNUMBER(O14)),IFERROR(T14/O14-1,""),"") | U15: =IF(AND(ISNUMBER(U14),ISNUMBER(P14)),IFERROR(U14/P14-1,""),"") | ... BZ15: =IF(AND(ISNUMBER(BZ14),ISNUMBER(BU14)),IFERROR(BZ14/BU14-1,""),"") -> 0.089680498 | CA15: =IFERROR(CA14/BV14-1,"") -> 0.13072464 | CB15: =CHOOSE(MATCH($CF$2,{"Bull","Base","Bear"},0),$CO$51,$CP$51,$CQ$51) -> 0.12 | CC15: =CHOOSE(MATCH($CF$2,{"Bull","Base","Bear"},0),$CO$52,$CP$52,$CQ$52) -> 0.11 | CD15: =CHOOSE(MATCH($CF$2,{"Bull","Base","Bear"},0),$CO$53,$CP$53,$CQ$53) -> 0.1 | CE15: =CHOOSE(MATCH($CF$2,{"Bull","Base","Bear"},0),$CO$54,$CP$54,$CQ$54) -> 0.09 | CN15: FY26 Adjusted EPS ($) | CO15: 1.39 | CP15: 1.355 | CQ15: 1.32 | CR15: On 405m shares; 26% non-GAAP tax rate (memo; model Adjusted EPS shown in the bridge).
B16: Sequential q/q % (Q3/Q4-26E: 1H/26 average q/q before outlook calibration) | K16: =IF(AND(ISNUMBER(K14),ISNUMBER(J14)),IFERROR(K14/J14-1,""),"") | L16: =IF(AND(ISNUMBER(L14),ISNUMBER(K14)),IFERROR(L14/K14-1,""),"") | M16: =IF(AND(ISNUMBER(M14),ISNUMBER(L14)),IFERROR(M14/L14-1,""),"") | O16: =IF(AND(ISNUMBER(O14),ISNUMBER(M14)),IFERROR(O14/M14-1,""),"") | P16: =IF(AND(ISNUMBER(P14),ISNUMBER(O14)),IFERROR(P14/O14-1,""),"") | Q16: =IF(AND(ISNUMBER(Q14),ISNUMBER(P14)),IFERROR(Q14/P14-1,""),"") | R16: =IF(AND(ISNUMBER(R14),ISNUMBER(Q14)),IFERROR(R14/Q14-1,""),"") | T16: =IF(AND(ISNUMBER(T14),ISNUMBER(R14)),IFERROR(T14/R14-1,""),"") | U16: =IF(AND(ISNUMBER(U14),ISNUMBER(T14)),IFERROR(U14/T14-1,""),"") | V16: =IF(AND(ISNUMBER(V14),ISNUMBER(U14)),IFERROR(V14/U14-1,""),"") | W16: =IF(AND(ISNUMBER(W14),ISNUMBER(V14)),IFERROR(W14/V14-1,""),"") | Y16: =IF(AND(ISNUMBER(Y14),ISNUMBER(W14)),IFERROR(Y14/W14-1,""),"") | Z16: =IF(AND(ISNUMBER(Z14),ISNUMBER(Y14)),IFERROR(Z14/Y14-1,""),"") | AA16: =IF(AND(ISNUMBER(AA14),ISNUMBER(Z14)),IFERROR(AA14/Z14-1,""),"") | AB16: =IF(AND(ISNUMBER(AB14),ISNUMBER(AA14)),IFERROR(AB14/AA14-1,""),"") | AD16: =IF(AND(ISNUMBER(AD14),ISNUMBER(AB14)),IFERROR(AD14/AB14-1,""),"") | AE16: =IF(AND(ISNUMBER(AE14),ISNUMBER(AD14)),IFERROR(AE14/AD14-1,""),"") | AF16: =IF(AND(ISNUMBER(AF14),ISNUMBER(AE14)),IFERROR(AF14/AE14-1,""),"") | AG16: =IF(AND(ISNUMBER(AG14),ISNUMBER(AF14)),IFERROR(AG14/AF14-1,""),"") | AI16: =IF(AND(ISNUMBER(AI14),ISNUMBER(AG14)),IFERROR(AI14/AG14-1,""),"") | AJ16: =IF(AND(ISNUMBER(AJ14),ISNUMBER(AI14)),IFERROR(AJ14/AI14-1,""),"") | AK16: =IF(AND(ISNUMBER(AK14),ISNUMBER(AJ14)),IFERROR(AK14/AJ14-1,""),"") | AL16: =IF(AND(ISNUMBER(AL14),ISNUMBER(AK14)),IFERROR(AL14/AK14-1,""),"") | AN16: =IF(AND(ISNUMBER(AN14),ISNUMBER(AL14)),IFERROR(AN14/AL14-1,""),"") | AO16: =IF(AND(ISNUMBER(AO14),ISNUMBER(AN14)),IFERROR(AO14/AN14-1,""),"") | AP16: =IF(AND(ISNUMBER(AP14),ISNUMBER(AO14)),IFERROR(AP14/AO14-1,""),"") | AQ16: =IF(AND(ISNUMBER(AQ14),ISNUMBER(AP14)),IFERROR(AQ14/AP14-1,""),"") | AS16: =IF(AND(ISNUMBER(AS14),ISNUMBER(AQ14)),IFERROR(AS14/AQ14-1,""),"") | AT16: =IF(AND(ISNUMBER(AT14),ISNUMBER(AS14)),IFERROR(AT14/AS14-1,""),"") -> 0.0027777778 | AU16: =IF(AND(ISNUMBER(AU14),ISNUMBER(AT14)),IFERROR(AU14/AT14-1,""),"") -> 0.040720222 | AV16: =IF(AND(ISNUMBER(AV14),ISNUMBER(AU14)),IFERROR(AV14/AU14-1,""),"") -> 0.06913761 | AX16: =IF(AND(ISNUMBER(AX14),ISNUMBER(AV14)),IFERROR(AX14/AV14-1,""),"") -> 0.021348105 | AY16: =IF(AND(ISNUMBER(AY14),ISNUMBER(AX14)),IFERROR(AY14/AX14-1,""),"") -> 0.037883404 | AZ16: =IF(AND(ISNUMBER(AZ14),ISNUMBER(AY14)),IFERROR(AZ14/AY14-1,""),"") -> 0.028026226 | BA16: =IF(AND(ISNUMBER(BA14),ISNUMBER(AZ14)),IFERROR(BA14/AZ14-1,""),"") -> 0.04058865 | BC16: =IF(AND(ISNUMBER(BC14),ISNUMBER(BA14)),IFERROR(BC14/BA14-1,""),"") -> -0.0038785927 | BD16: =IF(AND(ISNUMBER(BD14),ISNUMBER(BC14)),IFERROR(BD14/BC14-1,""),"") -> 0.033977997 | BE16: =IF(AND(ISNUMBER(BE14),ISNUMBER(BD14)),IFERROR(BE14/BD14-1,""),"") -> 0.046254685 | BF16: =IF(AND(ISNUMBER(BF14),ISNUMBER(BE14)),IFERROR(BF14/BE14-1,""),"") -> 0.040661449 | BH16: =IF(AND(ISNUMBER(BH14),ISNUMBER(BF14)),IFERROR(BH14/BF14-1,""),"") -> 0.02779953 | BI16: =IF(AND(ISNUMBER(BI14),ISNUMBER(BH14)),IFERROR(BI14/BH14-1,""),"") -> 0.047619048 | BJ16: =IF(AND(ISNUMBER(BJ14),ISNUMBER(BI14)),IFERROR(BJ14/BI14-1,""),"") -> 0.03030303 | BK16: =IF(AND(ISNUMBER(BK14),ISNUMBER(BJ14)),IFERROR(BK14/BJ14-1,""),"") -> 0.014705882 | BM16: =IF(AND(ISNUMBER(BM14),ISNUMBER(BK14)),IFERROR(BM14/BK14-1,""),"") -> 0 | BN16: =IF(AND(ISNUMBER(BN14),ISNUMBER(BM14)),IFERROR(BN14/BM14-1,""),"") -> 0.014492754 | BO16: =IF(AND(ISNUMBER(BO14),ISNUMBER(BN14)),IFERROR(BO14/BN14-1,""),"") -> 0.014285714 | BP16: =IF(AND(ISNUMBER(BP14),ISNUMBER(BO14)),IFERROR(BP14/BO14-1,""),"") -> 0.014084507 | BR16: =IF(AND(ISNUMBER(BR14),ISNUMBER(BP14)),IFERROR(BR14/BP14-1,""),"") -> 0.013888889 | BS16: =IF(AND(ISNUMBER(BS14),ISNUMBER(BR14)),IFERROR(BS14/BR14-1,""),"") -> 0.04109589 | BT16: =IF(AND(ISNUMBER(BT14),ISNUMBER(BS14)),IFERROR(BT14/BS14-1,""),"") -> 0.039473684 | BU16: =IF(AND(ISNUMBER(BU14),ISNUMBER(BT14)),IFERROR(BU14/BT14-1,""),"") -> 0.063291139 | BW16: =IF(AND(ISNUMBER(BW14),ISNUMBER(BU14)),IFERROR(BW14/BU14-1,""),"") -> 0.011904762 | BX16: =IF(AND(ISNUMBER(BX14),ISNUMBER(BW14)),IFERROR(BX14/BW14-1,""),"") -> 0.023529412 | BY16: =((BW14/BU14-1)+(BX14/BW14-1))/2 -> 0.017717087 | BZ16: =BY16 -> 0.017717087 | CN16: FY26 Commercial Real Estate Adjusted EBITDA ($m) | CO16: 690 | CP16: 680 | CQ16: 670 | CR16: Segment guidance (Q2-26 release) — drives the CRE margin calibration.
B17: Other Commercial Real Estate (Matterport from Feb-25, STR, Ten-X, BizBuySell, Realla) | BH17: 18 | BI17: 19 | BJ17: 20 | BK17: 24 | BL17: =SUM(BH17,BI17,BJ17,BK17) -> 81 | BM17: 17 | BN17: 18 | BO17: 19 | BP17: 22 | BQ17: 77 | BR17: 31 | BS17: 60 | BT17: 64 | BU17: 62 | BV17: 216 | BW17: 56 | BX17: 57 | BY17: =BX17*(1+BY19+BY92) -> 55.217045 | BZ17: =BX17*((1+BZ19)^2+2*BZ92) -> 53.522838 | CA17: =SUM(BW17,BX17,BY17,BZ17) -> 221.73988 | CB17: =CA17*(1+CB18) -> 232.82688 | CC17: =CB17*(1+CC18) -> 244.46822 | CD17: =CC17*(1+CD18) -> 256.69163 | CE17: =CD17*(1+CE18) -> 269.52621 | CF17: As CoStar. 2027E+: scenario lever OCRE_growth. Q1/25 → Q2/25 step-up = Matterport (closed 28-Feb-2025). | CH17: =IFERROR((CE17/BV17)^(1/5)-1,"n/m") -> 0.045272325 | CI17: =IFERROR((BV17/AW17)^(1/5)-1,"n/m") -> n/m | CJ17: =IFERROR((BV17/X17)^(1/10)-1,"n/m") -> n/m | CK17: =IFERROR((BV17/C17)^(1/19)-1,"n/m") -> n/m | CN17: FY26 Residential Real Estate Adjusted EBITDA ($m) | CO17: 130 | CP17: 120 | CQ17: 110 | CR17: Segment guidance — drives the Residential margin calibration. CRE + Residential = consolidated guide.
B18: y/y % | D18: =IF(AND(ISNUMBER(D17),ISNUMBER(C17)),IFERROR(D17/C17-1,""),"") | E18: =IF(AND(ISNUMBER(E17),ISNUMBER(D17)),IFERROR(E17/D17-1,""),"") | F18: =IF(AND(ISNUMBER(F17),ISNUMBER(E17)),IFERROR(F17/E17-1,""),"") | G18: =IF(AND(ISNUMBER(G17),ISNUMBER(F17)),IFERROR(G17/F17-1,""),"") | H18: =IF(AND(ISNUMBER(H17),ISNUMBER(G17)),IFERROR(H17/G17-1,""),"") | I18: =IF(AND(ISNUMBER(I17),ISNUMBER(H17)),IFERROR(I17/H17-1,""),"") | N18: =IF(AND(ISNUMBER(N17),ISNUMBER(I17)),IFERROR(N17/I17-1,""),"") | O18: =IF(AND(ISNUMBER(O17),ISNUMBER(J17)),IFERROR(O17/J17-1,""),"") | P18: =IF(AND(ISNUMBER(P17),ISNUMBER(K17)),IFERROR(P17/K17-1,""),"") | Q18: =IF(AND(ISNUMBER(Q17),ISNUMBER(L17)),IFERROR(Q17/L17-1,""),"") | R18: =IF(AND(ISNUMBER(R17),ISNUMBER(M17)),IFERROR(R17/M17-1,""),"") | S18: =IF(AND(ISNUMBER(S17),ISNUMBER(N17)),IFERROR(S17/N17-1,""),"") | T18: =IF(AND(ISNUMBER(T17),ISNUMBER(O17)),IFERROR(T17/O17-1,""),"") | U18: =IF(AND(ISNUMBER(U17),ISNUMBER(P17)),IFERROR(U17/P17-1,""),"") | ... BZ18: =IF(AND(ISNUMBER(BZ17),ISNUMBER(BU17)),IFERROR(BZ17/BU17-1,""),"") -> -0.13672841 | CA18: =IFERROR(CA17/BV17-1,"") -> 0.026573536 | CB18: =CHOOSE(MATCH($CF$2,{"Bull","Base","Bear"},0),$CO$56,$CP$56,$CQ$56) -> 0.05 | CC18: =CHOOSE(MATCH($CF$2,{"Bull","Base","Bear"},0),$CO$57,$CP$57,$CQ$57) -> 0.05 | CD18: =CHOOSE(MATCH($CF$2,{"Bull","Base","Bear"},0),$CO$58,$CP$58,$CQ$58) -> 0.05 | CE18: =CHOOSE(MATCH($CF$2,{"Bull","Base","Bear"},0),$CO$59,$CP$59,$CQ$59) -> 0.05 | CN18: FY26 point estimates (all cases; Q2-26 guidance reconciliation)
B19: Sequential q/q % (Q3/Q4-26E: 1H/26 average q/q before outlook calibration) | K19: =IF(AND(ISNUMBER(K17),ISNUMBER(J17)),IFERROR(K17/J17-1,""),"") | L19: =IF(AND(ISNUMBER(L17),ISNUMBER(K17)),IFERROR(L17/K17-1,""),"") | M19: =IF(AND(ISNUMBER(M17),ISNUMBER(L17)),IFERROR(M17/L17-1,""),"") | O19: =IF(AND(ISNUMBER(O17),ISNUMBER(M17)),IFERROR(O17/M17-1,""),"") | P19: =IF(AND(ISNUMBER(P17),ISNUMBER(O17)),IFERROR(P17/O17-1,""),"") | Q19: =IF(AND(ISNUMBER(Q17),ISNUMBER(P17)),IFERROR(Q17/P17-1,""),"") | R19: =IF(AND(ISNUMBER(R17),ISNUMBER(Q17)),IFERROR(R17/Q17-1,""),"") | T19: =IF(AND(ISNUMBER(T17),ISNUMBER(R17)),IFERROR(T17/R17-1,""),"") | U19: =IF(AND(ISNUMBER(U17),ISNUMBER(T17)),IFERROR(U17/T17-1,""),"") | V19: =IF(AND(ISNUMBER(V17),ISNUMBER(U17)),IFERROR(V17/U17-1,""),"") | W19: =IF(AND(ISNUMBER(W17),ISNUMBER(V17)),IFERROR(W17/V17-1,""),"") | Y19: =IF(AND(ISNUMBER(Y17),ISNUMBER(W17)),IFERROR(Y17/W17-1,""),"") | Z19: =IF(AND(ISNUMBER(Z17),ISNUMBER(Y17)),IFERROR(Z17/Y17-1,""),"") | AA19: =IF(AND(ISNUMBER(AA17),ISNUMBER(Z17)),IFERROR(AA17/Z17-1,""),"") | AB19: =IF(AND(ISNUMBER(AB17),ISNUMBER(AA17)),IFERROR(AB17/AA17-1,""),"") | AD19: =IF(AND(ISNUMBER(AD17),ISNUMBER(AB17)),IFERROR(AD17/AB17-1,""),"") | AE19: =IF(AND(ISNUMBER(AE17),ISNUMBER(AD17)),IFERROR(AE17/AD17-1,""),"") | AF19: =IF(AND(ISNUMBER(AF17),ISNUMBER(AE17)),IFERROR(AF17/AE17-1,""),"") | AG19: =IF(AND(ISNUMBER(AG17),ISNUMBER(AF17)),IFERROR(AG17/AF17-1,""),"") | AI19: =IF(AND(ISNUMBER(AI17),ISNUMBER(AG17)),IFERROR(AI17/AG17-1,""),"") | AJ19: =IF(AND(ISNUMBER(AJ17),ISNUMBER(AI17)),IFERROR(AJ17/AI17-1,""),"") | AK19: =IF(AND(ISNUMBER(AK17),ISNUMBER(AJ17)),IFERROR(AK17/AJ17-1,""),"") | AL19: =IF(AND(ISNUMBER(AL17),ISNUMBER(AK17)),IFERROR(AL17/AK17-1,""),"") | AN19: =IF(AND(ISNUMBER(AN17),ISNUMBER(AL17)),IFERROR(AN17/AL17-1,""),"") | AO19: =IF(AND(ISNUMBER(AO17),ISNUMBER(AN17)),IFERROR(AO17/AN17-1,""),"") | AP19: =IF(AND(ISNUMBER(AP17),ISNUMBER(AO17)),IFERROR(AP17/AO17-1,""),"") | AQ19: =IF(AND(ISNUMBER(AQ17),ISNUMBER(AP17)),IFERROR(AQ17/AP17-1,""),"") | AS19: =IF(AND(ISNUMBER(AS17),ISNUMBER(AQ17)),IFERROR(AS17/AQ17-1,""),"") | AT19: =IF(AND(ISNUMBER(AT17),ISNUMBER(AS17)),IFERROR(AT17/AS17-1,""),"") | AU19: =IF(AND(ISNUMBER(AU17),ISNUMBER(AT17)),IFERROR(AU17/AT17-1,""),"") | AV19: =IF(AND(ISNUMBER(AV17),ISNUMBER(AU17)),IFERROR(AV17/AU17-1,""),"") | AX19: =IF(AND(ISNUMBER(AX17),ISNUMBER(AV17)),IFERROR(AX17/AV17-1,""),"") | AY19: =IF(AND(ISNUMBER(AY17),ISNUMBER(AX17)),IFERROR(AY17/AX17-1,""),"") | AZ19: =IF(AND(ISNUMBER(AZ17),ISNUMBER(AY17)),IFERROR(AZ17/AY17-1,""),"") | BA19: =IF(AND(ISNUMBER(BA17),ISNUMBER(AZ17)),IFERROR(BA17/AZ17-1,""),"") | BC19: =IF(AND(ISNUMBER(BC17),ISNUMBER(BA17)),IFERROR(BC17/BA17-1,""),"") | BD19: =IF(AND(ISNUMBER(BD17),ISNUMBER(BC17)),IFERROR(BD17/BC17-1,""),"") | BE19: =IF(AND(ISNUMBER(BE17),ISNUMBER(BD17)),IFERROR(BE17/BD17-1,""),"") | BF19: =IF(AND(ISNUMBER(BF17),ISNUMBER(BE17)),IFERROR(BF17/BE17-1,""),"") | BH19: =IF(AND(ISNUMBER(BH17),ISNUMBER(BF17)),IFERROR(BH17/BF17-1,""),"") | BI19: =IF(AND(ISNUMBER(BI17),ISNUMBER(BH17)),IFERROR(BI17/BH17-1,""),"") -> 0.055555556 | BJ19: =IF(AND(ISNUMBER(BJ17),ISNUMBER(BI17)),IFERROR(BJ17/BI17-1,""),"") -> 0.052631579 | BK19: =IF(AND(ISNUMBER(BK17),ISNUMBER(BJ17)),IFERROR(BK17/BJ17-1,""),"") -> 0.2 | BM19: =IF(AND(ISNUMBER(BM17),ISNUMBER(BK17)),IFERROR(BM17/BK17-1,""),"") -> -0.29166667 | BN19: =IF(AND(ISNUMBER(BN17),ISNUMBER(BM17)),IFERROR(BN17/BM17-1,""),"") -> 0.058823529 | BO19: =IF(AND(ISNUMBER(BO17),ISNUMBER(BN17)),IFERROR(BO17/BN17-1,""),"") -> 0.055555556 | BP19: =IF(AND(ISNUMBER(BP17),ISNUMBER(BO17)),IFERROR(BP17/BO17-1,""),"") -> 0.15789474 | BR19: =IF(AND(ISNUMBER(BR17),ISNUMBER(BP17)),IFERROR(BR17/BP17-1,""),"") -> 0.40909091 | BS19: =IF(AND(ISNUMBER(BS17),ISNUMBER(BR17)),IFERROR(BS17/BR17-1,""),"") -> 0.93548387 | BT19: =IF(AND(ISNUMBER(BT17),ISNUMBER(BS17)),IFERROR(BT17/BS17-1,""),"") -> 0.066666667 | BU19: =IF(AND(ISNUMBER(BU17),ISNUMBER(BT17)),IFERROR(BU17/BT17-1,""),"") -> -0.03125 | BW19: =IF(AND(ISNUMBER(BW17),ISNUMBER(BU17)),IFERROR(BW17/BU17-1,""),"") -> -0.096774194 | BX19: =IF(AND(ISNUMBER(BX17),ISNUMBER(BW17)),IFERROR(BX17/BW17-1,""),"") -> 0.017857143 | BY19: =((BW17/BU17-1)+(BX17/BW17-1))/2 -> -0.039458525 | BZ19: =BY19 -> -0.039458525 | CN19: Stock-based compensation ($m) | CP19: 156 | CR19: Guidance reconciliation (FY).
B20: Commercial Real Estate — revenues | C20: =IF(ISNUMBER(C17),C11+C14+C17,"") | D20: =IF(ISNUMBER(D17),D11+D14+D17,"") | E20: =IF(ISNUMBER(E17),E11+E14+E17,"") | F20: =IF(ISNUMBER(F17),F11+F14+F17,"") | G20: =IF(ISNUMBER(G17),G11+G14+G17,"") | H20: =IF(ISNUMBER(H17),H11+H14+H17,"") | I20: =IF(ISNUMBER(I17),I11+I14+I17,"") | J20: =IF(ISNUMBER(J17),J11+J14+J17,"") | ... BX20: =IF(ISNUMBER(BX17),BX11+BX14+BX17,"") -> 481 | BY20: =BY11+BY14+BY17 -> 490.39132 | BZ20: =BZ11+BZ14+BZ17 -> 500.01148 | CA20: =CA11+CA14+CA17 -> 1943.4028 | CB20: =CB11+CB14+CB17 -> 2120.023 | CC20: =CC11+CC14+CC17 -> 2309.4144 | CD20: =CD11+CD14+CD17 -> 2503.737 | CE20: =CE11+CE14+CE17 -> 2701.1597 | CH20: =IFERROR((CE20/BV20)^(1/5)-1,"n/m") -> 0.086138331 | CI20: =IFERROR((BV20/AW20)^(1/5)-1,"n/m") -> n/m | CJ20: =IFERROR((BV20/X20)^(1/10)-1,"n/m") -> n/m | CK20: =IFERROR((BV20/C20)^(1/19)-1,"n/m") -> n/m | CN20: Amortization of acquired intangible assets ($m) | CP20: 251 | CR20: $108m in cost of revenues + $143m in operating expenses.
B21: y/y % | D21: =IF(AND(ISNUMBER(D20),ISNUMBER(C20)),IFERROR(D20/C20-1,""),"") | E21: =IF(AND(ISNUMBER(E20),ISNUMBER(D20)),IFERROR(E20/D20-1,""),"") | F21: =IF(AND(ISNUMBER(F20),ISNUMBER(E20)),IFERROR(F20/E20-1,""),"") | G21: =IF(AND(ISNUMBER(G20),ISNUMBER(F20)),IFERROR(G20/F20-1,""),"") | H21: =IF(AND(ISNUMBER(H20),ISNUMBER(G20)),IFERROR(H20/G20-1,""),"") | I21: =IF(AND(ISNUMBER(I20),ISNUMBER(H20)),IFERROR(I20/H20-1,""),"") | N21: =IF(AND(ISNUMBER(N20),ISNUMBER(I20)),IFERROR(N20/I20-1,""),"") | O21: =IF(AND(ISNUMBER(O20),ISNUMBER(J20)),IFERROR(O20/J20-1,""),"") | P21: =IF(AND(ISNUMBER(P20),ISNUMBER(K20)),IFERROR(P20/K20-1,""),"") | Q21: =IF(AND(ISNUMBER(Q20),ISNUMBER(L20)),IFERROR(Q20/L20-1,""),"") | R21: =IF(AND(ISNUMBER(R20),ISNUMBER(M20)),IFERROR(R20/M20-1,""),"") | S21: =IF(AND(ISNUMBER(S20),ISNUMBER(N20)),IFERROR(S20/N20-1,""),"") | T21: =IF(AND(ISNUMBER(T20),ISNUMBER(O20)),IFERROR(T20/O20-1,""),"") | U21: =IF(AND(ISNUMBER(U20),ISNUMBER(P20)),IFERROR(U20/P20-1,""),"") | ... CA21: =IF(AND(ISNUMBER(CA20),ISNUMBER(BV20)),IFERROR(CA20/BV20-1,""),"") -> 0.087522548 | CB21: =IF(AND(ISNUMBER(CB20),ISNUMBER(CA20)),IFERROR(CB20/CA20-1,""),"") -> 0.090881952 | CC21: =IF(AND(ISNUMBER(CC20),ISNUMBER(CB20)),IFERROR(CC20/CB20-1,""),"") -> 0.089334598 | CD21: =IF(AND(ISNUMBER(CD20),ISNUMBER(CC20)),IFERROR(CD20/CC20-1,""),"") -> 0.084143665 | CE21: =IF(AND(ISNUMBER(CE20),ISNUMBER(CD20)),IFERROR(CE20/CD20-1,""),"") -> 0.078851186 | CN21: Depreciation & other amortization ($m) | CP21: 77
B22: Commercial Real Estate — Adjusted EBITDA (segment) | BM22: 143 | BN22: 144 | BO22: 153 | BP22: 162 | BQ22: 602 | BR22: 151 | BS22: 161 | BT22: 183 | BU22: 177 | BV22: 672 | BW22: 161 | BX22: 172 | BY22: =BY20*BY24 -> 177.05518 | BZ22: =BZ20*BZ24 -> 169.94482 | CA22: =SUM(BW22,BX22,BY22,BZ22) -> 680 | CB22: =CB20*CB24 -> 773.80841 | CC22: =CC20*CC24 -> 866.03041 | CD22: =CD20*CD24 -> 963.93876 | CE22: =CE20*CE24 -> 1066.9581 | CH22: =IFERROR((CE22/BV22)^(1/5)-1,"n/m") -> 0.096871155 | CI22: =IFERROR((BV22/AW22)^(1/5)-1,"n/m") -> n/m | CJ22: =IFERROR((BV22/X22)^(1/10)-1,"n/m") -> n/m | CK22: =IFERROR((BV22/C22)^(1/19)-1,"n/m") -> n/m | CN22: Interest income, net ($m) | CP22: 13 | CR22: Pre-Zonda cash balance (deal closed after guidance).
B23: Adjusted EBITDA margin before outlook calibration % (Q3/Q4-26E helper) | BY23: =BT24+(BW22+BX22)/(BW20+BX20)-(BR22+BS22)/(BR20+BS20) -> 0.38147372 | BZ23: =BU24+(BW22+BX22)/(BW20+BX20)-(BR22+BS22)/(BR20+BS20) -> 0.36030677 | CF23: Prior-year quarter margin + (1H/26 − 1H/25 margin drift). | CN23: Other expense, net ($m) | CP23: 3
B24: Adjusted EBITDA margin % | C24: =IF(AND(ISNUMBER(C22),ISNUMBER(C20)),IFERROR(C22/C20,""),"") | D24: =IF(AND(ISNUMBER(D22),ISNUMBER(D20)),IFERROR(D22/D20,""),"") | E24: =IF(AND(ISNUMBER(E22),ISNUMBER(E20)),IFERROR(E22/E20,""),"") | F24: =IF(AND(ISNUMBER(F22),ISNUMBER(F20)),IFERROR(F22/F20,""),"") | G24: =IF(AND(ISNUMBER(G22),ISNUMBER(G20)),IFERROR(G22/G20,""),"") | H24: =IF(AND(ISNUMBER(H22),ISNUMBER(H20)),IFERROR(H22/H20,""),"") | I24: =IF(AND(ISNUMBER(I22),ISNUMBER(I20)),IFERROR(I22/I20,""),"") | J24: =IF(AND(ISNUMBER(J22),ISNUMBER(J20)),IFERROR(J22/J20,""),"") | ... BX24: =IF(AND(ISNUMBER(BX22),ISNUMBER(BX20)),IFERROR(BX22/BX20,""),"") -> 0.35758836 | BY24: =BY23+$BY97 -> 0.36104878 | BZ24: =BZ23+$BY97 -> 0.33988183 | CA24: =IF(AND(ISNUMBER(CA22),ISNUMBER(CA20)),IFERROR(CA22/CA20,""),"") -> 0.34990173 | CB24: =CHOOSE(MATCH($CF$2,{"Bull","Base","Bear"},0),$CO$66,$CP$66,$CQ$66) -> 0.365 | CC24: =CHOOSE(MATCH($CF$2,{"Bull","Base","Bear"},0),$CO$67,$CP$67,$CQ$67) -> 0.375 | CD24: =CHOOSE(MATCH($CF$2,{"Bull","Base","Bear"},0),$CO$68,$CP$68,$CQ$68) -> 0.385 | CE24: =CHOOSE(MATCH($CF$2,{"Bull","Base","Bear"},0),$CO$69,$CP$69,$CQ$69) -> 0.395 | CF24: Q3/Q4-26E: margin before calibration + CRE outlook calibration Δ (Group block; to segment guidance). 2027E+: scenario lever CRE_margin. | CH24: =IFERROR(AVERAGE(CA24,CB24,CC24,CD24,CE24),"n/m") -> 0.37398035 | CI24: =IFERROR(AVERAGE(BB24,BG24,BL24,BQ24,BV24),"n/m") -> 0.38670449 | CJ24: =IFERROR(AVERAGE(AC24,AH24,AM24,AR24,AW24,BB24,BG24,BL24,BQ24,BV24),"n/m") -> 0.38670449 | CK24: =IFERROR(AVERAGE(C24,D24,E24,F24,G24,H24,I24,N24,S24,X24,AC24,AH24,AM24,AR24,AW24,BB24,BG24,BL24,BQ24,BV24),"n/m") -> 0.38670449 | CN24: Income tax expense ($m, mid-point) | CP24: 92.5 | CR24: $87–98m.
B25: Memo: Commercial Real Estate — EBITDA (segment, as reported) | BM25: 126 | BN25: 125 | BO25: 136 | BP25: 132 | BQ25: 519 | BR25: 103 | BS25: 118 | BT25: 114 | BU25: 145 | BV25: 480 | BW25: 127 | BX25: 162 | CN25: GAAP tax rate (implied) | CP25: =CP24/(CP14+CP24) -> 0.28461538 | CR25: Tax $92.5m / pre-tax $325m = 28.5%.
CN26: Acquisition & integration related costs ($m) | CP26: 15 | CR26: Excludes Zonda closing costs (estimated separately in the Zonda block).
B27: Residential Real Estate (Apartments.com network · Homes.com · Domain from Aug-25 · OnTheMarket · Land.com) — excludes Zonda | CF27: RESIDENTIAL REAL ESTATE — modelling logic | CN27: Restructuring & related costs ($m) | CP27: 4
B28: Residential Real Estate — revenues (legacy, ex-Zonda) | BH28: 236 | BI28: 250 | BJ28: 259 | BK28: 267 | BL28: =SUM(BH28,BI28,BJ28,BK28) -> 1012 | BM28: 287 | BN28: 304 | BO28: 313 | BP28: 318 | BQ28: 1221 | BR28: 323 | BS28: 335 | BT28: 373 | BU28: 429 | BV28: 1460 | BW28: 425 | BX28: 444 | BY28: =BX28*(1+BY30+BY92) -> 455.48608 | BZ28: =BX28*((1+BZ30)^2+2*BZ92) -> 467.11112 | CA28: =SUM(BW28,BX28,BY28,BZ28) -> 1791.5972 | CB28: =CA28*(1+CB29) -> 2006.5889 | CC28: =CB28*(1+CC29) -> 2227.3136 | CD28: =CC28*(1+CD29) -> 2450.045 | CE28: =CD28*(1+CE29) -> 2670.5491 | CF28: Q3/Q4-26E as CoStar (sequential). 2027E+: scenario lever RESI_growth. Q3/26 y/y growth flatters as Domain (Aug-25) anniversaries. | CH28: =IFERROR((CE28/BV28)^(1/5)-1,"n/m") -> 0.12836483 | CI28: =IFERROR((BV28/AW28)^(1/5)-1,"n/m") -> n/m | CJ28: =IFERROR((BV28/X28)^(1/10)-1,"n/m") -> n/m | CK28: =IFERROR((BV28/C28)^(1/19)-1,"n/m") -> n/m | CN28: Settlements & impairments ($m) | CP28: -18 | CR28: Q2-26 credit (litigation accrual release).
B29: y/y % | D29: =IF(AND(ISNUMBER(D28),ISNUMBER(C28)),IFERROR(D28/C28-1,""),"") | E29: =IF(AND(ISNUMBER(E28),ISNUMBER(D28)),IFERROR(E28/D28-1,""),"") | F29: =IF(AND(ISNUMBER(F28),ISNUMBER(E28)),IFERROR(F28/E28-1,""),"") | G29: =IF(AND(ISNUMBER(G28),ISNUMBER(F28)),IFERROR(G28/F28-1,""),"") | H29: =IF(AND(ISNUMBER(H28),ISNUMBER(G28)),IFERROR(H28/G28-1,""),"") | I29: =IF(AND(ISNUMBER(I28),ISNUMBER(H28)),IFERROR(I28/H28-1,""),"") | N29: =IF(AND(ISNUMBER(N28),ISNUMBER(I28)),IFERROR(N28/I28-1,""),"") | O29: =IF(AND(ISNUMBER(O28),ISNUMBER(J28)),IFERROR(O28/J28-1,""),"") | P29: =IF(AND(ISNUMBER(P28),ISNUMBER(K28)),IFERROR(P28/K28-1,""),"") | Q29: =IF(AND(ISNUMBER(Q28),ISNUMBER(L28)),IFERROR(Q28/L28-1,""),"") | R29: =IF(AND(ISNUMBER(R28),ISNUMBER(M28)),IFERROR(R28/M28-1,""),"") | S29: =IF(AND(ISNUMBER(S28),ISNUMBER(N28)),IFERROR(S28/N28-1,""),"") | T29: =IF(AND(ISNUMBER(T28),ISNUMBER(O28)),IFERROR(T28/O28-1,""),"") | U29: =IF(AND(ISNUMBER(U28),ISNUMBER(P28)),IFERROR(U28/P28-1,""),"") | ... BZ29: =IF(AND(ISNUMBER(BZ28),ISNUMBER(BU28)),IFERROR(BZ28/BU28-1,""),"") -> 0.088837119 | CA29: =IFERROR(CA28/BV28-1,"") -> 0.22712137 | CB29: =CHOOSE(MATCH($CF$2,{"Bull","Base","Bear"},0),$CO$61,$CP$61,$CQ$61) -> 0.12 | CC29: =CHOOSE(MATCH($CF$2,{"Bull","Base","Bear"},0),$CO$62,$CP$62,$CQ$62) -> 0.11 | CD29: =CHOOSE(MATCH($CF$2,{"Bull","Base","Bear"},0),$CO$63,$CP$63,$CQ$63) -> 0.1 | CE29: =CHOOSE(MATCH($CF$2,{"Bull","Base","Bear"},0),$CO$64,$CP$64,$CQ$64) -> 0.09 | CN29: Adjusted diluted shares (m) | CP29: 405
B30: Sequential q/q % (Q3/Q4-26E: 1H/26 average q/q before outlook calibration) | K30: =IF(AND(ISNUMBER(K28),ISNUMBER(J28)),IFERROR(K28/J28-1,""),"") | L30: =IF(AND(ISNUMBER(L28),ISNUMBER(K28)),IFERROR(L28/K28-1,""),"") | M30: =IF(AND(ISNUMBER(M28),ISNUMBER(L28)),IFERROR(M28/L28-1,""),"") | O30: =IF(AND(ISNUMBER(O28),ISNUMBER(M28)),IFERROR(O28/M28-1,""),"") | P30: =IF(AND(ISNUMBER(P28),ISNUMBER(O28)),IFERROR(P28/O28-1,""),"") | Q30: =IF(AND(ISNUMBER(Q28),ISNUMBER(P28)),IFERROR(Q28/P28-1,""),"") | R30: =IF(AND(ISNUMBER(R28),ISNUMBER(Q28)),IFERROR(R28/Q28-1,""),"") | T30: =IF(AND(ISNUMBER(T28),ISNUMBER(R28)),IFERROR(T28/R28-1,""),"") | U30: =IF(AND(ISNUMBER(U28),ISNUMBER(T28)),IFERROR(U28/T28-1,""),"") | V30: =IF(AND(ISNUMBER(V28),ISNUMBER(U28)),IFERROR(V28/U28-1,""),"") | W30: =IF(AND(ISNUMBER(W28),ISNUMBER(V28)),IFERROR(W28/V28-1,""),"") | Y30: =IF(AND(ISNUMBER(Y28),ISNUMBER(W28)),IFERROR(Y28/W28-1,""),"") | Z30: =IF(AND(ISNUMBER(Z28),ISNUMBER(Y28)),IFERROR(Z28/Y28-1,""),"") | AA30: =IF(AND(ISNUMBER(AA28),ISNUMBER(Z28)),IFERROR(AA28/Z28-1,""),"") | AB30: =IF(AND(ISNUMBER(AB28),ISNUMBER(AA28)),IFERROR(AB28/AA28-1,""),"") | AD30: =IF(AND(ISNUMBER(AD28),ISNUMBER(AB28)),IFERROR(AD28/AB28-1,""),"") | AE30: =IF(AND(ISNUMBER(AE28),ISNUMBER(AD28)),IFERROR(AE28/AD28-1,""),"") | AF30: =IF(AND(ISNUMBER(AF28),ISNUMBER(AE28)),IFERROR(AF28/AE28-1,""),"") | AG30: =IF(AND(ISNUMBER(AG28),ISNUMBER(AF28)),IFERROR(AG28/AF28-1,""),"") | AI30: =IF(AND(ISNUMBER(AI28),ISNUMBER(AG28)),IFERROR(AI28/AG28-1,""),"") | AJ30: =IF(AND(ISNUMBER(AJ28),ISNUMBER(AI28)),IFERROR(AJ28/AI28-1,""),"") | AK30: =IF(AND(ISNUMBER(AK28),ISNUMBER(AJ28)),IFERROR(AK28/AJ28-1,""),"") | AL30: =IF(AND(ISNUMBER(AL28),ISNUMBER(AK28)),IFERROR(AL28/AK28-1,""),"") | AN30: =IF(AND(ISNUMBER(AN28),ISNUMBER(AL28)),IFERROR(AN28/AL28-1,""),"") | AO30: =IF(AND(ISNUMBER(AO28),ISNUMBER(AN28)),IFERROR(AO28/AN28-1,""),"") | AP30: =IF(AND(ISNUMBER(AP28),ISNUMBER(AO28)),IFERROR(AP28/AO28-1,""),"") | AQ30: =IF(AND(ISNUMBER(AQ28),ISNUMBER(AP28)),IFERROR(AQ28/AP28-1,""),"") | AS30: =IF(AND(ISNUMBER(AS28),ISNUMBER(AQ28)),IFERROR(AS28/AQ28-1,""),"") | AT30: =IF(AND(ISNUMBER(AT28),ISNUMBER(AS28)),IFERROR(AT28/AS28-1,""),"") | AU30: =IF(AND(ISNUMBER(AU28),ISNUMBER(AT28)),IFERROR(AU28/AT28-1,""),"") | AV30: =IF(AND(ISNUMBER(AV28),ISNUMBER(AU28)),IFERROR(AV28/AU28-1,""),"") | AX30: =IF(AND(ISNUMBER(AX28),ISNUMBER(AV28)),IFERROR(AX28/AV28-1,""),"") | AY30: =IF(AND(ISNUMBER(AY28),ISNUMBER(AX28)),IFERROR(AY28/AX28-1,""),"") | AZ30: =IF(AND(ISNUMBER(AZ28),ISNUMBER(AY28)),IFERROR(AZ28/AY28-1,""),"") | BA30: =IF(AND(ISNUMBER(BA28),ISNUMBER(AZ28)),IFERROR(BA28/AZ28-1,""),"") | BC30: =IF(AND(ISNUMBER(BC28),ISNUMBER(BA28)),IFERROR(BC28/BA28-1,""),"") | BD30: =IF(AND(ISNUMBER(BD28),ISNUMBER(BC28)),IFERROR(BD28/BC28-1,""),"") | BE30: =IF(AND(ISNUMBER(BE28),ISNUMBER(BD28)),IFERROR(BE28/BD28-1,""),"") | BF30: =IF(AND(ISNUMBER(BF28),ISNUMBER(BE28)),IFERROR(BF28/BE28-1,""),"") | BH30: =IF(AND(ISNUMBER(BH28),ISNUMBER(BF28)),IFERROR(BH28/BF28-1,""),"") | BI30: =IF(AND(ISNUMBER(BI28),ISNUMBER(BH28)),IFERROR(BI28/BH28-1,""),"") -> 0.059322034 | BJ30: =IF(AND(ISNUMBER(BJ28),ISNUMBER(BI28)),IFERROR(BJ28/BI28-1,""),"") -> 0.036 | BK30: =IF(AND(ISNUMBER(BK28),ISNUMBER(BJ28)),IFERROR(BK28/BJ28-1,""),"") -> 0.030888031 | BM30: =IF(AND(ISNUMBER(BM28),ISNUMBER(BK28)),IFERROR(BM28/BK28-1,""),"") -> 0.074906367 | BN30: =IF(AND(ISNUMBER(BN28),ISNUMBER(BM28)),IFERROR(BN28/BM28-1,""),"") -> 0.059233449 | BO30: =IF(AND(ISNUMBER(BO28),ISNUMBER(BN28)),IFERROR(BO28/BN28-1,""),"") -> 0.029605263 | BP30: =IF(AND(ISNUMBER(BP28),ISNUMBER(BO28)),IFERROR(BP28/BO28-1,""),"") -> 0.015974441 | BR30: =IF(AND(ISNUMBER(BR28),ISNUMBER(BP28)),IFERROR(BR28/BP28-1,""),"") -> 0.01572327 | BS30: =IF(AND(ISNUMBER(BS28),ISNUMBER(BR28)),IFERROR(BS28/BR28-1,""),"") -> 0.037151703 | BT30: =IF(AND(ISNUMBER(BT28),ISNUMBER(BS28)),IFERROR(BT28/BS28-1,""),"") -> 0.11343284 | BU30: =IF(AND(ISNUMBER(BU28),ISNUMBER(BT28)),IFERROR(BU28/BT28-1,""),"") -> 0.15013405 | BW30: =IF(AND(ISNUMBER(BW28),ISNUMBER(BU28)),IFERROR(BW28/BU28-1,""),"") -> -0.0093240093 | BX30: =IF(AND(ISNUMBER(BX28),ISNUMBER(BW28)),IFERROR(BX28/BW28-1,""),"") -> 0.044705882 | BY30: =((BW28/BU28-1)+(BX28/BW28-1))/2 -> 0.017690937 | BZ30: =BY30 -> 0.017690937 | CN30: Q3/26 guidance (memo; mid-point used for SBC, D&A, amortization, interest, other, acquisition costs) | CO30: High | CP30: Mid | CQ30: Low
B31: Residential Real Estate — Adjusted EBITDA (segment, ex-Zonda) | BM31: -131 | BN31: -103 | BO31: -77 | BP31: -50 | BQ31: -361 | BR31: -85 | BS31: -76 | BT31: -69 | BU31: 0 | BV31: -230 | BW31: -29 | BX31: 12 | BY31: =BY28*BY33 -> 24.976622 | BZ31: =BZ28*BZ33 -> 112.02338 | CA31: =SUM(BW31,BX31,BY31,BZ31) -> 120 | CB31: =CB28*CB33 -> 180.593 | CC31: =CC28*CC33 -> 311.82391 | CD31: =CD28*CD33 -> 465.50855 | CE31: =CE28*CE33 -> 640.93178 | CH31: =IFERROR((CE31/BV31)^(1/5)-1,"n/m") -> -2.2274867 | CI31: =IFERROR((BV31/AW31)^(1/5)-1,"n/m") -> n/m | CJ31: =IFERROR((BV31/X31)^(1/10)-1,"n/m") -> n/m | CK31: =IFERROR((BV31/C31)^(1/19)-1,"n/m") -> n/m | CN31: Q3/26 revenues ($m) | CO31: 945 | CP31: 940 | CQ31: 935 | CR31: Memo check only — FY calibration drives the Q3/Q4 split.
B32: Adjusted EBITDA margin before outlook calibration % (Q3/Q4-26E helper) | BY32: =BT33+(BW31+BX31)/(BW28+BX28)-(BR31+BS31)/(BR28+BS28) -> 0.04013154 | BZ32: =BU33+(BW31+BX31)/(BW28+BX28)-(BR31+BS31)/(BR28+BS28) -> 0.22511814 | CF32: Prior-year quarter margin + 1H margin drift (+22pp: Homes.com marketing cut). Q4 seasonally strongest (lower marketing). | CN32: Q3/26 Adjusted EBITDA ($m) | CO32: 210 | CP32: 200 | CQ32: 190 | CR32: Memo check only.
B33: Adjusted EBITDA margin % | C33: =IF(AND(ISNUMBER(C31),ISNUMBER(C28)),IFERROR(C31/C28,""),"") | D33: =IF(AND(ISNUMBER(D31),ISNUMBER(D28)),IFERROR(D31/D28,""),"") | E33: =IF(AND(ISNUMBER(E31),ISNUMBER(E28)),IFERROR(E31/E28,""),"") | F33: =IF(AND(ISNUMBER(F31),ISNUMBER(F28)),IFERROR(F31/F28,""),"") | G33: =IF(AND(ISNUMBER(G31),ISNUMBER(G28)),IFERROR(G31/G28,""),"") | H33: =IF(AND(ISNUMBER(H31),ISNUMBER(H28)),IFERROR(H31/H28,""),"") | I33: =IF(AND(ISNUMBER(I31),ISNUMBER(I28)),IFERROR(I31/I28,""),"") | J33: =IF(AND(ISNUMBER(J31),ISNUMBER(J28)),IFERROR(J31/J28,""),"") | ... BX33: =IF(AND(ISNUMBER(BX31),ISNUMBER(BX28)),IFERROR(BX31/BX28,""),"") -> 0.027027027 | BY33: =BY32+$BZ97 -> 0.054835093 | BZ33: =BZ32+$BZ97 -> 0.23982169 | CA33: =IF(AND(ISNUMBER(CA31),ISNUMBER(CA28)),IFERROR(CA31/CA28,""),"") -> 0.066979341 | CB33: =CHOOSE(MATCH($CF$2,{"Bull","Base","Bear"},0),$CO$71,$CP$71,$CQ$71) -> 0.09 | CC33: =CHOOSE(MATCH($CF$2,{"Bull","Base","Bear"},0),$CO$72,$CP$72,$CQ$72) -> 0.14 | CD33: =CHOOSE(MATCH($CF$2,{"Bull","Base","Bear"},0),$CO$73,$CP$73,$CQ$73) -> 0.19 | CE33: =CHOOSE(MATCH($CF$2,{"Bull","Base","Bear"},0),$CO$74,$CP$74,$CQ$74) -> 0.24 | CF33: 2027E+: scenario lever RESI_margin (Homes.com net investment −$100m+ p.a.; Adjusted EBITDA positive 2030 per company). | CH33: =IFERROR(AVERAGE(CA33,CB33,CC33,CD33,CE33),"n/m") -> 0.14539587 | CI33: =IFERROR(AVERAGE(BB33,BG33,BL33,BQ33,BV33),"n/m") -> -0.22659677 | CJ33: =IFERROR(AVERAGE(AC33,AH33,AM33,AR33,AW33,BB33,BG33,BL33,BQ33,BV33),"n/m") -> -0.22659677 | CK33: =IFERROR(AVERAGE(C33,D33,E33,F33,G33,H33,I33,N33,S33,X33,AC33,AH33,AM33,AR33,AW33,BB33,BG33,BL33,BQ33,BV33),"n/m") -> -0.22659677 | CN33: Q3/26 stock-based compensation ($m) | CP33: 34
B34: Memo: Residential Real Estate — EBITDA (segment, as reported) | BM34: -139 | BN34: -113 | BO34: -85 | BP34: -59 | BQ34: -396 | BR34: -104 | BS34: -89 | BT34: -101 | BU34: -16 | BV34: -310 | BW34: -46 | BX34: -5 | CN34: Q3/26 amortization of acquired intangibles ($m) | CP34: 62
CN35: Q3/26 depreciation & other amortization ($m) | CP35: 23
B36: Legacy product lines & geographic segments (as originally reported; memo — not forecast) | CF36: LEGACY DISCLOSURE — product lines 2015–Q3/25 (first disclosed Q1/15 comparatives); North America / International segments 2007–Q3/25 | CN36: Q3/26 interest income, net ($m) | CP36: 2
B37: Memo: CoStar Suite / CoStar (Q1/15–Q3/25) | T37: 86.81 | U37: 88.771 | V37: 91.35 | W37: 93.509 | X37: 360.44 | Y37: 97.634 | Z37: 101.074 | AA37: 103.261 | AB37: 106.487 | AC37: 408.456 | AD37: 109.979 | AE37: 113.794 | AF37: 117.314 | AG37: 122.098 | AH37: 463.185 | AI37: 130.361 | AJ37: 133.812 | AK37: 139.084 | AL37: 141.938 | AM37: 545.195 | AN37: 147.701 | AO37: 152.825 | AP37: 156.013 | AQ37: 161.259 | AR37: 617.798 | AS37: 164.956 | AT37: 165.053 | AU37: 165.988 | AV37: 168.738 | AW37: 664.735 | AX37: 172.184 | AY37: 176.979 | AZ37: 183.265 | BA37: 190.393 | BB37: 722.821 | BC37: 198.649 | BD37: 206.566 | BE37: 212.69 | BF37: 219.075 | BG37: 836.98 | BH37: 225.013 | BI37: 229.169 | BJ37: 233.36 | BK37: 237.7 | BL37: 925.2 | BM37: 250.3 | BN37: 253 | BO37: 256.9 | BP37: 260.3 | BQ37: 1020.5 | BR37: 265.1 | BS37: 270.9 | BT37: 277 | CN37: Q3/26 other expense, net ($m) | CP37: 1
B38: Memo: Information Services (Q1/15–Q3/25) | T38: 18.537 | U38: 18.752 | V38: 19.126 | W38: 19.375 | X38: 75.79 | Y38: 19.425 | Z38: 19.425 | AA38: 19.486 | AB38: 18.842 | AC38: 77.178 | AD38: 18.336 | AE38: 18.312 | AF38: 18.716 | AG38: 17.254 | AH38: 72.618 | AI38: 15.06 | AJ38: 15.681 | AK38: 17.535 | AL38: 19.199 | AM38: 67.624 | AN38: 18.85 | AO38: 20.777 | AP38: 19.471 | AQ38: 29.348 | AR38: 88.446 | AS38: 32.382 | AT38: 30.536 | AU38: 33.174 | AV38: 33.978 | AW38: 130.07 | AX38: 34.696 | AY38: 35.157 | AZ38: 35.926 | BA38: 35.876 | BB38: 141.655 | BC38: 37.215 | BD38: 38.502 | BE38: 41.013 | BF38: 40.652 | BG38: 157.382 | BH38: 41.629 | BI38: 41.921 | BJ38: 44.636 | BK38: 42.7 | BL38: 170.9 | BM38: 33 | BN38: 33.4 | BO38: 33 | BP38: 36.5 | BQ38: 135.9 | BR38: 39.8 | BS38: 39.3 | BT38: 41.3 | CN38: Q3/26 acquisition & integration costs ($m) | CP38: 2
B39: Memo: Multifamily — Apartments.com network (Q1/15–Q3/25) | T39: 26.133 | U39: 34.742 | V39: 49.312 | W39: 50.443 | X39: 160.63 | Y39: 52.238 | Z39: 54.86 | AA39: 57.654 | AB39: 60.083 | AC39: 224.835 | AD39: 63.991 | AE39: 68.076 | AF39: 72.257 | AG39: 75.531 | AH39: 279.855 | AI39: 87.683 | AJ39: 104.793 | AK39: 104.778 | AL39: 108.541 | AM39: 405.795 | AN39: 114.268 | AO39: 120.488 | AP39: 125.707 | AQ39: 130.168 | AR39: 490.631 | AS39: 137.46 | AT39: 145.541 | AU39: 155.184 | AV39: 160.37 | AW39: 598.555 | AX39: 166.147 | AY39: 171.357 | AZ39: 171.125 | BA39: 170.051 | BB39: 678.68 | BC39: 175.477 | BD39: 182.359 | BE39: 189.536 | BF39: 198.016 | BG39: 745.388 | BH39: 210.697 | BI39: 224.291 | BJ39: 235.343 | BK39: 243.8 | BL39: 914.2 | BM39: 254.8 | BN39: 264.2 | BO39: 271.8 | BP39: 276.5 | BQ39: 1067.3 | BR39: 282.5 | BS39: 292.3 | BT39: 303 | CH39: =IFERROR((CE39/BV39)^(1/5)-1,"n/m") -> n/m | CI39: =IFERROR((BV39/AW39)^(1/5)-1,"n/m") -> -1 | CJ39: =IFERROR((BV39/X39)^(1/10)-1,"n/m") -> -1 | CK39: =IFERROR((BV39/C39)^(1/19)-1,"n/m") -> n/m | CN39: 2H/26 share repurchases ($m) | CO39: 413 | CP39: 113 | CQ39: 0 | CR39: 2026 plan $700m under the $1.5bn authorization (1H/26: $587m). Bull = $1.0bn for the year.
B40: Multifamily y/y % | D40: =IF(AND(ISNUMBER(D39),ISNUMBER(C39)),IFERROR(D39/C39-1,""),"") | E40: =IF(AND(ISNUMBER(E39),ISNUMBER(D39)),IFERROR(E39/D39-1,""),"") | F40: =IF(AND(ISNUMBER(F39),ISNUMBER(E39)),IFERROR(F39/E39-1,""),"") | G40: =IF(AND(ISNUMBER(G39),ISNUMBER(F39)),IFERROR(G39/F39-1,""),"") | H40: =IF(AND(ISNUMBER(H39),ISNUMBER(G39)),IFERROR(H39/G39-1,""),"") | I40: =IF(AND(ISNUMBER(I39),ISNUMBER(H39)),IFERROR(I39/H39-1,""),"") | N40: =IF(AND(ISNUMBER(N39),ISNUMBER(I39)),IFERROR(N39/I39-1,""),"") | O40: =IF(AND(ISNUMBER(O39),ISNUMBER(J39)),IFERROR(O39/J39-1,""),"") | P40: =IF(AND(ISNUMBER(P39),ISNUMBER(K39)),IFERROR(P39/K39-1,""),"") | Q40: =IF(AND(ISNUMBER(Q39),ISNUMBER(L39)),IFERROR(Q39/L39-1,""),"") | R40: =IF(AND(ISNUMBER(R39),ISNUMBER(M39)),IFERROR(R39/M39-1,""),"") | S40: =IF(AND(ISNUMBER(S39),ISNUMBER(N39)),IFERROR(S39/N39-1,""),"") | T40: =IF(AND(ISNUMBER(T39),ISNUMBER(O39)),IFERROR(T39/O39-1,""),"") | U40: =IF(AND(ISNUMBER(U39),ISNUMBER(P39)),IFERROR(U39/P39-1,""),"") | ... BX40: =IF(AND(ISNUMBER(BX39),ISNUMBER(BS39)),IFERROR(BX39/BS39-1,""),"") | CN40: Minimum net debt / Adjusted EBITDA (x) — buyback floor 2027E+ | CO40: 1 | CP40: 0.5 | CQ40: 0 | CR40: CoStar has historically run net cash; Base lets net debt drift to 0.5x via buybacks.
B41: Memo: Commercial property & land (LoopNet, Land.com, Ten-X, BizBuySell; Q1/15–Q2/21) | T41: 27.54 | U41: 28.392 | V41: 29.29 | W41: 29.682 | X41: 114.904 | Y41: 30.442 | Z41: 31.51 | AA41: 32.31 | AB41: 32.899 | AC41: 127.161 | AD41: 34.247 | AE41: 36.971 | AF41: 39.246 | AG41: 39.108 | AH41: 149.572 | AI41: 40.614 | AJ41: 42.732 | AK41: 44.128 | AL41: 45.893 | AM41: 173.218 | AN41: 47.606 | AO41: 49.67 | AP41: 51.617 | AQ41: 53.951 | AR41: 202.844 | AS41: 57.049 | AT41: 56.029 | AU41: 71.274 | AV41: 81.307 | AW41: 265.659 | AX41: 84.67 | AY41: 96.84 | CN41: Medium-term targets (7-Jan-26 release) — memo, not forced
B42: Memo: LoopNet (Q1/20–Q3/25) | AS42: 43.2 | AT42: 43.32 | AU42: 45.084 | AV42: 48.201 | AW42: 179.805 | AX42: 49.23 | AY42: 51.095 | AZ42: 52.527 | BA42: 54.659 | BB42: 207.511 | BC42: 54.447 | BD42: 56.297 | BE42: 58.901 | BF42: 61.296 | BG42: 230.941 | BH42: 63.237 | BI42: 65.563 | BJ42: 67.481 | BK42: 68.5 | BL42: 264.8 | BM42: 69.1 | BN42: 69.8 | BO42: 70.9 | BP42: 71.9 | BQ42: 281.7 | BR42: 72.8 | BS42: 75.7 | BT42: 79.3 | CN42: Revenue CAGR 2025–28 (~15%) | CP42: 0.15 | CR42: Model shows the gap in the Group block.
B43: Memo: Residential — Homes.com, Homesnap, OnTheMarket (Q1/20–Q3/25) | AS43: 0 | AT43: 0 | AU43: 0 | AV43: 0 | AW43: 0 | AX43: 11.105 | AY43: 18.087 | AZ43: 24.747 | BA43: 20.644 | BB43: 74.583 | BC43: 18.06 | BD43: 20.154 | BE43: 19.351 | BF43: 16.182 | BG43: 73.747 | BH43: 13.153 | BI43: 12.708 | BJ43: 10.293 | BK43: 10 | BL43: 46.1 | BM43: 18.6 | BN43: 26.2 | BO43: 27.7 | BP43: 28.1 | BQ43: 100.6 | BR43: 27.2 | BS43: 28.4 | BT43: 54.9 | CN43: 2028 Adjusted EBITDA ($m) | CP43: 1250 | CR43: Homes.com: revenue > expenses exiting 2029; positive Adjusted EBITDA in 2030.
B44: Memo: Other Marketplaces / Other revenues (Ten-X, Land.com, BizBuySell; 2025 incl. Matterport & Domain) | AS44: 13.849 | AT44: 12.709 | AU44: 26.19 | AV44: 33.106 | AW44: 85.854 | AX44: 24.335 | AY44: 27.658 | AZ44: 31.729 | BA44: 35.163 | BB44: 118.885 | BC44: 31.977 | BD44: 32.43 | BE44: 35.43 | BF44: 38.124 | BG44: 137.961 | BH44: 30.637 | BI44: 32.254 | BJ44: 33.556 | BK44: 37.4 | BL44: 133.8 | BM44: 30.6 | BN44: 31.2 | BO44: 32.3 | BP44: 36.1 | BQ44: 130.2 | BR44: 44.8 | BS44: 74.7 | BT44: 78.1
B45: Check: Σ legacy product lines vs consolidated revenues (should be 0) | C45: =IF(ISNUMBER(C37),ROUND(N(C37)+N(C38)+N(C39)+IF(ISNUMBER(C42),N(C42)+N(C43)+N(C44),N(C41))-C121,1),"") | D45: =IF(ISNUMBER(D37),ROUND(N(D37)+N(D38)+N(D39)+IF(ISNUMBER(D42),N(D42)+N(D43)+N(D44),N(D41))-D121,1),"") | E45: =IF(ISNUMBER(E37),ROUND(N(E37)+N(E38)+N(E39)+IF(ISNUMBER(E42),N(E42)+N(E43)+N(E44),N(E41))-E121,1),"") | F45: =IF(ISNUMBER(F37),ROUND(N(F37)+N(F38)+N(F39)+IF(ISNUMBER(F42),N(F42)+N(F43)+N(F44),N(F41))-F121,1),"") | G45: =IF(ISNUMBER(G37),ROUND(N(G37)+N(G38)+N(G39)+IF(ISNUMBER(G42),N(G42)+N(G43)+N(G44),N(G41))-G121,1),"") | H45: =IF(ISNUMBER(H37),ROUND(N(H37)+N(H38)+N(H39)+IF(ISNUMBER(H42),N(H42)+N(H43)+N(H44),N(H41))-H121,1),"") | I45: =IF(ISNUMBER(I37),ROUND(N(I37)+N(I38)+N(I39)+IF(ISNUMBER(I42),N(I42)+N(I43)+N(I44),N(I41))-I121,1),"") | J45: =IF(ISNUMBER(J37),ROUND(N(J37)+N(J38)+N(J39)+IF(ISNUMBER(J42),N(J42)+N(J43)+N(J44),N(J41))-J121,1),"") | ... BX45: =IF(ISNUMBER(BX37),ROUND(N(BX37)+N(BX38)+N(BX39)+IF(ISNUMBER(BX42),N(BX42)+N(BX43)+N(BX44),N(BX41))-BX121,1),"") | CN45: COSTAR_growth (CoStar revenues y/y) | CO45: 0.02 | CP45: Δ → | CQ45: -0.02 | CR45: CoStar (incl. Information Services) grew 8.6% y/y in 1H/26 (61 straight quarters of double-digit group growth). AI products (Rent Benchmark), France entry.
B46: Memo: North America (United States to Q1/14) — revenues (external) | D46: 170.298 | E46: 190.075 | F46: 191.556 | G46: 208.463 | H46: 233.381 | I46: 330.805 | J46: 99.296 | K46: 104.236 | L46: 107.23 | M46: 110.055 | N46: 420.817 | O46: 113.326 | P46: 141.849 | Q46: 146.899 | R46: 150.067 | S46: 552.141 | T46: 153.017 | U46: 164.486 | V46: 182.556 | W46: 186.514 | X46: 686.573 | Y46: 193.261 | Z46: 199.859 | AA46: 205.637 | AB46: 210.735 | AC46: 809.492 | AD46: 219.341 | AE46: 229.826 | AF46: 239.537 | AG46: 245.76 | AH46: 934.464 | AI46: 264.795 | AJ46: 288.288 | AK46: 296.916 | AL46: 307.302 | AM46: 1157.301 | AN46: 319.237 | AO46: 334.562 | AP46: 343.784 | AQ46: 362.484 | AR46: 1360.067 | AS46: 377.447 | AT46: 384.362 | AU46: 410.904 | AV46: 429.389 | AW46: 1602.102 | AX46: 441.763 | AY46: 463.774 | AZ46: 482.952 | BA46: 489.146 | BB46: 1877.635 | BC46: 497.577 | BD46: 517.437 | BE46: 537.624 | BF46: 553.35 | BG46: 2105.988 | BH46: 563.579 | BI46: 584.307 | BJ46: 602.744 | BK46: 615.1 | BL46: 2365.7 | BM46: 623.3 | BN46: 643.8 | BO46: 658.2 | BP46: 674.5 | BQ46: 2599.8 | BR46: 697.4 | BS46: 744 | BT46: 769.1 | CN46: 2027E | CO46: =CP46+$CO$45 -> 0.11 | CP46: 0.09 | CQ46: =CP46+$CQ$45 -> 0.07
B47: Memo: International — revenues (external) | D47: 22.507 | E47: 22.353 | F47: 18.103 | G47: 17.797 | H47: 18.357 | I47: 19.131 | J47: 4.737 | K47: 4.763 | L47: 5.071 | M47: 5.555 | N47: 20.126 | O47: 5.75 | P47: 5.859 | Q47: 6.157 | R47: 6.029 | S47: 23.795 | T47: 6.003 | U47: 6.171 | V47: 6.522 | W47: 6.495 | X47: 25.191 | Y47: 6.478 | Z47: 7.01 | AA47: 7.074 | AB47: 7.576 | AC47: 28.138 | AD47: 7.212 | AE47: 7.327 | AF47: 7.996 | AG47: 8.231 | AH47: 30.766 | AI47: 8.923 | AJ47: 8.73 | AK47: 8.609 | AL47: 8.269 | AM47: 34.531 | AN47: 9.188 | AO47: 9.198 | AP47: 9.024 | AQ47: 12.242 | AR47: 39.652 | AS47: 14.4 | AT47: 12.797 | AU47: 14.716 | AV47: 15.004 | AW47: 56.917 | AX47: 15.934 | AY47: 16.559 | AZ47: 16.367 | BA47: 17.64 | BB47: 66.5 | BC47: 18.248 | BD47: 18.871 | BE47: 19.297 | BF47: 19.995 | BG47: 76.411 | BH47: 20.787 | BI47: 21.599 | BJ47: 21.925 | BK47: 25 | BL47: 89.3 | BM47: 33.1 | BN47: 34 | BO47: 34.4 | BP47: 34.9 | BQ47: 136.4 | BR47: 34.8 | BS47: 37.3 | BT47: 64.5 | CN47: 2028E | CO47: =CP47+$CO$45 -> 0.11 | CP47: 0.09 | CQ47: =CP47+$CQ$45 -> 0.07
B48: Memo: North America — EBITDA | D48: 32.872 | E48: 58.813 | F48: 47.697 | G48: 39.607 | H48: 38.099 | I48: 70.199 | J48: 9.286 | K48: 26.468 | L48: 30.855 | M48: 30.739 | N48: 97.348 | O48: 26.368 | P48: 37.09 | Q48: 42.929 | R48: 42.526 | S48: 148.913 | T48: 13.677 | U48: -1.854 | V48: 20.993 | W48: 54.276 | X48: 87.092 | Y48: 46.864 | Z48: 45.127 | AA48: 56.305 | AB48: 62.605 | AC48: 210.901 | AD48: 54.433 | AE48: 43.364 | AF48: 72.267 | AG48: 66.842 | AH48: 236.906 | AI48: 71.055 | AJ48: 64.762 | AK48: 94.088 | AL48: 128.131 | AM48: 358.036 | AN48: 115.268 | AO48: 95.001 | AP48: 115.973 | AQ48: 125.457 | AR48: 451.699 | AS48: 102.413 | AT48: 112.292 | AU48: 107.906 | AV48: 88.241 | AW48: 410.852 | AX48: 135.858 | AY48: 130.176 | AZ48: 119.823 | BA48: 171.268 | BB48: 557.125 | BC48: 155.962 | BD48: 138.527 | BE48: 127.965 | BF48: 154.788 | BG48: 577.242 | BH48: 96.656 | BI48: 104.614 | BJ48: 88.91 | BK48: 112.8 | BL48: 402.9 | BM48: 3.2 | BN48: 30.8 | BO48: 63.5 | BP48: 84.1 | BQ48: 181.5 | BR48: 9.1 | BS48: 43.3 | BT48: 33.2 | CN48: 2029E | CO48: =CP48+$CO$45 -> 0.105 | CP48: 0.085 | CQ48: =CP48+$CQ$45 -> 0.065
B49: Memo: International — EBITDA | D49: 1.127 | E49: -2.224 | F49: -1.186 | G49: -3.183 | H49: -3.476 | I49: -10.007 | J49: -1.718 | K49: -1.136 | L49: -1.063 | M49: 0.781 | N49: -3.136 | O49: 0.624 | P49: 0.489 | Q49: 0.763 | R49: 0.461 | S49: 2.337 | T49: 0.629 | U49: 0.399 | V49: 1.096 | W49: 0.771 | X49: 2.895 | Y49: 0.958 | Z49: 0.432 | AA49: 1.371 | AB49: 1.408 | AC49: 4.169 | AD49: 0.527 | AE49: 0.379 | AF49: 0.365 | AG49: -0.718 | AH49: 0.553 | AI49: -0.627 | AJ49: -0.404 | AK49: -2.967 | AL49: -2.731 | AM49: -6.729 | AN49: -2.117 | AO49: -1.447 | AP49: -2.882 | AQ49: -0.541 | AR49: -6.987 | AS49: -2.293 | AT49: -2.994 | AU49: 0.579 | AV49: 0.002 | AW49: -4.706 | AX49: -0.322 | AY49: 3.156 | AZ49: 2.849 | BA49: 2.173 | BB49: 7.856 | BC49: 2.468 | BD49: 1.481 | BE49: 1.184 | BF49: 0.28 | BG49: 5.413 | BH49: 1.192 | BI49: 0.595 | BJ49: -0.191 | BK49: -14.8 | BL49: -13.2 | BM49: -15.9 | BN49: -18.7 | BO49: -12.7 | BP49: -11.2 | BQ49: -58.5 | BR49: -9.9 | BS49: -14.7 | BT49: -20.5 | CN49: 2030E | CO49: =CP49+$CO$45 -> 0.1 | CP49: 0.08 | CQ49: =CP49+$CQ$45 -> 0.06
B50: Check: Σ geographic segment EBITDA vs consolidated EBITDA (should be 0; ±0.1 rounding) | C50: =IF(AND(ISNUMBER(C48),ISNUMBER(C49)),IF(ABS(C48+C49-C159)<=0.15,0,ROUND(C48+C49-C159,1)),"") | D50: =IF(AND(ISNUMBER(D48),ISNUMBER(D49)),IF(ABS(D48+D49-D159)<=0.15,0,ROUND(D48+D49-D159,1)),"") -> 0 | E50: =IF(AND(ISNUMBER(E48),ISNUMBER(E49)),IF(ABS(E48+E49-E159)<=0.15,0,ROUND(E48+E49-E159,1)),"") -> 0 | F50: =IF(AND(ISNUMBER(F48),ISNUMBER(F49)),IF(ABS(F48+F49-F159)<=0.15,0,ROUND(F48+F49-F159,1)),"") -> 0 | G50: =IF(AND(ISNUMBER(G48),ISNUMBER(G49)),IF(ABS(G48+G49-G159)<=0.15,0,ROUND(G48+G49-G159,1)),"") -> 0 | H50: =IF(AND(ISNUMBER(H48),ISNUMBER(H49)),IF(ABS(H48+H49-H159)<=0.15,0,ROUND(H48+H49-H159,1)),"") -> 0 | I50: =IF(AND(ISNUMBER(I48),ISNUMBER(I49)),IF(ABS(I48+I49-I159)<=0.15,0,ROUND(I48+I49-I159,1)),"") -> 0 | J50: =IF(AND(ISNUMBER(J48),ISNUMBER(J49)),IF(ABS(J48+J49-J159)<=0.15,0,ROUND(J48+J49-J159,1)),"") -> 0 | ... BX50: =IF(AND(ISNUMBER(BX48),ISNUMBER(BX49)),IF(ABS(BX48+BX49-BX159)<=0.15,0,ROUND(BX48+BX49-BX159,1)),"") | CN50: LOOPNET_growth (LoopNet revenues y/y) | CO50: 0.03 | CP50: Δ → | CQ50: -0.03 | CR50: 1H/26 +15% y/y; marketplace ad pricing + diamond/platinum listings.
CN51: 2027E | CO51: =CP51+$CO$50 -> 0.15 | CP51: 0.12 | CQ51: =CP51+$CQ$50 -> 0.09
B52: Zonda — new-home data, analytics & marketplaces (NewHomeSource, Livabl); acquired 21-Aug-2026 for $800m cash; Residential segment | CF52: ZONDA — modelling logic (closed 21-Aug-2026; NOT in company FY26 guidance) | CN52: 2028E | CO52: =CP52+$CO$50 -> 0.14 | CP52: 0.11 | CQ52: =CP52+$CQ$50 -> 0.08
B53: Memo: Zonda standalone revenues (pre-acquisition; not consolidated) | BV53: 170 | CF53: Closing release (8-K Ex. 99.1, 21-Aug-2026): ~$170m revenue in 2025 at a 23% Adjusted EBITDA margin; 3,000+ customers; 104% net retention. | CN53: 2029E | CO53: =CP53+$CO$50 -> 0.13 | CP53: 0.1 | CQ53: =CP53+$CQ$50 -> 0.07
B54: Memo: Zonda standalone Adjusted EBITDA margin (FY2025) | BV54: 0.23 | CN54: 2030E | CO54: =CP54+$CO$50 -> 0.12 | CP54: 0.09 | CQ54: =CP54+$CQ$50 -> 0.06
B55: Days consolidated in period (closing 21-Aug-2026) | BY55: 41 | BZ55: 92 | CA55: =SUM(BW55,BX55,BY55,BZ55) -> 133 | CB55: =DATE(2027,12,31)-DATE(2027,1,1)+1 -> 365 | CC55: =DATE(2028,12,31)-DATE(2028,1,1)+1 -> 366 | CD55: =DATE(2029,12,31)-DATE(2029,1,1)+1 -> 365 | CE55: =DATE(2030,12,31)-DATE(2030,1,1)+1 -> 365 | CF55: 41 days in Q3/26 (21-Aug → 30-Sep), full Q4/26. | CN55: OCRE_growth (Other Commercial RE revenues y/y) | CO55: 0.03 | CP55: Δ → | CQ55: -0.03 | CR55: Matterport, STR, Ten-X, BizBuySell, Realla.
B56: Revenue growth y/y % | CA56: 0.08 | CB56: =CHOOSE(MATCH($CF$2,{"Bull","Base","Bear"},0),$CO$76,$CP$76,$CQ$76) -> 0.08 | CC56: =CHOOSE(MATCH($CF$2,{"Bull","Base","Bear"},0),$CO$77,$CP$77,$CQ$77) -> 0.08 | CD56: =CHOOSE(MATCH($CF$2,{"Bull","Base","Bear"},0),$CO$78,$CP$78,$CQ$78) -> 0.08 | CE56: =CHOOSE(MATCH($CF$2,{"Bull","Base","Bear"},0),$CO$79,$CP$79,$CQ$79) -> 0.08 | CF56: 2026E run-rate = FY2025 × (1 + 8%) (input). 2027E+: scenario lever ZONDA_growth. | CN56: 2027E | CO56: =CP56+$CO$55 -> 0.08 | CP56: 0.05 | CQ56: =CP56+$CQ$55 -> 0.02
B57: Annual revenue run-rate (standalone basis) | CA57: =BV53*(1+CA56) -> 183.6 | CB57: =CA57*(1+CB56) -> 198.288 | CC57: =CB57*(1+CC56) -> 214.15104 | CD57: =CC57*(1+CD56) -> 231.28312 | CE57: =CD57*(1+CE56) -> 249.78577 | CN57: 2028E | CO57: =CP57+$CO$55 -> 0.08 | CP57: 0.05 | CQ57: =CP57+$CQ$55 -> 0.02
B58: Revenues (consolidated from closing) | BY58: =$CA57*BY55/365 -> 20.623562 | BZ58: =$CA57*BZ55/365 -> 46.27726 | CA58: =SUM(BW58,BX58,BY58,BZ58) -> 66.900822 | CB58: =CB57 -> 198.288 | CC58: =CC57 -> 214.15104 | CD58: =CD57 -> 231.28312 | CE58: =CE57 -> 249.78577 | CN58: 2029E | CO58: =CP58+$CO$55 -> 0.08 | CP58: 0.05 | CQ58: =CP58+$CQ$55 -> 0.02
B59: Adjusted EBITDA margin % | BY59: =$CA59 -> 0.23 | BZ59: =$CA59 -> 0.23 | CA59: =BV54 -> 0.23 | CB59: =CHOOSE(MATCH($CF$2,{"Bull","Base","Bear"},0),$CO$81,$CP$81,$CQ$81) -> 0.25 | CC59: =CHOOSE(MATCH($CF$2,{"Bull","Base","Bear"},0),$CO$82,$CP$82,$CQ$82) -> 0.27 | CD59: =CHOOSE(MATCH($CF$2,{"Bull","Base","Bear"},0),$CO$83,$CP$83,$CQ$83) -> 0.29 | CE59: =CHOOSE(MATCH($CF$2,{"Bull","Base","Bear"},0),$CO$84,$CP$84,$CQ$84) -> 0.3 | CF59: 2026E = FY2025 standalone margin (23%). 2027E+: scenario lever ZONDA_margin (cost & cross-sell synergies). | CN59: 2030E | CO59: =CP59+$CO$55 -> 0.08 | CP59: 0.05 | CQ59: =CP59+$CQ$55 -> 0.02
B60: Adjusted EBITDA contribution | BY60: =BY58*BY59 -> 4.7434192 | BZ60: =BZ58*BZ59 -> 10.64377 | CA60: =SUM(BW60,BX60,BY60,BZ60) -> 15.387189 | CB60: =CB58*CB59 -> 49.572 | CC60: =CC58*CC59 -> 57.820781 | CD60: =CD58*CD59 -> 67.072106 | CE60: =CE58*CE59 -> 74.935732 | CN60: RESI_growth (Residential RE revenues y/y, ex-Zonda) | CO60: 0.03 | CP60: Δ → | CQ60: -0.03 | CR60: Apartments.com (~70% of segment), Homes.com (31k+ agent subscribers, ~$100m run-rate), Domain, OnTheMarket, Land.com.
B61: Standalone depreciation & other amortization % of revenues | CA61: 0.02 | CF61: Estimate (capitalised software, equipment); no standalone financials filed. | CN61: 2027E | CO61: =CP61+$CO$60 -> 0.15 | CP61: 0.12 | CQ61: =CP61+$CQ$60 -> 0.09
B62: Standalone depreciation & other amortization (within D&A) | BY62: =BY58*$CA61 -> 0.41247123 | BZ62: =BZ58*$CA61 -> 0.92554521 | CA62: =SUM(BW62,BX62,BY62,BZ62) -> 1.3380164 | CB62: =CB58*$CA61 -> 3.96576 | CC62: =CC58*$CA61 -> 4.2830208 | CD62: =CD58*$CA61 -> 4.6256625 | CE62: =CE58*$CA61 -> 4.9957155 | CN62: 2028E | CO62: =CP62+$CO$60 -> 0.14 | CP62: 0.11 | CQ62: =CP62+$CQ$60 -> 0.08
B63: Amortization of acquired intangibles (estimated purchase-price allocation) | BY63: =$CA323/$CA324*BY55/365 -> 3.5945205 | BZ63: =$CA323/$CA324*BZ55/365 -> 8.0657534 | CA63: =SUM(BW63,BX63,BY63,BZ63) -> 11.660274 | CB63: =$CA323/$CA324 -> 32 | CC63: =$CA323/$CA324 -> 32 | CD63: =$CA323/$CA324 -> 32 | CE63: =$CA323/$CA324 -> 32 | CF63: $320m acquired intangibles (40% of consideration; estimate) over 10 years straight-line → $32m p.a. Replace with the PPA in the Q3-26 10-Q. | CN63: 2029E | CO63: =CP63+$CO$60 -> 0.13 | CP63: 0.1 | CQ63: =CP63+$CQ$60 -> 0.07
B64: Transaction & integration costs (added back in Adjusted EBITDA / Adjusted Net Income) | BY64: 8 | BZ64: 2 | CA64: =SUM(BW64,BX64,BY64,BZ64) -> 10 | CB64: 5 | CC64: 0 | CD64: 0 | CE64: 0 | CF64: Estimate: advisory (BofA, Latham) & closing costs $8m in Q3/26, integration $2m Q4/26 and $5m in 2027. | CN64: 2030E | CO64: =CP64+$CO$60 -> 0.12 | CP64: 0.09 | CQ64: =CP64+$CQ$60 -> 0.06
CN65: CRE_margin (Commercial RE Adjusted EBITDA margin) | CO65: 0.02 | CP65: Δ → | CQ65: -0.02 | CR65: FY26 guide ~35%; FY25 37.2%. Operating leverage on a largely fixed research/data cost base.
B66: Future acquisitions (M&A lever — bolt-ons, unallocated; deals closed from 2027E) | CF66: M&A LEVER — acquired revenues = spend ÷ EV/sales; mid-year convention | CN66: 2027E | CO66: =CP66+$CO$65 -> 0.385 | CP66: 0.365 | CQ66: =CP66+$CQ$65 -> 0.345
B67: Acquisition spend (USDm, scenario) | CA67: 0 | CB67: =CHOOSE(MATCH($CF$2,{"Bull","Base","Bear"},0),$CO$86,$CP$86,$CQ$86) -> 0 | CC67: =CHOOSE(MATCH($CF$2,{"Bull","Base","Bear"},0),$CO$87,$CP$87,$CQ$87) -> 0 | CD67: =CHOOSE(MATCH($CF$2,{"Bull","Base","Bear"},0),$CO$88,$CP$88,$CQ$88) -> 0 | CE67: =CHOOSE(MATCH($CF$2,{"Bull","Base","Bear"},0),$CO$89,$CP$89,$CQ$89) -> 0 | CF67: Scenario lever M&A_spend. CoStar deployed $0.1–2.3bn p.a. on acquisitions in 2018–25 (ForRent, STR, Ten-X, Homes.com, Matterport, Domain) plus Zonda ($0.8bn) in 2026. | CN67: 2028E | CO67: =CP67+$CO$65 -> 0.395 | CP67: 0.375 | CQ67: =CP67+$CQ$65 -> 0.355
B68: Purchase multiple — EV / sales (x) | CB68: 6 | CC68: 6 | CD68: 6 | CE68: 6 | CN68: 2029E | CO68: =CP68+$CO$65 -> 0.405 | CP68: 0.385 | CQ68: =CP68+$CQ$65 -> 0.365
B69: Annualised revenues acquired in the year | CA69: 0 | CB69: =IFERROR(CB67/CB68,0) -> 0 | CC69: =IFERROR(CC67/CC68,0) -> 0 | CD69: =IFERROR(CD67/CD68,0) -> 0 | CE69: =IFERROR(CE67/CE68,0) -> 0 | CN69: 2030E | CO69: =CP69+$CO$65 -> 0.415 | CP69: 0.395 | CQ69: =CP69+$CQ$65 -> 0.375
B70: Growth of acquired businesses after acquisition % | CB70: 0.08 | CC70: 0.08 | CD70: 0.08 | CE70: 0.08 | CN70: RESI_margin (Residential RE Adjusted EBITDA margin, ex-Zonda) | CO70: 0.04 | CP70: Δ → | CQ70: -0.04 | CR70: FY26 guide ~6.7%; Homes.com net investment to fall by $100m+ p.a. to 2030 (7-Jan-26). Apartments.com margins ~40%+.
B71: Run-rate revenues of businesses acquired (year end) | CA71: 0 | CB71: =CA71*(1+CB70)+CB69 -> 0 | CC71: =CB71*(1+CC70)+CC69 -> 0 | CD71: =CC71*(1+CD70)+CD69 -> 0 | CE71: =CD71*(1+CE70)+CE69 -> 0 | CN71: 2027E | CO71: =CP71+$CO$70 -> 0.13 | CP71: 0.09 | CQ71: =CP71+$CQ$70 -> 0.05
B72: Revenues from future acquisitions | CA72: 0 | CB72: =CA71*(1+CB70)+0.5*CB69 -> 0 | CC72: =CB71*(1+CC70)+0.5*CC69 -> 0 | CD72: =CC71*(1+CD70)+0.5*CD69 -> 0 | CE72: =CD71*(1+CE70)+0.5*CE69 -> 0 | CF72: Mid-year convention: deals close evenly through the year (half a year of revenues in year 1). | CN72: 2028E | CO72: =CP72+$CO$70 -> 0.18 | CP72: 0.14 | CQ72: =CP72+$CQ$70 -> 0.1
B73: Adjusted EBITDA margin of acquired businesses % | CB73: 0.25 | CC73: 0.25 | CD73: 0.25 | CE73: 0.25 | CN73: 2029E | CO73: =CP73+$CO$70 -> 0.23 | CP73: 0.19 | CQ73: =CP73+$CQ$70 -> 0.15
B74: Adjusted EBITDA from future acquisitions | CA74: 0 | CB74: =CB72*CB73 -> 0 | CC74: =CC72*CC73 -> 0 | CD74: =CD72*CD73 -> 0 | CE74: =CE72*CE73 -> 0 | CN74: 2030E | CO74: =CP74+$CO$70 -> 0.28 | CP74: 0.24 | CQ74: =CP74+$CQ$70 -> 0.2
B75: Acquired intangibles % of spend (balance = goodwill) | CB75: 0.4 | CC75: 0.4 | CD75: 0.4 | CE75: 0.4 | CF75: Asset-light information / marketplace targets: consideration mostly goodwill & intangibles. | CN75: ZONDA_growth (Zonda revenues y/y) | CO75: 0.03 | CP75: Δ → | CQ75: -0.03 | CR75: Majority subscription; 104% net customer retention (deal release).
B76: Intangible amortization life (years) | CB76: 10 | CC76: 10 | CD76: 10 | CE76: 10 | CN76: 2027E | CO76: =CP76+$CO$75 -> 0.11 | CP76: 0.08 | CQ76: =CP76+$CQ$75 -> 0.05
B77: Acquired intangibles (gross) in the year | CA77: 0 | CB77: =CB67*CB75 -> 0 | CC77: =CC67*CC75 -> 0 | CD77: =CD67*CD75 -> 0 | CE77: =CE67*CE75 -> 0 | CN77: 2028E | CO77: =CP77+$CO$75 -> 0.11 | CP77: 0.08 | CQ77: =CP77+$CQ$75 -> 0.05
B78: Cumulative acquired intangibles (gross) | CA78: 0 | CB78: =CA78+CB77 -> 0 | CC78: =CB78+CC77 -> 0 | CD78: =CC78+CD77 -> 0 | CE78: =CD78+CE77 -> 0 | CN78: 2029E | CO78: =CP78+$CO$75 -> 0.11 | CP78: 0.08 | CQ78: =CP78+$CQ$75 -> 0.05
B79: Amortization of future-acquisition intangibles | CA79: 0 | CB79: =IFERROR(CA78/CB76+0.5*CB77/CB76,0) -> 0 | CC79: =IFERROR(CB78/CC76+0.5*CC77/CC76,0) -> 0 | CD79: =IFERROR(CC78/CD76+0.5*CD77/CD76,0) -> 0 | CE79: =IFERROR(CD78/CE76+0.5*CE77/CE76,0) -> 0 | CN79: 2030E | CO79: =CP79+$CO$75 -> 0.11 | CP79: 0.08 | CQ79: =CP79+$CQ$75 -> 0.05
B80: Goodwill from future acquisitions | CA80: 0 | CB80: =CB67-CB77 -> 0 | CC80: =CC67-CC77 -> 0 | CD80: =CD67-CD77 -> 0 | CE80: =CE67-CE77 -> 0 | CN80: ZONDA_margin (Zonda Adjusted EBITDA margin) | CO80: 0.02 | CP80: Δ → | CQ80: -0.02 | CR80: FY2025 ~23% (closing release 21-Aug-26); cross-sell / cost synergies.
CN81: 2027E | CO81: =CP81+$CO$80 -> 0.27 | CP81: 0.25 | CQ81: =CP81+$CQ$80 -> 0.23
B82: Group Total — revenues & Adjusted EBITDA (segment build) → outlook calibration | CF82: GROUP TOTAL (CONSOLIDATED) — modelling logic | CN82: 2028E | CO82: =CP82+$CO$80 -> 0.29 | CP82: 0.27 | CQ82: =CP82+$CQ$80 -> 0.25
B83: Revenues (segment build) | C83: =IF(ISNUMBER(C20),C20+C28,"") | D83: =IF(ISNUMBER(D20),D20+D28,"") | E83: =IF(ISNUMBER(E20),E20+E28,"") | F83: =IF(ISNUMBER(F20),F20+F28,"") | G83: =IF(ISNUMBER(G20),G20+G28,"") | H83: =IF(ISNUMBER(H20),H20+H28,"") | I83: =IF(ISNUMBER(I20),I20+I28,"") | J83: =IF(ISNUMBER(J20),J20+J28,"") | ... BX83: =IF(ISNUMBER(BX20),BX20+BX28,"") -> 925 | BY83: =BY20+BY28+N(BY58)+N(BY72) -> 966.50096 | BZ83: =BZ20+BZ28+N(BZ58)+N(BZ72) -> 1013.3999 | CA83: =CA20+CA28+N(CA58)+N(CA72) -> 3801.9008 | CB83: =CB20+CB28+N(CB58)+N(CB72) -> 4324.8999 | CC83: =CC20+CC28+N(CC58)+N(CC72) -> 4750.8791 | CD83: =CD20+CD28+N(CD58)+N(CD72) -> 5185.0652 | CE83: =CE20+CE28+N(CE58)+N(CE72) -> 5621.4945 | CF83: Σ CoStar + LoopNet + Other CRE + Residential + Zonda + future M&A. Segment detail available from Q1/23 (revenues) and Q1/24 (Adjusted EBITDA). | CH83: =IFERROR((CE83/BV83)^(1/5)-1,"n/m") -> 0.11602494 | CI83: =IFERROR((BV83/AW83)^(1/5)-1,"n/m") -> n/m | CJ83: =IFERROR((BV83/X83)^(1/10)-1,"n/m") -> n/m | CK83: =IFERROR((BV83/C83)^(1/19)-1,"n/m") -> n/m | CN83: 2029E | CO83: =CP83+$CO$80 -> 0.31 | CP83: 0.29 | CQ83: =CP83+$CQ$80 -> 0.27
B84: Adjusted EBITDA (segment build) | C84: =IF(ISNUMBER(C22),C22+C31,"") | D84: =IF(ISNUMBER(D22),D22+D31,"") | E84: =IF(ISNUMBER(E22),E22+E31,"") | F84: =IF(ISNUMBER(F22),F22+F31,"") | G84: =IF(ISNUMBER(G22),G22+G31,"") | H84: =IF(ISNUMBER(H22),H22+H31,"") | I84: =IF(ISNUMBER(I22),I22+I31,"") | J84: =IF(ISNUMBER(J22),J22+J31,"") | ... BX84: =IF(ISNUMBER(BX22),BX22+BX31,"") -> 184 | BY84: =BY22+BY31+N(BY60)+N(BY74) -> 206.77523 | BZ84: =BZ22+BZ31+N(BZ60)+N(BZ74) -> 292.61196 | CA84: =CA22+CA31+N(CA60)+N(CA74) -> 815.38719 | CB84: =CB22+CB31+N(CB60)+N(CB74) -> 1003.9734 | CC84: =CC22+CC31+N(CC60)+N(CC74) -> 1235.6751 | CD84: =CD22+CD31+N(CD60)+N(CD74) -> 1496.5194 | CE84: =CE22+CE31+N(CE60)+N(CE74) -> 1782.8256 | CH84: =IFERROR((CE84/BV84)^(1/5)-1,"n/m") -> 0.32171347 | CI84: =IFERROR((BV84/AW84)^(1/5)-1,"n/m") -> n/m | CJ84: =IFERROR((BV84/X84)^(1/10)-1,"n/m") -> n/m | CK84: =IFERROR((BV84/C84)^(1/19)-1,"n/m") -> n/m | CN84: 2030E | CO84: =CP84+$CO$80 -> 0.32 | CP84: 0.3 | CQ84: =CP84+$CQ$80 -> 0.28
B85: Adjusted EBITDA margin % | C85: =IF(AND(ISNUMBER(C84),ISNUMBER(C83)),IFERROR(C84/C83,""),"") | D85: =IF(AND(ISNUMBER(D84),ISNUMBER(D83)),IFERROR(D84/D83,""),"") | E85: =IF(AND(ISNUMBER(E84),ISNUMBER(E83)),IFERROR(E84/E83,""),"") | F85: =IF(AND(ISNUMBER(F84),ISNUMBER(F83)),IFERROR(F84/F83,""),"") | G85: =IF(AND(ISNUMBER(G84),ISNUMBER(G83)),IFERROR(G84/G83,""),"") | H85: =IF(AND(ISNUMBER(H84),ISNUMBER(H83)),IFERROR(H84/H83,""),"") | I85: =IF(AND(ISNUMBER(I84),ISNUMBER(I83)),IFERROR(I84/I83,""),"") | J85: =IF(AND(ISNUMBER(J84),ISNUMBER(J83)),IFERROR(J84/J83,""),"") | ... CE85: =IF(AND(ISNUMBER(CE84),ISNUMBER(CE83)),IFERROR(CE84/CE83,""),"") -> 0.31714441 | CN85: M&A_spend (future acquisitions, $m p.a.) | CO85: 500 | CP85: Δ → | CQ85: 0 | CR85: Base: no further deals after Zonda (capital returned via buybacks). Bull adds $0.5bn p.a. of bolt-ons.
B86: Check: segment build vs consolidated revenues (should be 0; ±1 rounding — recast segment data in whole $m) | C86: =IF(ISNUMBER(C83),IF(ABS(C83-C121)<=1.5,0,ROUND(C83-C121,1)),"") | D86: =IF(ISNUMBER(D83),IF(ABS(D83-D121)<=1.5,0,ROUND(D83-D121,1)),"") | E86: =IF(ISNUMBER(E83),IF(ABS(E83-E121)<=1.5,0,ROUND(E83-E121,1)),"") | F86: =IF(ISNUMBER(F83),IF(ABS(F83-F121)<=1.5,0,ROUND(F83-F121,1)),"") | G86: =IF(ISNUMBER(G83),IF(ABS(G83-G121)<=1.5,0,ROUND(G83-G121,1)),"") | H86: =IF(ISNUMBER(H83),IF(ABS(H83-H121)<=1.5,0,ROUND(H83-H121,1)),"") | I86: =IF(ISNUMBER(I83),IF(ABS(I83-I121)<=1.5,0,ROUND(I83-I121,1)),"") | J86: =IF(ISNUMBER(J83),IF(ABS(J83-J121)<=1.5,0,ROUND(J83-J121,1)),"") | ... BX86: =IF(ISNUMBER(BX83),IF(ABS(BX83-BX121)<=1.5,0,ROUND(BX83-BX121,1)),"") -> 0 | BY86: =ROUND(BY83-BY121,1) -> 0 | BZ86: =ROUND(BZ83-BZ121,1) -> 0 | CA86: =ROUND(CA83-CA121,1) -> 0 | CB86: =ROUND(CB83-CB121,1) -> 0 | CC86: =ROUND(CC83-CC121,1) -> 0 | CD86: =ROUND(CD83-CD121,1) -> 0 | CE86: =ROUND(CE83-CE121,1) -> 0 | CN86: 2027E | CO86: =CP86+$CO$85 -> 500 | CP86: 0 | CQ86: =CP86+$CQ$85 -> 0
B87: Check: segment build vs Adjusted EBITDA bridge (should be 0; ±1 rounding — recast segment data in whole $m) | C87: =IF(ISNUMBER(C84),IF(ABS(C84-C168)<=1.5,0,ROUND(C84-C168,1)),"") | D87: =IF(ISNUMBER(D84),IF(ABS(D84-D168)<=1.5,0,ROUND(D84-D168,1)),"") | E87: =IF(ISNUMBER(E84),IF(ABS(E84-E168)<=1.5,0,ROUND(E84-E168,1)),"") | F87: =IF(ISNUMBER(F84),IF(ABS(F84-F168)<=1.5,0,ROUND(F84-F168,1)),"") | G87: =IF(ISNUMBER(G84),IF(ABS(G84-G168)<=1.5,0,ROUND(G84-G168,1)),"") | H87: =IF(ISNUMBER(H84),IF(ABS(H84-H168)<=1.5,0,ROUND(H84-H168,1)),"") | I87: =IF(ISNUMBER(I84),IF(ABS(I84-I168)<=1.5,0,ROUND(I84-I168,1)),"") | J87: =IF(ISNUMBER(J84),IF(ABS(J84-J168)<=1.5,0,ROUND(J84-J168,1)),"") | ... BX87: =IF(ISNUMBER(BX84),IF(ABS(BX84-BX168)<=1.5,0,ROUND(BX84-BX168,1)),"") -> 0 | BY87: =ROUND(BY84-BY168,1) -> 0 | BZ87: =ROUND(BZ84-BZ168,1) -> 0 | CA87: =ROUND(CA84-CA168,1) -> 0 | CB87: =ROUND(CB84-CB168,1) -> 0 | CC87: =ROUND(CC84-CC168,1) -> 0 | CD87: =ROUND(CD84-CD168,1) -> 0 | CE87: =ROUND(CE84-CE168,1) -> 0 | CN87: 2028E | CO87: =CP87+$CO$85 -> 500 | CP87: 0 | CQ87: =CP87+$CQ$85 -> 0
B88: Memo: revenues — legacy CoStar (ex-Zonda & future M&A) | C88: =C121 -> 158.889 | D88: =D121 -> 192.805 | E88: =E121 -> 212.428 | F88: =F121 -> 209.659 | G88: =G121 -> 226.26 | H88: =H121 -> 251.738 | I88: =I121 -> 349.936 | J88: =J121 -> 104.033 | ... BX88: =BX121 -> 925 | BY88: =BY83-N(BY58)-N(BY72) -> 945.8774 | BZ88: =BZ83-N(BZ58)-N(BZ72) -> 967.1226 | CA88: =CA83-N(CA58)-N(CA72) -> 3735 | CB88: =CB83-N(CB58)-N(CB72) -> 4126.6119 | CC88: =CC83-N(CC58)-N(CC72) -> 4536.7281 | CD88: =CD83-N(CD58)-N(CD72) -> 4953.782 | CE88: =CE83-N(CE58)-N(CE72) -> 5371.7087 | CN88: 2029E | CO88: =CP88+$CO$85 -> 500 | CP88: 0 | CQ88: =CP88+$CQ$85 -> 0
B89: Memo: FY26 revenue guidance — legacy ex-Zonda (scenario end-point) | CA89: =CHOOSE(MATCH($CF$2,{"Bull","Base","Bear"},0),$CO$12,$CP$12,$CQ$12) -> 3735 | CF89: Q2-26 release (28-Jul-26): $3.715–3.755bn. Drives the revenue-outlook calibration below. | CN89: 2030E | CO89: =CP89+$CO$85 -> 500 | CP89: 0 | CQ89: =CP89+$CQ$85 -> 0
B90: Legacy revenues before revenue calibration (Q3/Q4-26E helper) | BY90: =BX11*(1+BY13)+BX14*(1+BY16)+BX17*(1+BY19)+BX28*(1+BY30) -> 938.31218 | BZ90: =BX11*(1+BZ13)^2+BX14*(1+BZ16)^2+BX17*(1+BZ19)^2+BX28*(1+BZ30)^2 -> 951.99215
B91: Revenue sensitivity to +1.00 of sequential growth (Q3+Q4 helper) | BY91: =3*(BX11+BX14+BX17+BX28) -> 2775
B92: Outlook calibration: Δ sequential growth applied to all legacy product lines (Q3/Q4-26E) | BY92: =(CA89-(BW88+BX88)-BY90-BZ90)/BY91 -> 0.0081786197 | BZ92: =BY92 -> 0.0081786197 | CF92: Solves the uniform growth shift Δ (linearised: +Δ × Q2 base in Q3, +2Δ × Q2 base in Q4) so that legacy FY26 revenues = the guidance end-point of the active scenario.
B93: Check: legacy FY26 revenues vs guidance end-point (should be 0) | CA93: =ROUND(CA88-CA89,1) -> 0
B94: Memo: Adjusted EBITDA — legacy CoStar (ex-Zonda & future M&A) | C94: =C168 -> 25.89 | D94: =D168 -> 33.999 | E94: =E168 -> 56.589 | F94: =F168 -> 54.332 | G94: =G168 -> 51.317 | H94: =H168 -> 56.947 | I94: =I168 -> 86.398 | J94: =J168 -> 25.67 | ... BX94: =BX168 -> 184 | BY94: =BY84-N(BY60)-N(BY74) -> 202.03181 | BZ94: =BZ84-N(BZ60)-N(BZ74) -> 281.96819 | CA94: =CA84-N(CA60)-N(CA74) -> 800 | CB94: =CB84-N(CB60)-N(CB74) -> 954.4014 | CC94: =CC84-N(CC60)-N(CC74) -> 1177.8543 | CD94: =CD84-N(CD60)-N(CD74) -> 1429.4473 | CE94: =CE84-N(CE60)-N(CE74) -> 1707.8898
B95: Memo: FY26 Adjusted EBITDA guidance — legacy ex-Zonda (scenario end-point) | CA95: =CHOOSE(MATCH($CF$2,{"Bull","Base","Bear"},0),$CO$13,$CP$13,$CQ$13) -> 800 | CF95: $780–820m affirmed (Q2-26 release).
B96: Legacy Adjusted EBITDA before margin calibration (Q3/Q4-26E helper) | BY96: =BY20*BY23+BY28*BY32 -> 205.35076 | BZ96: =BZ20*BZ23+BZ28*BZ32 -> 285.31271
B97: Outlook calibration: Δ segment Adjusted EBITDA margin, Q3/Q4-26E (Q3/26E col. = Commercial RE; Q4/26E col. = Residential RE) | BY97: =(CHOOSE(MATCH($CF$2,{"Bull","Base","Bear"},0),$CO$16,$CP$16,$CQ$16)-(BW22+BX22)-BY20*BY23-BZ20*BZ23)/(BY20+BZ20) -> -0.020424943 | BZ97: =(CHOOSE(MATCH($CF$2,{"Bull","Base","Bear"},0),$CO$17,$CP$17,$CQ$17)-(BW31+BX31)-BY28*BY32-BZ28*BZ32)/(BY28+BZ28) -> 0.014703553 | CF97: Solves the margin shift per segment so FY26 segment Adjusted EBITDA = segment guidance end-points (CRE $670–690m; Residential $110–130m; total = $780–820m consolidated guide) for the active scenario.
B98: Check: legacy FY26 Adjusted EBITDA vs guidance end-point (should be 0) | CA98: =ROUND(CA94-CA95,1) -> 0
B99: Memo: Q3/26E legacy revenues / Adjusted EBITDA vs Q3 guidance mid-point ($940m / $200m) | BY99: =ROUND(BY88-$CP$31,1) -> 5.9 | BZ99: =ROUND(BY94-$CP$32,1) -> 2 | CF99: Q3/26E column = revenue gap; Q4/26E column = Q3/26E Adjusted EBITDA gap (memo — not forced).
B100: Check: FY26E segment Adjusted EBITDA vs segment guidance end-points (should be 0; Q3/26E col. = CRE, Q4/26E col. = Residential) | BY100: =ROUND(CA22-CHOOSE(MATCH($CF$2,{"Bull","Base","Bear"},0),$CO$16,$CP$16,$CQ$16),1) -> 0 | BZ100: =ROUND(CA31-CHOOSE(MATCH($CF$2,{"Bull","Base","Bear"},0),$CO$17,$CP$17,$CQ$17),1) -> 0
...

Sheet Bull-Base-Bear
B2: CoStar Group (CSGP) — Bull / Base / Bear Case P&L Summary | J2: Share price ($): | K2: =Model!$CA$388 -> 30.78
B3: Adjusted figures (company current definition: Adjusted EBITDA adds back SBC; Adjusted EPS at a 26% assumed tax rate) · USD | J3: As of: | K3: =TODAY() -> 46301
B5: Scenario: | C5: =Model!$CF$2 -> Base | N5: Scenario: | O5: Bull | P5: Snapshot (values) — Model run with switch = Bull, captured 06-Oct-2026; re-run to refresh | Z5: Scenario: | AA5: Bear | AB5: Snapshot (values) — Model run with switch = Bear, captured 06-Oct-2026; re-run to refresh
B7: (USDm, except EPS and shares) | C7: 2025A | D7: 2026E | E7: 2027E | F7: 2028E | G7: 2029E | H7: 2030E | I7: 25-'30 CAGR | J7: LT Hist Avg | K7: LT Hist Min | L7: LT Hist Max | N7: (USDm, except EPS and shares) | O7: 2025A | P7: 2026E | Q7: 2027E | R7: 2028E | S7: 2029E | T7: 2030E | U7: 25-'30 CAGR | V7: LT Hist Avg | W7: LT Hist Min | X7: LT Hist Max | Z7: (USDm, except EPS and shares) | AA7: 2025A | AB7: 2026E | AC7: 2027E | AD7: 2028E | AE7: 2029E | AF7: 2030E | AG7: 25-'30 CAGR | AH7: LT Hist Avg | AI7: LT Hist Min | AJ7: LT Hist Max
B9: Revenues | C9: =Model!BV121 -> 3247 | D9: =Model!CA121 -> 3801.9008 | E9: =Model!CB121 -> 4324.8999 | F9: =Model!CC121 -> 4750.8791 | G9: =Model!CD121 -> 5185.0652 | H9: =Model!CE121 -> 5621.4945 | I9: =IFERROR((H9/C9)^(1/5)-1,"n/m") -> 0.11602494 | N9: Revenues | O9: 3247 | P9: 3821.9008 | Q9: 4493.0581 | R9: 5139.8641 | S9: 5828.2125 | T9: 6553.8917 | U9: 0.15080938 | Z9: Revenues | AA9: 3247 | AB9: 3781.9008 | AC9: 4199.4627 | AD9: 4501.5722 | AE9: 4793.3687 | AF9: 5069.4852 | AG9: 0.093191672
B10: Revenues y/y % | D10: =IFERROR(D9/C9-1,"") -> 0.17089647 | E10: =IFERROR(E9/D9-1,"") -> 0.13756253 | F10: =IFERROR(F9/E9-1,"") -> 0.098494585 | G10: =IFERROR(G9/F9-1,"") -> 0.091390673 | H10: =IFERROR(H9/G9-1,"") -> 0.084170463 | N10: Revenues y/y % | P10: 0.177056 | Q10: 0.17560823 | R10: 0.14395676 | S10: 0.13392346 | T10: 0.12451145 | Z10: Revenues y/y % | AB10: 0.16473693 | AC10: 0.11041058 | AD10: 0.071940047 | AE10: 0.064821009 | AF10: 0.057603863
B11: Commercial Real Estate revenues y/y % | C11: =Model!BV204 -> 0.17953795 | D11: =Model!CA204 -> 0.087522548 | E11: =Model!CB204 -> 0.090881952 | F11: =Model!CC204 -> 0.089334598 | G11: =Model!CD204 -> 0.084143665 | H11: =Model!CE204 -> 0.078851186 | N11: Commercial Real Estate revenues y/y % | O11: 0.17953795 | P11: 0.093342357 | Q11: 0.1138374 | R11: 0.11230295 | S11: 0.10711613 | T11: 0.10182495 | Z11: Commercial Real Estate revenues y/y % | AA11: 0.17953795 | AB11: 0.081702738 | AC11: 0.067926918 | AD11: 0.066405079 | AE11: 0.061248595 | AF11: 0.055993451
B12: Residential Real Estate revenues y/y % (ex-Zonda) | C12: =Model!BV205 -> 0.1957412 | D12: =Model!CA205 -> 0.22712137 | E12: =Model!CB205 -> 0.12 | F12: =Model!CC205 -> 0.11 | G12: =Model!CD205 -> 0.1 | H12: =Model!CE205 -> 0.09 | N12: Residential Real Estate revenues y/y % (ex-Zonda) | O12: 0.1957412 | P12: 0.23369672 | Q12: 0.15 | R12: 0.14 | S12: 0.13 | T12: 0.12 | Z12: Residential Real Estate revenues y/y % (ex-Zonda) | AA12: 0.1957412 | AB12: 0.22054603 | AC12: 0.09 | AD12: 0.08 | AE12: 0.07 | AF12: 0.06
B13: Adjusted EBITDA (company definition; adds back SBC) | C13: =Model!BV168 -> 442 | D13: =Model!CA168 -> 815.38719 | E13: =Model!CB168 -> 1003.9734 | F13: =Model!CC168 -> 1235.6751 | G13: =Model!CD168 -> 1496.5194 | H13: =Model!CE168 -> 1782.8256 | I13: =IFERROR((H13/C13)^(1/5)-1,"n/m") -> 0.32171347 | N13: Adjusted EBITDA (company definition; adds back SBC) | O13: 442 | P13: 835.38719 | Q13: 1172.5647 | R13: 1479.7078 | S13: 1834.1367 | T13: 2234.8487 | U13: 0.38281847 | Z13: Adjusted EBITDA (company definition; adds back SBC) | AA13: 442 | AB13: 795.38719 | AC13: 853.64372 | AD13: 1041.8735 | AE13: 1246.7969 | AF13: 1463.4808 | AG13: 0.27055348
B14: Adjusted EBITDA margin % | C14: =IFERROR(C13/C9,"") -> 0.13612565 | D14: =IFERROR(D13/D9,"") -> 0.2144683 | E14: =IFERROR(E13/E9,"") -> 0.23213795 | F14: =IFERROR(F13/F9,"") -> 0.26009399 | G14: =IFERROR(G13/G9,"") -> 0.28862114 | H14: =IFERROR(H13/H9,"") -> 0.31714441 | J14: =IFERROR(AVERAGE(Model!C169,Model!D169,Model!E169,Model!F169,Model!G169,Model!H169,Model!I169,Model!N169,Model!S169,Model!X169,Model!AC169,Model!AH169,Model!AM169,Model!AR169,Model!AW169,Model!BB169,Model!BG169,Model!BL169,Model!BQ169,Model!BV169),"n/m") -> 0.25494591 | K14: =IFERROR(MIN(Model!C169,Model!D169,Model!E169,Model!F169,Model!G169,Model!H169,Model!I169,Model!N169,Model!S169,Model!X169,Model!AC169,Model!AH169,Model!AM169,Model!AR169,Model!AW169,Model!BB169,Model!BG169,Model!BL169,Model!BQ169,Model!BV169),"n/m") -> 0.088005263 | L14: =IFERROR(MAX(Model!C169,Model!D169,Model!E169,Model!F169,Model!G169,Model!H169,Model!I169,Model!N169,Model!S169,Model!X169,Model!AC169,Model!AH169,Model!AM169,Model!AR169,Model!AW169,Model!BB169,Model!BG169,Model!BL169,Model!BQ169,Model!BV169),"n/m") -> 0.36200123 | N14: Adjusted EBITDA margin % | O14: 0.13612565 | P14: 0.21857898 | Q14: 0.26097253 | R14: 0.2878885 | S14: 0.31469969 | T14: 0.34099567 | V14: 0.25494591 | W14: 0.088005263 | X14: 0.36200123 | Z14: Adjusted EBITDA margin % | AA14: 0.13612565 | AB14: 0.21031413 | AC14: 0.20327451 | AD14: 0.23144659 | AE14: 0.26010871 | AF14: 0.2886843 | AH14: 0.25494591 | AI14: 0.088005263 | AJ14: 0.36200123
B16: Income from Operations (GAAP) | C16: =Model!BV131 -> -72 | D16: =Model!CA131 -> 307.3889 | E16: =Model!CB131 -> 469.82961 | F16: =Model!CC131 -> 706.1206 | G16: =Model!CD131 -> 954.04538 | H16: =Model!CE131 -> 1245.2929 | I16: =IFERROR((H16/C16)^(1/5)-1,"n/m") -> -2.7684297 | N16: Income from Operations (GAAP) | O16: -72 | P16: 327.3889 | Q16: 607.99514 | R16: 886.03622 | S16: 1191.7875 | T16: 1559.5074 | U16: -2.8498265 | Z16: Income from Operations (GAAP) | AA16: -72 | AB16: 287.3889 | AC16: 327.27703 | AD16: 527.77605 | AE16: 728.60809 | AF16: 960.17271 | AG16: -2.6788171
B17: Income from operations y/y % | D17: =IFERROR(D16/C16-1,"") -> -5.2692903 | E17: =IFERROR(E16/D16-1,"") -> 0.52845341 | F17: =IFERROR(F16/E16-1,"") -> 0.50292911 | G17: =IFERROR(G16/F16-1,"") -> 0.35110826 | H17: =IFERROR(H16/G16-1,"") -> 0.3052764 | N17: Income from operations y/y % | P17: -5.547068 | Q17: 0.8571037 | R17: 0.45730807 | S17: 0.34507765 | T17: 0.30854483 | Z17: Income from operations y/y % | AB17: -4.9915125 | AC17: 0.13879498 | AD17: 0.61262782 | AE17: 0.3805251 | AF17: 0.3178178
B18: Operating margin (GAAP) % | C18: =IFERROR(C16/C9,"") -> -0.022174315 | D18: =IFERROR(D16/D9,"") -> 0.080851372 | E18: =IFERROR(E16/E9,"") -> 0.10863364 | F18: =IFERROR(F16/F9,"") -> 0.14862946 | G18: =IFERROR(G16/G9,"") -> 0.18399872 | H18: =IFERROR(H16/H9,"") -> 0.22152346 | J18: =IFERROR(AVERAGE(Model!C213,Model!D213,Model!E213,Model!F213,Model!G213,Model!H213,Model!I213,Model!N213,Model!S213,Model!X213,Model!AC213,Model!AH213,Model!AM213,Model!AR213,Model!AW213,Model!BB213,Model!BG213,Model!BL213,Model!BQ213,Model!BV213),"n/m") -> 0.13027222 | K18: =IFERROR(MIN(Model!C213,Model!D213,Model!E213,Model!F213,Model!G213,Model!H213,Model!I213,Model!N213,Model!S213,Model!X213,Model!AC213,Model!AH213,Model!AM213,Model!AR213,Model!AW213,Model!BB213,Model!BG213,Model!BL213,Model!BQ213,Model!BV213),"n/m") -> -0.022174315 | L18: =IFERROR(MAX(Model!C213,Model!D213,Model!E213,Model!F213,Model!G213,Model!H213,Model!I213,Model!N213,Model!S213,Model!X213,Model!AC213,Model!AH213,Model!AM213,Model!AR213,Model!AW213,Model!BB213,Model!BG213,Model!BL213,Model!BQ213,Model!BV213),"n/m") -> 0.25972856 | N18: Operating margin (GAAP) % | O18: -0.022174315 | P18: 0.085661275 | Q18: 0.13531878 | R18: 0.17238514 | S18: 0.20448594 | T18: 0.23795135 | V18: 0.13027222 | W18: -0.022174315 | X18: 0.25972856 | Z18: Operating margin (GAAP) % | AA18: -0.022174315 | AB18: 0.075990596 | AC18: 0.077933074 | AD18: 0.1172426 | AE18: 0.15200335 | AF18: 0.18940241 | AH18: 0.13027222 | AI18: -0.022174315 | AJ18: 0.25972856
B20: Adjusted Net Income (company definition, 26% assumed tax) | C20: =Model!BV192 -> 364.08 | D20: =Model!CA192 -> 550.47639 | E20: =Model!CB192 -> 661.08108 | F20: =Model!CC192 -> 820.73116 | G20: =Model!CD192 -> 1003.6745 | H20: =Model!CE192 -> 1194.3011 | I20: =IFERROR((H20/C20)^(1/5)-1,"n/m") -> 0.26818731 | N20: Adjusted Net Income (company definition, 26% assumed tax) | O20: 364.08 | P20: 565.27639 | Q20: 775.72924 | R20: 969.3924 | S20: 1207.9627 | T20: 1469.4236 | U20: 0.32187393 | Z20: Adjusted Net Income (company definition, 26% assumed tax) | AA20: 364.08 | AB20: 535.67639 | AC20: 554.26488 | AD20: 692.52081 | AE20: 839.4137 | AF20: 986.43785 | AG20: 0.22060342
B22: FDSO (m) | C22: =Model!BV145 -> 420.7 | D22: =Model!CA145 -> 405.7072 | E22: =Model!CB145 -> 390.55054 | F22: =Model!CC145 -> 365.85034 | G22: =Model!CD145 -> 338.23807 | H22: =Model!CE145 -> 307.6637 | I22: =IFERROR((H22/C22)^(1/5)-1,"n/m") -> -0.060664473 | N22: FDSO (m) | O22: 420.7 | P22: 403.27055 | Q22: 380.89922 | R22: 358.49913 | S22: 333.8961 | T22: 303.53119 | U22: -0.063201551 | Z22: FDSO (m) | AA22: 420.7 | AB22: 406.625 | AC22: 401.87457 | AD22: 388.23059 | AE22: 367.84081 | AF22: 345.30983 | AG22: -0.038725799
B24: Adjusted EPS — Diluted ($) | C24: =Model!BV196 -> 0.86541478 | D24: =Model!CA196 -> 1.3568317 | E24: =Model!CB196 -> 1.6926902 | F24: =Model!CC196 -> 2.2433522 | G24: =Model!CD196 -> 2.9673612 | H24: =Model!CE196 -> 3.8818396 | I24: =IFERROR((H24/C24)^(1/5)-1,"n/m") -> 0.35008979 | N24: Adjusted EPS — Diluted ($) | O24: 0.86541478 | P24: 1.4017299 | Q24: 2.0365735 | R24: 2.70403 | S24: 3.6177803 | T24: 4.8410958 | U24: 0.41105478 | Z24: Adjusted EPS — Diluted ($) | AA24: 0.86541478 | AB24: 1.317372 | AC24: 1.3791987 | AD24: 1.7837873 | AE24: 2.2820026 | AF24: 2.8566746 | AG24: 0.26977653
B25: EPS y/y % | D25: =IFERROR(D24/C24-1,"") -> 0.56783976 | E25: =IFERROR(E24/D24-1,"") -> 0.24753146 | F25: =IFERROR(F24/E24-1,"") -> 0.32531762 | G25: =IFERROR(G24/F24-1,"") -> 0.32273532 | H25: =IFERROR(H24/G24-1,"") -> 0.30817899 | N25: EPS y/y % | P25: 0.61972031 | Q25: 0.45290007 | R25: 0.32773506 | S25: 0.33792165 | T25: 0.3381398 | Z25: EPS y/y % | AB25: 0.52224346 | AC25: 0.046931832 | AD25: 0.29335053 | AE25: 0.27930196 | AF25: 0.25182794
B27: P / E (x) — assumed (Adjusted EPS) | G27: 22 | H27: 22 | N27: P / E (x) — assumed (Adjusted EPS) | S27: 28 | T27: 28 | Z27: P / E (x) — assumed (Adjusted EPS) | AD27: 16 | AE27: 16 | AF27: 16
B28: Price Target ($) | G28: =G27*G24 -> 65.281946 | H28: =H27*H24 -> 85.40047 | N28: Price Target ($) | S28: =S27*S24 -> 101.29785 | T28: =T27*T24 -> 135.55068 | Z28: Price Target ($) | AD28: =AD27*AD24 -> 28.540597 | AE28: =AE27*AE24 -> 36.512042 | AF28: =AF27*AF24 -> 45.706794
B29: Upside / (Downside) vs current | G29: =IFERROR(G28/$K$2-1,"") -> 1.1209209 | H29: =IFERROR(H28/$K$2-1,"") -> 1.7745442 | N29: Upside / (Downside) vs current | S29: =IFERROR(S28/$K$2-1,"") -> 2.2910282 | T29: =IFERROR(T28/$K$2-1,"") -> 3.4038559 | Z29: Upside / (Downside) vs current | AD29: =IFERROR(AD28/$K$2-1,"") -> -0.07275512 | AE29: =IFERROR(AE28/$K$2-1,"") -> 0.18622619 | AF29: =IFERROR(AF28/$K$2-1,"") -> 0.48495109
B30: IRR (to Dec-Y-1) | G30: =IFERROR((G28/$K$2)^(1/((DATE(2029-1,12,31)-$K$3)/365.25))-1,"") -> 0.39951263 | H30: =IFERROR((H28/$K$2)^(1/((DATE(2030-1,12,31)-$K$3)/365.25))-1,"") -> 0.37072621 | N30: IRR (to Dec-Y-1) | S30: =IFERROR((S28/$K$2)^(1/((DATE(2029-1,12,31)-$K$3)/365.25))-1,"") -> 0.70325441 | T30: =IFERROR((T28/$K$2)^(1/((DATE(2030-1,12,31)-$K$3)/365.25))-1,"") -> 0.58106951 | Z30: IRR (to Dec-Y-1) | AD30: =IFERROR((AD28/$K$2)^(1/((DATE(2028-1,12,31)-$K$3)/365.25))-1,"") -> -0.05934176 | AE30: =IFERROR((AE28/$K$2)^(1/((DATE(2029-1,12,31)-$K$3)/365.25))-1,"") -> 0.079338096 | AF30: =IFERROR((AF28/$K$2)^(1/((DATE(2030-1,12,31)-$K$3)/365.25))-1,"") -> 0.12995409
B32: Free Cash Flow (CFO − capex incl. campuses) | C32: =Model!BV248 -> 41 | D32: =Model!CA248 -> 453.83716 | E32: =Model!CB248 -> 694.57496 | F32: =Model!CC248 -> 893.96844 | G32: =Model!CD248 -> 1096.1414 | H32: =Model!CE248 -> 1281.1175 | I32: =IFERROR((H32/C32)^(1/5)-1,"n/m") -> 0.99049469 | N32: Free Cash Flow (CFO − capex incl. campuses) | O32: 41 | P32: 467.64186 | Q32: 803.85832 | R32: 1044.3609 | S32: 1309.7546 | T32: 1573.3862 | U32: 1.0740074 | Z32: Free Cash Flow (CFO − capex incl. campuses) | AA32: 41 | AB32: 440.03245 | AC32: 588.57011 | AD32: 765.44321 | AE32: 930.40127 | AF32: 1070.4777 | AG32: 0.92025432
B33: FCF % | C33: =IFERROR(C32/C9,"") -> 0.01262704 | D33: =IFERROR(D32/D9,"") -> 0.11937112 | E33: =IFERROR(E32/E9,"") -> 0.16059908 | F33: =IFERROR(F32/F9,"") -> 0.18816906 | G33: =IFERROR(G32/G9,"") -> 0.21140359 | H33: =IFERROR(H32/H9,"") -> 0.22789625 | J33: =IFERROR(AVERAGE(Model!C250,Model!D250,Model!E250,Model!F250,Model!G250,Model!H250,Model!I250,Model!N250,Model!S250,Model!X250,Model!AC250,Model!AH250,Model!AM250,Model!AR250,Model!AW250,Model!BB250,Model!BG250,Model!BL250,Model!BQ250,Model!BV250),"n/m") -> 0.14836925 | K33: =IFERROR(MIN(Model!C250,Model!D250,Model!E250,Model!F250,Model!G250,Model!H250,Model!I250,Model!N250,Model!S250,Model!X250,Model!AC250,Model!AH250,Model!AM250,Model!AR250,Model!AW250,Model!BB250,Model!BG250,Model!BL250,Model!BQ250,Model!BV250),"n/m") -> -0.089649879 | L33: =IFERROR(MAX(Model!C250,Model!D250,Model!E250,Model!F250,Model!G250,Model!H250,Model!I250,Model!N250,Model!S250,Model!X250,Model!AC250,Model!AH250,Model!AM250,Model!AR250,Model!AW250,Model!BB250,Model!BG250,Model!BL250,Model!BQ250,Model!BV250),"n/m") -> 0.29404688 | N33: FCF % | O33: 0.01262704 | P33: 0.12235845 | Q33: 0.17891118 | R33: 0.20318842 | S33: 0.22472664 | T33: 0.240069 | V33: 0.14836925 | W33: -0.089649879 | X33: 0.29404688 | Z33: FCF % | AA33: 0.01262704 | AB33: 0.11635219 | AC33: 0.14015367 | AD33: 0.17003908 | AE33: 0.19410175 | AF33: 0.21116102 | AH33: 0.14836925 | AI33: -0.089649879 | AJ33: 0.29404688
B34: FCF / share ($) | C34: =IFERROR(C32/C22,"") -> 0.09745662 | D34: =IFERROR(D32/D22,"") -> 1.1186323 | E34: =IFERROR(E32/E22,"") -> 1.7784509 | F34: =IFERROR(F32/F22,"") -> 2.4435359 | G34: =IFERROR(G32/G22,"") -> 3.2407393 | H34: =IFERROR(H32/H22,"") -> 4.1640192 | N34: FCF / share ($) | O34: 0.09745662 | P34: 1.1596231 | Q34: 2.1104226 | R34: 2.9131476 | S34: 3.9226412 | T34: 5.1836064 | Z34: FCF / share ($) | AA34: 0.09745662 | AB34: 1.0821579 | AC34: 1.4645617 | AD34: 1.97162 | AE34: 2.5293585 | AF34: 3.1000498
B35: FCF Yield (on PT) | G35: =IFERROR(G34/G$28,"") -> 0.049642198 | H35: =IFERROR(H34/H$28,"") -> 0.048758738 | N35: FCF Yield (on PT) | S35: =IFERROR(S34/S$28,"") -> 0.038723835 | T35: =IFERROR(T34/T$28,"") -> 0.038241094 | Z35: FCF Yield (on PT) | AD35: =IFERROR(AD34/AD$28,"") -> 0.069081246 | AE35: =IFERROR(AE34/AE$28,"") -> 0.069274637 | AF35: =IFERROR(AF34/AF$28,"") -> 0.067824703
B36: Adjusted EBITDA — pro forma (2026E incl. Zonda full year) | C36: =Model!BV177 -> 442 | D36: =Model!CA177 -> 842.228 | E36: =Model!CB177 -> 1003.9734 | F36: =Model!CC177 -> 1235.6751 | G36: =Model!CD177 -> 1496.5194 | H36: =Model!CE177 -> 1782.8256 | I36: =IFERROR((H36/C36)^(1/5)-1,"n/m") -> 0.32171347 | N36: Adjusted EBITDA — pro forma (2026E incl. Zonda full year) | O36: 442 | P36: 862.228 | Q36: 1172.5647 | R36: 1479.7078 | S36: 1834.1367 | T36: 2234.8487 | U36: 0.38281847 | Z36: Adjusted EBITDA — pro forma (2026E incl. Zonda full year) | AA36: 442 | AB36: 822.228 | AC36: 853.64372 | AD36: 1041.8735 | AE36: 1246.7969 | AF36: 1463.4808 | AG36: 0.27055348
B37: Adjusted EBITDA (pro forma) % of revenues | C37: =IFERROR(C36/C9,"") -> 0.13612565 | D37: =IFERROR(D36/D9,"") -> 0.22152814 | E37: =IFERROR(E36/E9,"") -> 0.23213795 | F37: =IFERROR(F36/F9,"") -> 0.26009399 | G37: =IFERROR(G36/G9,"") -> 0.28862114 | H37: =IFERROR(H36/H9,"") -> 0.31714441 | J37: =IFERROR(AVERAGE(Model!C169,Model!D169,Model!E169,Model!F169,Model!G169,Model!H169,Model!I169,Model!N169,Model!S169,Model!X169,Model!AC169,Model!AH169,Model!AM169,Model!AR169,Model!AW169,Model!BB169,Model!BG169,Model!BL169,Model!BQ169,Model!BV169),"n/m") -> 0.25494591 | K37: =IFERROR(MIN(Model!C169,Model!D169,Model!E169,Model!F169,Model!G169,Model!H169,Model!I169,Model!N169,Model!S169,Model!X169,Model!AC169,Model!AH169,Model!AM169,Model!AR169,Model!AW169,Model!BB169,Model!BG169,Model!BL169,Model!BQ169,Model!BV169),"n/m") -> 0.088005263 | L37: =IFERROR(MAX(Model!C169,Model!D169,Model!E169,Model!F169,Model!G169,Model!H169,Model!I169,Model!N169,Model!S169,Model!X169,Model!AC169,Model!AH169,Model!AM169,Model!AR169,Model!AW169,Model!BB169,Model!BG169,Model!BL169,Model!BQ169,Model!BV169),"n/m") -> 0.36200123 | N37: Adjusted EBITDA (pro forma) % of revenues | O37: 0.13612565 | P37: 0.22560188 | Q37: 0.26097253 | R37: 0.2878885 | S37: 0.31469969 | T37: 0.34099567 | V37: 0.25494591 | W37: 0.088005263 | X37: 0.36200123 | Z37: Adjusted EBITDA (pro forma) % of revenues | AA37: 0.13612565 | AB37: 0.21741131 | AC37: 0.20327451 | AD37: 0.23144659 | AE37: 0.26010871 | AF37: 0.2886843 | AH37: 0.25494591 | AI37: 0.088005263 | AJ37: 0.36200123
B39: Net Debt (negative = net cash) | C39: =Model!BV383 -> -740 | D39: =Model!CA383 -> 337.16284 | E39: =Model!CB383 -> 501.9867 | F39: =Model!CC383 -> 617.83755 | G39: =Model!CD383 -> 748.25971 | H39: =Model!CE383 -> 891.41279 | N39: Net Debt (negative = net cash) | O39: -740 | P39: 623.35814 | Q39: 1172.5647 | R39: 1479.7078 | S39: 1834.1367 | T39: 2234.8487 | Z39: Net Debt (negative = net cash) | AA39: -740 | AB39: 237.96755 | AC39: 0 | AD39: 0 | AE39: 0 | AF39: 0
B40: Net Debt / Adjusted EBITDA (x) | C40: =IFERROR(C39/C36,"") -> -1.6742081 | D40: =IFERROR(D39/D36,"") -> 0.40032253 | E40: =IFERROR(E39/E36,"") -> 0.5 | F40: =IFERROR(F39/F36,"") -> 0.5 | G40: =IFERROR(G39/G36,"") -> 0.5 | H40: =IFERROR(H39/H36,"") -> 0.5 | N40: Net Debt / Adjusted EBITDA (x) | O40: -1.6742081 | P40: 0.72296207 | Q40: 1 | R40: 1 | S40: 1 | T40: 1 | Z40: Net Debt / Adjusted EBITDA (x) | AA40: -1.6742081 | AB40: 0.28941795 | AC40: 0 | AD40: 0 | AE40: 0 | AF40: 0
B41: Share repurchases ($m) | D41: =Model!CA259 -> 113 | E41: =Model!CB259 -> 849.39882 | F41: =Model!CC259 -> 999.81929 | G41: =Model!CD259 -> 1216.5636 | H41: =Model!CE259 -> 1414.2706 | N41: Share repurchases ($m) | P41: 413 | Q41: 843.06491 | R41: 841.50394 | S41: 1154.1835 | T41: 1464.0982 | Z41: Share repurchases ($m) | AB41: 0 | AC41: 340.60256 | AD41: 755.44321 | AE41: 920.40127 | AF41: 1060.4777
B42: Implied avg buyback price ($) | D42: =Model!CA258 -> 30.78 | E42: =Model!CB258 -> 33.2424 | F42: =Model!CC258 -> 35.901792 | G42: =Model!CD258 -> 38.773935 | H42: =Model!CE258 -> 41.87585 | N42: Implied avg buyback price ($) | P42: 30.78 | Q42: 33.2424 | R42: 35.901792 | S42: 38.773935 | T42: 41.87585 | Z42: Implied avg buyback price ($) | AB42: 30.78 | AC42: 33.2424 | AD42: 35.901792 | AE42: 38.773935 | AF42: 41.87585
B43: Shares repurchased (m) | D43: =Model!CA260 -> 3.6712151 | E43: =Model!CB260 -> 25.551669 | F43: =Model!CC260 -> 27.848729 | G43: =Model!CD260 -> 31.375808 | H43: =Model!CE260 -> 33.772941 | N43: Shares repurchased (m) | P43: 13.417804 | Q43: 25.361133 | R43: 23.439051 | S43: 29.766994 | T43: 34.962829 | Z43: Shares repurchased (m) | AB43: 0 | AC43: 10.246028 | AD43: 21.041936 | AE43: 23.737628 | AF43: 25.324326
B45: ROIC | C45: =Model!BV366 -> 0.019394575 | D45: =Model!CA366 -> 0.041561589 | E45: =Model!CB366 -> 0.059214573 | F45: =Model!CC366 -> 0.083649728 | G45: =Model!CD366 -> 0.11106808 | H45: =Model!CE366 -> 0.14365415 | J45: =IFERROR(AVERAGE(Model!C366,Model!D366,Model!E366,Model!F366,Model!G366,Model!H366,Model!I366,Model!N366,Model!S366,Model!X366,Model!AC366,Model!AH366,Model!AM366,Model!AR366,Model!AW366,Model!BB366,Model!BG366,Model!BL366,Model!BQ366,Model!BV366),"n/m") -> 0.10707723 | K45: =IFERROR(MIN(Model!C366,Model!D366,Model!E366,Model!F366,Model!G366,Model!H366,Model!I366,Model!N366,Model!S366,Model!X366,Model!AC366,Model!AH366,Model!AM366,Model!AR366,Model!AW366,Model!BB366,Model!BG366,Model!BL366,Model!BQ366,Model!BV366),"n/m") -> 0.019394575 | L45: =IFERROR(MAX(Model!C366,Model!D366,Model!E366,Model!F366,Model!G366,Model!H366,Model!I366,Model!N366,Model!S366,Model!X366,Model!AC366,Model!AH366,Model!AM366,Model!AR366,Model!AW366,Model!BB366,Model!BG366,Model!BL366,Model!BQ366,Model!BV366),"n/m") -> 0.23968582 | N45: ROIC | O45: 0.019394575 | P45: 0.043316015 | Q45: 0.069029852 | R45: 0.091614284 | S45: 0.11598547 | T45: 0.14392073 | V45: 0.10707723 | W45: 0.019394575 | X45: 0.23968582 | Z45: ROIC | AA45: 0.019394575 | AB45: 0.039807099 | AC45: 0.045937812 | AD45: 0.066281152 | AE45: 0.088235417 | AF45: 0.11388072 | AH45: 0.10707723 | AI45: 0.019394575 | AJ45: 0.23968582
B46: RONTA | C46: =Model!BV377 -> 0.048098798 | D46: =Model!CA377 -> 0.15880568 | E46: =Model!CB377 -> 0.23208482 | F46: =Model!CC377 -> 0.33099326 | G46: =Model!CD377 -> 0.4279734 | H46: =Model!CE377 -> 0.54107884 | J46: =IFERROR(AVERAGE(Model!C377,Model!D377,Model!E377,Model!F377,Model!G377,Model!H377,Model!I377,Model!N377,Model!S377,Model!X377,Model!AC377,Model!AH377,Model!AM377,Model!AR377,Model!AW377,Model!BB377,Model!BG377,Model!BL377,Model!BQ377,Model!BV377),"n/m") -> 0.10363777 | K46: =IFERROR(MIN(Model!C377,Model!D377,Model!E377,Model!F377,Model!G377,Model!H377,Model!I377,Model!N377,Model!S377,Model!X377,Model!AC377,Model!AH377,Model!AM377,Model!AR377,Model!AW377,Model!BB377,Model!BG377,Model!BL377,Model!BQ377,Model!BV377),"n/m") -> 0.01578251 | L46: =IFERROR(MAX(Model!C377,Model!D377,Model!E377,Model!F377,Model!G377,Model!H377,Model!I377,Model!N377,Model!S377,Model!X377,Model!AC377,Model!AH377,Model!AM377,Model!AR377,Model!AW377,Model!BB377,Model!BG377,Model!BL377,Model!BQ377,Model!BV377),"n/m") -> 0.23751427 | N46: RONTA | O46: 0.048098798 | P46: 0.18733478 | Q46: 0.29965796 | R46: 0.40548799 | S46: 0.52687844 | T46: 0.67168438 | V46: 0.10363777 | W46: 0.01578251 | X46: 0.23751427 | Z46: RONTA | AA46: 0.048098798 | AB46: 0.14556614 | AC46: 0.14532545 | AD46: 0.20290195 | AE46: 0.26305728 | AF46: 0.33185736 | AH46: 0.10363777 | AI46: 0.01578251 | AJ46: 0.23751427
B48: Implied Market Cap (USDm) | G48: =G28*G22 -> 22080.839 | H48: =H28*H22 -> 26274.624 | N48: Implied Market Cap (USDm) | S48: =S28*S22 -> 33822.957 | T48: =T28*T22 -> 41143.86 | Z48: Implied Market Cap (USDm) | AD48: =AD28*AD22 -> 11080.333 | AE48: =AE28*AE22 -> 13430.619 | AF48: =AF28*AF22 -> 15783.006
B49: (+) Net Debt & NCI | G49: =G39+Model!CD296 -> 761.25971 | H49: =H39+Model!CE296 -> 904.41279 | N49: (+) Net Debt & NCI | S49: =S39+Model!CD296 -> 1847.1367 | T49: =T39+Model!CE296 -> 2247.8487 | Z49: (+) Net Debt & NCI | AD49: =AD39+Model!CC296 -> 13 | AE49: =AE39+Model!CD296 -> 13 | AF49: =AF39+Model!CE296 -> 13
B50: Implied Enterprise Value (USDm) | G50: =G48+G49 -> 22842.099 | H50: =H48+H49 -> 27179.037 | N50: Implied Enterprise Value (USDm) | S50: =S48+S49 -> 35670.094 | T50: =T48+T49 -> 43391.709 | Z50: Implied Enterprise Value (USDm) | AD50: =AD48+AD49 -> 11093.333 | AE50: =AE48+AE49 -> 13443.619 | AF50: =AF48+AF49 -> 15796.006
B51: Implied EV / Adjusted EBITDA (x) | G51: =IFERROR(G50/G36,"") -> 15.263483 | H51: =IFERROR(H50/H36,"") -> 15.244922 | N51: Implied EV / Adjusted EBITDA (x) | S51: =IFERROR(S50/S36,"") -> 19.447893 | T51: =IFERROR(T50/T36,"") -> 19.415949 | Z51: Implied EV / Adjusted EBITDA (x) | AD51: =IFERROR(AD50/AD36,"") -> 10.647485 | AE51: =IFERROR(AE50/AE36,"") -> 10.782525 | AF51: =IFERROR(AF50/AF36,"") -> 10.793449

Sheet DCF
B2: DCF VALUATION — COSTAR GROUP (CSGP)
B4: 1. WACC BUILD
B5: Risk-free rate (US 10Y govt) | C5: 0.0425 | D5: Assumption (~US 10Y Treasury yield); update to market
B6: Equity risk premium | C6: 0.05 | D6: US implied ERP ~4.5–5.5% (Damodaran)
B7: Levered beta | C7: 1.1 | D7: Information-services / online-marketplace peers (Verisk, MSCI, Zillow, Rightmove) ~0.8–1.4; elevated by Homes.com execution risk and 2026 share-price collapse
B8: Cost of equity | C8: =C5+C7*C6 -> 0.0975
B9: Pre-tax cost of debt | C9: 0.055 | D9: BBB- / Baa3; 2.80% 2030 notes trade wide of coupon; marginal cost ~5.5%
B10: Tax rate | C10: 0.26 | D10: Company assumed non-GAAP rate (26%); model 2027E+ GAAP ETR 27%
B11: After-tax cost of debt | C11: =C9*(1-C10) -> 0.0407
B12: Target D/V | C12: 0.1 | D12: Net debt ~$0.3–0.9bn (0.5x Adj. EBITDA buyback floor) vs ~$12bn market cap
B13: WACC | C13: =C8*(1-C12)+C11*C12 -> 0.09182
B15: Valuation date (live) | C15: =TODAY() -> 46301 | D15: Periods = (Dec-31-Year − today) / 365.25; cash flows assumed at year-end
B16: 2. UNLEVERED FREE CASH FLOW BUILD (USDm)
D17: 2026E | E17: 2027E | F17: 2028E | G17: 2029E | H17: 2030E | I17: 2031E | J17: 2032E | K17: 2033E | L17: 2034E | M17: 2035E | N17: Terminal | P17: CAGR 26–30E | Q17: CAGR 26–35E
B18: Adj. EBIT less SBC and acquisition & integration costs | D18: =Model!CA175-Model!CA162-Model!CA163 -> 293.3889 | E18: =Model!CB175-Model!CB162-Model!CB163 -> 469.82961 | F18: =Model!CC175-Model!CC162-Model!CC163 -> 706.1206 | G18: =Model!CD175-Model!CD162-Model!CD163 -> 954.04538 | H18: =Model!CE175-Model!CE162-Model!CE163 -> 1245.2929 | I18: =H18*(1+I$26) -> 1369.8222 | J18: =I18*(1+J$26) -> 1493.1062 | K18: =J18*(1+K$26) -> 1612.5547 | L18: =K18*(1+L$26) -> 1725.4335 | M18: =L18*(1+M$26) -> 1828.9595 | P18: =IFERROR((H18/D18)^(1/(COLUMNS(D18:H18)-1))-1,"n/m") -> 0.43534718 | Q18: =IFERROR((M18/D18)^(1/(COLUMNS(D18:M18)-1))-1,"n/m") -> 0.22548137
B19: × (1 − tax rate) | D19: =1-$C$10 -> 0.74 | E19: =1-$C$10 -> 0.74 | F19: =1-$C$10 -> 0.74 | G19: =1-$C$10 -> 0.74 | H19: =1-$C$10 -> 0.74 | I19: =1-$C$10 -> 0.74 | J19: =1-$C$10 -> 0.74 | K19: =1-$C$10 -> 0.74 | ... M19: =1-$C$10 -> 0.74
B20: NOPAT | D20: =D18*D19 -> 217.10778 | E20: =E18*E19 -> 347.67391 | F20: =F18*F19 -> 522.52924 | G20: =G18*G19 -> 705.99358 | H20: =H18*H19 -> 921.51676 | I20: =I18*I19 -> 1013.6684 | J20: =J18*J19 -> 1104.8986 | K20: =K18*K19 -> 1193.2905 | ... M20: =M18*M19 -> 1353.4301
B21: plus D&A (incl. acquired-intangible amortization) | D21: =Model!CA141 -> 356.99829 | E21: =Model!CB141 -> 360.1478 | F21: =Model!CC141 -> 343.51934 | G21: =Model!CD141 -> 339.07143 | H21: =Model!CE141 -> 316.67288 | I21: =H21*(1+I$26) -> 348.34017 | J21: =I21*(1+J$26) -> 379.69078 | K21: =J21*(1+K$26) -> 410.06604 | L21: =K21*(1+L$26) -> 438.77067 | M21: =L21*(1+M$26) -> 465.09691
B22: − Capex (incl. campuses) and acquisitions (Zonda 2026E; M&A 2027E–30E) | D22: =Model!CA228+Model!CA229+Model!CA230 -> -998.51324 | E22: =Model!CB228+Model!CB229+Model!CB230 -> -166.498 | F22: =Model!CC228+Model!CC229+Model!CC230 -> -135.01758 | G22: =Model!CD228+Model!CD229+Model!CD230 -> -123.7013 | H22: =Model!CE228+Model!CE229+Model!CE230 -> -132.42989 | I22: =Model!CE228*(1+I$26)+Model!CE229 -> -143.67288 | J22: =I22*(1+J$26) -> -156.60344 | K22: =J22*(1+K$26) -> -169.13171 | L22: =K22*(1+L$26) -> -180.97093 | M22: =L22*(1+M$26) -> -191.82919
B23: − Δ Working capital (CF statement) | D23: =Model!CA226 -> -263.37976 | E23: =Model!CB226 -> -155.12281 | F23: =Model!CC226 -> -170.21378 | G23: =Model!CD226 -> -185.48607 | H23: =Model!CE226 -> -200.78181 | I23: =H23*(1+I$26) -> -220.85999 | J23: =I23*(1+J$26) -> -240.73739 | K23: =J23*(1+K$26) -> -259.99638 | L23: =K23*(1+L$26) -> -278.19612 | M23: =L23*(1+M$26) -> -294.88789
B24: Unlevered FCF | D24: =D20+D21+D22+D23 -> -687.78692 | E24: =E20+E21+E22+E23 -> 386.2009 | F24: =F20+F21+F22+F23 -> 560.81722 | G24: =G20+G21+G22+G23 -> 735.87764 | H24: =H20+H21+H22+H23 -> 904.97794 | I24: =I20+I21+I22+I23 -> 997.47574 | J24: =J20+J21+J22+J23 -> 1087.2486 | K24: =K20+K21+K22+K23 -> 1174.2284 | ... M24: =M20+M21+M22+M23 -> 1331.8099 | N24: =M24*(1+$C$27) -> 1378.4232 | P24: =IFERROR((H24/D24)^(1/(COLUMNS(D24:H24)-1))-1,"n/m") -> n/m | Q24: =IFERROR((M24/D24)^(1/(COLUMNS(D24:M24)-1))-1,"n/m") -> -2.0761866
B25: Terminal Value (Gordon Growth) | N25: =N24/($C$13-$C$27) -> 24259.473
B26: Fade-period growth (2031E–35E; 10% → 6% linear) | I26: 0.1 | J26: =I26+($M$26-$I$26)/4 -> 0.09 | K26: =J26+($M$26-$I$26)/4 -> 0.08 | L26: =K26+($M$26-$I$26)/4 -> 0.07 | M26: 0.06
B27: Terminal growth rate | C27: 0.035
B29: Discount period (years) | D29: =(DATE(2026,12,31)-$C$15)/365.25 -> 0.23545517 | E29: =(DATE(2027,12,31)-$C$15)/365.25 -> 1.2347707 | F29: =(DATE(2028,12,31)-$C$15)/365.25 -> 2.2368241 | G29: =(DATE(2029,12,31)-$C$15)/365.25 -> 3.2361396 | H29: =(DATE(2030,12,31)-$C$15)/365.25 -> 4.2354552 | I29: =(DATE(2031,12,31)-$C$15)/365.25 -> 5.2347707 | J29: =(DATE(2032,12,31)-$C$15)/365.25 -> 6.2368241 | K29: =(DATE(2033,12,31)-$C$15)/365.25 -> 7.2361396 | L29: =(DATE(2034,12,31)-$C$15)/365.25 -> 8.2354552 | M29: =(DATE(2035,12,31)-$C$15)/365.25 -> 9.2347707 | N29: =M29 -> 9.2347707
B30: Discount factor | D30: =1/(1+$C$13)^D29 -> 0.97952864 | E30: =1/(1+$C$13)^E29 -> 0.89720608 | F30: =1/(1+$C$13)^F29 -> 0.82160452 | G30: =1/(1+$C$13)^G29 -> 0.75255438 | H30: =1/(1+$C$13)^H29 -> 0.68930743 | I30: =1/(1+$C$13)^I29 -> 0.63137594 | J30: =1/(1+$C$13)^J29 -> 0.57817411 | K30: =1/(1+$C$13)^K29 -> 0.5295826 | ... N30: =1/(1+$C$13)^N29 -> 0.4443077
B31: PV of UFCF | D31: =D24*D30 -> -673.70699 | E31: =E24*E30 -> 346.50179 | F31: =F24*F30 -> 460.76996 | G31: =G24*G30 -> 553.78794 | H31: =H24*H30 -> 623.80802 | I31: =I24*I30 -> 629.78218 | J31: =J24*J30 -> 628.61896 | K31: =K24*K30 -> 621.85095 | ... M31: =M24*M30 -> 591.73339 | N31: =N25*N30 -> 10778.671
D32: CoStar's Adjusted EBITDA adds back stock-based compensation (~4% of revenues 2027E+); the DCF deducts SBC (a real cost) and acquisition costs from Adjusted EBIT. Adjusted EBIT deducts all D&A incl. ~$0.2bn p.a. of acquired-intangible amortization (tax-effected), which is added back below NOPAT. 2026E includes the $0.8bn Zonda payment.
B33: IMPLIED ROIC — invested capital roll-forward (USDm)
B34: Opening invested capital | D34: =Model!BV363 -> 7631 | E34: =D38 -> 8535.8947 | F34: =E38 -> 8497.3677 | G34: =F38 -> 8459.0797 | H34: =G38 -> 8429.1957 | I34: =H38 -> 8445.7345 | J34: =I38 -> 8461.9272 | K34: =J38 -> 8479.5772 | L34: =K38 -> 8498.6393 | M34: =L38 -> 8519.0357
B35: plus Capex and acquisitions | D35: =-D22 -> 998.51324 | E35: =-E22 -> 166.498 | F35: =-F22 -> 135.01758 | G35: =-G22 -> 123.7013 | H35: =-H22 -> 132.42989 | I35: =-I22 -> 143.67288 | J35: =-J22 -> 156.60344 | K35: =-K22 -> 169.13171 | ... M35: =-M22 -> 191.82919
B36: less D&A | D36: =-D21 -> -356.99829 | E36: =-E21 -> -360.1478 | F36: =-F21 -> -343.51934 | G36: =-G21 -> -339.07143 | H36: =-H21 -> -316.67288 | I36: =-I21 -> -348.34017 | J36: =-J21 -> -379.69078 | K36: =-K21 -> -410.06604 | ... M36: =-M21 -> -465.09691
B37: plus Δ Working capital investment | D37: =-D23 -> 263.37976 | E37: =-E23 -> 155.12281 | F37: =-F23 -> 170.21378 | G37: =-G23 -> 185.48607 | H37: =-H23 -> 200.78181 | I37: =-I23 -> 220.85999 | J37: =-J23 -> 240.73739 | K37: =-K23 -> 259.99638 | ... M37: =-M23 -> 294.88789
B38: Closing invested capital | D38: =SUM(D34:D37) -> 8535.8947 | E38: =SUM(E34:E37) -> 8497.3677 | F38: =SUM(F34:F37) -> 8459.0797 | G38: =SUM(G34:G37) -> 8429.1957 | H38: =SUM(H34:H37) -> 8445.7345 | I38: =SUM(I34:I37) -> 8461.9272 | J38: =SUM(J34:J37) -> 8479.5772 | K38: =SUM(K34:K37) -> 8498.6393 | ... M38: =SUM(M34:M37) -> 8540.6558
B39: NOPAT (row 20) | D39: =D20 -> 217.10778 | E39: =E20 -> 347.67391 | F39: =F20 -> 522.52924 | G39: =G20 -> 705.99358 | H39: =H20 -> 921.51676 | I39: =I20 -> 1013.6684 | J39: =J20 -> 1104.8986 | K39: =K20 -> 1193.2905 | ... M39: =M20 -> 1353.4301
B40: Implied ROIC (NOPAT / avg. invested capital) | D40: =IFERROR(D39/AVERAGE(D34,D38),"") -> 0.026858316 | E40: =IFERROR(E39/AVERAGE(E34,E38),"") -> 0.040822938 | F40: =IFERROR(F39/AVERAGE(F34,F38),"") -> 0.061631924 | G40: =IFERROR(G39/AVERAGE(G34,G38),"") -> 0.083607539 | H40: =IFERROR(H39/AVERAGE(H34,H38),"") -> 0.10921725 | I40: =IFERROR(I39/AVERAGE(I34,I38),"") -> 0.1199064 | J40: =IFERROR(J39/AVERAGE(J34,J38),"") -> 0.13043689 | K40: =IFERROR(K39/AVERAGE(K34,K38),"") -> 0.14056724 | ... M40: =IFERROR(M39/AVERAGE(M34,M38),"") -> 0.15866993
B41: Reinvestment rate (net investment / NOPAT) | D41: =IFERROR(SUM(D35:D37)/D39,"") -> 4.1679515 | E41: =IFERROR(SUM(E35:E37)/E39,"") -> -0.11081357 | F41: =IFERROR(SUM(F35:F37)/F39,"") -> -0.07327432 | G41: =IFERROR(SUM(G35:G37)/G39,"") -> -0.042329087 | H41: =IFERROR(SUM(H35:H37)/H39,"") -> 0.017947386 | I41: =IFERROR(SUM(I35:I37)/I39,"") -> 0.015974354 | J41: =IFERROR(SUM(J35:J37)/J39,"") -> 0.015974354 | K41: =IFERROR(SUM(K35:K37)/K39,"") -> 0.015974354 | ... M41: =IFERROR(SUM(M35:M37)/M39,"") -> 0.015974354
B42: Implied terminal RONIC (g / reinvestment rate) | N42: =IFERROR($C$27/M41,"") -> 2.1910119
D43: Opening IC = Model 2025A book IC (equity + net debt), rolled forward with capex, acquisitions (Zonda $0.8bn), D&A and working capital.
B44: 3. VALUATION SUMMARY
B45: Sum of PV (explicit + fade) | C45: =SUM(D31:M31) -> 4392.6061
B46: PV of Terminal Value | C46: =N31 -> 10778.671
B47: Enterprise Value | C47: =C45+C46 -> 15171.277
B48: Less: Net debt + NCI (Model 2026E YE, post-Zonda) | C48: =Model!CA383+Model!CA296 -> 350.16284 | D48: CSGP-specific: Domain NCI (Model BS) deducted alongside net debt; YE2026E net debt is after the $0.8bn Zonda payment and 2026 buybacks.
B49: Equity Value | C49: =C47-C48 -> 14821.114
B50: Diluted shares (m, Model 2026E YE) | C50: =Model!CA389 -> 402.32637
B51: Implied share price ($) | C51: =C49/C50 -> 36.838534
B52: Current share price ($) | C52: =Model!CA388 -> 30.78
B53: Implied upside / (downside) | C53: =C51/C52-1 -> 0.19683347
B54: Required discount to DCF value for target IRR | C54: =1-((1+C13)/(1+H54))^H55 -> 0.14422496 | D54: vs. current | E54: Target IRR | H54: 0.15
B55: Max entry price for target IRR ($) | C55: =C51*(1-C54) -> 31.525498 | D55: =C55/C52-1 -> 0.024220212 | E55: Years for discount to close | H55: 3
B58: 4. SENSITIVITY: IMPLIED PRICE ($) — WACC × Terminal Growth
D60: WACC →
B61: Terminal growth ↓ | D61: =F61-0.01 -> 0.08182 | E61: =F61-0.005 -> 0.08682 | F61: =$C$13 -> 0.09182 | G61: =F61+0.005 -> 0.09682 | H61: =F61+0.01 -> 0.10182
B62: =B64-0.01 -> 0.025 | D62: =IFERROR((SUMPRODUCT($D$24:$M$24,1/(1+D$61)^$D$29:$M$29)+($M$24*(1+$B62)/(D$61-$B62))/(1+D$61)^$M$29-$C$48)/$C$50,"") -> 39.59157 | E62: =IFERROR((SUMPRODUCT($D$24:$M$24,1/(1+E$61)^$D$29:$M$29)+($M$24*(1+$B62)/(E$61-$B62))/(1+E$61)^$M$29-$C$48)/$C$50,"") -> 35.813295 | F62: =IFERROR((SUMPRODUCT($D$24:$M$24,1/(1+F$61)^$D$29:$M$29)+($M$24*(1+$B62)/(F$61-$B62))/(1+F$61)^$M$29-$C$48)/$C$50,"") -> 32.609016 | G62: =IFERROR((SUMPRODUCT($D$24:$M$24,1/(1+G$61)^$D$29:$M$29)+($M$24*(1+$B62)/(G$61-$B62))/(1+G$61)^$M$29-$C$48)/$C$50,"") -> 29.858593 | H62: =IFERROR((SUMPRODUCT($D$24:$M$24,1/(1+H$61)^$D$29:$M$29)+($M$24*(1+$B62)/(H$61-$B62))/(1+H$61)^$M$29-$C$48)/$C$50,"") -> 27.473178
B63: =B64-0.005 -> 0.03 | D63: =IFERROR((SUMPRODUCT($D$24:$M$24,1/(1+D$61)^$D$29:$M$29)+($M$24*(1+$B63)/(D$61-$B63))/(1+D$61)^$M$29-$C$48)/$C$50,"") -> 42.533121 | E63: =IFERROR((SUMPRODUCT($D$24:$M$24,1/(1+E$61)^$D$29:$M$29)+($M$24*(1+$B63)/(E$61-$B63))/(1+E$61)^$M$29-$C$48)/$C$50,"") -> 38.187148 | F63: =IFERROR((SUMPRODUCT($D$24:$M$24,1/(1+F$61)^$D$29:$M$29)+($M$24*(1+$B63)/(F$61-$B63))/(1+F$61)^$M$29-$C$48)/$C$50,"") -> 34.552733 | G63: =IFERROR((SUMPRODUCT($D$24:$M$24,1/(1+G$61)^$D$29:$M$29)+($M$24*(1+$B63)/(G$61-$B63))/(1+G$61)^$M$29-$C$48)/$C$50,"") -> 31.469893 | H63: =IFERROR((SUMPRODUCT($D$24:$M$24,1/(1+H$61)^$D$29:$M$29)+($M$24*(1+$B63)/(H$61-$B63))/(1+H$61)^$M$29-$C$48)/$C$50,"") -> 28.823205
B64: =$C$27 -> 0.035 | D64: =IFERROR((SUMPRODUCT($D$24:$M$24,1/(1+D$61)^$D$29:$M$29)+($M$24*(1+$B64)/(D$61-$B64))/(1+D$61)^$M$29-$C$48)/$C$50,"") -> 46.102941 | E64: =IFERROR((SUMPRODUCT($D$24:$M$24,1/(1+E$61)^$D$29:$M$29)+($M$24*(1+$B64)/(E$61-$B64))/(1+E$61)^$M$29-$C$48)/$C$50,"") -> 41.019097 | F64: =IFERROR((SUMPRODUCT($D$24:$M$24,1/(1+F$61)^$D$29:$M$29)+($M$24*(1+$B64)/(F$61-$B64))/(1+F$61)^$M$29-$C$48)/$C$50,"") -> 36.838534 | G64: =IFERROR((SUMPRODUCT($D$24:$M$24,1/(1+G$61)^$D$29:$M$29)+($M$24*(1+$B64)/(G$61-$B64))/(1+G$61)^$M$29-$C$48)/$C$50,"") -> 33.341837 | H64: =IFERROR((SUMPRODUCT($D$24:$M$24,1/(1+H$61)^$D$29:$M$29)+($M$24*(1+$B64)/(H$61-$B64))/(1+H$61)^$M$29-$C$48)/$C$50,"") -> 30.375271
B65: =B64+0.005 -> 0.04 | D65: =IFERROR((SUMPRODUCT($D$24:$M$24,1/(1+D$61)^$D$29:$M$29)+($M$24*(1+$B65)/(D$61-$B65))/(1+D$61)^$M$29-$C$48)/$C$50,"") -> 50.526376 | E65: =IFERROR((SUMPRODUCT($D$24:$M$24,1/(1+E$61)^$D$29:$M$29)+($M$24*(1+$B65)/(E$61-$B65))/(1+E$61)^$M$29-$C$48)/$C$50,"") -> 44.455904 | F65: =IFERROR((SUMPRODUCT($D$24:$M$24,1/(1+F$61)^$D$29:$M$29)+($M$24*(1+$B65)/(F$61-$B65))/(1+F$61)^$M$29-$C$48)/$C$50,"") -> 39.565439 | G65: =IFERROR((SUMPRODUCT($D$24:$M$24,1/(1+G$61)^$D$29:$M$29)+($M$24*(1+$B65)/(G$61-$B65))/(1+G$61)^$M$29-$C$48)/$C$50,"") -> 35.543232 | H65: =IFERROR((SUMPRODUCT($D$24:$M$24,1/(1+H$61)^$D$29:$M$29)+($M$24*(1+$B65)/(H$61-$B65))/(1+H$61)^$M$29-$C$48)/$C$50,"") -> 32.1784
B66: =B64+0.01 -> 0.045 | D66: =IFERROR((SUMPRODUCT($D$24:$M$24,1/(1+D$61)^$D$29:$M$29)+($M$24*(1+$B66)/(D$61-$B66))/(1+D$61)^$M$29-$C$48)/$C$50,"") -> 56.151179 | E66: =IFERROR((SUMPRODUCT($D$24:$M$24,1/(1+E$61)^$D$29:$M$29)+($M$24*(1+$B66)/(E$61-$B66))/(1+E$61)^$M$29-$C$48)/$C$50,"") -> 48.714521 | F66: =IFERROR((SUMPRODUCT($D$24:$M$24,1/(1+F$61)^$D$29:$M$29)+($M$24*(1+$B66)/(F$61-$B66))/(1+F$61)^$M$29-$C$48)/$C$50,"") -> 42.874767 | G66: =IFERROR((SUMPRODUCT($D$24:$M$24,1/(1+G$61)^$D$29:$M$29)+($M$24*(1+$B66)/(G$61-$B66))/(1+G$61)^$M$29-$C$48)/$C$50,"") -> 38.169443 | H66: =IFERROR((SUMPRODUCT($D$24:$M$24,1/(1+H$61)^$D$29:$M$29)+($M$24*(1+$B66)/(H$61-$B66))/(1+H$61)^$M$29-$C$48)/$C$50,"") -> 34.298869
B69: 5. REVERSE DCF
B70: To solve for the market-implied path: Data ▸ What-If Analysis ▸ Goal Seek — set C51 to the current price (C52) by changing C27 (terminal growth) or DCF!M26 (fade-end growth).
B72: 6. MAUBOUSSIN EV / NOPAT — TWO-STAGE FRAMEWORK
B73: EV/NOPAT = 1/r + [g × (1 − r/ROIIC) / (r × (r − g))] × [1 − ((1+g)/(1+r))^N]
B74: Formula source: Mauboussin & Rappaport, "Expectations Investing" (2021); Counterpoint Global, "What Does a Price-Earnings Multiple Mean?" (2014)
B76: Input | C76: Value | D76: Rationale (CoStar Group characteristics)
B77: r (Cost of capital / WACC) | C77: =$C$13 -> 0.09182 | D77: Linked from Section 1 WACC build
B78: g (NOPAT growth, Stage 1) | C78: 0.12 | D78: Model Adjusted EBIT CAGR 2026–30E ~30% (Homes.com investment roll-off) normalising; 12% through-cycle subscription + marketplace growth.
B79: ROIIC (Return on incremental invested capital) | C79: 0.3 | D79: Asset-light subscription data (CoStar ~40% margins, ~90% renewal) and marketplaces; acquisitions (Matterport, Domain, Zonda) dilute incremental returns.
B80: N (Years of value creation / CAP) | C80: 15 | D80: Proprietary research database (35+ years), network effects in Apartments.com/LoopNet; AI disruption risk to listings portals caps duration.
B82: Calculation | C82: Value
B83: Steady-state component: 1 / r | C83: =1/C77 -> 10.890873
B84: Value-creation factor: 1 − r / ROIIC | C84: =1-C77/C79 -> 0.69393333
B85: Growth multiplier: g × (1 − r/ROIIC) / (r × (r − g)) | C85: =C78*C84/(C77*(C77-C78)) -> -32.18257
B86: Time decay: 1 − ((1+g)/(1+r))^N | C86: =1-((1+C78)/(1+C77))^C80 -> -0.46556356
B87: PVGO component (growth value) | C87: =C85*C86 -> 14.983032
B88: Mauboussin EV / NOPAT (steady-state + PVGO) | C88: =C83+C87 -> 25.873905
B90: VALUATION — Applied to 2028E NOPAT | C90: USDm
B91: 2028E Adj. EBIT less SBC and acquisition costs | C91: =Model!CC175-Model!CC162-Model!CC163 -> 706.1206
B92: Tax rate (from WACC build) | C92: =$C$10 -> 0.26
B93: 2028E NOPAT | C93: =C91*(1-C92) -> 522.52924
B94: × Mauboussin EV/NOPAT multiple | C94: =C88 -> 25.873905
B95: Implied Enterprise Value (2028E basis) | C95: =C93*C94 -> 13519.872
B96: Less: YE2027 net debt + NCI (Model) | C96: =Model!CB383+Model!CB296 -> 514.9867
B97: Implied Equity Value | C97: =C95-C96 -> 13004.885
B98: Diluted shares 2028E (m, Model) | C98: =Model!CC389 -> 352.92597
B99: Implied share price 2028 ($) | C99: =C97/C98 -> 36.848762
B101: Current share price ($) | C101: =C52 -> 30.78
B102: Implied upside / (downside) | C102: =C99/C101-1 -> 0.19716577
B104: MARKET-IMPLIED EV/NOPAT TODAY | C104: USDm
B105: Current market cap (spot × diluted shares) | C105: =C52*C50 -> 12383.606
B106: Plus: YE2026 net debt + NCI | C106: =C48 -> 350.16284
B107: Implied Enterprise Value (today) | C107: =C105+C106 -> 12733.769
B108: CSGP market-implied EV/NOPAT (on 2028E NOPAT) | C108: =C107/C93 -> 24.369485
B110: Multiple gap (Mauboussin − Market) | C110: =C88-C108 -> 1.5044201
B111: Implied re-rating headroom | C111: =C88/C108-1 -> 0.061733766

Sheet Charts
B2: CoStar Group — Historical Operating Performance (2006–2025)
B3: All historicals · USDm · Linked to Model. Revenue growth vs Adjusted EBITDA growth; Adjusted EBITDA = company definition in force (EBITDA to 2008).
C7: 2006 | D7: 2007 | E7: 2008 | F7: 2009 | G7: 2010 | H7: 2011 | I7: 2012 | J7: 2013 | K7: 2014 | L7: 2015 | M7: 2016 | N7: 2017 | O7: 2018 | P7: 2019 | Q7: 2020 | R7: 2021 | S7: 2022 | T7: 2023 | U7: 2024 | V7: 2025
B8: Revenues y/y % | C8: =IFERROR(Model!C203+0,NA()) -> 0 | D8: =IFERROR(Model!D203+0,NA()) -> 0.21345719 | E8: =IFERROR(Model!E203+0,NA()) -> 0.10177641 | F8: =IFERROR(Model!F203+0,NA()) -> -0.013035005 | G8: =IFERROR(Model!G203+0,NA()) -> 0.079180956 | H8: =IFERROR(Model!H203+0,NA()) -> 0.11260497 | I8: =IFERROR(Model!I203+0,NA()) -> 0.39008016 | J8: =IFERROR(Model!N203+0,NA()) -> 0.26006756 | K8: =IFERROR(Model!S203+0,NA()) -> 0.30614615 | L8: =IFERROR(Model!X203+0,NA()) -> 0.2358387 | M8: =IFERROR(Model!AC203+0,NA()) -> 0.1768367 | N8: =IFERROR(Model!AH203+0,NA()) -> 0.15233456 | O8: =IFERROR(Model!AM203+0,NA()) -> 0.23476477 | P8: =IFERROR(Model!AR203+0,NA()) -> 0.17442643 | Q8: =IFERROR(Model!AW203+0,NA()) -> 0.18525147 | R8: =IFERROR(Model!BB203+0,NA()) -> 0.17185819 | S8: =IFERROR(Model!BG203+0,NA()) -> 0.12255528 | T8: =IFERROR(Model!BL203+0,NA()) -> 0.12490887 | U8: =IFERROR(Model!BQ203+0,NA()) -> 0.11454175 | V8: =IFERROR(Model!BV203+0,NA()) -> 0.18668226
B9: Adjusted EBITDA y/y % | C9: =IFERROR(Model!C206+0,NA()) -> 0 | D9: =IFERROR(Model!D206+0,NA()) -> 0.31320973 | E9: =IFERROR(Model!E206+0,NA()) -> 0.66443131 | F9: =IFERROR(Model!F206+0,NA()) -> -0.039884076 | G9: =IFERROR(Model!G206+0,NA()) -> -0.055492159 | H9: =IFERROR(Model!H206+0,NA()) -> 0.10971023 | I9: =IFERROR(Model!I206+0,NA()) -> 0.51716508 | J9: =IFERROR(Model!N206+0,NA()) -> 0.58291859 | K9: =IFERROR(Model!S206+0,NA()) -> 0.37808293 | L9: =IFERROR(Model!X206+0,NA()) -> -0.28030223 | M9: =IFERROR(Model!AC206+0,NA()) -> 0.88382483 | N9: =IFERROR(Model!AH206+0,NA()) -> 0.09497421 | O9: =IFERROR(Model!AM206+0,NA()) -> 0.49405626 | P9: =IFERROR(Model!AR206+0,NA()) -> 0.21213716 | Q9: =IFERROR(Model!AW206+0,NA()) -> 0.091742649 | R9: =IFERROR(Model!BB206+0,NA()) -> 0.17032607 | S9: =IFERROR(Model!BG206+0,NA()) -> 0.03723 | T9: =IFERROR(Model!BL206+0,NA()) -> -0.26777074 | U9: =IFERROR(Model!BQ206+0,NA()) -> -0.51027049 | V9: =IFERROR(Model!BV206+0,NA()) -> 0.83554817
C11: =C7 -> 2006 | D11: =D7 -> 2007 | E11: =E7 -> 2008 | F11: =F7 -> 2009 | G11: =G7 -> 2010 | H11: =H7 -> 2011 | I11: =I7 -> 2012 | J11: =J7 -> 2013 | ... V11: =V7 -> 2025
B12: Adjusted EBITDA | C12: =IFERROR(Model!C168+0,0) -> 25.89 | D12: =IFERROR(Model!D168+0,0) -> 33.999 | E12: =IFERROR(Model!E168+0,0) -> 56.589 | F12: =IFERROR(Model!F168+0,0) -> 54.332 | G12: =IFERROR(Model!G168+0,0) -> 51.317 | H12: =IFERROR(Model!H168+0,0) -> 56.947 | I12: =IFERROR(Model!I168+0,0) -> 86.398 | J12: =IFERROR(Model!N168+0,0) -> 136.761 | K12: =IFERROR(Model!S168+0,0) -> 188.468 | L12: =IFERROR(Model!X168+0,0) -> 135.64 | M12: =IFERROR(Model!AC168+0,0) -> 255.522 | N12: =IFERROR(Model!AH168+0,0) -> 279.79 | O12: =IFERROR(Model!AM168+0,0) -> 418.022 | P12: =IFERROR(Model!AR168+0,0) -> 506.7 | Q12: =IFERROR(Model!AW168+0,0) -> 553.186 | R12: =IFERROR(Model!BB168+0,0) -> 647.408 | S12: =IFERROR(Model!BG168+0,0) -> 671.511 | T12: =IFERROR(Model!BL168+0,0) -> 491.7 | U12: =IFERROR(Model!BQ168+0,0) -> 240.8 | V12: =IFERROR(Model!BV168+0,0) -> 442
B13: Income from Operations (GAAP) | C13: =IFERROR(Model!C131+0,0) -> 14.081 | D13: =IFERROR(Model!D131+0,0) -> 17.852 | E13: =IFERROR(Model!E131+0,0) -> 39.788 | F13: =IFERROR(Model!F131+0,0) -> 31.835 | G13: =IFERROR(Model!G131+0,0) -> 22.775 | H13: =IFERROR(Model!H131+0,0) -> 21.771 | I13: =IFERROR(Model!I131+0,0) -> 27.44 | J13: =IFERROR(Model!N131+0,0) -> 54.154 | K13: =IFERROR(Model!S131+0,0) -> 80.878 | L13: =IFERROR(Model!X131+0,0) -> 11.455 | M13: =IFERROR(Model!AC131+0,0) -> 144.905 | N13: =IFERROR(Model!AH131+0,0) -> 173.816 | O13: =IFERROR(Model!AM131+0,0) -> 273.564 | P13: =IFERROR(Model!AR131+0,0) -> 363.547 | Q13: =IFERROR(Model!AW131+0,0) -> 289.202 | R13: =IFERROR(Model!BB131+0,0) -> 432.337 | S13: =IFERROR(Model!BG131+0,0) -> 450.949 | T13: =IFERROR(Model!BL131+0,0) -> 282.3 | U13: =IFERROR(Model!BQ131+0,0) -> 4.7 | V13: =IFERROR(Model!BV131+0,0) -> -72
B14: Adj. EBITDA Margin % | C14: =IFERROR(Model!C169+0,0) -> 0.16294394 | D14: =IFERROR(Model!D169+0,0) -> 0.17633879 | E14: =IFERROR(Model!E169+0,0) -> 0.26639144 | F14: =IFERROR(Model!F169+0,0) -> 0.25914461 | G14: =IFERROR(Model!G169+0,0) -> 0.22680545 | H14: =IFERROR(Model!H169+0,0) -> 0.22621535 | I14: =IFERROR(Model!I169+0,0) -> 0.24689658 | J14: =IFERROR(Model!N169+0,0) -> 0.31015573 | K14: =IFERROR(Model!S169+0,0) -> 0.32723775 | L14: =IFERROR(Model!X169+0,0) -> 0.19056878 | M14: =IFERROR(Model!AC169+0,0) -> 0.30505354 | N14: =IFERROR(Model!AH169+0,0) -> 0.28986874 | O14: =IFERROR(Model!AM169+0,0) -> 0.35073903 | P14: =IFERROR(Model!AR169+0,0) -> 0.36200123 | Q14: =IFERROR(Model!AW169+0,0) -> 0.33344163 | R14: =IFERROR(Model!BB169+0,0) -> 0.33300568 | S14: =IFERROR(Model!BG169+0,0) -> 0.30769396 | T14: =IFERROR(Model!BL169+0,0) -> 0.20028513 | U14: =IFERROR(Model!BQ169+0,0) -> 0.088005263 | V14: =IFERROR(Model!BV169+0,0) -> 0.13612565
B15: GAAP Op. Margin % | C15: =IFERROR(Model!C213+0,0) -> 0.088621616 | D15: =IFERROR(Model!D213+0,0) -> 0.09259096 | E15: =IFERROR(Model!E213+0,0) -> 0.18730111 | F15: =IFERROR(Model!F213+0,0) -> 0.1518418 | G15: =IFERROR(Model!G213+0,0) -> 0.10065853 | H15: =IFERROR(Model!H213+0,0) -> 0.086482772 | I15: =IFERROR(Model!I213+0,0) -> 0.078414339 | J15: =IFERROR(Model!N213+0,0) -> 0.12281406 | K15: =IFERROR(Model!S213+0,0) -> 0.1404288 | L15: =IFERROR(Model!X213+0,0) -> 0.016093818 | M15: =IFERROR(Model!AC213+0,0) -> 0.17299404 | N15: =IFERROR(Model!AH213+0,0) -> 0.18007729 | O15: =IFERROR(Model!AM213+0,0) -> 0.22953235 | P15: =IFERROR(Model!AR213+0,0) -> 0.25972856 | Q15: =IFERROR(Model!AW213+0,0) -> 0.17432109 | R15: =IFERROR(Model!BB213+0,0) -> 0.22238013 | S15: =IFERROR(Model!BG213+0,0) -> 0.20662995 | T15: =IFERROR(Model!BL213+0,0) -> 0.11498982 | U15: =IFERROR(Model!BQ213+0,0) -> 0.0017177107 | V15: =IFERROR(Model!BV213+0,0) -> -0.022174315
C17: =C7 -> 2006 | D17: =D7 -> 2007 | E17: =E7 -> 2008 | F17: =F7 -> 2009 | G17: =G7 -> 2010 | H17: =H7 -> 2011 | I17: =I7 -> 2012 | J17: =J7 -> 2013 | ... V17: =V7 -> 2025
B18: ROIC | C18: =IFERROR(Model!C366+0,NA()) -> 0.091870555 | D18: =IFERROR(Model!D366+0,NA()) -> 0.11349135 | E18: =IFERROR(Model!E366+0,NA()) -> 0.22069501 | F18: =IFERROR(Model!F366+0,NA()) -> 0.17885622 | G18: =IFERROR(Model!G366+0,NA()) -> 0.13187921 | H18: =IFERROR(Model!H366+0,NA()) -> 0.23968582 | I18: =IFERROR(Model!I366+0,NA()) -> 0.03955329 | J18: =IFERROR(Model!N366+0,NA()) -> 0.072670775 | K18: =IFERROR(Model!S366+0,NA()) -> 0.053385129 | L18: =IFERROR(Model!X366+0,NA()) -> 0.023971013 | M18: =IFERROR(Model!AC366+0,NA()) -> 0.080627939 | N18: =IFERROR(Model!AH366+0,NA()) -> 0.093077059 | O18: =IFERROR(Model!AM366+0,NA()) -> 0.13281592 | P18: =IFERROR(Model!AR366+0,NA()) -> 0.13668956 | Q18: =IFERROR(Model!AW366+0,NA()) -> 0.12554151 | R18: =IFERROR(Model!BB366+0,NA()) -> 0.1344036 | S18: =IFERROR(Model!BG366+0,NA()) -> 0.1381549 | T18: =IFERROR(Model!BL366+0,NA()) -> 0.091323397 | U18: =IFERROR(Model!BQ366+0,NA()) -> 0.023457717 | V18: =IFERROR(Model!BV366+0,NA()) -> 0.019394575
B19: RONTA | C19: =IFERROR(Model!C377+0,NA()) -> 0.037035771 | D19: =IFERROR(Model!D377+0,NA()) -> 0.05463755 | E19: =IFERROR(Model!E377+0,NA()) -> 0.10180342 | F19: =IFERROR(Model!F377+0,NA()) -> 0.092538532 | G19: =IFERROR(Model!G377+0,NA()) -> 0.07892829 | H19: =IFERROR(Model!H377+0,NA()) -> 0.044321112 | I19: =IFERROR(Model!I377+0,NA()) -> 0.17296972 | J19: =IFERROR(Model!N377+0,NA()) -> 0.19565732 | K19: =IFERROR(Model!S377+0,NA()) -> 0.1212314 | L19: =IFERROR(Model!X377+0,NA()) -> 0.07537036 | M19: =IFERROR(Model!AC377+0,NA()) -> 0.18804052 | N19: =IFERROR(Model!AH377+0,NA()) -> 0.1063221 | O19: =IFERROR(Model!AM377+0,NA()) -> 0.20281229 | P19: =IFERROR(Model!AR377+0,NA()) -> 0.23751427 | Q19: =IFERROR(Model!AW377+0,NA()) -> 0.083425807 | R19: =IFERROR(Model!BB377+0,NA()) -> 0.092772447 | S19: =IFERROR(Model!BG377+0,NA()) -> 0.074168451 | T19: =IFERROR(Model!BL377+0,NA()) -> 0.049324774 | U19: =IFERROR(Model!BQ377+0,NA()) -> 0.01578251 | V19: =IFERROR(Model!BV377+0,NA()) -> 0.048098798
B20: Adj. EBITDA margin % | C20: =IFERROR(Model!C169+0,NA()) -> 0.16294394 | D20: =IFERROR(Model!D169+0,NA()) -> 0.17633879 | E20: =IFERROR(Model!E169+0,NA()) -> 0.26639144 | F20: =IFERROR(Model!F169+0,NA()) -> 0.25914461 | G20: =IFERROR(Model!G169+0,NA()) -> 0.22680545 | H20: =IFERROR(Model!H169+0,NA()) -> 0.22621535 | I20: =IFERROR(Model!I169+0,NA()) -> 0.24689658 | J20: =IFERROR(Model!N169+0,NA()) -> 0.31015573 | K20: =IFERROR(Model!S169+0,NA()) -> 0.32723775 | L20: =IFERROR(Model!X169+0,NA()) -> 0.19056878 | M20: =IFERROR(Model!AC169+0,NA()) -> 0.30505354 | N20: =IFERROR(Model!AH169+0,NA()) -> 0.28986874 | O20: =IFERROR(Model!AM169+0,NA()) -> 0.35073903 | P20: =IFERROR(Model!AR169+0,NA()) -> 0.36200123 | Q20: =IFERROR(Model!AW169+0,NA()) -> 0.33344163 | R20: =IFERROR(Model!BB169+0,NA()) -> 0.33300568 | S20: =IFERROR(Model!BG169+0,NA()) -> 0.30769396 | T20: =IFERROR(Model!BL169+0,NA()) -> 0.20028513 | U20: =IFERROR(Model!BQ169+0,NA()) -> 0.088005263 | V20: =IFERROR(Model!BV169+0,NA()) -> 0.13612565
B21: FCF margin % | C21: =IFERROR(Model!C250+0,NA()) -> 0.12456495 | D21: =IFERROR(Model!D250+0,NA()) -> 0.19429475 | E21: =IFERROR(Model!E250+0,NA()) -> 0.17536295 | F21: =IFERROR(Model!F250+0,NA()) -> 0.13843908 | G21: =IFERROR(Model!G250+0,NA()) -> -0.079947848 | H21: =IFERROR(Model!H250+0,NA()) -> 0.042393282 | I21: =IFERROR(Model!I250+0,NA()) -> 0.20372868 | J21: =IFERROR(Model!N250+0,NA()) -> 0.20242072 | K21: =IFERROR(Model!S250+0,NA()) -> 0.20221865 | L21: =IFERROR(Model!X250+0,NA()) -> 0.13513468 | M21: =IFERROR(Model!AC250+0,NA()) -> 0.21152299 | N21: =IFERROR(Model!AH250+0,NA()) -> 0.21777607 | O21: =IFERROR(Model!AM250+0,NA()) -> 0.2566016 | P21: =IFERROR(Model!AR250+0,NA()) -> 0.29404688 | Q21: =IFERROR(Model!AW250+0,NA()) -> 0.26386618 | R21: =IFERROR(Model!BB250+0,NA()) -> 0.14440715 | S21: =IFERROR(Model!BG250+0,NA()) -> 0.17635501 | T21: =IFERROR(Model!BL250+0,NA()) -> 0.141222 | U21: =IFERROR(Model!BQ250+0,NA()) -> -0.089649879 | V21: =IFERROR(Model!BV250+0,NA()) -> 0.01262704
