Workbook

Sheet Model
CF1: SCENARIO SWITCH ▼ (Bull / Base / Bear) — drives all scenario-linked forecast drivers
B2: Curtiss-Wright Corporation (NYSE: CW) — 3-Statement Financial Model | CF2: Base
B3: US GAAP as reported · USD millions (per-share data in USD; shares in millions) · Source: Curtiss-Wright Forms 10-K / 10-Q and Form 8-K earnings releases (Ex. 99.1), 10b5-1 / credit-agreement 8-Ks (2026), SEC EDGAR CIK 0000026324 (investor-relations releases are the same documents as filed on EDGAR)
B4: Basis notes: calendar fiscal year. Segments: Flow Control / Motion Control / Metal Treatment (to 2012) → Flow Control / Controls / Surface Technologies (2013) → Commercial/Industrial, Defense, Energy→Power (2014–2020) → Aerospace & Industrial, Defense Electronics, Naval & Power (current; 2020 restated in the 2021 releases). Adjusted (non-GAAP) framework from Q2/18 (first-year purchase accounting; later restructuring, exited businesses, activism, legal, FY26 Restructuring Program and 2026 equity-securities gain). Income statement as originally reported in each period (discontinued operations 2012–17; ASU 2017-07 pension reclass from 2018). FY26 guidance raised 5-Aug-2026; $300m of 10b5-1 buybacks Aug–Oct 2026; $200m 4.24% notes mature Dec-2026.
CH5: Forecast | CI5: Historical | CJ5: Historical | CK5: Historical
B6: (USDm) | C6: 2006 | D6: 2007 | E6: 2008 | F6: 2009 | G6: 2010 | H6: 2011 | I6: 2012 | J6: Q1/13 | K6: Q2/13 | L6: Q3/13 | M6: Q4/13 | N6: 2013 | O6: Q1/14 | P6: Q2/14 | Q6: Q3/14 | R6: Q4/14 | S6: 2014 | T6: Q1/15 | U6: Q2/15 | V6: Q3/15 | W6: Q4/15 | X6: 2015 | Y6: Q1/16 | Z6: Q2/16 | AA6: Q3/16 | AB6: Q4/16 | AC6: 2016 | AD6: Q1/17 | AE6: Q2/17 | AF6: Q3/17 | AG6: Q4/17 | AH6: 2017 | AI6: Q1/18 | AJ6: Q2/18 | AK6: Q3/18 | AL6: Q4/18 | AM6: 2018 | AN6: Q1/19 | AO6: Q2/19 | AP6: Q3/19 | AQ6: Q4/19 | AR6: 2019 | AS6: Q1/20 | AT6: Q2/20 | AU6: Q3/20 | AV6: Q4/20 | AW6: 2020 | AX6: Q1/21 | AY6: Q2/21 | AZ6: Q3/21 | BA6: Q4/21 | BB6: 2021 | BC6: Q1/22 | BD6: Q2/22 | BE6: Q3/22 | BF6: Q4/22 | BG6: 2022 | BH6: Q1/23 | BI6: Q2/23 | BJ6: Q3/23 | BK6: Q4/23 | BL6: 2023 | BM6: Q1/24 | BN6: Q2/24 | BO6: Q3/24 | BP6: Q4/24 | BQ6: 2024 | BR6: Q1/25 | BS6: Q2/25 | BT6: Q3/25 | BU6: Q4/25 | BV6: 2025 | BW6: Q1/26 | BX6: Q2/26 | BY6: Q3/26E | BZ6: Q4/26E | CA6: 2026E | CB6: 2027E | CC6: 2028E | CD6: 2029E | CE6: 2030E | CF6: Modelling Notes | CH6: 5Y CAGR | CI6: 5Y CAGR | CJ6: 10Y CAGR | CK6: 19Y CAGR
CH7: 25-'30 | CI7: 20-'25 | CJ7: 15-'25 | CK7: 06-'25
B8: SEGMENT P&L — AEROSPACE & INDUSTRIAL · DEFENSE ELECTRONICS · NAVAL & POWER (growth × incremental-margin build) | CF8: SEGMENT BUILD — modelling logic (sales growth → sales → Adjusted OI via incremental margins)
CM9: SCENARIO INPUT TABLE — driver assumptions per Bull / Base / Bear | CN9: Bull | CO9: Base | CP9: Bear | CQ9: Bull / Bear = Base + Δ (Δ inputs on each lever header). Outlook block = high / mid / low end of the FY26 guidance ranges.
B10: Aerospace & Industrial (actuation, sensors & controls, surface treatment, industrial vehicles & valves) — current segment basis from Q1/20 | CF10: AEROSPACE & INDUSTRIAL — modelling logic
B11: Sales | AS11: 226.728 | AT11: 177.411 | AU11: 188.768 | AV11: 212.766 | AW11: 805.673 | AX11: 180.331 | AY11: 199.713 | AZ11: 196.296 | BA11: 209.994 | BB11: 786.334 | BC11: 191.112 | BD11: 208.572 | BE11: 213.093 | BF11: 223.258 | BG11: 836.035 | BH11: 202.447 | BI11: 226.26 | BJ11: 220.297 | BK11: 238.224 | BL11: 887.228 | BM11: 219.325 | BN11: 233.232 | BO11: 228.659 | BP11: 250.917 | BQ11: 932.133 | BR11: 227.246 | BS11: 239.138 | BT11: 247.985 | BU11: 262.391 | BV11: 976.76 | BW11: 254.919 | BX11: 267.765 | BY11: =BT11*(1+BY13) -> 263.01834 | BZ11: =BU11*(1+BZ13) -> 278.29766 | CA11: =SUM(BW11,BX11,BY11,BZ11) -> 1064 | CB11: =CA11*(1+CB13) -> 1138.48 | CC11: =CB11*(1+CC13) -> 1212.4812 | CD11: =CC11*(1+CD13) -> 1285.2301 | CE11: =CD11*(1+CE13) -> 1362.3439 | CF11: Q3/Q4-26E: prior-year quarter × (1 + guidance-implied 2H/26 y/y growth + revenue calibration Δ). 2027E+: prior year × (1 + scenario lever). | CH11: =IFERROR((CE11/BV11)^(1/5)-1,"n/m") -> 0.068808196 | CI11: =IFERROR((BV11/AW11)^(1/5)-1,"n/m") -> 0.039263827 | CJ11: =IFERROR((BV11/X11)^(1/10)-1,"n/m") -> n/m | CK11: =IFERROR((BV11/C11)^(1/19)-1,"n/m") -> n/m | CM11: FY26 outlook — Q2-26 release (5-Aug-26), Adjusted (non-GAAP) | CN11: High | CO11: Mid | CP11: Low | CQ11: Raised on 5-Aug-26 (Form 8-K Ex. 99.1, guidance tables). Segment ranges drive the Q3/Q4-26E build; total ranges drive the calibration.
B12: Sales y/y % | D12: =IF(AND(ISNUMBER(D11),ISNUMBER(C11)),IFERROR(D11/C11-1,""),"") | E12: =IF(AND(ISNUMBER(E11),ISNUMBER(D11)),IFERROR(E11/D11-1,""),"") | F12: =IF(AND(ISNUMBER(F11),ISNUMBER(E11)),IFERROR(F11/E11-1,""),"") | G12: =IF(AND(ISNUMBER(G11),ISNUMBER(F11)),IFERROR(G11/F11-1,""),"") | H12: =IF(AND(ISNUMBER(H11),ISNUMBER(G11)),IFERROR(H11/G11-1,""),"") | I12: =IF(AND(ISNUMBER(I11),ISNUMBER(H11)),IFERROR(I11/H11-1,""),"") | N12: =IF(AND(ISNUMBER(N11),ISNUMBER(I11)),IFERROR(N11/I11-1,""),"") | O12: =IF(AND(ISNUMBER(O11),ISNUMBER(J11)),IFERROR(O11/J11-1,""),"") | P12: =IF(AND(ISNUMBER(P11),ISNUMBER(K11)),IFERROR(P11/K11-1,""),"") | Q12: =IF(AND(ISNUMBER(Q11),ISNUMBER(L11)),IFERROR(Q11/L11-1,""),"") | R12: =IF(AND(ISNUMBER(R11),ISNUMBER(M11)),IFERROR(R11/M11-1,""),"") | S12: =IF(AND(ISNUMBER(S11),ISNUMBER(N11)),IFERROR(S11/N11-1,""),"") | T12: =IF(AND(ISNUMBER(T11),ISNUMBER(O11)),IFERROR(T11/O11-1,""),"") | U12: =IF(AND(ISNUMBER(U11),ISNUMBER(P11)),IFERROR(U11/P11-1,""),"") | ... BX12: =IF(AND(ISNUMBER(BX11),ISNUMBER(BS11)),IFERROR(BX11/BS11-1,""),"") -> 0.11970912 | BY12: =IFERROR(BY11/BT11-1,"") -> 0.060621973 | BZ12: =IFERROR(BZ11/BU11-1,"") -> 0.060621973 | CA12: =IFERROR(CA11/BV11-1,"") -> 0.089315697 | CB12: =IFERROR(CB11/CA11-1,"") -> 0.07 | CC12: =IFERROR(CC11/CB11-1,"") -> 0.065 | CD12: =IFERROR(CD11/CC11-1,"") -> 0.06 | CE12: =IFERROR(CE11/CD11-1,"") -> 0.06 | CM12: FY26 total sales ($m) | CN12: 3813 | CO12: 3790.5 | CP12: 3768 | CQ12: Raised to $3,768–3,813m (from $3,740–3,795m); +8–9% vs 2025.
B13: Forecast sales growth driver % (Q3/Q4-26E: guidance-implied 2H y/y + calibration; 2027E+: lever) | BY13: =($CA$21-$BW$11-$BX$11)/($BT$11+$BU$11)-1+BY89 -> 0.060621973 | BZ13: =($CA$21-$BW$11-$BX$11)/($BT$11+$BU$11)-1+BZ89 -> 0.060621973 | CA13: =IFERROR(CA11/BV11-1,"") -> 0.089315697 | CB13: =CHOOSE(MATCH($CF$2,{"Bull","Base","Bear"},0),$CN$40,$CO$40,$CP$40) -> 0.07 | CC13: =CHOOSE(MATCH($CF$2,{"Bull","Base","Bear"},0),$CN$41,$CO$41,$CP$41) -> 0.065 | CD13: =CHOOSE(MATCH($CF$2,{"Bull","Base","Bear"},0),$CN$42,$CO$42,$CP$42) -> 0.06 | CE13: =CHOOSE(MATCH($CF$2,{"Bull","Base","Bear"},0),$CN$43,$CO$43,$CP$43) -> 0.06 | CF13: FY26: (segment guidance end-point − 1H/26) ÷ 2H/25 − 1, by scenario (high / mid / low). 2027E–30E: scenario lever (table →). | CM13: FY26 Adjusted operating income ($m) | CN13: 736 | CO13: 728 | CP13: 720 | CQ13: Raised to $720–736m (from $712–729m); margin 19.1–19.3%.
B14: Operating income (GAAP, as reported) | AS14: 32.14 | AT14: 9.615 | AU14: 23.88 | AV14: 34.079 | AW14: 99.714 | AX14: 19.025 | AY14: 31.977 | AZ14: 30.872 | BA14: 39.943 | BB14: 121.817 | BC14: 24.853 | BD14: 32.464 | BE14: 39.08 | BF14: 40.599 | BG14: 136.996 | BH14: 26.545 | BI14: 35.665 | BJ14: 39.014 | BK14: 44.054 | BL14: 145.278 | BM14: 27.466 | BN14: 35.246 | BO14: 37.435 | BP14: 47.876 | BQ14: 148.023 | BR14: 29.922 | BS14: 39.006 | BT14: 45.439 | BU14: 51.799 | BV14: 166.166 | BW14: 38.498 | BX14: 49.004 | BY14: =BY17-BY16 -> 48.237616 | BZ14: =BZ17-BZ16 -> 55.483185 | CA14: =SUM(BW14,BX14,BY14,BZ14) -> 191.2228 | CB14: =CB17-CB16 -> 219.5668 | CC14: =CC17-CC16 -> 241.76716 | CD14: =CD17-CD16 -> 263.59182 | CE14: =CE17-CE16 -> 286.72596 | CM14: FY26 Adjusted diluted EPS ($) | CN14: 15.4 | CO14: 15.25 | CP14: 15.1 | CQ14: Raised to $15.10–15.40 (memo; model output compared below).
B15: Operating margin (GAAP) % | C15: =IF(AND(ISNUMBER(C14),ISNUMBER(C11)),IFERROR(C14/C11,""),"") | D15: =IF(AND(ISNUMBER(D14),ISNUMBER(D11)),IFERROR(D14/D11,""),"") | E15: =IF(AND(ISNUMBER(E14),ISNUMBER(E11)),IFERROR(E14/E11,""),"") | F15: =IF(AND(ISNUMBER(F14),ISNUMBER(F11)),IFERROR(F14/F11,""),"") | G15: =IF(AND(ISNUMBER(G14),ISNUMBER(G11)),IFERROR(G14/G11,""),"") | H15: =IF(AND(ISNUMBER(H14),ISNUMBER(H11)),IFERROR(H14/H11,""),"") | I15: =IF(AND(ISNUMBER(I14),ISNUMBER(I11)),IFERROR(I14/I11,""),"") | J15: =IF(AND(ISNUMBER(J14),ISNUMBER(J11)),IFERROR(J14/J11,""),"") | ... BX15: =IF(AND(ISNUMBER(BX14),ISNUMBER(BX11)),IFERROR(BX14/BX11,""),"") -> 0.18301122 | BY15: =IFERROR(BY14/BY11,"") -> 0.1834002 | BZ15: =IFERROR(BZ14/BZ11,"") -> 0.19936634 | CA15: =IFERROR(CA14/CA11,"") -> 0.17972068 | CB15: =IFERROR(CB14/CB11,"") -> 0.1928596 | CC15: =IFERROR(CC14/CC11,"") -> 0.19939869 | CD15: =IFERROR(CD14/CD11,"") -> 0.2050931 | CE15: =IFERROR(CE14/CE11,"") -> 0.21046519 | CM15: FY26 free cash flow ($m) | CN15: 605 | CO15: 595 | CP15: 585 | CQ15: Raised to $585–605m; capex up ~$25m y/y (memo; model output compared below).
B16: (+) Adjustments (first-year purchase accounting, restructuring, exited businesses) | AS16: -3.74 | AT16: 3.185 | AU16: -0.98 | AV16: -0.362 | AW16: -1.879 | AX16: -0.525 | AY16: -1.477 | AZ16: -0.072 | BA16: 0.493 | BB16: -1.586 | BC16: 0 | BD16: 0 | BE16: 0 | BF16: 0.703 | BG16: 0.703 | BH16: 0 | BI16: 0 | BJ16: 0 | BK16: 0 | BL16: 0 | BM16: 0 | BN16: 2.619 | BO16: 1.926 | BP16: 5.694 | BQ16: 10.239 | BR16: 1.764 | BS16: 0.582 | BT16: 0.57 | BU16: 0.938 | BV16: 3.855 | BW16: 0.703 | BX16: 0.399 | BY16: =MAX(0,($CO$30-$BW$16-$BX$16)/2) -> 2.449 | BZ16: =MAX(0,($CO$30-$BW$16-$BX$16)/2) -> 2.449 | CA16: =SUM(BW16,BX16,BY16,BZ16) -> 6 | CB16: 0 | CC16: 0 | CD16: 0 | CE16: 0 | CF16: Q3/Q4-26E: remaining FY26 Restructuring Program cost per the guidance adjustment column, spread evenly. 2027E+: none assumed. | CM16: A&I sales ($m) | CN16: 1070 | CO16: 1064 | CP16: 1058 | CQ16: +8–10% vs 2025.
B17: Adjusted operating income | AS17: =AS14+AS16 -> 28.4 | AT17: =AT14+AT16 -> 12.8 | AU17: =AU14+AU16 -> 22.9 | AV17: =AV14+AV16 -> 33.717 | AW17: =AW14+AW16 -> 97.835 | AX17: =AX14+AX16 -> 18.5 | AY17: =AY14+AY16 -> 30.5 | AZ17: =AZ14+AZ16 -> 30.8 | ... BX17: =BX14+BX16 -> 49.403 | BY17: =BY11*BY18 -> 50.686616 | BZ17: =BZ11*BZ18 -> 57.932185 | CA17: =SUM(BW17,BX17,BY17,BZ17) -> 197.2228 | CB17: =CA17+(CB11-CA11)*CB20 -> 219.5668 | CC17: =CB17+(CC11-CB11)*CC20 -> 241.76716 | CD17: =CC17+(CD11-CC11)*CD20 -> 263.59182 | CE17: =CD17+(CE11-CD11)*CE20 -> 286.72596 | CF17: 2027E+: prior-year Adjusted OI + Δ sales × incremental margin (scenario lever) — margin is an output, not an input. | CH17: =IFERROR((CE17/BV17)^(1/5)-1,"n/m") -> 0.1101787 | CI17: =IFERROR((BV17/AW17)^(1/5)-1,"n/m") -> 0.11686753 | CJ17: =IFERROR((BV17/X17)^(1/10)-1,"n/m") -> n/m | CK17: =IFERROR((BV17/C17)^(1/19)-1,"n/m") -> n/m | CM17: A&I Adjusted OI ($m) | CN17: 200 | CO17: 197.5 | CP17: 195 | CQ17: Adj. margin 18.5–18.7%.
B18: Adjusted operating margin % | C18: =IF(AND(ISNUMBER(C17),ISNUMBER(C11)),IFERROR(C17/C11,""),"") | D18: =IF(AND(ISNUMBER(D17),ISNUMBER(D11)),IFERROR(D17/D11,""),"") | E18: =IF(AND(ISNUMBER(E17),ISNUMBER(E11)),IFERROR(E17/E11,""),"") | F18: =IF(AND(ISNUMBER(F17),ISNUMBER(F11)),IFERROR(F17/F11,""),"") | G18: =IF(AND(ISNUMBER(G17),ISNUMBER(G11)),IFERROR(G17/G11,""),"") | H18: =IF(AND(ISNUMBER(H17),ISNUMBER(H11)),IFERROR(H17/H11,""),"") | I18: =IF(AND(ISNUMBER(I17),ISNUMBER(I11)),IFERROR(I17/I11,""),"") | J18: =IF(AND(ISNUMBER(J17),ISNUMBER(J11)),IFERROR(J17/J11,""),"") | ... BX18: =IF(AND(ISNUMBER(BX17),ISNUMBER(BX11)),IFERROR(BX17/BX11,""),"") -> 0.18450134 | BY18: =BY19+BY93 -> 0.19271134 | BZ18: =BZ19+BZ93 -> 0.20816627 | CA18: =IFERROR(CA17/CA11,"") -> 0.18535978 | CB18: =IFERROR(CB17/CB11,"") -> 0.1928596 | CC18: =IFERROR(CC17/CC11,"") -> 0.19939869 | CD18: =IFERROR(CD17/CD11,"") -> 0.2050931 | CE18: =IFERROR(CE17/CE11,"") -> 0.21046519 | CH18: =IFERROR(AVERAGE(CA18,CB18,CC18,CD18,CE18),"n/m") -> 0.19863527 | CI18: =IFERROR(AVERAGE(BB18,BG18,BL18,BQ18,BV18),"n/m") -> 0.16504006 | CJ18: =IFERROR(AVERAGE(AC18,AH18,AM18,AR18,AW18,BB18,BG18,BL18,BQ18,BV18),"n/m") -> 0.15777216 | CK18: =IFERROR(AVERAGE(C18,D18,E18,F18,G18,H18,I18,N18,S18,X18,AC18,AH18,AM18,AR18,AW18,BB18,BG18,BL18,BQ18,BV18),"n/m") -> 0.15777216 | CM18: Defense Electronics sales ($m) | CN18: 1075 | CO18: 1065 | CP18: 1055 | CQ18: +4–6%.
B19: Adjusted margin before outlook calibration % (Q3/Q4-26E helper) | BY19: =BT18+(($CA$22-$BW$17-$BX$17)-($BT$18*$BY$11+$BU$18*$BZ$11))/($BY$11+$BZ$11) -> 0.19322342 | BZ19: =BU18+(($CA$22-$BW$17-$BX$17)-($BT$18*$BY$11+$BU$18*$BZ$11))/($BY$11+$BZ$11) -> 0.20867835 | CF19: Prior-year quarter margin + uniform shift so that the segment hits its FY26 Adjusted OI guidance end-point (scenario). | CM19: Defense Electronics Adjusted OI ($m) | CN19: 298 | CO19: 294.5 | CP19: 291 | CQ19: Adj. margin 27.5–27.7%.
B20: Incremental Adjusted OI margin on Δ sales % (2027E+: lever) | BB20: =IFERROR((BB17-AW17)/(BB11-AW11),"") -> -1.1580744 | BG20: =IFERROR((BG17-BB17)/(BG11-BB11),"") -> 0.35146174 | BL20: =IFERROR((BL17-BG17)/(BL11-BG11),"") -> 0.14804758 | BQ20: =IFERROR((BQ17-BL17)/(BQ11-BL11),"") -> 0.28914375 | BV20: =IFERROR((BV17-BQ17)/(BV11-BQ11),"") -> 0.26349519 | CA20: =IFERROR((CA17-BV17)/(CA11-BV11),"") -> 0.31180423 | CB20: =CHOOSE(MATCH($CF$2,{"Bull","Base","Bear"},0),$CN$46,$CO$46,$CP$46) -> 0.3 | CC20: =CHOOSE(MATCH($CF$2,{"Bull","Base","Bear"},0),$CN$47,$CO$47,$CP$47) -> 0.3 | CD20: =CHOOSE(MATCH($CF$2,{"Bull","Base","Bear"},0),$CN$48,$CO$48,$CP$48) -> 0.3 | CE20: =CHOOSE(MATCH($CF$2,{"Bull","Base","Bear"},0),$CN$49,$CO$49,$CP$49) -> 0.3 | CM20: Naval & Power sales ($m) | CN20: 1668 | CO20: 1661.5 | CP20: 1655 | CQ20: +10–11%.
B21: Memo: FY26 sales guidance (scenario end-point) | CA21: =CHOOSE(MATCH($CF$2,{"Bull","Base","Bear"},0),$CN$16,$CO$16,$CP$16) -> 1064 | CM21: Naval & Power Adjusted OI ($m) | CN21: 283 | CO21: 280.5 | CP21: 278 | CQ21: Adj. margin 16.8–17.0%.
B22: Memo: FY26 Adjusted OI guidance (scenario end-point) | CA22: =CHOOSE(MATCH($CF$2,{"Bull","Base","Bear"},0),$CN$17,$CO$17,$CP$17) -> 197.5 | CM22: Corporate & other ($m) | CN22: -44 | CO22: -43.5 | CP22: -43 | CQ22: High OI end pairs with -$44m (764-43 = 721 ≈ 720 low; 780-44 = 736 high).
B24: Defense Electronics (embedded computing, tactical communications, turret aiming & stabilization) — current segment basis from Q1/20 | CF24: DEFENSE ELECTRONICS — modelling logic | CM24: FY26 point estimates (all cases)
B25: Sales | AS25: 139.581 | AT25: 139.613 | AU25: 148.324 | AV25: 181.239 | AW25: 608.757 | AX25: 181.212 | AY25: 162.351 | AZ25: 181.504 | BA25: 199.259 | BB25: 724.326 | BC25: 143.069 | BD25: 149.549 | BE25: 161.188 | BF25: 236.456 | BG25: 690.262 | BH25: 162.154 | BI25: 197.722 | BJ25: 216.285 | BK25: 239.751 | BL25: 815.912 | BM25: 211.741 | BN25: 228.461 | BO25: 243.029 | BP25: 227.475 | BQ25: 910.706 | BR25: 245.164 | BS25: 253.011 | BT25: 253.159 | BU25: 267.276 | BV25: 1018.61 | BW25: 256.288 | BX25: 245.987 | BY25: =BT25*(1+BY27) -> 273.73043 | BZ25: =BU25*(1+BZ27) -> 288.99457 | CA25: =SUM(BW25,BX25,BY25,BZ25) -> 1065 | CB25: =CA25*(1+CB27) -> 1128.9 | CC25: =CB25*(1+CC27) -> 1196.634 | CD25: =CC25*(1+CD27) -> 1262.4489 | CE25: =CD25*(1+CE27) -> 1331.8836 | CF25: Q3/Q4-26E: prior-year quarter × (1 + guidance-implied 2H/26 y/y growth + revenue calibration Δ). 2027E+: prior year × (1 + scenario lever). | CH25: =IFERROR((CE25/BV25)^(1/5)-1,"n/m") -> 0.055095242 | CI25: =IFERROR((BV25/AW25)^(1/5)-1,"n/m") -> 0.10844154 | CJ25: =IFERROR((BV25/X25)^(1/10)-1,"n/m") -> n/m | CK25: =IFERROR((BV25/C25)^(1/19)-1,"n/m") -> n/m | CM25: Interest expense ($m) | CO25: 41 | CQ25: ~$41m; $200m 4.24% notes due Dec-2026.
B26: Sales y/y % | D26: =IF(AND(ISNUMBER(D25),ISNUMBER(C25)),IFERROR(D25/C25-1,""),"") | E26: =IF(AND(ISNUMBER(E25),ISNUMBER(D25)),IFERROR(E25/D25-1,""),"") | F26: =IF(AND(ISNUMBER(F25),ISNUMBER(E25)),IFERROR(F25/E25-1,""),"") | G26: =IF(AND(ISNUMBER(G25),ISNUMBER(F25)),IFERROR(G25/F25-1,""),"") | H26: =IF(AND(ISNUMBER(H25),ISNUMBER(G25)),IFERROR(H25/G25-1,""),"") | I26: =IF(AND(ISNUMBER(I25),ISNUMBER(H25)),IFERROR(I25/H25-1,""),"") | N26: =IF(AND(ISNUMBER(N25),ISNUMBER(I25)),IFERROR(N25/I25-1,""),"") | O26: =IF(AND(ISNUMBER(O25),ISNUMBER(J25)),IFERROR(O25/J25-1,""),"") | P26: =IF(AND(ISNUMBER(P25),ISNUMBER(K25)),IFERROR(P25/K25-1,""),"") | Q26: =IF(AND(ISNUMBER(Q25),ISNUMBER(L25)),IFERROR(Q25/L25-1,""),"") | R26: =IF(AND(ISNUMBER(R25),ISNUMBER(M25)),IFERROR(R25/M25-1,""),"") | S26: =IF(AND(ISNUMBER(S25),ISNUMBER(N25)),IFERROR(S25/N25-1,""),"") | T26: =IF(AND(ISNUMBER(T25),ISNUMBER(O25)),IFERROR(T25/O25-1,""),"") | U26: =IF(AND(ISNUMBER(U25),ISNUMBER(P25)),IFERROR(U25/P25-1,""),"") | ... BX26: =IF(AND(ISNUMBER(BX25),ISNUMBER(BS25)),IFERROR(BX25/BS25-1,""),"") -> -0.027761639 | BY26: =IFERROR(BY25/BT25-1,"") -> 0.081258947 | BZ26: =IFERROR(BZ25/BU25-1,"") -> 0.081258947 | CA26: =IFERROR(CA25/BV25-1,"") -> 0.045542455 | CB26: =IFERROR(CB25/CA25-1,"") -> 0.06 | CC26: =IFERROR(CC25/CB25-1,"") -> 0.06 | CD26: =IFERROR(CD25/CC25-1,"") -> 0.055 | CE26: =IFERROR(CE25/CD25-1,"") -> 0.055 | CM26: Other income, net — GAAP ($m) | CO26: 51 | CQ26: Reported guidance $51m incl. $17m gain on equity securities (Q2/26); adjusted ~$34m.
B27: Forecast sales growth driver % (Q3/Q4-26E: guidance-implied 2H y/y + calibration; 2027E+: lever) | BY27: =($CA$35-$BW$25-$BX$25)/($BT$25+$BU$25)-1+BY89 -> 0.081258947 | BZ27: =($CA$35-$BW$25-$BX$25)/($BT$25+$BU$25)-1+BZ89 -> 0.081258947 | CA27: =IFERROR(CA25/BV25-1,"") -> 0.045542455 | CB27: =CHOOSE(MATCH($CF$2,{"Bull","Base","Bear"},0),$CN$52,$CO$52,$CP$52) -> 0.06 | CC27: =CHOOSE(MATCH($CF$2,{"Bull","Base","Bear"},0),$CN$53,$CO$53,$CP$53) -> 0.06 | CD27: =CHOOSE(MATCH($CF$2,{"Bull","Base","Bear"},0),$CN$54,$CO$54,$CP$54) -> 0.055 | CE27: =CHOOSE(MATCH($CF$2,{"Bull","Base","Bear"},0),$CN$55,$CO$55,$CP$55) -> 0.055 | CF27: FY26: (segment guidance end-point − 1H/26) ÷ 2H/25 − 1, by scenario (high / mid / low). 2027E–30E: scenario lever (table →). | CM27: Gain on equity securities — excluded from adjusted ($m) | CO27: 17 | CQ27: Guidance adjustment column (-$17m other income).
B28: Operating income (GAAP, as reported) | AS28: 24.063 | AT28: 24.736 | AU28: 35.103 | AV28: 34.846 | AW28: 118.748 | AX28: 36.623 | AY28: 29.271 | AZ28: 40.762 | BA28: 52.433 | BB28: 159.089 | BC28: 23.29 | BD28: 24.46 | BE28: 36.588 | BF28: 70.23 | BG28: 154.568 | BH28: 23.368 | BI28: 43.18 | BJ28: 56.212 | BK28: 69.015 | BL28: 191.775 | BM28: 48.081 | BN28: 58.244 | BO28: 63.639 | BP28: 54.775 | BQ28: 224.739 | BR28: 67.449 | BS28: 67.833 | BT28: 73.957 | BU28: 68.777 | BV28: 278.016 | BW28: 71.927 | BX28: 68.768 | BY28: =BY31-BY30 -> 79.338763 | BZ28: =BZ31-BZ30 -> 74.052074 | CA28: =SUM(BW28,BX28,BY28,BZ28) -> 294.08584 | CB28: =CB31-CB30 -> 314.65984 | CC28: =CC31-CC30 -> 336.33472 | CD28: =CD31-CD30 -> 356.07918 | CE28: =CE31-CE30 -> 376.90958 | CM28: Tax rate | CO28: 0.215 | CQ28: 21.5% (reported and adjusted).
B29: Operating margin (GAAP) % | C29: =IF(AND(ISNUMBER(C28),ISNUMBER(C25)),IFERROR(C28/C25,""),"") | D29: =IF(AND(ISNUMBER(D28),ISNUMBER(D25)),IFERROR(D28/D25,""),"") | E29: =IF(AND(ISNUMBER(E28),ISNUMBER(E25)),IFERROR(E28/E25,""),"") | F29: =IF(AND(ISNUMBER(F28),ISNUMBER(F25)),IFERROR(F28/F25,""),"") | G29: =IF(AND(ISNUMBER(G28),ISNUMBER(G25)),IFERROR(G28/G25,""),"") | H29: =IF(AND(ISNUMBER(H28),ISNUMBER(H25)),IFERROR(H28/H25,""),"") | I29: =IF(AND(ISNUMBER(I28),ISNUMBER(I25)),IFERROR(I28/I25,""),"") | J29: =IF(AND(ISNUMBER(J28),ISNUMBER(J25)),IFERROR(J28/J25,""),"") | ... BX29: =IF(AND(ISNUMBER(BX28),ISNUMBER(BX25)),IFERROR(BX28/BX25,""),"") -> 0.27955949 | BY29: =IFERROR(BY28/BY25,"") -> 0.28984268 | BZ29: =IFERROR(BZ28/BZ25,"") -> 0.25624037 | CA29: =IFERROR(CA28/CA25,"") -> 0.27613694 | CB29: =IFERROR(CB28/CB25,"") -> 0.27873136 | CC29: =IFERROR(CC28/CC25,"") -> 0.28106733 | CD29: =IFERROR(CD28/CD25,"") -> 0.28205434 | CE29: =IFERROR(CE28/CE25,"") -> 0.28298989 | CM29: Diluted shares (m) | CO29: 37.1 | CQ29: Memo — guidance predates the Aug–Oct 10b5-1 plans ($300m); model shares are built from the buyback schedule.
B30: (+) Adjustments (first-year purchase accounting, restructuring, exited businesses) | AS30: 2.737 | AT30: 8.764 | AU30: 3.597 | AV30: 10.492 | AW30: 25.625 | AX30: 1.577 | AY30: 1.529 | AZ30: 1.538 | BA30: 0.442 | BB30: 5.134 | BC30: 0 | BD30: 0 | BE30: 0 | BF30: 0 | BG30: 0 | BH30: 0 | BI30: 0 | BJ30: 0 | BK30: 0 | BL30: 0 | BM30: 0 | BN30: 0.523 | BO30: 0.819 | BP30: 0.587 | BQ30: 1.929 | BR30: 0 | BS30: 0.019 | BT30: 0 | BU30: 0.323 | BV30: 0.342 | BW30: 0.096 | BX30: 0.03 | BY30: =MAX(0,($CO$31-$BW$30-$BX$30)/2) -> 0 | BZ30: =MAX(0,($CO$31-$BW$30-$BX$30)/2) -> 0 | CA30: =SUM(BW30,BX30,BY30,BZ30) -> 0.126 | CB30: 0 | CC30: 0 | CD30: 0 | CE30: 0 | CF30: Q3/Q4-26E: remaining FY26 Restructuring Program cost per the guidance adjustment column, spread evenly. 2027E+: none assumed. | CM30: FY26 restructuring adjustment — A&I ($m) | CO30: 6 | CQ30: FY26 Restructuring Program, guidance adjustment column.
B31: Adjusted operating income | AS31: =AS28+AS30 -> 26.8 | AT31: =AT28+AT30 -> 33.5 | AU31: =AU28+AU30 -> 38.7 | AV31: =AV28+AV30 -> 45.338 | AW31: =AW28+AW30 -> 144.373 | AX31: =AX28+AX30 -> 38.2 | AY31: =AY28+AY30 -> 30.8 | AZ31: =AZ28+AZ30 -> 42.3 | ... BX31: =BX28+BX30 -> 68.798 | BY31: =BY25*BY32 -> 79.338763 | BZ31: =BZ25*BZ32 -> 74.052074 | CA31: =SUM(BW31,BX31,BY31,BZ31) -> 294.21184 | CB31: =CA31+(CB25-CA25)*CB34 -> 314.65984 | CC31: =CB31+(CC25-CB25)*CC34 -> 336.33472 | CD31: =CC31+(CD25-CC25)*CD34 -> 356.07918 | CE31: =CD31+(CE25-CD25)*CE34 -> 376.90958 | CF31: 2027E+: prior-year Adjusted OI + Δ sales × incremental margin (scenario lever) — margin is an output, not an input. | CH31: =IFERROR((CE31/BV31)^(1/5)-1,"n/m") -> 0.06249451 | CI31: =IFERROR((BV31/AW31)^(1/5)-1,"n/m") -> 0.14031161 | CJ31: =IFERROR((BV31/X31)^(1/10)-1,"n/m") -> n/m | CK31: =IFERROR((BV31/C31)^(1/19)-1,"n/m") -> n/m | CM31: FY26 restructuring adjustment — Defense Electronics ($m) | CO31: 0
B32: Adjusted operating margin % | C32: =IF(AND(ISNUMBER(C31),ISNUMBER(C25)),IFERROR(C31/C25,""),"") | D32: =IF(AND(ISNUMBER(D31),ISNUMBER(D25)),IFERROR(D31/D25,""),"") | E32: =IF(AND(ISNUMBER(E31),ISNUMBER(E25)),IFERROR(E31/E25,""),"") | F32: =IF(AND(ISNUMBER(F31),ISNUMBER(F25)),IFERROR(F31/F25,""),"") | G32: =IF(AND(ISNUMBER(G31),ISNUMBER(G25)),IFERROR(G31/G25,""),"") | H32: =IF(AND(ISNUMBER(H31),ISNUMBER(H25)),IFERROR(H31/H25,""),"") | I32: =IF(AND(ISNUMBER(I31),ISNUMBER(I25)),IFERROR(I31/I25,""),"") | J32: =IF(AND(ISNUMBER(J31),ISNUMBER(J25)),IFERROR(J31/J25,""),"") | ... BX32: =IF(AND(ISNUMBER(BX31),ISNUMBER(BX25)),IFERROR(BX31/BX25,""),"") -> 0.27968145 | BY32: =BY33+BY93 -> 0.28984268 | BZ32: =BZ33+BZ93 -> 0.25624037 | CA32: =IFERROR(CA31/CA25,"") -> 0.27625525 | CB32: =IFERROR(CB31/CB25,"") -> 0.27873136 | CC32: =IFERROR(CC31/CC25,"") -> 0.28106733 | CD32: =IFERROR(CD31/CD25,"") -> 0.28205434 | CE32: =IFERROR(CE31/CE25,"") -> 0.28298989 | CH32: =IFERROR(AVERAGE(CA32,CB32,CC32,CD32,CE32),"n/m") -> 0.28021963 | CI32: =IFERROR(AVERAGE(BB32,BG32,BL32,BQ32,BV32),"n/m") -> 0.24157211 | CJ32: =IFERROR(AVERAGE(AC32,AH32,AM32,AR32,AW32,BB32,BG32,BL32,BQ32,BV32),"n/m") -> 0.24083681 | CK32: =IFERROR(AVERAGE(C32,D32,E32,F32,G32,H32,I32,N32,S32,X32,AC32,AH32,AM32,AR32,AW32,BB32,BG32,BL32,BQ32,BV32),"n/m") -> 0.24083681 | CM32: FY26 restructuring adjustment — Naval & Power ($m) | CO32: 1
B33: Adjusted margin before outlook calibration % (Q3/Q4-26E helper) | BY33: =BT32+(($CA$36-$BW$31-$BX$31)-($BT$32*$BY$25+$BU$32*$BZ$25))/($BY$25+$BZ$25) -> 0.29035477 | BZ33: =BU32+(($CA$36-$BW$31-$BX$31)-($BT$32*$BY$25+$BU$32*$BZ$25))/($BY$25+$BZ$25) -> 0.25675245 | CF33: Prior-year quarter margin + uniform shift so that the segment hits its FY26 Adjusted OI guidance end-point (scenario). | CM33: Capex increase vs 2025 ($m) | CO33: 25 | CQ33: "Year-over-year increase of approximately $25 million compared with 2025".
B34: Incremental Adjusted OI margin on Δ sales % (2027E+: lever) | BB34: =IFERROR((BB31-AW31)/(BB25-AW25),"") -> 0.17175886 | BG34: =IFERROR((BG31-BB31)/(BG25-BB25),"") -> 0.28343706 | BL34: =IFERROR((BL31-BG31)/(BL25-BG25),"") -> 0.2961162 | BQ34: =IFERROR((BQ31-BL31)/(BQ25-BL25),"") -> 0.36809292 | BV34: =IFERROR((BV31-BQ31)/(BV25-BQ25),"") -> 0.47903692 | CA34: =IFERROR((CA31-BV31)/(CA25-BV25),"") -> 0.34175119 | CB34: =CHOOSE(MATCH($CF$2,{"Bull","Base","Bear"},0),$CN$58,$CO$58,$CP$58) -> 0.32 | CC34: =CHOOSE(MATCH($CF$2,{"Bull","Base","Bear"},0),$CN$59,$CO$59,$CP$59) -> 0.32 | CD34: =CHOOSE(MATCH($CF$2,{"Bull","Base","Bear"},0),$CN$60,$CO$60,$CP$60) -> 0.3 | CE34: =CHOOSE(MATCH($CF$2,{"Bull","Base","Bear"},0),$CN$61,$CO$61,$CP$61) -> 0.3 | CM34: Amortization of acquired intangibles FY26 ($m) | CO34: 60 | CQ34: FY2025 10-K expected amortization: 2026 $60m, 2027 $57m, 2028 $51m, 2029 $51m, 2030 $50m.
B35: Memo: FY26 sales guidance (scenario end-point) | CA35: =CHOOSE(MATCH($CF$2,{"Bull","Base","Bear"},0),$CN$18,$CO$18,$CP$18) -> 1065 | CM35: 2H/26 share repurchases ($m) | CN35: 400 | CO35: 300 | CP35: 300 | CQ35: 10b5-1 plans: $100m (10-Aug), $100m (18-Aug), $100m (10-Sep→30-Oct); $600m authorization left.
B36: Memo: FY26 Adjusted OI guidance (scenario end-point) | CA36: =CHOOSE(MATCH($CF$2,{"Bull","Base","Bear"},0),$CN$19,$CO$19,$CP$19) -> 294.5 | CM36: Minimum net debt / Adjusted EBITDA (x) — buyback floor 2027E+ | CN36: 1 | CO36: 0.5 | CP36: 0.25 | CQ36: CW ran 0.3–0.9x net leverage 2021–25; surplus FCF returned via buybacks once leverage is at the floor.
CM37: Minimum annual repurchases 2027E+ ($m) | CN37: 60 | CO37: 60 | CP37: 60 | CQ37: "Min. $60M share repurchase ... to offset dilution" (2025/2026 guidance).
B38: Naval & Power (naval pumps/valves/generators, arresting systems, commercial & government nuclear, process) — current segment basis from Q1/20 | CF38: NAVAL & POWER — modelling logic
B39: Sales | AS39: 234.922 | AT39: 233.023 | AU39: 234.522 | AV39: 274.439 | AW39: 976.906 | AX39: 235.516 | AY39: 259.431 | AZ39: 242.819 | BA39: 257.505 | BB39: 995.271 | BC39: 225.28 | BD39: 251.236 | BE39: 256.261 | BF39: 297.951 | BG39: 1030.728 | BH39: 266.259 | BI39: 280.414 | BJ39: 287.744 | BK39: 307.816 | BL39: 1142.233 | BM39: 282.101 | BN39: 323.098 | BO39: 327.23 | BP39: 345.921 | BQ39: 1278.35 | BR39: 333.235 | BS39: 384.427 | BT39: 368.026 | BU39: 417.314 | BV39: 1503.002 | BW39: 402.48 | BX39: 410.256 | BY39: =BT39*(1+BY41) -> 397.74775 | BZ39: =BU39*(1+BZ41) -> 451.01625 | CA39: =SUM(BW39,BX39,BY39,BZ39) -> 1661.5 | CB39: =CA39*(1+CB41) -> 1794.42 | CC39: =CB39*(1+CC41) -> 1929.0015 | CD39: =CC39*(1+CD41) -> 2064.0316 | CE39: =CD39*(1+CE41) -> 2208.5138 | CF39: Q3/Q4-26E: prior-year quarter × (1 + guidance-implied 2H/26 y/y growth + revenue calibration Δ). 2027E+: prior year × (1 + scenario lever). | CH39: =IFERROR((CE39/BV39)^(1/5)-1,"n/m") -> 0.080010835 | CI39: =IFERROR((BV39/AW39)^(1/5)-1,"n/m") -> 0.089987096 | CJ39: =IFERROR((BV39/X39)^(1/10)-1,"n/m") -> n/m | CK39: =IFERROR((BV39/C39)^(1/19)-1,"n/m") -> n/m | CM39: AI_g (Aerospace & Industrial sales growth y/y) | CN39: 0.03 | CO39: Δ → | CP39: -0.03 | CQ39: Commercial aero OEM ramp (narrow/widebody actuation, sensors, surface treatment), defense actuation; FY26 +8–10%.
B40: Sales y/y % | D40: =IF(AND(ISNUMBER(D39),ISNUMBER(C39)),IFERROR(D39/C39-1,""),"") | E40: =IF(AND(ISNUMBER(E39),ISNUMBER(D39)),IFERROR(E39/D39-1,""),"") | F40: =IF(AND(ISNUMBER(F39),ISNUMBER(E39)),IFERROR(F39/E39-1,""),"") | G40: =IF(AND(ISNUMBER(G39),ISNUMBER(F39)),IFERROR(G39/F39-1,""),"") | H40: =IF(AND(ISNUMBER(H39),ISNUMBER(G39)),IFERROR(H39/G39-1,""),"") | I40: =IF(AND(ISNUMBER(I39),ISNUMBER(H39)),IFERROR(I39/H39-1,""),"") | N40: =IF(AND(ISNUMBER(N39),ISNUMBER(I39)),IFERROR(N39/I39-1,""),"") | O40: =IF(AND(ISNUMBER(O39),ISNUMBER(J39)),IFERROR(O39/J39-1,""),"") | P40: =IF(AND(ISNUMBER(P39),ISNUMBER(K39)),IFERROR(P39/K39-1,""),"") | Q40: =IF(AND(ISNUMBER(Q39),ISNUMBER(L39)),IFERROR(Q39/L39-1,""),"") | R40: =IF(AND(ISNUMBER(R39),ISNUMBER(M39)),IFERROR(R39/M39-1,""),"") | S40: =IF(AND(ISNUMBER(S39),ISNUMBER(N39)),IFERROR(S39/N39-1,""),"") | T40: =IF(AND(ISNUMBER(T39),ISNUMBER(O39)),IFERROR(T39/O39-1,""),"") | U40: =IF(AND(ISNUMBER(U39),ISNUMBER(P39)),IFERROR(U39/P39-1,""),"") | ... BX40: =IF(AND(ISNUMBER(BX39),ISNUMBER(BS39)),IFERROR(BX39/BS39-1,""),"") -> 0.067188309 | BY40: =IFERROR(BY39/BT39-1,"") -> 0.080759926 | BZ40: =IFERROR(BZ39/BU39-1,"") -> 0.080759926 | CA40: =IFERROR(CA39/BV39-1,"") -> 0.10545428 | CB40: =IFERROR(CB39/CA39-1,"") -> 0.08 | CC40: =IFERROR(CC39/CB39-1,"") -> 0.075 | CD40: =IFERROR(CD39/CC39-1,"") -> 0.07 | CE40: =IFERROR(CE39/CD39-1,"") -> 0.07 | CM40: 2027E | CN40: =CO40+$CN$39 -> 0.1 | CO40: 0.07 | CP40: =CO40+$CP$39 -> 0.04
B41: Forecast sales growth driver % (Q3/Q4-26E: guidance-implied 2H y/y + calibration; 2027E+: lever) | BY41: =($CA$49-$BW$39-$BX$39)/($BT$39+$BU$39)-1+BY89 -> 0.080759926 | BZ41: =($CA$49-$BW$39-$BX$39)/($BT$39+$BU$39)-1+BZ89 -> 0.080759926 | CA41: =IFERROR(CA39/BV39-1,"") -> 0.10545428 | CB41: =CHOOSE(MATCH($CF$2,{"Bull","Base","Bear"},0),$CN$64,$CO$64,$CP$64) -> 0.08 | CC41: =CHOOSE(MATCH($CF$2,{"Bull","Base","Bear"},0),$CN$65,$CO$65,$CP$65) -> 0.075 | CD41: =CHOOSE(MATCH($CF$2,{"Bull","Base","Bear"},0),$CN$66,$CO$66,$CP$66) -> 0.07 | CE41: =CHOOSE(MATCH($CF$2,{"Bull","Base","Bear"},0),$CN$67,$CO$67,$CP$67) -> 0.07 | CF41: FY26: (segment guidance end-point − 1H/26) ÷ 2H/25 − 1, by scenario (high / mid / low). 2027E–30E: scenario lever (table →). | CM41: 2028E | CN41: =CO41+$CN$39 -> 0.095 | CO41: 0.065 | CP41: =CO41+$CP$39 -> 0.035
B42: Operating income (GAAP, as reported) | AS42: 28.11 | AT42: 29.146 | AU42: 33.367 | AV42: 17.528 | AW42: 108.151 | AX42: 38.057 | AY42: 43.095 | AZ42: 35.483 | BA42: 25.025 | BB42: 141.66 | BC42: 27.288 | BD42: 50.001 | BE42: 41.576 | BF42: 58.717 | BG42: 177.582 | BH42: 37.937 | BI42: 46.782 | BJ42: 47.663 | BK42: 56.845 | BL42: 189.227 | BM42: 35.191 | BN42: 46.283 | BO42: 53.039 | BP42: 65.15 | BQ42: 199.663 | BR42: 41.863 | BS42: 60.416 | BT42: 57.721 | BU42: 71.284 | BV42: 231.284 | BW42: 59.777 | BX42: 71.019 | BY42: =BY45-BY44 -> 66.738812 | BZ42: =BZ45-BZ44 -> 81.53055 | CA42: =SUM(BW42,BX42,BY42,BZ42) -> 279.06536 | CB42: =CB45-CB44 -> 313.29536 | CC42: =CC45-CC44 -> 346.94074 | CD42: =CD45-CD44 -> 380.69826 | CE42: =CE45-CE44 -> 416.81882 | CM42: 2029E | CN42: =CO42+$CN$39 -> 0.09 | CO42: 0.06 | CP42: =CO42+$CP$39 -> 0.03
B43: Operating margin (GAAP) % | C43: =IF(AND(ISNUMBER(C42),ISNUMBER(C39)),IFERROR(C42/C39,""),"") | D43: =IF(AND(ISNUMBER(D42),ISNUMBER(D39)),IFERROR(D42/D39,""),"") | E43: =IF(AND(ISNUMBER(E42),ISNUMBER(E39)),IFERROR(E42/E39,""),"") | F43: =IF(AND(ISNUMBER(F42),ISNUMBER(F39)),IFERROR(F42/F39,""),"") | G43: =IF(AND(ISNUMBER(G42),ISNUMBER(G39)),IFERROR(G42/G39,""),"") | H43: =IF(AND(ISNUMBER(H42),ISNUMBER(H39)),IFERROR(H42/H39,""),"") | I43: =IF(AND(ISNUMBER(I42),ISNUMBER(I39)),IFERROR(I42/I39,""),"") | J43: =IF(AND(ISNUMBER(J42),ISNUMBER(J39)),IFERROR(J42/J39,""),"") | ... BX43: =IF(AND(ISNUMBER(BX42),ISNUMBER(BX39)),IFERROR(BX42/BX39,""),"") -> 0.17310899 | BY43: =IFERROR(BY42/BY39,"") -> 0.1677918 | BZ43: =IFERROR(BZ42/BZ39,"") -> 0.18077076 | CA43: =IFERROR(CA42/CA39,"") -> 0.16795989 | CB43: =IFERROR(CB42/CB39,"") -> 0.17459422 | CC43: =IFERROR(CC42/CC39,"") -> 0.17985509 | CD43: =IFERROR(CD42/CD39,"") -> 0.18444401 | CE43: =IFERROR(CE42/CE39,"") -> 0.18873272 | CM43: 2030E | CN43: =CO43+$CN$39 -> 0.09 | CO43: 0.06 | CP43: =CO43+$CP$39 -> 0.03
B44: (+) Adjustments (first-year purchase accounting, restructuring, exited businesses) | AS44: 5.39 | AT44: 9.154 | AU44: 8.633 | AV44: 39.513 | AW44: 62.715 | AX44: 2.543 | AY44: 0.405 | AZ44: 8.417 | BA44: 22.802 | BB44: 34.139 | BC44: 5.427 | BD44: 0 | BE44: 6.905 | BF44: 1.724 | BG44: 14.056 | BH44: 2.676 | BI44: 2.659 | BJ44: 1.333 | BK44: 2.529 | BL44: 9.198 | BM44: 0 | BN44: 0.342 | BO44: 0.759 | BP44: 0.962 | BQ44: 2.063 | BR44: 3.069 | BS44: 3.134 | BT44: 3.532 | BU44: 3.539 | BV44: 13.272 | BW44: 0.111 | BX44: 0.088 | BY44: =MAX(0,($CO$32-$BW$44-$BX$44)/2) -> 0.4005 | BZ44: =MAX(0,($CO$32-$BW$44-$BX$44)/2) -> 0.4005 | CA44: =SUM(BW44,BX44,BY44,BZ44) -> 1 | CB44: 0 | CC44: 0 | CD44: 0 | CE44: 0 | CF44: Q3/Q4-26E: remaining FY26 Restructuring Program cost per the guidance adjustment column, spread evenly. 2027E+: none assumed.
B45: Adjusted operating income | AS45: =AS42+AS44 -> 33.5 | AT45: =AT42+AT44 -> 38.3 | AU45: =AU42+AU44 -> 42 | AV45: =AV42+AV44 -> 57.041 | AW45: =AW42+AW44 -> 170.866 | AX45: =AX42+AX44 -> 40.6 | AY45: =AY42+AY44 -> 43.5 | AZ45: =AZ42+AZ44 -> 43.9 | ... BX45: =BX42+BX44 -> 71.107 | BY45: =BY39*BY46 -> 67.139312 | BZ45: =BZ39*BZ46 -> 81.93105 | CA45: =SUM(BW45,BX45,BY45,BZ45) -> 280.06536 | CB45: =CA45+(CB39-CA39)*CB48 -> 313.29536 | CC45: =CB45+(CC39-CB39)*CC48 -> 346.94074 | CD45: =CC45+(CD39-CC39)*CD48 -> 380.69826 | CE45: =CD45+(CE39-CD39)*CE48 -> 416.81882 | CF45: 2027E+: prior-year Adjusted OI + Δ sales × incremental margin (scenario lever) — margin is an output, not an input. | CH45: =IFERROR((CE45/BV45)^(1/5)-1,"n/m") -> 0.1125353 | CI45: =IFERROR((BV45/AW45)^(1/5)-1,"n/m") -> 0.074346897 | CJ45: =IFERROR((BV45/X45)^(1/10)-1,"n/m") -> n/m | CK45: =IFERROR((BV45/C45)^(1/19)-1,"n/m") -> n/m | CM45: AI_inc (A&I incremental Adjusted OI margin on Δ sales) | CN45: 0.075 | CO45: Δ → | CP45: -0.075 | CQ45: FY26 guide implies ~32% (Δ OI $27.5m / Δ sales $87m); restructuring savings.
B46: Adjusted operating margin % | C46: =IF(AND(ISNUMBER(C45),ISNUMBER(C39)),IFERROR(C45/C39,""),"") | D46: =IF(AND(ISNUMBER(D45),ISNUMBER(D39)),IFERROR(D45/D39,""),"") | E46: =IF(AND(ISNUMBER(E45),ISNUMBER(E39)),IFERROR(E45/E39,""),"") | F46: =IF(AND(ISNUMBER(F45),ISNUMBER(F39)),IFERROR(F45/F39,""),"") | G46: =IF(AND(ISNUMBER(G45),ISNUMBER(G39)),IFERROR(G45/G39,""),"") | H46: =IF(AND(ISNUMBER(H45),ISNUMBER(H39)),IFERROR(H45/H39,""),"") | I46: =IF(AND(ISNUMBER(I45),ISNUMBER(I39)),IFERROR(I45/I39,""),"") | J46: =IF(AND(ISNUMBER(J45),ISNUMBER(J39)),IFERROR(J45/J39,""),"") | ... BX46: =IF(AND(ISNUMBER(BX45),ISNUMBER(BX39)),IFERROR(BX45/BX39,""),"") -> 0.17332349 | BY46: =BY47+BY93 -> 0.16879872 | BZ46: =BZ47+BZ93 -> 0.18165875 | CA46: =IFERROR(CA45/CA39,"") -> 0.16856176 | CB46: =IFERROR(CB45/CB39,"") -> 0.17459422 | CC46: =IFERROR(CC45/CC39,"") -> 0.17985509 | CD46: =IFERROR(CD45/CD39,"") -> 0.18444401 | CE46: =IFERROR(CE45/CE39,"") -> 0.18873272 | CH46: =IFERROR(AVERAGE(CA46,CB46,CC46,CD46,CE46),"n/m") -> 0.17923756 | CI46: =IFERROR(AVERAGE(BB46,BG46,BL46,BQ46,BV46),"n/m") -> 0.1713579 | CJ46: =IFERROR(AVERAGE(AC46,AH46,AM46,AR46,AW46,BB46,BG46,BL46,BQ46,BV46),"n/m") -> 0.17194913 | CK46: =IFERROR(AVERAGE(C46,D46,E46,F46,G46,H46,I46,N46,S46,X46,AC46,AH46,AM46,AR46,AW46,BB46,BG46,BL46,BQ46,BV46),"n/m") -> 0.17194913 | CM46: 2027E | CN46: =CO46+$CN$45 -> 0.375 | CO46: 0.3 | CP46: =CO46+$CP$45 -> 0.225
B47: Adjusted margin before outlook calibration % (Q3/Q4-26E helper) | BY47: =BT46+(($CA$50-$BW$45-$BX$45)-($BT$46*$BY$39+$BU$46*$BZ$39))/($BY$39+$BZ$39) -> 0.1693108 | BZ47: =BU46+(($CA$50-$BW$45-$BX$45)-($BT$46*$BY$39+$BU$46*$BZ$39))/($BY$39+$BZ$39) -> 0.18217084 | CF47: Prior-year quarter margin + uniform shift so that the segment hits its FY26 Adjusted OI guidance end-point (scenario). | CM47: 2028E | CN47: =CO47+$CN$45 -> 0.375 | CO47: 0.3 | CP47: =CO47+$CP$45 -> 0.225
B48: Incremental Adjusted OI margin on Δ sales % (2027E+: lever) | BB48: =IFERROR((BB45-AW45)/(BB39-AW39),"") -> 0.26860877 | BG48: =IFERROR((BG45-BB45)/(BG39-BB39),"") -> 0.4467101 | BL48: =IFERROR((BL45-BG45)/(BL39-BG39),"") -> 0.060867226 | BQ48: =IFERROR((BQ45-BL45)/(BQ39-BL39),"") -> 0.024251196 | BV48: =IFERROR((BV45-BQ45)/(BV39-BQ39),"") -> 0.19065043 | CA48: =IFERROR((CA45-BV45)/(CA39-BV39),"") -> 0.22403665 | CB48: =CHOOSE(MATCH($CF$2,{"Bull","Base","Bear"},0),$CN$70,$CO$70,$CP$70) -> 0.25 | CC48: =CHOOSE(MATCH($CF$2,{"Bull","Base","Bear"},0),$CN$71,$CO$71,$CP$71) -> 0.25 | CD48: =CHOOSE(MATCH($CF$2,{"Bull","Base","Bear"},0),$CN$72,$CO$72,$CP$72) -> 0.25 | CE48: =CHOOSE(MATCH($CF$2,{"Bull","Base","Bear"},0),$CN$73,$CO$73,$CP$73) -> 0.25 | CM48: 2029E | CN48: =CO48+$CN$45 -> 0.375 | CO48: 0.3 | CP48: =CO48+$CP$45 -> 0.225
B49: Memo: FY26 sales guidance (scenario end-point) | CA49: =CHOOSE(MATCH($CF$2,{"Bull","Base","Bear"},0),$CN$20,$CO$20,$CP$20) -> 1661.5 | CM49: 2030E | CN49: =CO49+$CN$45 -> 0.375 | CO49: 0.3 | CP49: =CO49+$CP$45 -> 0.225
B50: Memo: FY26 Adjusted OI guidance (scenario end-point) | CA50: =CHOOSE(MATCH($CF$2,{"Bull","Base","Bear"},0),$CN$21,$CO$21,$CP$21) -> 280.5
CM51: DE_g (Defense Electronics sales growth y/y) | CN51: 0.03 | CO51: Δ → | CP51: -0.03 | CQ51: Record orders, embedded computing (fighter / UAV), tactical comms; FY26 +4–6%.
B52: Corporate & other; reconciling items to consolidated (legacy segment structure before 2020) | CF52: CORPORATE & RECONCILING ITEMS | CM52: 2027E | CN52: =CO52+$CN$51 -> 0.09 | CO52: 0.06 | CP52: =CO52+$CP$51 -> 0.03
B53: Corporate & other (GAAP) | AS53: -11.867 | AT53: -8.148 | AU53: -7.777 | AV53: -9.973 | AW53: -37.765 | AX53: -8.639 | AY53: -9.76 | AZ53: -9.448 | BA53: -12.036 | BB53: -39.883 | BC53: -14.921 | BD53: -8.82 | BE53: -9.661 | BF53: -12.301 | BG53: -45.703 | BH53: -9.235 | BI53: -12.852 | BJ53: -10.37 | BK53: -9.221 | BL53: -41.678 | BM53: -10.777 | BN53: -10.876 | BO53: -9.21 | BP53: -12.965 | BQ53: -43.828 | BR53: -10.029 | BS53: -10.948 | BT53: -10.866 | BU53: -10.102 | BV53: -41.945 | BW53: -10.693 | BX53: -10.1 | BY53: =BY55-BY54 -> -11.3535 | BZ53: =BZ55-BZ54 -> -11.3535 | CA53: =SUM(BW53,BX53,BY53,BZ53) -> -43.5 | CB53: =CB55-CB54 -> -45.2298 | CC53: =CC55-CC54 -> -49.424284 | CD53: =CD55-CD54 -> -53.646566 | CE53: =CE55-CE54 -> -58.121291 | CM53: 2028E | CN53: =CO53+$CN$51 -> 0.09 | CO53: 0.06 | CP53: =CO53+$CP$51 -> 0.03
B54: (+) Corporate adjustments (activism costs, restructuring) | AS54: 3.167 | AT54: 2.048 | AU54: 4.077 | AV54: 6.677 | AW54: 15.691 | AX54: 0.139 | AY54: -0.04 | AZ54: -0.052 | BA54: -0.022 | BB54: 0.053 | BC54: 4.876 | BD54: 0 | BE54: 0 | BF54: 0 | BG54: 4.876001 | BH54: 0 | BI54: 0 | BJ54: 0 | BK54: -0.001 | BL54: 0 | BM54: 0 | BN54: 0.964 | BO54: 0.66 | BP54: 1.414 | BQ54: 3.038 | BR54: -0.028 | BS54: 0 | BT54: 0.02 | BU54: 0.012 | BV54: 0.004 | BW54: 0 | BX54: 0 | BY54: 0 | BZ54: 0 | CA54: =SUM(BW54,BX54,BY54,BZ54) -> 0 | CB54: 0 | CC54: 0 | CD54: 0 | CE54: 0 | CM54: 2029E | CN54: =CO54+$CN$51 -> 0.085 | CO54: 0.055 | CP54: =CO54+$CP$51 -> 0.025
B55: Adjusted corporate & other | AS55: =AS53+AS54 -> -8.7 | AT55: =AT53+AT54 -> -6.1 | AU55: =AU53+AU54 -> -3.7 | AV55: =AV53+AV54 -> -3.296 | AW55: =AW53+AW54 -> -22.074 | AX55: =AX53+AX54 -> -8.5 | AY55: =AY53+AY54 -> -9.8 | AZ55: =AZ53+AZ54 -> -9.5 | ... BX55: =BX53+BX54 -> -10.1 | BY55: =($CA$57-$BW$55-$BX$55)/2 -> -11.3535 | BZ55: =($CA$57-$BW$55-$BX$55)/2 -> -11.3535 | CA55: =SUM(BW55,BX55,BY55,BZ55) -> -43.5 | CB55: =CB79*CB56 -> -45.2298 | CC55: =CC79*CC56 -> -49.424284 | CD55: =CD79*CD56 -> -53.646566 | CE55: =CE79*CE56 -> -58.121291 | CF55: Q3/Q4-26E: FY26 guidance (−$43–44m) less 1H/26, spread evenly. 2027E+: % of sales input. | CM55: 2030E | CN55: =CO55+$CN$51 -> 0.085 | CO55: 0.055 | CP55: =CO55+$CP$51 -> 0.025
B56: Adjusted corporate & other % of sales | C56: =IF(AND(ISNUMBER(C55),ISNUMBER(C79)),IFERROR(C55/C79,""),"") | D56: =IF(AND(ISNUMBER(D55),ISNUMBER(D79)),IFERROR(D55/D79,""),"") | E56: =IF(AND(ISNUMBER(E55),ISNUMBER(E79)),IFERROR(E55/E79,""),"") | F56: =IF(AND(ISNUMBER(F55),ISNUMBER(F79)),IFERROR(F55/F79,""),"") | G56: =IF(AND(ISNUMBER(G55),ISNUMBER(G79)),IFERROR(G55/G79,""),"") | H56: =IF(AND(ISNUMBER(H55),ISNUMBER(H79)),IFERROR(H55/H79,""),"") | I56: =IF(AND(ISNUMBER(I55),ISNUMBER(I79)),IFERROR(I55/I79,""),"") | J56: =IF(AND(ISNUMBER(J55),ISNUMBER(J79)),IFERROR(J55/J79,""),"") | ... BX56: =IF(AND(ISNUMBER(BX55),ISNUMBER(BX79)),IFERROR(BX55/BX79,""),"") -> -0.010930641 | BY56: =IFERROR(BY55/BY79,"") -> -0.012149323 | BZ56: =IFERROR(BZ55/BZ79,"") -> -0.011149372 | CA56: =IFERROR(CA55/CA79,"") -> -0.011476059 | CB56: -0.011 | CC56: -0.011 | CD56: -0.011 | CE56: -0.011 | CF56: 2027E+: −1.1% input (FY25 −1.2%; FY26 guidance ~−1.15%).
B57: Memo: FY26 corporate guidance (scenario end-point) | CA57: =CHOOSE(MATCH($CF$2,{"Bull","Base","Bear"},0),$CN$22,$CO$22,$CP$22) -> -43.5 | CM57: DE_inc (Defense Electronics incremental Adjusted OI margin) | CN57: 0.075 | CO57: Δ → | CP57: -0.075 | CQ57: FY26 guide implies ~36% (Δ OI $16.5m / Δ sales $46m); segment margin ~27.6%.
B58: Sales not on current segment basis (pre-2020: total company under legacy segments) | C58: 1282.155 | D58: 1592.124 | E58: 1830.14 | F58: 1809.69 | G58: 1893.134 | H58: 2054.13 | I58: 2097.716 | J58: 592.687 | K58: 617.687 | L58: 600.667 | M58: 699.73 | N58: 2510.771 | O58: 641.412 | P58: 652.452 | Q58: 559.494 | R58: 572.586 | S58: 2243.126 | T58: 546.199 | U58: 545.194 | V58: 525.535 | W58: 588.755 | X58: 2205.683 | Y58: 503.507 | Z58: 532.766 | AA58: 507.092 | AB58: 565.566 | AC58: 2108.931 | AD58: 523.591 | AE58: 567.653 | AF58: 567.901 | AG58: 611.881 | AH58: 2271.026 | AI58: 547.522 | AJ58: 620.298 | AK58: 595.393 | AL58: 648.622 | AM58: 2411.835 | AN58: 578.314 | AO58: 638.996 | AP58: 614.88 | AQ58: 655.771 | AR58: 2487.961 | CM58: 2027E | CN58: =CO58+$CN$57 -> 0.395 | CO58: 0.32 | CP58: =CO58+$CP$57 -> 0.245
B59: GAAP operating income not on current segment basis (pre-2020; incl. corporate) | C59: 140.628 | D59: 179.184 | E59: 199.182 | F59: 169.319 | G59: 179.823 | H59: 204.956 | I59: 161.446 | J59: 38.026 | K59: 57.788 | L59: 62.887 | M59: 74.918 | N59: 233.619 | O59: 59.101 | P59: 76.65 | Q59: 74.14 | R59: 74.931 | S59: 282.373 | T59: 72.835 | U59: 65.442 | V59: 63.813 | W59: 108.527 | X59: 310.617 | Y59: 57.263 | Z59: 68.089 | AA59: 76.573 | AB59: 106.173 | AC59: 308.098 | AD59: 51.227 | AE59: 83.271 | AF59: 96.55 | AG59: 108.695 | AH59: 339.743 | AI59: 64.498 | AJ59: 102.076 | AK59: 97.047 | AL59: 110.005 | AM59: 373.626 | AN59: 72.045 | AO59: 105.685 | AP59: 105.569 | AQ59: 120.654 | AR59: 403.953 | CM59: 2028E | CN59: =CO59+$CN$57 -> 0.395 | CO59: 0.32 | CP59: =CO59+$CP$57 -> 0.245
B60: (+) Adjustments in periods before the current segment basis | C60: =C158 -> 0 | D60: =D158 -> 0 | E60: =E158 -> 0 | F60: =F158 -> 0 | G60: =G158 -> 0 | H60: =H158 -> 0 | I60: =I158 -> 40.002 | J60: =J158 -> 0 | ... AR60: =AR158 -> 7.047 | CM60: 2029E | CN60: =CO60+$CN$57 -> 0.375 | CO60: 0.3 | CP60: =CO60+$CP$57 -> 0.225
CM61: 2030E | CN61: =CO61+$CN$57 -> 0.375 | CO61: 0.3 | CP61: =CO61+$CP$57 -> 0.225
B62: Future acquisitions (M&A lever — bolt-ons, unallocated across segments; deals closed from 2027E) | CF62: M&A LEVER — acquired sales = spend ÷ EV/sales; mid-year convention
B63: Acquisition spend (USDm, scenario) | CB63: =CHOOSE(MATCH($CF$2,{"Bull","Base","Bear"},0),$CN$76,$CO$76,$CP$76) -> 300 | CC63: =CHOOSE(MATCH($CF$2,{"Bull","Base","Bear"},0),$CN$77,$CO$77,$CP$77) -> 300 | CD63: =CHOOSE(MATCH($CF$2,{"Bull","Base","Bear"},0),$CN$78,$CO$78,$CP$78) -> 300 | CE63: =CHOOSE(MATCH($CF$2,{"Bull","Base","Bear"},0),$CN$79,$CO$79,$CP$79) -> 300 | CF63: Scenario lever M&A_spend. Historical acquisitions (cash flow statement): see "Acquisitions, net of cash acquired". | CM63: NP_g (Naval & Power sales growth y/y) | CN63: 0.03 | CO63: Δ → | CP63: -0.03 | CQ63: Virginia/Columbia-class submarine ramp, commercial nuclear (AP1000, SMR/advanced reactors); FY26 +10–11%.
B64: Purchase multiple — EV / sales (x) | CB64: 3 | CC64: 3 | CD64: 3 | CE64: 3 | CF64: Input 3.0x: CW bolt-ons (e.g., PacStar ~$400m / ~$100m+ sales, Arresting Systems ~$240m / ~$80m) typically 2.5–4x sales. | CM64: 2027E | CN64: =CO64+$CN$63 -> 0.11 | CO64: 0.08 | CP64: =CO64+$CP$63 -> 0.05
B65: Annualised sales acquired in the year | CB65: =IFERROR(CB63/CB64,0) -> 100 | CC65: =IFERROR(CC63/CC64,0) -> 100 | CD65: =IFERROR(CD63/CD64,0) -> 100 | CE65: =IFERROR(CE63/CE64,0) -> 100 | CM65: 2028E | CN65: =CO65+$CN$63 -> 0.105 | CO65: 0.075 | CP65: =CO65+$CP$63 -> 0.045
B66: Growth of acquired businesses after acquisition % | CB66: 0.05 | CC66: 0.05 | CD66: 0.05 | CE66: 0.05 | CM66: 2029E | CN66: =CO66+$CN$63 -> 0.1 | CO66: 0.07 | CP66: =CO66+$CP$63 -> 0.04
B67: Run-rate sales of businesses acquired (year end) | CA67: 0 | CB67: =CA67*(1+CB66)+CB65 -> 100 | CC67: =CB67*(1+CC66)+CC65 -> 205 | CD67: =CC67*(1+CD66)+CD65 -> 315.25 | CE67: =CD67*(1+CE66)+CE65 -> 431.0125 | CM67: 2030E | CN67: =CO67+$CN$63 -> 0.1 | CO67: 0.07 | CP67: =CO67+$CP$63 -> 0.04
B68: Sales from future acquisitions | CA68: 0 | CB68: =CA67*(1+CB66)+CB65*0.5 -> 50 | CC68: =CB67*(1+CC66)+CC65*0.5 -> 155 | CD68: =CC67*(1+CD66)+CD65*0.5 -> 265.25 | CE68: =CD67*(1+CE66)+CE65*0.5 -> 381.0125 | CF68: Mid-year convention: half a year of acquired sales in the year of the deal.
B69: Adjusted operating margin of acquired businesses % (after amortization) | CB69: 0.15 | CC69: 0.15 | CD69: 0.15 | CE69: 0.15 | CM69: NP_inc (Naval & Power incremental Adjusted OI margin) | CN69: 0.075 | CO69: Δ → | CP69: -0.075 | CQ69: FY26 guide implies ~22% (Δ OI $35.5m / Δ sales $158.5m); mix of development-stage nuclear revenue.
B70: Adjusted operating income from future acquisitions | CA70: 0 | CB70: =CB68*CB69 -> 7.5 | CC70: =CC68*CC69 -> 23.25 | CD70: =CD68*CD69 -> 39.7875 | CE70: =CE68*CE69 -> 57.151875 | CM70: 2027E | CN70: =CO70+$CN$69 -> 0.325 | CO70: 0.25 | CP70: =CO70+$CP$69 -> 0.175
B71: PP&E % of spend | CB71: 0.1 | CC71: 0.1 | CD71: 0.1 | CE71: 0.1 | CM71: 2028E | CN71: =CO71+$CN$69 -> 0.325 | CO71: 0.25 | CP71: =CO71+$CP$69 -> 0.175
B72: Acquired intangibles % of spend | CB72: 0.4 | CC72: 0.4 | CD72: 0.4 | CE72: 0.4 | CF72: CW purchase-price allocations: ~35–45% intangibles (customer relationships, technology), balance mostly goodwill. | CM72: 2029E | CN72: =CO72+$CN$69 -> 0.325 | CO72: 0.25 | CP72: =CO72+$CP$69 -> 0.175
B73: Intangible amortization life (years) | CB73: 15 | CC73: 15 | CD73: 15 | CE73: 15 | CM73: 2030E | CN73: =CO73+$CN$69 -> 0.325 | CO73: 0.25 | CP73: =CO73+$CP$69 -> 0.175
B74: Cumulative acquired intangibles (gross) | CA74: 0 | CB74: =CA74+CB63*CB72 -> 120 | CC74: =CB74+CC63*CC72 -> 240 | CD74: =CC74+CD63*CD72 -> 360 | CE74: =CD74+CE63*CE72 -> 480
B75: Amortization of future-acquisition intangibles | CA75: 0 | CB75: =(CA74+0.5*CB63*CB72)/CB73 -> 4 | CC75: =(CB74+0.5*CC63*CC72)/CC73 -> 12 | CD75: =(CC74+0.5*CD63*CD72)/CD73 -> 20 | CE75: =(CD74+0.5*CE63*CE72)/CE73 -> 28 | CM75: M&A_spend (bolt-on acquisitions, $m) | CN75: 300 | CO75: Δ → | CP75: -300 | CQ75: CW: "acquisitions remain top priority"; spend $488m (2020), $287m (2022), $226m (2024), ~$10m (2025).
B76: Depreciation of acquired businesses | CA76: 0 | CB76: =CB68*0.02 -> 1 | CC76: =CC68*0.02 -> 3.1 | CD76: =CD68*0.02 -> 5.305 | CE76: =CE68*0.02 -> 7.62025 | CF76: 2% of acquired sales. | CM76: 2027E | CN76: =CO76+$CN$75 -> 600 | CO76: 300 | CP76: =CO76+$CP$75 -> 0
CM77: 2028E | CN77: =CO77+$CN$75 -> 600 | CO77: 300 | CP77: =CO77+$CP$75 -> 0
B78: Group Total — sales & Adjusted operating income (segment build) — CW's primary profit KPI | CF78: GROUP TOTAL (CONSOLIDATED) — modelling logic | CM78: 2029E | CN78: =CO78+$CN$75 -> 600 | CO78: 300 | CP78: =CO78+$CP$75 -> 0
B79: Sales (segment build) | C79: =N(C11)+N(C25)+N(C39)+N(C58)+N(C68) -> 1282.155 | D79: =N(D11)+N(D25)+N(D39)+N(D58)+N(D68) -> 1592.124 | E79: =N(E11)+N(E25)+N(E39)+N(E58)+N(E68) -> 1830.14 | F79: =N(F11)+N(F25)+N(F39)+N(F58)+N(F68) -> 1809.69 | G79: =N(G11)+N(G25)+N(G39)+N(G58)+N(G68) -> 1893.134 | H79: =N(H11)+N(H25)+N(H39)+N(H58)+N(H68) -> 2054.13 | I79: =N(I11)+N(I25)+N(I39)+N(I58)+N(I68) -> 2097.716 | J79: =N(J11)+N(J25)+N(J39)+N(J58)+N(J68) -> 592.687 | ... CE79: =N(CE11)+N(CE25)+N(CE39)+N(CE58)+N(CE68) -> 5283.7538 | CF79: Σ segments + legacy-basis periods + future M&A. | CH79: =IFERROR((CE79/BV79)^(1/5)-1,"n/m") -> 0.085963719 | CI79: =IFERROR((BV79/AW79)^(1/5)-1,"n/m") -> 0.079058717 | CJ79: =IFERROR((BV79/X79)^(1/10)-1,"n/m") -> 0.047206404 | CK79: =IFERROR((BV79/C79)^(1/19)-1,"n/m") -> 0.054249601 | CM79: 2030E | CN79: =CO79+$CN$75 -> 600 | CO79: 300 | CP79: =CO79+$CP$75 -> 0
B80: Sales y/y % | D80: =IF(AND(ISNUMBER(D79),ISNUMBER(C79)),IFERROR(D79/C79-1,""),"") -> 0.24175626 | E80: =IF(AND(ISNUMBER(E79),ISNUMBER(D79)),IFERROR(E79/D79-1,""),"") -> 0.14949589 | F80: =IF(AND(ISNUMBER(F79),ISNUMBER(E79)),IFERROR(F79/E79-1,""),"") -> -0.011174009 | G80: =IF(AND(ISNUMBER(G79),ISNUMBER(F79)),IFERROR(G79/F79-1,""),"") -> 0.046109555 | H80: =IF(AND(ISNUMBER(H79),ISNUMBER(G79)),IFERROR(H79/G79-1,""),"") -> 0.085042052 | I80: =IF(AND(ISNUMBER(I79),ISNUMBER(H79)),IFERROR(I79/H79-1,""),"") -> 0.021218715 | N80: =IF(AND(ISNUMBER(N79),ISNUMBER(I79)),IFERROR(N79/I79-1,""),"") -> 0.19690702 | O80: =IF(AND(ISNUMBER(O79),ISNUMBER(J79)),IFERROR(O79/J79-1,""),"") -> 0.08221034 | P80: =IF(AND(ISNUMBER(P79),ISNUMBER(K79)),IFERROR(P79/K79-1,""),"") -> 0.056282551 | Q80: =IF(AND(ISNUMBER(Q79),ISNUMBER(L79)),IFERROR(Q79/L79-1,""),"") -> -0.068545467 | R80: =IF(AND(ISNUMBER(R79),ISNUMBER(M79)),IFERROR(R79/M79-1,""),"") -> -0.18170437 | S80: =IF(AND(ISNUMBER(S79),ISNUMBER(N79)),IFERROR(S79/N79-1,""),"") -> -0.10659873 | T80: =IF(AND(ISNUMBER(T79),ISNUMBER(O79)),IFERROR(T79/O79-1,""),"") -> -0.14844281 | U80: =IF(AND(ISNUMBER(U79),ISNUMBER(P79)),IFERROR(U79/P79-1,""),"") -> -0.16439217 | ... BX80: =IF(AND(ISNUMBER(BX79),ISNUMBER(BS79)),IFERROR(BX79/BS79-1,""),"") -> 0.054110539 | BY80: =IFERROR(BY79/BT79-1,"") -> 0.075159665 | BZ80: =IFERROR(BZ79/BU79-1,"") -> 0.075320913 | CA80: =IFERROR(CA79/BV79-1,"") -> 0.083503984 | CB80: =IFERROR(CB79/CA79-1,"") -> 0.084764543 | CC80: =IFERROR(CC79/CB79-1,"") -> 0.092737171 | CD80: =IFERROR(CD79/CC79-1,"") -> 0.085429307 | CE80: =IFERROR(CE79/CD79-1,"") -> 0.083411215
B81: Memo: company organic sales growth % (as published) | C81: 0.11 | D81: 0.13 | E81: 0.06 | F81: -0.02 | G81: 0.03 | H81: 0.03 | J81: 0 | K81: -0.02 | L81: 0.03 | M81: 0.01 | N81: 0.01 | O81: 0.02 | P81: 0.04 | Q81: 0.04 | R81: -0.03 | S81: 0.02 | T81: 0.03 | U81: -0.02 | V81: -0.04 | W81: 0.04 | X81: 0 | Y81: -0.07 | Z81: -0.02 | AA81: -0.03 | AB81: -0.03 | AC81: -0.04 | AD81: 0.03 | AE81: 0.05 | AF81: 0.08 | AG81: 0.03 | AH81: 0.05 | AI81: 0.03 | AJ81: 0.04 | AK81: 0.02 | AL81: 0.03 | AM81: 0.03 | AN81: 0.02 | AO81: 0.03 | AP81: 0.03 | AQ81: 0.01 | AR81: 0.02 | AS81: 0.01 | AT81: -0.17 | AU81: -0.1 | AV81: -0.05 | AW81: -0.08 | AX81: -0.08 | AY81: 0.06 | AZ81: 0.01 | BA81: -0.02 | BB81: -0.01 | BC81: -0.06 | BD81: -0.01 | BE81: 0.01 | BF81: 0.12 | BG81: 0.03 | BH81: 0.11 | BI81: 0.12 | BJ81: 0.14 | BK81: 0.03 | BL81: 0.1 | BM81: 0.13 | BN81: 0.11 | BO81: 0.1 | BP81: 0.05 | BQ81: 0.09 | BR81: 0.11 | BS81: 0.09 | BT81: 0.06 | BU81: 0.11 | BV81: 0.09 | BW81: 0.12 | BX81: 0.05
B82: Adjusted operating income (segment build) | C82: =N(C17)+N(C31)+N(C45)+N(C55)+N(C59)+N(C60)+N(C70) -> 140.628 | D82: =N(D17)+N(D31)+N(D45)+N(D55)+N(D59)+N(D60)+N(D70) -> 179.184 | E82: =N(E17)+N(E31)+N(E45)+N(E55)+N(E59)+N(E60)+N(E70) -> 199.182 | F82: =N(F17)+N(F31)+N(F45)+N(F55)+N(F59)+N(F60)+N(F70) -> 169.319 | G82: =N(G17)+N(G31)+N(G45)+N(G55)+N(G59)+N(G60)+N(G70) -> 179.823 | H82: =N(H17)+N(H31)+N(H45)+N(H55)+N(H59)+N(H60)+N(H70) -> 204.956 | I82: =N(I17)+N(I31)+N(I45)+N(I55)+N(I59)+N(I60)+N(I70) -> 201.448 | J82: =N(J17)+N(J31)+N(J45)+N(J55)+N(J59)+N(J60)+N(J70) -> 38.026 | ... CE82: =N(CE17)+N(CE31)+N(CE45)+N(CE55)+N(CE59)+N(CE60)+N(CE70) -> 1079.4849 | CH82: =IFERROR((CE82/BV82)^(1/5)-1,"n/m") -> 0.10644014 | CI82: =IFERROR((BV82/AW82)^(1/5)-1,"n/m") -> 0.1073376 | CJ82: =IFERROR((BV82/X82)^(1/10)-1,"n/m") -> 0.083848048 | CK82: =IFERROR((BV82/C82)^(1/19)-1,"n/m") -> 0.083993277
B83: Adjusted operating margin % | C83: =IF(AND(ISNUMBER(C82),ISNUMBER(C79)),IFERROR(C82/C79,""),"") -> 0.10968097 | D83: =IF(AND(ISNUMBER(D82),ISNUMBER(D79)),IFERROR(D82/D79,""),"") -> 0.112544 | E83: =IF(AND(ISNUMBER(E82),ISNUMBER(E79)),IFERROR(E82/E79,""),"") -> 0.1088343 | F83: =IF(AND(ISNUMBER(F82),ISNUMBER(F79)),IFERROR(F82/F79,""),"") -> 0.093562433 | G83: =IF(AND(ISNUMBER(G82),ISNUMBER(G79)),IFERROR(G82/G79,""),"") -> 0.094986937 | H83: =IF(AND(ISNUMBER(H82),ISNUMBER(H79)),IFERROR(H82/H79,""),"") -> 0.099777521 | I83: =IF(AND(ISNUMBER(I82),ISNUMBER(I79)),IFERROR(I82/I79,""),"") -> 0.096032065 | J83: =IF(AND(ISNUMBER(J82),ISNUMBER(J79)),IFERROR(J82/J79,""),"") -> 0.064158654 | ... BX83: =IF(AND(ISNUMBER(BX82),ISNUMBER(BX79)),IFERROR(BX82/BX79,""),"") -> 0.19394637 | BY83: =IFERROR(BY82/BY79,"") -> 0.19883561 | BZ83: =IFERROR(BZ82/BZ79,"") -> 0.19891989 | CA83: =IFERROR(CA82/CA79,"") -> 0.1920591 | CB83: =IFERROR(CB82/CB79,"") -> 0.19694348 | CC83: =IFERROR(CC82/CC79,"") -> 0.20005453 | CD83: =IFERROR(CD82/CD79,"") -> 0.20227972 | CE83: =IFERROR(CE82/CE79,"") -> 0.20430266 | CH83: =IFERROR(AVERAGE(CA83,CB83,CC83,CD83,CE83),"n/m") -> 0.1991279 | CI83: =IFERROR(AVERAGE(BB83,BG83,BL83,BQ83,BV83),"n/m") -> 0.17511401 | CJ83: =IFERROR(AVERAGE(AC83,AH83,AM83,AR83,AW83,BB83,BG83,BL83,BQ83,BV83),"n/m") -> 0.1658349 | CK83: =IFERROR(AVERAGE(C83,D83,E83,F83,G83,H83,I83,N83,S83,X83,AC83,AH83,AM83,AR83,AW83,BB83,BG83,BL83,BQ83,BV83),"n/m") -> 0.13623148
B84: Check: segment build vs consolidated sales (should be 0) | C84: =ROUND(C79-C114,1) -> 0 | D84: =ROUND(D79-D114,1) -> 0 | E84: =ROUND(E79-E114,1) -> 0 | F84: =ROUND(F79-F114,1) -> 0 | G84: =ROUND(G79-G114,1) -> 0 | H84: =ROUND(H79-H114,1) -> 0 | I84: =ROUND(I79-I114,1) -> 0 | J84: =ROUND(J79-J114,1) -> 0 | ... CE84: =ROUND(CE79-CE114,1) -> 0
B85: Check: segment build vs Adjusted OI bridge (should be 0) | C85: =ROUND(C82-C159,1) -> 0 | D85: =ROUND(D82-D159,1) -> 0 | E85: =ROUND(E82-E159,1) -> 0 | F85: =ROUND(F82-F159,1) -> 0 | G85: =ROUND(G82-G159,1) -> 0 | H85: =ROUND(H82-H159,1) -> 0 | I85: =ROUND(I82-I159,1) -> 0 | J85: =ROUND(J82-J159,1) -> 0 | ... CE85: =ROUND(CE82-CE159,1) -> 0
B86: Memo: FY26 sales guidance (scenario end-point) | CA86: =CHOOSE(MATCH($CF$2,{"Bull","Base","Bear"},0),$CN$12,$CO$12,$CP$12) -> 3790.5 | CF86: Q2-26 release: $3,768–3,813m. Drives the revenue-outlook calibration below.
B87: Sales before revenue calibration (Q3/Q4-26E helper) | BY87: =BT11*($CA$21-$BW$11-$BX$11)/($BT$11+$BU$11)+BT25*($CA$35-$BW$25-$BX$25)/($BT$25+$BU$25)+BT39*($CA$49-$BW$39-$BX$39)/($BT$39+$BU$39) -> 934.49653 | BZ87: =BU11*($CA$21-$BW$11-$BX$11)/($BT$11+$BU$11)+BU25*($CA$35-$BW$25-$BX$25)/($BT$25+$BU$25)+BU39*($CA$49-$BW$39-$BX$39)/($BT$39+$BU$39) -> 1018.3085 | CF87: Σ segments at the guidance-implied 2H growth rates.
B88: Revenue sensitivity to +1.00 of growth (Q3/Q4-26E helper) | BY88: =BT11+BT25+BT39 -> 869.17 | BZ88: =BU11+BU25+BU39 -> 946.981
B89: Outlook calibration: Δ y/y growth applied to all segments (Q3/Q4-26E) | BY89: =($CA$86-$BW$79-$BX$79-$BY$87-$BZ$87)/($BY$88+$BZ$88) -> 0 | BZ89: =($CA$86-$BW$79-$BX$79-$BY$87-$BZ$87)/($BY$88+$BZ$88) -> 0 | CF89: Solves the uniform growth shift so that FY26 sales = total guidance end-point (segment ranges do not sum exactly to the total range).
B90: Check: FY26 sales vs guidance end-point (should be 0) | CA90: =ROUND(CA79-CA86,1) -> 0
B91: Memo: FY26 Adjusted OI guidance (scenario end-point) | CA91: =CHOOSE(MATCH($CF$2,{"Bull","Base","Bear"},0),$CN$13,$CO$13,$CP$13) -> 728 | CF91: Q2-26 release: $720–736m (19.1–19.3% margin).
B92: Adjusted OI before margin calibration (Q3/Q4-26E helper) | BY92: =BY11*BY19+BY25*BY33+BY39*BY47+BY55 -> 186.28973 | BZ92: =BZ11*BZ19+BZ25*BZ33+BZ39*BZ47+BZ55 -> 203.08327
B93: Outlook calibration: Δ Adjusted margin applied to all segments (Q3/Q4-26E) | BY93: =($CA$91-$BW$82-$BX$82-$BY$92-$BZ$92)/($BY$11+$BZ$11+$BY$25+$BZ$25+$BY$39+$BZ$39) -> -0.0005120839 | BZ93: =($CA$91-$BW$82-$BX$82-$BY$92-$BZ$92)/($BY$11+$BZ$11+$BY$25+$BZ$25+$BY$39+$BZ$39) -> -0.0005120839 | CF93: Solves the uniform margin shift so that FY26 Adjusted OI = total guidance end-point for the active scenario.
B94: Check: FY26 Adjusted OI vs guidance end-point (should be 0) | CA94: =ROUND(CA82-CA91,1) -> 0
B95: Memo: FY26 Adjusted EPS guidance (scenario end-point) vs model | CA95: =CHOOSE(MATCH($CF$2,{"Bull","Base","Bear"},0),$CN$14,$CO$14,$CP$14) -> 15.25 | CF95: Not forced — model EPS reflects the post-guidance buybacks ($300m Aug–Oct) and model interest / other income.
B96: Model Adjusted EPS − guidance ($) | CA96: =CA191-CA95 -> 0.15651346
B97: Memo: FY26 FCF guidance (scenario end-point) — drives the 2026E receivables calibration | CA97: =CHOOSE(MATCH($CF$2,{"Bull","Base","Bear"},0),$CN$15,$CO$15,$CP$15) -> 595
B99: Cost drivers & D&A | CF99: COST DRIVERS — inputs that drive forecast cost lines
B100: Depreciation & amortization (total; cash-flow statement) | C100: 50.791 | D100: 62.699 | E100: 74.251 | F100: 76.48 | G100: 79.946 | H100: 88.3 | I100: 93.896 | J100: 30.4 | K100: 29.833 | L100: 29.427 | M100: 31.837 | N100: 121.497 | O100: 30.952 | P100: 30.434 | Q100: 29.548 | R100: 27.997 | S100: 118.931 | T100: 25.708 | U100: 25.83 | V100: 24.89 | W100: 24.382 | X100: 100.81 | Y100: 24.487 | Z100: 24.5 | AA100: 23.432 | AB100: 23.589 | AC100: 96.008 | AD100: 24.926 | AE100: 25.035 | AF100: 24.854 | AG100: 25.18 | AH100: 99.995 | AI100: 24.601 | AJ100: 26.656 | AK100: 25.889 | AL100: 25.803 | AM100: 102.949 | AN100: 25.793 | AO100: 25.807 | AP100: 25.398 | AQ100: 25.414 | AR100: 102.412 | AS100: 28.142 | AT100: 28.426 | AU100: 28.201 | AV100: 31.134 | AW100: 115.903 | AX100: 28.595 | AY100: 29.021 | AZ100: 28.624 | BA100: 28.144 | BB100: 114.384 | BC100: 27.363 | BD100: 26.282 | BE100: 29.875 | BF100: 28.507 | BG100: 112.027 | BH100: 28.927 | BI100: 29.048 | BJ100: 28.861 | BK100: 29.336 | BL100: 116.172 | BM100: 26.983 | BN100: 27.168 | BO100: 26.693 | BP100: 26.823 | BQ100: 107.667 | BR100: 30.821 | BS100: 31.307 | BT100: 31.191 | BU100: 31.498 | BV100: 124.817 | BW100: 28.365 | BX100: 28.37 | BY100: =BY102+BY101 -> 29.182431 | BZ100: =BZ102+BZ101 -> 29.514682 | CA100: =SUM(BW100,BX100,BY100,BZ100) -> 115.43211 | CB100: =CB102+CB101 -> 127.7888 | CC100: =CC102+CC101 -> 137.98987 | CD100: =CD102+CD101 -> 154.33637 | CE100: =CE102+CE101 -> 170.16031
B101: of which: amortization of acquired intangibles | G101: 26 | H101: 28.8 | I101: 24.9 | J101: 12.4 | K101: 11.8 | L101: 11.8 | M101: 3 | N101: 39 | O101: 10.3 | P101: 9.5 | Q101: 9.5 | R101: 9 | S101: 38.3 | T101: 8.6 | U101: 8.6 | V101: 9 | W101: 8.6 | X101: 34.8 | Y101: 8.4 | Z101: 8.4 | AA101: 8.1 | AB101: 8.5 | AC101: 33.4 | AD101: 9.6 | AE101: 9.5 | AF101: 9.7 | AG101: 9.6 | AH101: 38.4 | AI101: 9.6 | AJ101: 11.5 | AK101: 11.9 | AL101: 10.6 | AM101: 43.6 | AN101: 11.2 | AO101: 11.4 | AP101: 11.3 | AQ101: 11.1 | AR101: 45 | AS101: 14.1 | AT101: 14.6 | AU101: 14.3 | AV101: 18 | AW101: 61 | AX101: 15 | AY101: 15 | AZ101: 15 | BA101: 15 | BB101: 60 | BC101: 14 | BD101: 14 | BE101: 18 | BF101: 15 | BG101: 61 | BH101: 16 | BI101: 17 | BJ101: 16 | BK101: 16 | BL101: 65 | BM101: 14 | BN101: 15 | BO101: 14 | BP101: 14 | BQ101: 57 | BR101: 18 | BS101: 18 | BT101: 18 | BU101: 18 | BV101: 72 | BW101: 15 | BX101: 15 | BY101: =($CO$34-$BW$101-$BX$101)/2 -> 15 | BZ101: =($CO$34-$BW$101-$BX$101)/2 -> 15 | CA101: =SUM(BW101,BX101,BY101,BZ101) -> 60 | CB101: =57+N(CB75) -> 61 | CC101: =51+N(CC75) -> 63 | CD101: =51+N(CD75) -> 71 | CE101: =50+N(CE75) -> 78 | CF101: FY2025 10-K schedule: $60m (2026), $57m, $51m, $51m, $50m (2030) + amortization of future-M&A intangibles.
B102: of which: depreciation (total D&A − amortization) | G102: =IF(AND(ISNUMBER(G100),ISNUMBER(G101)),G100-G101,"") -> 53.946 | H102: =IF(AND(ISNUMBER(H100),ISNUMBER(H101)),H100-H101,"") -> 59.5 | I102: =IF(AND(ISNUMBER(I100),ISNUMBER(I101)),I100-I101,"") -> 68.996 | J102: =IF(AND(ISNUMBER(J100),ISNUMBER(J101)),J100-J101,"") -> 18 | K102: =IF(AND(ISNUMBER(K100),ISNUMBER(K101)),K100-K101,"") -> 18.033 | L102: =IF(AND(ISNUMBER(L100),ISNUMBER(L101)),L100-L101,"") -> 17.627 | M102: =IF(AND(ISNUMBER(M100),ISNUMBER(M101)),M100-M101,"") -> 28.837 | N102: =IF(AND(ISNUMBER(N100),ISNUMBER(N101)),N100-N101,"") -> 82.497 | ... BX102: =IF(AND(ISNUMBER(BX100),ISNUMBER(BX101)),BX100-BX101,"") -> 13.37 | BY102: =BY79*BY103 -> 14.182431 | BZ102: =BZ79*BZ103 -> 14.514682 | CA102: =SUM(BW102,BX102,BY102,BZ102) -> 55.432113 | CB102: =CB79*CB103+N(CB76) -> 66.7888 | CC102: =CC79*CC103+N(CC76) -> 74.989867 | CD102: =CD79*CD103+N(CD76) -> 83.336369 | CE102: =CE79*CE103+N(CE76) -> 92.16031
...

Sheet Bull-Base-Bear
B2: Curtiss-Wright (CW) — Bull / Base / Bear Case P&L Summary | J2: Share price ($): | K2: =Model!CA381 -> 544.21
B3: Adjusted figures (company definition: Adjusted operating income / Adjusted diluted EPS; Adjusted EBITDA = model definition) · USD millions · Live panel linked to Model — toggle scenario via Model!CF2. Bull and Bear panels are value snapshots generated from the Model with the switch set to each case. 2026E calibrated to the FY26 guidance end-points (high / mid / low). | J3: As of: | K3: =TODAY() -> 46302
B5: Scenario: | C5: =Model!$CF$2 -> Base | N5: Scenario: | O5: Bull | P5: Snapshot (values) — Model run with switch = Bull | Z5: Scenario: | AA5: Bear | AB5: Snapshot (values) — Model run with switch = Bear
B7: (USDm, except EPS and shares) | C7: 2025A | D7: 2026E | E7: 2027E | F7: 2028E | G7: 2029E | H7: 2030E | I7: 25-'30 CAGR | J7: LT Hist Avg | K7: LT Hist Min | L7: LT Hist Max | N7: (USDm, except EPS and shares) | O7: 2025A | P7: 2026E | Q7: 2027E | R7: 2028E | S7: 2029E | T7: 2030E | U7: 25-'30 CAGR | V7: LT Hist Avg | W7: LT Hist Min | X7: LT Hist Max | Z7: (USDm, except EPS and shares) | AA7: 2025A | AB7: 2026E | AC7: 2027E | AD7: 2028E | AE7: 2029E | AF7: 2030E | AG7: 25-'30 CAGR | AH7: LT Hist Avg | AI7: LT Hist Min | AJ7: LT Hist Max
B9: Sales | C9: =Model!BV114 -> 3498.372 | D9: =Model!CA114 -> 3790.5 | E9: =Model!CB114 -> 4111.8 | F9: =Model!CC114 -> 4493.1167 | G9: =Model!CD114 -> 4876.9605 | H9: =Model!CE114 -> 5283.7538 | I9: =IFERROR((H9/C9)^(1/5)-1,"n/m") -> 0.085963719 | N9: Sales | O9: 3498.372 | P9: 3813 | Q9: 4300.23 | R9: 4921.9079 | S9: 5571.5524 | T9: 6272.348 | U9: =IFERROR((T9/O9)^(1/5)-1,"n/m") -> 0.1238616 | Z9: Sales | AA9: 3498.372 | AB9: 3768 | AC9: 3924.72 | AD9: 4074.0294 | AE9: 4208.8136 | AF9: 4348.2277 | AG9: =IFERROR((AF9/AA9)^(1/5)-1,"n/m") -> 0.044453857
B10: Sales y/y % | D10: =IFERROR(D9/C9-1,"") -> 0.083503984 | E10: =IFERROR(E9/D9-1,"") -> 0.084764543 | F10: =IFERROR(F9/E9-1,"") -> 0.092737171 | G10: =IFERROR(G9/F9-1,"") -> 0.085429307 | H10: =IFERROR(H9/G9-1,"") -> 0.083411215 | N10: Sales y/y % | P10: 0.089935547 | Q10: 0.12778127 | R10: 0.14456852 | S10: 0.13199039 | T10: 0.12578103 | Z10: Sales y/y % | AB10: 0.077072421 | AC10: 0.041592357 | AD10: 0.038043338 | AE10: 0.033083738 | AF10: 0.033124328
B11: Naval & Power sales y/y % (largest segment; growth driver) | C11: =Model!BV212 -> 0.17573591 | D11: =Model!CA212 -> 0.10545428 | E11: =Model!CB212 -> 0.08 | F11: =Model!CC212 -> 0.075 | G11: =Model!CD212 -> 0.07 | H11: =Model!CE212 -> 0.07 | N11: Naval & Power sales y/y % (largest segment; growth driver) | O11: 0.17573591 | P11: 0.10977896 | Q11: 0.11 | R11: 0.105 | S11: 0.1 | T11: 0.1 | Z11: Naval & Power sales y/y % (largest segment; growth driver) | AA11: 0.17573591 | AB11: 0.10112961 | AC11: 0.05 | AD11: 0.045 | AE11: 0.04 | AF11: 0.04
B12: Adjusted operating income (company KPI) | C12: =Model!BV159 -> 650.994 | D12: =Model!CA159 -> 728 | E12: =Model!CB159 -> 809.7922 | F12: =Model!CC159 -> 898.86833 | G12: =Model!CD159 -> 986.5102 | H12: =Model!CE159 -> 1079.4849 | I12: =IFERROR((H12/C12)^(1/5)-1,"n/m") -> 0.10644014 | N12: Adjusted operating income (company KPI) | O12: 650.994 | P12: 736 | Q12: 885.66972 | R12: 1057.0994 | S12: 1233.728 | T12: 1425.4721 | U12: =IFERROR((T12/O12)^(1/5)-1,"n/m") -> 0.16970501 | Z12: Adjusted operating income (company KPI) | AA12: 650.994 | AB12: 720 | AC12: 751.58558 | AD12: 780.27985 | AE12: 805.49176 | AF12: 831.54921 | AG12: =IFERROR((AF12/AA12)^(1/5)-1,"n/m") -> 0.050176253
B13: Adjusted operating margin % | C13: =IFERROR(C12/C9,"") -> 0.18608484 | D13: =IFERROR(D12/D9,"") -> 0.1920591 | E13: =IFERROR(E12/E9,"") -> 0.19694348 | F13: =IFERROR(F12/F9,"") -> 0.20005453 | G13: =IFERROR(G12/G9,"") -> 0.20227972 | H13: =IFERROR(H12/H9,"") -> 0.20430266 | J13: =IFERROR(AVERAGE(Model!C160,Model!D160,Model!E160,Model!F160,Model!G160,Model!H160,Model!I160,Model!N160,Model!S160,Model!X160,Model!AC160,Model!AH160,Model!AM160,Model!AR160,Model!AW160,Model!BB160,Model!BG160,Model!BL160,Model!BQ160,Model!BV160),"") -> 0.13623148 | K13: =IFERROR(MIN(Model!C160,Model!D160,Model!E160,Model!F160,Model!G160,Model!H160,Model!I160,Model!N160,Model!S160,Model!X160,Model!AC160,Model!AH160,Model!AM160,Model!AR160,Model!AW160,Model!BB160,Model!BG160,Model!BL160,Model!BQ160,Model!BV160),"") -> 0.093046718 | L13: =IFERROR(MAX(Model!C160,Model!D160,Model!E160,Model!F160,Model!G160,Model!H160,Model!I160,Model!N160,Model!S160,Model!X160,Model!AC160,Model!AH160,Model!AM160,Model!AR160,Model!AW160,Model!BB160,Model!BG160,Model!BL160,Model!BQ160,Model!BV160),"") -> 0.18608484 | N13: Adjusted operating margin % | O13: 0.18608484 | P13: 0.19302387 | Q13: 0.20595869 | R13: 0.21477431 | S13: 0.22143344 | T13: 0.22726292 | V13: 0.13623148 | W13: 0.093046718 | X13: 0.18608484 | Z13: Adjusted operating margin % | AA13: 0.18608484 | AB13: 0.1910828 | AC13: 0.19150043 | AD13: 0.19152533 | AE13: 0.19138214 | AF13: 0.19123865 | AH13: 0.13623148 | AI13: 0.093046718 | AJ13: 0.18608484
B15: Operating income (GAAP) | C15: =Model!BV123 -> 633.521 | D15: =Model!CA123 -> 720.874 | E15: =Model!CB123 -> 809.7922 | F15: =Model!CC123 -> 898.86833 | G15: =Model!CD123 -> 986.5102 | H15: =Model!CE123 -> 1079.4849 | I15: =IFERROR((H15/C15)^(1/5)-1,"n/m") -> 0.11247719 | N15: Operating income (GAAP) | O15: 633.521 | P15: 728.874 | Q15: 885.66972 | R15: 1057.0994 | S15: 1233.728 | T15: 1425.4721 | U15: =IFERROR((T15/O15)^(1/5)-1,"n/m") -> 0.17608726 | Z15: Operating income (GAAP) | AA15: 633.521 | AB15: 712.874 | AC15: 751.58558 | AD15: 780.27985 | AE15: 805.49176 | AF15: 831.54921 | AG15: =IFERROR((AF15/AA15)^(1/5)-1,"n/m") -> 0.055906316
B16: Operating income y/y % | D16: =IFERROR(D15/C15-1,"") -> 0.13788493 | E16: =IFERROR(E15/D15-1,"") -> 0.12334777 | F16: =IFERROR(F15/E15-1,"") -> 0.10999875 | G16: =IFERROR(G15/F15-1,"") -> 0.097502452 | H16: =IFERROR(H15/G15-1,"") -> 0.094246112 | N16: Operating income y/y % | P16: 0.15051277 | Q16: 0.21512047 | R16: 0.19355933 | S16: 0.16708806 | T16: 0.15541846 | Z16: Operating income y/y % | AB16: 0.12525709 | AC16: 0.054303538 | AD16: 0.03817832 | AE16: 0.032311362 | AF16: 0.032349739
B17: Operating margin (GAAP) % | C17: =IFERROR(C15/C9,"") -> 0.18109023 | D17: =IFERROR(D15/D9,"") -> 0.19017913 | E17: =IFERROR(E15/E9,"") -> 0.19694348 | F17: =IFERROR(F15/F9,"") -> 0.20005453 | G17: =IFERROR(G15/G9,"") -> 0.20227972 | H17: =IFERROR(H15/H9,"") -> 0.20430266 | J17: =IFERROR(AVERAGE(Model!C124,Model!D124,Model!E124,Model!F124,Model!G124,Model!H124,Model!I124,Model!N124,Model!S124,Model!X124,Model!AC124,Model!AH124,Model!AM124,Model!AR124,Model!AW124,Model!BB124,Model!BG124,Model!BL124,Model!BQ124,Model!BV124),"") -> 0.13144665 | K17: =IFERROR(MIN(Model!C124,Model!D124,Model!E124,Model!F124,Model!G124,Model!H124,Model!I124,Model!N124,Model!S124,Model!X124,Model!AC124,Model!AH124,Model!AM124,Model!AR124,Model!AW124,Model!BB124,Model!BG124,Model!BL124,Model!BQ124,Model!BV124),"") -> 0.076962754 | L17: =IFERROR(MAX(Model!C124,Model!D124,Model!E124,Model!F124,Model!G124,Model!H124,Model!I124,Model!N124,Model!S124,Model!X124,Model!AC124,Model!AH124,Model!AM124,Model!AR124,Model!AW124,Model!BB124,Model!BG124,Model!BL124,Model!BQ124,Model!BV124),"") -> 0.18109023 | N17: Operating margin (GAAP) % | O17: 0.18109023 | P17: 0.191155 | Q17: 0.20595869 | R17: 0.21477431 | S17: 0.22143344 | T17: 0.22726292 | V17: 0.13144665 | W17: 0.076962754 | X17: 0.18109023 | Z17: Operating margin (GAAP) % | AA17: 0.18109023 | AB17: 0.18919161 | AC17: 0.19150043 | AD17: 0.19152533 | AE17: 0.19138214 | AF17: 0.19123865 | AH17: 0.13144665 | AI17: 0.076962754 | AJ17: 0.18109023
B19: Adjusted net earnings | C19: =Model!BV189 -> 497.85842 | D19: =Model!CA189 -> 568.89077 | E19: =Model!CB189 -> 637.70049 | F19: =Model!CC189 -> 703.73998 | G19: =Model!CD189 -> 768.95149 | H19: =Model!CE189 -> 838.05972 | I19: =IFERROR((H19/C19)^(1/5)-1,"n/m") -> 0.10977215 | N19: Adjusted net earnings | O19: 497.85842 | P19: 575.17077 | Q19: 694.77951 | R19: 804.20272 | S19: 931.81057 | T19: 1071.2906 | U19: =IFERROR((T19/O19)^(1/5)-1,"n/m") -> 0.16562884 | Z19: Adjusted net earnings | AA19: 497.85842 | AB19: 562.61077 | AC19: 592.06532 | AD19: 617.11309 | AE19: 634.85935 | AF19: 653.84253 | AG19: =IFERROR((AF19/AA19)^(1/5)-1,"n/m") -> 0.056023208
B21: FDSO (m) | C21: =Model!BV143 -> 37.631 | D21: =Model!CA143 -> 36.925341 | E21: =Model!CB143 -> 36.423811 | F21: =Model!CC143 -> 35.94746 | G21: =Model!CD143 -> 35.473648 | H21: =Model!CE143 -> 34.938293 | I21: =IFERROR((H21/C21)^(1/5)-1,"n/m") -> -0.014739243 | N21: FDSO (m) | O21: 37.631 | P21: 36.902372 | Q21: 36.057861 | R21: 35.447148 | S21: 35.007245 | T21: 34.382138 | U21: =IFERROR((T21/O21)^(1/5)-1,"n/m") -> -0.017896126 | Z21: FDSO (m) | AA21: 37.631 | AB21: 36.925341 | AC21: 36.420443 | AD21: 35.796924 | AE21: 35.086715 | AF21: 34.41381 | AG21: =IFERROR((AF21/AA21)^(1/5)-1,"n/m") -> -0.017715255
B23: Adjusted EPS — Diluted ($) | C23: =Model!BV191 -> 13.230008 | D23: =Model!CA191 -> 15.406513 | E23: =Model!CB191 -> 17.507792 | F23: =Model!CC191 -> 19.576904 | G23: =Model!CD191 -> 21.676696 | H23: =Model!CE191 -> 23.986853 | I23: =IFERROR((H23/C23)^(1/5)-1,"n/m") -> 0.12637405 | N23: Adjusted EPS — Diluted ($) | O23: 13.230008 | P23: 15.586282 | Q23: 19.268462 | R23: 22.687374 | S23: 26.617649 | T23: 31.158347 | U23: =IFERROR((T23/O23)^(1/5)-1,"n/m") -> 0.18686921 | Z23: Adjusted EPS — Diluted ($) | AA23: 13.230008 | AB23: 15.236441 | AC23: 16.256401 | AD23: 17.239277 | AE23: 18.094009 | AF23: 18.999423 | AG23: =IFERROR((AF23/AA23)^(1/5)-1,"n/m") -> 0.075068317
B24: EPS y/y % | D24: =IFERROR(D23/C23-1,"") -> 0.16451281 | E24: =IFERROR(E23/D23-1,"") -> 0.13638895 | F24: =IFERROR(F23/E23-1,"") -> 0.11818238 | G24: =IFERROR(G23/F23-1,"") -> 0.10725864 | H24: =IFERROR(H23/G23-1,"") -> 0.1065733 | N24: EPS y/y % | P24: 0.17810073 | Q24: 0.23624494 | R24: 0.17743567 | S24: 0.17323621 | T24: 0.17058973 | Z24: EPS y/y % | AB24: 0.15165773 | AC24: 0.066942161 | AD24: 0.060460882 | AE24: 0.04958052 | AF24: 0.050039405
B26: P / E (x) — assumed (adjusted EPS) | G26: 28 | H26: 28 | N26: P / E (x) — assumed (adjusted EPS) | S26: 32 | T26: 32 | Z26: P / E (x) — assumed (adjusted EPS) | AE26: 24 | AF26: 24
B27: Price Target ($) | G27: =G26*G23 -> 606.9475 | H27: =H26*H23 -> 671.6319 | N27: Price Target ($) | S27: =S26*S23 -> 851.76477 | T27: =T26*T23 -> 997.06709 | Z27: Price Target ($) | AE27: =AE26*AE23 -> 434.25623 | AF27: =AF26*AF23 -> 455.98615
B28: Upside / (Downside) vs current | G28: =IFERROR(G27/$K$2-1,"") -> 0.11528178 | H28: =IFERROR(H27/$K$2-1,"") -> 0.23414104 | N28: Upside / (Downside) vs current | S28: =IFERROR(S27/$K$2-1,"") -> 0.56513987 | T28: =IFERROR(T27/$K$2-1,"") -> 0.83213666 | Z28: Upside / (Downside) vs current | AE28: =IFERROR(AE27/$K$2-1,"") -> -0.20204291 | AF28: =IFERROR(AF27/$K$2-1,"") -> -0.16211361
B29: IRR (to Dec-Y-1) | G29: =IFERROR((G27/$K$2)^(1/((DATE(2029-1,12,31)-$K$3)/365.25))-1,"") -> 0.050049659 | H29: =IFERROR((H27/$K$2)^(1/((DATE(2030-1,12,31)-$K$3)/365.25))-1,"") -> 0.067226388 | N29: IRR (to Dec-Y-1) | S29: =IFERROR((S27/$K$2)^(1/((DATE(2029-1,12,31)-$K$3)/365.25))-1,"") -> 0.22203598 | T29: =IFERROR((T27/$K$2)^(1/((DATE(2030-1,12,31)-$K$3)/365.25))-1,"") -> 0.20593931 | Z29: IRR (to Dec-Y-1) | AE29: =IFERROR((AE27/$K$2)^(1/((DATE(2029-1,12,31)-$K$3)/365.25))-1,"") -> -0.096090331 | AF29: =IFERROR((AF27/$K$2)^(1/((DATE(2030-1,12,31)-$K$3)/365.25))-1,"") -> -0.053232529
B31: Free Cash Flow (CFO − net capex) | C31: =Model!BV257 -> 553.71 | D31: =Model!CA257 -> 595 | E31: =Model!CB257 -> 623.11068 | F31: =Model!CC257 -> 682.26568 | G31: =Model!CD257 -> 755.04 | H31: =Model!CE257 -> 828.94351 | I31: =IFERROR((H31/C31)^(1/5)-1,"n/m") -> 0.084048004 | N31: Free Cash Flow (CFO − net capex) | O31: 553.71 | P31: 605 | Q31: 672.39007 | R31: 776.06662 | S31: 917.58763 | T31: 1068.2718 | U31: =IFERROR((T31/O31)^(1/5)-1,"n/m") -> 0.14045953 | Z31: Free Cash Flow (CFO − net capex) | AA31: 553.71 | AB31: 585 | AC31: 587.9775 | AD31: 604.82136 | AE31: 623.27602 | AF31: 639.99373 | AG31: =IFERROR((AF31/AA31)^(1/5)-1,"n/m") -> 0.029386981
B32: FCF % | C32: =IFERROR(C31/C9,"") -> 0.15827648 | D32: =IFERROR(D31/D9,"") -> 0.15697138 | E32: =IFERROR(E31/E9,"") -> 0.15154207 | F32: =IFERROR(F31/F9,"") -> 0.15184686 | G32: =IFERROR(G31/G9,"") -> 0.15481774 | H32: =IFERROR(H31/H9,"") -> 0.15688534 | J32: =IFERROR(AVERAGE(Model!C259,Model!D259,Model!E259,Model!F259,Model!G259,Model!H259,Model!I259,Model!N259,Model!S259,Model!X259,Model!AC259,Model!AH259,Model!AM259,Model!AR259,Model!AW259,Model!BB259,Model!BG259,Model!BL259,Model!BQ259,Model!BV259),"") -> 0.10025119 | K32: =IFERROR(MIN(Model!C259,Model!D259,Model!E259,Model!F259,Model!G259,Model!H259,Model!I259,Model!N259,Model!S259,Model!X259,Model!AC259,Model!AH259,Model!AM259,Model!AR259,Model!AW259,Model!BB259,Model!BG259,Model!BL259,Model!BQ259,Model!BV259),"") -> 0.033140806 | L32: =IFERROR(MAX(Model!C259,Model!D259,Model!E259,Model!F259,Model!G259,Model!H259,Model!I259,Model!N259,Model!S259,Model!X259,Model!AC259,Model!AH259,Model!AM259,Model!AR259,Model!AW259,Model!BB259,Model!BG259,Model!BL259,Model!BQ259,Model!BV259),"") -> 0.17848901 | N32: FCF % | O32: 0.15827648 | P32: 0.15866772 | Q32: 0.15636142 | R32: 0.15767597 | S32: 0.16469155 | T32: 0.17031449 | V32: 0.10025119 | W32: 0.033140806 | X32: 0.17848901 | Z32: FCF % | AA32: 0.15827648 | AB32: 0.15525478 | AC32: 0.14981387 | AD32: 0.14845778 | AE32: 0.14808829 | AF32: 0.14718496 | AH32: 0.10025119 | AI32: 0.033140806 | AJ32: 0.17848901
B33: FCF / share ($) | C33: =IFERROR(C31/C21,"") -> 14.714198 | D33: =IFERROR(D31/D21,"") -> 16.113595 | E33: =IFERROR(E31/E21,"") -> 17.107235 | F33: =IFERROR(F31/F21,"") -> 18.979524 | G33: =IFERROR(G31/G21,"") -> 21.284532 | H33: =IFERROR(H31/H21,"") -> 23.72593 | N33: FCF / share ($) | O33: 14.714198 | P33: 16.39461 | Q33: 18.647531 | R33: 21.893626 | S33: 26.211363 | T33: 31.070545 | Z33: FCF / share ($) | AA33: 14.714198 | AB33: 15.842778 | AC33: 16.144161 | AD33: 16.895903 | AE33: 17.763875 | AF33: 18.597003
B34: FCF Yield (on PT) | G34: =IFERROR(G33/G27,"") -> 0.035068161 | H34: =IFERROR(H33/H27,"") -> 0.035325795 | N34: FCF Yield (on PT) | S34: =IFERROR(S33/S27,"") -> 0.030773007 | T34: =IFERROR(T33/T27,"") -> 0.031161941 | Z34: FCF Yield (on PT) | AE34: =IFERROR(AE33/AE27,"") -> 0.040906437 | AF34: =IFERROR(AF33/AF27,"") -> 0.04078414
B35: Adjusted EBITDA (model: Adjusted OI + D&A) | C35: =Model!BV174 -> 775.811 | D35: =Model!CA174 -> 843.43211 | E35: =Model!CB174 -> 937.581 | F35: =Model!CC174 -> 1036.8582 | G35: =Model!CD174 -> 1140.8466 | H35: =Model!CE174 -> 1249.6453 | I35: =IFERROR((H35/C35)^(1/5)-1,"n/m") -> 0.10003414 | N35: Adjusted EBITDA (model: Adjusted OI + D&A) | O35: 775.811 | P35: 851.76281 | Q35: 1021.4734 | R35: 1217.0499 | S35: 1424.4829 | T35: 1647.0702 | U35: =IFERROR((T35/O35)^(1/5)-1,"n/m") -> 0.16249538 | Z35: Adjusted EBITDA (model: Adjusted OI + D&A) | AA35: 775.811 | AB35: 835.10141 | AC35: 871.3811 | AD35: 896.46433 | AE35: 923.83278 | AF35: 951.12085 | AG35: =IFERROR((AF35/AA35)^(1/5)-1,"n/m") -> 0.041587967
B36: Adjusted EBITDA % of sales | C36: =IFERROR(C35/C9,"") -> 0.22176344 | D36: =IFERROR(D35/D9,"") -> 0.2225121 | E36: =IFERROR(E35/E9,"") -> 0.22802203 | F36: =IFERROR(F35/F9,"") -> 0.23076592 | G36: =IFERROR(G35/G9,"") -> 0.23392573 | H36: =IFERROR(H35/H9,"") -> 0.2365071 | J36: =IFERROR(AVERAGE(Model!C175,Model!D175,Model!E175,Model!F175,Model!G175,Model!H175,Model!I175,Model!N175,Model!S175,Model!X175,Model!AC175,Model!AH175,Model!AM175,Model!AR175,Model!AW175,Model!BB175,Model!BG175,Model!BL175,Model!BQ175,Model!BV175),"") -> 0.17929397 | K36: =IFERROR(MIN(Model!C175,Model!D175,Model!E175,Model!F175,Model!G175,Model!H175,Model!I175,Model!N175,Model!S175,Model!X175,Model!AC175,Model!AH175,Model!AM175,Model!AR175,Model!AW175,Model!BB175,Model!BG175,Model!BL175,Model!BQ175,Model!BV175),"") -> 0.13582382 | L36: =IFERROR(MAX(Model!C175,Model!D175,Model!E175,Model!F175,Model!G175,Model!H175,Model!I175,Model!N175,Model!S175,Model!X175,Model!AC175,Model!AH175,Model!AM175,Model!AR175,Model!AW175,Model!BB175,Model!BG175,Model!BL175,Model!BQ175,Model!BV175),"") -> 0.22176344 | N36: Adjusted EBITDA % of sales | O36: 0.22176344 | P36: 0.2233839 | Q36: 0.23753925 | R36: 0.24727197 | S36: 0.25567073 | T36: 0.26259229 | V36: 0.17929397 | W36: 0.13582382 | X36: 0.22176344 | Z36: Adjusted EBITDA % of sales | AA36: 0.22176344 | AB36: 0.22162989 | AC36: 0.22202376 | AD36: 0.22004365 | AE36: 0.21949957 | AF36: 0.21873759 | AH36: 0.17929397 | AI36: 0.13582382 | AJ36: 0.22176344
B38: Net Debt | C38: =Model!BV376 -> 586.539 | D38: =Model!CA376 -> 347.03295 | E38: =Model!CB376 -> 468.7905 | F38: =Model!CC376 -> 518.4291 | G38: =Model!CD376 -> 570.42328 | H38: =Model!CE376 -> 624.82263 | N38: Net Debt | O38: 586.539 | P38: 437.00907 | Q38: 1021.4734 | R38: 1217.0499 | S38: 1424.4829 | T38: 1647.0702 | Z38: Net Debt | AA38: 586.539 | AB38: 357.03295 | AC38: 217.84527 | AD38: 224.11608 | AE38: 230.95819 | AF38: 237.78021
B39: Net Debt / Adjusted EBITDA (x) | C39: =IFERROR(C38/C35,"") -> 0.75603336 | D39: =IFERROR(D38/D35,"") -> 0.41145333 | E39: =IFERROR(E38/E35,"") -> 0.5 | F39: =IFERROR(F38/F35,"") -> 0.5 | G39: =IFERROR(G38/G35,"") -> 0.5 | H39: =IFERROR(H38/H35,"") -> 0.5 | N39: Net Debt / Adjusted EBITDA (x) | O39: 0.75603336 | P39: 0.51306427 | Q39: 1 | R39: 1 | S39: 1 | T39: 1 | Z39: Net Debt / Adjusted EBITDA (x) | AA39: 0.75603336 | AB39: 0.42753245 | AC39: 0.25 | AD39: 0.25 | AE39: 0.25 | AF39: 0.25
B40: Share repurchases ($m) | D40: =Model!CA266 -> 300 | E40: =Model!CB266 -> 414.68199 | F40: =Model!CC266 -> 399.11245 | G40: =Model!CD266 -> 471.38509 | H40: =Model!CE266 -> 544.74549 | N40: Share repurchases ($m) | P40: 400 | Q40: 626.87059 | R40: 339.50342 | S40: 489.95292 | T40: 652.9283 | Z40: Share repurchases ($m) | AB40: 300 | AC40: 418.60358 | AD40: 578.30835 | AE40: 594.84724 | AF40: 608.88382
B41: Implied avg buyback price ($) | D41: =Model!CA265 -> 544.21 | E41: =Model!CB265 -> 582.3047 | F41: =Model!CC265 -> 623.06603 | G41: =Model!CD265 -> 666.68065 | H41: =Model!CE265 -> 713.3483 | N41: Implied avg buyback price ($) | P41: 544.21 | Q41: 582.3047 | R41: 623.06603 | S41: 666.68065 | T41: 713.3483 | Z41: Implied avg buyback price ($) | AB41: 544.21 | AC41: 582.3047 | AD41: 623.06603 | AE41: 666.68065 | AF41: 713.3483
B42: Shares repurchased (m) | D42: =Model!CA267 -> 0.55125779 | E42: =Model!CB267 -> 0.71213918 | F42: =Model!CC267 -> 0.64056205 | G42: =Model!CD267 -> 0.70706281 | H42: =Model!CE267 -> 0.76364588 | N42: Shares repurchased (m) | P42: 0.73501038 | Q42: 1.0765336 | R42: 0.54489156 | S42: 0.73491396 | T42: 0.91530084 | Z42: Shares repurchased (m) | AB42: 0.55125779 | AC42: 0.71887378 | AD42: 0.92816543 | AE42: 0.89225214 | AF42: 0.85355755
B44: ROIC | C44: =Model!BV359 -> 0.16295131 | D44: =Model!CA359 -> 0.1848843 | E44: =Model!CB359 -> 0.18294905 | F44: =Model!CC359 -> 0.18413109 | G44: =Model!CD359 -> 0.18505091 | H44: =Model!CE359 -> 0.18682259 | J44: =IFERROR(AVERAGE(Model!C359,Model!D359,Model!E359,Model!F359,Model!G359,Model!H359,Model!I359,Model!N359,Model!S359,Model!X359,Model!AC359,Model!AH359,Model!AM359,Model!AR359,Model!AW359,Model!BB359,Model!BG359,Model!BL359,Model!BQ359,Model!BV359),"") -> 0.10962339 | K44: =IFERROR(MIN(Model!C359,Model!D359,Model!E359,Model!F359,Model!G359,Model!H359,Model!I359,Model!N359,Model!S359,Model!X359,Model!AC359,Model!AH359,Model!AM359,Model!AR359,Model!AW359,Model!BB359,Model!BG359,Model!BL359,Model!BQ359,Model!BV359),"") -> 0.06600687 | L44: =IFERROR(MAX(Model!C359,Model!D359,Model!E359,Model!F359,Model!G359,Model!H359,Model!I359,Model!N359,Model!S359,Model!X359,Model!AC359,Model!AH359,Model!AM359,Model!AR359,Model!AW359,Model!BB359,Model!BG359,Model!BL359,Model!BQ359,Model!BV359),"") -> 0.16295131 | N44: ROIC | O44: 0.16295131 | P44: 0.1871213 | Q44: 0.1838191 | R44: 0.18641137 | S44: 0.18945961 | T44: 0.19406752 | V44: 0.10962339 | W44: 0.06600687 | X44: 0.16295131 | Z44: ROIC | AA44: 0.16295131 | AB44: 0.18265244 | AC44: 0.18644946 | AD44: 0.19096546 | AE44: 0.19450245 | AF44: 0.19794745 | AH44: 0.10962339 | AI44: 0.06600687 | AJ44: 0.16295131
B45: RONTA | C45: =Model!BV370 -> 0.28390171 | D45: =Model!CA370 -> 0.30370136 | E45: =Model!CB370 -> 0.3313625 | F45: =Model!CC370 -> 0.34781781 | G45: =Model!CD370 -> 0.35504826 | H45: =Model!CE370 -> 0.36230667 | J45: =IFERROR(AVERAGE(Model!C370,Model!D370,Model!E370,Model!F370,Model!G370,Model!H370,Model!I370,Model!N370,Model!S370,Model!X370,Model!AC370,Model!AH370,Model!AM370,Model!AR370,Model!AW370,Model!BB370,Model!BG370,Model!BL370,Model!BQ370,Model!BV370),"") -> 0.18635808 | K45: =IFERROR(MIN(Model!C370,Model!D370,Model!E370,Model!F370,Model!G370,Model!H370,Model!I370,Model!N370,Model!S370,Model!X370,Model!AC370,Model!AH370,Model!AM370,Model!AR370,Model!AW370,Model!BB370,Model!BG370,Model!BL370,Model!BQ370,Model!BV370),"") -> 0.11731518 | L45: =IFERROR(MAX(Model!C370,Model!D370,Model!E370,Model!F370,Model!G370,Model!H370,Model!I370,Model!N370,Model!S370,Model!X370,Model!AC370,Model!AH370,Model!AM370,Model!AR370,Model!AW370,Model!BB370,Model!BG370,Model!BL370,Model!BQ370,Model!BV370),"") -> 0.28390171 | N45: RONTA | O45: 0.28390171 | P45: 0.32299785 | Q45: 0.36221484 | R45: 0.39128276 | S45: 0.41581356 | T45: 0.43941481 | V45: 0.18635808 | W45: 0.11731518 | X45: 0.28390171 | Z45: RONTA | AA45: 0.28390171 | AB45: 0.30140369 | AC45: 0.27720575 | AD45: 0.27634528 | AE45: 0.27439669 | AF45: 0.27260135 | AH45: 0.18635808 | AI45: 0.11731518 | AJ45: 0.28390171
B47: Implied Market Cap (USDm) | G47: =G27*G21 -> 21530.642 | H47: =H27*H21 -> 23465.672 | N47: Implied Market Cap (USDm) | S47: =S27*S21 -> 29817.938 | T47: =T27*T21 -> 34281.298 | Z47: Implied Market Cap (USDm) | AE47: =AE27*AE21 -> 15236.624 | AF47: =AF27*AF21 -> 15692.221
B48: (+) Net Debt | G48: =G38 -> 570.42328 | H48: =H38 -> 624.82263 | N48: (+) Net Debt | S48: =S38 -> 1424.4829 | T48: =T38 -> 1647.0702 | Z48: (+) Net Debt | AE48: =AE38 -> 230.95819 | AF48: =AF38 -> 237.78021
B49: Implied Enterprise Value (USDm) | G49: =G47+G48 -> 22101.065 | H49: =H47+H48 -> 24090.495 | N49: Implied Enterprise Value (USDm) | S49: =S47+S48 -> 31242.421 | T49: =T47+T48 -> 35928.369 | Z49: Implied Enterprise Value (USDm) | AE49: =AE47+AE48 -> 15467.583 | AF49: =AF47+AF48 -> 15930.001
B50: Implied EV / Adjusted EBITDA (x) | G50: =IFERROR(G49/G35,"") -> 19.372513 | H50: =IFERROR(H49/H35,"") -> 19.277867 | N50: Implied EV / Adjusted EBITDA (x) | S50: =IFERROR(S49/S35,"") -> 21.932465 | T50: =IFERROR(T49/T35,"") -> 21.813502 | Z50: Implied EV / Adjusted EBITDA (x) | AE50: =IFERROR(AE49/AE35,"") -> 16.742838 | AF50: =IFERROR(AF49/AF35,"") -> 16.748661

Sheet DCF
B2: DCF VALUATION — CURTISS-WRIGHT (CW)
B4: 1. WACC BUILD
B5: Risk-free rate (US 10Y govt) | C5: 0.055 | D5: Assumption (kept consistent with the other models in the coverage set); update to market
B6: Equity risk premium | C6: 0.05 | D6: US implied ERP ~4.5–5.5% (Damodaran)
B7: Levered beta | C7: 0.95 | D7: A&D / defense-electronics peers (HEI, TDG, MOG, PH aerospace, BWXT) ~0.85–1.1; ~70% A&D mix, long-cycle naval & nuclear backlog
B8: Cost of equity | C8: =C5+C7*C6 -> 0.1025
B9: Pre-tax cost of debt | C9: 0.055 | D9: BBB-rated private-placement notes 3.1–4.6%; marginal cost ~5.5%
B10: Tax rate | C10: 0.22 | D10: Model 2027E+ effective tax rate
B11: After-tax cost of debt | C11: =C9*(1-C10) -> 0.0429
B12: Target D/V | C12: 0.05 | D12: Net debt ~$0.4bn vs ~$20bn market cap; net leverage ~0.5x Adjusted EBITDA
B13: WACC | C13: =C8*(1-C12)+C11*C12 -> 0.09952
B15: Valuation date (live) | C15: =TODAY() -> 46302 | D15: Periods = (Dec-31-Year − today) / 365.25; cash flows assumed at year-end
B16: 2. UNLEVERED FREE CASH FLOW BUILD (USDm)
D17: 2026E | E17: 2027E | F17: 2028E | G17: 2029E | H17: 2030E | I17: 2031E | J17: 2032E | K17: 2033E | L17: 2034E | M17: 2035E | N17: Terminal | P17: CAGR 27–30E | Q17: CAGR 27–35E
B18: Operating income (GAAP) = Adjusted OI less restructuring & other adjustments | D18: =Model!CA123 -> 720.874 | E18: =Model!CB123 -> 809.7922 | F18: =Model!CC123 -> 898.86833 | G18: =Model!CD123 -> 986.5102 | H18: =Model!CE123 -> 1079.4849 | I18: =H18*(1+I$26) -> 1155.0489 | J18: =I18*(1+J$26) -> 1230.1271 | K18: =J18*(1+K$26) -> 1303.9347 | L18: =K18*(1+L$26) -> 1375.6511 | M18: =L18*(1+M$26) -> 1444.4337
B19: × (1 − tax rate) | D19: =1-$C$10 -> 0.78 | E19: =1-$C$10 -> 0.78 | F19: =1-$C$10 -> 0.78 | G19: =1-$C$10 -> 0.78 | H19: =1-$C$10 -> 0.78 | I19: =1-$C$10 -> 0.78 | J19: =1-$C$10 -> 0.78 | K19: =1-$C$10 -> 0.78 | ... M19: =1-$C$10 -> 0.78
B20: NOPAT | D20: =D18*D19 -> 562.28172 | E20: =E18*E19 -> 631.63792 | F20: =F18*F19 -> 701.1173 | G20: =G18*G19 -> 769.47795 | H20: =H18*H19 -> 841.99826 | I20: =I18*I19 -> 900.93814 | J20: =J18*J19 -> 959.49912 | K20: =K18*K19 -> 1017.0691 | ... M20: =M18*M19 -> 1126.6583
B21: plus D&A | D21: =Model!CA100 -> 115.43211 | E21: =Model!CB100 -> 127.7888 | F21: =Model!CC100 -> 137.98987 | G21: =Model!CD100 -> 154.33637 | H21: =Model!CE100 -> 170.16031 | I21: =H21*(1+I$26) -> 182.07153 | J21: =I21*(1+J$26) -> 193.90618 | K21: =J21*(1+K$26) -> 205.54055 | L21: =K21*(1+L$26) -> 216.84528 | M21: =L21*(1+M$26) -> 227.68755
B22: − Capex (PP&E, net of grants) and acquisitions (M&A 2027E–30E) | D22: =Model!CA237+Model!CA238+Model!CA239 -> -106.164 | E22: =Model!CB237+Model!CB238+Model!CB239 -> -419.2422 | F22: =Model!CC237+Model!CC238+Model!CC239 -> -430.30038 | G22: =Model!CD237+Model!CD238+Model!CD239 -> -441.43186 | H22: =Model!CE237+Model!CE238+Model!CE239 -> -453.22886 | I22: =Model!CE237*(1+I$26) -> -163.95488 | J22: =I22*(1+J$26) -> -174.61195 | K22: =J22*(1+K$26) -> -185.08866 | L22: =K22*(1+L$26) -> -195.26854 | M22: =L22*(1+M$26) -> -205.03197
B23: − Δ Working capital (CF statement, excl. non-cash pension) | D23: =Model!CA234-Model!CA235 -> 4.4466434 | E23: =Model!CB234-Model!CB235 -> -28.974907 | F23: =Model!CC234-Model!CC235 -> -37.862158 | G23: =Model!CD234-Model!CD235 -> -38.393204 | H23: =Model!CE234-Model!CE235 -> -40.67581 | I23: =H23*(1+I$26) -> -43.523116 | J23: =I23*(1+J$26) -> -46.352119 | K23: =J23*(1+K$26) -> -49.133246 | L23: =K23*(1+L$26) -> -51.835575 | M23: =L23*(1+M$26) -> -54.427353
B24: Unlevered FCF | D24: =D20+D21+D22+D23 -> 575.99648 | E24: =E20+E21+E22+E23 -> 311.20961 | F24: =F20+F21+F22+F23 -> 370.94462 | G24: =G20+G21+G22+G23 -> 443.98926 | H24: =H20+H21+H22+H23 -> 518.2539 | I24: =I20+I21+I22+I23 -> 875.53167 | J24: =J20+J21+J22+J23 -> 932.44123 | K24: =K20+K21+K22+K23 -> 988.38771 | ... M24: =M20+M21+M22+M23 -> 1094.8865 | N24: =M24*(1+$C$27) -> 1138.6819 | P24: =IFERROR((H24/E24)^(1/3)-1,"n/m") -> 0.1853043 | Q24: =IFERROR((M24/E24)^(1/8)-1,"n/m") -> 0.17027927
B25: Terminal Value (Gordon Growth) | N25: =N24/($C$13-$C$27) -> 19131.081
B26: Fade-period growth (2031E–35E; 7% → 5% linear) | I26: 0.07 | J26: =I26+($M$26-$I$26)/4 -> 0.065 | K26: =J26+($M$26-$I$26)/4 -> 0.06 | L26: =K26+($M$26-$I$26)/4 -> 0.055 | M26: 0.05
B27: Terminal growth rate | C27: 0.04
B29: Discount period (years) | D29: =(DATE(2026,12,31)-$C$15)/365.25 -> 0.23271732 | E29: =(DATE(2027,12,31)-$C$15)/365.25 -> 1.2320329 | F29: =(DATE(2028,12,31)-$C$15)/365.25 -> 2.2340862 | G29: =(DATE(2029,12,31)-$C$15)/365.25 -> 3.2334018 | H29: =(DATE(2030,12,31)-$C$15)/365.25 -> 4.2327173 | I29: =(DATE(2031,12,31)-$C$15)/365.25 -> 5.2320329 | J29: =(DATE(2032,12,31)-$C$15)/365.25 -> 6.2340862 | K29: =(DATE(2033,12,31)-$C$15)/365.25 -> 7.2334018 | L29: =(DATE(2034,12,31)-$C$15)/365.25 -> 8.2327173 | M29: =(DATE(2035,12,31)-$C$15)/365.25 -> 9.2320329 | N29: =M29 -> 9.2320329
B30: Discount factor | D30: =1/(1+$C$13)^D29 -> 0.97816319 | E30: =1/(1+$C$13)^E29 -> 0.88968524 | F30: =1/(1+$C$13)^F29 -> 0.80900023 | G30: =1/(1+$C$13)^G29 -> 0.7358236 | H30: =1/(1+$C$13)^H29 -> 0.66926603 | I30: =1/(1+$C$13)^I29 -> 0.6087288 | J30: =1/(1+$C$13)^J29 -> 0.55352356 | K30: =1/(1+$C$13)^K29 -> 0.50345561 | ... N30: =1/(1+$C$13)^N29 -> 0.41649646
B31: PV of UFCF | D31: =D24*D30*0 -> 0 | E31: =E24*E30 -> 276.8786 | F31: =F24*F30 -> 300.09429 | G31: =G24*G30 -> 326.69778 | H31: =H24*H30 -> 346.84973 | I31: =I24*I30 -> 532.96135 | J31: =J24*J30 -> 516.12819 | K31: =K24*K30 -> 497.60933 | L31: =L24*L30 -> 477.49194 | M31: =M24*M30 -> 456.01635 | N31: =N25*N30 -> 7968.0276
D32: 2026E is shown for reference but excluded from the PV (×0): its cash flow (incl. the 2H/26 $300m buybacks) is already reflected in YE2026E net debt, which is deducted below. Adjusted OI expenses stock-based compensation; acquisition spend from the M&A lever is deducted in 2027E–30E; fade and terminal value assume no new acquisitions. Non-service pension income sits below operating income and is excluded from UFCF (CW plans are overfunded).
B33: IMPLIED ROIC — invested capital roll-forward (USDm)
B34: Opening invested capital | E34: =Model!CA356 -> 3107.1062 | F34: =E38 -> 3427.5346 | G34: =F38 -> 3757.7072 | H34: =G38 -> 4083.1959 | I34: =H38 -> 4406.9403 | J34: =I38 -> 4432.3467 | K34: =J38 -> 4459.4046 | L34: =K38 -> 4488.086 | M34: =L38 -> 4518.3448
B35: plus Capex and acquisitions | E35: =-E22 -> 419.2422 | F35: =-F22 -> 430.30038 | G35: =-G22 -> 441.43186 | H35: =-H22 -> 453.22886 | I35: =-I22 -> 163.95488 | J35: =-J22 -> 174.61195 | K35: =-K22 -> 185.08866 | L35: =-L22 -> 195.26854 | M35: =-M22 -> 205.03197
B36: less D&A | E36: =-E21 -> -127.7888 | F36: =-F21 -> -137.98987 | G36: =-G21 -> -154.33637 | H36: =-H21 -> -170.16031 | I36: =-I21 -> -182.07153 | J36: =-J21 -> -193.90618 | K36: =-K21 -> -205.54055 | L36: =-L21 -> -216.84528 | M36: =-M21 -> -227.68755
B37: plus Δ Working capital investment | E37: =-E23 -> 28.974907 | F37: =-F23 -> 37.862158 | G37: =-G23 -> 38.393204 | H37: =-H23 -> 40.67581 | I37: =-I23 -> 43.523116 | J37: =-J23 -> 46.352119 | K37: =-K23 -> 49.133246 | L37: =-L23 -> 51.835575 | M37: =-M23 -> 54.427353
B38: Closing invested capital | E38: =SUM(E34:E37) -> 3427.5346 | F38: =SUM(F34:F37) -> 3757.7072 | G38: =SUM(G34:G37) -> 4083.1959 | H38: =SUM(H34:H37) -> 4406.9403 | I38: =SUM(I34:I37) -> 4432.3467 | J38: =SUM(J34:J37) -> 4459.4046 | K38: =SUM(K34:K37) -> 4488.086 | L38: =SUM(L34:L37) -> 4518.3448 | M38: =SUM(M34:M37) -> 4550.1166
B39: NOPAT (row 20) | E39: =E20 -> 631.63792 | F39: =F20 -> 701.1173 | G39: =G20 -> 769.47795 | H39: =H20 -> 841.99826 | I39: =I20 -> 900.93814 | J39: =J20 -> 959.49912 | K39: =K20 -> 1017.0691 | L39: =L20 -> 1073.0079 | M39: =M20 -> 1126.6583
B40: Implied ROIC (NOPAT / avg. invested capital) | E40: =IFERROR(E39/AVERAGE(E34,E38),"") -> 0.19331986 | F40: =IFERROR(F39/AVERAGE(F34,F38),"") -> 0.19515482 | G40: =IFERROR(G39/AVERAGE(G34,G38),"") -> 0.19627279 | H40: =IFERROR(H39/AVERAGE(H34,H38),"") -> 0.19834741 | I40: =IFERROR(I39/AVERAGE(I34,I38),"") -> 0.2038486 | J40: =IFERROR(J39/AVERAGE(J34,J38),"") -> 0.2158178 | K40: =IFERROR(K39/AVERAGE(K34,K38),"") -> 0.22734175 | L40: =IFERROR(L39/AVERAGE(L34,L38),"") -> 0.23827594 | M40: =IFERROR(M39/AVERAGE(M34,M38),"") -> 0.24847837
B41: Reinvestment rate (net investment / NOPAT) | E41: =IFERROR(SUM(E35:E37)/E39,"") -> 0.50729745 | F41: =IFERROR(SUM(F35:F37)/F39,"") -> 0.47092359 | G41: =IFERROR(SUM(G35:G37)/G39,"") -> 0.42299937 | H41: =IFERROR(SUM(H35:H37)/H39,"") -> 0.38449528 | I41: =IFERROR(SUM(I35:I37)/I39,"") -> 0.028200009 | J41: =IFERROR(SUM(J35:J37)/J39,"") -> 0.028200009 | K41: =IFERROR(SUM(K35:K37)/K39,"") -> 0.028200009 | L41: =IFERROR(SUM(L35:L37)/L39,"") -> 0.028200009 | M41: =IFERROR(SUM(M35:M37)/M39,"") -> 0.028200009
B42: Implied terminal RONIC (g / reinvestment rate) | N42: =IFERROR($C$27/M41,"") -> 1.4184393
D43: Opening IC = Model YE2026E book invested capital (equity + net debt), rolled forward with capex + M&A − D&A + ΔWC.
B44: 3. VALUATION SUMMARY
B45: Sum of PV (2027E–35E explicit + fade) | C45: =SUM(E31:M31) -> 3730.7276
B46: PV of Terminal Value | C46: =N31 -> 7968.0276
B47: Enterprise Value | C47: =C45+C46 -> 11698.755
B48: Less: Net debt (Model YE2026E) | C48: =Model!CA376 -> 347.03295 | D48: CW has no NCI; pension plans overfunded (prepaid pension asset) — not deducted.
B49: Equity Value | C49: =C47-C48 -> 11351.722
B50: Diluted shares (m, Model YE2026E) | C50: =Model!CA383 -> 36.66088
B51: Implied share price ($) | C51: =C49/C50 -> 309.64129
B52: Current share price ($) | C52: =Model!CA381 -> 544.21
B53: Implied upside / (downside) | C53: =C51/C52-1 -> -0.4310261
B54: Required discount to DCF value for target IRR | C54: =1-((1+C13)/(1+H54))^H55 -> 0.12599105 | D54: vs. current | E54: Target IRR | H54: 0.15
B55: Max entry price for target IRR ($) | C55: =C51*(1-C54) -> 270.62926 | D55: =C55/C52-1 -> -0.50271172 | E55: Years for discount to close | H55: 3
B58: 4. SENSITIVITY: IMPLIED PRICE ($) — WACC × Terminal Growth
D60: WACC →
B61: Terminal growth ↓ | D61: =F61-0.01 -> 0.08952 | E61: =F61-0.005 -> 0.09452 | F61: =$C$13 -> 0.09952 | G61: =F61+0.005 -> 0.10452 | H61: =F61+0.01 -> 0.10952
B62: =B64-0.01 -> 0.03 | D62: =IFERROR((SUMPRODUCT($E$24:$M$24/(1+D$61)^$E$29:$M$29)+($M$24*(1+$B62)/(D$61-$B62))/(1+D$61)^$M$29-$C$48)/$C$50,"") -> 331.96651 | E62: =IFERROR((SUMPRODUCT($E$24:$M$24/(1+E$61)^$E$29:$M$29)+($M$24*(1+$B62)/(E$61-$B62))/(1+E$61)^$M$29-$C$48)/$C$50,"") -> 302.09107 | F62: =IFERROR((SUMPRODUCT($E$24:$M$24/(1+F$61)^$E$29:$M$29)+($M$24*(1+$B62)/(F$61-$B62))/(1+F$61)^$M$29-$C$48)/$C$50,"") -> 276.58851 | G62: =IFERROR((SUMPRODUCT($E$24:$M$24/(1+G$61)^$E$29:$M$29)+($M$24*(1+$B62)/(G$61-$B62))/(1+G$61)^$M$29-$C$48)/$C$50,"") -> 254.57648 | H62: =IFERROR((SUMPRODUCT($E$24:$M$24/(1+H$61)^$E$29:$M$29)+($M$24*(1+$B62)/(H$61-$B62))/(1+H$61)^$M$29-$C$48)/$C$50,"") -> 235.39462
B63: =B64-0.005 -> 0.035 | D63: =IFERROR((SUMPRODUCT($E$24:$M$24/(1+D$61)^$E$29:$M$29)+($M$24*(1+$B63)/(D$61-$B63))/(1+D$61)^$M$29-$C$48)/$C$50,"") -> 354.68587 | E63: =IFERROR((SUMPRODUCT($E$24:$M$24/(1+E$61)^$E$29:$M$29)+($M$24*(1+$B63)/(E$61-$B63))/(1+E$61)^$M$29-$C$48)/$C$50,"") -> 320.57899 | F63: =IFERROR((SUMPRODUCT($E$24:$M$24/(1+F$61)^$E$29:$M$29)+($M$24*(1+$B63)/(F$61-$B63))/(1+F$61)^$M$29-$C$48)/$C$50,"") -> 291.83418 | G63: =IFERROR((SUMPRODUCT($E$24:$M$24/(1+G$61)^$E$29:$M$29)+($M$24*(1+$B63)/(G$61-$B63))/(1+G$61)^$M$29-$C$48)/$C$50,"") -> 267.29239 | H63: =IFERROR((SUMPRODUCT($E$24:$M$24/(1+H$61)^$E$29:$M$29)+($M$24*(1+$B63)/(H$61-$B63))/(1+H$61)^$M$29-$C$48)/$C$50,"") -> 246.1057
B64: =$C$27 -> 0.04 | D64: =IFERROR((SUMPRODUCT($E$24:$M$24/(1+D$61)^$E$29:$M$29)+($M$24*(1+$B64)/(D$61-$B64))/(1+D$61)^$M$29-$C$48)/$C$50,"") -> 381.99314 | E64: =IFERROR((SUMPRODUCT($E$24:$M$24/(1+E$61)^$E$29:$M$29)+($M$24*(1+$B64)/(E$61-$B64))/(1+E$61)^$M$29-$C$48)/$C$50,"") -> 342.45795 | F64: =IFERROR((SUMPRODUCT($E$24:$M$24/(1+F$61)^$E$29:$M$29)+($M$24*(1+$B64)/(F$61-$B64))/(1+F$61)^$M$29-$C$48)/$C$50,"") -> 309.64129 | G64: =IFERROR((SUMPRODUCT($E$24:$M$24/(1+G$61)^$E$29:$M$29)+($M$24*(1+$B64)/(G$61-$B64))/(1+G$61)^$M$29-$C$48)/$C$50,"") -> 281.97914 | H64: =IFERROR((SUMPRODUCT($E$24:$M$24/(1+H$61)^$E$29:$M$29)+($M$24*(1+$B64)/(H$61-$B64))/(1+H$61)^$M$29-$C$48)/$C$50,"") -> 258.35749
B65: =B64+0.005 -> 0.045 | D65: =IFERROR((SUMPRODUCT($E$24:$M$24/(1+D$61)^$E$29:$M$29)+($M$24*(1+$B65)/(D$61-$B65))/(1+D$61)^$M$29-$C$48)/$C$50,"") -> 415.43411 | E65: =IFERROR((SUMPRODUCT($E$24:$M$24/(1+E$61)^$E$29:$M$29)+($M$24*(1+$B65)/(E$61-$B65))/(1+E$61)^$M$29-$C$48)/$C$50,"") -> 368.75511 | F65: =IFERROR((SUMPRODUCT($E$24:$M$24/(1+F$61)^$E$29:$M$29)+($M$24*(1+$B65)/(F$61-$B65))/(1+F$61)^$M$29-$C$48)/$C$50,"") -> 330.71456 | G65: =IFERROR((SUMPRODUCT($E$24:$M$24/(1+G$61)^$E$29:$M$29)+($M$24*(1+$B65)/(G$61-$B65))/(1+G$61)^$M$29-$C$48)/$C$50,"") -> 299.13342 | H65: =IFERROR((SUMPRODUCT($E$24:$M$24/(1+H$61)^$E$29:$M$29)+($M$24*(1+$B65)/(H$61-$B65))/(1+H$61)^$M$29-$C$48)/$C$50,"") -> 272.5082
B66: =B64+0.01 -> 0.05 | D66: =IFERROR((SUMPRODUCT($E$24:$M$24/(1+D$61)^$E$29:$M$29)+($M$24*(1+$B66)/(D$61-$B66))/(1+D$61)^$M$29-$C$48)/$C$50,"") -> 457.33688 | E66: =IFERROR((SUMPRODUCT($E$24:$M$24/(1+E$61)^$E$29:$M$29)+($M$24*(1+$B66)/(E$61-$B66))/(1+E$61)^$M$29-$C$48)/$C$50,"") -> 400.9591 | F66: =IFERROR((SUMPRODUCT($E$24:$M$24/(1+F$61)^$E$29:$M$29)+($M$24*(1+$B66)/(F$61-$B66))/(1+F$61)^$M$29-$C$48)/$C$50,"") -> 356.04333 | G66: =IFERROR((SUMPRODUCT($E$24:$M$24/(1+G$61)^$E$29:$M$29)+($M$24*(1+$B66)/(G$61-$B66))/(1+G$61)^$M$29-$C$48)/$C$50,"") -> 319.43412 | H66: =IFERROR((SUMPRODUCT($E$24:$M$24/(1+H$61)^$E$29:$M$29)+($M$24*(1+$B66)/(H$61-$B66))/(1+H$61)^$M$29-$C$48)/$C$50,"") -> 289.03638
B69: 5. REVERSE DCF
B70: To solve for the market-implied path: Data ▸ What-If Analysis ▸ Goal Seek — set C51 to the current price (C52) by changing C27 (terminal growth) or the fade-period growth inputs (I26 / M26).
B72: 6. MAUBOUSSIN EV / NOPAT — TWO-STAGE FRAMEWORK
B73: EV/NOPAT = 1/r + [g × (1 − r/ROIIC) / (r × (r − g))] × [1 − ((1+g)/(1+r))^N]
B74: Formula source: Mauboussin & Rappaport, "Expectations Investing" (2021); Counterpoint Global, "What Does a Price-Earnings Multiple Mean?" (2020).
B76: Input | C76: Value | D76: Rationale (Curtiss-Wright characteristics)
B77: r (Cost of capital / WACC) | C77: =$C$13 -> 0.09952 | D77: Linked from Section 1 WACC build
B78: g (NOPAT growth, Stage 1) | C78: 0.09 | D78: Model Adjusted OI CAGR 2026–30E ~10%: high-single-digit sales growth (naval, nuclear, defense electronics, commercial aero) + ~30% incrementals
B79: ROIIC (Return on incremental invested capital) | C79: 0.2 | D79: Asset-light engineered products (capex ~3% of sales) earn high organic returns; bolt-on M&A at ~3x sales earns ~10–12% after tax
B80: N (Years of value creation / CAP) | C80: 15 | D80: Sole-source positions on Virginia/Columbia-class submarines and Ford-class carriers, AP1000 reactor coolant pumps, 70%+ A&D mix with multi-decade platforms
B82: Calculation | C82: Value
B83: Steady-state component: 1 / r | C83: =1/C77 -> 10.048232
B84: Value-creation factor: 1 − r / ROIIC | C84: =1-C77/C79 -> 0.5024
B85: Growth multiplier: g × (1 − r/ROIIC) / (r × (r − g)) | C85: =C78*C84/(C77*(C77-C78)) -> 47.724878
B86: Time decay: 1 − ((1+g)/(1+r))^N | C86: =1-((1+C78)/(1+C77))^C80 -> 0.12229117
B87: PVGO component (growth value) | C87: =C85*C86 -> 5.8363312
B88: Mauboussin EV / NOPAT (steady-state + PVGO) | C88: =C83+C87 -> 15.884563
B90: VALUATION — Applied to 2028E NOPAT | C90: USDm
B91: 2028E operating income (GAAP = Adjusted OI; no adjustments forecast) | C91: =Model!CC123 -> 898.86833
B92: Tax rate (from WACC build) | C92: =$C$10 -> 0.22
B93: 2028E NOPAT | C93: =C91*(1-C92) -> 701.1173
B94: × Mauboussin EV/NOPAT multiple | C94: =C88 -> 15.884563
B95: Implied Enterprise Value (2028E basis) | C95: =C93*C94 -> 11136.942
B96: Less: YE2027 net debt (Model) | C96: =Model!CB376 -> 468.7905
B97: Implied Equity Value | C97: =C95-C96 -> 10668.151
B98: Diluted shares 2028E (m, Model) | C98: =Model!CC383 -> 35.727179
B99: Implied share price 2028 ($) | C99: =C97/C98 -> 298.60044
B101: Current share price ($) | C101: =C52 -> 544.21
B102: Implied upside / (downside) | C102: =C99/C101-1 -> -0.45131395
B104: MARKET-IMPLIED EV/NOPAT TODAY | C104: USDm
B105: Current market cap (spot × diluted shares) | C105: =C52*C50 -> 19951.218
B106: Plus: YE2026 net debt | C106: =C48 -> 347.03295
B107: Implied Enterprise Value (today) | C107: =C105+C106 -> 20298.251
B108: CW market-implied EV/NOPAT (on 2028E NOPAT) | C108: =C107/C93 -> 28.95129
B110: Multiple gap (Mauboussin − Market) | C110: =C88-C108 -> -13.066728
B111: Implied re-rating headroom | C111: =C88/C108-1 -> -0.4513349

Sheet Charts
B2: Curtiss-Wright — Historical Operating Performance (2006–2025)
B3: All historicals · USDm · Linked to Model. Organic growth = company-published (excludes acquisitions / divestitures in the last 12 months and FX; blank where not published). Adjusted OI per CW reconciliations from Q2/18 (2012 / 2015 company adjusted; other years = GAAP).
C7: 2006 | D7: 2007 | E7: 2008 | F7: 2009 | G7: 2010 | H7: 2011 | I7: 2012 | J7: 2013 | K7: 2014 | L7: 2015 | M7: 2016 | N7: 2017 | O7: 2018 | P7: 2019 | Q7: 2020 | R7: 2021 | S7: 2022 | T7: 2023 | U7: 2024 | V7: 2025
B8: Net sales growth y/y % | C8: =IFERROR(Model!C209+0,0) -> 0 | D8: =IFERROR(Model!D209+0,0) -> 0.24175626 | E8: =IFERROR(Model!E209+0,0) -> 0.14949589 | F8: =IFERROR(Model!F209+0,0) -> -0.011174009 | G8: =IFERROR(Model!G209+0,0) -> 0.046109555 | H8: =IFERROR(Model!H209+0,0) -> 0.085042052 | I8: =IFERROR(Model!I209+0,0) -> 0.021218715 | J8: =IFERROR(Model!N209+0,0) -> 0.19690702 | K8: =IFERROR(Model!S209+0,0) -> -0.10659873 | L8: =IFERROR(Model!X209+0,0) -> -0.01669233 | M8: =IFERROR(Model!AC209+0,0) -> -0.043864871 | N8: =IFERROR(Model!AH209+0,0) -> 0.076861215 | O8: =IFERROR(Model!AM209+0,0) -> 0.062002372 | P8: =IFERROR(Model!AR209+0,0) -> 0.031563519 | Q8: =IFERROR(Model!AW209+0,0) -> -0.038837024 | R8: =IFERROR(Model!BB209+0,0) -> 0.047920911 | S8: =IFERROR(Model!BG209+0,0) -> 0.020389229 | T8: =IFERROR(Model!BL209+0,0) -> 0.11276699 | U8: =IFERROR(Model!BQ209+0,0) -> 0.096934919 | V8: =IFERROR(Model!BV209+0,0) -> 0.12084593
B9: Organic sales growth % (company-published) | C9: =IFERROR(Model!C81+0,0) -> 0.11 | D9: =IFERROR(Model!D81+0,0) -> 0.13 | E9: =IFERROR(Model!E81+0,0) -> 0.06 | F9: =IFERROR(Model!F81+0,0) -> -0.02 | G9: =IFERROR(Model!G81+0,0) -> 0.03 | H9: =IFERROR(Model!H81+0,0) -> 0.03 | I9: =IFERROR(Model!I81+0,0) -> 0 | J9: =IFERROR(Model!N81+0,0) -> 0.01 | K9: =IFERROR(Model!S81+0,0) -> 0.02 | L9: =IFERROR(Model!X81+0,0) -> 0 | M9: =IFERROR(Model!AC81+0,0) -> -0.04 | N9: =IFERROR(Model!AH81+0,0) -> 0.05 | O9: =IFERROR(Model!AM81+0,0) -> 0.03 | P9: =IFERROR(Model!AR81+0,0) -> 0.02 | Q9: =IFERROR(Model!AW81+0,0) -> -0.08 | R9: =IFERROR(Model!BB81+0,0) -> -0.01 | S9: =IFERROR(Model!BG81+0,0) -> 0.03 | T9: =IFERROR(Model!BL81+0,0) -> 0.1 | U9: =IFERROR(Model!BQ81+0,0) -> 0.09 | V9: =IFERROR(Model!BV81+0,0) -> 0.09
C11: =C7 -> 2006 | D11: =D7 -> 2007 | E11: =E7 -> 2008 | F11: =F7 -> 2009 | G11: =G7 -> 2010 | H11: =H7 -> 2011 | I11: =I7 -> 2012 | J11: =J7 -> 2013 | ... V11: =V7 -> 2025
B12: Adjusted operating income | C12: =Model!C159 -> 140.628 | D12: =Model!D159 -> 179.184 | E12: =Model!E159 -> 199.182 | F12: =Model!F159 -> 169.319 | G12: =Model!G159 -> 179.823 | H12: =Model!H159 -> 204.956 | I12: =Model!I159 -> 201.448 | J12: =Model!N159 -> 233.619 | K12: =Model!S159 -> 282.373 | L12: =Model!X159 -> 291 | M12: =Model!AC159 -> 308.098 | N12: =Model!AH159 -> 339.743 | O12: =Model!AM159 -> 382 | P12: =Model!AR159 -> 411 | Q12: =Model!AW159 -> 391 | R12: =Model!BB159 -> 420.423 | S12: =Model!BG159 -> 443.078 | T12: =Model!BL159 -> 493.8 | U12: =Model!BQ159 -> 545.866 | V12: =Model!BV159 -> 650.994
B13: Operating income (GAAP) | C13: =Model!C123 -> 140.628 | D13: =Model!D123 -> 179.184 | E13: =Model!E123 -> 199.182 | F13: =Model!F123 -> 169.319 | G13: =Model!G123 -> 179.823 | H13: =Model!H123 -> 204.956 | I13: =Model!I123 -> 161.446 | J13: =Model!N123 -> 233.619 | K13: =Model!S123 -> 282.373 | L13: =Model!X123 -> 310.617 | M13: =Model!AC123 -> 308.098 | N13: =Model!AH123 -> 339.743 | O13: =Model!AM123 -> 373.626 | P13: =Model!AR123 -> 403.953 | Q13: =Model!AW123 -> 288.848 | R13: =Model!BB123 -> 382.683 | S13: =Model!BG123 -> 423.443 | T13: =Model!BL123 -> 484.602 | U13: =Model!BQ123 -> 528.597 | V13: =Model!BV123 -> 633.521
B14: Adj. OI margin % | C14: =Model!C160 -> 0.10968097 | D14: =Model!D160 -> 0.112544 | E14: =Model!E160 -> 0.1088343 | F14: =Model!F160 -> 0.093562433 | G14: =Model!G160 -> 0.094986937 | H14: =Model!H160 -> 0.099777521 | I14: =Model!I160 -> 0.096032065 | J14: =Model!N160 -> 0.093046718 | K14: =Model!S160 -> 0.1258837 | L14: =Model!X160 -> 0.13193192 | M14: =Model!AC160 -> 0.14609202 | N14: =Model!AH160 -> 0.1495989 | O14: =Model!AM160 -> 0.15838563 | P14: =Model!AR160 -> 0.16519552 | Q14: =Model!AW160 -> 0.16350693 | R14: =Model!BB160 -> 0.16777118 | S14: =Model!BG160 -> 0.17327871 | T14: =Model!BL160 -> 0.17354491 | U14: =Model!BQ160 -> 0.1748904 | V14: =Model!BV160 -> 0.18608484
B15: GAAP Op. margin % | C15: =Model!C124 -> 0.10968097 | D15: =Model!D124 -> 0.112544 | E15: =Model!E124 -> 0.1088343 | F15: =Model!F124 -> 0.093562433 | G15: =Model!G124 -> 0.094986937 | H15: =Model!H124 -> 0.099777521 | I15: =Model!I124 -> 0.076962754 | J15: =Model!N124 -> 0.093046718 | K15: =Model!S124 -> 0.1258837 | L15: =Model!X124 -> 0.14082577 | M15: =Model!AC124 -> 0.14609202 | N15: =Model!AH124 -> 0.1495989 | O15: =Model!AM124 -> 0.15491358 | P15: =Model!AR124 -> 0.16236308 | Q15: =Model!AW124 -> 0.12078938 | R15: =Model!BB124 -> 0.15271091 | S15: =Model!BG124 -> 0.16559987 | T15: =Model!BL124 -> 0.17031229 | U15: =Model!BQ124 -> 0.16935757 | V15: =Model!BV124 -> 0.18109023
C17: =C7 -> 2006 | D17: =D7 -> 2007 | E17: =E7 -> 2008 | F17: =F7 -> 2009 | G17: =G7 -> 2010 | H17: =H7 -> 2011 | I17: =I7 -> 2012 | J17: =J7 -> 2013 | ... V17: =V7 -> 2025
B18: ROIC | C18: =IFERROR(Model!C359+0,NA()) -> 0.0960941 | D18: =IFERROR(Model!D359+0,NA()) -> 0.089146551 | E18: =IFERROR(Model!E359+0,NA()) -> 0.097412815 | F18: =IFERROR(Model!F359+0,NA()) -> 0.077789344 | G18: =IFERROR(Model!G359+0,NA()) -> 0.081346883 | H18: =IFERROR(Model!H359+0,NA()) -> 0.089138215 | I18: =IFERROR(Model!I359+0,NA()) -> 0.06600687 | J18: =IFERROR(Model!N359+0,NA()) -> 0.069669356 | K18: =IFERROR(Model!S359+0,NA()) -> 0.09801532 | L18: =IFERROR(Model!X359+0,NA()) -> 0.10582131 | M18: =IFERROR(Model!AC359+0,NA()) -> 0.12781385 | N18: =IFERROR(Model!AH359+0,NA()) -> 0.13052605 | O18: =IFERROR(Model!AM359+0,NA()) -> 0.14657895 | P18: =IFERROR(Model!AR359+0,NA()) -> 0.14872441 | Q18: =IFERROR(Model!AW359+0,NA()) -> 0.11306383 | R18: =IFERROR(Model!BB359+0,NA()) -> 0.1170805 | S18: =IFERROR(Model!BG359+0,NA()) -> 0.11209053 | T18: =IFERROR(Model!BL359+0,NA()) -> 0.1272027 | U18: =IFERROR(Model!BQ359+0,NA()) -> 0.13599495 | V18: =IFERROR(Model!BV359+0,NA()) -> 0.16295131
B19: RONTA | C19: =IFERROR(Model!C370+0,NA()) -> 0.13075141 | D19: =IFERROR(Model!D370+0,NA()) -> 0.15613351 | E19: =IFERROR(Model!E370+0,NA()) -> 0.17178268 | F19: =IFERROR(Model!F370+0,NA()) -> 0.13741087 | G19: =IFERROR(Model!G370+0,NA()) -> 0.13715438 | H19: =IFERROR(Model!H370+0,NA()) -> 0.12798232 | I19: =IFERROR(Model!I370+0,NA()) -> 0.11731518 | J19: =IFERROR(Model!N370+0,NA()) -> 0.12123344 | K19: =IFERROR(Model!S370+0,NA()) -> 0.13122937 | L19: =IFERROR(Model!X370+0,NA()) -> 0.16634734 | M19: =IFERROR(Model!AC370+0,NA()) -> 0.16871011 | N19: =IFERROR(Model!AH370+0,NA()) -> 0.19981394 | O19: =IFERROR(Model!AM370+0,NA()) -> 0.28142113 | P19: =IFERROR(Model!AR370+0,NA()) -> 0.23224698 | Q19: =IFERROR(Model!AW370+0,NA()) -> 0.24021203 | R19: =IFERROR(Model!BB370+0,NA()) -> 0.23167365 | S19: =IFERROR(Model!BG370+0,NA()) -> 0.22116879 | T19: =IFERROR(Model!BL370+0,NA()) -> 0.222637 | U19: =IFERROR(Model!BQ370+0,NA()) -> 0.2480357 | V19: =IFERROR(Model!BV370+0,NA()) -> 0.28390171
B20: Adj. OI margin % | C20: =IFERROR(Model!C160+0,NA()) -> 0.10968097 | D20: =IFERROR(Model!D160+0,NA()) -> 0.112544 | E20: =IFERROR(Model!E160+0,NA()) -> 0.1088343 | F20: =IFERROR(Model!F160+0,NA()) -> 0.093562433 | G20: =IFERROR(Model!G160+0,NA()) -> 0.094986937 | H20: =IFERROR(Model!H160+0,NA()) -> 0.099777521 | I20: =IFERROR(Model!I160+0,NA()) -> 0.096032065 | J20: =IFERROR(Model!N160+0,NA()) -> 0.093046718 | K20: =IFERROR(Model!S160+0,NA()) -> 0.1258837 | L20: =IFERROR(Model!X160+0,NA()) -> 0.13193192 | M20: =IFERROR(Model!AC160+0,NA()) -> 0.14609202 | N20: =IFERROR(Model!AH160+0,NA()) -> 0.1495989 | O20: =IFERROR(Model!AM160+0,NA()) -> 0.15838563 | P20: =IFERROR(Model!AR160+0,NA()) -> 0.16519552 | Q20: =IFERROR(Model!AW160+0,NA()) -> 0.16350693 | R20: =IFERROR(Model!BB160+0,NA()) -> 0.16777118 | S20: =IFERROR(Model!BG160+0,NA()) -> 0.17327871 | T20: =IFERROR(Model!BL160+0,NA()) -> 0.17354491 | U20: =IFERROR(Model!BQ160+0,NA()) -> 0.1748904 | V20: =IFERROR(Model!BV160+0,NA()) -> 0.18608484
B21: FCF margin % | C21: =IFERROR(Model!C259+0,NA()) -> 0.080855279 | D21: =IFERROR(Model!D259+0,NA()) -> 0.053201258 | E21: =IFERROR(Model!E259+0,NA()) -> 0.041616488 | F21: =IFERROR(Model!F259+0,NA()) -> 0.066826915 | G21: =IFERROR(Model!G259+0,NA()) -> 0.06271611 | H21: =IFERROR(Model!H259+0,NA()) -> 0.057216924 | I21: =IFERROR(Model!I259+0,NA()) -> 0.033140806 | J21: =IFERROR(Model!N259+0,NA()) -> 0.065949862 | K21: =IFERROR(Model!S259+0,NA()) -> 0.11798312 | L21: =IFERROR(Model!X259+0,NA()) -> 0.057563576 | M21: =IFERROR(Model!AC259+0,NA()) -> 0.17848901 | N21: =IFERROR(Model!AH259+0,NA()) -> 0.14795383 | O21: =IFERROR(Model!AM259+0,NA()) -> 0.11727834 | P21: =IFERROR(Model!AR259+0,NA()) -> 0.14134144 | Q21: =IFERROR(Model!AW259+0,NA()) -> 0.089356326 | R21: =IFERROR(Model!BB259+0,NA()) -> 0.13829591 | S21: =IFERROR(Model!BG259+0,NA()) -> 0.10033496 | T21: =IFERROR(Model!BL259+0,NA()) -> 0.14178211 | U21: =IFERROR(Model!BQ259+0,NA()) -> 0.15484516 | V21: =IFERROR(Model!BV259+0,NA()) -> 0.15827648
