Workbook

Sheet Model
CF1: SCENARIO SWITCH ▼ (Bull / Base / Bear) — drives all scenario-linked forecast drivers
B2: Danaher Corporation (NYSE: DHR) — 3-Statement Financial Model | CF2: Base
B3: US GAAP as reported · USD millions (per-share data in USD; shares in millions, split-adjusted) · Source: Danaher Forms 10-K / 10-Q and Form 8-K earnings releases (Ex. 99.1), deal 8-Ks (Masimo Feb-2026; financing Apr–Jun 2026), SEC EDGAR CIK 0000313616; Masimo standalone history from Masimo Corp. filings (CIK 0000937556) (investor-relations releases are the same documents as filed on EDGAR)
B4: Basis notes: calendar fiscal year (quarters end on the Friday nearest the calendar quarter end). Hybrid recast: income statement, segments and adjusted EPS of the periods before each separation use the restated continuing-operations comparatives of the following year's filings (Apex JV 2010, Communications 2015, Fortive 2-Jul-2016, ASU 2017-07 pension recast, Envista Dec-2019, Veralto 30-Sep-2023); balance sheet and cash flow as originally reported. 2-for-1 split Jun-2010. Segments: Biotechnology / Life Sciences / Diagnostics from Q4-22 (legacy segments in memo rows). Cytiva 31-Mar-2020; Aldevron Aug-2021; Abcam Dec-2023; Masimo 10-Jun-2026 (in Diagnostics; modelled separately); StatLab pending (assumed closed end-2026). Q3/26E–Q4/26E calibrated to FY26 core-growth and adjusted-EPS guidance.
CH5: Forecast | CI5: Historical | CJ5: Historical | CK5: Historical
B6: (USDm) | C6: 2006 | D6: 2007 | E6: 2008 | F6: 2009 | G6: 2010 | H6: 2011 | I6: 2012 | J6: Q1/13 | K6: Q2/13 | L6: Q3/13 | M6: Q4/13 | N6: 2013 | O6: Q1/14 | P6: Q2/14 | Q6: Q3/14 | R6: Q4/14 | S6: 2014 | T6: Q1/15 | U6: Q2/15 | V6: Q3/15 | W6: Q4/15 | X6: 2015 | Y6: Q1/16 | Z6: Q2/16 | AA6: Q3/16 | AB6: Q4/16 | AC6: 2016 | AD6: Q1/17 | AE6: Q2/17 | AF6: Q3/17 | AG6: Q4/17 | AH6: 2017 | AI6: Q1/18 | AJ6: Q2/18 | AK6: Q3/18 | AL6: Q4/18 | AM6: 2018 | AN6: Q1/19 | AO6: Q2/19 | AP6: Q3/19 | AQ6: Q4/19 | AR6: 2019 | AS6: Q1/20 | AT6: Q2/20 | AU6: Q3/20 | AV6: Q4/20 | AW6: 2020 | AX6: Q1/21 | AY6: Q2/21 | AZ6: Q3/21 | BA6: Q4/21 | BB6: 2021 | BC6: Q1/22 | BD6: Q2/22 | BE6: Q3/22 | BF6: Q4/22 | BG6: 2022 | BH6: Q1/23 | BI6: Q2/23 | BJ6: Q3/23 | BK6: Q4/23 | BL6: 2023 | BM6: Q1/24 | BN6: Q2/24 | BO6: Q3/24 | BP6: Q4/24 | BQ6: 2024 | BR6: Q1/25 | BS6: Q2/25 | BT6: Q3/25 | BU6: Q4/25 | BV6: 2025 | BW6: Q1/26 | BX6: Q2/26 | BY6: Q3/26E | BZ6: Q4/26E | CA6: 2026E | CB6: 2027E | CC6: 2028E | CD6: 2029E | CE6: 2030E | CF6: Modelling Notes | CH6: 5Y CAGR | CI6: 5Y CAGR | CJ6: 10Y CAGR | CK6: 19Y CAGR
CH7: 25-'30 | CI7: 20-'25 | CJ7: 15-'25 | CK7: 06-'25
B8: SEGMENT P&L — BIOTECHNOLOGY · LIFE SCIENCES · DIAGNOSTICS (+ MASIMO · STATLAB) · CORE GROWTH BRIDGE | CF8: SEGMENT BUILD — modelling logic (prior-year sales × (1 + core growth + FX) → segment sales × adjusted operating margin → adjusted operating profit → adjusted EPS)
CN9: SCENARIO INPUT TABLE — driver assumptions per Bull / Base / Bear | CO9: Bull | CP9: Base | CQ9: Bear | CR9: Bull / Bear = Base + Δ (Δ inputs on each block header). Outlook block = high / mid / low end of FY26 guidance ranges.
B10: Biotechnology (bioprocessing — Cytiva, Pall Biotech; discovery & medical — Aldevron, Abcam reagents to 2024 in Life Sciences) | CF10: BIOTECHNOLOGY — modelling logic
B11: Biotechnology sales | BB11: 8570 | BF11: 2223 | BG11: 8758 | BH11: 1864 | BI11: 1885 | BJ11: 1664 | BK11: 1759 | BL11: 7172 | BM11: 1524 | BN11: 1713 | BO11: 1653 | BP11: 1869 | BQ11: 6759 | BR11: 1612 | BS11: 1850 | BT11: 1798 | BU11: 2033 | BV11: 7293 | BW11: 1797 | BX11: 1920 | BY11: =BT11*(1+BY13+BY16) -> 1891.1714 | BZ11: =BU11*(1+BZ13+BZ16) -> 2185.108 | CA11: =SUM(BW11,BX11,BY11,BZ11) -> 7793.2795 | CB11: =CA11*(1+CB13) -> 8338.809 | CC11: =CB11*(1+CC13) -> 8964.2197 | CD11: =CC11*(1+CD13) -> 9636.5362 | CE11: =CD11*(1+CE13) -> 10359.276 | CF11: Segment sales as reported (hybrid recast basis: periods before a segment recast / spin-off on the restated comparatives). Q3/Q4-26E: prior-year quarter × (1 + core growth + FX). 2027E+: prior year × (1 + scenario core growth); FX nil. | CH11: =IFERROR((CE11/BV11)^(1/5)-1,"n/m") -> 0.072715711 | CI11: =IFERROR((BV11/AW11)^(1/5)-1,"n/m") -> n/m | CJ11: =IFERROR((BV11/X11)^(1/10)-1,"n/m") -> n/m | CK11: =IFERROR((BV11/C11)^(1/19)-1,"n/m") -> n/m | CN11: FY26 outlook — Q2-26 release (21-Jul-26) | CO11: High | CP11: Mid | CQ11: Low | CR11: Raised adjusted EPS in the Q2-26 release ($8.45–8.60 vs $8.35–8.55 in Q1-26; $8.35–8.50 in Jan-26). Includes Masimo (closed 10-Jun-2026); excludes pending StatLab.
B12: Sales y/y % | D12: =IF(AND(ISNUMBER(D11),ISNUMBER(C11)),IFERROR(D11/C11-1,""),"") | E12: =IF(AND(ISNUMBER(E11),ISNUMBER(D11)),IFERROR(E11/D11-1,""),"") | F12: =IF(AND(ISNUMBER(F11),ISNUMBER(E11)),IFERROR(F11/E11-1,""),"") | G12: =IF(AND(ISNUMBER(G11),ISNUMBER(F11)),IFERROR(G11/F11-1,""),"") | H12: =IF(AND(ISNUMBER(H11),ISNUMBER(G11)),IFERROR(H11/G11-1,""),"") | I12: =IF(AND(ISNUMBER(I11),ISNUMBER(H11)),IFERROR(I11/H11-1,""),"") | N12: =IF(AND(ISNUMBER(N11),ISNUMBER(I11)),IFERROR(N11/I11-1,""),"") | O12: =IF(AND(ISNUMBER(O11),ISNUMBER(J11)),IFERROR(O11/J11-1,""),"") | P12: =IF(AND(ISNUMBER(P11),ISNUMBER(K11)),IFERROR(P11/K11-1,""),"") | Q12: =IF(AND(ISNUMBER(Q11),ISNUMBER(L11)),IFERROR(Q11/L11-1,""),"") | R12: =IF(AND(ISNUMBER(R11),ISNUMBER(M11)),IFERROR(R11/M11-1,""),"") | S12: =IF(AND(ISNUMBER(S11),ISNUMBER(N11)),IFERROR(S11/N11-1,""),"") | T12: =IF(AND(ISNUMBER(T11),ISNUMBER(O11)),IFERROR(T11/O11-1,""),"") | U12: =IF(AND(ISNUMBER(U11),ISNUMBER(P11)),IFERROR(U11/P11-1,""),"") | ... CA12: =IF(AND(ISNUMBER(CA11),ISNUMBER(BV11)),IFERROR(CA11/BV11-1,""),"") -> 0.06859721 | CB12: =IF(AND(ISNUMBER(CB11),ISNUMBER(CA11)),IFERROR(CB11/CA11-1,""),"") -> 0.07 | CC12: =IF(AND(ISNUMBER(CC11),ISNUMBER(CB11)),IFERROR(CC11/CB11-1,""),"") -> 0.075 | CD12: =IF(AND(ISNUMBER(CD11),ISNUMBER(CC11)),IFERROR(CD11/CC11-1,""),"") -> 0.075 | CE12: =IF(AND(ISNUMBER(CE11),ISNUMBER(CD11)),IFERROR(CE11/CD11-1,""),"") -> 0.075 | CN12: FY26 core sales growth (non-GAAP) | CO12: 0.04 | CP12: 0.035 | CQ12: 0.03 | CR12: Guided +3.0% to +4.0% (Q2-26 release). Drives the Q3/Q4-26E core-growth calibration.
B13: Core sales growth % (non-GAAP, as published) | BF13: 0.04 | BG13: 0.06 | BH13: -0.13 | BI13: -0.165 | BJ13: -0.21 | BK13: -0.225 | BL13: -0.18 | BM13: -0.17 | BN13: -0.07 | BO13: 0 | BP13: 0.08 | BQ13: -0.045 | BR13: 0.07 | BS13: 0.06 | BT13: 0.065 | BU13: 0.06 | BV13: 0.065 | BW13: 0.07 | BX13: 0.025 | BY13: =BY14+$BY$128 -> 0.061819486 | BZ13: =BZ14+$BY$128 -> 0.081819486 | CB13: =CHOOSE(MATCH($CF$2,{"Bull","Base","Bear"},0),$CO$33,$CP$33,$CQ$33) -> 0.07 | CC13: =CHOOSE(MATCH($CF$2,{"Bull","Base","Bear"},0),$CO$34,$CP$34,$CQ$34) -> 0.075 | CD13: =CHOOSE(MATCH($CF$2,{"Bull","Base","Bear"},0),$CO$35,$CP$35,$CQ$35) -> 0.075 | CE13: =CHOOSE(MATCH($CF$2,{"Bull","Base","Bear"},0),$CO$36,$CP$36,$CQ$36) -> 0.075 | CF13: Q3/Q4-26E: segment input (row below) + core-growth outlook calibration Δ (Group block). 2027E–2030E: scenario lever (Bull/Base/Bear table →). | CH13: =IFERROR(AVERAGE(CA13,CB13,CC13,CD13,CE13),"n/m") -> 0.07375 | CI13: =IFERROR(AVERAGE(BB13,BG13,BL13,BQ13,BV13),"n/m") -> -0.025 | CJ13: =IFERROR(AVERAGE(AC13,AH13,AM13,AR13,AW13,BB13,BG13,BL13,BQ13,BV13),"n/m") -> -0.025 | CK13: =IFERROR(AVERAGE(C13,D13,E13,F13,G13,H13,I13,N13,S13,X13,AC13,AH13,AM13,AR13,AW13,BB13,BG13,BL13,BQ13,BV13),"n/m") -> -0.025 | CN13: FY26 adjusted diluted EPS ($) | CO13: 8.6 | CP13: 8.525 | CQ13: 8.45 | CR13: Guided $8.45–8.60 (raised in Q2-26). Drives the Q3/Q4-26E adjusted-margin calibration.
B14: Q3/Q4-26E core growth input before outlook calibration | BY14: 0.05 | BZ14: 0.07 | CF14: Q2-26 release segment guidance: Q3 +MSD; FY +MSD. Q4 input +7% (bioprocessing; Q4-25 comparison +6%). | CN14: 2H/26 share repurchases ($m) | CO14: 1000 | CP14: 500 | CQ14: 0 | CR14: Q2/26: 5.0m shares for $903m; ~32m shares of authorization left. Net debt ~2.6x Adjusted EBITDA after Masimo — Base assumes modest repurchases.
B15: Acquisitions / divestitures contribution % (as published) | BF15: 0 | BG15: 0.005 | BH15: 0 | BI15: 0 | BJ15: 0.005 | BK15: 0 | BL15: 0 | BM15: 0 | BN15: 0 | BO15: 0 | BP15: 0 | BQ15: 0 | BR15: 0 | BS15: 0 | BT15: 0 | BU15: 0 | BV15: 0 | BW15: 0 | BX15: 0
B16: Currency contribution % (as published) | BF16: -0.05 | BG16: -0.045 | BH16: -0.03 | BI16: -0.005 | BJ16: 0.015 | BK16: 0.015 | BL16: 0 | BM16: -0.01 | BN16: -0.02 | BO16: -0.005 | BP16: -0.015 | BQ16: -0.015 | BR16: -0.01 | BS16: 0.02 | BT16: 0.025 | BU16: 0.03 | BV16: 0.015 | BW16: 0.045 | BX16: 0.015 | BY16: -0.01 | BZ16: -0.007 | CB16: 0 | CC16: 0 | CD16: 0 | CE16: 0 | CF16: Q3/Q4-26E: company FX guidance (Q3 ~−1.0%; FY ~+0.5% → Q4 implied). 2027E+: nil. | CN16: FY26 point estimates (all cases)
B17: Biotechnology operating profit (GAAP) | BB17: 3074 | BF17: 693 | BG17: 3008 | BH17: 596 | BI17: 480 | BJ17: 417 | BK17: 416 | BL17: 1909 | BM17: 325 | BN17: 462 | BO17: 390 | BP17: 508 | BQ17: 1685 | BR17: 441 | BS17: 531 | BT17: 352 | BU17: 540 | BV17: 1864 | BW17: 534 | BX17: 556 | BY17: =BY22-BY19-BY21 -> 460.10026 | BZ17: =BZ22-BZ19-BZ21 -> 656.6742 | CA17: =SUM(BW17,BX17,BY17,BZ17) -> 2206.7745 | CB17: =CB22-CB19-CB21 -> 2454.4794 | CC17: =CC22-CC19-CC21 -> 2746.3377 | CD17: =CD22-CD19-CD21 -> 3063.447 | CE17: =CE22-CE19-CE21 -> 3512.8719 | CN17: Interest expense, net ($m) | CP17: 310 | CR17: Q2-26 release: FY26 interest expense, net ~$(310)m (Q3 ~$(115)m) after the Masimo financing.
B18: Operating margin (GAAP) % | C18: =IF(AND(ISNUMBER(C17),ISNUMBER(C11)),IFERROR(C17/C11,""),"") | D18: =IF(AND(ISNUMBER(D17),ISNUMBER(D11)),IFERROR(D17/D11,""),"") | E18: =IF(AND(ISNUMBER(E17),ISNUMBER(E11)),IFERROR(E17/E11,""),"") | F18: =IF(AND(ISNUMBER(F17),ISNUMBER(F11)),IFERROR(F17/F11,""),"") | G18: =IF(AND(ISNUMBER(G17),ISNUMBER(G11)),IFERROR(G17/G11,""),"") | H18: =IF(AND(ISNUMBER(H17),ISNUMBER(H11)),IFERROR(H17/H11,""),"") | I18: =IF(AND(ISNUMBER(I17),ISNUMBER(I11)),IFERROR(I17/I11,""),"") | J18: =IF(AND(ISNUMBER(J17),ISNUMBER(J11)),IFERROR(J17/J11,""),"") | ... CE18: =IF(AND(ISNUMBER(CE17),ISNUMBER(CE11)),IFERROR(CE17/CE11,""),"") -> 0.33910399 | CN18: Adjusted effective tax rate | CP18: 0.17 | CR18: Q2-26 release: effective tax rate ~17.0% (non-GAAP supplemental).
B19: Amortization of acquired intangibles in segment | BG19: 812 | BH19: 217 | BI19: 218 | BJ19: 214 | BK19: 215 | BL19: 864 | BM19: 218 | BN19: 214 | BO19: 218 | BP19: 213 | BQ19: 863 | BR19: 213 | BS19: 228 | BT19: 231 | BU19: 230 | BV19: 902 | BW19: 234 | BX19: 231 | BY19: =BY172*BY20 -> 230.6198 | BZ19: =BZ172*BZ20 -> 229.75688 | CA19: =SUM(BW19,BX19,BY19,BZ19) -> 925.37668 | CB19: =CB172*CB20 -> 839.35018 | CC19: =CC172*CC20 -> 839.35018 | CD19: =CD172*CD20 -> 839.35018 | CE19: =CE172*CE20 -> 734.43141 | CF19: Segment amortization as published (segment note; 2024+). Forecast = existing-intangibles schedule × segment share (1H/26). | CN19: Capital expenditures ($m) | CP19: 1150 | CR19: 1H/26 $506m; FY25 $1,156m (not guided).
B20: Segment share of amortization (existing intangibles) % | C20: =IF(ISNUMBER(C19),IFERROR(C19/(C19+C37+C55),""),"") | D20: =IF(ISNUMBER(D19),IFERROR(D19/(D19+D37+D55),""),"") | E20: =IF(ISNUMBER(E19),IFERROR(E19/(E19+E37+E55),""),"") | F20: =IF(ISNUMBER(F19),IFERROR(F19/(F19+F37+F55),""),"") | G20: =IF(ISNUMBER(G19),IFERROR(G19/(G19+G37+G55),""),"") | H20: =IF(ISNUMBER(H19),IFERROR(H19/(H19+H37+H55),""),"") | I20: =IF(ISNUMBER(I19),IFERROR(I19/(I19+I37+I55),""),"") | J20: =IF(ISNUMBER(J19),IFERROR(J19/(J19+J37+J55),""),"") | ... BX20: =IF(ISNUMBER(BX19),IFERROR(BX19/(BX19+BX37+BX55),""),"") -> 0.51061008 | BY20: =IFERROR((BW19+BX19)/((BW19+BX19)+(BW37+BX37)+(BW55+BX55)),"") -> 0.52459386 | BZ20: =IFERROR((BW19+BX19)/((BW19+BX19)+(BW37+BX37)+(BW55+BX55)),"") -> 0.52459386 | CA20: =$BY$20 -> 0.52459386 | CB20: =$BY$20 -> 0.52459386 | CC20: =$BY$20 -> 0.52459386 | CD20: =$BY$20 -> 0.52459386 | CE20: =$BY$20 -> 0.52459386 | CN20: Q3/26 adjusted operating profit margin | CP20: 0.265 | CR20: Q2-26 release: Q3/26 adjusted operating profit margin ~26.5% (Q1/26 guide was ~28.5%; actual 30.2%). Drives the Q3 margin calibration.
B21: Other operating profit adjustments in segment (impairments, step-up, contingencies; company definition) | BM21: 0 | BN21: 0 | BO21: 0 | BP21: 0 | BQ21: 0 | BR21: 15 | BS21: 0 | BT21: 86 | BU21: 0 | BV21: 101 | BW21: 0 | BX21: 0 | BY21: 0 | BZ21: 0 | CA21: =SUM(BW21,BX21,BY21,BZ21) -> 0 | CB21: 0 | CC21: 0 | CD21: 0 | CE21: 0 | CF21: Published by segment from the Q4-25 release (FY24, Q4-24, FY25, Q4-25); 2025–26 quarters allocated from the release footnotes (see comments). Blank = not disclosed by segment. | CN21: Q3/26 amortization of acquired intangibles ($m) | CP21: 500 | CR21: Q2-26 release: Q3 ~$(500)m incl. Masimo.
B22: Biotechnology adjusted operating profit (non-GAAP) | C22: =IF(AND(ISNUMBER(C17),ISNUMBER(C19)),C17+C19+N(C21),"") | D22: =IF(AND(ISNUMBER(D17),ISNUMBER(D19)),D17+D19+N(D21),"") | E22: =IF(AND(ISNUMBER(E17),ISNUMBER(E19)),E17+E19+N(E21),"") | F22: =IF(AND(ISNUMBER(F17),ISNUMBER(F19)),F17+F19+N(F21),"") | G22: =IF(AND(ISNUMBER(G17),ISNUMBER(G19)),G17+G19+N(G21),"") | H22: =IF(AND(ISNUMBER(H17),ISNUMBER(H19)),H17+H19+N(H21),"") | I22: =IF(AND(ISNUMBER(I17),ISNUMBER(I19)),I17+I19+N(I21),"") | J22: =IF(AND(ISNUMBER(J17),ISNUMBER(J19)),J17+J19+N(J21),"") | ... BX22: =IF(AND(ISNUMBER(BX17),ISNUMBER(BX19)),BX17+BX19+N(BX21),"") -> 787 | BY22: =BY11*BY23 -> 690.72006 | BZ22: =BZ11*BZ23 -> 886.43107 | CA22: =SUM(BW22,BX22,BY22,BZ22) -> 3132.1511 | CB22: =CB11*CB23 -> 3293.8296 | CC22: =CC11*CC23 -> 3585.6879 | CD22: =CD11*CD23 -> 3902.7971 | CE22: =CE11*CE23 -> 4247.3033 | CF22: Company definition (Q4-25 release): operating profit + amortization of intangibles + other operating profit adjustments. Historical where segment amortization is disclosed (2024+). Forecast = sales × adjusted margin. | CH22: =IFERROR((CE22/BV22)^(1/5)-1,"n/m") -> 0.081775439 | CI22: =IFERROR((BV22/AW22)^(1/5)-1,"n/m") -> n/m | CJ22: =IFERROR((BV22/X22)^(1/10)-1,"n/m") -> n/m | CK22: =IFERROR((BV22/C22)^(1/19)-1,"n/m") -> n/m | CN22: FY26 amortization of acquired intangibles ($m) | CP22: 1900 | CR22: Q2-26 release: FY26 ~$(1,900)m incl. Masimo (10-K schedule pre-Masimo ~$1.7bn).
B23: Adjusted operating margin % | C23: =IF(AND(ISNUMBER(C22),ISNUMBER(C11)),IFERROR(C22/C11,""),"") | D23: =IF(AND(ISNUMBER(D22),ISNUMBER(D11)),IFERROR(D22/D11,""),"") | E23: =IF(AND(ISNUMBER(E22),ISNUMBER(E11)),IFERROR(E22/E11,""),"") | F23: =IF(AND(ISNUMBER(F22),ISNUMBER(F11)),IFERROR(F22/F11,""),"") | G23: =IF(AND(ISNUMBER(G22),ISNUMBER(G11)),IFERROR(G22/G11,""),"") | H23: =IF(AND(ISNUMBER(H22),ISNUMBER(H11)),IFERROR(H22/H11,""),"") | I23: =IF(AND(ISNUMBER(I22),ISNUMBER(I11)),IFERROR(I22/I11,""),"") | J23: =IF(AND(ISNUMBER(J22),ISNUMBER(J11)),IFERROR(J22/J11,""),"") | ... BX23: =IF(AND(ISNUMBER(BX22),ISNUMBER(BX11)),IFERROR(BX22/BX11,""),"") -> 0.40989583 | BY23: =BY24+BY134 -> 0.36523397 | BZ23: =BZ24+BZ134 -> 0.40566922 | CA23: =IF(AND(ISNUMBER(CA22),ISNUMBER(CA11)),IFERROR(CA22/CA11,""),"") -> 0.40190412 | CB23: =CHOOSE(MATCH($CF$2,{"Bull","Base","Bear"},0),$CO$48,$CP$48,$CQ$48) -> 0.395 | CC23: =CHOOSE(MATCH($CF$2,{"Bull","Base","Bear"},0),$CO$49,$CP$49,$CQ$49) -> 0.4 | CD23: =CHOOSE(MATCH($CF$2,{"Bull","Base","Bear"},0),$CO$50,$CP$50,$CQ$50) -> 0.405 | CE23: =CHOOSE(MATCH($CF$2,{"Bull","Base","Bear"},0),$CO$51,$CP$51,$CQ$51) -> 0.41 | CF23: Q3/Q4-26E: margin before calibration + outlook calibration Δ of the quarter (Group block: Q3 margin guidance, Q4 FY26 EPS guidance). 2027E–2030E: scenario lever. | CH23: =IFERROR(AVERAGE(CA23,CB23,CC23,CD23,CE23),"n/m") -> 0.40238082 | CI23: =IFERROR(AVERAGE(BB23,BG23,BL23,BQ23,BV23),"n/m") -> 0.39822767 | CJ23: =IFERROR(AVERAGE(AC23,AH23,AM23,AR23,AW23,BB23,BG23,BL23,BQ23,BV23),"n/m") -> 0.39822767 | CK23: =IFERROR(AVERAGE(C23,D23,E23,F23,G23,H23,I23,N23,S23,X23,AC23,AH23,AM23,AR23,AW23,BB23,BG23,BL23,BQ23,BV23),"n/m") -> 0.39822767
B24: Adjusted operating margin before outlook calibration % (Q3/Q4-26E helper) | BY24: =BT23+((BW22+BX22)/(BW11+BX11)-(BR22+BS22)/(BR11+BS11)) -> 0.37794988 | BZ24: =BU23+((BW22+BX22)/(BW11+BX11)-(BR22+BS22)/(BR11+BS11)) -> 0.38462041 | CF24: Prior-year quarter adjusted margin + (1H/26 − 1H/25 adjusted margin drift).
B25: Incremental adjusted operating margin (Δ adj. op. profit / Δ sales) | D25: =IFERROR((D22-C22)/(D11-C11),"") | E25: =IFERROR((E22-D22)/(E11-D11),"") | F25: =IFERROR((F22-E22)/(F11-E11),"") | G25: =IFERROR((G22-F22)/(G11-F11),"") | H25: =IFERROR((H22-G22)/(H11-G11),"") | I25: =IFERROR((I22-H22)/(I11-H11),"") | N25: =IFERROR((N22-I22)/(N11-I11),"") | O25: =IFERROR((O22-J22)/(O11-J11),"") | P25: =IFERROR((P22-K22)/(P11-K11),"") | Q25: =IFERROR((Q22-L22)/(Q11-L11),"") | R25: =IFERROR((R22-M22)/(R11-M11),"") | S25: =IFERROR((S22-N22)/(S11-N11),"") | T25: =IFERROR((T22-O22)/(T11-O11),"") | U25: =IFERROR((U22-P22)/(U11-P11),"") | ... CA25: =IFERROR((CA22-BV22)/(CA11-BV11),"") -> 0.53000604 | CB25: =IFERROR((CB22-CA22)/(CB11-CA11),"") -> 0.2963697 | CC25: =IFERROR((CC22-CB22)/(CC11-CB11),"") -> 0.46666667 | CD25: =IFERROR((CD22-CC22)/(CD11-CC11),"") -> 0.47166667 | CE25: =IFERROR((CE22-CD22)/(CE11-CD11),"") -> 0.47666667
B26: Depreciation in segment | BG26: 190 | BH26: 40 | BI26: 39 | BJ26: 40 | BK26: 43 | BL26: 162 | BM26: 42 | BN26: 35 | BO26: 36 | BP26: 38 | BQ26: 151 | BR26: 34 | BS26: 38 | BT26: 38 | BU26: 39 | BV26: 149 | BW26: 40 | BX26: 40
B28: Life Sciences (Beckman Coulter Life Sciences, Leica Microsystems, SCIEX, Molecular Devices, IDT, Abcam, Aldevron, Pall Industrial) | CF28: LIFE SCIENCES — modelling logic
B29: Life Sciences sales | V29: 804.5 | W29: 1374.1 | X29: 3314.6 | Y29: 1258.1 | Z29: 1328.3 | AA29: 1325.4 | AB29: 1454.1 | AC29: 5365.9 | AD29: 1308.1 | AE29: 1384.3 | AF29: 1392.6 | AG29: 1625.1 | AH29: 5710.1 | AI29: 1476 | AJ29: 1605.2 | AK29: 1596.7 | AL29: 1793.5 | AM29: 6471.4 | AN29: 1626.9 | AO29: 1712.6 | AP29: 1695.6 | AQ29: 1916 | AR29: 6951.1 | AS29: 1650.4 | AT29: 2642.4 | AU29: 2922.5 | AV29: 3361 | AW29: 10576 | AX29: 3546 | AY29: 3734 | AZ29: 3632 | BA29: 4046 | BB29: 6388 | BC29: 3882 | BD29: 3967 | BE29: 3776 | BF29: 1946 | BG29: 7036 | BH29: 1709 | BI29: 1796 | BJ29: 1706 | BK29: 1930 | BL29: 7141 | BM29: 1745 | BN29: 1770 | BO29: 1782 | BP29: 2032 | BQ29: 7329 | BR29: 1680 | BS29: 1777 | BT29: 1792 | BU29: 2085 | BV29: 7334 | BW29: 1737 | BX29: 1879 | BY29: =BT29*(1+BY31+BY34) -> 1857.9805 | BZ29: =BU29*(1+BZ31+BZ34) -> 2178.4486 | CA29: =SUM(BW29,BX29,BY29,BZ29) -> 7652.4291 | CB29: =CA29*(1+CB31) -> 7958.5263 | CC29: =CB29*(1+CC31) -> 8316.66 | CD29: =CC29*(1+CD31) -> 8690.9097 | CE29: =CD29*(1+CE31) -> 9082.0006 | CF29: Segment sales as reported (hybrid recast basis: periods before a segment recast / spin-off on the restated comparatives). Q3/Q4-26E: prior-year quarter × (1 + core growth + FX). 2027E+: prior year × (1 + scenario core growth); FX nil. | CH29: =IFERROR((CE29/BV29)^(1/5)-1,"n/m") -> 0.043681834 | CI29: =IFERROR((BV29/AW29)^(1/5)-1,"n/m") -> -0.070597379 | CJ29: =IFERROR((BV29/X29)^(1/10)-1,"n/m") -> 0.082657224 | CK29: =IFERROR((BV29/C29)^(1/19)-1,"n/m") -> n/m
B30: Sales y/y % | D30: =IF(AND(ISNUMBER(D29),ISNUMBER(C29)),IFERROR(D29/C29-1,""),"") | E30: =IF(AND(ISNUMBER(E29),ISNUMBER(D29)),IFERROR(E29/D29-1,""),"") | F30: =IF(AND(ISNUMBER(F29),ISNUMBER(E29)),IFERROR(F29/E29-1,""),"") | G30: =IF(AND(ISNUMBER(G29),ISNUMBER(F29)),IFERROR(G29/F29-1,""),"") | H30: =IF(AND(ISNUMBER(H29),ISNUMBER(G29)),IFERROR(H29/G29-1,""),"") | I30: =IF(AND(ISNUMBER(I29),ISNUMBER(H29)),IFERROR(I29/H29-1,""),"") | N30: =IF(AND(ISNUMBER(N29),ISNUMBER(I29)),IFERROR(N29/I29-1,""),"") | O30: =IF(AND(ISNUMBER(O29),ISNUMBER(J29)),IFERROR(O29/J29-1,""),"") | P30: =IF(AND(ISNUMBER(P29),ISNUMBER(K29)),IFERROR(P29/K29-1,""),"") | Q30: =IF(AND(ISNUMBER(Q29),ISNUMBER(L29)),IFERROR(Q29/L29-1,""),"") | R30: =IF(AND(ISNUMBER(R29),ISNUMBER(M29)),IFERROR(R29/M29-1,""),"") | S30: =IF(AND(ISNUMBER(S29),ISNUMBER(N29)),IFERROR(S29/N29-1,""),"") | T30: =IF(AND(ISNUMBER(T29),ISNUMBER(O29)),IFERROR(T29/O29-1,""),"") | U30: =IF(AND(ISNUMBER(U29),ISNUMBER(P29)),IFERROR(U29/P29-1,""),"") | ... CA30: =IF(AND(ISNUMBER(CA29),ISNUMBER(BV29)),IFERROR(CA29/BV29-1,""),"") -> 0.04341821 | CB30: =IF(AND(ISNUMBER(CB29),ISNUMBER(CA29)),IFERROR(CB29/CA29-1,""),"") -> 0.04 | CC30: =IF(AND(ISNUMBER(CC29),ISNUMBER(CB29)),IFERROR(CC29/CB29-1,""),"") -> 0.045 | CD30: =IF(AND(ISNUMBER(CD29),ISNUMBER(CC29)),IFERROR(CD29/CC29-1,""),"") -> 0.045 | CE30: =IF(AND(ISNUMBER(CE29),ISNUMBER(CD29)),IFERROR(CE29/CD29-1,""),"") -> 0.045 | CN30: Minimum net debt / Adjusted EBITDA (x) — buyback floor 2027E+ | CO30: 2.25 | CP30: 2 | CQ30: 1.75 | CR30: Danaher de-levers to ~2x after large deals (Cytiva 2020, Aldevron 2021) before resuming buybacks / M&A. Net debt ~2.6x at 26-Jun-26 (model Adjusted EBITDA). Buybacks absorb surplus cash once leverage reaches the scenario floor.
B31: Core sales growth % (non-GAAP, as published) | AA31: 0.03 | AC31: 0.035 | AD31: 0.03 | AE31: 0.035 | AF31: 0.03 | AH31: 0.04 | AI31: 0.055 | AJ31: 0.075 | AK31: 0.095 | AM31: 0.075 | AN31: 0.07 | AO31: 0.075 | AP31: 0.065 | AR31: 0.07 | AS31: 0.025 | AT31: 0 | AU31: 0.085 | AW31: 0.055 | AX31: 0.205 | AY31: 0.35 | AZ31: 0.2 | BB31: 0.23 | BC31: 0.075 | BD31: 0.07 | BE31: 0.08 | BF31: 0.13 | BG31: 0.095 | BH31: 0.05 | BI31: 0.055 | BJ31: -0.025 | BK31: -0.04 | BL31: 0.01 | BM31: -0.03 | BN31: -0.055 | BO31: -0.02 | BP31: 0.01 | BQ31: -0.02 | BR31: -0.04 | BS31: -0.025 | BT31: -0.01 | BU31: 0.005 | BV31: -0.015 | BW31: 0.005 | BX31: 0.055 | BY31: =BY32+$BY$128 -> 0.046819486 | BZ31: =BZ32+$BY$128 -> 0.051819486 | CB31: =CHOOSE(MATCH($CF$2,{"Bull","Base","Bear"},0),$CO$38,$CP$38,$CQ$38) -> 0.04 | CC31: =CHOOSE(MATCH($CF$2,{"Bull","Base","Bear"},0),$CO$39,$CP$39,$CQ$39) -> 0.045 | CD31: =CHOOSE(MATCH($CF$2,{"Bull","Base","Bear"},0),$CO$40,$CP$40,$CQ$40) -> 0.045 | CE31: =CHOOSE(MATCH($CF$2,{"Bull","Base","Bear"},0),$CO$41,$CP$41,$CQ$41) -> 0.045 | CF31: Q3/Q4-26E: segment input (row below) + core-growth outlook calibration Δ (Group block). 2027E–2030E: scenario lever (Bull/Base/Bear table →). | CH31: =IFERROR(AVERAGE(CA31,CB31,CC31,CD31,CE31),"n/m") -> 0.04375 | CI31: =IFERROR(AVERAGE(BB31,BG31,BL31,BQ31,BV31),"n/m") -> 0.06 | CJ31: =IFERROR(AVERAGE(AC31,AH31,AM31,AR31,AW31,BB31,BG31,BL31,BQ31,BV31),"n/m") -> 0.0575 | CK31: =IFERROR(AVERAGE(C31,D31,E31,F31,G31,H31,I31,N31,S31,X31,AC31,AH31,AM31,AR31,AW31,BB31,BG31,BL31,BQ31,BV31),"n/m") -> 0.0575
B32: Q3/Q4-26E core growth input before outlook calibration | BY32: 0.035 | BZ32: 0.04 | CF32: Q2-26 release: Q3 +3.0–4.0%; FY +3.0–4.0%. Q4 input +4%. | CN32: BIO_CORE (Biotechnology core growth) | CO32: 0.02 | CP32: Δ → | CQ32: -0.025 | CR32: Bioprocessing (Cytiva / Pall): consumables recovery after the 2023–24 destock; FY25 +6.5%, 1H/26 +4.7%; long-term HSD.
B33: Acquisitions / divestitures contribution % (as published) | AA33: 0.61 | AC33: 0.59 | AD33: 0.025 | AE33: 0.025 | AF33: 0.01 | AH33: 0.02 | AI33: 0.015 | AJ33: 0.06 | AK33: 0.065 | AM33: 0.05 | AN33: 0.07 | AO33: 0.02 | AP33: 0.01 | AR33: 0.025 | AS33: 0 | AT33: 0.555 | AU33: 0.63 | AW33: 0.465 | AX33: 0.905 | AY33: 0.02 | AZ33: 0.025 | BB33: 0.165 | BC33: 0.04 | BD33: 0.04 | BE33: 0.025 | BF33: 0 | BG33: 0.055 | BH33: 0.01 | BI33: -0.01 | BJ33: 0.01 | BK33: 0.025 | BL33: 0.015 | BM33: 0.06 | BN33: 0.06 | BO33: 0.07 | BP33: 0.05 | BQ33: 0.06 | BR33: 0.02 | BS33: 0.015 | BT33: 0 | BU33: 0 | BV33: 0.005 | BW33: 0 | BX33: 0 | CN33: 2027E | CO33: =CP33+$CO$32 -> 0.09 | CP33: 0.07 | CQ33: =CP33+$CQ$32 -> 0.045
B34: Currency contribution % (as published) | AA34: 0.005 | AC34: -0.005 | AD34: -0.015 | AE34: -0.02 | AF34: 0.01 | AH34: 0.005 | AI34: 0.06 | AJ34: 0.025 | AK34: -0.015 | AM34: 0.01 | AN34: -0.04 | AO34: -0.03 | AP34: -0.015 | AR34: -0.02 | AS34: -0.01 | AT34: -0.01 | AU34: 0.01 | AW34: 0 | AX34: 0.04 | AY34: 0.045 | AZ34: 0.02 | BB34: 0.02 | BC34: -0.02 | BD34: -0.05 | BE34: -0.065 | BF34: -0.05 | BG34: -0.05 | BH34: -0.035 | BI34: 0.01 | BJ34: 0.005 | BK34: 0.005 | BL34: -0.01 | BM34: -0.01 | BN34: -0.02 | BO34: -0.005 | BP34: -0.005 | BQ34: -0.015 | BR34: -0.015 | BS34: 0.015 | BT34: 0.015 | BU34: 0.02 | BV34: 0.01 | BW34: 0.03 | BX34: 0 | BY34: -0.01 | BZ34: -0.007 | CB34: 0 | CC34: 0 | CD34: 0 | CE34: 0 | CF34: Q3/Q4-26E: company FX guidance (Q3 ~−1.0%; FY ~+0.5% → Q4 implied). 2027E+: nil. | CN34: 2028E | CO34: =CP34+$CO$32 -> 0.095 | CP34: 0.075 | CQ34: =CP34+$CQ$32 -> 0.05
B35: Life Sciences operating profit (GAAP) | V35: 51.5 | W35: 132.6 | X35: 329.2 | Y35: 177.2 | Z35: 192.2 | AA35: 204.7 | AB35: 244.8 | AC35: 818.9 | AD35: 211.6 | AE35: 221.6 | AF35: 246.8 | AG35: 324.3 | AH35: 1004.3 | AI35: 271.3 | AJ35: 291.5 | AK35: 312.8 | AL35: 353.7 | AM35: 1229.3 | AN35: 309 | AO35: 344 | AP35: 342.5 | AQ35: 405.9 | AR35: 1401.4 | AS35: 325.6 | AT35: 412.4 | AU35: 504.9 | AV35: 811 | AW35: 2054 | AX35: 1151 | AY35: 1144 | AZ35: 975 | BA35: 1097 | BB35: 1293 | BC35: 1118 | BD35: 1174 | BE35: 1045 | BF35: 392 | BG35: 1414 | BH35: 321 | BI35: 340 | BJ35: 313 | BK35: 235 | BL35: 1209 | BM35: 235 | BN35: 233 | BO35: 35 | BP35: 376 | BQ35: 879 | BR35: 201 | BS35: -239 | BT35: 222 | BU35: 336 | BV35: 520 | BW35: 225 | BX35: 244 | BY35: =BY40-BY37-BY39 -> 240.15797 | BZ35: =BZ40-BZ37-BZ39 -> 447.98695 | CA35: =SUM(BW35,BX35,BY35,BZ35) -> 1157.1449 | CB35: =CB40-CB37-CB39 -> 1243.737 | CC35: =CC40-CC37-CC39 -> 1365.9004 | CD35: =CD40-CD37-CD39 -> 1495.4324 | CE35: =CE40-CE37-CE39 -> 1701.1152 | CN35: 2029E | CO35: =CP35+$CO$32 -> 0.095 | CP35: 0.075 | CQ35: =CP35+$CQ$32 -> 0.05
B36: Operating margin (GAAP) % | C36: =IF(AND(ISNUMBER(C35),ISNUMBER(C29)),IFERROR(C35/C29,""),"") | D36: =IF(AND(ISNUMBER(D35),ISNUMBER(D29)),IFERROR(D35/D29,""),"") | E36: =IF(AND(ISNUMBER(E35),ISNUMBER(E29)),IFERROR(E35/E29,""),"") | F36: =IF(AND(ISNUMBER(F35),ISNUMBER(F29)),IFERROR(F35/F29,""),"") | G36: =IF(AND(ISNUMBER(G35),ISNUMBER(G29)),IFERROR(G35/G29,""),"") | H36: =IF(AND(ISNUMBER(H35),ISNUMBER(H29)),IFERROR(H35/H29,""),"") | I36: =IF(AND(ISNUMBER(I35),ISNUMBER(I29)),IFERROR(I35/I29,""),"") | J36: =IF(AND(ISNUMBER(J35),ISNUMBER(J29)),IFERROR(J35/J29,""),"") | ... CE36: =IF(AND(ISNUMBER(CE35),ISNUMBER(CE29)),IFERROR(CE35/CE29,""),"") -> 0.18730622 | CN36: 2030E | CO36: =CP36+$CO$32 -> 0.095 | CP36: 0.075 | CQ36: =CP36+$CQ$32 -> 0.05
B37: Amortization of acquired intangibles in segment | AA37: 76.1 | AB37: 76.1 | AC37: 299.4 | AD37: 76.6 | AE37: 76.4 | AF37: 76.9 | AG37: 79 | AH37: 308.9 | AI37: 80.7 | AJ37: 90.5 | AK37: 84.2 | AL37: 88.4 | AM37: 343.8 | AN37: 89.6 | AO37: 89.1 | AP37: 89 | AQ37: 88.9 | AR37: 356.6 | AS37: 89.6 | AT37: 247.9 | AU37: 263.7 | AV37: 268.8 | AW37: 870 | AX37: 277 | AY37: 280 | AZ37: 298 | BA37: 328 | BB37: 1183 | BC37: 321 | BD37: 310 | BE37: 300 | BG37: 419 | BH37: 105 | BI37: 104 | BJ37: 104 | BK37: 116 | BL37: 429 | BM37: 141 | BN37: 140 | BO37: 147 | BP37: 148 | BQ37: 576 | BR37: 149 | BS37: 150 | BT37: 154 | BU37: 151 | BV37: 604 | BW37: 152 | BX37: 151 | BY37: =BY172*BY38 -> 150.27484 | BZ37: =BZ172*BZ38 -> 149.71255 | CA37: =SUM(BW37,BX37,BY37,BZ37) -> 602.98738 | CB37: =CB172*CB38 -> 546.93141 | CC37: =CC172*CC38 -> 546.93141 | CD37: =CD172*CD38 -> 546.93141 | CE37: =CE172*CE38 -> 478.56498 | CF37: Segment amortization as published (segment note; 2024+). Forecast = existing-intangibles schedule × segment share (1H/26). | CN37: LS_CORE (Life Sciences core growth) | CO37: 0.015 | CP37: Δ → | CQ37: -0.02 | CR37: Instruments (pharma / academic capex), reagents (Abcam, IDT), genomic medicines (Aldevron); FY25 −1.5%, 1H/26 +3.0%; guided +3–4% FY26.
B38: Segment share of amortization (existing intangibles) % | C38: =IF(ISNUMBER(C37),IFERROR(C37/(C19+C37+C55),""),"") | D38: =IF(ISNUMBER(D37),IFERROR(D37/(D19+D37+D55),""),"") | E38: =IF(ISNUMBER(E37),IFERROR(E37/(E19+E37+E55),""),"") | F38: =IF(ISNUMBER(F37),IFERROR(F37/(F19+F37+F55),""),"") | G38: =IF(ISNUMBER(G37),IFERROR(G37/(G19+G37+G55),""),"") | H38: =IF(ISNUMBER(H37),IFERROR(H37/(H19+H37+H55),""),"") | I38: =IF(ISNUMBER(I37),IFERROR(I37/(I19+I37+I55),""),"") | J38: =IF(ISNUMBER(J37),IFERROR(J37/(J19+J37+J55),""),"") | ... BX38: =IF(ISNUMBER(BX37),IFERROR(BX37/(BX19+BX37+BX55),""),"") -> 0.33377542 | BY38: =IFERROR((BW37+BX37)/((BW19+BX19)+(BW37+BX37)+(BW55+BX55)),"") -> 0.34183213 | BZ38: =IFERROR((BW37+BX37)/((BW19+BX19)+(BW37+BX37)+(BW55+BX55)),"") -> 0.34183213 | CA38: =$BY$38 -> 0.34183213 | CB38: =$BY$38 -> 0.34183213 | CC38: =$BY$38 -> 0.34183213 | CD38: =$BY$38 -> 0.34183213 | CE38: =$BY$38 -> 0.34183213 | CN38: 2027E | CO38: =CP38+$CO$37 -> 0.055 | CP38: 0.04 | CQ38: =CP38+$CQ$37 -> 0.02
B39: Other operating profit adjustments in segment (impairments, step-up, contingencies; company definition) | BM39: 25 | BN39: 0 | BO39: 222 | BP39: 0 | BQ39: 247 | BR39: 0 | BS39: 432 | BT39: 0 | BU39: 14 | BV39: 446 | BW39: 0 | BX39: 0 | BY39: 0 | BZ39: 0 | CA39: =SUM(BW39,BX39,BY39,BZ39) -> 0 | CB39: 0 | CC39: 0 | CD39: 0 | CE39: 0 | CF39: Published by segment from the Q4-25 release (FY24, Q4-24, FY25, Q4-25); 2025–26 quarters allocated from the release footnotes (see comments). Blank = not disclosed by segment. | CN39: 2028E | CO39: =CP39+$CO$37 -> 0.06 | CP39: 0.045 | CQ39: =CP39+$CQ$37 -> 0.025
B40: Life Sciences adjusted operating profit (non-GAAP) | C40: =IF(AND(ISNUMBER(C35),ISNUMBER(C37)),C35+C37+N(C39),"") | D40: =IF(AND(ISNUMBER(D35),ISNUMBER(D37)),D35+D37+N(D39),"") | E40: =IF(AND(ISNUMBER(E35),ISNUMBER(E37)),E35+E37+N(E39),"") | F40: =IF(AND(ISNUMBER(F35),ISNUMBER(F37)),F35+F37+N(F39),"") | G40: =IF(AND(ISNUMBER(G35),ISNUMBER(G37)),G35+G37+N(G39),"") | H40: =IF(AND(ISNUMBER(H35),ISNUMBER(H37)),H35+H37+N(H39),"") | I40: =IF(AND(ISNUMBER(I35),ISNUMBER(I37)),I35+I37+N(I39),"") | J40: =IF(AND(ISNUMBER(J35),ISNUMBER(J37)),J35+J37+N(J39),"") | ... BX40: =IF(AND(ISNUMBER(BX35),ISNUMBER(BX37)),BX35+BX37+N(BX39),"") -> 395 | BY40: =BY29*BY41 -> 390.4328 | BZ40: =BZ29*BZ41 -> 597.69949 | CA40: =SUM(BW40,BX40,BY40,BZ40) -> 1760.1323 | CB40: =CB29*CB41 -> 1790.6684 | CC40: =CC29*CC41 -> 1912.8318 | CD40: =CD29*CD41 -> 2042.3638 | CE40: =CE29*CE41 -> 2179.6802 | CF40: Company definition (Q4-25 release): operating profit + amortization of intangibles + other operating profit adjustments. Historical where segment amortization is disclosed (2024+). Forecast = sales × adjusted margin. | CH40: =IFERROR((CE40/BV40)^(1/5)-1,"n/m") -> 0.067821408 | CI40: =IFERROR((BV40/AW40)^(1/5)-1,"n/m") -> -0.1169517 | CJ40: =IFERROR((BV40/X40)^(1/10)-1,"n/m") -> n/m | CK40: =IFERROR((BV40/C40)^(1/19)-1,"n/m") -> n/m | CN40: 2029E | CO40: =CP40+$CO$37 -> 0.06 | CP40: 0.045 | CQ40: =CP40+$CQ$37 -> 0.025
B41: Adjusted operating margin % | C41: =IF(AND(ISNUMBER(C40),ISNUMBER(C29)),IFERROR(C40/C29,""),"") | D41: =IF(AND(ISNUMBER(D40),ISNUMBER(D29)),IFERROR(D40/D29,""),"") | E41: =IF(AND(ISNUMBER(E40),ISNUMBER(E29)),IFERROR(E40/E29,""),"") | F41: =IF(AND(ISNUMBER(F40),ISNUMBER(F29)),IFERROR(F40/F29,""),"") | G41: =IF(AND(ISNUMBER(G40),ISNUMBER(G29)),IFERROR(G40/G29,""),"") | H41: =IF(AND(ISNUMBER(H40),ISNUMBER(H29)),IFERROR(H40/H29,""),"") | I41: =IF(AND(ISNUMBER(I40),ISNUMBER(I29)),IFERROR(I40/I29,""),"") | J41: =IF(AND(ISNUMBER(J40),ISNUMBER(J29)),IFERROR(J40/J29,""),"") | ... BX41: =IF(AND(ISNUMBER(BX40),ISNUMBER(BX29)),IFERROR(BX40/BX29,""),"") -> 0.2102182 | BY41: =BY42+BY134 -> 0.21013826 | BZ41: =BZ42+BZ134 -> 0.27436933 | CA41: =IF(AND(ISNUMBER(CA40),ISNUMBER(CA29)),IFERROR(CA40/CA29,""),"") -> 0.23000962 | CB41: =CHOOSE(MATCH($CF$2,{"Bull","Base","Bear"},0),$CO$53,$CP$53,$CQ$53) -> 0.225 | CC41: =CHOOSE(MATCH($CF$2,{"Bull","Base","Bear"},0),$CO$54,$CP$54,$CQ$54) -> 0.23 | CD41: =CHOOSE(MATCH($CF$2,{"Bull","Base","Bear"},0),$CO$55,$CP$55,$CQ$55) -> 0.235 | CE41: =CHOOSE(MATCH($CF$2,{"Bull","Base","Bear"},0),$CO$56,$CP$56,$CQ$56) -> 0.24 | CF41: Q3/Q4-26E: margin before calibration + outlook calibration Δ of the quarter (Group block: Q3 margin guidance, Q4 FY26 EPS guidance). 2027E–2030E: scenario lever. | CH41: =IFERROR(AVERAGE(CA41,CB41,CC41,CD41,CE41),"n/m") -> 0.23200192 | CI41: =IFERROR(AVERAGE(BB41,BG41,BL41,BQ41,BV41),"n/m") -> 0.26475966 | CJ41: =IFERROR(AVERAGE(AC41,AH41,AM41,AR41,AW41,BB41,BG41,BL41,BQ41,BV41),"n/m") -> 0.2534655 | CK41: =IFERROR(AVERAGE(C41,D41,E41,F41,G41,H41,I41,N41,S41,X41,AC41,AH41,AM41,AR41,AW41,BB41,BG41,BL41,BQ41,BV41),"n/m") -> 0.2534655 | CN41: 2030E | CO41: =CP41+$CO$37 -> 0.06 | CP41: 0.045 | CQ41: =CP41+$CQ$37 -> 0.025
B42: Adjusted operating margin before outlook calibration % (Q3/Q4-26E helper) | BY42: =BT41+((BW40+BX40)/(BW29+BX29)-(BR40+BS40)/(BR29+BS29)) -> 0.22285417 | BZ42: =BU41+((BW40+BX40)/(BW29+BX29)-(BR40+BS40)/(BR29+BS29)) -> 0.25332052 | CF42: Prior-year quarter adjusted margin + (1H/26 − 1H/25 adjusted margin drift). | CN42: DX_CORE (Diagnostics core growth, legacy ex Masimo / StatLab) | CO42: 0.015 | CP42: Δ → | CQ42: -0.02 | CR42: Clinical diagnostics (Beckman, Radiometer, Leica) MSD; Cepheid respiratory normalising (~$1.6bn FY26 vs ~$1.9bn FY25).
B43: Incremental adjusted operating margin (Δ adj. op. profit / Δ sales) | D43: =IFERROR((D40-C40)/(D29-C29),"") | E43: =IFERROR((E40-D40)/(E29-D29),"") | F43: =IFERROR((F40-E40)/(F29-E29),"") | G43: =IFERROR((G40-F40)/(G29-F29),"") | H43: =IFERROR((H40-G40)/(H29-G29),"") | I43: =IFERROR((I40-H40)/(I29-H29),"") | N43: =IFERROR((N40-I40)/(N29-I29),"") | O43: =IFERROR((O40-J40)/(O29-J29),"") | P43: =IFERROR((P40-K40)/(P29-K29),"") | Q43: =IFERROR((Q40-L40)/(Q29-L29),"") | R43: =IFERROR((R40-M40)/(R29-M29),"") | S43: =IFERROR((S40-N40)/(S29-N29),"") | T43: =IFERROR((T40-O40)/(T29-O29),"") | U43: =IFERROR((U40-P40)/(U29-P29),"") | ... CA43: =IFERROR((CA40-BV40)/(CA29-BV29),"") -> 0.59709451 | CB43: =IFERROR((CB40-CA40)/(CB29-CA29),"") -> 0.099759582 | CC43: =IFERROR((CC40-CB40)/(CC29-CB29),"") -> 0.34111111 | CD43: =IFERROR((CD40-CC40)/(CD29-CC29),"") -> 0.34611111 | CE43: =IFERROR((CE40-CD40)/(CE29-CD29),"") -> 0.35111111 | CN43: 2027E | CO43: =CP43+$CO$42 -> 0.055 | CP43: 0.04 | CQ43: =CP43+$CQ$42 -> 0.02
B44: Depreciation in segment | AA44: 30.3 | AB44: 34.3 | AC44: 126.8 | AD44: 30.1 | AE44: 29 | AF44: 29.5 | AG44: 30.4 | AH44: 119 | AI44: 30.6 | AJ44: 31.6 | AK44: 32.6 | AL44: 32.6 | AM44: 127.4 | AN44: 32.3 | AO44: 32.8 | AP44: 31.7 | AQ44: 33.7 | AR44: 130.5 | AS44: 33.2 | AT44: 48.2 | AU44: 51 | AV44: 50.6 | AW44: 183 | AX44: 52 | AY44: 64 | AZ44: 71 | BA44: 71 | BB44: 258 | BC44: 72 | BD44: 70 | BE44: 69 | BG44: 112 | BH44: 29 | BI44: 32 | BJ44: 31 | BK44: 37 | BL44: 129 | BM44: 38 | BN44: 41 | BO44: 44 | BP44: 44 | BQ44: 167 | BR44: 45 | BS44: 45 | BT44: 47 | BU44: 48 | BV44: 185 | BW44: 48 | BX44: 48 | CN44: 2028E | CO44: =CP44+$CO$42 -> 0.06 | CP44: 0.045 | CQ44: =CP44+$CQ$42 -> 0.025
CN45: 2029E | CO45: =CP45+$CO$42 -> 0.065 | CP45: 0.05 | CQ45: =CP45+$CQ$42 -> 0.03
B46: Diagnostics (Beckman Coulter Diagnostics, Radiometer, Leica Biosystems, Cepheid; Masimo from 10-Jun-2026) | CF46: DIAGNOSTICS — modelling logic | CN46: 2030E | CO46: =CP46+$CO$42 -> 0.065 | CP46: 0.05 | CQ46: =CP46+$CQ$42 -> 0.03
B47: Diagnostics sales (legacy, ex Masimo & StatLab) | V47: 1175.8 | W47: 1287.5 | X47: 4832.5 | Y47: 1136.2 | Z47: 1257.6 | AA47: 1212.7 | AB47: 1431.8 | AC47: 5038.3 | AD47: 1327.3 | AE47: 1440 | AF47: 1448.7 | AG47: 1623.9 | AH47: 5839.9 | AI47: 1519.7 | AJ47: 1550.9 | AK47: 1502.5 | AL47: 1684.5 | AM47: 6257.6 | AN47: 1536.8 | AO47: 1618.3 | AP47: 1601.9 | AQ47: 1804.5 | AR47: 6561.5 | AS47: 1627 | AT47: 1660.2 | AU47: 1889.1 | AV47: 2227 | AW47: 7403 | AX47: 2178 | AY47: 2336 | AZ47: 2449 | BA47: 2881 | BB47: 9844 | BC47: 2644 | BD47: 2561 | BE47: 2679 | BF47: 2965 | BG47: 10849 | BH47: 2376 | BI47: 2231 | BJ47: 2254 | BK47: 2716 | BL47: 9577 | BM47: 2527 | BN47: 2260 | BO47: 2363 | BP47: 2637 | BQ47: 9787 | BR47: 2449 | BS47: 2309 | BT47: 2463 | BU47: 2720 | BV47: 9941 | BW47: 2417 | BX47: 2374 | BY47: =BT47*(1+BY49+BY52) -> 2467.4814 | BZ47: =BU47*(1+BZ49+BZ52) -> 2855.509 | CA47: =SUM(BW47,BX47,BY47,BZ47) -> 10113.99 | CB47: =CA47*(1+CB49) -> 10518.55 | CC47: =CB47*(1+CC49) -> 10991.885 | CD47: =CC47*(1+CD49) -> 11541.479 | CE47: =CD47*(1+CE49) -> 12118.553 | CF47: Segment sales as reported (hybrid recast basis: periods before a segment recast / spin-off on the restated comparatives). Q3/Q4-26E: prior-year quarter × (1 + core growth + FX). 2027E+: prior year × (1 + scenario core growth); FX nil. Diagnostics shown ex Masimo (from 10-Jun-2026) and StatLab — both modelled in their own blocks below. | CH47: =IFERROR((CE47/BV47)^(1/5)-1,"n/m") -> 0.040409091 | CI47: =IFERROR((BV47/AW47)^(1/5)-1,"n/m") -> 0.060729055 | CJ47: =IFERROR((BV47/X47)^(1/10)-1,"n/m") -> 0.074795455 | CK47: =IFERROR((BV47/C47)^(1/19)-1,"n/m") -> n/m | CN47: BIO_OPM (Biotechnology adjusted operating margin) | CO47: 0.01 | CP47: Δ → | CQ47: -0.015 | CR47: FY25 39.3% (adjusted operating profit $2,867m / sales $7,293m); bioprocessing volume leverage.
B48: Sales y/y % | D48: =IF(AND(ISNUMBER(D47),ISNUMBER(C47)),IFERROR(D47/C47-1,""),"") | E48: =IF(AND(ISNUMBER(E47),ISNUMBER(D47)),IFERROR(E47/D47-1,""),"") | F48: =IF(AND(ISNUMBER(F47),ISNUMBER(E47)),IFERROR(F47/E47-1,""),"") | G48: =IF(AND(ISNUMBER(G47),ISNUMBER(F47)),IFERROR(G47/F47-1,""),"") | H48: =IF(AND(ISNUMBER(H47),ISNUMBER(G47)),IFERROR(H47/G47-1,""),"") | I48: =IF(AND(ISNUMBER(I47),ISNUMBER(H47)),IFERROR(I47/H47-1,""),"") | N48: =IF(AND(ISNUMBER(N47),ISNUMBER(I47)),IFERROR(N47/I47-1,""),"") | O48: =IF(AND(ISNUMBER(O47),ISNUMBER(J47)),IFERROR(O47/J47-1,""),"") | P48: =IF(AND(ISNUMBER(P47),ISNUMBER(K47)),IFERROR(P47/K47-1,""),"") | Q48: =IF(AND(ISNUMBER(Q47),ISNUMBER(L47)),IFERROR(Q47/L47-1,""),"") | R48: =IF(AND(ISNUMBER(R47),ISNUMBER(M47)),IFERROR(R47/M47-1,""),"") | S48: =IF(AND(ISNUMBER(S47),ISNUMBER(N47)),IFERROR(S47/N47-1,""),"") | T48: =IF(AND(ISNUMBER(T47),ISNUMBER(O47)),IFERROR(T47/O47-1,""),"") | U48: =IF(AND(ISNUMBER(U47),ISNUMBER(P47)),IFERROR(U47/P47-1,""),"") | ... CA48: =IF(AND(ISNUMBER(CA47),ISNUMBER(BV47)),IFERROR(CA47/BV47-1,""),"") -> 0.01740171 | CB48: =IF(AND(ISNUMBER(CB47),ISNUMBER(CA47)),IFERROR(CB47/CA47-1,""),"") -> 0.04 | CC48: =IF(AND(ISNUMBER(CC47),ISNUMBER(CB47)),IFERROR(CC47/CB47-1,""),"") -> 0.045 | CD48: =IF(AND(ISNUMBER(CD47),ISNUMBER(CC47)),IFERROR(CD47/CC47-1,""),"") -> 0.05 | CE48: =IF(AND(ISNUMBER(CE47),ISNUMBER(CD47)),IFERROR(CE47/CD47-1,""),"") -> 0.05 | CN48: 2027E | CO48: =CP48+$CO$47 -> 0.405 | CP48: 0.395 | CQ48: =CP48+$CQ$47 -> 0.38
B49: Core sales growth % (non-GAAP, as published) | AA49: 0.03 | AC49: 0.025 | AD49: 0.025 | AE49: 0.025 | AF49: 0.04 | AH49: 0.04 | AI49: 0.095 | AJ49: 0.05 | AK49: 0.055 | AM49: 0.065 | AN49: 0.05 | AO49: 0.075 | AP49: 0.08 | AR49: 0.07 | AS49: 0.08 | AT49: 0.05 | AU49: 0.175 | AW49: 0.135 | AX49: 0.31 | AY49: 0.37 | AZ49: 0.285 | BB49: 0.31 | BC49: 0.225 | BD49: 0.125 | BE49: 0.135 | BF49: 0.075 | BG49: 0.135 | BH49: -0.075 | BI49: -0.115 | BJ49: -0.155 | BK49: -0.085 | BL49: -0.105 | BM49: 0.075 | BN49: 0.03 | BO49: 0.05 | BP49: -0.02 | BQ49: 0.03 | BR49: -0.015 | BS49: 0.02 | BT49: 0.035 | BU49: 0.02 | BV49: 0.015 | BW49: -0.04 | BX49: 0.02 | BY49: =BY50+$BY$128 -> 0.011819486 | BZ49: =BZ50+$BY$128 -> 0.056819486 | CB49: =CHOOSE(MATCH($CF$2,{"Bull","Base","Bear"},0),$CO$43,$CP$43,$CQ$43) -> 0.04 | CC49: =CHOOSE(MATCH($CF$2,{"Bull","Base","Bear"},0),$CO$44,$CP$44,$CQ$44) -> 0.045 | CD49: =CHOOSE(MATCH($CF$2,{"Bull","Base","Bear"},0),$CO$45,$CP$45,$CQ$45) -> 0.05 | CE49: =CHOOSE(MATCH($CF$2,{"Bull","Base","Bear"},0),$CO$46,$CP$46,$CQ$46) -> 0.05 | CF49: Q3/Q4-26E: segment input (row below) + core-growth outlook calibration Δ (Group block). 2027E–2030E: scenario lever (Bull/Base/Bear table →). | CH49: =IFERROR(AVERAGE(CA49,CB49,CC49,CD49,CE49),"n/m") -> 0.04625 | CI49: =IFERROR(AVERAGE(BB49,BG49,BL49,BQ49,BV49),"n/m") -> 0.077 | CJ49: =IFERROR(AVERAGE(AC49,AH49,AM49,AR49,AW49,BB49,BG49,BL49,BQ49,BV49),"n/m") -> 0.072 | CK49: =IFERROR(AVERAGE(C49,D49,E49,F49,G49,H49,I49,N49,S49,X49,AC49,AH49,AM49,AR49,AW49,BB49,BG49,BL49,BQ49,BV49),"n/m") -> 0.072 | CN49: 2028E | CO49: =CP49+$CO$47 -> 0.41 | CP49: 0.4 | CQ49: =CP49+$CQ$47 -> 0.385
B50: Q3/Q4-26E core growth input before outlook calibration | BY50: 0 | BZ50: 0.045 | CF50: Q2-26 release: Q3 flat (respiratory +2.5 pt headwind); FY up slightly; Q4 respiratory flat → input +4.5%. | CN50: 2029E | CO50: =CP50+$CO$47 -> 0.415 | CP50: 0.405 | CQ50: =CP50+$CQ$47 -> 0.39
B51: Acquisitions / divestitures contribution % (as published) | AA51: 0 | AC51: 0.03 | AD51: 0.155 | AE51: 0.135 | AF51: 0.15 | AH51: 0.12 | AI51: 0 | AJ51: 0 | AK51: 0 | AM51: 0 | AN51: 0 | AO51: 0 | AP51: 0 | AR51: 0 | AS51: 0 | AT51: 0 | AU51: 0 | AW51: 0 | AX51: 0 | AY51: 0 | AZ51: 0 | BB51: 0.005 | BC51: 0.01 | BD51: 0.01 | BE51: 0.005 | BF51: 0 | BG51: 0.005 | BH51: 0 | BI51: 0 | BJ51: 0 | BK51: 0 | BL51: 0 | BM51: 0 | BN51: 0 | BO51: 0 | BP51: 0 | BQ51: 0 | BR51: -0.005 | BS51: 0.005 | BT51: -0.005 | BU51: -0.01 | BV51: 0.005 | BW51: 0 | BX51: 0.04 | CN51: 2030E | CO51: =CP51+$CO$47 -> 0.42 | CP51: 0.41 | CQ51: =CP51+$CQ$47 -> 0.395
B52: Currency contribution % (as published) | AA52: 0 | AC52: -0.01 | AD52: -0.01 | AE52: -0.015 | AF52: 0.005 | AH52: 0 | AI52: 0.05 | AJ52: 0.025 | AK52: -0.02 | AM52: 0.005 | AN52: -0.04 | AO52: -0.03 | AP52: -0.015 | AR52: -0.02 | AS52: -0.02 | AT52: -0.025 | AU52: 0.005 | AW52: -0.005 | AX52: 0.03 | AY52: 0.035 | AZ52: 0.01 | BB52: 0.015 | BC52: -0.02 | BD52: -0.04 | BE52: -0.045 | BF52: -0.045 | BG52: -0.04 | BH52: -0.025 | BI52: -0.015 | BJ52: -0.005 | BK52: 0 | BL52: -0.01 | BM52: -0.01 | BN52: -0.015 | BO52: 0 | BP52: -0.01 | BQ52: -0.01 | BR52: -0.01 | BS52: -0.005 | BT52: 0.01 | BU52: 0.02 | BV52: -0.005 | BW52: 0.025 | BX52: 0.01 | BY52: -0.01 | BZ52: -0.007 | CB52: 0 | CC52: 0 | CD52: 0 | CE52: 0 | CF52: Q3/Q4-26E: company FX guidance (Q3 ~−1.0%; FY ~+0.5% → Q4 implied). 2027E+: nil. | CN52: LS_OPM (Life Sciences adjusted operating margin) | CO52: 0.01 | CP52: Δ → | CQ52: -0.015 | CR52: FY25 21.4% ($1,570m / $7,334m); FY24 23.2%; cost actions and Abcam integration.
B53: Diagnostics operating profit (GAAP) (legacy, ex Masimo & StatLab) | V53: 159.2 | W53: 235.9 | X53: 746.2 | Y53: 180.2 | Z53: 232.2 | AA53: 193.9 | AB53: 180.1 | AC53: 786.4 | AD53: 154.6 | AE53: 157.6 | AF53: 242.7 | AG53: 316.7 | AH53: 871.6 | AI53: 248 | AJ53: 274.3 | AK53: 235.1 | AL53: 316.4 | AM53: 1073.8 | AN53: 233.1 | AO53: 282.9 | AP53: 266 | AQ53: 352.1 | AR53: 1134.1 | AS53: 251.2 | AT53: 293.2 | AU53: 408 | AV53: 586 | AW53: 1538 | AX53: 626 | AY53: 649 | AZ53: 145 | BA53: 893 | BB53: 2313 | BC53: 886 | BD53: 800 | BE53: 761 | BF53: 989 | BG53: 3436 | BH53: 677 | BI53: 424 | BJ53: 539 | BK53: 766 | BL53: 2406 | BM53: 830 | BN53: 556 | BO53: 615 | BP53: 624 | BQ53: 2625 | BR53: 718 | BS53: 554 | BT53: 665 | BU53: 713 | BV53: 2650 | BW53: 674 | BX53: 514.4 | BY53: =BY58-BY55-BY57 -> 611.57642 | BZ53: =BZ58-BZ55-BZ57 -> 756.96928 | CA53: =SUM(BW53,BX53,BY53,BZ53) -> 2556.9457 | CB53: =CB58-CB55-CB57 -> 2836.6611 | CC53: =CC58-CC55-CC57 -> 3028.8876 | CD53: =CD58-CD55-CD57 -> 3248.7253 | CE53: =CE58-CE55-CE57 -> 3509.155 | CN53: 2027E | CO53: =CP53+$CO$52 -> 0.235 | CP53: 0.225 | CQ53: =CP53+$CQ$52 -> 0.21
B54: Operating margin (GAAP) % | C54: =IF(AND(ISNUMBER(C53),ISNUMBER(C47)),IFERROR(C53/C47,""),"") | D54: =IF(AND(ISNUMBER(D53),ISNUMBER(D47)),IFERROR(D53/D47,""),"") | E54: =IF(AND(ISNUMBER(E53),ISNUMBER(E47)),IFERROR(E53/E47,""),"") | F54: =IF(AND(ISNUMBER(F53),ISNUMBER(F47)),IFERROR(F53/F47,""),"") | G54: =IF(AND(ISNUMBER(G53),ISNUMBER(G47)),IFERROR(G53/G47,""),"") | H54: =IF(AND(ISNUMBER(H53),ISNUMBER(H47)),IFERROR(H53/H47,""),"") | I54: =IF(AND(ISNUMBER(I53),ISNUMBER(I47)),IFERROR(I53/I47,""),"") | J54: =IF(AND(ISNUMBER(J53),ISNUMBER(J47)),IFERROR(J53/J47,""),"") | ... CE54: =IF(AND(ISNUMBER(CE53),ISNUMBER(CE47)),IFERROR(CE53/CE47,""),"") -> 0.28956882 | CN54: 2028E | CO54: =CP54+$CO$52 -> 0.24 | CP54: 0.23 | CQ54: =CP54+$CQ$52 -> 0.215
B55: Amortization of acquired intangibles in segment | AA55: 33.9 | AB55: 47.6 | AC55: 149.4 | AD55: 56.1 | AE55: 49.9 | AF55: 54.2 | AG55: 53.2 | AH55: 213.4 | AI55: 53.1 | AJ55: 52.6 | AK55: 52.1 | AL55: 52 | AM55: 209.8 | AN55: 52 | AO55: 51.8 | AP55: 51.3 | AQ55: 51.4 | AR55: 206.5 | AS55: 51.4 | AT55: 51.3 | AU55: 51.3 | AV55: 51 | AW55: 205 | AX55: 51 | AY55: 51 | AZ55: 52 | BA55: 51 | BB55: 205 | BC55: 51 | BD55: 50 | BE55: 50 | BF55: 52 | BG55: 203 | BH55: 50 | BI55: 50 | BJ55: 49 | BK55: 49 | BL55: 198 | BM55: 48 | BN55: 48 | BO55: 49 | BP55: 47 | BQ55: 192 | BR55: 48 | BS55: 48 | BT55: 48 | BU55: 47 | BV55: 191 | BW55: 48 | BX55: 70.4 | BY55: =BY172*BY56 -> 58.721256 | BZ55: =BZ172*BZ56 -> 58.501536 | CA55: =SUM(BW55,BX55,BY55,BZ55) -> 235.62279 | CB55: =CB172*CB56 -> 213.71841 | CC55: =CC172*CC56 -> 213.71841 | CD55: =CD172*CD56 -> 213.71841 | CE55: =CE172*CE56 -> 187.00361 | CF55: Segment amortization as published (segment note; 2024+). Forecast = existing-intangibles schedule × segment share (1H/26). | CN55: 2029E | CO55: =CP55+$CO$52 -> 0.245 | CP55: 0.235 | CQ55: =CP55+$CQ$52 -> 0.22
B56: Segment share of amortization (existing intangibles) % | C56: =IF(ISNUMBER(C55),IFERROR(C55/(C19+C37+C55),""),"") | D56: =IF(ISNUMBER(D55),IFERROR(D55/(D19+D37+D55),""),"") | E56: =IF(ISNUMBER(E55),IFERROR(E55/(E19+E37+E55),""),"") | F56: =IF(ISNUMBER(F55),IFERROR(F55/(F19+F37+F55),""),"") | G56: =IF(ISNUMBER(G55),IFERROR(G55/(G19+G37+G55),""),"") | H56: =IF(ISNUMBER(H55),IFERROR(H55/(H19+H37+H55),""),"") | I56: =IF(ISNUMBER(I55),IFERROR(I55/(I19+I37+I55),""),"") | J56: =IF(ISNUMBER(J55),IFERROR(J55/(J19+J37+J55),""),"") | ... BX56: =IF(ISNUMBER(BX55),IFERROR(BX55/(BX19+BX37+BX55),""),"") -> 0.1556145 | BY56: =IFERROR((BW55+BX55)/((BW19+BX19)+(BW37+BX37)+(BW55+BX55)),"") -> 0.13357401 | BZ56: =IFERROR((BW55+BX55)/((BW19+BX19)+(BW37+BX37)+(BW55+BX55)),"") -> 0.13357401 | CA56: =$BY$56 -> 0.13357401 | CB56: =$BY$56 -> 0.13357401 | CC56: =$BY$56 -> 0.13357401 | CD56: =$BY$56 -> 0.13357401 | CE56: =$BY$56 -> 0.13357401 | CN56: 2030E | CO56: =CP56+$CO$52 -> 0.25 | CP56: 0.24 | CQ56: =CP56+$CQ$52 -> 0.225
B57: Other operating profit adjustments in segment (impairments, step-up, contingencies; company definition) | BM57: 0 | BN57: 0 | BO57: 0 | BP57: 99 | BQ57: 99 | BR57: 0 | BS57: 0 | BT57: 15 | BU57: -10 | BV57: 5 | BW57: 17 | BX57: 0 | BY57: 0 | BZ57: 0 | CA57: =SUM(BW57,BX57,BY57,BZ57) -> 17 | CB57: 0 | CC57: 0 | CD57: 0 | CE57: 0 | CF57: Published by segment from the Q4-25 release (FY24, Q4-24, FY25, Q4-25); 2025–26 quarters allocated from the release footnotes (see comments). Blank = not disclosed by segment. | CN57: DX_OPM (Diagnostics adjusted operating margin, legacy) | CO57: 0.01 | CP57: Δ → | CQ57: -0.015 | CR57: FY25 28.6% ($2,846m / $9,941m); respiratory mix headwind fading.
B58: Diagnostics adjusted operating profit (non-GAAP) (legacy, ex Masimo & StatLab) | C58: =IF(AND(ISNUMBER(C53),ISNUMBER(C55)),C53+C55+N(C57),"") | D58: =IF(AND(ISNUMBER(D53),ISNUMBER(D55)),D53+D55+N(D57),"") | E58: =IF(AND(ISNUMBER(E53),ISNUMBER(E55)),E53+E55+N(E57),"") | F58: =IF(AND(ISNUMBER(F53),ISNUMBER(F55)),F53+F55+N(F57),"") | G58: =IF(AND(ISNUMBER(G53),ISNUMBER(G55)),G53+G55+N(G57),"") | H58: =IF(AND(ISNUMBER(H53),ISNUMBER(H55)),H53+H55+N(H57),"") | I58: =IF(AND(ISNUMBER(I53),ISNUMBER(I55)),I53+I55+N(I57),"") | J58: =IF(AND(ISNUMBER(J53),ISNUMBER(J55)),J53+J55+N(J57),"") | ... BX58: =IF(AND(ISNUMBER(BX53),ISNUMBER(BX55)),BX53+BX55+N(BX57),"") -> 584.8 | BY58: =BY47*BY59 -> 670.29768 | BZ58: =BZ47*BZ59 -> 815.47082 | CA58: =SUM(BW58,BX58,BY58,BZ58) -> 2809.5685 | CB58: =CB47*CB59 -> 3050.3795 | CC58: =CC47*CC59 -> 3242.606 | CD58: =CD47*CD59 -> 3462.4437 | CE58: =CE47*CE59 -> 3696.1587 | CF58: Company definition (Q4-25 release): operating profit + amortization of intangibles + other operating profit adjustments. Historical where segment amortization is disclosed (2024+). Forecast = sales × adjusted margin. | CH58: =IFERROR((CE58/BV58)^(1/5)-1,"n/m") -> 0.053666425 | CI58: =IFERROR((BV58/AW58)^(1/5)-1,"n/m") -> 0.10303045 | CJ58: =IFERROR((BV58/X58)^(1/10)-1,"n/m") -> n/m | CK58: =IFERROR((BV58/C58)^(1/19)-1,"n/m") -> n/m | CN58: 2027E | CO58: =CP58+$CO$57 -> 0.3 | CP58: 0.29 | CQ58: =CP58+$CQ$57 -> 0.275
B59: Adjusted operating margin % | C59: =IF(AND(ISNUMBER(C58),ISNUMBER(C47)),IFERROR(C58/C47,""),"") | D59: =IF(AND(ISNUMBER(D58),ISNUMBER(D47)),IFERROR(D58/D47,""),"") | E59: =IF(AND(ISNUMBER(E58),ISNUMBER(E47)),IFERROR(E58/E47,""),"") | F59: =IF(AND(ISNUMBER(F58),ISNUMBER(F47)),IFERROR(F58/F47,""),"") | G59: =IF(AND(ISNUMBER(G58),ISNUMBER(G47)),IFERROR(G58/G47,""),"") | H59: =IF(AND(ISNUMBER(H58),ISNUMBER(H47)),IFERROR(H58/H47,""),"") | I59: =IF(AND(ISNUMBER(I58),ISNUMBER(I47)),IFERROR(I58/I47,""),"") | J59: =IF(AND(ISNUMBER(J58),ISNUMBER(J47)),IFERROR(J58/J47,""),"") | ... BX59: =IF(AND(ISNUMBER(BX58),ISNUMBER(BX47)),IFERROR(BX58/BX47,""),"") -> 0.2463353 | BY59: =BY60+BY134 -> 0.27165258 | BZ59: =BZ60+BZ134 -> 0.28557809 | CA59: =IF(AND(ISNUMBER(CA58),ISNUMBER(CA47)),IFERROR(CA58/CA47,""),"") -> 0.27779031 | CB59: =CHOOSE(MATCH($CF$2,{"Bull","Base","Bear"},0),$CO$58,$CP$58,$CQ$58) -> 0.29 | CC59: =CHOOSE(MATCH($CF$2,{"Bull","Base","Bear"},0),$CO$59,$CP$59,$CQ$59) -> 0.295 | CD59: =CHOOSE(MATCH($CF$2,{"Bull","Base","Bear"},0),$CO$60,$CP$60,$CQ$60) -> 0.3 | CE59: =CHOOSE(MATCH($CF$2,{"Bull","Base","Bear"},0),$CO$61,$CP$61,$CQ$61) -> 0.305 | CF59: Q3/Q4-26E: margin before calibration + outlook calibration Δ of the quarter (Group block: Q3 margin guidance, Q4 FY26 EPS guidance). 2027E–2030E: scenario lever. | CH59: =IFERROR(AVERAGE(CA59,CB59,CC59,CD59,CE59),"n/m") -> 0.29355806 | CI59: =IFERROR(AVERAGE(BB59,BG59,BL59,BQ59,BV59),"n/m") -> 0.28946995 | CJ59: =IFERROR(AVERAGE(AC59,AH59,AM59,AR59,AW59,BB59,BG59,BL59,BQ59,BV59),"n/m") -> 0.24637625 | CK59: =IFERROR(AVERAGE(C59,D59,E59,F59,G59,H59,I59,N59,S59,X59,AC59,AH59,AM59,AR59,AW59,BB59,BG59,BL59,BQ59,BV59),"n/m") -> 0.24637625 | CN59: 2028E | CO59: =CP59+$CO$57 -> 0.305 | CP59: 0.295 | CQ59: =CP59+$CQ$57 -> 0.28
B60: Adjusted operating margin before outlook calibration % (Q3/Q4-26E helper) | BY60: =BT59+((BW58+BX58)/(BW47+BX47)-(BR58+BS58)/(BR47+BS47)) -> 0.28436849 | BZ60: =BU59+((BW58+BX58)/(BW47+BX47)-(BR58+BS58)/(BR47+BS47)) -> 0.26452928 | CF60: Prior-year quarter adjusted margin + (1H/26 − 1H/25 adjusted margin drift). | CN60: 2029E | CO60: =CP60+$CO$57 -> 0.31 | CP60: 0.3 | CQ60: =CP60+$CQ$57 -> 0.285
B61: Incremental adjusted operating margin (Δ adj. op. profit / Δ sales) | D61: =IFERROR((D58-C58)/(D47-C47),"") | E61: =IFERROR((E58-D58)/(E47-D47),"") | F61: =IFERROR((F58-E58)/(F47-E47),"") | G61: =IFERROR((G58-F58)/(G47-F47),"") | H61: =IFERROR((H58-G58)/(H47-G47),"") | I61: =IFERROR((I58-H58)/(I47-H47),"") | N61: =IFERROR((N58-I58)/(N47-I47),"") | O61: =IFERROR((O58-J58)/(O47-J47),"") | P61: =IFERROR((P58-K58)/(P47-K47),"") | Q61: =IFERROR((Q58-L58)/(Q47-L47),"") | R61: =IFERROR((R58-M58)/(R47-M47),"") | S61: =IFERROR((S58-N58)/(S47-N47),"") | T61: =IFERROR((T58-O58)/(T47-O47),"") | U61: =IFERROR((U58-P58)/(U47-P47),"") | ... CA61: =IFERROR((CA58-BV58)/(CA47-BV47),"") -> -0.21059841 | CB61: =IFERROR((CB58-CA58)/(CB47-CA47),"") -> 0.59524232 | CC61: =IFERROR((CC58-CB58)/(CC47-CB47),"") -> 0.40611111 | CD61: =IFERROR((CD58-CC58)/(CD47-CC47),"") -> 0.4 | CE61: =IFERROR((CE58-CD58)/(CE47-CD47),"") -> 0.405 | CN61: 2030E | CO61: =CP61+$CO$57 -> 0.315 | CP61: 0.305 | CQ61: =CP61+$CQ$57 -> 0.29
B62: Depreciation in segment | AA62: 82.3 | AB62: 92.7 | AC62: 332.1 | AD62: 87.6 | AE62: 91.6 | AF62: 92.6 | AG62: 96.3 | AH62: 368.1 | AI62: 94.3 | AJ62: 98 | AK62: 92.2 | AL62: 94.7 | AM62: 379.2 | AN62: 91.6 | AO62: 94.2 | AP62: 94.3 | AQ62: 95.9 | AR62: 376 | AS62: 94.1 | AT62: 100.8 | AU62: 95.7 | AV62: 106.4 | AW62: 397 | AX62: 93 | AY62: 102 | AZ62: 105 | BA62: 109 | BB62: 409 | BC62: 94 | BD62: 98 | BE62: 98 | BF62: 97 | BG62: 387 | BH62: 93 | BI62: 96 | BJ62: 93 | BK62: 97 | BL62: 379 | BM62: 97 | BN62: 100 | BO62: 95 | BP62: 102 | BQ62: 394 | BR62: 100 | BS62: 100 | BT62: 101 | BU62: 106 | BV62: 407 | BW62: 102 | BX62: 107 | CN62: MS_G (Masimo sales growth) | CO62: 0.02 | CP62: Δ → | CQ62: -0.03 | CR62: Company: Masimo high-single-digit core growth long term; 1Q26 standalone +8.5% y/y.
CN63: 2027E | CO63: =CP63+$CO$62 -> 0.1 | CP63: 0.08 | CQ63: =CP63+$CQ$62 -> 0.05
B64: Masimo (pulse oximetry & patient monitoring; acquired 10-Jun-2026 for ~$9.9bn EV; standalone operating company in Diagnostics) | CF64: MASIMO — modelling logic (standalone history from Masimo's own SEC filings; consolidated from closing) | CN64: 2028E | CO64: =CP64+$CO$62 -> 0.1 | CP64: 0.08 | CQ64: =CP64+$CQ$62 -> 0.05
B65: Memo: Masimo standalone sales (pre-acquisition; MASI filings, continuing operations) | BM65: 339.6 | BN65: 343.9 | BO65: 343.3 | BP65: 368.4 | BQ65: 1395.2 | BR65: 372 | BS65: 370.9 | BT65: 371.5 | BU65: 412.5 | BV65: 1526.9 | BW65: 403.6 | CF65: Masimo Corp. Forms 10-K / 10-Q (XBRL), continuing operations (consumer audio sold 2025); Q4 = FY − 9M. 2023 not on the recast basis (omitted). | CN65: 2029E | CO65: =CP65+$CO$62 -> 0.095 | CP65: 0.075 | CQ65: =CP65+$CQ$62 -> 0.045
B66: Standalone sales growth y/y % | D66: =IF(AND(ISNUMBER(D65),ISNUMBER(C65)),IFERROR(D65/C65-1,""),"") | E66: =IF(AND(ISNUMBER(E65),ISNUMBER(D65)),IFERROR(E65/D65-1,""),"") | F66: =IF(AND(ISNUMBER(F65),ISNUMBER(E65)),IFERROR(F65/E65-1,""),"") | G66: =IF(AND(ISNUMBER(G65),ISNUMBER(F65)),IFERROR(G65/F65-1,""),"") | H66: =IF(AND(ISNUMBER(H65),ISNUMBER(G65)),IFERROR(H65/G65-1,""),"") | I66: =IF(AND(ISNUMBER(I65),ISNUMBER(H65)),IFERROR(I65/H65-1,""),"") | N66: =IF(AND(ISNUMBER(N65),ISNUMBER(I65)),IFERROR(N65/I65-1,""),"") | O66: =IF(AND(ISNUMBER(O65),ISNUMBER(J65)),IFERROR(O65/J65-1,""),"") | P66: =IF(AND(ISNUMBER(P65),ISNUMBER(K65)),IFERROR(P65/K65-1,""),"") | Q66: =IF(AND(ISNUMBER(Q65),ISNUMBER(L65)),IFERROR(Q65/L65-1,""),"") | R66: =IF(AND(ISNUMBER(R65),ISNUMBER(M65)),IFERROR(R65/M65-1,""),"") | S66: =IF(AND(ISNUMBER(S65),ISNUMBER(N65)),IFERROR(S65/N65-1,""),"") | T66: =IF(AND(ISNUMBER(T65),ISNUMBER(O65)),IFERROR(T65/O65-1,""),"") | U66: =IF(AND(ISNUMBER(U65),ISNUMBER(P65)),IFERROR(U65/P65-1,""),"") | ... BX66: =IF(AND(ISNUMBER(BX65),ISNUMBER(BS65)),IFERROR(BX65/BS65-1,""),"") | CN66: 2030E | CO66: =CP66+$CO$62 -> 0.095 | CP66: 0.075 | CQ66: =CP66+$CQ$62 -> 0.045
B67: Memo: Masimo standalone operating income (GAAP, MASI filings) | BM67: 53.1 | BN67: 41.9 | BO67: 38.2 | BP67: -70.2 | BQ67: 63 | BR67: 78 | BS67: 64.5 | BT67: 83.6 | BU67: 83.9 | BV67: 310 | BW67: 77.4 | CN67: ST_G (StatLab sales growth) | CO67: 0.02 | CP67: Δ → | CQ67: -0.03 | CR67: Company: StatLab high-single-digit core growth long term.
B68: Standalone operating margin (GAAP) % | C68: =IF(AND(ISNUMBER(C67),ISNUMBER(C65)),IFERROR(C67/C65,""),"") | D68: =IF(AND(ISNUMBER(D67),ISNUMBER(D65)),IFERROR(D67/D65,""),"") | E68: =IF(AND(ISNUMBER(E67),ISNUMBER(E65)),IFERROR(E67/E65,""),"") | F68: =IF(AND(ISNUMBER(F67),ISNUMBER(F65)),IFERROR(F67/F65,""),"") | G68: =IF(AND(ISNUMBER(G67),ISNUMBER(G65)),IFERROR(G67/G65,""),"") | H68: =IF(AND(ISNUMBER(H67),ISNUMBER(H65)),IFERROR(H67/H65,""),"") | I68: =IF(AND(ISNUMBER(I67),ISNUMBER(I65)),IFERROR(I67/I65,""),"") | J68: =IF(AND(ISNUMBER(J67),ISNUMBER(J65)),IFERROR(J67/J65,""),"") | ... BX68: =IF(AND(ISNUMBER(BX67),ISNUMBER(BX65)),IFERROR(BX67/BX65,""),"") | CN68: 2027E | CO68: =CP68+$CO$67 -> 0.1 | CP68: 0.08 | CQ68: =CP68+$CQ$67 -> 0.05
B69: Pro forma Masimo sales (full period, standalone basis) | C69: =IF(ISNUMBER(C65),C65,"") | D69: =IF(ISNUMBER(D65),D65,"") | E69: =IF(ISNUMBER(E65),E65,"") | F69: =IF(ISNUMBER(F65),F65,"") | G69: =IF(ISNUMBER(G65),G65,"") | H69: =IF(ISNUMBER(H65),H65,"") | I69: =IF(ISNUMBER(I65),I65,"") | J69: =IF(ISNUMBER(J65),J65,"") | ... BW69: =IF(ISNUMBER(BW65),BW65,"") -> 403.6 | BX69: =BS65*(1+BW66) -> 402.40656 | BY69: =BT65*(1+BY70) -> 401.22 | BZ69: =BU65*(1+BZ70) -> 445.5 | CA69: =SUM(BW69,BX69,BY69,BZ69) -> 1652.7266 | CB69: =CA69*(1+CB70)+CB71-CA71 -> 1794.9447 | CC69: =CB69*(1+CC70)+CC71-CB71 -> 1953.5403 | CD69: =CC69*(1+CD70)+CD71-CC71 -> 2115.0558 | CE69: =CD69*(1+CE70)+CE71-CD71 -> 2283.685 | CF69: Q2/26 = Q2/25 standalone × (1 + Q1/26 standalone growth) (Masimo stopped filing after closing). Forecast = prior year × (1 + growth) + revenue synergies. | CN69: 2028E | CO69: =CP69+$CO$67 -> 0.1 | CP69: 0.08 | CQ69: =CP69+$CQ$67 -> 0.05
B70: Masimo sales growth % (standalone basis) | D70: =IF(AND(ISNUMBER(D69),ISNUMBER(C69)),IFERROR(D69/C69-1,""),"") | E70: =IF(AND(ISNUMBER(E69),ISNUMBER(D69)),IFERROR(E69/D69-1,""),"") | F70: =IF(AND(ISNUMBER(F69),ISNUMBER(E69)),IFERROR(F69/E69-1,""),"") | G70: =IF(AND(ISNUMBER(G69),ISNUMBER(F69)),IFERROR(G69/F69-1,""),"") | H70: =IF(AND(ISNUMBER(H69),ISNUMBER(G69)),IFERROR(H69/G69-1,""),"") | I70: =IF(AND(ISNUMBER(I69),ISNUMBER(H69)),IFERROR(I69/H69-1,""),"") | N70: =IF(AND(ISNUMBER(N69),ISNUMBER(I69)),IFERROR(N69/I69-1,""),"") | O70: =IF(AND(ISNUMBER(O69),ISNUMBER(J69)),IFERROR(O69/J69-1,""),"") | P70: =IF(AND(ISNUMBER(P69),ISNUMBER(K69)),IFERROR(P69/K69-1,""),"") | Q70: =IF(AND(ISNUMBER(Q69),ISNUMBER(L69)),IFERROR(Q69/L69-1,""),"") | R70: =IF(AND(ISNUMBER(R69),ISNUMBER(M69)),IFERROR(R69/M69-1,""),"") | S70: =IF(AND(ISNUMBER(S69),ISNUMBER(N69)),IFERROR(S69/N69-1,""),"") | T70: =IF(AND(ISNUMBER(T69),ISNUMBER(O69)),IFERROR(T69/O69-1,""),"") | U70: =IF(AND(ISNUMBER(U69),ISNUMBER(P69)),IFERROR(U69/P69-1,""),"") | ... BX70: =IF(AND(ISNUMBER(BX69),ISNUMBER(BS69)),IFERROR(BX69/BS69-1,""),"") -> 0.084946237 | BY70: 0.08 | BZ70: 0.08 | CA70: =IF(AND(ISNUMBER(CA69),ISNUMBER(BV69)),IFERROR(CA69/BV69-1,""),"") -> 0.082406549 | CB70: =CHOOSE(MATCH($CF$2,{"Bull","Base","Bear"},0),$CO$63,$CP$63,$CQ$63) -> 0.08 | CC70: =CHOOSE(MATCH($CF$2,{"Bull","Base","Bear"},0),$CO$64,$CP$64,$CQ$64) -> 0.08 | CD70: =CHOOSE(MATCH($CF$2,{"Bull","Base","Bear"},0),$CO$65,$CP$65,$CQ$65) -> 0.075 | CE70: =CHOOSE(MATCH($CF$2,{"Bull","Base","Bear"},0),$CO$66,$CP$66,$CQ$66) -> 0.075 | CF70: Company: high-single-digit core growth long term (Feb-2026 deal release). Scenario lever 2027E+. | CN70: 2029E | CO70: =CP70+$CO$67 -> 0.1 | CP70: 0.08 | CQ70: =CP70+$CQ$67 -> 0.05
B71: Revenue synergies (cumulative run-rate; >$50m by year 5) | CA71: 0 | CB71: 10 | CC71: 25 | CD71: 40 | CE71: 50 | CN71: 2030E | CO71: =CP71+$CO$67 -> 0.1 | CP71: 0.08 | CQ71: =CP71+$CQ$67 -> 0.05
B72: Days consolidated in period (closing 10-Jun-2026) | BX72: 16 | BY72: 91 | BZ72: 98 | CA72: =SUM(BW72,BX72,BY72,BZ72) -> 205 | CB72: 365 | CC72: 365 | CD72: 365 | CE72: 365 | CN72: M&A_spend (bolt-on acquisitions, $m) | CO72: 1500 | CP72: Δ → | CQ72: -1000 | CR72: Danaher deployed ~$10bn on Masimo in 2026 (plus StatLab). Base resumes bolt-ons as leverage falls toward ~2x.
B73: Masimo sales consolidated (in Diagnostics) | BX73: 92 | BY73: =BY69 -> 401.22 | BZ73: =BZ69 -> 445.5 | CA73: =SUM(BW73,BX73,BY73,BZ73) -> 938.72 | CB73: =CB69 -> 1794.9447 | CC73: =CC69 -> 1953.5403 | CD73: =CD69 -> 2115.0558 | CE73: =CE69 -> 2283.685 | CF73: Q2/26: sales contributed since closing (10-Q acquisition note). Q3/Q4-26E: pro forma quarter (full quarter consolidated). 2027E+: full year. | CN73: 2027E | CO73: =MAX(0,CP73+$CO$72) -> 2500 | CP73: 1000 | CQ73: =MAX(0,CP73+$CQ$72) -> 0
B74: Adjusted operating margin of Masimo (before purchase accounting & synergies) % | BY74: 0.23 | BZ74: 0.25 | CA74: =IF(AND(ISNUMBER(CA76),ISNUMBER(CA73)),IFERROR(CA76/CA73,""),"") -> 0.24379538 | CB74: 0.26 | CC74: 0.265 | CD74: 0.27 | CE74: 0.275 | CF74: Masimo standalone FY25 GAAP operating margin 20.3% (MASI 10-K, continuing operations); Danaher target EBITDA >$530m in 2027 under its ownership (Feb-2026 deal release) → ~26% adjusted operating margin + depreciation. Synergies added separately. | CN74: 2028E | CO74: =MAX(0,CP74+$CO$72) -> 3500 | CP74: 2000 | CQ74: =MAX(0,CP74+$CQ$72) -> 1000
B75: (+) Cost synergies realised (>$125m run-rate by year 5) | BY75: 0 | BZ75: 5 | CB75: 30 | CC75: 60 | CD75: 90 | CE75: 115 | CN75: 2029E | CO75: =MAX(0,CP75+$CO$72) -> 4000 | CP75: 2500 | CQ75: =MAX(0,CP75+$CQ$72) -> 1500
B76: Masimo adjusted operating profit contribution | BX76: 20.2 | BY76: =BY73*BY74+BY75 -> 92.2806 | BZ76: =BZ73*BZ74+BZ75 -> 116.375 | CA76: =SUM(BW76,BX76,BY76,BZ76) -> 228.8556 | CB76: =CB73*CB74+CB75 -> 496.68562 | CC76: =CC73*CC74+CC75 -> 577.68817 | CD76: =CD73*CD74+CD75 -> 661.06506 | CE76: =CE73*CE74+CE75 -> 743.01336 | CF76: Q2/26: stub-period estimate (sales contributed × Q1/26 standalone operating margin + amortization add-back). Forecast = sales × margin + cost synergies. | CN76: 2030E | CO76: =MAX(0,CP76+$CO$72) -> 4000 | CP76: 2500 | CQ76: =MAX(0,CP76+$CQ$72) -> 1500
B77: Adjusted operating margin incl. synergies % | C77: =IF(AND(ISNUMBER(C76),ISNUMBER(C73)),IFERROR(C76/C73,""),"") | D77: =IF(AND(ISNUMBER(D76),ISNUMBER(D73)),IFERROR(D76/D73,""),"") | E77: =IF(AND(ISNUMBER(E76),ISNUMBER(E73)),IFERROR(E76/E73,""),"") | F77: =IF(AND(ISNUMBER(F76),ISNUMBER(F73)),IFERROR(F76/F73,""),"") | G77: =IF(AND(ISNUMBER(G76),ISNUMBER(G73)),IFERROR(G76/G73,""),"") | H77: =IF(AND(ISNUMBER(H76),ISNUMBER(H73)),IFERROR(H76/H73,""),"") | I77: =IF(AND(ISNUMBER(I76),ISNUMBER(I73)),IFERROR(I76/I73,""),"") | J77: =IF(AND(ISNUMBER(J76),ISNUMBER(J73)),IFERROR(J76/J73,""),"") | ... CE77: =IF(AND(ISNUMBER(CE76),ISNUMBER(CE73)),IFERROR(CE76/CE73,""),"") -> 0.32535721
B78: (−) Amortization of Masimo acquired intangibles (within total amortization) | BX78: 10.6 | BY78: =$BX$402/$BX$407*BY72/365 -> 60.38411 | BZ78: =$BX$402/$BX$407*BZ72/365 -> 65.029041 | CA78: =SUM(BW78,BX78,BY78,BZ78) -> 136.01315 | CB78: =$BX$402/$BX$407 -> 242.2 | CC78: =$BX$402/$BX$407 -> 242.2 | CD78: =$BX$402/$BX$407 -> 242.2 | CE78: =$BX$402/$BX$407 -> 242.2 | CF78: Preliminary PPA intangibles ÷ weighted useful life (schedule block). Non-cash; added back in adjusted results.
B79: (−) Inventory fair-value step-up & acquisition-related items expensed | BX79: 108 | BY79: 30 | BZ79: 0 | CA79: =SUM(BW79,BX79,BY79,BZ79) -> 138 | CB79: 0 | CC79: 0 | CD79: 0 | CE79: 0 | CF79: Q2/26: $108m (inventory step-up $46m, transaction costs $34m, share-based / change-in-control payments). Q3/26E input: remaining inventory step-up (estimate; total step-up not disclosed).
B80: Memo: Masimo EBITDA (adjusted operating profit + D&A ex purchase accounting; company target >$530m in 2027) | BY80: =BY76+BY73*BY81 -> 100.305 | BZ80: =BZ76+BZ73*BZ81 -> 125.285 | CA80: =CA76+CA73*CA81 -> 247.63 | CB80: =CB76+CB73*CB81 -> 532.58451 | CC80: =CC76+CC73*CC81 -> 616.75897 | CD80: =CD76+CD73*CD81 -> 703.36618 | CE80: =CE76+CE73*CE81 -> 788.68706
B81: Masimo depreciation % of sales (standalone) | BY81: 0.02 | BZ81: 0.02 | CA81: 0.02 | CB81: 0.02 | CC81: 0.02 | CD81: 0.02 | CE81: 0.02
B83: StatLab (histology consumables; pending — Leica Biosystems / Diagnostics; ~$250m 2025 sales; closing assumed end-2026) | CF83: STATLAB — pending acquisition (announced Jul-2026, expected to close by end-2026); excluded from FY26 guidance
B84: Closing assumed (1 = consolidated from 1-Jan-2027; purchase price paid in 2026E) | CA84: 1 | CB84: 1 | CC84: 1 | CD84: 1 | CE84: 1 | CF84: Company: expected to close by the end of 2026, subject to regulatory approvals. Set 2026E to 0 to exclude the deal.
B85: StatLab sales (pro forma, standalone) | CA85: 270 | CB85: =CA85*(1+CB86) -> 291.6 | CC85: =CB85*(1+CC86) -> 314.928 | CD85: =CC85*(1+CD86) -> 340.12224 | CE85: =CD85*(1+CE86) -> 367.33202 | CF85: Q2-26 release: StatLab ~$250m revenue in FY2025; 2026E pro forma at +8%.
B86: StatLab sales growth % | CB86: =CHOOSE(MATCH($CF$2,{"Bull","Base","Bear"},0),$CO$68,$CP$68,$CQ$68) -> 0.08 | CC86: =CHOOSE(MATCH($CF$2,{"Bull","Base","Bear"},0),$CO$69,$CP$69,$CQ$69) -> 0.08 | CD86: =CHOOSE(MATCH($CF$2,{"Bull","Base","Bear"},0),$CO$70,$CP$70,$CQ$70) -> 0.08 | CE86: =CHOOSE(MATCH($CF$2,{"Bull","Base","Bear"},0),$CO$71,$CP$71,$CQ$71) -> 0.08 | CF86: Company: high-single-digit core growth long term.
B87: StatLab sales consolidated (in Diagnostics) | CA87: 0 | CB87: =CB85*$CA$84 -> 291.6 | CC87: =CC85*$CA$84 -> 314.928 | CD87: =CD85*$CA$84 -> 340.12224 | CE87: =CE85*$CA$84 -> 367.33202
B88: Adjusted operating margin of StatLab % | CA88: 0 | CB88: 0.3 | CC88: 0.3 | CD88: 0.3 | CE88: 0.3 | CF88: Assumption: histology consumables (>85% recurring revenue); ~30% adjusted operating margin before synergies.
B89: StatLab adjusted operating profit contribution | CA89: 0 | CB89: =CB87*CB88 -> 87.48 | CC89: =CC87*CC88 -> 94.4784 | CD89: =CD87*CD88 -> 102.03667 | CE89: =CE87*CE88 -> 110.19961
B90: (−) Amortization of StatLab acquired intangibles | CA90: 0 | CB90: =IFERROR($CA$91*CB93/CB94,0)*$CA$84 -> 54 | CC90: =IFERROR($CA$91*CC93/CC94,0)*$CA$84 -> 54 | CD90: =IFERROR($CA$91*CD93/CD94,0)*$CA$84 -> 54 | CE90: =IFERROR($CA$91*CE93/CE94,0)*$CA$84 -> 54
B91: Purchase price (enterprise value, cash; scenario-neutral input) | CA91: =CA85*CA92*CA84 -> 2025 | CF91: Purchase price = 2026E pro forma sales × EV/sales input × closing switch. Paid in 2026E (funded with commercial paper).
B92: Purchase multiple — EV / sales (x) | CA92: 7.5 | CF92: ASSUMPTION — purchase price not disclosed in any SEC filing. 7.5x sales (~$2.0bn) for a recurring-revenue consumables business; update when disclosed.
B93: Acquired intangibles % of price | CA93: 0.4 | CB93: 0.4 | CC93: 0.4 | CD93: 0.4 | CE93: 0.4
B94: Intangible amortization life (years) | CA94: 15 | CB94: 15 | CC94: 15 | CD94: 15 | CE94: 15
B96: Future acquisitions (M&A lever — bolt-ons, unallocated; deals closed from 2027E) | CF96: M&A LEVER — acquired sales = spend ÷ EV/sales; mid-year convention
B97: Acquisition spend (USDm, scenario) | CA97: 0 | CB97: =MAX(0,CHOOSE(MATCH($CF$2,{"Bull","Base","Bear"},0),$CO$73,$CP$73,$CQ$73)) -> 1000 | CC97: =MAX(0,CHOOSE(MATCH($CF$2,{"Bull","Base","Bear"},0),$CO$74,$CP$74,$CQ$74)) -> 2000 | CD97: =MAX(0,CHOOSE(MATCH($CF$2,{"Bull","Base","Bear"},0),$CO$75,$CP$75,$CQ$75)) -> 2500 | CE97: =MAX(0,CHOOSE(MATCH($CF$2,{"Bull","Base","Bear"},0),$CO$76,$CP$76,$CQ$76)) -> 2500 | CF97: Scenario lever M&A_spend. Danaher acquisitions: Cytiva $20.7bn (2020), Aldevron $9.6bn (2021), Abcam $5.6bn (2023), Masimo $9.8bn (2026).
B98: Purchase multiple — EV / sales (x) | CA98: 0 | CB98: 6 | CC98: 6 | CD98: 6 | CE98: 6 | CF98: Danaher life-science / diagnostics deals: Abcam ~11x, Aldevron ~16x, Cytiva ~6x, Masimo ~6.5x sales; 6.0x input for bolt-ons.
B99: Annualised sales acquired in the year | CA99: 0 | CB99: =IFERROR(CB97/CB98,0) -> 166.66667 | CC99: =IFERROR(CC97/CC98,0) -> 333.33333 | CD99: =IFERROR(CD97/CD98,0) -> 416.66667 | CE99: =IFERROR(CE97/CE98,0) -> 416.66667
B100: Growth of acquired businesses after acquisition % | CA100: 0 | CB100: 0.06 | CC100: 0.06 | CD100: 0.06 | CE100: 0.06
B101: Run-rate sales of businesses acquired (year end) | CA101: 0 | CB101: =CA101*(1+CB100)+CB99 -> 166.66667 | CC101: =CB101*(1+CC100)+CC99 -> 510 | CD101: =CC101*(1+CD100)+CD99 -> 957.26667 | CE101: =CD101*(1+CE100)+CE99 -> 1431.3693
B102: Sales from future acquisitions | CA102: 0 | CB102: =CA101*(1+CB100)+0.5*CB99 -> 83.333333 | CC102: =CB101*(1+CC100)+0.5*CC99 -> 343.33333 | CD102: =CC101*(1+CD100)+0.5*CD99 -> 748.93333 | CE102: =CD101*(1+CE100)+0.5*CE99 -> 1223.036 | CF102: Mid-year convention: deals close evenly through the year (half a year of sales in year 1). Unallocated to segments.
B103: Adjusted operating margin of acquired businesses % | CA103: 0 | CB103: 0.25 | CC103: 0.25 | CD103: 0.25 | CE103: 0.25
...

Sheet Bull-Base-Bear
B2: Danaher Corporation (DHR) — Bull / Base / Bear Case P&L Summary | J2: Share price ($): | K2: =Model!$CA$464 -> 221.21
B3: Adjusted figures (company definitions: core sales growth, adjusted operating profit, adjusted diluted EPS incl. add-back of acquired-intangible amortization; Adjusted EBITDA = model definition) · USD millions · Live panel linked to Model — toggle scenario via Model!CF2. Bull and Bear panels are value snapshots generated from the Model with the switch set to each case. 2026E includes Masimo from 10-Jun-2026; StatLab assumed closed end-2026. | J3: As of: | K3: =TODAY() -> 46301
B5: Scenario: | C5: =Model!$CF$2 -> Base | N5: Scenario: | O5: Bull | P5: Snapshot (values) — Model run with switch = Bull | Z5: Scenario: | AA5: Bear | AB5: Snapshot (values) — Model run with switch = Bear
B7: (USDm, except EPS and shares) | C7: 2025A | D7: 2026E | E7: 2027E | F7: 2028E | G7: 2029E | H7: 2030E | I7: 25-'30 CAGR | J7: LT Hist Avg | K7: LT Hist Min | L7: LT Hist Max | N7: (USDm, except EPS and shares) | O7: 2025A | P7: 2026E | Q7: 2027E | R7: 2028E | S7: 2029E | T7: 2030E | U7: 25-'30 CAGR | V7: LT Hist Avg | W7: LT Hist Min | X7: LT Hist Max | Z7: (USDm, except EPS and shares) | AA7: 2025A | AB7: 2026E | AC7: 2027E | AD7: 2028E | AE7: 2029E | AF7: 2030E | AG7: 25-'30 CAGR | AH7: LT Hist Avg | AI7: LT Hist Min | AJ7: LT Hist Max
B9: Sales | C9: =Model!BV178 -> 24568 | D9: =Model!CA178 -> 26498.419 | E9: =Model!CB178 -> 28985.763 | F9: =Model!CC178 -> 30884.566 | G9: =Model!CD178 -> 33073.036 | H9: =Model!CE178 -> 35433.883 | I9: =IFERROR((H9/C9)^(1/5)-1,"n/m") -> 0.075993849 | N9: Sales | O9: 24568 | P9: 26621.259 | Q9: 29702.454 | R9: 32395.807 | S9: 35464.939 | T9: 38800.719 | U9: 0.095705883 | Z9: Sales | AA9: 24568 | AB9: 26375.579 | AC9: 28168.378 | AD9: 29224.288 | AE9: 30495.931 | AF9: 31860.725 | AG9: 0.053360842
B10: Sales y/y % | D10: =IFERROR(D9/C9-1,"") -> 0.078574528 | E10: =IFERROR(E9/D9-1,"") -> 0.093867652 | F10: =IFERROR(F9/E9-1,"") -> 0.065508114 | G10: =IFERROR(G9/F9-1,"") -> 0.070859671 | H10: =IFERROR(H9/G9-1,"") -> 0.071382824 | N10: Sales y/y % | P10: 0.083574528 | Q10: 0.11574188 | R10: 0.090677812 | S10: 0.094738536 | T10: 0.094058538 | Z10: Sales y/y % | AB10: 0.073574528 | AC10: 0.067971945 | AD10: 0.037485653 | AE10: 0.043513203 | AF10: 0.044753316
B11: Core sales growth % (non-GAAP) | C11: =Model!BV275 -> 0.02 | D11: =Model!CA275 -> 0.035 | E11: =Model!CB275 -> 0.047406087 | F11: =Model!CC275 -> 0.056020698 | G11: =Model!CD275 -> 0.057241218 | H11: =Model!CE275 -> 0.056745442 | N11: Core sales growth % (non-GAAP) | O11: 0.02 | P11: 0.04 | Q11: 0.06335471 | R11: 0.072497496 | S11: 0.0730845 | T11: 0.072012633 | Z11: Core sales growth % (non-GAAP) | AA11: 0.02 | AB11: 0.03 | AC11: 0.02664042 | AD11: 0.033994741 | AE11: 0.035528977 | AF11: 0.035388132
B12: Adjusted EBITDA (model definition) | C12: =Model!BV227 -> 7689 | D12: =Model!CA227 -> 8416.5095 | E12: =Model!CB227 -> 9261.6202 | F12: =Model!CC227 -> 10055.048 | G12: =Model!CD227 -> 10953.254 | H12: =Model!CE227 -> 11919.924 | I12: =IFERROR((H12/C12)^(1/5)-1,"n/m") -> 0.091643228 | N12: Adjusted EBITDA (model definition) | O12: 7689 | P12: 8478.5362 | Q12: 9760.6638 | R12: 10823.16 | S12: 12026.382 | T12: 13337.556 | U12: 0.11645514 | Z12: Adjusted EBITDA (model definition) | AA12: 7689 | AB12: 8354.3807 | AC12: 8610.4472 | AD12: 9120.7153 | AE12: 9703.0939 | AF12: 10319.184 | AG12: 0.060608484
B13: Adjusted EBITDA margin % | C13: =IFERROR(C12/C9,"") -> 0.31296809 | D13: =IFERROR(D12/D9,"") -> 0.31762308 | E13: =IFERROR(E12/E9,"") -> 0.31952307 | F13: =IFERROR(F12/F9,"") -> 0.32556869 | G13: =IFERROR(G12/G9,"") -> 0.33118382 | H13: =IFERROR(H12/H9,"") -> 0.33639903 | J13: =IFERROR(AVERAGE(Model!C228,Model!D228,Model!E228,Model!F228,Model!G228,Model!H228,Model!I228,Model!N228,Model!S228,Model!X228,Model!AC228,Model!AH228,Model!AM228,Model!AR228,Model!AW228,Model!BB228,Model!BG228,Model!BL228,Model!BQ228,Model!BV228),"") -> 0.24791445 | K13: =IFERROR(MIN(Model!C228,Model!D228,Model!E228,Model!F228,Model!G228,Model!H228,Model!I228,Model!N228,Model!S228,Model!X228,Model!AC228,Model!AH228,Model!AM228,Model!AR228,Model!AW228,Model!BB228,Model!BG228,Model!BL228,Model!BQ228,Model!BV228),"") -> 0.17942047 | L13: =IFERROR(MAX(Model!C228,Model!D228,Model!E228,Model!F228,Model!G228,Model!H228,Model!I228,Model!N228,Model!S228,Model!X228,Model!AC228,Model!AH228,Model!AM228,Model!AR228,Model!AW228,Model!BB228,Model!BG228,Model!BL228,Model!BQ228,Model!BV228),"") -> 0.36666291 | N13: Adjusted EBITDA margin % | O13: 0.31296809 | P13: 0.31848742 | Q13: 0.32861473 | R13: 0.3340914 | S13: 0.33910625 | T13: 0.34374507 | V13: 0.24791445 | W13: 0.17942047 | X13: 0.36666291 | Z13: Adjusted EBITDA margin % | AA13: 0.31296809 | AB13: 0.31674682 | AC13: 0.30567778 | AD13: 0.31209366 | AE13: 0.31817667 | AF13: 0.32388415 | AH13: 0.24791445 | AI13: 0.17942047 | AJ13: 0.36666291
B15: Operating Profit (GAAP) | C15: =Model!BV185 -> 4690 | D15: =Model!CA185 -> 5517.7075 | E15: =Model!CB185 -> 6453.5282 | F15: =Model!CC185 -> 7148.0929 | G15: =Model!CD185 -> 7918.4569 | H15: =Model!CE185 -> 8945.2736 | I15: =IFERROR((H15/C15)^(1/5)-1,"n/m") -> 0.13784776 | N15: Operating Profit (GAAP) | O15: 4690 | P15: 5575.8226 | Q15: 6910.3544 | R15: 7809.3571 | S15: 8817.4358 | T15: 10118.534 | U15: 0.16624272 | Z15: Operating Profit (GAAP) | AA15: 4690 | AB15: 5459.4904 | AC15: 5841.0275 | AD15: 6305.229 | AE15: 6814.8534 | AF15: 7548.6346 | AG15: 0.099864315
B16: Operating profit y/y % | D16: =IFERROR(D15/C15-1,"") -> 0.17648348 | E16: =IFERROR(E15/D15-1,"") -> 0.16960316 | F16: =IFERROR(F15/E15-1,"") -> 0.10762558 | G16: =IFERROR(G15/F15-1,"") -> 0.10777196 | H16: =IFERROR(H15/G15-1,"") -> 0.12967384 | N16: Operating profit y/y % | P16: 0.18887475 | Q16: 0.23934259 | R16: 0.13009502 | S16: 0.12908601 | T16: 0.14755965 | Z16: Operating profit y/y % | AB16: 0.16407044 | AC16: 0.069885123 | AD16: 0.079472568 | AE16: 0.080825674 | AF16: 0.10767381
B17: Operating margin (GAAP) % | C17: =IFERROR(C15/C9,"") -> 0.19089873 | D17: =IFERROR(D15/D9,"") -> 0.2082278 | E17: =IFERROR(E15/E9,"") -> 0.22264475 | F17: =IFERROR(F15/F9,"") -> 0.23144547 | G17: =IFERROR(G15/G9,"") -> 0.23942334 | H17: =IFERROR(H15/H9,"") -> 0.25244971 | J17: =IFERROR(AVERAGE(Model!C288,Model!D288,Model!E288,Model!F288,Model!G288,Model!H288,Model!I288,Model!N288,Model!S288,Model!X288,Model!AC288,Model!AH288,Model!AM288,Model!AR288,Model!AW288,Model!BB288,Model!BG288,Model!BL288,Model!BQ288,Model!BV288),"") -> 0.18114768 | K17: =IFERROR(MIN(Model!C288,Model!D288,Model!E288,Model!F288,Model!G288,Model!H288,Model!I288,Model!N288,Model!S288,Model!X288,Model!AC288,Model!AH288,Model!AM288,Model!AR288,Model!AW288,Model!BB288,Model!BG288,Model!BL288,Model!BQ288,Model!BV288),"") -> 0.1379002 | L17: =IFERROR(MAX(Model!C288,Model!D288,Model!E288,Model!F288,Model!G288,Model!H288,Model!I288,Model!N288,Model!S288,Model!X288,Model!AC288,Model!AH288,Model!AM288,Model!AR288,Model!AW288,Model!BB288,Model!BG288,Model!BL288,Model!BQ288,Model!BV288),"") -> 0.28285103 | N17: Operating margin (GAAP) % | O17: 0.19089873 | P17: 0.20945 | Q17: 0.23265264 | R17: 0.24106074 | S17: 0.24862403 | T17: 0.26078212 | V17: 0.18114768 | W17: 0.1379002 | X17: 0.28285103 | Z17: Operating margin (GAAP) % | AA17: 0.19089873 | AB17: 0.20699035 | AC17: 0.20736116 | AD17: 0.21575304 | AE17: 0.22346763 | AF17: 0.23692601 | AH17: 0.18114768 | AI17: 0.1379002 | AJ17: 0.28285103
B19: Adjusted Net Earnings (continuing operations, attributable to common) | C19: =Model!BV262 -> 5582.678 | D19: =Model!CA262 -> 6035.1452 | E19: =Model!CB262 -> 6579.9381 | F19: =Model!CC262 -> 7228.8626 | G19: =Model!CD262 -> 7848.6301 | H19: =Model!CE262 -> 8535.563 | I19: =IFERROR((H19/C19)^(1/5)-1,"n/m") -> 0.088624036 | N19: Adjusted Net Earnings (continuing operations, attributable to common) | O19: 5582.678 | P19: 6083.3807 | Q19: 6966.547 | R19: 7754.4261 | S19: 8589.7608 | T19: 9518.6471 | U19: 0.11261915 | Z19: Adjusted Net Earnings (continuing operations, attributable to common) | AA19: 5582.678 | AB19: 5986.825 | AC19: 6069.6509 | AD19: 6555.9391 | AE19: 6975.7686 | AF19: 7409.2472 | AG19: 0.058245184
B21: FDSO (m) | C21: =Model!BV209 -> 716.1 | D21: =Model!CA209 -> 707.93493 | E21: =Model!CB209 -> 701.43901 | F21: =Model!CC209 -> 689.62062 | G21: =Model!CD209 -> 670.81054 | H21: =Model!CE209 -> 651.66626 | I21: =IFERROR((H21/C21)^(1/5)-1,"n/m") -> -0.018680762 | N21: FDSO (m) | O21: 716.1 | P21: 707.36985 | Q21: 695.12896 | R21: 679.51135 | S21: 660.57442 | T21: 640.07981 | U21: -0.022195368 | Z21: FDSO (m) | AA21: 716.1 | AB21: 708.5 | AC21: 706.9 | AD21: 701.1576 | AE21: 686.52837 | AF21: 670.50598 | AG21: -0.013071258
B23: Adjusted EPS — Diluted ($) | C23: =Model!BV266 -> 7.7959475 | D23: =Model!CA266 -> 8.525 | E23: =Model!CB266 -> 9.3806276 | F23: =Model!CC266 -> 10.482376 | G23: =Model!CD266 -> 11.700219 | H23: =Model!CE266 -> 13.098059 | I23: =IFERROR((H23/C23)^(1/5)-1,"n/m") -> 0.10934749 | N23: Adjusted EPS — Diluted ($) | O23: 7.7959475 | P23: 8.6 | Q23: 10.021949 | R23: 11.411768 | S23: 13.003472 | T23: 14.871032 | U23: 0.13787469 | Z23: Adjusted EPS — Diluted ($) | AA23: 7.7959475 | AB23: 8.45 | AC23: 8.5862936 | AD23: 9.3501648 | AE23: 10.160933 | AF23: 11.050233 | AG23: 0.072260984
B24: EPS y/y % | D24: =IFERROR(D23/C23-1,"") -> 0.093516857 | E24: =IFERROR(E23/D23-1,"") -> 0.10036687 | F24: =IFERROR(F23/E23-1,"") -> 0.11744932 | G24: =IFERROR(G23/F23-1,"") -> 0.11618005 | H24: =IFERROR(H23/G23-1,"") -> 0.11947127 | N24: EPS y/y % | P24: 0.10313724 | Q24: 0.16534292 | R24: 0.13867754 | S24: 0.13947911 | T24: 0.14362012 | Z24: EPS y/y % | AB24: 0.083896474 | AC24: 0.016129419 | AD24: 0.088964019 | AE24: 0.086711616 | AF24: 0.087521498
B26: P / E (x) — assumed (adjusted EPS) | G26: 23 | H26: 25 | N26: P / E (x) — assumed (adjusted EPS) | S26: 27 | T26: 28 | Z26: P / E (x) — assumed (adjusted EPS) | AD26: 18 | AE26: 18 | AF26: 20
B27: Price Target ($) | G27: =G26*G23 -> 269.10503 | H27: =H26*H23 -> 327.45147 | N27: Price Target ($) | S27: =S26*S23 -> 351.09373 | T27: =T26*T23 -> 416.38889 | Z27: Price Target ($) | AD27: =AD26*AD23 -> 168.30297 | AE27: =AE26*AE23 -> 182.89679 | AF27: =AF26*AF23 -> 221.00465
B28: Upside / (Downside) vs current | G28: =IFERROR(G27/$K$2-1,"") -> 0.21651387 | H28: =IFERROR(H27/$K$2-1,"") -> 0.48027426 | N28: Upside / (Downside) vs current | S28: =IFERROR(S27/$K$2-1,"") -> 0.58715128 | T28: =IFERROR(T27/$K$2-1,"") -> 0.88232399 | Z28: Upside / (Downside) vs current | AD28: =IFERROR(AD27/$K$2-1,"") -> -0.23917108 | AE28: =IFERROR(AE27/$K$2-1,"") -> -0.17319837 | AF28: =IFERROR(AF27/$K$2-1,"") -> -0.00092828288
B29: IRR (to Dec-Y-1) | G29: =IFERROR((G27/$K$2)^(1/((DATE(2029-1,12,31)-$K$3)/365.25))-1,"") -> 0.09157264 | H29: =IFERROR((H27/$K$2)^(1/((DATE(2030-1,12,31)-$K$3)/365.25))-1,"") -> 0.12885319 | N29: IRR (to Dec-Y-1) | S29: =IFERROR((S27/$K$2)^(1/((DATE(2029-1,12,31)-$K$3)/365.25))-1,"") -> 0.22938784 | T29: =IFERROR((T27/$K$2)^(1/((DATE(2030-1,12,31)-$K$3)/365.25))-1,"") -> 0.21585939 | Z29: IRR (to Dec-Y-1) | AD29: =IFERROR((AD27/$K$2)^(1/((DATE(2028-1,12,31)-$K$3)/365.25))-1,"") -> -0.19858351 | AE29: =IFERROR((AE27/$K$2)^(1/((DATE(2029-1,12,31)-$K$3)/365.25))-1,"") -> -0.081512531 | AF29: =IFERROR((AF27/$K$2)^(1/((DATE(2030-1,12,31)-$K$3)/365.25))-1,"") -> -0.00028694088
B31: Free Cash Flow | C31: =Model!BV325 -> 5293 | D31: =Model!CA325 -> 6480.4482 | E31: =Model!CB325 -> 6524.3547 | F31: =Model!CC325 -> 7169.0648 | G31: =Model!CD325 -> 7801.1436 | H31: =Model!CE325 -> 8476.1766 | I31: =IFERROR((H31/C31)^(1/5)-1,"n/m") -> 0.098751852 | N31: Free Cash Flow | O31: 5293 | P31: 6538.2476 | Q31: 6940.5335 | R31: 7718.3381 | S31: 8573.8501 | T31: 9498.7526 | U31: 0.12406891 | Z31: Free Cash Flow | AA31: 5293 | AB31: 6422.5575 | AC31: 5975.7093 | AD31: 6474.5105 | AE31: 6901.4871 | AF31: 7317.9185 | AG31: 0.066932969
B32: FCF % | C32: =IFERROR(C31/C9,"") -> 0.21544285 | D32: =IFERROR(D31/D9,"") -> 0.24455981 | E32: =IFERROR(E31/E9,"") -> 0.22508825 | F32: =IFERROR(F31/F9,"") -> 0.23212451 | G32: =IFERROR(G31/G9,"") -> 0.23587625 | H32: =IFERROR(H31/H9,"") -> 0.23921106 | J32: =IFERROR(AVERAGE(Model!C329,Model!D329,Model!E329,Model!F329,Model!G329,Model!H329,Model!I329,Model!N329,Model!S329,Model!X329,Model!AC329,Model!AH329,Model!AM329,Model!AR329,Model!AW329,Model!BB329,Model!BG329,Model!BL329,Model!BQ329,Model!BV329),"") -> 0.18309383 | K32: =IFERROR(MIN(Model!C329,Model!D329,Model!E329,Model!F329,Model!G329,Model!H329,Model!I329,Model!N329,Model!S329,Model!X329,Model!AC329,Model!AH329,Model!AM329,Model!AR329,Model!AW329,Model!BB329,Model!BG329,Model!BL329,Model!BQ329,Model!BV329),"") -> 0.13123056 | L32: =IFERROR(MAX(Model!C329,Model!D329,Model!E329,Model!F329,Model!G329,Model!H329,Model!I329,Model!N329,Model!S329,Model!X329,Model!AC329,Model!AH329,Model!AM329,Model!AR329,Model!AW329,Model!BB329,Model!BG329,Model!BL329,Model!BQ329,Model!BV329),"") -> 0.2768457 | N32: FCF % | O32: 0.21544285 | P32: 0.2456025 | Q32: 0.23366869 | R32: 0.23825114 | S32: 0.24175567 | T32: 0.24480868 | V32: 0.18309383 | W32: 0.13123056 | X32: 0.2768457 | Z32: FCF % | AA32: 0.21544285 | AB32: 0.24350395 | AC32: 0.21214247 | AD32: 0.22154553 | AE32: 0.22630846 | AF32: 0.22968462 | AH32: 0.18309383 | AI32: 0.13123056 | AJ32: 0.2768457
B33: FCF / share ($) | C33: =IFERROR(C31/C21,"") -> 7.3914258 | D33: =IFERROR(D31/D21,"") -> 9.1540168 | E33: =IFERROR(E31/E21,"") -> 9.3013855 | F33: =IFERROR(F31/F21,"") -> 10.395665 | G33: =IFERROR(G31/G21,"") -> 11.629429 | H33: =IFERROR(H31/H21,"") -> 13.006929 | N33: FCF / share ($) | O33: 7.3914258 | P33: 9.2430397 | Q33: 9.9845265 | R33: 11.358659 | S33: 12.979385 | T33: 14.83995 | Z33: FCF / share ($) | AA33: 7.3914258 | AB33: 9.0650071 | AC33: 8.4534011 | AD33: 9.2340303 | AE33: 10.052734 | AF33: 10.914024
B34: FCF Yield (on PT) | F34: =IFERROR(F33/F$27,"") | G34: =IFERROR(G33/G$27,"") -> 0.043215205 | H34: =IFERROR(H33/H$27,"") -> 0.039721699 | N34: FCF Yield (on PT) | R34: =IFERROR(R33/R$27,"") | S34: =IFERROR(S33/S$27,"") -> 0.036968434 | T34: =IFERROR(T33/T$27,"") -> 0.035639641 | Z34: FCF Yield (on PT) | AD34: =IFERROR(AD33/AD$27,"") -> 0.054865523 | AE34: =IFERROR(AE33/AE$27,"") -> 0.054963972 | AF34: =IFERROR(AF33/AF$27,"") -> 0.049383685
B35: Adjusted EBITDA — pro forma (2026E incl. Masimo full year) | C35: =Model!BV231 -> 7689 | D35: =Model!CA231 -> 8604.8611 | E35: =Model!CB231 -> 9261.6202 | F35: =Model!CC231 -> 10055.048 | G35: =Model!CD231 -> 10953.254 | H35: =Model!CE231 -> 11919.924 | I35: =IFERROR((H35/C35)^(1/5)-1,"n/m") -> 0.091643228 | N35: Adjusted EBITDA — pro forma (2026E incl. Masimo full year) | O35: 7689 | P35: 8666.8878 | Q35: 9760.6638 | R35: 10823.16 | S35: 12026.382 | T35: 13337.556 | U35: 0.11645514 | Z35: Adjusted EBITDA — pro forma (2026E incl. Masimo full year) | AA35: 7689 | AB35: 8542.7323 | AC35: 8610.4472 | AD35: 9120.7153 | AE35: 9703.0939 | AF35: 10319.184 | AG35: 0.060608484
B36: Adjusted EBITDA (pro forma) % of sales | C36: =IFERROR(C35/C9,"") -> 0.31296809 | D36: =IFERROR(D35/D9,"") -> 0.32473111 | E36: =IFERROR(E35/E9,"") -> 0.31952307 | F36: =IFERROR(F35/F9,"") -> 0.32556869 | G36: =IFERROR(G35/G9,"") -> 0.33118382 | H36: =IFERROR(H35/H9,"") -> 0.33639903 | J36: =IFERROR(AVERAGE(Model!C286,Model!D286,Model!E286,Model!F286,Model!G286,Model!H286,Model!I286,Model!N286,Model!S286,Model!X286,Model!AC286,Model!AH286,Model!AM286,Model!AR286,Model!AW286,Model!BB286,Model!BG286,Model!BL286,Model!BQ286,Model!BV286),"") -> 0.24791445 | K36: =IFERROR(MIN(Model!C286,Model!D286,Model!E286,Model!F286,Model!G286,Model!H286,Model!I286,Model!N286,Model!S286,Model!X286,Model!AC286,Model!AH286,Model!AM286,Model!AR286,Model!AW286,Model!BB286,Model!BG286,Model!BL286,Model!BQ286,Model!BV286),"") -> 0.17942047 | L36: =IFERROR(MAX(Model!C286,Model!D286,Model!E286,Model!F286,Model!G286,Model!H286,Model!I286,Model!N286,Model!S286,Model!X286,Model!AC286,Model!AH286,Model!AM286,Model!AR286,Model!AW286,Model!BB286,Model!BG286,Model!BL286,Model!BQ286,Model!BV286),"") -> 0.36666291 | N36: Adjusted EBITDA (pro forma) % of sales | O36: 0.31296809 | P36: 0.32556266 | Q36: 0.32861473 | R36: 0.3340914 | S36: 0.33910625 | T36: 0.34374507 | V36: 0.24791445 | W36: 0.17942047 | X36: 0.36666291 | Z36: Adjusted EBITDA (pro forma) % of sales | AA36: 0.31296809 | AB36: 0.32388795 | AC36: 0.30567778 | AD36: 0.31209366 | AE36: 0.31817667 | AF36: 0.32388415 | AH36: 0.24791445 | AI36: 0.17942047 | AJ36: 0.36666291
B38: Net Debt | C38: =Model!BV459 -> 13803 | D38: =Model!CA459 -> 21167.888 | E38: =Model!CB459 -> 18523.24 | F38: =Model!CC459 -> 20110.096 | G38: =Model!CD459 -> 21906.509 | H38: =Model!CE459 -> 23839.848 | N38: Net Debt | O38: 13803 | P38: 21609.184 | Q38: 21961.494 | R38: 24352.111 | S38: 27059.36 | T38: 30009.501 | Z38: Net Debt | AA38: 13803 | AB38: 20726.682 | AC38: 16119.485 | AD38: 15961.252 | AE38: 16980.414 | AF38: 18058.571
B39: Net Debt / Adjusted EBITDA (x) | C39: =IFERROR(C38/C35,"") -> 1.7951619 | D39: =IFERROR(D38/D35,"") -> 2.4599918 | E39: =IFERROR(E38/E35,"") -> 2 | F39: =IFERROR(F38/F35,"") -> 2 | G39: =IFERROR(G38/G35,"") -> 2 | H39: =IFERROR(H38/H35,"") -> 2 | N39: Net Debt / Adjusted EBITDA (x) | O39: 1.7951619 | P39: 2.4933038 | Q39: 2.25 | R39: 2.25 | S39: 2.25 | T39: 2.25 | Z39: Net Debt / Adjusted EBITDA (x) | AA39: 1.7951619 | AB39: 2.4262357 | AC39: 1.8720845 | AD39: 1.75 | AE39: 1.75 | AF39: 1.75
B40: Share repurchases ($m) | D40: =Model!CA338 -> 500 | E40: =Model!CB338 -> 1515.1735 | F40: =Model!CC338 -> 5276.841 | G40: =Model!CD338 -> 5524.1077 | H40: =Model!CE338 -> 6235.2578 | N40: Share repurchases ($m) | P40: 1000 | Q40: 3432.2872 | R40: 5149.9332 | S40: 5728.6451 | T40: 6799.4979 | AB40: 0 | AC40: 0 | AD40: 3820.429 | AE40: 4816.5082 | AF40: 5181.9393
B41: Implied avg buyback price ($) | D41: =Model!CA337 -> 221.21 | E41: =Model!CB337 -> 236.6947 | F41: =Model!CC337 -> 253.26333 | G41: =Model!CD337 -> 270.99176 | H41: =Model!CE337 -> 289.96119 | N41: Implied avg buyback price ($) | P41: 221.21 | Q41: 236.6947 | R41: 253.26333 | S41: 270.99176 | T41: 289.96119 | AB41: 221.21 | AC41: 236.6947 | AD41: 253.26333 | AE41: 270.99176 | AF41: 289.96119
B42: Shares repurchased (m) | D42: =Model!CA339 -> 2.2602956 | E42: =Model!CB339 -> 6.4013832 | F42: =Model!CC339 -> 20.835393 | G42: =Model!CD339 -> 20.384781 | H42: =Model!CE339 -> 21.503767 | N42: Shares repurchased (m) | P42: 4.5205913 | Q42: 14.500904 | R42: 20.334303 | S42: 21.139555 | T42: 23.449683 | AB42: 0 | AC42: 0 | AD42: 15.084809 | AE42: 17.773633 | AF42: 17.871148
B44: ROIC | C44: =Model!BV442 -> 0.067196955 | D44: =Model!CA442 -> 0.062438184 | E44: =Model!CB442 -> 0.071538933 | F44: =Model!CC442 -> 0.07824088 | G44: =Model!CD442 -> 0.085092043 | H44: =Model!CE442 -> 0.094192943 | J44: =IFERROR(AVERAGE(Model!C442,Model!D442,Model!E442,Model!F442,Model!G442,Model!H442,Model!I442,Model!N442,Model!S442,Model!X442,Model!AC442,Model!AH442,Model!AM442,Model!AR442,Model!AW442,Model!BB442,Model!BG442,Model!BL442,Model!BQ442,Model!BV442),"") -> 0.090953744 | K44: =IFERROR(MIN(Model!C442,Model!D442,Model!E442,Model!F442,Model!G442,Model!H442,Model!I442,Model!N442,Model!S442,Model!X442,Model!AC442,Model!AH442,Model!AM442,Model!AR442,Model!AW442,Model!BB442,Model!BG442,Model!BL442,Model!BQ442,Model!BV442),"") -> 0.054413349 | L44: =IFERROR(MAX(Model!C442,Model!D442,Model!E442,Model!F442,Model!G442,Model!H442,Model!I442,Model!N442,Model!S442,Model!X442,Model!AC442,Model!AH442,Model!AM442,Model!AR442,Model!AW442,Model!BB442,Model!BG442,Model!BL442,Model!BQ442,Model!BV442),"") -> 0.13199238 | N44: ROIC | O44: 0.067196955 | P44: 0.063086329 | Q44: 0.075131662 | R44: 0.082326744 | S44: 0.089739649 | T44: 0.099367 | V44: 0.090953744 | W44: 0.054413349 | X44: 0.13199238 | Z44: ROIC | AA44: 0.067196955 | AB44: 0.061789042 | AC44: 0.065606069 | AD44: 0.070825569 | AE44: 0.076074877 | AF44: 0.083529713 | AH44: 0.090953744 | AI44: 0.054413349 | AJ44: 0.13199238
B45: RONTA | C45: =Model!BV453 -> 0.28411923 | D45: =Model!CA453 -> 0.33903964 | E45: =Model!CB453 -> 0.36404012 | F45: =Model!CC453 -> 0.39871872 | G45: =Model!CD453 -> 0.42368431 | H45: =Model!CE453 -> 0.45925462 | J45: =IFERROR(AVERAGE(Model!C453,Model!D453,Model!E453,Model!F453,Model!G453,Model!H453,Model!I453,Model!N453,Model!S453,Model!X453,Model!AC453,Model!AH453,Model!AM453,Model!AR453,Model!AW453,Model!BB453,Model!BG453,Model!BL453,Model!BQ453,Model!BV453),"") -> 0.3775129 | K45: =IFERROR(MIN(Model!C453,Model!D453,Model!E453,Model!F453,Model!G453,Model!H453,Model!I453,Model!N453,Model!S453,Model!X453,Model!AC453,Model!AH453,Model!AM453,Model!AR453,Model!AW453,Model!BB453,Model!BG453,Model!BL453,Model!BQ453,Model!BV453),"") -> 0.099371425 | L45: =IFERROR(MAX(Model!C453,Model!D453,Model!E453,Model!F453,Model!G453,Model!H453,Model!I453,Model!N453,Model!S453,Model!X453,Model!AC453,Model!AH453,Model!AM453,Model!AR453,Model!AW453,Model!BB453,Model!BG453,Model!BL453,Model!BQ453,Model!BV453),"") -> 0.61569755 | N45: RONTA | O45: 0.28411923 | P45: 0.34272148 | Q45: 0.39974001 | R45: 0.43177506 | S45: 0.46513323 | T45: 0.50934116 | V45: 0.3775129 | W45: 0.099371425 | X45: 0.61569755 | Z45: RONTA | AA45: 0.28411923 | AB45: 0.33535578 | AC45: 0.28374445 | AD45: 0.29444058 | AE45: 0.32648095 | AF45: 0.37230208 | AH45: 0.3775129 | AI45: 0.099371425 | AJ45: 0.61569755
B47: Implied Market Cap (USDm) | F47: =F27*F21 -> 0 | G47: =G27*G21 -> 180518.49 | H47: =H27*H21 -> 213389.08 | N47: Implied Market Cap (USDm) | R47: =R27*R21 -> 0 | S47: =S27*S21 -> 231923.54 | T47: =T27*T21 -> 266522.12 | Z47: Implied Market Cap (USDm) | AD47: =AD27*AD21 -> 118006.9 | AE47: =AE27*AE21 -> 125563.83 | AF47: =AF27*AF21 -> 148184.94
B48: (+) Net Debt & NCI | F48: =F38+Model!CC374 -> 20121.096 | G48: =G38+Model!CD374 -> 21917.509 | H48: =H38+Model!CE374 -> 23850.848 | N48: (+) Net Debt & NCI | R48: =R38+Model!CC374 -> 24363.111 | S48: =S38+Model!CD374 -> 27070.36 | T48: =T38+Model!CE374 -> 30020.501 | Z48: (+) Net Debt & NCI | AD48: =AD38+Model!CC374 -> 15972.252 | AE48: =AE38+Model!CD374 -> 16991.414 | AF48: =AF38+Model!CE374 -> 18069.571
B49: Implied Enterprise Value (USDm) | F49: =F47+F48 -> 20121.096 | G49: =G47+G48 -> 202436 | H49: =H47+H48 -> 237239.92 | N49: Implied Enterprise Value (USDm) | R49: =R47+R48 -> 24363.111 | S49: =S47+S48 -> 258993.9 | T49: =T47+T48 -> 296542.62 | Z49: Implied Enterprise Value (USDm) | AD49: =AD47+AD48 -> 133979.15 | AE49: =AE47+AE48 -> 142555.25 | AF49: =AF47+AF48 -> 166254.51
B50: Implied EV / Adjusted EBITDA (x) | F50: =IFERROR(F49/F35,"") -> 2.001094 | G50: =IFERROR(G49/G35,"") -> 18.481813 | H50: =IFERROR(H49/H35,"") -> 19.902805 | N50: Implied EV / Adjusted EBITDA (x) | R50: =IFERROR(R49/R35,"") -> 2.2510163 | S50: =IFERROR(S49/S35,"") -> 21.535479 | T50: =IFERROR(T49/T35,"") -> 22.233655 | Z50: Implied EV / Adjusted EBITDA (x) | AD50: =IFERROR(AD49/AD35,"") -> 14.689545 | AE50: =IFERROR(AE49/AE35,"") -> 14.691731 | AF50: =IFERROR(AF49/AF35,"") -> 16.111208

Sheet DCF
B2: DCF VALUATION — DANAHER CORPORATION (DHR)
B4: 1. WACC BUILD
B5: Risk-free rate (US 10Y govt) | C5: 0.0425 | D5: Assumption (~US 10Y Treasury yield); update to market
B6: Equity risk premium | C6: 0.05 | D6: US implied ERP ~4.5–5.5% (Damodaran)
B7: Levered beta | C7: 0.95 | D7: Life-science tools & diagnostics peers (TMO, A, RVTY, WAT, ABT diagnostics) ~0.8–1.1; ~80% recurring revenue (consumables, service) dampens cyclicality
B8: Cost of equity | C8: =C5+C7*C6 -> 0.09
B9: Pre-tax cost of debt | C9: 0.045 | D9: Investment grade (A- / A3); 2026 Masimo financing: €3.0bn notes 3.25–4.0% (floating 2028), CHF 1.65–2.51% private placement; USD marginal cost ~4.5–5.0%
B10: Tax rate | C10: 0.17 | D10: Model 2027E+ adjusted effective tax rate (FY26 guidance ~17%)
B11: After-tax cost of debt | C11: =C9*(1-C10) -> 0.03735
B12: Target D/V | C12: 0.15 | D12: Net debt ~$22bn at 26-Jun-26 (post Masimo) vs ~$156bn market cap ($221 × ~705m shares) → ~12–15% D/V
B13: WACC | C13: =C8*(1-C12)+C11*C12 -> 0.0821025
B15: Valuation date (live) | C15: =TODAY() -> 46301 | D15: Periods = (Dec-31-Year − today) / 365.25; cash flows assumed at year-end
B16: 2. UNLEVERED FREE CASH FLOW BUILD (USDm)
D17: 2026E | E17: 2027E | F17: 2028E | G17: 2029E | H17: 2030E | I17: 2031E | J17: 2032E | K17: 2033E | L17: 2034E | M17: 2035E | N17: Terminal | P17: CAGR 26–30E | Q17: CAGR 26–35E
B18: Adjusted operating profit (before acquired-intangible amortization) less other operating profit adjustments | D18: =Model!CA243-Model!CA241 -> 7417.7075 | E18: =Model!CB243-Model!CB241 -> 8363.0615 | F18: =Model!CC243-Model!CC241 -> 9097.6262 | G18: =Model!CD243-Model!CD241 -> 9927.9902 | H18: =Model!CE243-Model!CE241 -> 10821.474 | I18: =H18*(1+I$26) -> 11470.762 | J18: =I18*(1+J$26) -> 12115.992 | K18: =J18*(1+K$26) -> 12752.082 | L18: =K18*(1+L$26) -> 13373.746 | M18: =L18*(1+M$26) -> 13975.565 | P18: =(H18/D18)^(1/(COLUMNS(D18:H18)-1))-1 -> 0.099016404 | Q18: =(M18/D18)^(1/(COLUMNS(D18:M18)-1))-1 -> 0.07291824
B19: × (1 − tax rate) | D19: =1-$C$10 -> 0.83 | E19: =1-$C$10 -> 0.83 | F19: =1-$C$10 -> 0.83 | G19: =1-$C$10 -> 0.83 | H19: =1-$C$10 -> 0.83 | I19: =1-$C$10 -> 0.83 | J19: =1-$C$10 -> 0.83 | K19: =1-$C$10 -> 0.83 | ... M19: =1-$C$10 -> 0.83
B20: NOPAT | D20: =D18*D19 -> 6156.6972 | E20: =E18*E19 -> 6941.3411 | F20: =F18*F19 -> 7551.0298 | G20: =G18*G19 -> 8240.2319 | H20: =H18*H19 -> 8981.8231 | I20: =I18*I19 -> 9520.7325 | J20: =J18*J19 -> 10056.274 | K20: =K18*K19 -> 10584.228 | ... M20: =M18*M19 -> 11599.719
B21: plus depreciation (acquired-intangible amortization is excluded from EBIT above, as in adjusted EPS) | D21: =Model!CA170 -> 843.80198 | E21: =Model!CB170 -> 898.55866 | F21: =Model!CC170 -> 957.42155 | G21: =Model!CD170 -> 1025.2641 | H21: =Model!CE170 -> 1098.4504 | I21: =H21*(1+I$26) -> 1164.3574 | J21: =I21*(1+J$26) -> 1229.8525 | K21: =J21*(1+K$26) -> 1294.4198 | L21: =K21*(1+L$26) -> 1357.5227 | M21: =L21*(1+M$26) -> 1418.6112
B22: − Capex (PP&E) and acquisitions (M&A lever 2027E–30E; Masimo / StatLab in opening invested capital) | D22: =Model!CA303 -> -1150 | E22: =Model!CB303+Model!CB305 -> -2304.3594 | F22: =Model!CC303+Model!CC305 -> -3389.8055 | G22: =Model!CD303+Model!CD305 -> -3988.2866 | H22: =Model!CE303+Model!CE305 -> -4094.5247 | I22: =Model!CE303*(1+I$26) -> -1690.1962 | J22: =I22*(1+J$26) -> -1785.2698 | K22: =J22*(1+K$26) -> -1878.9964 | L22: =K22*(1+L$26) -> -1970.5975 | M22: =L22*(1+M$26) -> -2059.2744
B23: − Δ Working capital (CF statement) | D23: =Model!CA301 -> 380.24629 | E23: =Model!CB301 -> 58.672073 | F23: =Model!CC301 -> 51.055372 | G23: =Model!CD301 -> 56.943613 | H23: =Model!CE301 -> 73.76529 | I23: =H23*(1+I$26) -> 78.191207 | J23: =I23*(1+J$26) -> 82.589463 | K23: =J23*(1+K$26) -> 86.92541 | L23: =K23*(1+L$26) -> 91.163023 | M23: =L23*(1+M$26) -> 95.265359
B24: Unlevered FCF | D24: =D20+D21+D22+D23 -> 6230.7455 | E24: =E20+E21+E22+E23 -> 5594.2124 | F24: =F20+F21+F22+F23 -> 5169.7012 | G24: =G20+G21+G22+G23 -> 5334.153 | H24: =H20+H21+H22+H23 -> 6059.514 | I24: =I20+I21+I22+I23 -> 9073.0849 | J24: =J20+J21+J22+J23 -> 9583.4459 | K24: =K20+K21+K22+K23 -> 10086.577 | ... M24: =M20+M21+M22+M23 -> 11054.321 | N24: =M24*(1+$C$27) -> 11441.222 | P24: =(H24/D24)^(1/(COLUMNS(D24:H24)-1))-1 -> -0.0069423865 | Q24: =(M24/D24)^(1/(COLUMNS(D24:M24)-1))-1 -> 0.065775625
B25: Terminal Value (Gordon Growth) | N25: =N24/($C$13-$C$27) -> 242900.53
B26: Fade-period growth (2031E–35E; 6% → 4.5% linear) | I26: 0.06 | J26: =I26+($M$26-$I$26)/4 -> 0.05625 | K26: =J26+($M$26-$I$26)/4 -> 0.0525 | L26: =K26+($M$26-$I$26)/4 -> 0.04875 | M26: 0.045
B27: Terminal growth rate | C27: 0.035
B29: Discount period (years) | D29: =(DATE(2026,12,31)-$C$15)/365.25 -> 0.23545517 | E29: =(DATE(2027,12,31)-$C$15)/365.25 -> 1.2347707 | F29: =(DATE(2028,12,31)-$C$15)/365.25 -> 2.2368241 | G29: =(DATE(2029,12,31)-$C$15)/365.25 -> 3.2361396 | H29: =(DATE(2030,12,31)-$C$15)/365.25 -> 4.2354552 | I29: =(DATE(2031,12,31)-$C$15)/365.25 -> 5.2347707 | J29: =(DATE(2032,12,31)-$C$15)/365.25 -> 6.2368241 | K29: =(DATE(2033,12,31)-$C$15)/365.25 -> 7.2361396 | L29: =(DATE(2034,12,31)-$C$15)/365.25 -> 8.2354552 | M29: =(DATE(2035,12,31)-$C$15)/365.25 -> 9.2347707 | N29: =M29 -> 9.2347707
B30: Discount factor | D30: =1/(1+$C$13)^D29 -> 0.98159272 | E30: =1/(1+$C$13)^E29 -> 0.9071652 | F30: =1/(1+$C$13)^F29 -> 0.83819992 | G30: =1/(1+$C$13)^G29 -> 0.77464491 | H30: =1/(1+$C$13)^H29 -> 0.71590884 | I30: =1/(1+$C$13)^I29 -> 0.66162633 | J30: =1/(1+$C$13)^J29 -> 0.61132762 | K30: =1/(1+$C$13)^K29 -> 0.56497479 | ... N30: =1/(1+$C$13)^N29 -> 0.48254651
B31: PV of UFCF | D31: =D24*D30 -> 6116.0544 | E31: =E24*E30 -> 5074.8749 | F31: =F24*F30 -> 4333.2432 | G31: =G24*G30 -> 4132.0745 | H31: =H24*H30 -> 4338.0597 | I31: =I24*I30 -> 6002.9919 | J31: =J24*J30 -> 5858.6251 | K31: =K24*K30 -> 5698.6616 | ... M31: =M24*M30 -> 5334.2239 | N31: =N25*N30 -> 117210.8
D32: Danaher's adjusted operating profit expenses stock-based compensation and excludes ~$1.9bn p.a. of acquired-intangible amortization (largely not tax-deductible, finite-lived): NOPAT is taxed on adjusted operating profit and only depreciation is added back, so the terminal value carries no perpetual amortization add-back. Masimo ($9.8bn, closed Jun-26) and StatLab (assumed ~$2.0bn) consideration is excluded from 2026E UFCF and added to opening invested capital.
B33: IMPLIED ROIC — invested capital roll-forward (USDm)
B34: Opening invested capital | D34: =Model!BV439+Model!BX397+Model!BX398+Model!CA91 -> 78257 | E34: =D38 -> 78182.952 | F34: =E38 -> 79530.08 | G34: =F38 -> 81911.409 | H34: =G38 -> 84817.488 | I34: =H38 -> 87739.797 | J34: =I38 -> 88187.444 | K34: =J38 -> 88660.272 | L34: =K38 -> 89157.924 | M34: =L38 -> 89679.835
B35: plus Capex and acquisitions | D35: =-D22 -> 1150 | E35: =-E22 -> 2304.3594 | F35: =-F22 -> 3389.8055 | G35: =-G22 -> 3988.2866 | H35: =-H22 -> 4094.5247 | I35: =-I22 -> 1690.1962 | J35: =-J22 -> 1785.2698 | K35: =-K22 -> 1878.9964 | ... M35: =-M22 -> 2059.2744
B36: less depreciation | D36: =-D21 -> -843.80198 | E36: =-E21 -> -898.55866 | F36: =-F21 -> -957.42155 | G36: =-G21 -> -1025.2641 | H36: =-H21 -> -1098.4504 | I36: =-I21 -> -1164.3574 | J36: =-J21 -> -1229.8525 | K36: =-K21 -> -1294.4198 | ... M36: =-M21 -> -1418.6112
B37: plus Δ Working capital investment | D37: =-D23 -> -380.24629 | E37: =-E23 -> -58.672073 | F37: =-F23 -> -51.055372 | G37: =-G23 -> -56.943613 | H37: =-H23 -> -73.76529 | I37: =-I23 -> -78.191207 | J37: =-J23 -> -82.589463 | K37: =-K23 -> -86.92541 | ... M37: =-M23 -> -95.265359
B38: Closing invested capital | D38: =SUM(D34:D37) -> 78182.952 | E38: =SUM(E34:E37) -> 79530.08 | F38: =SUM(F34:F37) -> 81911.409 | G38: =SUM(G34:G37) -> 84817.488 | H38: =SUM(H34:H37) -> 87739.797 | I38: =SUM(I34:I37) -> 88187.444 | J38: =SUM(J34:J37) -> 88660.272 | K38: =SUM(K34:K37) -> 89157.924 | ... M38: =SUM(M34:M37) -> 90225.233
B39: NOPAT (row 20) | D39: =D20 -> 6156.6972 | E39: =E20 -> 6941.3411 | F39: =F20 -> 7551.0298 | G39: =G20 -> 8240.2319 | H39: =H20 -> 8981.8231 | I39: =I20 -> 9520.7325 | J39: =J20 -> 10056.274 | K39: =K20 -> 10584.228 | ... M39: =M20 -> 11599.719
B40: Implied ROIC (NOPAT / avg. invested capital) | D40: =IFERROR(D39/AVERAGE(D34,D38),"") -> 0.078710038 | E40: =IFERROR(E39/AVERAGE(E34,E38),"") -> 0.088024952 | F40: =IFERROR(F39/AVERAGE(F34,F38),"") -> 0.093545096 | G40: =IFERROR(G39/AVERAGE(G34,G38),"") -> 0.098845876 | H40: =IFERROR(H39/AVERAGE(H34,H38),"") -> 0.10410251 | I40: =IFERROR(I39/AVERAGE(I34,I38),"") -> 0.10823489 | J40: =IFERROR(J39/AVERAGE(J34,J38),"") -> 0.11372806 | K40: =IFERROR(K39/AVERAGE(K34,K38),"") -> 0.1190455 | ... M40: =IFERROR(M39/AVERAGE(M34,M38),"") -> 0.12895377
B41: Reinvestment rate (net investment / NOPAT) | D41: =IFERROR(SUM(D35:D37)/D39,"") -> -0.012027272 | E41: =IFERROR(SUM(E35:E37)/E39,"") -> 0.19407325 | F41: =IFERROR(SUM(F35:F37)/F39,"") -> 0.31536474 | G41: =IFERROR(SUM(G35:G37)/G39,"") -> 0.35266955 | H41: =IFERROR(SUM(H35:H37)/H39,"") -> 0.32535812 | I41: =IFERROR(SUM(I35:I37)/I39,"") -> 0.047018191 | J41: =IFERROR(SUM(J35:J37)/J39,"") -> 0.047018191 | K41: =IFERROR(SUM(K35:K37)/K39,"") -> 0.047018191 | ... M41: =IFERROR(SUM(M35:M37)/M39,"") -> 0.047018191
B42: Implied terminal RONIC (g / reinvestment rate) | N42: =IFERROR($C$27/M41,"") -> 0.74439274
D43: Opening IC = Model 2025A book invested capital (equity + net debt) + Masimo consideration (cash $9,843m + replacement awards $45m) + StatLab assumed price, rolled forward with DCF net investment (capex + M&A − depreciation + ΔWC). Terminal incremental ROIC = g / reinvestment rate.
B44: 3. VALUATION SUMMARY
B45: Sum of PV (explicit + fade) | C45: =SUM(D31:M31) -> 52412.125
B46: PV of Terminal Value | C46: =N31 -> 117210.8
B47: Enterprise Value | C47: =C45+C46 -> 169622.93
B48: Less: Net debt + NCI (Model 2026E YE, post Masimo & StatLab) | C48: =Model!CA459+Model!CA374 -> 21178.888 | D48: DHR-specific: NCI immaterial (~$11m); net debt includes the Masimo financing (euro CP, €/CHF notes) and the assumed StatLab funding.
B49: Equity Value | C49: =C47-C48 -> 148444.04
B50: Diluted shares (m, Model 2026E period end) | C50: =Model!CA465 -> 703.7397
B51: Implied share price ($) | C51: =C49/C50 -> 210.936
B52: Current share price ($) | C52: =Model!CA464 -> 221.21
B53: Implied upside / (downside) | C53: =C51/C52-1 -> -0.046444551
B54: Required discount to DCF value for target IRR | C54: =1-((1+C13)/(1+H54))^H55 -> 0.1668721 | D54: vs. current | E54: Target IRR | H54: 0.15
B55: Max entry price for target IRR ($) | C55: =C51*(1-C54) -> 175.73667 | D55: =C55/C52-1 -> -0.20556635 | E55: Years for discount to close | H55: 3
B58: 4. SENSITIVITY: IMPLIED PRICE ($) — WACC × Terminal Growth
D60: WACC →
B61: Terminal growth ↓ | D61: =F61-0.01 -> 0.0721025 | E61: =F61-0.005 -> 0.0771025 | F61: =$C$13 -> 0.0821025 | G61: =F61+0.005 -> 0.0871025 | H61: =F61+0.01 -> 0.0921025
B62: =B64-0.01 -> 0.025 | D62: {=IFERROR((SUMPRODUCT($D$24:$M$24/(1+D$61)^$D$29:$M$29)+($M$24*(1+$B62)/(D$61-$B62))/(1+D$61)^$M$29-$C$48)/$C$50,"")} -> 227.53643 | E62: {=IFERROR((SUMPRODUCT($D$24:$M$24/(1+E$61)^$D$29:$M$29)+($M$24*(1+$B62)/(E$61-$B62))/(1+E$61)^$M$29-$C$48)/$C$50,"")} -> 201.70521 | F62: {=IFERROR((SUMPRODUCT($D$24:$M$24/(1+F$61)^$D$29:$M$29)+($M$24*(1+$B62)/(F$61-$B62))/(1+F$61)^$M$29-$C$48)/$C$50,"")} -> 180.44101 | G62: {=IFERROR((SUMPRODUCT($D$24:$M$24/(1+G$61)^$D$29:$M$29)+($M$24*(1+$B62)/(G$61-$B62))/(1+G$61)^$M$29-$C$48)/$C$50,"")} -> 162.63941 | H62: {=IFERROR((SUMPRODUCT($D$24:$M$24/(1+H$61)^$D$29:$M$29)+($M$24*(1+$B62)/(H$61-$B62))/(1+H$61)^$M$29-$C$48)/$C$50,"")} -> 147.52522
B63: =B64-0.005 -> 0.03 | D63: {=IFERROR((SUMPRODUCT($D$24:$M$24/(1+D$61)^$D$29:$M$29)+($M$24*(1+$B63)/(D$61-$B63))/(1+D$61)^$M$29-$C$48)/$C$50,"")} -> 249.85925 | E63: {=IFERROR((SUMPRODUCT($D$24:$M$24/(1+E$61)^$D$29:$M$29)+($M$24*(1+$B63)/(E$61-$B63))/(1+E$61)^$M$29-$C$48)/$C$50,"")} -> 219.06555 | F63: {=IFERROR((SUMPRODUCT($D$24:$M$24/(1+F$61)^$D$29:$M$29)+($M$24*(1+$B63)/(F$61-$B63))/(1+F$61)^$M$29-$C$48)/$C$50,"")} -> 194.22528 | G63: {=IFERROR((SUMPRODUCT($D$24:$M$24/(1+G$61)^$D$29:$M$29)+($M$24*(1+$B63)/(G$61-$B63))/(1+G$61)^$M$29-$C$48)/$C$50,"")} -> 173.77329 | H63: {=IFERROR((SUMPRODUCT($D$24:$M$24/(1+H$61)^$D$29:$M$29)+($M$24*(1+$B63)/(H$61-$B63))/(1+H$61)^$M$29-$C$48)/$C$50,"")} -> 156.64851
B64: =$C$27 -> 0.035 | D64: {=IFERROR((SUMPRODUCT($D$24:$M$24/(1+D$61)^$D$29:$M$29)+($M$24*(1+$B64)/(D$61-$B64))/(1+D$61)^$M$29-$C$48)/$C$50,"")} -> 278.1986 | E64: {=IFERROR((SUMPRODUCT($D$24:$M$24/(1+E$61)^$D$29:$M$29)+($M$24*(1+$B64)/(E$61-$B64))/(1+E$61)^$M$29-$C$48)/$C$50,"")} -> 240.54924 | F64: {=IFERROR((SUMPRODUCT($D$24:$M$24/(1+F$61)^$D$29:$M$29)+($M$24*(1+$B64)/(F$61-$B64))/(1+F$61)^$M$29-$C$48)/$C$50,"")} -> 210.936 | G64: {=IFERROR((SUMPRODUCT($D$24:$M$24/(1+G$61)^$D$29:$M$29)+($M$24*(1+$B64)/(G$61-$B64))/(1+G$61)^$M$29-$C$48)/$C$50,"")} -> 187.0441 | H64: {=IFERROR((SUMPRODUCT($D$24:$M$24/(1+H$61)^$D$29:$M$29)+($M$24*(1+$B64)/(H$61-$B64))/(1+H$61)^$M$29-$C$48)/$C$50,"")} -> 167.36952
B65: =B64+0.005 -> 0.04 | D65: {=IFERROR((SUMPRODUCT($D$24:$M$24/(1+D$61)^$D$29:$M$29)+($M$24*(1+$B65)/(D$61-$B65))/(1+D$61)^$M$29-$C$48)/$C$50,"")} -> 315.36572 | E65: {=IFERROR((SUMPRODUCT($D$24:$M$24/(1+E$61)^$D$29:$M$29)+($M$24*(1+$B65)/(E$61-$B65))/(1+E$61)^$M$29-$C$48)/$C$50,"")} -> 267.82329 | F65: {=IFERROR((SUMPRODUCT($D$24:$M$24/(1+F$61)^$D$29:$M$29)+($M$24*(1+$B65)/(F$61-$B65))/(1+F$61)^$M$29-$C$48)/$C$50,"")} -> 231.61577 | G65: {=IFERROR((SUMPRODUCT($D$24:$M$24/(1+G$61)^$D$29:$M$29)+($M$24*(1+$B65)/(G$61-$B65))/(1+G$61)^$M$29-$C$48)/$C$50,"")} -> 203.13233 | H65: {=IFERROR((SUMPRODUCT($D$24:$M$24/(1+H$61)^$D$29:$M$29)+($M$24*(1+$B65)/(H$61-$B65))/(1+H$61)^$M$29-$C$48)/$C$50,"")} -> 180.1482
B66: =B64+0.01 -> 0.045 | D66: {=IFERROR((SUMPRODUCT($D$24:$M$24/(1+D$61)^$D$29:$M$29)+($M$24*(1+$B66)/(D$61-$B66))/(1+D$61)^$M$29-$C$48)/$C$50,"")} -> 366.24638 | E66: {=IFERROR((SUMPRODUCT($D$24:$M$24/(1+E$61)^$D$29:$M$29)+($M$24*(1+$B66)/(E$61-$B66))/(1+E$61)^$M$29-$C$48)/$C$50,"")} -> 303.59327 | F66: {=IFERROR((SUMPRODUCT($D$24:$M$24/(1+F$61)^$D$29:$M$29)+($M$24*(1+$B66)/(F$61-$B66))/(1+F$61)^$M$29-$C$48)/$C$50,"")} -> 257.86923 | G66: {=IFERROR((SUMPRODUCT($D$24:$M$24/(1+G$61)^$D$29:$M$29)+($M$24*(1+$B66)/(G$61-$B66))/(1+G$61)^$M$29-$C$48)/$C$50,"")} -> 223.04176 | H66: {=IFERROR((SUMPRODUCT($D$24:$M$24/(1+H$61)^$D$29:$M$29)+($M$24*(1+$B66)/(H$61-$B66))/(1+H$61)^$M$29-$C$48)/$C$50,"")} -> 195.63983
B69: 5. REVERSE DCF
B70: To solve for the market-implied path: Data ▸ What-If Analysis ▸ Goal Seek — set C51 to the current price (C52) by changing C27 (terminal growth) or the fade-period growth inputs (I26:M26).
B72: 6. MAUBOUSSIN EV / NOPAT — TWO-STAGE FRAMEWORK
B73: EV/NOPAT = 1/r + [g × (1 − r/ROIIC) / (r × (r − g))] × [1 − ((1+g)/(1+r))^N]
B74: Formula source: Mauboussin & Rappaport, "Expectations Investing" (2021); Counterpoint Global, "What Does a Price-Earnings Multiple Mean?" (2020).
B76: Input | C76: Value | D76: Rationale (Danaher characteristics)
B77: r (Cost of capital / WACC) | C77: =$C$13 -> 0.0821025 | D77: Linked from Section 1 WACC build
B78: g (NOPAT growth, Stage 1) | C78: 0.08 | D78: Model NOPAT CAGR 2026–30E: mid-single-digit core growth (bioprocessing HSD), 50–100 bps p.a. adjusted-margin expansion, Masimo synergies, amortization roll-off → ~8% NOPAT growth
B79: ROIIC (Return on incremental invested capital) | C79: 0.12 | D79: Consumables-heavy portfolio (~80% recurring) and DBS earn high returns on organic investment (capex ~4–5% of sales); acquired growth (Cytiva, Aldevron, Abcam, Masimo) earns ~5–7% after tax on purchase price, diluting incremental returns
B80: N (Years of value creation / CAP) | C80: 15 | D80: Installed-base razor / razor-blade franchises (bioprocessing, clinical diagnostics, Cepheid), regulatory switching costs, multi-decade DBS compounding record
B82: Calculation | C82: Value
B83: Steady-state component: 1 / r | C83: =1/C77 -> 12.179897
B84: Value-creation factor: 1 − r / ROIIC | C84: =1-C77/C79 -> 0.3158125
B85: Growth multiplier: g × (1 − r/ROIIC) / (r × (r − g)) | C85: =C78*C84/(C77*(C77-C78)) -> 146.36152
B86: Time decay: 1 − ((1+g)/(1+r))^N | C86: =1-((1+C78)/(1+C77))^C80 -> 0.028751578
B87: PVGO component (growth value) | C87: =C85*C86 -> 4.2081247
B88: Mauboussin EV / NOPAT (steady-state + PVGO) | C88: =C83+C87 -> 16.388022
B90: VALUATION — Applied to 2028E NOPAT | C90: USDm
B91: 2028E adjusted operating profit less other operating profit adjustments | C91: =Model!CC243-Model!CC241 -> 9097.6262
B92: Tax rate (from WACC build) | C92: =$C$10 -> 0.17
B93: 2028E NOPAT | C93: =C91*(1-C92) -> 7551.0298
B94: × Mauboussin EV/NOPAT multiple | C94: =C88 -> 16.388022
B95: Implied Enterprise Value (2028E basis) | C95: =C93*C94 -> 123746.44
B96: Less: YE2027 net debt + NCI (Model) | C96: =Model!CB459+Model!CB374 -> 18534.24
B97: Implied Equity Value | C97: =C95-C96 -> 105212.2
B98: Diluted shares 2028E (m, Model) | C98: =Model!CC465 -> 680.10293
B99: Implied share price 2028 ($) | C99: =C97/C98 -> 154.70041
B101: Current share price ($) | C101: =C52 -> 221.21
B102: Implied upside / (downside) | C102: =C99/C101-1 -> -0.30066269
B104: MARKET-IMPLIED EV/NOPAT TODAY | C104: USDm
B105: Current market cap (spot × diluted shares) | C105: =C52*C50 -> 155674.26
B106: Plus: YE2026 net debt + NCI | C106: =C48 -> 21178.888
B107: Implied Enterprise Value (today) | C107: =C105+C106 -> 176853.15
B108: DHR market-implied EV/NOPAT (on 2028E NOPAT) | C108: =C107/C93 -> 23.421064
B110: Multiple gap (Mauboussin − Market) | C110: =C88-C108 -> -7.0330418
B111: Implied re-rating headroom | C111: =C88/C108-1 -> -0.30028704

Sheet Charts
B2: Danaher Corporation — Historical Operating Performance (2006–2025)
B3: All historicals · USDm · Linked to Model. Bars = core sales growth (non-GAAP, as published) vs total sales growth (y/y; hybrid recast basis around the Fortive, Envista and Veralto separations). Adjusted EBITDA = model definition (adjusted operating profit + depreciation). ROIC / RONTA on Adjusted EBIT (after amortization).
C7: 2006 | D7: 2007 | E7: 2008 | F7: 2009 | G7: 2010 | H7: 2011 | I7: 2012 | J7: 2013 | K7: 2014 | L7: 2015 | M7: 2016 | N7: 2017 | O7: 2018 | P7: 2019 | Q7: 2020 | R7: 2021 | S7: 2022 | T7: 2023 | U7: 2024 | V7: 2025
B8: Core sales growth % | C8: =IFERROR(Model!C275+0,IFERROR(Model!C275+0,0)) -> 0 | D8: =IFERROR(Model!D275+0,IFERROR(Model!D275+0,0)) -> 0.045 | E8: =IFERROR(Model!E275+0,IFERROR(Model!E275+0,0)) -> 0.025 | F8: =IFERROR(Model!F275+0,IFERROR(Model!F275+0,0)) -> -0.12 | G8: =IFERROR(Model!G275+0,IFERROR(Model!G275+0,0)) -> 0.115 | H8: =IFERROR(Model!H275+0,IFERROR(Model!H275+0,0)) -> 0.07 | I8: =IFERROR(Model!I275+0,IFERROR(Model!I275+0,0)) -> 0.025 | J8: =IFERROR(Model!N275+0,IFERROR(Model!N275+0,0)) -> 0.025 | K8: =IFERROR(Model!S275+0,IFERROR(Model!S275+0,0)) -> 0.035 | L8: =IFERROR(Model!X275+0,IFERROR(Model!X275+0,0)) -> 0.03 | M8: =IFERROR(Model!AC275+0,IFERROR(Model!AC275+0,0)) -> 0.03 | N8: =IFERROR(Model!AH275+0,IFERROR(Model!AH275+0,0)) -> 0.035 | O8: =IFERROR(Model!AM275+0,IFERROR(Model!AM275+0,0)) -> 0.06 | P8: =IFERROR(Model!AR275+0,IFERROR(Model!AR275+0,0)) -> 0.06 | Q8: =IFERROR(Model!AW275+0,IFERROR(Model!AW275+0,0)) -> 0.065 | R8: =IFERROR(Model!BB275+0,IFERROR(Model!BB275+0,0)) -> 0.23 | S8: =IFERROR(Model!BG275+0,IFERROR(Model!BG275+0,0)) -> 0.095 | T8: =IFERROR(Model!BL275+0,IFERROR(Model!BL275+0,0)) -> -0.1 | U8: =IFERROR(Model!BQ275+0,IFERROR(Model!BQ275+0,0)) -> -0.015 | V8: =IFERROR(Model!BV275+0,IFERROR(Model!BV275+0,0)) -> 0.02
B9: Total sales growth % | C9: =IFERROR(Model!C274+0,IFERROR(Model!C274+0,0)) -> 0 | D9: =IFERROR(Model!D274+0,IFERROR(Model!D274+0,0)) -> 0.16477747 | E9: =IFERROR(Model!E274+0,IFERROR(Model!E274+0,0)) -> 0.15160667 | F9: =IFERROR(Model!F274+0,IFERROR(Model!F274+0,0)) -> -0.11912581 | G9: =IFERROR(Model!G274+0,IFERROR(Model!G274+0,0)) -> 0.12204848 | H9: =IFERROR(Model!H274+0,IFERROR(Model!H274+0,0)) -> 0.28211155 | I9: =IFERROR(Model!I274+0,IFERROR(Model!I274+0,0)) -> 0.13485597 | J9: =IFERROR(Model!N274+0,IFERROR(Model!N274+0,0)) -> 0.046965017 | K9: =IFERROR(Model!S274+0,IFERROR(Model!S274+0,0)) -> 0.0018830422 | L9: =IFERROR(Model!X274+0,IFERROR(Model!X274+0,0)) -> -0.24643939 | M9: =IFERROR(Model!AC274+0,IFERROR(Model!AC274+0,0)) -> 0.16965158 | N9: =IFERROR(Model!AH274+0,IFERROR(Model!AH274+0,0)) -> 0.085728332 | O9: =IFERROR(Model!AM274+0,IFERROR(Model!AM274+0,0)) -> -0.069897489 | P9: =IFERROR(Model!AR274+0,IFERROR(Model!AR274+0,0)) -> 0.050596827 | Q9: =IFERROR(Model!AW274+0,IFERROR(Model!AW274+0,0)) -> 0.24414469 | R9: =IFERROR(Model!BB274+0,IFERROR(Model!BB274+0,0)) -> 0.32171064 | S9: =IFERROR(Model!BG274+0,IFERROR(Model!BG274+0,0)) -> -0.09540624 | T9: =IFERROR(Model!BL274+0,IFERROR(Model!BL274+0,0)) -> -0.1033292 | U9: =IFERROR(Model!BQ274+0,IFERROR(Model!BQ274+0,0)) -> -0.00062787777 | V9: =IFERROR(Model!BV274+0,IFERROR(Model!BV274+0,0)) -> 0.029026178
C11: =C7 -> 2006 | D11: =D7 -> 2007 | E11: =E7 -> 2008 | F11: =F7 -> 2009 | G11: =G7 -> 2010 | H11: =H7 -> 2011 | I11: =I7 -> 2012 | J11: =J7 -> 2013 | ... V11: =V7 -> 2025
B12: Adjusted EBITDA (model) | C12: =Model!C227 -> 1706.7 | D12: =Model!D227 -> 2067.1 | E12: =Model!E227 -> 2314.8 | F12: =Model!F227 -> 2006.8 | G12: =Model!G227 -> 2493.1 | H12: =Model!H227 -> 3368.8 | I12: =Model!I227 -> 4004.9 | J12: =Model!N227 -> 4188.9 | K12: =Model!S227 -> 4336.2 | L12: =Model!X227 -> 3247.5 | M12: =Model!AC227 -> 3945 | N12: =Model!AH227 -> 4293.7 | O12: =Model!AM227 -> 4294.2 | P12: =Model!AR227 -> 4551.9 | Q12: =Model!AW227 -> 6596 | R12: =Model!BB227 -> 10294 | S12: =Model!BG227 -> 9769 | T12: =Model!BL227 -> 7530 | U12: =Model!BQ227 -> 7561 | V12: =Model!BV227 -> 7689
B13: Operating Profit (GAAP) | C13: =Model!C185 -> 1500.3 | D13: =Model!D185 -> 1740.7 | E13: =Model!E185 -> 1869.5 | F13: =Model!F185 -> 1542.4 | G13: =Model!G185 -> 2049.6 | H13: =Model!H185 -> 2617.2 | I13: =Model!I185 -> 3165.1 | J13: =Model!N185 -> 3274.9 | K13: =Model!S185 -> 3346.6 | L13: =Model!X185 -> 2162.2 | M13: =Model!AC185 -> 2750.9 | N13: =Model!AH185 -> 2990.4 | O13: =Model!AM185 -> 3055.1 | P13: =Model!AR185 -> 3269.4 | Q13: =Model!AW185 -> 4231 | R13: =Model!BB185 -> 7465 | S13: =Model!BG185 -> 7536 | T13: =Model!BL185 -> 5202 | U13: =Model!BQ185 -> 4863 | V13: =Model!BV185 -> 4690
B14: Adj. EBITDA Margin % | C14: =Model!C286 -> 0.180296 | D14: =Model!D286 -> 0.18747676 | E14: =Model!E286 -> 0.1823036 | F14: =Model!F286 -> 0.17942047 | G14: =Model!G286 -> 0.19865339 | H14: =Model!H286 -> 0.20936577 | I14: =Model!I286 -> 0.21932159 | J14: =Model!N286 -> 0.21910765 | K14: =Model!S286 -> 0.22638613 | L14: =Model!X286 -> 0.22499428 | M14: =Model!AC286 -> 0.23367531 | N14: =Model!AH286 -> 0.23424824 | O14: =Model!AM286 -> 0.2518814 | P14: =Model!AR286 -> 0.2541385 | Q14: =Model!AW286 -> 0.29599713 | R14: =Model!BB286 -> 0.34950599 | S14: =Model!BG286 -> 0.36666291 | T14: =Model!BL286 -> 0.31519464 | U14: =Model!BQ286 -> 0.3166911 | V14: =Model!BV286 -> 0.31296809
B15: GAAP Op. Margin % | C15: =Model!C288 -> 0.15849188 | D15: =Model!D288 -> 0.15787373 | E15: =Model!E288 -> 0.14723371 | F15: =Model!F288 -> 0.1379002 | G15: =Model!G288 -> 0.16331474 | H15: =Model!H288 -> 0.16265498 | I15: =Model!I288 -> 0.17333136 | J15: =Model!N288 -> 0.1712993 | K15: =Model!S288 -> 0.17472068 | L15: =Model!X288 -> 0.1498022 | M15: =Model!AC288 -> 0.16294484 | N15: =Model!AH288 -> 0.16314506 | O15: =Model!AM288 -> 0.17920052 | P15: =Model!AR288 -> 0.18253485 | Q15: =Model!AW288 -> 0.18986717 | R15: =Model!BB288 -> 0.25345466 | S15: =Model!BG288 -> 0.28285103 | T15: =Model!BL288 -> 0.21774801 | U15: =Model!BQ288 -> 0.20368586 | V15: =Model!BV288 -> 0.19089873
C17: =C7 -> 2006 | D17: =D7 -> 2007 | E17: =E7 -> 2008 | F17: =F7 -> 2009 | G17: =G7 -> 2010 | H17: =H7 -> 2011 | I17: =I7 -> 2012 | J17: =J7 -> 2013 | ... V17: =V7 -> 2025
B18: ROIC | C18: =IFERROR(Model!C442+0,NA()) -> 0.13199238 | D18: =IFERROR(Model!D442+0,NA()) -> 0.10608222 | E18: =IFERROR(Model!E442+0,NA()) -> 0.12363648 | F18: =IFERROR(Model!F442+0,NA()) -> 0.10481631 | G18: =IFERROR(Model!G442+0,NA()) -> 0.10793692 | H18: =IFERROR(Model!H442+0,NA()) -> 0.099416192 | I18: =IFERROR(Model!I442+0,NA()) -> 0.1062557 | J18: =IFERROR(Model!N442+0,NA()) -> 0.10901419 | K18: =IFERROR(Model!S442+0,NA()) -> 0.10729369 | L18: =IFERROR(Model!X442+0,NA()) -> 0.054413349 | M18: =IFERROR(Model!AC442+0,NA()) -> 0.067562696 | N18: =IFERROR(Model!AH442+0,NA()) -> 0.070816885 | O18: =IFERROR(Model!AM442+0,NA()) -> 0.067238954 | P18: =IFERROR(Model!AR442+0,NA()) -> 0.077084701 | Q18: =IFERROR(Model!AW442+0,NA()) -> 0.071168534 | R18: =IFERROR(Model!BB442+0,NA()) -> 0.10480747 | S18: =IFERROR(Model!BG442+0,NA()) -> 0.10549103 | T18: =IFERROR(Model!BL442+0,NA()) -> 0.06798309 | U18: =IFERROR(Model!BQ442+0,NA()) -> 0.068867132 | V18: =IFERROR(Model!BV442+0,NA()) -> 0.067196955
B19: RONTA | C19: =IFERROR(Model!C453+0,NA()) -> 0.54516321 | D19: =IFERROR(Model!D453+0,NA()) -> 0.43073185 | E19: =IFERROR(Model!E453+0,NA()) -> 0.48292138 | F19: =IFERROR(Model!F453+0,NA()) -> 0.30554769 | G19: =IFERROR(Model!G453+0,NA()) -> 0.33165416 | H19: =IFERROR(Model!H453+0,NA()) -> 0.3886336 | I19: =IFERROR(Model!I453+0,NA()) -> 0.34607646 | J19: =IFERROR(Model!N453+0,NA()) -> 0.31426561 | K19: =IFERROR(Model!S453+0,NA()) -> 0.34991512 | L19: =IFERROR(Model!X453+0,NA()) -> 0.2974758 | M19: =IFERROR(Model!AC453+0,NA()) -> 0.43248201 | N19: =IFERROR(Model!AH453+0,NA()) -> 0.48954148 | O19: =IFERROR(Model!AM453+0,NA()) -> 0.45754535 | P19: =IFERROR(Model!AR453+0,NA()) -> 0.099371425 | Q19: =IFERROR(Model!AW453+0,NA()) -> 0.32403267 | R19: =IFERROR(Model!BB453+0,NA()) -> 0.61569755 | S19: =IFERROR(Model!BG453+0,NA()) -> 0.40771965 | T19: =IFERROR(Model!BL453+0,NA()) -> 0.28857522 | U19: =IFERROR(Model!BQ453+0,NA()) -> 0.35878849 | V19: =IFERROR(Model!BV453+0,NA()) -> 0.28411923
B20: Adj. EBITDA margin % | C20: =IFERROR(Model!C286+0,NA()) -> 0.180296 | D20: =IFERROR(Model!D286+0,NA()) -> 0.18747676 | E20: =IFERROR(Model!E286+0,NA()) -> 0.1823036 | F20: =IFERROR(Model!F286+0,NA()) -> 0.17942047 | G20: =IFERROR(Model!G286+0,NA()) -> 0.19865339 | H20: =IFERROR(Model!H286+0,NA()) -> 0.20936577 | I20: =IFERROR(Model!I286+0,NA()) -> 0.21932159 | J20: =IFERROR(Model!N286+0,NA()) -> 0.21910765 | K20: =IFERROR(Model!S286+0,NA()) -> 0.22638613 | L20: =IFERROR(Model!X286+0,NA()) -> 0.22499428 | M20: =IFERROR(Model!AC286+0,NA()) -> 0.23367531 | N20: =IFERROR(Model!AH286+0,NA()) -> 0.23424824 | O20: =IFERROR(Model!AM286+0,NA()) -> 0.2518814 | P20: =IFERROR(Model!AR286+0,NA()) -> 0.2541385 | Q20: =IFERROR(Model!AW286+0,NA()) -> 0.29599713 | R20: =IFERROR(Model!BB286+0,NA()) -> 0.34950599 | S20: =IFERROR(Model!BG286+0,NA()) -> 0.36666291 | T20: =IFERROR(Model!BL286+0,NA()) -> 0.31519464 | U20: =IFERROR(Model!BQ286+0,NA()) -> 0.3166911 | V20: =IFERROR(Model!BV286+0,NA()) -> 0.31296809
B21: FCF margin % | C21: =IFERROR(Model!C329+0,NA()) -> 0.14996672 | D21: =IFERROR(Model!D329+0,NA()) -> 0.14082297 | E21: =IFERROR(Model!E329+0,NA()) -> 0.13123056 | F21: =IFERROR(Model!F329+0,NA()) -> 0.14469508 | G21: =IFERROR(Model!G329+0,NA()) -> 0.14877291 | H21: =IFERROR(Model!H329+0,NA()) -> 0.14900096 | I21: =IFERROR(Model!I329+0,NA()) -> 0.16668857 | J21: =IFERROR(Model!N329+0,NA()) -> 0.15868815 | K21: =IFERROR(Model!S329+0,NA()) -> 0.16502558 | L21: =IFERROR(Model!X329+0,NA()) -> 0.22135696 | M21: =IFERROR(Model!AC329+0,NA()) -> 0.14795882 | N21: =IFERROR(Model!AH329+0,NA()) -> 0.15771126 | O21: =IFERROR(Model!AM329+0,NA()) -> 0.19782386 | P21: =IFERROR(Model!AR329+0,NA()) -> 0.16943125 | Q21: =IFERROR(Model!AW329+0,NA()) -> 0.24349309 | R21: =IFERROR(Model!BB329+0,NA()) -> 0.24028113 | S21: =IFERROR(Model!BG329+0,NA()) -> 0.2768457 | T21: =IFERROR(Model!BL329+0,NA()) -> 0.21427375 | U21: =IFERROR(Model!BQ329+0,NA()) -> 0.22236649 | V21: =IFERROR(Model!BV329+0,NA()) -> 0.21544285
