Workbook

Sheet Model
AT1: SCENARIO SWITCH ▼ (Bull / Base / Bear) — drives all scenario-linked forecast drivers
B2: ESAB Corporation (NYSE: ESAB) — 3-Statement Financial Model | AT2: Base
B3: US GAAP as reported · USD millions (per-share data in USD; shares in millions) · Source: ESAB Forms 10-K / 10-Q, Form 10 information statement (10-12B/A, 17-Mar-2022; carve-out combined financial statements 2019–2021), Form 8-K earnings releases (Ex. 99.1) and Eddyfi deal 8-Ks / 8-K/A (Ex. 99.1–99.3), SEC EDGAR CIK 0001877322; pre-spin Colfax 10-K "Fabrication Technology" segment data 2012–2021 (CIK 0001420800) as memo
B4: Basis notes: calendar fiscal year (fiscal quarters end on the Friday nearest quarter end). Spun off from Colfax on 4-Apr-2022: 2019–Q1/22 carve-out (combined) basis, 2012–2018 Colfax segment memo only. Two reportable segments (Americas; EMEA & APAC). "Core" = excluding Russia (from Q2/22). Adjusted EBITDA / adjusted EPS = company definitions (restructuring, acquisition-amortization & other, separation costs 2022–23, pension settlements, performance option awards; MCPS if-converted). Eddyfi Technologies acquired 1-Jun-2026 ($1.45bn) — inside the segments in Q2/26 actuals, modelled separately from Q3/26E; FY26 outlook (6-Aug-2026) includes Eddyfi. Asbestos activity of divested Colfax businesses reported in discontinued operations.
AV5: Forecast | AW5: Historical | AX5: Historical | AY5: Historical
B6: (USDm) | C6: 2012 | D6: 2013 | E6: 2014 | F6: 2015 | G6: 2016 | H6: 2017 | I6: 2018 | J6: 2019 | K6: 2020 | L6: Q1/21 | M6: Q2/21 | N6: Q3/21 | O6: Q4/21 | P6: 2021 | Q6: Q1/22 | R6: Q2/22 | S6: Q3/22 | T6: Q4/22 | U6: 2022 | V6: Q1/23 | W6: Q2/23 | X6: Q3/23 | Y6: Q4/23 | Z6: 2023 | AA6: Q1/24 | AB6: Q2/24 | AC6: Q3/24 | AD6: Q4/24 | AE6: 2024 | AF6: Q1/25 | AG6: Q2/25 | AH6: Q3/25 | AI6: Q4/25 | AJ6: 2025 | AK6: Q1/26 | AL6: Q2/26 | AM6: Q3/26E | AN6: Q4/26E | AO6: 2026E | AP6: 2027E | AQ6: 2028E | AR6: 2029E | AS6: 2030E | AT6: Modelling Notes | AV6: 5Y CAGR | AW6: 5Y CAGR | AX6: 10Y CAGR | AY6: 13Y CAGR
AV7: 25-'30 | AW7: 20-'25 | AX7: 15-'25 | AY7: 12-'25
B8: SEGMENT P&L — AMERICAS · EMEA & APAC (organic × acquisitions × FX build) · EDDYFI (acquired 1-Jun-2026) | AT8: SEGMENT BUILD — modelling logic (prior-year net sales × (1 + organic + acquisitions + FX) → segment adjusted EBITDA; Eddyfi modelled separately from Q3/26E)
BB9: SCENARIO INPUT TABLE — driver assumptions per Bull / Base / Bear | BC9: Bull | BD9: Base | BE9: Bear | BF9: Bull / Bear = Base + Δ (Δ inputs on each lever header). Outlook block = high / mid / low end of the FY26 ranges.
B10: Americas (welding & cutting equipment, consumables, gas control, automation — North & South America) | AT10: AMERICAS — modelling logic
B11: Net sales | J11: 939.673 | K11: 767.414 | L11: 226.2 | M11: 253.6 | N11: 260 | O11: 264.4 | P11: 1004.2 | Q11: 272.3 | R11: 291.1 | S11: 281.4 | T11: 283.6 | U11: 1128.4 | V11: 291.6 | W11: 310.3 | X11: 305.8 | Y11: 307.3 | Z11: 1215 | AA11: 296 | AB11: 309.8 | AC11: 288.8 | AD11: 282.1 | AE11: 1176.7 | AF11: 280.7 | AG11: 282.7 | AH11: 292.7 | AI11: 274.2 | AJ11: 1130.3 | AK11: 288.4 | AL11: 315.9 | AM11: =AH11*(1+AM12) -> 305.6147 | AN11: =AI11*(1+AN12) -> 286.29843 | AO11: =SUM(AK11,AL11,AM11,AN11) -> 1196.2131 | AP11: =(AO11-N(AO19))*(1+AP12) -> 1234.0777 | AQ11: =(AP11-N(AP19))*(1+AQ12) -> 1283.4408 | AR11: =(AQ11-N(AQ19))*(1+AR12) -> 1328.3612 | AS11: =(AR11-N(AR19))*(1+AS12) -> 1374.8538 | AT11: Historical: as reported (Q2/26 includes one month of Eddyfi). Q3/Q4-26E: legacy business only = prior-year quarter × (1 + organic + acquisitions + FX); Eddyfi in its own block. 2027E+: legacy 2026E (ex-Eddyfi June) × (1 + organic lever + FX). | AV11: =IFERROR((AS11/AJ11)^(1/5)-1,"n/m") -> 0.039950241 | AW11: =IFERROR((AJ11/K11)^(1/5)-1,"n/m") -> 0.08051998 | AX11: =IFERROR((AJ11/F11)^(1/10)-1,"n/m") -> n/m | AY11: =IFERROR((AJ11/C11)^(1/13)-1,"n/m") -> n/m | BB11: FY26 outlook — Q2-26 release (6-Aug-26); includes Eddyfi from 1-Jun-26 | BC11: High | BD11: Mid | BE11: Low | BF11: Updated outlook: total core sales growth 11.0–14.0% (core organic 2–4%, M&A ~9%, FX 0–1%); core adjusted EBITDA $615–625m; core adjusted EPS $5.40–5.50.
B12: Net sales y/y % | K12: =IF(AND(ISNUMBER(K11),ISNUMBER(J11)),IFERROR(K11/J11-1,""),"") -> -0.18331803 | P12: =IF(AND(ISNUMBER(P11),ISNUMBER(K11)),IFERROR(P11/K11-1,""),"") -> 0.30855053 | Q12: =IF(AND(ISNUMBER(Q11),ISNUMBER(L11)),IFERROR(Q11/L11-1,""),"") -> 0.20380195 | R12: =IF(AND(ISNUMBER(R11),ISNUMBER(M11)),IFERROR(R11/M11-1,""),"") -> 0.14787066 | S12: =IF(AND(ISNUMBER(S11),ISNUMBER(N11)),IFERROR(S11/N11-1,""),"") -> 0.082307692 | T12: =IF(AND(ISNUMBER(T11),ISNUMBER(O11)),IFERROR(T11/O11-1,""),"") -> 0.072617247 | U12: =IF(AND(ISNUMBER(U11),ISNUMBER(P11)),IFERROR(U11/P11-1,""),"") -> 0.12368054 | V12: =IF(AND(ISNUMBER(V11),ISNUMBER(Q11)),IFERROR(V11/Q11-1,""),"") -> 0.070877708 | W12: =IF(AND(ISNUMBER(W11),ISNUMBER(R11)),IFERROR(W11/R11-1,""),"") -> 0.065956716 | ... AL12: =IF(AND(ISNUMBER(AL11),ISNUMBER(AG11)),IFERROR(AL11/AG11-1,""),"") -> 0.11743898 | AM12: =AM13+AM14+AM15 -> 0.044122646 | AN12: =AN13+AN14+AN15 -> 0.044122646 | AO12: =IFERROR(AO11/AJ11-1,"") -> 0.05831472 | AP12: =AP13+AP14+AP15 -> 0.04 | AQ12: =AQ13+AQ14+AQ15 -> 0.04 | AR12: =AR13+AR14+AR15 -> 0.035 | AS12: =AS13+AS14+AS15 -> 0.035 | BB12: FY26 core sales growth (ex-Russia) | BC12: 0.14 | BD12: 0.125 | BE12: 0.11 | BF12: Raised from 6–9% (M&A contribution ~9% from ~4% after the Eddyfi close). Drives the Q3/Q4-26E organic calibration.
B13: Organic growth % (company; price, mix & volume) | Q13: 0.211 | R13: 0.15 | S13: 0.104 | T13: 0.052 | U13: 0.127 | V13: 0.045 | W13: 0.041 | X13: 0.04 | Y13: 0.088 | Z13: 0.054 | AA13: 0.031 | AB13: 0.04 | AC13: 0.02 | AD13: -0.015 | AE13: 0.019 | AF13: -0.024 | AG13: -0.072 | AH13: 0.001 | AI13: -0.049 | AJ13: -0.037 | AK13: -0.007 | AL13: 0.049 | AM13: =$AL$13+AM118 -> 0.044122646 | AN13: =$AL$13+AN118 -> 0.044122646 | AO13: =IFERROR(AO16/AJ11,"") -> 0.032569343 | AP13: =CHOOSE(MATCH($AT$2,{"Bull","Base","Bear"},0),$BC$21,$BD$21,$BE$21) -> 0.04 | AQ13: =CHOOSE(MATCH($AT$2,{"Bull","Base","Bear"},0),$BC$22,$BD$22,$BE$22) -> 0.04 | AR13: =CHOOSE(MATCH($AT$2,{"Bull","Base","Bear"},0),$BC$23,$BD$23,$BE$23) -> 0.035 | AS13: =CHOOSE(MATCH($AT$2,{"Bull","Base","Bear"},0),$BC$24,$BD$24,$BE$24) -> 0.035 | AT13: Q3/Q4-26E: Q2/26 y/y organic + outlook calibration Δ. 2027E+: scenario lever. ESAB does not split organic growth into price and volume. | BB13: FY26 core adjusted EBITDA ($m) | BC13: 625 | BD13: 620 | BE13: 615 | BF13: Raised to $615–625m (from $575–595m). Drives the Q3/Q4-26E margin calibration.
B14: Acquisitions % (excl. Eddyfi in forecast) | Q14: 0 | R14: 0 | S14: 0 | T14: 0.04 | U14: 0.011 | V14: 0.048 | W14: 0.047 | X14: 0.052 | Y14: 0.008 | Z14: 0.039 | AA14: 0.003 | AB14: 0.009 | AC14: 0.009 | AD14: 0.026 | AE14: 0.012 | AF14: 0.032 | AG14: 0.026 | AH14: 0.026 | AI14: 0.009 | AJ14: 0.024 | AK14: 0 | AL14: 0.034 | AM14: 0 | AN14: 0 | AO14: =IFERROR(AO17/AJ11,"") -> 0.0084933204 | AP14: 0 | AQ14: 0 | AR14: 0 | AS14: 0 | AT14: Eddyfi (Americas share) modelled in the Eddyfi block from Q3/26E; no other Americas deals to anniversary. | BB14: FY26 core adjusted EPS ($; memo) | BC14: 5.5 | BD14: 5.45 | BE14: 5.4 | BF14: $5.40–5.50 (memo; compare with model core adjusted EPS).
B15: Foreign currency translation % | Q15: -0.007 | R15: -0.002 | S15: -0.022 | T15: -0.02 | U15: -0.014 | V15: -0.022 | W15: -0.022 | X15: -0.005 | Y15: -0.012 | Z15: -0.015 | AA15: -0.018 | AB15: -0.051 | AC15: -0.085 | AD15: -0.093 | AE15: -0.062 | AF15: -0.061 | AG15: -0.042 | AH15: -0.014 | AI15: 0.012 | AJ15: -0.027 | AK15: 0.035 | AL15: 0.034 | AM15: 0 | AN15: 0 | AO15: =IFERROR(AO18/AJ11,"") -> 0.017252057 | AP15: 0 | AQ15: 0 | AR15: 0 | AS15: 0 | AT15: Q3/Q4-26E: FX input (spot vs prior-year rates). 2027E+: EMEA & APAC FX lever; Americas 0%. | BB15: FY26 point estimates / capital returns | BC15: Bull | BD15: Base | BE15: Bear
B16: Δ Net sales — organic ($) | Q16: 47.7 | R16: 38.1 | S16: 27.1 | T16: 13.8 | U16: 127.3 | V16: 12.2 | W16: 11.9 | X16: 11.3 | Y16: 25.1 | Z16: 60.5 | AA16: 8.9 | AB16: 12.5 | AC16: 6.2 | AD16: -4.6 | AE16: 23 | AF16: -7 | AG16: -22.4 | AH16: 0.4 | AI16: -13.9 | AJ16: -43 | AK16: -2.1 | AL16: 13.9 | AM16: =AH11*AM13 -> 12.914698 | AN16: =AI11*AN13 -> 12.098429 | AO16: =SUM(AK16,AL16,AM16,AN16) -> 36.813128 | AP16: =(AO11-N(AO19))*AP13 -> 47.464525 | AQ16: =(AP11-N(AP19))*AQ13 -> 49.363106 | AR16: =(AQ11-N(AQ19))*AR13 -> 44.920427 | AS16: =(AR11-N(AR19))*AS13 -> 46.492641 | BB16: FY26 capital expenditures ($m) | BC16: 75 | BD16: 70 | BE16: 65 | BF16: No explicit FY26 capex guidance; 1H/26 $31.4m, FY25 $47.3m. Eddyfi adds capitalized development / equipment.
B17: Δ Net sales — acquisitions ($) | Q17: 0 | R17: 0 | S17: 0 | T17: 10.7 | U17: 10.7 | V17: 13 | W17: 13.8 | X17: 14.6 | Y17: 2.2 | Z17: 43.7 | AA17: 0.9 | AB17: 2.7 | AC17: 2.8 | AD17: 7.9 | AE17: 14.3 | AF17: 9.6 | AG17: 8.2 | AH17: 7.4 | AI17: 2.7 | AJ17: 27.9 | AK17: 0 | AL17: 9.6 | AM17: =AH11*AM14 -> 0 | AN17: =AI11*AN14 -> 0 | AO17: =SUM(AK17,AL17,AM17,AN17) -> 9.6 | AP17: 0 | AQ17: 0 | AR17: 0 | AS17: 0 | BB17: 2H/26 effective tax rate | BC17: 0.22 | BD17: 0.23 | BE17: 0.24 | BF17: ESAB adjusted tax rate ~22–23%.
B18: Δ Net sales — FX ($) | Q18: -1.6 | R18: -0.6 | S18: -5.7 | T18: -5.3 | U18: -13.8 | V18: -5.9 | W18: -6.5 | X18: -1.5 | Y18: -3.5 | Z18: -17.5 | AA18: -5.3 | AB18: -15.7 | AC18: -26 | AD18: -28.5 | AE18: -75.5 | AF18: -17.9 | AG18: -12.9 | AH18: -3.9 | AI18: 3.4 | AJ18: -31.3 | AK18: 9.8 | AL18: 9.7 | AM18: =AH11*AM15 -> 0 | AN18: =AI11*AN15 -> 0 | AO18: =SUM(AK18,AL18,AM18,AN18) -> 19.5 | AP18: =(AO11-N(AO19))*AP15 -> 0 | AQ18: =(AP11-N(AP19))*AQ15 -> 0 | AR18: =(AQ11-N(AQ19))*AR15 -> 0 | AS18: =(AR11-N(AR19))*AS15 -> 0 | BB18: 2H/26 share repurchases ($m) | BC18: 0 | BD18: 0 | BE18: 0 | BF18: Post-Eddyfi deleveraging: no 2H buybacks in Base.
B19: Memo: Eddyfi net sales included in the segment (from 1-Jun-2026) | AL19: 9.6 | AM19: 0 | AN19: 0 | AO19: =SUM(AK19,AL19,AM19,AN19) -> 9.6 | AP19: 0 | AQ19: 0 | AR19: 0 | AS19: 0 | AT19: Q2/26: Eddyfi sales since closing $21.4m (10-Q Note 3) — Americas $9.6m (MD&A), EMEA & APAC $11.8m (derived). Removed from the 2026E base when growing the legacy segments in 2027E. | BB19: Minimum net debt / Adjusted EBITDA (x) — buyback floor 2027E+ | BC19: 2.5 | BD19: 2 | BE19: 1.75 | BF19: ESAB targets net leverage < 3.0x by YE2026 after Eddyfi and ~2x over time; buybacks resume once leverage reaches the floor.
B20: Adjusted EBITDA (segment, company definition) | K20: 111.588 | L20: 33.3 | M20: 38 | N20: 42.6 | O20: 45.7 | P20: 159.6 | Q20: 44 | R20: 48.6 | S20: 46.4 | T20: 49.6 | U20: 188.6 | V20: 49.4 | W20: 58.3 | X20: 57.2 | Y20: 59.8 | Z20: 224.7 | AA20: 54.1 | AB20: 64.7 | AC20: 59.4 | AD20: 61 | AE20: 239.2 | AF20: 54.5 | AG20: 56.8 | AH20: 57.3 | AI20: 56.8 | AJ20: 225.4 | AK20: 56 | AL20: 64 | AM20: =AM11*AM23 -> 65.481983 | AN20: =AN11*AN23 -> 64.602579 | AO20: =SUM(AK20,AL20,AM20,AN20) -> 250.08456 | AP20: =AO20-N(AO21)+AP26 -> 261.47944 | AQ20: =AP20-N(AP21)+AQ26 -> 276.28837 | AR20: =AQ20-N(AQ21)+AR26 -> 289.7645 | AS20: =AR20-N(AR21)+AS26 -> 303.71229 | AT20: 2027E+: legacy prior-year adjusted EBITDA + Δ bridge (organic $ × incremental margin + FX $ × prior margin). | AV20: =IFERROR((AS20/AJ20)^(1/5)-1,"n/m") -> 0.061455255 | AW20: =IFERROR((AJ20/K20)^(1/5)-1,"n/m") -> 0.15097869 | AX20: =IFERROR((AJ20/F20)^(1/10)-1,"n/m") -> n/m | AY20: =IFERROR((AJ20/C20)^(1/13)-1,"n/m") -> n/m | BB20: AM_org (Americas organic growth y/y) | BC20: 0.02 | BD20: Δ → | BE20: -0.02 | BF20: US equipment & automation demand, tariff-driven pricing, Latin America; 2025 −4%, Q2/26 +4.9%. Company organic outlook 2–4% (2026).
B21: Memo: Eddyfi adjusted EBITDA included in the segment (estimate) | AL21: 2.84448 | AM21: 0 | AN21: 0 | AO21: =SUM(AK21,AL21,AM21,AN21) -> 2.84448 | AP21: 0 | AQ21: 0 | AR21: 0 | AS21: 0 | AT21: June 2026 Eddyfi sales × 2026E standalone margin (not separately disclosed). | BB21: 2027E | BC21: =BD21+$BC$20 -> 0.06 | BD21: 0.04 | BE21: =BD21+$BE$20 -> 0.02
B22: Adjusted EBITDA margin before outlook calibration % (Q3/Q4-26E helper) | AM22: =AH23+($AK$20+$AL$20-$AL$21)/($AK$11+$AL$11-$AL$19)-($AF$20+$AG$20)/($AF$11+$AG$11) -> 0.19521236 | AN22: =AI23+($AK$20+$AL$20-$AL$21)/($AK$11+$AL$11-$AL$19)-($AF$20+$AG$20)/($AF$11+$AG$11) -> 0.20659684 | AT22: Prior-year quarter margin + (1H/26 legacy − 1H/25 margin drift). | BB22: 2028E | BC22: =BD22+$BC$20 -> 0.06 | BD22: 0.04 | BE22: =BD22+$BE$20 -> 0.02
B23: Adjusted EBITDA margin % | J23: =IF(AND(ISNUMBER(J20),ISNUMBER(J11)),IFERROR(J20/J11,""),"") | K23: =IF(AND(ISNUMBER(K20),ISNUMBER(K11)),IFERROR(K20/K11,""),"") -> 0.14540782 | L23: =IF(AND(ISNUMBER(L20),ISNUMBER(L11)),IFERROR(L20/L11,""),"") -> 0.14721485 | M23: =IF(AND(ISNUMBER(M20),ISNUMBER(M11)),IFERROR(M20/M11,""),"") -> 0.14984227 | N23: =IF(AND(ISNUMBER(N20),ISNUMBER(N11)),IFERROR(N20/N11,""),"") -> 0.16384615 | O23: =IF(AND(ISNUMBER(O20),ISNUMBER(O11)),IFERROR(O20/O11,""),"") -> 0.17284418 | P23: =IF(AND(ISNUMBER(P20),ISNUMBER(P11)),IFERROR(P20/P11,""),"") -> 0.15893248 | Q23: =IF(AND(ISNUMBER(Q20),ISNUMBER(Q11)),IFERROR(Q20/Q11,""),"") -> 0.16158649 | ... AL23: =IF(AND(ISNUMBER(AL20),ISNUMBER(AL11)),IFERROR(AL20/AL11,""),"") -> 0.20259576 | AM23: =AM22+AM122 -> 0.2142632 | AN23: =AN22+AN122 -> 0.22564769 | AO23: =IFERROR(AO20/AO11,"") -> 0.20906355 | AP23: =IFERROR(AP20/AP11,"") -> 0.21188248 | AQ23: =IFERROR(AQ20/AQ11,"") -> 0.21527162 | AR23: =IFERROR(AR20/AR11,"") -> 0.21813683 | AS23: =IFERROR(AS20/AS11,"") -> 0.22090515 | AV23: =IFERROR(AVERAGE(AO23,AP23,AQ23,AR23,AS23),"n/m") -> 0.21505193 | AW23: =IFERROR(AVERAGE(K23,P23,U23,Z23,AE23,AJ23),"n/m") -> 0.17651906 | AX23: =IFERROR(AVERAGE(F23,G23,H23,I23,J23,K23,P23,U23,Z23,AE23,AJ23),"n/m") -> 0.17651906 | AY23: =IFERROR(AVERAGE(C23,D23,E23,F23,G23,H23,I23,J23,K23,P23,U23,Z23,AE23,AJ23),"n/m") -> 0.17651906 | BB23: 2029E | BC23: =BD23+$BC$20 -> 0.055 | BD23: 0.035 | BE23: =BD23+$BE$20 -> 0.015
B24: Incremental adjusted EBITDA margin (Δ adj. EBITDA / Δ net sales) | K24: =IFERROR((K20-J20)/(K11-J11),"") -> -0.64779199 | P24: =IFERROR((P20-K20)/(P11-K11),"") -> 0.20276537 | Q24: =IFERROR((Q20-L20)/(Q11-L11),"") -> 0.23210412 | R24: =IFERROR((R20-M20)/(R11-M11),"") -> 0.28266667 | S24: =IFERROR((S20-N20)/(S11-N11),"") -> 0.17757009 | T24: =IFERROR((T20-O20)/(T11-O11),"") -> 0.203125 | U24: =IFERROR((U20-P20)/(U11-P11),"") -> 0.23349436 | V24: =IFERROR((V20-Q20)/(V11-Q11),"") -> 0.27979275 | W24: =IFERROR((W20-R20)/(W11-R11),"") -> 0.50520833 | ... AO24: =IFERROR((AO20-AJ20)/(AO11-AJ11),"") -> 0.37450145 | AP24: =IFERROR((AP20-AO20)/(AP11-AO11),"") -> 0.30093808 | AQ24: =IFERROR((AQ20-AP20)/(AQ11-AP11),"") -> 0.3 | AR24: =IFERROR((AR20-AQ20)/(AR11-AQ11),"") -> 0.3 | AS24: =IFERROR((AS20-AR20)/(AS11-AR11),"") -> 0.3 | BB24: 2030E | BC24: =BD24+$BC$20 -> 0.055 | BD24: 0.035 | BE24: =BD24+$BE$20 -> 0.015
B25: Organic incremental adjusted EBITDA margin % (input) | AP25: 0.3 | AQ25: 0.3 | AR25: 0.3 | AS25: 0.3 | AT25: Input: incremental margin on organic sales growth (EBXai productivity; ESAB delivered ~30–35% organic incrementals in 2023–25). | BB25: EA_org (EMEA & APAC organic growth y/y) | BC25: 0.02 | BD25: Δ → | BE25: -0.02 | BF25: Europe resilient, India/Asia growth, Middle East disruption in 2026; 2025 ~0%, 1H/26 −0.8%.
B26: Δ Adjusted EBITDA (organic × incremental + FX × prior margin) | AP26: =AP16*AP25+AP18*AO23 -> 14.239358 | AQ26: =AQ16*AQ25+AQ18*AP23 -> 14.808932 | AR26: =AR16*AR25+AR18*AQ23 -> 13.476128 | AS26: =AS16*AS25+AS18*AR23 -> 13.947792 | BB26: 2027E | BC26: =BD26+$BC$25 -> 0.05 | BD26: 0.03 | BE26: =BD26+$BE$25 -> 0.01
B27: Operating income (GAAP, segment) | J27: 95.2 | K27: 61.5 | L27: 22.4 | M27: 27.1 | N27: 31.6 | O27: 30.1 | P27: 111.2 | Q27: 30.2 | R27: 35.8 | S27: 36.6 | T27: 33.7 | U27: 136.2 | V27: 39.9 | W27: 46.1 | X27: 46.5 | Y27: 50.1 | Z27: 182.5 | AA27: 46 | AB27: 55.9 | AC27: 49.9 | AD27: 51.5 | AE27: 203.2 | AF27: 43.2 | AG27: 42.4 | AH27: 45.3 | AI27: 36.8 | AJ27: 167.8 | AK27: 35.2 | AL27: 22.5 | AT27: Historical disclosure only. | BB27: 2028E | BC27: =BD27+$BC$25 -> 0.05 | BD27: 0.03 | BE27: =BD27+$BE$25 -> 0.01
B28: Restructuring & other related charges (segment) | J28: 13.8 | K28: 12.4 | L28: 2.4 | M28: 2.1 | N28: 1.8 | O28: 5.3 | P28: 11.6 | Q28: 3.6 | R28: 3.6 | S28: 1.9 | T28: 2.3 | U28: 11.4 | V28: 0.9 | W28: 3 | X28: 1.6 | Y28: 1.1 | Z28: 6.5 | AA28: 0.2 | AB28: 0.8 | AC28: 0.9 | AD28: 1 | AE28: 3 | AF28: 1.7 | AG28: 0.5 | AH28: 2.2 | AI28: 7.2 | AJ28: 11.6 | AK28: 9 | AL28: 18.3 | BB28: 2029E | BC28: =BD28+$BC$25 -> 0.05 | BD28: 0.03 | BE28: =BD28+$BE$25 -> 0.01
B29: Acquisition-amortization & other related charges (segment) | J29: 20.1 | K29: 19.4 | L29: 4.7 | M29: 4.7 | N29: 4.6 | O29: 4.5 | P29: 18.5 | Q29: 4.1 | R29: 4.2 | S29: 4 | T29: 7.8 | U29: 20.1 | V29: 5.3 | W29: 5.4 | X29: 5.2 | Y29: 5 | Z29: 20.9 | AA29: 4.4 | AB29: 4.3 | AC29: 4.8 | AD29: 5 | AE29: 18.6 | AF29: 5.6 | AG29: 10 | AH29: 5.8 | AI29: 7.7 | AJ29: 29.2 | AK29: 7.7 | AL29: 18.2 | BB29: 2030E | BC29: =BD29+$BC$25 -> 0.05 | BD29: 0.03 | BE29: =BD29+$BE$25 -> 0.01
B30: Depreciation & other amortization (segment) | L30: 3.5 | M30: 3.7 | N30: 3.9 | O30: 3.8 | P30: 15 | Q30: 3.5 | R30: 3.4 | S30: 3.2 | T30: 3.3 | U30: 13.4 | V30: 3.3 | W30: 3.8 | X30: 3.9 | Y30: 3.7 | Z30: 14.8 | AA30: 3.5 | AB30: 3.7 | AC30: 3.8 | AD30: 3.5 | AE30: 14.5 | AF30: 3.9 | AG30: 3.8 | AH30: 3.9 | AI30: 5 | AJ30: 16.7 | AK30: 4.2 | AL30: 4.7 | BB30: EA_fx (EMEA & APAC FX translation y/y) | BC30: 0.01 | BD30: Δ → | BE30: -0.01 | BF30: Base 0% (constant currency); Bull weaker USD, Bear stronger USD.
BB31: 2027E | BC31: =BD31+$BC$30 -> 0.01 | BD31: 0 | BE31: =BD31+$BE$30 -> -0.01
B32: EMEA & APAC (Europe, Middle East, Africa, Asia Pacific; includes Russia) | AT32: EMEA & APAC — modelling logic | BB32: 2028E | BC32: =BD32+$BC$30 -> 0.01 | BD32: 0 | BE32: =BD32+$BE$30 -> -0.01
B33: Net sales | J33: 1307.353 | K33: 1182.655 | L33: 342 | M33: 376.2 | N33: 346 | O33: 359.8 | P33: 1423.9 | Q33: 375.6 | R33: 370.1 | S33: 338.9 | T33: 380.5 | U33: 1465.1 | V33: 392.4 | W33: 410.1 | X33: 375.2 | Y33: 382 | Z33: 1559.8 | AA33: 393.7 | AB33: 397.3 | AC33: 384.4 | AD33: 388.6 | AE33: 1564.1 | AF33: 397.5 | AG33: 432.9 | AH33: 435.1 | AI33: 446.8 | AJ33: 1712.2 | AK33: 457.2 | AL33: 491.7 | AM33: =AH33*(1+AM34) -> 455.16796 | AN33: =AI33*(1+AN34) -> 448.642 | AO33: =SUM(AK33,AL33,AM33,AN33) -> 1852.71 | AP33: =(AO33-N(AO41))*(1+AP34) -> 1896.1373 | AQ33: =(AP33-N(AP41))*(1+AQ34) -> 1953.0214 | AR33: =(AQ33-N(AQ41))*(1+AR34) -> 2011.612 | AS33: =(AR33-N(AR41))*(1+AS34) -> 2071.9604 | AT33: Historical: as reported (Q2/26 includes one month of Eddyfi). Q3/Q4-26E: legacy business only = prior-year quarter × (1 + organic + acquisitions + FX); Eddyfi in its own block. 2027E+: legacy 2026E (ex-Eddyfi June) × (1 + organic lever + FX). | AV33: =IFERROR((AS33/AJ33)^(1/5)-1,"n/m") -> 0.038880013 | AW33: =IFERROR((AJ33/K33)^(1/5)-1,"n/m") -> 0.076810506 | AX33: =IFERROR((AJ33/F33)^(1/10)-1,"n/m") -> n/m | AY33: =IFERROR((AJ33/C33)^(1/13)-1,"n/m") -> n/m | BB33: 2029E | BC33: =BD33+$BC$30 -> 0.01 | BD33: 0 | BE33: =BD33+$BE$30 -> -0.01
B34: Net sales y/y % | K34: =IF(AND(ISNUMBER(K33),ISNUMBER(J33)),IFERROR(K33/J33-1,""),"") -> -0.095382043 | P34: =IF(AND(ISNUMBER(P33),ISNUMBER(K33)),IFERROR(P33/K33-1,""),"") -> 0.20398595 | Q34: =IF(AND(ISNUMBER(Q33),ISNUMBER(L33)),IFERROR(Q33/L33-1,""),"") -> 0.098245614 | R34: =IF(AND(ISNUMBER(R33),ISNUMBER(M33)),IFERROR(R33/M33-1,""),"") -> -0.016214779 | S34: =IF(AND(ISNUMBER(S33),ISNUMBER(N33)),IFERROR(S33/N33-1,""),"") -> -0.020520231 | T34: =IF(AND(ISNUMBER(T33),ISNUMBER(O33)),IFERROR(T33/O33-1,""),"") -> 0.057531962 | U34: =IF(AND(ISNUMBER(U33),ISNUMBER(P33)),IFERROR(U33/P33-1,""),"") -> 0.028934616 | V34: =IF(AND(ISNUMBER(V33),ISNUMBER(Q33)),IFERROR(V33/Q33-1,""),"") -> 0.044728435 | W34: =IF(AND(ISNUMBER(W33),ISNUMBER(R33)),IFERROR(W33/R33-1,""),"") -> 0.1080789 | ... AL34: =IF(AND(ISNUMBER(AL33),ISNUMBER(AG33)),IFERROR(AL33/AG33-1,""),"") -> 0.13582814 | AM34: =AM35+AM36+AM37 -> 0.046122646 | AN34: =AN35+AN36+AN37 -> 0.0041226457 | AO34: =IFERROR(AO33/AJ33-1,"") -> 0.082063989 | AP34: =AP35+AP36+AP37 -> 0.03 | AQ34: =AQ35+AQ36+AQ37 -> 0.03 | AR34: =AR35+AR36+AR37 -> 0.03 | AS34: =AS35+AS36+AS37 -> 0.03 | BB34: 2030E | BC34: =BD34+$BC$30 -> 0.01 | BD34: 0 | BE34: =BD34+$BE$30 -> -0.01
B35: Organic growth % (company; price, mix & volume) | Q35: 0.156 | R35: 0.044 | S35: 0.048 | T35: 0.113 | U35: 0.089 | V35: 0.049 | W35: 0.111 | X35: 0.106 | Y35: 0.015 | Z35: 0.069 | AA35: 0.02 | AB35: -0.01 | AC35: 0.001 | AD35: 0.014 | AE35: 0.006 | AF35: 0.015 | AG35: 0.017 | AH35: 0.028 | AI35: -0.03 | AJ35: 0.007 | AK35: -0.027 | AL35: 0.009 | AM35: =$AL$35+AM118 -> 0.0041226457 | AN35: =$AL$35+AN118 -> 0.0041226457 | AO35: =IFERROR(AO38/AJ33,"") -> -0.0016728412 | AP35: =CHOOSE(MATCH($AT$2,{"Bull","Base","Bear"},0),$BC$26,$BD$26,$BE$26) -> 0.03 | AQ35: =CHOOSE(MATCH($AT$2,{"Bull","Base","Bear"},0),$BC$27,$BD$27,$BE$27) -> 0.03 | AR35: =CHOOSE(MATCH($AT$2,{"Bull","Base","Bear"},0),$BC$28,$BD$28,$BE$28) -> 0.03 | AS35: =CHOOSE(MATCH($AT$2,{"Bull","Base","Bear"},0),$BC$29,$BD$29,$BE$29) -> 0.03 | AT35: Q3/Q4-26E: Q2/26 y/y organic + outlook calibration Δ. 2027E+: scenario lever. ESAB does not split organic growth into price and volume. | BB35: EDD_g (Eddyfi sales growth y/y) | BC35: 0.03 | BD35: Δ → | BE35: -0.03 | BF35: Company: high-single-digit organic growth (aerospace & defense, nuclear, energy, civil infrastructure inspection).
B36: Acquisitions % (excl. Eddyfi in forecast) | Q36: 0 | R36: 0 | S36: 0 | T36: 0.008 | U36: 0.002 | V36: 0.017 | W36: 0.014 | X36: 0.02 | Y36: 0.006 | Z36: 0.014 | AA36: 0 | AB36: 0 | AC36: 0.01 | AD36: 0.014 | AE36: 0.006 | AF36: 0.013 | AG36: 0.032 | AH36: 0.069 | AI36: 0.112 | AJ36: 0.056 | AK36: 0.108 | AL36: 0.106 | AM36: 0.042 | AN36: 0 | AO36: =IFERROR(AO39/AJ33,"") -> 0.062536036 | AP36: 0 | AQ36: 0 | AR36: 0 | AS36: 0 | AT36: EWM GmbH (acquired 22-Aug-2025) anniversaries in Q3/26: Q3/26E = 49 of 91 days of the Q2/26 non-Eddyfi acquisition contribution ($46.0m − $11.8m Eddyfi = $34.2m) ÷ Q3/25 EMEA & APAC sales = 4.2%; Q4/26E 0%. | BB36: 2027E | BC36: =BD36+$BC$35 -> 0.11 | BD36: 0.08 | BE36: =BD36+$BE$35 -> 0.05
B37: Foreign currency translation % | Q37: -0.058 | R37: -0.06 | S37: -0.069 | T37: -0.063 | U37: -0.062 | V37: -0.021 | W37: -0.017 | X37: -0.019 | Y37: -0.016 | Z37: -0.018 | AA37: -0.017 | AB37: -0.021 | AC37: 0.014 | AD37: -0.01 | AE37: -0.009 | AF37: -0.019 | AG37: 0.041 | AH37: 0.036 | AI37: 0.067 | AJ37: 0.031 | AK37: 0.069 | AL37: 0.021 | AM37: 0 | AN37: 0 | AO37: =IFERROR(AO40/AJ33,"") -> 0.021259199 | AP37: =CHOOSE(MATCH($AT$2,{"Bull","Base","Bear"},0),$BC$31,$BD$31,$BE$31) -> 0 | AQ37: =CHOOSE(MATCH($AT$2,{"Bull","Base","Bear"},0),$BC$32,$BD$32,$BE$32) -> 0 | AR37: =CHOOSE(MATCH($AT$2,{"Bull","Base","Bear"},0),$BC$33,$BD$33,$BE$33) -> 0 | AS37: =CHOOSE(MATCH($AT$2,{"Bull","Base","Bear"},0),$BC$34,$BD$34,$BE$34) -> 0 | AT37: Q3/Q4-26E: FX input (spot vs prior-year rates). 2027E+: EMEA & APAC FX lever; Americas 0%. | BB37: 2028E | BC37: =BD37+$BC$35 -> 0.11 | BD37: 0.08 | BE37: =BD37+$BE$35 -> 0.05
B38: Δ Net sales — organic ($) | Q38: 53.5 | R38: 16.5 | S38: 16.7 | T38: 40.6 | U38: 126.9 | V38: 18.3 | W38: 41.2 | X38: 36 | Y38: 5.6 | Z38: 101.1 | AA38: 7.7 | AB38: -4.1 | AC38: 0.4 | AD38: 5.3 | AE38: 9.3 | AF38: 5.9 | AG38: 6.8 | AH38: 10.6 | AI38: -11.7 | AJ38: 11.6 | AK38: -10.5 | AL38: 4 | AM38: =AH33*AM35 -> 1.7937631 | AN38: =AI33*AN35 -> 1.8419981 | AO38: =SUM(AK38,AL38,AM38,AN38) -> -2.8642388 | AP38: =(AO33-N(AO41))*AP35 -> 55.227299 | AQ38: =(AP33-N(AP41))*AQ35 -> 56.884118 | AR38: =(AQ33-N(AQ41))*AR35 -> 58.590641 | AS38: =(AR33-N(AR41))*AS35 -> 60.348361 | BB38: 2029E | BC38: =BD38+$BC$35 -> 0.11 | BD38: 0.08 | BE38: =BD38+$BE$35 -> 0.05
B39: Δ Net sales — acquisitions ($) | Q39: 0 | R39: 0 | S39: 0 | T39: 2.8 | U39: 2.8 | V39: 6.3 | W39: 5.2 | X39: 6.7 | Y39: 2.1 | Z39: 20.2 | AA39: 0.1 | AB39: 0 | AC39: 3.8 | AD39: 5.3 | AE39: 9.2 | AF39: 5.2 | AG39: 12.7 | AH39: 26.4 | AI39: 43.7 | AJ39: 88 | AK39: 42.8 | AL39: 46 | AM39: =AH33*AM36 -> 18.2742 | AN39: =AI33*AN36 -> 0 | AO39: =SUM(AK39,AL39,AM39,AN39) -> 107.0742 | AP39: 0 | AQ39: 0 | AR39: 0 | AS39: 0 | BB39: 2030E | BC39: =BD39+$BC$35 -> 0.11 | BD39: 0.08 | BE39: =BD39+$BE$35 -> 0.05
B40: Δ Net sales — FX ($) | Q40: -19.9 | R40: -22.6 | S40: -23.8 | T40: -22.7 | U40: -88.5 | V40: -7.8 | W40: -6.4 | X40: -6.4 | Y40: -6.2 | Z40: -26.7 | AA40: -6.6 | AB40: -8.8 | AC40: 5.1 | AD40: -4 | AE40: -14.2 | AF40: -7.4 | AG40: 16.1 | AH40: 13.7 | AI40: 26.2 | AJ40: 48.5 | AK40: 27.5 | AL40: 8.9 | AM40: =AH33*AM37 -> 0 | AN40: =AI33*AN37 -> 0 | AO40: =SUM(AK40,AL40,AM40,AN40) -> 36.4 | AP40: =(AO33-N(AO41))*AP37 -> 0 | AQ40: =(AP33-N(AP41))*AQ37 -> 0 | AR40: =(AQ33-N(AQ41))*AR37 -> 0 | AS40: =(AR33-N(AR41))*AS37 -> 0 | BB40: EDD_m (Eddyfi adjusted EBITDA margin before synergies) | BC40: 0.02 | BD40: Δ → | BE40: -0.02 | BF40: Deal metrics: ~$80m adj. EBITDA on ~$270m 2026E revenue (29.6%); gross margin > 65%.
B41: Memo: Eddyfi net sales included in the segment (from 1-Jun-2026) | AL41: 11.8 | AM41: 0 | AN41: 0 | AO41: =SUM(AK41,AL41,AM41,AN41) -> 11.8 | AP41: 0 | AQ41: 0 | AR41: 0 | AS41: 0 | AT41: Q2/26: Eddyfi sales since closing $21.4m (10-Q Note 3) — Americas $9.6m (MD&A), EMEA & APAC $11.8m (derived). Removed from the 2026E base when growing the legacy segments in 2027E. | BB41: 2027E | BC41: =BD41+$BC$40 -> 0.32 | BD41: 0.3 | BE41: =BD41+$BE$40 -> 0.28
B42: Adjusted EBITDA (segment, company definition) | K42: 189.558 | L42: 61 | M42: 66.7 | N42: 59.9 | O42: 56.9 | P42: 244.6 | Q42: 65.3 | R42: 61.9 | S42: 58.6 | T42: 62.3 | U42: 248.2 | V42: 68.6 | W42: 73.8 | X42: 65.3 | Y42: 68.6 | Z42: 276.4 | AA42: 75 | AB42: 76.2 | AC42: 68.1 | AD42: 70.2 | AE42: 289.6 | AF42: 79.4 | AG42: 86.7 | AH42: 82.2 | AI42: 86 | AJ42: 334.3 | AK42: 80.6 | AL42: 87.3 | AM42: =AM33*AM45 -> 83.472163 | AN42: =AN33*AN45 -> 83.871547 | AO42: =SUM(AK42,AL42,AM42,AN42) -> 335.24371 | AP42: =AO42-N(AO43)+AP48 -> 348.31556 | AQ42: =AP42-N(AP43)+AQ48 -> 365.38079 | AR42: =AQ42-N(AQ43)+AR48 -> 382.95799 | AS42: =AR42-N(AR43)+AS48 -> 401.06249 | AT42: 2027E+: legacy prior-year adjusted EBITDA + Δ bridge (organic $ × incremental margin + FX $ × prior margin). | AV42: =IFERROR((AS42/AJ42)^(1/5)-1,"n/m") -> 0.037086867 | AW42: =IFERROR((AJ42/K42)^(1/5)-1,"n/m") -> 0.12015688 | AX42: =IFERROR((AJ42/F42)^(1/10)-1,"n/m") -> n/m | AY42: =IFERROR((AJ42/C42)^(1/13)-1,"n/m") -> n/m | BB42: 2028E | BC42: =BD42+$BC$40 -> 0.33 | BD42: 0.31 | BE42: =BD42+$BE$40 -> 0.29
B43: Memo: Eddyfi adjusted EBITDA included in the segment (estimate) | AL43: 3.49634 | AM43: 0 | AN43: 0 | AO43: =SUM(AK43,AL43,AM43,AN43) -> 3.49634 | AP43: 0 | AQ43: 0 | AR43: 0 | AS43: 0 | AT43: June 2026 Eddyfi sales × 2026E standalone margin (not separately disclosed). | BB43: 2029E | BC43: =BD43+$BC$40 -> 0.34 | BD43: 0.32 | BE43: =BD43+$BE$40 -> 0.3
B44: Adjusted EBITDA margin before outlook calibration % (Q3/Q4-26E helper) | AM44: =AH45+($AK$42+$AL$42-$AL$43)/($AK$33+$AL$33-$AL$41)-($AF$42+$AG$42)/($AF$33+$AG$33) -> 0.16433676 | AN44: =AI45+($AK$42+$AL$42-$AL$43)/($AK$33+$AL$33-$AL$41)-($AF$42+$AG$42)/($AF$33+$AG$33) -> 0.16789453 | AT44: Prior-year quarter margin + (1H/26 legacy − 1H/25 margin drift). | BB44: 2030E | BC44: =BD44+$BC$40 -> 0.34 | BD44: 0.32 | BE44: =BD44+$BE$40 -> 0.3
B45: Adjusted EBITDA margin % | J45: =IF(AND(ISNUMBER(J42),ISNUMBER(J33)),IFERROR(J42/J33,""),"") | K45: =IF(AND(ISNUMBER(K42),ISNUMBER(K33)),IFERROR(K42/K33,""),"") -> 0.16028174 | L45: =IF(AND(ISNUMBER(L42),ISNUMBER(L33)),IFERROR(L42/L33,""),"") -> 0.17836257 | M45: =IF(AND(ISNUMBER(M42),ISNUMBER(M33)),IFERROR(M42/M33,""),"") -> 0.17729931 | N45: =IF(AND(ISNUMBER(N42),ISNUMBER(N33)),IFERROR(N42/N33,""),"") -> 0.17312139 | O45: =IF(AND(ISNUMBER(O42),ISNUMBER(O33)),IFERROR(O42/O33,""),"") -> 0.15814341 | P45: =IF(AND(ISNUMBER(P42),ISNUMBER(P33)),IFERROR(P42/P33,""),"") -> 0.17178173 | Q45: =IF(AND(ISNUMBER(Q42),ISNUMBER(Q33)),IFERROR(Q42/Q33,""),"") -> 0.17385517 | ... AL45: =IF(AND(ISNUMBER(AL42),ISNUMBER(AL33)),IFERROR(AL42/AL33,""),"") -> 0.17754728 | AM45: =AM44+AM122 -> 0.18338761 | AN45: =AN44+AN122 -> 0.18694537 | AO45: =IFERROR(AO42/AO33,"") -> 0.18094776 | AP45: =IFERROR(AP42/AP33,"") -> 0.18369744 | AQ45: =IFERROR(AQ42/AQ33,"") -> 0.18708489 | AR45: =IFERROR(AR42/AR33,"") -> 0.19037368 | AS45: =IFERROR(AS42/AS33,"") -> 0.19356668 | AV45: =IFERROR(AVERAGE(AO45,AP45,AQ45,AR45,AS45),"n/m") -> 0.18713409 | AW45: =IFERROR(AVERAGE(K45,P45,U45,Z45,AE45,AJ45),"n/m") -> 0.17651236 | AX45: =IFERROR(AVERAGE(F45,G45,H45,I45,J45,K45,P45,U45,Z45,AE45,AJ45),"n/m") -> 0.17651236 | AY45: =IFERROR(AVERAGE(C45,D45,E45,F45,G45,H45,I45,J45,K45,P45,U45,Z45,AE45,AJ45),"n/m") -> 0.17651236 | BB45: EDD_syn (synergy realisation % of $20m run-rate) | BC45: 0.25 | BD45: Δ → | BE45: -0.25 | BF45: Company: $20m annualized run-rate synergies.
B46: Incremental adjusted EBITDA margin (Δ adj. EBITDA / Δ net sales) | K46: =IFERROR((K42-J42)/(K33-J33),"") -> -1.5201367 | P46: =IFERROR((P42-K42)/(P33-K33),"") -> 0.2281581 | Q46: =IFERROR((Q42-L42)/(Q33-L33),"") -> 0.12797619 | R46: =IFERROR((R42-M42)/(R33-M33),"") -> 0.78688525 | S46: =IFERROR((S42-N42)/(S33-N33),"") -> 0.18309859 | T46: =IFERROR((T42-O42)/(T33-O33),"") -> 0.26086957 | U46: =IFERROR((U42-P42)/(U33-P33),"") -> 0.087378641 | V46: =IFERROR((V42-Q42)/(V33-Q33),"") -> 0.19642857 | W46: =IFERROR((W42-R42)/(W33-R33),"") -> 0.2975 | ... AO46: =IFERROR((AO42-AJ42)/(AO33-AJ33),"") -> 0.0067163153 | AP46: =IFERROR((AP42-AO42)/(AP33-AO33),"") -> 0.30100536 | AQ46: =IFERROR((AQ42-AP42)/(AQ33-AP33),"") -> 0.3 | AR46: =IFERROR((AR42-AQ42)/(AR33-AQ33),"") -> 0.3 | AS46: =IFERROR((AS42-AR42)/(AS33-AR33),"") -> 0.3 | BB46: 2027E | BC46: =BD46+$BC$45 -> 0.75 | BD46: 0.5 | BE46: =BD46+$BE$45 -> 0.25
B47: Organic incremental adjusted EBITDA margin % (input) | AP47: 0.3 | AQ47: 0.3 | AR47: 0.3 | AS47: 0.3 | AT47: Input: incremental margin on organic sales growth (EBXai productivity; ESAB delivered ~30–35% organic incrementals in 2023–25). | BB47: 2028E | BC47: =BD47+$BC$45 -> 1.25 | BD47: 1 | BE47: =BD47+$BE$45 -> 0.75
B48: Δ Adjusted EBITDA (organic × incremental + FX × prior margin) | AP48: =AP38*AP47+AP40*AO45 -> 16.56819 | AQ48: =AQ38*AQ47+AQ40*AP45 -> 17.065235 | AR48: =AR38*AR47+AR40*AQ45 -> 17.577192 | AS48: =AS38*AS47+AS40*AR45 -> 18.104508 | BB48: 2029E | BC48: =BD48+$BC$45 -> 1.25 | BD48: 1 | BE48: =BD48+$BE$45 -> 0.75
B49: Operating income (GAAP, segment) | J49: 160.9 | K49: 140.6 | L49: 49.9 | M49: 55.1 | N49: 47 | O49: 42.9 | P49: 195 | Q49: 53.4 | R49: 50 | S49: 44.4 | T49: 44.9 | U49: 192.8 | V49: 50.8 | W49: 62.6 | X49: 54.7 | Y49: 53.6 | Z49: 221.7 | AA49: 64.7 | AB49: 63.4 | AC49: 56.1 | AD49: 60 | AE49: 244.2 | AF49: 66.6 | AG49: 66.7 | AH49: 61.3 | AI49: 49.8 | AJ49: 244.3 | AK49: 55.3 | AL49: 56.2 | AT49: Historical disclosure only. | BB49: 2030E | BC49: =BD49+$BC$45 -> 1.25 | BD49: 1 | BE49: =BD49+$BE$45 -> 0.75
B50: Restructuring & other related charges (segment) | J50: 9.3 | K50: 9.2 | L50: 0.7 | M50: 1.4 | N50: 2.4 | O50: 2.9 | P50: 7.4 | Q50: 1.7 | R50: 1.1 | S50: 4.8 | T50: 4.1 | U50: 11.7 | V50: 8.5 | W50: 2.2 | X50: 1.6 | Y50: 5.3 | Z50: 17.6 | AA50: 1.7 | AB50: 4 | AC50: 1 | AD50: 0.7 | AE50: 7.2 | AF50: 2.8 | AG50: 0.9 | AH50: 2.1 | AI50: 10.3 | AJ50: 16.1 | AK50: 1.2 | AL50: 0 | BB50: MA_spend (bolt-on acquisitions, $m) | BC50: 100 | BD50: Δ → | BE50: -100 | BF50: Base: deleveraging pause in 2027E after Eddyfi; bolt-ons resume 2028E.
B51: Acquisition-amortization & other related charges (segment) | J51: 15.6 | K51: 17 | L51: 4.4 | M51: 4.4 | N51: 4.3 | O51: 4.3 | P51: 17.4 | Q51: 3.6 | R51: 3.4 | S51: 3.3 | T51: 3.9 | U51: 14.1 | V51: 4 | W51: 3.8 | X51: 4 | Y51: 4 | Z51: 15.9 | AA51: 3.3 | AB51: 3.3 | AC51: 5.2 | AD51: 3.9 | AE51: 15.9 | AF51: 4 | AG51: 11.5 | AH51: 10.7 | AI51: 16.6 | AJ51: 42.9 | AK51: 15.1 | AL51: 23.1 | BB51: 2027E | BC51: =BD51+$BC$50 -> 100 | BD51: 0 | BE51: =BD51+$BE$50 -> -100
B52: Depreciation & other amortization (segment) | L52: 6.1 | M52: 5.9 | N52: 5.8 | O52: 5.7 | P52: 23.5 | Q52: 5.5 | R52: 5.5 | S52: 5.1 | T52: 5.4 | U52: 21.5 | V52: 5.3 | W52: 5.2 | X52: 5 | Y52: 5.7 | Z52: 21.2 | AA52: 5.3 | AB52: 5.5 | AC52: 5.7 | AD52: 5.7 | AE52: 22.2 | AF52: 6 | AG52: 7.6 | AH52: 8.1 | AI52: 9.3 | AJ52: 31 | AK52: 8.9 | AL52: 7.6 | BB52: 2028E | BC52: =BD52+$BC$50 -> 250 | BD52: 150 | BE52: =BD52+$BE$50 -> 50
B53: Memo: Russia net sales (excluded from "core") | M53: 44 | N53: 44.2 | O53: 48.8 | P53: 137 | Q53: 40.9 | R53: 29.5 | S53: 43.3 | T53: 49.9 | U53: 122.6 | V53: 37.1 | W53: 40.3 | X53: 36.9 | Y53: 39.4 | Z53: 153.8 | AA53: 33.6 | AB53: 40.7 | AC53: 37.7 | AD53: 37.6 | AE53: 149.6 | AF53: 31.3 | AG53: 37.1 | AH53: 40.4 | AI53: 33.3 | AJ53: 142.2 | AK53: 31.1 | AL53: 41.4 | AM53: =($AK$53+$AL$53)/2 -> 36.25 | AN53: =($AK$53+$AL$53)/2 -> 36.25 | AO53: =SUM(AK53,AL53,AM53,AN53) -> 145 | AP53: =AO53*(1+CHOOSE(MATCH($AT$2,{"Bull","Base","Bear"},0),$BC$31,$BD$31,$BE$31)) -> 145 | AQ53: =AP53*(1+CHOOSE(MATCH($AT$2,{"Bull","Base","Bear"},0),$BC$32,$BD$32,$BE$32)) -> 145 | AR53: =AQ53*(1+CHOOSE(MATCH($AT$2,{"Bull","Base","Bear"},0),$BC$33,$BD$33,$BE$33)) -> 145 | AS53: =AR53*(1+CHOOSE(MATCH($AT$2,{"Bull","Base","Bear"},0),$BC$34,$BD$34,$BE$34)) -> 145 | AT53: ESAB continues to operate in Russia (in-country for in-country); excluded from "core" metrics. Forecast: 1H/26 run-rate, then flat (FX only). | BB53: 2029E | BC53: =BD53+$BC$50 -> 300 | BD53: 200 | BE53: =BD53+$BE$50 -> 100
B54: Memo: Russia adjusted EBITDA | M54: 11.9 | N54: 11.2 | O54: 4.9 | P54: 28 | Q54: 8.4 | R54: 5.5 | S54: 9.5 | T54: 5 | U54: 20 | V54: 5.3 | W54: 5.6 | X54: 4.7 | Y54: 2.7 | Z54: 18.4 | AA54: 5.9 | AB54: 6.9 | AC54: 2.6 | AD54: 2.6 | AE54: 18.1 | AF54: 6 | AG54: 5 | AH54: 6.1 | AI54: 2.5 | AJ54: 19.7 | AK54: 0.7 | AL54: 1.8 | AM54: =($AK$54+$AL$54)/2 -> 1.25 | AN54: =($AK$54+$AL$54)/2 -> 1.25 | AO54: =SUM(AK54,AL54,AM54,AN54) -> 5 | AP54: =AP53*AO54/AO53 -> 5 | AQ54: =AQ53*AP54/AP53 -> 5 | AR54: =AR53*AQ54/AQ53 -> 5 | AS54: =AS53*AR54/AR53 -> 5 | BB54: 2030E | BC54: =BD54+$BC$50 -> 300 | BD54: 200 | BE54: =BD54+$BE$50 -> 100
B56: Product lines (memo; revenue disaggregation — 10-K / 10-Q) | AT56: PRODUCT LINES — historical disclosure only
B57: Equipment net sales | J57: 703.024 | K57: 607.504 | L57: 173.75 | M57: 198.856 | N57: 192.365 | O57: 193.296 | P57: 758.267 | Q57: 188.348 | R57: 190.574 | S57: 168.633 | T57: 193.269 | U57: 740.824 | V57: 200.219 | W57: 226.049 | X57: 209.037 | Y57: 219.644 | Z57: 854.949 | AA57: 214.86 | AB57: 231.659 | AC57: 219.415 | AD57: 227.379 | AE57: 893.313 | AF57: 232.488 | AG57: 231.939 | AH57: 249.948 | AI57: 257.619 | AJ57: 971.994 | AK57: 264.733 | AL57: 313.015 | AV57: =IFERROR((AS57/AJ57)^(1/5)-1,"n/m") -> -1 | AW57: =IFERROR((AJ57/K57)^(1/5)-1,"n/m") -> 0.09855774 | AX57: =IFERROR((AJ57/F57)^(1/10)-1,"n/m") -> n/m | AY57: =IFERROR((AJ57/C57)^(1/13)-1,"n/m") -> n/m
B58: Consumables net sales | J58: 1544.002 | K58: 1342.565 | L58: 394.378 | M58: 430.948 | N58: 413.603 | O58: 430.919 | P58: 1669.848 | Q58: 459.563 | R58: 470.603 | S58: 451.632 | T58: 470.858 | U58: 1852.656 | V58: 483.781 | W58: 494.373 | X58: 471.959 | Y58: 469.704 | Z58: 1919.817 | AA58: 474.884 | AB58: 475.394 | AC58: 453.835 | AD58: 443.377 | AE58: 1847.49 | AF58: 445.65 | AG58: 483.647 | AH58: 477.897 | AI58: 463.367 | AJ58: 1870.561 | AK58: 480.864 | AL58: 494.612 | AV58: =IFERROR((AS58/AJ58)^(1/5)-1,"n/m") -> -1 | AW58: =IFERROR((AJ58/K58)^(1/5)-1,"n/m") -> 0.068580663 | AX58: =IFERROR((AJ58/F58)^(1/10)-1,"n/m") -> n/m | AY58: =IFERROR((AJ58/C58)^(1/13)-1,"n/m") -> n/m
B59: Equipment % of net sales | J59: =IFERROR(J57/(J57+J58),"") -> 0.31286865 | K59: =IFERROR(K57/(K57+K58),"") -> 0.31152949 | L59: =IFERROR(L57/(L57+L58),"") -> 0.30582897 | M59: =IFERROR(M57/(M57+M58),"") -> 0.31574268 | N59: =IFERROR(N57/(N57+N58),"") -> 0.31745076 | O59: =IFERROR(O57/(O57+O58),"") -> 0.30966254 | P59: =IFERROR(P57/(P57+P58),"") -> 0.31228628 | Q59: =IFERROR(Q57/(Q57+Q58),"") -> 0.29070042 | ... AL59: =IFERROR(AL57/(AL57+AL58),"") -> 0.38757372
B61: Pre-spin history (memo): Colfax "Fabrication Technology" segment as reported by Colfax (2012–2021; Colfax 10-K filings) | AT61: COLFAX FABRICATION TECHNOLOGY — ESAB under Colfax ownership (not the carve-out basis); for long-run context only
B62: Fabrication Technology — net sales | C62: 2012.724 | D62: 2103.161 | E62: 2294.878 | F62: 1985.237 | G62: 1800.492 | H62: 1937.282 | I62: 2193.083 | J62: 2247.026 | K62: 1950.069 | P62: 2428.115 | AV62: =IFERROR((AS62/AJ62)^(1/5)-1,"n/m") -> n/m | AW62: =IFERROR((AJ62/K62)^(1/5)-1,"n/m") -> -1 | AX62: =IFERROR((AJ62/F62)^(1/10)-1,"n/m") -> -1 | AY62: =IFERROR((AJ62/C62)^(1/13)-1,"n/m") -> -1
B63: Fabrication Technology — segment operating income (before restructuring & certain other charges) | C63: 140.184 | D63: 219.634 | E63: 265.813 | F63: 198.337 | G63: 195.197 | H63: 224.362 | I63: 249.934 | J63: 302.601 | K63: 246.011 | P63: 356.315
B64: Fabrication Technology — adjusted EBITA (segment operating income + acquisition amortization; disclosed from FY2019 10-K) | H64: 256.3 | I64: 290 | J64: 338.2 | K64: 282.3 | P64: 395.1
B65: Fabrication Technology — organic growth % (existing businesses) | C65: 0.02 | D65: -0.015 | E65: -0.023 | F65: -0.058 | G65: -0.051 | H65: 0.033 | I65: 0.089 | J65: 0.015 | K65: -0.097 | P65: 0.234
B66: Fabrication Technology — acquisitions % | D66: 0.081 | E66: 0.165 | F66: 0.054 | G66: 0.001 | H66: 0.027 | I66: 0.062 | J66: 0.05 | K66: 0 | P66: 0.001
B67: Fabrication Technology — foreign currency % | D67: -0.021 | E67: -0.051 | F67: -0.13 | G67: -0.042 | H67: 0.016 | I67: -0.019 | J67: -0.04 | K67: -0.035 | P67: 0.01
B68: Fabrication Technology — segment operating margin % | C68: =IFERROR(C63/C62,"") -> 0.069648894 | D68: =IFERROR(D63/D62,"") -> 0.10443043 | E68: =IFERROR(E63/E62,"") -> 0.11582882 | F68: =IFERROR(F63/F62,"") -> 0.099905956 | G68: =IFERROR(G63/G62,"") -> 0.10841314 | H68: =IFERROR(H63/H62,"") -> 0.11581277 | I68: =IFERROR(I63/I62,"") -> 0.11396468 | J68: =IFERROR(J63/J62,"") -> 0.13466733 | K68: =IFERROR(K63/K62,"") -> 0.12615502 | P68: =IFERROR(P63/P62,"") -> 0.14674552
B70: EDDYFI TECHNOLOGIES — advanced inspection & monitoring (NDT); acquired 1-Jun-2026 for $1.45bn; reported across both segments | AT70: EDDYFI — modelling logic (closed 1-Jun-2026; in company FY26 guidance)
B71: Memo: Eddyfi standalone net sales (pre-acquisition; not consolidated) | AJ71: 238.8 | AK71: 57.1 | AT71: Eddyfi audited FY2025 (IFRS; continuing operations after the Jun-2025 sale of NDT Global) and unaudited Q1-2026 (8-K/A 6-Aug-2026 Ex. 99.1/99.2). EBITDA = operating income + continuing D&A (IFRS basis; not comparable with ESAB's $80m 2026E adjusted EBITDA).
B72: Memo: Eddyfi standalone EBITDA (pre-acquisition) | AJ72: 77.4 | AK72: 13.8
B73: Days consolidated in period (closing 1-Jun-2026) | AL73: 33 | AM73: 91 | AN73: 90 | AO73: =SUM(AK73,AL73,AM73,AN73) -> 214 | AP73: 365 | AQ73: 365 | AR73: 365 | AS73: 365 | AT73: Q2/26: 1-Jun to 3-Jul (33 days, inside the segment actuals). Q3/26E 91 days, Q4/26E 90 days.
B74: Annual net sales run-rate (standalone basis) | AO74: 270 | AP74: =AO74*(1+AP75) -> 291.6 | AQ74: =AP74*(1+AQ75) -> 314.928 | AR74: =AQ74*(1+AR75) -> 340.12224 | AS74: =AR74*(1+AS75) -> 367.33202 | AT74: 2026E: company deal metric ~$270m 2026E revenue. 2027E+: × (1 + scenario lever EDD_g; company: high-single-digit organic growth).
B75: Sales growth y/y % | AP75: =CHOOSE(MATCH($AT$2,{"Bull","Base","Bear"},0),$BC$36,$BD$36,$BE$36) -> 0.08 | AQ75: =CHOOSE(MATCH($AT$2,{"Bull","Base","Bear"},0),$BC$37,$BD$37,$BE$37) -> 0.08 | AR75: =CHOOSE(MATCH($AT$2,{"Bull","Base","Bear"},0),$BC$38,$BD$38,$BE$38) -> 0.08 | AS75: =CHOOSE(MATCH($AT$2,{"Bull","Base","Bear"},0),$BC$39,$BD$39,$BE$39) -> 0.08
B76: Net sales (consolidated from closing) | AL76: 21.4 | AM76: =$AO$74*AM73/365 -> 67.315068 | AN76: =$AO$74*AN73/365 -> 66.575342 | AO76: =SUM(AK76,AL76,AM76,AN76) -> 155.29041 | AP76: =AP74 -> 291.6 | AQ76: =AQ74 -> 314.928 | AR76: =AR74 -> 340.12224 | AS76: =AS74 -> 367.33202 | AT76: Q2/26 (memo) = June 2026 contribution already inside the segment actuals; Q3/26E onward added in the group build.
B77: Standalone adjusted EBITDA margin % (before synergies) | AO77: 0.2963 | AP77: =CHOOSE(MATCH($AT$2,{"Bull","Base","Bear"},0),$BC$41,$BD$41,$BE$41) -> 0.3 | AQ77: =CHOOSE(MATCH($AT$2,{"Bull","Base","Bear"},0),$BC$42,$BD$42,$BE$42) -> 0.31 | AR77: =CHOOSE(MATCH($AT$2,{"Bull","Base","Bear"},0),$BC$43,$BD$43,$BE$43) -> 0.32 | AS77: =CHOOSE(MATCH($AT$2,{"Bull","Base","Bear"},0),$BC$44,$BD$44,$BE$44) -> 0.32 | AT77: Deal metrics: ~$80m adjusted EBITDA on ~$270m 2026E revenue (29.6%); gross margin > 65%.
B78: (+) Cost synergies realised ($20m run-rate target) | AM78: 0 | AN78: 0 | AO78: =SUM(AK78,AL78,AM78,AN78) -> 0 | AP78: =20*CHOOSE(MATCH($AT$2,{"Bull","Base","Bear"},0),$BC$46,$BD$46,$BE$46) -> 10 | AQ78: =20*CHOOSE(MATCH($AT$2,{"Bull","Base","Bear"},0),$BC$47,$BD$47,$BE$47) -> 20 | AR78: =20*CHOOSE(MATCH($AT$2,{"Bull","Base","Bear"},0),$BC$48,$BD$48,$BE$48) -> 20 | AS78: =20*CHOOSE(MATCH($AT$2,{"Bull","Base","Bear"},0),$BC$49,$BD$49,$BE$49) -> 20 | AT78: Company: $20m annualized run-rate synergies ($100m adjusted EBITDA incl. synergies).
B79: Adjusted EBITDA (consolidated) | AM79: =AM76*$AO$77+AM78 -> 19.945455 | AN79: =AN76*$AO$77+AN78 -> 19.726274 | AO79: =SUM(AK79,AL79,AM79,AN79) -> 39.671729 | AP79: =AP76*AP77+AP78 -> 97.48 | AQ79: =AQ76*AQ77+AQ78 -> 117.62768 | AR79: =AR76*AR77+AR78 -> 128.83912 | AS79: =AS76*AS77+AS78 -> 137.54625
B80: Adjusted EBITDA margin % | AM80: =IFERROR(AM79/AM76,"") -> 0.2963 | AN80: =IFERROR(AN79/AN76,"") -> 0.2963 | AO80: =IFERROR(AO79/AO76,"") -> 0.25546799 | AP80: =IFERROR(AP79/AP76,"") -> 0.33429355 | AQ80: =IFERROR(AQ79/AQ76,"") -> 0.37350658 | AR80: =IFERROR(AR79/AR76,"") -> 0.37880239 | AS80: =IFERROR(AS79/AS76,"") -> 0.37444666
B81: (−) Purchase-accounting amortization of acquired intangibles (added back in adjusted EBITDA / adjusted EPS) | AM81: =57.7*AM73/365 -> 14.385479 | AN81: =57.7*AN73/365 -> 14.227397 | AO81: =SUM(AK81,AL81,AM81,AN81) -> 28.612877 | AP81: 57.7 | AQ81: 52.6 | AR81: 49.2 | AS81: 49.2 | AT81: Pro forma amortization $57.7m p.a. (8-K/A Ex. 99.3 note 8(B)): customer relationships $563m/15–20y ($35.2m), technology $89m/10y ($8.9m), trade names $66m/5–20y ($5.1m), backlog $17m/2y ($8.5m, ends May-2028). Added back in adjusted EBITDA / adjusted EPS.
B82: (−) Inventory fair-value step-up expensed | AM82: 4.6 | AN82: 0 | AO82: =SUM(AK82,AL82,AM82,AN82) -> 4.6 | AP82: 0 | AQ82: 0 | AR82: 0 | AS82: 0 | AT82: $5.9m inventory fair-value step-up (pro forma note 8(A)); ~$1.3m assumed expensed in June, balance in Q3/26E. Added back (acquisition-amortization & other).
B83: Standalone D&A (depreciation & other amortization) % of sales | AM83: 0.015 | AN83: 0.015 | AO83: 0.015 | AP83: 0.015 | AQ83: 0.015 | AR83: 0.015 | AS83: 0.015
B84: Standalone D&A (in depreciation & other amortization) | AM84: =AM76*AM83 -> 1.009726 | AN84: =AN76*AN83 -> 0.99863014 | AO84: =AO76*AO83 -> 2.3293562 | AP84: =AP76*AP83 -> 4.374 | AQ84: =AQ76*AQ83 -> 4.72392 | AR84: =AR76*AR83 -> 5.1018336 | AS84: =AS76*AS83 -> 5.5099803
B86: Future acquisitions (M&A lever — bolt-ons, unallocated; deals closed from 2027E) | AT86: M&A LEVER — acquired sales = spend ÷ EV/sales; mid-year convention
B87: Acquisition spend (USDm, scenario) | AO87: 0 | AP87: =MAX(0,CHOOSE(MATCH($AT$2,{"Bull","Base","Bear"},0),$BC$51,$BD$51,$BE$51)) -> 0 | AQ87: =MAX(0,CHOOSE(MATCH($AT$2,{"Bull","Base","Bear"},0),$BC$52,$BD$52,$BE$52)) -> 150 | AR87: =MAX(0,CHOOSE(MATCH($AT$2,{"Bull","Base","Bear"},0),$BC$53,$BD$53,$BE$53)) -> 200 | AS87: =MAX(0,CHOOSE(MATCH($AT$2,{"Bull","Base","Bear"},0),$BC$54,$BD$54,$BE$54)) -> 200 | AT87: ESAB deployed ~$50–300m p.a. on bolt-ons in 2022–25 (gas control, automation, cutting; e.g. Ohio Medical, SUMIG, Bavaria, DeltaP, Aktiv); Base pauses in 2027E to delever after Eddyfi.
B88: Purchase multiple — EV / sales (x) | AP88: 2 | AQ88: 2 | AR88: 2 | AS88: 2
B89: Annualised sales acquired in the year | AO89: 0 | AP89: =IFERROR(AP87/AP88,0) -> 0 | AQ89: =IFERROR(AQ87/AQ88,0) -> 75 | AR89: =IFERROR(AR87/AR88,0) -> 100 | AS89: =IFERROR(AS87/AS88,0) -> 100
B90: Growth of acquired businesses after acquisition % | AP90: 0.04 | AQ90: 0.04 | AR90: 0.04 | AS90: 0.04
B91: Run-rate sales of businesses acquired (year end) | AO91: 0 | AP91: =AO91*(1+AP90)+AP89 -> 0 | AQ91: =AP91*(1+AQ90)+AQ89 -> 75 | AR91: =AQ91*(1+AR90)+AR89 -> 178 | AS91: =AR91*(1+AS90)+AS89 -> 285.12
B92: Net sales from future acquisitions | AO92: 0 | AP92: =AO91*(1+AP90)+AP89*0.5 -> 0 | AQ92: =AP91*(1+AQ90)+AQ89*0.5 -> 37.5 | AR92: =AQ91*(1+AR90)+AR89*0.5 -> 128 | AS92: =AR91*(1+AS90)+AS89*0.5 -> 235.12
B93: Adjusted EBITDA margin of acquired businesses % | AP93: 0.18 | AQ93: 0.18 | AR93: 0.18 | AS93: 0.18
B94: Adjusted EBITDA from future acquisitions | AO94: 0 | AP94: =AP92*AP93 -> 0 | AQ94: =AQ92*AQ93 -> 6.75 | AR94: =AR92*AR93 -> 23.04 | AS94: =AS92*AS93 -> 42.3216
B95: Depreciation & other amortization % of acquired sales | AP95: 0.02 | AQ95: 0.02 | AR95: 0.02 | AS95: 0.02
B96: Depreciation & other amortization from future acquisitions | AO96: 0 | AP96: =AP92*AP95 -> 0 | AQ96: =AQ92*AQ95 -> 0.75 | AR96: =AR92*AR95 -> 2.56 | AS96: =AS92*AS95 -> 4.7024
B97: PP&E % of spend | AP97: 0.1 | AQ97: 0.1 | AR97: 0.1 | AS97: 0.1
B98: Acquired intangibles % of spend | AP98: 0.45 | AQ98: 0.45 | AR98: 0.45 | AS98: 0.45
B99: Intangible amortization life (years) | AP99: 15 | AQ99: 15 | AR99: 15 | AS99: 15
B100: Cumulative acquired intangibles (gross) | AO100: 0 | AP100: =AO100+AP87*AP98 -> 0 | AQ100: =AP100+AQ87*AQ98 -> 67.5 | AR100: =AQ100+AR87*AR98 -> 157.5 | AS100: =AR100+AS87*AS98 -> 247.5
B101: Amortization of future-acquisition intangibles (adjusted out) | AO101: 0 | AP101: =(AO100+AP87*AP98*0.5)/AP99 -> 0 | AQ101: =(AP100+AQ87*AQ98*0.5)/AQ99 -> 2.25 | AR101: =(AQ100+AR87*AR98*0.5)/AR99 -> 7.5 | AS101: =(AR100+AS87*AS98*0.5)/AS99 -> 13.5
B103: Group Total — net sales & adjusted EBITDA (segment build + Eddyfi) → core (ex-Russia) metrics (ESAB's primary KPIs) | AT103: GROUP TOTAL (CONSOLIDATED) — modelling logic
B104: Net sales (segment build) | J104: =N(J11)+N(J33) -> 2247.026 | K104: =N(K11)+N(K33) -> 1950.069 | L104: =N(L11)+N(L33) -> 568.2 | M104: =N(M11)+N(M33) -> 629.8 | N104: =N(N11)+N(N33) -> 606 | O104: =N(O11)+N(O33) -> 624.2 | P104: =N(P11)+N(P33) -> 2428.1 | Q104: =N(Q11)+N(Q33) -> 647.9 | ... AL104: =N(AL11)+N(AL33) -> 807.6 | AM104: =N(AM11)+N(AM33)+N(AM76) -> 828.09773 | AN104: =N(AN11)+N(AN33)+N(AN76) -> 801.51577 | AO104: =SUM(AK104,AL104,AM104,AN104) -> 3182.8135 | AP104: =N(AP11)+N(AP33)+N(AP76)+N(AP92) -> 3421.8149 | AQ104: =N(AQ11)+N(AQ33)+N(AQ76)+N(AQ92) -> 3588.8901 | AR104: =N(AR11)+N(AR33)+N(AR76)+N(AR92) -> 3808.0954 | AS104: =N(AS11)+N(AS33)+N(AS76)+N(AS92) -> 4049.2662 | AT104: Σ Americas + EMEA & APAC (+ Eddyfi from Q3/26E + future M&A). 2026E = sum of quarters. | AV104: =IFERROR((AS104/AJ104)^(1/5)-1,"n/m") -> 0.073334704 | AW104: =IFERROR((AJ104/K104)^(1/5)-1,"n/m") -> 0.078276397 | AX104: =IFERROR((AJ104/F104)^(1/10)-1,"n/m") -> n/m | AY104: =IFERROR((AJ104/C104)^(1/13)-1,"n/m") -> n/m
B105: Adjusted EBITDA (segment build) | K105: =N(K20)+N(K42) -> 301.146 | L105: =N(L20)+N(L42) -> 94.3 | M105: =N(M20)+N(M42) -> 104.7 | N105: =N(N20)+N(N42) -> 102.5 | O105: =N(O20)+N(O42) -> 102.6 | P105: =N(P20)+N(P42) -> 404.2 | Q105: =N(Q20)+N(Q42) -> 109.3 | R105: =N(R20)+N(R42) -> 110.5 | ... AL105: =N(AL20)+N(AL42) -> 151.3 | AM105: =N(AM20)+N(AM42)+N(AM79) -> 168.8996 | AN105: =N(AN20)+N(AN42)+N(AN79) -> 168.2004 | AO105: =SUM(AK105,AL105,AM105,AN105) -> 625 | AP105: =N(AP20)+N(AP42)+N(AP79)+N(AP94) -> 707.275 | AQ105: =N(AQ20)+N(AQ42)+N(AQ79)+N(AQ94) -> 766.04685 | AR105: =N(AR20)+N(AR42)+N(AR79)+N(AR94) -> 824.6016 | AS105: =N(AS20)+N(AS42)+N(AS79)+N(AS94) -> 884.64263 | AV105: =IFERROR((AS105/AJ105)^(1/5)-1,"n/m") -> 0.095878765 | AW105: =IFERROR((AJ105/K105)^(1/5)-1,"n/m") -> 0.13197189 | AX105: =IFERROR((AJ105/F105)^(1/10)-1,"n/m") -> n/m | AY105: =IFERROR((AJ105/C105)^(1/13)-1,"n/m") -> n/m
...

Sheet Bull-Base-Bear
B2: ESAB Corporation (ESAB) — Bull / Base / Bear Case P&L Summary | J2: Share price ($): | K2: =Model!$AO$419 -> 69.94
B3: Adjusted figures (company definitions: adjusted EBITDA; core adjusted net income / EPS excluding Russia, MCPS if-converted) · USD millions · Live panel linked to Model — toggle scenario via Model!AT2. Bull and Bear panels are value snapshots generated from the Model with the switch set to each case. 2026E includes Eddyfi from 1-Jun-2026; adjusted EBITDA for leverage / EV is pro forma for Eddyfi full year in 2026E. | J3: As of: | K3: =TODAY() -> 2026-10-07 00:00:00
B5: Scenario: | C5: =Model!$AT$2 -> Base | N5: Scenario: | O5: Bull | P5: Snapshot (values) — Model run with switch = Bull | Z5: Scenario: | AA5: Bear | AB5: Snapshot (values) — Model run with switch = Bear
B7: (USDm, except EPS and shares) | C7: 2025A | D7: 2026E | E7: 2027E | F7: 2028E | G7: 2029E | H7: 2030E | I7: 25-'30 CAGR | J7: LT Hist Avg | K7: LT Hist Min | L7: LT Hist Max | N7: (USDm, except EPS and shares) | O7: 2025A | P7: 2026E | Q7: 2027E | R7: 2028E | S7: 2029E | T7: 2030E | U7: 25-'30 CAGR | V7: LT Hist Avg | W7: LT Hist Min | X7: LT Hist Max | Z7: (USDm, except EPS and shares) | AA7: 2025A | AB7: 2026E | AC7: 2027E | AD7: 2028E | AE7: 2029E | AF7: 2030E | AG7: 25-'30 CAGR | AH7: LT Hist Avg | AI7: LT Hist Min | AJ7: LT Hist Max
B9: Net sales | C9: =Model!AJ136 -> 2842.555 | D9: =Model!AO136 -> 3182.8135 | E9: =Model!AP136 -> 3421.8149 | F9: =Model!AQ136 -> 3588.8901 | G9: =Model!AR136 -> 3808.0954 | H9: =Model!AS136 -> 4049.2662 | I9: =IFERROR((H9/C9)^(1/5)-1,"n/m") -> 0.07333055 | N9: Net sales | O9: 2842.555 | P9: 3223.318 | Q9: 3576.8092 | R9: 3894.4028 | S9: 4275.6549 | T9: 4691.3486 | U9: 0.10539569 | Z9: Net sales | AA9: 2842.555 | AB9: 3142.309 | AC9: 3293.9339 | AD9: 3344.4925 | AE9: 3416.1472 | AF9: 3503.3601 | AG9: 0.042689933
B10: Net sales y/y % | D10: =IFERROR(D9/C9-1,"") -> 0.11970164 | E10: =IFERROR(E9/D9-1,"") -> 0.07509124 | F10: =IFERROR(F9/E9-1,"") -> 0.048826494 | G10: =IFERROR(G9/F9-1,"") -> 0.061078857 | H10: =IFERROR(H9/G9-1,"") -> 0.063331076 | N10: Net sales y/y % | P10: 0.13395097 | Q10: 0.10966688 | R10: 0.088792422 | S10: 0.097897446 | T10: 0.097223406 | Z10: Net sales y/y % | AB10: 0.10545231 | AC10: 0.048252693 | AD10: 0.015348999 | AE10: 0.021424684 | AF10: 0.025529622
B11: Core organic growth % (ex-Russia) | C11: =Model!AJ235 -> -0.002 | D11: =Model!AO235 -> 0.012572266 | E11: =Model!AP235 -> 0.033804519 | F11: =Model!AQ235 -> 0.032423932 | G11: =Model!AR235 -> 0.030056437 | H11: =Model!AS235 -> 0.029166863 | N11: Core organic growth % (ex-Russia) | O11: -0.002 | P11: 0.027572266 | Q11: 0.053739088 | R11: 0.05111755 | S11: 0.047809364 | T11: 0.045923584 | Z11: Core organic growth % (ex-Russia) | AA11: -0.002 | AB11: -0.0024277343 | AC11: 0.013871719 | AD11: 0.013346352 | AE11: 0.011377011 | AF11: 0.011206861
B12: Adjusted EBITDA (company definition) | C12: =Model!AJ189 -> 559.726 | D12: =Model!AO189 -> 624.982 | E12: =Model!AP189 -> 707.275 | F12: =Model!AQ189 -> 766.04685 | G12: =Model!AR189 -> 824.6016 | H12: =Model!AS189 -> 884.64263 | I12: =IFERROR((H12/C12)^(1/5)-1,"n/m") -> 0.095868584 | N12: Adjusted EBITDA (company definition) | O12: 559.726 | P12: 629.982 | Q12: 752.37768 | R12: 848.62738 | S12: 948.14669 | T12: 1052.5559 | U12: 0.13462915 | Z12: Adjusted EBITDA (company definition) | AA12: 559.726 | AB12: 619.982 | AC12: 667.53707 | AD12: 696.03497 | AE12: 718.00384 | AF12: 739.89747 | AG12: 0.057399772
B13: Adjusted EBITDA margin % | C13: =Model!AJ190 -> 0.19690947 | D13: =Model!AO190 -> 0.19636149 | E13: =Model!AP190 -> 0.20669587 | F13: =Model!AQ190 -> 0.21344951 | G13: =Model!AR190 -> 0.21653911 | H13: =Model!AS190 -> 0.21846986 | J13: =IFERROR(AVERAGE(Model!J190,Model!K190,Model!P190,Model!U190,Model!Z190,Model!AE190,Model!AJ190),"") -> 0.17387673 | K13: =IFERROR(MIN(Model!J190,Model!K190,Model!P190,Model!U190,Model!Z190,Model!AE190,Model!AJ190),"") -> 0.15442838 | L13: =IFERROR(MAX(Model!J190,Model!K190,Model!P190,Model!U190,Model!Z190,Model!AE190,Model!AJ190),"") -> 0.19690947 | N13: Adjusted EBITDA margin % | O13: 0.19690947 | P13: 0.19544519 | Q13: 0.21034884 | R13: 0.2179095 | S13: 0.22175473 | T13: 0.22436105 | V13: 0.17387673 | W13: 0.15442838 | X13: 0.19690947 | Z13: Adjusted EBITDA margin % | AA13: 0.19690947 | AB13: 0.19730141 | AC13: 0.20265649 | AD13: 0.20811378 | AE13: 0.21017942 | AF13: 0.21119652 | AH13: 0.17387673 | AI13: 0.15442838 | AJ13: 0.19690947
B15: Operating income (GAAP) | C15: =Model!AJ144 -> 412.17 | D15: =Model!AO144 -> 380.08277 | E15: =Model!AP144 -> 501.98734 | F15: =Model!AQ144 -> 578.60307 | G15: =Model!AR144 -> 637.66022 | H15: =Model!AS144 -> 693.23441 | I15: =IFERROR((H15/C15)^(1/5)-1,"n/m") -> 0.10958543 | N15: Operating income (GAAP) | O15: 412.17 | P15: 385.08277 | Q15: 542.89632 | R15: 651.29437 | S15: 745.42184 | T15: 839.25539 | U15: 0.15282544 | Z15: Operating income (GAAP) | AA15: 412.17 | AB15: 375.08277 | AC15: 464.40719 | AD15: 514.28645 | AE15: 542.40145 | AF15: 565.5846 | AG15: 0.065330203
B16: Operating income y/y % | D16: =IFERROR(D15/C15-1,"") -> -0.077849511 | E16: =IFERROR(E15/D15-1,"") -> 0.32073166 | F16: =IFERROR(F15/E15-1,"") -> 0.15262481 | G16: =IFERROR(G15/F15-1,"") -> 0.10206851 | H16: =IFERROR(H15/G15-1,"") -> 0.08715329 | N16: Operating income y/y % | P16: -0.065718594 | Q16: 0.40981723 | R16: 0.1996662 | S16: 0.1445237 | T16: 0.12587979 | Z16: Operating income y/y % | AB16: -0.089980428 | AC16: 0.2381459 | AD16: 0.10740415 | AE16: 0.054667985 | AF16: 0.042741682
B17: Operating margin (GAAP) % | C17: =Model!AJ246 -> 0.14499983 | D17: =Model!AO246 -> 0.11941723 | E17: =Model!AP246 -> 0.14670207 | F17: =Model!AQ246 -> 0.16122061 | G17: =Model!AR246 -> 0.16744859 | H17: =Model!AS246 -> 0.17120001 | J17: =IFERROR(AVERAGE(Model!J246,Model!K246,Model!P246,Model!U246,Model!Z246,Model!AE246,Model!AJ246),"") -> 0.13207439 | K17: =IFERROR(MIN(Model!J246,Model!K246,Model!P246,Model!U246,Model!Z246,Model!AE246,Model!AJ246),"") -> 0.10365069 | L17: =IFERROR(MAX(Model!J246,Model!K246,Model!P246,Model!U246,Model!Z246,Model!AE246,Model!AJ246),"") -> 0.16325508 | N17: Operating margin (GAAP) % | O17: 0.14499983 | P17: 0.11946782 | Q17: 0.1517823 | R17: 0.16723857 | S17: 0.17434097 | T17: 0.17889427 | V17: 0.13207439 | W17: 0.10365069 | X17: 0.16325508 | Z17: Operating margin (GAAP) % | AA17: 0.14499983 | AB17: 0.11936534 | AC17: 0.14098862 | AD17: 0.15377115 | AE17: 0.15877579 | AF17: 0.16144061 | AH17: 0.13207439 | AI17: 0.10365069 | AJ17: 0.16325508
B19: Core adjusted net income (continuing ops, ex-Russia) | C19: =Model!AJ220 -> 324.493 | D19: =Model!AO220 -> 334.79372 | E19: =Model!AP220 -> 389.82392 | F19: =Model!AQ220 -> 441.41024 | G19: =Model!AR220 -> 484.88186 | H19: =Model!AS220 -> 525.1913 | I19: =IFERROR((H19/C19)^(1/5)-1,"n/m") -> 0.10108904 | N19: Core adjusted net income (continuing ops, ex-Russia) | O19: 324.493 | P19: 340.0975 | Q19: 421.87793 | R19: 495.87438 | S19: 556.23746 | T19: 619.43308 | U19: 0.13804075 | Z19: Core adjusted net income (continuing ops, ex-Russia) | AA19: 324.493 | AB19: 329.58993 | AC19: 361.41058 | AD19: 391.24324 | AE19: 411.62064 | AF19: 428.95151 | AG19: 0.057403088
B21: FDSO (m; incl. MCPS if-converted) | C21: =Model!AJ223 -> 61.266294 | D21: =Model!AO223 -> 63.307258 | E21: =Model!AP223 -> 64.065302 | F21: =Model!AQ223 -> 63.712067 | G21: =Model!AR223 -> 62.031076 | H21: =Model!AS223 -> 57.559192 | I21: =IFERROR((H21/C21)^(1/5)-1,"n/m") -> -0.012405609 | N21: FDSO (m; incl. MCPS if-converted) | O21: 61.266294 | P21: 63.307258 | Q21: 63.204293 | R21: 60.010702 | S21: 55.80935 | T21: 50.119013 | U21: -0.039369925 | Z21: FDSO (m; incl. MCPS if-converted) | AA21: 61.266294 | AB21: 63.307258 | AC21: 64.065302 | AD21: 64.365302 | AE21: 64.518148 | AF21: 61.596079 | AG21: 0.0010742534
B23: Core adjusted EPS — Diluted ($) | C23: =Model!AJ227 -> 5.2964359 | D23: =Model!AO227 -> 5.5179078 | E23: =Model!AP227 -> 6.0847902 | F23: =Model!AQ227 -> 6.9282046 | G23: =Model!AR227 -> 7.8167573 | H23: =Model!AS227 -> 9.124369 | I23: =IFERROR((H23/C23)^(1/5)-1,"n/m") -> 0.1149203 | N23: Core adjusted EPS — Diluted ($) | O23: 5.2964359 | P23: 5.6028169 | Q23: 6.6748303 | R23: 8.2630991 | S23: 9.9667432 | T23: 12.359243 | U23: 0.18468157 | Z23: Core adjusted EPS — Diluted ($) | AA23: 5.2964359 | AB23: 5.4345997 | AC23: 5.6412843 | AD23: 6.0784806 | AE23: 6.3799203 | AF23: 6.9639418 | AG23: 0.056268388
B24: EPS y/y % | D24: =IFERROR(D23/C23-1,"") -> 0.041815275 | E24: =IFERROR(E23/D23-1,"") -> 0.10273501 | F24: =IFERROR(F23/E23-1,"") -> 0.13861028 | G24: =IFERROR(G23/F23-1,"") -> 0.1282515 | H24: =IFERROR(H23/G23-1,"") -> 0.16728315 | N24: EPS y/y % | P24: 0.05784664 | Q24: 0.19133471 | R24: 0.23794895 | S24: 0.20617495 | T24: 0.24004835 | Z24: EPS y/y % | AB24: 0.026086172 | AC24: 0.038031248 | AD24: 0.07749944 | AE24: 0.049591285 | AF24: 0.091540566
B26: P / E (x) — assumed (adjusted EPS) | G26: 16 | H26: 16 | N26: P / E (x) — assumed (adjusted EPS) | S26: 19 | T26: 19 | Z26: P / E (x) — assumed (adjusted EPS) | AD26: 13 | AE26: 13 | AF26: 13
B27: Price Target ($) | G27: =G26*G23 -> 125.06812 | H27: =H26*H23 -> 145.9899 | N27: Price Target ($) | S27: =S26*S23 -> 189.36812 | T27: =T26*T23 -> 234.82563 | Z27: Price Target ($) | AD27: =AD26*AD23 -> 79.020248 | AE27: =AE26*AE23 -> 82.938964 | AF27: =AF26*AF23 -> 90.531244
B28: Upside / (Downside) vs current | G28: =IFERROR(G27/$K$2-1,"") -> 0.78822013 | H28: =IFERROR(H27/$K$2-1,"") -> 1.0873592 | N28: Upside / (Downside) vs current | S28: =IFERROR(S27/$K$2-1,"") -> 1.7075796 | T28: =IFERROR(T27/$K$2-1,"") -> 2.3575297 | Z28: Upside / (Downside) vs current | AD28: =IFERROR(AD27/$K$2-1,"") -> 0.12982911 | AE28: =IFERROR(AE27/$K$2-1,"") -> 0.18585879 | AF28: =IFERROR(AF27/$K$2-1,"") -> 0.29441298
B29: IRR (to Dec-Y-1) | G29: =IFERROR((G27/$K$2)^(1/((DATE(2029-1,12,31)-$K$3)/365.25))-1,"") -> 0.29713814 | H29: =IFERROR((H27/$K$2)^(1/((DATE(2030-1,12,31)-$K$3)/365.25))-1,"") -> 0.25557425 | N29: IRR (to Dec-Y-1) | S29: =IFERROR((S27/$K$2)^(1/((DATE(2029-1,12,31)-$K$3)/365.25))-1,"") -> 0.56180862 | T29: =IFERROR((T27/$K$2)^(1/((DATE(2030-1,12,31)-$K$3)/365.25))-1,"") -> 0.45439747 | Z29: IRR (to Dec-Y-1) | AD29: =IFERROR((AD27/$K$2)^(1/((DATE(2028-1,12,31)-$K$3)/365.25))-1,"") -> 0.10415156 | AE29: =IFERROR((AE27/$K$2)^(1/((DATE(2029-1,12,31)-$K$3)/365.25))-1,"") -> 0.079289427 | AF29: =IFERROR((AF27/$K$2)^(1/((DATE(2030-1,12,31)-$K$3)/365.25))-1,"") -> 0.083081094
B31: Free Cash Flow | C31: =Model!AJ281 -> 213.28 | D31: =Model!AO281 -> 255.64936 | E31: =Model!AP281 -> 378.62344 | F31: =Model!AQ281 -> 441.30207 | G31: =Model!AR281 -> 479.26273 | H31: =Model!AS281 -> 518.12534 | I31: =IFERROR((H31/C31)^(1/5)-1,"n/m") -> 0.19425465 | N31: Free Cash Flow | O31: 213.28 | P31: 252.30229 | Q31: 401.71571 | R31: 484.13898 | S31: 539.42725 | T31: 601.54987 | U31: 0.23045093 | Z31: Free Cash Flow | AA31: 213.28 | AB31: 259.09646 | AC31: 357.02467 | AD31: 400.54947 | AE31: 417.05197 | AF31: 432.1005 | AG31: 0.15166701
B32: FCF % | C32: =Model!AJ284 -> 0.07503109 | D32: =Model!AO284 -> 0.080321817 | E32: =Model!AP284 -> 0.11064989 | F32: =Model!AQ284 -> 0.12296338 | G32: =Model!AR284 -> 0.12585366 | H32: =Model!AS284 -> 0.12795537 | J32: =IFERROR(AVERAGE(Model!J284,Model!K284,Model!P284,Model!U284,Model!Z284,Model!AE284,Model!AJ284),"") -> 0.096094779 | K32: =IFERROR(MIN(Model!J284,Model!K284,Model!P284,Model!U284,Model!Z284,Model!AE284,Model!AJ284),"") -> 0.067135663 | L32: =IFERROR(MAX(Model!J284,Model!K284,Model!P284,Model!U284,Model!Z284,Model!AE284,Model!AJ284),"") -> 0.13796589 | N32: FCF % | O32: 0.07503109 | P32: 0.078274091 | Q32: 0.11231119 | R32: 0.12431662 | S32: 0.12616249 | T32: 0.12822536 | V32: 0.096094779 | W32: 0.067135663 | X32: 0.13796589 | Z32: FCF % | AA32: 0.07503109 | AB32: 0.082454165 | AC32: 0.10838854 | AD32: 0.1197639 | AE32: 0.12208255 | AF32: 0.12333888 | AH32: 0.096094779 | AI32: 0.067135663 | AJ32: 0.13796589
B33: FCF / share ($) | C33: =IFERROR(C31/C21,"") -> 3.4811964 | D33: =IFERROR(D31/D21,"") -> 4.0382315 | E33: =IFERROR(E31/E21,"") -> 5.909961 | F33: =IFERROR(F31/F21,"") -> 6.9265069 | G33: =IFERROR(G31/G21,"") -> 7.7261715 | H33: =IFERROR(H31/H21,"") -> 9.0016091 | N33: FCF / share ($) | O33: 3.4811964 | P33: 3.9853611 | Q33: 6.3558295 | R33: 8.0675439 | S33: 9.6655355 | T33: 12.002429 | Z33: FCF / share ($) | AA33: 3.4811964 | AB33: 4.0926818 | AC33: 5.5728243 | AD33: 6.2230651 | AE33: 6.4641032 | AF33: 7.015065
B34: FCF Yield (on PT) | F34: =IFERROR(F33/F$27,"") | G34: =IFERROR(G33/G$27,"") -> 0.061775709 | H34: =IFERROR(H33/H$27,"") -> 0.061659121 | N34: FCF Yield (on PT) | R34: =IFERROR(R33/R$27,"") | S34: =IFERROR(S33/S$27,"") -> 0.051040985 | T34: =IFERROR(T33/T$27,"") -> 0.05111209 | Z34: FCF Yield (on PT) | AD34: =IFERROR(AD33/AD$27,"") -> 0.078752791 | AE34: =IFERROR(AE33/AE$27,"") -> 0.077938076 | AF34: =IFERROR(AF33/AF$27,"") -> 0.077487779
B35: Adjusted EBITDA — pro forma (2026E incl. Eddyfi full year) | C35: =Model!AJ415 -> 559.726 | D35: =Model!AO415 -> 658.0783 | E35: =Model!AP415 -> 707.275 | F35: =Model!AQ415 -> 766.04685 | G35: =Model!AR415 -> 824.6016 | H35: =Model!AS415 -> 884.64263 | I35: =IFERROR((H35/C35)^(1/5)-1,"n/m") -> 0.095868584 | N35: Adjusted EBITDA — pro forma (2026E incl. Eddyfi full year) | O35: 559.726 | P35: 663.0783 | Q35: 752.37768 | R35: 848.62738 | S35: 948.14669 | T35: 1052.5559 | U35: 0.13462915 | Z35: Adjusted EBITDA — pro forma (2026E incl. Eddyfi full year) | AA35: 559.726 | AB35: 653.0783 | AC35: 667.53707 | AD35: 696.03497 | AE35: 718.00384 | AF35: 739.89747 | AG35: 0.057399772
B36: Adjusted EBITDA (pro forma) % of net sales | C36: =IFERROR(C35/C9,"") -> 0.19690947 | D36: =IFERROR(D35/D9,"") -> 0.20675993 | E36: =IFERROR(E35/E9,"") -> 0.20669587 | F36: =IFERROR(F35/F9,"") -> 0.21344951 | G36: =IFERROR(G35/G9,"") -> 0.21653911 | H36: =IFERROR(H35/H9,"") -> 0.21846986 | J36: =IFERROR(AVERAGE(Model!J190,Model!K190,Model!P190,Model!U190,Model!Z190,Model!AE190,Model!AJ190),"") -> 0.17387673 | K36: =IFERROR(MIN(Model!J190,Model!K190,Model!P190,Model!U190,Model!Z190,Model!AE190,Model!AJ190),"") -> 0.15442838 | L36: =IFERROR(MAX(Model!J190,Model!K190,Model!P190,Model!U190,Model!Z190,Model!AE190,Model!AJ190),"") -> 0.19690947 | N36: Adjusted EBITDA (pro forma) % of net sales | O36: 0.19690947 | P36: 0.20571297 | Q36: 0.21034884 | R36: 0.2179095 | S36: 0.22175473 | T36: 0.22436105 | V36: 0.17387673 | W36: 0.15442838 | X36: 0.19690947 | Z36: Adjusted EBITDA (pro forma) % of net sales | AA36: 0.19690947 | AB36: 0.20783389 | AC36: 0.20265649 | AD36: 0.20811378 | AE36: 0.21017942 | AF36: 0.21119652 | AH36: 0.17387673 | AI36: 0.15442838 | AJ36: 0.19690947
B38: Net Debt | C38: =Model!AJ414 -> 1049.089 | D38: =Model!AO414 -> 1993.6474 | E38: =Model!AP414 -> 1657.9064 | F38: =Model!AQ414 -> 1519.3837 | G38: =Model!AR414 -> 1636.4932 | H38: =Model!AS414 -> 1756.5753 | N38: Net Debt | O38: 1049.089 | P38: 1996.9945 | Q38: 1868.2342 | R38: 2108.8584 | S38: 2357.6567 | T38: 2618.6797 | Z38: Net Debt | AA38: 1049.089 | AB38: 1990.2003 | AC38: 1676.058 | AD38: 1371.7087 | AE38: 1243.7967 | AF38: 1282.1106
B39: Net Debt / Adjusted EBITDA (x) | C39: =IFERROR(C38/C35,"") -> 1.8742903 | D39: =IFERROR(D38/D35,"") -> 3.0294987 | E39: =IFERROR(E38/E35,"") -> 2.344076 | F39: =IFERROR(F38/F35,"") -> 1.9834083 | G39: =IFERROR(G38/G35,"") -> 1.9845865 | H39: =IFERROR(H38/H35,"") -> 1.9856326 | N39: Net Debt / Adjusted EBITDA (x) | O39: 1.8742903 | P39: 3.0117023 | Q39: 2.4831069 | R39: 2.4850229 | S39: 2.4865949 | T39: 2.4879246 | Z39: Net Debt / Adjusted EBITDA (x) | AA39: 1.8742903 | AB39: 3.0474145 | AC39: 2.510809 | AD39: 1.9707469 | AE39: 1.7322981 | AF39: 1.7328219
B40: Share repurchases ($m) | D40: =Model!AO293 -> 0 | E40: =Model!AP293 -> 0 | F40: =Model!AQ293 -> 106.57922 | G40: =Model!AR293 -> 352.99079 | H40: =Model!AS293 -> 398.3332 | N40: Share repurchases ($m) | P40: 0 | Q40: 130.073 | R40: 429.52154 | S40: 448.32215 | T40: 527.25326
B41: Implied avg buyback price ($) | D41: =Model!AO292 -> 69.94 | E41: =Model!AP292 -> 75.5352 | F41: =Model!AQ292 -> 81.578016 | G41: =Model!AR292 -> 88.104257 | H41: =Model!AS292 -> 95.152598 | N41: Implied avg buyback price ($) | P41: 69.94 | Q41: 75.5352 | R41: 81.578016 | S41: 88.104257 | T41: 95.152598
B42: Shares repurchased (m) | D42: =Model!AO294 -> 0 | E42: =Model!AP294 -> 0 | F42: =Model!AQ294 -> 1.3064699 | G42: =Model!AR294 -> 4.0065123 | H42: =Model!AS294 -> 4.1862567 | N42: Shares repurchased (m) | P42: 0 | Q42: 1.7220184 | R42: 5.2651629 | S42: 5.0885413 | T42: 5.5411336
B44: ROIC | C44: =Model!AJ397 -> 0.12395001 | D44: =Model!AO397 -> 0.094723216 | E44: =Model!AP397 -> 0.1077261 | F44: =Model!AQ397 -> 0.11473909 | G44: =Model!AR397 -> 0.11986751 | H44: =Model!AS397 -> 0.12487139 | J44: =IFERROR(AVERAGE(Model!J397,Model!K397,Model!P397,Model!U397,Model!Z397,Model!AE397,Model!AJ397),"") -> 0.11895184 | K44: =IFERROR(MIN(Model!J397,Model!K397,Model!P397,Model!U397,Model!Z397,Model!AE397,Model!AJ397),"") -> 0.081782149 | L44: =IFERROR(MAX(Model!J397,Model!K397,Model!P397,Model!U397,Model!Z397,Model!AE397,Model!AJ397),"") -> 0.14780085 | N44: ROIC | O44: 0.12395001 | P44: 0.096050737 | Q44: 0.11189622 | R44: 0.12138919 | S44: 0.12904685 | T44: 0.1366238 | V44: 0.11895184 | W44: 0.081782149 | X44: 0.14780085 | Z44: ROIC | AA44: 0.12395001 | AB44: 0.093424302 | AC44: 0.10186496 | AD44: 0.10692429 | AE44: 0.10950985 | AF44: 0.11196308 | AH44: 0.11895184 | AI44: 0.081782149 | AJ44: 0.14780085
B45: RONTA | C45: =Model!AJ408 -> 0.27289074 | D45: =Model!AO408 -> 0.27373304 | E45: =Model!AP408 -> 0.27163673 | F45: =Model!AQ408 -> 0.26791248 | G45: =Model!AR408 -> 0.29725975 | H45: =Model!AS408 -> 0.32874601 | J45: =IFERROR(AVERAGE(Model!J408,Model!K408,Model!P408,Model!U408,Model!Z408,Model!AE408,Model!AJ408),"") -> 0.29044232 | K45: =IFERROR(MIN(Model!J408,Model!K408,Model!P408,Model!U408,Model!Z408,Model!AE408,Model!AJ408),"") -> 0.2569119 | L45: =IFERROR(MAX(Model!J408,Model!K408,Model!P408,Model!U408,Model!Z408,Model!AE408,Model!AJ408),"") -> 0.33757774 | N45: RONTA | O45: 0.27289074 | P45: 0.27657469 | Q45: 0.31518812 | R45: 0.34187961 | S45: 0.36452615 | T45: 0.38576945 | V45: 0.29044232 | W45: 0.2569119 | X45: 0.33757774 | Z45: RONTA | AA45: 0.27289074 | AB45: 0.27095759 | AC45: 0.26090297 | AD45: 0.23044184 | AE45: 0.22110257 | AF45: 0.22816399 | AH45: 0.29044232 | AI45: 0.2569119 | AJ45: 0.33757774
B47: Implied Market Cap (USDm) | F47: =F27*F21 -> 0 | G47: =G27*G21 -> 7758.1098 | H47: =H27*H21 -> 8403.0608 | N47: Implied Market Cap (USDm) | R47: =R27*R21 -> 0 | S47: =S27*S21 -> 10568.512 | T47: =T27*T21 -> 11769.228 | Z47: Implied Market Cap (USDm) | AD47: =AD27*AD21 -> 5086.1621 | AE47: =AE27*AE21 -> 5351.0684 | AF47: =AF27*AF21 -> 5576.3697
B48: (+) Net Debt & NCI | F48: =F38+Model!AQ328+Model!AQ424 -> 1636.9628 | G48: =G38+Model!AR328+Model!AR424 -> 1761.7942 | H48: =H38+Model!AS328+Model!AS424 -> 1890.0872 | N48: (+) Net Debt & NCI | R48: =R38+Model!AQ328+Model!AQ424 -> 2226.4375 | S48: =S38+Model!AR328+Model!AR424 -> 2482.9577 | T48: =T38+Model!AS328+Model!AS424 -> 2752.1917 | Z48: (+) Net Debt & NCI | AD48: =AD38+Model!AQ328+Model!AQ424 -> 1489.2878 | AE48: =AE38+Model!AR328+Model!AR424 -> 1369.0977 | AF48: =AF38+Model!AS328+Model!AS424 -> 1415.6225
B49: Implied Enterprise Value (USDm) | F49: =F47+F48 -> 1636.9628 | G49: =G47+G48 -> 9519.904 | H49: =H47+H48 -> 10293.148 | N49: Implied Enterprise Value (USDm) | R49: =R47+R48 -> 2226.4375 | S49: =S47+S48 -> 13051.469 | T49: =T47+T48 -> 14521.42 | Z49: Implied Enterprise Value (USDm) | AD49: =AD47+AD48 -> 6575.45 | AE49: =AE47+AE48 -> 6720.1661 | AF49: =AF47+AF48 -> 6991.9922
B50: Implied EV / Adjusted EBITDA (x) | F50: =IFERROR(F49/F35,"") -> 2.1368964 | G50: =IFERROR(G49/G35,"") -> 11.544853 | H50: =IFERROR(H49/H35,"") -> 11.635374 | N50: Implied EV / Adjusted EBITDA (x) | R50: =IFERROR(R49/R35,"") -> 2.6235749 | S50: =IFERROR(S49/S35,"") -> 13.765243 | T50: =IFERROR(T49/T35,"") -> 13.796341 | Z50: Implied EV / Adjusted EBITDA (x) | AD50: =IFERROR(AD49/AD35,"") -> 9.4470109 | AE50: =IFERROR(AE49/AE35,"") -> 9.3595128 | AF50: =IFERROR(AF49/AF35,"") -> 9.4499474

Sheet DCF
B2: DCF VALUATION — ESAB CORPORATION (ESAB)
B4: 1. WACC BUILD
B5: Risk-free rate (US 10Y govt) | C5: 0.055 | D5: Assumption (~US 10Y Treasury yield); update to market
B6: Equity risk premium | C6: 0.05 | D6: US implied ERP ~4.5–5.5% (Damodaran)
B7: Levered beta | C7: 1.2 | D7: Welding / fabrication peers (Lincoln Electric, ITW, Kennametal) ~1.0–1.2; higher financial leverage post-Eddyfi (~3x) and Europe / emerging-market exposure → 1.2
B8: Cost of equity | C8: =C5+C7*C6 -> 0.115
B9: Pre-tax cost of debt | C9: 0.058 | D9: BB-rated senior unsecured notes: 6.25% 2029, 5.625% 2031 (Mar-2026); TLA / revolver SOFR + 1.125–1.75%; marginal cost ~5.75–6.0%
B10: Tax rate | C10: 0.235 | D10: Model 2027E+ effective tax rate
B11: After-tax cost of debt | C11: =C9*(1-C10) -> 0.04437
B12: Target D/V | C12: 0.35 | D12: Net debt ~$2.1bn at YE2026E vs ~$4.3bn market cap ($69.94 × ~62m shares); target leverage < 3.0x YE26, ~2x medium term
B13: WACC | C13: =C8*(1-C12)+C11*C12 -> 0.0902795
B15: Valuation date (live) | C15: =TODAY() -> 2026-10-07 00:00:00 | D15: Periods = (Dec-31-Year − today) / 365.25; cash flows assumed at year-end
B16: 2. UNLEVERED FREE CASH FLOW BUILD (USDm)
D17: 2026E | E17: 2027E | F17: 2028E | G17: 2029E | H17: 2030E | I17: 2031E | J17: 2032E | K17: 2033E | L17: 2034E | M17: 2035E | N17: Terminal | P17: CAGR 26–30E | Q17: CAGR 26–35E
B18: Adj. EBITA less restructuring, transaction & integration costs (cash items) | D18: =Model!AO200-Model!AO142-Model!AO130 -> 472.59564 | E18: =Model!AP200-Model!AP142-Model!AP130 -> 614.68734 | F18: =Model!AQ200-Model!AQ142-Model!AQ130 -> 685.55307 | G18: =Model!AR200-Model!AR142-Model!AR130 -> 741.16022 | H18: =Model!AS200-Model!AS142-Model!AS130 -> 796.83441 | I18: =H18*(1+I$26) -> 844.64448 | J18: =I18*(1+J$26) -> 892.15573 | K18: =J18*(1+K$26) -> 938.9939 | L18: =K18*(1+L$26) -> 984.76986 | M18: =L18*(1+M$26) -> 1029.0845 | P18: =(H18/D18)^(1/(COLUMNS(D18:H18)-1))-1 -> 0.13951381 | Q18: =(M18/D18)^(1/(COLUMNS(D18:M18)-1))-1 -> 0.09031317
B19: × (1 − tax rate) | D19: =1-$C$10 -> 0.765 | E19: =1-$C$10 -> 0.765 | F19: =1-$C$10 -> 0.765 | G19: =1-$C$10 -> 0.765 | H19: =1-$C$10 -> 0.765 | I19: =1-$C$10 -> 0.765 | J19: =1-$C$10 -> 0.765 | K19: =1-$C$10 -> 0.765 | ... M19: =1-$C$10 -> 0.765
B20: NOPAT | D20: =D18*D19 -> 361.53567 | E20: =E18*E19 -> 470.23582 | F20: =F18*F19 -> 524.4481 | G20: =G18*G19 -> 566.98757 | H20: =H18*H19 -> 609.57832 | I20: =I18*I19 -> 646.15302 | J20: =J18*J19 -> 682.49913 | K20: =K18*K19 -> 718.33034 | ... M20: =M18*M19 -> 787.24964
B21: plus depreciation & other amortization | D21: =Model!AO127 -> 52.808356 | E21: =Model!AP127 -> 57.587654 | F21: =Model!AQ127 -> 60.493776 | G21: =Model!AR127 -> 64.441378 | H21: =Model!AS127 -> 68.808222 | I21: =H21*(1+I$26) -> 72.936715 | J21: =I21*(1+J$26) -> 77.039405 | K21: =J21*(1+K$26) -> 81.083974 | L21: =K21*(1+L$26) -> 85.036818 | M21: =L21*(1+M$26) -> 88.863475
B22: − Capex and acquisitions (M&A 2027E–30E) | D22: =Model!AO260 -> -70 | E22: =Model!AP260+Model!AP261 -> -75.279928 | F22: =Model!AQ260+Model!AQ261 -> -228.95558 | G22: =Model!AR260+Model!AR261 -> -283.7781 | H22: =Model!AS260+Model!AS261 -> -289.08386 | I22: =Model!AS260*(1+I$26) -> -94.428888 | J22: =I22*(1+J$26) -> -99.740513 | K22: =J22*(1+K$26) -> -104.97689 | L22: =K22*(1+L$26) -> -110.09451 | M22: =L22*(1+M$26) -> -115.04877
B23: − Δ Working capital (CF statement) | D23: =Model!AO258 -> -11.393119 | E23: =Model!AP258 -> -13.386644 | F23: =Model!AQ258 -> -12.969574 | G23: =Model!AR258 -> -19.406954 | H23: =Model!AS258 -> -21.995519 | I23: =H23*(1+I$26) -> -23.31525 | J23: =I23*(1+J$26) -> -24.626733 | K23: =J23*(1+K$26) -> -25.919636 | L23: =K23*(1+L$26) -> -27.183218 | M23: =L23*(1+M$26) -> -28.406463
B24: Unlevered FCF | D24: =D20+D21+D22+D23 -> 332.9509 | E24: =E20+E21+E22+E23 -> 439.1569 | F24: =F20+F21+F22+F23 -> 343.01672 | G24: =G20+G21+G22+G23 -> 328.2439 | H24: =H20+H21+H22+H23 -> 367.30717 | I24: =I20+I21+I22+I23 -> 601.3456 | J24: =J20+J21+J22+J23 -> 635.17129 | K24: =K20+K21+K22+K23 -> 668.51778 | ... M24: =M20+M21+M22+M23 -> 732.65789 | N24: =M24*(1+$C$27) -> 758.30091 | P24: =(H24/D24)^(1/(COLUMNS(D24:H24)-1))-1 -> 0.024854711 | Q24: =(M24/D24)^(1/(COLUMNS(D24:M24)-1))-1 -> 0.091585837
B25: Terminal Value (Gordon Growth) | N25: =N24/($C$13-$C$27) -> 13717.579
B26: Fade-period growth (2031E–35E; 6% → 4.5% linear) | I26: 0.06 | J26: =I26+($M$26-$I$26)/4 -> 0.05625 | K26: =J26+($M$26-$I$26)/4 -> 0.0525 | L26: =K26+($M$26-$I$26)/4 -> 0.04875 | M26: 0.045
B27: Terminal growth rate | C27: 0.035
B29: Discount period (years) | D29: =(DATE(2026,12,31)-$C$15)/365.25 -> 0.23271732 | E29: =(DATE(2027,12,31)-$C$15)/365.25 -> 1.2320329 | F29: =(DATE(2028,12,31)-$C$15)/365.25 -> 2.2340862 | G29: =(DATE(2029,12,31)-$C$15)/365.25 -> 3.2334018 | H29: =(DATE(2030,12,31)-$C$15)/365.25 -> 4.2327173 | I29: =(DATE(2031,12,31)-$C$15)/365.25 -> 5.2320329 | J29: =(DATE(2032,12,31)-$C$15)/365.25 -> 6.2340862 | K29: =(DATE(2033,12,31)-$C$15)/365.25 -> 7.2334018 | L29: =(DATE(2034,12,31)-$C$15)/365.25 -> 8.2327173 | M29: =(DATE(2035,12,31)-$C$15)/365.25 -> 9.2320329 | N29: =M29 -> 9.2320329
B30: Discount factor | D30: =1/(1+$C$13)^D29 -> 0.98008624 | E30: =1/(1+$C$13)^E29 -> 0.89898437 | F30: =1/(1+$C$13)^F29 -> 0.82439854 | G30: =1/(1+$C$13)^G29 -> 0.75617978 | H30: =1/(1+$C$13)^H29 -> 0.69360611 | I30: =1/(1+$C$13)^I29 -> 0.63621039 | J30: =1/(1+$C$13)^J29 -> 0.58342607 | K30: =1/(1+$C$13)^K29 -> 0.53514772 | ... N30: =1/(1+$C$13)^N29 -> 0.45024549
B31: PV of UFCF | D31: =D24*D30 -> 326.3206 | E31: =E24*E30 -> 394.79519 | F31: =F24*F30 -> 282.78248 | G31: =G24*G30 -> 248.2114 | H31: =H24*H30 -> 254.7665 | I31: =I24*I30 -> 382.58232 | J31: =J24*J30 -> 370.57549 | K31: =K24*K30 -> 357.75576 | ... M31: =M24*M30 -> 329.87591 | N31: =N25*N30 -> 6176.2781
D32: ESAB-specific: adjusted EBITA excludes amortization of acquired intangibles (Eddyfi PPA ~$58m p.a.) and the performance option awards; NOPAT is struck on adjusted EBITA less cash restructuring and integration costs (row 18). Eddyfi cash consideration (closed 1-Jun-2026) sits in YE2026E net debt, not in UFCF. Acquisition spend from the M&A lever is deducted in 2027E–30E. Asbestos liabilities of divested Colfax businesses (net of insurance, ~$55m) are deducted as a debt-like item; MCPS conversion shares are included in the diluted share count.
B33: IMPLIED ROIC — invested capital roll-forward (USDm)
B34: Opening invested capital | D34: =Model!AJ394+Model!AO352 -> 4754.618 | E34: =D38 -> 4783.2028 | F34: =E38 -> 4814.2817 | G34: =F38 -> 4995.7131 | H34: =G38 -> 5234.4567 | I34: =H38 -> 5476.7279 | J34: =I38 -> 5521.5353 | K34: =J38 -> 5568.8632 | L34: =K38 -> 5618.6757 | M34: =L38 -> 5670.9166
B35: plus Capex and acquisitions | D35: =-D22 -> 70 | E35: =-E22 -> 75.279928 | F35: =-F22 -> 228.95558 | G35: =-G22 -> 283.7781 | H35: =-H22 -> 289.08386 | I35: =-I22 -> 94.428888 | J35: =-J22 -> 99.740513 | K35: =-K22 -> 104.97689 | ... M35: =-M22 -> 115.04877
B36: less DD&A | D36: =-D21 -> -52.808356 | E36: =-E21 -> -57.587654 | F36: =-F21 -> -60.493776 | G36: =-G21 -> -64.441378 | H36: =-H21 -> -68.808222 | I36: =-I21 -> -72.936715 | J36: =-J21 -> -77.039405 | K36: =-K21 -> -81.083974 | ... M36: =-M21 -> -88.863475
B37: plus Δ Working capital investment | D37: =-D23 -> 11.393119 | E37: =-E23 -> 13.386644 | F37: =-F23 -> 12.969574 | G37: =-G23 -> 19.406954 | H37: =-H23 -> 21.995519 | I37: =-I23 -> 23.31525 | J37: =-J23 -> 24.626733 | K37: =-K23 -> 25.919636 | ... M37: =-M23 -> 28.406463
B38: Closing invested capital | D38: =SUM(D34:D37) -> 4783.2028 | E38: =SUM(E34:E37) -> 4814.2817 | F38: =SUM(F34:F37) -> 4995.7131 | G38: =SUM(G34:G37) -> 5234.4567 | H38: =SUM(H34:H37) -> 5476.7279 | I38: =SUM(I34:I37) -> 5521.5353 | J38: =SUM(J34:J37) -> 5568.8632 | K38: =SUM(K34:K37) -> 5618.6757 | ... M38: =SUM(M34:M37) -> 5725.5084
B39: NOPAT (row 20) | D39: =D20 -> 361.53567 | E39: =E20 -> 470.23582 | F39: =F20 -> 524.4481 | G39: =G20 -> 566.98757 | H39: =H20 -> 609.57832 | I39: =I20 -> 646.15302 | J39: =J20 -> 682.49913 | K39: =K20 -> 718.33034 | ... M39: =M20 -> 787.24964
B40: Implied ROIC (NOPAT / avg. invested capital) | D40: =IFERROR(D39/AVERAGE(D34,D38),"") -> 0.075810959 | E40: =IFERROR(E39/AVERAGE(E34,E38),"") -> 0.097991473 | F40: =IFERROR(F39/AVERAGE(F34,F38),"") -> 0.10692118 | G40: =IFERROR(G39/AVERAGE(G34,G38),"") -> 0.11084617 | H40: =IFERROR(H39/AVERAGE(H34,H38),"") -> 0.1138209 | I40: =IFERROR(I39/AVERAGE(I34,I38),"") -> 0.11750092 | J40: =IFERROR(J39/AVERAGE(J34,J38),"") -> 0.12307928 | K40: =IFERROR(K39/AVERAGE(K34,K38),"") -> 0.12841615 | ... M40: =IFERROR(M39/AVERAGE(M34,M38),"") -> 0.1381573
B41: Reinvestment rate (net investment / NOPAT) | D41: =IFERROR(SUM(D35:D37)/D39,"") -> 0.079064849 | E41: =IFERROR(SUM(E35:E37)/E39,"") -> 0.066092198 | F41: =IFERROR(SUM(F35:F37)/F39,"") -> 0.34594726 | G41: =IFERROR(SUM(G35:G37)/G39,"") -> 0.42107391 | H41: =IFERROR(SUM(H35:H37)/H39,"") -> 0.39744057 | I41: =IFERROR(SUM(I35:I37)/I39,"") -> 0.06934491 | J41: =IFERROR(SUM(J35:J37)/J39,"") -> 0.06934491 | K41: =IFERROR(SUM(K35:K37)/K39,"") -> 0.06934491 | ... M41: =IFERROR(SUM(M35:M37)/M39,"") -> 0.06934491
B42: Implied terminal RONIC (g / reinvestment rate) | N42: =IFERROR($C$27/M41,"") -> 0.50472342
D43: Opening IC = Model 2025A book invested capital (equity + net debt) + Eddyfi consideration ($1.49bn), rolled forward with capex + M&A − D&A + ΔWC.
B44: 3. VALUATION SUMMARY
B45: Sum of PV (explicit + fade) | C45: =SUM(D31:M31) -> 3291.8146
B46: PV of Terminal Value | C46: =N31 -> 6176.2781
B47: Enterprise Value | C47: =C45+C46 -> 9468.0927
B48: Less: Net debt + NCI + net asbestos (Model 2026E YE, post-Eddyfi) | C48: =Model!AO414+Model!AO328+Model!AO424 -> 2097.0104 | D48: ESAB-specific: NCI (~$40m) and net asbestos liabilities (~$55m) deducted alongside net debt; YE2026E net debt includes the Eddyfi purchase price.
B49: Equity Value | C49: =C47-C48 -> 7371.0823
B50: Diluted shares (m, Model 2026E incl. MCPS conversion shares) | C50: =Model!AO420 -> 63.962298
B51: Implied share price ($) | C51: =C49/C50 -> 115.24105
B52: Current share price ($) | C52: =Model!AO419 -> 69.94
B53: Implied upside / (downside) | C53: =C51/C52-1 -> 0.64771303
B54: Required discount to DCF value for target IRR | C54: =1-((1+C13)/(1+H54))^H55 -> 0.14784221 | D54: vs. current | E54: Target IRR | H54: 0.15
B55: Max entry price for target IRR ($) | C55: =C51*(1-C54) -> 98.203558 | D55: =C55/C52-1 -> 0.40411149 | E55: Years for discount to close | H55: 3
B58: 4. SENSITIVITY: IMPLIED PRICE ($) — WACC × Terminal Growth
D60: WACC →
B61: Terminal growth ↓ | D61: =F61-0.01 -> 0.0802795 | E61: =F61-0.005 -> 0.0852795 | F61: =$C$13 -> 0.0902795 | G61: =F61+0.005 -> 0.0952795 | H61: =F61+0.01 -> 0.1002795
B62: =B64-0.01 -> 0.025 | D62: {=IFERROR((SUMPRODUCT($D$24:$M$24/(1+D$61)^$D$29:$M$29)+($M$24*(1+$B62)/(D$61-$B62))/(1+D$61)^$M$29-$C$48)/$C$50,"")} -> 125.15344 | E62: {=IFERROR((SUMPRODUCT($D$24:$M$24/(1+E$61)^$D$29:$M$29)+($M$24*(1+$B62)/(E$61-$B62))/(1+E$61)^$M$29-$C$48)/$C$50,"")} -> 111.3342 | F62: {=IFERROR((SUMPRODUCT($D$24:$M$24/(1+F$61)^$D$29:$M$29)+($M$24*(1+$B62)/(F$61-$B62))/(1+F$61)^$M$29-$C$48)/$C$50,"")} -> 99.65904 | G62: {=IFERROR((SUMPRODUCT($D$24:$M$24/(1+G$61)^$D$29:$M$29)+($M$24*(1+$B62)/(G$61-$B62))/(1+G$61)^$M$29-$C$48)/$C$50,"")} -> 89.669497 | H62: {=IFERROR((SUMPRODUCT($D$24:$M$24/(1+H$61)^$D$29:$M$29)+($M$24*(1+$B62)/(H$61-$B62))/(1+H$61)^$M$29-$C$48)/$C$50,"")} -> 81.028951
B63: =B64-0.005 -> 0.03 | D63: {=IFERROR((SUMPRODUCT($D$24:$M$24/(1+D$61)^$D$29:$M$29)+($M$24*(1+$B63)/(D$61-$B63))/(1+D$61)^$M$29-$C$48)/$C$50,"")} -> 136.06588 | E63: {=IFERROR((SUMPRODUCT($D$24:$M$24/(1+E$61)^$D$29:$M$29)+($M$24*(1+$B63)/(E$61-$B63))/(1+E$61)^$M$29-$C$48)/$C$50,"")} -> 120.09682 | F63: {=IFERROR((SUMPRODUCT($D$24:$M$24/(1+F$61)^$D$29:$M$29)+($M$24*(1+$B63)/(F$61-$B63))/(1+F$61)^$M$29-$C$48)/$C$50,"")} -> 106.8038 | G63: {=IFERROR((SUMPRODUCT($D$24:$M$24/(1+G$61)^$D$29:$M$29)+($M$24*(1+$B63)/(G$61-$B63))/(1+G$61)^$M$29-$C$48)/$C$50,"")} -> 95.571113 | H63: {=IFERROR((SUMPRODUCT($D$24:$M$24/(1+H$61)^$D$29:$M$29)+($M$24*(1+$B63)/(H$61-$B63))/(1+H$61)^$M$29-$C$48)/$C$50,"")} -> 85.958277
B64: =$C$27 -> 0.035 | D64: {=IFERROR((SUMPRODUCT($D$24:$M$24/(1+D$61)^$D$29:$M$29)+($M$24*(1+$B64)/(D$61-$B64))/(1+D$61)^$M$29-$C$48)/$C$50,"")} -> 149.38832 | E64: {=IFERROR((SUMPRODUCT($D$24:$M$24/(1+E$61)^$D$29:$M$29)+($M$24*(1+$B64)/(E$61-$B64))/(1+E$61)^$M$29-$C$48)/$C$50,"")} -> 130.60222 | F64: {=IFERROR((SUMPRODUCT($D$24:$M$24/(1+F$61)^$D$29:$M$29)+($M$24*(1+$B64)/(F$61-$B64))/(1+F$61)^$M$29-$C$48)/$C$50,"")} -> 115.24105 | G64: {=IFERROR((SUMPRODUCT($D$24:$M$24/(1+G$61)^$D$29:$M$29)+($M$24*(1+$B64)/(G$61-$B64))/(1+G$61)^$M$29-$C$48)/$C$50,"")} -> 102.45177 | H64: {=IFERROR((SUMPRODUCT($D$24:$M$24/(1+H$61)^$D$29:$M$29)+($M$24*(1+$B64)/(H$61-$B64))/(1+H$61)^$M$29-$C$48)/$C$50,"")} -> 91.642714
B65: =B64+0.005 -> 0.04 | D65: {=IFERROR((SUMPRODUCT($D$24:$M$24/(1+D$61)^$D$29:$M$29)+($M$24*(1+$B65)/(D$61-$B65))/(1+D$61)^$M$29-$C$48)/$C$50,"")} -> 166.01827 | E65: {=IFERROR((SUMPRODUCT($D$24:$M$24/(1+E$61)^$D$29:$M$29)+($M$24*(1+$B65)/(E$61-$B65))/(1+E$61)^$M$29-$C$48)/$C$50,"")} -> 143.42774 | F65: {=IFERROR((SUMPRODUCT($D$24:$M$24/(1+F$61)^$D$29:$M$29)+($M$24*(1+$B65)/(F$61-$B65))/(1+F$61)^$M$29-$C$48)/$C$50,"")} -> 125.35636 | G65: {=IFERROR((SUMPRODUCT($D$24:$M$24/(1+G$61)^$D$29:$M$29)+($M$24*(1+$B65)/(G$61-$B65))/(1+G$61)^$M$29-$C$48)/$C$50,"")} -> 110.57713 | H65: {=IFERROR((SUMPRODUCT($D$24:$M$24/(1+H$61)^$D$29:$M$29)+($M$24*(1+$B65)/(H$61-$B65))/(1+H$61)^$M$29-$C$48)/$C$50,"")} -> 98.270164
B66: =B64+0.01 -> 0.045 | D66: {=IFERROR((SUMPRODUCT($D$24:$M$24/(1+D$61)^$D$29:$M$29)+($M$24*(1+$B66)/(D$61-$B66))/(1+D$61)^$M$29-$C$48)/$C$50,"")} -> 187.36199 | E66: {=IFERROR((SUMPRODUCT($D$24:$M$24/(1+E$61)^$D$29:$M$29)+($M$24*(1+$B66)/(E$61-$B66))/(1+E$61)^$M$29-$C$48)/$C$50,"")} -> 159.43739 | F66: {=IFERROR((SUMPRODUCT($D$24:$M$24/(1+F$61)^$D$29:$M$29)+($M$24*(1+$B66)/(F$61-$B66))/(1+F$61)^$M$29-$C$48)/$C$50,"")} -> 137.70565 | G66: {=IFERROR((SUMPRODUCT($D$24:$M$24/(1+G$61)^$D$29:$M$29)+($M$24*(1+$B66)/(G$61-$B66))/(1+G$61)^$M$29-$C$48)/$C$50,"")} -> 120.31853 | H66: {=IFERROR((SUMPRODUCT($D$24:$M$24/(1+H$61)^$D$29:$M$29)+($M$24*(1+$B66)/(H$61-$B66))/(1+H$61)^$M$29-$C$48)/$C$50,"")} -> 106.09651
B69: 5. REVERSE DCF
B70: To solve for the market-implied path: Data ▸ What-If Analysis ▸ Goal Seek — set C51 to the current price (C52) by changing C27 (terminal growth) or the fade-period growth inputs (I26:M26).
B72: 6. MAUBOUSSIN EV / NOPAT — TWO-STAGE FRAMEWORK
B73: EV/NOPAT = 1/r + [g × (1 − r/ROIIC) / (r × (r − g))] × [1 − ((1+g)/(1+r))^N]
B74: Formula source: Mauboussin & Rappaport, "Expectations Investing" (2021); Counterpoint Global, "What Does a Price-Earnings Multiple Mean?" (2020).
B76: Input | C76: Value | D76: Rationale (ESAB characteristics)
B77: r (Cost of capital / WACC) | C77: =$C$13 -> 0.0902795 | D77: Linked from Section 1 WACC build
B78: g (NOPAT growth, Stage 1) | C78: 0.1 | D78: Model adjusted EBITA CAGR 2026–30E: low/mid-single-digit organic growth, Eddyfi high-single-digit growth and synergies, EBXai margin expansion, deleveraging → ~10% NOPAT growth
B79: ROIIC (Return on incremental invested capital) | C79: 0.18 | D79: Consumables-heavy welding franchise (~60% of sales) and gas control earn high returns on organic capital; acquired growth (Eddyfi ~18x EBITDA) earns ~5–6% after tax on purchase price initially
B80: N (Years of value creation / CAP) | C80: 12 | D80: Global #2 in welding & cutting; installed base and consumables pull-through; EBXai continuous-improvement system; workflow extension into inspection / monitoring (Eddyfi); Russia and Europe cyclicality offset
B82: Calculation | C82: Value
B83: Steady-state component: 1 / r | C83: =1/C77 -> 11.076712
B84: Value-creation factor: 1 − r / ROIIC | C84: =1-C77/C79 -> 0.49844722
B85: Growth multiplier: g × (1 − r/ROIIC) / (r × (r − g)) | C85: =C78*C84/(C77*(C77-C78)) -> -56.799097
B86: Time decay: 1 − ((1+g)/(1+r))^N | C86: =1-((1+C78)/(1+C77))^C80 -> -0.11239254
B87: PVGO component (growth value) | C87: =C85*C86 -> 6.3837945
B88: Mauboussin EV / NOPAT (steady-state + PVGO) | C88: =C83+C87 -> 17.460506
B90: VALUATION — Applied to 2028E NOPAT | C90: USDm
B91: 2028E Adj. EBITA less restructuring & integration costs | C91: =Model!AQ200-Model!AQ142-Model!AQ130 -> 685.55307
B92: Tax rate (from WACC build) | C92: =$C$10 -> 0.235
B93: 2028E NOPAT | C93: =C91*(1-C92) -> 524.4481
B94: × Mauboussin EV/NOPAT multiple | C94: =C88 -> 17.460506
B95: Implied Enterprise Value (2028E basis) | C95: =C93*C94 -> 9157.1293
B96: Less: YE2027 net debt + NCI + net asbestos (Model) | C96: =Model!AP414+Model!AP328+Model!AP424 -> 1768.208
B97: Implied Equity Value | C97: =C95-C96 -> 7388.9213
B98: Diluted shares 2028E (m, Model) | C98: =Model!AQ420 -> 63.208832
B99: Implied share price 2028 ($) | C99: =C97/C98 -> 116.89698
B101: Current share price ($) | C101: =C52 -> 69.94
B102: Implied upside / (downside) | C102: =C99/C101-1 -> 0.67138941
B104: MARKET-IMPLIED EV/NOPAT TODAY | C104: USDm
B105: Current market cap (spot × diluted shares) | C105: =C52*C50 -> 4473.5231
B106: Plus: YE2026 net debt + NCI + net asbestos | C106: =C48 -> 2097.0104
B107: Implied Enterprise Value (today) | C107: =C105+C106 -> 6570.5335
B108: ESAB market-implied EV/NOPAT (on 2028E NOPAT) | C108: =C107/C93 -> 12.528472
B110: Multiple gap (Mauboussin − Market) | C110: =C88-C108 -> 4.9320339
B111: Implied re-rating headroom | C111: =C88/C108-1 -> 0.39366603

Sheet Charts
B2: ESAB — Historical Operating Performance (2012–2025; 2012–2018 = Colfax "Fabrication Technology" segment)
B3: USDm · Linked to Model. 2012–2018: pre-spin Colfax segment data (organic / acquisitions / FX and segment operating income); 2019–2025: ESAB carve-out / stand-alone reporting (adjusted EBITDA per company reconciliations). Not strictly comparable across the two bases.
C7: 2012 | D7: 2013 | E7: 2014 | F7: 2015 | G7: 2016 | H7: 2017 | I7: 2018 | J7: 2019 | K7: 2020 | L7: 2021 | M7: 2022 | N7: 2023 | O7: 2024 | P7: 2025
B8: Organic growth % | C8: =IFERROR(Model!C234+0,IFERROR(Model!C65+0,0)) -> 0 | D8: =IFERROR(Model!D234+0,IFERROR(Model!D65+0,0)) -> 0 | E8: =IFERROR(Model!E234+0,IFERROR(Model!E65+0,0)) -> 0 | F8: =IFERROR(Model!F234+0,IFERROR(Model!F65+0,0)) -> 0 | G8: =IFERROR(Model!G234+0,IFERROR(Model!G65+0,0)) -> 0 | H8: =IFERROR(Model!H234+0,IFERROR(Model!H65+0,0)) -> 0 | I8: =IFERROR(Model!I234+0,IFERROR(Model!I65+0,0)) -> 0 | J8: =IFERROR(Model!J234+0,IFERROR(Model!J65+0,0)) -> 0 | K8: =IFERROR(Model!K234+0,IFERROR(Model!K65+0,0)) -> -0.097 | L8: =IFERROR(Model!P234+0,IFERROR(Model!P65+0,0)) -> 0.234 | M8: =IFERROR(Model!U234+0,IFERROR(Model!U65+0,0)) -> 0.105 | N8: =IFERROR(Model!Z234+0,IFERROR(Model!Z65+0,0)) -> 0.062 | O8: =IFERROR(Model!AE234+0,IFERROR(Model!AE65+0,0)) -> 0.012 | P8: =IFERROR(Model!AJ234+0,IFERROR(Model!AJ65+0,0)) -> -0.011
B9: Acquisitions % | C9: =IFERROR(Model!C236+0,IFERROR(Model!C66+0,0)) -> 0 | D9: =IFERROR(Model!D236+0,IFERROR(Model!D66+0,0)) -> 0 | E9: =IFERROR(Model!E236+0,IFERROR(Model!E66+0,0)) -> 0 | F9: =IFERROR(Model!F236+0,IFERROR(Model!F66+0,0)) -> 0 | G9: =IFERROR(Model!G236+0,IFERROR(Model!G66+0,0)) -> 0 | H9: =IFERROR(Model!H236+0,IFERROR(Model!H66+0,0)) -> 0 | I9: =IFERROR(Model!I236+0,IFERROR(Model!I66+0,0)) -> 0 | J9: =IFERROR(Model!J236+0,IFERROR(Model!J66+0,0)) -> 0 | K9: =IFERROR(Model!K236+0,IFERROR(Model!K66+0,0)) -> 0 | L9: =IFERROR(Model!P236+0,IFERROR(Model!P66+0,0)) -> 0.001 | M9: =IFERROR(Model!U236+0,IFERROR(Model!U66+0,0)) -> 0.006 | N9: =IFERROR(Model!Z236+0,IFERROR(Model!Z66+0,0)) -> 0.025 | O9: =IFERROR(Model!AE236+0,IFERROR(Model!AE66+0,0)) -> 0.008 | P9: =IFERROR(Model!AJ236+0,IFERROR(Model!AJ66+0,0)) -> 0.042
B10: Foreign currency % | C10: =IFERROR(Model!C237+0,IFERROR(Model!C67+0,0)) -> 0 | D10: =IFERROR(Model!D237+0,IFERROR(Model!D67+0,0)) -> 0 | E10: =IFERROR(Model!E237+0,IFERROR(Model!E67+0,0)) -> 0 | F10: =IFERROR(Model!F237+0,IFERROR(Model!F67+0,0)) -> 0 | G10: =IFERROR(Model!G237+0,IFERROR(Model!G67+0,0)) -> 0 | H10: =IFERROR(Model!H237+0,IFERROR(Model!H67+0,0)) -> 0 | I10: =IFERROR(Model!I237+0,IFERROR(Model!I67+0,0)) -> 0 | J10: =IFERROR(Model!J237+0,IFERROR(Model!J67+0,0)) -> 0 | K10: =IFERROR(Model!K237+0,IFERROR(Model!K67+0,0)) -> -0.035 | L10: =IFERROR(Model!P237+0,IFERROR(Model!P67+0,0)) -> 0.01 | M10: =IFERROR(Model!U237+0,IFERROR(Model!U67+0,0)) -> -0.042 | N10: =IFERROR(Model!Z237+0,IFERROR(Model!Z67+0,0)) -> -0.017 | O10: =IFERROR(Model!AE237+0,IFERROR(Model!AE67+0,0)) -> -0.032 | P10: =IFERROR(Model!AJ237+0,IFERROR(Model!AJ67+0,0)) -> 0.006
C11: =C7 -> 2012 | D11: =D7 -> 2013 | E11: =E7 -> 2014 | F11: =F7 -> 2015 | G11: =G7 -> 2016 | H11: =H7 -> 2017 | I11: =I7 -> 2018 | J11: =J7 -> 2019 | ... P11: =P7 -> 2025
B12: Adjusted EBITDA (ESAB, 2019+) | C12: =IFERROR(Model!C189+0,NA()) -> 0 | D12: =IFERROR(Model!D189+0,NA()) -> 0 | E12: =IFERROR(Model!E189+0,NA()) -> 0 | F12: =IFERROR(Model!F189+0,NA()) -> 0 | G12: =IFERROR(Model!G189+0,NA()) -> 0 | H12: =IFERROR(Model!H189+0,NA()) -> 0 | I12: =IFERROR(Model!I189+0,NA()) -> 0 | J12: =IFERROR(Model!J189+0,NA()) -> 353.663 | K12: =IFERROR(Model!K189+0,NA()) -> 301.146 | L12: =IFERROR(Model!P189+0,NA()) -> 404.168 | M12: =IFERROR(Model!U189+0,NA()) -> 436.761 | N12: =IFERROR(Model!Z189+0,NA()) -> 501.176 | O12: =IFERROR(Model!AE189+0,NA()) -> 528.777 | P12: =IFERROR(Model!AJ189+0,NA()) -> 559.726
B13: Operating income (GAAP, 2019+) | C13: =IFERROR(Model!C144+0,NA()) -> 0 | D13: =IFERROR(Model!D144+0,NA()) -> 0 | E13: =IFERROR(Model!E144+0,NA()) -> 0 | F13: =IFERROR(Model!F144+0,NA()) -> 0 | G13: =IFERROR(Model!G144+0,NA()) -> 0 | H13: =IFERROR(Model!H144+0,NA()) -> 0 | I13: =IFERROR(Model!I144+0,NA()) -> 0 | J13: =IFERROR(Model!J144+0,NA()) -> 256.08 | K13: =IFERROR(Model!K144+0,NA()) -> 202.126 | L13: =IFERROR(Model!P144+0,NA()) -> 306.214 | M13: =IFERROR(Model!U144+0,NA()) -> 329.065 | N13: =IFERROR(Model!Z144+0,NA()) -> 404.166 | O13: =IFERROR(Model!AE144+0,NA()) -> 447.45 | P13: =IFERROR(Model!AJ144+0,NA()) -> 412.17
B14: Adj. EBITDA margin % | C14: =IFERROR(Model!C190+0,NA()) -> 0 | D14: =IFERROR(Model!D190+0,NA()) -> 0 | E14: =IFERROR(Model!E190+0,NA()) -> 0 | F14: =IFERROR(Model!F190+0,NA()) -> 0 | G14: =IFERROR(Model!G190+0,NA()) -> 0 | H14: =IFERROR(Model!H190+0,NA()) -> 0 | I14: =IFERROR(Model!I190+0,NA()) -> 0 | J14: =IFERROR(Model!J190+0,NA()) -> 0.15739159 | K14: =IFERROR(Model!K190+0,NA()) -> 0.15442838 | L14: =IFERROR(Model!P190+0,NA()) -> 0.1664534 | M14: =IFERROR(Model!U190+0,NA()) -> 0.16840731 | N14: =IFERROR(Model!Z190+0,NA()) -> 0.18061919 | O14: =IFERROR(Model!AE190+0,NA()) -> 0.19292777 | P14: =IFERROR(Model!AJ190+0,NA()) -> 0.19690947
B15: GAAP Op. margin % | C15: =IFERROR(Model!C246+0,NA()) -> #N/A | D15: =IFERROR(Model!D246+0,NA()) -> #N/A | E15: =IFERROR(Model!E246+0,NA()) -> #N/A | F15: =IFERROR(Model!F246+0,NA()) -> #N/A | G15: =IFERROR(Model!G246+0,NA()) -> #N/A | H15: =IFERROR(Model!H246+0,NA()) -> #N/A | I15: =IFERROR(Model!I246+0,NA()) -> #N/A | J15: =IFERROR(Model!J246+0,NA()) -> 0.11396397 | K15: =IFERROR(Model!K246+0,NA()) -> 0.10365069 | L15: =IFERROR(Model!P246+0,NA()) -> 0.12611182 | M15: =IFERROR(Model!U246+0,NA()) -> 0.12688164 | N15: =IFERROR(Model!Z246+0,NA()) -> 0.14565769 | O15: =IFERROR(Model!AE246+0,NA()) -> 0.16325508 | P15: =IFERROR(Model!AJ246+0,NA()) -> 0.14499983
B16: Colfax Fab. Tech. segment op. income (pre-spin) | C16: =IFERROR(Model!C63+0,NA()) -> 140.184 | D16: =IFERROR(Model!D63+0,NA()) -> 219.634 | E16: =IFERROR(Model!E63+0,NA()) -> 265.813 | F16: =IFERROR(Model!F63+0,NA()) -> 198.337 | G16: =IFERROR(Model!G63+0,NA()) -> 195.197 | H16: =IFERROR(Model!H63+0,NA()) -> 224.362 | I16: =IFERROR(Model!I63+0,NA()) -> 249.934 | J16: =IFERROR(Model!J63+0,NA()) -> 302.601 | K16: =IFERROR(Model!K63+0,NA()) -> 246.011 | L16: =IFERROR(Model!P63+0,NA()) -> 356.315 | M16: =IFERROR(Model!U63+0,NA()) -> 0 | N16: =IFERROR(Model!Z63+0,NA()) -> 0 | O16: =IFERROR(Model!AE63+0,NA()) -> 0 | P16: =IFERROR(Model!AJ63+0,NA()) -> 0
C17: =C7 -> 2012 | D17: =D7 -> 2013 | E17: =E7 -> 2014 | F17: =F7 -> 2015 | G17: =G7 -> 2016 | H17: =H7 -> 2017 | I17: =I7 -> 2018 | J17: =J7 -> 2019 | ... P17: =P7 -> 2025
B18: ROIC | C18: =IFERROR(Model!C397+0,NA()) -> 0 | D18: =IFERROR(Model!D397+0,NA()) -> 0 | E18: =IFERROR(Model!E397+0,NA()) -> 0 | F18: =IFERROR(Model!F397+0,NA()) -> 0 | G18: =IFERROR(Model!G397+0,NA()) -> 0 | H18: =IFERROR(Model!H397+0,NA()) -> 0 | I18: =IFERROR(Model!I397+0,NA()) -> 0 | J18: =IFERROR(Model!J397+0,NA()) -> 0 | K18: =IFERROR(Model!K397+0,NA()) -> 0.081782149 | L18: =IFERROR(Model!P397+0,NA()) -> 0.11116395 | M18: =IFERROR(Model!U397+0,NA()) -> 0.12200131 | N18: =IFERROR(Model!Z397+0,NA()) -> 0.12701279 | O18: =IFERROR(Model!AE397+0,NA()) -> 0.14780085 | P18: =IFERROR(Model!AJ397+0,NA()) -> 0.12395001
B19: RONTA | C19: =IFERROR(Model!C408+0,NA()) -> 0 | D19: =IFERROR(Model!D408+0,NA()) -> 0 | E19: =IFERROR(Model!E408+0,NA()) -> 0 | F19: =IFERROR(Model!F408+0,NA()) -> 0 | G19: =IFERROR(Model!G408+0,NA()) -> 0 | H19: =IFERROR(Model!H408+0,NA()) -> 0 | I19: =IFERROR(Model!I408+0,NA()) -> 0 | J19: =IFERROR(Model!J408+0,NA()) -> 0 | K19: =IFERROR(Model!K408+0,NA()) -> 0.2569119 | L19: =IFERROR(Model!P408+0,NA()) -> 0.33757774 | M19: =IFERROR(Model!U408+0,NA()) -> 0.27976574 | N19: =IFERROR(Model!Z408+0,NA()) -> 0.29055911 | O19: =IFERROR(Model!AE408+0,NA()) -> 0.30494868 | P19: =IFERROR(Model!AJ408+0,NA()) -> 0.27289074
B20: Adj. EBITDA margin % | C20: =IFERROR(Model!C190+0,NA()) -> 0 | D20: =IFERROR(Model!D190+0,NA()) -> 0 | E20: =IFERROR(Model!E190+0,NA()) -> 0 | F20: =IFERROR(Model!F190+0,NA()) -> 0 | G20: =IFERROR(Model!G190+0,NA()) -> 0 | H20: =IFERROR(Model!H190+0,NA()) -> 0 | I20: =IFERROR(Model!I190+0,NA()) -> 0 | J20: =IFERROR(Model!J190+0,NA()) -> 0.15739159 | K20: =IFERROR(Model!K190+0,NA()) -> 0.15442838 | L20: =IFERROR(Model!P190+0,NA()) -> 0.1664534 | M20: =IFERROR(Model!U190+0,NA()) -> 0.16840731 | N20: =IFERROR(Model!Z190+0,NA()) -> 0.18061919 | O20: =IFERROR(Model!AE190+0,NA()) -> 0.19292777 | P20: =IFERROR(Model!AJ190+0,NA()) -> 0.19690947
B21: FCF margin % | C21: =IFERROR(Model!C284+0,NA()) -> 0 | D21: =IFERROR(Model!D284+0,NA()) -> 0 | E21: =IFERROR(Model!E284+0,NA()) -> 0 | F21: =IFERROR(Model!F284+0,NA()) -> 0 | G21: =IFERROR(Model!G284+0,NA()) -> 0 | H21: =IFERROR(Model!H284+0,NA()) -> 0 | I21: =IFERROR(Model!I284+0,NA()) -> 0 | J21: =IFERROR(Model!J284+0,NA()) -> 0.091399921 | K21: =IFERROR(Model!K284+0,NA()) -> 0.13796589 | L21: =IFERROR(Model!P284+0,NA()) -> 0.088609065 | M21: =IFERROR(Model!U284+0,NA()) -> 0.067135663 | N21: =IFERROR(Model!Z284+0,NA()) -> 0.10174407 | O21: =IFERROR(Model!AE284+0,NA()) -> 0.11077775 | P21: =IFERROR(Model!AJ284+0,NA()) -> 0.07503109
