Workbook

Sheet Model
CG1: SCENARIO SWITCH ▼ (Bull / Base / Bear) — drives all scenario-linked forecast drivers
B2: Fair Isaac Corporation (NYSE: FICO) — 3-Statement Financial Model | CG2: Base
B3: US GAAP as reported · USD millions (per-share data in USD; shares in millions) · Fiscal years ended 30 September (2026 = Oct-2025 – Sep-2026) · Source: Fair Isaac Forms 10-K / 10-Q, Form 8-K earnings releases (Ex. 99.1) and financing / restructuring 8-Ks, SEC EDGAR (CIK 814547); XBRL company facts; investor-relations releases at fico.com are the same documents as filed on EDGAR
B4: Basis notes: as originally reported. Segments: Strategy Machine Solutions / Scoring Solutions / Professional Services / Analytic Software Tools (FY2006–09), Applications / Scores / Tools (FY2010–15), Applications / Scores / DMS (FY2016–Q3/21), Scores / Software (FY2021 10-K on). Disc ops FY2007–09. Non-GAAP published from Q1 FY13. Q4/26E calibrated to FY26 revenue and non-GAAP EPS guidance (29-Jul-2026) plus the Oct-2026 restructuring; $1.5bn ASR (Jun-2026) settles in Q4 FY26.
CI5: Forecast | CJ5: Historical | CK5: Historical | CL5: Historical
B6: (USDm) | C6: 2006 | D6: 2007 | E6: 2008 | F6: 2009 | G6: 2010 | H6: 2011 | I6: 2012 | J6: Q1/13 | K6: Q2/13 | L6: Q3/13 | M6: Q4/13 | N6: 2013 | O6: Q1/14 | P6: Q2/14 | Q6: Q3/14 | R6: Q4/14 | S6: 2014 | T6: Q1/15 | U6: Q2/15 | V6: Q3/15 | W6: Q4/15 | X6: 2015 | Y6: Q1/16 | Z6: Q2/16 | AA6: Q3/16 | AB6: Q4/16 | AC6: 2016 | AD6: Q1/17 | AE6: Q2/17 | AF6: Q3/17 | AG6: Q4/17 | AH6: 2017 | AI6: Q1/18 | AJ6: Q2/18 | AK6: Q3/18 | AL6: Q4/18 | AM6: 2018 | AN6: Q1/19 | AO6: Q2/19 | AP6: Q3/19 | AQ6: Q4/19 | AR6: 2019 | AS6: Q1/20 | AT6: Q2/20 | AU6: Q3/20 | AV6: Q4/20 | AW6: 2020 | AX6: Q1/21 | AY6: Q2/21 | AZ6: Q3/21 | BA6: Q4/21 | BB6: 2021 | BC6: Q1/22 | BD6: Q2/22 | BE6: Q3/22 | BF6: Q4/22 | BG6: 2022 | BH6: Q1/23 | BI6: Q2/23 | BJ6: Q3/23 | BK6: Q4/23 | BL6: 2023 | BM6: Q1/24 | BN6: Q2/24 | BO6: Q3/24 | BP6: Q4/24 | BQ6: 2024 | BR6: Q1/25 | BS6: Q2/25 | BT6: Q3/25 | BU6: Q4/25 | BV6: 2025 | BW6: Q1/26 | BX6: Q2/26 | BY6: Q3/26 | BZ6: Q4/26E | CA6: 2026E | CB6: 2027E | CC6: 2028E | CD6: 2029E | CE6: 2030E | CF6: 2031E | CG6: Modelling Notes | CI6: 5Y CAGR | CJ6: 5Y CAGR | CK6: 10Y CAGR | CL6: 19Y CAGR
CI7: 26-'31 | CJ7: 20-'25 | CK7: 15-'25 | CL7: 06-'25
B8: SEGMENT P&L — SCORES · SOFTWARE (revenue streams × segment operating margin) | CG8: SEGMENT BUILD — modelling logic (revenue streams → segment revenue → segment operating income at the segment margin → + unallocated corporate expenses = non-GAAP operating income → GAAP P&L)
CO9: SCENARIO INPUT TABLE — driver assumptions per Bull / Base / Bear | CP9: Bull | CQ9: Base | CR9: Bear | CS9: Bull / Bear = Base + Δ (Δ inputs on each block header). Outlook block = FY26 guidance (point guidance: high = mid = low).
B10: Scores (B2B and B2C scoring; "Scoring Solutions" product-line segment in FY2006–09) | CG10: SCORES — modelling logic
B11: B2B scores (FICO Scores sold to lenders through the credit bureaus; mortgage, auto, card, personal loans) | AR11: 302.103 | AW11: 381.929 | AX11: 100.144 | AY11: 119.319 | AZ11: 115.862 | BA11: 111.213 | BB11: 446.538 | BC11: 112.968 | BD11: 125.243 | BE11: 119.01 | BF11: 118.221 | BG11: 475.442 | BH11: 124.905 | BI11: 144.874 | BJ11: 148.128 | BK11: 143.088 | BL11: 560.995 | BM11: 140.442 | BN11: 185.508 | BO11: 188.754 | BP11: 197.139 | BQ11: 711.843 | BR11: 182.391 | BS11: 242.494 | BT11: 268.479 | BU11: 255.231 | BV11: 948.595 | BW11: 248.613 | BX11: 417.629 | BY11: 400.043 | BZ11: =BU11*(1+BZ12) -> 384.14405 | CA11: =SUM(BW11:BZ11) -> 1450.4291 | CB11: =CA11*(1+CB12) -> 1667.9934 | CC11: =CB11*(1+CC12) -> 1868.1526 | CD11: =CC11*(1+CD12) -> 2054.9679 | CE11: =CD11*(1+CE12) -> 2239.915 | CF11: =CE11*(1+CF12) -> 2419.1082 | CG11: Revenue streams from the 10-Q / 10-K MD&A tables (first published in the FY2021 10-K: FY2019–21 annual; FY2021 quarters from the FY2022 10-Q comparatives; Q4 = fiscal year − nine months). Q4/26E: prior-year quarter × (1 + growth). 2027E+: prior year × (1 + scenario lever). | CI11: =IFERROR((CF11/CA11)^(1/5)-1,"n/m") -> 0.1077245 | CJ11: =IFERROR((BV11/AW11)^(1/5)-1,"n/m") -> 0.19955355 | CK11: =IFERROR((BV11/X11)^(1/10)-1,"n/m") -> n/m | CL11: =IFERROR((BV11/C11)^(1/19)-1,"n/m") -> n/m | CO11: FY26 guidance — Q3 FY26 release (29-Jul-2026; point guidance) | CP11: High | CQ11: Mid | CR11: Low | CS11: Revenue $2.53bn (raised from $2.45bn), GAAP net income $850m / EPS $36.86, non-GAAP net income $979m / EPS $42.43 (raised from $40.45); reconciliation: SBC $188m, income tax adjustments −$46m, excess tax benefit −$13m. No segment, margin, tax, interest or cash-flow guidance. Point guidance, so high = mid = low.
B12: y/y % | D12: =IF(AND(ISNUMBER(D11),ISNUMBER(C11)),IFERROR(D11/C11-1,""),"") | E12: =IF(AND(ISNUMBER(E11),ISNUMBER(D11)),IFERROR(E11/D11-1,""),"") | F12: =IF(AND(ISNUMBER(F11),ISNUMBER(E11)),IFERROR(F11/E11-1,""),"") | G12: =IF(AND(ISNUMBER(G11),ISNUMBER(F11)),IFERROR(G11/F11-1,""),"") | H12: =IF(AND(ISNUMBER(H11),ISNUMBER(G11)),IFERROR(H11/G11-1,""),"") | I12: =IF(AND(ISNUMBER(I11),ISNUMBER(H11)),IFERROR(I11/H11-1,""),"") | N12: =IF(AND(ISNUMBER(N11),ISNUMBER(I11)),IFERROR(N11/I11-1,""),"") | O12: =IF(AND(ISNUMBER(O11),ISNUMBER(J11)),IFERROR(O11/J11-1,""),"") | P12: =IF(AND(ISNUMBER(P11),ISNUMBER(K11)),IFERROR(P11/K11-1,""),"") | Q12: =IF(AND(ISNUMBER(Q11),ISNUMBER(L11)),IFERROR(Q11/L11-1,""),"") | R12: =IF(AND(ISNUMBER(R11),ISNUMBER(M11)),IFERROR(R11/M11-1,""),"") | S12: =IF(AND(ISNUMBER(S11),ISNUMBER(N11)),IFERROR(S11/N11-1,""),"") | T12: =IF(AND(ISNUMBER(T11),ISNUMBER(O11)),IFERROR(T11/O11-1,""),"") | U12: =IF(AND(ISNUMBER(U11),ISNUMBER(P11)),IFERROR(U11/P11-1,""),"") | ... BY12: =IF(AND(ISNUMBER(BY11),ISNUMBER(BT11)),IFERROR(BY11/BT11-1,""),"") -> 0.4900346 | BZ12: =BZ13+$BZ$97 -> 0.50508383 | CA12: =IF(AND(ISNUMBER(CA11),ISNUMBER(BV11)),IFERROR(CA11/BV11-1,""),"") -> 0.52902878 | CB12: =CHOOSE(MATCH($CG$2,{"Bull","Base","Bear"},0),$CP$33,$CQ$33,$CR$33) -> 0.15 | CC12: =CHOOSE(MATCH($CG$2,{"Bull","Base","Bear"},0),$CP$34,$CQ$34,$CR$34) -> 0.12 | CD12: =CHOOSE(MATCH($CG$2,{"Bull","Base","Bear"},0),$CP$35,$CQ$35,$CR$35) -> 0.1 | CE12: =CHOOSE(MATCH($CG$2,{"Bull","Base","Bear"},0),$CP$36,$CQ$36,$CR$36) -> 0.09 | CF12: =CHOOSE(MATCH($CG$2,{"Bull","Base","Bear"},0),$CP$37,$CQ$37,$CR$37) -> 0.08 | CG12: Q4/26E: 9M FY26 y/y growth of the stream + revenue-guidance calibration Δ (Group block). 2027E–2031E: scenario lever (Bull/Base/Bear table →). | CO12: FY26 revenue ($m) | CP12: 2530 | CQ12: 2530 | CR12: 2530 | CS12: Guided $2.53bn. Drives the Q4/26E revenue calibration.
B13: Q4/26E growth before revenue calibration (9M FY26 y/y) | BZ13: =IFERROR(SUM(BW11:BY11)/SUM(BR11:BT11)-1,0) -> 0.53784304 | CO13: FY26 non-GAAP EPS ($) | CP13: 42.43 | CQ13: 42.43 | CR13: 42.43 | CS13: Guided $42.43. Drives the Q4/26E segment-margin calibration.
B14: B2C scores (myFICO.com subscriptions; royalties on scores sold to consumers through the bureaus) | AR14: 119.074 | AW14: 146.618 | AX14: 44.507 | AY14: 49.4 | AZ14: 56.34 | BA14: 57.362 | BB14: 207.609 | BC14: 56.519 | BD14: 58.499 | BE14: 60.345 | BF14: 55.838 | BG14: 231.201 | BH14: 53.083 | BI14: 53.633 | BJ14: 53.65 | BK14: 52.467 | BL14: 212.833 | BM14: 51.67 | BN14: 51.377 | BO14: 52.696 | BP14: 52.064 | BQ14: 207.807 | BR14: 53.284 | BS14: 54.545 | BT14: 55.83 | BU14: 56.321 | BV14: 219.98 | BW14: 55.921 | BX14: 57.344 | BY14: 58.854 | BZ14: =BU14*(1+BZ15) -> 57.387362 | CA14: =SUM(BW14:BZ14) -> 229.50636 | CB14: =CA14*(1+CB15) -> 238.68662 | CC14: =CB14*(1+CC15) -> 248.23408 | CD14: =CC14*(1+CD15) -> 258.16344 | CE14: =CD14*(1+CE15) -> 265.90835 | CF14: =CE14*(1+CF15) -> 273.8856 | CI14: =IFERROR((CF14/CA14)^(1/5)-1,"n/m") -> 0.035988402 | CJ14: =IFERROR((BV14/AW14)^(1/5)-1,"n/m") -> 0.084524035 | CK14: =IFERROR((BV14/X14)^(1/10)-1,"n/m") -> n/m | CL14: =IFERROR((BV14/C14)^(1/19)-1,"n/m") -> n/m | CO14: FY26 GAAP net income ($m) — memo | CP14: 850 | CQ14: 850 | CR14: 850 | CS14: Guided $850m (information row; excludes the $27m Q4 restructuring announced 6-Oct-2026).
B15: y/y % | D15: =IF(AND(ISNUMBER(D14),ISNUMBER(C14)),IFERROR(D14/C14-1,""),"") | E15: =IF(AND(ISNUMBER(E14),ISNUMBER(D14)),IFERROR(E14/D14-1,""),"") | F15: =IF(AND(ISNUMBER(F14),ISNUMBER(E14)),IFERROR(F14/E14-1,""),"") | G15: =IF(AND(ISNUMBER(G14),ISNUMBER(F14)),IFERROR(G14/F14-1,""),"") | H15: =IF(AND(ISNUMBER(H14),ISNUMBER(G14)),IFERROR(H14/G14-1,""),"") | I15: =IF(AND(ISNUMBER(I14),ISNUMBER(H14)),IFERROR(I14/H14-1,""),"") | N15: =IF(AND(ISNUMBER(N14),ISNUMBER(I14)),IFERROR(N14/I14-1,""),"") | O15: =IF(AND(ISNUMBER(O14),ISNUMBER(J14)),IFERROR(O14/J14-1,""),"") | P15: =IF(AND(ISNUMBER(P14),ISNUMBER(K14)),IFERROR(P14/K14-1,""),"") | Q15: =IF(AND(ISNUMBER(Q14),ISNUMBER(L14)),IFERROR(Q14/L14-1,""),"") | R15: =IF(AND(ISNUMBER(R14),ISNUMBER(M14)),IFERROR(R14/M14-1,""),"") | S15: =IF(AND(ISNUMBER(S14),ISNUMBER(N14)),IFERROR(S14/N14-1,""),"") | T15: =IF(AND(ISNUMBER(T14),ISNUMBER(O14)),IFERROR(T14/O14-1,""),"") | U15: =IF(AND(ISNUMBER(U14),ISNUMBER(P14)),IFERROR(U14/P14-1,""),"") | ... BY15: =IF(AND(ISNUMBER(BY14),ISNUMBER(BT14)),IFERROR(BY14/BT14-1,""),"") -> 0.054164428 | BZ15: =BZ16+$BZ$97 -> 0.018933643 | CA15: =IF(AND(ISNUMBER(CA14),ISNUMBER(BV14)),IFERROR(CA14/BV14-1,""),"") -> 0.043305581 | CB15: =CHOOSE(MATCH($CG$2,{"Bull","Base","Bear"},0),$CP$39,$CQ$39,$CR$39) -> 0.04 | CC15: =CHOOSE(MATCH($CG$2,{"Bull","Base","Bear"},0),$CP$40,$CQ$40,$CR$40) -> 0.04 | CD15: =CHOOSE(MATCH($CG$2,{"Bull","Base","Bear"},0),$CP$41,$CQ$41,$CR$41) -> 0.04 | CE15: =CHOOSE(MATCH($CG$2,{"Bull","Base","Bear"},0),$CP$42,$CQ$42,$CR$42) -> 0.03 | CF15: =CHOOSE(MATCH($CG$2,{"Bull","Base","Bear"},0),$CP$43,$CQ$43,$CR$43) -> 0.03 | CO15: FY26 GAAP EPS ($) — memo | CP15: 36.86 | CQ15: 36.86 | CR15: 36.86 | CS15: Guided $36.86 (information row).
B16: Q4/26E growth before revenue calibration (9M FY26 y/y) | BZ16: =IFERROR(SUM(BW14:BY14)/SUM(BR14:BT14)-1,0) -> 0.051692849 | CO16: Q4/26E share repurchases ($m; cash) | CP16: 500 | CQ16: 300 | CR16: 100 | CS16: Assumption. $800m left on the June 2026 program at 30-Jun-2026, of which $300m is the ASR prepayment (settles in Q4 with no further cash) → $500m available; 9M FY26 $3,046m.
B17: Scores — segment revenue | C17: =IF(AND(ISNUMBER(C11),ISNUMBER(C14)),C11+C14,C21) -> 177.152 | D17: =IF(AND(ISNUMBER(D11),ISNUMBER(D14)),D11+D14,D21) -> 180.444 | E17: =IF(AND(ISNUMBER(E11),ISNUMBER(E14)),E11+E14,E21) -> 156.816 | F17: =IF(AND(ISNUMBER(F11),ISNUMBER(F14)),F11+F14,F21) -> 131.621 | G17: =IF(AND(ISNUMBER(G11),ISNUMBER(G14)),G11+G14,G21) -> 172.339 | H17: =IF(AND(ISNUMBER(H11),ISNUMBER(H14)),H11+H14,H21) -> 168.567 | I17: =IF(AND(ISNUMBER(I11),ISNUMBER(I14)),I11+I14,I21) -> 175.623 | J17: =IF(AND(ISNUMBER(J11),ISNUMBER(J14)),J11+J14,J21) -> 43.447 | ... BY17: =IF(AND(ISNUMBER(BY11),ISNUMBER(BY14)),BY11+BY14,BY21) -> 458.897 | BZ17: =BZ11+BZ14 -> 441.53141 | CA17: =CA11+CA14 -> 1679.9354 | CB17: =CB11+CB14 -> 1906.68 | CC17: =CC11+CC14 -> 2116.3867 | CD17: =CD11+CD14 -> 2313.1313 | CE17: =CE11+CE14 -> 2505.8233 | CF17: =CF11+CF14 -> 2692.9938 | CG17: History: Σ revenue streams where all are published, otherwise segment revenue as reported. | CI17: =IFERROR((CF17/CA17)^(1/5)-1,"n/m") -> 0.098976873 | CJ17: =IFERROR((BV17/AW17)^(1/5)-1,"n/m") -> 0.17196488 | CK17: =IFERROR((BV17/X17)^(1/10)-1,"n/m") -> 0.18895976 | CL17: =IFERROR((BV17/C17)^(1/19)-1,"n/m") -> 0.10438782
B18: Segment revenue y/y % | D18: =IF(AND(ISNUMBER(D17),ISNUMBER(C17)),IFERROR(D17/C17-1,""),"") -> 0.018582912 | E18: =IF(AND(ISNUMBER(E17),ISNUMBER(D17)),IFERROR(E17/D17-1,""),"") -> -0.13094367 | F18: =IF(AND(ISNUMBER(F17),ISNUMBER(E17)),IFERROR(F17/E17-1,""),"") -> -0.160666 | G18: =IF(AND(ISNUMBER(G17),ISNUMBER(F17)),IFERROR(G17/F17-1,""),"") -> 0.30935793 | H18: =IF(AND(ISNUMBER(H17),ISNUMBER(G17)),IFERROR(H17/G17-1,""),"") -> -0.021887095 | I18: =IF(AND(ISNUMBER(I17),ISNUMBER(H17)),IFERROR(I17/H17-1,""),"") -> 0.041858727 | N18: =IF(AND(ISNUMBER(N17),ISNUMBER(I17)),IFERROR(N17/I17-1,""),"") -> 0.029551938 | O18: =IF(AND(ISNUMBER(O17),ISNUMBER(J17)),IFERROR(O17/J17-1,""),"") -> 0.085920777 | P18: =IF(AND(ISNUMBER(P17),ISNUMBER(K17)),IFERROR(P17/K17-1,""),"") -> 0.086151332 | Q18: =IF(AND(ISNUMBER(Q17),ISNUMBER(L17)),IFERROR(Q17/L17-1,""),"") -> -0.038640991 | R18: =IF(AND(ISNUMBER(R17),ISNUMBER(M17)),IFERROR(R17/M17-1,""),"") -> -0.0011050442 | S18: =IF(AND(ISNUMBER(S17),ISNUMBER(N17)),IFERROR(S17/N17-1,""),"") -> 0.031280937 | T18: =IF(AND(ISNUMBER(T17),ISNUMBER(O17)),IFERROR(T17/O17-1,""),"") -> -0.068651971 | U18: =IF(AND(ISNUMBER(U17),ISNUMBER(P17)),IFERROR(U17/P17-1,""),"") -> 0.043441013 | ... CA18: =IF(AND(ISNUMBER(CA17),ISNUMBER(BV17)),IFERROR(CA17/BV17-1,""),"") -> 0.43759315 | CB18: =IF(AND(ISNUMBER(CB17),ISNUMBER(CA17)),IFERROR(CB17/CA17-1,""),"") -> 0.13497222 | CC18: =IF(AND(ISNUMBER(CC17),ISNUMBER(CB17)),IFERROR(CC17/CB17-1,""),"") -> 0.10998525 | CD18: =IF(AND(ISNUMBER(CD17),ISNUMBER(CC17)),IFERROR(CD17/CC17-1,""),"") -> 0.092962513 | CE18: =IF(AND(ISNUMBER(CE17),ISNUMBER(CD17)),IFERROR(CE17/CD17-1,""),"") -> 0.083303533 | CF18: =IF(AND(ISNUMBER(CF17),ISNUMBER(CE17)),IFERROR(CF17/CE17-1,""),"") -> 0.074694192 | CO18: Q4/26E and FY26 point estimates (all cases)
B19: % of total revenue | C19: =IF(AND(ISNUMBER(C17),ISNUMBER(C87)),IFERROR(C17/C87,""),"") -> 0.21463474 | D19: =IF(AND(ISNUMBER(D17),ISNUMBER(D87)),IFERROR(D17/D87,""),"") -> 0.21945524 | E19: =IF(AND(ISNUMBER(E17),ISNUMBER(E87)),IFERROR(E17/E87,""),"") -> 0.21053593 | F19: =IF(AND(ISNUMBER(F17),ISNUMBER(F87)),IFERROR(F17/F87,""),"") -> 0.20867876 | G19: =IF(AND(ISNUMBER(G17),ISNUMBER(G87)),IFERROR(G17/G87,""),"") -> 0.28455542 | H19: =IF(AND(ISNUMBER(H17),ISNUMBER(H87)),IFERROR(H17/H87,""),"") -> 0.27202134 | I19: =IF(AND(ISNUMBER(I17),ISNUMBER(I87)),IFERROR(I17/I87,""),"") -> 0.25963487 | J19: =IF(AND(ISNUMBER(J17),ISNUMBER(J87)),IFERROR(J17/J87,""),"") -> 0.22864435 | ... CF19: =IF(AND(ISNUMBER(CF17),ISNUMBER(CF87)),IFERROR(CF17/CF87,""),"") -> 0.67723396 | CI19: =IFERROR(AVERAGE(CB19,CC19,CD19,CE19,CF19),"n/m") -> 0.68192686 | CJ19: =IFERROR(AVERAGE(BB19,BG19,BL19,BQ19,BV19),"n/m") -> 0.52872544 | CK19: =IFERROR(AVERAGE(AC19,AH19,AM19,AR19,AW19,BB19,BG19,BL19,BQ19,BV19),"n/m") -> 0.43060828 | CL19: =IFERROR(AVERAGE(C19,D19,E19,F19,G19,H19,I19,N19,S19,X19,AC19,AH19,AM19,AR19,AW19,BB19,BG19,BL19,BQ19,BV19),"n/m") -> 0.33509722 | CO19: Q4/26E interest expense, net ($m) | CQ19: 78 | CS19: Not guided. Full quarter on ~$5.6bn debt: notes $3.4bn at ~5.5%, term loan $1.5bn at 5.86%, revolver ~$0.7bn at 5.64% (Q3 $59.9m incl. 25 days of the term loan).
B20: B2B % of Scores revenue | C20: =IF(ISNUMBER(C11),IFERROR(C11/C17,""),"") | D20: =IF(ISNUMBER(D11),IFERROR(D11/D17,""),"") | E20: =IF(ISNUMBER(E11),IFERROR(E11/E17,""),"") | F20: =IF(ISNUMBER(F11),IFERROR(F11/F17,""),"") | G20: =IF(ISNUMBER(G11),IFERROR(G11/G17,""),"") | H20: =IF(ISNUMBER(H11),IFERROR(H11/H17,""),"") | I20: =IF(ISNUMBER(I11),IFERROR(I11/I17,""),"") | J20: =IF(ISNUMBER(J11),IFERROR(J11/J17,""),"") | ... CF20: =IF(ISNUMBER(CF11),IFERROR(CF11/CF17,""),"") -> 0.89829698 | CI20: =IFERROR(AVERAGE(CB20,CC20,CD20,CE20,CF20),"n/m") -> 0.88761944 | CJ20: =IFERROR(AVERAGE(BB20,BG20,BL20,BQ20,BV20),"n/m") -> 0.73323911 | CK20: =IFERROR(AVERAGE(AC20,AH20,AM20,AR20,AW20,BB20,BG20,BL20,BQ20,BV20),"n/m") -> 0.72944001 | CL20: =IFERROR(AVERAGE(C20,D20,E20,F20,G20,H20,I20,N20,S20,X20,AC20,AH20,AM20,AR20,AW20,BB20,BG20,BL20,BQ20,BV20),"n/m") -> 0.72944001 | CO20: Q4/26E other income (expense), net ($m) | CQ20: 3 | CS20: 9M FY26 $9.9m (Q3 $11.9m incl. investment gains).
B21: Memo: Scores segment revenue as reported (segment note) | C21: 177.152 | D21: 180.444 | E21: 156.816 | F21: 131.621 | G21: 172.339 | H21: 168.567 | I21: 175.623 | J21: 43.447 | K21: 44.062 | L21: 47.152 | M21: 46.152 | N21: 180.813 | O21: 47.18 | P21: 47.858 | Q21: 45.33 | R21: 46.101 | S21: 186.469 | T21: 43.941 | U21: 49.937 | V21: 55.754 | W21: 57.375 | X21: 207.007 | Y21: 56.002 | Z21: 61.116 | AA21: 61.13 | AB21: 62.811 | AC21: 241.059 | AD21: 59.382 | AE21: 65.433 | AF21: 69.514 | AG21: 72.025 | AH21: 266.354 | AI21: 69.915 | AJ21: 87.91 | AK21: 92.105 | AL21: 92.718 | AM21: 342.648 | AN21: 85.683 | AO21: 104.403 | AP21: 115.146 | AQ21: 115.945 | AR21: 421.177 | AS21: 115.138 | AT21: 129.148 | AU21: 131.55 | AV21: 152.711 | AW21: 528.547 | AX21: 144.651 | AY21: 168.719 | AZ21: 172.202 | BA21: 168.575 | BB21: 654.147 | BC21: 169.487 | BD21: 183.742 | BE21: 179.355 | BF21: 174.059 | BG21: 706.643 | BH21: 177.988 | BI21: 198.507 | BJ21: 201.778 | BK21: 195.555 | BL21: 773.828 | BM21: 192.112 | BN21: 236.885 | BO21: 241.45 | BP21: 249.203 | BQ21: 919.65 | BR21: 235.675 | BS21: 297.039 | BT21: 324.309 | BU21: 311.552 | BV21: 1168.575 | BW21: 304.534 | BX21: 474.973 | BY21: 458.897 | CO21: Q4/26E depreciation & amortization ($m) | CQ21: 4.3 | CS21: Q3 $4.2m; rising with capitalized software.
B22: Check: revenue streams vs segment revenue (should be 0) | C22: =IF(AND(ISNUMBER(C11),ISNUMBER(C14),ISNUMBER(C21)),IF(ABS(C17-C21)<=0.15,0,ROUND(C17-C21,1)),"") | D22: =IF(AND(ISNUMBER(D11),ISNUMBER(D14),ISNUMBER(D21)),IF(ABS(D17-D21)<=0.15,0,ROUND(D17-D21,1)),"") | E22: =IF(AND(ISNUMBER(E11),ISNUMBER(E14),ISNUMBER(E21)),IF(ABS(E17-E21)<=0.15,0,ROUND(E17-E21,1)),"") | F22: =IF(AND(ISNUMBER(F11),ISNUMBER(F14),ISNUMBER(F21)),IF(ABS(F17-F21)<=0.15,0,ROUND(F17-F21,1)),"") | G22: =IF(AND(ISNUMBER(G11),ISNUMBER(G14),ISNUMBER(G21)),IF(ABS(G17-G21)<=0.15,0,ROUND(G17-G21,1)),"") | H22: =IF(AND(ISNUMBER(H11),ISNUMBER(H14),ISNUMBER(H21)),IF(ABS(H17-H21)<=0.15,0,ROUND(H17-H21,1)),"") | I22: =IF(AND(ISNUMBER(I11),ISNUMBER(I14),ISNUMBER(I21)),IF(ABS(I17-I21)<=0.15,0,ROUND(I17-I21,1)),"") | J22: =IF(AND(ISNUMBER(J11),ISNUMBER(J14),ISNUMBER(J21)),IF(ABS(J17-J21)<=0.15,0,ROUND(J17-J21,1)),"") | ... BY22: =IF(AND(ISNUMBER(BY11),ISNUMBER(BY14),ISNUMBER(BY21)),IF(ABS(BY17-BY21)<=0.15,0,ROUND(BY17-BY21,1)),"") -> 0 | CO22: Q4/26E share-based compensation ($m) | CQ22: 46.1 | CS22: FY26 guidance $188m − 9M actual $141.9m.
B23: Scores segment operating income | C23: 112.413 | D23: 115.317 | E23: 90.458 | F23: 75.888 | G23: 110.651 | H23: 113.398 | I23: 122.936 | J23: 29.666 | K23: 31.128 | L23: 34.175 | M23: 34.063 | N23: 129.032 | O23: 36.805 | P23: 36.919 | Q23: 33.886 | R23: 34.672 | S23: 142.282 | T23: 31.049 | U23: 35.319 | V23: 41.018 | W23: 43.828 | X23: 151.214 | Y23: 41.833 | Z23: 47.026 | AA23: 46.809 | AB23: 49.416 | AC23: 185.084 | AD23: 46.063 | AE23: 50.949 | AF23: 55.501 | AG23: 59.405 | AH23: 211.918 | AI23: 54.028 | AJ23: 71.499 | AK23: 75.731 | AL23: 77.914 | AM23: 279.171 | AN23: 72.201 | AO23: 88.236 | AP23: 99.296 | AQ23: 101.623 | AR23: 361.356 | AS23: 97.426 | AT23: 113.488 | AU23: 110.217 | AV23: 133.179 | AW23: 454.31 | AX23: 123.025 | AY23: 146.542 | AZ23: 146.784 | BA23: 144.333 | BB23: 560.684 | BC23: 147.503 | BD23: 162.716 | BE23: 160.148 | BF23: 152.439 | BG23: 622.806 | BH23: 156.692 | BI23: 175.405 | BJ23: 176.999 | BK23: 171.975 | BL23: 681.071 | BM23: 168.654 | BN23: 212.208 | BO23: 212.989 | BP23: 219.503 | BQ23: 813.354 | BR23: 203.771 | BS23: 264.97 | BT23: 284.711 | BU23: 272.791 | BV23: 1026.243 | BW23: 267.853 | BX23: 432.476 | BY23: 416.886 | BZ23: =BZ17*BZ24 -> 385.55731 | CA23: =SUM(BW23:BZ23) -> 1502.7723 | CB23: =CB17*CB24 -> 1725.5454 | CC23: =CC17*CC24 -> 1915.33 | CD23: =CD17*CD24 -> 2093.3838 | CE23: =CE17*CE24 -> 2267.7701 | CF23: =CF17*CF24 -> 2437.1594 | CG23: Segment operating income as reported (company measure: excludes share-based compensation, amortization, restructuring & acquisition costs and unallocated corporate expenses; FY2006–09 segment results were after amortization and corporate costs). Forecast = segment revenue × segment margin. | CI23: =IFERROR((CF23/CA23)^(1/5)-1,"n/m") -> 0.10153462 | CJ23: =IFERROR((BV23/AW23)^(1/5)-1,"n/m") -> 0.17700845 | CK23: =IFERROR((BV23/X23)^(1/10)-1,"n/m") -> 0.21106045 | CL23: =IFERROR((BV23/C23)^(1/19)-1,"n/m") -> 0.12343808 | CO23: Q4/26E restructuring charges ($m) | CQ23: 27 | CS23: 8-K Item 2.05 (1-Oct-2026): ~$27.0m pre-tax in Q4 FY26 (15% workforce reduction).
B24: Segment operating margin % | C24: =IF(AND(ISNUMBER(C23),ISNUMBER(C17)),IFERROR(C23/C17,""),"") -> 0.63455676 | D24: =IF(AND(ISNUMBER(D23),ISNUMBER(D17)),IFERROR(D23/D17,""),"") -> 0.63907362 | E24: =IF(AND(ISNUMBER(E23),ISNUMBER(E17)),IFERROR(E23/E17,""),"") -> 0.57684165 | F24: =IF(AND(ISNUMBER(F23),ISNUMBER(F17)),IFERROR(F23/F17,""),"") -> 0.57656453 | G24: =IF(AND(ISNUMBER(G23),ISNUMBER(G17)),IFERROR(G23/G17,""),"") -> 0.64205432 | H24: =IF(AND(ISNUMBER(H23),ISNUMBER(H17)),IFERROR(H23/H17,""),"") -> 0.67271767 | I24: =IF(AND(ISNUMBER(I23),ISNUMBER(I17)),IFERROR(I23/I17,""),"") -> 0.69999943 | J24: =IF(AND(ISNUMBER(J23),ISNUMBER(J17)),IFERROR(J23/J17,""),"") -> 0.68280894 | ... BY24: =IF(AND(ISNUMBER(BY23),ISNUMBER(BY17)),IFERROR(BY23/BY17,""),"") -> 0.90845222 | BZ24: =BZ25+$BZ$104 -> 0.87322736 | CA24: =IF(AND(ISNUMBER(CA23),ISNUMBER(CA17)),IFERROR(CA23/CA17,""),"") -> 0.89454172 | CB24: =CHOOSE(MATCH($CG$2,{"Bull","Base","Bear"},0),$CP$63,$CQ$63,$CR$63) -> 0.905 | CC24: =CHOOSE(MATCH($CG$2,{"Bull","Base","Bear"},0),$CP$64,$CQ$64,$CR$64) -> 0.905 | CD24: =CHOOSE(MATCH($CG$2,{"Bull","Base","Bear"},0),$CP$65,$CQ$65,$CR$65) -> 0.905 | CE24: =CHOOSE(MATCH($CG$2,{"Bull","Base","Bear"},0),$CP$66,$CQ$66,$CR$66) -> 0.905 | CF24: =CHOOSE(MATCH($CG$2,{"Bull","Base","Bear"},0),$CP$67,$CQ$67,$CR$67) -> 0.905 | CG24: Q4/26E: margin before calibration + non-GAAP-EPS-guidance calibration Δ (Group block). 2027E+: scenario lever. | CI24: =IFERROR(AVERAGE(CB24,CC24,CD24,CE24,CF24),"n/m") -> 0.905 | CJ24: =IFERROR(AVERAGE(BB24,BG24,BL24,BQ24,BV24),"n/m") -> 0.87624613 | CK24: =IFERROR(AVERAGE(AC24,AH24,AM24,AR24,AW24,BB24,BG24,BL24,BQ24,BV24),"n/m") -> 0.84769094 | CL24: =IFERROR(AVERAGE(C24,D24,E24,F24,G24,H24,I24,N24,S24,X24,AC24,AH24,AM24,AR24,AW24,BB24,BG24,BL24,BQ24,BV24),"n/m") -> 0.75629247 | CO24: Q4/26E purchases of property and equipment ($m) | CQ24: 0.6 | CS24: 9M FY26 $1.4m.
B25: Q4/26E margin before EPS calibration (prior-year quarter + 9M FY26 y/y drift) | BZ25: =BU24+IFERROR(SUM(BW23:BY23)/SUM(BW17:BY17)-SUM(BR23:BT23)/SUM(BR17:BT17),0) -> 0.8985781 | CO25: Q4/26E capitalized internal-use software ($m) | CQ25: 9.5 | CS25: 9M FY26 $26.5m (Q3 $9.2m).
B26: Incremental segment margin (Δ operating income / Δ revenue) | D26: =IFERROR((D23-C23)/(D17-C17),"") -> 0.88213852 | E26: =IFERROR((E23-D23)/(E17-D17),"") -> 1.0520992 | F26: =IFERROR((F23-E23)/(F17-E17),"") -> 0.57828934 | G26: =IFERROR((G23-F23)/(G17-F17),"") -> 0.85375018 | H26: =IFERROR((H23-G23)/(H17-G17),"") -> -0.72826087 | I26: =IFERROR((I23-H23)/(I17-H17),"") -> 1.3517574 | N26: =IFERROR((N23-I23)/(N17-I17),"") -> 1.1745665 | O26: =IFERROR((O23-J23)/(O17-J17),"") -> 1.9124029 | P26: =IFERROR((P23-K23)/(P17-K17),"") -> 1.5255532 | Q26: =IFERROR((Q23-L23)/(Q17-L17),"") -> 0.1586169 | R26: =IFERROR((R23-M23)/(R17-M17),"") -> -11.941176 | S26: =IFERROR((S23-N23)/(S17-N17),"") -> 2.342645 | T26: =IFERROR((T23-O23)/(T17-O17),"") -> 1.7770917 | U26: =IFERROR((U23-P23)/(U17-P17),"") -> -0.76960077 | ... CA26: =IFERROR((CA23-BV23)/(CA17-BV17),"") -> 0.93188541 | CB26: =IFERROR((CB23-CA23)/(CB17-CA17),"") -> 0.98248471 | CC26: =IFERROR((CC23-CB23)/(CC17-CB17),"") -> 0.905 | CD26: =IFERROR((CD23-CC23)/(CD17-CC17),"") -> 0.905 | CE26: =IFERROR((CE23-CD23)/(CE17-CD17),"") -> 0.905 | CF26: =IFERROR((CF23-CE23)/(CF17-CE17),"") -> 0.905 | CO26: Q4/26E non-GAAP effective tax rate | CQ26: 0.255 | CS26: 9M FY26 25.4% (non-GAAP tax = GAAP tax − income tax adjustments − excess tax benefit).
CO27: Q4/26E tax rate on adjusting items | CQ27: 0.245 | CS27: FY26 guidance: income tax adjustments −$46m on SBC $188m = 24.5%.
B28: Software (= consolidated revenue − Scores: Strategy Machine Solutions + Professional Services + Analytic Software Tools to FY2009; Applications + Tools / Decision Management Software FY2010–Q3/21; Software from FY2021) | CG28: SOFTWARE — modelling logic | CO28: Q4/26E excess tax benefit line ($m; + = shortfall added back) | CQ28: 3.37 | CS28: FY26 guidance −$13m − 9M actual $-16.4m.
B29: Platform software (FICO Platform: SaaS / cloud decisioning) | AR29: 39.175 | AW29: 65.665 | AX29: 14.125 | AY29: 15.312 | AZ29: 14.178 | BA29: 23.269 | BB29: 66.884 | BC29: 22.072 | BD29: 39.802 | BE29: 27.806 | BF29: 26.572 | BG29: 116.252 | BH29: 30.828 | BI29: 38.682 | BJ29: 40.317 | BK29: 44.923 | BL29: 154.75 | BM29: 45.173 | BN29: 47.325 | BO29: 51.78 | BP29: 55.726 | BQ29: 200.004 | BR29: 53.822 | BS29: 56.464 | BT29: 61.479 | BU29: 65.291 | BV29: 237.056 | BW29: 73.857 | BX29: 86.963 | BY29: 101.845 | BZ29: =BU29*(1+BZ30) -> 97.704862 | CA29: =SUM(BW29:BZ29) -> 360.36986 | CB29: =CA29*(1+CB30) -> 468.48082 | CC29: =CB29*(1+CC30) -> 585.60103 | CD29: =CC29*(1+CD30) -> 702.72123 | CE29: =CD29*(1+CE30) -> 822.18384 | CF29: =CE29*(1+CF30) -> 945.51142 | CG29: Revenue streams from the 10-Q / 10-K MD&A tables (first published in the FY2021 10-K: FY2019–21 annual; FY2021 quarters from the FY2022 10-Q comparatives; Q4 = fiscal year − nine months). Q4/26E: prior-year quarter × (1 + growth). 2027E+: prior year × (1 + scenario lever). | CI29: =IFERROR((CF29/CA29)^(1/5)-1,"n/m") -> 0.21278457 | CJ29: =IFERROR((BV29/AW29)^(1/5)-1,"n/m") -> 0.29271682 | CK29: =IFERROR((BV29/X29)^(1/10)-1,"n/m") -> n/m | CL29: =IFERROR((BV29/C29)^(1/19)-1,"n/m") -> n/m
B30: y/y % | D30: =IF(AND(ISNUMBER(D29),ISNUMBER(C29)),IFERROR(D29/C29-1,""),"") | E30: =IF(AND(ISNUMBER(E29),ISNUMBER(D29)),IFERROR(E29/D29-1,""),"") | F30: =IF(AND(ISNUMBER(F29),ISNUMBER(E29)),IFERROR(F29/E29-1,""),"") | G30: =IF(AND(ISNUMBER(G29),ISNUMBER(F29)),IFERROR(G29/F29-1,""),"") | H30: =IF(AND(ISNUMBER(H29),ISNUMBER(G29)),IFERROR(H29/G29-1,""),"") | I30: =IF(AND(ISNUMBER(I29),ISNUMBER(H29)),IFERROR(I29/H29-1,""),"") | N30: =IF(AND(ISNUMBER(N29),ISNUMBER(I29)),IFERROR(N29/I29-1,""),"") | O30: =IF(AND(ISNUMBER(O29),ISNUMBER(J29)),IFERROR(O29/J29-1,""),"") | P30: =IF(AND(ISNUMBER(P29),ISNUMBER(K29)),IFERROR(P29/K29-1,""),"") | Q30: =IF(AND(ISNUMBER(Q29),ISNUMBER(L29)),IFERROR(Q29/L29-1,""),"") | R30: =IF(AND(ISNUMBER(R29),ISNUMBER(M29)),IFERROR(R29/M29-1,""),"") | S30: =IF(AND(ISNUMBER(S29),ISNUMBER(N29)),IFERROR(S29/N29-1,""),"") | T30: =IF(AND(ISNUMBER(T29),ISNUMBER(O29)),IFERROR(T29/O29-1,""),"") | U30: =IF(AND(ISNUMBER(U29),ISNUMBER(P29)),IFERROR(U29/P29-1,""),"") | ... BY30: =IF(AND(ISNUMBER(BY29),ISNUMBER(BT29)),IFERROR(BY29/BT29-1,""),"") -> 0.65658192 | BZ30: =BZ31+$BZ$97 -> 0.49645222 | CA30: =IF(AND(ISNUMBER(CA29),ISNUMBER(BV29)),IFERROR(CA29/BV29-1,""),"") -> 0.52018874 | CB30: =CHOOSE(MATCH($CG$2,{"Bull","Base","Bear"},0),$CP$45,$CQ$45,$CR$45) -> 0.3 | CC30: =CHOOSE(MATCH($CG$2,{"Bull","Base","Bear"},0),$CP$46,$CQ$46,$CR$46) -> 0.25 | CD30: =CHOOSE(MATCH($CG$2,{"Bull","Base","Bear"},0),$CP$47,$CQ$47,$CR$47) -> 0.2 | CE30: =CHOOSE(MATCH($CG$2,{"Bull","Base","Bear"},0),$CP$48,$CQ$48,$CR$48) -> 0.17 | CF30: =CHOOSE(MATCH($CG$2,{"Bull","Base","Bear"},0),$CP$49,$CQ$49,$CR$49) -> 0.15 | CG30: Q4/26E: 9M FY26 y/y growth of the stream + revenue-guidance calibration Δ (Group block). 2027E–2031E: scenario lever (Bull/Base/Bear table →). | CO30: Maximum net debt / adjusted EBITDA before buybacks (x) — buyback floor 2027E+ | CP30: 3.25 | CQ30: 3 | CR30: 2.5 | CS30: Net debt $5.28bn at 30-Jun-2026 ≈ 3.5x LTM adjusted EBITDA (model); credit-agreement covenant 4.5x to Dec-2026, 4.0x to Dec-2027, 3.5x thereafter. Target (assumption) = leverage up to which free cash flow and debt capacity are returned via buybacks; FICO has bought back stock every year since FY2013. Bull = more buybacks (higher target).
B31: Q4/26E growth before revenue calibration (9M FY26 y/y) | BZ31: =IFERROR(SUM(BW29:BY29)/SUM(BR29:BT29)-1,0) -> 0.52921142
B32: Non-platform software (on-premises & SaaS point solutions: fraud, originations, customer management) | AR32: 517.793 | AW32: 518.911 | AX32: 112.33 | AY32: 110.239 | AZ32: 116.052 | BA32: 112.383 | BB32: 451.004 | BC32: 104.266 | BD32: 109.286 | BE32: 114.731 | BF32: 120.216 | BG32: 448.499 | BH32: 113.732 | BI32: 115.902 | BJ32: 131.742 | BK32: 124.056 | BL32: 485.432 | BM32: 123.495 | BN32: 129.855 | BO32: 132.005 | BP32: 125.981 | BQ32: 511.336 | BR32: 132.189 | BS32: 127.362 | BT32: 126.436 | BU32: 117.102 | BV32: 503.089 | BW32: 114.364 | BX32: 112.268 | BY32: 95.124 | BZ32: =BU32*(1+BZ33) -> 93.77922 | CA32: =SUM(BW32:BZ32) -> 415.53522 | CB32: =CA32*(1+CB33) -> 353.20494 | CC32: =CB32*(1+CC33) -> 317.88444 | CD32: =CC32*(1+CD33) -> 295.63253 | CE32: =CD32*(1+CE33) -> 280.85091 | CF32: =CE32*(1+CF33) -> 269.61687 | CI32: =IFERROR((CF32/CA32)^(1/5)-1,"n/m") -> -0.082876452 | CJ32: =IFERROR((BV32/AW32)^(1/5)-1,"n/m") -> -0.0061739209 | CK32: =IFERROR((BV32/X32)^(1/10)-1,"n/m") -> n/m | CL32: =IFERROR((BV32/C32)^(1/19)-1,"n/m") -> n/m | CO32: SC_B2B (B2B scores revenue y/y) | CP32: 0.05 | CQ32: Δ → | CR32: -0.12 | CS32: 9M FY26 +54%, FY25 +33%, FY24 +27% — mortgage origination score unit price (10-Q MD&A). Base assumes pricing gains moderate. Bear: FHFA approval of other score models / VantageScore competition (10-K risk factors).
B33: y/y % | D33: =IF(AND(ISNUMBER(D32),ISNUMBER(C32)),IFERROR(D32/C32-1,""),"") | E33: =IF(AND(ISNUMBER(E32),ISNUMBER(D32)),IFERROR(E32/D32-1,""),"") | F33: =IF(AND(ISNUMBER(F32),ISNUMBER(E32)),IFERROR(F32/E32-1,""),"") | G33: =IF(AND(ISNUMBER(G32),ISNUMBER(F32)),IFERROR(G32/F32-1,""),"") | H33: =IF(AND(ISNUMBER(H32),ISNUMBER(G32)),IFERROR(H32/G32-1,""),"") | I33: =IF(AND(ISNUMBER(I32),ISNUMBER(H32)),IFERROR(I32/H32-1,""),"") | N33: =IF(AND(ISNUMBER(N32),ISNUMBER(I32)),IFERROR(N32/I32-1,""),"") | O33: =IF(AND(ISNUMBER(O32),ISNUMBER(J32)),IFERROR(O32/J32-1,""),"") | P33: =IF(AND(ISNUMBER(P32),ISNUMBER(K32)),IFERROR(P32/K32-1,""),"") | Q33: =IF(AND(ISNUMBER(Q32),ISNUMBER(L32)),IFERROR(Q32/L32-1,""),"") | R33: =IF(AND(ISNUMBER(R32),ISNUMBER(M32)),IFERROR(R32/M32-1,""),"") | S33: =IF(AND(ISNUMBER(S32),ISNUMBER(N32)),IFERROR(S32/N32-1,""),"") | T33: =IF(AND(ISNUMBER(T32),ISNUMBER(O32)),IFERROR(T32/O32-1,""),"") | U33: =IF(AND(ISNUMBER(U32),ISNUMBER(P32)),IFERROR(U32/P32-1,""),"") | ... BY33: =IF(AND(ISNUMBER(BY32),ISNUMBER(BT32)),IFERROR(BY32/BT32-1,""),"") -> -0.24765099 | BZ33: =BZ34+$BZ$97 -> -0.19916636 | CA33: =IF(AND(ISNUMBER(CA32),ISNUMBER(BV32)),IFERROR(CA32/BV32-1,""),"") -> -0.17403239 | CB33: =CHOOSE(MATCH($CG$2,{"Bull","Base","Bear"},0),$CP$51,$CQ$51,$CR$51) -> -0.15 | CC33: =CHOOSE(MATCH($CG$2,{"Bull","Base","Bear"},0),$CP$52,$CQ$52,$CR$52) -> -0.1 | CD33: =CHOOSE(MATCH($CG$2,{"Bull","Base","Bear"},0),$CP$53,$CQ$53,$CR$53) -> -0.07 | CE33: =CHOOSE(MATCH($CG$2,{"Bull","Base","Bear"},0),$CP$54,$CQ$54,$CR$54) -> -0.05 | CF33: =CHOOSE(MATCH($CG$2,{"Bull","Base","Bear"},0),$CP$55,$CQ$55,$CR$55) -> -0.04 | CO33: 2027E | CP33: =CQ33+$CP$32 -> 0.2 | CQ33: 0.15 | CR33: =CQ33+$CR$32 -> 0.03
B34: Q4/26E growth before revenue calibration (9M FY26 y/y) | BZ34: =IFERROR(SUM(BW32:BY32)/SUM(BR32:BT32)-1,0) -> -0.16640716 | CO34: 2028E | CP34: =CQ34+$CP$32 -> 0.17 | CQ34: 0.12 | CR34: =CQ34+$CR$32 -> 0
B35: Professional services | BA35: 30.35 | BB35: 144.501 | BC35: 26.536 | BD35: 24.365 | BE35: 27.074 | BF35: 27.901 | BG35: 105.876 | BH35: 22.322 | BI35: 27.175 | BJ35: 24.851 | BK35: 25.199 | BL35: 99.547 | BM35: 21.279 | BN35: 19.744 | BO35: 22.614 | BP35: 22.899 | BQ35: 86.536 | BR35: 18.282 | BS35: 17.87 | BT35: 24.191 | BU35: 21.806 | BV35: 82.149 | BW35: 19.204 | BX35: 17.473 | BY35: 18.322 | BZ35: =BU35*(1+BZ36) -> 19.160505 | CA35: =SUM(BW35:BZ35) -> 74.159505 | CB35: =CA35*(1+CB36) -> 70.45153 | CC35: =CB35*(1+CC36) -> 68.337984 | CD35: =CC35*(1+CD36) -> 68.337984 | CE35: =CD35*(1+CE36) -> 68.337984 | CF35: =CE35*(1+CF36) -> 68.337984 | CI35: =IFERROR((CF35/CA35)^(1/5)-1,"n/m") -> -0.016217556 | CJ35: =IFERROR((BV35/AW35)^(1/5)-1,"n/m") -> n/m | CK35: =IFERROR((BV35/X35)^(1/10)-1,"n/m") -> n/m | CL35: =IFERROR((BV35/C35)^(1/19)-1,"n/m") -> n/m | CO35: 2029E | CP35: =CQ35+$CP$32 -> 0.15 | CQ35: 0.1 | CR35: =CQ35+$CR$32 -> -0.02
B36: y/y % | D36: =IF(AND(ISNUMBER(D35),ISNUMBER(C35)),IFERROR(D35/C35-1,""),"") | E36: =IF(AND(ISNUMBER(E35),ISNUMBER(D35)),IFERROR(E35/D35-1,""),"") | F36: =IF(AND(ISNUMBER(F35),ISNUMBER(E35)),IFERROR(F35/E35-1,""),"") | G36: =IF(AND(ISNUMBER(G35),ISNUMBER(F35)),IFERROR(G35/F35-1,""),"") | H36: =IF(AND(ISNUMBER(H35),ISNUMBER(G35)),IFERROR(H35/G35-1,""),"") | I36: =IF(AND(ISNUMBER(I35),ISNUMBER(H35)),IFERROR(I35/H35-1,""),"") | N36: =IF(AND(ISNUMBER(N35),ISNUMBER(I35)),IFERROR(N35/I35-1,""),"") | O36: =IF(AND(ISNUMBER(O35),ISNUMBER(J35)),IFERROR(O35/J35-1,""),"") | P36: =IF(AND(ISNUMBER(P35),ISNUMBER(K35)),IFERROR(P35/K35-1,""),"") | Q36: =IF(AND(ISNUMBER(Q35),ISNUMBER(L35)),IFERROR(Q35/L35-1,""),"") | R36: =IF(AND(ISNUMBER(R35),ISNUMBER(M35)),IFERROR(R35/M35-1,""),"") | S36: =IF(AND(ISNUMBER(S35),ISNUMBER(N35)),IFERROR(S35/N35-1,""),"") | T36: =IF(AND(ISNUMBER(T35),ISNUMBER(O35)),IFERROR(T35/O35-1,""),"") | U36: =IF(AND(ISNUMBER(U35),ISNUMBER(P35)),IFERROR(U35/P35-1,""),"") | ... BY36: =IF(AND(ISNUMBER(BY35),ISNUMBER(BT35)),IFERROR(BY35/BT35-1,""),"") -> -0.24261089 | BZ36: =BZ37+$BZ$97 -> -0.1213196 | CA36: =IF(AND(ISNUMBER(CA35),ISNUMBER(BV35)),IFERROR(CA35/BV35-1,""),"") -> -0.097256147 | CB36: =CHOOSE(MATCH($CG$2,{"Bull","Base","Bear"},0),$CP$57,$CQ$57,$CR$57) -> -0.05 | CC36: =CHOOSE(MATCH($CG$2,{"Bull","Base","Bear"},0),$CP$58,$CQ$58,$CR$58) -> -0.03 | CD36: =CHOOSE(MATCH($CG$2,{"Bull","Base","Bear"},0),$CP$59,$CQ$59,$CR$59) -> 0 | CE36: =CHOOSE(MATCH($CG$2,{"Bull","Base","Bear"},0),$CP$60,$CQ$60,$CR$60) -> 0 | CF36: =CHOOSE(MATCH($CG$2,{"Bull","Base","Bear"},0),$CP$61,$CQ$61,$CR$61) -> 0 | CO36: 2030E | CP36: =CQ36+$CP$32 -> 0.14 | CQ36: 0.09 | CR36: =CQ36+$CR$32 -> -0.03
B37: Q4/26E growth before revenue calibration (9M FY26 y/y) | BZ37: =IFERROR(SUM(BW35:BY35)/SUM(BR35:BT35)-1,0) -> -0.088560396 | CO37: 2031E | CP37: =CQ37+$CP$32 -> 0.13 | CQ37: 0.08 | CR37: =CQ37+$CR$32 -> -0.04
B38: Software — segment revenue | C38: =IF(AND(ISNUMBER(C29),ISNUMBER(C32),ISNUMBER(C35)),C29+C32+C35,C42) -> 648.213 | D38: =IF(AND(ISNUMBER(D29),ISNUMBER(D32),ISNUMBER(D35)),D29+D32+D35,D42) -> 641.792 | E38: =IF(AND(ISNUMBER(E29),ISNUMBER(E32),ISNUMBER(E35)),E29+E32+E35,E42) -> 588.026 | F38: =IF(AND(ISNUMBER(F29),ISNUMBER(F32),ISNUMBER(F35)),F29+F32+F35,F42) -> 499.114 | G38: =IF(AND(ISNUMBER(G29),ISNUMBER(G32),ISNUMBER(G35)),G29+G32+G35,G42) -> 433.304 | H38: =IF(AND(ISNUMBER(H29),ISNUMBER(H32),ISNUMBER(H35)),H29+H32+H35,H42) -> 451.116 | I38: =IF(AND(ISNUMBER(I29),ISNUMBER(I32),ISNUMBER(I35)),I29+I32+I35,I42) -> 500.8 | J38: =IF(AND(ISNUMBER(J29),ISNUMBER(J32),ISNUMBER(J35)),J29+J32+J35,J42) -> 146.573 | ... BY38: =IF(AND(ISNUMBER(BY29),ISNUMBER(BY32),ISNUMBER(BY35)),BY29+BY32+BY35,BY42) -> 215.291 | BZ38: =BZ29+BZ32+BZ35 -> 210.64459 | CA38: =CA29+CA32+CA35 -> 850.06459 | CB38: =CB29+CB32+CB35 -> 892.13729 | CC38: =CC29+CC32+CC35 -> 971.82345 | CD38: =CD29+CD32+CD35 -> 1066.6917 | CE38: =CE29+CE32+CE35 -> 1171.3727 | CF38: =CF29+CF32+CF35 -> 1283.4663 | CI38: =IFERROR((CF38/CA38)^(1/5)-1,"n/m") -> 0.085891684 | CJ38: =IFERROR((BV38/AW38)^(1/5)-1,"n/m") -> 0.014280251 | CK38: =IFERROR((BV38/X38)^(1/10)-1,"n/m") -> 0.026707034 | CL38: =IFERROR((BV38/C38)^(1/19)-1,"n/m") -> 0.012598631 | CO38: SC_B2C (B2C scores revenue y/y) | CP38: 0.02 | CQ38: Δ → | CR38: -0.04 | CS38: 9M FY26 +5%, FY25 +6%, FY24 −2% (myFICO subscriptions; royalties on scores sold through the bureaus).
B39: Segment revenue y/y % | D39: =IF(AND(ISNUMBER(D38),ISNUMBER(C38)),IFERROR(D38/C38-1,""),"") -> -0.0099056946 | E39: =IF(AND(ISNUMBER(E38),ISNUMBER(D38)),IFERROR(E38/D38-1,""),"") -> -0.083774806 | F39: =IF(AND(ISNUMBER(F38),ISNUMBER(E38)),IFERROR(F38/E38-1,""),"") -> -0.1512042 | G39: =IF(AND(ISNUMBER(G38),ISNUMBER(F38)),IFERROR(G38/F38-1,""),"") -> -0.13185364 | H39: =IF(AND(ISNUMBER(H38),ISNUMBER(G38)),IFERROR(H38/G38-1,""),"") -> 0.041107398 | I39: =IF(AND(ISNUMBER(I38),ISNUMBER(H38)),IFERROR(I38/H38-1,""),"") -> 0.11013575 | N39: =IF(AND(ISNUMBER(N38),ISNUMBER(I38)),IFERROR(N38/I38-1,""),"") -> 0.12346446 | O39: =IF(AND(ISNUMBER(O38),ISNUMBER(J38)),IFERROR(O38/J38-1,""),"") -> -0.064200091 | P39: =IF(AND(ISNUMBER(P38),ISNUMBER(K38)),IFERROR(P38/K38-1,""),"") -> 0.017307024 | Q39: =IF(AND(ISNUMBER(Q38),ISNUMBER(L38)),IFERROR(Q38/L38-1,""),"") -> 0.11462451 | R39: =IF(AND(ISNUMBER(R38),ISNUMBER(M38)),IFERROR(R38/M38-1,""),"") -> 0.21705566 | S39: =IF(AND(ISNUMBER(S38),ISNUMBER(N38)),IFERROR(S38/N38-1,""),"") -> 0.070890157 | T39: =IF(AND(ISNUMBER(T38),ISNUMBER(O38)),IFERROR(T38/O38-1,""),"") -> 0.061576373 | U39: =IF(AND(ISNUMBER(U38),ISNUMBER(P38)),IFERROR(U38/P38-1,""),"") -> 0.14220517 | ... CA39: =IF(AND(ISNUMBER(CA38),ISNUMBER(BV38)),IFERROR(CA38/BV38-1,""),"") -> 0.03377209 | CB39: =IF(AND(ISNUMBER(CB38),ISNUMBER(CA38)),IFERROR(CB38/CA38-1,""),"") -> 0.049493534 | CC39: =IF(AND(ISNUMBER(CC38),ISNUMBER(CB38)),IFERROR(CC38/CB38-1,""),"") -> 0.089320519 | CD39: =IF(AND(ISNUMBER(CD38),ISNUMBER(CC38)),IFERROR(CD38/CC38-1,""),"") -> 0.097618856 | CE39: =IF(AND(ISNUMBER(CE38),ISNUMBER(CD38)),IFERROR(CE38/CD38-1,""),"") -> 0.098136114 | CF39: =IF(AND(ISNUMBER(CF38),ISNUMBER(CE38)),IFERROR(CF38/CE38-1,""),"") -> 0.095694169 | CO39: 2027E | CP39: =CQ39+$CP$38 -> 0.06 | CQ39: 0.04 | CR39: =CQ39+$CR$38 -> 0
B40: % of total revenue | C40: =IF(AND(ISNUMBER(C38),ISNUMBER(C87)),IFERROR(C38/C87,""),"") -> 0.78536526 | D40: =IF(AND(ISNUMBER(D38),ISNUMBER(D87)),IFERROR(D38/D87,""),"") -> 0.78054476 | E40: =IF(AND(ISNUMBER(E38),ISNUMBER(E87)),IFERROR(E38/E87,""),"") -> 0.78946407 | F40: =IF(AND(ISNUMBER(F38),ISNUMBER(F87)),IFERROR(F38/F87,""),"") -> 0.79132124 | G40: =IF(AND(ISNUMBER(G38),ISNUMBER(G87)),IFERROR(G38/G87,""),"") -> 0.71544458 | H40: =IF(AND(ISNUMBER(H38),ISNUMBER(H87)),IFERROR(H38/H87,""),"") -> 0.72797866 | I40: =IF(AND(ISNUMBER(I38),ISNUMBER(I87)),IFERROR(I38/I87,""),"") -> 0.74036513 | J40: =IF(AND(ISNUMBER(J38),ISNUMBER(J87)),IFERROR(J38/J87,""),"") -> 0.77135565 | ... CF40: =IF(AND(ISNUMBER(CF38),ISNUMBER(CF87)),IFERROR(CF38/CF87,""),"") -> 0.32276604 | CO40: 2028E | CP40: =CQ40+$CP$38 -> 0.06 | CQ40: 0.04 | CR40: =CQ40+$CR$38 -> 0
B41: Platform % of on-premises & SaaS software revenue | C41: =IF(ISNUMBER(C29),IFERROR(C29/(C29+C32),""),"") | D41: =IF(ISNUMBER(D29),IFERROR(D29/(D29+D32),""),"") | E41: =IF(ISNUMBER(E29),IFERROR(E29/(E29+E32),""),"") | F41: =IF(ISNUMBER(F29),IFERROR(F29/(F29+F32),""),"") | G41: =IF(ISNUMBER(G29),IFERROR(G29/(G29+G32),""),"") | H41: =IF(ISNUMBER(H29),IFERROR(H29/(H29+H32),""),"") | I41: =IF(ISNUMBER(I29),IFERROR(I29/(I29+I32),""),"") | J41: =IF(ISNUMBER(J29),IFERROR(J29/(J29+J32),""),"") | ... CF41: =IF(ISNUMBER(CF29),IFERROR(CF29/(CF29+CF32),""),"") -> 0.77811654 | CI41: =IFERROR(AVERAGE(CB41,CC41,CD41,CE41,CF41),"n/m") -> 0.68913672 | CJ41: =IFERROR(AVERAGE(BB41,BG41,BL41,BQ41,BV41),"n/m") -> 0.23563411 | CK41: =IFERROR(AVERAGE(AC41,AH41,AM41,AR41,AW41,BB41,BG41,BL41,BQ41,BV41),"n/m") -> 0.19440514 | CL41: =IFERROR(AVERAGE(C41,D41,E41,F41,G41,H41,I41,N41,S41,X41,AC41,AH41,AM41,AR41,AW41,BB41,BG41,BL41,BQ41,BV41),"n/m") -> 0.19440514 | CO41: 2029E | CP41: =CQ41+$CP$38 -> 0.06 | CQ41: 0.04 | CR41: =CQ41+$CR$38 -> 0
B42: Memo: Software segment revenue as reported (= consolidated revenue − Scores) | C42: 648.213 | D42: 641.792 | E42: 588.026 | F42: 499.114 | G42: 433.304 | H42: 451.116 | I42: 500.8 | J42: 146.573 | K42: 135.263 | L42: 136.62 | M42: 144.175 | N42: 562.631 | O42: 137.163 | P42: 137.604 | Q42: 152.28 | R42: 175.469 | S42: 602.516 | T42: 145.609 | U42: 157.172 | V42: 153.612 | W42: 175.381 | X42: 631.774 | Y42: 144.074 | Z42: 145.562 | AA42: 177.648 | AB42: 173.013 | AC42: 640.297 | AD42: 160.218 | AE42: 162.945 | AF42: 161.472 | AG42: 181.18 | AH42: 665.815 | AI42: 165.406 | AJ42: 169.948 | AK42: 167.4 | AL42: 187.073 | AM42: 689.827 | AN42: 176.573 | AO42: 173.831 | AP42: 199.103 | AQ42: 189.399 | AR42: 738.906 | AS42: 183.366 | AT42: 178.823 | AU42: 182.181 | AV42: 221.645 | AW42: 766.015 | AX42: 167.763 | AY42: 162.642 | AZ42: 165.982 | BA42: 166.002 | BB42: 662.389 | BC42: 152.874 | BD42: 173.453 | BE42: 169.611 | BF42: 174.689 | BG42: 670.627 | BH42: 166.882 | BI42: 181.759 | BJ42: 196.91 | BK42: 194.178 | BL42: 739.729 | BM42: 189.947 | BN42: 196.924 | BO42: 206.399 | BP42: 204.606 | BQ42: 797.876 | BR42: 204.293 | BS42: 201.696 | BT42: 212.106 | BU42: 204.199 | BV42: 822.294 | BW42: 207.425 | BX42: 216.704 | BY42: 215.291 | CO42: 2030E | CP42: =CQ42+$CP$38 -> 0.05 | CQ42: 0.03 | CR42: =CQ42+$CR$38 -> -0.01
B43: Check: revenue streams vs segment revenue (should be 0) | C43: =IF(AND(ISNUMBER(C29),ISNUMBER(C32),ISNUMBER(C35),ISNUMBER(C42)),IF(ABS(C38-C42)<=0.15,0,ROUND(C38-C42,1)),"") | D43: =IF(AND(ISNUMBER(D29),ISNUMBER(D32),ISNUMBER(D35),ISNUMBER(D42)),IF(ABS(D38-D42)<=0.15,0,ROUND(D38-D42,1)),"") | E43: =IF(AND(ISNUMBER(E29),ISNUMBER(E32),ISNUMBER(E35),ISNUMBER(E42)),IF(ABS(E38-E42)<=0.15,0,ROUND(E38-E42,1)),"") | F43: =IF(AND(ISNUMBER(F29),ISNUMBER(F32),ISNUMBER(F35),ISNUMBER(F42)),IF(ABS(F38-F42)<=0.15,0,ROUND(F38-F42,1)),"") | G43: =IF(AND(ISNUMBER(G29),ISNUMBER(G32),ISNUMBER(G35),ISNUMBER(G42)),IF(ABS(G38-G42)<=0.15,0,ROUND(G38-G42,1)),"") | H43: =IF(AND(ISNUMBER(H29),ISNUMBER(H32),ISNUMBER(H35),ISNUMBER(H42)),IF(ABS(H38-H42)<=0.15,0,ROUND(H38-H42,1)),"") | I43: =IF(AND(ISNUMBER(I29),ISNUMBER(I32),ISNUMBER(I35),ISNUMBER(I42)),IF(ABS(I38-I42)<=0.15,0,ROUND(I38-I42,1)),"") | J43: =IF(AND(ISNUMBER(J29),ISNUMBER(J32),ISNUMBER(J35),ISNUMBER(J42)),IF(ABS(J38-J42)<=0.15,0,ROUND(J38-J42,1)),"") | ... BY43: =IF(AND(ISNUMBER(BY29),ISNUMBER(BY32),ISNUMBER(BY35),ISNUMBER(BY42)),IF(ABS(BY38-BY42)<=0.15,0,ROUND(BY38-BY42,1)),"") -> 0 | CO43: 2031E | CP43: =CQ43+$CP$38 -> 0.05 | CQ43: 0.03 | CR43: =CQ43+$CR$38 -> -0.01
B44: Software segment operating income | C44: 102.057 | D44: 70.332 | E44: 69.715 | F44: 72.498 | G44: 101.687 | H44: 120.251 | I44: 150.425 | J44: 36.433 | K44: 33.54 | L44: 31.363 | M44: 45.062 | N44: 146.398 | O44: 34.13 | P44: 37.849 | Q44: 40.944 | R44: 60.774 | S44: 173.697 | T44: 27.176 | U44: 34.15 | V44: 34.83 | W44: 57.102 | X44: 153.258 | Y44: 31.343 | Z44: 30.487 | AA44: 54.64 | AB44: 48.141 | AC44: 164.611 | AD44: 31.336 | AE44: 32.339 | AF44: 34.803 | AG44: 50.204 | AH44: 148.682 | AI44: 30.934 | AJ44: 30.996 | AK44: 25.021 | AL44: 46.978 | AM44: 133.929 | AN44: 29.413 | AO44: 21.804 | AP44: 43.474 | AQ44: 31.355 | AR44: 126.046 | AS44: 16.711 | AT44: 20.013 | AU44: 27.281 | AV44: 66.061 | AW44: 130.066 | AX44: 20.684 | AY44: 17.2 | AZ44: 20.186 | BA44: 47.077 | BB44: 105.147 | BC44: 34.293 | BD44: 53.5 | BE44: 47.563 | BF44: 50.096 | BG44: 185.452 | BH44: 45.765 | BI44: 54.867 | BJ44: 75.649 | BK44: 64.91 | BL44: 241.191 | BM44: 55.122 | BN44: 64.162 | BO44: 70.34 | BP44: 67.905 | BQ44: 257.529 | BR44: 60.742 | BS44: 63.324 | BT44: 67.942 | BU44: 55.686 | BV44: 247.694 | BW44: 58.614 | BX44: 62.594 | BY44: 55.04 | BZ44: =BZ38*BZ45 -> 44.729603 | CA44: =SUM(BW44:BZ44) -> 220.9776 | CB44: =CB38*CB45 -> 240.87707 | CC44: =CC38*CC45 -> 281.8288 | CD44: =CD38*CD45 -> 330.67444 | CE44: =CE38*CE45 -> 374.83927 | CF44: =CF38*CF45 -> 423.54387 | CI44: =IFERROR((CF44/CA44)^(1/5)-1,"n/m") -> 0.13896408 | CJ44: =IFERROR((BV44/AW44)^(1/5)-1,"n/m") -> 0.13749721 | CK44: =IFERROR((BV44/X44)^(1/10)-1,"n/m") -> 0.04917814 | CL44: =IFERROR((BV44/C44)^(1/19)-1,"n/m") -> 0.047772471 | CO44: SW_PLAT (platform software revenue y/y) | CP44: 0.08 | CQ44: Δ → | CR44: -0.12 | CS44: 9M FY26 +53%; platform ARR +62% and net retention 148% at 30-Jun-2026 (Q3 FY26 release); FY25 +19%.
B45: Segment operating margin % | C45: =IF(AND(ISNUMBER(C44),ISNUMBER(C38)),IFERROR(C44/C38,""),"") -> 0.15744362 | D45: =IF(AND(ISNUMBER(D44),ISNUMBER(D38)),IFERROR(D44/D38,""),"") -> 0.10958691 | E45: =IF(AND(ISNUMBER(E44),ISNUMBER(E38)),IFERROR(E44/E38,""),"") -> 0.11855768 | F45: =IF(AND(ISNUMBER(F44),ISNUMBER(F38)),IFERROR(F44/F38,""),"") -> 0.14525339 | G45: =IF(AND(ISNUMBER(G44),ISNUMBER(G38)),IFERROR(G44/G38,""),"") -> 0.23467819 | H45: =IF(AND(ISNUMBER(H44),ISNUMBER(H38)),IFERROR(H44/H38,""),"") -> 0.26656337 | I45: =IF(AND(ISNUMBER(I44),ISNUMBER(I38)),IFERROR(I44/I38,""),"") -> 0.30036941 | J45: =IF(AND(ISNUMBER(J44),ISNUMBER(J38)),IFERROR(J44/J38,""),"") -> 0.24856556 | ... BY45: =IF(AND(ISNUMBER(BY44),ISNUMBER(BY38)),IFERROR(BY44/BY38,""),"") -> 0.25565398 | BZ45: =BZ46+$BZ$104 -> 0.21234632 | CA45: =IF(AND(ISNUMBER(CA44),ISNUMBER(CA38)),IFERROR(CA44/CA38,""),"") -> 0.2599539 | CB45: =CHOOSE(MATCH($CG$2,{"Bull","Base","Bear"},0),$CP$69,$CQ$69,$CR$69) -> 0.27 | CC45: =CHOOSE(MATCH($CG$2,{"Bull","Base","Bear"},0),$CP$70,$CQ$70,$CR$70) -> 0.29 | CD45: =CHOOSE(MATCH($CG$2,{"Bull","Base","Bear"},0),$CP$71,$CQ$71,$CR$71) -> 0.31 | CE45: =CHOOSE(MATCH($CG$2,{"Bull","Base","Bear"},0),$CP$72,$CQ$72,$CR$72) -> 0.32 | CF45: =CHOOSE(MATCH($CG$2,{"Bull","Base","Bear"},0),$CP$73,$CQ$73,$CR$73) -> 0.33 | CI45: =IFERROR(AVERAGE(CB45,CC45,CD45,CE45,CF45),"n/m") -> 0.304 | CJ45: =IFERROR(AVERAGE(BB45,BG45,BL45,BQ45,BV45),"n/m") -> 0.27706377 | CK45: =IFERROR(AVERAGE(AC45,AH45,AM45,AR45,AW45,BB45,BG45,BL45,BQ45,BV45),"n/m") -> 0.24002414 | CL45: =IFERROR(AVERAGE(C45,D45,E45,F45,G45,H45,I45,N45,S45,X45,AC45,AH45,AM45,AR45,AW45,BB45,BG45,BL45,BQ45,BV45),"n/m") -> 0.22618831 | CO45: 2027E | CP45: =CQ45+$CP$44 -> 0.38 | CQ45: 0.3 | CR45: =CQ45+$CR$44 -> 0.18
B46: Q4/26E margin before EPS calibration (prior-year quarter + 9M FY26 y/y drift) | BZ46: =BU45+IFERROR(SUM(BW44:BY44)/SUM(BW38:BY38)-SUM(BR44:BT44)/SUM(BR38:BT38),0) -> 0.23769706 | CO46: 2028E | CP46: =CQ46+$CP$44 -> 0.33 | CQ46: 0.25 | CR46: =CQ46+$CR$44 -> 0.13
B47: Incremental segment margin (Δ operating income / Δ revenue) | D47: =IFERROR((D44-C44)/(D38-C38),"") -> 4.9408192 | E47: =IFERROR((E44-D44)/(E38-D38),"") -> 0.011475654 | F47: =IFERROR((F44-E44)/(F38-E38),"") -> -0.031300612 | G47: =IFERROR((G44-F44)/(G38-F38),"") -> -0.44353442 | H47: =IFERROR((H44-G44)/(H38-G38),"") -> 1.0422187 | I47: =IFERROR((I44-H44)/(I38-H38),"") -> 0.60731825 | N47: =IFERROR((N44-I44)/(N38-I38),"") -> -0.065129142 | O47: =IFERROR((O44-J44)/(O38-J38),"") -> 0.24473964 | P47: =IFERROR((P44-K44)/(P38-K38),"") -> 1.8406664 | Q47: =IFERROR((Q44-L44)/(Q38-L38),"") -> 0.61181354 | R47: =IFERROR((R44-M44)/(R38-M38),"") -> 0.50207708 | S47: =IFERROR((S44-N44)/(S38-N38),"") -> 0.68444277 | T47: =IFERROR((T44-O44)/(T38-O38),"") -> -0.82334833 | U47: =IFERROR((U44-P44)/(U38-P38),"") -> -0.18903312 | ... CA47: =IFERROR((CA44-BV44)/(CA38-BV38),"") -> -0.96203934 | CB47: =IFERROR((CB44-CA44)/(CB38-CA38),"") -> 0.47297807 | CC47: =IFERROR((CC44-CB44)/(CC38-CB38),"") -> 0.51391272 | CD47: =IFERROR((CD44-CC44)/(CD38-CC38),"") -> 0.51487845 | CE47: =IFERROR((CE44-CD44)/(CE38-CD38),"") -> 0.42189929 | CF47: =IFERROR((CF44-CE44)/(CF38-CE38),"") -> 0.43449958 | CO47: 2029E | CP47: =CQ47+$CP$44 -> 0.28 | CQ47: 0.2 | CR47: =CQ47+$CR$44 -> 0.08
B48: Legacy software segments (as originally reported; replaced by "Software" in the FY2021 10-K): | CO48: 2030E | CP48: =CQ48+$CP$44 -> 0.25 | CQ48: 0.17 | CR48: =CQ48+$CR$44 -> 0.05
B49: Strategy Machine Solutions (FY2006–09) — revenue | C49: 457.211 | D49: 439.273 | E49: 388.108 | F49: 338.753 | CO49: 2031E | CP49: =CQ49+$CP$44 -> 0.23 | CQ49: 0.15 | CR49: =CQ49+$CR$44 -> 0.03
B50: Strategy Machine Solutions (FY2006–09) — segment operating income | C50: 85.975 | D50: 62.205 | E50: 61.478 | F50: 70.775 | CO50: SW_NONPLAT (non-platform software revenue y/y) | CP50: 0.05 | CQ50: Δ → | CR50: -0.05 | CS50: 9M FY26 −17%; non-platform ARR −17% and net retention 82% at 30-Jun-2026 (migration to the platform, de-emphasis).
B51: Professional Services (FY2006–09) — revenue | C51: 145.271 | D51: 151.086 | E51: 147.864 | F51: 111.174 | CO51: 2027E | CP51: =CQ51+$CP$50 -> -0.1 | CQ51: -0.15 | CR51: =CQ51+$CR$50 -> -0.2
B52: Professional Services (FY2006–09) — segment operating income | C52: 13.333 | D52: 7.056 | E52: 0.627 | F52: -5.997 | CO52: 2028E | CP52: =CQ52+$CP$50 -> -0.05 | CQ52: -0.1 | CR52: =CQ52+$CR$50 -> -0.15
B53: Applications (FY2010–Q3/21) — revenue | G53: 367.258 | H53: 383.028 | I53: 424.604 | J53: 124.707 | K53: 117.215 | L53: 114.983 | M53: 119.179 | N53: 476.084 | O53: 111.916 | P53: 115.61 | Q53: 129.856 | R53: 146.874 | S53: 504.256 | T53: 115.498 | U53: 134.388 | V53: 127.134 | W53: 149.254 | X53: 526.274 | Y53: 120.141 | Z53: 121.917 | AA53: 141.565 | AB53: 149.019 | AC53: 532.642 | AD53: 134.765 | AE53: 134.337 | AF53: 133.782 | AG53: 150.283 | AH53: 553.167 | AI53: 141.409 | AJ53: 146.699 | AK53: 141.618 | AL53: 155.845 | AM53: 585.571 | AN53: 147.659 | AO53: 141.815 | AP53: 165.637 | AQ53: 149.923 | AR53: 605.034 | AS53: 152.178 | AT53: 140.279 | AU53: 141.46 | AV53: 168.129 | AW53: 602.046 | AX53: 135.361 | AY53: 129.514 | AZ53: 133.213 | CO53: 2029E | CP53: =CQ53+$CP$50 -> -0.02 | CQ53: -0.07 | CR53: =CQ53+$CR$50 -> -0.12
B54: Applications (FY2010–Q3/21) — segment operating income | G54: 93.275 | H54: 106.561 | I54: 132.826 | J54: 32.972 | K54: 30.93 | L54: 27.295 | M54: 38.665 | N54: 129.862 | O54: 29.954 | P54: 36.659 | Q54: 43.443 | R54: 59.438 | S54: 169.494 | T54: 26.604 | U54: 39.353 | V54: 36.906 | W54: 56.745 | X54: 159.608 | Y54: 32.704 | Z54: 33.962 | AA54: 49.033 | AB54: 52.572 | AC54: 168.271 | AD54: 34.968 | AE54: 34.883 | AF54: 38.425 | AG54: 51.224 | AH54: 159.5 | AI54: 38.79 | AJ54: 39.66 | AK54: 34.39 | AL54: 51.736 | AM54: 164.576 | AN54: 40.061 | AO54: 30.172 | AP54: 52.237 | AQ54: 38.692 | AR54: 161.162 | AS54: 36.168 | AT54: 28.823 | AU54: 30.399 | AV54: 58.151 | AW54: 153.541 | AX54: 35.502 | AY54: 27.372 | AZ54: 35.429 | CO54: 2030E | CP54: =CQ54+$CP$50 -> 0 | CQ54: -0.05 | CR54: =CQ54+$CR$50 -> -0.1
B55: Analytic Software Tools (FY2006–09) / Tools (FY2010–16) — revenue | C55: 45.731 | D55: 51.433 | E55: 52.054 | F55: 49.187 | G55: 66.046 | H55: 68.088 | I55: 76.196 | J55: 21.866 | K55: 18.048 | L55: 21.637 | M55: 24.996 | N55: 86.547 | O55: 25.247 | P55: 21.994 | Q55: 22.424 | R55: 28.595 | S55: 98.26 | T55: 30.111 | U55: 22.784 | V55: 26.478 | W55: 26.127 | X55: 105.5 | Y55: 23.933 | Z55: 23.645 | AA55: 36.083 | CO55: 2031E | CP55: =CQ55+$CP$50 -> 0.01 | CQ55: -0.04 | CR55: =CQ55+$CR$50 -> -0.09
B56: Analytic Software Tools (FY2006–09) / Tools (FY2010–16) — segment operating income | C56: 2.749 | D56: 1.071 | E56: 7.61 | F56: 7.72 | G56: 8.412 | H56: 13.69 | I56: 17.599 | J56: 3.461 | K56: 2.61 | L56: 4.068 | M56: 6.397 | N56: 16.536 | O56: 4.176 | P56: 1.19 | Q56: -2.499 | R56: 1.336 | S56: 4.203 | T56: 0.572 | U56: -5.203 | V56: -2.076 | W56: 0.357 | X56: -6.35 | Y56: -1.361 | Z56: -3.475 | AA56: 5.607 | CO56: SW_PS (professional services revenue y/y) | CP56: 0.03 | CQ56: Δ → | CR56: -0.03 | CS56: 9M FY26 −9%; FY25 −5%; FY22–25 declining as implementations move to partners.
B57: Decision Management Software (FY2016–Q3/21) — revenue | AB57: 23.994 | AC57: 107.655 | AD57: 25.453 | AE57: 28.608 | AF57: 27.69 | AG57: 30.897 | AH57: 112.648 | AI57: 23.997 | AJ57: 23.249 | AK57: 25.782 | AL57: 31.228 | AM57: 104.256 | AN57: 28.914 | AO57: 32.016 | AP57: 33.466 | AQ57: 39.476 | AR57: 133.872 | AS57: 31.188 | AT57: 38.544 | AU57: 40.721 | AV57: 53.516 | AW57: 163.969 | AX57: 32.402 | AY57: 33.128 | AZ57: 32.769 | CO57: 2027E | CP57: =CQ57+$CP$56 -> -0.02 | CQ57: -0.05 | CR57: =CQ57+$CR$56 -> -0.08
B58: Decision Management Software (FY2016–Q3/21) — segment operating income | AB58: -4.431 | AC58: -3.66 | AD58: -3.632 | AE58: -2.544 | AF58: -3.622 | AG58: -1.02 | AH58: -10.818 | AI58: -7.856 | AJ58: -8.664 | AK58: -9.369 | AL58: -4.758 | AM58: -30.647 | AN58: -10.648 | AO58: -8.368 | AP58: -8.763 | AQ58: -7.337 | AR58: -35.116 | AS58: -19.457 | AT58: -8.81 | AU58: -3.118 | AV58: 7.91 | AW58: -23.475 | AX58: -14.818 | AY58: -10.172 | AZ58: -15.243 | CO58: 2028E | CP58: =CQ58+$CP$56 -> 0 | CQ58: -0.03 | CR58: =CQ58+$CR$56 -> -0.06
B59: Check: legacy software segments vs Software revenue (should be 0) | C59: =IF(OR(ISNUMBER(C49),ISNUMBER(C51),ISNUMBER(C53),ISNUMBER(C55),ISNUMBER(C57)),IF(ABS(N(C49)+N(C51)+N(C53)+N(C55)+N(C57)-C42)<=0.15,0,ROUND(N(C49)+N(C51)+N(C53)+N(C55)+N(C57)-C42,1)),"") -> 0 | D59: =IF(OR(ISNUMBER(D49),ISNUMBER(D51),ISNUMBER(D53),ISNUMBER(D55),ISNUMBER(D57)),IF(ABS(N(D49)+N(D51)+N(D53)+N(D55)+N(D57)-D42)<=0.15,0,ROUND(N(D49)+N(D51)+N(D53)+N(D55)+N(D57)-D42,1)),"") -> 0 | E59: =IF(OR(ISNUMBER(E49),ISNUMBER(E51),ISNUMBER(E53),ISNUMBER(E55),ISNUMBER(E57)),IF(ABS(N(E49)+N(E51)+N(E53)+N(E55)+N(E57)-E42)<=0.15,0,ROUND(N(E49)+N(E51)+N(E53)+N(E55)+N(E57)-E42,1)),"") -> 0 | F59: =IF(OR(ISNUMBER(F49),ISNUMBER(F51),ISNUMBER(F53),ISNUMBER(F55),ISNUMBER(F57)),IF(ABS(N(F49)+N(F51)+N(F53)+N(F55)+N(F57)-F42)<=0.15,0,ROUND(N(F49)+N(F51)+N(F53)+N(F55)+N(F57)-F42,1)),"") -> 0 | G59: =IF(OR(ISNUMBER(G49),ISNUMBER(G51),ISNUMBER(G53),ISNUMBER(G55),ISNUMBER(G57)),IF(ABS(N(G49)+N(G51)+N(G53)+N(G55)+N(G57)-G42)<=0.15,0,ROUND(N(G49)+N(G51)+N(G53)+N(G55)+N(G57)-G42,1)),"") -> 0 | H59: =IF(OR(ISNUMBER(H49),ISNUMBER(H51),ISNUMBER(H53),ISNUMBER(H55),ISNUMBER(H57)),IF(ABS(N(H49)+N(H51)+N(H53)+N(H55)+N(H57)-H42)<=0.15,0,ROUND(N(H49)+N(H51)+N(H53)+N(H55)+N(H57)-H42,1)),"") -> 0 | I59: =IF(OR(ISNUMBER(I49),ISNUMBER(I51),ISNUMBER(I53),ISNUMBER(I55),ISNUMBER(I57)),IF(ABS(N(I49)+N(I51)+N(I53)+N(I55)+N(I57)-I42)<=0.15,0,ROUND(N(I49)+N(I51)+N(I53)+N(I55)+N(I57)-I42,1)),"") -> 0 | J59: =IF(OR(ISNUMBER(J49),ISNUMBER(J51),ISNUMBER(J53),ISNUMBER(J55),ISNUMBER(J57)),IF(ABS(N(J49)+N(J51)+N(J53)+N(J55)+N(J57)-J42)<=0.15,0,ROUND(N(J49)+N(J51)+N(J53)+N(J55)+N(J57)-J42,1)),"") -> 0 | ... BY59: =IF(OR(ISNUMBER(BY49),ISNUMBER(BY51),ISNUMBER(BY53),ISNUMBER(BY55),ISNUMBER(BY57)),IF(ABS(N(BY49)+N(BY51)+N(BY53)+N(BY55)+N(BY57)-BY42)<=0.15,0,ROUND(N(BY49)+N(BY51)+N(BY53)+N(BY55)+N(BY57)-BY42,1)),"") | CO59: 2029E | CP59: =CQ59+$CP$56 -> 0.03 | CQ59: 0 | CR59: =CQ59+$CR$56 -> -0.03
CO60: 2030E | CP60: =CQ60+$CP$56 -> 0.03 | CQ60: 0 | CR60: =CQ60+$CR$56 -> -0.03
B61: Unallocated corporate expenses (corporate functions; allocated to the segments in FY2006–09) | CG61: CORPORATE — unallocated corporate expenses (negative = cost); share-based compensation, amortization and restructuring are not allocated (adjusting items below) | CO61: 2031E | CP61: =CQ61+$CP$56 -> 0.03 | CQ61: 0 | CR61: =CQ61+$CR$56 -> -0.03
B62: Unallocated corporate expenses | C62: 0 | D62: 0 | E62: 0 | F62: 0 | G62: -69.166 | H62: -70.68 | I62: -71.705 | J62: -10.612 | K62: -21.445 | L62: -20.004 | M62: -18.905 | N62: -70.966 | O62: -21.757 | P62: -24.072 | Q62: -25.424 | R62: -30.298 | S62: -101.551 | T62: -21.619 | U62: -19.753 | V62: -20.773 | W62: -27.599 | X62: -89.744 | Y62: -24.062 | Z62: -21.882 | AA62: -29.24 | AB62: -35.428 | AC62: -110.612 | AD62: -24.633 | AE62: -25.223 | AF62: -26.724 | AG62: -28.418 | AH62: -104.998 | AI62: -26.76 | AJ62: -33.493 | AK62: -31.922 | AL62: -33.08 | AM62: -125.255 | AN62: -29.254 | AO62: -39.506 | AP62: -36.019 | AQ62: -39.976 | AR62: -144.755 | AS62: -34.21 | AT62: -33.785 | AU62: -31.315 | AV62: -45.394 | AW62: -144.704 | AX62: -30.253 | AY62: -33.392 | AZ62: -33.82 | BA62: -39.347 | BB62: -136.812 | BC62: -35.788 | BD62: -35.68 | BE62: -38.015 | BF62: -38.945 | BG62: -148.428 | BH62: -34.082 | BI62: -43.183 | BJ62: -42.347 | BK62: -36.814 | BL62: -156.426 | BM62: -40.568 | BN62: -45.806 | BO62: -50.368 | BP62: -50.156 | BQ62: -186.898 | BR62: -44.331 | BS62: -40.942 | BT62: -48.205 | BU62: -48.02 | BV62: -181.498 | BW62: -48.149 | BX62: -47.295 | BY62: -56.967 | BZ62: =BU62*(1+BZ63) -> -54.83133 | CA62: =SUM(BW62:BZ62) -> -207.24233 | CB62: =CB127*CB64 -> -209.9113 | CC62: =CC127*CC64 -> -231.61576 | CD62: =CD127*CD64 -> -253.48673 | CE62: =CE127*CE64 -> -275.7897 | CF62: =CF127*CF64 -> -298.2345 | CG62: MD&A segment operating-income summary. Q4/26E: prior-year quarter × (1 + 9M FY26 y/y). 2027E+: % of revenue (scenario-neutral input). | CO62: SC_M (Scores segment operating margin) | CP62: 0.01 | CQ62: Δ → | CR62: -0.04 | CS62: 9M FY26 90.2% (Q3 91%), FY25 87.8%, FY22 88.1%: very high incremental margins on price; held flat (Bear: price concessions).
B63: Unallocated corporate expenses y/y % | D63: =IF(AND(ISNUMBER(D62),ISNUMBER(C62)),IFERROR(D62/C62-1,""),"") | E63: =IF(AND(ISNUMBER(E62),ISNUMBER(D62)),IFERROR(E62/D62-1,""),"") | F63: =IF(AND(ISNUMBER(F62),ISNUMBER(E62)),IFERROR(F62/E62-1,""),"") | G63: =IF(AND(ISNUMBER(G62),ISNUMBER(F62)),IFERROR(G62/F62-1,""),"") | H63: =IF(AND(ISNUMBER(H62),ISNUMBER(G62)),IFERROR(H62/G62-1,""),"") -> 0.021889368 | I63: =IF(AND(ISNUMBER(I62),ISNUMBER(H62)),IFERROR(I62/H62-1,""),"") -> 0.014501981 | N63: =IF(AND(ISNUMBER(N62),ISNUMBER(I62)),IFERROR(N62/I62-1,""),"") -> -0.010306115 | O63: =IF(AND(ISNUMBER(O62),ISNUMBER(J62)),IFERROR(O62/J62-1,""),"") -> 1.0502262 | P63: =IF(AND(ISNUMBER(P62),ISNUMBER(K62)),IFERROR(P62/K62-1,""),"") -> 0.12249942 | Q63: =IF(AND(ISNUMBER(Q62),ISNUMBER(L62)),IFERROR(Q62/L62-1,""),"") -> 0.27094581 | R63: =IF(AND(ISNUMBER(R62),ISNUMBER(M62)),IFERROR(R62/M62-1,""),"") -> 0.6026448 | S63: =IF(AND(ISNUMBER(S62),ISNUMBER(N62)),IFERROR(S62/N62-1,""),"") -> 0.43098103 | T63: =IF(AND(ISNUMBER(T62),ISNUMBER(O62)),IFERROR(T62/O62-1,""),"") -> -0.0063427862 | U63: =IF(AND(ISNUMBER(U62),ISNUMBER(P62)),IFERROR(U62/P62-1,""),"") -> -0.17942007 | ... BY63: =IF(AND(ISNUMBER(BY62),ISNUMBER(BT62)),IFERROR(BY62/BT62-1,""),"") -> 0.18176538 | BZ63: =IFERROR(SUM(BW62:BY62)/SUM(BR62:BT62)-1,0) -> 0.1418436 | CA63: =IF(AND(ISNUMBER(CA62),ISNUMBER(BV62)),IFERROR(CA62/BV62-1,""),"") -> 0.1418436 | CB63: =IF(AND(ISNUMBER(CB62),ISNUMBER(CA62)),IFERROR(CB62/CA62-1,""),"") -> 0.012878492 | CC63: =IF(AND(ISNUMBER(CC62),ISNUMBER(CB62)),IFERROR(CC62/CB62-1,""),"") -> 0.10339826 | CD63: =IF(AND(ISNUMBER(CD62),ISNUMBER(CC62)),IFERROR(CD62/CC62-1,""),"") -> 0.094427809 | CE63: =IF(AND(ISNUMBER(CE62),ISNUMBER(CD62)),IFERROR(CE62/CD62-1,""),"") -> 0.087984782 | CF63: =IF(AND(ISNUMBER(CF62),ISNUMBER(CE62)),IFERROR(CF62/CE62-1,""),"") -> 0.081383746 | CO63: 2027E | CP63: =CQ63+$CP$62 -> 0.915 | CQ63: 0.905 | CR63: =CQ63+$CR$62 -> 0.865
B64: Unallocated corporate expenses % of revenue | C64: =IF(AND(ISNUMBER(C62),ISNUMBER(C127)),IFERROR(C62/C127,""),"") -> 0 | D64: =IF(AND(ISNUMBER(D62),ISNUMBER(D127)),IFERROR(D62/D127,""),"") -> 0 | E64: =IF(AND(ISNUMBER(E62),ISNUMBER(E127)),IFERROR(E62/E127,""),"") -> 0 | F64: =IF(AND(ISNUMBER(F62),ISNUMBER(F127)),IFERROR(F62/F127,""),"") -> 0 | G64: =IF(AND(ISNUMBER(G62),ISNUMBER(G127)),IFERROR(G62/G127,""),"") -> -0.11420259 | H64: =IF(AND(ISNUMBER(H62),ISNUMBER(H127)),IFERROR(H62/H127,""),"") -> -0.11405832 | I64: =IF(AND(ISNUMBER(I62),ISNUMBER(I127)),IFERROR(I62/I127,""),"") -> -0.10600615 | J64: =IF(AND(ISNUMBER(J62),ISNUMBER(J127)),IFERROR(J62/J127,""),"") -> -0.055846753 | ... CA64: =IF(AND(ISNUMBER(CA62),ISNUMBER(CA127)),IFERROR(CA62/CA127,""),"") -> -0.081913964 | CB64: -0.075 | CC64: -0.075 | CD64: -0.075 | CE64: -0.075 | CF64: -0.075 | CG64: Input −7.5% of revenue from FY2027 (9M FY26 −8.1%, FY25 −9.1%, FY24 −10.9%; operating leverage and the Oct-2026 workforce reduction — assumption). | CI64: =IFERROR(AVERAGE(CB64,CC64,CD64,CE64,CF64),"n/m") -> -0.075 | CJ64: =IFERROR(AVERAGE(BB64,BG64,BL64,BQ64,BV64),"n/m") -> -0.10300423 | CK64: =IFERROR(AVERAGE(AC64,AH64,AM64,AR64,AW64,BB64,BG64,BL64,BQ64,BV64),"n/m") -> -0.11110351 | CL64: =IFERROR(AVERAGE(C64,D64,E64,F64,G64,H64,I64,N64,S64,X64,AC64,AH64,AM64,AR64,AW64,BB64,BG64,BL64,BQ64,BV64),"n/m") -> -0.088823111 | CO64: 2028E | CP64: =CQ64+$CP$62 -> 0.915 | CQ64: 0.905 | CR64: =CQ64+$CR$62 -> 0.865
CO65: 2029E | CP65: =CQ65+$CP$62 -> 0.915 | CQ65: 0.905 | CR65: =CQ65+$CR$62 -> 0.865
B66: Revenue mix & growth contribution (outputs) | CG66: MIX — outputs | CO66: 2030E | CP66: =CQ66+$CP$62 -> 0.915 | CQ66: 0.905 | CR66: =CQ66+$CR$62 -> 0.865
B67: Contribution to total revenue growth — Scores (pp) | D67: =IFERROR((D17-C17)/C87,"") -> 0.0039885384 | E67: =IFERROR((E17-D17)/D87,"") -> -0.028736275 | F67: =IFERROR((F17-E17)/E87,"") -> -0.033825966 | G67: =IFERROR((G17-F17)/F87,"") -> 0.06455643 | H67: =IFERROR((H17-G17)/G87,"") -> -0.0062280915 | I67: =IFERROR((I17-H17)/H87,"") -> 0.011386467 | N67: =IFERROR((N17-I17)/I87,"") -> 0.0076727137 | O67: =IFERROR((O17-J17)/J87,"") -> 0.0196453 | P67: =IFERROR((P17-K17)/K87,"") -> 0.02116827 | Q67: =IFERROR((Q17-L17)/L87,"") -> -0.0099144592 | R67: =IFERROR((R17-M17)/M87,"") -> -0.00026795988 | S67: =IFERROR((S17-N17)/N87,"") -> 0.007607836 | T67: =IFERROR((T17-O17)/O87,"") -> -0.017570507 | U67: =IFERROR((U17-P17)/P87,"") -> 0.011209844 | ... CA67: =IFERROR((CA17-BV17)/BV87,"") -> 0.25685287 | CB67: =IFERROR((CB17-CA17)/CA87,"") -> 0.089622376 | CC67: =IFERROR((CC17-CB17)/CB87,"") -> 0.074926889 | CD67: =IFERROR((CD17-CC17)/CC87,"") -> 0.063708302 | CE67: =IFERROR((CE17-CD17)/CD87,"") -> 0.057012456 | CF67: =IFERROR((CF17-CE17)/CE87,"") -> 0.050900318 | CO67: 2031E | CP67: =CQ67+$CP$62 -> 0.915 | CQ67: 0.905 | CR67: =CQ67+$CR$62 -> 0.865
B68: Contribution to total revenue growth — Software (pp) | D68: =IFERROR((D38-C38)/C87,"") -> -0.0077795884 | E68: =IFERROR((E38-D38)/D87,"") -> -0.065389985 | F68: =IFERROR((F38-E38)/E87,"") -> -0.11937028 | G68: =IFERROR((G38-F38)/F87,"") -> -0.10433859 | H68: =IFERROR((H38-G38)/G87,"") -> 0.029410065 | I68: =IFERROR((I38-H38)/H87,"") -> 0.080176477 | N68: =IFERROR((N38-I38)/I87,"") -> 0.091408778 | O68: =IFERROR((O38-J38)/J87,"") -> -0.049521103 | P68: =IFERROR((P38-K38)/K87,"") -> 0.01305451 | Q68: =IFERROR((Q38-L38)/L87,"") -> 0.085214287 | R68: =IFERROR((R38-M38)/M87,"") -> 0.16442228 | S68: =IFERROR((S38-N38)/N87,"") -> 0.053648963 | T68: =IFERROR((T38-O38)/O87,"") -> 0.045816765 | U68: =IFERROR((U38-P38)/P87,"") -> 0.10550948 | ... CA68: =IFERROR((CA38-BV38)/BV87,"") -> 0.013948977 | CB68: =IFERROR((CB38-CA38)/CA87,"") -> 0.016629526 | CC68: =IFERROR((CC38-CB38)/CB87,"") -> 0.028471371 | CD68: =IFERROR((CD38-CC38)/CC87,"") -> 0.030719507 | CE68: =IFERROR((CE38-CD38)/CD87,"") -> 0.030972326 | CF68: =IFERROR((CF38-CE38)/CE87,"") -> 0.030483428 | CO68: SW_M (Software segment operating margin) | CP68: 0.03 | CQ68: Δ → | CR68: -0.04 | CS68: 9M FY26 27.6%, FY25 30.1%, FY23 32.6%; platform scale and the Oct-2026 15% workforce reduction (savings not quantified — assumption).
B69: Check: Scores + Software contributions vs total revenue growth (should be 0) | D69: =IF(AND(ISNUMBER(D67),ISNUMBER(D88)),IF(ABS(D67+D68+IFERROR(D77/C87,0)-D88)<0.0005,0,D67+D68-D88),"") -> 0 | E69: =IF(AND(ISNUMBER(E67),ISNUMBER(E88)),IF(ABS(E67+E68+IFERROR(E77/D87,0)-E88)<0.0005,0,E67+E68-E88),"") -> 0 | F69: =IF(AND(ISNUMBER(F67),ISNUMBER(F88)),IF(ABS(F67+F68+IFERROR(F77/E87,0)-F88)<0.0005,0,F67+F68-F88),"") -> 0 | G69: =IF(AND(ISNUMBER(G67),ISNUMBER(G88)),IF(ABS(G67+G68+IFERROR(G77/F87,0)-G88)<0.0005,0,G67+G68-G88),"") -> 0 | H69: =IF(AND(ISNUMBER(H67),ISNUMBER(H88)),IF(ABS(H67+H68+IFERROR(H77/G87,0)-H88)<0.0005,0,H67+H68-H88),"") -> 0 | I69: =IF(AND(ISNUMBER(I67),ISNUMBER(I88)),IF(ABS(I67+I68+IFERROR(I77/H87,0)-I88)<0.0005,0,I67+I68-I88),"") -> 0 | N69: =IF(AND(ISNUMBER(N67),ISNUMBER(N88)),IF(ABS(N67+N68+IFERROR(N77/I87,0)-N88)<0.0005,0,N67+N68-N88),"") -> 0 | O69: =IF(AND(ISNUMBER(O67),ISNUMBER(O88)),IF(ABS(O67+O68+IFERROR(O77/J87,0)-O88)<0.0005,0,O67+O68-O88),"") -> 0 | P69: =IF(AND(ISNUMBER(P67),ISNUMBER(P88)),IF(ABS(P67+P68+IFERROR(P77/K87,0)-P88)<0.0005,0,P67+P68-P88),"") -> 0 | Q69: =IF(AND(ISNUMBER(Q67),ISNUMBER(Q88)),IF(ABS(Q67+Q68+IFERROR(Q77/L87,0)-Q88)<0.0005,0,Q67+Q68-Q88),"") -> 0 | R69: =IF(AND(ISNUMBER(R67),ISNUMBER(R88)),IF(ABS(R67+R68+IFERROR(R77/M87,0)-R88)<0.0005,0,R67+R68-R88),"") -> 0 | S69: =IF(AND(ISNUMBER(S67),ISNUMBER(S88)),IF(ABS(S67+S68+IFERROR(S77/N87,0)-S88)<0.0005,0,S67+S68-S88),"") -> 0 | T69: =IF(AND(ISNUMBER(T67),ISNUMBER(T88)),IF(ABS(T67+T68+IFERROR(T77/O87,0)-T88)<0.0005,0,T67+T68-T88),"") -> 0 | U69: =IF(AND(ISNUMBER(U67),ISNUMBER(U88)),IF(ABS(U67+U68+IFERROR(U77/P87,0)-U88)<0.0005,0,U67+U68-U88),"") -> 0 | ... CA69: =IF(AND(ISNUMBER(CA67),ISNUMBER(CA88)),IF(ABS(CA67+CA68+IFERROR(CA77/BV87,0)-CA88)<0.0005,0,CA67+CA68-CA88),"") -> 0 | CB69: =IF(AND(ISNUMBER(CB67),ISNUMBER(CB88)),IF(ABS(CB67+CB68+IFERROR(CB77/CA87,0)-CB88)<0.0005,0,CB67+CB68-CB88),"") -> 0 | CC69: =IF(AND(ISNUMBER(CC67),ISNUMBER(CC88)),IF(ABS(CC67+CC68+IFERROR(CC77/CB87,0)-CC88)<0.0005,0,CC67+CC68-CC88),"") -> 0 | CD69: =IF(AND(ISNUMBER(CD67),ISNUMBER(CD88)),IF(ABS(CD67+CD68+IFERROR(CD77/CC87,0)-CD88)<0.0005,0,CD67+CD68-CD88),"") -> 0 | CE69: =IF(AND(ISNUMBER(CE67),ISNUMBER(CE88)),IF(ABS(CE67+CE68+IFERROR(CE77/CD87,0)-CE88)<0.0005,0,CE67+CE68-CE88),"") -> 0 | CF69: =IF(AND(ISNUMBER(CF67),ISNUMBER(CF88)),IF(ABS(CF67+CF68+IFERROR(CF77/CE87,0)-CF88)<0.0005,0,CF67+CF68-CF88),"") -> 0 | CO69: 2027E | CP69: =CQ69+$CP$68 -> 0.3 | CQ69: 0.27 | CR69: =CQ69+$CR$68 -> 0.23
CO70: 2028E | CP70: =CQ70+$CP$68 -> 0.32 | CQ70: 0.29 | CR70: =CQ70+$CR$68 -> 0.25
B71: Future acquisitions (M&A lever — software bolt-ons, unallocated; deals closed from 2027E) | CG71: M&A LEVER — acquired revenue = spend ÷ EV/sales; mid-year convention | CO71: 2029E | CP71: =CQ71+$CP$68 -> 0.34 | CQ71: 0.31 | CR71: =CQ71+$CR$68 -> 0.27
B72: Acquisition spend (USDm, scenario) | CA72: 0 | CB72: =MAX(0,CHOOSE(MATCH($CG$2,{"Bull","Base","Bear"},0),$CP$75,$CQ$75,$CR$75)) -> 0 | CC72: =MAX(0,CHOOSE(MATCH($CG$2,{"Bull","Base","Bear"},0),$CP$76,$CQ$76,$CR$76)) -> 0 | CD72: =MAX(0,CHOOSE(MATCH($CG$2,{"Bull","Base","Bear"},0),$CP$77,$CQ$77,$CR$77)) -> 0 | CE72: =MAX(0,CHOOSE(MATCH($CG$2,{"Bull","Base","Bear"},0),$CP$78,$CQ$78,$CR$78)) -> 0 | CF72: =MAX(0,CHOOSE(MATCH($CG$2,{"Bull","Base","Bear"},0),$CP$79,$CQ$79,$CR$79)) -> 0 | CG72: Scenario lever M&A_spend (Base $0). Funded from cash / revolver (debt schedule). | CO72: 2030E | CP72: =CQ72+$CP$68 -> 0.35 | CQ72: 0.32 | CR72: =CQ72+$CR$68 -> 0.28
B73: Purchase multiple — EV / sales (x) | CA73: 0 | CB73: 6 | CC73: 6 | CD73: 6 | CE73: 6 | CF73: 6 | CG73: Assumption (software bolt-ons ~5–8x revenue); FICO has spent little on acquisitions since FY2014. | CO73: 2031E | CP73: =CQ73+$CP$68 -> 0.36 | CQ73: 0.33 | CR73: =CQ73+$CR$68 -> 0.29
B74: Annualised revenue acquired in the year | CA74: 0 | CB74: =IFERROR(CB72/CB73,0) -> 0 | CC74: =IFERROR(CC72/CC73,0) -> 0 | CD74: =IFERROR(CD72/CD73,0) -> 0 | CE74: =IFERROR(CE72/CE73,0) -> 0 | CF74: =IFERROR(CF72/CF73,0) -> 0 | CO74: M&A_spend (software bolt-ons, $m) | CP74: 0 | CQ74: Δ → | CR74: 0 | CS74: FICO has made no material acquisition since FY2014 and returns capital through buybacks; Base $0 (lever available).
B75: Growth of acquired businesses after acquisition % | CA75: 0 | CB75: 0.08 | CC75: 0.08 | CD75: 0.08 | CE75: 0.08 | CF75: 0.08 | CO75: 2027E | CP75: =MAX(0,CQ75+$CP$74) -> 0 | CQ75: 0 | CR75: =MAX(0,CQ75+$CR$74) -> 0
B76: Run-rate revenue of businesses acquired (year end) | CA76: 0 | CB76: =CA76*(1+CB75)+CB74 -> 0 | CC76: =CB76*(1+CC75)+CC74 -> 0 | CD76: =CC76*(1+CD75)+CD74 -> 0 | CE76: =CD76*(1+CE75)+CE74 -> 0 | CF76: =CE76*(1+CF75)+CF74 -> 0 | CO76: 2028E | CP76: =MAX(0,CQ76+$CP$74) -> 0 | CQ76: 0 | CR76: =MAX(0,CQ76+$CR$74) -> 0
B77: Revenue from future acquisitions | CA77: 0 | CB77: =CA76*(1+CB75)+0.5*CB74 -> 0 | CC77: =CB76*(1+CC75)+0.5*CC74 -> 0 | CD77: =CC76*(1+CD75)+0.5*CD74 -> 0 | CE77: =CD76*(1+CE75)+0.5*CE74 -> 0 | CF77: =CE76*(1+CF75)+0.5*CF74 -> 0 | CG77: Mid-year convention. | CO77: 2029E | CP77: =MAX(0,CQ77+$CP$74) -> 0 | CQ77: 0 | CR77: =MAX(0,CQ77+$CR$74) -> 0
B78: Operating margin of acquired businesses (before amortization) % | CA78: 0 | CB78: 0.2 | CC78: 0.2 | CD78: 0.2 | CE78: 0.2 | CF78: 0.2 | CO78: 2030E | CP78: =MAX(0,CQ78+$CP$74) -> 0 | CQ78: 0 | CR78: =MAX(0,CQ78+$CR$74) -> 0
B79: Operating income from future acquisitions | CA79: 0 | CB79: =CB77*CB78 -> 0 | CC79: =CC77*CC78 -> 0 | CD79: =CD77*CD78 -> 0 | CE79: =CE77*CE78 -> 0 | CF79: =CF77*CF78 -> 0 | CO79: 2031E | CP79: =MAX(0,CQ79+$CP$74) -> 0 | CQ79: 0 | CR79: =MAX(0,CQ79+$CR$74) -> 0
B80: PP&E % of spend | CA80: 0 | CB80: 0.02 | CC80: 0.02 | CD80: 0.02 | CE80: 0.02 | CF80: 0.02
B81: Acquired intangibles % of spend | CA81: 0 | CB81: 0.3 | CC81: 0.3 | CD81: 0.3 | CE81: 0.3 | CF81: 0.3 | CG81: Assumption for software targets (technology and customer relationships).
B82: Intangible amortization life (years) | CA82: 0 | CB82: 8 | CC82: 8 | CD82: 8 | CE82: 8 | CF82: 8
B83: Cumulative acquired intangibles (gross) | CA83: 0 | CB83: =CA83+CB72*CB81 -> 0 | CC83: =CB83+CC72*CC81 -> 0 | CD83: =CC83+CD72*CD81 -> 0 | CE83: =CD83+CE72*CE81 -> 0 | CF83: =CE83+CF72*CF81 -> 0
B84: Amortization of future-acquisition intangibles (adjusted out of non-GAAP) | CA84: 0 | CB84: =IFERROR((CA83+0.5*CB72*CB81)/CB82,0) -> 0 | CC84: =IFERROR((CB83+0.5*CC72*CC81)/CC82,0) -> 0 | CD84: =IFERROR((CC83+0.5*CD72*CD81)/CD82,0) -> 0 | CE84: =IFERROR((CD83+0.5*CE72*CE81)/CE82,0) -> 0 | CF84: =IFERROR((CE83+0.5*CF72*CF81)/CF82,0) -> 0 | CG84: FICO excludes amortization of acquired intangibles from its non-GAAP measures.
B86: Group Total — revenue & non-GAAP operating income (segment build) → FY26 guidance calibration | CG86: GROUP TOTAL (CONSOLIDATED) — modelling logic
B87: Revenue (segment build) | C87: =IF(ISNUMBER(C17),C17+C38,C127) -> 825.365 | D87: =IF(ISNUMBER(D17),D17+D38,D127) -> 822.236 | E87: =IF(ISNUMBER(E17),E17+E38,E127) -> 744.842 | F87: =IF(ISNUMBER(F17),F17+F38,F127) -> 630.735 | G87: =IF(ISNUMBER(G17),G17+G38,G127) -> 605.643 | H87: =IF(ISNUMBER(H17),H17+H38,H127) -> 619.683 | I87: =IF(ISNUMBER(I17),I17+I38,I127) -> 676.423 | J87: =IF(ISNUMBER(J17),J17+J38,J127) -> 190.02 | ... BY87: =IF(ISNUMBER(BY17),BY17+BY38,BY127) -> 674.188 | BZ87: =BZ17+BZ38+N(BZ77) -> 652.176 | CA87: =CA17+CA38+N(CA77) -> 2530 | CB87: =CB17+CB38+N(CB77) -> 2798.8173 | CC87: =CC17+CC38+N(CC77) -> 3088.2102 | CD87: =CD17+CD38+N(CD77) -> 3379.8231 | CE87: =CE17+CE38+N(CE77) -> 3677.1961 | CF87: =CF17+CF38+N(CF77) -> 3976.4601 | CG87: Σ segment revenue (+ future acquisitions from 2027E). | CI87: =IFERROR((CF87/CA87)^(1/5)-1,"n/m") -> 0.094649847 | CJ87: =IFERROR((BV87/AW87)^(1/5)-1,"n/m") -> 0.089893258 | CK87: =IFERROR((BV87/X87)^(1/10)-1,"n/m") -> 0.090283426 | CL87: =IFERROR((BV87/C87)^(1/19)-1,"n/m") -> 0.047432726
B88: Revenue y/y % | D88: =IF(AND(ISNUMBER(D87),ISNUMBER(C87)),IFERROR(D87/C87-1,""),"") -> -0.00379105 | E88: =IF(AND(ISNUMBER(E87),ISNUMBER(D87)),IFERROR(E87/D87-1,""),"") -> -0.094126261 | F88: =IF(AND(ISNUMBER(F87),ISNUMBER(E87)),IFERROR(F87/E87-1,""),"") -> -0.15319625 | G88: =IF(AND(ISNUMBER(G87),ISNUMBER(F87)),IFERROR(G87/F87-1,""),"") -> -0.039782159 | H88: =IF(AND(ISNUMBER(H87),ISNUMBER(G87)),IFERROR(H87/G87-1,""),"") -> 0.023181974 | I88: =IF(AND(ISNUMBER(I87),ISNUMBER(H87)),IFERROR(I87/H87-1,""),"") -> 0.091562944 | N88: =IF(AND(ISNUMBER(N87),ISNUMBER(I87)),IFERROR(N87/I87-1,""),"") -> 0.099081492 | O88: =IF(AND(ISNUMBER(O87),ISNUMBER(J87)),IFERROR(O87/J87-1,""),"") -> -0.029875803 | P88: =IF(AND(ISNUMBER(P87),ISNUMBER(K87)),IFERROR(P87/K87-1,""),"") -> 0.03422278 | Q88: =IF(AND(ISNUMBER(Q87),ISNUMBER(L87)),IFERROR(Q87/L87-1,""),"") -> 0.075299828 | R88: =IF(AND(ISNUMBER(R87),ISNUMBER(M87)),IFERROR(R87/M87-1,""),"") -> 0.16415432 | S88: =IF(AND(ISNUMBER(S87),ISNUMBER(N87)),IFERROR(S87/N87-1,""),"") -> 0.061256799 | T88: =IF(AND(ISNUMBER(T87),ISNUMBER(O87)),IFERROR(T87/O87-1,""),"") -> 0.028246258 | U88: =IF(AND(ISNUMBER(U87),ISNUMBER(P87)),IFERROR(U87/P87-1,""),"") -> 0.11671933 | ... CA88: =IF(AND(ISNUMBER(CA87),ISNUMBER(BV87)),IFERROR(CA87/BV87-1,""),"") -> 0.27080185 | CB88: =IF(AND(ISNUMBER(CB87),ISNUMBER(CA87)),IFERROR(CB87/CA87-1,""),"") -> 0.1062519 | CC88: =IF(AND(ISNUMBER(CC87),ISNUMBER(CB87)),IFERROR(CC87/CB87-1,""),"") -> 0.10339826 | CD88: =IF(AND(ISNUMBER(CD87),ISNUMBER(CC87)),IFERROR(CD87/CC87-1,""),"") -> 0.094427809 | CE88: =IF(AND(ISNUMBER(CE87),ISNUMBER(CD87)),IFERROR(CE87/CD87-1,""),"") -> 0.087984782 | CF88: =IF(AND(ISNUMBER(CF87),ISNUMBER(CE87)),IFERROR(CF87/CE87-1,""),"") -> 0.081383746
B89: Check: segment build vs consolidated revenue (should be 0) | C89: =IF(AND(ISNUMBER(C87),ISNUMBER(C127)),IF(ABS(C87-C127)<=0.15,0,ROUND(C87-C127,1)),"") -> 0 | D89: =IF(AND(ISNUMBER(D87),ISNUMBER(D127)),IF(ABS(D87-D127)<=0.15,0,ROUND(D87-D127,1)),"") -> 0 | E89: =IF(AND(ISNUMBER(E87),ISNUMBER(E127)),IF(ABS(E87-E127)<=0.15,0,ROUND(E87-E127,1)),"") -> 0 | F89: =IF(AND(ISNUMBER(F87),ISNUMBER(F127)),IF(ABS(F87-F127)<=0.15,0,ROUND(F87-F127,1)),"") -> 0 | G89: =IF(AND(ISNUMBER(G87),ISNUMBER(G127)),IF(ABS(G87-G127)<=0.15,0,ROUND(G87-G127,1)),"") -> 0 | H89: =IF(AND(ISNUMBER(H87),ISNUMBER(H127)),IF(ABS(H87-H127)<=0.15,0,ROUND(H87-H127,1)),"") -> 0 | I89: =IF(AND(ISNUMBER(I87),ISNUMBER(I127)),IF(ABS(I87-I127)<=0.15,0,ROUND(I87-I127,1)),"") -> 0 | J89: =IF(AND(ISNUMBER(J87),ISNUMBER(J127)),IF(ABS(J87-J127)<=0.15,0,ROUND(J87-J127,1)),"") -> 0 | ... CF89: =IF(AND(ISNUMBER(CF87),ISNUMBER(CF127)),IF(ABS(CF87-CF127)<=0.15,0,ROUND(CF87-CF127,1)),"") -> 0
B90: Non-GAAP operating income (segment build: segment operating income + unallocated corporate) | C90: =IF(ISNUMBER(C23),C23+C44+C62+N(C79),"") -> 214.47 | D90: =IF(ISNUMBER(D23),D23+D44+D62+N(D79),"") -> 185.649 | E90: =IF(ISNUMBER(E23),E23+E44+E62+N(E79),"") -> 160.173 | F90: =IF(ISNUMBER(F23),F23+F44+F62+N(F79),"") -> 148.386 | G90: =IF(ISNUMBER(G23),G23+G44+G62+N(G79),"") -> 143.172 | H90: =IF(ISNUMBER(H23),H23+H44+H62+N(H79),"") -> 162.969 | I90: =IF(ISNUMBER(I23),I23+I44+I62+N(I79),"") -> 201.656 | J90: =IF(ISNUMBER(J23),J23+J44+J62+N(J79),"") -> 55.487 | ... CF90: =IF(ISNUMBER(CF23),CF23+CF44+CF62+N(CF79),"") -> 2562.4687 | CG90: Σ segment operating income + unallocated corporate expenses (+ future acquisitions). Model measure: FICO publishes no non-GAAP operating income; = GAAP operating income + its non-GAAP adjusting items. Drives the GAAP P&L below. | CI90: =IFERROR((CF90/CA90)^(1/5)-1,"n/m") -> 0.11061312 | CJ90: =IFERROR((BV90/AW90)^(1/5)-1,"n/m") -> 0.19964757 | CK90: =IFERROR((BV90/X90)^(1/10)-1,"n/m") -> 0.17665963 | CL90: =IFERROR((BV90/C90)^(1/19)-1,"n/m") -> 0.089462131
B91: Non-GAAP operating margin % | C91: =IF(AND(ISNUMBER(C90),ISNUMBER(C127)),IFERROR(C90/C127,""),"") -> 0.25984867 | D91: =IF(AND(ISNUMBER(D90),ISNUMBER(D127)),IFERROR(D90/D127,""),"") -> 0.22578554 | E91: =IF(AND(ISNUMBER(E90),ISNUMBER(E127)),IFERROR(E90/E127,""),"") -> 0.21504292 | F91: =IF(AND(ISNUMBER(F90),ISNUMBER(F127)),IFERROR(F90/F127,""),"") -> 0.23525886 | G91: =IF(AND(ISNUMBER(G90),ISNUMBER(G127)),IFERROR(G90/G127,""),"") -> 0.23639669 | H91: =IF(AND(ISNUMBER(H90),ISNUMBER(H127)),IFERROR(H90/H127,""),"") -> 0.26298769 | I91: =IF(AND(ISNUMBER(I90),ISNUMBER(I127)),IFERROR(I90/I127,""),"") -> 0.29812115 | J91: =IF(AND(ISNUMBER(J90),ISNUMBER(J127)),IFERROR(J90/J127,""),"") -> 0.2920061 | ... CF91: =IF(AND(ISNUMBER(CF90),ISNUMBER(CF127)),IFERROR(CF90/CF127,""),"") -> 0.64440953 | CI91: =IFERROR(AVERAGE(CB91,CC91,CD91,CE91,CF91),"n/m") -> 0.63886585 | CJ91: =IFERROR(AVERAGE(BB91,BG91,BL91,BQ91,BV91),"n/m") -> 0.49006118 | CK91: =IFERROR(AVERAGE(AC91,AH91,AM91,AR91,AW91,BB91,BG91,BL91,BQ91,BV91),"n/m") -> 0.39095599 | CL91: =IFERROR(AVERAGE(C91,D91,E91,F91,G91,H91,I91,N91,S91,X91,AC91,AH91,AM91,AR91,AW91,BB91,BG91,BL91,BQ91,BV91),"n/m") -> 0.32229006
B92: Non-GAAP operating income y/y % | D92: =IF(AND(ISNUMBER(D90),ISNUMBER(C90)),IFERROR(D90/C90-1,""),"") -> -0.13438243 | E92: =IF(AND(ISNUMBER(E90),ISNUMBER(D90)),IFERROR(E90/D90-1,""),"") -> -0.1372267 | F92: =IF(AND(ISNUMBER(F90),ISNUMBER(E90)),IFERROR(F90/E90-1,""),"") -> -0.073589182 | G92: =IF(AND(ISNUMBER(G90),ISNUMBER(F90)),IFERROR(G90/F90-1,""),"") -> -0.035138086 | H92: =IF(AND(ISNUMBER(H90),ISNUMBER(G90)),IFERROR(H90/G90-1,""),"") -> 0.13827424 | I92: =IF(AND(ISNUMBER(I90),ISNUMBER(H90)),IFERROR(I90/H90-1,""),"") -> 0.23738871 | N92: =IF(AND(ISNUMBER(N90),ISNUMBER(I90)),IFERROR(N90/I90-1,""),"") -> 0.013924703 | O92: =IF(AND(ISNUMBER(O90),ISNUMBER(J90)),IFERROR(O90/J90-1,""),"") -> -0.11370231 | P92: =IF(AND(ISNUMBER(P90),ISNUMBER(K90)),IFERROR(P90/K90-1,""),"") -> 0.17289406 | Q92: =IF(AND(ISNUMBER(Q90),ISNUMBER(L90)),IFERROR(Q90/L90-1,""),"") -> 0.085035358 | R92: =IF(AND(ISNUMBER(R90),ISNUMBER(M90)),IFERROR(R90/M90-1,""),"") -> 0.081833278 | S92: =IF(AND(ISNUMBER(S90),ISNUMBER(N90)),IFERROR(S90/N90-1,""),"") -> 0.048732295 | T92: =IF(AND(ISNUMBER(T90),ISNUMBER(O90)),IFERROR(T90/O90-1,""),"") -> -0.25564277 | U92: =IF(AND(ISNUMBER(U90),ISNUMBER(P90)),IFERROR(U90/P90-1,""),"") -> -0.019330914 | ... CA92: =IF(AND(ISNUMBER(CA90),ISNUMBER(BV90)),IFERROR(CA90/BV90-1,""),"") -> 0.38818514 | CB92: =IF(AND(ISNUMBER(CB90),ISNUMBER(CA90)),IFERROR(CB90/CA90-1,""),"") -> 0.15826074 | CC92: =IF(AND(ISNUMBER(CC90),ISNUMBER(CB90)),IFERROR(CC90/CB90-1,""),"") -> 0.11900397 | CD92: =IF(AND(ISNUMBER(CD90),ISNUMBER(CC90)),IFERROR(CD90/CC90-1,""),"") -> 0.10431141 | CE92: =IF(AND(ISNUMBER(CE90),ISNUMBER(CD90)),IFERROR(CE90/CD90-1,""),"") -> 0.090413112 | CF92: =IF(AND(ISNUMBER(CF90),ISNUMBER(CE90)),IFERROR(CF90/CE90-1,""),"") -> 0.082663269
B93: Check: segment build vs non-GAAP operating income bridge (should be 0) | C93: =IF(AND(ISNUMBER(C90),ISNUMBER(C167)),IF(ABS(C90-C167)<=0.15,0,ROUND(C90-C167,1)),"") -> 0 | D93: =IF(AND(ISNUMBER(D90),ISNUMBER(D167)),IF(ABS(D90-D167)<=0.15,0,ROUND(D90-D167,1)),"") -> 0 | E93: =IF(AND(ISNUMBER(E90),ISNUMBER(E167)),IF(ABS(E90-E167)<=0.15,0,ROUND(E90-E167,1)),"") -> 0 | F93: =IF(AND(ISNUMBER(F90),ISNUMBER(F167)),IF(ABS(F90-F167)<=0.15,0,ROUND(F90-F167,1)),"") -> 0 | G93: =IF(AND(ISNUMBER(G90),ISNUMBER(G167)),IF(ABS(G90-G167)<=0.15,0,ROUND(G90-G167,1)),"") -> 0 | H93: =IF(AND(ISNUMBER(H90),ISNUMBER(H167)),IF(ABS(H90-H167)<=0.15,0,ROUND(H90-H167,1)),"") -> 0 | I93: =IF(AND(ISNUMBER(I90),ISNUMBER(I167)),IF(ABS(I90-I167)<=0.15,0,ROUND(I90-I167,1)),"") -> 0 | J93: =IF(AND(ISNUMBER(J90),ISNUMBER(J167)),IF(ABS(J90-J167)<=0.15,0,ROUND(J90-J167,1)),"") -> 0 | ... CF93: =IF(AND(ISNUMBER(CF90),ISNUMBER(CF167)),IF(ABS(CF90-CF167)<=0.15,0,ROUND(CF90-CF167,1)),"") -> 0
B94: Memo: FY26 revenue guidance (scenario end-point) | CA94: =CHOOSE(MATCH($CG$2,{"Bull","Base","Bear"},0),$CP$12,$CQ$12,$CR$12) -> 2530 | CG94: Company FY26 revenue guidance $2.53bn (raised 29-Jul-2026 from $2.45bn; $2.35bn initial, 5-Nov-2025). Drives the revenue calibration.
B95: Revenue before calibration (Q4/26E helper) | BZ95: =BU11*(1+BZ13)+BU14*(1+BZ16)+BU29*(1+BZ31)+BU32*(1+BZ34)+BU35*(1+BZ37) -> 669.07159
B96: Revenue sensitivity to +1.00 of growth (Q4/26E helper) | BZ96: =BU11+BU14+BU29+BU32+BU35 -> 515.751
B97: Guidance calibration: Δ y/y growth applied to all revenue streams (Q4/26E) | BZ97: =(CA94-SUM(BW87:BY87)-BZ95)/BZ96 -> -0.032759206 | CG97: Solves the uniform growth shift (vs 9M FY26 y/y rates) so that FY26 revenue = the guidance end-point for the active scenario.
B98: Check: FY26 revenue vs guidance end-point (should be 0) | CA98: =ROUND(CA87-CA94,1) -> 0
B99: Memo: FY26 non-GAAP EPS guidance (scenario end-point, $) | CA99: =CHOOSE(MATCH($CG$2,{"Bull","Base","Bear"},0),$CP$13,$CQ$13,$CR$13) -> 42.43 | CG99: Company FY26 non-GAAP EPS guidance $42.43 (raised 29-Jul-2026 from $40.45; $38.17 initial). Drives the segment-margin calibration.
B100: Non-GAAP net income required (FY26E diluted shares × EPS guidance) | CA100: =CA99*CA204 -> 972.85941
B101: Q4/26E non-GAAP operating income required ((NI − 9M actual) ÷ (1 − Q4 non-GAAP tax rate) + Q4 net interest − other income) | CA101: =(CA100-SUM(BW201:BY201))/(1-$CQ$26)+BZ139-BZ140-BZ196 -> 375.45558
...

Sheet Bull-Base-Bear
B2: Fair Isaac Corporation (FICO) — Bull / Base / Bear Case P&L Summary | J2: Share price ($): | K2: =Model!$CB$389 -> 740
B3: Non-GAAP figures (company definition: non-GAAP net income / EPS; model non-GAAP operating income and adjusted EBITDA) · USD millions · fiscal years ended 30 September · Live panel linked to Model — toggle scenario via Model!CG2. Bull and Bear panels are value snapshots generated from the Model with the switch set to each case. FY2026E = Q1–Q3 actual + Q4 calibrated to the FY26 guidance (revenue $2.53bn, non-GAAP EPS $42.43). | J3: As of: | K3: =TODAY() -> 2026-10-13 00:00:00
B5: Scenario: | C5: =Model!$CG$2 -> Base | N5: Scenario: | O5: Bull | P5: Snapshot (values) — Model run with switch = Bull | Z5: Scenario: | AA5: Bear | AB5: Snapshot (values) — Model run with switch = Bear
B7: (USDm, except EPS and shares) | C7: 2026E | D7: 2027E | E7: 2028E | F7: 2029E | G7: 2030E | H7: 2031E | I7: 26-'31 CAGR | J7: LT Hist Avg | K7: LT Hist Min | L7: LT Hist Max | N7: (USDm, except EPS and shares) | O7: 2026E | P7: 2027E | Q7: 2028E | R7: 2029E | S7: 2030E | T7: 2031E | U7: 26-'31 CAGR | V7: LT Hist Avg | W7: LT Hist Min | X7: LT Hist Max | Z7: (USDm, except EPS and shares) | AA7: 2026E | AB7: 2027E | AC7: 2028E | AD7: 2029E | AE7: 2030E | AF7: 2031E | AG7: 26-'31 CAGR | AH7: LT Hist Avg | AI7: LT Hist Min | AJ7: LT Hist Max
B9: Revenue | C9: =Model!CA127 -> 2530 | D9: =Model!CB127 -> 2798.8173 | E9: =Model!CC127 -> 3088.2102 | F9: =Model!CD127 -> 3379.8231 | G9: =Model!CE127 -> 3677.1961 | H9: =Model!CF127 -> 3976.4601 | I9: =IFERROR((H9/C9)^(1/5)-1,"n/m") -> 0.094649847 | N9: Revenue | O9: 2530 | P9: 2927.76 | Q9: 3383.6575 | R9: 3884.8633 | S9: 4440.2924 | T9: 5050.9055 | U9: 0.14828514 | Z9: Revenue | AA9: 2530 | AB9: 2549.3396 | AC9: 2550.6625 | AD9: 2523.3934 | AE9: 2476.3925 | AF9: 2411.7105 | AG9: -0.0095309037
B10: Revenue y/y % | D10: =IFERROR(D9/C9-1,"") -> 0.1062519 | E10: =IFERROR(E9/D9-1,"") -> 0.10339826 | F10: =IFERROR(F9/E9-1,"") -> 0.094427809 | G10: =IFERROR(G9/F9-1,"") -> 0.087984782 | H10: =IFERROR(H9/G9-1,"") -> 0.081383746 | N10: Revenue y/y % | P10: 0.1572174 | Q10: 0.15571545 | R10: 0.14812545 | S10: 0.14297262 | T10: 0.13751643 | Z10: Revenue y/y % | AB10: 0.0076441273 | AC10: 0.00051892092 | AD10: -0.010691 | AE10: -0.018626081 | AF10: -0.02611945
B11: Scores segment revenue y/y % | C11: =Model!CA216 -> 0.43759315 | D11: =Model!CB216 -> 0.13497222 | E11: =Model!CC216 -> 0.10998525 | F11: =Model!CD216 -> 0.092962513 | G11: =Model!CE216 -> 0.083303533 | H11: =Model!CF216 -> 0.074694192 | N11: Scores segment revenue y/y % | O11: 0.43759315 | P11: 0.18087373 | Q11: 0.15651046 | R11: 0.13988413 | S11: 0.13059306 | T11: 0.12223433 | Z11: Scores segment revenue y/y % | AA11: 0.43759315 | AB11: 0.025901515 | AC11: 0 | AD11: -0.017336661 | AE11: -0.027289673 | AF11: -0.035862246
B12: Adjusted EBITDA (model) | C12: =Model!CA183 -> 1545.8696 | D12: =Model!CB183 -> 1790.9017 | E12: =Model!CC183 -> 2002.2487 | F12: =Model!CD183 -> 2209.6101 | G12: =Model!CE183 -> 2408.2373 | H12: =Model!CF183 -> 2606.2804 | I12: =IFERROR((H12/C12)^(1/5)-1,"n/m") -> 0.11011931 | N12: Adjusted EBITDA (model) | O12: 1543.9455 | P12: 1914.1999 | Q12: 2233.1594 | R12: 2576.3126 | S12: 2939.1589 | T12: 3333.4893 | U12: 0.16641587 | Z12: Adjusted EBITDA (model) | AA12: 1547.7937 | AB12: 1521.932 | AC12: 1538.6919 | AD12: 1531.9227 | AE12: 1503.1728 | AF12: 1463.0694 | AG12: -0.011195641
B13: Adjusted EBITDA margin % | C13: =IFERROR(C12/C9,"") -> 0.61101565 | D13: =IFERROR(D12/D9,"") -> 0.63987804 | E13: =IFERROR(E12/E9,"") -> 0.64835247 | F13: =IFERROR(F12/F9,"") -> 0.65376503 | G13: =IFERROR(G12/G9,"") -> 0.6549113 | H13: =IFERROR(H12/H9,"") -> 0.65542729 | J13: =IFERROR(AVERAGE(Model!C184,Model!D184,Model!E184,Model!F184,Model!G184,Model!H184,Model!I184,Model!N184,Model!S184,Model!X184,Model!AC184,Model!AH184,Model!AM184,Model!AR184,Model!AW184,Model!BB184,Model!BG184,Model!BL184,Model!BQ184,Model!BV184),"") -> 0.35212441 | K13: =IFERROR(MIN(Model!C184,Model!D184,Model!E184,Model!F184,Model!G184,Model!H184,Model!I184,Model!N184,Model!S184,Model!X184,Model!AC184,Model!AH184,Model!AM184,Model!AR184,Model!AW184,Model!BB184,Model!BG184,Model!BL184,Model!BQ184,Model!BV184),"") -> 0.27108031 | L13: =IFERROR(MAX(Model!C184,Model!D184,Model!E184,Model!F184,Model!G184,Model!H184,Model!I184,Model!N184,Model!S184,Model!X184,Model!AC184,Model!AH184,Model!AM184,Model!AR184,Model!AW184,Model!BB184,Model!BG184,Model!BL184,Model!BQ184,Model!BV184),"") -> 0.56195712 | N13: Adjusted EBITDA margin % | O13: 0.61025514 | P13: 0.65381039 | Q13: 0.65998388 | R13: 0.66316685 | S13: 0.66192914 | T13: 0.65997854 | V13: 0.35212441 | W13: 0.27108031 | X13: 0.56195712 | Z13: Adjusted EBITDA margin % | AA13: 0.61177615 | AB13: 0.59699069 | AC13: 0.60325187 | AD13: 0.60708833 | AE13: 0.60700104 | AF13: 0.60665218 | AH13: 0.35212441 | AI13: 0.27108031 | AJ13: 0.56195712
B15: Operating income (GAAP) | C15: =Model!CA135 -> 1301.4976 | D15: =Model!CB135 -> 1549.9963 | E15: =Model!CC135 -> 1743.1919 | F15: =Model!CD135 -> 1927.2243 | G15: =Model!CE135 -> 2102.0616 | H15: =Model!CF135 -> 2276.1636 | I15: =IFERROR((H15/C15)^(1/5)-1,"n/m") -> 0.11828377 | N15: Operating income (GAAP) | O15: 1299.5735 | P15: 1662.9791 | Q15: 1950.4668 | R15: 2253.5235 | S15: 2571.9355 | T15: 2917.4168 | U15: 0.17554573 | Z15: Operating income (GAAP) | AA15: 1303.4217 | AB15: 1300.9849 | AC15: 1322.6389 | AD15: 1318.0512 | AE15: 1293.0614 | AF15: 1258.1326 | AG15: -0.0070479119
B16: Operating income y/y % | D16: =IFERROR(D15/C15-1,"") -> 0.19093294 | E16: =IFERROR(E15/D15-1,"") -> 0.12464257 | F16: =IFERROR(F15/E15-1,"") -> 0.1055721 | G16: =IFERROR(G15/F15-1,"") -> 0.090719733 | H16: =IFERROR(H15/G15-1,"") -> 0.082824427 | N16: Operating income y/y % | P16: 0.27963453 | Q16: 0.17287511 | R16: 0.15537649 | S16: 0.14129518 | T16: 0.13432737 | Z16: Operating income y/y % | AB16: -0.0018695557 | AC16: 0.01664438 | AD16: -0.0034686163 | AE16: -0.01895966 | AF16: -0.027012514
B17: Operating margin (GAAP) % | C17: =IFERROR(C15/C9,"") -> 0.51442592 | D17: =IFERROR(D15/D9,"") -> 0.55380404 | E17: =IFERROR(E15/E9,"") -> 0.56446673 | F17: =IFERROR(F15/F9,"") -> 0.57021455 | G17: =IFERROR(G15/G9,"") -> 0.57164794 | H17: =IFERROR(H15/H9,"") -> 0.57240953 | J17: =IFERROR(AVERAGE(Model!C226,Model!D226,Model!E226,Model!F226,Model!G226,Model!H226,Model!I226,Model!N226,Model!S226,Model!X226,Model!AC226,Model!AH226,Model!AM226,Model!AR226,Model!AW226,Model!BB226,Model!BG226,Model!BL226,Model!BQ226,Model!BV226),"") -> 0.25333516 | K17: =IFERROR(MIN(Model!C226,Model!D226,Model!E226,Model!F226,Model!G226,Model!H226,Model!I226,Model!N226,Model!S226,Model!X226,Model!AC226,Model!AH226,Model!AM226,Model!AR226,Model!AW226,Model!BB226,Model!BG226,Model!BL226,Model!BQ226,Model!BV226),"") -> 0.16393433 | L17: =IFERROR(MAX(Model!C226,Model!D226,Model!E226,Model!F226,Model!G226,Model!H226,Model!I226,Model!N226,Model!S226,Model!X226,Model!AC226,Model!AH226,Model!AM226,Model!AR226,Model!AW226,Model!BB226,Model!BG226,Model!BL226,Model!BQ226,Model!BV226),"") -> 0.46454588 | N17: Operating margin (GAAP) % | O17: 0.51366541 | P17: 0.5680039 | Q17: 0.57643742 | R17: 0.58007794 | S17: 0.57922661 | T17: 0.57760273 | V17: 0.25333516 | W17: 0.16393433 | X17: 0.46454588 | Z17: Operating margin (GAAP) % | AA17: 0.51518643 | AB17: 0.51032229 | AC17: 0.51854721 | AD17: 0.52233282 | AE17: 0.52215528 | AF17: 0.52167645 | AH17: 0.25333516 | AI17: 0.16393433 | AJ17: 0.46454588
B19: Non-GAAP Net Income | C19: =Model!CA201 -> 972.85941 | D19: =Model!CB201 -> 1094.4293 | E19: =Model!CC201 -> 1251.8589 | F19: =Model!CD201 -> 1355.855 | G19: =Model!CE201 -> 1474.3475 | H19: =Model!CF201 -> 1593.5992 | I19: =IFERROR((H19/C19)^(1/5)-1,"n/m") -> 0.10373752 | N19: Non-GAAP Net Income | O19: 971.42596 | P19: 1177.8202 | Q19: 1388.0163 | R19: 1570.1482 | S19: 1787.5096 | T19: 2025.2007 | U19: 0.15827498 | Z19: Non-GAAP Net Income | AA19: 974.29285 | AB19: 902.50801 | AC19: 951.28901 | AD19: 941.28978 | AE19: 920.26323 | AF19: 891.65189 | AG19: -0.017571023
B21: FDSO (m) | C21: =Model!CA153 -> 22.928574 | D21: =Model!CB153 -> 20.474889 | E21: =Model!CC153 -> 18.918259 | F21: =Model!CD153 -> 16.983654 | G21: =Model!CE153 -> 15.116438 | H21: =Model!CF153 -> 13.306447 | I21: =IFERROR((H21/C21)^(1/5)-1,"n/m") -> -0.10311448 | N21: FDSO (m) | O21: 22.894791 | P21: 19.752994 | Q21: 17.441005 | R21: 14.834814 | S21: 12.169578 | T21: 9.4335358 | U21: -0.1624947 | Z21: FDSO (m) | AA21: 22.962358 | AB21: 21.392865 | AC21: 21.279682 | AD21: 20.687018 | AE21: 19.950299 | AF21: 19.341095 | AG21: -0.033742416
B23: Non-GAAP EPS — Diluted ($) | C23: =Model!CA205 -> 42.43 | D23: =Model!CB205 -> 53.452271 | E23: =Model!CC205 -> 66.171989 | F23: =Model!CD205 -> 79.83294 | G23: =Model!CE205 -> 97.532729 | H23: =Model!CF205 -> 119.76143 | I23: =IFERROR((H23/C23)^(1/5)-1,"n/m") -> 0.23063367 | N23: Non-GAAP EPS — Diluted ($) | O23: 42.43 | P23: 59.627425 | Q23: 79.583506 | R23: 105.84212 | S23: 146.88345 | T23: 214.68098 | U23: 0.38300614 | Z23: Non-GAAP EPS — Diluted ($) | AA23: 42.43 | AB23: 42.187337 | AC23: 44.704098 | AD23: 45.501473 | AE23: 46.12779 | AF23: 46.101417 | AG23: 0.016736109
B24: EPS y/y % | D24: =IFERROR(D23/C23-1,"") -> 0.25977541 | E24: =IFERROR(E23/D23-1,"") -> 0.23796405 | F24: =IFERROR(F23/E23-1,"") -> 0.20644613 | G24: =IFERROR(G23/F23-1,"") -> 0.22171035 | H24: =IFERROR(H23/G23-1,"") -> 0.22791022 | N24: EPS y/y % | P24: 0.40531287 | Q24: 0.33467957 | R24: 0.32995044 | S24: 0.38775991 | T24: 0.46157369 | Z24: EPS y/y % | AB24: -0.0057191284 | AC24: 0.05965678 | AD24: 0.017836739 | AE24: 0.013764758 | AF24: -0.00057175161
B26: P / E (x) — assumed (non-GAAP EPS) | G26: 30 | H26: 30 | N26: P / E (x) — assumed (non-GAAP EPS) | S26: 38 | T26: 38 | Z26: P / E (x) — assumed (non-GAAP EPS) | AD26: 20 | AE26: 20 | AF26: 20
B27: Price Target ($) | G27: =G26*G23 -> 2925.9819 | H27: =H26*H23 -> 3592.843 | N27: Price Target ($) | S27: =S26*S23 -> 5581.571 | T27: =T26*T23 -> 8157.8774 | Z27: Price Target ($) | AD27: =AD26*AD23 -> 910.02947 | AE27: =AE26*AE23 -> 922.5558 | AF27: =AF26*AF23 -> 922.02833
B28: Upside / (Downside) vs current | G28: =IFERROR(G27/$K$2-1,"") -> 2.9540295 | H28: =IFERROR(H27/$K$2-1,"") -> 3.8551933 | N28: Upside / (Downside) vs current | S28: =IFERROR(S27/$K$2-1,"") -> 6.5426636 | T28: =IFERROR(T27/$K$2-1,"") -> 10.024159 | Z28: Upside / (Downside) vs current | AD28: =IFERROR(AD27/$K$2-1,"") -> 0.22976955 | AE28: =IFERROR(AE27/$K$2-1,"") -> 0.24669703 | AF28: =IFERROR(AF27/$K$2-1,"") -> 0.24598423
B29: IRR (to 30-Sep of Y-1) | G29: =IFERROR((G27/$K$2)^(1/((DATE(2030-1,9,30)-$K$3)/365.25))-1,"") -> 0.58985039 | H29: =IFERROR((H27/$K$2)^(1/((DATE(2031-1,9,30)-$K$3)/365.25))-1,"") -> 0.48967594 | N29: IRR (to 30-Sep of Y-1) | S29: =IFERROR((S27/$K$2)^(1/((DATE(2030-1,9,30)-$K$3)/365.25))-1,"") -> 0.97675071 | T29: =IFERROR((T27/$K$2)^(1/((DATE(2031-1,9,30)-$K$3)/365.25))-1,"") -> 0.83200174 | Z29: IRR (to 30-Sep of Y-1) | AD29: =IFERROR((AD27/$K$2)^(1/((DATE(2029-1,9,30)-$K$3)/365.25))-1,"") -> 0.11094807 | AE29: =IFERROR((AE27/$K$2)^(1/((DATE(2030-1,9,30)-$K$3)/365.25))-1,"") -> 0.077199397 | AF29: =IFERROR((AF27/$K$2)^(1/((DATE(2031-1,9,30)-$K$3)/365.25))-1,"") -> 0.057042653
B31: Free Cash Flow | C31: =Model!CA258 -> 1002.3757 | D31: =Model!CB258 -> 1116.9485 | E31: =Model!CC258 -> 1280.1248 | F31: =Model!CD258 -> 1386.8439 | G31: =Model!CE258 -> 1507.974 | H31: =Model!CF258 -> 1630.0355 | I31: =IFERROR((H31/C31)^(1/5)-1,"n/m") -> 0.10213122 | N31: Free Cash Flow | O31: 1000.9423 | P31: 1196.4564 | Q31: 1412.5113 | R31: 1597.6736 | S31: 1818.2338 | T31: 2059.6175 | U31: 0.15524875 | Z31: Free Cash Flow | AA31: 1003.8092 | AB31: 932.53982 | AC31: 985.8248 | AD31: 976.69934 | AE31: 956.0041 | AF31: 927.47211 | AG31: -0.01569444
B32: FCF % | C32: =IFERROR(C31/C9,"") -> 0.39619595 | D32: =IFERROR(D31/D9,"") -> 0.39907874 | E32: =IFERROR(E31/E9,"") -> 0.41451999 | F32: =IFERROR(F31/F9,"") -> 0.41033032 | G32: =IFERROR(G31/G9,"") -> 0.41008802 | H32: =IFERROR(H31/H9,"") -> 0.40992126 | J32: =IFERROR(AVERAGE(Model!C263,Model!D263,Model!E263,Model!F263,Model!G263,Model!H263,Model!I263,Model!N263,Model!S263,Model!X263,Model!AC263,Model!AH263,Model!AM263,Model!AR263,Model!AW263,Model!BB263,Model!BG263,Model!BL263,Model!BQ263,Model!BV263),"") -> 0.22755881 | K32: =IFERROR(MIN(Model!C263,Model!D263,Model!E263,Model!F263,Model!G263,Model!H263,Model!I263,Model!N263,Model!S263,Model!X263,Model!AC263,Model!AH263,Model!AM263,Model!AR263,Model!AW263,Model!BB263,Model!BG263,Model!BL263,Model!BQ263,Model!BV263),"") -> 0.12873205 | L32: =IFERROR(MAX(Model!C263,Model!D263,Model!E263,Model!F263,Model!G263,Model!H263,Model!I263,Model!N263,Model!S263,Model!X263,Model!AC263,Model!AH263,Model!AM263,Model!AR263,Model!AW263,Model!BB263,Model!BG263,Model!BL263,Model!BQ263,Model!BV263),"") -> 0.37139561 | N32: FCF % | O32: 0.39562937 | P32: 0.40865932 | Q32: 0.41745103 | R32: 0.41125607 | S32: 0.40948515 | T32: 0.40777193 | V32: 0.22755881 | W32: 0.12873205 | X32: 0.37139561 | Z32: FCF % | AA32: 0.39676253 | AB32: 0.36579662 | AC32: 0.38649754 | AD32: 0.38705789 | AE32: 0.38604709 | AF32: 0.38457025 | AH32: 0.22755881 | AI32: 0.12873205 | AJ32: 0.37139561
B33: FCF / share ($) | C33: =IFERROR(C31/C21,"") -> 43.717317 | D33: =IFERROR(D31/D21,"") -> 54.552115 | E33: =IFERROR(E31/E21,"") -> 67.666101 | F33: =IFERROR(F31/F21,"") -> 81.65757 | G33: =IFERROR(G31/G21,"") -> 99.757233 | H33: =IFERROR(H31/H21,"") -> 122.49968 | N33: FCF / share ($) | O33: 43.719216 | P33: 60.570891 | Q33: 80.987953 | R33: 107.69758 | S33: 149.40812 | T33: 218.32933 | Z33: FCF / share ($) | AA33: 43.715423 | AB33: 43.591161 | AC33: 46.327045 | AD33: 47.213153 | AE33: 47.919286 | AF33: 47.953443
B34: FCF Yield (on PT) | F34: =IFERROR(F33/F$27,"") | G34: =IFERROR(G33/G$27,"") -> 0.034093592 | H34: =IFERROR(H33/H$27,"") -> 0.034095472 | N34: FCF Yield (on PT) | R34: =IFERROR(R33/R$27,"") | S34: =IFERROR(S33/S$27,"") -> 0.026768113 | T34: =IFERROR(T33/T$27,"") -> 0.026763007 | Z34: FCF Yield (on PT) | AD34: =IFERROR(AD33/AD$27,"") -> 0.051880906 | AE34: =IFERROR(AE33/AE$27,"") -> 0.051941883 | AF34: =IFERROR(AF33/AF$27,"") -> 0.052008644
B35: Adjusted EBITDA (leverage basis) | C35: =Model!CA183 -> 1545.8696 | D35: =Model!CB183 -> 1790.9017 | E35: =Model!CC183 -> 2002.2487 | F35: =Model!CD183 -> 2209.6101 | G35: =Model!CE183 -> 2408.2373 | H35: =Model!CF183 -> 2606.2804 | I35: =IFERROR((H35/C35)^(1/5)-1,"n/m") -> 0.11011931 | N35: Adjusted EBITDA (leverage basis) | O35: 1543.9455 | P35: 1914.1999 | Q35: 2233.1594 | R35: 2576.3126 | S35: 2939.1589 | T35: 3333.4893 | U35: 0.16641587 | Z35: Adjusted EBITDA (leverage basis) | AA35: 1547.7937 | AB35: 1521.932 | AC35: 1538.6919 | AD35: 1531.9227 | AE35: 1503.1728 | AF35: 1463.0694 | AG35: -0.011195641
B36: Adjusted EBITDA % of revenue | C36: =IFERROR(C35/C9,"") -> 0.61101565 | D36: =IFERROR(D35/D9,"") -> 0.63987804 | E36: =IFERROR(E35/E9,"") -> 0.64835247 | F36: =IFERROR(F35/F9,"") -> 0.65376503 | G36: =IFERROR(G35/G9,"") -> 0.6549113 | H36: =IFERROR(H35/H9,"") -> 0.65542729 | J36: =IFERROR(AVERAGE(Model!C225,Model!D225,Model!E225,Model!F225,Model!G225,Model!H225,Model!I225,Model!N225,Model!S225,Model!X225,Model!AC225,Model!AH225,Model!AM225,Model!AR225,Model!AW225,Model!BB225,Model!BG225,Model!BL225,Model!BQ225,Model!BV225),"") -> 0.35212441 | K36: =IFERROR(MIN(Model!C225,Model!D225,Model!E225,Model!F225,Model!G225,Model!H225,Model!I225,Model!N225,Model!S225,Model!X225,Model!AC225,Model!AH225,Model!AM225,Model!AR225,Model!AW225,Model!BB225,Model!BG225,Model!BL225,Model!BQ225,Model!BV225),"") -> 0.27108031 | L36: =IFERROR(MAX(Model!C225,Model!D225,Model!E225,Model!F225,Model!G225,Model!H225,Model!I225,Model!N225,Model!S225,Model!X225,Model!AC225,Model!AH225,Model!AM225,Model!AR225,Model!AW225,Model!BB225,Model!BG225,Model!BL225,Model!BQ225,Model!BV225),"") -> 0.56195712 | N36: Adjusted EBITDA % of revenue | O36: 0.61025514 | P36: 0.65381039 | Q36: 0.65998388 | R36: 0.66316685 | S36: 0.66192914 | T36: 0.65997854 | V36: 0.35212441 | W36: 0.27108031 | X36: 0.56195712 | Z36: Adjusted EBITDA % of revenue | AA36: 0.61177615 | AB36: 0.59699069 | AC36: 0.60325187 | AD36: 0.60708833 | AE36: 0.60700104 | AF36: 0.60665218 | AH36: 0.35212441 | AI36: 0.27108031 | AJ36: 0.56195712
B38: Net Debt | C38: =Model!CA383 -> 5322.5103 | D38: =Model!CB383 -> 5316.6122 | E38: =Model!CC383 -> 5950.6531 | F38: =Model!CD383 -> 6572.7374 | G38: =Model!CE383 -> 7168.6188 | H38: =Model!CF383 -> 7762.7483 | N38: Net Debt | O38: 5523.9437 | P38: 6165.0568 | Q38: 7201.6751 | R38: 8316.9228 | S38: 9496.1734 | T38: 10777.747 | Z38: Net Debt | AA38: 5121.0768 | AB38: 4255.3132 | AC38: 3790.6369 | AD38: 3773.7137 | AE38: 3701.839 | AF38: 3601.5805
B39: Net Debt / Adjusted EBITDA (x) | C39: =IFERROR(C38/C35,"") -> 3.4430526 | D39: =IFERROR(D38/D35,"") -> 2.9686789 | E39: =IFERROR(E38/E35,"") -> 2.971985 | F39: =IFERROR(F38/F35,"") -> 2.9746141 | G39: =IFERROR(G38/G35,"") -> 2.9767079 | H39: =IFERROR(H38/H35,"") -> 2.9784778 | N39: Net Debt / Adjusted EBITDA (x) | O39: 3.57781 | P39: 3.2206964 | Q39: 3.2248818 | R39: 3.2282274 | S39: 3.2309153 | T39: 3.2331729 | Z39: Net Debt / Adjusted EBITDA (x) | AA39: 3.3086302 | AB39: 2.7959943 | AC39: 2.463545 | AD39: 2.4633839 | AE39: 2.4626836 | AF39: 2.4616607
B40: Share repurchases ($m; FY2026E = Q4) | D40: =Model!CB276 -> 1035.293 | E40: =Model!CC276 -> 1827.9901 | F40: =Model!CD276 -> 1912.2546 | G40: =Model!CE276 -> 1996.4763 | H40: =Model!CF276 -> 2106.0125 | N40: Share repurchases ($m; FY2026E = Q4) | P40: 1757.1701 | Q40: 2352.318 | R40: 2598.0663 | S40: 2862.6339 | T40: 3184.3586 | AB40: 0 | AC40: 454.32459 | AD40: 893.93403 | AE40: 819.97928 | AF40: 765.39203
B41: Implied avg buyback price ($) | D41: =Model!CB275 -> 799.2 | E41: =Model!CC275 -> 863.136 | F41: =Model!CD275 -> 932.18688 | G41: =Model!CE275 -> 1006.7618 | H41: =Model!CF275 -> 1087.3028 | N41: Implied avg buyback price ($) | P41: 799.2 | Q41: 863.136 | R41: 932.18688 | S41: 1006.7618 | T41: 1087.3028 | AB41: 799.2 | AC41: 863.136 | AD41: 932.18688 | AE41: 1006.7618 | AF41: 1087.3028
B42: Shares repurchased (m) | D42: =Model!CB277 -> 1.2954117 | E42: =Model!CC277 -> 2.1178472 | F42: =Model!CD277 -> 2.051364 | G42: =Model!CE277 -> 1.9830672 | H42: =Model!CF277 -> 1.9369145 | N42: Shares repurchased (m) | P42: 2.1986613 | Q42: 2.7253156 | R42: 2.7870659 | S42: 2.8434072 | T42: 2.928677 | AB42: 0 | AC42: 0.52636502 | AD42: 0.9589644 | AE42: 0.81447195 | AF42: 0.70393643
B44: ROIC | C44: =Model!CA366 -> 0.87741218 | D44: =Model!CB366 -> 1.0020601 | E44: =Model!CC366 -> 1.0887916 | F44: =Model!CD366 -> 1.1657053 | G44: =Model!CE366 -> 1.2301435 | H44: =Model!CF366 -> 1.287781 | J44: =IFERROR(AVERAGE(Model!C366,Model!D366,Model!E366,Model!F366,Model!G366,Model!H366,Model!I366,Model!N366,Model!S366,Model!X366,Model!AC366,Model!AH366,Model!AM366,Model!AR366,Model!AW366,Model!BB366,Model!BG366,Model!BL366,Model!BQ366,Model!BV366),"") -> 0.23057775 | K44: =IFERROR(MIN(Model!C366,Model!D366,Model!E366,Model!F366,Model!G366,Model!H366,Model!I366,Model!N366,Model!S366,Model!X366,Model!AC366,Model!AH366,Model!AM366,Model!AR366,Model!AW366,Model!BB366,Model!BG366,Model!BL366,Model!BQ366,Model!BV366),"") -> 0.089689362 | L44: =IFERROR(MAX(Model!C366,Model!D366,Model!E366,Model!F366,Model!G366,Model!H366,Model!I366,Model!N366,Model!S366,Model!X366,Model!AC366,Model!AH366,Model!AM366,Model!AR366,Model!AW366,Model!BB366,Model!BG366,Model!BL366,Model!BQ366,Model!BV366),"") -> 0.63913839 | N44: ROIC | O44: 0.87615453 | P44: 1.0686994 | Q44: 1.2023138 | R44: 1.3324677 | S44: 1.4540591 | T44: 1.5721731 | V44: 0.23057775 | W44: 0.089689362 | X44: 0.63913839 | Z44: ROIC | AA44: 0.87866984 | AB44: 0.85147176 | AC44: 0.84729972 | AD44: 0.83095053 | AE44: 0.80333132 | AF44: 0.7712458 | AH44: 0.23057775 | AI44: 0.089689362 | AJ44: 0.63913839
B45: RONTA | C45: =Model!CA377 -> 1.5130022 | D45: =Model!CB377 -> 1.6933493 | E45: =Model!CC377 -> 1.802669 | F45: =Model!CD377 -> 1.8916103 | G45: =Model!CE377 -> 1.9571805 | H45: =Model!CF377 -> 2.009921 | J45: =IFERROR(AVERAGE(Model!C377,Model!D377,Model!E377,Model!F377,Model!G377,Model!H377,Model!I377,Model!N377,Model!S377,Model!X377,Model!AC377,Model!AH377,Model!AM377,Model!AR377,Model!AW377,Model!BB377,Model!BG377,Model!BL377,Model!BQ377,Model!BV377),"") -> 0.58673449 | K45: =IFERROR(MIN(Model!C377,Model!D377,Model!E377,Model!F377,Model!G377,Model!H377,Model!I377,Model!N377,Model!S377,Model!X377,Model!AC377,Model!AH377,Model!AM377,Model!AR377,Model!AW377,Model!BB377,Model!BG377,Model!BL377,Model!BQ377,Model!BV377),"") -> 0.15634971 | L45: =IFERROR(MAX(Model!C377,Model!D377,Model!E377,Model!F377,Model!G377,Model!H377,Model!I377,Model!N377,Model!S377,Model!X377,Model!AC377,Model!AH377,Model!AM377,Model!AR377,Model!AW377,Model!BB377,Model!BG377,Model!BL377,Model!BQ377,Model!BV377),"") -> 1.1282412 | N45: RONTA | O45: 1.5108335 | P45: 1.7994775 | Q45: 1.9746112 | R45: 2.1335536 | S45: 2.2692817 | T45: 2.3915569 | V45: 0.58673449 | W45: 0.15634971 | X45: 1.1282412 | Z45: RONTA | AA45: 1.5151709 | AB45: 1.449134 | AC45: 1.064033 | AD45: 1.0212655 | AE45: 0.9176921 | AF45: 0.80485587 | AH45: 0.58673449 | AI45: 0.15634971 | AJ45: 1.1282412
B47: Implied Market Cap (USDm) | F47: =F27*F21 -> 0 | G47: =G27*G21 -> 44230.424 | H47: =H27*H21 -> 47807.977 | N47: Implied Market Cap (USDm) | R47: =R27*R21 -> 0 | S47: =S27*S21 -> 67925.364 | T47: =T27*T21 -> 76957.628 | Z47: Implied Market Cap (USDm) | AD47: =AD27*AD21 -> 18825.796 | AE47: =AE27*AE21 -> 18405.265 | AF47: =AF27*AF21 -> 17833.038
B48: (+) Net Debt & NCI | F48: =F38+Model!CD393 -> 6572.7374 | G48: =G38+Model!CE393 -> 7168.6188 | H48: =H38+Model!CF393 -> 7762.7483 | N48: (+) Net Debt & NCI | R48: =R38+Model!CD393 -> 8316.9228 | S48: =S38+Model!CE393 -> 9496.1734 | T48: =T38+Model!CF393 -> 10777.747 | Z48: (+) Net Debt & NCI | AD48: =AD38+Model!CD393 -> 3773.7137 | AE48: =AE38+Model!CE393 -> 3701.839 | AF48: =AF38+Model!CF393 -> 3601.5805
B49: Implied Enterprise Value (USDm) | F49: =F47+F48 -> 6572.7374 | G49: =G47+G48 -> 51399.043 | H49: =H47+H48 -> 55570.725 | N49: Implied Enterprise Value (USDm) | R49: =R47+R48 -> 8316.9228 | S49: =S47+S48 -> 77421.537 | T49: =T47+T48 -> 87735.375 | Z49: Implied Enterprise Value (USDm) | AD49: =AD47+AD48 -> 22599.509 | AE49: =AE47+AE48 -> 22107.104 | AF49: =AF47+AF48 -> 21434.618
B50: Implied EV / Adjusted EBITDA (x) | F50: =IFERROR(F49/F35,"") -> 2.9746141 | G50: =IFERROR(G49/G35,"") -> 21.343014 | H50: =IFERROR(H49/H35,"") -> 21.321852 | N50: Implied EV / Adjusted EBITDA (x) | R50: =IFERROR(R49/R35,"") -> 3.2282274 | S50: =IFERROR(S49/S35,"") -> 26.341392 | T50: =IFERROR(T49/T35,"") -> 26.319381 | Z50: Implied EV / Adjusted EBITDA (x) | AD50: =IFERROR(AD49/AD35,"") -> 14.752383 | AE50: =IFERROR(AE49/AE35,"") -> 14.706961 | AF50: =IFERROR(AF49/AF35,"") -> 14.650445

Sheet DCF
B2: DCF VALUATION — FAIR ISAAC CORPORATION (FICO)
B4: 1. WACC BUILD
B5: Risk-free rate (US 10Y govt) | C5: 0.0425 | D5: Assumption (~US 10Y Treasury yield, Oct-2026; government rate sources not reachable from the build environment); update to market
B6: Equity risk premium | C6: 0.05 | D6: Assumption: US implied ERP ~4.5–5.5%
B7: Levered beta | C7: 1.1 | D7: Assumption: credit-data and analytics peers (EFX, TRU, MCO, SPGI, VRSK) ~0.9–1.2; higher financial leverage (net debt ~3.5x EBITDA) and mortgage-score pricing risk
B8: Cost of equity | C8: =C5+C7*C6 -> 0.0975
B9: Pre-tax cost of debt | C9: 0.06 | D9: 2025 Senior Notes 6.00% (due 2033) and 2026 Senior Notes 6.25% (due 2034); term loan 5.86% and revolver 5.64% at 30-Jun-2026 (Q3 FY26 10-Q)
B10: Tax rate | C10: 0.25 | D10: Model non-GAAP effective tax rate FY2027E+ (9M FY26 25.4%; FY2025 24.3%)
B11: After-tax cost of debt | C11: =C9*(1-C10) -> 0.045
B12: Target D/V | C12: 0.25 | D12: Debt ~$5.6bn at 30-Jun-2026 vs ~$16bn market cap ($740 × ~21.8m diluted shares)
B13: WACC | C13: =C8*(1-C12)+C11*C12 -> 0.084375
B15: Valuation date (live) | C15: =TODAY() -> 2026-10-13 00:00:00 | D15: Periods = (30-Sep of fiscal year − today) / 365.25; cash flows assumed at fiscal year-end (30 September); FY2026E (ended 30-Sep-2026) is the base year
B16: 2. UNLEVERED FREE CASH FLOW BUILD (USDm)
D17: 2027E | E17: 2028E | F17: 2029E | G17: 2030E | H17: 2031E | I17: 2032E | J17: 2033E | K17: 2034E | L17: 2035E | M17: 2036E | N17: Terminal | P17: CAGR 27–31E | Q17: CAGR 27–36E
B18: Adj. EBITA after SBC less restructuring & acquisition costs | D18: =Model!CB189-Model!CB191 -> 1561.9963 | E18: =Model!CC189-Model!CC191 -> 1755.1919 | F18: =Model!CD189-Model!CD191 -> 1939.2243 | G18: =Model!CE189-Model!CE191 -> 2114.0616 | H18: =Model!CF189-Model!CF191 -> 2288.1636 | I18: =H18*(1+I$26) -> 2471.2167 | J18: =I18*(1+J$26) -> 2650.3799 | K18: =J18*(1+K$26) -> 2822.6546 | L18: =K18*(1+L$26) -> 2984.9573 | M18: =L18*(1+M$26) -> 3134.2051 | P18: =(H18/D18)^(1/(COLUMNS(D18:H18)-1))-1 -> 0.10014965 | Q18: =(M18/D18)^(1/(COLUMNS(D18:M18)-1))-1 -> 0.080451475
B19: × (1 − tax rate) | D19: =1-$C$10 -> 0.75 | E19: =1-$C$10 -> 0.75 | F19: =1-$C$10 -> 0.75 | G19: =1-$C$10 -> 0.75 | H19: =1-$C$10 -> 0.75 | I19: =1-$C$10 -> 0.75 | J19: =1-$C$10 -> 0.75 | K19: =1-$C$10 -> 0.75 | ... M19: =1-$C$10 -> 0.75
B20: NOPAT | D20: =D18*D19 -> 1171.4973 | E20: =E18*E19 -> 1316.3939 | F20: =F18*F19 -> 1454.4182 | G20: =G18*G19 -> 1585.5462 | H20: =H18*H19 -> 1716.1227 | I20: =I18*I19 -> 1853.4125 | J20: =J18*J19 -> 1987.7849 | K20: =K18*K19 -> 2116.991 | ... M20: =M18*M19 -> 2350.6538
B21: plus depreciation & software amortization | D21: =Model!CB114 -> 22.390538 | E21: =Model!CC114 -> 24.705681 | F21: =Model!CD114 -> 27.038585 | G21: =Model!CE114 -> 29.417569 | H21: =Model!CF114 -> 31.81168 | I21: =H21*(1+I$26) -> 34.356615 | J21: =I21*(1+J$26) -> 36.847469 | K21: =J21*(1+K$26) -> 39.242555 | L21: =K21*(1+L$26) -> 41.499002 | M21: =L21*(1+M$26) -> 43.573952
B22: − Capex (PP&E + capitalized software) and acquisitions (M&A lever 2027E–31E) | D22: =Model!CB268+Model!CB240 -> -44.781077 | E22: =Model!CC268+Model!CC240 -> -49.411362 | F22: =Model!CD268+Model!CD240 -> -54.077169 | G22: =Model!CE268+Model!CE240 -> -58.835137 | H22: =Model!CF268+Model!CF240 -> -63.623361 | I22: =Model!CF268*(1+I$26) -> -68.71323 | J22: =I22*(1+J$26) -> -73.694939 | K22: =J22*(1+K$26) -> -78.48511 | L22: =K22*(1+L$26) -> -82.998004 | M22: =L22*(1+M$26) -> -87.147904
B23: − Δ Working capital (CF statement) | D23: =Model!CB236 -> -10.686409 | E23: =Model!CC236 -> -11.504356 | F23: =Model!CD236 -> -11.592612 | G23: =Model!CE236 -> -11.821595 | H23: =Model!CF236 -> -11.896768 | I23: =H23*(1+I$26) -> -12.84851 | J23: =I23*(1+J$26) -> -13.780027 | K23: =J23*(1+K$26) -> -14.675729 | L23: =K23*(1+L$26) -> -15.519583 | M23: =L23*(1+M$26) -> -16.295562
B24: Unlevered FCF | D24: =D20+D21+D22+D23 -> 1138.4203 | E24: =E20+E21+E22+E23 -> 1280.1839 | F24: =F20+F21+F22+F23 -> 1415.787 | G24: =G20+G21+G22+G23 -> 1544.307 | H24: =H20+H21+H22+H23 -> 1672.4143 | I24: =I20+I21+I22+I23 -> 1806.2074 | J24: =J20+J21+J22+J23 -> 1937.1574 | K24: =K20+K21+K22+K23 -> 2063.0727 | ... M24: =M20+M21+M22+M23 -> 2290.7843 | N24: =M24*(1+$C$27) -> 2382.4157 | P24: =(H24/D24)^(1/(COLUMNS(D24:H24)-1))-1 -> 0.10093152 | Q24: =(M24/D24)^(1/(COLUMNS(D24:M24)-1))-1 -> 0.080792684
B25: Terminal Value (Gordon Growth) | N25: =N24/($C$13-$C$27) -> 53688.241
B26: Fade-period growth (2032E–36E; 8.0% → 5.0% linear) | I26: 0.08 | J26: =I26+($M$26-$I$26)/4 -> 0.0725 | K26: =J26+($M$26-$I$26)/4 -> 0.065 | L26: =K26+($M$26-$I$26)/4 -> 0.0575 | M26: 0.05
B27: Terminal growth rate | C27: 0.04
B29: Discount period (years) | D29: =(DATE(2027,9,30)-$C$15)/365.25 -> 0.96372348 | E29: =(DATE(2028,9,30)-$C$15)/365.25 -> 1.9657769 | F29: =(DATE(2029,9,30)-$C$15)/365.25 -> 2.9650924 | G29: =(DATE(2030,9,30)-$C$15)/365.25 -> 3.9644079 | H29: =(DATE(2031,9,30)-$C$15)/365.25 -> 4.9637235 | I29: =(DATE(2032,9,30)-$C$15)/365.25 -> 5.9657769 | J29: =(DATE(2033,9,30)-$C$15)/365.25 -> 6.9650924 | K29: =(DATE(2034,9,30)-$C$15)/365.25 -> 7.9644079 | L29: =(DATE(2035,9,30)-$C$15)/365.25 -> 8.9637235 | M29: =(DATE(2036,9,30)-$C$15)/365.25 -> 9.9657769 | N29: =M29 -> 9.9657769
B30: Discount factor | D30: =1/(1+$C$13)^D29 -> 0.92490408 | E30: =1/(1+$C$13)^E29 -> 0.85279562 | F30: =1/(1+$C$13)^F29 -> 0.78648337 | G30: =1/(1+$C$13)^G29 -> 0.72532747 | H30: =1/(1+$C$13)^H29 -> 0.66892697 | I30: =1/(1+$C$13)^I29 -> 0.6167753 | J30: =1/(1+$C$13)^J29 -> 0.56881568 | K30: =1/(1+$C$13)^K29 -> 0.52458533 | ... N30: =1/(1+$C$13)^N29 -> 0.44607613
B31: PV of UFCF | D31: =D24*D30 -> 1052.9296 | E31: =E24*E30 -> 1091.7352 | F31: =F24*F30 -> 1113.4929 | G31: =G24*G30 -> 1120.1283 | H31: =H24*H30 -> 1118.723 | I31: =I24*I30 -> 1114.0241 | J31: =J24*J30 -> 1101.8855 | K31: =K24*K30 -> 1082.2577 | ... M31: =M24*M30 -> 1021.8642 | N31: =N25*N30 -> 23949.043
D32: FICO's non-GAAP measures exclude share-based compensation (~7% of revenue); the model NOPAT deducts it (row 18 = adjusted EBITDA − depreciation − SBC − restructuring) and taxes the result at the non-GAAP rate. Acquired-intangible amortization is nil. Restructuring (the Oct-2026 workforce reduction, mostly in FY2026) is a cash cost. Row 22 includes capitalized internal-use software and any M&A from the lever (Base $0); the fade period and terminal value assume no acquisitions. Operating leases (~$17m) are left in operating costs and excluded from net debt.
B33: IMPLIED ROIC — invested capital roll-forward (USDm)
B34: Opening invested capital | D34: =Model!CA363 -> 1139.7542 | E34: =D38 -> 1172.8311 | F34: =E38 -> 1209.0411 | G34: =F38 -> 1247.6723 | H34: =G38 -> 1288.9115 | I34: =H38 -> 1332.62 | J34: =I38 -> 1379.8251 | K34: =J38 -> 1430.4526 | L34: =K38 -> 1484.3709 | M34: =L38 -> 1541.3894
B35: plus Capex and acquisitions | D35: =-D22 -> 44.781077 | E35: =-E22 -> 49.411362 | F35: =-F22 -> 54.077169 | G35: =-G22 -> 58.835137 | H35: =-H22 -> 63.623361 | I35: =-I22 -> 68.71323 | J35: =-J22 -> 73.694939 | K35: =-K22 -> 78.48511 | ... M35: =-M22 -> 87.147904
B36: less DD&A | D36: =-D21 -> -22.390538 | E36: =-E21 -> -24.705681 | F36: =-F21 -> -27.038585 | G36: =-G21 -> -29.417569 | H36: =-H21 -> -31.81168 | I36: =-I21 -> -34.356615 | J36: =-J21 -> -36.847469 | K36: =-K21 -> -39.242555 | ... M36: =-M21 -> -43.573952
B37: plus Δ Working capital investment | D37: =-D23 -> 10.686409 | E37: =-E23 -> 11.504356 | F37: =-F23 -> 11.592612 | G37: =-G23 -> 11.821595 | H37: =-H23 -> 11.896768 | I37: =-I23 -> 12.84851 | J37: =-J23 -> 13.780027 | K37: =-K23 -> 14.675729 | ... M37: =-M23 -> 16.295562
B38: Closing invested capital | D38: =SUM(D34:D37) -> 1172.8311 | E38: =SUM(E34:E37) -> 1209.0411 | F38: =SUM(F34:F37) -> 1247.6723 | G38: =SUM(G34:G37) -> 1288.9115 | H38: =SUM(H34:H37) -> 1332.62 | I38: =SUM(I34:I37) -> 1379.8251 | J38: =SUM(J34:J37) -> 1430.4526 | K38: =SUM(K34:K37) -> 1484.3709 | ... M38: =SUM(M34:M37) -> 1601.259
B39: NOPAT (row 20) | D39: =D20 -> 1171.4973 | E39: =E20 -> 1316.3939 | F39: =F20 -> 1454.4182 | G39: =G20 -> 1585.5462 | H39: =H20 -> 1716.1227 | I39: =I20 -> 1853.4125 | J39: =J20 -> 1987.7849 | K39: =K20 -> 2116.991 | ... M39: =M20 -> 2350.6538
B40: Implied ROIC (NOPAT / avg. invested capital) | D40: =IFERROR(D39/AVERAGE(D34,D38),"") -> 1.0131495 | E40: =IFERROR(E39/AVERAGE(E34,E38),"") -> 1.1053438 | F40: =IFERROR(F39/AVERAGE(F34,F38),"") -> 1.1840357 | G40: =IFERROR(G39/AVERAGE(G34,G38),"") -> 1.2501429 | H40: =IFERROR(H39/AVERAGE(H34,H38),"") -> 1.309252 | I40: =IFERROR(I39/AVERAGE(I34,I38),"") -> 1.3665991 | J40: =IFERROR(J39/AVERAGE(J34,J38),"") -> 1.4146538 | K40: =IFERROR(K39/AVERAGE(K34,K38),"") -> 1.4525689 | ... M40: =IFERROR(M39/AVERAGE(M34,M38),"") -> 1.49597
B41: Reinvestment rate (net investment / NOPAT) | D41: =IFERROR(SUM(D35:D37)/D39,"") -> 0.028234763 | E41: =IFERROR(SUM(E35:E37)/E39,"") -> 0.027506993 | F41: =IFERROR(SUM(F35:F37)/F39,"") -> 0.026561271 | G41: =IFERROR(SUM(G35:G37)/G39,"") -> 0.026009437 | H41: =IFERROR(SUM(H35:H37)/H39,"") -> 0.025469303 | I41: =IFERROR(SUM(I35:I37)/I39,"") -> 0.025469303 | J41: =IFERROR(SUM(J35:J37)/J39,"") -> 0.025469303 | K41: =IFERROR(SUM(K35:K37)/K39,"") -> 0.025469303 | ... M41: =IFERROR(SUM(M35:M37)/M39,"") -> 0.025469303
B42: Implied terminal RONIC (g / reinvestment rate) | N42: =IFERROR($C$27/M41,"") -> 1.5705181
D43: Opening IC = Model FY2026E book IC (stockholders' deficit + net debt at 30-Sep-2026), rolled forward with capex + M&A − depreciation + ΔWC.
B44: 3. VALUATION SUMMARY
B45: Sum of PV (explicit + fade) | C45: =SUM(D31:M31) -> 10872.534
B46: PV of Terminal Value | C46: =N31 -> 23949.043
B47: Enterprise Value | C47: =C45+C46 -> 34821.577
B48: Less: Net debt + NCI (Model FY2026E year end, 30-Sep-2026) | C48: =Model!CA383+Model!CA393 -> 5322.5103 | D48: FICO: no noncontrolling interests; net debt (debt − cash − marketable securities) at the base-year end (≈ valuation date) so that FY2027E+ cash flows are not double counted.
B49: Equity Value | C49: =C47-C48 -> 29499.067
B50: Diluted shares (m, Model FY2026E period end) | C50: =Model!CA390 -> 20.980595
B51: Implied share price ($) | C51: =C49/C50 -> 1406.0167
B52: Current share price ($) | C52: =Model!CA389 -> 740
B53: Implied upside / (downside) | C53: =C51/C52-1 -> 0.9000226
B54: Required discount to DCF value for target IRR | C54: =1-((1+C13)/(1+H54))^H55 -> 0.16161216 | D54: vs. current | E54: Target IRR | H54: 0.15
B55: Max entry price for target IRR ($) | C55: =C51*(1-C54) -> 1178.7873 | D55: =C55/C52-1 -> 0.59295584 | E55: Years for discount to close | H55: 3
B58: 4. SENSITIVITY: IMPLIED PRICE ($) — WACC × Terminal Growth
D60: WACC →
B61: Terminal growth ↓ | D61: =F61-0.01 -> 0.074375 | E61: =F61-0.005 -> 0.079375 | F61: =$C$13 -> 0.084375 | G61: =F61+0.005 -> 0.089375 | H61: =F61+0.01 -> 0.094375
B62: =B64-0.01 -> 0.03 | D62: {=IFERROR((SUMPRODUCT($D$24:$M$24/(1+D$61)^$D$29:$M$29)+($M$24*(1+$B62)/(D$61-$B62))/(1+D$61)^$M$29-$C$48)/$C$50,"")} -> 1531.3182 | E62: {=IFERROR((SUMPRODUCT($D$24:$M$24/(1+E$61)^$D$29:$M$29)+($M$24*(1+$B62)/(E$61-$B62))/(1+E$61)^$M$29-$C$48)/$C$50,"")} -> 1341.6654 | F62: {=IFERROR((SUMPRODUCT($D$24:$M$24/(1+F$61)^$D$29:$M$29)+($M$24*(1+$B62)/(F$61-$B62))/(1+F$61)^$M$29-$C$48)/$C$50,"")} -> 1187.1311 | G62: {=IFERROR((SUMPRODUCT($D$24:$M$24/(1+G$61)^$D$29:$M$29)+($M$24*(1+$B62)/(G$61-$B62))/(1+G$61)^$M$29-$C$48)/$C$50,"")} -> 1058.835 | H62: {=IFERROR((SUMPRODUCT($D$24:$M$24/(1+H$61)^$D$29:$M$29)+($M$24*(1+$B62)/(H$61-$B62))/(1+H$61)^$M$29-$C$48)/$C$50,"")} -> 950.65604
B63: =B64-0.005 -> 0.035 | D63: {=IFERROR((SUMPRODUCT($D$24:$M$24/(1+D$61)^$D$29:$M$29)+($M$24*(1+$B63)/(D$61-$B63))/(1+D$61)^$M$29-$C$48)/$C$50,"")} -> 1695.5437 | E63: {=IFERROR((SUMPRODUCT($D$24:$M$24/(1+E$61)^$D$29:$M$29)+($M$24*(1+$B63)/(E$61-$B63))/(1+E$61)^$M$29-$C$48)/$C$50,"")} -> 1467.2901 | F63: {=IFERROR((SUMPRODUCT($D$24:$M$24/(1+F$61)^$D$29:$M$29)+($M$24*(1+$B63)/(F$61-$B63))/(1+F$61)^$M$29-$C$48)/$C$50,"")} -> 1285.4911 | G63: {=IFERROR((SUMPRODUCT($D$24:$M$24/(1+G$61)^$D$29:$M$29)+($M$24*(1+$B63)/(G$61-$B63))/(1+G$61)^$M$29-$C$48)/$C$50,"")} -> 1137.324 | H63: {=IFERROR((SUMPRODUCT($D$24:$M$24/(1+H$61)^$D$29:$M$29)+($M$24*(1+$B63)/(H$61-$B63))/(1+H$61)^$M$29-$C$48)/$C$50,"")} -> 1014.2858
B64: =$C$27 -> 0.04 | D64: {=IFERROR((SUMPRODUCT($D$24:$M$24/(1+D$61)^$D$29:$M$29)+($M$24*(1+$B64)/(D$61-$B64))/(1+D$61)^$M$29-$C$48)/$C$50,"")} -> 1907.544 | E64: {=IFERROR((SUMPRODUCT($D$24:$M$24/(1+E$61)^$D$29:$M$29)+($M$24*(1+$B64)/(E$61-$B64))/(1+E$61)^$M$29-$C$48)/$C$50,"")} -> 1624.8195 | F64: {=IFERROR((SUMPRODUCT($D$24:$M$24/(1+F$61)^$D$29:$M$29)+($M$24*(1+$B64)/(F$61-$B64))/(1+F$61)^$M$29-$C$48)/$C$50,"")} -> 1406.0167 | G64: {=IFERROR((SUMPRODUCT($D$24:$M$24/(1+G$61)^$D$29:$M$29)+($M$24*(1+$B64)/(G$61-$B64))/(1+G$61)^$M$29-$C$48)/$C$50,"")} -> 1231.7096 | H64: {=IFERROR((SUMPRODUCT($D$24:$M$24/(1+H$61)^$D$29:$M$29)+($M$24*(1+$B64)/(H$61-$B64))/(1+H$61)^$M$29-$C$48)/$C$50,"")} -> 1089.6176
B65: =B64+0.005 -> 0.045 | D65: {=IFERROR((SUMPRODUCT($D$24:$M$24/(1+D$61)^$D$29:$M$29)+($M$24*(1+$B65)/(D$61-$B65))/(1+D$61)^$M$29-$C$48)/$C$50,"")} -> 2191.7145 | E65: {=IFERROR((SUMPRODUCT($D$24:$M$24/(1+E$61)^$D$29:$M$29)+($M$24*(1+$B65)/(E$61-$B65))/(1+E$61)^$M$29-$C$48)/$C$50,"")} -> 1828.1756 | F65: {=IFERROR((SUMPRODUCT($D$24:$M$24/(1+F$61)^$D$29:$M$29)+($M$24*(1+$B65)/(F$61-$B65))/(1+F$61)^$M$29-$C$48)/$C$50,"")} -> 1557.152 | G65: {=IFERROR((SUMPRODUCT($D$24:$M$24/(1+G$61)^$D$29:$M$29)+($M$24*(1+$B65)/(G$61-$B65))/(1+G$61)^$M$29-$C$48)/$C$50,"")} -> 1347.3652 | H65: {=IFERROR((SUMPRODUCT($D$24:$M$24/(1+H$61)^$D$29:$M$29)+($M$24*(1+$B65)/(H$61-$B65))/(1+H$61)^$M$29-$C$48)/$C$50,"")} -> 1180.2065
B66: =B64+0.01 -> 0.05 | D66: {=IFERROR((SUMPRODUCT($D$24:$M$24/(1+D$61)^$D$29:$M$29)+($M$24*(1+$B66)/(D$61-$B66))/(1+D$61)^$M$29-$C$48)/$C$50,"")} -> 2592.4678 | E66: {=IFERROR((SUMPRODUCT($D$24:$M$24/(1+E$61)^$D$29:$M$29)+($M$24*(1+$B66)/(E$61-$B66))/(1+E$61)^$M$29-$C$48)/$C$50,"")} -> 2100.7593 | F66: {=IFERROR((SUMPRODUCT($D$24:$M$24/(1+F$61)^$D$29:$M$29)+($M$24*(1+$B66)/(F$61-$B66))/(1+F$61)^$M$29-$C$48)/$C$50,"")} -> 1752.254 | G66: {=IFERROR((SUMPRODUCT($D$24:$M$24/(1+G$61)^$D$29:$M$29)+($M$24*(1+$B66)/(G$61-$B66))/(1+G$61)^$M$29-$C$48)/$C$50,"")} -> 1492.3937 | H66: {=IFERROR((SUMPRODUCT($D$24:$M$24/(1+H$61)^$D$29:$M$29)+($M$24*(1+$B66)/(H$61-$B66))/(1+H$61)^$M$29-$C$48)/$C$50,"")} -> 1291.2098
B69: 5. REVERSE DCF
B70: To solve for the market-implied path: Data ▸ What-If Analysis ▸ Goal Seek — set C51 to the current price (C52) by changing C27 (terminal growth) or the fade-period growth inputs (I26:M26).
B72: 6. MAUBOUSSIN EV / NOPAT — TWO-STAGE FRAMEWORK
B73: EV/NOPAT = 1/r + [g × (1 − r/ROIIC) / (r × (r − g))] × [1 − ((1+g)/(1+r))^N]
B74: Formula source: Mauboussin & Rappaport, "Expectations Investing" (2021); Counterpoint Global, "What Does a Price-Earnings Multiple Mean?" (2020).
B76: Input | C76: Value | D76: Rationale (Fair Isaac characteristics)
B77: r (Cost of capital / WACC) | C77: =$C$13 -> 0.084375 | D77: Linked from Section 1 WACC build
B78: g (NOPAT growth, Stage 1) | C78: 0.11 | D78: Model non-GAAP operating income CAGR FY2026–31E: B2B Scores pricing and platform software growth with stable Scores margins → ~10–12% NOPAT growth
B79: ROIIC (Return on incremental invested capital) | C79: 0.6 | D79: Capital-light model: the FICO Score is embedded in US lending (90% of top lenders, release boilerplate) and Scores earn ~90% segment margins; book invested capital is small because of buybacks
B80: N (Years of value creation / CAP) | C80: 15 | D80: Long competitive-advantage period from the score's entrenchment with lenders and the GSEs; risks: FHFA approval of alternative scores and bureau competition (VantageScore) — 10-K risk factors
B82: Calculation | C82: Value
B83: Steady-state component: 1 / r | C83: =1/C77 -> 11.851852
B84: Value-creation factor: 1 − r / ROIIC | C84: =1-C77/C79 -> 0.859375
B85: Growth multiplier: g × (1 − r/ROIIC) / (r × (r − g)) | C85: =C78*C84/(C77*(C77-C78)) -> -43.721771
B86: Time decay: 1 − ((1+g)/(1+r))^N | C86: =1-((1+C78)/(1+C77))^C80 -> -0.41955504
B87: PVGO component (growth value) | C87: =C85*C86 -> 18.343689
B88: Mauboussin EV / NOPAT (steady-state + PVGO) | C88: =C83+C87 -> 30.195541
B90: VALUATION — Applied to FY2029E NOPAT | C90: USDm
B91: FY2029E Adj. EBITA after SBC less restructuring & acquisition costs | C91: =Model!CD189-Model!CD191 -> 1939.2243
B92: Tax rate (from WACC build) | C92: =$C$10 -> 0.25
B93: FY2029E NOPAT | C93: =C91*(1-C92) -> 1454.4182
B94: × Mauboussin EV/NOPAT multiple | C94: =C88 -> 30.195541
B95: Implied Enterprise Value (FY2029E basis) | C95: =C93*C94 -> 43916.945
B96: Less: FY2028E year-end net debt + NCI (Model) | C96: =Model!CC383+Model!CC393 -> 5950.6531
B97: Implied Equity Value | C97: =C95-C96 -> 37966.292
B98: Diluted shares FY2029E (m, Model) | C98: =Model!CD390 -> 16.032972
B99: Implied share price FY2029 ($) | C99: =C97/C98 -> 2368.0134
B101: Current share price ($) | C101: =C52 -> 740
B102: Implied upside / (downside) | C102: =C99/C101-1 -> 2.2000181
B104: MARKET-IMPLIED EV/NOPAT TODAY | C104: USDm
B105: Current market cap (spot × diluted shares) | C105: =C52*C50 -> 15525.64
B106: Plus: FY2026E year-end net debt + NCI | C106: =C48 -> 5322.5103
B107: Implied Enterprise Value (today) | C107: =C105+C106 -> 20848.15
B108: FICO market-implied EV/NOPAT (on FY2029E NOPAT) | C108: =C107/C93 -> 14.334357
B110: Multiple gap (Mauboussin − Market) | C110: =C88-C108 -> 15.861184
B111: Implied re-rating headroom | C111: =C88/C108-1 -> 1.1065152

Sheet Charts
B2: Fair Isaac Corporation — Operating Performance (FY2012–FY2025) and Model Forecast (FY2026E–FY2031E)
B3: USDm · fiscal years ended 30 September · Linked to Model. Bars = contribution of each segment to total revenue growth (pp). Adjusted EBITDA = model definition (FICO publishes no EBITDA; excludes SBC). ROIC / RONTA on adjusted EBITA after SBC.
C7: 2012 | D7: 2013 | E7: 2014 | F7: 2015 | G7: 2016 | H7: 2017 | I7: 2018 | J7: 2019 | K7: 2020 | L7: 2021 | M7: 2022 | N7: 2023 | O7: 2024 | P7: 2025 | Q7: 2026E | R7: 2027E | S7: 2028E | T7: 2029E | U7: 2030E | V7: 2031E
B8: Scores contribution to growth (pp) | C8: =IFERROR(Model!I67+0,0) -> 0.011386467 | D8: =IFERROR(Model!N67+0,0) -> 0.0076727137 | E8: =IFERROR(Model!S67+0,0) -> 0.007607836 | F8: =IFERROR(Model!X67+0,0) -> 0.026030913 | G8: =IFERROR(Model!AC67+0,0) -> 0.040597009 | H8: =IFERROR(Model!AH67+0,0) -> 0.028700094 | I8: =IFERROR(Model!AM67+0,0) -> 0.081845674 | J8: =IFERROR(Model!AR67+0,0) -> 0.076058984 | K8: =IFERROR(Model!AW67+0,0) -> 0.092553722 | L8: =IFERROR(Model!BB67+0,0) -> 0.097021232 | M8: =IFERROR(Model!BG67+0,0) -> 0.039874337 | N8: =IFERROR(Model!BL67+0,0) -> 0.048781285 | O8: =IFERROR(Model!BQ67+0,0) -> 0.09634391 | P8: =IFERROR(Model!BV67+0,0) -> 0.1449323 | Q8: =IFERROR(Model!CA67+0,0) -> 0.25685287 | R8: =IFERROR(Model!CB67+0,0) -> 0.089622376 | S8: =IFERROR(Model!CC67+0,0) -> 0.074926889 | T8: =IFERROR(Model!CD67+0,0) -> 0.063708302 | U8: =IFERROR(Model!CE67+0,0) -> 0.057012456 | V8: =IFERROR(Model!CF67+0,0) -> 0.050900318
B9: Software contribution to growth (pp) | C9: =IFERROR(Model!I68+0,0) -> 0.080176477 | D9: =IFERROR(Model!N68+0,0) -> 0.091408778 | E9: =IFERROR(Model!S68+0,0) -> 0.053648963 | F9: =IFERROR(Model!X68+0,0) -> 0.037083088 | G9: =IFERROR(Model!AC68+0,0) -> 0.010161174 | H9: =IFERROR(Model!AH68+0,0) -> 0.028953113 | I9: =IFERROR(Model!AM68+0,0) -> 0.025759278 | J9: =IFERROR(Model!AR68+0,0) -> 0.047535291 | K9: =IFERROR(Model!AW68+0,0) -> 0.023368156 | L9: =IFERROR(Model!BB68+0,0) -> -0.080047151 | M9: =IFERROR(Model!BG68+0,0) -> 0.0062573298 | N9: =IFERROR(Model!BL68+0,0) -> 0.050173169 | O9: =IFERROR(Model!BQ68+0,0) -> 0.03841745 | P9: =IFERROR(Model!BV68+0,0) -> 0.014216961 | Q9: =IFERROR(Model!CA68+0,0) -> 0.013948977 | R9: =IFERROR(Model!CB68+0,0) -> 0.016629526 | S9: =IFERROR(Model!CC68+0,0) -> 0.028471371 | T9: =IFERROR(Model!CD68+0,0) -> 0.030719507 | U9: =IFERROR(Model!CE68+0,0) -> 0.030972326 | V9: =IFERROR(Model!CF68+0,0) -> 0.030483428
C11: =C7 -> 2012 | D11: =D7 -> 2013 | E11: =E7 -> 2014 | F11: =F7 -> 2015 | G11: =G7 -> 2016 | H11: =H7 -> 2017 | I11: =I7 -> 2018 | J11: =J7 -> 2019 | ... V11: =V7 -> 2031E
B12: Adjusted EBITDA | C12: =Model!I183 -> 215.563 | D12: =Model!N183 -> 224.761 | E12: =Model!S183 -> 234.956 | F12: =Model!X183 -> 235.827 | G12: =Model!AC183 -> 258.344 | H12: =Model!AH183 -> 279.021 | I12: =Model!AM183 -> 314.317 | J12: =Model!AR183 -> 370.409 | K12: =Model!AW183 -> 468.254 | L12: =Model!BB183 -> 559.101 | M12: =Model!BG183 -> 676.096 | N12: =Model!BL183 -> 785.714 | O12: =Model!BQ183 -> 910.929 | P12: =Model!BV183 -> 1118.783 | Q12: =Model!CA183 -> 1545.8696 | R12: =Model!CB183 -> 1790.9017 | S12: =Model!CC183 -> 2002.2487 | T12: =Model!CD183 -> 2209.6101 | U12: =Model!CE183 -> 2408.2373 | V12: =Model!CF183 -> 2606.2804
B13: Operating income (GAAP) | C13: =Model!I135 -> 168.358 | D13: =Model!N135 -> 161.593 | E13: =Model!S135 -> 161.868 | F13: =Model!X135 -> 137.505 | G13: =Model!AC135 -> 169.592 | H13: =Model!AH135 -> 177.2 | I13: =Model!AM135 -> 206.437 | J13: =Model!AR135 -> 253.548 | K13: =Model!AW135 -> 295.969 | L13: =Model!BB135 -> 505.489 | M13: =Model!BG135 -> 542.414 | N13: =Model!BL135 -> 642.83 | O13: =Model!BQ135 -> 733.629 | P13: =Model!BV135 -> 924.85 | Q13: =Model!CA135 -> 1301.4976 | R13: =Model!CB135 -> 1549.9963 | S13: =Model!CC135 -> 1743.1919 | T13: =Model!CD135 -> 1927.2243 | U13: =Model!CE135 -> 2102.0616 | V13: =Model!CF135 -> 2276.1636
B14: Adj. EBITDA Margin % | C14: =Model!I225 -> 0.31868077 | D14: =Model!N225 -> 0.30232405 | E14: =Model!S225 -> 0.29779527 | F14: =Model!X225 -> 0.28115444 | G14: =Model!AC225 -> 0.29312105 | H14: =Model!AH225 -> 0.29932448 | I14: =Model!AM225 -> 0.30443062 | J14: =Model!AR225 -> 0.31929526 | K14: =Model!AW225 -> 0.36170844 | L14: =Model!BB225 -> 0.42467582 | M14: =Model!BG225 -> 0.49089576 | N14: =Model!BL225 -> 0.51911755 | O14: =Model!BQ225 -> 0.53037276 | P14: =Model!BV225 -> 0.56195712 | Q14: =Model!CA225 -> 0.61101565 | R14: =Model!CB225 -> 0.63987804 | S14: =Model!CC225 -> 0.64835247 | T14: =Model!CD225 -> 0.65376503 | U14: =Model!CE225 -> 0.6549113 | V14: =Model!CF225 -> 0.65542729
B15: Operating Margin % | C15: =Model!I226 -> 0.24889455 | D15: =Model!N226 -> 0.21735733 | E15: =Model!S226 -> 0.20515979 | F15: =Model!X226 -> 0.16393433 | G15: =Model!AC226 -> 0.19242168 | H15: =Model!AH226 -> 0.19009429 | I15: =Model!AM226 -> 0.19994382 | J15: =Model!AR226 -> 0.21856022 | K15: =Model!AW226 -> 0.22862482 | L15: =Model!BB226 -> 0.3839538 | M15: =Model!BG226 -> 0.39383273 | N15: =Model!BL226 -> 0.42471476 | O15: =Model!BQ226 -> 0.42714288 | P15: =Model!BV226 -> 0.46454588 | Q15: =Model!CA226 -> 0.51442592 | R15: =Model!CB226 -> 0.55380404 | S15: =Model!CC226 -> 0.56446673 | T15: =Model!CD226 -> 0.57021455 | U15: =Model!CE226 -> 0.57164794 | V15: =Model!CF226 -> 0.57240953
C17: =C7 -> 2012 | D17: =D7 -> 2013 | E17: =E7 -> 2014 | F17: =F7 -> 2015 | G17: =G7 -> 2016 | H17: =H7 -> 2017 | I17: =I7 -> 2018 | J17: =J7 -> 2019 | ... V17: =V7 -> 2031E
B18: ROIC | C18: =IFERROR(Model!I366+0,NA()) -> 0.1421842 | D18: =IFERROR(Model!N366+0,NA()) -> 0.13875265 | E18: =IFERROR(Model!S366+0,NA()) -> 0.14034321 | F18: =IFERROR(Model!X366+0,NA()) -> 0.13184677 | G18: =IFERROR(Model!AC366+0,NA()) -> 0.14614861 | H18: =IFERROR(Model!AH366+0,NA()) -> 0.1480652 | I18: =IFERROR(Model!AM366+0,NA()) -> 0.1762019 | J18: =IFERROR(Model!AR366+0,NA()) -> 0.19810146 | K18: =IFERROR(Model!AW366+0,NA()) -> 0.25943412 | L18: =IFERROR(Model!BB366+0,NA()) -> 0.35539185 | M18: =IFERROR(Model!BG366+0,NA()) -> 0.46817697 | N18: =IFERROR(Model!BL366+0,NA()) -> 0.47786597 | O18: =IFERROR(Model!BQ366+0,NA()) -> 0.53542472 | P18: =IFERROR(Model!BV366+0,NA()) -> 0.63913839 | Q18: =IFERROR(Model!CA366+0,NA()) -> 0.87741218 | R18: =IFERROR(Model!CB366+0,NA()) -> 1.0020601 | S18: =IFERROR(Model!CC366+0,NA()) -> 1.0887916 | T18: =IFERROR(Model!CD366+0,NA()) -> 1.1657053 | U18: =IFERROR(Model!CE366+0,NA()) -> 1.2301435 | V18: =IFERROR(Model!CF366+0,NA()) -> 1.287781
B19: RONTA | C19: =IFERROR(Model!I377+0,NA()) -> 0.61602206 | D19: =IFERROR(Model!N377+0,NA()) -> 0.66598234 | E19: =IFERROR(Model!S377+0,NA()) -> 0.63664849 | F19: =IFERROR(Model!X377+0,NA()) -> 0.57219743 | G19: =IFERROR(Model!AC377+0,NA()) -> 0.61130826 | H19: =IFERROR(Model!AH377+0,NA()) -> 0.54322537 | I19: =IFERROR(Model!AM377+0,NA()) -> 0.64069625 | J19: =IFERROR(Model!AR377+0,NA()) -> 0.56972446 | K19: =IFERROR(Model!AW377+0,NA()) -> 0.54747729 | L19: =IFERROR(Model!BB377+0,NA()) -> 0.70084186 | M19: =IFERROR(Model!BG377+0,NA()) -> 1.1073673 | N19: =IFERROR(Model!BL377+0,NA()) -> 0.99127907 | O19: =IFERROR(Model!BQ377+0,NA()) -> 0.9869362 | P19: =IFERROR(Model!BV377+0,NA()) -> 1.1282412 | Q19: =IFERROR(Model!CA377+0,NA()) -> 1.5130022 | R19: =IFERROR(Model!CB377+0,NA()) -> 1.6933493 | S19: =IFERROR(Model!CC377+0,NA()) -> 1.802669 | T19: =IFERROR(Model!CD377+0,NA()) -> 1.8916103 | U19: =IFERROR(Model!CE377+0,NA()) -> 1.9571805 | V19: =IFERROR(Model!CF377+0,NA()) -> 2.009921
B20: Adj. EBITDA margin % | C20: =IFERROR(Model!I225+0,NA()) -> 0.31868077 | D20: =IFERROR(Model!N225+0,NA()) -> 0.30232405 | E20: =IFERROR(Model!S225+0,NA()) -> 0.29779527 | F20: =IFERROR(Model!X225+0,NA()) -> 0.28115444 | G20: =IFERROR(Model!AC225+0,NA()) -> 0.29312105 | H20: =IFERROR(Model!AH225+0,NA()) -> 0.29932448 | I20: =IFERROR(Model!AM225+0,NA()) -> 0.30443062 | J20: =IFERROR(Model!AR225+0,NA()) -> 0.31929526 | K20: =IFERROR(Model!AW225+0,NA()) -> 0.36170844 | L20: =IFERROR(Model!BB225+0,NA()) -> 0.42467582 | M20: =IFERROR(Model!BG225+0,NA()) -> 0.49089576 | N20: =IFERROR(Model!BL225+0,NA()) -> 0.51911755 | O20: =IFERROR(Model!BQ225+0,NA()) -> 0.53037276 | P20: =IFERROR(Model!BV225+0,NA()) -> 0.56195712 | Q20: =IFERROR(Model!CA225+0,NA()) -> 0.61101565 | R20: =IFERROR(Model!CB225+0,NA()) -> 0.63987804 | S20: =IFERROR(Model!CC225+0,NA()) -> 0.64835247 | T20: =IFERROR(Model!CD225+0,NA()) -> 0.65376503 | U20: =IFERROR(Model!CE225+0,NA()) -> 0.6549113 | V20: =IFERROR(Model!CF225+0,NA()) -> 0.65542729
B21: FCF margin % | C21: =IFERROR(Model!I263+0,NA()) -> 0.15413876 | D21: =IFERROR(Model!N263+0,NA()) -> 0.1506139 | E21: =IFERROR(Model!S263+0,NA()) -> 0.20588985 | F21: =IFERROR(Model!X263+0,NA()) -> 0.12873205 | G21: =IFERROR(Model!AC263+0,NA()) -> 0.18523956 | H21: =IFERROR(Model!AH263+0,NA()) -> 0.22079258 | I21: =IFERROR(Model!AM263+0,NA()) -> 0.18572169 | J21: =IFERROR(Model!AR263+0,NA()) -> 0.2037518 | K21: =IFERROR(Model!AW263+0,NA()) -> 0.26489809 | L21: =IFERROR(Model!BB263+0,NA()) -> 0.3161691 | M21: =IFERROR(Model!BG263+0,NA()) -> 0.36552092 | N21: =IFERROR(Model!BL263+0,NA()) -> 0.30701057 | O21: =IFERROR(Model!BQ263+0,NA()) -> 0.35365578 | P21: =IFERROR(Model!BV263+0,NA()) -> 0.37139561 | Q21: =IFERROR(Model!CA263+0,NA()) -> 0.39619595 | R21: =IFERROR(Model!CB263+0,NA()) -> 0.39907874 | S21: =IFERROR(Model!CC263+0,NA()) -> 0.41451999 | T21: =IFERROR(Model!CD263+0,NA()) -> 0.41033032 | U21: =IFERROR(Model!CE263+0,NA()) -> 0.41008802 | V21: =IFERROR(Model!CF263+0,NA()) -> 0.40992126
