Workbook

Sheet Model
AC1: SCENARIO SWITCH ▼ (Bull / Base / Bear) — drives all scenario-linked forecast drivers
B2: General Electric Company, operating as GE Aerospace (NYSE: GE) — 3-Statement Financial Model | AC2: Base
B3: US GAAP · USD millions (per-share data in USD; shares in millions) · Calendar fiscal years · Source: General Electric Company Forms 10-K / 10-Q, Form 8-K earnings releases (Ex. 99.1), the 11-Apr-2024 supplemental GE Aerospace financial information (8-K Ex. 99.1) and the CPP deal 8-K (8-Sep-2026), SEC EDGAR (CIK 40545); XBRL company facts (cross-check, dividends per share); investor-relations releases are the same documents as filed on EDGAR
B4: Basis notes: GE Aerospace continuing operations — GE HealthCare spun 3-Jan-2023 and GE Vernova spun 2-Apr-2024 (both discontinued operations). FY2022–23 and the 2023 quarters are the recast comparatives first presented on that basis (2024 10-Qs / 10-K / releases; Q1-23 = H1-23 − Q2-23, Q4 = FY − 9M); Q1-24 from the Q1-25 10-Q; Q2-24+ as originally reported. Balance sheet from 31-Dec-2023; cash flow from Q3-23. Segments CES / DPT (Jan-2026 recast: Aeroderivative to DPT; recast 2025 in memo rows). Run-off insurance and U.S. tax equity outside operating profit. Pending: CPP ($11.75bn, close 2H-27, toggle). Q3/Q4-26E calibrated to the 16-Jul-2026 FY26 guidance.
AE5: Forecast | AF5: Historical | AG5: Historical | AH5: Historical
B6: (USDm) | C6: 2022 | D6: Q1/23 | E6: Q2/23 | F6: Q3/23 | G6: Q4/23 | H6: 2023 | I6: Q1/24 | J6: Q2/24 | K6: Q3/24 | L6: Q4/24 | M6: 2024 | N6: Q1/25 | O6: Q2/25 | P6: Q3/25 | Q6: Q4/25 | R6: 2025 | S6: Q1/26 | T6: Q2/26 | U6: Q3/26E | V6: Q4/26E | W6: 2026E | X6: 2027E | Y6: 2028E | Z6: 2029E | AA6: 2030E | AB6: 2031E | AC6: Modelling Notes | AE6: 5Y CAGR | AF6: 3Y CAGR | AG6: 2Y CAGR | AH6: 1Y / level
AE7: 26-'31 | AF7: 22-'25 | AG7: 23-'25 | AH7: '25-'26E
B8: SEGMENT BUILD — COMMERCIAL ENGINES & SERVICES · DEFENSE & PROPULSION TECHNOLOGIES (revenue × segment operating profit margin) | AC8: SEGMENT BUILD — modelling logic (CES services + equipment, DPT → segment revenue × margin → + adjusted Corporate & Other operating costs = operating profit → GAAP P&L)
AK9: SCENARIO INPUT TABLE — driver assumptions per Bull / Base / Bear | AL9: Bull | AM9: Base | AN9: Bear | AO9: Bull / Bear = Base + Δ (Δ inputs on each block header). Outlook block = high / mid / low end of the FY26 guidance ranges.
B10: Commercial Engines & Services (CES) — commercial and business-jet engines (CFM LEAP / CFM56, GE9X, GEnx, GE90, Passport), services (MRO, spare parts); Aeroderivative moved to DPT from Q1-26 | AC10: CES — modelling logic
B11: CES services revenue (internal shop visits, spare parts, long-term service agreements) | C11: 13688 | D11: 3933 | E11: 4130 | F11: 4853 | G11: 4770 | H11: 17686 | I11: 4390 | J11: 4705 | K11: 5317 | L11: 5363 | M11: 19775 | N11: 5118 | O11: 6059 | P11: 6820 | Q11: 7012 | R11: 25010 | S11: 6817 | T11: 7434 | U11: =($W$14-SUM(S11:T11))*P11/(P11+Q11) -> 7480.45 | V11: =($W$14-SUM(S11:T11))*Q11/(P11+Q11) -> 7691.0434 | W11: =SUM(S11:V11) -> 29422.493 | X11: =W11*(1+X12) -> 33541.642 | Y11: =X11*(1+Y12) -> 37231.223 | Z11: =Y11*(1+Z12) -> 40582.033 | AA11: =Z11*(1+AA12) -> 43828.596 | AB11: =AA11*(1+AB12) -> 46896.598 | AC11: History as reported in each period (Jan-2026 structure from Q1-26). Q3/Q4-26E = (FY26E target − H1-26) × Q3/Q4-25 share of 2H-25. 2027E+: prior year × (1 + scenario growth). | AE11: =IFERROR((AB11/W11)^(1/5)-1,"n/m") -> 0.09772201 | AF11: =IFERROR((R11/C11)^(1/3)-1,"n/m") -> 0.22252542 | AG11: =IFERROR((R11/H11)^(1/2)-1,"n/m") -> 0.18916477 | AH11: =IFERROR(W11/R11-1,"n/m") -> 0.17642916 | AK11: FY26 guidance — Q2-26 release (16-Jul-2026) | AL11: High | AM11: Mid | AN11: Low | AO11: Adjusted revenue growth high-teens (prior LDD); operating profit $10.55–10.75B; adjusted EPS $7.65–7.85; FCF $8.9–9.2B. CES revenue ~+20% (services low 20s, equipment ~20%), CES operating profit $10.25–10.35B; DPT revenue LDD, operating profit $1.6–1.7B; Corporate cost & eliminations $(1.2)–(1.3)B (22-Jan-2026). Numeric mapping of qualitative growth guides (high-teens, ~20%, low 20s, LDD) = assumption.
B12: y/y % (2026: vs the recast prior year) | H12: =IF(AND(ISNUMBER(H11),ISNUMBER(C11)),IFERROR(H11/C11-1,""),"") -> 0.29208065 | I12: =IF(AND(ISNUMBER(I11),ISNUMBER(D11)),IFERROR(I11/D11-1,""),"") -> 0.11619629 | J12: =IF(AND(ISNUMBER(J11),ISNUMBER(E11)),IFERROR(J11/E11-1,""),"") -> 0.13922518 | K12: =IF(AND(ISNUMBER(K11),ISNUMBER(F11)),IFERROR(K11/F11-1,""),"") -> 0.095610962 | L12: =IF(AND(ISNUMBER(L11),ISNUMBER(G11)),IFERROR(L11/G11-1,""),"") -> 0.12431866 | M12: =IF(AND(ISNUMBER(M11),ISNUMBER(H11)),IFERROR(M11/H11-1,""),"") -> 0.11811602 | N12: =IF(AND(ISNUMBER(N11),ISNUMBER(I11)),IFERROR(N11/I11-1,""),"") -> 0.16583144 | O12: =IF(AND(ISNUMBER(O11),ISNUMBER(J11)),IFERROR(O11/J11-1,""),"") -> 0.28777896 | ... R12: =IF(AND(ISNUMBER(R11),ISNUMBER(M11)),IFERROR(R11/M11-1,""),"") -> 0.26472819 | S12: =IF(AND(ISNUMBER(S11),ISNUMBER(N11)),IFERROR(S11/IF(ISNUMBER(N13),N13,N11)-1,""),"") -> 0.38697864 | T12: =IF(AND(ISNUMBER(T11),ISNUMBER(O11)),IFERROR(T11/IF(ISNUMBER(O13),O13,O11)-1,""),"") -> 0.26407074 | U12: =IF(AND(ISNUMBER(U11),ISNUMBER(P11)),IFERROR(U11/P11-1,""),"") -> 0.096840182 | V12: =IF(AND(ISNUMBER(V11),ISNUMBER(Q11)),IFERROR(V11/Q11-1,""),"") -> 0.096840182 | W12: =$W$11/$R$13-1 -> 0.21580551 | X12: =CHOOSE(MATCH($AC$2,{"Bull","Base","Bear"},0),$AL$35,$AM$35,$AN$35) -> 0.14 | Y12: =CHOOSE(MATCH($AC$2,{"Bull","Base","Bear"},0),$AL$36,$AM$36,$AN$36) -> 0.11 | Z12: =CHOOSE(MATCH($AC$2,{"Bull","Base","Bear"},0),$AL$37,$AM$37,$AN$37) -> 0.09 | AA12: =CHOOSE(MATCH($AC$2,{"Bull","Base","Bear"},0),$AL$38,$AM$38,$AN$38) -> 0.08 | AB12: =CHOOSE(MATCH($AC$2,{"Bull","Base","Bear"},0),$AL$39,$AM$39,$AN$39) -> 0.07 | AC12: 2026 quarters and FY2026E vs the Jan-2026 recast comparatives (memo row). 2027E+: scenario lever. | AK12: FY26 adjusted revenue growth (high-teens → 19 / 18 / 17%) | AL12: 0.19 | AM12: 0.18 | AN12: 0.17 | AO12: Guided "high-teens" (raised from LDD, 16-Jul-2026); numeric mapping is an assumption. Drives the revenue calibration.
B13: Memo: on the Jan-2026 segment structure (Q1–Q2/25 recast in the 2026 10-Qs; FY2025 revised, $bn estimate) | N13: 4915 | O13: 5881 | R13: 24200 | AK13: FY26 operating profit ($m) | AL13: 10750 | AM13: 10650 | AN13: 10550 | AO13: Guided $10.55–10.75B. Drives the 2H segment-margin calibration.
B14: FY26E target = FY2025 revised × (1 + guided growth + calibration Δ) | W14: =$R$13*(1+W15+W119) -> 29422.493 | AK14: FY26 adjusted EPS ($) — memo | AL14: 7.85 | AM14: 7.75 | AN14: 7.65 | AO14: Guided $7.65–7.85 (information row; compare the model).
B15: FY26 guided growth (scenario end-point; before calibration) | W15: =CHOOSE(MATCH($AC$2,{"Bull","Base","Bear"},0),$AL$16,$AM$16,$AN$16) -> 0.22 | AK15: FY26 free cash flow ($m) | AL15: 9200 | AM15: 9050 | AN15: 8900 | AO15: Guided $8.9–9.2B. Drives the 2026E customer-advances calibration (FCF bridge section).
B16: CES equipment revenue (install and spare engines) | C16: 5125 | D16: 1299 | E16: 1607 | F16: 1604 | G16: 1659 | H16: 6169 | I16: 1706 | J16: 1427 | K16: 1686 | L16: 2287 | M16: 7106 | N16: 1858 | O16: 1931 | P16: 2059 | Q16: 2455 | R16: 8304 | S16: 2102 | T16: 2297 | U16: =($W$19-SUM(S16:T16))*P16/(P16+Q16) -> 2193.4245 | V16: =($W$19-SUM(S16:T16))*Q16/(P16+Q16) -> 2615.2779 | W16: =SUM(S16:V16) -> 9207.7024 | X16: =W16*(1+X17) -> 10312.627 | Y16: =X16*(1+Y17) -> 11343.889 | Z16: =Y16*(1+Z17) -> 12251.401 | AA16: =Z16*(1+AA17) -> 12986.485 | AB16: =AA16*(1+AB17) -> 13635.809 | AE16: =IFERROR((AB16/W16)^(1/5)-1,"n/m") -> 0.081697748 | AF16: =IFERROR((R16/C16)^(1/3)-1,"n/m") -> 0.17453102 | AG16: =IFERROR((R16/H16)^(1/2)-1,"n/m") -> 0.16020915 | AH16: =IFERROR(W16/R16-1,"n/m") -> 0.10882737 | AK16: FY26 CES services revenue growth (low 20s → 23 / 22 / 21%) | AL16: 0.23 | AM16: 0.22 | AN16: 0.21 | AO16: Guided "low 20s" on the FY2025 revised base $24.2B (assumption mapping).
B17: y/y % (2026: vs the recast prior year) | H17: =IF(AND(ISNUMBER(H16),ISNUMBER(C16)),IFERROR(H16/C16-1,""),"") -> 0.20370732 | I17: =IF(AND(ISNUMBER(I16),ISNUMBER(D16)),IFERROR(I16/D16-1,""),"") -> 0.31331794 | J17: =IF(AND(ISNUMBER(J16),ISNUMBER(E16)),IFERROR(J16/E16-1,""),"") -> -0.11200996 | K17: =IF(AND(ISNUMBER(K16),ISNUMBER(F16)),IFERROR(K16/F16-1,""),"") -> 0.051122195 | L17: =IF(AND(ISNUMBER(L16),ISNUMBER(G16)),IFERROR(L16/G16-1,""),"") -> 0.37854129 | M17: =IF(AND(ISNUMBER(M16),ISNUMBER(H16)),IFERROR(M16/H16-1,""),"") -> 0.15188847 | N17: =IF(AND(ISNUMBER(N16),ISNUMBER(I16)),IFERROR(N16/I16-1,""),"") -> 0.089097304 | O17: =IF(AND(ISNUMBER(O16),ISNUMBER(J16)),IFERROR(O16/J16-1,""),"") -> 0.35318851 | ... R17: =IF(AND(ISNUMBER(R16),ISNUMBER(M16)),IFERROR(R16/M16-1,""),"") -> 0.16858992 | S17: =IF(AND(ISNUMBER(S16),ISNUMBER(N16)),IFERROR(S16/IF(ISNUMBER(N18),N18,N16)-1,""),"") -> 0.20182962 | T17: =IF(AND(ISNUMBER(T16),ISNUMBER(O16)),IFERROR(T16/IF(ISNUMBER(O18),O18,O16)-1,""),"") -> 0.30141643 | U17: =IF(AND(ISNUMBER(U16),ISNUMBER(P16)),IFERROR(U16/P16-1,""),"") -> 0.065286319 | V17: =IF(AND(ISNUMBER(V16),ISNUMBER(Q16)),IFERROR(V16/Q16-1,""),"") -> 0.065286319 | W17: =$W$16/$R$18-1 -> 0.19580551 | X17: =CHOOSE(MATCH($AC$2,{"Bull","Base","Bear"},0),$AL$41,$AM$41,$AN$41) -> 0.12 | Y17: =CHOOSE(MATCH($AC$2,{"Bull","Base","Bear"},0),$AL$42,$AM$42,$AN$42) -> 0.1 | Z17: =CHOOSE(MATCH($AC$2,{"Bull","Base","Bear"},0),$AL$43,$AM$43,$AN$43) -> 0.08 | AA17: =CHOOSE(MATCH($AC$2,{"Bull","Base","Bear"},0),$AL$44,$AM$44,$AN$44) -> 0.06 | AB17: =CHOOSE(MATCH($AC$2,{"Bull","Base","Bear"},0),$AL$45,$AM$45,$AN$45) -> 0.05 | AK17: FY26 CES equipment revenue growth (~20% → 21 / 20 / 19%) | AL17: 0.21 | AM17: 0.2 | AN17: 0.19 | AO17: Guided "~20%" on the FY2025 revised base $7.7B (assumption mapping).
B18: Memo: on the Jan-2026 segment structure (Q1–Q2/25 recast in the 2026 10-Qs; FY2025 revised, $bn estimate) | N18: 1749 | O18: 1765 | R18: 7700 | AK18: FY26 DPT revenue growth (LDD → 12 / 11 / 10%) | AL18: 0.12 | AM18: 0.11 | AN18: 0.1 | AO18: Guided "low double digits" on the FY2025 revised base $12.2B (assumption mapping).
B19: FY26E target = FY2025 revised × (1 + guided growth + calibration Δ) | W19: =$R$18*(1+W20+W119) -> 9207.7024 | AK19: FY26 CES operating profit ($m) | AL19: 10350 | AM19: 10300 | AN19: 10250 | AO19: Guided $10.25–10.35B.
B20: FY26 guided growth (scenario end-point; before calibration) | W20: =CHOOSE(MATCH($AC$2,{"Bull","Base","Bear"},0),$AL$17,$AM$17,$AN$17) -> 0.2 | AK20: FY26 DPT operating profit ($m) | AL20: 1700 | AM20: 1650 | AN20: 1600 | AO20: Guided $1.6–1.7B.
B21: CES — segment revenue | C21: =C11+C16 -> 18813 | D21: =D11+D16 -> 5232 | E21: =E11+E16 -> 5737 | F21: =F11+F16 -> 6457 | G21: =G11+G16 -> 6429 | H21: =H11+H16 -> 23855 | I21: =I11+I16 -> 6096 | J21: =J11+J16 -> 6132 | ... AB21: =AB11+AB16 -> 60532.406 | AE21: =IFERROR((AB21/W21)^(1/5)-1,"n/m") -> 0.093987112 | AF21: =IFERROR((R21/C21)^(1/3)-1,"n/m") -> 0.20982599 | AG21: =IFERROR((R21/H21)^(1/2)-1,"n/m") -> 0.18174475 | AH21: =IFERROR(W21/R21-1,"n/m") -> 0.15957843 | AK21: FY26 Corporate cost & eliminations ($m) | AL21: -1200 | AM21: -1250 | AN21: -1300 | AO21: Corporate cost & eliminations (adjusted Corporate & Other operating costs): $(1.2)-(1.3)B per the Q4-25 release (22-Jan-2026); not restated in the Q1-26 / Q2-26 releases. The 16-Jul-2026 total and segment ranges imply about $(1.3)B at the mid-points.
B22: CES revenue y/y % (2026: vs recast prior year) | H22: =IF(AND(ISNUMBER(H21),ISNUMBER(C21)),IFERROR(H21/C21-1,""),"") -> 0.26800617 | I22: =IF(AND(ISNUMBER(I21),ISNUMBER(D21)),IFERROR(I21/D21-1,""),"") -> 0.16513761 | J22: =IF(AND(ISNUMBER(J21),ISNUMBER(E21)),IFERROR(J21/E21-1,""),"") -> 0.068851316 | K22: =IF(AND(ISNUMBER(K21),ISNUMBER(F21)),IFERROR(K21/F21-1,""),"") -> 0.084559393 | L22: =IF(AND(ISNUMBER(L21),ISNUMBER(G21)),IFERROR(L21/G21-1,""),"") -> 0.18992067 | M22: =IF(AND(ISNUMBER(M21),ISNUMBER(H21)),IFERROR(M21/H21-1,""),"") -> 0.12684972 | N22: =IF(AND(ISNUMBER(N21),ISNUMBER(I21)),IFERROR(N21/I21-1,""),"") -> 0.14435696 | O22: =IF(AND(ISNUMBER(O21),ISNUMBER(J21)),IFERROR(O21/J21-1,""),"") -> 0.30300065 | ... R22: =IF(AND(ISNUMBER(R21),ISNUMBER(M21)),IFERROR(R21/M21-1,""),"") -> 0.23931401 | S22: =IF(AND(ISNUMBER(S21),ISNUMBER(N21)),IFERROR(S21/IF(ISNUMBER(N23),N23,N21)-1,""),"") -> 0.33858622 | T22: =IF(AND(ISNUMBER(T21),ISNUMBER(O21)),IFERROR(T21/IF(ISNUMBER(O23),O23,O21)-1,""),"") -> 0.2726916 | U22: =IF(AND(ISNUMBER(U21),ISNUMBER(P21)),IFERROR(U21/P21-1,""),"") -> 0.089522983 | V22: =IF(AND(ISNUMBER(V21),ISNUMBER(Q21)),IFERROR(V21/Q21-1,""),"") -> 0.088657575 | W22: =$W$21/$R$23-1 -> 0.21097793 | X22: =IF(AND(ISNUMBER(X21),ISNUMBER(W21)),IFERROR(X21/W21-1,""),"") -> 0.1352329 | Y22: =IF(AND(ISNUMBER(Y21),ISNUMBER(X21)),IFERROR(Y21/X21-1,""),"") -> 0.10764843 | Z22: =IF(AND(ISNUMBER(Z21),ISNUMBER(Y21)),IFERROR(Z21/Y21-1,""),"") -> 0.08766467 | AA22: =IF(AND(ISNUMBER(AA21),ISNUMBER(Z21)),IFERROR(AA21/Z21-1,""),"") -> 0.075362255 | AB22: =IF(AND(ISNUMBER(AB21),ISNUMBER(AA21)),IFERROR(AB21/AA21-1,""),"") -> 0.065428508 | AK22: 2H-26E share repurchases ($m) | AL22: 5000 | AM22: 4000 | AN22: 3000 | AO22: H1-26 $4,527m (Q2 $2,012m at $292.17); ~$18.0bn left on the $20bn authorization (Dec-2025) at 30-Jun-2026. Scenario input (assumption).
B23: Memo: CES revenue on the Jan-2026 structure (recast) | N23: 6663 | O23: 7646 | R23: 31900
B24: Memo: CES segment revenue as reported | C24: 18813 | D24: 5232 | E24: 5737 | F24: 6457 | G24: 6429 | H24: 23855 | I24: 6095 | J24: 6132 | K24: 7003 | L24: 7650 | M24: 26881 | N24: 6977 | O24: 7990 | P24: 8880 | Q24: 9468 | R24: 33314 | S24: 8920 | T24: 9731 | AK24: Q3/Q4-26E and FY26 point estimates (all cases)
B25: Check: services + equipment vs CES segment revenue (should be 0) | C25: =IF(ISNUMBER(C24),IF(ABS(C21-C24)<=1.01,0,ROUND(C21-C24,0)),"") -> 0 | D25: =IF(ISNUMBER(D24),IF(ABS(D21-D24)<=1.01,0,ROUND(D21-D24,0)),"") -> 0 | E25: =IF(ISNUMBER(E24),IF(ABS(E21-E24)<=1.01,0,ROUND(E21-E24,0)),"") -> 0 | F25: =IF(ISNUMBER(F24),IF(ABS(F21-F24)<=1.01,0,ROUND(F21-F24,0)),"") -> 0 | G25: =IF(ISNUMBER(G24),IF(ABS(G21-G24)<=1.01,0,ROUND(G21-G24,0)),"") -> 0 | H25: =IF(ISNUMBER(H24),IF(ABS(H21-H24)<=1.01,0,ROUND(H21-H24,0)),"") -> 0 | I25: =IF(ISNUMBER(I24),IF(ABS(I21-I24)<=1.01,0,ROUND(I21-I24,0)),"") -> 0 | J25: =IF(ISNUMBER(J24),IF(ABS(J21-J24)<=1.01,0,ROUND(J21-J24,0)),"") -> 0 | ... T25: =IF(ISNUMBER(T24),IF(ABS(T21-T24)<=1.01,0,ROUND(T21-T24,0)),"") -> 0 | AK25: Q3/Q4-26E interest and other financial charges ($m per quarter) | AM25: 222 | AO25: H1-26 $444m (run-rate).
B26: CES segment operating profit | C26: 4164 | D26: 1214 | E26: 1389 | F26: 1545 | G26: 1495 | H26: 5643 | I26: 1419 | J26: 1679 | K26: 1799 | L26: 2158 | M26: 7055 | N26: 1920 | O26: 2232 | P26: 2436 | Q26: 2273 | R26: 8861 | S26: 2356 | T26: 2657 | U26: =U21*U27 -> 2541.7847 | V26: =V21*V27 -> 2707.9583 | W26: =SUM(S26:V26) -> 10262.743 | X26: =X21*X27 -> 11752.944 | Y26: =Y21*Y27 -> 13212.431 | Z26: =Z21*Z27 -> 14582.028 | AA26: =AA21*AA27 -> 15908.223 | AB26: =AB21*AB27 -> 17070.139 | AC26: Segment profit as reported (company measure; after amortization and stock-based compensation). Forecast = segment revenue × margin. | AE26: =IFERROR((AB26/W26)^(1/5)-1,"n/m") -> 0.10712006 | AF26: =IFERROR((R26/C26)^(1/3)-1,"n/m") -> 0.28624591 | AG26: =IFERROR((R26/H26)^(1/2)-1,"n/m") -> 0.25310177 | AH26: =IFERROR(W26/R26-1,"n/m") -> 0.15819242 | AK26: Q3/Q4-26E adjusted effective tax rate | AM26: 0.165 | AO26: H1-26 15.7% (Q2 16.7%); FY2025 17.3%. Not guided in the releases — assumption.
B27: CES operating profit margin % | C27: =IF(AND(ISNUMBER(C26),ISNUMBER(C21)),IFERROR(C26/C21,""),"") -> 0.22133631 | D27: =IF(AND(ISNUMBER(D26),ISNUMBER(D21)),IFERROR(D26/D21,""),"") -> 0.23203364 | E27: =IF(AND(ISNUMBER(E26),ISNUMBER(E21)),IFERROR(E26/E21,""),"") -> 0.2421126 | F27: =IF(AND(ISNUMBER(F26),ISNUMBER(F21)),IFERROR(F26/F21,""),"") -> 0.23927521 | G27: =IF(AND(ISNUMBER(G26),ISNUMBER(G21)),IFERROR(G26/G21,""),"") -> 0.23254005 | H27: =IF(AND(ISNUMBER(H26),ISNUMBER(H21)),IFERROR(H26/H21,""),"") -> 0.23655418 | I27: =IF(AND(ISNUMBER(I26),ISNUMBER(I21)),IFERROR(I26/I21,""),"") -> 0.23277559 | J27: =IF(AND(ISNUMBER(J26),ISNUMBER(J21)),IFERROR(J26/J21,""),"") -> 0.27380952 | ... T27: =IF(AND(ISNUMBER(T26),ISNUMBER(T21)),IFERROR(T26/T21,""),"") -> 0.27304491 | U27: =$W$28+$W$123 -> 0.26274733 | V27: =$W$28+$W$123 -> 0.26274733 | W27: =IF(AND(ISNUMBER(W26),ISNUMBER(W21)),IFERROR(W26/W21,""),"") -> 0.26566635 | X27: =CHOOSE(MATCH($AC$2,{"Bull","Base","Bear"},0),$AL$53,$AM$53,$AN$53) -> 0.268 | Y27: =CHOOSE(MATCH($AC$2,{"Bull","Base","Bear"},0),$AL$54,$AM$54,$AN$54) -> 0.272 | Z27: =CHOOSE(MATCH($AC$2,{"Bull","Base","Bear"},0),$AL$55,$AM$55,$AN$55) -> 0.276 | AA27: =CHOOSE(MATCH($AC$2,{"Bull","Base","Bear"},0),$AL$56,$AM$56,$AN$56) -> 0.28 | AB27: =CHOOSE(MATCH($AC$2,{"Bull","Base","Bear"},0),$AL$57,$AM$57,$AN$57) -> 0.282 | AC27: Q3/Q4-26E: 2H margin implied by the CES operating-profit guide end-point + operating-profit calibration Δ (Group block). 2027E+: scenario lever. | AE27: =IFERROR(AVERAGE(X27,Y27,Z27,AA27,AB27),"n/m") -> 0.2756 | AF27: =IFERROR(AVERAGE(H27,M27,R27),"n/m") -> 0.25499716 | AG27: =IFERROR(AVERAGE(M27,R27),"n/m") -> 0.26421865 | AH27: =IFERROR(W27+0,"n/m") -> 0.26566635 | AK27: Tax rate on adjusting items | AM27: 0.21 | AO27: H1-26 company tax effects ~21% (non-operating benefit, separation, restructuring).
B28: 2H-26E margin before calibration = (CES operating-profit guide − H1-26) ÷ 2H-26E revenue | W28: =(CHOOSE(MATCH($AC$2,{"Bull","Base","Bear"},0),$AL$19,$AM$19,$AN$19)-SUM(S26:T26))/SUM(U21:V21) -> 0.26461202 | AK28: 2H-26E capex % of adjusted revenue | AM28: 0.028 | AO28: H1-26 2.7%; FY2025 3.0% (not guided).
B29: Memo: CES operating profit on the Jan-2026 structure (recast) | N29: 1910 | O29: 2208 | R29: 8600 | AK29: 2H-26E provision less cash taxes paid ($m) | AM29: 400 | AO29: H1-26 $517m; FY2025 $666m.
B30: Incremental margin (Δ profit / Δ revenue) | H30: =IFERROR((H26-C26)/(H21-C21),"") -> 0.29333598 | I30: =IFERROR((I26-D26)/(I21-D21),"") -> 0.23726852 | J30: =IFERROR((J26-E26)/(J21-E21),"") -> 0.73417722 | K30: =IFERROR((K26-F26)/(K21-F21),"") -> 0.46520147 | L30: =IFERROR((L26-G26)/(L21-G21),"") -> 0.54299754 | M30: =IFERROR((M26-H26)/(M21-H21),"") -> 0.4666226 | N30: =IFERROR((N26-I26)/(N21-I21),"") -> 0.56931818 | O30: =IFERROR((O26-J26)/(O21-J21),"") -> 0.29763186 | ... W30: =IFERROR((W26-R26)/(W21-R21),"") -> 0.26367407 | X30: =IFERROR((X26-W26)/(X21-W21),"") -> 0.28525655 | Y30: =IFERROR((Y26-X26)/(Y21-X21),"") -> 0.309158 | Z30: =IFERROR((Z26-Y26)/(Z21-Y21),"") -> 0.32162842 | AA30: =IFERROR((AA26-Z26)/(AA21-Z21),"") -> 0.33307697 | AB30: =IFERROR((AB26-AA26)/(AB21-AA21),"") -> 0.31256772 | AK30: FY26 pension / OPEB cash contributions & payments ($m) | AM30: 350 | AO30: H1-26: pension line −$526m incl. −$354m non-cash benefit income → ~$170m cash per half.
B31: Operating statistics (memo):
B32: Commercial engine deliveries (units; incl. LEAP) | C32: 1663 | D32: 481 | E32: 543 | F32: 520 | G32: 531 | H32: 2075 | I32: 489 | J32: 402 | K32: 501 | L32: 519 | M32: 1911 | N32: 444 | O32: 551 | P32: 664 | Q32: 727 | R32: 2386 | S32: 640 | T32: 659 | AK32: Maximum net debt / adjusted EBITDA before buybacks (x) — buyback floor 2027E+ | AL32: 1.5 | AM32: 1 | AN32: 0.5 | AO32: Net debt ~$9.8bn at 30-Jun-2026 (borrowings $19.2bn − cash $9.3bn) ≈ 0.8x adjusted EBITDA (model definition); ~1.4x pro forma for CPP ($11.75bn, 2H-27). Target = leverage up to which surplus cash is returned via buybacks (assumption; GE publishes no leverage target in its filings).
B33: of which LEAP engines (units) | C33: 1136 | D33: 366 | E33: 419 | F33: 389 | G33: 396 | H33: 1570 | I33: 367 | J33: 297 | K33: 365 | L33: 378 | M33: 1407 | N33: 319 | O33: 410 | P33: 511 | Q33: 562 | R33: 1802 | S33: 520 | T33: 510
B34: Implied CES equipment revenue per commercial engine ($m; incl. spare engines, other equipment) | C34: =IF(ISNUMBER(C32),IFERROR(C16/C32,""),"") -> 3.0817799 | D34: =IF(ISNUMBER(D32),IFERROR(D16/D32,""),"") -> 2.7006237 | E34: =IF(ISNUMBER(E32),IFERROR(E16/E32,""),"") -> 2.9594843 | F34: =IF(ISNUMBER(F32),IFERROR(F16/F32,""),"") -> 3.0846154 | G34: =IF(ISNUMBER(G32),IFERROR(G16/G32,""),"") -> 3.1242938 | H34: =IF(ISNUMBER(H32),IFERROR(H16/H32,""),"") -> 2.973012 | I34: =IF(ISNUMBER(I32),IFERROR(I16/I32,""),"") -> 3.4887526 | J34: =IF(ISNUMBER(J32),IFERROR(J16/J32,""),"") -> 3.5497512 | ... T34: =IF(ISNUMBER(T32),IFERROR(T16/T32,""),"") -> 3.4855842 | AK34: CES_SV (CES services revenue y/y) | AL34: 0.03 | AM34: Δ → | AN34: -0.05 | AO34: FY26 guided low 20s; H1-26 +32% (shop-visit output, spare parts, price). LEAP shop-visit ramp and a young fleet sustain double-digit growth into 2027–28, normalising to high-single digits (assumption).
B35: Internal shop visit revenue growth % (as reported; n/d for derived Q4s) | C35: 0.22 | E35: 0.12 | F35: 0.02 | H35: 0.1 | I35: 0.21 | J35: 0.14 | K35: -0.01 | M35: 0.03 | N35: 0.11 | O35: 0.22 | P35: 0.33 | R35: 0.24 | S35: 0.35 | T35: 0.25 | AK35: 2027E | AL35: =AM35+$AL$34 -> 0.17 | AM35: 0.14 | AN35: =AM35+$AN$34 -> 0.09
B36: CES orders | D36: 6194 | E36: 6653 | F36: 7603 | G36: 8642 | H36: 29092 | I36: 8315 | J36: 9152 | K36: 9799 | L36: 12947 | M36: 40213 | N36: 9583 | O36: 11690 | P36: 10301 | Q36: 22842 | R36: 54415 | S36: 17331 | T36: 12932 | AK36: 2028E | AL36: =AM36+$AL$34 -> 0.14 | AM36: 0.11 | AN36: =AM36+$AN$34 -> 0.06
B37: CES book-to-bill (orders / revenue) | C37: =IF(ISNUMBER(C36),IFERROR(C36/C21,""),"") | D37: =IF(ISNUMBER(D36),IFERROR(D36/D21,""),"") -> 1.1838685 | E37: =IF(ISNUMBER(E36),IFERROR(E36/E21,""),"") -> 1.1596653 | F37: =IF(ISNUMBER(F36),IFERROR(F36/F21,""),"") -> 1.1774818 | G37: =IF(ISNUMBER(G36),IFERROR(G36/G21,""),"") -> 1.3442215 | H37: =IF(ISNUMBER(H36),IFERROR(H36/H21,""),"") -> 1.2195347 | I37: =IF(ISNUMBER(I36),IFERROR(I36/I21,""),"") -> 1.3640092 | J37: =IF(ISNUMBER(J36),IFERROR(J36/J21,""),"") -> 1.4924984 | ... T37: =IF(ISNUMBER(T36),IFERROR(T36/T21,""),"") -> 1.3289487 | AK37: 2029E | AL37: =AM37+$AL$34 -> 0.12 | AM37: 0.09 | AN37: =AM37+$AN$34 -> 0.04
B38: CES remaining performance obligation (period end) | E38: 137535 | F38: 137535 | H38: 137535 | I38: 153644 | J38: 143004 | K38: 148513 | M38: 153644 | N38: 153752 | O38: 155232 | P38: 157196 | R38: 169822 | S38: 181055 | T38: 179900 | AK38: 2030E | AL38: =AM38+$AL$34 -> 0.11 | AM38: 0.08 | AN38: =AM38+$AN$34 -> 0.03
AK39: 2031E | AL39: =AM39+$AL$34 -> 0.1 | AM39: 0.07 | AN39: =AM39+$AN$34 -> 0.02
B40: Defense & Propulsion Technologies (DPT) — Defense & Systems (military engines, Aeroderivative from Q1-26) · Propulsion & Additive Technologies (Avio Aero, Unison, Dowty, Colibrium Additive) | AC40: DPT — modelling logic | AK40: CES_EQ (CES equipment revenue y/y) | AL40: 0.04 | AM40: Δ → | AN40: -0.08 | AO40: FY26 guided ~20% (LEAP deliveries +41% in H1-26); airframer rate increases (A320neo / 737 MAX), GE9X entry into service (assumption).
B41: DPT — segment revenue | C41: 7989 | D41: 1966 | E41: 2375 | F41: 2205 | G41: 2415 | H41: 8961 | I41: 2312 | J41: 2401 | K41: 2243 | L41: 2523 | M41: 9478 | N41: 2324 | O41: 2563 | P41: 2828 | Q41: 2839 | R41: 10554 | S41: 3214 | T41: 3443 | U41: =($W$44-SUM(S41:T41))*P41/(P41+Q41) -> 3410.2812 | V41: =($W$44-SUM(S41:T41))*Q41/(P41+Q41) -> 3423.5461 | W41: =SUM(S41:V41) -> 13490.827 | X41: =W41*(1+X42) -> 14570.093 | Y41: =X41*(1+Y42) -> 15590 | Z41: =Y41*(1+Z42) -> 16525.4 | AA41: =Z41*(1+AA42) -> 17516.924 | AB41: =AA41*(1+AB42) -> 18392.77 | AC41: Q3/Q4-26E = (FY26E target − H1-26) × Q3/Q4-25 share of 2H-25. 2027E+: prior year × (1 + scenario growth). | AE41: =IFERROR((AB41/W41)^(1/5)-1,"n/m") -> 0.063951209 | AF41: =IFERROR((R41/C41)^(1/3)-1,"n/m") -> 0.097256653 | AG41: =IFERROR((R41/H41)^(1/2)-1,"n/m") -> 0.085251279 | AH41: =IFERROR(W41/R41-1,"n/m") -> 0.27826675 | AK41: 2027E | AL41: =AM41+$AL$40 -> 0.16 | AM41: 0.12 | AN41: =AM41+$AN$40 -> 0.04
B42: y/y % (2026: vs the recast prior year) | H42: =IF(AND(ISNUMBER(H41),ISNUMBER(C41)),IFERROR(H41/C41-1,""),"") -> 0.12166729 | I42: =IF(AND(ISNUMBER(I41),ISNUMBER(D41)),IFERROR(I41/D41-1,""),"") -> 0.17599186 | J42: =IF(AND(ISNUMBER(J41),ISNUMBER(E41)),IFERROR(J41/E41-1,""),"") -> 0.010947368 | K42: =IF(AND(ISNUMBER(K41),ISNUMBER(F41)),IFERROR(K41/F41-1,""),"") -> 0.01723356 | L42: =IF(AND(ISNUMBER(L41),ISNUMBER(G41)),IFERROR(L41/G41-1,""),"") -> 0.044720497 | M42: =IF(AND(ISNUMBER(M41),ISNUMBER(H41)),IFERROR(M41/H41-1,""),"") -> 0.057694454 | N42: =IF(AND(ISNUMBER(N41),ISNUMBER(I41)),IFERROR(N41/I41-1,""),"") -> 0.0051903114 | O42: =IF(AND(ISNUMBER(O41),ISNUMBER(J41)),IFERROR(O41/J41-1,""),"") -> 0.067471887 | ... R42: =IF(AND(ISNUMBER(R41),ISNUMBER(M41)),IFERROR(R41/M41-1,""),"") -> 0.11352606 | S42: =IF(AND(ISNUMBER(S41),ISNUMBER(N41)),IFERROR(S41/IF(ISNUMBER(N43),N43,N41)-1,""),"") -> 0.19125278 | T42: =IF(AND(ISNUMBER(T41),ISNUMBER(O41)),IFERROR(T41/IF(ISNUMBER(O43),O43,O41)-1,""),"") -> 0.15614506 | U42: =IF(AND(ISNUMBER(U41),ISNUMBER(P41)),IFERROR(U41/P41-1,""),"") -> 0.20589858 | V42: =IF(AND(ISNUMBER(V41),ISNUMBER(Q41)),IFERROR(V41/Q41-1,""),"") -> 0.20589858 | W42: =$W$41/$R$43-1 -> 0.10580551 | X42: =CHOOSE(MATCH($AC$2,{"Bull","Base","Bear"},0),$AL$47,$AM$47,$AN$47) -> 0.08 | Y42: =CHOOSE(MATCH($AC$2,{"Bull","Base","Bear"},0),$AL$48,$AM$48,$AN$48) -> 0.07 | Z42: =CHOOSE(MATCH($AC$2,{"Bull","Base","Bear"},0),$AL$49,$AM$49,$AN$49) -> 0.06 | AA42: =CHOOSE(MATCH($AC$2,{"Bull","Base","Bear"},0),$AL$50,$AM$50,$AN$50) -> 0.06 | AB42: =CHOOSE(MATCH($AC$2,{"Bull","Base","Bear"},0),$AL$51,$AM$51,$AN$51) -> 0.05 | AK42: 2028E | AL42: =AM42+$AL$40 -> 0.14 | AM42: 0.1 | AN42: =AM42+$AN$40 -> 0.02
B43: Memo: on the Jan-2026 segment structure (recast) | N43: 2698 | O43: 2978 | R43: 12200 | AK43: 2029E | AL43: =AM43+$AL$40 -> 0.12 | AM43: 0.08 | AN43: =AM43+$AN$40 -> 0
B44: FY26E target = FY2025 revised × (1 + guided growth + calibration Δ) | W44: =$R$43*(1+W45+W119) -> 13490.827 | AK44: 2030E | AL44: =AM44+$AL$40 -> 0.1 | AM44: 0.06 | AN44: =AM44+$AN$40 -> -0.02
B45: FY26 guided growth (scenario end-point; before calibration) | W45: =CHOOSE(MATCH($AC$2,{"Bull","Base","Bear"},0),$AL$18,$AM$18,$AN$18) -> 0.11 | AK45: 2031E | AL45: =AM45+$AL$40 -> 0.09 | AM45: 0.05 | AN45: =AM45+$AN$40 -> -0.03
B46: Memo: Defense & Systems revenue | C46: 5426 | D46: 1280 | E46: 1625 | F46: 1455 | G46: 1567 | H46: 5927 | I46: 1495 | J46: 1529 | K46: 1428 | L46: 1657 | M46: 6109 | N46: 1497 | O46: 1614 | P46: 1777 | Q46: 1687 | R46: 6574 | S46: 2090 | T46: 2213 | AK46: DPT_G (DPT revenue y/y) | AL46: 0.03 | AM46: Δ → | AN46: -0.04 | AO46: FY26 guided LDD; defense budgets, F110 / T408 / XA102 programs, Avio Aero; P&AT growth (assumption).
B47: Memo: Propulsion & Additive Technologies revenue | C47: 2563 | D47: 686 | E47: 750 | F47: 750 | G47: 848 | H47: 3034 | I47: 817 | J47: 871 | K47: 815 | L47: 867 | M47: 3370 | N47: 828 | O47: 949 | P47: 1051 | Q47: 1152 | R47: 3980 | S47: 1124 | T47: 1230 | AK47: 2027E | AL47: =AM47+$AL$46 -> 0.11 | AM47: 0.08 | AN47: =AM47+$AN$46 -> 0.04
B48: Memo: DPT equipment revenue | C48: 3405 | D48: 857 | E48: 1137 | F48: 878 | G48: 1129 | H48: 4000 | I48: 1009 | J48: 1071 | K48: 936 | L48: 1191 | M48: 4208 | N48: 1050 | O48: 1233 | P48: 1434 | Q48: 1411 | R48: 5128 | S48: 1605 | T48: 1744 | AK48: 2028E | AL48: =AM48+$AL$46 -> 0.1 | AM48: 0.07 | AN48: =AM48+$AN$46 -> 0.03
B49: Memo: DPT services revenue | C49: 4584 | D49: 1109 | E49: 1238 | F49: 1327 | G49: 1287 | H49: 4961 | I49: 1303 | J49: 1329 | K49: 1306 | L49: 1331 | M49: 5270 | N49: 1274 | O49: 1329 | P49: 1394 | Q49: 1428 | R49: 5426 | S49: 1608 | T49: 1699 | AK49: 2029E | AL49: =AM49+$AL$46 -> 0.09 | AM49: 0.06 | AN49: =AM49+$AN$46 -> 0.02
B50: Check: D&S + P&AT vs DPT revenue (should be 0) | C50: =IF(ISNUMBER(C46),IF(ABS(C46+C47-C41)<=1.01,0,ROUND(C46+C47-C41,0)),"") -> 0 | D50: =IF(ISNUMBER(D46),IF(ABS(D46+D47-D41)<=1.01,0,ROUND(D46+D47-D41,0)),"") -> 0 | E50: =IF(ISNUMBER(E46),IF(ABS(E46+E47-E41)<=1.01,0,ROUND(E46+E47-E41,0)),"") -> 0 | F50: =IF(ISNUMBER(F46),IF(ABS(F46+F47-F41)<=1.01,0,ROUND(F46+F47-F41,0)),"") -> 0 | G50: =IF(ISNUMBER(G46),IF(ABS(G46+G47-G41)<=1.01,0,ROUND(G46+G47-G41,0)),"") -> 0 | H50: =IF(ISNUMBER(H46),IF(ABS(H46+H47-H41)<=1.01,0,ROUND(H46+H47-H41,0)),"") -> 0 | I50: =IF(ISNUMBER(I46),IF(ABS(I46+I47-I41)<=1.01,0,ROUND(I46+I47-I41,0)),"") -> 0 | J50: =IF(ISNUMBER(J46),IF(ABS(J46+J47-J41)<=1.01,0,ROUND(J46+J47-J41,0)),"") -> 0 | ... T50: =IF(ISNUMBER(T46),IF(ABS(T46+T47-T41)<=1.01,0,ROUND(T46+T47-T41,0)),"") -> 0 | AK50: 2030E | AL50: =AM50+$AL$46 -> 0.09 | AM50: 0.06 | AN50: =AM50+$AN$46 -> 0.02
B51: DPT segment operating profit | C51: 976 | D51: 201 | E51: 201 | F51: 269 | G51: 237 | H51: 908 | I51: 256 | J51: 344 | K51: 220 | L51: 241 | M51: 1061 | N51: 296 | O51: 362 | P51: 386 | Q51: 252 | R51: 1296 | S51: 379 | T51: 475 | U51: =U41*U52 -> 390.86832 | V51: =V41*V52 -> 392.38867 | W51: =SUM(S51:V51) -> 1637.257 | X51: =X41*X52 -> 1894.1121 | Y51: =Y41*Y52 -> 2104.65 | Z51: =Z41*Z52 -> 2313.556 | AA51: =AA41*AA52 -> 2539.954 | AB51: =AB41*AB52 -> 2758.9155 | AE51: =IFERROR((AB51/W51)^(1/5)-1,"n/m") -> 0.1100034 | AF51: =IFERROR((R51/C51)^(1/3)-1,"n/m") -> 0.099136748 | AG51: =IFERROR((R51/H51)^(1/2)-1,"n/m") -> 0.19470196 | AH51: =IFERROR(W51/R51-1,"n/m") -> 0.26331558 | AK51: 2031E | AL51: =AM51+$AL$46 -> 0.08 | AM51: 0.05 | AN51: =AM51+$AN$46 -> 0.01
B52: DPT operating profit margin % | C52: =IF(AND(ISNUMBER(C51),ISNUMBER(C41)),IFERROR(C51/C41,""),"") -> 0.12216798 | D52: =IF(AND(ISNUMBER(D51),ISNUMBER(D41)),IFERROR(D51/D41,""),"") -> 0.10223805 | E52: =IF(AND(ISNUMBER(E51),ISNUMBER(E41)),IFERROR(E51/E41,""),"") -> 0.084631579 | F52: =IF(AND(ISNUMBER(F51),ISNUMBER(F41)),IFERROR(F51/F41,""),"") -> 0.12199546 | G52: =IF(AND(ISNUMBER(G51),ISNUMBER(G41)),IFERROR(G51/G41,""),"") -> 0.098136646 | H52: =IF(AND(ISNUMBER(H51),ISNUMBER(H41)),IFERROR(H51/H41,""),"") -> 0.10132798 | I52: =IF(AND(ISNUMBER(I51),ISNUMBER(I41)),IFERROR(I51/I41,""),"") -> 0.11072664 | J52: =IF(AND(ISNUMBER(J51),ISNUMBER(J41)),IFERROR(J51/J41,""),"") -> 0.14327364 | ... T52: =IF(AND(ISNUMBER(T51),ISNUMBER(T41)),IFERROR(T51/T41,""),"") -> 0.13796108 | U52: =$W$53+$W$123 -> 0.11461469 | V52: =$W$53+$W$123 -> 0.11461469 | W52: =IF(AND(ISNUMBER(W51),ISNUMBER(W41)),IFERROR(W51/W41,""),"") -> 0.12136076 | X52: =CHOOSE(MATCH($AC$2,{"Bull","Base","Bear"},0),$AL$59,$AM$59,$AN$59) -> 0.13 | Y52: =CHOOSE(MATCH($AC$2,{"Bull","Base","Bear"},0),$AL$60,$AM$60,$AN$60) -> 0.135 | Z52: =CHOOSE(MATCH($AC$2,{"Bull","Base","Bear"},0),$AL$61,$AM$61,$AN$61) -> 0.14 | AA52: =CHOOSE(MATCH($AC$2,{"Bull","Base","Bear"},0),$AL$62,$AM$62,$AN$62) -> 0.145 | AB52: =CHOOSE(MATCH($AC$2,{"Bull","Base","Bear"},0),$AL$63,$AM$63,$AN$63) -> 0.15 | AE52: =IFERROR(AVERAGE(X52,Y52,Z52,AA52,AB52),"n/m") -> 0.14 | AF52: =IFERROR(AVERAGE(H52,M52,R52),"n/m") -> 0.11202282 | AG52: =IFERROR(AVERAGE(M52,R52),"n/m") -> 0.11737025 | AH52: =IFERROR(W52+0,"n/m") -> 0.12136076 | AK52: CES_M (CES operating profit margin) | AL52: 0.01 | AM52: Δ → | AN52: -0.02 | AO52: FY2025 26.6% (as reported; ~27% revised), H1-26 26.9%, FY26 guide ~27%; services mix supports expansion while LEAP / GE9X install engines dilute (assumption).
B53: 2H-26E margin before calibration = (DPT operating-profit guide − H1-26) ÷ 2H-26E revenue | W53: =(CHOOSE(MATCH($AC$2,{"Bull","Base","Bear"},0),$AL$20,$AM$20,$AN$20)-SUM(S51:T51))/SUM(U41:V41) -> 0.11647939 | AK53: 2027E | AL53: =AM53+$AL$52 -> 0.278 | AM53: 0.268 | AN53: =AM53+$AN$52 -> 0.248
B54: Memo: DPT operating profit on the Jan-2026 structure (recast) | N54: 325 | O54: 403 | R54: 1500 | AK54: 2028E | AL54: =AM54+$AL$52 -> 0.282 | AM54: 0.272 | AN54: =AM54+$AN$52 -> 0.252
B55: Incremental margin (Δ profit / Δ revenue) | H55: =IFERROR((H51-C51)/(H41-C41),"") -> -0.069958848 | I55: =IFERROR((I51-D51)/(I41-D41),"") -> 0.15895954 | J55: =IFERROR((J51-E51)/(J41-E41),"") -> 5.5 | K55: =IFERROR((K51-F51)/(K41-F41),"") -> -1.2894737 | L55: =IFERROR((L51-G51)/(L41-G41),"") -> 0.037037037 | M55: =IFERROR((M51-H51)/(M41-H41),"") -> 0.2959381 | N55: =IFERROR((N51-I51)/(N41-I41),"") -> 3.3333333 | O55: =IFERROR((O51-J51)/(O41-J41),"") -> 0.11111111 | ... W55: =IFERROR((W51-R51)/(W41-R41),"") -> 0.1161992 | X55: =IFERROR((X51-W51)/(X41-W41),"") -> 0.23799055 | Y55: =IFERROR((Y51-X51)/(Y41-X41),"") -> 0.20642857 | Z55: =IFERROR((Z51-Y51)/(Z41-Y41),"") -> 0.22333333 | AA55: =IFERROR((AA51-Z51)/(AA41-Z41),"") -> 0.22833333 | AB55: =IFERROR((AB51-AA51)/(AB41-AA41),"") -> 0.25 | AK55: 2029E | AL55: =AM55+$AL$52 -> 0.286 | AM55: 0.276 | AN55: =AM55+$AN$52 -> 0.256
B56: Defense engine deliveries (units; incl. Aeroderivative from Q1-26) | C56: 632 | D56: 80 | E56: 228 | F56: 95 | G56: 153 | H56: 556 | I56: 125 | J56: 87 | K56: 94 | L56: 184 | M56: 490 | N56: 131 | O56: 160 | P56: 172 | Q56: 172 | R56: 635 | S56: 185 | T56: 199 | AK56: 2030E | AL56: =AM56+$AL$52 -> 0.29 | AM56: 0.28 | AN56: =AM56+$AN$52 -> 0.26
B57: DPT orders | D57: 2266 | E57: 3092 | F57: 2548 | G57: 2319 | H57: 10224 | I57: 3029 | J57: 2334 | K57: 3044 | L57: 2840 | M57: 11248 | N57: 3031 | O57: 2897 | P57: 2898 | Q57: 4571 | R57: 13397 | S57: 6174 | T57: 4138 | AK57: 2031E | AL57: =AM57+$AL$52 -> 0.292 | AM57: 0.282 | AN57: =AM57+$AN$52 -> 0.262
B58: DPT book-to-bill (orders / revenue) | C58: =IF(ISNUMBER(C57),IFERROR(C57/C41,""),"") | D58: =IF(ISNUMBER(D57),IFERROR(D57/D41,""),"") -> 1.1525941 | E58: =IF(ISNUMBER(E57),IFERROR(E57/E41,""),"") -> 1.3018947 | F58: =IF(ISNUMBER(F57),IFERROR(F57/F41,""),"") -> 1.1555556 | G58: =IF(ISNUMBER(G57),IFERROR(G57/G41,""),"") -> 0.96024845 | H58: =IF(ISNUMBER(H57),IFERROR(H57/H41,""),"") -> 1.1409441 | I58: =IF(ISNUMBER(I57),IFERROR(I57/I41,""),"") -> 1.3101211 | J58: =IF(ISNUMBER(J57),IFERROR(J57/J41,""),"") -> 0.97209496 | ... T58: =IF(ISNUMBER(T57),IFERROR(T57/T41,""),"") -> 1.2018588 | AK58: DPT_M (DPT operating profit margin) | AL58: 0.01 | AM58: Δ → | AN58: -0.015 | AO58: FY2025 12.3% (as reported), H1-26 12.8%, FY26 guide ~12%; volume and price vs next-generation investment (assumption).
B59: DPT remaining performance obligation (period end) | E59: 16468 | F59: 16468 | H59: 16468 | I59: 17991 | J59: 16761 | K59: 17576 | M59: 17991 | N59: 18847 | O59: 19164 | P59: 19089 | R59: 20742 | S59: 30027 | T59: 30663 | AK59: 2027E | AL59: =AM59+$AL$58 -> 0.14 | AM59: 0.13 | AN59: =AM59+$AN$58 -> 0.115
AK60: 2028E | AL60: =AM60+$AL$58 -> 0.145 | AM60: 0.135 | AN60: =AM60+$AN$58 -> 0.12
B61: Eliminations & other (inter-segment revenue eliminations; inside Corporate & Other revenue) | AC61: ELIMINATIONS — % of segment revenue | AK61: 2029E | AL61: =AM61+$AL$58 -> 0.15 | AM61: 0.14 | AN61: =AM61+$AN$58 -> 0.125
B62: Eliminations and other (revenue) | C62: -620 | D62: -153 | E62: -205 | F62: -202 | G62: -297 | H62: -857 | I62: -332 | J62: -310 | K62: -303 | L62: -294 | M62: -1239 | N62: -300 | O62: -402 | P62: -403 | Q62: -441 | R62: -1546 | S62: -519 | T62: -540 | U62: =(U21+U41)*U63 -> -547.52128 | V62: =(V21+V41)*V63 -> -574.54181 | W62: =SUM(S62:V62) -> -2181.0631 | X62: =(X21+X41)*X63 -> -2453.8232 | Y62: =(Y21+Y41)*Y63 -> -2694.9347 | Z62: =(Z21+Z41)*Z63 -> -2913.071 | AA62: =(AA21+AA41)*AA63 -> -3121.9442 | AB62: =(AB21+AB41)*AB63 -> -3314.8574 | AK62: 2030E | AL62: =AM62+$AL$58 -> 0.155 | AM62: 0.145 | AN62: =AM62+$AN$58 -> 0.13
B63: Eliminations % of segment revenue | C63: =IFERROR(C62/(C21+C41),"") -> -0.023132602 | D63: =IFERROR(D62/(D21+D41),"") -> -0.021255904 | E63: =IFERROR(E62/(E21+E41),"") -> -0.025271203 | F63: =IFERROR(F62/(F21+F41),"") -> -0.023320249 | G63: =IFERROR(G62/(G21+G41),"") -> -0.03358209 | H63: =IFERROR(H62/(H21+H41),"") -> -0.02611531 | I63: =IFERROR(I62/(I21+I41),"") -> -0.039486204 | J63: =IFERROR(J62/(J21+J41),"") -> -0.036329544 | ... T63: =IFERROR(T62/(T21+T41),"") -> -0.040989828 | U63: =IFERROR(SUM(S62:T62)/(SUM(S21:T21)+SUM(S41:T41)),0) -> -0.04184613 | V63: =IFERROR(SUM(S62:T62)/(SUM(S21:T21)+SUM(S41:T41)),0) -> -0.04184613 | W63: =IFERROR(W62/(W21+W41),"") -> -0.04184613 | X63: -0.042 | Y63: -0.042 | Z63: -0.042 | AA63: -0.042 | AB63: -0.042 | AC63: Q3/Q4-26E: H1-26 ratio; 2027E+: input (FY2026E level). | AE63: =IFERROR(AVERAGE(X63,Y63,Z63,AA63,AB63),"n/m") -> -0.042 | AF63: =IFERROR(AVERAGE(H63,M63,R63),"n/m") -> -0.031811415 | AG63: =IFERROR(AVERAGE(M63,R63),"n/m") -> -0.034659467 | AH63: =IFERROR(W63+0,"n/m") -> -0.04184613 | AK63: 2031E | AL63: =AM63+$AL$58 -> 0.16 | AM63: 0.15 | AN63: =AM63+$AN$58 -> 0.135
AK64: CPP_SYN (CPP net-synergy realisation multiplier) | AL64: 0.25 | AM64: Δ → | AN64: -0.5 | AO64: Deck: ~$200m net synergies by year 3, >2x by year 6. Multiplier on the phased run-rate (assumption).
B65: Run-off insurance (North American Life & Health; outside operating profit) · U.S. tax equity investments | AC65: INSURANCE / TAX EQUITY — excluded from adjusted revenue, operating profit and adjusted EPS (company definitions) | AK65: 2027E | AL65: =MAX(0,AM65+$AL$64) -> 1.25 | AM65: 1 | AN65: =MAX(0,AM65+$AN$64) -> 0.5
B66: Insurance revenue | C66: 2957 | D66: 792 | E66: 847 | F66: 842 | G66: 909 | H66: 3389 | I66: 879 | J66: 871 | K66: 899 | L66: 932 | M66: 3581 | N66: 934 | O66: 872 | P66: 875 | Q66: 852 | R66: 3533 | S66: 778 | T66: 715 | U66: =SUM(S66:T66)/2 -> 746.5 | V66: =SUM(S66:T66)/2 -> 746.5 | W66: =SUM(S66:V66) -> 2986 | X66: =W66*(1+X67) -> 2896.42 | Y66: =X66*(1+Y67) -> 2809.5274 | Z66: =Y66*(1+Z67) -> 2725.2416 | AA66: =Z66*(1+AA67) -> 2643.4843 | AB66: =AA66*(1+AB67) -> 2564.1798 | AC66: Q3/Q4-26E: H1-26 run-rate (the annual premium-deficiency / assumption review in Q3 is not forecast). 2027E+: run-off decline (input). | AE66: =IFERROR((AB66/W66)^(1/5)-1,"n/m") -> -0.03 | AF66: =IFERROR((R66/C66)^(1/3)-1,"n/m") -> 0.061119033 | AG66: =IFERROR((R66/H66)^(1/2)-1,"n/m") -> 0.021024197 | AH66: =IFERROR(W66/R66-1,"n/m") -> -0.15482593 | AK66: 2028E | AL66: =MAX(0,AM66+$AL$64) -> 1.25 | AM66: 1 | AN66: =MAX(0,AM66+$AN$64) -> 0.5
B67: Insurance revenue y/y % | H67: =IF(AND(ISNUMBER(H66),ISNUMBER(C66)),IFERROR(H66/C66-1,""),"") -> 0.14609401 | I67: =IF(AND(ISNUMBER(I66),ISNUMBER(D66)),IFERROR(I66/D66-1,""),"") -> 0.10984848 | J67: =IF(AND(ISNUMBER(J66),ISNUMBER(E66)),IFERROR(J66/E66-1,""),"") -> 0.028335301 | K67: =IF(AND(ISNUMBER(K66),ISNUMBER(F66)),IFERROR(K66/F66-1,""),"") -> 0.067695962 | L67: =IF(AND(ISNUMBER(L66),ISNUMBER(G66)),IFERROR(L66/G66-1,""),"") -> 0.02530253 | M67: =IF(AND(ISNUMBER(M66),ISNUMBER(H66)),IFERROR(M66/H66-1,""),"") -> 0.05665388 | N67: =IF(AND(ISNUMBER(N66),ISNUMBER(I66)),IFERROR(N66/I66-1,""),"") -> 0.062571104 | O67: =IF(AND(ISNUMBER(O66),ISNUMBER(J66)),IFERROR(O66/J66-1,""),"") -> 0.0011481056 | ... W67: =IF(AND(ISNUMBER(W66),ISNUMBER(R66)),IFERROR(W66/R66-1,""),"") -> -0.15482593 | X67: -0.03 | Y67: -0.03 | Z67: -0.03 | AA67: -0.03 | AB67: -0.03 | AK67: 2029E | AL67: =MAX(0,AM67+$AL$64) -> 1.25 | AM67: 1 | AN67: =MAX(0,AM67+$AN$64) -> 0.5
B68: Insurance costs and expenses (company non-GAAP table) | D68: 721 | E68: 784 | F68: 742 | G68: 810 | H68: 3057 | I68: 679 | J68: 701 | K68: 728 | L68: 452 | M68: 2560 | N68: 728 | O68: 725 | P68: 514 | Q68: 574 | R68: 2541 | S68: 648 | T68: 544 | U68: =U66*(1-U70) -> 596 | V68: =V66*(1-V70) -> 596 | W68: =SUM(S68:V68) -> 2384 | X68: =X66*(1-X70) -> 2259.2076 | Y68: =Y66*(1-Y70) -> 2191.4314 | Z68: =Z66*(1-Z70) -> 2125.6884 | AA68: =AA66*(1-AA70) -> 2061.9178 | AB68: =AB66*(1-AB70) -> 2000.0602 | AK68: 2030E | AL68: =MAX(0,AM68+$AL$64) -> 1.25 | AM68: 1 | AN68: =MAX(0,AM68+$AN$64) -> 0.5
B69: Insurance profit (pre-tax; revenue − costs) | C69: =IF(ISNUMBER(C68),C66-C68,"") | D69: =IF(ISNUMBER(D68),D66-D68,"") -> 71 | E69: =IF(ISNUMBER(E68),E66-E68,"") -> 63 | F69: =IF(ISNUMBER(F68),F66-F68,"") -> 100 | G69: =IF(ISNUMBER(G68),G66-G68,"") -> 99 | H69: =IF(ISNUMBER(H68),H66-H68,"") -> 332 | I69: =IF(ISNUMBER(I68),I66-I68,"") -> 200 | J69: =IF(ISNUMBER(J68),J66-J68,"") -> 170 | ... AB69: =IF(ISNUMBER(AB68),AB66-AB68,"") -> 564.11956 | AK69: 2031E | AL69: =MAX(0,AM69+$AL$64) -> 1.25 | AM69: 1 | AN69: =MAX(0,AM69+$AN$64) -> 0.5
B70: Insurance profit margin % | C70: =IF(AND(ISNUMBER(C69),ISNUMBER(C66)),IFERROR(C69/C66,""),"") | D70: =IF(AND(ISNUMBER(D69),ISNUMBER(D66)),IFERROR(D69/D66,""),"") -> 0.089646465 | E70: =IF(AND(ISNUMBER(E69),ISNUMBER(E66)),IFERROR(E69/E66,""),"") -> 0.074380165 | F70: =IF(AND(ISNUMBER(F69),ISNUMBER(F66)),IFERROR(F69/F66,""),"") -> 0.11876485 | G70: =IF(AND(ISNUMBER(G69),ISNUMBER(G66)),IFERROR(G69/G66,""),"") -> 0.10891089 | H70: =IF(AND(ISNUMBER(H69),ISNUMBER(H66)),IFERROR(H69/H66,""),"") -> 0.097964001 | I70: =IF(AND(ISNUMBER(I69),ISNUMBER(I66)),IFERROR(I69/I66,""),"") -> 0.22753129 | J70: =IF(AND(ISNUMBER(J69),ISNUMBER(J66)),IFERROR(J69/J66,""),"") -> 0.19517796 | ... T70: =IF(AND(ISNUMBER(T69),ISNUMBER(T66)),IFERROR(T69/T66,""),"") -> 0.23916084 | U70: =IFERROR((SUM(S66:T66)-SUM(S68:T68))/SUM(S66:T66),0) -> 0.2016075 | V70: =IFERROR((SUM(S66:T66)-SUM(S68:T68))/SUM(S66:T66),0) -> 0.2016075 | W70: =IF(AND(ISNUMBER(W69),ISNUMBER(W66)),IFERROR(W69/W66,""),"") -> 0.2016075 | X70: 0.22 | Y70: 0.22 | Z70: 0.22 | AA70: 0.22 | AB70: 0.22 | AE70: =IFERROR(AVERAGE(X70,Y70,Z70,AA70,AB70),"n/m") -> 0.22 | AF70: =IFERROR(AVERAGE(H70,M70,R70),"n/m") -> 0.22128703 | AG70: =IFERROR(AVERAGE(M70,R70),"n/m") -> 0.28294855 | AH70: =IFERROR(W70+0,"n/m") -> 0.2016075 | AK70: M&A_spend (bolt-ons beyond CPP, $m) | AL70: 500 | AM70: Δ → | AN70: -500 | AO70: No acquisitions disclosed beyond CPP; Base assumes no bolt-ons during CPP integration and $0.5bn a year from 2029 (assumption).
B71: U.S. tax equity profit (loss), pre-tax (adjusted-EPS table) | D71: -43 | E71: -53 | F71: -47 | G71: -33 | H71: -176 | I71: -43 | J71: -52 | K71: -59 | L71: -37 | M71: -191 | N71: -55 | O71: -66 | P71: -60 | Q71: -40 | R71: -220 | S71: -67 | T71: -77 | U71: =SUM(S71:T71)/2 -> -72 | V71: =SUM(S71:T71)/2 -> -72 | W71: =SUM(S71:V71) -> -288 | X71: -280 | Y71: -280 | Z71: -280 | AA71: -280 | AB71: -280 | AC71: Renewable-energy tax-equity investments retained at the GE Vernova spin; pre-tax losses offset by tax credits (below). Forecast: H1-26 run-rate, then input. | AK71: 2027E | AL71: =MAX(0,AM71+$AL$70) -> 500 | AM71: 0 | AN71: =MAX(0,AM71+$AN$70) -> 0
B72: U.S. tax equity tax benefit (credits) | D72: 53 | E72: 66 | F72: 54 | G72: 44 | H72: 217 | I72: 58 | J72: 61 | K72: 70 | L72: 46 | M72: 235 | N72: 63 | O72: 77 | P72: 71 | Q72: 47 | R72: 259 | S72: 75 | T72: 86 | U72: =SUM(S72:T72)/2 -> 80.5 | V72: =SUM(S72:T72)/2 -> 80.5 | W72: =SUM(S72:V72) -> 322 | X72: 320 | Y72: 320 | Z72: 320 | AA72: 320 | AB72: 320 | AK72: 2028E | AL72: =MAX(0,AM72+$AL$70) -> 500 | AM72: 0 | AN72: =MAX(0,AM72+$AN$70) -> 0
AK73: 2029E | AL73: =MAX(0,AM73+$AL$70) -> 1000 | AM73: 500 | AN73: =MAX(0,AM73+$AN$70) -> 0
B74: Pending acquisition — Consolidated Precision Products (CPP; castings), $11.75bn cash, close expected 2H-2027 (8-K 8-Sep-2026) | AC74: CPP — deal block (toggle; closing-year share; standalone revenue and EBITDA from the deal deck; synergies phased; PPA assumed) | AK74: 2030E | AL74: =MAX(0,AM74+$AL$70) -> 1000 | AM74: 500 | AN74: =MAX(0,AM74+$AN$70) -> 0
B75: Include CPP (1 = yes, 0 = no) | X75: 1 | Y75: 1 | Z75: 1 | AA75: 1 | AB75: 1 | AK75: 2031E | AL75: =MAX(0,AM75+$AL$70) -> 1000 | AM75: 500 | AN75: =MAX(0,AM75+$AN$70) -> 0
B76: Closing year flag (1 in the closing year) | X76: 1 | Y76: 0 | Z76: 0 | AA76: 0 | AB76: 0
B77: Share of the year consolidated (closing 30-Sep-2027 assumed → 0.25) | X77: 0.25 | Y77: 1 | Z77: 1 | AA77: 1 | AB77: 1 | AC77: Closing date not disclosed beyond "second half of 2027" — assumption.
B78: CPP standalone revenue (full year) | X78: =2000.0 -> 2000 | Y78: =X78*(1+Y79) -> 2160 | Z78: =Y78*(1+Z79) -> 2332.8 | AA78: =Z78*(1+AA79) -> 2519.424 | AB78: =AA78*(1+AB79) -> 2720.9779 | AC78: ~$2.0bn 2027E revenue (deal presentation, 8-K 8-Sep-2026). 2028E+: growth input (assumption).
B79: CPP revenue growth % | X79: 0.08 | Y79: 0.08 | Z79: 0.08 | AA79: 0.08 | AB79: 0.08
B80: Share of CPP revenue sold to GE Aerospace (eliminated on consolidation; assumption — not disclosed) | X80: 0.25 | Y80: 0.25 | Z80: 0.25 | AA80: 0.25 | AB80: 0.25
B81: CPP revenue consolidated (external) | X81: =X75*X77*X78*(1-X80) -> 375 | Y81: =Y75*Y77*Y78*(1-Y80) -> 1620 | Z81: =Z75*Z77*Z78*(1-Z80) -> 1749.6 | AA81: =AA75*AA77*AA78*(1-AA80) -> 1889.568 | AB81: =AB75*AB77*AB78*(1-AB80) -> 2040.7334
B82: CPP EBITDA margin before synergies % ($11.75bn ÷ ~26x ≈ $452m on ~$2.0bn) | X82: 0.226 | Y82: 0.226 | Z82: 0.226 | AA82: 0.226 | AB82: 0.226
B83: Net synergies (run-rate ~$200m by year 3 × phasing × scenario realisation) | X83: =X75*200.0*0.0*CHOOSE(MATCH($AC$2,{"Bull","Base","Bear"},0),$AL$65,$AM$65,$AN$65) -> 0 | Y83: =Y75*200.0*0.25*CHOOSE(MATCH($AC$2,{"Bull","Base","Bear"},0),$AL$66,$AM$66,$AN$66) -> 50 | Z83: =Z75*200.0*0.6*CHOOSE(MATCH($AC$2,{"Bull","Base","Bear"},0),$AL$67,$AM$67,$AN$67) -> 120 | AA83: =AA75*200.0*1.0*CHOOSE(MATCH($AC$2,{"Bull","Base","Bear"},0),$AL$68,$AM$68,$AN$68) -> 200 | AB83: =AB75*200.0*1.2*CHOOSE(MATCH($AC$2,{"Bull","Base","Bear"},0),$AL$69,$AM$69,$AN$69) -> 240 | AC83: Deck: ~$200m net synergies by year 3, >2x by year 6. Phasing 0% / 25% / 60% / 100% / 120% for 2027E–31E (assumption); realisation = scenario multiplier.
B84: CPP depreciation (% of standalone revenue; assumption) | X84: =X75*X77*X78*0.05 -> 25 | Y84: =Y75*Y77*Y78*0.05 -> 108 | Z84: =Z75*Z77*Z78*0.05 -> 116.64 | AA84: =AA75*AA77*AA78*0.05 -> 125.9712 | AB84: =AB75*AB77*AB78*0.05 -> 136.0489
B85: Amortization of acquired CPP intangibles (PPA; 35% of price over 15 years — assumption) | X85: =X75*X77*11750.0*0.35/15 -> 68.541667 | Y85: =Y75*Y77*11750.0*0.35/15 -> 274.16667 | Z85: =Z75*Z77*11750.0*0.35/15 -> 274.16667 | AA85: =AA75*AA77*11750.0*0.35/15 -> 274.16667 | AB85: =AB75*AB77*11750.0*0.35/15 -> 274.16667
B86: CPP operating profit (EBITDA incl. inter-company sales − depreciation − PPA amortization + synergies) | X86: =X75*X77*X78*X82-X84-X85+X83 -> 19.458333 | Y86: =Y75*Y77*Y78*Y82-Y84-Y85+Y83 -> 155.99333 | Z86: =Z75*Z77*Z78*Z82-Z84-Z85+Z83 -> 256.40613 | AA86: =AA75*AA77*AA78*AA82-AA84-AA85+AA83 -> 369.25196 | AB86: =AB75*AB77*AB78*AB82-AB84-AB85+AB83 -> 444.72545 | AC86: Margin on sales to GE Aerospace stays in the group (lower GE cost of sales), so the full standalone EBITDA is consolidated while only external revenue is. GE operating profit is after amortization; the deck's accretion basis excludes deal amortization.
B87: Memo: CPP EBITDA for the full closing year (pro forma; leverage / EV) | X87: =X75*X78*X82+X83 -> 452 | Y87: =Y75*Y78*Y82+Y83 -> 538.16 | Z87: =Z75*Z78*Z82+Z83 -> 647.2128 | AA87: =AA75*AA78*AA82+AA83 -> 769.38982 | AB87: =AB75*AB78*AB82+AB83 -> 854.94101
B89: Future acquisitions (M&A lever — bolt-ons beyond CPP; deals closed from 2027E) | AC89: M&A LEVER — acquired revenue = spend ÷ EV/sales; mid-year convention
B90: Acquisition spend (USDm, scenario) | X90: =MAX(0,CHOOSE(MATCH($AC$2,{"Bull","Base","Bear"},0),$AL$71,$AM$71,$AN$71)) -> 0 | Y90: =MAX(0,CHOOSE(MATCH($AC$2,{"Bull","Base","Bear"},0),$AL$72,$AM$72,$AN$72)) -> 0 | Z90: =MAX(0,CHOOSE(MATCH($AC$2,{"Bull","Base","Bear"},0),$AL$73,$AM$73,$AN$73)) -> 500 | AA90: =MAX(0,CHOOSE(MATCH($AC$2,{"Bull","Base","Bear"},0),$AL$74,$AM$74,$AN$74)) -> 500 | AB90: =MAX(0,CHOOSE(MATCH($AC$2,{"Bull","Base","Bear"},0),$AL$75,$AM$75,$AN$75)) -> 500 | AC90: Scenario lever M&A_spend (bolt-ons beyond CPP). Funded from cash / revolver (debt schedule).
B91: Purchase multiple — EV / sales (x) | X91: 4 | Y91: 4 | Z91: 4 | AA91: 4 | AB91: 4 | AC91: Aerospace components bolt-ons; CPP at ~5.9x 2027E sales. 4.0x input (assumption).
B92: Annualised revenue acquired in the year | X92: =IFERROR(X90/X91,0) -> 0 | Y92: =IFERROR(Y90/Y91,0) -> 0 | Z92: =IFERROR(Z90/Z91,0) -> 125 | AA92: =IFERROR(AA90/AA91,0) -> 125 | AB92: =IFERROR(AB90/AB91,0) -> 125
B93: Growth of acquired businesses after acquisition % | X93: 0.06 | Y93: 0.06 | Z93: 0.06 | AA93: 0.06 | AB93: 0.06
B94: Run-rate revenue of businesses acquired (year end) | X94: =N(W94)*(1+X93)+X92 -> 0 | Y94: =N(X94)*(1+Y93)+Y92 -> 0 | Z94: =N(Y94)*(1+Z93)+Z92 -> 125 | AA94: =N(Z94)*(1+AA93)+AA92 -> 257.5 | AB94: =N(AA94)*(1+AB93)+AB92 -> 397.95
B95: Revenue from future acquisitions | X95: =N(W94)*(1+X93)+0.5*X92 -> 0 | Y95: =N(X94)*(1+Y93)+0.5*Y92 -> 0 | Z95: =N(Y94)*(1+Z93)+0.5*Z92 -> 62.5 | AA95: =N(Z94)*(1+AA93)+0.5*AA92 -> 195 | AB95: =N(AA94)*(1+AB93)+0.5*AB92 -> 335.45 | AC95: Mid-year convention.
B96: Operating margin of acquired businesses (after amortization) % | X96: 0.16 | Y96: 0.16 | Z96: 0.16 | AA96: 0.16 | AB96: 0.16
B97: Operating profit from future acquisitions | X97: =X95*X96 -> 0 | Y97: =Y95*Y96 -> 0 | Z97: =Z95*Z96 -> 10 | AA97: =AA95*AA96 -> 31.2 | AB97: =AB95*AB96 -> 53.672
B98: PP&E % of spend | X98: 0.15 | Y98: 0.15 | Z98: 0.15 | AA98: 0.15 | AB98: 0.15
B99: Acquired intangibles % of spend | X99: 0.35 | Y99: 0.35 | Z99: 0.35 | AA99: 0.35 | AB99: 0.35
B100: Intangible amortization life (years) | X100: 15 | Y100: 15 | Z100: 15 | AA100: 15 | AB100: 15
B101: Cumulative acquired intangibles (gross) | X101: =N(W101)+X90*X99 -> 0 | Y101: =N(X101)+Y90*Y99 -> 0 | Z101: =N(Y101)+Z90*Z99 -> 175 | AA101: =N(Z101)+AA90*AA99 -> 350 | AB101: =N(AA101)+AB90*AB99 -> 525
...

Sheet Bull-Base-Bear
B2: General Electric Company, operating as GE Aerospace (GE) — Bull / Base / Bear Case P&L Summary | J2: Share price ($): | K2: =Model!$X$471 -> 308
B3: Company non-GAAP definitions (adjusted revenue, operating profit, adjusted EPS, FCF); adjusted EBITDA = operating profit + D&A (model) · USD millions · Live panel linked to Model — toggle scenario via Model!AC2. Bull and Bear panels are value snapshots generated from the Model with the switch set to each case. FY2026E = H1 actual + 2H calibrated to the FY26 guidance (adjusted revenue high-teens, operating profit $10.55–10.75B). CPP ($11.75bn) from 2H-27. | J3: As of: | K3: =TODAY() -> 2026-10-13 00:00:00
B5: Scenario: | C5: =Model!$AC$2 -> Base | N5: Scenario: | O5: Bull | P5: Snapshot (values) — Model run with switch = Bull | Z5: Scenario: | AA5: Bear | AB5: Snapshot (values) — Model run with switch = Bear
B7: (USDm, except EPS and shares) | C7: 2026E | D7: 2027E | E7: 2028E | F7: 2029E | G7: 2030E | H7: 2031E | I7: 26-'31 CAGR | J7: LT Hist Avg | K7: LT Hist Min | L7: LT Hist Max | N7: (USDm, except EPS and shares) | O7: 2026E | P7: 2027E | Q7: 2028E | R7: 2029E | S7: 2030E | T7: 2031E | U7: 26-'31 CAGR | V7: LT Hist Avg | W7: LT Hist Min | X7: LT Hist Max | Z7: (USDm, except EPS and shares) | AA7: 2026E | AB7: 2027E | AC7: 2028E | AD7: 2029E | AE7: 2030E | AF7: 2031E | AG7: 26-'31 CAGR | AH7: LT Hist Avg | AI7: LT Hist Min | AJ7: LT Hist Max
B9: Adjusted revenue | C9: =Model!W105 -> 49939.96 | D9: =Model!X105 -> 56345.539 | E9: =Model!Y105 -> 63090.178 | F9: =Model!Z105 -> 68257.863 | G9: =Model!AA105 -> 73294.628 | H9: =Model!AB105 -> 77986.503 | I9: =IFERROR((H9/C9)^(1/5)-1,"n/m") -> 0.093236822 | N9: Adjusted revenue | O9: 50363.18 | P9: 58481.533 | Q9: 67406.165 | R9: 75131.953 | S9: 83102.711 | T9: 91082.231 | U9: 0.12580741 | Z9: Adjusted revenue | AA9: 49516.74 | AB9: 53261.867 | AC9: 56916.617 | AD9: 58612.544 | AE9: 59854.52 | AF9: 60567.585 | AG9: 0.041112457
B10: Adjusted revenue y/y % | D10: =IFERROR(D9/C9-1,"") -> 0.12826561 | E10: =IFERROR(E9/D9-1,"") -> 0.11970137 | F10: =IFERROR(F9/E9-1,"") -> 0.0819095 | G10: =IFERROR(G9/F9-1,"") -> 0.073790261 | H10: =IFERROR(H9/G9-1,"") -> 0.064013891 | N10: Adjusted revenue y/y % | P10: 0.16119619 | Q10: 0.15260599 | R10: 0.11461545 | S10: 0.10609013 | T10: 0.096019973 | Z10: Adjusted revenue y/y % | AB10: 0.075633548 | AC10: 0.068618507 | AD10: 0.029796703 | AE10: 0.021189601 | AF10: 0.011913299
B11: CES revenue y/y % | C11: =Model!W259 -> 0.21097793 | D11: =Model!X259 -> 0.1352329 | E11: =Model!Y259 -> 0.10764843 | F11: =Model!Z259 -> 0.08766467 | G11: =Model!AA259 -> 0.075362255 | H11: =Model!AB259 -> 0.065428508 | N11: CES revenue y/y % | O11: 0.22099388 | P11: 0.1676162 | Q11: 0.14 | R11: 0.12 | S11: 0.10763175 | T11: 0.097648068 | Z11: CES revenue y/y % | AA11: 0.20096197 | AB11: 0.078083508 | AC11: 0.050803569 | AD11: 0.031073156 | AE11: 0.019177727 | AF11: 0.0095937405
B12: Adjusted EBITDA (operating profit + D&A) | C12: =Model!W224 -> 11907 | D12: =Model!X224 -> 13777.983 | E12: =Model!Y224 -> 15833.7 | F12: =Model!Z224 -> 17525.083 | G12: =Model!AA224 -> 19197.499 | H12: =Model!AB224 -> 20658.915 | I12: =IFERROR((H12/C12)^(1/5)-1,"n/m") -> 0.11650592 | N12: Adjusted EBITDA (operating profit + D&A) | O12: 12007 | P12: 14892.377 | Q12: 17582.406 | R12: 20025.785 | S12: 22571.531 | T12: 24993.28 | U12: 0.15791785 | Z12: Adjusted EBITDA (operating profit + D&A) | AA12: 11807 | AB12: 11991.243 | AC12: 13184.022 | AD12: 13893.143 | AE12: 14476.005 | AF12: 14826.737 | AG12: 0.046601143
B13: Adjusted EBITDA margin % | C13: =IFERROR(C12/C9,"") -> 0.2384263 | D13: =IFERROR(D12/D9,"") -> 0.2445266 | E13: =IFERROR(E12/E9,"") -> 0.25096933 | F13: =IFERROR(F12/F9,"") -> 0.25674819 | G13: =IFERROR(G12/G9,"") -> 0.26192231 | H13: =IFERROR(H12/H9,"") -> 0.26490372 | J13: =IFERROR(AVERAGE(Model!C225,Model!H225,Model!M225,Model!R225),"") -> 0.23129992 | K13: =IFERROR(MIN(Model!C225,Model!H225,Model!M225,Model!R225),"") -> 0.21083263 | L13: =IFERROR(MAX(Model!C225,Model!H225,Model!M225,Model!R225),"") -> 0.24280516 | N13: Adjusted EBITDA margin % | O13: 0.2384083 | P13: 0.25465093 | Q13: 0.26084271 | R13: 0.26654152 | S13: 0.27161005 | T13: 0.27440347 | V13: 0.23129992 | W13: 0.21083263 | X13: 0.24280516 | Z13: Adjusted EBITDA margin % | AA13: 0.23844461 | AB13: 0.22513749 | AC13: 0.23163749 | AD13: 0.23703362 | AE13: 0.24185316 | AF13: 0.24479657 | AH13: 0.23129992 | AI13: 0.21083263 | AJ13: 0.24280516
B15: Profit before tax (GAAP) | C15: =Model!W172 -> 10301 | D15: =Model!X172 -> 12265.538 | E15: =Model!Y172 -> 13543.22 | F15: =Model!Z172 -> 15189.124 | G15: =Model!AA172 -> 16612.473 | H15: =Model!AB172 -> 17861.293 | I15: =IFERROR((H15/C15)^(1/5)-1,"n/m") -> 0.11636626 | N15: Profit before tax (GAAP) | O15: 10401 | P15: 13295.333 | Q15: 14851.545 | R15: 17055.756 | S15: 19196.207 | T15: 21234.648 | U15: 0.15343731 | Z15: Profit before tax (GAAP) | AA15: 10201 | AB15: 10539.014 | AC15: 11010.84 | AD15: 11771.555 | AE15: 12265.23 | AF15: 12565.889 | AG15: 0.042581692
B16: Profit before tax y/y % | D16: =IFERROR(D15/C15-1,"") -> 0.19071333 | E16: =IFERROR(E15/D15-1,"") -> 0.1041684 | F16: =IFERROR(F15/E15-1,"") -> 0.12152978 | G16: =IFERROR(G15/F15-1,"") -> 0.093708409 | H16: =IFERROR(H15/G15-1,"") -> 0.075173671 | N16: Profit before tax y/y % | P16: 0.27827452 | Q16: 0.11704944 | R16: 0.14841629 | S16: 0.12549727 | T16: 0.10618983 | Z16: Profit before tax y/y % | AB16: 0.0331354 | AC16: 0.044769441 | AD16: 0.069087869 | AE16: 0.041937878 | AF16: 0.024513154
B17: Profit margin (GAAP) % | C17: =IFERROR(C15/C9,"") -> 0.20626769 | D17: =IFERROR(D15/D9,"") -> 0.21768428 | E17: =IFERROR(E15/E9,"") -> 0.21466447 | F17: =IFERROR(F15/F9,"") -> 0.22252563 | G17: =IFERROR(G15/G9,"") -> 0.22665334 | H17: =IFERROR(H15/H9,"") -> 0.22903057 | J17: =IFERROR(AVERAGE(Model!C268,Model!H268,Model!M268,Model!R268),"") -> 0.19064439 | K17: =IFERROR(MIN(Model!C268,Model!H268,Model!M268,Model!R268),"") -> 0.052232403 | L17: =IFERROR(MAX(Model!C268,Model!H268,Model!M268,Model!R268),"") -> 0.29537739 | N17: Profit margin (GAAP) % | O17: 0.20651992 | P17: 0.22734242 | Q17: 0.22032918 | R17: 0.22701068 | S17: 0.23099375 | T17: 0.23313711 | V17: 0.19064439 | W17: 0.052232403 | X17: 0.29537739 | Z17: Profit margin (GAAP) % | AA17: 0.20601114 | AB17: 0.19787166 | AC17: 0.19345563 | AD17: 0.20083679 | AE17: 0.20491735 | AF17: 0.20746888 | AH17: 0.19064439 | AI17: 0.052232403 | AJ17: 0.29537739
B19: Adjusted Net Income | C19: =Model!W243 -> 8194.385 | D19: =Model!X243 -> 9444.0103 | E19: =Model!Y243 -> 10619.953 | F19: =Model!Z243 -> 11893.544 | G19: =Model!AA243 -> 13106.452 | H19: =Model!AB243 -> 14174.054 | I19: =IFERROR((H19/C19)^(1/5)-1,"n/m") -> 0.1158236 | N19: Adjusted Net Income | O19: 8277.885 | P19: 10298.74 | Q19: 11705.862 | R19: 13442.848 | S19: 15250.951 | T19: 16973.939 | U19: 0.15444341 | Z19: Adjusted Net Income | AA19: 8110.885 | AB19: 8010.9955 | AC19: 8518.0775 | AD19: 9056.9619 | AE19: 9498.2403 | AF19: 9778.8686 | AG19: 0.038111671
B21: FDSO (m) | C21: =Model!W190 -> 1044.7845 | D21: =Model!X190 -> 1034.8266 | E21: =Model!Y190 -> 1022.3489 | F21: =Model!Z190 -> 995.66575 | G21: =Model!AA190 -> 969.86928 | H21: =Model!AB190 -> 944.90357 | I21: =IFERROR((H21/C21)^(1/5)-1,"n/m") -> -0.019896018 | N21: FDSO (m) | O21: 1043.9728 | P21: 1018.643 | Q21: 989.22747 | R21: 953.90532 | S21: 918.12814 | T21: 881.99946 | U21: -0.033157292 | Z21: FDSO (m) | AA21: 1045.5962 | AB21: 1038.8223 | AC21: 1042.8223 | AD21: 1039.1397 | AE21: 1026.942 | AF21: 1015.0109 | AG21: -0.0059199843
B23: Adjusted EPS — Diluted ($) | C23: =Model!W248 -> 7.8431341 | D23: =Model!X248 -> 9.1261762 | E23: =Model!Y248 -> 10.387796 | F23: =Model!Z248 -> 11.945318 | G23: =Model!AA248 -> 13.513627 | H23: =Model!AB248 -> 15.00053 | I23: =IFERROR((H23/C23)^(1/5)-1,"n/m") -> 0.13847472 | N23: Adjusted EPS — Diluted ($) | O23: 7.9292151 | P23: 10.110255 | Q23: 11.833337 | R23: 14.092435 | S23: 16.610918 | T23: 19.24484 | U23: 0.19403436 | Z23: Adjusted EPS — Diluted ($) | AA23: 7.7571868 | AB23: 7.7116133 | AC23: 8.1682928 | AD23: 8.7158268 | AE23: 9.2490519 | AF23: 9.6342498 | AG23: 0.044293874
B24: EPS y/y % | D24: =IFERROR(D23/C23-1,"") -> 0.16358792 | E24: =IFERROR(E23/D23-1,"") -> 0.13824194 | F24: =IFERROR(F23/E23-1,"") -> 0.1499376 | G24: =IFERROR(G23/F23-1,"") -> 0.13129074 | H24: =IFERROR(H23/G23-1,"") -> 0.11002984 | N24: EPS y/y % | P24: 0.27506382 | Q24: 0.17042913 | R24: 0.19090956 | S24: 0.17871173 | T24: 0.15856574 | Z24: EPS y/y % | AB24: -0.005875006 | AC24: 0.059219707 | AD24: 0.067031638 | AE24: 0.061178947 | AF24: 0.041647283
B26: P / E (x) — assumed (adjusted EPS) | G26: 36 | H26: 36 | N26: P / E (x) — assumed (adjusted EPS) | S26: 42 | T26: 42 | Z26: P / E (x) — assumed (adjusted EPS) | AD26: 28 | AE26: 28 | AF26: 28
B27: Price Target ($) | G27: =G26*G23 -> 486.49058 | H27: =H26*H23 -> 540.01907 | N27: Price Target ($) | S27: =S26*S23 -> 697.65856 | T27: =T26*T23 -> 808.2833 | Z27: Price Target ($) | AD27: =AD26*AD23 -> 244.04315 | AE27: =AE26*AE23 -> 258.97345 | AF27: =AF26*AF23 -> 269.75899
B28: Upside / (Downside) vs current | G28: =IFERROR(G27/$K$2-1,"") -> 0.57951488 | H28: =IFERROR(H27/$K$2-1,"") -> 0.75330866 | N28: Upside / (Downside) vs current | S28: =IFERROR(S27/$K$2-1,"") -> 1.2651252 | T28: =IFERROR(T27/$K$2-1,"") -> 1.6242964 | Z28: Upside / (Downside) vs current | AD28: =IFERROR(AD27/$K$2-1,"") -> -0.20765211 | AE28: =IFERROR(AE27/$K$2-1,"") -> -0.1591771 | AF28: =IFERROR(AF27/$K$2-1,"") -> -0.12415911
B29: IRR (to 31-Dec of Y-1) | G29: =IFERROR((G27/$K$2)^(1/((DATE(2030-1,12,31)-$K$3)/365.25))-1,"") -> 0.15268677 | H29: =IFERROR((H27/$K$2)^(1/((DATE(2031-1,12,31)-$K$3)/365.25))-1,"") -> 0.14244997 | N29: IRR (to 31-Dec of Y-1) | S29: =IFERROR((S27/$K$2)^(1/((DATE(2030-1,12,31)-$K$3)/365.25))-1,"") -> 0.28937959 | T29: =IFERROR((T27/$K$2)^(1/((DATE(2031-1,12,31)-$K$3)/365.25))-1,"") -> 0.25712805 | Z29: IRR (to 31-Dec of Y-1) | AD29: =IFERROR((AD27/$K$2)^(1/((DATE(2029-1,12,31)-$K$3)/365.25))-1,"") -> -0.099635088 | AE29: =IFERROR((AE27/$K$2)^(1/((DATE(2030-1,12,31)-$K$3)/365.25))-1,"") -> -0.052467044 | AF29: =IFERROR((AF27/$K$2)^(1/((DATE(2031-1,12,31)-$K$3)/365.25))-1,"") -> -0.030953355
B31: Free Cash Flow | C31: =Model!W281 -> 9050 | D31: =Model!X281 -> 11058.815 | E31: =Model!Y281 -> 12393.114 | F31: =Model!Z281 -> 13376.764 | G31: =Model!AA281 -> 14574.508 | H31: =Model!AB281 -> 15514.258 | I31: =IFERROR((H31/C31)^(1/5)-1,"n/m") -> 0.11382378 | N31: Free Cash Flow | O31: 9200 | P31: 12276.871 | Q31: 13885.486 | R31: 15396.073 | S31: 17253.113 | T31: 18895.307 | U31: 0.15481715 | Z31: Free Cash Flow | AA31: 8900 | AB31: 9058.2312 | AC31: 9740.4284 | AD31: 9940.2015 | AE31: 10319.923 | AF31: 10468.999 | AG31: 0.033006439
B32: FCF % | C32: =IFERROR(C31/C9,"") -> 0.18121761 | D32: =IFERROR(D31/D9,"") -> 0.1962678 | E32: =IFERROR(E31/E9,"") -> 0.19643491 | F32: =IFERROR(F31/F9,"") -> 0.19597397 | G32: =IFERROR(G31/G9,"") -> 0.19884824 | H32: =IFERROR(H31/H9,"") -> 0.19893517 | J32: =IFERROR(AVERAGE(Model!C293,Model!H293,Model!M293,Model!R293),"") -> 0.16787129 | K32: =IFERROR(MIN(Model!C293,Model!H293,Model!M293,Model!R293),"") -> 0.14844019 | L32: =IFERROR(MAX(Model!C293,Model!H293,Model!M293,Model!R293),"") -> 0.1817967 | N32: FCF % | O32: 0.18267314 | P32: 0.20992731 | Q32: 0.20599727 | R32: 0.20492044 | S32: 0.20761192 | T32: 0.20745328 | V32: 0.16787129 | W32: 0.14844019 | X32: 0.1817967 | Z32: FCF % | AA32: 0.1797372 | AB32: 0.17006973 | AC32: 0.17113506 | AD32: 0.16959171 | AE32: 0.17241677 | AF32: 0.17284821 | AH32: 0.16787129 | AI32: 0.14844019 | AJ32: 0.1817967
B33: FCF / share ($) | C33: =IFERROR(C31/C21,"") -> 8.6620733 | D33: =IFERROR(D31/D21,"") -> 10.686635 | E33: =IFERROR(E31/E21,"") -> 12.122196 | F33: =IFERROR(F31/F21,"") -> 13.434995 | G33: =IFERROR(G31/G21,"") -> 15.027291 | H33: =IFERROR(H31/H21,"") -> 16.41888 | N33: FCF / share ($) | O33: 8.81249 | P33: 12.052182 | Q33: 14.036697 | R33: 16.140043 | S33: 18.791618 | T33: 21.423264 | Z33: FCF / share ($) | AA33: 8.5118902 | AB33: 8.7197123 | AC33: 9.3404493 | AD33: 9.5657987 | AE33: 10.049178 | AF33: 10.314174
B34: FCF Yield (on PT) | F34: =IFERROR(F33/F$27,"") | G34: =IFERROR(G33/G$27,"") -> 0.030889172 | H34: =IFERROR(H33/H$27,"") -> 0.030404259 | N34: FCF Yield (on PT) | R34: =IFERROR(R33/R$27,"") | S34: =IFERROR(S33/S$27,"") -> 0.026935265 | T34: =IFERROR(T33/T$27,"") -> 0.026504648 | Z34: FCF Yield (on PT) | AD34: =IFERROR(AD33/AD$27,"") -> 0.039197161 | AE34: =IFERROR(AE33/AE$27,"") -> 0.038803892 | AF34: =IFERROR(AF33/AF$27,"") -> 0.038234772
B35: Adjusted EBITDA (pro forma CPP full year in 2027E) | C35: =Model!W227 -> 11907 | D35: =Model!X227 -> 14116.983 | E35: =Model!Y227 -> 15833.7 | F35: =Model!Z227 -> 17525.083 | G35: =Model!AA227 -> 19197.499 | H35: =Model!AB227 -> 20658.915 | I35: =IFERROR((H35/C35)^(1/5)-1,"n/m") -> 0.11650592 | N35: Adjusted EBITDA (pro forma CPP full year in 2027E) | O35: 12007 | P35: 15231.377 | Q35: 17582.406 | R35: 20025.785 | S35: 22571.531 | T35: 24993.28 | U35: 0.15791785 | Z35: Adjusted EBITDA (pro forma CPP full year in 2027E) | AA35: 11807 | AB35: 12330.243 | AC35: 13184.022 | AD35: 13893.143 | AE35: 14476.005 | AF35: 14826.737 | AG35: 0.046601143
B36: Adjusted EBITDA (pro forma) % of adjusted revenue | C36: =IFERROR(C35/C9,"") -> 0.2384263 | D36: =IFERROR(D35/D9,"") -> 0.25054305 | E36: =IFERROR(E35/E9,"") -> 0.25096933 | F36: =IFERROR(F35/F9,"") -> 0.25674819 | G36: =IFERROR(G35/G9,"") -> 0.26192231 | H36: =IFERROR(H35/H9,"") -> 0.26490372 | J36: =IFERROR(AVERAGE(Model!C267,Model!H267,Model!M267,Model!R267),"") -> 0.23129992 | K36: =IFERROR(MIN(Model!C267,Model!H267,Model!M267,Model!R267),"") -> 0.21083263 | L36: =IFERROR(MAX(Model!C267,Model!H267,Model!M267,Model!R267),"") -> 0.24280516 | N36: Adjusted EBITDA (pro forma) % of adjusted revenue | O36: 0.2384083 | P36: 0.26044764 | Q36: 0.26084271 | R36: 0.26654152 | S36: 0.27161005 | T36: 0.27440347 | V36: 0.23129992 | W36: 0.21083263 | X36: 0.24280516 | Z36: Adjusted EBITDA (pro forma) % of adjusted revenue | AA36: 0.23844461 | AB36: 0.23150227 | AC36: 0.23163749 | AD36: 0.23703362 | AE36: 0.24185316 | AF36: 0.24479657 | AH36: 0.23129992 | AI36: 0.21083263 | AJ36: 0.24280516
B38: Net Debt | C38: =Model!W465 -> 10558.145 | D38: =Model!X465 -> 14116.983 | E38: =Model!Y465 -> 15833.7 | F38: =Model!Z465 -> 17525.083 | G38: =Model!AA465 -> 19197.499 | H38: =Model!AB465 -> 20658.915 | N38: Net Debt | O38: 11406.619 | P38: 22847.065 | Q38: 26373.61 | R38: 30038.677 | S38: 33857.297 | T38: 37489.92 | Z38: Net Debt | AA38: 9709.6708 | AB38: 14777.915 | AC38: 7857.8792 | AD38: 6946.5717 | AE38: 7238.0024 | AF38: 7413.3686
B39: Net Debt / Adjusted EBITDA (x) | C39: =IFERROR(C38/C35,"") -> 0.88671747 | D39: =IFERROR(D38/D35,"") -> 1 | E39: =IFERROR(E38/E35,"") -> 1 | F39: =IFERROR(F38/F35,"") -> 1 | G39: =IFERROR(G38/G35,"") -> 1 | H39: =IFERROR(H38/H35,"") -> 1 | N39: Net Debt / Adjusted EBITDA (x) | O39: 0.94999741 | P39: 1.5 | Q39: 1.5 | R39: 1.5 | S39: 1.5 | T39: 1.5 | Z39: Net Debt / Adjusted EBITDA (x) | AA39: 0.82236562 | AB39: 1.1985097 | AC39: 0.59601532 | AD39: 0.5 | AE39: 0.5 | AF39: 0.5
B40: Share repurchases ($m; FY2026E = 2H) | D40: =Model!X338 -> 498.19707 | E40: =Model!Y338 -> 11301.234 | F40: =Model!Z338 -> 11604.27 | G40: =Model!AA338 -> 12438.656 | H40: =Model!AB338 -> 12783.288 | N40: Share repurchases ($m; FY2026E = 2H) | P40: 9104.8805 | Q40: 14175.837 | R40: 15203.405 | S40: 16916.03 | T40: 18051.397 | AB40: 0 | AC40: 0 | AD40: 5961.5058 | AE40: 7136.2275 | AF40: 6712.2417
B41: Implied avg buyback price ($) | D41: =Model!X337 -> 332.64 | E41: =Model!Y337 -> 359.2512 | F41: =Model!Z337 -> 387.9913 | G41: =Model!AA337 -> 419.0306 | H41: =Model!AB337 -> 452.55305 | N41: Implied avg buyback price ($) | P41: 332.64 | Q41: 359.2512 | R41: 387.9913 | S41: 419.0306 | T41: 452.55305 | AB41: 332.64 | AC41: 359.2512 | AD41: 387.9913 | AE41: 419.0306 | AF41: 452.55305
B42: Shares repurchased (m) | D42: =Model!X339 -> 1.4977065 | E42: =Model!Y339 -> 31.457749 | F42: =Model!Z339 -> 29.908584 | G42: =Model!AA339 -> 29.684362 | H42: =Model!AB339 -> 28.247049 | N42: Shares repurchased (m) | P42: 27.371575 | Q42: 39.4594 | R42: 39.184914 | S42: 40.369438 | T42: 39.887915 | AB42: 0 | AC42: 0 | AD42: 15.36505 | AE42: 17.030325 | AF42: 14.831945
B44: ROIC | C44: =Model!W447 -> 0.31935731 | D44: =Model!X447 -> 0.25925911 | E44: =Model!Y447 -> 0.29901478 | F44: =Model!Z447 -> 0.33208645 | G44: =Model!AA447 -> 0.36522213 | H44: =Model!AB447 -> 0.39301733 | J44: =IFERROR(AVERAGE(Model!C447,Model!H447,Model!M447,Model!R447),"") -> 0.20880481 | K44: =IFERROR(MIN(Model!C447,Model!H447,Model!M447,Model!R447),"") -> 0.1171593 | L44: =IFERROR(MAX(Model!C447,Model!H447,Model!M447,Model!R447),"") -> 0.27815169 | N44: ROIC | O44: 0.32310604 | P44: 0.28134415 | Q44: 0.33308913 | R44: 0.380477 | S44: 0.43098453 | T44: 0.47829921 | V44: 0.20880481 | W44: 0.1171593 | X44: 0.27815169 | Z44: ROIC | AA44: 0.31562637 | AB44: 0.21916681 | AC44: 0.23723464 | AD44: 0.24980269 | AE44: 0.26011366 | AF44: 0.26519029 | AH44: 0.20880481 | AI44: 0.1171593 | AJ44: 0.27815169
B45: RONTA | C45: =Model!W459 -> 0.32632787 | D45: =Model!X459 -> 0.35524766 | E45: =Model!Y459 -> 0.41804085 | F45: =Model!Z459 -> 0.47710265 | G45: =Model!AA459 -> 0.53911923 | H45: =Model!AB459 -> 0.5952346 | J45: =IFERROR(AVERAGE(Model!C459,Model!H459,Model!M459,Model!R459),"") -> 0.22066741 | K45: =IFERROR(MIN(Model!C459,Model!H459,Model!M459,Model!R459),"") -> 0.14409608 | L45: =IFERROR(MAX(Model!C459,Model!H459,Model!M459,Model!R459),"") -> 0.28281287 | N45: RONTA | O45: 0.33017559 | P45: 0.39096308 | Q45: 0.47916945 | R45: 0.57122216 | S45: 0.67616904 | T45: 0.78401146 | V45: 0.22066741 | W45: 0.14409608 | X45: 0.28281287 | Z45: RONTA | AA45: 0.32249882 | AB45: 0.2985539 | AC45: 0.32777984 | AD45: 0.34872349 | AE45: 0.36658021 | AF45: 0.37677742 | AH45: 0.22066741 | AI45: 0.14409608 | AJ45: 0.28281287
B47: Implied Market Cap (USDm) | F47: =IF(ISNUMBER(F27),F27*F21,"") | G47: =IF(ISNUMBER(G27),G27*G21,"") -> 471832.27 | H47: =IF(ISNUMBER(H27),H27*H21,"") -> 510265.95 | N47: Implied Market Cap (USDm) | R47: =IF(ISNUMBER(R27),R27*R21,"") | S47: =IF(ISNUMBER(S27),S27*S21,"") -> 640539.95 | T47: =IF(ISNUMBER(T27),T27*T21,"") -> 712905.44 | Z47: Implied Market Cap (USDm) | AD47: =IF(ISNUMBER(AD27),AD27*AD21,"") -> 253594.93 | AE47: =IF(ISNUMBER(AE27),AE27*AE21,"") -> 265950.73 | AF47: =IF(ISNUMBER(AF27),AF27*AF21,"") -> 273808.32
B48: (+) Net Debt & NCI | F48: =IF(ISNUMBER(F27),F38+Model!Z377,"") | G48: =IF(ISNUMBER(G27),G38+Model!AA377,"") -> 19424.499 | H48: =IF(ISNUMBER(H27),H38+Model!AB377,"") -> 20885.915 | N48: (+) Net Debt & NCI | R48: =IF(ISNUMBER(R27),R38+Model!Z377,"") | S48: =IF(ISNUMBER(S27),S38+Model!AA377,"") -> 34084.297 | T48: =IF(ISNUMBER(T27),T38+Model!AB377,"") -> 37716.92 | Z48: (+) Net Debt & NCI | AD48: =IF(ISNUMBER(AD27),AD38+Model!Z377,"") -> 7173.5717 | AE48: =IF(ISNUMBER(AE27),AE38+Model!AA377,"") -> 7465.0024 | AF48: =IF(ISNUMBER(AF27),AF38+Model!AB377,"") -> 7640.3686
B49: Implied Enterprise Value (USDm) | F49: =IF(ISNUMBER(F27),F47+F48,"") | G49: =IF(ISNUMBER(G27),G47+G48,"") -> 491256.77 | H49: =IF(ISNUMBER(H27),H47+H48,"") -> 531151.86 | N49: Implied Enterprise Value (USDm) | R49: =IF(ISNUMBER(R27),R47+R48,"") | S49: =IF(ISNUMBER(S27),S47+S48,"") -> 674624.25 | T49: =IF(ISNUMBER(T27),T47+T48,"") -> 750622.36 | Z49: Implied Enterprise Value (USDm) | AD49: =IF(ISNUMBER(AD27),AD47+AD48,"") -> 260768.51 | AE49: =IF(ISNUMBER(AE27),AE47+AE48,"") -> 273415.73 | AF49: =IF(ISNUMBER(AF27),AF47+AF48,"") -> 281448.69
B50: Implied EV / Adjusted EBITDA (x) | F50: =IFERROR(F49/F35,"") | G50: =IFERROR(G49/G35,"") -> 25.589624 | H50: =IFERROR(H49/H35,"") -> 25.71054 | N50: Implied EV / Adjusted EBITDA (x) | R50: =IFERROR(R49/R35,"") | S50: =IFERROR(S49/S35,"") -> 29.88828 | T50: =IFERROR(T49/T35,"") -> 30.032967 | Z50: Implied EV / Adjusted EBITDA (x) | AD50: =IFERROR(AD49/AD35,"") -> 18.769583 | AE50: =IFERROR(AE49/AE35,"") -> 18.887513 | AF50: =IFERROR(AF49/AF35,"") -> 18.98251

Sheet DCF
B2: DCF VALUATION — GENERAL ELECTRIC COMPANY, OPERATING AS GE AEROSPACE (GE)
B4: 1. WACC BUILD
B5: Risk-free rate (US 10Y govt) | C5: 0.0425 | D5: Assumption (~US 10Y Treasury yield, Oct-2026; government rate sources not reachable from the build environment); update to market
B6: Equity risk premium | C6: 0.05 | D6: Assumption: US implied ERP ~4.5–5.5%
B7: Levered beta | C7: 1.1 | D7: Assumption: aero-engine and aerospace peers (RTX, Safran, Rolls-Royce, MTU, HEI, TDG) ~1.0–1.3; long-cycle services annuity vs airline-traffic and production-rate cyclicality
B8: Cost of equity | C8: =C5+C7*C6 -> 0.0975
B9: Pre-tax cost of debt | C9: 0.05 | D9: A2 / A- ratings (Q2-26 10-Q); 2025 senior notes at 4.3% (2030) and 4.9% (2036); CPP acquisition debt (2027E) assumed ~5%
B10: Tax rate | C10: 0.17 | D10: Model 2027E+ adjusted effective tax rate (FY2025 adjusted 17.3%; H1-26 15.7%)
B11: After-tax cost of debt | C11: =C9*(1-C10) -> 0.0415
B12: Target D/V | C12: 0.05 | D12: Net debt ~$10bn at 30-Jun-2026 (~$15bn pro forma for CPP) vs ~$320bn market cap ($308.00 × ~1,043m diluted shares)
B13: WACC | C13: =C8*(1-C12)+C11*C12 -> 0.0947
B15: Valuation date (live) | C15: =TODAY() -> 2026-10-13 00:00:00 | D15: Periods = (31-Dec of the fiscal year − today) / 365.25; cash flows assumed at year end; FY2026E (ends 31-Dec-2026, ~3 months after the valuation date) is the base year
B16: 2. UNLEVERED FREE CASH FLOW BUILD (USDm)
D17: 2027E | E17: 2028E | F17: 2029E | G17: 2030E | H17: 2031E | I17: 2032E | J17: 2033E | K17: 2034E | L17: 2035E | M17: 2036E | N17: Terminal | P17: CAGR 27–31E | Q17: CAGR 27–36E
B18: Operating profit (full-cost) less restructuring & separation costs | D18: =Model!X229-Model!X231 -> 12107.876 | E18: =Model!Y229-Model!Y231 -> 13645.819 | F18: =Model!Z229-Model!Z231 -> 15355.543 | G18: =Model!AA229-Model!AA231 -> 16916.263 | H18: =Model!AB229-Model!AB231 -> 18277.789 | I18: =H18*(1+I$26) -> 19922.79 | J18: =I18*(1+J$26) -> 21516.613 | K18: =J18*(1+K$26) -> 23022.776 | L18: =K18*(1+L$26) -> 24404.143 | M18: =L18*(1+M$26) -> 25624.35 | P18: =IFERROR((H18/D18)^(1/(COLUMNS(D18:H18)-1))-1,"n/m") -> 0.10844442 | Q18: =IFERROR((M18/D18)^(1/(COLUMNS(D18:M18)-1))-1,"n/m") -> 0.086866239
B19: × (1 − tax rate) | D19: =1-$C$10 -> 0.83 | E19: =1-$C$10 -> 0.83 | F19: =1-$C$10 -> 0.83 | G19: =1-$C$10 -> 0.83 | H19: =1-$C$10 -> 0.83 | I19: =1-$C$10 -> 0.83 | J19: =1-$C$10 -> 0.83 | K19: =1-$C$10 -> 0.83 | ... M19: =1-$C$10 -> 0.83
B20: NOPAT | D20: =D18*D19 -> 10049.537 | E20: =E18*E19 -> 11326.03 | F20: =F18*F19 -> 12745.101 | G20: =G18*G19 -> 14040.498 | H20: =H18*H19 -> 15170.565 | I20: =I18*I19 -> 16535.916 | J20: =J18*J19 -> 17858.789 | K20: =K18*K19 -> 19108.904 | ... M20: =M18*M19 -> 21268.21
B21: plus D&A (PP&E depreciation + amortization of intangibles, incl. CPP PPA) | D21: =Model!X132 -> 1520.1069 | E21: =Model!Y132 -> 1937.88 | F21: =Model!Z132 -> 2069.5394 | G21: =Model!AA132 -> 2181.2358 | H21: =Model!AB132 -> 2281.1258 | I21: =H21*(1+I$26) -> 2486.4271 | J21: =I21*(1+J$26) -> 2685.3413 | K21: =J21*(1+K$26) -> 2873.3152 | L21: =K21*(1+L$26) -> 3045.7141 | M21: =L21*(1+M$26) -> 3197.9998
B22: − Capex (PP&E) and acquisitions (CPP $11.75bn in 2027E; M&A lever) | D22: =Model!X309+Model!X311 -> -13440.366 | E22: =Model!Y309+Model!Y311 -> -2018.8857 | F22: =Model!Z309+Model!Z311 -> -2615.9937 | G22: =Model!AA309+Model!AA311 -> -2698.8388 | H22: =Model!AB309+Model!AB311 -> -2839.5951 | I22: =Model!AB309*(1+I$26) -> -2550.1586 | J22: =I22*(1+J$26) -> -2754.1713 | K22: =J22*(1+K$26) -> -2946.9633 | L22: =K22*(1+L$26) -> -3123.7811 | M22: =L22*(1+M$26) -> -3279.9702
B23: − Δ Working capital (CF statement) | D23: =Model!X306 -> 1302.9663 | E23: =Model!Y306 -> 1361.9709 | F23: =Model!Z306 -> 1079.4279 | G23: =Model!AA306 -> 1045.4215 | H23: =Model!AB306 -> 968.0189 | I23: =H23*(1+I$26) -> 1055.1406 | J23: =I23*(1+J$26) -> 1139.5519 | K23: =J23*(1+K$26) -> 1219.3205 | L23: =K23*(1+L$26) -> 1292.4797 | M23: =L23*(1+M$26) -> 1357.1037
B24: Unlevered FCF | D24: =D20+D21+D22+D23 -> -567.75575 | E24: =E20+E21+E22+E23 -> 12606.995 | F24: =F20+F21+F22+F23 -> 13278.074 | G24: =G20+G21+G22+G23 -> 14568.317 | H24: =H20+H21+H22+H23 -> 15580.114 | I24: =I20+I21+I22+I23 -> 17527.325 | J24: =J20+J21+J22+J23 -> 18929.511 | K24: =K20+K21+K22+K23 -> 20254.577 | ... M24: =M20+M21+M22+M23 -> 22543.344 | N24: =M24*(1+$C$27) -> 23332.361 | P24: =IFERROR((H24/D24)^(1/(COLUMNS(D24:H24)-1))-1,"n/m") -> n/m | Q24: =IFERROR((M24/D24)^(1/(COLUMNS(D24:M24)-1))-1,"n/m") -> -2.505396
B25: Terminal Value (Gordon Growth) | N25: =N24/($C$13-$C$27) -> 390826.81
B26: Fade-period growth (2032E–36E; 9.0% → 5.0% linear) | I26: 0.09 | J26: =I26+($M$26-$I$26)/4 -> 0.08 | K26: =J26+($M$26-$I$26)/4 -> 0.07 | L26: =K26+($M$26-$I$26)/4 -> 0.06 | M26: 0.05
B27: Terminal growth rate | C27: 0.035
B29: Discount period (years) | D29: =(DATE(2027,12,31)-$C$15)/365.25 -> 1.2156057 | E29: =(DATE(2028,12,31)-$C$15)/365.25 -> 2.2176591 | F29: =(DATE(2029,12,31)-$C$15)/365.25 -> 3.2169747 | G29: =(DATE(2030,12,31)-$C$15)/365.25 -> 4.2162902 | H29: =(DATE(2031,12,31)-$C$15)/365.25 -> 5.2156057 | I29: =(DATE(2032,12,31)-$C$15)/365.25 -> 6.2176591 | J29: =(DATE(2033,12,31)-$C$15)/365.25 -> 7.2169747 | K29: =(DATE(2034,12,31)-$C$15)/365.25 -> 8.2162902 | L29: =(DATE(2035,12,31)-$C$15)/365.25 -> 9.2156057 | M29: =(DATE(2036,12,31)-$C$15)/365.25 -> 10.217659 | N29: =M29 -> 10.217659
B30: Discount factor | D30: =1/(1+$C$13)^D29 -> 0.89584449 | E30: =1/(1+$C$13)^E29 -> 0.818195 | F30: =1/(1+$C$13)^F29 -> 0.74746111 | G30: =1/(1+$C$13)^G29 -> 0.68284224 | H30: =1/(1+$C$13)^H29 -> 0.62380975 | I30: =1/(1+$C$13)^I29 -> 0.56973953 | J30: =1/(1+$C$13)^J29 -> 0.52048489 | K30: =1/(1+$C$13)^K29 -> 0.47548838 | ... N30: =1/(1+$C$13)^N29 -> 0.39673076
B31: PV of UFCF | D31: =D24*D30 -> -508.62086 | E31: =E24*E30 -> 10314.981 | F31: =F24*F30 -> 9924.8443 | G31: =G24*G30 -> 9947.8619 | H31: =H24*H30 -> 9719.0273 | I31: =I24*I30 -> 9986.0097 | J31: =J24*J30 -> 9852.5244 | K31: =K24*K30 -> 9630.8157 | ... M31: =M24*M30 -> 8943.6379 | N31: =N25*N30 -> 155053.02
D32: GE Aerospace operating profit already deducts amortization of intangibles and stock-based compensation (neither is adjusted out); D&A is added back in row 21. Restructuring and separation costs (cash; excluded from operating profit) are deducted in row 18. Run-off insurance, U.S. tax equity and non-operating pension income are excluded from NOPAT, and the insurance balance sheet from net debt. Row 22 includes the $11.75bn CPP consideration in FY2027E (its operating profit is in NOPAT from closing) and bolt-ons from the M&A lever; the fade period and terminal value assume no further acquisitions.
B33: IMPLIED ROIC — invested capital roll-forward (USDm)
B34: Opening invested capital | D34: =Model!W444 -> 27995.445 | E34: =D38 -> 38612.738 | F34: =E38 -> 37331.773 | G34: =F38 -> 36798.799 | H34: =G38 -> 36270.981 | I34: =H38 -> 35861.431 | J34: =I38 -> 34870.022 | K34: =J38 -> 33799.3 | L34: =K38 -> 32653.628 | M34: =L38 -> 31439.215
B35: plus Capex and acquisitions | D35: =-D22 -> 13440.366 | E35: =-E22 -> 2018.8857 | F35: =-F22 -> 2615.9937 | G35: =-G22 -> 2698.8388 | H35: =-H22 -> 2839.5951 | I35: =-I22 -> 2550.1586 | J35: =-J22 -> 2754.1713 | K35: =-K22 -> 2946.9633 | ... M35: =-M22 -> 3279.9702
B36: less DD&A | D36: =-D21 -> -1520.1069 | E36: =-E21 -> -1937.88 | F36: =-F21 -> -2069.5394 | G36: =-G21 -> -2181.2358 | H36: =-H21 -> -2281.1258 | I36: =-I21 -> -2486.4271 | J36: =-J21 -> -2685.3413 | K36: =-K21 -> -2873.3152 | ... M36: =-M21 -> -3197.9998
B37: plus Δ Working capital investment | D37: =-D23 -> -1302.9663 | E37: =-E23 -> -1361.9709 | F37: =-F23 -> -1079.4279 | G37: =-G23 -> -1045.4215 | H37: =-H23 -> -968.0189 | I37: =-I23 -> -1055.1406 | J37: =-J23 -> -1139.5519 | K37: =-K23 -> -1219.3205 | ... M37: =-M23 -> -1357.1037
B38: Closing invested capital | D38: =SUM(D34:D37) -> 38612.738 | E38: =SUM(E34:E37) -> 37331.773 | F38: =SUM(F34:F37) -> 36798.799 | G38: =SUM(G34:G37) -> 36270.981 | H38: =SUM(H34:H37) -> 35861.431 | I38: =SUM(I34:I37) -> 34870.022 | J38: =SUM(J34:J37) -> 33799.3 | K38: =SUM(K34:K37) -> 32653.628 | ... M38: =SUM(M34:M37) -> 30164.082
B39: NOPAT (row 20) | D39: =D20 -> 10049.537 | E39: =E20 -> 11326.03 | F39: =F20 -> 12745.101 | G39: =G20 -> 14040.498 | H39: =H20 -> 15170.565 | I39: =I20 -> 16535.916 | J39: =J20 -> 17858.789 | K39: =K20 -> 19108.904 | ... M39: =M20 -> 21268.21
B40: Implied ROIC (NOPAT / avg. invested capital) | D40: =IFERROR(D39/AVERAGE(D34,D38),"") -> 0.30175083 | E40: =IFERROR(E39/AVERAGE(E34,E38),"") -> 0.2982712 | F40: =IFERROR(F39/AVERAGE(F34,F38),"") -> 0.34385546 | G40: =IFERROR(G39/AVERAGE(G34,G38),"") -> 0.38430383 | H40: =IFERROR(H39/AVERAGE(H34,H38),"") -> 0.42063102 | I40: =IFERROR(I39/AVERAGE(I34,I38),"") -> 0.46756895 | J40: =IFERROR(J39/AVERAGE(J34,J38),"") -> 0.52013879 | K40: =IFERROR(K39/AVERAGE(K34,K38),"") -> 0.57511098 | ... M40: =IFERROR(M39/AVERAGE(M34,M38),"") -> 0.69048935
B41: Reinvestment rate (net investment / NOPAT) | D41: =IFERROR(SUM(D35:D37)/D39,"") -> 1.0564957 | E41: =IFERROR(SUM(E35:E37)/E39,"") -> -0.11309923 | F41: =IFERROR(SUM(F35:F37)/F39,"") -> -0.041817915 | G41: =IFERROR(SUM(G35:G37)/G39,"") -> -0.037592573 | H41: =IFERROR(SUM(H35:H37)/H39,"") -> -0.026996332 | I41: =IFERROR(SUM(I35:I37)/I39,"") -> -0.059954894 | J41: =IFERROR(SUM(J35:J37)/J39,"") -> -0.059954894 | K41: =IFERROR(SUM(K35:K37)/K39,"") -> -0.059954894 | ... M41: =IFERROR(SUM(M35:M37)/M39,"") -> -0.059954894
B42: Implied terminal RONIC (g / reinvestment rate) | N42: =IFERROR($C$27/M41,"") -> -0.5837722
D43: Opening IC = Model FY2026E book IC (equity + net debt at 31-Dec-2026E), rolled forward with capex + acquisitions − D&A + ΔWC.
B44: 3. VALUATION SUMMARY
B45: Sum of PV (explicit + fade) | C45: =SUM(D31:M31) -> 87137.195
B46: PV of Terminal Value | C46: =N31 -> 155053.02
B47: Enterprise Value | C47: =C45+C46 -> 242190.21
B48: Less: Net debt + NCI (Model FY2026E year end, 31-Dec-2026) | C48: =Model!W465+Model!W377 -> 10785.145 | D48: GE Aerospace: NCI ~$0.2bn; net debt at the base-year end so that FY2027E+ cash flows are not double counted. Run-off insurance (investment securities vs insurance liabilities) not deducted (assumed self-funding).
B49: Equity Value | C49: =C47-C48 -> 231405.07
B50: Diluted shares (m, Model FY2026E period end) | C50: =Model!W472 -> 1033.5755
B51: Implied share price ($) | C51: =C49/C50 -> 223.88792
B52: Current share price ($) | C52: =Model!W471 -> 308
B53: Implied upside / (downside) | C53: =C51/C52-1 -> -0.27309117
B54: Required discount to DCF value for target IRR | C54: =1-((1+C13)/(1+H54))^H55 -> 0.137435 | D54: vs. current | E54: Target IRR | H54: 0.15
B55: Max entry price for target IRR ($) | C55: =C51*(1-C54) -> 193.11788 | D55: =C55/C52-1 -> -0.37299388 | E55: Years for discount to close | H55: 3
B58: 4. SENSITIVITY: IMPLIED PRICE ($) — WACC × Terminal Growth
D60: WACC →
B61: Terminal growth ↓ | D61: =F61-0.01 -> 0.0847 | E61: =F61-0.005 -> 0.0897 | F61: =$C$13 -> 0.0947 | G61: =F61+0.005 -> 0.0997 | H61: =F61+0.01 -> 0.1047
B62: =B64-0.01 -> 0.025 | D62: {=IFERROR((SUMPRODUCT($D$24:$M$24/(1+D$61)^$D$29:$M$29)+($M$24*(1+$B62)/(D$61-$B62))/(1+D$61)^$M$29-$C$48)/$C$50,"")} -> 241.96784 | E62: {=IFERROR((SUMPRODUCT($D$24:$M$24/(1+E$61)^$D$29:$M$29)+($M$24*(1+$B62)/(E$61-$B62))/(1+E$61)^$M$29-$C$48)/$C$50,"")} -> 219.93775 | F62: {=IFERROR((SUMPRODUCT($D$24:$M$24/(1+F$61)^$D$29:$M$29)+($M$24*(1+$B62)/(F$61-$B62))/(1+F$61)^$M$29-$C$48)/$C$50,"")} -> 201.12332 | G62: {=IFERROR((SUMPRODUCT($D$24:$M$24/(1+G$61)^$D$29:$M$29)+($M$24*(1+$B62)/(G$61-$B62))/(1+G$61)^$M$29-$C$48)/$C$50,"")} -> 184.87708 | H62: {=IFERROR((SUMPRODUCT($D$24:$M$24/(1+H$61)^$D$29:$M$29)+($M$24*(1+$B62)/(H$61-$B62))/(1+H$61)^$M$29-$C$48)/$C$50,"")} -> 170.71409
B63: =B64-0.005 -> 0.03 | D63: {=IFERROR((SUMPRODUCT($D$24:$M$24/(1+D$61)^$D$29:$M$29)+($M$24*(1+$B63)/(D$61-$B63))/(1+D$61)^$M$29-$C$48)/$C$50,"")} -> 257.75167 | E63: {=IFERROR((SUMPRODUCT($D$24:$M$24/(1+E$61)^$D$29:$M$29)+($M$24*(1+$B63)/(E$61-$B63))/(1+E$61)^$M$29-$C$48)/$C$50,"")} -> 232.72817 | F63: {=IFERROR((SUMPRODUCT($D$24:$M$24/(1+F$61)^$D$29:$M$29)+($M$24*(1+$B63)/(F$61-$B63))/(1+F$61)^$M$29-$C$48)/$C$50,"")} -> 211.626 | G63: {=IFERROR((SUMPRODUCT($D$24:$M$24/(1+G$61)^$D$29:$M$29)+($M$24*(1+$B63)/(G$61-$B63))/(1+G$61)^$M$29-$C$48)/$C$50,"")} -> 193.59958 | H63: {=IFERROR((SUMPRODUCT($D$24:$M$24/(1+H$61)^$D$29:$M$29)+($M$24*(1+$B63)/(H$61-$B63))/(1+H$61)^$M$29-$C$48)/$C$50,"")} -> 178.02978
B64: =$C$27 -> 0.035 | D64: {=IFERROR((SUMPRODUCT($D$24:$M$24/(1+D$61)^$D$29:$M$29)+($M$24*(1+$B64)/(D$61-$B64))/(1+D$61)^$M$29-$C$48)/$C$50,"")} -> 276.71131 | E64: {=IFERROR((SUMPRODUCT($D$24:$M$24/(1+E$61)^$D$29:$M$29)+($M$24*(1+$B64)/(E$61-$B64))/(1+E$61)^$M$29-$C$48)/$C$50,"")} -> 247.85687 | F64: {=IFERROR((SUMPRODUCT($D$24:$M$24/(1+F$61)^$D$29:$M$29)+($M$24*(1+$B64)/(F$61-$B64))/(1+F$61)^$M$29-$C$48)/$C$50,"")} -> 223.88792 | G64: {=IFERROR((SUMPRODUCT($D$24:$M$24/(1+G$61)^$D$29:$M$29)+($M$24*(1+$B64)/(G$61-$B64))/(1+G$61)^$M$29-$C$48)/$C$50,"")} -> 203.67023 | H64: {=IFERROR((SUMPRODUCT($D$24:$M$24/(1+H$61)^$D$29:$M$29)+($M$24*(1+$B64)/(H$61-$B64))/(1+H$61)^$M$29-$C$48)/$C$50,"")} -> 186.39507
B65: =B64+0.005 -> 0.04 | D65: {=IFERROR((SUMPRODUCT($D$24:$M$24/(1+D$61)^$D$29:$M$29)+($M$24*(1+$B65)/(D$61-$B65))/(1+D$61)^$M$29-$C$48)/$C$50,"")} -> 299.91249 | E65: {=IFERROR((SUMPRODUCT($D$24:$M$24/(1+E$61)^$D$29:$M$29)+($M$24*(1+$B65)/(E$61-$B65))/(1+E$61)^$M$29-$C$48)/$C$50,"")} -> 266.02958 | F65: {=IFERROR((SUMPRODUCT($D$24:$M$24/(1+F$61)^$D$29:$M$29)+($M$24*(1+$B65)/(F$61-$B65))/(1+F$61)^$M$29-$C$48)/$C$50,"")} -> 238.39151 | G65: {=IFERROR((SUMPRODUCT($D$24:$M$24/(1+G$61)^$D$29:$M$29)+($M$24*(1+$B65)/(G$61-$B65))/(1+G$61)^$M$29-$C$48)/$C$50,"")} -> 215.42775 | H65: {=IFERROR((SUMPRODUCT($D$24:$M$24/(1+H$61)^$D$29:$M$29)+($M$24*(1+$B65)/(H$61-$B65))/(1+H$61)^$M$29-$C$48)/$C$50,"")} -> 196.0533
B66: =B64+0.01 -> 0.045 | D66: {=IFERROR((SUMPRODUCT($D$24:$M$24/(1+D$61)^$D$29:$M$29)+($M$24*(1+$B66)/(D$61-$B66))/(1+D$61)^$M$29-$C$48)/$C$50,"")} -> 328.95779 | E66: {=IFERROR((SUMPRODUCT($D$24:$M$24/(1+E$61)^$D$29:$M$29)+($M$24*(1+$B66)/(E$61-$B66))/(1+E$61)^$M$29-$C$48)/$C$50,"")} -> 288.26777 | F66: {=IFERROR((SUMPRODUCT($D$24:$M$24/(1+F$61)^$D$29:$M$29)+($M$24*(1+$B66)/(F$61-$B66))/(1+F$61)^$M$29-$C$48)/$C$50,"")} -> 255.81332 | G66: {=IFERROR((SUMPRODUCT($D$24:$M$24/(1+G$61)^$D$29:$M$29)+($M$24*(1+$B66)/(G$61-$B66))/(1+G$61)^$M$29-$C$48)/$C$50,"")} -> 229.33473 | H66: {=IFERROR((SUMPRODUCT($D$24:$M$24/(1+H$61)^$D$29:$M$29)+($M$24*(1+$B66)/(H$61-$B66))/(1+H$61)^$M$29-$C$48)/$C$50,"")} -> 207.32932
B69: 5. REVERSE DCF
B70: To solve for the market-implied path: Data ▸ What-If Analysis ▸ Goal Seek — set C51 to the current price (C52) by changing C27 (terminal growth) or the fade-period growth inputs (I26:M26).
B72: 6. MAUBOUSSIN EV / NOPAT — TWO-STAGE FRAMEWORK
B73: EV/NOPAT = 1/r + [g × (1 − r/ROIIC) / (r × (r − g))] × [1 − ((1+g)/(1+r))^N]
B74: Formula source: Mauboussin & Rappaport, "Expectations Investing" (2021); Counterpoint Global, "What Does a Price-Earnings Multiple Mean?" (2020).
B76: Input | C76: Value | D76: Rationale (GE Aerospace characteristics)
B77: r (Cost of capital / WACC) | C77: =$C$13 -> 0.0947 | D77: Linked from Section 1 WACC build
B78: g (NOPAT growth, Stage 1) | C78: 0.11 | D78: Model operating profit CAGR FY2026–31E: services growth on a ~50,000-engine commercial installed base, LEAP shop-visit ramp, DPT, plus CPP → ~11% NOPAT growth
B79: ROIIC (Return on incremental invested capital) | C79: 0.35 | D79: Installed-base aftermarket (CES services ~60% of revenue) earns very high incremental returns; new engines are sold near cost and repaid by decades of services
B80: N (Years of value creation / CAP) | C80: 20 | D80: Duopoly / joint-venture positions (CFM with Safran) on narrowbody and widebody platforms, certification barriers and 25–30-year engine lives sustain a long competitive-advantage period
B82: Calculation | C82: Value
B83: Steady-state component: 1 / r | C83: =1/C77 -> 10.559662
B84: Value-creation factor: 1 − r / ROIIC | C84: =1-C77/C79 -> 0.72942857
B85: Growth multiplier: g × (1 − r/ROIIC) / (r × (r − g)) | C85: =C78*C84/(C77*(C77-C78)) -> -55.377589
B86: Time decay: 1 − ((1+g)/(1+r))^N | C86: =1-((1+C78)/(1+C77))^C80 -> -0.31994919
B87: PVGO component (growth value) | C87: =C85*C86 -> 17.718015
B88: Mauboussin EV / NOPAT (steady-state + PVGO) | C88: =C83+C87 -> 28.277677
B90: VALUATION — Applied to FY2029E NOPAT | C90: USDm
B91: FY2029E operating profit less restructuring & separation costs | C91: =Model!Z229-Model!Z231 -> 15355.543
B92: Tax rate (from WACC build) | C92: =$C$10 -> 0.17
B93: FY2029E NOPAT | C93: =C91*(1-C92) -> 12745.101
B94: × Mauboussin EV/NOPAT multiple | C94: =C88 -> 28.277677
B95: Implied Enterprise Value (FY2029E basis) | C95: =C93*C94 -> 360401.85
B96: Less: FY2028E year-end net debt + NCI (Model) | C96: =Model!Y465+Model!Y377 -> 16060.7
B97: Implied Equity Value | C97: =C95-C96 -> 344341.15
B98: Diluted shares FY2029E (m, Model) | C98: =Model!Z472 -> 982.71146
B99: Implied share price FY2029 ($) | C99: =C97/C98 -> 350.39903
B101: Current share price ($) | C101: =C52 -> 308
B102: Implied upside / (downside) | C102: =C99/C101-1 -> 0.1376592
B104: MARKET-IMPLIED EV/NOPAT TODAY | C104: USDm
B105: Current market cap (spot × diluted shares) | C105: =C52*C50 -> 318341.25
B106: Plus: FY2026E year-end net debt + NCI | C106: =C48 -> 10785.145
B107: Implied Enterprise Value (today) | C107: =C105+C106 -> 329126.4
B108: GE market-implied EV/NOPAT (on FY2029E NOPAT) | C108: =C107/C93 -> 25.823758
B110: Multiple gap (Mauboussin − Market) | C110: =C88-C108 -> 2.4539192
B111: Implied re-rating headroom | C111: =C88/C108-1 -> 0.095025644

Sheet Charts
B2: General Electric Company (GE Aerospace) — Operating Performance (FY2023–FY2025) and Model Forecast (FY2026E–FY2031E)
B3: USDm · calendar years · Linked to Model. Bars = contribution of each segment to adjusted revenue growth (pp; segments as reported in each year, Jan-2026 structure from 2026). Adjusted EBITDA = operating profit + D&A (model). ROIC / RONTA on operating profit (full-cost); charts start in 2023, the first year with a GE Aerospace balance sheet.
C7: 2023 | D7: 2024 | E7: 2025 | F7: 2026E | G7: 2027E | H7: 2028E | I7: 2029E | J7: 2030E | K7: 2031E
B8: CES contribution to growth (pp) | C8: =IFERROR(Model!H272+0,0) -> 0.19257505 | D8: =IFERROR(Model!M272+0,0) -> 0.094683814 | E8: =IFERROR(Model!R272+0,0) -> 0.18317198 | F8: =IFERROR(Model!W272+0,0) -> 0.12561306 | G8: =IFERROR(Model!X272+0,0) -> 0.10460708 | H8: =IFERROR(Model!Y272+0,0) -> 0.083783799 | I8: =IFERROR(Model!Z272+0,0) -> 0.067495788 | J8: =IFERROR(Model!AA272+0,0) -> 0.058332425 | K8: =IFERROR(Model!AB272+0,0) -> 0.050717577
B9: DPT contribution to growth (pp) | C9: =IFERROR(Model!H273+0,0) -> 0.037124742 | D9: =IFERROR(Model!M273+0,0) -> 0.016176977 | E9: =IFERROR(Model!R273+0,0) -> 0.030637813 | F9: =IFERROR(Model!W273+0,0) -> 0.069392449 | G9: =IFERROR(Model!X273+0,0) -> 0.021611274 | H9: =IFERROR(Model!Y273+0,0) -> 0.018100928 | I9: =IFERROR(Model!Z273+0,0) -> 0.014826397 | J9: =IFERROR(Model!AA273+0,0) -> 0.014526151 | K9: =IFERROR(Model!AB273+0,0) -> 0.011949664
C11: =C7 -> 2023 | D11: =D7 -> 2024 | E11: =E7 -> 2025 | F11: =F7 -> 2026E | G11: =G7 -> 2027E | H11: =H7 -> 2028E | I11: =I7 -> 2029E | J11: =J7 -> 2030E | K11: =K7 -> 2031E
B12: Adjusted EBITDA | C12: =Model!H224 -> 6738 | D12: =Model!M224 -> 8438 | E12: =Model!R224 -> 10276 | F12: =Model!W224 -> 11907 | G12: =Model!X224 -> 13777.983 | H12: =Model!Y224 -> 15833.7 | I12: =Model!Z224 -> 17525.083 | J12: =Model!AA224 -> 19197.499 | K12: =Model!AB224 -> 20658.915
B13: Profit before tax (GAAP) | C13: =Model!H172 -> 10441 | D13: =Model!M172 -> 7620 | E13: =Model!R172 -> 10000 | F13: =Model!W172 -> 10301 | G13: =Model!X172 -> 12265.538 | H13: =Model!Y172 -> 13543.22 | I13: =Model!Z172 -> 15189.124 | J13: =Model!AA172 -> 16612.473 | K13: =Model!AB172 -> 17861.293
B14: Adj. EBITDA Margin % | C14: =Model!H267 -> 0.21083263 | D14: =Model!M267 -> 0.24026196 | E14: =Model!R267 -> 0.24280516 | F14: =Model!W267 -> 0.2384263 | G14: =Model!X267 -> 0.2445266 | H14: =Model!Y267 -> 0.25096933 | I14: =Model!Z267 -> 0.25674819 | J14: =Model!AA267 -> 0.26192231 | K14: =Model!AB267 -> 0.26490372
B15: Profit Margin (GAAP) % | C15: =Model!H268 -> 0.29537739 | D15: =Model!M268 -> 0.19688905 | E15: =Model!R268 -> 0.21807873 | F15: =Model!W268 -> 0.19463039 | G15: =Model!X268 -> 0.2070414 | H15: =Model!Y268 -> 0.2055126 | I15: =Model!Z268 -> 0.21398224 | J15: =Model!AA268 -> 0.21876331 | K15: =Model!AB268 -> 0.22173981
C17: =C7 -> 2023 | D17: =D7 -> 2024 | E17: =E7 -> 2025 | F17: =F7 -> 2026E | G17: =G7 -> 2027E | H17: =H7 -> 2028E | I17: =I7 -> 2029E | J17: =J7 -> 2030E | K17: =K7 -> 2031E
B18: ROIC | C18: =IFERROR(Model!H447+0,NA()) -> 0.1171593 | D18: =IFERROR(Model!M447+0,NA()) -> 0.23110345 | E18: =IFERROR(Model!R447+0,NA()) -> 0.27815169 | F18: =IFERROR(Model!W447+0,NA()) -> 0.31935731 | G18: =IFERROR(Model!X447+0,NA()) -> 0.25925911 | H18: =IFERROR(Model!Y447+0,NA()) -> 0.29901478 | I18: =IFERROR(Model!Z447+0,NA()) -> 0.33208645 | J18: =IFERROR(Model!AA447+0,NA()) -> 0.36522213 | K18: =IFERROR(Model!AB447+0,NA()) -> 0.39301733
B19: RONTA | C19: =IFERROR(Model!H459+0,NA()) -> 0.14409608 | D19: =IFERROR(Model!M459+0,NA()) -> 0.23509329 | E19: =IFERROR(Model!R459+0,NA()) -> 0.28281287 | F19: =IFERROR(Model!W459+0,NA()) -> 0.32632787 | G19: =IFERROR(Model!X459+0,NA()) -> 0.35524766 | H19: =IFERROR(Model!Y459+0,NA()) -> 0.41804085 | I19: =IFERROR(Model!Z459+0,NA()) -> 0.47710265 | J19: =IFERROR(Model!AA459+0,NA()) -> 0.53911923 | K19: =IFERROR(Model!AB459+0,NA()) -> 0.5952346
B20: Adj. EBITDA margin % | C20: =IFERROR(Model!H267+0,NA()) -> 0.21083263 | D20: =IFERROR(Model!M267+0,NA()) -> 0.24026196 | E20: =IFERROR(Model!R267+0,NA()) -> 0.24280516 | F20: =IFERROR(Model!W267+0,NA()) -> 0.2384263 | G20: =IFERROR(Model!X267+0,NA()) -> 0.2445266 | H20: =IFERROR(Model!Y267+0,NA()) -> 0.25096933 | I20: =IFERROR(Model!Z267+0,NA()) -> 0.25674819 | J20: =IFERROR(Model!AA267+0,NA()) -> 0.26192231 | K20: =IFERROR(Model!AB267+0,NA()) -> 0.26490372
B21: FCF margin % | C21: =IFERROR(Model!H293+0,NA()) -> 0.14844019 | D21: =IFERROR(Model!M293+0,NA()) -> 0.17337699 | E21: =IFERROR(Model!R293+0,NA()) -> 0.1817967 | F21: =IFERROR(Model!W293+0,NA()) -> 0.18121761 | G21: =IFERROR(Model!X293+0,NA()) -> 0.1962678 | H21: =IFERROR(Model!Y293+0,NA()) -> 0.19643491 | I21: =IFERROR(Model!Z293+0,NA()) -> 0.19597397 | J21: =IFERROR(Model!AA293+0,NA()) -> 0.19884824 | K21: =IFERROR(Model!AB293+0,NA()) -> 0.19893517
