Workbook

Sheet Model
CF1: SCENARIO SWITCH ▼ (Bull / Base / Bear) — drives all scenario-linked forecast drivers
B2: Alphabet Inc. (NASDAQ: GOOG) — 3-Statement Financial Model | CF2: Base
B3: US GAAP as originally reported · USD millions (per-share data in USD; shares in millions, split-adjusted) · Calendar fiscal year · Source: SEC EDGAR only — Google Inc. (CIK 1288776, to Q3-2015) and Alphabet Inc. (CIK 1652044) Forms 10-K / 10-Q (XBRL instance documents), Form 8-K earnings releases (Ex. 99.1); investor-relations releases are the same documents as filed on EDGAR. Capex outlook from the earnings call is UNVERIFIED.
B4: Basis notes: statements as originally reported; revenue types and segments from the latest filing presenting the period (recasts: Cloud split Q4-20, performance fees to OI&E 2019, Google DeepMind to Alphabet-level 2023). Splits: 2-for-1 Class C dividend Apr-2014, 20-for-1 Jul-2022. Disc ops: Motorola Home 2012–13, Motorola Mobile 2014. Deals: Wiz (11-Mar-2026, $29.5bn), Intersect (10-Mar-2026, $5.9bn); GFiber divestiture pending (late 2026). Jun-2026: $30.5bn common + $19.0bn 6.25% mandatory convertible preferred. No company guidance: Q3–Q4/26E from the 1H26 run-rate with scenario shifts.
CH5: Forecast | CI5: Historical | CJ5: Historical | CK5: Historical
B6: (USDm) | C6: 2006 | D6: 2007 | E6: 2008 | F6: 2009 | G6: 2010 | H6: 2011 | I6: 2012 | J6: Q1/13 | K6: Q2/13 | L6: Q3/13 | M6: Q4/13 | N6: 2013 | O6: Q1/14 | P6: Q2/14 | Q6: Q3/14 | R6: Q4/14 | S6: 2014 | T6: Q1/15 | U6: Q2/15 | V6: Q3/15 | W6: Q4/15 | X6: 2015 | Y6: Q1/16 | Z6: Q2/16 | AA6: Q3/16 | AB6: Q4/16 | AC6: 2016 | AD6: Q1/17 | AE6: Q2/17 | AF6: Q3/17 | AG6: Q4/17 | AH6: 2017 | AI6: Q1/18 | AJ6: Q2/18 | AK6: Q3/18 | AL6: Q4/18 | AM6: 2018 | AN6: Q1/19 | AO6: Q2/19 | AP6: Q3/19 | AQ6: Q4/19 | AR6: 2019 | AS6: Q1/20 | AT6: Q2/20 | AU6: Q3/20 | AV6: Q4/20 | AW6: 2020 | AX6: Q1/21 | AY6: Q2/21 | AZ6: Q3/21 | BA6: Q4/21 | BB6: 2021 | BC6: Q1/22 | BD6: Q2/22 | BE6: Q3/22 | BF6: Q4/22 | BG6: 2022 | BH6: Q1/23 | BI6: Q2/23 | BJ6: Q3/23 | BK6: Q4/23 | BL6: 2023 | BM6: Q1/24 | BN6: Q2/24 | BO6: Q3/24 | BP6: Q4/24 | BQ6: 2024 | BR6: Q1/25 | BS6: Q2/25 | BT6: Q3/25 | BU6: Q4/25 | BV6: 2025 | BW6: Q1/26 | BX6: Q2/26 | BY6: Q3/26E | BZ6: Q4/26E | CA6: 2026E | CB6: 2027E | CC6: 2028E | CD6: 2029E | CE6: 2030E | CF6: Modelling Notes | CH6: 5Y CAGR | CI6: 5Y CAGR | CJ6: 10Y CAGR | CK6: 19Y CAGR
CH7: 25-'30 | CI7: 20-'25 | CJ7: 15-'25 | CK7: 06-'25
B8: REVENUE BUILD — GOOGLE SERVICES (Search · YouTube · Network · Subscriptions/platforms/devices) · GOOGLE CLOUD · OTHER BETS | CF8: REVENUE BUILD — modelling logic (revenue by type → segment revenue → segment operating income → Alphabet-level costs → GAAP P&L)
CN9: SCENARIO INPUT TABLE — driver assumptions per Bull / Base / Bear | CO9: Bull | CP9: Base | CQ9: Bear | CR9: Bull / Bear = Base + Δ (Δ inputs on each block header). Alphabet gives no revenue / margin / EPS guidance: the Q3–Q4/26E block holds scenario shifts vs the 1H26 run-rate.
B10: Revenues by type (current taxonomy; latest filing presenting the period — annual from FY2017, quarterly from Q1/19) | CF10: REVENUE TYPES — Q3–Q4/26E: prior-year quarter × (1 + 1H26 y/y growth + scenario shift); 2027E–2030E: scenario levers
B11: Google Search & other | AH11: 69811 | AM11: 85296 | AN11: 22547 | AO11: 23642 | AP11: 24741 | AQ11: 27185 | AR11: 98115 | AS11: 24502 | AT11: 21319 | AU11: 26338 | AV11: 31903 | AW11: 104062 | AX11: 31879 | AY11: 35845 | AZ11: 37926 | BA11: 43301 | BB11: 148951 | BC11: 39618 | BD11: 40689 | BE11: 39539 | BF11: 42604 | BG11: 162450 | BH11: 40359 | BI11: 42628 | BJ11: 44026 | BK11: 48020 | BL11: 175033 | BM11: 46156 | BN11: 48509 | BO11: 49385 | BP11: 54034 | BQ11: 198084 | BR11: 50702 | BS11: 54190 | BT11: 56567 | BU11: 63073 | BV11: 224532 | BW11: 60399 | BX11: 63271 | BY11: =BT11*(1+BY12) -> 66693.751 | BZ11: =BU11*(1+BZ12) -> 74364.469 | CA11: =SUM(BW11:BZ11) -> 264728.22 | CB11: =CA11*(1+CB12) -> 293848.32 | CC11: =CB11*(1+CC12) -> 320294.67 | CD11: =CC11*(1+CD12) -> 345918.25 | CE11: =CD11*(1+CE12) -> 370132.52 | CF11: Revenue types per the 10-Q / 10-K revenue note (XBRL; latest filing presenting the period). YouTube ads and Cloud are disclosed from FY2017 (annual) / Q1-19 (quarterly). | CH11: =IFERROR((CE11/BV11)^(1/5)-1,"n/m") -> 0.10513619 | CI11: =IFERROR((BV11/AW11)^(1/5)-1,"n/m") -> 0.16626493 | CJ11: =IFERROR((BV11/X11)^(1/10)-1,"n/m") -> n/m | CK11: =IFERROR((BV11/C11)^(1/19)-1,"n/m") -> n/m | CN11: Q3–Q4/26E outlook — Alphabet gives no revenue, margin or EPS guidance (scenario shifts vs the 1H26 run-rate) | CO11: Bull | CP11: Base | CQ11: Bear | CR11: Capex outlook 2026 $195–205bn (raised from $180–190bn) is call-only (22-Jul-2026) and UNVERIFIED; the Q2-26 10-Q says only that 2026 technical-infrastructure investment will "significantly increase" vs 2025 (1H26 $80.6bn).
B12: y/y % | D12: =IF(AND(ISNUMBER(D11),ISNUMBER(C11)),IFERROR(D11/C11-1,""),"") | E12: =IF(AND(ISNUMBER(E11),ISNUMBER(D11)),IFERROR(E11/D11-1,""),"") | F12: =IF(AND(ISNUMBER(F11),ISNUMBER(E11)),IFERROR(F11/E11-1,""),"") | G12: =IF(AND(ISNUMBER(G11),ISNUMBER(F11)),IFERROR(G11/F11-1,""),"") | H12: =IF(AND(ISNUMBER(H11),ISNUMBER(G11)),IFERROR(H11/G11-1,""),"") | I12: =IF(AND(ISNUMBER(I11),ISNUMBER(H11)),IFERROR(I11/H11-1,""),"") | N12: =IF(AND(ISNUMBER(N11),ISNUMBER(I11)),IFERROR(N11/I11-1,""),"") | O12: =IF(AND(ISNUMBER(O11),ISNUMBER(J11)),IFERROR(O11/J11-1,""),"") | P12: =IF(AND(ISNUMBER(P11),ISNUMBER(K11)),IFERROR(P11/K11-1,""),"") | Q12: =IF(AND(ISNUMBER(Q11),ISNUMBER(L11)),IFERROR(Q11/L11-1,""),"") | R12: =IF(AND(ISNUMBER(R11),ISNUMBER(M11)),IFERROR(R11/M11-1,""),"") | S12: =IF(AND(ISNUMBER(S11),ISNUMBER(N11)),IFERROR(S11/N11-1,""),"") | T12: =IF(AND(ISNUMBER(T11),ISNUMBER(O11)),IFERROR(T11/O11-1,""),"") | U12: =IF(AND(ISNUMBER(U11),ISNUMBER(P11)),IFERROR(U11/P11-1,""),"") | ... BX12: =IF(AND(ISNUMBER(BX11),ISNUMBER(BS11)),IFERROR(BX11/BS11-1,""),"") -> 0.16757704 | BY12: =BY13+BY97 -> 0.17902223 | BZ12: =BY13+BY97 -> 0.17902223 | CA12: =IF(AND(ISNUMBER(CA11),ISNUMBER(BV11)),IFERROR(CA11/BV11-1,""),"") -> 0.17902223 | CB12: =CHOOSE(MATCH($CF$2,{"Bull","Base","Bear"},0),$CO$30,$CP$30,$CQ$30) -> 0.11 | CC12: =CHOOSE(MATCH($CF$2,{"Bull","Base","Bear"},0),$CO$31,$CP$31,$CQ$31) -> 0.09 | CD12: =CHOOSE(MATCH($CF$2,{"Bull","Base","Bear"},0),$CO$32,$CP$32,$CQ$32) -> 0.08 | CE12: =CHOOSE(MATCH($CF$2,{"Bull","Base","Bear"},0),$CO$33,$CP$33,$CQ$33) -> 0.07 | CF12: Q3–Q4/26E: 1H26 y/y growth + scenario shift (Group block). 2027E–2030E: scenario lever (Bull/Base/Bear table →). | CH12: =IFERROR(AVERAGE(CA12,CB12,CC12,CD12,CE12),"n/m") -> 0.10580445 | CI12: =IFERROR(AVERAGE(BB12,BG12,BL12,BQ12,BV12),"n/m") -> 0.17293338 | CJ12: =IFERROR(AVERAGE(AC12,AH12,AM12,AR12,AW12,BB12,BG12,BL12,BQ12,BV12),"n/m") -> 0.16217263 | CK12: =IFERROR(AVERAGE(C12,D12,E12,F12,G12,H12,I12,N12,S12,X12,AC12,AH12,AM12,AR12,AW12,BB12,BG12,BL12,BQ12,BV12),"n/m") -> 0.16217263 | CN12: Q3–Q4/26E revenue growth shift vs 1H26 y/y (pp; all revenue types) | CO12: 0.02 | CP12: 0 | CQ12: -0.03 | CR12: Base = 1H26 y/y run-rate (Search +17.9%, YouTube +11.8%, Network −2.3%, subscriptions +17.2%, Cloud +73% incl. Wiz from 11-Mar-2026). Assumption.
B13: 1H26 y/y growth (Q3–Q4/26E driver before scenario shift) | BY13: =IFERROR(SUM(BW11:BX11)/SUM(BR11:BS11)-1,0) -> 0.17902223 | BZ13: =IFERROR(SUM(BW11:BX11)/SUM(BR11:BS11)-1,0) -> 0.17902223 | CN13: Q3–Q4/26E Services / Cloud operating-margin shift (pp) | CO13: 0.01 | CP13: 0 | CQ13: -0.015 | CR13: Base = Q2-26 margins (Services with last year's sequential seasonality). Bear reflects leased third-party data-centre capacity in Q3 (call, unverified).
B14: YouTube ads | AH14: 8150 | AM14: 11155 | AN14: 3025 | AO14: 3603 | AP14: 3804 | AQ14: 4717 | AR14: 15149 | AS14: 4038 | AT14: 3812 | AU14: 5037 | AV14: 6885 | AW14: 19772 | AX14: 6005 | AY14: 7002 | AZ14: 7205 | BA14: 8633 | BB14: 28845 | BC14: 6869 | BD14: 7340 | BE14: 7071 | BF14: 7963 | BG14: 29243 | BH14: 6693 | BI14: 7665 | BJ14: 7952 | BK14: 9200 | BL14: 31510 | BM14: 8090 | BN14: 8663 | BO14: 8921 | BP14: 10473 | BQ14: 36147 | BR14: 8927 | BS14: 9796 | BT14: 10261 | BU14: 11383 | BV14: 40367 | BW14: 9883 | BX14: 11055 | BY14: =BT14*(1+BY15) -> 11474.914 | BZ14: =BU14*(1+BZ15) -> 12729.651 | CA14: =SUM(BW14:BZ14) -> 45142.565 | CB14: =CA14*(1+CB15) -> 50108.247 | CC14: =CB14*(1+CC15) -> 55119.072 | CD14: =CC14*(1+CD15) -> 60079.788 | CE14: =CD14*(1+CE15) -> 64886.172 | CH14: =IFERROR((CE14/BV14)^(1/5)-1,"n/m") -> 0.099575704 | CI14: =IFERROR((BV14/AW14)^(1/5)-1,"n/m") -> 0.15344044 | CJ14: =IFERROR((BV14/X14)^(1/10)-1,"n/m") -> n/m | CK14: =IFERROR((BV14/C14)^(1/19)-1,"n/m") -> n/m | CN14: 2H26E share repurchases ($m) | CO14: 5000 | CP14: 0 | CQ14: 0 | CR14: No repurchases in 1H26 after the Jun-2026 equity raise; $69.5bn authorization remaining.
B15: y/y % | D15: =IF(AND(ISNUMBER(D14),ISNUMBER(C14)),IFERROR(D14/C14-1,""),"") | E15: =IF(AND(ISNUMBER(E14),ISNUMBER(D14)),IFERROR(E14/D14-1,""),"") | F15: =IF(AND(ISNUMBER(F14),ISNUMBER(E14)),IFERROR(F14/E14-1,""),"") | G15: =IF(AND(ISNUMBER(G14),ISNUMBER(F14)),IFERROR(G14/F14-1,""),"") | H15: =IF(AND(ISNUMBER(H14),ISNUMBER(G14)),IFERROR(H14/G14-1,""),"") | I15: =IF(AND(ISNUMBER(I14),ISNUMBER(H14)),IFERROR(I14/H14-1,""),"") | N15: =IF(AND(ISNUMBER(N14),ISNUMBER(I14)),IFERROR(N14/I14-1,""),"") | O15: =IF(AND(ISNUMBER(O14),ISNUMBER(J14)),IFERROR(O14/J14-1,""),"") | P15: =IF(AND(ISNUMBER(P14),ISNUMBER(K14)),IFERROR(P14/K14-1,""),"") | Q15: =IF(AND(ISNUMBER(Q14),ISNUMBER(L14)),IFERROR(Q14/L14-1,""),"") | R15: =IF(AND(ISNUMBER(R14),ISNUMBER(M14)),IFERROR(R14/M14-1,""),"") | S15: =IF(AND(ISNUMBER(S14),ISNUMBER(N14)),IFERROR(S14/N14-1,""),"") | T15: =IF(AND(ISNUMBER(T14),ISNUMBER(O14)),IFERROR(T14/O14-1,""),"") | U15: =IF(AND(ISNUMBER(U14),ISNUMBER(P14)),IFERROR(U14/P14-1,""),"") | ... BX15: =IF(AND(ISNUMBER(BX14),ISNUMBER(BS14)),IFERROR(BX14/BS14-1,""),"") -> 0.12852185 | BY15: =BY16+BY97 -> 0.11830369 | BZ15: =BY16+BY97 -> 0.11830369 | CA15: =IF(AND(ISNUMBER(CA14),ISNUMBER(BV14)),IFERROR(CA14/BV14-1,""),"") -> 0.11830369 | CB15: =CHOOSE(MATCH($CF$2,{"Bull","Base","Bear"},0),$CO$35,$CP$35,$CQ$35) -> 0.11 | CC15: =CHOOSE(MATCH($CF$2,{"Bull","Base","Bear"},0),$CO$36,$CP$36,$CQ$36) -> 0.1 | CD15: =CHOOSE(MATCH($CF$2,{"Bull","Base","Bear"},0),$CO$37,$CP$37,$CQ$37) -> 0.09 | CE15: =CHOOSE(MATCH($CF$2,{"Bull","Base","Bear"},0),$CO$38,$CP$38,$CQ$38) -> 0.08 | CH15: =IFERROR(AVERAGE(CA15,CB15,CC15,CD15,CE15),"n/m") -> 0.099660738 | CI15: =IFERROR(AVERAGE(BB15,BG15,BL15,BQ15,BV15),"n/m") -> 0.16282142 | CJ15: =IFERROR(AVERAGE(AC15,AH15,AM15,AR15,AW15,BB15,BG15,BL15,BQ15,BV15),"n/m") -> 0.23075414 | CK15: =IFERROR(AVERAGE(C15,D15,E15,F15,G15,H15,I15,N15,S15,X15,AC15,AH15,AM15,AR15,AW15,BB15,BG15,BL15,BQ15,BV15),"n/m") -> 0.23075414
B16: 1H26 y/y growth (Q3–Q4/26E driver before scenario shift) | BY16: =IFERROR(SUM(BW14:BX14)/SUM(BR14:BS14)-1,0) -> 0.11830369 | BZ16: =IFERROR(SUM(BW14:BX14)/SUM(BR14:BS14)-1,0) -> 0.11830369 | CN16: Q3–Q4/26E point estimates (all cases)
B17: Google Network | AH17: 17616 | AM17: 20010 | AN17: 5015 | AO17: 5249 | AP17: 5251 | AQ17: 6032 | AR17: 21547 | AS17: 5223 | AT17: 4736 | AU17: 5720 | AV17: 7411 | AW17: 23090 | AX17: 6800 | AY17: 7597 | AZ17: 7999 | BA17: 9305 | BB17: 31701 | BC17: 8174 | BD17: 8259 | BE17: 7872 | BF17: 8475 | BG17: 32780 | BH17: 7496 | BI17: 7850 | BJ17: 7669 | BK17: 8297 | BL17: 31312 | BM17: 7413 | BN17: 7444 | BO17: 7548 | BP17: 7954 | BQ17: 30359 | BR17: 7256 | BS17: 7354 | BT17: 7354 | BU17: 7828 | BV17: 29792 | BW17: 6971 | BX17: 7303 | BY17: =BT17*(1+BY18) -> 7184.8731 | BZ17: =BU17*(1+BZ18) -> 7647.9721 | CA17: =SUM(BW17:BZ17) -> 29106.845 | CB17: =CA17*(1+CB18) -> 28233.64 | CC17: =CB17*(1+CC18) -> 27386.631 | CD17: =CC17*(1+CD18) -> 26565.032 | CE17: =CD17*(1+CE18) -> 25768.081 | CH17: =IFERROR((CE17/BV17)^(1/5)-1,"n/m") -> -0.028603616 | CI17: =IFERROR((BV17/AW17)^(1/5)-1,"n/m") -> 0.052289278 | CJ17: =IFERROR((BV17/X17)^(1/10)-1,"n/m") -> n/m | CK17: =IFERROR((BV17/C17)^(1/19)-1,"n/m") -> n/m | CN17: Optional FY26 revenue target ($m; blank = driver-based) | CR17: Blank by default (no company guidance). Enter a value (e.g. consensus) to solve the 2H revenue shift to it.
B18: y/y % | D18: =IF(AND(ISNUMBER(D17),ISNUMBER(C17)),IFERROR(D17/C17-1,""),"") | E18: =IF(AND(ISNUMBER(E17),ISNUMBER(D17)),IFERROR(E17/D17-1,""),"") | F18: =IF(AND(ISNUMBER(F17),ISNUMBER(E17)),IFERROR(F17/E17-1,""),"") | G18: =IF(AND(ISNUMBER(G17),ISNUMBER(F17)),IFERROR(G17/F17-1,""),"") | H18: =IF(AND(ISNUMBER(H17),ISNUMBER(G17)),IFERROR(H17/G17-1,""),"") | I18: =IF(AND(ISNUMBER(I17),ISNUMBER(H17)),IFERROR(I17/H17-1,""),"") | N18: =IF(AND(ISNUMBER(N17),ISNUMBER(I17)),IFERROR(N17/I17-1,""),"") | O18: =IF(AND(ISNUMBER(O17),ISNUMBER(J17)),IFERROR(O17/J17-1,""),"") | P18: =IF(AND(ISNUMBER(P17),ISNUMBER(K17)),IFERROR(P17/K17-1,""),"") | Q18: =IF(AND(ISNUMBER(Q17),ISNUMBER(L17)),IFERROR(Q17/L17-1,""),"") | R18: =IF(AND(ISNUMBER(R17),ISNUMBER(M17)),IFERROR(R17/M17-1,""),"") | S18: =IF(AND(ISNUMBER(S17),ISNUMBER(N17)),IFERROR(S17/N17-1,""),"") | T18: =IF(AND(ISNUMBER(T17),ISNUMBER(O17)),IFERROR(T17/O17-1,""),"") | U18: =IF(AND(ISNUMBER(U17),ISNUMBER(P17)),IFERROR(U17/P17-1,""),"") | ... BX18: =IF(AND(ISNUMBER(BX17),ISNUMBER(BS17)),IFERROR(BX17/BS17-1,""),"") -> -0.0069350014 | BY18: =BY19+BY97 -> -0.022997947 | BZ18: =BY19+BY97 -> -0.022997947 | CA18: =IF(AND(ISNUMBER(CA17),ISNUMBER(BV17)),IFERROR(CA17/BV17-1,""),"") -> -0.022997947 | CB18: =CHOOSE(MATCH($CF$2,{"Bull","Base","Bear"},0),$CO$40,$CP$40,$CQ$40) -> -0.03 | CC18: =CHOOSE(MATCH($CF$2,{"Bull","Base","Bear"},0),$CO$41,$CP$41,$CQ$41) -> -0.03 | CD18: =CHOOSE(MATCH($CF$2,{"Bull","Base","Bear"},0),$CO$42,$CP$42,$CQ$42) -> -0.03 | CE18: =CHOOSE(MATCH($CF$2,{"Bull","Base","Bear"},0),$CO$43,$CP$43,$CQ$43) -> -0.03 | CH18: =IFERROR(AVERAGE(CA18,CB18,CC18,CD18,CE18),"n/m") -> -0.028599589 | CI18: =IFERROR(AVERAGE(BB18,BG18,BL18,BQ18,BV18),"n/m") -> 0.062614652 | CJ18: =IFERROR(AVERAGE(AC18,AH18,AM18,AR18,AW18,BB18,BG18,BL18,BQ18,BV18),"n/m") -> 0.074674367 | CK18: =IFERROR(AVERAGE(C18,D18,E18,F18,G18,H18,I18,N18,S18,X18,AC18,AH18,AM18,AR18,AW18,BB18,BG18,BL18,BQ18,BV18),"n/m") -> 0.074674367 | CN18: FY26 capital expenditures ($m) — UNVERIFIED call guidance mid-point | CP18: 200000 | CR18: UNVERIFIED - Q2-2026 earnings call (CFO), reported by secondary sources (w.media, Nasdaq/Motley Fool); not in any EDGAR filing. The Q2-26 10-Q states only that 2026 investment in technical infrastructure will 'significantly increase, relative to 2025'.
B19: 1H26 y/y growth (Q3–Q4/26E driver before scenario shift) | BY19: =IFERROR(SUM(BW17:BX17)/SUM(BR17:BS17)-1,0) -> -0.022997947 | BZ19: =IFERROR(SUM(BW17:BX17)/SUM(BR17:BS17)-1,0) -> -0.022997947 | CN19: Q3–Q4/26E depreciation, sequential growth | CP19: 0.096 | CR19: Q2/Q1-26 +9.6% ($7,104m vs $6,482m); capex ramp.
B20: Google subscriptions, platforms & devices | AH20: 10914 | AM20: 14063 | AN20: 3620 | AO20: 4080 | AP20: 4050 | AQ20: 5264 | AR20: 17014 | AS20: 4435 | AT20: 5124 | AU20: 5478 | AV20: 6674 | AW20: 21711 | AX20: 6494 | AY20: 6623 | AZ20: 6754 | BA20: 8161 | BB20: 28032 | BC20: 6811 | BD20: 6553 | BE20: 6895 | BF20: 8796 | BG20: 29055 | BH20: 7413 | BI20: 8142 | BJ20: 8339 | BK20: 10794 | BL20: 34688 | BM20: 8739 | BN20: 9312 | BO20: 10656 | BP20: 11633 | BQ20: 40340 | BR20: 10379 | BS20: 11203 | BT20: 12870 | BU20: 13578 | BV20: 48030 | BW20: 12384 | BX20: 12911 | BY20: =BT20*(1+BY21) -> 15084.174 | BZ20: =BU20*(1+BZ21) -> 15913.98 | CA20: =SUM(BW20:BZ20) -> 56293.154 | CB20: =CA20*(1+CB21) -> 64174.196 | CC20: =CB20*(1+CC21) -> 71875.099 | CD20: =CC20*(1+CD21) -> 79781.36 | CE20: =CD20*(1+CE21) -> 87759.496 | CF20: "Google other" to Q4-23, renamed "Google subscriptions, platforms, and devices" from Q1-24 (no recast). | CH20: =IFERROR((CE20/BV20)^(1/5)-1,"n/m") -> 0.12812262 | CI20: =IFERROR((BV20/AW20)^(1/5)-1,"n/m") -> 0.17210509 | CJ20: =IFERROR((BV20/X20)^(1/10)-1,"n/m") -> n/m | CK20: =IFERROR((BV20/C20)^(1/19)-1,"n/m") -> n/m | CN20: Q3–Q4/26E amortization of intangibles ($m per quarter) | CP20: 370 | CR20: Q2-26 $367m (Wiz intangibles from Mar-2026).
B21: y/y % | D21: =IF(AND(ISNUMBER(D20),ISNUMBER(C20)),IFERROR(D20/C20-1,""),"") | E21: =IF(AND(ISNUMBER(E20),ISNUMBER(D20)),IFERROR(E20/D20-1,""),"") | F21: =IF(AND(ISNUMBER(F20),ISNUMBER(E20)),IFERROR(F20/E20-1,""),"") | G21: =IF(AND(ISNUMBER(G20),ISNUMBER(F20)),IFERROR(G20/F20-1,""),"") | H21: =IF(AND(ISNUMBER(H20),ISNUMBER(G20)),IFERROR(H20/G20-1,""),"") | I21: =IF(AND(ISNUMBER(I20),ISNUMBER(H20)),IFERROR(I20/H20-1,""),"") | N21: =IF(AND(ISNUMBER(N20),ISNUMBER(I20)),IFERROR(N20/I20-1,""),"") | O21: =IF(AND(ISNUMBER(O20),ISNUMBER(J20)),IFERROR(O20/J20-1,""),"") | P21: =IF(AND(ISNUMBER(P20),ISNUMBER(K20)),IFERROR(P20/K20-1,""),"") | Q21: =IF(AND(ISNUMBER(Q20),ISNUMBER(L20)),IFERROR(Q20/L20-1,""),"") | R21: =IF(AND(ISNUMBER(R20),ISNUMBER(M20)),IFERROR(R20/M20-1,""),"") | S21: =IF(AND(ISNUMBER(S20),ISNUMBER(N20)),IFERROR(S20/N20-1,""),"") | T21: =IF(AND(ISNUMBER(T20),ISNUMBER(O20)),IFERROR(T20/O20-1,""),"") | U21: =IF(AND(ISNUMBER(U20),ISNUMBER(P20)),IFERROR(U20/P20-1,""),"") | ... BX21: =IF(AND(ISNUMBER(BX20),ISNUMBER(BS20)),IFERROR(BX20/BS20-1,""),"") -> 0.15245916 | BY21: =BY22+BY97 -> 0.17204152 | BZ21: =BY22+BY97 -> 0.17204152 | CA21: =IF(AND(ISNUMBER(CA20),ISNUMBER(BV20)),IFERROR(CA20/BV20-1,""),"") -> 0.17204152 | CB21: =CHOOSE(MATCH($CF$2,{"Bull","Base","Bear"},0),$CO$45,$CP$45,$CQ$45) -> 0.14 | CC21: =CHOOSE(MATCH($CF$2,{"Bull","Base","Bear"},0),$CO$46,$CP$46,$CQ$46) -> 0.12 | CD21: =CHOOSE(MATCH($CF$2,{"Bull","Base","Bear"},0),$CO$47,$CP$47,$CQ$47) -> 0.11 | CE21: =CHOOSE(MATCH($CF$2,{"Bull","Base","Bear"},0),$CO$48,$CP$48,$CQ$48) -> 0.1 | CH21: =IFERROR(AVERAGE(CA21,CB21,CC21,CD21,CE21),"n/m") -> 0.1284083 | CI21: =IFERROR(AVERAGE(BB21,BG21,BL21,BQ21,BV21),"n/m") -> 0.17501565 | CJ21: =IFERROR(AVERAGE(AC21,AH21,AM21,AR21,AW21,BB21,BG21,BL21,BQ21,BV21),"n/m") -> 0.20618937 | CK21: =IFERROR(AVERAGE(C21,D21,E21,F21,G21,H21,I21,N21,S21,X21,AC21,AH21,AM21,AR21,AW21,BB21,BG21,BL21,BQ21,BV21),"n/m") -> 0.20618937 | CN21: Q3–Q4/26E effective tax rate | CP21: 0.18 | CR21: 1H26 19.1% incl. tax on equity-security gains; FY2025 16.8%.
B22: 1H26 y/y growth (Q3–Q4/26E driver before scenario shift) | BY22: =IFERROR(SUM(BW20:BX20)/SUM(BR20:BS20)-1,0) -> 0.17204152 | BZ22: =IFERROR(SUM(BW20:BX20)/SUM(BR20:BS20)-1,0) -> 0.17204152 | CN22: Q3–Q4/26E interest yield on cash + marketable securities (annual) | CP22: 0.033 | CR22: Q2-26 $1,430m on ~$185bn average cash and securities (~3.1%); $242.5bn at 30-Jun-2026.
B23: Google Cloud | AH23: 4056 | AM23: 5838 | AN23: 1825 | AO23: 2100 | AP23: 2379 | AQ23: 2614 | AR23: 8918 | AS23: 2777 | AT23: 3007 | AU23: 3444 | AV23: 3831 | AW23: 13059 | AX23: 4047 | AY23: 4628 | AZ23: 4990 | BA23: 5541 | BB23: 19206 | BC23: 5821 | BD23: 6276 | BE23: 6868 | BF23: 7315 | BG23: 26280 | BH23: 7454 | BI23: 8031 | BJ23: 8411 | BK23: 9192 | BL23: 33088 | BM23: 9574 | BN23: 10347 | BO23: 11353 | BP23: 11955 | BQ23: 43229 | BR23: 12260 | BS23: 13624 | BT23: 15157 | BU23: 17664 | BV23: 58705 | BW23: 20028 | BX23: 24768 | BY23: =BT23*(1+BY24) -> 26231.377 | BZ23: =BU23*(1+BZ24) -> 30570.103 | CA23: =SUM(BW23:BZ23) -> 101597.48 | CB23: =CA23*(1+CB24) -> 147316.35 | CC23: =CB23*(1+CC24) -> 194457.58 | CD23: =CC23*(1+CD24) -> 243071.97 | CE23: =CD23*(1+CE24) -> 291686.37 | CF23: Google Cloud segment revenues (from Q4-20; earlier the Google Cloud revenue type, incl. in the Google segment). Includes Wiz from 11-Mar-2026. | CH23: =IFERROR((CE23/BV23)^(1/5)-1,"n/m") -> 0.37799679 | CI23: =IFERROR((BV23/AW23)^(1/5)-1,"n/m") -> 0.35068176 | CJ23: =IFERROR((BV23/X23)^(1/10)-1,"n/m") -> n/m | CK23: =IFERROR((BV23/C23)^(1/19)-1,"n/m") -> n/m | CN23: Q3–Q4/26E interest expense ($m per quarter) | CP23: 1150 | CR23: Q2-26 $1,278m (net of $363m capitalized interest); ~$100bn of debt at ~4.0% weighted coupon.
B24: y/y % | D24: =IF(AND(ISNUMBER(D23),ISNUMBER(C23)),IFERROR(D23/C23-1,""),"") | E24: =IF(AND(ISNUMBER(E23),ISNUMBER(D23)),IFERROR(E23/D23-1,""),"") | F24: =IF(AND(ISNUMBER(F23),ISNUMBER(E23)),IFERROR(F23/E23-1,""),"") | G24: =IF(AND(ISNUMBER(G23),ISNUMBER(F23)),IFERROR(G23/F23-1,""),"") | H24: =IF(AND(ISNUMBER(H23),ISNUMBER(G23)),IFERROR(H23/G23-1,""),"") | I24: =IF(AND(ISNUMBER(I23),ISNUMBER(H23)),IFERROR(I23/H23-1,""),"") | N24: =IF(AND(ISNUMBER(N23),ISNUMBER(I23)),IFERROR(N23/I23-1,""),"") | O24: =IF(AND(ISNUMBER(O23),ISNUMBER(J23)),IFERROR(O23/J23-1,""),"") | P24: =IF(AND(ISNUMBER(P23),ISNUMBER(K23)),IFERROR(P23/K23-1,""),"") | Q24: =IF(AND(ISNUMBER(Q23),ISNUMBER(L23)),IFERROR(Q23/L23-1,""),"") | R24: =IF(AND(ISNUMBER(R23),ISNUMBER(M23)),IFERROR(R23/M23-1,""),"") | S24: =IF(AND(ISNUMBER(S23),ISNUMBER(N23)),IFERROR(S23/N23-1,""),"") | T24: =IF(AND(ISNUMBER(T23),ISNUMBER(O23)),IFERROR(T23/O23-1,""),"") | U24: =IF(AND(ISNUMBER(U23),ISNUMBER(P23)),IFERROR(U23/P23-1,""),"") | ... BX24: =IF(AND(ISNUMBER(BX23),ISNUMBER(BS23)),IFERROR(BX23/BS23-1,""),"") -> 0.81796829 | BY24: =BY25+BY97 -> 0.73064441 | BZ24: =BY25+BY97 -> 0.73064441 | CA24: =IF(AND(ISNUMBER(CA23),ISNUMBER(BV23)),IFERROR(CA23/BV23-1,""),"") -> 0.73064441 | CB24: =CHOOSE(MATCH($CF$2,{"Bull","Base","Bear"},0),$CO$50,$CP$50,$CQ$50) -> 0.45 | CC24: =CHOOSE(MATCH($CF$2,{"Bull","Base","Bear"},0),$CO$51,$CP$51,$CQ$51) -> 0.32 | CD24: =CHOOSE(MATCH($CF$2,{"Bull","Base","Bear"},0),$CO$52,$CP$52,$CQ$52) -> 0.25 | CE24: =CHOOSE(MATCH($CF$2,{"Bull","Base","Bear"},0),$CO$53,$CP$53,$CQ$53) -> 0.2 | CH24: =IFERROR(AVERAGE(CA24,CB24,CC24,CD24,CE24),"n/m") -> 0.39012888 | CI24: =IFERROR(AVERAGE(BB24,BG24,BL24,BQ24,BV24),"n/m") -> 0.35251494 | CJ24: =IFERROR(AVERAGE(AC24,AH24,AM24,AR24,AW24,BB24,BG24,BL24,BQ24,BV24),"n/m") -> 0.39923044 | CK24: =IFERROR(AVERAGE(C24,D24,E24,F24,G24,H24,I24,N24,S24,X24,AC24,AH24,AM24,AR24,AW24,BB24,BG24,BL24,BQ24,BV24),"n/m") -> 0.39923044 | CN24: Q3–Q4/26E preferred dividends accrued ($m per quarter) | CP24: 296.875 | CR24: 6.25% × $19.0bn liquidation preference ÷ 4.
B25: 1H26 y/y growth (Q3–Q4/26E driver before scenario shift) | BY25: =IFERROR(SUM(BW23:BX23)/SUM(BR23:BS23)-1,0) -> 0.73064441 | BZ25: =IFERROR(SUM(BW23:BX23)/SUM(BR23:BS23)-1,0) -> 0.73064441 | CN25: 2H26E deferred income taxes ($m) | CP25: 0 | CR25: Not forecast (assumption).
B26: Other Bets | N26: 12 | S26: 327 | T26: 80 | U26: 74 | V26: 141 | W26: 150 | X26: 445 | Y26: 165 | Z26: 185 | AA26: 197 | AB26: -259 | AC26: 288 | AD26: 132 | AE26: 97 | AF26: 117 | AG26: 131 | AH26: 477 | AI26: 150 | AJ26: 145 | AK26: 146 | AL26: 154 | AM26: 595 | AN26: 170 | AO26: 162 | AP26: 155 | AQ26: 172 | AR26: 659 | AS26: 135 | AT26: 148 | AU26: 178 | AV26: 196 | AW26: 657 | AX26: 198 | AY26: 192 | AZ26: 182 | BA26: 181 | BB26: 753 | BC26: 440 | BD26: 193 | BE26: 209 | BF26: 226 | BG26: 1068 | BH26: 288 | BI26: 285 | BJ26: 297 | BK26: 657 | BL26: 1527 | BM26: 495 | BN26: 365 | BO26: 388 | BP26: 400 | BQ26: 1648 | BR26: 450 | BS26: 373 | BT26: 344 | BU26: 370 | BV26: 1537 | BW26: 411 | BX26: 382 | BY26: =BT26*(1+BY27) -> 331.46051 | BZ26: =BU26*(1+BZ27) -> 356.51276 | CA26: =SUM(BW26:BZ26) -> 1480.9733 | CB26: =CA26*(1+CB27) -> 1036.6813 | CC26: =CB26*(1+CC27) -> 1295.8516 | CD26: =CC26*(1+CD27) -> 1619.8145 | CE26: =CD26*(1+CE27) -> 2024.7681 | CF26: Other Bets segment revenues (from FY2015; recast basis where presented).
B27: y/y % | D27: =IF(AND(ISNUMBER(D26),ISNUMBER(C26)),IFERROR(D26/C26-1,""),"") | E27: =IF(AND(ISNUMBER(E26),ISNUMBER(D26)),IFERROR(E26/D26-1,""),"") | F27: =IF(AND(ISNUMBER(F26),ISNUMBER(E26)),IFERROR(F26/E26-1,""),"") | G27: =IF(AND(ISNUMBER(G26),ISNUMBER(F26)),IFERROR(G26/F26-1,""),"") | H27: =IF(AND(ISNUMBER(H26),ISNUMBER(G26)),IFERROR(H26/G26-1,""),"") | I27: =IF(AND(ISNUMBER(I26),ISNUMBER(H26)),IFERROR(I26/H26-1,""),"") | N27: =IF(AND(ISNUMBER(N26),ISNUMBER(I26)),IFERROR(N26/I26-1,""),"") | O27: =IF(AND(ISNUMBER(O26),ISNUMBER(J26)),IFERROR(O26/J26-1,""),"") | P27: =IF(AND(ISNUMBER(P26),ISNUMBER(K26)),IFERROR(P26/K26-1,""),"") | Q27: =IF(AND(ISNUMBER(Q26),ISNUMBER(L26)),IFERROR(Q26/L26-1,""),"") | R27: =IF(AND(ISNUMBER(R26),ISNUMBER(M26)),IFERROR(R26/M26-1,""),"") | S27: =IF(AND(ISNUMBER(S26),ISNUMBER(N26)),IFERROR(S26/N26-1,""),"") -> 26.25 | T27: =IF(AND(ISNUMBER(T26),ISNUMBER(O26)),IFERROR(T26/O26-1,""),"") | U27: =IF(AND(ISNUMBER(U26),ISNUMBER(P26)),IFERROR(U26/P26-1,""),"") | ... BX27: =IF(AND(ISNUMBER(BX26),ISNUMBER(BS26)),IFERROR(BX26/BS26-1,""),"") -> 0.024128686 | BY27: =BY28+BY97 -> -0.036452005 | BZ27: =BY28+BY97 -> -0.036452005 | CA27: =IF(AND(ISNUMBER(CA26),ISNUMBER(BV26)),IFERROR(CA26/BV26-1,""),"") -> -0.036452005 | CB27: =CHOOSE(MATCH($CF$2,{"Bull","Base","Bear"},0),$CO$55,$CP$55,$CQ$55) -> -0.3 | CC27: =CHOOSE(MATCH($CF$2,{"Bull","Base","Bear"},0),$CO$56,$CP$56,$CQ$56) -> 0.25 | CD27: =CHOOSE(MATCH($CF$2,{"Bull","Base","Bear"},0),$CO$57,$CP$57,$CQ$57) -> 0.25 | CE27: =CHOOSE(MATCH($CF$2,{"Bull","Base","Bear"},0),$CO$58,$CP$58,$CQ$58) -> 0.25 | CN27: Target net debt / adjusted EBITDA (x; negative = net-cash floor) — buyback plug 2027E+ | CO27: -0.1 | CP27: -0.25 | CQ27: -0.4 | CR27: Alphabet is net cash ($142bn at 30-Jun-2026 after the $49.6bn equity raise; $100bn of debt vs $242bn of cash and marketable securities). Negative target = net-cash floor: buybacks return liquidity above |x| × adjusted EBITDA. Bull −0.10x (more buybacks), Base −0.25x, Bear −0.40x (assumption).
B28: 1H26 y/y growth (Q3–Q4/26E driver before scenario shift) | BY28: =IFERROR(SUM(BW26:BX26)/SUM(BR26:BS26)-1,0) -> -0.036452005 | BZ28: =IFERROR(SUM(BW26:BX26)/SUM(BR26:BS26)-1,0) -> -0.036452005
B29: Hedging gains (losses) (not allocated to segments; derived = revenues − segment revenues) | AM29: -138 | AR29: 455 | AS29: 49 | AT29: 151 | AU29: -22 | AV29: -2 | AW29: 176 | AX29: -109 | AY29: -7 | AZ29: 62 | BA29: 203 | BB29: 149 | BC29: 278 | BD29: 375 | BE29: 638 | BF29: 669 | BG29: 1960 | BH29: 84 | BI29: 3 | BJ29: -1 | BK29: 150 | BL29: 236 | BM29: 72 | BN29: 102 | BO29: 17 | BP29: 20 | BQ29: 211 | BR29: 260 | BS29: -112 | BT29: -207 | BU29: -67 | BV29: -127 | BW29: -180 | BX29: 106 | BY29: =0 -> 0 | BZ29: =0 -> 0 | CA29: =SUM(BW29:BZ29) -> -74 | CB29: =0 -> 0 | CC29: =0 -> 0 | CD29: =0 -> 0 | CE29: =0 -> 0 | CF29: Cash-flow hedging gains / losses recorded in revenues (Alphabet-level). Forecast nil. | CN29: SEARCH (Google Search & other y/y) | CO29: 0.02 | CP29: Δ → | CQ29: -0.04 | CR29: 1H26 +17.9% (FY2025 +13.4%, FY2024 +13.2%); AI Overviews / AI Mode monetisation vs competition from AI assistants. Assumption.
B30: Revenues not split on the current taxonomy / basis differences (derived) | C30: =IF(ISNUMBER(C132),C132-(N(C11)+N(C14)+N(C17)+N(C20)+N(C23)+N(C26)+N(C29)),"") -> 10604.917 | D30: =IF(ISNUMBER(D132),D132-(N(D11)+N(D14)+N(D17)+N(D20)+N(D23)+N(D26)+N(D29)),"") -> 16593.986 | E30: =IF(ISNUMBER(E132),E132-(N(E11)+N(E14)+N(E17)+N(E20)+N(E23)+N(E26)+N(E29)),"") -> 21795.55 | F30: =IF(ISNUMBER(F132),F132-(N(F11)+N(F14)+N(F17)+N(F20)+N(F23)+N(F26)+N(F29)),"") -> 23650.563 | G30: =IF(ISNUMBER(G132),G132-(N(G11)+N(G14)+N(G17)+N(G20)+N(G23)+N(G26)+N(G29)),"") -> 29321 | H30: =IF(ISNUMBER(H132),H132-(N(H11)+N(H14)+N(H17)+N(H20)+N(H23)+N(H26)+N(H29)),"") -> 37905 | I30: =IF(ISNUMBER(I132),I132-(N(I11)+N(I14)+N(I17)+N(I20)+N(I23)+N(I26)+N(I29)),"") -> 50175 | J30: =IF(ISNUMBER(J132),J132-(N(J11)+N(J14)+N(J17)+N(J20)+N(J23)+N(J26)+N(J29)),"") -> 13969 | ... BX30: =IF(ISNUMBER(BX132),BX132-(N(BX11)+N(BX14)+N(BX17)+N(BX20)+N(BX23)+N(BX26)+N(BX29)),"") -> 0 | BY30: =0 -> 0 | BZ30: =0 -> 0 | CA30: =SUM(BW30:BZ30) -> 0 | CB30: =0 -> 0 | CC30: =0 -> 0 | CD30: =0 -> 0 | CE30: =0 -> 0 | CF30: Consolidated revenues (as originally reported) − Σ revenue types (latest filing presenting the period). Equals total revenues before FY2017 / Q1-19 (legacy split in the memo block below); Other Bets before FY2015. | CN30: 2027E | CO30: =CP30+$CO$29 -> 0.13 | CP30: 0.11 | CQ30: =CP30+$CQ$29 -> 0.07
B31: Total revenues (revenue build) | C31: =IF(ISNUMBER(C132),N(C11)+N(C14)+N(C17)+N(C20)+N(C23)+N(C26)+N(C29)+N(C30),"") -> 10604.917 | D31: =IF(ISNUMBER(D132),N(D11)+N(D14)+N(D17)+N(D20)+N(D23)+N(D26)+N(D29)+N(D30),"") -> 16593.986 | E31: =IF(ISNUMBER(E132),N(E11)+N(E14)+N(E17)+N(E20)+N(E23)+N(E26)+N(E29)+N(E30),"") -> 21795.55 | F31: =IF(ISNUMBER(F132),N(F11)+N(F14)+N(F17)+N(F20)+N(F23)+N(F26)+N(F29)+N(F30),"") -> 23650.563 | G31: =IF(ISNUMBER(G132),N(G11)+N(G14)+N(G17)+N(G20)+N(G23)+N(G26)+N(G29)+N(G30),"") -> 29321 | H31: =IF(ISNUMBER(H132),N(H11)+N(H14)+N(H17)+N(H20)+N(H23)+N(H26)+N(H29)+N(H30),"") -> 37905 | I31: =IF(ISNUMBER(I132),N(I11)+N(I14)+N(I17)+N(I20)+N(I23)+N(I26)+N(I29)+N(I30),"") -> 50175 | J31: =IF(ISNUMBER(J132),N(J11)+N(J14)+N(J17)+N(J20)+N(J23)+N(J26)+N(J29)+N(J30),"") -> 13969 | ... BX31: =IF(ISNUMBER(BX132),N(BX11)+N(BX14)+N(BX17)+N(BX20)+N(BX23)+N(BX26)+N(BX29)+N(BX30),"") -> 119796 | BY31: =N(BY11)+N(BY14)+N(BY17)+N(BY20)+N(BY23)+N(BY26)+N(BY29) -> 127000.55 | BZ31: =N(BZ11)+N(BZ14)+N(BZ17)+N(BZ20)+N(BZ23)+N(BZ26)+N(BZ29) -> 141582.69 | CA31: =N(CA11)+N(CA14)+N(CA17)+N(CA20)+N(CA23)+N(CA26)+N(CA29) -> 498275.24 | CB31: =N(CB11)+N(CB14)+N(CB17)+N(CB20)+N(CB23)+N(CB26)+N(CB29) -> 584717.43 | CC31: =N(CC11)+N(CC14)+N(CC17)+N(CC20)+N(CC23)+N(CC26)+N(CC29) -> 670428.9 | CD31: =N(CD11)+N(CD14)+N(CD17)+N(CD20)+N(CD23)+N(CD26)+N(CD29) -> 757036.21 | CE31: =N(CE11)+N(CE14)+N(CE17)+N(CE20)+N(CE23)+N(CE26)+N(CE29) -> 842257.41 | CH31: =IFERROR((CE31/BV31)^(1/5)-1,"n/m") -> 0.1589463 | CI31: =IFERROR((BV31/AW31)^(1/5)-1,"n/m") -> 0.17154839 | CJ31: =IFERROR((BV31/X31)^(1/10)-1,"n/m") -> 0.18307716 | CK31: =IFERROR((BV31/C31)^(1/19)-1,"n/m") -> 0.21098272 | CN31: 2028E | CO31: =CP31+$CO$29 -> 0.11 | CP31: 0.09 | CQ31: =CP31+$CQ$29 -> 0.05
B32: Total revenues y/y % | D32: =IF(AND(ISNUMBER(D31),ISNUMBER(C31)),IFERROR(D31/C31-1,""),"") -> 0.56474454 | E32: =IF(AND(ISNUMBER(E31),ISNUMBER(D31)),IFERROR(E31/D31-1,""),"") -> 0.31346079 | F32: =IF(AND(ISNUMBER(F31),ISNUMBER(E31)),IFERROR(F31/E31-1,""),"") -> 0.085109713 | G32: =IF(AND(ISNUMBER(G31),ISNUMBER(F31)),IFERROR(G31/F31-1,""),"") -> 0.23975907 | H32: =IF(AND(ISNUMBER(H31),ISNUMBER(G31)),IFERROR(H31/G31-1,""),"") -> 0.29275946 | I32: =IF(AND(ISNUMBER(I31),ISNUMBER(H31)),IFERROR(I31/H31-1,""),"") -> 0.323704 | N32: =IF(AND(ISNUMBER(N31),ISNUMBER(I31)),IFERROR(N31/I31-1,""),"") -> 0.19232686 | O32: =IF(AND(ISNUMBER(O31),ISNUMBER(J31)),IFERROR(O31/J31-1,""),"") -> 0.10387286 | P32: =IF(AND(ISNUMBER(P31),ISNUMBER(K31)),IFERROR(P31/K31-1,""),"") -> 0.13115916 | Q32: =IF(AND(ISNUMBER(Q31),ISNUMBER(L31)),IFERROR(Q31/L31-1,""),"") -> 0.10944739 | R32: =IF(AND(ISNUMBER(R31),ISNUMBER(M31)),IFERROR(R31/M31-1,""),"") -> 0.073852177 | S32: =IF(AND(ISNUMBER(S31),ISNUMBER(N31)),IFERROR(S31/N31-1,""),"") -> 0.10323443 | T32: =IF(AND(ISNUMBER(T31),ISNUMBER(O31)),IFERROR(T31/O31-1,""),"") -> 0.11919585 | U32: =IF(AND(ISNUMBER(U31),ISNUMBER(P31)),IFERROR(U31/P31-1,""),"") -> 0.11106236 | ... CA32: =IF(AND(ISNUMBER(CA31),ISNUMBER(BV31)),IFERROR(CA31/BV31-1,""),"") -> 0.23691834 | CB32: =IF(AND(ISNUMBER(CB31),ISNUMBER(CA31)),IFERROR(CB31/CA31-1,""),"") -> 0.17348283 | CC32: =IF(AND(ISNUMBER(CC31),ISNUMBER(CB31)),IFERROR(CC31/CB31-1,""),"") -> 0.14658614 | CD32: =IF(AND(ISNUMBER(CD31),ISNUMBER(CC31)),IFERROR(CD31/CC31-1,""),"") -> 0.12918194 | CE32: =IF(AND(ISNUMBER(CE31),ISNUMBER(CD31)),IFERROR(CE31/CD31-1,""),"") -> 0.11257215 | CH32: =IFERROR(AVERAGE(CA32,CB32,CC32,CD32,CE32),"n/m") -> 0.15974828 | CI32: =IFERROR(AVERAGE(BB32,BG32,BL32,BQ32,BV32),"n/m") -> 0.17713997 | CJ32: =IFERROR(AVERAGE(AC32,AH32,AM32,AR32,AW32,BB32,BG32,BL32,BQ32,BV32),"n/m") -> 0.18624361 | CK32: =IFERROR(AVERAGE(C32,D32,E32,F32,G32,H32,I32,N32,S32,X32,AC32,AH32,AM32,AR32,AW32,BB32,BG32,BL32,BQ32,BV32),"n/m") -> 0.2165113 | CN32: 2029E | CO32: =CP32+$CO$29 -> 0.1 | CP32: 0.08 | CQ32: =CP32+$CQ$29 -> 0.04
B33: Google Services revenues (Σ Search, YouTube, Network, subscriptions/platforms/devices) | C33: =IF(ISNUMBER(C11),C11+C14+C17+C20,"") | D33: =IF(ISNUMBER(D11),D11+D14+D17+D20,"") | E33: =IF(ISNUMBER(E11),E11+E14+E17+E20,"") | F33: =IF(ISNUMBER(F11),F11+F14+F17+F20,"") | G33: =IF(ISNUMBER(G11),G11+G14+G17+G20,"") | H33: =IF(ISNUMBER(H11),H11+H14+H17+H20,"") | I33: =IF(ISNUMBER(I11),I11+I14+I17+I20,"") | J33: =IF(ISNUMBER(J11),J11+J14+J17+J20,"") | ... CE33: =IF(ISNUMBER(CE11),CE11+CE14+CE17+CE20,"") -> 548546.27 | CH33: =IFERROR((CE33/BV33)^(1/5)-1,"n/m") -> 0.098637732 | CI33: =IFERROR((BV33/AW33)^(1/5)-1,"n/m") -> 0.15238766 | CJ33: =IFERROR((BV33/X33)^(1/10)-1,"n/m") -> n/m | CK33: =IFERROR((BV33/C33)^(1/19)-1,"n/m") -> n/m | CN33: 2030E | CO33: =CP33+$CO$29 -> 0.09 | CP33: 0.07 | CQ33: =CP33+$CQ$29 -> 0.03
B34: Google Services y/y % | D34: =IF(AND(ISNUMBER(D33),ISNUMBER(C33)),IFERROR(D33/C33-1,""),"") | E34: =IF(AND(ISNUMBER(E33),ISNUMBER(D33)),IFERROR(E33/D33-1,""),"") | F34: =IF(AND(ISNUMBER(F33),ISNUMBER(E33)),IFERROR(F33/E33-1,""),"") | G34: =IF(AND(ISNUMBER(G33),ISNUMBER(F33)),IFERROR(G33/F33-1,""),"") | H34: =IF(AND(ISNUMBER(H33),ISNUMBER(G33)),IFERROR(H33/G33-1,""),"") | I34: =IF(AND(ISNUMBER(I33),ISNUMBER(H33)),IFERROR(I33/H33-1,""),"") | N34: =IF(AND(ISNUMBER(N33),ISNUMBER(I33)),IFERROR(N33/I33-1,""),"") | O34: =IF(AND(ISNUMBER(O33),ISNUMBER(J33)),IFERROR(O33/J33-1,""),"") | P34: =IF(AND(ISNUMBER(P33),ISNUMBER(K33)),IFERROR(P33/K33-1,""),"") | Q34: =IF(AND(ISNUMBER(Q33),ISNUMBER(L33)),IFERROR(Q33/L33-1,""),"") | R34: =IF(AND(ISNUMBER(R33),ISNUMBER(M33)),IFERROR(R33/M33-1,""),"") | S34: =IF(AND(ISNUMBER(S33),ISNUMBER(N33)),IFERROR(S33/N33-1,""),"") | T34: =IF(AND(ISNUMBER(T33),ISNUMBER(O33)),IFERROR(T33/O33-1,""),"") | U34: =IF(AND(ISNUMBER(U33),ISNUMBER(P33)),IFERROR(U33/P33-1,""),"") | ... CA34: =IF(AND(ISNUMBER(CA33),ISNUMBER(BV33)),IFERROR(CA33/BV33-1,""),"") -> 0.15333109 | CB34: =IF(AND(ISNUMBER(CB33),ISNUMBER(CA33)),IFERROR(CB33/CA33-1,""),"") -> 0.10396322 | CC34: =IF(AND(ISNUMBER(CC33),ISNUMBER(CB33)),IFERROR(CC33/CB33-1,""),"") -> 0.087796043 | CD34: =IF(AND(ISNUMBER(CD33),ISNUMBER(CC33)),IFERROR(CD33/CC33-1,""),"") -> 0.079357275 | CE34: =IF(AND(ISNUMBER(CE33),ISNUMBER(CD33)),IFERROR(CE33/CD33-1,""),"") -> 0.070659196 | CN34: YOUTUBE (YouTube ads y/y) | CO34: 0.02 | CP34: Δ → | CQ34: -0.04 | CR34: 1H26 +11.8% (FY2025 +11.7%). Assumption.
B35: Memo: Google Services segment revenues as reported (segment note) | AM35: 130524 | AR35: 151825 | AS35: 38198 | AT35: 34991 | AU35: 42573 | AV35: 52873 | AW35: 168635 | AX35: 51178 | AY35: 57067 | AZ35: 59884 | BA35: 69400 | BB35: 237529 | BC35: 61472 | BD35: 62841 | BE35: 61377 | BF35: 67838 | BG35: 253528 | BH35: 61961 | BI35: 66285 | BJ35: 67986 | BK35: 76311 | BL35: 272543 | BM35: 70398 | BN35: 73928 | BO35: 76510 | BP35: 84094 | BQ35: 304930 | BR35: 77264 | BS35: 82543 | BT35: 87052 | BU35: 95862 | BV35: 342721 | BW35: 89637 | BX35: 94540 | CN35: 2027E | CO35: =CP35+$CO$34 -> 0.13 | CP35: 0.11 | CQ35: =CP35+$CQ$34 -> 0.07
B36: Check: revenue types vs Google Services segment revenues (should be 0) | C36: =IF(AND(ISNUMBER(C33),ISNUMBER(C35)),IF(ABS(C33-C35)<=1,0,ROUND(C33-C35,0)),"") | D36: =IF(AND(ISNUMBER(D33),ISNUMBER(D35)),IF(ABS(D33-D35)<=1,0,ROUND(D33-D35,0)),"") | E36: =IF(AND(ISNUMBER(E33),ISNUMBER(E35)),IF(ABS(E33-E35)<=1,0,ROUND(E33-E35,0)),"") | F36: =IF(AND(ISNUMBER(F33),ISNUMBER(F35)),IF(ABS(F33-F35)<=1,0,ROUND(F33-F35,0)),"") | G36: =IF(AND(ISNUMBER(G33),ISNUMBER(G35)),IF(ABS(G33-G35)<=1,0,ROUND(G33-G35,0)),"") | H36: =IF(AND(ISNUMBER(H33),ISNUMBER(H35)),IF(ABS(H33-H35)<=1,0,ROUND(H33-H35,0)),"") | I36: =IF(AND(ISNUMBER(I33),ISNUMBER(I35)),IF(ABS(I33-I35)<=1,0,ROUND(I33-I35,0)),"") | J36: =IF(AND(ISNUMBER(J33),ISNUMBER(J35)),IF(ABS(J33-J35)<=1,0,ROUND(J33-J35,0)),"") | ... BX36: =IF(AND(ISNUMBER(BX33),ISNUMBER(BX35)),IF(ABS(BX33-BX35)<=1,0,ROUND(BX33-BX35,0)),"") -> 0 | CN36: 2028E | CO36: =CP36+$CO$34 -> 0.12 | CP36: 0.1 | CQ36: =CP36+$CQ$34 -> 0.06
B37: Google advertising (Search + YouTube + Network) | C37: =IF(ISNUMBER(C11),C11+C14+C17,"") | D37: =IF(ISNUMBER(D11),D11+D14+D17,"") | E37: =IF(ISNUMBER(E11),E11+E14+E17,"") | F37: =IF(ISNUMBER(F11),F11+F14+F17,"") | G37: =IF(ISNUMBER(G11),G11+G14+G17,"") | H37: =IF(ISNUMBER(H11),H11+H14+H17,"") | I37: =IF(ISNUMBER(I11),I11+I14+I17,"") | J37: =IF(ISNUMBER(J11),J11+J14+J17,"") | ... CE37: =IF(ISNUMBER(CE11),CE11+CE14+CE17,"") -> 460786.78 | CH37: =IFERROR((CE37/BV37)^(1/5)-1,"n/m") -> 0.093519739 | CI37: =IFERROR((BV37/AW37)^(1/5)-1,"n/m") -> 0.14935668 | CJ37: =IFERROR((BV37/X37)^(1/10)-1,"n/m") -> n/m | CK37: =IFERROR((BV37/C37)^(1/19)-1,"n/m") -> n/m | CN37: 2029E | CO37: =CP37+$CO$34 -> 0.11 | CP37: 0.09 | CQ37: =CP37+$CQ$34 -> 0.05
B38: Google Cloud % of total revenues | C38: =IF(AND(ISNUMBER(C23),ISNUMBER(C132)),IFERROR(C23/C132,""),"") | D38: =IF(AND(ISNUMBER(D23),ISNUMBER(D132)),IFERROR(D23/D132,""),"") | E38: =IF(AND(ISNUMBER(E23),ISNUMBER(E132)),IFERROR(E23/E132,""),"") | F38: =IF(AND(ISNUMBER(F23),ISNUMBER(F132)),IFERROR(F23/F132,""),"") | G38: =IF(AND(ISNUMBER(G23),ISNUMBER(G132)),IFERROR(G23/G132,""),"") | H38: =IF(AND(ISNUMBER(H23),ISNUMBER(H132)),IFERROR(H23/H132,""),"") | I38: =IF(AND(ISNUMBER(I23),ISNUMBER(I132)),IFERROR(I23/I132,""),"") | J38: =IF(AND(ISNUMBER(J23),ISNUMBER(J132)),IFERROR(J23/J132,""),"") | ... CE38: =IF(AND(ISNUMBER(CE23),ISNUMBER(CE132)),IFERROR(CE23/CE132,""),"") -> 0.34569878 | CH38: =IFERROR(AVERAGE(CA38,CB38,CC38,CD38,CE38),"n/m") -> 0.28239203 | CI38: =IFERROR(AVERAGE(BB38,BG38,BL38,BQ38,BV38),"n/m") -> 0.1088675 | CJ38: =IFERROR(AVERAGE(AC38,AH38,AM38,AR38,AW38,BB38,BG38,BL38,BQ38,BV38),"n/m") -> 0.083359882 | CK38: =IFERROR(AVERAGE(C38,D38,E38,F38,G38,H38,I38,N38,S38,X38,AC38,AH38,AM38,AR38,AW38,BB38,BG38,BL38,BQ38,BV38),"n/m") -> 0.083359882 | CN38: 2030E | CO38: =CP38+$CO$34 -> 0.1 | CP38: 0.08 | CQ38: =CP38+$CQ$34 -> 0.04
B39: Contribution to revenue growth — Google Services (pp) | D39: =IFERROR((D33-C33)/C132,"") | E39: =IFERROR((E33-D33)/D132,"") | F39: =IFERROR((F33-E33)/E132,"") | G39: =IFERROR((G33-F33)/F132,"") | H39: =IFERROR((H33-G33)/G132,"") | I39: =IFERROR((I33-H33)/H132,"") | N39: =IFERROR((N33-I33)/I132,"") | O39: =IFERROR((O33-J33)/J132,"") | P39: =IFERROR((P33-K33)/K132,"") | Q39: =IFERROR((Q33-L33)/L132,"") | R39: =IFERROR((R33-M33)/M132,"") | S39: =IFERROR((S33-N33)/N132,"") | T39: =IFERROR((T33-O33)/O132,"") | U39: =IFERROR((U33-P33)/P132,"") | ... CA39: =IFERROR((CA33-BV33)/BV132,"") -> 0.13044957 | CB39: =IFERROR((CB33-CA33)/CA132,"") -> 0.082471733 | CC39: =IFERROR((CC33-CB33)/CB132,"") -> 0.065501983 | CD39: =IFERROR((CD33-CC33)/CC132,"") -> 0.056141688 | CE39: =IFERROR((CE33-CD33)/CD132,"") -> 0.047759089 | CN39: NETWORK (Google Network y/y) | CO39: 0.02 | CP39: Δ → | CQ39: -0.03 | CR39: 1H26 −2.3% (FY2025 −1.9%, FY2024 −3.0%): structural decline. Assumption.
B40: Contribution to revenue growth — Google Cloud (pp) | D40: =IFERROR((D23-C23)/C132,"") -> 0 | E40: =IFERROR((E23-D23)/D132,"") -> 0 | F40: =IFERROR((F23-E23)/E132,"") -> 0 | G40: =IFERROR((G23-F23)/F132,"") -> 0 | H40: =IFERROR((H23-G23)/G132,"") -> 0 | I40: =IFERROR((I23-H23)/H132,"") -> 0 | N40: =IFERROR((N23-I23)/I132,"") -> 0 | O40: =IFERROR((O23-J23)/J132,"") -> 0 | P40: =IFERROR((P23-K23)/K132,"") -> 0 | Q40: =IFERROR((Q23-L23)/L132,"") -> 0 | R40: =IFERROR((R23-M23)/M132,"") -> 0 | S40: =IFERROR((S23-N23)/N132,"") -> 0 | T40: =IFERROR((T23-O23)/O132,"") -> 0 | U40: =IFERROR((U23-P23)/P132,"") -> 0 | ... CA40: =IFERROR((CA23-BV23)/BV132,"") -> 0.10647628 | CB40: =IFERROR((CB23-CA23)/CA132,"") -> 0.091754241 | CC40: =IFERROR((CC23-CB23)/CB132,"") -> 0.080599269 | CD40: =IFERROR((CD23-CC23)/CC132,"") -> 0.07245474 | CE40: =IFERROR((CE23-CD23)/CD132,"") -> 0.064134277 | CN40: 2027E | CO40: =CP40+$CO$39 -> -0.01 | CP40: -0.03 | CQ40: =CP40+$CQ$39 -> -0.06
B41: Operating KPIs: | CN41: 2028E | CO41: =CP41+$CO$39 -> -0.01 | CP41: -0.03 | CQ41: =CP41+$CQ$39 -> -0.06
B42: Traffic acquisition costs (TAC; release) | T42: 3345 | U42: 3377 | V42: 3566 | W42: 4055 | X42: 14343 | Y42: 3788 | Z42: 3975 | AA42: 4182 | AB42: 4848 | AC42: 16793 | AD42: 4629 | AE42: 5091 | AF42: 5502 | AG42: 6450 | AH42: 21672 | AI42: 6288 | AJ42: 6420 | AK42: 6582 | AL42: 7436 | AM42: 26726 | AN42: 6860 | AO42: 7238 | AP42: 7490 | AQ42: 8501 | AR42: 30089 | AS42: 7452 | AT42: 6694 | AU42: 8166 | AV42: 10466 | AW42: 32778 | AX42: 9712 | AY42: 10929 | AZ42: 11498 | BA42: 13427 | BB42: 45566 | BC42: 11990 | BD42: 12214 | BE42: 11826 | BF42: 12925 | BG42: 48955 | BH42: 11721 | BI42: 12537 | BJ42: 12642 | BK42: 13986 | BL42: 50886 | BM42: 12946 | BN42: 13387 | BO42: 13719 | BP42: 14848 | BQ42: 54900 | BR42: 13748 | BS42: 14705 | BT42: 14876 | BU42: 16597 | BV42: 59926 | BW42: 15228 | BX42: 16179 | CF42: Total TAC from the earnings releases (annual = Σ quarters). TAC is inside cost of revenues and Google Services costs. | CH42: =IFERROR((CE42/BV42)^(1/5)-1,"n/m") -> -1 | CI42: =IFERROR((BV42/AW42)^(1/5)-1,"n/m") -> 0.12825318 | CJ42: =IFERROR((BV42/X42)^(1/10)-1,"n/m") -> 0.15371232 | CK42: =IFERROR((BV42/C42)^(1/19)-1,"n/m") -> n/m | CN42: 2029E | CO42: =CP42+$CO$39 -> -0.01 | CP42: -0.03 | CQ42: =CP42+$CQ$39 -> -0.06
B43: TAC % of Google advertising revenues | C43: =IF(AND(ISNUMBER(C42),ISNUMBER(C37)),IFERROR(C42/C37,""),"") | D43: =IF(AND(ISNUMBER(D42),ISNUMBER(D37)),IFERROR(D42/D37,""),"") | E43: =IF(AND(ISNUMBER(E42),ISNUMBER(E37)),IFERROR(E42/E37,""),"") | F43: =IF(AND(ISNUMBER(F42),ISNUMBER(F37)),IFERROR(F42/F37,""),"") | G43: =IF(AND(ISNUMBER(G42),ISNUMBER(G37)),IFERROR(G42/G37,""),"") | H43: =IF(AND(ISNUMBER(H42),ISNUMBER(H37)),IFERROR(H42/H37,""),"") | I43: =IF(AND(ISNUMBER(I42),ISNUMBER(I37)),IFERROR(I42/I37,""),"") | J43: =IF(AND(ISNUMBER(J42),ISNUMBER(J37)),IFERROR(J42/J37,""),"") | ... BX43: =IF(AND(ISNUMBER(BX42),ISNUMBER(BX37)),IFERROR(BX42/BX37,""),"") -> 0.19820162 | CH43: =IFERROR(AVERAGE(CA43,CB43,CC43,CD43,CE43),"n/m") -> n/m | CI43: =IFERROR(AVERAGE(BB43,BG43,BL43,BQ43,BV43),"n/m") -> 0.21207408 | CJ43: =IFERROR(AVERAGE(AC43,AH43,AM43,AR43,AW43,BB43,BG43,BL43,BQ43,BV43),"n/m") -> 0.21809922 | CK43: =IFERROR(AVERAGE(C43,D43,E43,F43,G43,H43,I43,N43,S43,X43,AC43,AH43,AM43,AR43,AW43,BB43,BG43,BL43,BQ43,BV43),"n/m") -> 0.21809922 | CN43: 2030E | CO43: =CP43+$CO$39 -> -0.01 | CP43: -0.03 | CQ43: =CP43+$CQ$39 -> -0.06
B44: Revenue backlog — remaining performance obligations (period end; Google Cloud ~99%) | AR44: 11400 | AS44: 12800 | AT44: 14800 | AU44: 19000 | AW44: 29800 | AX44: 30700 | AY44: 35300 | AZ44: 37100 | BB44: 51000 | BC44: 50500 | BD44: 51200 | BE44: 52400 | BG44: 64300 | BH44: 61700 | BI44: 60600 | BJ44: 64900 | BL44: 74100 | BM44: 72500 | BN44: 78800 | BO44: 86800 | BQ44: 93200 | BR44: 92400 | BS44: 108200 | BT44: 157700 | BV44: 242800 | BW44: 467600 | BX44: 519500 | CF44: 10-Q / 10-K revenue note (XBRL RevenueRemainingPerformanceObligation); Google Cloud $513.9bn of $519.5bn at 30-Jun-2026, about half recognised within 24 months. | CN44: SUBS (subscriptions, platforms & devices y/y) | CO44: 0.02 | CP44: Δ → | CQ44: -0.04 | CR44: 1H26 +17.2% (FY2025 +19.1%): YouTube subscriptions, Google One / AI plans, Play. Assumption.
B45: Employees (period end; release) | AG45: 80110 | AH45: 80110 | AI45: 85050 | AJ45: 89058 | AK45: 94372 | AL45: 98771 | AM45: 98771 | AN45: 103459 | AO45: 107646 | AP45: 114096 | AQ45: 118899 | AR45: 118899 | AS45: 123048 | AT45: 127498 | AU45: 132121 | AV45: 135301 | AW45: 135301 | AX45: 139995 | AY45: 144056 | AZ45: 150028 | BA45: 156500 | BB45: 156500 | BC45: 163906 | BD45: 174014 | BE45: 186779 | BF45: 190234 | BG45: 190234 | BH45: 190711 | BI45: 181798 | BJ45: 182381 | BK45: 182502 | BL45: 182502 | BM45: 180895 | BN45: 179582 | BO45: 181269 | BP45: 183323 | BQ45: 183323 | BR45: 185719 | BS45: 187103 | BT45: 190167 | BU45: 190820 | BV45: 190820 | BW45: 194668 | BX45: 198933 | CH45: =IFERROR((CE45/BV45)^(1/5)-1,"n/m") -> -1 | CI45: =IFERROR((BV45/AW45)^(1/5)-1,"n/m") -> 0.071185233 | CJ45: =IFERROR((BV45/X45)^(1/10)-1,"n/m") -> n/m | CK45: =IFERROR((BV45/C45)^(1/19)-1,"n/m") -> n/m | CN45: 2027E | CO45: =CP45+$CO$44 -> 0.16 | CP45: 0.14 | CQ45: =CP45+$CQ$44 -> 0.1
B46: Legacy revenue split, as first reported (Google websites / properties incl. YouTube; Network members; other incl. Cloud, Play, hardware; Motorola Mobile 2012–13): | CN46: 2028E | CO46: =CP46+$CO$44 -> 0.14 | CP46: 0.12 | CQ46: =CP46+$CQ$44 -> 0.08
B47: Google websites / properties | C47: 6332.797 | D47: 10624.7 | E47: 14413.8 | F47: 15722.486 | G47: 19444 | H47: 26145 | I47: 31221 | J47: 8640 | K47: 8868 | L47: 9394 | M47: 10551 | N47: 37453 | O47: 10469 | P47: 10935 | Q47: 11252 | R47: 12429 | S47: 45085 | T47: 11932 | U47: 12402 | V47: 13087 | W47: 14936 | X47: 52357 | Y47: 14328 | Z47: 15400 | AA47: 16089 | AB47: 17968 | AC47: 63785 | AD47: 17403 | AE47: 18425 | AF47: 19723 | AG47: 22237 | AH47: 77788 | AI47: 21998 | AJ47: 23262 | AK47: 24054 | AL47: 27022 | AM47: 96336 | AN47: 25682 | AO47: 27335 | AP47: 28647 | AQ47: 31600 | AR47: 113264 | AS47: 28540 | AT47: 25131 | AU47: 31375 | CN47: 2029E | CO47: =CP47+$CO$44 -> 0.13 | CP47: 0.11 | CQ47: =CP47+$CQ$44 -> 0.07
B48: Google Network Members' websites / properties | C48: 4159.831 | D48: 5787.9 | E48: 6714.7 | F48: 7166.318 | G48: 8792 | H48: 10386 | I48: 12465 | J48: 3262 | K48: 3193 | L48: 3148 | M48: 3522 | N48: 13125 | O48: 3397 | P48: 3424 | Q48: 3430 | R48: 3720 | S48: 13971 | T48: 3576 | U48: 3621 | V48: 3694 | W48: 4142 | X48: 15033 | Y48: 3692 | Z48: 3743 | AA48: 3732 | AB48: 4431 | AC48: 15598 | AD48: 4008 | AE48: 4247 | AF48: 4342 | AG48: 4990 | AH48: 17587 | AI48: 4644 | AJ48: 4825 | AK48: 4900 | AL48: 5613 | AM48: 19982 | AN48: 5038 | AO48: 5266 | AP48: 5269 | AQ48: 5974 | AR48: 21547 | AS48: 5223 | AT48: 4736 | AU48: 5720 | AV48: 7411 | AW48: 23090 | CN48: 2030E | CO48: =CP48+$CO$44 -> 0.12 | CP48: 0.1 | CQ48: =CP48+$CQ$44 -> 0.06
B49: Other revenues (licensing, Cloud, Play, hardware) | C49: 112.289 | D49: 181.4 | E49: 667.1 | F49: 761.759 | G49: 1085 | H49: 1374 | I49: 2353 | J49: 1049 | K49: 1046 | L49: 1230 | M49: 1647 | N49: 4972 | O49: 1554 | P49: 1596 | Q49: 1841 | R49: 1954 | S49: 6945 | T49: 1750 | U49: 1704 | V49: 1894 | W49: 1803 | X49: 7151 | Y49: 2071 | Z49: 2172 | AA49: 2433 | AB49: 3404 | AC49: 10080 | AD49: 3095 | AE49: 3090 | AF49: 3405 | AG49: 4687 | AH49: 14277 | AI49: 4354 | AJ49: 4425 | AK49: 4640 | AL49: 6487 | AM49: 19906 | AN49: 5449 | AO49: 6181 | AP49: 6428 | CN49: CLOUD (Google Cloud y/y) | CO49: 0.08 | CP49: Δ → | CQ49: -0.12 | CR49: 1H26 +73% (Q2-26 +82%; Wiz from 11-Mar-2026; TPU system sales); backlog $513.9bn at 30-Jun-2026 (about half within 24 months) vs FY2025 revenue $58.7bn. Capacity-constrained. Assumption.
B50: Motorola Mobile (hardware and other) | I50: 4136 | J50: 1018 | K50: 998 | L50: 1139 | M50: 618 | N50: 3773 | CN50: 2027E | CO50: =CP50+$CO$49 -> 0.53 | CP50: 0.45 | CQ50: =CP50+$CQ$49 -> 0.33
B51: Other Bets revenues | X51: 448 | Y51: 166 | Z51: 185 | AA51: 197 | AB51: 261 | AC51: 809 | AD51: 244 | AE51: 248 | AF51: 302 | AG51: 409 | AH51: 1203 | AI51: 150 | AJ51: 145 | AK51: 146 | AL51: 154 | AM51: 595 | AN51: 170 | AO51: 162 | AP51: 155 | AQ51: 172 | AR51: 659 | AS51: 135 | AT51: 148 | AU51: 178 | CN51: 2028E | CO51: =CP51+$CO$49 -> 0.4 | CP51: 0.32 | CQ51: =CP51+$CQ$49 -> 0.2
B52: Not split / basis differences (derived; FY2013 Motorola after the Home disposal, Other Bets in 2015 quarters) | C52: =IF(ISNUMBER(C47),C132-(N(C47)+N(C48)+N(C49)+N(C50)+N(C51)),"") -> 0 | D52: =IF(ISNUMBER(D47),D132-(N(D47)+N(D48)+N(D49)+N(D50)+N(D51)),"") -> -0.014 | E52: =IF(ISNUMBER(E47),E132-(N(E47)+N(E48)+N(E49)+N(E50)+N(E51)),"") -> -0.05 | F52: =IF(ISNUMBER(F47),F132-(N(F47)+N(F48)+N(F49)+N(F50)+N(F51)),"") -> 0 | G52: =IF(ISNUMBER(G47),G132-(N(G47)+N(G48)+N(G49)+N(G50)+N(G51)),"") -> 0 | H52: =IF(ISNUMBER(H47),H132-(N(H47)+N(H48)+N(H49)+N(H50)+N(H51)),"") -> 0 | I52: =IF(ISNUMBER(I47),I132-(N(I47)+N(I48)+N(I49)+N(I50)+N(I51)),"") -> 0 | J52: =IF(ISNUMBER(J47),J132-(N(J47)+N(J48)+N(J49)+N(J50)+N(J51)),"") -> 0 | ... BX52: =IF(ISNUMBER(BX47),BX132-(N(BX47)+N(BX48)+N(BX49)+N(BX50)+N(BX51)),"") | CN52: 2029E | CO52: =CP52+$CO$49 -> 0.33 | CP52: 0.25 | CQ52: =CP52+$CQ$49 -> 0.13
CN53: 2030E | CO53: =CP53+$CO$49 -> 0.28 | CP53: 0.2 | CQ53: =CP53+$CQ$49 -> 0.08
B54: Segment operating income (company measure; latest filing presenting the period — annual from FY2018, quarterly from Q1/20) | CF54: SEGMENTS — Q3–Q4/26E margins: last actual quarter + sequential seasonality (Services) / held (Cloud) + scenario shift; 2027E+: scenario levers | CN54: OB (Other Bets revenues y/y) | CO54: 0.1 | CP54: Δ → | CQ54: -0.1 | CR54: GFiber (internet services; revenue not disclosed) deconsolidated at its late-2026 closing → 2027E −30% (assumption); Waymo growth thereafter.
B55: Google Services operating income | AM55: 43137 | AR55: 48999 | AS55: 11548 | AT55: 9539 | AU55: 14453 | AV55: 19066 | AW55: 54606 | AX55: 19546 | AY55: 22343 | AZ55: 23973 | BA55: 22270 | BB55: 88132 | BC55: 21973 | BD55: 21621 | BE55: 18883 | BF55: 20222 | BG55: 82699 | BH55: 21737 | BI55: 23454 | BJ55: 23937 | BK55: 26730 | BL55: 95858 | BM55: 27897 | BN55: 29674 | BO55: 30856 | BP55: 32836 | BQ55: 121263 | BR55: 32682 | BS55: 33063 | BT55: 33527 | BU55: 40132 | BV55: 139404 | BW55: 40589 | BX55: 39544 | BY55: =BY33*BY56 -> 40462.41 | BZ55: =BZ33*BZ56 -> 48286.612 | CA55: =SUM(BW55:BZ55) -> 168882.02 | CB55: =CB33*CB56 -> 183273.05 | CC55: =CC33*CC56 -> 192243.57 | CD55: =CD33*CD56 -> 202376.05 | CE55: =CE33*CE56 -> 211190.31 | CH55: =IFERROR((CE55/BV55)^(1/5)-1,"n/m") -> 0.08662515 | CI55: =IFERROR((BV55/AW55)^(1/5)-1,"n/m") -> 0.2061657 | CJ55: =IFERROR((BV55/X55)^(1/10)-1,"n/m") -> n/m | CK55: =IFERROR((BV55/C55)^(1/19)-1,"n/m") -> n/m | CN55: 2027E | CO55: =CP55+$CO$54 -> -0.2 | CP55: -0.3 | CQ55: =CP55+$CQ$54 -> -0.4
B56: Google Services operating margin % | C56: =IF(AND(ISNUMBER(C55),ISNUMBER(C33)),IFERROR(C55/C33,""),"") | D56: =IF(AND(ISNUMBER(D55),ISNUMBER(D33)),IFERROR(D55/D33,""),"") | E56: =IF(AND(ISNUMBER(E55),ISNUMBER(E33)),IFERROR(E55/E33,""),"") | F56: =IF(AND(ISNUMBER(F55),ISNUMBER(F33)),IFERROR(F55/F33,""),"") | G56: =IF(AND(ISNUMBER(G55),ISNUMBER(G33)),IFERROR(G55/G33,""),"") | H56: =IF(AND(ISNUMBER(H55),ISNUMBER(H33)),IFERROR(H55/H33,""),"") | I56: =IF(AND(ISNUMBER(I55),ISNUMBER(I33)),IFERROR(I55/I33,""),"") | J56: =IF(AND(ISNUMBER(J55),ISNUMBER(J33)),IFERROR(J55/J33,""),"") | ... BX56: =IF(AND(ISNUMBER(BX55),ISNUMBER(BX33)),IFERROR(BX55/BX33,""),"") -> 0.41827798 | BY56: =BY57+BY102 -> 0.40286073 | BZ56: =BZ57+BY102 -> 0.43636658 | CA56: =IF(AND(ISNUMBER(CA55),ISNUMBER(CA33)),IFERROR(CA55/CA33,""),"") -> 0.42725653 | CB56: =CHOOSE(MATCH($CF$2,{"Bull","Base","Bear"},0),$CO$60,$CP$60,$CQ$60) -> 0.42 | CC56: =CHOOSE(MATCH($CF$2,{"Bull","Base","Bear"},0),$CO$61,$CP$61,$CQ$61) -> 0.405 | CD56: =CHOOSE(MATCH($CF$2,{"Bull","Base","Bear"},0),$CO$62,$CP$62,$CQ$62) -> 0.395 | CE56: =CHOOSE(MATCH($CF$2,{"Bull","Base","Bear"},0),$CO$63,$CP$63,$CQ$63) -> 0.385 | CH56: =IFERROR(AVERAGE(CA56,CB56,CC56,CD56,CE56),"n/m") -> 0.40645131 | CI56: =IFERROR(AVERAGE(BB56,BG56,BL56,BQ56,BV56),"n/m") -> 0.37067559 | CJ56: =IFERROR(AVERAGE(AC56,AH56,AM56,AR56,AW56,BB56,BG56,BL56,BQ56,BV56),"n/m") -> 0.35380176 | CK56: =IFERROR(AVERAGE(C56,D56,E56,F56,G56,H56,I56,N56,S56,X56,AC56,AH56,AM56,AR56,AW56,BB56,BG56,BL56,BQ56,BV56),"n/m") -> 0.35380176 | CN56: 2028E | CO56: =CP56+$CO$54 -> 0.35 | CP56: 0.25 | CQ56: =CP56+$CQ$54 -> 0.15
B57: Q3–Q4/26E margin before scenario shift (prior quarter + last year's sequential change) | BY57: =BX56+(BT56-BS56) -> 0.40286073 | BZ57: =BY57+(BU56-BT56) -> 0.43636658 | CF57: Q3E = Q2-26 margin + (Q3-25 − Q2-25); Q4E = Q3E + (Q4-25 − Q3-25): sequential seasonality of the prior year (ODFL approach). | CN57: 2029E | CO57: =CP57+$CO$54 -> 0.35 | CP57: 0.25 | CQ57: =CP57+$CQ$54 -> 0.15
B58: Google Cloud operating income | AM58: -4348 | AR58: -4645 | AS58: -1730 | AT58: -1426 | AU58: -1208 | AV58: -1243 | AW58: -5607 | AX58: -974 | AY58: -591 | AZ58: -644 | BA58: -73 | BB58: -2282 | BC58: -706 | BD58: -590 | BE58: -440 | BF58: -186 | BG58: -1922 | BH58: 191 | BI58: 395 | BJ58: 266 | BK58: 864 | BL58: 1716 | BM58: 900 | BN58: 1172 | BO58: 1947 | BP58: 2093 | BQ58: 6112 | BR58: 2177 | BS58: 2826 | BT58: 3594 | BU58: 5313 | BV58: 13910 | BW58: 6598 | BX58: 8814 | BY58: =BY23*BY59 -> 9334.761 | BZ58: =BZ23*BZ59 -> 10878.75 | CA58: =SUM(BW58:BZ58) -> 35625.511 | CB58: =CB23*CB59 -> 48614.394 | CC58: =CC23*CC59 -> 62226.425 | CD58: =CD23*CD59 -> 77783.031 | CE58: =CE23*CE59 -> 93339.637 | CN58: 2030E | CO58: =CP58+$CO$54 -> 0.35 | CP58: 0.25 | CQ58: =CP58+$CQ$54 -> 0.15
B59: Google Cloud operating margin % | C59: =IF(AND(ISNUMBER(C58),ISNUMBER(C23)),IFERROR(C58/C23,""),"") | D59: =IF(AND(ISNUMBER(D58),ISNUMBER(D23)),IFERROR(D58/D23,""),"") | E59: =IF(AND(ISNUMBER(E58),ISNUMBER(E23)),IFERROR(E58/E23,""),"") | F59: =IF(AND(ISNUMBER(F58),ISNUMBER(F23)),IFERROR(F58/F23,""),"") | G59: =IF(AND(ISNUMBER(G58),ISNUMBER(G23)),IFERROR(G58/G23,""),"") | H59: =IF(AND(ISNUMBER(H58),ISNUMBER(H23)),IFERROR(H58/H23,""),"") | I59: =IF(AND(ISNUMBER(I58),ISNUMBER(I23)),IFERROR(I58/I23,""),"") | J59: =IF(AND(ISNUMBER(J58),ISNUMBER(J23)),IFERROR(J58/J23,""),"") | ... BX59: =IF(AND(ISNUMBER(BX58),ISNUMBER(BX23)),IFERROR(BX58/BX23,""),"") -> 0.3558624 | BY59: =BX59+BY102 -> 0.3558624 | BZ59: =BX59+BY102 -> 0.3558624 | CA59: =IF(AND(ISNUMBER(CA58),ISNUMBER(CA23)),IFERROR(CA58/CA23,""),"") -> 0.35065349 | CB59: =CHOOSE(MATCH($CF$2,{"Bull","Base","Bear"},0),$CO$65,$CP$65,$CQ$65) -> 0.33 | CC59: =CHOOSE(MATCH($CF$2,{"Bull","Base","Bear"},0),$CO$66,$CP$66,$CQ$66) -> 0.32 | CD59: =CHOOSE(MATCH($CF$2,{"Bull","Base","Bear"},0),$CO$67,$CP$67,$CQ$67) -> 0.32 | CE59: =CHOOSE(MATCH($CF$2,{"Bull","Base","Bear"},0),$CO$68,$CP$68,$CQ$68) -> 0.32 | CF59: Q3–Q4/26E: Q2-26 margin held (Cloud margins have risen with scale, not seasonally; management flagged leased third-party data-centre capacity in Q3 — call, unverified) + scenario shift. | CH59: =IFERROR(AVERAGE(CA59,CB59,CC59,CD59,CE59),"n/m") -> 0.3281307 | CI59: =IFERROR(AVERAGE(BB59,BG59,BL59,BQ59,BV59),"n/m") -> 0.047648644 | CJ59: =IFERROR(AVERAGE(AC59,AH59,AM59,AR59,AW59,BB59,BG59,BL59,BQ59,BV59),"n/m") -> -0.18209352 | CK59: =IFERROR(AVERAGE(C59,D59,E59,F59,G59,H59,I59,N59,S59,X59,AC59,AH59,AM59,AR59,AW59,BB59,BG59,BL59,BQ59,BV59),"n/m") -> -0.18209352 | CN59: SVC_M (Google Services operating margin) | CO59: 0.015 | CP59: Δ → | CQ59: -0.025 | CR59: 1H26 43.5% (FY2025 40.7%, FY2024 39.8%). Steps down as allocated AI-infrastructure depreciation rises (model D&A 6% → 14% of revenues 2025–30E on $250–300bn p.a. capex), keeping group adjusted EBITDA margin ~42–44% (1H26 41%). Assumption.
B60: Incremental Google Cloud margin (Δ operating income / Δ revenues) | D60: =IFERROR((D58-C58)/(D23-C23),"") | E60: =IFERROR((E58-D58)/(E23-D23),"") | F60: =IFERROR((F58-E58)/(F23-E23),"") | G60: =IFERROR((G58-F58)/(G23-F23),"") | H60: =IFERROR((H58-G58)/(H23-G23),"") | I60: =IFERROR((I58-H58)/(I23-H23),"") | N60: =IFERROR((N58-I58)/(N23-I23),"") | O60: =IFERROR((O58-J58)/(O23-J23),"") | P60: =IFERROR((P58-K58)/(P23-K23),"") | Q60: =IFERROR((Q58-L58)/(Q23-L23),"") | R60: =IFERROR((R58-M58)/(R23-M23),"") | S60: =IFERROR((S58-N58)/(S23-N23),"") | T60: =IFERROR((T58-O58)/(T23-O23),"") | U60: =IFERROR((U58-P58)/(U23-P23),"") | ... CA60: =IFERROR((CA58-BV58)/(CA23-BV23),"") -> 0.50627782 | CB60: =IFERROR((CB58-CA58)/(CB23-CA23),"") -> 0.28410335 | CC60: =IFERROR((CC58-CB58)/(CC23-CB23),"") -> 0.28875 | CD60: =IFERROR((CD58-CC58)/(CD23-CC23),"") -> 0.32 | CE60: =IFERROR((CE58-CD58)/(CE23-CD23),"") -> 0.32 | CN60: 2027E | CO60: =CP60+$CO$59 -> 0.435 | CP60: 0.42 | CQ60: =CP60+$CQ$59 -> 0.395
B61: Other Bets operating income (loss) | AM61: -3358 | AR61: -4824 | AS61: -1121 | AT61: -1116 | AU61: -1103 | AV61: -1136 | AW61: -4476 | AX61: -1145 | AY61: -1398 | AZ61: -1288 | BA61: -220 | BB61: -4051 | BC61: -835 | BD61: -1339 | BE61: -1225 | BF61: -1237 | BG61: -4636 | BH61: -1225 | BI61: -813 | BJ61: -1194 | BK61: -863 | BL61: -4095 | BM61: -1020 | BN61: -1134 | BO61: -1116 | BP61: -1174 | BQ61: -4444 | BR61: -1226 | BS61: -1246 | BT61: -1426 | BU61: -3617 | BV61: -7515 | BW61: -2100 | BX61: -1799 | BY61: =BX61 -> -1799 | BZ61: =BY61 -> -1799 | CA61: =SUM(BW61:BZ61) -> -7497 | CB61: =CHOOSE(MATCH($CF$2,{"Bull","Base","Bear"},0),$CO$70,$CP$70,$CQ$70) -> -8000 | CC61: =CHOOSE(MATCH($CF$2,{"Bull","Base","Bear"},0),$CO$71,$CP$71,$CQ$71) -> -8500 | CD61: =CHOOSE(MATCH($CF$2,{"Bull","Base","Bear"},0),$CO$72,$CP$72,$CQ$72) -> -9000 | CE61: =CHOOSE(MATCH($CF$2,{"Bull","Base","Bear"},0),$CO$73,$CP$73,$CQ$73) -> -9000 | CF61: Q3–Q4/26E: Q2-26 loss held. 2027E+: scenario lever ($m; Waymo scale-up; GFiber deconsolidated at closing). | CN61: 2028E | CO61: =CP61+$CO$59 -> 0.42 | CP61: 0.405 | CQ61: =CP61+$CQ$59 -> 0.38
B62: Alphabet-level activities (shared AI research & frontier models, corporate costs, fines & settlements, hedging) | AM62: -7907 | AR62: -5299 | AS62: -720 | AT62: -614 | AU62: -929 | AV62: -1036 | AW62: -3299 | AX62: -990 | AY62: -993 | AZ62: -1010 | BA62: -92 | BB62: -3085 | BC62: -338 | BD62: -239 | BE62: -83 | BF62: -639 | BG62: -1299 | BH62: -3288 | BI62: -1198 | BJ62: -1666 | BK62: -3034 | BL62: -9186 | BM62: -2305 | BN62: -2287 | BO62: -3166 | BP62: -2783 | BQ62: -10541 | BR62: -3027 | BS62: -3372 | BT62: -4467 | BU62: -5894 | BV62: -16760 | BW62: -5391 | BX62: -5789 | BY62: =BX62*(1+BY63) -> -6216.383 | BZ62: =BY62*(1+BY63) -> -6675.3184 | CA62: =SUM(BW62:BZ62) -> -24071.701 | CB62: =-CB132*CB64 -> -29244.205 | CC62: =-CC132*CC64 -> -33548.112 | CD62: =-CD132*CD64 -> -36384.458 | CE62: =-CE132*CE64 -> -38812.902 | CF62: Includes Google DeepMind / general AI model development (from 2023), EC fines and legal settlements, severance and office-space charges, and hedging gains. Q3–Q4/26E: prior quarter × (1 + Q2/Q1-26 sequential growth); 2027E+: % of revenues (scenario lever). | CN62: 2029E | CO62: =CP62+$CO$59 -> 0.41 | CP62: 0.395 | CQ62: =CP62+$CQ$59 -> 0.37
B63: Q3–Q4/26E sequential growth of Alphabet-level costs (Q2/Q1-26) | BY63: =IFERROR(BX62/BW62-1,0) -> 0.073826748 | BZ63: =IFERROR(BX62/BW62-1,0) -> 0.073826748 | CN63: 2030E | CO63: =CP63+$CO$59 -> 0.4 | CP63: 0.385 | CQ63: =CP63+$CQ$59 -> 0.36
B64: Alphabet-level costs % of revenues | C64: =IF(ISNUMBER(C62),IFERROR(-C62/C132,""),"") | D64: =IF(ISNUMBER(D62),IFERROR(-D62/D132,""),"") | E64: =IF(ISNUMBER(E62),IFERROR(-E62/E132,""),"") | F64: =IF(ISNUMBER(F62),IFERROR(-F62/F132,""),"") | G64: =IF(ISNUMBER(G62),IFERROR(-G62/G132,""),"") | H64: =IF(ISNUMBER(H62),IFERROR(-H62/H132,""),"") | I64: =IF(ISNUMBER(I62),IFERROR(-I62/I132,""),"") | J64: =IF(ISNUMBER(J62),IFERROR(-J62/J132,""),"") | ... CA64: =IF(ISNUMBER(CA62),IFERROR(-CA62/CA132,""),"") -> 0.04831005 | CB64: =CHOOSE(MATCH($CF$2,{"Bull","Base","Bear"},0),$CO$75,$CP$75,$CQ$75) -> 0.05 | CC64: =CHOOSE(MATCH($CF$2,{"Bull","Base","Bear"},0),$CO$76,$CP$76,$CQ$76) -> 0.05 | CD64: =CHOOSE(MATCH($CF$2,{"Bull","Base","Bear"},0),$CO$77,$CP$77,$CQ$77) -> 0.048 | CE64: =CHOOSE(MATCH($CF$2,{"Bull","Base","Bear"},0),$CO$78,$CP$78,$CQ$78) -> 0.046 | CH64: =IFERROR(AVERAGE(CA64,CB64,CC64,CD64,CE64),"n/m") -> 0.04846201 | CI64: =IFERROR(AVERAGE(BB64,BG64,BL64,BQ64,BV64),"n/m") -> 0.023634213 | CJ64: =IFERROR(AVERAGE(AC64,AH64,AM64,AR64,AW64,BB64,BG64,BL64,BQ64,BV64),"n/m") -> 0.028346945 | CK64: =IFERROR(AVERAGE(C64,D64,E64,F64,G64,H64,I64,N64,S64,X64,AC64,AH64,AM64,AR64,AW64,BB64,BG64,BL64,BQ64,BV64),"n/m") -> 0.028346945 | CN64: CLOUD_M (Google Cloud operating margin) | CO64: 0.02 | CP64: Δ → | CQ64: -0.05 | CR64: 1H26 34.4%, Q2-26 35.6% (FY2025 23.7%, FY2024 14.1%); depreciation of new capacity, leased third-party data centres and Wiz amortization offset scale. Assumption.
B65: Segment recast / basis difference (consolidated OI as originally reported − Σ segments as recast) | C65: =IF(ISNUMBER(C55),C140-(N(C55)+N(C58)+N(C61)+N(C62)),"") | D65: =IF(ISNUMBER(D55),D140-(N(D55)+N(D58)+N(D61)+N(D62)),"") | E65: =IF(ISNUMBER(E55),E140-(N(E55)+N(E58)+N(E61)+N(E62)),"") | F65: =IF(ISNUMBER(F55),F140-(N(F55)+N(F58)+N(F61)+N(F62)),"") | G65: =IF(ISNUMBER(G55),G140-(N(G55)+N(G58)+N(G61)+N(G62)),"") | H65: =IF(ISNUMBER(H55),H140-(N(H55)+N(H58)+N(H61)+N(H62)),"") | I65: =IF(ISNUMBER(I55),I140-(N(I55)+N(I58)+N(I61)+N(I62)),"") | J65: =IF(ISNUMBER(J55),J140-(N(J55)+N(J58)+N(J61)+N(J62)),"") | ... BX65: =IF(ISNUMBER(BX55),BX140-(N(BX55)+N(BX58)+N(BX61)+N(BX62)),"") -> 0 | BY65: =0 -> 0 | BZ65: =0 -> 0 | CA65: =SUM(BW65:BZ65) -> 0 | CB65: =0 -> 0 | CC65: =0 -> 0 | CD65: =0 -> 0 | CE65: =0 -> 0 | CF65: 2018: performance fees reclassified from operating expenses to OI&E in 2019 and segments recast ($1,203m); otherwise 0. | CN65: 2027E | CO65: =CP65+$CO$64 -> 0.35 | CP65: 0.33 | CQ65: =CP65+$CQ$64 -> 0.28
B66: Operating income (segment build) | C66: =IF(ISNUMBER(C55),N(C55)+N(C58)+N(C61)+N(C62)+N(C65),"") | D66: =IF(ISNUMBER(D55),N(D55)+N(D58)+N(D61)+N(D62)+N(D65),"") | E66: =IF(ISNUMBER(E55),N(E55)+N(E58)+N(E61)+N(E62)+N(E65),"") | F66: =IF(ISNUMBER(F55),N(F55)+N(F58)+N(F61)+N(F62)+N(F65),"") | G66: =IF(ISNUMBER(G55),N(G55)+N(G58)+N(G61)+N(G62)+N(G65),"") | H66: =IF(ISNUMBER(H55),N(H55)+N(H58)+N(H61)+N(H62)+N(H65),"") | I66: =IF(ISNUMBER(I55),N(I55)+N(I58)+N(I61)+N(I62)+N(I65),"") | J66: =IF(ISNUMBER(J55),N(J55)+N(J58)+N(J61)+N(J62)+N(J65),"") | ... CE66: =IF(ISNUMBER(CE55),N(CE55)+N(CE58)+N(CE61)+N(CE62)+N(CE65),"") -> 256717.05 | CN66: 2028E | CO66: =CP66+$CO$64 -> 0.34 | CP66: 0.32 | CQ66: =CP66+$CQ$64 -> 0.27
B67: Check: segment build vs consolidated operating income (should be 0) | C67: =IF(AND(ISNUMBER(C66),ISNUMBER(C140)),IF(ABS(C66-C140)<=1,0,ROUND(C66-C140,0)),"") | D67: =IF(AND(ISNUMBER(D66),ISNUMBER(D140)),IF(ABS(D66-D140)<=1,0,ROUND(D66-D140,0)),"") | E67: =IF(AND(ISNUMBER(E66),ISNUMBER(E140)),IF(ABS(E66-E140)<=1,0,ROUND(E66-E140,0)),"") | F67: =IF(AND(ISNUMBER(F66),ISNUMBER(F140)),IF(ABS(F66-F140)<=1,0,ROUND(F66-F140,0)),"") | G67: =IF(AND(ISNUMBER(G66),ISNUMBER(G140)),IF(ABS(G66-G140)<=1,0,ROUND(G66-G140,0)),"") | H67: =IF(AND(ISNUMBER(H66),ISNUMBER(H140)),IF(ABS(H66-H140)<=1,0,ROUND(H66-H140,0)),"") | I67: =IF(AND(ISNUMBER(I66),ISNUMBER(I140)),IF(ABS(I66-I140)<=1,0,ROUND(I66-I140,0)),"") | J67: =IF(AND(ISNUMBER(J66),ISNUMBER(J140)),IF(ABS(J66-J140)<=1,0,ROUND(J66-J140,0)),"") | ... CE67: =IF(AND(ISNUMBER(CE66),ISNUMBER(CE140)),IF(ABS(CE66-CE140)<=1,0,ROUND(CE66-CE140,0)),"") -> 0 | CN67: 2029E | CO67: =CP67+$CO$64 -> 0.34 | CP67: 0.32 | CQ67: =CP67+$CQ$64 -> 0.27
B68: Legacy segment structures, as reported (memo): | CN68: 2030E | CO68: =CP68+$CO$64 -> 0.34 | CP68: 0.32 | CQ68: =CP68+$CQ$64 -> 0.27
B69: Google segment operating income (2015–2020 basis; incl. Cloud) | G69: 11757 | H69: 14216 | I69: 16308 | J69: 4403 | K69: 4208 | L69: 4635 | M69: 3014 | N69: 16260 | S69: 18965 | T69: 5188 | U69: 5608 | V69: 5807 | W69: 6716 | X69: 23319 | Y69: 6245 | Z69: 6990 | AA69: 6774 | AB69: 7046 | AC69: 27055 | AD69: 7446 | AE69: 7664 | AF69: 8582 | AG69: 8764 | AH69: 32456 | AI69: 8368 | AJ69: 8959 | AK69: 9490 | AL69: 9838 | AM69: 36655 | AN69: 9188 | AO69: 10280 | AP69: 10746 | AQ69: 11459 | AR69: 41673 | AS69: 9270 | AT69: 7572 | AU69: 12589 | CN69: OB_OI (Other Bets operating income, $m) | CO69: 1000 | CP69: Δ → | CQ69: -1500 | CR69: FY2025 $(7.5)bn, 1H26 $(3.9)bn: Waymo expansion. Assumption.
B70: Other Bets operating loss (2015–2020 basis) | N70: -527 | S70: -1893 | T70: -633 | U70: -660 | V70: -980 | W70: -1183 | X70: -3456 | Y70: -774 | Z70: -855 | AA70: -861 | AB70: -251 | AC70: -2741 | AD70: -703 | AE70: -633 | AF70: -650 | AG70: -748 | AH70: -2734 | AI70: -571 | AJ70: -732 | AK70: -727 | AL70: -1328 | AM70: -3358 | AN70: -868 | AO70: -989 | AP70: -941 | AQ70: -2026 | AR70: -4824 | AS70: -1121 | AT70: -1116 | AU70: -1103 | CN70: 2027E | CO70: =CP70+$CO$69 -> -7000 | CP70: -8000 | CQ70: =CP70+$CQ$69 -> -9500
B71: Unallocated / Alphabet-level (2015–2020 basis) | N71: -330 | S71: -576 | T71: -108 | U71: -123 | V71: -119 | W71: -153 | X71: -503 | Y71: -129 | Z71: -167 | AA71: -146 | AB71: -156 | AC71: -598 | AD71: -175 | AE71: -2899 | AF71: -150 | AG71: -320 | AH71: -3544 | AI71: -164 | AJ71: -5182 | AK71: -138 | AL71: -289 | AM71: -5773 | AN71: -1712 | AO71: -111 | AP71: -628 | AQ71: -167 | AR71: -2618 | AS71: -172 | AT71: -73 | AU71: -273 | CN71: 2028E | CO71: =CP71+$CO$69 -> -7500 | CP71: -8500 | CQ71: =CP71+$CQ$69 -> -10000
B72: Motorola Mobile operating loss (2012–2013) | H72: 0 | I72: -393 | J72: -179 | K72: -218 | L72: -248 | CN72: 2029E | CO72: =CP72+$CO$69 -> -8000 | CP72: -9000 | CQ72: =CP72+$CQ$69 -> -10500
CN73: 2030E | CO73: =CP73+$CO$69 -> -8000 | CP73: -9000 | CQ73: =CP73+$CQ$69 -> -10500
B74: Future acquisitions (M&A lever — unallocated; deals closed from 2027E) | CF74: M&A LEVER — acquired revenue = spend ÷ EV/sales; mid-year convention | CN74: ALPHA_P (Alphabet-level costs % of revenues) | CO74: -0.005 | CP74: Δ → | CQ74: 0.007 | CR74: FY2025 4.2%, 1H26 4.9%: frontier AI model development (Google DeepMind), corporate costs, fines & settlements. Assumption.
B75: Acquisition spend (USDm, scenario) | CA75: 0 | CB75: =MAX(0,CHOOSE(MATCH($CF$2,{"Bull","Base","Bear"},0),$CO$85,$CP$85,$CQ$85)) -> 5000 | CC75: =MAX(0,CHOOSE(MATCH($CF$2,{"Bull","Base","Bear"},0),$CO$86,$CP$86,$CQ$86)) -> 5000 | CD75: =MAX(0,CHOOSE(MATCH($CF$2,{"Bull","Base","Bear"},0),$CO$87,$CP$87,$CQ$87)) -> 5000 | CE75: =MAX(0,CHOOSE(MATCH($CF$2,{"Bull","Base","Bear"},0),$CO$88,$CP$88,$CQ$88)) -> 5000 | CF75: Scenario lever M&A_spend (Base $5bn p.a.). Funded from cash / commercial paper (debt schedule). | CN75: 2027E | CO75: =CP75+$CO$74 -> 0.045 | CP75: 0.05 | CQ75: =CP75+$CQ$74 -> 0.057
B76: Purchase multiple — EV / sales (x) | CA76: 0 | CB76: 15 | CC76: 15 | CD76: 15 | CE76: 15 | CF76: Wiz $29.5bn (Mar-2026) at a reported ~$1bn ARR (press, unverified) ≈ 30x; Mandiant $5.4bn (2022). 15x input (assumption). | CN76: 2028E | CO76: =CP76+$CO$74 -> 0.045 | CP76: 0.05 | CQ76: =CP76+$CQ$74 -> 0.057
B77: Annualised revenue acquired in the year | CA77: 0 | CB77: =IFERROR(CB75/CB76,0) -> 333.33333 | CC77: =IFERROR(CC75/CC76,0) -> 333.33333 | CD77: =IFERROR(CD75/CD76,0) -> 333.33333 | CE77: =IFERROR(CE75/CE76,0) -> 333.33333 | CN77: 2029E | CO77: =CP77+$CO$74 -> 0.043 | CP77: 0.048 | CQ77: =CP77+$CQ$74 -> 0.055
B78: Revenue from future acquisitions (mid-year; grows with the acquired base at 20%) | CA78: 0 | CB78: =CA78*1.2+0.5*CB77+0.5*CA77 -> 166.66667 | CC78: =CB78*1.2+0.5*CC77+0.5*CB77 -> 533.33333 | CD78: =CC78*1.2+0.5*CD77+0.5*CC77 -> 973.33333 | CE78: =CD78*1.2+0.5*CE77+0.5*CD77 -> 1501.3333 | CN78: 2030E | CO78: =CP78+$CO$74 -> 0.041 | CP78: 0.046 | CQ78: =CP78+$CQ$74 -> 0.053
B79: Operating margin of acquired businesses (after amortization) % | CA79: 0 | CB79: 0 | CC79: 0 | CD79: 0 | CE79: 0 | CN79: CAPEX (purchases of property & equipment, $m) | CO79: -10000 | CP79: Δ → | CQ79: 15000 | CR79: 2026E $200bn (UNVERIFIED call outlook); "increase significantly in 2027" (call, unverified; no figure). Assumption.
B80: Operating income from future acquisitions | CA80: 0 | CB80: =CB78*CB79 -> 0 | CC80: =CC78*CC79 -> 0 | CD80: =CD78*CD79 -> 0 | CE80: =CE78*CE79 -> 0 | CN80: 2027E | CO80: =MAX(0,CP80+$CO$79) -> 240000 | CP80: 250000 | CQ80: =MAX(0,CP80+$CQ$79) -> 265000
B81: Acquired intangibles % of spend (Wiz 28%) | CA81: 0 | CB81: 0.28 | CC81: 0.28 | CD81: 0.28 | CE81: 0.28 | CN81: 2028E | CO81: =MAX(0,CP81+$CO$79) -> 260000 | CP81: 270000 | CQ81: =MAX(0,CP81+$CQ$79) -> 285000
B82: Intangible amortization life (years; Wiz 7–10) | CA82: 0 | CB82: 8 | CC82: 8 | CD82: 8 | CE82: 8 | CN82: 2029E | CO82: =MAX(0,CP82+$CO$79) -> 275000 | CP82: 285000 | CQ82: =MAX(0,CP82+$CQ$79) -> 300000
B83: Cumulative acquired intangibles (gross) | CA83: 0 | CB83: =CA83+CB75*CB81 -> 1400 | CC83: =CB83+CC75*CC81 -> 2800 | CD83: =CC83+CD75*CD81 -> 4200 | CE83: =CD83+CE75*CE81 -> 5600 | CN83: 2030E | CO83: =MAX(0,CP83+$CO$79) -> 290000 | CP83: 300000 | CQ83: =MAX(0,CP83+$CQ$79) -> 315000
B84: Amortization of future-acquisition intangibles | CA84: 0 | CB84: =IFERROR((CA83+0.5*CB75*CB81)/CB82,0) -> 87.5 | CC84: =IFERROR((CB83+0.5*CC75*CC81)/CC82,0) -> 262.5 | CD84: =IFERROR((CC83+0.5*CD75*CD81)/CD82,0) -> 437.5 | CE84: =IFERROR((CD83+0.5*CE75*CE81)/CE82,0) -> 612.5 | CN84: M&A_spend (acquisitions, $m) | CO84: 5000 | CP84: Δ → | CQ84: -5000 | CR84: Wiz $29.5bn and Intersect $5.9bn in 2026; FY2021–25 $0.5–6.3bn p.a. Base $5bn p.a. (assumption).
CN85: 2027E | CO85: =MAX(0,CP85+$CO$84) -> 10000 | CP85: 5000 | CQ85: =MAX(0,CP85+$CQ$84) -> 0
B86: Pending divestiture — GFiber (contribution to a new entity; agreement Mar-2026, close expected late 2026; held for sale) | CF86: DIVESTITURE — modelled at 31-Dec-2026: $1.5bn cash, $2.0bn note receivable and a 49.99% equity-method interest; no gain assumed | CN86: 2028E | CO86: =MAX(0,CP86+$CO$84) -> 10000 | CP86: 5000 | CQ86: =MAX(0,CP86+$CQ$84) -> 0
B87: Cash proceeds | CA87: 1500 | CB87: 0 | CC87: 0 | CD87: 0 | CE87: 0 | CF87: GFiber pending contribution to a new entity (agreement Mar-2026, close expected late 2026): Alphabet to receive $1.5bn cash, a $2.0bn note receivable and a 49.99% equity interest (equity method); held for sale (PP&E $7.1bn in other current assets at 30-Jun-2026). Results stay in Other Bets to closing. Q2-26 10-Q Note 8. | CN87: 2029E | CO87: =MAX(0,CP87+$CO$84) -> 10000 | CP87: 5000 | CQ87: =MAX(0,CP87+$CQ$84) -> 0
B88: Held-for-sale assets derecognised (property & equipment $7.1bn at 30-Jun-2026) | CA88: 7100 | CB88: 0 | CC88: 0 | CD88: 0 | CE88: 0 | CN88: 2030E | CO88: =MAX(0,CP88+$CO$84) -> 10000 | CP88: 5000 | CQ88: =MAX(0,CP88+$CQ$84) -> 0
B89: Non-cash consideration recognised (note receivable $2.0bn + equity interest; assumption: carrying value, no gain) | CA89: =CA88-CA87 -> 5600 | CB89: 0 | CC89: 0 | CD89: 0 | CE89: 0 | CF89: The equity interest is assumed to be recognised at the carrying value of the net assets contributed less cash and note (no gain or loss; not disclosed).
B91: Group total — revenues & operating income (build) · Q3–Q4/26E outlook (no company guidance) | CF91: GROUP TOTAL — modelling logic
B92: Total revenues (build) | C92: =C31 -> 10604.917 | D92: =D31 -> 16593.986 | E92: =E31 -> 21795.55 | F92: =F31 -> 23650.563 | G92: =G31 -> 29321 | H92: =H31 -> 37905 | I92: =I31 -> 50175 | J92: =J31 -> 13969 | ... BX92: =BX31 -> 119796 | BY92: =BY31+N(BY78) -> 127000.55 | BZ92: =BZ31+N(BZ78) -> 141582.69 | CA92: =CA31+N(CA78) -> 498275.24 | CB92: =CB31+N(CB78) -> 584884.1 | CC92: =CC31+N(CC78) -> 670962.24 | CD92: =CD31+N(CD78) -> 758009.55 | CE92: =CE31+N(CE78) -> 843758.74 | CH92: =IFERROR((CE92/BV92)^(1/5)-1,"n/m") -> 0.15935917 | CI92: =IFERROR((BV92/AW92)^(1/5)-1,"n/m") -> 0.17154839 | CJ92: =IFERROR((BV92/X92)^(1/10)-1,"n/m") -> 0.18307716 | CK92: =IFERROR((BV92/C92)^(1/19)-1,"n/m") -> 0.21098272
B93: Revenues y/y % | D93: =IF(AND(ISNUMBER(D92),ISNUMBER(C92)),IFERROR(D92/C92-1,""),"") -> 0.56474454 | E93: =IF(AND(ISNUMBER(E92),ISNUMBER(D92)),IFERROR(E92/D92-1,""),"") -> 0.31346079 | F93: =IF(AND(ISNUMBER(F92),ISNUMBER(E92)),IFERROR(F92/E92-1,""),"") -> 0.085109713 | G93: =IF(AND(ISNUMBER(G92),ISNUMBER(F92)),IFERROR(G92/F92-1,""),"") -> 0.23975907 | H93: =IF(AND(ISNUMBER(H92),ISNUMBER(G92)),IFERROR(H92/G92-1,""),"") -> 0.29275946 | I93: =IF(AND(ISNUMBER(I92),ISNUMBER(H92)),IFERROR(I92/H92-1,""),"") -> 0.323704 | N93: =IF(AND(ISNUMBER(N92),ISNUMBER(I92)),IFERROR(N92/I92-1,""),"") -> 0.19232686 | O93: =IF(AND(ISNUMBER(O92),ISNUMBER(J92)),IFERROR(O92/J92-1,""),"") -> 0.10387286 | P93: =IF(AND(ISNUMBER(P92),ISNUMBER(K92)),IFERROR(P92/K92-1,""),"") -> 0.13115916 | Q93: =IF(AND(ISNUMBER(Q92),ISNUMBER(L92)),IFERROR(Q92/L92-1,""),"") -> 0.10944739 | R93: =IF(AND(ISNUMBER(R92),ISNUMBER(M92)),IFERROR(R92/M92-1,""),"") -> 0.073852177 | S93: =IF(AND(ISNUMBER(S92),ISNUMBER(N92)),IFERROR(S92/N92-1,""),"") -> 0.10323443 | T93: =IF(AND(ISNUMBER(T92),ISNUMBER(O92)),IFERROR(T92/O92-1,""),"") -> 0.11919585 | U93: =IF(AND(ISNUMBER(U92),ISNUMBER(P92)),IFERROR(U92/P92-1,""),"") -> 0.11106236 | ... CA93: =IF(AND(ISNUMBER(CA92),ISNUMBER(BV92)),IFERROR(CA92/BV92-1,""),"") -> 0.23691834 | CB93: =IF(AND(ISNUMBER(CB92),ISNUMBER(CA92)),IFERROR(CB92/CA92-1,""),"") -> 0.17381731 | CC93: =IF(AND(ISNUMBER(CC92),ISNUMBER(CB92)),IFERROR(CC92/CB92-1,""),"") -> 0.14717127 | CD93: =IF(AND(ISNUMBER(CD92),ISNUMBER(CC92)),IFERROR(CD92/CC92-1,""),"") -> 0.12973504 | CE93: =IF(AND(ISNUMBER(CE92),ISNUMBER(CD92)),IFERROR(CE92/CD92-1,""),"") -> 0.11312416
B94: Check: revenue build vs consolidated revenues (should be 0) | C94: =IF(ISNUMBER(C92),IF(ABS(C92-C132)<=1,0,ROUND(C92-C132,0)),"") -> 0 | D94: =IF(ISNUMBER(D92),IF(ABS(D92-D132)<=1,0,ROUND(D92-D132,0)),"") -> 0 | E94: =IF(ISNUMBER(E92),IF(ABS(E92-E132)<=1,0,ROUND(E92-E132,0)),"") -> 0 | F94: =IF(ISNUMBER(F92),IF(ABS(F92-F132)<=1,0,ROUND(F92-F132,0)),"") -> 0 | G94: =IF(ISNUMBER(G92),IF(ABS(G92-G132)<=1,0,ROUND(G92-G132,0)),"") -> 0 | H94: =IF(ISNUMBER(H92),IF(ABS(H92-H132)<=1,0,ROUND(H92-H132,0)),"") -> 0 | I94: =IF(ISNUMBER(I92),IF(ABS(I92-I132)<=1,0,ROUND(I92-I132,0)),"") -> 0 | J94: =IF(ISNUMBER(J92),IF(ABS(J92-J132)<=1,0,ROUND(J92-J132,0)),"") -> 0 | ... CE94: =IF(ISNUMBER(CE92),IF(ABS(CE92-CE132)<=1,0,ROUND(CE92-CE132,0)),"") -> 0
B95: Operating income (build) | C95: =C66 | D95: =D66 | E95: =E66 | F95: =F66 | G95: =G66 | H95: =H66 | I95: =I66 | J95: =J66 | ... BX95: =BX66 -> 40770 | BY95: =BY66+N(BY80) -> 41781.788 | BZ95: =BZ66+N(BZ80) -> 50691.044 | CA95: =CA66+N(CA80) -> 172938.83 | CB95: =CB66+N(CB80) -> 194643.24 | CC95: =CC66+N(CC80) -> 212421.88 | CD95: =CD66+N(CD80) -> 234774.62 | CE95: =CE66+N(CE80) -> 256717.05 | CH95: =IFERROR((CE95/BV95)^(1/5)-1,"n/m") -> 0.14748428 | CI95: =IFERROR((BV95/AW95)^(1/5)-1,"n/m") -> 0.25636021 | CJ95: =IFERROR((BV95/X95)^(1/10)-1,"n/m") -> n/m | CK95: =IFERROR((BV95/C95)^(1/19)-1,"n/m") -> n/m
B96: Operating margin % | C96: =IF(AND(ISNUMBER(C95),ISNUMBER(C132)),IFERROR(C95/C132,""),"") | D96: =IF(AND(ISNUMBER(D95),ISNUMBER(D132)),IFERROR(D95/D132,""),"") | E96: =IF(AND(ISNUMBER(E95),ISNUMBER(E132)),IFERROR(E95/E132,""),"") | F96: =IF(AND(ISNUMBER(F95),ISNUMBER(F132)),IFERROR(F95/F132,""),"") | G96: =IF(AND(ISNUMBER(G95),ISNUMBER(G132)),IFERROR(G95/G132,""),"") | H96: =IF(AND(ISNUMBER(H95),ISNUMBER(H132)),IFERROR(H95/H132,""),"") | I96: =IF(AND(ISNUMBER(I95),ISNUMBER(I132)),IFERROR(I95/I132,""),"") | J96: =IF(AND(ISNUMBER(J95),ISNUMBER(J132)),IFERROR(J95/J132,""),"") | ... CE96: =IF(AND(ISNUMBER(CE95),ISNUMBER(CE132)),IFERROR(CE95/CE132,""),"") -> 0.30425409 | CH96: =IFERROR(AVERAGE(CA96,CB96,CC96,CD96,CE96),"n/m") -> 0.32208729 | CI96: =IFERROR(AVERAGE(BB96,BG96,BL96,BQ96,BV96),"n/m") -> 0.29715557 | CJ96: =IFERROR(AVERAGE(AC96,AH96,AM96,AR96,AW96,BB96,BG96,BL96,BQ96,BV96),"n/m") -> 0.2644371 | CK96: =IFERROR(AVERAGE(C96,D96,E96,F96,G96,H96,I96,N96,S96,X96,AC96,AH96,AM96,AR96,AW96,BB96,BG96,BL96,BQ96,BV96),"n/m") -> 0.2644371
B97: Q3–Q4/26E revenue growth shift vs 1H26 y/y trend (scenario; applied to every revenue type) | BY97: =IF(ISNUMBER($CP$17),($CP$17-SUM(BW31:BX31)-BY98)/BY99,CHOOSE(MATCH($CF$2,{"Bull","Base","Bear"},0),$CO$12,$CP$12,$CQ$12)) -> 0 | BZ97: =BY97 -> 0 | CF97: No revenue guidance: Base = 1H26 y/y run-rate; Bull / Bear shift. If an FY26 revenue target is entered in the outlook block (optional, blank by default), the shift is solved to hit it.
B98: 2H26E revenues before the shift (helper) | BY98: =(BT11+BU11)*(1+BY13)+(BT14+BU14)*(1+BY16)+(BT17+BU17)*(1+BY19)+(BT20+BU20)*(1+BY22)+(BT23+BU23)*(1+BY25)+(BT26+BU26)*(1+BY28) -> 268583.24
B99: 2H26E revenue sensitivity to +1.00 of growth (helper) | BY99: =BT11+BU11+BT14+BU14+BT17+BU17+BT20+BU20+BT23+BU23+BT26+BU26 -> 216449
B100: Memo: FY26 revenue target (optional input; blank = driver-based) | CA100: =IF(ISNUMBER($CP$17),$CP$17,"n/a") -> n/a
B101: Check: FY26 revenues vs target, when a target is entered (should be 0) | CA101: =IF(ISNUMBER($CP$17),ROUND(CA132-$CP$17,0),"")
...

Sheet Bull-Base-Bear
B2: Alphabet Inc. (GOOG) — Bull / Base / Bear Case P&L Summary | J2: Share price ($): | K2: =Model!$CA$407 -> 350
B3: Model-defined adjusted figures (adjusted EBITDA / operating income / EPS exclude company-reconciled EC fines and severance charges, equity-security gains and the Tax Act; Alphabet publishes no EBITDA or adjusted EPS) · USD millions · Live panel linked to Model — toggle scenario via Model!CF2. Bull and Bear panels are value snapshots generated from the Model with the switch set to each case. 2026E = Q1–Q2 actual + Q3–Q4 estimate (no company guidance). | J3: As of: | K3: =TODAY() -> 2026-10-13 00:00:00
B5: Scenario: | C5: =Model!$CF$2 -> Base | N5: Scenario: | O5: Bull | P5: Snapshot (values) — Model run with switch = Bull | Z5: Scenario: | AA5: Bear | AB5: Snapshot (values) — Model run with switch = Bear
B7: (USDm, except EPS and shares) | C7: 2025A | D7: 2026E | E7: 2027E | F7: 2028E | G7: 2029E | H7: 2030E | I7: 25-'30 CAGR | J7: LT Hist Avg | K7: LT Hist Min | L7: LT Hist Max | N7: (USDm, except EPS and shares) | O7: 2025A | P7: 2026E | Q7: 2027E | R7: 2028E | S7: 2029E | T7: 2030E | U7: 25-'30 CAGR | V7: LT Hist Avg | W7: LT Hist Min | X7: LT Hist Max | Z7: (USDm, except EPS and shares) | AA7: 2025A | AB7: 2026E | AC7: 2027E | AD7: 2028E | AE7: 2029E | AF7: 2030E | AG7: 25-'30 CAGR | AH7: LT Hist Avg | AI7: LT Hist Min | AJ7: LT Hist Max
B9: Revenues | C9: =Model!BV132 -> 402836 | D9: =Model!CA132 -> 498275.24 | E9: =Model!CB132 -> 584884.1 | F9: =Model!CC132 -> 670962.24 | G9: =Model!CD132 -> 758009.55 | H9: =Model!CE132 -> 843758.74 | I9: =IFERROR((H9/C9)^(1/5)-1,"n/m") -> 0.15935917 | N9: Revenues | O9: 402836 | P9: 502604.22 | Q9: 606355.04 | R9: 718406.35 | S9: 841460.72 | T9: 974322 | U9: 0.1932044 | Z9: Revenues | AA9: 402836 | AB9: 491781.77 | AC9: 549699.33 | AD9: 596689.15 | AE9: 635070.54 | AF9: 663838.88 | AG9: 0.1050626
B10: Revenues y/y % | D10: =IFERROR(D9/C9-1,"") -> 0.23691834 | E10: =IFERROR(E9/D9-1,"") -> 0.17381731 | F10: =IFERROR(F9/E9-1,"") -> 0.14717127 | G10: =IFERROR(G9/F9-1,"") -> 0.12973504 | H10: =IFERROR(H9/G9-1,"") -> 0.11312416 | N10: Revenues y/y % | P10: 0.2476646 | Q10: 0.20642649 | R10: 0.18479489 | S10: 0.17128798 | T10: 0.15789362 | Z10: Revenues y/y % | AB10: 0.22079895 | AC10: 0.11777087 | AD10: 0.085482764 | AE10: 0.064323931 | AF10: 0.045299438
B11: Google Cloud revenues y/y % | C11: =Model!BV230 -> 0.35800042 | D11: =Model!CA230 -> 0.73064441 | E11: =Model!CB230 -> 0.45 | F11: =Model!CC230 -> 0.32 | G11: =Model!CD230 -> 0.25 | H11: =Model!CE230 -> 0.2 | N11: Google Cloud revenues y/y % | O11: 0.35800042 | P11: 0.74182608 | Q11: 0.53 | R11: 0.4 | S11: 0.33 | T11: 0.28 | Z11: Google Cloud revenues y/y % | AA11: 0.35800042 | AB11: 0.71387191 | AC11: 0.33 | AD11: 0.2 | AE11: 0.13 | AF11: 0.08
B12: Adjusted EBITDA (model) | C12: =Model!BV191 -> 153632 | D12: =Model!CA191 -> 204129.25 | E12: =Model!CB191 -> 244974.62 | F12: =Model!CC191 -> 286016.96 | G12: =Model!CD191 -> 331272.46 | H12: =Model!CE191 -> 375223.2 | I12: =IFERROR((H12/C12)^(1/5)-1,"n/m") -> 0.19553308 | N12: Adjusted EBITDA (model) | O12: 153632 | P12: 208622.97 | Q12: 265933.87 | R12: 315961.49 | S12: 373500.21 | T12: 433081.09 | U12: 0.23031837 | Z12: Adjusted EBITDA (model) | AA12: 153632 | AB12: 197550.49 | AC12: 210807.6 | AD12: 239741.89 | AE12: 270285.34 | AF12: 297678.14 | AG12: 0.1414399
B13: Adjusted EBITDA margin % | C13: =IFERROR(C12/C9,"") -> 0.38137604 | D13: =IFERROR(D12/D9,"") -> 0.40967168 | E13: =IFERROR(E12/E9,"") -> 0.41884301 | F13: =IFERROR(F12/F9,"") -> 0.42627878 | G13: =IFERROR(G12/G9,"") -> 0.4370294 | H13: =IFERROR(H12/H9,"") -> 0.44470437 | J13: =IFERROR(AVERAGE(Model!C192,Model!D192,Model!E192,Model!F192,Model!G192,Model!H192,Model!I192,Model!N192,Model!S192,Model!X192,Model!AC192,Model!AH192,Model!AM192,Model!AR192,Model!AW192,Model!BB192,Model!BG192,Model!BL192,Model!BQ192,Model!BV192),"") -> 0.34277958 | K13: =IFERROR(MIN(Model!C192,Model!D192,Model!E192,Model!F192,Model!G192,Model!H192,Model!I192,Model!N192,Model!S192,Model!X192,Model!AC192,Model!AH192,Model!AM192,Model!AR192,Model!AW192,Model!BB192,Model!BG192,Model!BL192,Model!BQ192,Model!BV192),"") -> 0.29476019 | L13: =IFERROR(MAX(Model!C192,Model!D192,Model!E192,Model!F192,Model!G192,Model!H192,Model!I192,Model!N192,Model!S192,Model!X192,Model!AC192,Model!AH192,Model!AM192,Model!AR192,Model!AW192,Model!BB192,Model!BG192,Model!BL192,Model!BQ192,Model!BV192),"") -> 0.41590951 | N13: Adjusted EBITDA margin % | O13: 0.38137604 | P13: 0.41508399 | Q13: 0.43857782 | R13: 0.43980887 | S13: 0.44387123 | T13: 0.44449483 | V13: 0.34277958 | W13: 0.29476019 | X13: 0.41590951 | Z13: Adjusted EBITDA margin % | AA13: 0.38137604 | AB13: 0.40170357 | AC13: 0.38349619 | AD13: 0.40178691 | AE13: 0.42559892 | AF13: 0.44841925 | AH13: 0.34277958 | AI13: 0.29476019 | AJ13: 0.41590951
B15: Income from operations (GAAP) | C15: =Model!BV140 -> 129039 | D15: =Model!CA140 -> 172938.83 | E15: =Model!CB140 -> 194643.24 | F15: =Model!CC140 -> 212421.88 | G15: =Model!CD140 -> 234774.62 | H15: =Model!CE140 -> 256717.05 | I15: =IFERROR((H15/C15)^(1/5)-1,"n/m") -> 0.14748428 | N15: Income from operations (GAAP) | O15: 129039 | P15: 177432.54 | Q15: 215515 | R15: 243253.91 | S15: 278732.63 | T15: 317030.91 | U15: 0.19695031 | Z15: Income from operations (GAAP) | AA15: 129039 | AB15: 166360.07 | AC15: 160563.73 | AD15: 164684.31 | AE15: 170973.38 | AF15: 175181.8 | AG15: 0.063049777
B16: Operating income y/y % | D16: =IFERROR(D15/C15-1,"") -> 0.34020592 | E16: =IFERROR(E15/D15-1,"") -> 0.12550338 | F16: =IFERROR(F15/E15-1,"") -> 0.091339623 | G16: =IFERROR(G15/F15-1,"") -> 0.10522805 | H16: =IFERROR(H15/G15-1,"") -> 0.093461672 | N16: Operating income y/y % | P16: 0.37503036 | Q16: 0.21463061 | R16: 0.12870988 | S16: 0.14585056 | T16: 0.1374015 | Z16: Operating income y/y % | AB16: 0.28922316 | AC16: -0.034842146 | AD16: 0.025663232 | AE16: 0.03818863 | AF16: 0.02461451
B17: Operating margin (GAAP) % | C17: =IFERROR(C15/C9,"") -> 0.32032639 | D17: =IFERROR(D15/D9,"") -> 0.34707491 | E17: =IFERROR(E15/E9,"") -> 0.33278942 | F17: =IFERROR(F15/F9,"") -> 0.3165929 | G17: =IFERROR(G15/G9,"") -> 0.30972515 | H17: =IFERROR(H15/H9,"") -> 0.30425409 | J17: =IFERROR(AVERAGE(Model!C239,Model!D239,Model!E239,Model!F239,Model!G239,Model!H239,Model!I239,Model!N239,Model!S239,Model!X239,Model!AC239,Model!AH239,Model!AM239,Model!AR239,Model!AW239,Model!BB239,Model!BG239,Model!BL239,Model!BQ239,Model!BV239),"") -> 0.27853231 | K17: =IFERROR(MIN(Model!C239,Model!D239,Model!E239,Model!F239,Model!G239,Model!H239,Model!I239,Model!N239,Model!S239,Model!X239,Model!AC239,Model!AH239,Model!AM239,Model!AR239,Model!AW239,Model!BB239,Model!BG239,Model!BL239,Model!BQ239,Model!BV239),"") -> 0.19237825 | L17: =IFERROR(MAX(Model!C239,Model!D239,Model!E239,Model!F239,Model!G239,Model!H239,Model!I239,Model!N239,Model!S239,Model!X239,Model!AC239,Model!AH239,Model!AM239,Model!AR239,Model!AW239,Model!BB239,Model!BG239,Model!BL239,Model!BQ239,Model!BV239),"") -> 0.35404659 | N17: Operating margin (GAAP) % | O17: 0.32032639 | P17: 0.35302637 | Q17: 0.35542707 | R17: 0.33860211 | S17: 0.33124853 | T17: 0.32538617 | V17: 0.27853231 | W17: 0.19237825 | X17: 0.35404659 | Z17: Operating margin (GAAP) % | AA17: 0.32032639 | AB17: 0.33828027 | AC17: 0.29209372 | AD17: 0.27599682 | AE17: 0.26921951 | AF17: 0.26389205 | AH17: 0.27853231 | AI17: 0.19237825 | AJ17: 0.35404659
B19: Adjusted Net Income (model) | C19: =Model!BV207 -> 116603.8 | D19: =Model!CA207 -> 144596.06 | E19: =Model!CB207 -> 162952.16 | F19: =Model!CC207 -> 176055.03 | G19: =Model!CD207 -> 194039.03 | H19: =Model!CE207 -> 212409.08 | I19: =IFERROR((H19/C19)^(1/5)-1,"n/m") -> 0.12743645 | N19: Adjusted Net Income (model) | O19: 116603.8 | P19: 148280.9 | Q19: 180144.02 | R19: 200576.69 | S19: 229978.7 | T19: 261726.69 | U19: 0.17551198 | Z19: Adjusted Net Income (model) | AA19: 116603.8 | AB19: 139201.47 | AC19: 134683.2 | AD19: 136244.82 | AE19: 139631.71 | AF19: 141595.15 | AG19: 0.039602064
B21: FDSO (m) | C21: =Model!BV159 -> 12230 | D21: =Model!CA159 -> 12364.626 | E21: =Model!CB159 -> 12508.809 | F21: =Model!CC159 -> 12588.631 | G21: =Model!CD159 -> 12699.797 | H21: =Model!CE159 -> 12825.184 | I21: =IFERROR((H21/C21)^(1/5)-1,"n/m") -> 0.0095490546 | N21: FDSO (m) | O21: 12230 | P21: 12361.054 | Q21: 12421.043 | R21: 12417.434 | S21: 12465.915 | T21: 12446.329 | U21: 0.0035129077 | Z21: FDSO (m) | AA21: 12230 | AB21: 12364.626 | AC21: 12545.265 | AD21: 12661.541 | AE21: 12772.707 | AF21: 12898.094 | AG21: 0.010694295
B23: Adjusted EPS — Diluted ($) | C23: =Model!BV209 -> 9.5342437 | D23: =Model!CA209 -> 11.694334 | E23: =Model!CB209 -> 13.026992 | F23: =Model!CC209 -> 13.98524 | G23: =Model!CD209 -> 15.278909 | H23: =Model!CE209 -> 16.561874 | I23: =IFERROR((H23/C23)^(1/5)-1,"n/m") -> 0.11677233 | N23: Adjusted EPS — Diluted ($) | O23: 9.5342437 | P23: 11.995813 | Q23: 14.503131 | R23: 16.152829 | S23: 18.448602 | T23: 21.028424 | U23: 0.17139697 | Z23: Adjusted EPS — Diluted ($) | AA23: 9.5342437 | AB23: 11.258042 | AC23: 10.73578 | AD23: 10.760524 | AE23: 10.932037 | AF23: 10.97799 | AG23: 0.028601891
B24: EPS y/y % | D24: =IFERROR(D23/C23-1,"") -> 0.22656123 | E24: =IFERROR(E23/D23-1,"") -> 0.11395759 | F24: =IFERROR(F23/E23-1,"") -> 0.073558701 | G24: =IFERROR(G23/F23-1,"") -> 0.092502397 | H24: =IFERROR(H23/G23-1,"") -> 0.083969714 | N24: EPS y/y % | P24: 0.25818197 | Q24: 0.20901609 | R24: 0.11374765 | S24: 0.14212828 | T24: 0.13983836 | Z24: EPS y/y % | AB24: 0.1808007 | AC24: -0.046390114 | AD24: 0.0023048784 | AE24: 0.015939097 | AF24: 0.0042034928
B26: P / E (x) — assumed (adjusted EPS) | G26: 26 | H26: 26 | N26: P / E (x) — assumed (adjusted EPS) | S26: 30 | T26: 30 | Z26: P / E (x) — assumed (adjusted EPS) | AD26: 20 | AE26: 20 | AF26: 20
B27: Price Target ($) | G27: =G26*G23 -> 397.25162 | H27: =H26*H23 -> 430.60873 | N27: Price Target ($) | S27: =S26*S23 -> 553.45807 | T27: =T26*T23 -> 630.85273 | Z27: Price Target ($) | AD27: =AD26*AD23 -> 215.21049 | AE27: =AE26*AE23 -> 218.64075 | AF27: =AF26*AF23 -> 219.5598
B28: Upside / (Downside) vs current | G28: =IFERROR(G27/$K$2-1,"") -> 0.13500464 | H28: =IFERROR(H27/$K$2-1,"") -> 0.23031065 | N28: Upside / (Downside) vs current | S28: =IFERROR(S27/$K$2-1,"") -> 0.58130877 | T28: =IFERROR(T27/$K$2-1,"") -> 0.80243638 | Z28: Upside / (Downside) vs current | AD28: =IFERROR(AD27/$K$2-1,"") -> -0.38511289 | AE28: =IFERROR(AE27/$K$2-1,"") -> -0.37531214 | AF28: =IFERROR(AF27/$K$2-1,"") -> -0.37268627
B29: IRR (to Dec-Y-1) | G29: =IFERROR((G27/$K$2)^(1/((DATE(2029-1,12,31)-$K$3)/365.25))-1,"") -> 0.058765692 | H29: =IFERROR((H27/$K$2)^(1/((DATE(2030-1,12,31)-$K$3)/365.25))-1,"") -> 0.06654993 | N29: IRR (to Dec-Y-1) | S29: =IFERROR((S27/$K$2)^(1/((DATE(2029-1,12,31)-$K$3)/365.25))-1,"") -> 0.2295375 | T29: =IFERROR((T27/$K$2)^(1/((DATE(2030-1,12,31)-$K$3)/365.25))-1,"") -> 0.20097602 | Z29: IRR (to Dec-Y-1) | AD29: =IFERROR((AD27/$K$2)^(1/((DATE(2028-1,12,31)-$K$3)/365.25))-1,"") -> -0.32972092 | AE29: =IFERROR((AE27/$K$2)^(1/((DATE(2029-1,12,31)-$K$3)/365.25))-1,"") -> -0.19116641 | AF29: =IFERROR((AF27/$K$2)^(1/((DATE(2030-1,12,31)-$K$3)/365.25))-1,"") -> -0.13493661
B31: Free Cash Flow | C31: =Model!BV273 -> 73266 | D31: =Model!CA273 -> -2821.4772 | E31: =Model!CB273 -> 8523.4065 | F31: =Model!CC273 -> 26877.572 | G31: =Model!CD273 -> 57836.084 | H31: =Model!CE273 -> 88769.812 | I31: =IFERROR((H31/C31)^(1/5)-1,"n/m") -> 0.039136415 | N31: Free Cash Flow | O31: 73266 | P31: 1139.7089 | Q31: 36284.752 | R31: 64010.17 | S31: 108030.73 | T31: 154839.92 | U31: 0.16143816 | Z31: Free Cash Flow | AA31: 73266 | AB31: -8630.5793 | AC31: -35763.039 | AD31: -31880.431 | AE31: -17460.223 | AF31: -5571.8398 | AG31: -1.5973367
B32: FCF % | C32: =IFERROR(C31/C9,"") -> 0.1818755 | D32: =IFERROR(D31/D9,"") -> -0.0056624873 | E32: =IFERROR(E31/E9,"") -> 0.014572813 | F32: =IFERROR(F31/F9,"") -> 0.040058249 | G32: =IFERROR(G31/G9,"") -> 0.076299941 | H32: =IFERROR(H31/H9,"") -> 0.10520758 | J32: =IFERROR(AVERAGE(Model!C277,Model!D277,Model!E277,Model!F277,Model!G277,Model!H277,Model!I277,Model!N277,Model!S277,Model!X277,Model!AC277,Model!AH277,Model!AM277,Model!AR277,Model!AW277,Model!BB277,Model!BG277,Model!BL277,Model!BQ277,Model!BV277),"") -> 0.22665589 | K32: =IFERROR(MIN(Model!C277,Model!D277,Model!E277,Model!F277,Model!G277,Model!H277,Model!I277,Model!N277,Model!S277,Model!X277,Model!AC277,Model!AH277,Model!AM277,Model!AR277,Model!AW277,Model!BB277,Model!BG277,Model!BL277,Model!BQ277,Model!BV277),"") -> 0.15820114 | L32: =IFERROR(MAX(Model!C277,Model!D277,Model!E277,Model!F277,Model!G277,Model!H277,Model!I277,Model!N277,Model!S277,Model!X277,Model!AC277,Model!AH277,Model!AM277,Model!AR277,Model!AW277,Model!BB277,Model!BG277,Model!BL277,Model!BQ277,Model!BV277),"") -> 0.35966628 | N32: FCF % | O32: 0.1818755 | P32: 0.0022676071 | Q32: 0.059840769 | R32: 0.089100228 | S32: 0.12838476 | T32: 0.15892068 | V32: 0.22665589 | W32: 0.15820114 | X32: 0.35966628 | Z32: FCF % | AA32: 0.1818755 | AB32: -0.017549612 | AC32: -0.065059274 | AD32: -0.053428877 | AE32: -0.02749336 | AF32: -0.0083933616 | AH32: 0.22665589 | AI32: 0.15820114 | AJ32: 0.35966628
B33: FCF / share ($) | C33: =IFERROR(C31/C21,"") -> 5.9906787 | D33: =IFERROR(D31/D21,"") -> -0.22818946 | E33: =IFERROR(E31/E21,"") -> 0.68139231 | F33: =IFERROR(F31/F21,"") -> 2.1350671 | G33: =IFERROR(G31/G21,"") -> 4.5540952 | H33: =IFERROR(H31/H21,"") -> 6.9215237 | N33: FCF / share ($) | O33: 5.9906787 | P33: 0.092201593 | Q33: 2.9212323 | R33: 5.1548628 | S33: 8.6660896 | T33: 12.44061 | Z33: FCF / share ($) | AA33: 5.9906787 | AB33: -0.69800572 | AC33: -2.8507202 | AD33: -2.517895 | AE33: -1.3669947 | AF33: -0.4319894
B34: FCF Yield (on PT) | F34: =IFERROR(F33/F$27,"") | G34: =IFERROR(G33/G$27,"") -> 0.011464007 | H34: =IFERROR(H33/H$27,"") -> 0.016073812 | N34: FCF Yield (on PT) | R34: =IFERROR(R33/R$27,"") | S34: =IFERROR(S33/S$27,"") -> 0.015658078 | T34: =IFERROR(T33/T$27,"") -> 0.019720307 | Z34: FCF Yield (on PT) | AD34: =IFERROR(AD33/AD$27,"") -> -0.011699685 | AE34: =IFERROR(AE33/AE$27,"") -> -0.0062522413 | AF34: =IFERROR(AF33/AF$27,"") -> -0.001967525
B35: Adjusted EBITDA (leverage basis) | C35: =Model!BV191 -> 153632 | D35: =Model!CA191 -> 204129.25 | E35: =Model!CB191 -> 244974.62 | F35: =Model!CC191 -> 286016.96 | G35: =Model!CD191 -> 331272.46 | H35: =Model!CE191 -> 375223.2 | I35: =IFERROR((H35/C35)^(1/5)-1,"n/m") -> 0.19553308 | N35: Adjusted EBITDA (leverage basis) | O35: 153632 | P35: 208622.97 | Q35: 265933.87 | R35: 315961.49 | S35: 373500.21 | T35: 433081.09 | U35: 0.23031837 | Z35: Adjusted EBITDA (leverage basis) | AA35: 153632 | AB35: 197550.49 | AC35: 210807.6 | AD35: 239741.89 | AE35: 270285.34 | AF35: 297678.14 | AG35: 0.1414399
B36: Adjusted EBITDA % of revenues | C36: =IFERROR(C35/C9,"") -> 0.38137604 | D36: =IFERROR(D35/D9,"") -> 0.40967168 | E36: =IFERROR(E35/E9,"") -> 0.41884301 | F36: =IFERROR(F35/F9,"") -> 0.42627878 | G36: =IFERROR(G35/G9,"") -> 0.4370294 | H36: =IFERROR(H35/H9,"") -> 0.44470437 | J36: =IFERROR(AVERAGE(Model!C238,Model!D238,Model!E238,Model!F238,Model!G238,Model!H238,Model!I238,Model!N238,Model!S238,Model!X238,Model!AC238,Model!AH238,Model!AM238,Model!AR238,Model!AW238,Model!BB238,Model!BG238,Model!BL238,Model!BQ238,Model!BV238),"") -> 0.34277958 | K36: =IFERROR(MIN(Model!C238,Model!D238,Model!E238,Model!F238,Model!G238,Model!H238,Model!I238,Model!N238,Model!S238,Model!X238,Model!AC238,Model!AH238,Model!AM238,Model!AR238,Model!AW238,Model!BB238,Model!BG238,Model!BL238,Model!BQ238,Model!BV238),"") -> 0.29476019 | L36: =IFERROR(MAX(Model!C238,Model!D238,Model!E238,Model!F238,Model!G238,Model!H238,Model!I238,Model!N238,Model!S238,Model!X238,Model!AC238,Model!AH238,Model!AM238,Model!AR238,Model!AW238,Model!BB238,Model!BG238,Model!BL238,Model!BQ238,Model!BV238),"") -> 0.41590951 | N36: Adjusted EBITDA % of revenues | O36: 0.38137604 | P36: 0.41508399 | Q36: 0.43857782 | R36: 0.43980887 | S36: 0.44387123 | T36: 0.44449483 | V36: 0.34277958 | W36: 0.29476019 | X36: 0.41590951 | Z36: Adjusted EBITDA % of revenues | AA36: 0.38137604 | AB36: 0.40170357 | AC36: 0.38349619 | AD36: 0.40178691 | AE36: 0.42559892 | AF36: 0.44841925 | AH36: 0.34277958 | AI36: 0.29476019 | AJ36: 0.41590951
B38: Net Debt (negative = net cash) | C38: =Model!BV401 -> -78300 | D38: =Model!CA401 -> -120505.2 | E38: =Model!CB401 -> -61243.654 | F38: =Model!CC401 -> -43932.771 | G38: =Model!CD401 -> -54066.777 | H38: =Model!CE401 -> -91584.275 | N38: Net Debt (negative = net cash) | O38: -78300 | P38: -119469.53 | Q38: -26593.387 | R38: -31596.149 | S38: -37350.021 | T38: -43308.109 | Z38: Net Debt (negative = net cash) | AA38: -78300 | AB38: -114696.1 | AC38: -45080.369 | AD38: 23161.801 | AE38: 78602.912 | AF38: 123487.29
B39: Net Debt / Adjusted EBITDA (x) | C39: =IFERROR(C38/C35,"") -> -0.50965945 | D39: =IFERROR(D38/D35,"") -> -0.59033772 | E39: =IFERROR(E38/E35,"") -> -0.25 | F39: =IFERROR(F38/F35,"") -> -0.15360198 | G39: =IFERROR(G38/G35,"") -> -0.16320939 | H39: =IFERROR(H38/H35,"") -> -0.24407946 | N39: Net Debt / Adjusted EBITDA (x) | O39: -0.50965945 | P39: -0.57265761 | Q39: -0.1 | R39: -0.1 | S39: -0.1 | T39: -0.1 | Z39: Net Debt / Adjusted EBITDA (x) | AA39: -0.50965945 | AB39: -0.58059131 | AC39: -0.21384603 | AD39: 0.096611407 | AE39: 0.29081456 | AF39: 0.41483494
B40: Share repurchases ($m; 2026E = 2H) | D40: =Model!CA286 -> 0 | E40: =Model!CB286 -> 27560.057 | F40: =Model!CC286 -> 0 | G40: =Model!CD286 -> 0 | H40: =Model!CE286 -> 0 | N40: Share repurchases ($m; 2026E = 2H) | P40: 5000 | Q40: 83111.681 | R40: 8123.2972 | S40: 46502.626 | T40: 87840.646 | AB40: 0 | AC40: 0 | AD40: 0 | AE40: 0 | AF40: 0
B41: Implied avg buyback price ($) | D41: =Model!CA285 -> 350 | E41: =Model!CB285 -> 378 | F41: =Model!CC285 -> 408.24 | G41: =Model!CD285 -> 440.8992 | H41: =Model!CE285 -> 476.17114 | N41: Implied avg buyback price ($) | P41: 350 | Q41: 378 | R41: 408.24 | S41: 440.8992 | T41: 476.17114 | AB41: 350 | AC41: 378 | AD41: 408.24 | AE41: 440.8992 | AF41: 476.17114
B42: Shares repurchased (m) | D42: =Model!CA287 -> 0 | E42: =Model!CB287 -> 72.910203 | F42: =Model!CC287 -> 0 | G42: =Model!CD287 -> 0 | H42: =Model!CE287 -> 0 | N42: Shares repurchased (m) | P42: 14.285714 | Q42: 219.87217 | R42: 19.898337 | S42: 105.47224 | T42: 184.47285 | AB42: 0 | AC42: 0 | AD42: 0 | AE42: 0 | AF42: 0
B44: ROIC | C44: =Model!BV384 -> 0.41098786 | D44: =Model!CA384 -> 0.30090251 | E44: =Model!CB384 -> 0.24179208 | F44: =Model!CC384 -> 0.20332356 | G44: =Model!CD384 -> 0.18404673 | H44: =Model!CE384 -> 0.17136984 | J44: =IFERROR(AVERAGE(Model!C384,Model!D384,Model!E384,Model!F384,Model!G384,Model!H384,Model!I384,Model!N384,Model!S384,Model!X384,Model!AC384,Model!AH384,Model!AM384,Model!AR384,Model!AW384,Model!BB384,Model!BG384,Model!BL384,Model!BQ384,Model!BV384),"") -> 0.46714538 | K44: =IFERROR(MIN(Model!C384,Model!D384,Model!E384,Model!F384,Model!G384,Model!H384,Model!I384,Model!N384,Model!S384,Model!X384,Model!AC384,Model!AH384,Model!AM384,Model!AR384,Model!AW384,Model!BB384,Model!BG384,Model!BL384,Model!BQ384,Model!BV384),"") -> 0.33257369 | L44: =IFERROR(MAX(Model!C384,Model!D384,Model!E384,Model!F384,Model!G384,Model!H384,Model!I384,Model!N384,Model!S384,Model!X384,Model!AC384,Model!AH384,Model!AM384,Model!AR384,Model!AW384,Model!BB384,Model!BG384,Model!BL384,Model!BQ384,Model!BV384),"") -> 0.67822935 | N44: ROIC | O44: 0.41098786 | P44: 0.30894766 | Q44: 0.26952571 | R44: 0.23528562 | S44: 0.22119877 | T44: 0.21442073 | V44: 0.46714538 | W44: 0.33257369 | X44: 0.67822935 | Z44: ROIC | AA44: 0.41098786 | AB44: 0.28913726 | AC44: 0.19674821 | AD44: 0.15435959 | AE44: 0.13077981 | AF44: 0.11390053 | AH44: 0.46714538 | AI44: 0.33257369 | AJ44: 0.67822935
B45: RONTA | C45: =Model!BV395 -> 0.4150974 | D45: =Model!CA395 -> 0.30129052 | E45: =Model!CB395 -> 0.2433313 | F45: =Model!CC395 -> 0.2051806 | G45: =Model!CD395 -> 0.18606243 | H45: =Model!CE395 -> 0.17347548 | J45: =IFERROR(AVERAGE(Model!C395,Model!D395,Model!E395,Model!F395,Model!G395,Model!H395,Model!I395,Model!N395,Model!S395,Model!X395,Model!AC395,Model!AH395,Model!AM395,Model!AR395,Model!AW395,Model!BB395,Model!BG395,Model!BL395,Model!BQ395,Model!BV395),"") -> 0.55215405 | K45: =IFERROR(MIN(Model!C395,Model!D395,Model!E395,Model!F395,Model!G395,Model!H395,Model!I395,Model!N395,Model!S395,Model!X395,Model!AC395,Model!AH395,Model!AM395,Model!AR395,Model!AW395,Model!BB395,Model!BG395,Model!BL395,Model!BQ395,Model!BV395),"") -> 0.40277333 | L45: =IFERROR(MAX(Model!C395,Model!D395,Model!E395,Model!F395,Model!G395,Model!H395,Model!I395,Model!N395,Model!S395,Model!X395,Model!AC395,Model!AH395,Model!AM395,Model!AR395,Model!AW395,Model!BB395,Model!BG395,Model!BL395,Model!BQ395,Model!BV395),"") -> 0.85490972 | N45: RONTA | O45: 0.4150974 | P45: 0.30934628 | Q45: 0.27275112 | R45: 0.23949777 | S45: 0.2260257 | T45: 0.21971659 | V45: 0.55215405 | W45: 0.40277333 | X45: 0.85490972 | Z45: RONTA | AA45: 0.4150974 | AB45: 0.28950976 | AC45: 0.19692399 | AD45: 0.15446506 | AE45: 0.13085272 | AF45: 0.11395451 | AH45: 0.55215405 | AI45: 0.40277333 | AJ45: 0.85490972
B47: Implied Market Cap (USDm) | F47: =F27*F21 -> 0 | G47: =G27*G21 -> 5045014.9 | H47: =H27*H21 -> 5522636 | N47: Implied Market Cap (USDm) | R47: =R27*R21 -> 0 | S47: =S27*S21 -> 6899361.1 | T47: =T27*T21 -> 7851800.6 | Z47: Implied Market Cap (USDm) | AD47: =AD27*AD21 -> 2724896.5 | AE47: =AE27*AE21 -> 2792634.2 | AF47: =AF27*AF21 -> 2831902.9
B48: (+) Net debt − non-marketable equity securities | F48: =F38+Model!CC411 -> -175393.77 | G48: =G38+Model!CD411 -> -185527.78 | H48: =H38+Model!CE411 -> -223045.27 | N48: (+) Net debt − non-marketable equity securities | R48: =R38+Model!CC411 -> -163057.15 | S48: =S38+Model!CD411 -> -168811.02 | T48: =T38+Model!CE411 -> -174769.11 | Z48: (+) Net debt − non-marketable equity securities | AD48: =AD38+Model!CC411 -> -108299.2 | AE48: =AE38+Model!CD411 -> -52858.088 | AF48: =AF38+Model!CE411 -> -7973.7069
B49: Implied Enterprise Value (USDm) | F49: =F47+F48 -> -175393.77 | G49: =G47+G48 -> 4859487.1 | H49: =H47+H48 -> 5299590.7 | N49: Implied Enterprise Value (USDm) | R49: =R47+R48 -> -163057.15 | S49: =S47+S48 -> 6730550 | T49: =T47+T48 -> 7677031.5 | Z49: Implied Enterprise Value (USDm) | AD49: =AD47+AD48 -> 2616597.3 | AE49: =AE47+AE48 -> 2739776.2 | AF49: =AF47+AF48 -> 2823929.2
B50: Implied EV / Adjusted EBITDA (x) | F50: =IFERROR(F49/F35,"") -> -0.61322857 | G50: =IFERROR(G49/G35,"") -> 14.669155 | H50: =IFERROR(H49/H35,"") -> 14.123836 | N50: Implied EV / Adjusted EBITDA (x) | R50: =IFERROR(R49/R35,"") -> -0.51606653 | S50: =IFERROR(S49/S35,"") -> 18.020204 | T50: =IFERROR(T49/T35,"") -> 17.726545 | Z50: Implied EV / Adjusted EBITDA (x) | AD50: =IFERROR(AD49/AD35,"") -> 10.914226 | AE50: =IFERROR(AE49/AE35,"") -> 10.136607 | AF50: =IFERROR(AF49/AF35,"") -> 9.4865188

Sheet DCF
B2: DCF VALUATION — ALPHABET INC. (GOOG)
B4: 1. WACC BUILD
B5: Risk-free rate (US 10Y govt) | C5: 0.0425 | D5: Assumption (~US 10Y Treasury yield, Oct-2026; government rate sources not reachable from the build environment); update to market
B6: Equity risk premium | C6: 0.05 | D6: Assumption: US implied ERP ~4.5–5.5%
B7: Levered beta | C7: 1.05 | D7: Assumption: mega-cap internet / cloud peers (MSFT, AMZN, META) ~1.0–1.2; advertising cyclicality offset by subscription and cloud backlog ($519.5bn RPO)
B8: Cost of equity | C8: =C5+C7*C6 -> 0.095
B9: Pre-tax cost of debt | C9: 0.047 | D9: 2026 senior notes: USD w.a. coupon 4.80% (15 years), GBP 5.31%, EUR 3.90%, CAD 4.35% (Q2-26 10-Q Note 6); AA+ / Aa2 issuer
B10: Tax rate | C10: 0.175 | D10: Model 2027E+ effective tax rate (FY2025 16.8%)
B11: After-tax cost of debt | C11: =C9*(1-C10) -> 0.038775
B12: Target D/V | C12: 0.05 | D12: Net cash ~$0.1tn at YE2026E vs ~$4.3tn market cap ($350 × ~12.3bn diluted shares); debt ~$100bn, preferred converts in 2029
B13: WACC | C13: =C8*(1-C12)+C11*C12 -> 0.09218875
B15: Valuation date (live) | C15: =TODAY() -> 2026-10-13 00:00:00 | D15: Periods = (31-Dec of the year − today) / 365.25; cash flows at year-end. 2026E UFCF is excluded from the sum: YE2026E net debt already reflects 2026 cash flows
B16: 2. UNLEVERED FREE CASH FLOW BUILD (USDm)
D17: 2026E | E17: 2027E | F17: 2028E | G17: 2029E | H17: 2030E | I17: 2031E | J17: 2032E | K17: 2033E | L17: 2034E | M17: 2035E | N17: Terminal | P17: CAGR 26–30E | Q17: CAGR 26–35E
B18: Adj. EBIT less cash adjusting items (EC fines, severance & office space) | D18: =Model!CA195-Model!CA197 -> 172938.83 | E18: =Model!CB195-Model!CB197 -> 194643.24 | F18: =Model!CC195-Model!CC197 -> 212421.88 | G18: =Model!CD195-Model!CD197 -> 234774.62 | H18: =Model!CE195-Model!CE197 -> 256717.05 | I18: =H18*(1+I$26) -> 279821.58 | J18: =I18*(1+J$26) -> 302906.87 | K18: =J18*(1+K$26) -> 325624.88 | L18: =K18*(1+L$26) -> 347604.56 | M18: =L18*(1+M$26) -> 368460.83 | P18: =IFERROR((H18/D18)^(1/(COLUMNS(D18:H18)-1))-1,"n/m") -> 0.1038004 | Q18: =IFERROR((M18/D18)^(1/(COLUMNS(D18:M18)-1))-1,"n/m") -> 0.087676806
B19: × (1 − tax rate) | D19: =1-$C$10 -> 0.825 | E19: =1-$C$10 -> 0.825 | F19: =1-$C$10 -> 0.825 | G19: =1-$C$10 -> 0.825 | H19: =1-$C$10 -> 0.825 | I19: =1-$C$10 -> 0.825 | J19: =1-$C$10 -> 0.825 | K19: =1-$C$10 -> 0.825 | ... M19: =1-$C$10 -> 0.825
B20: NOPAT | D20: =D18*D19 -> 142674.54 | E20: =E18*E19 -> 160580.67 | F20: =F18*F19 -> 175248.05 | G20: =G18*G19 -> 193689.06 | H20: =H18*H19 -> 211791.57 | I20: =I18*I19 -> 230852.81 | J20: =J18*J19 -> 249898.16 | K20: =K18*K19 -> 268640.53 | ... M20: =M18*M19 -> 303980.19
B21: plus D&A (depreciation + amortization of intangibles) | D21: =Model!CA155 -> 31190.422 | E21: =Model!CB155 -> 50331.376 | F21: =Model!CC155 -> 73595.081 | G21: =Model!CD155 -> 96497.834 | H21: =Model!CE155 -> 118506.15 | I21: =H21*(1+I$26) -> 129171.7 | J21: =I21*(1+J$26) -> 139828.36 | K21: =J21*(1+K$26) -> 150315.49 | L21: =K21*(1+L$26) -> 160461.79 | M21: =L21*(1+M$26) -> 170089.49
B22: − Capex (property & equipment) and acquisitions (M&A lever 2027E–30E; Wiz / Intersect in 2026E); fade: converges to the terminal reinvestment level | D22: =Model!CA254+Model!CA255 -> -233697 | E22: =Model!CB254+Model!CB255 -> -255000 | F22: =Model!CC254+Model!CC255 -> -275000 | G22: =Model!CD254+Model!CD255 -> -290000 | H22: =Model!CE254+Model!CE255 -> -305000 | I22: =$H$22+((-($M$21+$M$20*$C$27/$C$28))-$H$22)*1/5 -> -288657.21 | J22: =$H$22+((-($M$21+$M$20*$C$27/$C$28))-$H$22)*2/5 -> -272314.41 | K22: =$H$22+((-($M$21+$M$20*$C$27/$C$28))-$H$22)*3/5 -> -255971.62 | L22: =$H$22+((-($M$21+$M$20*$C$27/$C$28))-$H$22)*4/5 -> -239628.82 | M22: =$H$22+((-($M$21+$M$20*$C$27/$C$28))-$H$22)*5/5 -> -223286.03
B23: − Δ Working capital (CF statement) | D23: =Model!CA252 -> -9615.293 | E23: =Model!CB252 -> 7222.4062 | F23: =Model!CC252 -> 3614.9155 | G23: =Model!CD252 -> 3028.5945 | H23: =Model!CE252 -> 3010.2728 | I23: =H23*(1+I$26) -> 3281.1973 | J23: =I23*(1+J$26) -> 3551.8961 | K23: =J23*(1+K$26) -> 3818.2883 | L23: =K23*(1+L$26) -> 4076.0228 | M23: =L23*(1+M$26) -> 4320.5841
B24: Unlevered FCF | D24: =D20+D21+D22+D23 -> -69447.334 | E24: =E20+E21+E22+E23 -> -36865.544 | F24: =F20+F21+F22+F23 -> -22541.953 | G24: =G20+G21+G22+G23 -> 3215.491 | H24: =H20+H21+H22+H23 -> 28307.984 | I24: =I20+I21+I22+I23 -> 74648.498 | J24: =J20+J21+J22+J23 -> 120964.01 | K24: =K20+K21+K22+K23 -> 166802.69 | ... M24: =M20+M21+M22+M23 -> 255104.24 | N24: =M24*(1+$C$27) -> 264032.89 | P24: =IFERROR((H24/D24)^(1/(COLUMNS(D24:H24)-1))-1,"n/m") -> n/m | Q24: =IFERROR((M24/D24)^(1/(COLUMNS(D24:M24)-1))-1,"n/m") -> -2.1555392
B25: Terminal Value (Gordon Growth) | N25: =N24/($C$13-$C$27) -> 4616867.6
B26: Fade-period growth (2031E–35E; 9.0% → 6.0% linear) | I26: 0.09 | J26: =I26+($M$26-$I$26)/4 -> 0.0825 | K26: =J26+($M$26-$I$26)/4 -> 0.075 | L26: =K26+($M$26-$I$26)/4 -> 0.0675 | M26: 0.06
B27: Terminal growth rate | C27: 0.035
B28: Terminal RONIC on new investment (fade capex converges to D&A + NOPAT × g ÷ RONIC by 2035E) | C28: 0.2 | D28: Assumption. 2030E capex ($300bn, 36% of revenues, 2.6x D&A) is a build-out level; holding that intensity in perpetuity would imply ~88% reinvestment at ~7% returns. Model ROIC 2030E ~17%; 20% terminal RONIC = reinvestment of 17.5% of NOPAT at 3.5% growth.
B29: Discount period (years) | D29: =(DATE(2026,12,31)-$C$15)/365.25 -> 0.21629021 | E29: =(DATE(2027,12,31)-$C$15)/365.25 -> 1.2156057 | F29: =(DATE(2028,12,31)-$C$15)/365.25 -> 2.2176591 | G29: =(DATE(2029,12,31)-$C$15)/365.25 -> 3.2169747 | H29: =(DATE(2030,12,31)-$C$15)/365.25 -> 4.2162902 | I29: =(DATE(2031,12,31)-$C$15)/365.25 -> 5.2156057 | J29: =(DATE(2032,12,31)-$C$15)/365.25 -> 6.2176591 | K29: =(DATE(2033,12,31)-$C$15)/365.25 -> 7.2169747 | L29: =(DATE(2034,12,31)-$C$15)/365.25 -> 8.2162902 | M29: =(DATE(2035,12,31)-$C$15)/365.25 -> 9.2156057 | N29: =M29 -> 9.2156057
B30: Discount factor | D30: =1/(1+$C$13)^D29 -> 0.98110747 | E30: =1/(1+$C$13)^E29 -> 0.89834902 | F30: =1/(1+$C$13)^F29 -> 0.82237284 | G30: =1/(1+$C$13)^G29 -> 0.75300398 | H30: =1/(1+$C$13)^H29 -> 0.68948653 | I30: =1/(1+$C$13)^I29 -> 0.63132691 | J30: =1/(1+$C$13)^J29 -> 0.57793362 | K30: =1/(1+$C$13)^K29 -> 0.52918372 | ... N30: =1/(1+$C$13)^N29 -> 0.44367352
B31: PV of UFCF | D31: =D24*D30 -> -68135.298 | E31: =E24*E30 -> -33118.125 | F31: =F24*F30 -> -18537.89 | G31: =G24*G30 -> 2421.2775 | H31: =H24*H30 -> 19517.974 | I31: =I24*I30 -> 47127.605 | J31: =J24*J30 -> 69909.171 | K31: =K24*K30 -> 88269.268 | ... M31: =M24*M30 -> 113182.99 | N31: =N25*N30 -> 2048381.9
D32: Alphabet's adjusted EBIT (model) is after stock-based compensation (~6.5% of revenues) and amortization; only company-reconciled cash items (EC fines, severance and office-space charges) are added back, and they are deducted again in row 18. D&A (row 21) is added back in full because adjusted EBIT is full-cost. Row 22 includes capex at the call outlook / scenario levels ($200bn 2026E, $250–300bn 2027E–30E; unverified) and acquisitions. Equity-security gains are excluded from NOPAT; non-marketable equity stakes are added back at carrying value in the equity bridge (row 48). 2026E UFCF is not summed (net debt at YE2026E).
B33: IMPLIED ROIC — invested capital roll-forward (USDm)
B34: Opening invested capital | D34: =Model!BV381 -> 268278 | E34: =D38 -> 480399.87 | F34: =E38 -> 677846.09 | G34: =F38 -> 875636.09 | H34: =G38 -> 1066109.7 | I34: =H38 -> 1249593.2 | J34: =I38 -> 1405797.6 | K34: =J38 -> 1534731.7 | L34: =K38 -> 1636569.5 | M34: =L38 -> 1711660.6
B35: plus Capex and acquisitions | D35: =-D22 -> 233697 | E35: =-E22 -> 255000 | F35: =-F22 -> 275000 | G35: =-G22 -> 290000 | H35: =-H22 -> 305000 | I35: =-I22 -> 288657.21 | J35: =-J22 -> 272314.41 | K35: =-K22 -> 255971.62 | ... M35: =-M22 -> 223286.03
B36: less DD&A | D36: =-D21 -> -31190.422 | E36: =-E21 -> -50331.376 | F36: =-F21 -> -73595.081 | G36: =-G21 -> -96497.834 | H36: =-H21 -> -118506.15 | I36: =-I21 -> -129171.7 | J36: =-J21 -> -139828.36 | K36: =-K21 -> -150315.49 | ... M36: =-M21 -> -170089.49
B37: plus Δ Working capital investment | D37: =-D23 -> 9615.293 | E37: =-E23 -> -7222.4062 | F37: =-F23 -> -3614.9155 | G37: =-G23 -> -3028.5945 | H37: =-H23 -> -3010.2728 | I37: =-I23 -> -3281.1973 | J37: =-J23 -> -3551.8961 | K37: =-K23 -> -3818.2883 | ... M37: =-M23 -> -4320.5841
B38: Closing invested capital | D38: =SUM(D34:D37) -> 480399.87 | E38: =SUM(E34:E37) -> 677846.09 | F38: =SUM(F34:F37) -> 875636.09 | G38: =SUM(G34:G37) -> 1066109.7 | H38: =SUM(H34:H37) -> 1249593.2 | I38: =SUM(I34:I37) -> 1405797.6 | J38: =SUM(J34:J37) -> 1534731.7 | K38: =SUM(K34:K37) -> 1636569.5 | ... M38: =SUM(M34:M37) -> 1760536.5
B39: NOPAT (row 20) | D39: =D20 -> 142674.54 | E39: =E20 -> 160580.67 | F39: =F20 -> 175248.05 | G39: =G20 -> 193689.06 | H39: =H20 -> 211791.57 | I39: =I20 -> 230852.81 | J39: =J20 -> 249898.16 | K39: =K20 -> 268640.53 | ... M39: =M20 -> 303980.19
B40: Implied ROIC (NOPAT / avg. invested capital) | D40: =IFERROR(D39/AVERAGE(D34,D38),"") -> 0.38113731 | E40: =IFERROR(E39/AVERAGE(E34,E38),"") -> 0.27728251 | F40: =IFERROR(F39/AVERAGE(F34,F38),"") -> 0.22561965 | G40: =IFERROR(G39/AVERAGE(G34,G38),"") -> 0.19949992 | H40: =IFERROR(H39/AVERAGE(H34,H38),"") -> 0.18291774 | I40: =IFERROR(I39/AVERAGE(I34,I38),"") -> 0.17387483 | J40: =IFERROR(J39/AVERAGE(J34,J38),"") -> 0.16996815 | K40: =IFERROR(K39/AVERAGE(K34,K38),"") -> 0.16941975 | ... M40: =IFERROR(M39/AVERAGE(M34,M38),"") -> 0.17509386
B41: Reinvestment rate (net investment / NOPAT) | D41: =IFERROR(SUM(D35:D37)/D39,"") -> 1.4867535 | E41: =IFERROR(SUM(E35:E37)/E39,"") -> 1.2295765 | F41: =IFERROR(SUM(F35:F37)/F39,"") -> 1.1286288 | G41: =IFERROR(SUM(G35:G37)/G39,"") -> 0.9833987 | H41: =IFERROR(SUM(H35:H37)/H39,"") -> 0.86634036 | I41: =IFERROR(SUM(I35:I37)/I39,"") -> 0.67664029 | J41: =IFERROR(SUM(J35:J37)/J39,"") -> 0.51594677 | K41: =IFERROR(SUM(K35:K37)/K39,"") -> 0.3790859 | ... M41: =IFERROR(SUM(M35:M37)/M39,"") -> 0.16078663
B42: Implied terminal RONIC (g / reinvestment rate) | N42: =IFERROR($C$27/M41,"") -> 0.2176798
D43: Opening IC = Model 2025A invested capital (equity + net debt − non-marketable equity securities), rolled forward with capex + M&A − D&A + ΔWC (2026E includes Wiz / Intersect).
B44: 3. VALUATION SUMMARY
B45: Sum of PV (explicit + fade) | C45: =SUM(E31:M31) -> 391342.3
B46: PV of Terminal Value | C46: =N31 -> 2048381.9
B47: Enterprise Value | C47: =C45+C46 -> 2439724.2
B48: Less: Net debt − non-marketable equity securities (Model 2026E YE) | C48: =Model!CA401+Model!CA411 -> -251966.2 | D48: GOOG: net debt (debt − cash − marketable securities; negative = net cash) less non-marketable equity stakes at carrying value (outside invested capital). No NCI.
B49: Equity Value | C49: =C47-C48 -> 2691690.4
B50: Diluted shares (m, Model 2026E period end; incl. RSUs and preferred if-converted) | C50: =Model!CA408 -> 12485.751
B51: Implied share price ($) | C51: =C49/C50 -> 215.58098
B52: Current share price ($) | C52: =Model!CA407 -> 350
B53: Implied upside / (downside) | C53: =C51/C52-1 -> -0.38405435
B54: Required discount to DCF value for target IRR | C54: =1-((1+C13)/(1+H54))^H55 -> 0.14335758 | D54: vs. current | E54: Target IRR | H54: 0.15
B55: Max entry price for target IRR ($) | C55: =C51*(1-C54) -> 184.67581 | D55: =C55/C52-1 -> -0.47235483 | E55: Years for discount to close | H55: 3
B58: 4. SENSITIVITY: IMPLIED PRICE ($) — WACC × Terminal Growth
D60: WACC →
B61: Terminal growth ↓ | D61: =F61-0.01 -> 0.08218875 | E61: =F61-0.005 -> 0.08718875 | F61: =$C$13 -> 0.09218875 | G61: =F61+0.005 -> 0.09718875 | H61: =F61+0.01 -> 0.10218875
B62: =B64-0.01 -> 0.025 | D62: {=IFERROR((SUMPRODUCT($D$24:$M$24/(1+D$61)^$D$29:$M$29)+($M$24*(1+$B62)/(D$61-$B62))/(1+D$61)^$M$29-$C$48)/$C$50,"")} -> 225.35497 | E62: {=IFERROR((SUMPRODUCT($D$24:$M$24/(1+E$61)^$D$29:$M$29)+($M$24*(1+$B62)/(E$61-$B62))/(1+E$61)^$M$29-$C$48)/$C$50,"")} -> 203.12596 | F62: {=IFERROR((SUMPRODUCT($D$24:$M$24/(1+F$61)^$D$29:$M$29)+($M$24*(1+$B62)/(F$61-$B62))/(1+F$61)^$M$29-$C$48)/$C$50,"")} -> 184.35734 | G62: {=IFERROR((SUMPRODUCT($D$24:$M$24/(1+G$61)^$D$29:$M$29)+($M$24*(1+$B62)/(G$61-$B62))/(1+G$61)^$M$29-$C$48)/$C$50,"")} -> 168.32482 | H62: {=IFERROR((SUMPRODUCT($D$24:$M$24/(1+H$61)^$D$29:$M$29)+($M$24*(1+$B62)/(H$61-$B62))/(1+H$61)^$M$29-$C$48)/$C$50,"")} -> 154.49202
B63: =B64-0.005 -> 0.03 | D63: {=IFERROR((SUMPRODUCT($D$24:$M$24/(1+D$61)^$D$29:$M$29)+($M$24*(1+$B63)/(D$61-$B63))/(1+D$61)^$M$29-$C$48)/$C$50,"")} -> 243.24312 | E63: {=IFERROR((SUMPRODUCT($D$24:$M$24/(1+E$61)^$D$29:$M$29)+($M$24*(1+$B63)/(E$61-$B63))/(1+E$61)^$M$29-$C$48)/$C$50,"")} -> 217.57981 | F63: {=IFERROR((SUMPRODUCT($D$24:$M$24/(1+F$61)^$D$29:$M$29)+($M$24*(1+$B63)/(F$61-$B63))/(1+F$61)^$M$29-$C$48)/$C$50,"")} -> 196.20481 | G63: {=IFERROR((SUMPRODUCT($D$24:$M$24/(1+G$61)^$D$29:$M$29)+($M$24*(1+$B63)/(G$61-$B63))/(1+G$61)^$M$29-$C$48)/$C$50,"")} -> 178.15522 | H63: {=IFERROR((SUMPRODUCT($D$24:$M$24/(1+H$61)^$D$29:$M$29)+($M$24*(1+$B63)/(H$61-$B63))/(1+H$61)^$M$29-$C$48)/$C$50,"")} -> 162.73513
B64: =$C$27 -> 0.035 | D64: {=IFERROR((SUMPRODUCT($D$24:$M$24/(1+D$61)^$D$29:$M$29)+($M$24*(1+$B64)/(D$61-$B64))/(1+D$61)^$M$29-$C$48)/$C$50,"")} -> 264.92204 | E64: {=IFERROR((SUMPRODUCT($D$24:$M$24/(1+E$61)^$D$29:$M$29)+($M$24*(1+$B64)/(E$61-$B64))/(1+E$61)^$M$29-$C$48)/$C$50,"")} -> 234.80319 | F64: {=IFERROR((SUMPRODUCT($D$24:$M$24/(1+F$61)^$D$29:$M$29)+($M$24*(1+$B64)/(F$61-$B64))/(1+F$61)^$M$29-$C$48)/$C$50,"")} -> 210.12393 | G64: {=IFERROR((SUMPRODUCT($D$24:$M$24/(1+G$61)^$D$29:$M$29)+($M$24*(1+$B64)/(G$61-$B64))/(1+G$61)^$M$29-$C$48)/$C$50,"")} -> 189.56636 | H64: {=IFERROR((SUMPRODUCT($D$24:$M$24/(1+H$61)^$D$29:$M$29)+($M$24*(1+$B64)/(H$61-$B64))/(1+H$61)^$M$29-$C$48)/$C$50,"")} -> 172.2051
B65: =B64+0.005 -> 0.04 | D65: {=IFERROR((SUMPRODUCT($D$24:$M$24/(1+D$61)^$D$29:$M$29)+($M$24*(1+$B65)/(D$61-$B65))/(1+D$61)^$M$29-$C$48)/$C$50,"")} -> 291.73951 | E65: {=IFERROR((SUMPRODUCT($D$24:$M$24/(1+E$61)^$D$29:$M$29)+($M$24*(1+$B65)/(E$61-$B65))/(1+E$61)^$M$29-$C$48)/$C$50,"")} -> 255.67646 | F65: {=IFERROR((SUMPRODUCT($D$24:$M$24/(1+F$61)^$D$29:$M$29)+($M$24*(1+$B65)/(F$61-$B65))/(1+F$61)^$M$29-$C$48)/$C$50,"")} -> 226.71012 | G65: {=IFERROR((SUMPRODUCT($D$24:$M$24/(1+G$61)^$D$29:$M$29)+($M$24*(1+$B65)/(G$61-$B65))/(1+G$61)^$M$29-$C$48)/$C$50,"")} -> 202.97285 | H65: {=IFERROR((SUMPRODUCT($D$24:$M$24/(1+H$61)^$D$29:$M$29)+($M$24*(1+$B65)/(H$61-$B65))/(1+H$61)^$M$29-$C$48)/$C$50,"")} -> 183.19784
B66: =B64+0.01 -> 0.045 | D66: {=IFERROR((SUMPRODUCT($D$24:$M$24/(1+D$61)^$D$29:$M$29)+($M$24*(1+$B66)/(D$61-$B66))/(1+D$61)^$M$29-$C$48)/$C$50,"")} -> 325.76816 | E66: {=IFERROR((SUMPRODUCT($D$24:$M$24/(1+E$61)^$D$29:$M$29)+($M$24*(1+$B66)/(E$61-$B66))/(1+E$61)^$M$29-$C$48)/$C$50,"")} -> 281.49732 | F66: {=IFERROR((SUMPRODUCT($D$24:$M$24/(1+F$61)^$D$29:$M$29)+($M$24*(1+$B66)/(F$61-$B66))/(1+F$61)^$M$29-$C$48)/$C$50,"")} -> 246.81118 | G66: {=IFERROR((SUMPRODUCT($D$24:$M$24/(1+G$61)^$D$29:$M$29)+($M$24*(1+$B66)/(G$61-$B66))/(1+G$61)^$M$29-$C$48)/$C$50,"")} -> 218.94818 | H66: {=IFERROR((SUMPRODUCT($D$24:$M$24/(1+H$61)^$D$29:$M$29)+($M$24*(1+$B66)/(H$61-$B66))/(1+H$61)^$M$29-$C$48)/$C$50,"")} -> 196.11278
B69: 5. REVERSE DCF
B70: To solve for the market-implied path: Data ▸ What-If Analysis ▸ Goal Seek — set C51 to the current price (C52) by changing C27 (terminal growth) or the fade-period growth inputs (I26:M26).
B72: 6. MAUBOUSSIN EV / NOPAT — TWO-STAGE FRAMEWORK
B73: EV/NOPAT = 1/r + [g × (1 − r/ROIIC) / (r × (r − g))] × [1 − ((1+g)/(1+r))^N]
B74: Formula source: Mauboussin & Rappaport, "Expectations Investing" (2021); Counterpoint Global, "What Does a Price-Earnings Multiple Mean?" (2020).
B76: Input | C76: Value | D76: Rationale (Alphabet characteristics)
B77: r (Cost of capital / WACC) | C77: =$C$13 -> 0.09218875 | D77: Linked from Section 1 WACC build
B78: g (NOPAT growth, Stage 1) | C78: 0.1 | D78: Model adjusted EBIT CAGR 2025–30E: Search / YouTube / subscriptions high-single to low-double digit, Cloud 20–45% with rising margins, against rising depreciation → ~10% NOPAT growth
B79: ROIIC (Return on incremental invested capital) | C79: 0.2 | D79: Search and YouTube earn very high returns on little capital; incremental returns now hinge on AI infrastructure (capex ~45% of revenues in 2026E–27E) monetised through Cloud backlog and AI products
B80: N (Years of value creation / CAP) | C80: 15 | D80: Search distribution, data and TPU / infrastructure scale sustain a long competitive-advantage period; risks: AI-assistant substitution of search, antitrust remedies (US search and ad-tech cases, EC fines)
B82: Calculation | C82: Value
B83: Steady-state component: 1 / r | C83: =1/C77 -> 10.847311
B84: Value-creation factor: 1 − r / ROIIC | C84: =1-C77/C79 -> 0.53905625
B85: Growth multiplier: g × (1 − r/ROIIC) / (r × (r − g)) | C85: =C78*C84/(C77*(C77-C78)) -> -74.857552
B86: Time decay: 1 − ((1+g)/(1+r))^N | C86: =1-((1+C78)/(1+C77))^C80 -> -0.11281967
B87: PVGO component (growth value) | C87: =C85*C86 -> 8.4454047
B88: Mauboussin EV / NOPAT (steady-state + PVGO) | C88: =C83+C87 -> 19.292715
B90: VALUATION — Applied to 2028E NOPAT | C90: USDm
B91: 2028E Adj. EBIT less cash adjusting items | C91: =Model!CC195-Model!CC197 -> 212421.88
B92: Tax rate (from WACC build) | C92: =$C$10 -> 0.175
B93: 2028E NOPAT | C93: =C91*(1-C92) -> 175248.05
B94: × Mauboussin EV/NOPAT multiple | C94: =C88 -> 19.292715
B95: Implied Enterprise Value (2028E basis) | C95: =C93*C94 -> 3381010.7
B96: Less: YE2027 net debt − non-marketable equity securities (Model) | C96: =Model!CB401+Model!CB411 -> -192704.65
B97: Implied Equity Value | C97: =C95-C96 -> 3573715.4
B98: Diluted shares 2028E (m, Model) | C98: =Model!CC408 -> 12648.631
B99: Implied share price 2028 ($) | C99: =C97/C98 -> 282.53772
B101: Current share price ($) | C101: =C52 -> 350
B102: Implied upside / (downside) | C102: =C99/C101-1 -> -0.19274937
B104: MARKET-IMPLIED EV/NOPAT TODAY | C104: USDm
B105: Current market cap (spot × diluted shares) | C105: =C52*C50 -> 4370012.8
B106: Plus: YE2026 net debt − non-marketable equity securities | C106: =C48 -> -251966.2
B107: Implied Enterprise Value (today) | C107: =C105+C106 -> 4118046.7
B108: GOOG market-implied EV/NOPAT (on 2028E NOPAT) | C108: =C107/C93 -> 23.498388
B110: Multiple gap (Mauboussin − Market) | C110: =C88-C108 -> -4.2056725
B111: Implied re-rating headroom | C111: =C88/C108-1 -> -0.17897707

Sheet Charts
B2: Alphabet Inc. — Operating Performance (2011–2025) and Model Forecast (2026E–2030E)
B3: USDm · Linked to Model. Bars = contribution of Google Services and Google Cloud to total revenue growth (pp; current revenue taxonomy from 2017–18, earlier years n/a). Adjusted EBITDA and operating income = model definitions. ROIC / RONTA on adjusted EBIT (invested capital excludes equity stakes).
C7: 2011 | D7: 2012 | E7: 2013 | F7: 2014 | G7: 2015 | H7: 2016 | I7: 2017 | J7: 2018 | K7: 2019 | L7: 2020 | M7: 2021 | N7: 2022 | O7: 2023 | P7: 2024 | Q7: 2025 | R7: 2026E | S7: 2027E | T7: 2028E | U7: 2029E | V7: 2030E
B8: Google Services contribution to growth (pp) | C8: =IFERROR(Model!H39+0,0) -> 0 | D8: =IFERROR(Model!I39+0,0) -> 0 | E8: =IFERROR(Model!N39+0,0) -> 0 | F8: =IFERROR(Model!S39+0,0) -> 0 | G8: =IFERROR(Model!X39+0,0) -> 0 | H8: =IFERROR(Model!AC39+0,0) -> 0 | I8: =IFERROR(Model!AH39+0,0) -> 0 | J8: =IFERROR(Model!AM39+0,0) -> 0.21679672 | K8: =IFERROR(Model!AR39+0,0) -> 0.15568744 | L8: =IFERROR(Model!AW39+0,0) -> 0.10385711 | M8: =IFERROR(Model!BB39+0,0) -> 0.37744553 | N8: =IFERROR(Model!BG39+0,0) -> 0.062099 | O8: =IFERROR(Model!BL39+0,0) -> 0.067229773 | P8: =IFERROR(Model!BQ39+0,0) -> 0.1053599 | Q8: =IFERROR(Model!BV39+0,0) -> 0.10796873 | R8: =IFERROR(Model!CA39+0,0) -> 0.13044957 | S8: =IFERROR(Model!CB39+0,0) -> 0.082471733 | T8: =IFERROR(Model!CC39+0,0) -> 0.065501983 | U8: =IFERROR(Model!CD39+0,0) -> 0.056141688 | V8: =IFERROR(Model!CE39+0,0) -> 0.047759089
B9: Google Cloud contribution to growth (pp) | C9: =IFERROR(Model!H40+0,0) -> 0 | D9: =IFERROR(Model!I40+0,0) -> 0 | E9: =IFERROR(Model!N40+0,0) -> 0 | F9: =IFERROR(Model!S40+0,0) -> 0 | G9: =IFERROR(Model!X40+0,0) -> 0 | H9: =IFERROR(Model!AC40+0,0) -> 0 | I9: =IFERROR(Model!AH40+0,0) -> 0.044930876 | J9: =IFERROR(Model!AM40+0,0) -> 0.016075053 | K9: =IFERROR(Model!AR40+0,0) -> 0.022511493 | L9: =IFERROR(Model!AW40+0,0) -> 0.025584312 | M9: =IFERROR(Model!BB40+0,0) -> 0.033677209 | N9: =IFERROR(Model!BG40+0,0) -> 0.027457236 | O9: =IFERROR(Model!BL40+0,0) -> 0.024070486 | P9: =IFERROR(Model!BQ40+0,0) -> 0.032990234 | Q9: =IFERROR(Model!BV40+0,0) -> 0.044214869 | R9: =IFERROR(Model!CA40+0,0) -> 0.10647628 | S9: =IFERROR(Model!CB40+0,0) -> 0.091754241 | T9: =IFERROR(Model!CC40+0,0) -> 0.080599269 | U9: =IFERROR(Model!CD40+0,0) -> 0.07245474 | V9: =IFERROR(Model!CE40+0,0) -> 0.064134277
C11: =C7 -> 2011 | D11: =D7 -> 2012 | E11: =E7 -> 2013 | F11: =F7 -> 2014 | G11: =G7 -> 2015 | H11: =H7 -> 2016 | I11: =I7 -> 2017 | J11: =J7 -> 2018 | ... V11: =V7 -> 2030E
B12: Adjusted EBITDA (model) | C12: =Model!H191 -> 13593 | D12: =Model!I191 -> 15722 | E12: =Model!N191 -> 17905 | F12: =Model!S191 -> 21475 | G12: =Model!X191 -> 24423 | H12: =Model!AC191 -> 29860 | I12: =Model!AH191 -> 35797 | J12: =Model!AM191 -> 40427 | K12: =Model!AR191 -> 47709 | L12: =Model!AW191 -> 54921 | M12: =Model!BB191 -> 91155 | N12: =Model!BG191 -> 90770 | O12: =Model!BL191 -> 98797 | P12: =Model!BQ191 -> 128417 | Q12: =Model!BV191 -> 153632 | R12: =Model!CA191 -> 204129.25 | S12: =Model!CB191 -> 244974.62 | T12: =Model!CC191 -> 286016.96 | U12: =Model!CD191 -> 331272.46 | V12: =Model!CE191 -> 375223.2
B13: Income from operations (GAAP) | C13: =Model!H140 -> 11742 | D13: =Model!I140 -> 12760 | E13: =Model!N140 -> 13966 | F13: =Model!S140 -> 16496 | G13: =Model!X140 -> 19360 | H13: =Model!AC140 -> 23716 | I13: =Model!AH140 -> 26146 | J13: =Model!AM140 -> 26321 | K13: =Model!AR140 -> 34231 | L13: =Model!AW140 -> 41224 | M13: =Model!BB140 -> 78714 | N13: =Model!BG140 -> 74842 | O13: =Model!BL140 -> 84293 | P13: =Model!BQ140 -> 112390 | Q13: =Model!BV140 -> 129039 | R13: =Model!CA140 -> 172938.83 | S13: =Model!CB140 -> 194643.24 | T13: =Model!CC140 -> 212421.88 | U13: =Model!CD140 -> 234774.62 | V13: =Model!CE140 -> 256717.05
B14: Adj. EBITDA Margin % | C14: =Model!H238 -> 0.35860704 | D14: =Model!I238 -> 0.3133433 | E14: =Model!N238 -> 0.29928959 | F14: =Model!S238 -> 0.32537386 | G14: =Model!X238 -> 0.32568777 | H14: =Model!AC238 -> 0.33077809 | I14: =Model!AH238 -> 0.32291732 | J14: =Model!AM238 -> 0.29547797 | K14: =Model!AR238 -> 0.29476019 | L14: =Model!AW238 -> 0.30089247 | M14: =Model!BB238 -> 0.35381176 | N14: =Model!BG238 -> 0.32092803 | O14: =Model!BL238 -> 0.32140185 | P14: =Model!BQ238 -> 0.36688685 | Q14: =Model!BV238 -> 0.38137604 | R14: =Model!CA238 -> 0.40967168 | S14: =Model!CB238 -> 0.41884301 | T14: =Model!CC238 -> 0.42627878 | U14: =Model!CD238 -> 0.4370294 | V14: =Model!CE238 -> 0.44470437
B15: Operating Margin % | C15: =Model!H239 -> 0.30977444 | D15: =Model!I239 -> 0.25430992 | E15: =Model!N239 -> 0.23344756 | F15: =Model!S239 -> 0.24993561 | G15: =Model!X239 -> 0.2581712 | H15: =Model!AC239 -> 0.26271712 | I15: =Model!AH239 -> 0.23585765 | J15: =Model!AM239 -> 0.19237825 | K15: =Model!AR239 -> 0.21148915 | L15: =Model!AW239 -> 0.22585152 | M15: =Model!BB239 -> 0.30552289 | N15: =Model!BG239 -> 0.26461271 | O15: =Model!BL239 -> 0.2742181 | P15: =Model!BQ239 -> 0.32109777 | Q15: =Model!BV239 -> 0.32032639 | R15: =Model!CA239 -> 0.34707491 | S15: =Model!CB239 -> 0.33278942 | T15: =Model!CC239 -> 0.3165929 | U15: =Model!CD239 -> 0.30972515 | V15: =Model!CE239 -> 0.30425409
C17: =C7 -> 2011 | D17: =D7 -> 2012 | E17: =E7 -> 2013 | F17: =F7 -> 2014 | G17: =G7 -> 2015 | H17: =H7 -> 2016 | I17: =I7 -> 2017 | J17: =J7 -> 2018 | ... V17: =V7 -> 2030E
B18: ROIC | C18: =IFERROR(Model!H384+0,NA()) -> 0.54778631 | D18: =IFERROR(Model!I384+0,NA()) -> 0.37131237 | E18: =IFERROR(Model!N384+0,NA()) -> 0.39734709 | F18: =IFERROR(Model!S384+0,NA()) -> 0.33257369 | G18: =IFERROR(Model!X384+0,NA()) -> 0.34049115 | H18: =IFERROR(Model!AC384+0,NA()) -> 0.37683137 | I18: =IFERROR(Model!AH384+0,NA()) -> 0.5064742 | J18: =IFERROR(Model!AM384+0,NA()) -> 0.47177749 | K18: =IFERROR(Model!AR384+0,NA()) -> 0.42863173 | L18: =IFERROR(Model!AW384+0,NA()) -> 0.43114686 | M18: =IFERROR(Model!BB384+0,NA()) -> 0.67822935 | N18: =IFERROR(Model!BG384+0,NA()) -> 0.49708544 | O18: =IFERROR(Model!BL384+0,NA()) -> 0.4802019 | P18: =IFERROR(Model!BQ384+0,NA()) -> 0.459628 | Q18: =IFERROR(Model!BV384+0,NA()) -> 0.41098786 | R18: =IFERROR(Model!CA384+0,NA()) -> 0.30090251 | S18: =IFERROR(Model!CB384+0,NA()) -> 0.24179208 | T18: =IFERROR(Model!CC384+0,NA()) -> 0.20332356 | U18: =IFERROR(Model!CD384+0,NA()) -> 0.18404673 | V18: =IFERROR(Model!CE384+0,NA()) -> 0.17136984
B19: RONTA | C19: =IFERROR(Model!H395+0,NA()) -> 0.76550842 | D19: =IFERROR(Model!I395+0,NA()) -> 0.46922322 | E19: =IFERROR(Model!N395+0,NA()) -> 0.49368325 | F19: =IFERROR(Model!S395+0,NA()) -> 0.42578793 | G19: =IFERROR(Model!X395+0,NA()) -> 0.43228064 | H19: =IFERROR(Model!AC395+0,NA()) -> 0.45475633 | I19: =IFERROR(Model!AH395+0,NA()) -> 0.50734217 | J19: =IFERROR(Model!AM395+0,NA()) -> 0.48243438 | K19: =IFERROR(Model!AR395+0,NA()) -> 0.40277333 | L19: =IFERROR(Model!AW395+0,NA()) -> 0.40518465 | M19: =IFERROR(Model!BB395+0,NA()) -> 0.64126499 | N19: =IFERROR(Model!BG395+0,NA()) -> 0.51263986 | O19: =IFERROR(Model!BL395+0,NA()) -> 0.49696441 | P19: =IFERROR(Model!BQ395+0,NA()) -> 0.47515159 | Q19: =IFERROR(Model!BV395+0,NA()) -> 0.4150974 | R19: =IFERROR(Model!CA395+0,NA()) -> 0.30129052 | S19: =IFERROR(Model!CB395+0,NA()) -> 0.2433313 | T19: =IFERROR(Model!CC395+0,NA()) -> 0.2051806 | U19: =IFERROR(Model!CD395+0,NA()) -> 0.18606243 | V19: =IFERROR(Model!CE395+0,NA()) -> 0.17347548
B20: Adj. EBITDA margin % | C20: =IFERROR(Model!H238+0,NA()) -> 0.35860704 | D20: =IFERROR(Model!I238+0,NA()) -> 0.3133433 | E20: =IFERROR(Model!N238+0,NA()) -> 0.29928959 | F20: =IFERROR(Model!S238+0,NA()) -> 0.32537386 | G20: =IFERROR(Model!X238+0,NA()) -> 0.32568777 | H20: =IFERROR(Model!AC238+0,NA()) -> 0.33077809 | I20: =IFERROR(Model!AH238+0,NA()) -> 0.32291732 | J20: =IFERROR(Model!AM238+0,NA()) -> 0.29547797 | K20: =IFERROR(Model!AR238+0,NA()) -> 0.29476019 | L20: =IFERROR(Model!AW238+0,NA()) -> 0.30089247 | M20: =IFERROR(Model!BB238+0,NA()) -> 0.35381176 | N20: =IFERROR(Model!BG238+0,NA()) -> 0.32092803 | O20: =IFERROR(Model!BL238+0,NA()) -> 0.32140185 | P20: =IFERROR(Model!BQ238+0,NA()) -> 0.36688685 | Q20: =IFERROR(Model!BV238+0,NA()) -> 0.38137604 | R20: =IFERROR(Model!CA238+0,NA()) -> 0.40967168 | S20: =IFERROR(Model!CB238+0,NA()) -> 0.41884301 | T20: =IFERROR(Model!CC238+0,NA()) -> 0.42627878 | U20: =IFERROR(Model!CD238+0,NA()) -> 0.4370294 | V20: =IFERROR(Model!CE238+0,NA()) -> 0.44470437
B21: FCF margin % | C21: =IFERROR(Model!H277+0,NA()) -> 0.29354966 | D21: =IFERROR(Model!I277+0,NA()) -> 0.26598904 | E21: =IFERROR(Model!N277+0,NA()) -> 0.18890096 | F21: =IFERROR(Model!S277+0,NA()) -> 0.17298223 | G21: =IFERROR(Model!X277+0,NA()) -> 0.21481817 | H21: =IFERROR(Model!AC277+0,NA()) -> 0.28606877 | I21: =IFERROR(Model!AH277+0,NA()) -> 0.2156601 | J21: =IFERROR(Model!AM277+0,NA()) -> 0.16687741 | K21: =IFERROR(Model!AR277+0,NA()) -> 0.1913541 | L21: =IFERROR(Model!AW277+0,NA()) -> 0.23472144 | M21: =IFERROR(Model!BB277+0,NA()) -> 0.26010239 | N21: =IFERROR(Model!BG277+0,NA()) -> 0.21217243 | O21: =IFERROR(Model!BL277+0,NA()) -> 0.22607793 | P21: =IFERROR(Model!BQ277+0,NA()) -> 0.20788645 | Q21: =IFERROR(Model!BV277+0,NA()) -> 0.1818755 | R21: =IFERROR(Model!CA277+0,NA()) -> -0.0056624873 | S21: =IFERROR(Model!CB277+0,NA()) -> 0.014572813 | T21: =IFERROR(Model!CC277+0,NA()) -> 0.040058249 | U21: =IFERROR(Model!CD277+0,NA()) -> 0.076299941 | V21: =IFERROR(Model!CE277+0,NA()) -> 0.10520758
