Workbook

Sheet Model
CF1: SCENARIO SWITCH ▼ (Bull / Base / Bear) — drives all scenario-linked forecast drivers
B2: HEICO Corporation (NYSE: HEI, HEI.A) — 3-Statement Financial Model | CF2: Base
B3: US GAAP as reported · USD millions (per-share data in USD on the current share basis) · fiscal year ends 31 October · Source: HEICO Forms 10-K / 10-Q and Form 8-K earnings releases (Ex. 99.1), debt 8-K (16-Jul-2026), SEC EDGAR CIK 0000046619 (XBRL from Q3 FY2010; investor-relations releases are the same documents as filed on EDGAR)
B4: Basis notes: two operating segments — Flight Support Group (FSG) and Electronic Technologies Group (ETG); segment net sales include intersegment sales. Seven 5-for-4 stock splits (Apr-2010, Apr-2011, Apr-2012, Oct-2013, Apr-2017, Jan-2018, Jun-2018) — all share and per-share data restated to the current basis (×4.77 cumulative). SFAS 160 adopted FY2010 (FY2006–08 minority interests recast as NCI). ASU 2016-09 from FY2017 (stock-option excess tax benefits in income tax expense). Major deals: Wencor (Aug-2023, $1.9bn), Exxelia (Jan-2023); FY26 deals Rockmart, Ethos, Sherwood. Q4/26E–2030E = forecast. Common (HEI) and Class A (HEI.A) shares combined.
CH5: Forecast | CI5: Historical | CJ5: Historical | CK5: Historical
B6: (USDm) | C6: 2006 | D6: 2007 | E6: 2008 | F6: 2009 | G6: 2010 | H6: 2011 | I6: 2012 | J6: Q1/13 | K6: Q2/13 | L6: Q3/13 | M6: Q4/13 | N6: 2013 | O6: Q1/14 | P6: Q2/14 | Q6: Q3/14 | R6: Q4/14 | S6: 2014 | T6: Q1/15 | U6: Q2/15 | V6: Q3/15 | W6: Q4/15 | X6: 2015 | Y6: Q1/16 | Z6: Q2/16 | AA6: Q3/16 | AB6: Q4/16 | AC6: 2016 | AD6: Q1/17 | AE6: Q2/17 | AF6: Q3/17 | AG6: Q4/17 | AH6: 2017 | AI6: Q1/18 | AJ6: Q2/18 | AK6: Q3/18 | AL6: Q4/18 | AM6: 2018 | AN6: Q1/19 | AO6: Q2/19 | AP6: Q3/19 | AQ6: Q4/19 | AR6: 2019 | AS6: Q1/20 | AT6: Q2/20 | AU6: Q3/20 | AV6: Q4/20 | AW6: 2020 | AX6: Q1/21 | AY6: Q2/21 | AZ6: Q3/21 | BA6: Q4/21 | BB6: 2021 | BC6: Q1/22 | BD6: Q2/22 | BE6: Q3/22 | BF6: Q4/22 | BG6: 2022 | BH6: Q1/23 | BI6: Q2/23 | BJ6: Q3/23 | BK6: Q4/23 | BL6: 2023 | BM6: Q1/24 | BN6: Q2/24 | BO6: Q3/24 | BP6: Q4/24 | BQ6: 2024 | BR6: Q1/25 | BS6: Q2/25 | BT6: Q3/25 | BU6: Q4/25 | BV6: 2025 | BW6: Q1/26 | BX6: Q2/26 | BY6: Q3/26 | BZ6: Q4/26E | CA6: 2026E | CB6: 2027E | CC6: 2028E | CD6: 2029E | CE6: 2030E | CF6: Modelling Notes | CH6: 5Y CAGR | CI6: 5Y CAGR | CJ6: 10Y CAGR | CK6: 19Y CAGR
CH7: 25-'30 | CI7: 20-'25 | CJ7: 15-'25 | CK7: 06-'25
B8: SEGMENT P&L — FLIGHT SUPPORT GROUP · ELECTRONIC TECHNOLOGIES GROUP (organic + acquired growth build) | CF8: SEGMENT BUILD — modelling logic (net sales = prior year × (1 + organic + acquired growth); operating income = net sales × operating margin)
CN9: SCENARIO INPUT TABLE — driver assumptions per Bull / Base / Bear | CO9: Bull | CP9: Base | CQ9: Bear | CR9: Bull / Bear = Base + Δ (Δ inputs on each block header). FY26 target block = optional high / mid / low end-points.
B10: Flight Support Group (FSG) — aftermarket replacement parts (PMA), repair & overhaul parts and services, specialty products | CF10: FSG — modelling logic
B11: Net sales (incl. intersegment sales) | C11: 277.255 | D11: 383.911 | E11: 436.81 | F11: 395.423 | G11: 412.337 | H11: 539.563 | I11: 570.325 | J11: 138.998 | K11: 155.231 | L11: 181.331 | M11: 189.588 | N11: 665.148 | O11: 181.585 | P11: 194.892 | Q11: 191.561 | R11: 194.763 | S11: 762.801 | T11: 182.057 | U11: 202.775 | V11: 206.599 | W11: 218.269 | X11: 809.7 | Y11: 204.576 | Z11: 220.29 | AA11: 222.553 | AB11: 228.451 | AC11: 875.87 | AD11: 220.901 | AE11: 231.809 | AF11: 257.966 | AG11: 256.864 | AH11: 967.54 | AI11: 254.721 | AJ11: 267.836 | AK11: 285.126 | AL11: 290.254 | AM11: 1097.937 | AN11: 287.213 | AO11: 308.251 | AP11: 320.016 | AQ11: 324.703 | AR11: 1240.183 | AS11: 301.067 | AT11: 251.964 | AU11: 178.158 | AV11: 193.623 | AW11: 924.812 | AX11: 199.334 | AY11: 230.28 | AZ11: 237.118 | BA11: 260.357 | BB11: 927.089 | BC11: 272.681 | BD11: 306.313 | BE11: 330.259 | BF11: 345.959 | BG11: 1255.212 | BH11: 371.278 | BI11: 392.202 | BJ11: 405.04 | BK11: 601.665 | BL11: 1770.185 | BM11: 618.716 | BN11: 647.232 | BO11: 681.626 | BP11: 691.78 | BQ11: 2639.354 | BR11: 713.174 | BS11: 767.07 | BT11: 802.661 | BU11: 834.372 | BV11: 3117.277 | BW11: 820 | BX11: 929.427 | BY11: 947.803 | BZ11: =BU11*(1+BZ12) -> 984.55896 | CA11: =SUM(BW11,BX11,BY11,BZ11) -> 3681.789 | CB11: =CA11*(1+CB12) -> 4086.7857 | CC11: =CB11*(1+CC12) -> 4413.7286 | CD11: =CC11*(1+CD12) -> 4722.6896 | CE11: =CD11*(1+CE12) -> 5053.2779 | CF11: Q4/26E: Q4/25 × (1 + organic + acquired growth + outlook calibration Δ). 2027E+: prior year × (1 + organic lever + acquired growth input). | CH11: =IFERROR((CE11/BV11)^(1/5)-1,"n/m") -> 0.10143674 | CI11: =IFERROR((BV11/AW11)^(1/5)-1,"n/m") -> 0.27510042 | CJ11: =IFERROR((BV11/X11)^(1/10)-1,"n/m") -> 0.14431377 | CK11: =IFERROR((BV11/C11)^(1/19)-1,"n/m") -> 0.1358221 | CN11: FY26 targets — optional (e.g. consensus); HEICO gives no numerical guidance | CO11: High | CP11: Mid | CQ11: Low | CR11: Leave blank for the driver-based forecast; any number entered calibrates Q4/26E growth / margins for the active scenario.
B12: Net sales y/y % | D12: =IF(AND(ISNUMBER(D11),ISNUMBER(C11)),IFERROR(D11/C11-1,""),"") -> 0.38468558 | E12: =IF(AND(ISNUMBER(E11),ISNUMBER(D11)),IFERROR(E11/D11-1,""),"") -> 0.13778975 | F12: =IF(AND(ISNUMBER(F11),ISNUMBER(E11)),IFERROR(F11/E11-1,""),"") -> -0.094748289 | G12: =IF(AND(ISNUMBER(G11),ISNUMBER(F11)),IFERROR(G11/F11-1,""),"") -> 0.042774447 | H12: =IF(AND(ISNUMBER(H11),ISNUMBER(G11)),IFERROR(H11/G11-1,""),"") -> 0.30854859 | I12: =IF(AND(ISNUMBER(I11),ISNUMBER(H11)),IFERROR(I11/H11-1,""),"") -> 0.057012805 | N12: =IF(AND(ISNUMBER(N11),ISNUMBER(I11)),IFERROR(N11/I11-1,""),"") -> 0.16626134 | O12: =IF(AND(ISNUMBER(O11),ISNUMBER(J11)),IFERROR(O11/J11-1,""),"") -> 0.3063857 | P12: =IF(AND(ISNUMBER(P11),ISNUMBER(K11)),IFERROR(P11/K11-1,""),"") -> 0.25549665 | Q12: =IF(AND(ISNUMBER(Q11),ISNUMBER(L11)),IFERROR(Q11/L11-1,""),"") -> 0.056416167 | R12: =IF(AND(ISNUMBER(R11),ISNUMBER(M11)),IFERROR(R11/M11-1,""),"") -> 0.027296031 | S12: =IF(AND(ISNUMBER(S11),ISNUMBER(N11)),IFERROR(S11/N11-1,""),"") -> 0.14681394 | T12: =IF(AND(ISNUMBER(T11),ISNUMBER(O11)),IFERROR(T11/O11-1,""),"") -> 0.0025993336 | U12: =IF(AND(ISNUMBER(U11),ISNUMBER(P11)),IFERROR(U11/P11-1,""),"") -> 0.040448043 | ... BY12: =IF(AND(ISNUMBER(BY11),ISNUMBER(BT11)),IFERROR(BY11/BT11-1,""),"") -> 0.18082603 | BZ12: =BZ13+BZ14+BZ82 -> 0.18 | CA12: =IF(AND(ISNUMBER(CA11),ISNUMBER(BV11)),IFERROR(CA11/BV11-1,""),"") -> 0.18109137 | CB12: =CB13+CB14 -> 0.11 | CC12: =CC13+CC14 -> 0.08 | CD12: =CD13+CD14 -> 0.07 | CE12: =CE13+CE14 -> 0.07 | CF12: Forecast = organic growth + acquired growth (+ outlook calibration Δ in Q4/26E, zero unless a FY26 target is entered). | CN12: FY26 net sales target ($m) | CR12: Blank by default (HEICO Q3-26 release: qualitative outlook only — net sales growth at both segments for the remainder of FY26).
B13: Organic net sales growth % (company-reported; forecast = scenario lever FSG_org) | C13: 0.14 | D13: 0.21 | E13: 0.1 | H13: 0.21 | I13: 0.04 | K13: 0.07 | L13: 0.17 | M13: 0.14 | N13: 0.09 | O13: 0.19 | P13: 0.15 | Q13: 0.02 | R13: 0.03 | S13: 0.09 | T13: -0.01 | U13: -0.03 | X13: -0.01 | Y13: 0.01 | Z13: 0.04 | AA13: 0.04 | AB13: 0.04 | AC13: 0.03 | AD13: 0.08 | AE13: 0.05 | AF13: 0.06 | AG13: 0.02 | AH13: 0.05 | AI13: 0.04 | AJ13: 0.05 | AK13: 0.1 | AL13: 0.13 | AM13: 0.08 | AN13: 0.13 | AO13: 0.15 | AP13: 0.12 | AQ13: 0.12 | AR13: 0.13 | AS13: 0.04 | AZ13: 0.32 | BA13: 0.28 | BC13: 0.3 | BD13: 0.23 | BE13: 0.25 | BF13: 0.22 | BG13: 0.25 | BH13: 0.25 | BI13: 0.2 | BJ13: 0.19 | BK13: 0.2 | BL13: 0.21 | BM13: 0.12 | BN13: 0.12 | BO13: 0.15 | BP13: 0.12 | BQ13: 0.13 | BR13: 0.13 | BS13: 0.14 | BT13: 0.13 | BU13: 0.16 | BV13: 0.14 | BW13: 0.12 | BX13: 0.19 | BY13: 0.12 | BZ13: 0.12 | CB13: =CHOOSE(MATCH($CF$2,{"Bull","Base","Bear"},0),$CO$20,$CP$20,$CQ$20) -> 0.09 | CC13: =CHOOSE(MATCH($CF$2,{"Bull","Base","Bear"},0),$CO$21,$CP$21,$CQ$21) -> 0.08 | CD13: =CHOOSE(MATCH($CF$2,{"Bull","Base","Bear"},0),$CO$22,$CP$22,$CQ$22) -> 0.07 | CE13: =CHOOSE(MATCH($CF$2,{"Bull","Base","Bear"},0),$CO$23,$CP$23,$CQ$23) -> 0.07 | CF13: Q4/26E input: FSG organic +12% in Q3/26 and +15% in 9M/26 (Q3-26 release). 2027E+: scenario lever. | CN13: FY26 Adjusted EBITDA target ($m)
B14: Acquired growth % (total y/y − organic; forecast = input, deals closed to date) | C14: =IF(AND(ISNUMBER(C12),ISNUMBER(C13)),C12-C13,"") | D14: =IF(AND(ISNUMBER(D12),ISNUMBER(D13)),D12-D13,"") -> 0.17468558 | E14: =IF(AND(ISNUMBER(E12),ISNUMBER(E13)),E12-E13,"") -> 0.037789748 | F14: =IF(AND(ISNUMBER(F12),ISNUMBER(F13)),F12-F13,"") | G14: =IF(AND(ISNUMBER(G12),ISNUMBER(G13)),G12-G13,"") | H14: =IF(AND(ISNUMBER(H12),ISNUMBER(H13)),H12-H13,"") -> 0.09854859 | I14: =IF(AND(ISNUMBER(I12),ISNUMBER(I13)),I12-I13,"") -> 0.017012805 | J14: =IF(AND(ISNUMBER(J12),ISNUMBER(J13)),J12-J13,"") | ... BY14: =IF(AND(ISNUMBER(BY12),ISNUMBER(BY13)),BY12-BY13,"") -> 0.060826027 | BZ14: 0.06 | CB14: 0.02 | CC14: 0 | CD14: 0 | CE14: 0 | CF14: Q4/26E: Q3/26 acquired contribution (+6pp: Ethos Feb-26, Sherwood Apr-26 and other FY26 deals). 2027E: annualisation of FY26 deals (+2pp). Future deals sit in the M&A lever.
B15: Operating income (segment) | C15: 46.84 | D15: 67.408 | E15: 81.184 | F15: 60.003 | G15: 67.896 | H15: 95.001 | I15: 103.943 | J15: 24.245 | K15: 30.296 | L15: 32.649 | M15: 34.868 | N15: 122.058 | O15: 32.203 | P15: 36.886 | Q15: 34.234 | R15: 33.157 | S15: 136.48 | T15: 30.703 | U15: 37.545 | V15: 39.25 | W15: 42.3 | X15: 149.798 | Y15: 35.48 | Z15: 41.308 | AA15: 41.969 | AB15: 44.67 | AC15: 163.427 | AD15: 41.363 | AE15: 44.744 | AF15: 46.664 | AG15: 46.507 | AH15: 179.278 | AI15: 45.869 | AJ15: 51.488 | AK15: 54.712 | AL15: 54.554 | AM15: 206.623 | AN15: 52.88 | AO15: 62.166 | AP15: 64.797 | AQ15: 62.186 | AR15: 242.029 | AS15: 62.045 | AT15: 47.531 | AU15: 12.021 | AV15: 21.454 | AW15: 143.051 | AX15: 25.822 | AY15: 35.476 | AZ15: 42.059 | BA15: 48.573 | BB15: 151.93 | BC15: 52.376 | BD15: 66.197 | BE15: 70.756 | BF15: 77.838 | BG15: 267.167 | BH15: 83.609 | BI15: 99.912 | BJ15: 89.172 | BK15: 114.604 | BL15: 387.297 | BM15: 136.091 | BN15: 148.876 | BO15: 153.594 | BP15: 154.513 | BQ15: 593.074 | BR15: 166.116 | BS15: 184.98 | BT15: 198.326 | BU15: 200.973 | BV15: 750.395 | BW15: 200.733 | BX15: 243.064 | BY15: 245.299 | BZ15: =BZ11*BZ17 -> 251.73431 | CA15: =SUM(BW15,BX15,BY15,BZ15) -> 940.83031 | CB15: =CB11*CB17 -> 1042.1304 | CC15: =CC11*CC17 -> 1147.5694 | CD15: =CD11*CD17 -> 1227.8993 | CE15: =CE11*CE17 -> 1313.8522 | CH15: =IFERROR((CE15/BV15)^(1/5)-1,"n/m") -> 0.11853948 | CI15: =IFERROR((BV15/AW15)^(1/5)-1,"n/m") -> 0.39302787 | CJ15: =IFERROR((BV15/X15)^(1/10)-1,"n/m") -> 0.1748391 | CK15: =IFERROR((BV15/C15)^(1/19)-1,"n/m") -> 0.1571878 | CN15: Capital allocation (all cases unless stated)
B16: Operating margin before outlook calibration % (Q4/26E helper) | BZ16: =BU15/BU11+(SUM(BW15,BX15,BY15)/SUM(BW11,BX11,BY11)-SUM(BR15,BS15,BT15)/SUM(BR11,BS11,BT11)) -> 0.25568231 | CF16: Q4/25 margin + 9M/26 vs 9M/25 margin change (run-rate drift). | CN16: (see MINLEV block below for the buyback floor)
B17: Operating margin % | C17: =IF(AND(ISNUMBER(C15),ISNUMBER(C11)),IFERROR(C15/C11,""),"") -> 0.16894195 | D17: =IF(AND(ISNUMBER(D15),ISNUMBER(D11)),IFERROR(D15/D11,""),"") -> 0.17558236 | E17: =IF(AND(ISNUMBER(E15),ISNUMBER(E11)),IFERROR(E15/E11,""),"") -> 0.18585655 | F17: =IF(AND(ISNUMBER(F15),ISNUMBER(F11)),IFERROR(F15/F11,""),"") -> 0.15174383 | G17: =IF(AND(ISNUMBER(G15),ISNUMBER(G11)),IFERROR(G15/G11,""),"") -> 0.16466143 | H17: =IF(AND(ISNUMBER(H15),ISNUMBER(H11)),IFERROR(H15/H11,""),"") -> 0.17607026 | I17: =IF(AND(ISNUMBER(I15),ISNUMBER(I11)),IFERROR(I15/I11,""),"") -> 0.18225222 | J17: =IF(AND(ISNUMBER(J15),ISNUMBER(J11)),IFERROR(J15/J11,""),"") -> 0.17442697 | ... BY17: =IF(AND(ISNUMBER(BY15),ISNUMBER(BY11)),IFERROR(BY15/BY11,""),"") -> 0.258808 | BZ17: =BZ16+BZ86 -> 0.25568231 | CA17: =IF(AND(ISNUMBER(CA15),ISNUMBER(CA11)),IFERROR(CA15/CA11,""),"") -> 0.25553619 | CB17: =CHOOSE(MATCH($CF$2,{"Bull","Base","Bear"},0),$CO$26,$CP$26,$CQ$26) -> 0.255 | CC17: =CHOOSE(MATCH($CF$2,{"Bull","Base","Bear"},0),$CO$27,$CP$27,$CQ$27) -> 0.26 | CD17: =CHOOSE(MATCH($CF$2,{"Bull","Base","Bear"},0),$CO$28,$CP$28,$CQ$28) -> 0.26 | CE17: =CHOOSE(MATCH($CF$2,{"Bull","Base","Bear"},0),$CO$29,$CP$29,$CQ$29) -> 0.26 | CF17: Q4/26E: helper + outlook calibration Δ (zero unless a target is set). 2027E+: scenario lever FSG_OM. | CH17: =IFERROR(AVERAGE(CA17,CB17,CC17,CD17,CE17),"n/m") -> 0.25810724 | CI17: =IFERROR(AVERAGE(BB17,BG17,BL17,BQ17,BV17),"n/m") -> 0.21218784 | CJ17: =IFERROR(AVERAGE(AC17,AH17,AM17,AR17,AW17,BB17,BG17,BL17,BQ17,BV17),"n/m") -> 0.19708491 | CK17: =IFERROR(AVERAGE(C17,D17,E17,F17,G17,H17,I17,N17,S17,X17,AC17,AH17,AM17,AR17,AW17,BB17,BG17,BL17,BQ17,BV17),"n/m") -> 0.18616933 | CN17: Q4/26E share repurchases ($m) | CO17: 0 | CP17: 0 | CQ17: 0 | CR17: HEICO does not run an open-market buyback; zero in all cases.
B18: Depreciation & amortization (segment) | C18: 6.822 | D18: 8.047 | E18: 9.339 | F18: 9.801 | G18: 9.899 | H18: 10.661 | I18: 10.451 | J18: 2.835 | K18: 2.868 | L18: 4.069 | M18: 4.842 | N18: 14.614 | O18: 4.92 | P18: 4.943 | Q18: 5.02 | R18: 4.96 | S18: 19.843 | U18: 6.349 | V18: 6.402 | X18: 24.329 | Y18: 7.078 | Z18: 7.091 | AA18: 7.218 | AB18: 7.316 | AC18: 28.703 | AD18: 7.252 | AE18: 7.227 | AF18: 8.263 | AG18: 8.326 | AH18: 31.068 | AI18: 8.239 | AJ18: 8.222 | AK18: 8.087 | AL18: 8.304 | AM18: 32.852 | AN18: 8.158 | AO18: 8.323 | AP18: 8.458 | AQ18: 8.478 | AR18: 33.417 | AS18: 8.476 | AT18: 8.38 | AU18: 8.699 | AV18: 8.741 | AW18: 34.296 | AX18: 8.586 | AY18: 8.35 | AZ18: 8.259 | BA18: 9.445 | BB18: 34.64 | BC18: 9.231 | BD18: 9.442 | BE18: 10.363 | BF18: 10.888 | BG18: 39.924 | BH18: 10.909 | BI18: 10.529 | BJ18: 10.215 | BK18: 24.003 | BL18: 55.656 | BM18: 24.344 | BN18: 23.889 | BO18: 25.305 | BP18: 25.255 | BQ18: 98.793 | BR18: 25.832 | BS18: 28.449 | BT18: 28.581 | BU18: 27.838 | BV18: 110.7 | BW18: 27.875 | BX18: 29.891 | BY18: 32.457
B19: Segment EBITDA (operating income + D&A) | C19: =IF(AND(ISNUMBER(C15),ISNUMBER(C18)),C15+C18,"") -> 53.662 | D19: =IF(AND(ISNUMBER(D15),ISNUMBER(D18)),D15+D18,"") -> 75.455 | E19: =IF(AND(ISNUMBER(E15),ISNUMBER(E18)),E15+E18,"") -> 90.523 | F19: =IF(AND(ISNUMBER(F15),ISNUMBER(F18)),F15+F18,"") -> 69.804 | G19: =IF(AND(ISNUMBER(G15),ISNUMBER(G18)),G15+G18,"") -> 77.795 | H19: =IF(AND(ISNUMBER(H15),ISNUMBER(H18)),H15+H18,"") -> 105.662 | I19: =IF(AND(ISNUMBER(I15),ISNUMBER(I18)),I15+I18,"") -> 114.394 | J19: =IF(AND(ISNUMBER(J15),ISNUMBER(J18)),J15+J18,"") -> 27.08 | ... BY19: =IF(AND(ISNUMBER(BY15),ISNUMBER(BY18)),BY15+BY18,"") -> 277.756 | CN19: FSG_org (FSG organic net sales growth y/y) | CO19: 0.03 | CP19: Δ → | CQ19: -0.03 | CR19: FSG organic growth: FY25 ~13%, 9M/26 15% (commercial aftermarket, PMA share gains, defense). Base fades toward high-single digits.
B20: Segment EBITDA margin % | C20: =IF(AND(ISNUMBER(C19),ISNUMBER(C11)),IFERROR(C19/C11,""),"") -> 0.19354746 | D20: =IF(AND(ISNUMBER(D19),ISNUMBER(D11)),IFERROR(D19/D11,""),"") -> 0.19654295 | E20: =IF(AND(ISNUMBER(E19),ISNUMBER(E11)),IFERROR(E19/E11,""),"") -> 0.20723656 | F20: =IF(AND(ISNUMBER(F19),ISNUMBER(F11)),IFERROR(F19/F11,""),"") -> 0.17652994 | G20: =IF(AND(ISNUMBER(G19),ISNUMBER(G11)),IFERROR(G19/G11,""),"") -> 0.18866849 | H20: =IF(AND(ISNUMBER(H19),ISNUMBER(H11)),IFERROR(H19/H11,""),"") -> 0.19582885 | I20: =IF(AND(ISNUMBER(I19),ISNUMBER(I11)),IFERROR(I19/I11,""),"") -> 0.20057686 | J20: =IF(AND(ISNUMBER(J19),ISNUMBER(J11)),IFERROR(J19/J11,""),"") -> 0.19482295 | ... BY20: =IF(AND(ISNUMBER(BY19),ISNUMBER(BY11)),IFERROR(BY19/BY11,""),"") -> 0.29305246 | CN20: 2027E | CO20: =CP20+$CO$19 -> 0.12 | CP20: 0.09 | CQ20: =CP20+$CQ$19 -> 0.06
B21: Capital expenditures (segment) | C21: 8.189 | D21: 10.146 | E21: 10.735 | F21: 8.518 | G21: 7.343 | H21: 6.866 | I21: 7.045 | J21: 2.387 | K21: 2.911 | L21: 2.435 | M21: 2.457 | N21: 10.19 | O21: 2.025 | P21: 2.231 | Q21: 3.083 | R21: 2.098 | S21: 9.437 | U21: 3.863 | V21: 2.523 | X21: 11.737 | Y21: 3.705 | Z21: 4.71 | AA21: 5.034 | AB21: 4.985 | AC21: 18.434 | AD21: 3.872 | AE21: 4.688 | AF21: 3.745 | AG21: 3.36 | AH21: 15.665 | AI21: 2.297 | AJ21: 3.909 | AK21: 3.504 | AL21: 3.364 | AM21: 13.074 | AN21: 2.849 | AO21: 3.727 | AP21: 6.024 | AQ21: 4.436 | AR21: 17.036 | AS21: 4.118 | AT21: 2.647 | AU21: 1.624 | AV21: 2.454 | AW21: 10.843 | AX21: 1.988 | AY21: 2.105 | AZ21: 1.792 | BA21: 3.03 | BB21: 8.915 | BC21: 3.582 | BD21: 4.531 | BE21: 3.971 | BF21: 3.504 | BG21: 15.588 | BH21: 6.653 | BI21: 3.99 | BJ21: 4.791 | BK21: 7.341 | BL21: 22.775 | BM21: 6.732 | BN21: 5.982 | BO21: 7.925 | BP21: 6.859 | BQ21: 27.498 | BR21: 10.246 | BS21: 8.768 | BT21: 7.224 | BU21: 6.104 | BV21: 32.342 | BW21: 5.552 | BX21: 7.979 | BY21: 6.864 | CN21: 2028E | CO21: =CP21+$CO$19 -> 0.11 | CP21: 0.08 | CQ21: =CP21+$CQ$19 -> 0.05
B22: Memo: product line — Aftermarket replacement parts | S22: 327.416 | X22: 356.07 | AC22: 405.108 | AH22: 489.644 | AI22: 134.288 | AJ22: 139.567 | AK22: 150.729 | AL22: 157.978 | AM22: 582.562 | AN22: 159.497 | AO22: 167.225 | AP22: 173.992 | AQ22: 177.287 | AR22: 678.001 | AS22: 168.267 | AT22: 141.192 | AU22: 102.629 | AV22: 113.548 | AW22: 525.636 | AX22: 118.434 | AY22: 135.894 | AZ22: 136.357 | BA22: 144.532 | BB22: 535.217 | BC22: 150.901 | BD22: 173.981 | BE22: 187.453 | BF22: 182.565 | BG22: 694.9 | BH22: 208.643 | BI22: 218.343 | BJ22: 238.95 | BK22: 374.566 | BL22: 1040.502 | BM22: 395.154 | BN22: 403.725 | BO22: 432.699 | BP22: 426.853 | BQ22: 1658.431 | BR22: 456.028 | BS22: 469.962 | BT22: 486.296 | BU22: 510.037 | BV22: 1922.323 | BW22: 513.861 | BX22: 570.327 | BY22: 556.277 | CN22: 2029E | CO22: =CP22+$CO$19 -> 0.1 | CP22: 0.07 | CQ22: =CP22+$CQ$19 -> 0.04
B23: Memo: product line — Repair & overhaul parts and services | S23: 253.717 | X23: 258.952 | AC23: 251.357 | AH23: 270.482 | AI23: 68.324 | AJ23: 71.756 | AK23: 74.853 | AL23: 71.521 | AM23: 286.454 | AN23: 67.163 | AO23: 73.454 | AP23: 76.27 | AQ23: 82.436 | AR23: 299.323 | AS23: 69.287 | AT23: 52.629 | AU23: 32.601 | AV23: 38.647 | AW23: 193.164 | AX23: 42.412 | AY23: 50.706 | AZ23: 54.591 | BA23: 60.506 | BB23: 208.215 | BC23: 62.487 | BD23: 65.046 | BE23: 66.44 | BF23: 71.013 | BG23: 264.986 | BH23: 71.15 | BI23: 77.851 | BJ23: 80.924 | BK23: 136.641 | BL23: 366.566 | BM23: 135.582 | BN23: 148.181 | BO23: 149.895 | BP23: 159.579 | BQ23: 593.237 | BR23: 155.449 | BS23: 186.656 | BT23: 201.261 | BU23: 205.483 | BV23: 748.849 | BW23: 196.654 | BX23: 225.875 | BY23: 248.603 | CN23: 2030E | CO23: =CP23+$CO$19 -> 0.1 | CP23: 0.07 | CQ23: =CP23+$CQ$19 -> 0.04
B24: Memo: product line — Specialty products | S24: 181.668 | X24: 194.678 | AC24: 219.405 | AH24: 207.414 | AI24: 52.109 | AJ24: 56.513 | AK24: 59.544 | AL24: 60.755 | AM24: 228.921 | AN24: 60.553 | AO24: 67.572 | AP24: 69.754 | AQ24: 64.98 | AR24: 262.859 | AS24: 63.513 | AT24: 58.143 | AU24: 42.928 | AV24: 41.428 | AW24: 206.012 | AX24: 38.488 | AY24: 43.68 | AZ24: 46.17 | BA24: 55.319 | BB24: 183.657 | BC24: 59.293 | BD24: 67.286 | BE24: 76.366 | BF24: 92.381 | BG24: 295.326 | BH24: 91.485 | BI24: 96.008 | BJ24: 85.166 | BK24: 90.458 | BL24: 363.117 | BM24: 87.98 | BN24: 95.326 | BO24: 99.032 | BP24: 105.348 | BQ24: 387.686 | BR24: 101.697 | BS24: 110.452 | BT24: 115.104 | BU24: 118.852 | BV24: 446.105 | BW24: 109.485 | BX24: 133.225 | BY24: 142.923
B25: Memo: end market — Aerospace | AH25: 781.344 | AI25: 209.591 | AJ25: 220.083 | AK25: 230.633 | AL25: 229.752 | AM25: 890.059 | AN25: 235.173 | AO25: 249.225 | AP25: 258.157 | AQ25: 261.533 | AR25: 1004.088 | AS25: 239.923 | AT25: 188.655 | AU25: 114.627 | AV25: 125.989 | AW25: 669.194 | AX25: 135.056 | AY25: 163.026 | AZ25: 175.388 | BA25: 187.397 | BB25: 660.867 | BC25: 202.405 | BD25: 215.319 | BE25: 219.558 | BF25: 238.972 | BG25: 876.254 | BH25: 254.54 | BI25: 269.353 | BJ25: 288.069 | BK25: 445.688 | BL25: 1257.65 | BM25: 461.241 | BN25: 478.349 | BO25: 499.917 | BP25: 521.198 | BQ25: 1960.705 | BR25: 533.621 | BS25: 572.7 | BT25: 615.053 | BU25: 647.881 | BV25: 2369.255 | BW25: 626.472 | BX25: 675.013 | BY25: 668.382 | CN25: FSG_OM (FSG operating margin) | CO25: 0.015 | CP25: Δ → | CQ25: -0.015 | CR25: FSG operating margin: FY25 24.1%, 9M/26 25.6%; Wencor amortization rolling off supports modest expansion.
B26: Memo: end market — Defense & space | AH26: 146.708 | AI26: 34.782 | AJ26: 36.312 | AK26: 43.009 | AL26: 49.227 | AM26: 163.33 | AN26: 41.534 | AO26: 45.969 | AP26: 49.769 | AQ26: 52.804 | AR26: 190.076 | AS26: 50.253 | AT26: 54.142 | AU26: 53.269 | AV26: 55.609 | AW26: 213.273 | AX26: 54.044 | AY26: 56.254 | AZ26: 51.898 | BA26: 62.04 | BB26: 224.236 | BC26: 58.655 | BD26: 77.603 | BE26: 94.756 | BF26: 85.446 | BG26: 316.46 | BH26: 95.642 | BI26: 101.267 | BJ26: 98.777 | BK26: 138.543 | BL26: 434.229 | BM26: 138.772 | BN26: 149.906 | BO26: 161.16 | BP26: 150.968 | BQ26: 600.806 | BR26: 165.889 | BS26: 178.112 | BT26: 172.286 | BU26: 170.578 | BV26: 686.865 | BW26: 179.377 | BX26: 226.399 | BY26: 247.651 | CN26: 2027E | CO26: =CP26+$CO$25 -> 0.27 | CP26: 0.255 | CQ26: =CP26+$CQ$25 -> 0.24
B27: Memo: end market — Other industries | AH27: 39.488 | AI27: 10.348 | AJ27: 11.441 | AK27: 11.484 | AL27: 11.275 | AM27: 44.548 | AN27: 10.506 | AO27: 13.057 | AP27: 12.09 | AQ27: 10.366 | AR27: 46.019 | AS27: 10.891 | AT27: 9.167 | AU27: 10.262 | AV27: 12.025 | AW27: 42.345 | AX27: 10.234 | AY27: 11 | AZ27: 9.832 | BA27: 10.92 | BB27: 41.986 | BC27: 11.621 | BD27: 13.391 | BE27: 15.945 | BF27: 21.541 | BG27: 62.498 | BH27: 21.096 | BI27: 21.582 | BJ27: 18.194 | BK27: 17.434 | BL27: 78.306 | BM27: 18.703 | BN27: 18.977 | BO27: 20.549 | BP27: 19.614 | BQ27: 77.843 | BR27: 13.664 | BS27: 16.258 | BT27: 15.322 | BU27: 15.913 | BV27: 61.157 | BW27: 14.151 | BX27: 28.015 | BY27: 31.77 | CN27: 2028E | CO27: =CP27+$CO$25 -> 0.275 | CP27: 0.26 | CQ27: =CP27+$CQ$25 -> 0.245
CN28: 2029E | CO28: =CP28+$CO$25 -> 0.275 | CP28: 0.26 | CQ28: =CP28+$CQ$25 -> 0.245
B29: Electronic Technologies Group (ETG) — electronic components for defense, space, aerospace, medical, telecom & other markets | CF29: ETG — modelling logic | CN29: 2030E | CO29: =CP29+$CO$25 -> 0.275 | CP29: 0.26 | CQ29: =CP29+$CQ$25 -> 0.245
B30: Net sales (incl. intersegment sales) | C30: 115.021 | D30: 124.035 | E30: 146.044 | F30: 143.372 | G30: 205.648 | H30: 227.771 | I30: 331.598 | J30: 78.841 | K30: 83.937 | L30: 87.401 | M30: 99.854 | N30: 350.033 | O30: 87.492 | P30: 89.741 | Q30: 102.065 | R30: 100.106 | S30: 379.404 | T30: 89.221 | U30: 90.995 | V30: 97.223 | W30: 113.543 | X30: 390.982 | Y30: 104.152 | Z30: 132.566 | AA30: 136.215 | AB30: 138.339 | AC30: 511.272 | AD30: 126.165 | AE30: 141.169 | AF30: 137.86 | AG30: 169.067 | AH30: 574.261 | AI30: 155.658 | AJ30: 168.722 | AK30: 186.37 | AL30: 191.077 | AM30: 701.827 | AN30: 184.429 | AO30: 214.451 | AP30: 216.129 | AQ30: 219.513 | AR30: 834.522 | AS30: 208.411 | AT30: 218.955 | AU30: 210.919 | AV30: 236.702 | AW30: 874.987 | AX30: 223.55 | AY30: 243.089 | AZ30: 239.543 | BA30: 252.988 | BB30: 959.17 | BC30: 222.336 | BD30: 237.393 | BE30: 244.203 | BF30: 268.543 | BG30: 972.475 | BH30: 255.059 | BI30: 301.759 | BJ30: 325.867 | BK30: 342.537 | BL30: 1225.222 | BM30: 285.942 | BN30: 319.322 | BO30: 322.129 | BP30: 336.233 | BQ30: 1263.626 | BR30: 330.315 | BS30: 342.167 | BT30: 355.863 | BU30: 384.775 | BV30: 1413.12 | BW30: 370.675 | BX30: 459.532 | BY30: 483.487 | BZ30: =BU30*(1+BZ31) -> 507.903 | CA30: =SUM(BW30,BX30,BY30,BZ30) -> 1821.597 | CB30: =CA30*(1+CB31) -> 2076.6206 | CC30: =CB30*(1+CC31) -> 2221.984 | CD30: =CC30*(1+CD31) -> 2366.413 | CE30: =CD30*(1+CE31) -> 2520.2298 | CF30: Q4/26E: Q4/25 × (1 + organic + acquired growth + outlook calibration Δ). 2027E+: prior year × (1 + organic lever + acquired growth input). | CH30: =IFERROR((CE30/BV30)^(1/5)-1,"n/m") -> 0.12267027 | CI30: =IFERROR((BV30/AW30)^(1/5)-1,"n/m") -> 0.10061515 | CJ30: =IFERROR((BV30/X30)^(1/10)-1,"n/m") -> 0.13710934 | CK30: =IFERROR((BV30/C30)^(1/19)-1,"n/m") -> 0.14113478
B31: Net sales y/y % | D31: =IF(AND(ISNUMBER(D30),ISNUMBER(C30)),IFERROR(D30/C30-1,""),"") -> 0.078368298 | E31: =IF(AND(ISNUMBER(E30),ISNUMBER(D30)),IFERROR(E30/D30-1,""),"") -> 0.17744185 | F31: =IF(AND(ISNUMBER(F30),ISNUMBER(E30)),IFERROR(F30/E30-1,""),"") -> -0.018295856 | G31: =IF(AND(ISNUMBER(G30),ISNUMBER(F30)),IFERROR(G30/F30-1,""),"") -> 0.43436654 | H31: =IF(AND(ISNUMBER(H30),ISNUMBER(G30)),IFERROR(H30/G30-1,""),"") -> 0.10757702 | I31: =IF(AND(ISNUMBER(I30),ISNUMBER(H30)),IFERROR(I30/H30-1,""),"") -> 0.45583942 | N31: =IF(AND(ISNUMBER(N30),ISNUMBER(I30)),IFERROR(N30/I30-1,""),"") -> 0.055594425 | O31: =IF(AND(ISNUMBER(O30),ISNUMBER(J30)),IFERROR(O30/J30-1,""),"") -> 0.10972717 | P31: =IF(AND(ISNUMBER(P30),ISNUMBER(K30)),IFERROR(P30/K30-1,""),"") -> 0.069147098 | Q31: =IF(AND(ISNUMBER(Q30),ISNUMBER(L30)),IFERROR(Q30/L30-1,""),"") -> 0.1677784 | R31: =IF(AND(ISNUMBER(R30),ISNUMBER(M30)),IFERROR(R30/M30-1,""),"") -> 0.0025236846 | S31: =IF(AND(ISNUMBER(S30),ISNUMBER(N30)),IFERROR(S30/N30-1,""),"") -> 0.083909231 | T31: =IF(AND(ISNUMBER(T30),ISNUMBER(O30)),IFERROR(T30/O30-1,""),"") -> 0.019761807 | U31: =IF(AND(ISNUMBER(U30),ISNUMBER(P30)),IFERROR(U30/P30-1,""),"") -> 0.013973546 | ... BY31: =IF(AND(ISNUMBER(BY30),ISNUMBER(BT30)),IFERROR(BY30/BT30-1,""),"") -> 0.3586324 | BZ31: =BZ32+BZ33+BZ82 -> 0.32 | CA31: =IF(AND(ISNUMBER(CA30),ISNUMBER(BV30)),IFERROR(CA30/BV30-1,""),"") -> 0.28906038 | CB31: =CB32+CB33 -> 0.14 | CC31: =CC32+CC33 -> 0.07 | CD31: =CD32+CD33 -> 0.065 | CE31: =CE32+CE33 -> 0.065 | CF31: Forecast = organic growth + acquired growth (+ outlook calibration Δ in Q4/26E, zero unless a FY26 target is entered). | CN31: ETG_org (ETG organic net sales growth y/y) | CO31: 0.03 | CP31: Δ → | CQ31: -0.03 | CR31: ETG organic growth: FY25 ~11%, 9M/26 14% (defense, space, other electronics; lumpier, backlog-driven).
B32: Organic net sales growth % (company-reported; forecast = scenario lever ETG_org) | C32: 0.08 | D32: 0.05 | E32: 0.09 | G32: 0.12 | H32: 0.1 | I32: 0.07 | K32: 0.09 | L32: 0.01 | M32: 0.02 | N32: 0.03 | O32: 0.01 | P32: 0.02 | Q32: 0.09 | S32: 0.02 | T32: 0.02 | U32: 0.01 | W32: 0.05 | X32: 0.01 | Y32: 0.04 | Z32: 0.12 | AA32: 0.01 | AC32: 0.04 | AD32: 0.08 | AE32: 0.05 | AG32: 0.14 | AH32: 0.07 | AI32: 0.06 | AK32: 0.16 | AL32: 0.03 | AM32: 0.06 | AN32: 0.12 | AO32: 0.2 | AP32: 0.07 | AQ32: 0.04 | AR32: 0.1 | AS32: 0.06 | AT32: -0.02 | AU32: -0.06 | AW32: -0.01 | AY32: 0.03 | AZ32: 0.05 | BA32: 0.05 | BB32: 0.03 | BE32: 0.01 | BH32: 0 | BJ32: 0.02 | BK32: 0.06 | BL32: 0.01 | BN32: 0.04 | BR32: 0.11 | BS32: 0.04 | BT32: 0.07 | BU32: 0.07 | BV32: 0.07 | BW32: 0.06 | BX32: 0.17 | BY32: 0.18 | BZ32: 0.14 | CB32: =CHOOSE(MATCH($CF$2,{"Bull","Base","Bear"},0),$CO$32,$CP$32,$CQ$32) -> 0.08 | CC32: =CHOOSE(MATCH($CF$2,{"Bull","Base","Bear"},0),$CO$33,$CP$33,$CQ$33) -> 0.07 | CD32: =CHOOSE(MATCH($CF$2,{"Bull","Base","Bear"},0),$CO$34,$CP$34,$CQ$34) -> 0.065 | CE32: =CHOOSE(MATCH($CF$2,{"Bull","Base","Bear"},0),$CO$35,$CP$35,$CQ$35) -> 0.065 | CF32: Q4/26E input: ETG organic +18% in Q3/26 and +14% in 9M/26 (Q3-26 release). 2027E+: scenario lever. | CN32: 2027E | CO32: =CP32+$CO$31 -> 0.11 | CP32: 0.08 | CQ32: =CP32+$CQ$31 -> 0.05
B33: Acquired growth % (total y/y − organic; forecast = input, deals closed to date) | C33: =IF(AND(ISNUMBER(C31),ISNUMBER(C32)),C31-C32,"") | D33: =IF(AND(ISNUMBER(D31),ISNUMBER(D32)),D31-D32,"") -> 0.028368298 | E33: =IF(AND(ISNUMBER(E31),ISNUMBER(E32)),E31-E32,"") -> 0.087441851 | F33: =IF(AND(ISNUMBER(F31),ISNUMBER(F32)),F31-F32,"") | G33: =IF(AND(ISNUMBER(G31),ISNUMBER(G32)),G31-G32,"") -> 0.31436654 | H33: =IF(AND(ISNUMBER(H31),ISNUMBER(H32)),H31-H32,"") -> 0.0075770248 | I33: =IF(AND(ISNUMBER(I31),ISNUMBER(I32)),I31-I32,"") -> 0.38583942 | J33: =IF(AND(ISNUMBER(J31),ISNUMBER(J32)),J31-J32,"") | ... BY33: =IF(AND(ISNUMBER(BY31),ISNUMBER(BY32)),BY31-BY32,"") -> 0.1786324 | BZ33: 0.18 | CB33: 0.06 | CC33: 0 | CD33: 0 | CE33: 0 | CF33: Q4/26E: Q3/26 acquired contribution (+18pp: Rockmart Jan-26 and other FY25–26 deals). 2027E: annualisation (+6pp). Future deals sit in the M&A lever. | CN33: 2028E | CO33: =CP33+$CO$31 -> 0.1 | CP33: 0.07 | CQ33: =CP33+$CQ$31 -> 0.04
B34: Operating income (segment) | C34: 34.026 | D34: 33.87 | E34: 38.775 | F34: 39.981 | G34: 56.126 | H34: 59.465 | I34: 77.438 | J34: 15.546 | K34: 20.249 | L34: 21.516 | M34: 25.752 | N34: 83.063 | O34: 22.904 | P34: 18.136 | Q34: 21.455 | R34: 26.419 | S34: 88.914 | T34: 19.418 | U34: 22.206 | V34: 24.372 | W34: 32.837 | X34: 98.833 | Y34: 22.269 | Z34: 33.402 | AA34: 33.609 | AB34: 36.751 | AC34: 126.031 | AD34: 29.084 | AE34: 38.826 | AF34: 38.543 | AG34: 50.998 | AH34: 157.451 | AI34: 43.22 | AJ34: 48.13 | AK34: 56.021 | AL34: 57.137 | AM34: 204.508 | AN34: 51.602 | AO34: 67.352 | AP34: 62.206 | AQ34: 64.583 | AR34: 245.743 | AS34: 57.491 | AT34: 65.526 | AU34: 61.931 | AV34: 73.866 | AW34: 258.814 | AX34: 60.128 | AY34: 71.294 | AZ34: 68.997 | BA34: 76.887 | BB34: 277.306 | BC34: 55.588 | BD34: 65.988 | BE34: 68.029 | BF34: 79.868 | BG34: 269.473 | BH34: 56.537 | BI34: 67.979 | BJ34: 74.157 | BK34: 86.38 | BL34: 285.053 | BM34: 55.328 | BN34: 75.263 | BO34: 75.788 | BP34: 81.814 | BQ34: 288.193 | BR34: 76.456 | BS34: 77.88 | BT34: 80.998 | BU34: 89.618 | BV34: 324.952 | BW34: 73.246 | BX34: 121.809 | BY34: 125.565 | BZ34: =BZ30*BZ36 -> 126.02226 | CA34: =SUM(BW34,BX34,BY34,BZ34) -> 446.64226 | CB34: =CB30*CB36 -> 519.15514 | CC34: =CC30*CC36 -> 566.60593 | CD34: =CD30*CD36 -> 603.43531 | CE34: =CE30*CE36 -> 642.65861 | CH34: =IFERROR((CE34/BV34)^(1/5)-1,"n/m") -> 0.14612563 | CI34: =IFERROR((BV34/AW34)^(1/5)-1,"n/m") -> 0.046565201 | CJ34: =IFERROR((BV34/X34)^(1/10)-1,"n/m") -> 0.12639762 | CK34: =IFERROR((BV34/C34)^(1/19)-1,"n/m") -> 0.12610629 | CN34: 2029E | CO34: =CP34+$CO$31 -> 0.095 | CP34: 0.065 | CQ34: =CP34+$CQ$31 -> 0.035
B35: Operating margin before outlook calibration % (Q4/26E helper) | BZ35: =BU34/BU30+(SUM(BW34,BX34,BY34)/SUM(BW30,BX30,BY30)-SUM(BR34,BS34,BT34)/SUM(BR30,BS30,BT30)) -> 0.2481227 | CF35: Q4/25 margin + 9M/26 vs 9M/25 margin change (run-rate drift). | CN35: 2030E | CO35: =CP35+$CO$31 -> 0.095 | CP35: 0.065 | CQ35: =CP35+$CQ$31 -> 0.035
B36: Operating margin % | C36: =IF(AND(ISNUMBER(C34),ISNUMBER(C30)),IFERROR(C34/C30,""),"") -> 0.29582424 | D36: =IF(AND(ISNUMBER(D34),ISNUMBER(D30)),IFERROR(D34/D30,""),"") -> 0.27306809 | E36: =IF(AND(ISNUMBER(E34),ISNUMBER(E30)),IFERROR(E34/E30,""),"") -> 0.26550218 | F36: =IF(AND(ISNUMBER(F34),ISNUMBER(F30)),IFERROR(F34/F30,""),"") -> 0.27886198 | G36: =IF(AND(ISNUMBER(G34),ISNUMBER(G30)),IFERROR(G34/G30,""),"") -> 0.27292266 | H36: =IF(AND(ISNUMBER(H34),ISNUMBER(H30)),IFERROR(H34/H30,""),"") -> 0.26107362 | I36: =IF(AND(ISNUMBER(I34),ISNUMBER(I30)),IFERROR(I34/I30,""),"") -> 0.23352976 | J36: =IF(AND(ISNUMBER(J34),ISNUMBER(J30)),IFERROR(J34/J30,""),"") -> 0.19718167 | ... BY36: =IF(AND(ISNUMBER(BY34),ISNUMBER(BY30)),IFERROR(BY34/BY30,""),"") -> 0.25970709 | BZ36: =BZ35+BZ86 -> 0.2481227 | CA36: =IF(AND(ISNUMBER(CA34),ISNUMBER(CA30)),IFERROR(CA34/CA30,""),"") -> 0.24519269 | CB36: =CHOOSE(MATCH($CF$2,{"Bull","Base","Bear"},0),$CO$38,$CP$38,$CQ$38) -> 0.25 | CC36: =CHOOSE(MATCH($CF$2,{"Bull","Base","Bear"},0),$CO$39,$CP$39,$CQ$39) -> 0.255 | CD36: =CHOOSE(MATCH($CF$2,{"Bull","Base","Bear"},0),$CO$40,$CP$40,$CQ$40) -> 0.255 | CE36: =CHOOSE(MATCH($CF$2,{"Bull","Base","Bear"},0),$CO$41,$CP$41,$CQ$41) -> 0.255 | CF36: Q4/26E: helper + outlook calibration Δ (zero unless a target is set). 2027E+: scenario lever ETG_OM. | CH36: =IFERROR(AVERAGE(CA36,CB36,CC36,CD36,CE36),"n/m") -> 0.25203854 | CI36: =IFERROR(AVERAGE(BB36,BG36,BL36,BQ36,BV36),"n/m") -> 0.25137731 | CJ36: =IFERROR(AVERAGE(AC36,AH36,AM36,AR36,AW36,BB36,BG36,BL36,BQ36,BV36),"n/m") -> 0.26592287 | CK36: =IFERROR(AVERAGE(C36,D36,E36,F36,G36,H36,I36,N36,S36,X36,AC36,AH36,AM36,AR36,AW36,BB36,BG36,BL36,BQ36,BV36),"n/m") -> 0.26322225
B37: Depreciation & amortization (segment) | C37: 3.437 | D37: 3.786 | E37: 5.238 | F37: 4.728 | G37: 7.308 | H37: 7.502 | I37: 19.365 | J37: 5.113 | K37: 5.203 | L37: 5.226 | M37: 5.85 | N37: 21.392 | O37: 6.925 | P37: 6.946 | Q37: 6.911 | R37: 6.324 | S37: 27.106 | U37: 5.686 | V37: 5.317 | X37: 22.748 | Y37: 6.622 | Z37: 7.949 | AA37: 7.983 | AB37: 8.14 | AC37: 30.694 | AD37: 7.778 | AE37: 7.794 | AF37: 7.89 | AG37: 9.314 | AH37: 32.776 | AI37: 10.378 | AJ37: 10.473 | AK37: 10.848 | AL37: 10.865 | AM37: 42.564 | AN37: 11.382 | AO37: 11.69 | AP37: 12.183 | AQ37: 12.833 | AR37: 48.088 | AS37: 12.606 | AT37: 12.811 | AU37: 12.748 | AV37: 14.11 | AW37: 52.275 | AX37: 13.897 | AY37: 14.039 | AZ37: 14.109 | BA37: 14.225 | BB37: 56.27 | BC37: 13.458 | BD37: 13.513 | BE37: 12.932 | BF37: 14.389 | BG37: 54.292 | BH37: 15.607 | BI37: 18.656 | BJ37: 18.479 | BK37: 19.032 | BL37: 71.774 | BM37: 18.465 | BN37: 18.245 | BO37: 18.3 | BP37: 18.715 | BQ37: 73.725 | BR37: 19.5 | BS37: 19.537 | BT37: 20.297 | BU37: 22.495 | BV37: 81.829 | BW37: 22.284 | BX37: 25.916 | BY37: 26.634 | CN37: ETG_OM (ETG operating margin) | CO37: 0.015 | CP37: Δ → | CQ37: -0.015 | CR37: ETG operating margin: FY25 23.7%, 9M/26 24.6%.
B38: Segment EBITDA (operating income + D&A) | C38: =IF(AND(ISNUMBER(C34),ISNUMBER(C37)),C34+C37,"") -> 37.463 | D38: =IF(AND(ISNUMBER(D34),ISNUMBER(D37)),D34+D37,"") -> 37.656 | E38: =IF(AND(ISNUMBER(E34),ISNUMBER(E37)),E34+E37,"") -> 44.013 | F38: =IF(AND(ISNUMBER(F34),ISNUMBER(F37)),F34+F37,"") -> 44.709 | G38: =IF(AND(ISNUMBER(G34),ISNUMBER(G37)),G34+G37,"") -> 63.434 | H38: =IF(AND(ISNUMBER(H34),ISNUMBER(H37)),H34+H37,"") -> 66.967 | I38: =IF(AND(ISNUMBER(I34),ISNUMBER(I37)),I34+I37,"") -> 96.803 | J38: =IF(AND(ISNUMBER(J34),ISNUMBER(J37)),J34+J37,"") -> 20.659 | ... BY38: =IF(AND(ISNUMBER(BY34),ISNUMBER(BY37)),BY34+BY37,"") -> 152.199 | CN38: 2027E | CO38: =CP38+$CO$37 -> 0.265 | CP38: 0.25 | CQ38: =CP38+$CQ$37 -> 0.235
B39: Segment EBITDA margin % | C39: =IF(AND(ISNUMBER(C38),ISNUMBER(C30)),IFERROR(C38/C30,""),"") -> 0.32570574 | D39: =IF(AND(ISNUMBER(D38),ISNUMBER(D30)),IFERROR(D38/D30,""),"") -> 0.30359173 | E39: =IF(AND(ISNUMBER(E38),ISNUMBER(E30)),IFERROR(E38/E30,""),"") -> 0.30136808 | F39: =IF(AND(ISNUMBER(F38),ISNUMBER(F30)),IFERROR(F38/F30,""),"") -> 0.31183913 | G39: =IF(AND(ISNUMBER(G38),ISNUMBER(G30)),IFERROR(G38/G30,""),"") -> 0.30845911 | H39: =IF(AND(ISNUMBER(H38),ISNUMBER(H30)),IFERROR(H38/H30,""),"") -> 0.29401021 | I39: =IF(AND(ISNUMBER(I38),ISNUMBER(I30)),IFERROR(I38/I30,""),"") -> 0.29192878 | J39: =IF(AND(ISNUMBER(J38),ISNUMBER(J30)),IFERROR(J38/J30,""),"") -> 0.26203371 | ... BY39: =IF(AND(ISNUMBER(BY38),ISNUMBER(BY30)),IFERROR(BY38/BY30,""),"") -> 0.3147944 | CN39: 2028E | CO39: =CP39+$CO$37 -> 0.27 | CP39: 0.255 | CQ39: =CP39+$CQ$37 -> 0.24
B40: Capital expenditures (segment) | C40: 1.607 | D40: 2.3 | E40: 2.093 | F40: 1.67 | G40: 1.502 | H40: 2.543 | I40: 7.248 | J40: 2.035 | K40: 1.79 | L40: 1.673 | M40: 2.25 | N40: 7.748 | O40: 1.708 | P40: 1.051 | Q40: 1.605 | R40: 1.963 | S40: 6.327 | U40: 1.226 | V40: 1.6 | X40: 6.201 | Y40: 1.683 | Z40: 5.058 | AA40: 2.516 | AB40: 2.705 | AC40: 11.962 | AD40: 2.504 | AE40: 2.33 | AF40: 3.086 | AG40: 2.18 | AH40: 10.1 | AI40: 1.743 | AJ40: 2.242 | AK40: 2.937 | AL40: 2.609 | AM40: 9.531 | AN40: 3.058 | AO40: 2.954 | AP40: 2.996 | AQ40: 2.818 | AR40: 11.826 | AS40: 2.727 | AT40: 2.938 | AU40: 3.401 | AV40: 2.959 | AW40: 12.025 | AX40: 13.521 | AY40: 4.307 | AZ40: 5.921 | BA40: 2.747 | BB40: 26.496 | BC40: 5.07 | BD40: 2.925 | BE40: 3.879 | BF40: 3.656 | BG40: 15.53 | BH40: 4.089 | BI40: 6.969 | BJ40: 7.517 | BK40: 7.918 | BL40: 26.493 | BM40: 6.174 | BN40: 6.854 | BO40: 7.841 | BP40: 8.995 | BQ40: 29.864 | BR40: 7.089 | BS40: 7.189 | BT40: 5.453 | BU40: 5.347 | BV40: 25.078 | BW40: 7.831 | BX40: 9.552 | BY40: 15.569 | CN40: 2029E | CO40: =CP40+$CO$37 -> 0.27 | CP40: 0.255 | CQ40: =CP40+$CQ$37 -> 0.24
B41: Memo: product line — Electronic components for defense, space & aerospace | S41: 243.13 | X41: 255.095 | AC41: 371.297 | AH41: 420.991 | AI41: 117.341 | AJ41: 130.891 | AK41: 146.652 | AL41: 152.204 | AM41: 547.088 | AN41: 137.75 | AO41: 161.664 | AP41: 160.031 | AQ41: 174.24 | AR41: 633.685 | AS41: 160.713 | AT41: 168.962 | AU41: 165.189 | AV41: 185.037 | AW41: 679.901 | AX41: 167.089 | AY41: 178.259 | AZ41: 176.238 | BA41: 188.035 | BB41: 709.621 | BC41: 157.468 | BD41: 162.441 | BE41: 165.871 | BF41: 186.367 | BG41: 672.147 | BH41: 174.578 | BI41: 220.742 | BJ41: 248.919 | BK41: 274.135 | BL41: 918.374 | BM41: 220.646 | BN41: 253.758 | BO41: 257.974 | BP41: 272.133 | BQ41: 1004.511 | BR41: 263.622 | BS41: 276.091 | BT41: 290.68 | BU41: 311.814 | BV41: 1142.207 | BW41: 301.162 | BX41: 378.945 | BY41: 392.399 | CN41: 2030E | CO41: =CP41+$CO$37 -> 0.27 | CP41: 0.255 | CQ41: =CP41+$CQ$37 -> 0.24
B42: Memo: product line — Other electronic components | S42: 136.274 | X42: 135.887 | AC42: 139.975 | AH42: 153.27 | AI42: 38.317 | AJ42: 37.831 | AK42: 39.718 | AL42: 38.873 | AM42: 154.739 | AN42: 46.679 | AO42: 52.787 | AP42: 56.098 | AQ42: 45.273 | AR42: 200.837 | AS42: 47.698 | AT42: 49.993 | AU42: 45.73 | AV42: 51.665 | AW42: 195.086 | AX42: 56.461 | AY42: 64.83 | AZ42: 63.305 | BA42: 64.953 | BB42: 249.549 | BC42: 64.868 | BD42: 74.952 | BE42: 78.332 | BF42: 82.176 | BG42: 300.328 | BH42: 80.481 | BI42: 81.017 | BJ42: 76.948 | BK42: 68.402 | BL42: 306.848 | BM42: 65.296 | BN42: 65.564 | BO42: 64.155 | BP42: 64.1 | BQ42: 259.115 | BR42: 66.693 | BS42: 66.076 | BT42: 65.183 | BU42: 72.961 | BV42: 270.913 | BW42: 69.513 | BX42: 80.587 | BY42: 91.088
B43: Memo: end market — Aerospace | AH43: 48.832 | AI43: 15.523 | AJ43: 14.935 | AK43: 16.146 | AL43: 24.631 | AM43: 71.235 | AN43: 19.295 | AO43: 22.876 | AP43: 20.729 | AQ43: 22.704 | AR43: 85.604 | AS43: 20.338 | AT43: 21.721 | AU43: 14.482 | AV43: 15.116 | AW43: 71.657 | AX43: 17.551 | AY43: 19.724 | AZ43: 19.305 | BA43: 18.186 | BB43: 74.766 | BC43: 17.526 | BD43: 20.207 | BE43: 20.322 | BF43: 28.725 | BG43: 86.78 | BH43: 35.327 | BI43: 45.126 | BJ43: 52.685 | BK43: 50.481 | BL43: 183.619 | BM43: 49.556 | BN43: 54.509 | BO43: 57.812 | BP43: 56.17 | BQ43: 218.047 | BR43: 60.612 | BS43: 64.543 | BT43: 68.749 | BU43: 81.655 | BV43: 275.559 | BW43: 88.918 | BX43: 112.479 | BY43: 105.787 | CN43: MA_spend (future acquisitions, $m) | CO43: 400 | CP43: Δ → | CQ43: -400 | CR43: HEICO acquisition spend averaged ~$0.8bn p.a. over FY2021–25 incl. Wencor ($2.4bn in FY23); $1.0bn in 9M/26.
B44: Memo: end market — Defense & space | AH44: 368.234 | AI44: 97.082 | AJ44: 109.13 | AK44: 125.375 | AL44: 121.127 | AM44: 452.714 | AN44: 115.219 | AO44: 135.952 | AP44: 138.875 | AQ44: 140.983 | AR44: 531.029 | AS44: 133.11 | AT44: 139.491 | AU44: 141.282 | AV44: 163.698 | AW44: 577.581 | AX44: 142.092 | AY44: 149.361 | AZ44: 148.035 | BA44: 160.082 | BB44: 599.57 | BC44: 131.447 | BD44: 134.414 | BE44: 136.778 | BF44: 142.745 | BG44: 545.384 | BH44: 121.962 | BI44: 138.609 | BJ44: 153.19 | BK44: 189.653 | BL44: 603.414 | BM44: 135.776 | BN44: 164.981 | BO44: 169.67 | BP44: 180.22 | BQ44: 650.647 | BR44: 170.741 | BS44: 171.246 | BT44: 182.59 | BU44: 191.973 | BV44: 716.55 | BW44: 170.363 | BX44: 217.595 | BY44: 238.093 | CN44: 2027E | CO44: =CP44+$CO$43 -> 1200 | CP44: 800 | CQ44: =MAX(0,CP44+$CQ$43) -> 400
B45: Memo: end market — Other industries | AH45: 157.195 | AI45: 43.053 | AJ45: 44.657 | AK45: 44.849 | AL45: 45.319 | AM45: 177.878 | AN45: 49.915 | AO45: 55.623 | AP45: 56.525 | AQ45: 55.826 | AR45: 217.889 | AS45: 54.963 | AT45: 57.743 | AU45: 55.155 | AV45: 57.888 | AW45: 225.749 | AX45: 63.907 | AY45: 74.004 | AZ45: 72.203 | BA45: 74.72 | BB45: 284.834 | BC45: 73.363 | BD45: 82.772 | BE45: 87.103 | BF45: 97.073 | BG45: 340.311 | BH45: 97.77 | BI45: 118.024 | BJ45: 119.992 | BK45: 102.403 | BL45: 438.189 | BM45: 100.61 | BN45: 99.832 | BO45: 94.647 | BP45: 99.843 | BQ45: 394.932 | BR45: 98.962 | BS45: 106.378 | BT45: 104.524 | BU45: 111.147 | BV45: 421.011 | BW45: 111.394 | BX45: 129.458 | BY45: 139.607 | CN45: 2028E | CO45: =CP45+$CO$43 -> 1200 | CP45: 800 | CQ45: =MAX(0,CP45+$CQ$43) -> 400
CN46: 2029E | CO46: =CP46+$CO$43 -> 1300 | CP46: 900 | CQ46: =MAX(0,CP46+$CQ$43) -> 500
B47: Intersegment eliminations & corporate (other, primarily corporate) | CF47: ELIMINATIONS & CORPORATE — modelling logic | CN47: 2030E | CO47: =CP47+$CO$43 -> 1300 | CP47: 900 | CQ47: =MAX(0,CP47+$CQ$43) -> 500
B48: Intersegment sales (eliminated) | C48: -0.086 | D48: -0.022 | E48: -0.507 | F48: -0.499 | G48: -0.965 | H48: -2.443 | I48: -4.576 | J48: -1.349 | K48: -1.46 | L48: -1.599 | M48: -2.016 | N48: -6.424 | O48: -2.251 | P48: -2.401 | Q48: -2.596 | R48: -2.646 | S48: -9.894 | T48: -3.093 | U48: -2.349 | V48: -3.452 | W48: -3.14 | X48: -12.034 | Y48: -2.501 | Z48: -2.208 | AA48: -2.684 | AB48: -3.491 | AC48: -10.884 | AD48: -3.634 | AE48: -4.321 | AF48: -4.326 | AG48: -4.707 | AH48: -16.988 | AI48: -5.969 | AJ48: -5.956 | AK48: -5.671 | AL48: -4.447 | AM48: -22.043 | AN48: -5.496 | AO48: -7.054 | AP48: -3.821 | AQ48: -2.687 | AR48: -19.058 | AS48: -3.203 | AT48: -2.773 | AU48: -2.667 | AV48: -4.147 | AW48: -12.79 | AX48: -4.982 | AY48: -6.718 | AZ48: -4.954 | BA48: -3.923 | BB48: -20.577 | BC48: -4.674 | BD48: -4.893 | BE48: -4.934 | BF48: -4.864 | BG48: -19.365 | BH48: -5.422 | BI48: -6.12 | BJ48: -8.005 | BK48: -7.755 | BL48: -27.302 | BM48: -8.295 | BN48: -11.159 | BO48: -11.509 | BP48: -14.348 | BQ48: -45.311 | BR48: -13.267 | BS48: -11.417 | BT48: -10.933 | BU48: -9.736 | BV48: -45.353 | BW48: -12.093 | BX48: -13.246 | BY48: -18.24 | BZ48: =-(BZ11+BZ30)*BZ49 -> -16.215715 | CA48: =SUM(BW48,BX48,BY48,BZ48) -> -59.794715 | CB48: =-(CB11+CB30)*CB49 -> -66.965887 | CC48: =-(CC11+CC30)*CC49 -> -72.097532 | CD48: =-(CD11+CD30)*CD49 -> -77.023649 | CE48: =-(CE11+CE30)*CE49 -> -82.286748
B49: Intersegment sales % of segment sales | C49: =IFERROR(-C48/(C11+C30),"") -> 0.0002192334 | D49: =IFERROR(-D48/(D11+D30),"") -> 4.3311691e-05 | E49: =IFERROR(-E48/(E11+E30),"") -> 0.00086985763 | F49: =IFERROR(-F48/(F11+F30),"") -> 0.00092614074 | G49: =IFERROR(-G48/(G11+G30),"") -> 0.0015615266 | H49: =IFERROR(-H48/(H11+H30),"") -> 0.0031837505 | I49: =IFERROR(-I48/(I11+I30),"") -> 0.0050736038 | J49: =IFERROR(-J48/(J11+J30),"") -> 0.0061926469 | ... BY49: =IFERROR(-BY48/(BY11+BY30),"") -> 0.012743749 | BZ49: =-SUM(BW48,BX48,BY48)/(SUM(BW11,BX11,BY11)+SUM(BW30,BX30,BY30)) -> 0.010865077 | CA49: =IFERROR(-CA48/(CA11+CA30),"") -> 0.010865077 | CB49: =$CA$49 -> 0.010865077 | CC49: =$CA$49 -> 0.010865077 | CD49: =$CA$49 -> 0.010865077 | CE49: =$CA$49 -> 0.010865077 | CF49: Forecast held at the 9M/26 ratio. | CN49: MINLEV (minimum net debt / Adjusted EBITDA for buybacks, x) | CO49: 0.5 | CP49: Δ → | CQ49: -0.5 | CR49: Buyback floor: Bull 1.5x (more capital returned), Base 1.0x, Bear 0.5x.
B50: Other, primarily corporate — operating income (loss) | C50: -13.999 | D50: -15.264 | E50: -14.171 | F50: -11.729 | G50: -14.849 | H50: -16.035 | I50: -18.087 | J50: -4.852 | K50: -5.857 | L50: -5.759 | M50: -5.063 | N50: -21.531 | O50: -4.722 | P50: -5.851 | Q50: -5.576 | R50: -5.857 | S50: -22.006 | T50: -3.715 | U50: -3.963 | V50: -5.112 | W50: -6.185 | X50: -18.975 | Y50: -5.128 | Z50: -7.916 | AA50: -5.724 | AB50: -5.345 | AC50: -24.113 | AD50: -5.897 | AE50: -7.028 | AF50: -9.085 | AG50: -8.061 | AH50: -30.071 | AI50: -9.529 | AJ50: -8.053 | AK50: -9.31 | AL50: -7.994 | AM50: -34.886 | AN50: -6.535 | AO50: -10.335 | AP50: -7.589 | AQ50: -6.216 | AR50: -30.675 | AS50: -8.546 | AT50: -4.896 | AU50: -5.518 | AV50: -6.257 | AW50: -25.217 | AX50: -5.665 | AY50: -10.022 | AZ50: -10.218 | BA50: -10.431 | BB50: -36.336 | BC50: -9.142 | BD50: -9.408 | BE50: -10.038 | BF50: -11.208 | BG50: -39.796 | BH50: -10.712 | BI50: -10.801 | BJ50: -13.962 | BK50: -11.536 | BL50: -47.011 | BM50: -11.209 | BN50: -14.986 | BO50: -12.936 | BP50: -17.681 | BQ50: -56.812 | BR50: -15.767 | BS50: -14.708 | BT50: -14.305 | BU50: -11.569 | BV50: -56.349 | BW50: -14.08 | BX50: -14.436 | BY50: -15.667 | BZ50: =-BZ51*(BZ11+BZ30+BZ48) -> -16.440463 | CA50: =SUM(BW50,BX50,BY50,BZ50) -> -60.623463 | CB50: =-CB51*(CB11+CB30+CB48) -> -67.894027 | CC50: =-CC51*(CC11+CC30+CC48) -> -73.096795 | CD50: =-CD51*(CD11+CD30+CD48) -> -78.091188 | CE50: =-CE51*(CE11+CE30+CE48) -> -83.427233 | CN50: 2027E | CO50: =CP50+$CO$49 -> 1.5 | CP50: 1 | CQ50: =MAX(0,CP50+$CQ$49) -> 0.5
B51: Corporate costs % of net sales | C51: =IFERROR(-C50/(C11+C30+C48),"") -> 0.035694434 | D51: =IFERROR(-D50/(D11+D30+D48),"") -> 0.03005174 | E51: =IFERROR(-E50/(E11+E30+E48),"") -> 0.024334289 | F51: =IFERROR(-F50/(F11+F30+F48),"") -> 0.021789127 | G51: =IFERROR(-G50/(G11+G30+G48),"") -> 0.02406567 | H51: =IFERROR(-H50/(H11+H30+H48),"") -> 0.020963771 | I51: =IFERROR(-I50/(I11+I30+I48),"") -> 0.020156082 | J51: =IFERROR(-J50/(J11+J30+J48),"") -> 0.022412121 | ... BY51: =IFERROR(-BY50/(BY11+BY30+BY48),"") -> 0.011087364 | BZ51: =-SUM(BW50,BX50,BY50)/SUM(BW98,BX98,BY98) -> 0.011136667 | CA51: =IFERROR(-CA50/(CA11+CA30+CA48),"") -> 0.011136667 | CB51: =$CA$51 -> 0.011136667 | CC51: =$CA$51 -> 0.011136667 | CD51: =$CA$51 -> 0.011136667 | CE51: =$CA$51 -> 0.011136667 | CF51: Forecast held at the 9M/26 ratio (corporate costs incl. LCP-related expense). | CN51: 2028E | CO51: =CP51+$CO$49 -> 1.5 | CP51: 1 | CQ51: =MAX(0,CP51+$CQ$49) -> 0.5
B52: Corporate D&A (consolidated D&A − segments) | C52: 0.306 | D52: 0.334 | E52: 0.475 | F52: 0.438 | G52: 0.39 | H52: 0.38 | I52: 0.84 | J52: 0.192 | K52: 0.194 | L52: 0.2 | M52: 0.198 | N52: 0.784 | O52: 0.205 | P52: 0.2 | Q52: 0.2 | R52: 0.203 | S52: 0.808 | U52: 0.202 | V52: 0.206 | X52: 0.83 | Y52: 0.221 | Z52: 0.222 | AA52: 0.219 | AB52: 0.218 | AC52: 0.88 | AD52: 0.218 | AE52: 0.232 | AF52: 0.258 | AG52: 0.271 | AH52: 0.979 | AI52: 0.407 | AJ52: 0.37 | AK52: 0.499 | AL52: 0.499 | AM52: 1.775 | AN52: 0.497 | AO52: 0.498 | AP52: 0.497 | AQ52: 0.5 | AR52: 1.992 | AS52: 0.501 | AT52: 0.502 | AU52: 0.495 | AV52: 0.492 | AW52: 1.99 | AX52: 0.52 | AY52: 0.527 | AZ52: 0.529 | BA52: 0.533 | BB52: 2.109 | BC52: 0.533 | BD52: 0.53 | BE52: 0.524 | BF52: 0.53 | BG52: 2.117 | BH52: 0.544 | BI52: 0.539 | BJ52: 0.837 | BK52: 0.693 | BL52: 2.613 | BM52: 0.696 | BN52: 0.697 | BO52: 0.705 | BP52: 0.715 | BQ52: 2.813 | BR52: 0.893 | BS52: 0.891 | BT52: 0.889 | BU52: 0.874 | BV52: 3.547 | BW52: 0.849 | BX52: 0.827 | BY52: -0.348 | CN52: 2029E | CO52: =CP52+$CO$49 -> 1.5 | CP52: 1 | CQ52: =MAX(0,CP52+$CQ$49) -> 0.5
CN53: 2030E | CO53: =CP53+$CO$49 -> 1.5 | CP53: 1 | CQ53: =MAX(0,CP53+$CQ$49) -> 0.5
B54: Future acquisitions (M&A lever — bolt-ons, unallocated; deals closed from 2027E) | CF54: M&A LEVER — acquired sales = spend ÷ EV/sales; mid-year convention
B55: Acquisition spend (USDm, scenario) | CA55: 0 | CB55: =MAX(0,CHOOSE(MATCH($CF$2,{"Bull","Base","Bear"},0),$CO$44,$CP$44,$CQ$44)) -> 800 | CC55: =MAX(0,CHOOSE(MATCH($CF$2,{"Bull","Base","Bear"},0),$CO$45,$CP$45,$CQ$45)) -> 800 | CD55: =MAX(0,CHOOSE(MATCH($CF$2,{"Bull","Base","Bear"},0),$CO$46,$CP$46,$CQ$46)) -> 900 | CE55: =MAX(0,CHOOSE(MATCH($CF$2,{"Bull","Base","Bear"},0),$CO$47,$CP$47,$CQ$47)) -> 900 | CF55: Scenario lever MA_spend. HEICO deployed ~$0.2–0.6bn p.a. on acquisitions in FY2017–22, $2.4bn in FY2023 (Wencor, Exxelia), $0.2–0.6bn in FY2024–25 and $1.0bn in 9M/26.
B56: Purchase multiple — EV / sales (x) | CA56: 0 | CB56: 4 | CC56: =CB56 -> 4 | CD56: =CC56 -> 4 | CE56: =CD56 -> 4 | CF56: ~16x EBITDA at a ~25% EBITDA margin (HEICO niche aerospace / electronics bolt-ons; Wencor ~$1.9bn at ~3.7x sales).
B57: Annualised sales acquired in the year | CA57: 0 | CB57: =IFERROR(CB55/CB56,0) -> 200 | CC57: =IFERROR(CC55/CC56,0) -> 200 | CD57: =IFERROR(CD55/CD56,0) -> 225 | CE57: =IFERROR(CE55/CE56,0) -> 225
B58: Growth of acquired businesses after acquisition % | CA58: 0 | CB58: 0.07 | CC58: =CB58 -> 0.07 | CD58: =CC58 -> 0.07 | CE58: =CD58 -> 0.07
B59: Run-rate sales of businesses acquired (year end) | CA59: 0 | CB59: =CA59*(1+CB58)+CB57 -> 200 | CC59: =CB59*(1+CC58)+CC57 -> 414 | CD59: =CC59*(1+CD58)+CD57 -> 667.98 | CE59: =CD59*(1+CE58)+CE57 -> 939.7386
B60: Net sales from future acquisitions | CA60: 0 | CB60: =CA59*(1+CB58)+0.5*CB57 -> 100 | CC60: =CB59*(1+CC58)+0.5*CC57 -> 314 | CD60: =CC59*(1+CD58)+0.5*CD57 -> 555.48 | CE60: =CD59*(1+CE58)+0.5*CE57 -> 827.2386 | CF60: Mid-year convention: deals close evenly through the year (half a year of sales in year 1).
B61: Operating margin of acquired businesses % (after amortization) | CA61: 0 | CB61: 0.18 | CC61: =CB61 -> 0.18 | CD61: =CC61 -> 0.18 | CE61: =CD61 -> 0.18 | CF61: Below group margin in early years (purchase-accounting amortization, integration).
B62: Operating income from future acquisitions | CA62: 0 | CB62: =CB60*CB61 -> 18 | CC62: =CC60*CC61 -> 56.52 | CD62: =CD60*CD61 -> 99.9864 | CE62: =CE60*CE61 -> 148.90295
B63: D&A of acquired businesses % of sales (incl. amortization) | CA63: 0 | CB63: 0.08 | CC63: =CB63 -> 0.08 | CD63: =CC63 -> 0.08 | CE63: =CD63 -> 0.08
B64: D&A from future acquisitions | CA64: 0 | CB64: =CB60*CB63 -> 8 | CC64: =CC60*CC63 -> 25.12 | CD64: =CD60*CD63 -> 44.4384 | CE64: =CE60*CE63 -> 66.179088
B65: PP&E % of spend | CA65: 0 | CB65: 0.05 | CC65: =CB65 -> 0.05 | CD65: =CC65 -> 0.05 | CE65: =CD65 -> 0.05 | CF65: Asset-light niche businesses: consideration mostly goodwill and intangibles (Wencor PPA: PP&E ~4%, intangibles ~35%).
B66: Acquired intangibles % of spend | CA66: 0 | CB66: 0.35 | CC66: =CB66 -> 0.35 | CD66: =CC66 -> 0.35 | CE66: =CD66 -> 0.35
B67: Intangible amortization life (years) | CA67: 0 | CB67: 12 | CC67: =CB67 -> 12 | CD67: =CC67 -> 12 | CE67: =CD67 -> 12
B68: Cumulative acquired intangibles (gross) | CA68: 0 | CB68: =CA68+CB55*CB66 -> 280 | CC68: =CB68+CC55*CC66 -> 560 | CD68: =CC68+CD55*CD66 -> 875 | CE68: =CD68+CE55*CE66 -> 1190
B69: Amortization of future-acquisition intangibles (within D&A) | CA69: 0 | CB69: =(CA68+0.5*CB55*CB66)/CB67 -> 11.666667 | CC69: =(CB68+0.5*CC55*CC66)/CC67 -> 35 | CD69: =(CC68+0.5*CD55*CD66)/CD67 -> 59.791667 | CE69: =(CD68+0.5*CE55*CE66)/CE67 -> 86.041667
B71: Group total — net sales & operating income (segment build) → Adjusted EBITDA | CF71: GROUP TOTAL (CONSOLIDATED) — modelling logic
B72: Net sales (segment build) | C72: =N(C11)+N(C30)+N(C48)+N(C60) -> 392.19 | D72: =N(D11)+N(D30)+N(D48)+N(D60) -> 507.924 | E72: =N(E11)+N(E30)+N(E48)+N(E60) -> 582.347 | F72: =N(F11)+N(F30)+N(F48)+N(F60) -> 538.296 | G72: =N(G11)+N(G30)+N(G48)+N(G60) -> 617.02 | H72: =N(H11)+N(H30)+N(H48)+N(H60) -> 764.891 | I72: =N(I11)+N(I30)+N(I48)+N(I60) -> 897.347 | J72: =N(J11)+N(J30)+N(J48)+N(J60) -> 216.49 | ... BZ72: =N(BZ11)+N(BZ30)+N(BZ48)+N(BZ60) -> 1476.2462 | CA72: =SUM(BW72,BX72,BY72,BZ72) -> 5443.5912 | CB72: =N(CB11)+N(CB30)+N(CB48)+N(CB60) -> 6196.4404 | CC72: =N(CC11)+N(CC30)+N(CC48)+N(CC60) -> 6877.6151 | CD72: =N(CD11)+N(CD30)+N(CD48)+N(CD60) -> 7567.5589 | CE72: =N(CE11)+N(CE30)+N(CE48)+N(CE60) -> 8318.4596 | CF72: Σ FSG + ETG − intersegment sales + future M&A. | CH72: =IFERROR((CE72/BV72)^(1/5)-1,"n/m") -> 0.13150178 | CI72: =IFERROR((BV72/AW72)^(1/5)-1,"n/m") -> 0.20206511 | CJ72: =IFERROR((BV72/X72)^(1/10)-1,"n/m") -> 0.14201378 | CK72: =IFERROR((BV72/C72)^(1/19)-1,"n/m") -> 0.13683761
B73: Operating income (segment build) | C73: =N(C15)+N(C34)+N(C50)+N(C62) -> 66.867 | D73: =N(D15)+N(D34)+N(D50)+N(D62) -> 86.014 | E73: =N(E15)+N(E34)+N(E50)+N(E62) -> 105.788 | F73: =N(F15)+N(F34)+N(F50)+N(F62) -> 88.255 | G73: =N(G15)+N(G34)+N(G50)+N(G62) -> 109.173 | H73: =N(H15)+N(H34)+N(H50)+N(H62) -> 138.431 | I73: =N(I15)+N(I34)+N(I50)+N(I62) -> 163.294 | J73: =N(J15)+N(J34)+N(J50)+N(J62) -> 34.939 | ... BZ73: =N(BZ15)+N(BZ34)+N(BZ50)+N(BZ62) -> 361.31611 | CA73: =SUM(BW73,BX73,BY73,BZ73) -> 1326.8491 | CB73: =N(CB15)+N(CB34)+N(CB50)+N(CB62) -> 1511.3915 | CC73: =N(CC15)+N(CC34)+N(CC50)+N(CC62) -> 1697.5986 | CD73: =N(CD15)+N(CD34)+N(CD50)+N(CD62) -> 1853.2298 | CE73: =N(CE15)+N(CE34)+N(CE50)+N(CE62) -> 2021.9866 | CH73: =IFERROR((CE73/BV73)^(1/5)-1,"n/m") -> 0.14688794 | CI73: =IFERROR((BV73/AW73)^(1/5)-1,"n/m") -> 0.22024639 | CJ73: =IFERROR((BV73/X73)^(1/10)-1,"n/m") -> 0.16067212 | CK73: =IFERROR((BV73/C73)^(1/19)-1,"n/m") -> 0.15414701
B74: Operating margin % | C74: =IF(AND(ISNUMBER(C73),ISNUMBER(C72)),IFERROR(C73/C72,""),"") -> 0.17049644 | D74: =IF(AND(ISNUMBER(D73),ISNUMBER(D72)),IFERROR(D73/D72,""),"") -> 0.16934423 | E74: =IF(AND(ISNUMBER(E73),ISNUMBER(E72)),IFERROR(E73/E72,""),"") -> 0.18165801 | F74: =IF(AND(ISNUMBER(F73),ISNUMBER(F72)),IFERROR(F73/F72,""),"") -> 0.16395255 | G74: =IF(AND(ISNUMBER(G73),ISNUMBER(G72)),IFERROR(G73/G72,""),"") -> 0.17693592 | H74: =IF(AND(ISNUMBER(H73),ISNUMBER(H72)),IFERROR(H73/H72,""),"") -> 0.18098134 | I74: =IF(AND(ISNUMBER(I73),ISNUMBER(I72)),IFERROR(I73/I72,""),"") -> 0.1819742 | J74: =IF(AND(ISNUMBER(J73),ISNUMBER(J72)),IFERROR(J73/J72,""),"") -> 0.16138852 | ... CE74: =IF(AND(ISNUMBER(CE73),ISNUMBER(CE72)),IFERROR(CE73/CE72,""),"") -> 0.24307224 | CH74: =IFERROR(AVERAGE(CA74,CB74,CC74,CD74,CE74),"n/m") -> 0.24449023 | CI74: =IFERROR(AVERAGE(BB74,BG74,BL74,BQ74,BV74),"n/m") -> 0.21743684 | CJ74: =IFERROR(AVERAGE(AC74,AH74,AM74,AR74,AW74,BB74,BG74,BL74,BQ74,BV74),"n/m") -> 0.21258741 | CK74: =IFERROR(AVERAGE(C74,D74,E74,F74,G74,H74,I74,N74,S74,X74,AC74,AH74,AM74,AR74,AW74,BB74,BG74,BL74,BQ74,BV74),"n/m") -> 0.19530214
B75: Net sales y/y % | D75: =IF(AND(ISNUMBER(D72),ISNUMBER(C72)),IFERROR(D72/C72-1,""),"") -> 0.29509676 | E75: =IF(AND(ISNUMBER(E72),ISNUMBER(D72)),IFERROR(E72/D72-1,""),"") -> 0.14652389 | F75: =IF(AND(ISNUMBER(F72),ISNUMBER(E72)),IFERROR(F72/E72-1,""),"") -> -0.075643903 | G75: =IF(AND(ISNUMBER(G72),ISNUMBER(F72)),IFERROR(G72/F72-1,""),"") -> 0.14624667 | H75: =IF(AND(ISNUMBER(H72),ISNUMBER(G72)),IFERROR(H72/G72-1,""),"") -> 0.2396535 | I75: =IF(AND(ISNUMBER(I72),ISNUMBER(H72)),IFERROR(I72/H72-1,""),"") -> 0.17316977 | N75: =IF(AND(ISNUMBER(N72),ISNUMBER(I72)),IFERROR(N72/I72-1,""),"") -> 0.12415487 | O75: =IF(AND(ISNUMBER(O72),ISNUMBER(J72)),IFERROR(O72/J72-1,""),"") -> 0.23250958 | P75: =IF(AND(ISNUMBER(P72),ISNUMBER(K72)),IFERROR(P72/K72-1,""),"") -> 0.18730543 | Q75: =IF(AND(ISNUMBER(Q72),ISNUMBER(L72)),IFERROR(Q72/L72-1,""),"") -> 0.089457312 | R75: =IF(AND(ISNUMBER(R72),ISNUMBER(M72)),IFERROR(R72/M72-1,""),"") -> 0.016689513 | S75: =IF(AND(ISNUMBER(S72),ISNUMBER(N72)),IFERROR(S72/N72-1,""),"") -> 0.12248143 | T75: =IF(AND(ISNUMBER(T72),ISNUMBER(O72)),IFERROR(T72/O72-1,""),"") -> 0.0050932068 | U75: =IF(AND(ISNUMBER(U72),ISNUMBER(P72)),IFERROR(U72/P72-1,""),"") -> 0.032558321 | ... CA75: =IF(AND(ISNUMBER(CA72),ISNUMBER(BV72)),IFERROR(CA72/BV72-1,""),"") -> 0.21372081 | CB75: =IF(AND(ISNUMBER(CB72),ISNUMBER(CA72)),IFERROR(CB72/CA72-1,""),"") -> 0.1383001 | CC75: =IF(AND(ISNUMBER(CC72),ISNUMBER(CB72)),IFERROR(CC72/CB72-1,""),"") -> 0.10992999 | CD75: =IF(AND(ISNUMBER(CD72),ISNUMBER(CC72)),IFERROR(CD72/CC72-1,""),"") -> 0.10031731 | CE75: =IF(AND(ISNUMBER(CE72),ISNUMBER(CD72)),IFERROR(CE72/CD72-1,""),"") -> 0.099226266
B76: Check: segment build vs consolidated net sales (should be 0) | C76: =IF(ISNUMBER(C98),ROUND(C72-C98,1),"") -> 0 | D76: =IF(ISNUMBER(D98),ROUND(D72-D98,1),"") -> 0 | E76: =IF(ISNUMBER(E98),ROUND(E72-E98,1),"") -> 0 | F76: =IF(ISNUMBER(F98),ROUND(F72-F98,1),"") -> 0 | G76: =IF(ISNUMBER(G98),ROUND(G72-G98,1),"") -> 0 | H76: =IF(ISNUMBER(H98),ROUND(H72-H98,1),"") -> 0 | I76: =IF(ISNUMBER(I98),ROUND(I72-I98,1),"") -> 0 | J76: =IF(ISNUMBER(J98),ROUND(J72-J98,1),"") -> 0 | ... CE76: =IF(ISNUMBER(CE98),ROUND(CE72-CE98,1),"") -> 0
B77: Check: segment build vs consolidated operating income (should be 0) | C77: =IF(ISNUMBER(C102),ROUND(C73-C102,1),"") -> 0 | D77: =IF(ISNUMBER(D102),ROUND(D73-D102,1),"") -> 0 | E77: =IF(ISNUMBER(E102),ROUND(E73-E102,1),"") -> 0 | F77: =IF(ISNUMBER(F102),ROUND(F73-F102,1),"") -> 0 | G77: =IF(ISNUMBER(G102),ROUND(G73-G102,1),"") -> 0 | H77: =IF(ISNUMBER(H102),ROUND(H73-H102,1),"") -> 0 | I77: =IF(ISNUMBER(I102),ROUND(I73-I102,1),"") -> 0 | J77: =IF(ISNUMBER(J102),ROUND(J73-J102,1),"") -> 0 | ... CE77: =IF(ISNUMBER(CE102),ROUND(CE73-CE102,1),"") -> 0
B78: Memo: consolidated organic net sales growth % (company-reported, where stated) | AI78: 0.05 | AZ78: 0.17 | BA78: 0.16 | BC78: 0.13 | BD78: 0.09 | BE78: 0.13 | BF78: 0.11 | BH78: 0.14 | BI78: 0.1 | BJ78: 0.12 | BK78: 0.12 | BX78: 0.18 | BY78: 0.14
B79: Memo: FY26 net sales target — optional input (e.g. consensus; blank = driver-based) | CA79: =IF(CHOOSE(MATCH($CF$2,{"Bull","Base","Bear"},0),$CO$12,$CP$12,$CQ$12)=0,"",CHOOSE(MATCH($CF$2,{"Bull","Base","Bear"},0),$CO$12,$CP$12,$CQ$12)) | CF79: HEICO gives no numerical guidance (qualitative outlook only). Enter a FY26 net sales target in the scenario table (CO12:CQ12) to calibrate Q4/26E; leave blank for the driver-based forecast.
B80: Net sales before outlook calibration (Q4/26E helper) | BZ80: =(BU11*(1+BZ13+BZ14)+BU30*(1+BZ32+BZ33))*(1-BZ49) -> 1476.2462
B81: Net sales sensitivity to +1.00 of growth (Q4/26E helper) | BZ81: =(BU11+BU30)*(1-BZ49) -> 1205.9009
B82: Outlook calibration: Δ y/y growth applied to both segments (Q4/26E) | BZ82: =IF(ISNUMBER(CA79),(CA79-SUM(BW98,BX98,BY98)-BZ80)/BZ81,0) -> 0 | CF82: Solves the uniform growth shift so that FY26E net sales = the target when one is entered; zero otherwise.
B83: Check: FY26E net sales vs target (should be 0 when a target is set) | CA83: =IF(ISNUMBER(CA79),ROUND(CA98-CA79,1),"n/a") -> n/a
B84: Memo: FY26 Adjusted EBITDA target — optional input (blank = driver-based) | CA84: =IF(CHOOSE(MATCH($CF$2,{"Bull","Base","Bear"},0),$CO$13,$CP$13,$CQ$13)=0,"",CHOOSE(MATCH($CF$2,{"Bull","Base","Bear"},0),$CO$13,$CP$13,$CQ$13))
B85: Adjusted EBITDA before margin calibration (Q4/26E helper) | BZ85: =BZ11*BZ16+BZ30*BZ35+BZ50+BZ104+BZ114+BZ139 -> 423.37027 | CF85: Adjusted EBITDA = operating income + other income + D&A + adjusting items (EBITDA = net income + NCI + tax + interest + D&A).
B86: Outlook calibration: Δ operating margin applied to both segments (Q4/26E) | BZ86: =IF(ISNUMBER(CA84),(CA84-SUM(BW140,BX140,BY140)-BZ85)/(BZ11+BZ30),0) -> 0
B87: Check: FY26E Adjusted EBITDA vs target (should be 0 when a target is set) | CA87: =IF(ISNUMBER(CA84),ROUND(CA140-CA84,1),"n/a") -> n/a
B89: Cost drivers & D&A | CF89: COST DRIVERS — inputs that drive forecast cost lines
B90: Gross margin % (forecast driver) | C90: =IF(AND(ISNUMBER(C100),ISNUMBER(C98)),IFERROR(C100/C98,""),"") -> 0.36337744 | D90: =IF(AND(ISNUMBER(D100),ISNUMBER(D98)),IFERROR(D100/D98,""),"") -> 0.34937904 | E90: =IF(AND(ISNUMBER(E100),ISNUMBER(E98)),IFERROR(E100/E98,""),"") -> 0.36145975 | F90: =IF(AND(ISNUMBER(F100),ISNUMBER(F98)),IFERROR(F100/F98,""),"") -> 0.33626666 | G90: =IF(AND(ISNUMBER(G100),ISNUMBER(G98)),IFERROR(G100/G98,""),"") -> 0.36035623 | H90: =IF(AND(ISNUMBER(H100),ISNUMBER(H98)),IFERROR(H100/H98,""),"") -> 0.35879753 | I90: =IF(AND(ISNUMBER(I100),ISNUMBER(I98)),IFERROR(I100/I98,""),"") -> 0.3648934 | J90: =IF(AND(ISNUMBER(J100),ISNUMBER(J98)),IFERROR(J100/J98,""),"") -> 0.35839531 | ... BY90: =IF(AND(ISNUMBER(BY100),ISNUMBER(BY98)),IFERROR(BY100/BY98,""),"") -> 0.41115813 | BZ90: =SUM(BW100,BX100,BY100)/SUM(BW98,BX98,BY98) -> 0.40467265 | CA90: =CA100/CA98 -> 0.40467265 | CB90: 0.405 | CC90: =CB90 -> 0.405 | CD90: =CC90 -> 0.405 | CE90: =CD90 -> 0.405 | CF90: Q4/26E: 9M/26 gross margin (40.3%). 2027E+: 40.5% input (FY25 39.8%; mix shift to PMA/ETG). SG&A is the plug between gross profit and the segment operating-income build.
B91: Depreciation (D&A − amortization of intangibles) | C91: =IF(AND(ISNUMBER(C114),ISNUMBER(C93)),C114-C93,"") | D91: =IF(AND(ISNUMBER(D114),ISNUMBER(D93)),D114-D93,"") | E91: =IF(AND(ISNUMBER(E114),ISNUMBER(E93)),E114-E93,"") | F91: =IF(AND(ISNUMBER(F114),ISNUMBER(F93)),F114-F93,"") | G91: =IF(AND(ISNUMBER(G114),ISNUMBER(G93)),G114-G93,"") -> 10.797 | H91: =IF(AND(ISNUMBER(H114),ISNUMBER(H93)),H114-H93,"") -> 10.943 | I91: =IF(AND(ISNUMBER(I114),ISNUMBER(I93)),I114-I93,"") -> 14.456 | J91: =IF(AND(ISNUMBER(J114),ISNUMBER(J93)),J114-J93,"") -> 3.64 | ... BY91: =IF(AND(ISNUMBER(BY114),ISNUMBER(BY93)),BY114-BY93,"") -> 15.443 | BZ91: =BZ98*BZ92 -> 17.259825 | CA91: =SUM(BW91,BX91,BY91,BZ91) -> 63.644825 | CB91: =(CB98-N(CB60))*CB92 -> 73.157285 | CC91: =(CC98-N(CC60))*CC92 -> 78.763381 | CD91: =(CD98-N(CD60))*CD92 -> 84.144947 | CE91: =(CE98-N(CE60))*CE92 -> 89.894651
B92: Depreciation % of net sales | C92: =IF(AND(ISNUMBER(C91),ISNUMBER(C98)),IFERROR(C91/C98,""),"") | D92: =IF(AND(ISNUMBER(D91),ISNUMBER(D98)),IFERROR(D91/D98,""),"") | E92: =IF(AND(ISNUMBER(E91),ISNUMBER(E98)),IFERROR(E91/E98,""),"") | F92: =IF(AND(ISNUMBER(F91),ISNUMBER(F98)),IFERROR(F91/F98,""),"") | G92: =IF(AND(ISNUMBER(G91),ISNUMBER(G98)),IFERROR(G91/G98,""),"") -> 0.017498622 | H92: =IF(AND(ISNUMBER(H91),ISNUMBER(H98)),IFERROR(H91/H98,""),"") -> 0.014306614 | I92: =IF(AND(ISNUMBER(I91),ISNUMBER(I98)),IFERROR(I91/I98,""),"") -> 0.01610971 | J92: =IF(AND(ISNUMBER(J91),ISNUMBER(J98)),IFERROR(J91/J98,""),"") -> 0.01681371 | ... BY92: =IF(AND(ISNUMBER(BY91),ISNUMBER(BY98)),IFERROR(BY91/BY98,""),"") -> 0.010928842 | BZ92: =SUM(BW91,BX91,BY91)/SUM(BW98,BX98,BY98) -> 0.011691698 | CA92: =CA91/CA98 -> 0.011691698 | CB92: 0.012 | CC92: =CB92 -> 0.012 | CD92: =CC92 -> 0.012 | CE92: =CD92 -> 0.012 | CF92: 9M/26: 1.2% of net sales; 2027E+ 1.2% input (capex ~1.6% of sales).
B93: Amortization of acquired intangibles — existing (company schedule) | G93: 6.8 | H93: 7.6 | I93: 16.2 | J93: 4.5 | K93: 4.4 | L93: 5.4 | M93: 6.3 | N93: 20.6 | O93: 7.1 | P93: 7 | Q93: 7 | R93: 6.6 | S93: 27.7 | T93: 6.1 | U93: 7 | V93: 6.6 | W93: 7.3 | X93: 27 | Y93: 8.3 | Z93: 9.3 | AA93: 9.4 | AB93: 9.4 | AC93: 36.4 | AD93: 9.2 | AE93: 9.1 | AF93: 9.9 | AG93: 11.3 | AH93: 39.5 | AI93: 12.4 | AJ93: 12.4 | AK93: 12.7 | AL93: 12.6 | AM93: 50.1 | AN93: 12.8 | AO93: 13.1 | AP93: 13.7 | AQ93: 14.1 | AR93: 53.7 | AS93: 13.7 | AT93: 13.9 | AU93: 14.2 | AV93: 15.6 | AW93: 57.4 | AX93: 15.2 | AY93: 15.1 | AZ93: 15.2 | BA93: 15.8 | BB93: 61.3 | BC93: 15 | BD93: 15.2 | BE93: 15.2 | BF93: 17.1 | BG93: 62.5 | BH93: 17.8 | BI93: 19.1 | BJ93: 18.6 | BK93: 30.4 | BL93: 85.9 | BM93: 30.2 | BN93: 30.6 | BO93: 30.7 | BP93: 30.8 | BQ93: 122.3 | BR93: 32.2 | BS93: 34.8 | BT93: 34.7 | BU93: 36.2 | BV93: 137.9 | BW93: 35.9 | BX93: 40.8 | BY93: 43.3 | BZ93: 43.6 | CA93: =SUM(BW93,BX93,BY93,BZ93) -> 163.6 | CB93: 170.8 | CC93: 163.7 | CD93: 156.9 | CE93: 149 | CF93: Q3-26 Form 10-Q: remainder of FY26 $43.6m; FY27 $170.8m, FY28 $163.7m, FY29 $156.9m, FY30 $149.0m (intangibles held at 31-Jul-2026).
B94: SG&A % of net sales (output) | C94: =IF(AND(ISNUMBER(C101),ISNUMBER(C98)),IFERROR(C101/C98,""),"") -> 0.192881 | D94: =IF(AND(ISNUMBER(D101),ISNUMBER(D98)),IFERROR(D101/D98,""),"") -> 0.18003481 | E94: =IF(AND(ISNUMBER(E101),ISNUMBER(E98)),IFERROR(E101/E98,""),"") -> 0.17980173 | F94: =IF(AND(ISNUMBER(F101),ISNUMBER(F98)),IFERROR(F101/F98,""),"") -> 0.17231412 | G94: =IF(AND(ISNUMBER(G101),ISNUMBER(G98)),IFERROR(G101/G98,""),"") -> 0.18342031 | H94: =IF(AND(ISNUMBER(H101),ISNUMBER(H98)),IFERROR(H101/H98,""),"") -> 0.17781619 | I94: =IF(AND(ISNUMBER(I101),ISNUMBER(I98)),IFERROR(I101/I98,""),"") -> 0.18291921 | J94: =IF(AND(ISNUMBER(J101),ISNUMBER(J98)),IFERROR(J101/J98,""),"") -> 0.19700679 | ... CE94: =IF(AND(ISNUMBER(CE101),ISNUMBER(CE98)),IFERROR(CE101/CE98,""),"") -> 0.16192776 | CH94: =IFERROR(AVERAGE(CA94,CB94,CC94,CD94,CE94),"n/m") -> 0.1604443 | CI94: =IFERROR(AVERAGE(BB94,BG94,BL94,BQ94,BV94),"n/m") -> 0.17392491 | CJ94: =IFERROR(AVERAGE(AC94,AH94,AM94,AR94,AW94,BB94,BG94,BL94,BQ94,BV94),"n/m") -> 0.17485688 | CK94: =IFERROR(AVERAGE(C94,D94,E94,F94,G94,H94,I94,N94,S94,X94,AC94,AH94,AM94,AR94,AW94,BB94,BG94,BL94,BQ94,BV94),"n/m") -> 0.17739647
B95: Share-based compensation % of net sales | C95: =IF(AND(ISNUMBER(C115),ISNUMBER(C98)),IFERROR(C115/C98,""),"") -> 0.0035008542 | D95: =IF(AND(ISNUMBER(D115),ISNUMBER(D98)),IFERROR(D115/D98,""),"") -> 0.0012954694 | E95: =IF(AND(ISNUMBER(E115),ISNUMBER(E98)),IFERROR(E115/E98,""),"") -> 0.00024384087 | F95: =IF(AND(ISNUMBER(F115),ISNUMBER(F98)),IFERROR(F115/F98,""),"") -> 0.00033624623 | G95: =IF(AND(ISNUMBER(G115),ISNUMBER(G98)),IFERROR(G115/G98,""),"") -> 0.0021927976 | H95: =IF(AND(ISNUMBER(H115),ISNUMBER(H98)),IFERROR(H115/H98,""),"") -> 0.0034606238 | I95: =IF(AND(ISNUMBER(I115),ISNUMBER(I98)),IFERROR(I115/I98,""),"") -> 0.0043996358 | J95: =IF(AND(ISNUMBER(J115),ISNUMBER(J98)),IFERROR(J115/J98,""),"") -> 0.0050533512 | ... BY95: =IF(AND(ISNUMBER(BY115),ISNUMBER(BY98)),IFERROR(BY115/BY98,""),"") -> 0.0084370688 | BZ95: =SUM(BW115,BX115,BY115)/SUM(BW98,BX98,BY98) -> 0.0086806164 | CA95: =CA115/CA98 -> 0.0086806164 | CB95: 0.008 | CC95: =CB95 -> 0.008 | CD95: =CC95 -> 0.008 | CE95: =CD95 -> 0.008
B97: CONSOLIDATED STATEMENT OF OPERATIONS (US GAAP, as reported; fiscal year ends 31 October) | CF97: CONSOLIDATED IS — forecast logic
B98: Net sales | C98: 392.19 | D98: 507.924 | E98: 582.347 | F98: 538.296 | G98: 617.02 | H98: 764.891 | I98: 897.347 | J98: 216.49 | K98: 237.708 | L98: 267.133 | M98: 287.426 | N98: 1008.757 | O98: 266.826 | P98: 282.232 | Q98: 291.03 | R98: 292.223 | S98: 1132.311 | T98: 268.185 | U98: 291.421 | V98: 300.37 | W98: 328.672 | X98: 1188.648 | Y98: 306.227 | Z98: 350.648 | AA98: 356.084 | AB98: 363.299 | AC98: 1376.258 | AD98: 343.432 | AE98: 368.657 | AF98: 391.5 | AG98: 421.224 | AH98: 1524.813 | AI98: 404.41 | AJ98: 430.602 | AK98: 465.825 | AL98: 476.884 | AM98: 1777.721 | AN98: 466.146 | AO98: 515.648 | AP98: 532.324 | AQ98: 541.529 | AR98: 2055.647 | AS98: 506.275 | AT98: 468.146 | AU98: 386.41 | AV98: 426.178 | AW98: 1787.009 | AX98: 417.902 | AY98: 466.651 | AZ98: 471.707 | BA98: 509.422 | BB98: 1865.682 | BC98: 490.343 | BD98: 538.813 | BE98: 569.528 | BF98: 609.638 | BG98: 2208.322 | BH98: 620.915 | BI98: 687.841 | BJ98: 722.902 | BK98: 936.447 | BL98: 2968.105 | BM98: 896.363 | BN98: 955.395 | BO98: 992.246 | BP98: 1013.665 | BQ98: 3857.669 | BR98: 1030.222 | BS98: 1097.82 | BT98: 1147.591 | BU98: 1209.411 | BV98: 4485.044 | BW98: 1178.582 | BX98: 1375.713 | BY98: 1413.05 | BZ98: =BZ72 -> 1476.2462 | CA98: =SUM(BW98,BX98,BY98,BZ98) -> 5443.5912 | CB98: =CB72 -> 6196.4404 | CC98: =CC72 -> 6877.6151 | CD98: =CD72 -> 7567.5589 | CE98: =CE72 -> 8318.4596 | CF98: Forecast linked to the segment build. | CH98: =IFERROR((CE98/BV98)^(1/5)-1,"n/m") -> 0.13150178 | CI98: =IFERROR((BV98/AW98)^(1/5)-1,"n/m") -> 0.20206511 | CJ98: =IFERROR((BV98/X98)^(1/10)-1,"n/m") -> 0.14201378 | CK98: =IFERROR((BV98/C98)^(1/19)-1,"n/m") -> 0.13683761
B99: Cost of sales | C99: 249.677 | D99: 330.466 | E99: 371.852 | F99: 357.285 | G99: 394.673 | H99: 490.45 | I99: 569.911 | J99: 138.901 | K99: 148.26 | L99: 169.593 | M99: 180.822 | N99: 637.576 | O99: 174.709 | P99: 182.31 | Q99: 187.703 | R99: 189.277 | S99: 733.999 | T99: 174.388 | U99: 185.927 | V99: 192.278 | W99: 201.876 | X99: 754.469 | Y99: 194.031 | Z99: 216.619 | AA99: 222.501 | AB99: 227.615 | AC99: 860.766 | AD99: 218.015 | AE99: 228.275 | AF99: 242.603 | AG99: 261.195 | AH99: 950.088 | AI99: 249.619 | AJ99: 262.745 | AK99: 284.216 | AL99: 290.426 | AM99: 1087.006 | AN99: 283.909 | AO99: 306.261 | AP99: 319.493 | AQ99: 332.144 | AR99: 1241.807 | AS99: 308.228 | AT99: 289.256 | AU99: 242.927 | AV99: 264.471 | AW99: 1104.882 | AX99: 259.468 | AY99: 286.878 | AZ99: 286.99 | BA99: 304.923 | BB99: 1138.259 | BC99: 300.133 | BD99: 327.584 | BE99: 348.591 | BF99: 369.255 | BG99: 1345.563 | BH99: 377.116 | BI99: 421.329 | BJ99: 444.168 | BK99: 572.004 | BL99: 1814.617 | BM99: 549.594 | BN99: 583.6 | BO99: 602.976 | BP99: 619.773 | BQ99: 2355.943 | BR99: 624.56 | BS99: 660.016 | BT99: 690.434 | BU99: 723.57 | BV99: 2698.58 | BW99: 723.618 | BX99: 806.188 | BY99: 832.063 | BZ99: =BZ98*(1-BZ90) -> 878.84977 | CA99: =SUM(BW99,BX99,BY99,BZ99) -> 3240.7188 | CB99: =CB98*(1-CB90) -> 3686.8821 | CC99: =CC98*(1-CC90) -> 4092.181 | CD99: =CD98*(1-CD90) -> 4502.6976 | CE99: =CE98*(1-CE90) -> 4949.4834 | CF99: Forecast = net sales × (1 − gross margin input).
B100: Gross profit | C100: =C98-C99 -> 142.513 | D100: =D98-D99 -> 177.458 | E100: =E98-E99 -> 210.495 | F100: =F98-F99 -> 181.011 | G100: =G98-G99 -> 222.347 | H100: =H98-H99 -> 274.441 | I100: =I98-I99 -> 327.436 | J100: =J98-J99 -> 77.589 | ... CE100: =CE98-CE99 -> 3368.9761 | CH100: =IFERROR((CE100/BV100)^(1/5)-1,"n/m") -> 0.13527411 | CI100: =IFERROR((BV100/AW100)^(1/5)-1,"n/m") -> 0.21234383 | CJ100: =IFERROR((BV100/X100)^(1/10)-1,"n/m") -> 0.15194713 | CK100: =IFERROR((BV100/C100)^(1/19)-1,"n/m") -> 0.14234381
B101: Selling, general & administrative expenses | C101: 75.646 | D101: 91.444 | E101: 104.707 | F101: 92.756 | G101: 113.174 | H101: 136.01 | I101: 164.142 | J101: 42.65 | K101: 44.76 | L101: 49.134 | M101: 51.047 | N101: 187.591 | O101: 41.732 | P101: 50.751 | Q101: 53.214 | R101: 49.227 | S101: 194.924 | T101: 47.391 | U101: 49.706 | V101: 49.582 | W101: 57.844 | X101: 204.523 | Y101: 59.575 | Z101: 67.235 | AA101: 63.729 | AB101: 59.608 | AC101: 250.147 | AD101: 60.867 | AE101: 63.84 | AF101: 72.775 | AG101: 70.585 | AH101: 268.067 | AI101: 75.231 | AJ101: 76.292 | AK101: 80.186 | AL101: 82.761 | AM101: 314.47 | AN101: 84.29 | AO101: 90.204 | AP101: 93.417 | AQ101: 88.832 | AR101: 356.743 | AS101: 87.057 | AT101: 70.729 | AU101: 75.049 | AV101: 72.644 | AW101: 305.479 | AX101: 78.149 | AY101: 83.025 | AZ101: 83.879 | BA101: 89.47 | BB101: 334.523 | BC101: 91.388 | BD101: 88.452 | BE101: 92.19 | BF101: 93.885 | BG101: 365.915 | BH101: 114.365 | BI101: 109.422 | BJ101: 129.367 | BK101: 174.995 | BL101: 528.149 | BM101: 166.559 | BN101: 162.642 | BO101: 172.824 | BP101: 175.246 | BQ101: 677.271 | BR101: 178.857 | BS101: 189.652 | BT101: 192.138 | BU101: 206.819 | BV101: 767.466 | BW101: 195.065 | BX101: 219.088 | BY101: 225.79 | BZ101: =BZ100-BZ73 -> 236.08037 | CA101: =SUM(BW101,BX101,BY101,BZ101) -> 876.02337 | CB101: =CB100-CB73 -> 998.16689 | CC101: =CC100-CC73 -> 1087.8355 | CD101: =CD100-CD73 -> 1211.6316 | CE101: =CE100-CE73 -> 1346.9896 | CF101: Forecast = gross profit − segment-build operating income (plug; HEICO reports segment operating income, not segment gross profit).
B102: Operating income | C102: =C100-C101 -> 66.867 | D102: =D100-D101 -> 86.014 | E102: =E100-E101 -> 105.788 | F102: =F100-F101 -> 88.255 | G102: =G100-G101 -> 109.173 | H102: =H100-H101 -> 138.431 | I102: =I100-I101 -> 163.294 | J102: =J100-J101 -> 34.939 | ... CE102: =CE100-CE101 -> 2021.9866 | CH102: =IFERROR((CE102/BV102)^(1/5)-1,"n/m") -> 0.14688794 | CI102: =IFERROR((BV102/AW102)^(1/5)-1,"n/m") -> 0.22024639 | CJ102: =IFERROR((BV102/X102)^(1/10)-1,"n/m") -> 0.16067212 | CK102: =IFERROR((BV102/C102)^(1/19)-1,"n/m") -> 0.15414701
B103: Interest expense | C103: 3.523 | D103: 3.293 | E103: 2.314 | F103: 0.615 | G103: 0.508 | H103: 0.142 | I103: 2.432 | J103: 0.64 | K103: 0.803 | L103: 1.097 | M103: 1.177 | N103: 3.717 | O103: 1.281 | P103: 1.441 | Q103: 1.444 | R103: 1.275 | S103: 5.441 | T103: 1.112 | U103: 1.146 | V103: 1.088 | W103: 1.28 | X103: 4.626 | Y103: 1.567 | Z103: 2.333 | AA103: 2.294 | AB103: 2.078 | AC103: 8.272 | AD103: 1.969 | AE103: 1.96 | AF103: 2.447 | AG103: 3.414 | AH103: 9.79 | AI103: 4.725 | AJ103: 4.904 | AK103: 5.212 | AL103: 5.06 | AM103: 19.901 | AN103: 5.489 | AO103: 5.484 | AP103: 5.523 | AQ103: 5.199 | AR103: 21.695 | AS103: 4.283 | AT103: 3.759 | AU103: 2.602 | AV103: 2.515 | AW103: 13.159 | AX103: 2.448 | AY103: 2.083 | AZ103: 1.717 | BA103: 1.037 | BB103: 7.285 | BC103: 0.796 | BD103: 0.979 | BE103: 1.406 | BF103: 3.205 | BG103: 6.386 | BH103: 6.068 | BI103: 11.373 | BJ103: 12.12 | BK103: 43.423 | BL103: 72.984 | BM103: 38.607 | BN103: 38.512 | BO103: 36.788 | BP103: 35.406 | BQ103: 149.313 | BR103: 32.458 | BS103: 32.865 | BT103: 31.701 | BU103: 32.853 | BV103: 129.877 | BW103: 29.486 | BX103: 34.161 | BY103: 35.904 | BZ103: =(BY291*CA292+BY293*CA294)/4 -> 34.3675 | CA103: =SUM(BW103,BX103,BY103,BZ103) -> 133.9185 | CB103: =CA291*CB292+CA293*CB294 -> 130.8 | CC103: =CB291*CC292+CB293*CC294 -> 130.8 | CD103: =CC291*CD292+CC293*CD294 -> 130.8 | CE103: =CD291*CE292+CD293*CE294 -> 130.8 | CF103: Q4/26E: 31-Jul-26 balances ($2.4bn senior notes at ~5.45% effective incl. Jul-26 issue; $145m revolver at 4.6%) ÷ 4. 2027E+: rate × opening balance (no circularity).
...

Sheet Bull-Base-Bear
B2: HEICO Corporation (HEI) — Bull / Base / Bear Case P&L Summary | J2: Share price ($): | K2: =Model!$CA$339 -> 302.45
B3: Adjusted figures (model definition: Adjusted EBITDA / adjusted EPS — HEICO publishes only EBITDA) · USD millions · fiscal years ending 31 October · Live panel linked to Model — toggle scenario via Model!CF2. Bull and Bear panels are value snapshots generated from the Model with the switch set to each case. Share price = HEI (common) applied to all shares. | J3: As of: | K3: =TODAY() -> 46301
B5: Scenario: | C5: =Model!$CF$2 -> Base | N5: Scenario: | O5: Bull | P5: Snapshot (values) — Model run with switch = Bull | Z5: Scenario: | AA5: Bear | AB5: Snapshot (values) — Model run with switch = Bear
B7: (USDm, except EPS and shares) | C7: 2025A | D7: 2026E | E7: 2027E | F7: 2028E | G7: 2029E | H7: 2030E | I7: 25-'30 CAGR | J7: LT Hist Avg | K7: LT Hist Min | L7: LT Hist Max | N7: (USDm, except EPS and shares) | O7: 2025A | P7: 2026E | Q7: 2027E | R7: 2028E | S7: 2029E | T7: 2030E | U7: 25-'30 CAGR | V7: LT Hist Avg | W7: LT Hist Min | X7: LT Hist Max | Z7: (USDm, except EPS and shares) | AA7: 2025A | AB7: 2026E | AC7: 2027E | AD7: 2028E | AE7: 2029E | AF7: 2030E | AG7: 25-'30 CAGR | AH7: LT Hist Avg | AI7: LT Hist Min | AJ7: LT Hist Max
B9: Net sales | C9: =Model!BV98 -> 4485.044 | D9: =Model!CA98 -> 5443.5912 | E9: =Model!CB98 -> 6196.4404 | F9: =Model!CC98 -> 6877.6151 | G9: =Model!CD98 -> 7567.5589 | H9: =Model!CE98 -> 8318.4596 | I9: =IFERROR((H9/C9)^(1/5)-1,"n/m") -> 0.13150178 | N9: Net sales | O9: 4485.044 | P9: 5443.5912 | Q9: 6409.7482 | R9: 7398.2394 | S9: 8435.3387 | T9: 9577.7423 | U9: 0.1638561 | Z9: Net sales | AA9: 4485.044 | AB9: 5443.5912 | AC9: 5983.1327 | AD9: 6366.7893 | AE9: 6731.7709 | AF9: 7128.1724 | AG9: 0.097090102
B10: Net sales y/y % | D10: =IFERROR(D9/C9-1,"") -> 0.21372081 | E10: =IFERROR(E9/D9-1,"") -> 0.1383001 | F10: =IFERROR(F9/E9-1,"") -> 0.10992999 | G10: =IFERROR(G9/F9-1,"") -> 0.10031731 | H10: =IFERROR(H9/G9-1,"") -> 0.099226266 | N10: Net sales y/y % | P10: 0.21372081 | Q10: 0.17748521 | R10: 0.15421685 | S10: 0.14018191 | T10: 0.13543068 | Z10: Net sales y/y % | AB10: 0.21372081 | AC10: 0.099114983 | AD10: 0.06412303 | AE10: 0.057325841 | AF10: 0.058885176
B11: FSG net sales y/y % | C11: =Model!BV12 -> 0.18107575 | D11: =Model!CA12 -> 0.18109137 | E11: =Model!CB12 -> 0.11 | F11: =Model!CC12 -> 0.08 | G11: =Model!CD12 -> 0.07 | H11: =Model!CE12 -> 0.07 | N11: FSG net sales y/y % | O11: 0.18107575 | P11: 0.18109137 | Q11: 0.14 | R11: 0.11 | S11: 0.1 | T11: 0.1 | Z11: FSG net sales y/y % | AA11: 0.18107575 | AB11: 0.18109137 | AC11: 0.08 | AD11: 0.05 | AE11: 0.04 | AF11: 0.04
B12: Adjusted EBITDA (model definition) | C12: =Model!BV140 -> 1232.427 | D12: =Model!CA140 -> 1566.8443 | E12: =Model!CB140 -> 1768.1261 | F12: =Model!CC140 -> 1969.9593 | G12: =Model!CD140 -> 2143.4905 | H12: =Model!CE140 -> 2331.8376 | I12: =IFERROR((H12/C12)^(1/5)-1,"n/m") -> 0.13602378 | N12: Adjusted EBITDA (model definition) | O12: 1232.427 | P12: 1566.8443 | Q12: 1918.0224 | R12: 2211.1119 | S12: 2485.7066 | T12: 2787.7401 | U12: 0.17733002 | Z12: Adjusted EBITDA (model definition) | AA12: 1232.427 | AB12: 1566.8443 | AC12: 1623.1829 | AD12: 1742.2543 | AE12: 1827.2575 | AF12: 1919.2123 | AG12: 0.092628096
B13: Adjusted EBITDA margin % | C13: =IFERROR(C12/C9,"") -> 0.27478593 | D13: =IFERROR(D12/D9,"") -> 0.28783283 | E13: =IFERROR(E12/E9,"") -> 0.28534545 | F13: =IFERROR(F12/F9,"") -> 0.28643058 | G13: =IFERROR(G12/G9,"") -> 0.28324728 | H13: =IFERROR(H12/H9,"") -> 0.28032085 | J13: =IFERROR(AVERAGE(Model!C141,Model!D141,Model!E141,Model!F141,Model!G141,Model!H141,Model!I141,Model!N141,Model!S141,Model!X141,Model!AC141,Model!AH141,Model!AM141,Model!AR141,Model!AW141,Model!BB141,Model!BG141,Model!BL141,Model!BQ141,Model!BV141),"") -> 0.2340543 | K13: =IFERROR(MIN(Model!C141,Model!D141,Model!E141,Model!F141,Model!G141,Model!H141,Model!I141,Model!N141,Model!S141,Model!X141,Model!AC141,Model!AH141,Model!AM141,Model!AR141,Model!AW141,Model!BB141,Model!BG141,Model!BL141,Model!BQ141,Model!BV141),"") -> 0.1926951 | L13: =IFERROR(MAX(Model!C141,Model!D141,Model!E141,Model!F141,Model!G141,Model!H141,Model!I141,Model!N141,Model!S141,Model!X141,Model!AC141,Model!AH141,Model!AM141,Model!AR141,Model!AW141,Model!BB141,Model!BG141,Model!BL141,Model!BQ141,Model!BV141),"") -> 0.27478593 | N13: Adjusted EBITDA margin % | O13: 0.27478593 | P13: 0.28783283 | Q13: 0.29923521 | R13: 0.29887002 | S13: 0.29467775 | T13: 0.29106443 | V13: 0.2340543 | W13: 0.1926951 | X13: 0.27478593 | Z13: Adjusted EBITDA margin % | AA13: 0.27478593 | AB13: 0.28783283 | AC13: 0.27129314 | AD13: 0.27364723 | AE13: 0.27143787 | AF13: 0.26924325 | AH13: 0.2340543 | AI13: 0.1926951 | AJ13: 0.27478593
B15: Operating Income (GAAP) | C15: =Model!BV102 -> 1018.998 | D15: =Model!CA102 -> 1326.8491 | E15: =Model!CB102 -> 1511.3915 | F15: =Model!CC102 -> 1697.5986 | G15: =Model!CD102 -> 1853.2298 | H15: =Model!CE102 -> 2021.9866 | I15: =IFERROR((H15/C15)^(1/5)-1,"n/m") -> 0.14688794 | N15: Operating Income (GAAP) | O15: 1018.998 | P15: 1326.8491 | Q15: 1655.3281 | R15: 1921.8277 | S15: 2166.5713 | T15: 2435.9861 | U15: 0.19042022 | Z15: Operating Income (GAAP) | AA15: 1018.998 | AB15: 1326.8491 | AC15: 1372.408 | AD15: 1486.6994 | AE15: 1565.4876 | AF15: 1650.4363 | AG15: 0.10124789
B16: Operating income y/y % | D16: =IFERROR(D15/C15-1,"") -> 0.30211159 | E16: =IFERROR(E15/D15-1,"") -> 0.13908317 | F16: =IFERROR(F15/E15-1,"") -> 0.12320242 | G16: =IFERROR(G15/F15-1,"") -> 0.0916773 | H16: =IFERROR(H15/G15-1,"") -> 0.091060886 | N16: Operating income y/y % | P16: 0.30211159 | Q16: 0.24756316 | R16: 0.16099507 | S16: 0.12734938 | T16: 0.12435076 | Z16: Operating income y/y % | AB16: 0.30211159 | AC16: 0.034336115 | AD16: 0.083278078 | AE16: 0.052995363 | AF16: 0.054263402
B17: Operating margin (GAAP) % | C17: =IFERROR(C15/C9,"") -> 0.22719911 | D17: =IFERROR(D15/D9,"") -> 0.24374518 | E17: =IFERROR(E15/E9,"") -> 0.24391286 | F17: =IFERROR(F15/F9,"") -> 0.24682954 | G17: =IFERROR(G15/G9,"") -> 0.24489136 | H17: =IFERROR(H15/H9,"") -> 0.24307224 | J17: =IFERROR(AVERAGE(Model!C179,Model!D179,Model!E179,Model!F179,Model!G179,Model!H179,Model!I179,Model!N179,Model!S179,Model!X179,Model!AC179,Model!AH179,Model!AM179,Model!AR179,Model!AW179,Model!BB179,Model!BG179,Model!BL179,Model!BQ179,Model!BV179),"") -> 0.19530214 | K17: =IFERROR(MIN(Model!C179,Model!D179,Model!E179,Model!F179,Model!G179,Model!H179,Model!I179,Model!N179,Model!S179,Model!X179,Model!AC179,Model!AH179,Model!AM179,Model!AR179,Model!AW179,Model!BB179,Model!BG179,Model!BL179,Model!BQ179,Model!BV179),"") -> 0.16395255 | L17: =IFERROR(MAX(Model!C179,Model!D179,Model!E179,Model!F179,Model!G179,Model!H179,Model!I179,Model!N179,Model!S179,Model!X179,Model!AC179,Model!AH179,Model!AM179,Model!AR179,Model!AW179,Model!BB179,Model!BG179,Model!BL179,Model!BQ179,Model!BV179),"") -> 0.22719911 | N17: Operating margin (GAAP) % | O17: 0.22719911 | P17: 0.24374518 | Q17: 0.25825165 | R17: 0.25976825 | S17: 0.25684461 | T17: 0.25433823 | V17: 0.19530214 | W17: 0.16395255 | X17: 0.22719911 | Z17: Operating margin (GAAP) % | AA17: 0.22719911 | AB17: 0.24374518 | AC17: 0.22937949 | AD17: 0.2335085 | AE17: 0.23255213 | AF17: 0.23153709 | AH17: 0.19530214 | AI17: 0.16395255 | AJ17: 0.22719911
B19: Adjusted Net Income (attributable to HEICO) | C19: =Model!BV161 -> 674.87505 | D19: =Model!CA161 -> 906.79301 | E19: =Model!CB161 -> 1023.5469 | F19: =Model!CC161 -> 1161.1216 | G19: =Model!CD161 -> 1276.106 | H19: =Model!CE161 -> 1400.7879 | I19: =IFERROR((H19/C19)^(1/5)-1,"n/m") -> 0.15725697 | N19: Adjusted Net Income (attributable to HEICO) | O19: 674.87505 | P19: 906.79301 | Q19: 1129.891 | R19: 1302.6421 | S19: 1467.8741 | T19: 1652.3176 | U19: 0.19611801 | Z19: Adjusted Net Income (attributable to HEICO) | AA19: 674.87505 | AB19: 906.79301 | AC19: 920.86219 | AD19: 1005.3037 | AE19: 1063.5145 | AF19: 1126.2768 | AG19: 0.10785866
B21: FDSO (m) | C21: =Model!BV118 -> 140.771 | D21: =Model!CA118 -> 141.15875 | E21: =Model!CB118 -> 141.52441 | F21: =Model!CC118 -> 141.09338 | G21: =Model!CD118 -> 139.93619 | H21: =Model!CE118 -> 138.69482 | I21: =IFERROR((H21/C21)^(1/5)-1,"n/m") -> -0.0029672785 | N21: FDSO (m) | O21: 140.771 | P21: 141.15875 | Q21: 140.45028 | R21: 138.98491 | S21: 137.90613 | T21: 136.64129 | U21: -0.0059373588 | Z21: FDSO (m) | AA21: 140.771 | AB21: 141.15875 | AC21: 141.52441 | AD21: 141.70877 | AE21: 141.028 | AF21: 139.60809 | AG21: -0.0016576937
B23: Adjusted EPS — Diluted ($) | C23: =Model!BV163 -> 4.7941341 | D23: =Model!CA163 -> 6.4239235 | E23: =Model!CB163 -> 7.2322994 | F23: =Model!CC163 -> 8.2294547 | G23: =Model!CD163 -> 9.1191994 | H23: =Model!CE163 -> 10.099785 | I23: =IFERROR((H23/C23)^(1/5)-1,"n/m") -> 0.16070109 | N23: Adjusted EPS — Diluted ($) | O23: 4.7941341 | P23: 6.4239235 | Q23: 8.0447754 | R23: 9.3725437 | S23: 10.644008 | T23: 12.092374 | U23: 0.20326221 | Z23: Adjusted EPS — Diluted ($) | AA23: 4.7941341 | AB23: 6.4239235 | AC23: 6.5067377 | AD23: 7.0941533 | AE23: 7.5411586 | AF23: 8.0674184 | AG23: 0.1096982
B24: EPS y/y % | D24: =IFERROR(D23/C23-1,"") -> 0.33995491 | E24: =IFERROR(E23/D23-1,"") -> 0.12583834 | F24: =IFERROR(F23/E23-1,"") -> 0.13787528 | G24: =IFERROR(G23/F23-1,"") -> 0.10811708 | H24: =IFERROR(H23/G23-1,"") -> 0.10752982 | N24: EPS y/y % | P24: 0.33995491 | Q24: 0.25231494 | R24: 0.16504728 | S24: 0.13565845 | T24: 0.1360733 | Z24: EPS y/y % | AB24: 0.33995491 | AC24: 0.012891533 | AD24: 0.090278039 | AE24: 0.06301039 | AF24: 0.069785003
B26: P / E (x) — assumed (adjusted EPS) | F26: 42 | G26: 42 | H26: 42 | N26: P / E (x) — assumed (adjusted EPS) | R26: 48 | S26: 48 | T26: 48 | Z26: P / E (x) — assumed (adjusted EPS) | AD26: 34 | AE26: 34 | AF26: 34
B27: Price Target ($) | F27: =F26*F23 -> 345.6371 | G27: =G26*G23 -> 383.00637 | H27: =H26*H23 -> 424.19098 | N27: Price Target ($) | R27: 449.8821 | S27: 510.91241 | T27: 580.43394 | Z27: Price Target ($) | AD27: 241.20121 | AE27: 256.39939 | AF27: 274.29223
B28: Upside / (Downside) vs current | F28: =IFERROR(F27/$K$2-1,"") -> 0.14279087 | G28: =IFERROR(G27/$K$2-1,"") -> 0.26634608 | H28: =IFERROR(H27/$K$2-1,"") -> 0.40251605 | N28: Upside / (Downside) vs current | R28: 0.48745941 | S28: 0.68924584 | T28: 0.91910711 | Z28: Upside / (Downside) vs current | AD28: -0.20250881 | AE28: -0.15225858 | AF28: -0.093098938
B29: IRR (to fiscal year-end Y-1, 31-Oct) | F29: =IFERROR((F27/$K$2)^(1/((DATE(2028-1,10,31)-$K$3)/365.25))-1,"") -> 0.13315182 | G29: =IFERROR((G27/$K$2)^(1/((DATE(2029-1,10,31)-$K$3)/365.25))-1,"") -> 0.12084782 | H29: =IFERROR((H27/$K$2)^(1/((DATE(2030-1,10,31)-$K$3)/365.25))-1,"") -> 0.11651939 | N29: IRR (to fiscal year-end Y-1, 31-Oct) | R29: 0.45044575 | S29: 0.28826845 | T29: 0.23663304 | Z29: IRR (to fiscal year-end Y-1, 31-Oct) | AD29: -0.19097392 | AE29: -0.076702742 | AF29: -0.031338696
B31: Free Cash Flow | C31: =Model!BV214 -> 861.38 | D31: =Model!CA214 -> 1032.757 | E31: =Model!CB214 -> 1113.1481 | F31: =Model!CC214 -> 1288.9096 | G31: =Model!CD214 -> 1422.789 | H31: =Model!CE214 -> 1555.0475 | I31: =IFERROR((H31/C31)^(1/5)-1,"n/m") -> 0.12540742 | N31: Free Cash Flow | O31: 861.38 | P31: 1032.757 | Q31: 1177.6391 | R31: 1375.8734 | S31: 1562.8733 | T31: 1758.0667 | U31: 0.15336857 | Z31: Free Cash Flow | AA31: 861.38 | AB31: 1032.757 | AC31: 1052.5948 | AD31: 1184.1114 | AE31: 1254.7877 | AF31: 1318.1744 | AG31: 0.088818825
B32: FCF % | C32: =IFERROR(C31/C9,"") -> 0.19205609 | D32: =IFERROR(D31/D9,"") -> 0.18971979 | E32: =IFERROR(E31/E9,"") -> 0.17964316 | F32: =IFERROR(F31/F9,"") -> 0.18740648 | G32: =IFERROR(G31/G9,"") -> 0.18801162 | H32: =IFERROR(H31/H9,"") -> 0.18693935 | J32: =IFERROR(AVERAGE(Model!C216,Model!D216,Model!E216,Model!F216,Model!G216,Model!H216,Model!I216,Model!N216,Model!S216,Model!X216,Model!AC216,Model!AH216,Model!AM216,Model!AR216,Model!AW216,Model!BB216,Model!BG216,Model!BL216,Model!BQ216,Model!BV216),"") -> 0.1521048 | K32: =IFERROR(MIN(Model!C216,Model!D216,Model!E216,Model!F216,Model!G216,Model!H216,Model!I216,Model!N216,Model!S216,Model!X216,Model!AC216,Model!AH216,Model!AM216,Model!AR216,Model!AW216,Model!BB216,Model!BG216,Model!BL216,Model!BQ216,Model!BV216),"") -> 0.087737536 | L32: =IFERROR(MAX(Model!C216,Model!D216,Model!E216,Model!F216,Model!G216,Model!H216,Model!I216,Model!N216,Model!S216,Model!X216,Model!AC216,Model!AH216,Model!AM216,Model!AR216,Model!AW216,Model!BB216,Model!BG216,Model!BL216,Model!BQ216,Model!BV216),"") -> 0.21863372 | N32: FCF % | O32: 0.19205609 | P32: 0.18971979 | Q32: 0.18372626 | R32: 0.18597309 | S32: 0.18527689 | T32: 0.18355753 | V32: 0.1521048 | W32: 0.087737536 | X32: 0.21863372 | Z32: FCF % | AA32: 0.19205609 | AB32: 0.18971979 | AC32: 0.17592704 | AD32: 0.1859825 | AE32: 0.18639787 | AF32: 0.1849246 | AH32: 0.1521048 | AI32: 0.087737536 | AJ32: 0.21863372
B33: FCF / share ($) | C33: =IFERROR(C31/C21,"") -> 6.119016 | D33: =IFERROR(D31/D21,"") -> 7.3162804 | E33: =IFERROR(E31/E21,"") -> 7.8654145 | F33: =IFERROR(F31/F21,"") -> 9.1351532 | G33: =IFERROR(G31/G21,"") -> 10.167413 | H33: =IFERROR(H31/H21,"") -> 11.212008 | N33: FCF / share ($) | O33: 6.119016 | P33: 7.3162804 | Q33: 8.3847396 | R33: 9.8994446 | S33: 11.332877 | T33: 12.866292 | Z33: FCF / share ($) | AA33: 6.119016 | AB33: 7.3162804 | AC33: 7.4375499 | AD33: 8.3559499 | AE33: 8.8974369 | AF33: 9.4419635
B34: FCF Yield (on PT) | F34: =IFERROR(F33/F$27,"") -> 0.026429898 | G34: =IFERROR(G33/G$27,"") -> 0.026546328 | H34: =IFERROR(H33/H$27,"") -> 0.02643151 | N34: FCF Yield (on PT) | R34: 0.022004531 | S34: 0.022181645 | T34: 0.022166677 | Z34: FCF Yield (on PT) | AD34: 0.034643068 | AE34: 0.034701474 | AF34: 0.034423008
B35: Adjusted EBITDA (fiscal year) | C35: =Model!BV140 -> 1232.427 | D35: =Model!CA140 -> 1566.8443 | E35: =Model!CB140 -> 1768.1261 | F35: =Model!CC140 -> 1969.9593 | G35: =Model!CD140 -> 2143.4905 | H35: =Model!CE140 -> 2331.8376 | I35: =IFERROR((H35/C35)^(1/5)-1,"n/m") -> 0.13602378 | N35: Adjusted EBITDA (fiscal year) | O35: 1232.427 | P35: 1566.8443 | Q35: 1918.0224 | R35: 2211.1119 | S35: 2485.7066 | T35: 2787.7401 | U35: 0.17733002 | Z35: Adjusted EBITDA (fiscal year) | AA35: 1232.427 | AB35: 1566.8443 | AC35: 1623.1829 | AD35: 1742.2543 | AE35: 1827.2575 | AF35: 1919.2123 | AG35: 0.092628096
B36: Adjusted EBITDA % of net sales | C36: =IFERROR(C35/C9,"") -> 0.27478593 | D36: =IFERROR(D35/D9,"") -> 0.28783283 | E36: =IFERROR(E35/E9,"") -> 0.28534545 | F36: =IFERROR(F35/F9,"") -> 0.28643058 | G36: =IFERROR(G35/G9,"") -> 0.28324728 | H36: =IFERROR(H35/H9,"") -> 0.28032085 | J36: =IFERROR(AVERAGE(Model!C141,Model!D141,Model!E141,Model!F141,Model!G141,Model!H141,Model!I141,Model!N141,Model!S141,Model!X141,Model!AC141,Model!AH141,Model!AM141,Model!AR141,Model!AW141,Model!BB141,Model!BG141,Model!BL141,Model!BQ141,Model!BV141),"") -> 0.2340543 | K36: =IFERROR(MIN(Model!C141,Model!D141,Model!E141,Model!F141,Model!G141,Model!H141,Model!I141,Model!N141,Model!S141,Model!X141,Model!AC141,Model!AH141,Model!AM141,Model!AR141,Model!AW141,Model!BB141,Model!BG141,Model!BL141,Model!BQ141,Model!BV141),"") -> 0.1926951 | L36: =IFERROR(MAX(Model!C141,Model!D141,Model!E141,Model!F141,Model!G141,Model!H141,Model!I141,Model!N141,Model!S141,Model!X141,Model!AC141,Model!AH141,Model!AM141,Model!AR141,Model!AW141,Model!BB141,Model!BG141,Model!BL141,Model!BQ141,Model!BV141),"") -> 0.27478593 | N36: Adjusted EBITDA % of net sales | O36: 0.27478593 | P36: 0.28783283 | Q36: 0.29923521 | R36: 0.29887002 | S36: 0.29467775 | T36: 0.29106443 | V36: 0.2340543 | W36: 0.1926951 | X36: 0.27478593 | Z36: Adjusted EBITDA % of net sales | AA36: 0.27478593 | AB36: 0.28783283 | AC36: 0.27129314 | AD36: 0.27364723 | AE36: 0.27143787 | AF36: 0.26924325 | AH36: 0.2340543 | AI36: 0.1926951 | AJ36: 0.27478593
B38: Net Debt | C38: =Model!BV334 -> 1950.164 | D38: =Model!CA334 -> 2042.081 | E38: =Model!CB334 -> 1821.1558 | F38: =Model!CC334 -> 1969.9593 | G38: =Model!CD334 -> 2143.4905 | H38: =Model!CE334 -> 2331.8376 | I38: =IFERROR((H38/C38)^(1/5)-1,"n/m") -> 0.0363953 | N38: Net Debt | O38: 1950.164 | P38: 2042.081 | Q38: 2877.0336 | R38: 3316.6679 | S38: 3728.56 | T38: 4181.6102 | U38: 0.16480837 | Z38: Net Debt | AA38: 1950.164 | AB38: 2042.081 | AC38: 1476.244 | AD38: 871.12713 | AE38: 913.62877 | AF38: 959.60616 | AG38: -0.13223051
B39: Net Debt / Adjusted EBITDA (x) | C39: =IFERROR(C38/C35,"") -> 1.5823769 | D39: =IFERROR(D38/D35,"") -> 1.3033082 | E39: =IFERROR(E38/E35,"") -> 1.029992 | F39: =IFERROR(F38/F35,"") -> 1 | G39: =IFERROR(G38/G35,"") -> 1 | H39: =IFERROR(H38/H35,"") -> 1 | N39: Net Debt / Adjusted EBITDA (x) | O39: 1.5823769 | P39: 1.3033082 | Q39: 1.5 | R39: 1.5 | S39: 1.5 | T39: 1.5 | Z39: Net Debt / Adjusted EBITDA (x) | AA39: 1.5823769 | AB39: 1.3033082 | AC39: 0.90947486 | AD39: 0.5 | AE39: 0.5 | AF39: 0.5
B41: ROIC | C41: =Model!BV317 -> 0.12722348 | D41: =Model!CA317 -> 0.13639888 | E41: =Model!CB317 -> 0.13725401 | F41: =Model!CC317 -> 0.14101565 | G41: =Model!CD317 -> 0.14056632 | H41: =Model!CE317 -> 0.14100479 | J41: =IFERROR(AVERAGE(Model!C317,Model!D317,Model!E317,Model!F317,Model!G317,Model!H317,Model!I317,Model!N317,Model!S317,Model!X317,Model!AC317,Model!AH317,Model!AM317,Model!AR317,Model!AW317,Model!BB317,Model!BG317,Model!BL317,Model!BQ317,Model!BV317),"") -> 0.12116261 | K41: =IFERROR(MIN(Model!C317,Model!D317,Model!E317,Model!F317,Model!G317,Model!H317,Model!I317,Model!N317,Model!S317,Model!X317,Model!AC317,Model!AH317,Model!AM317,Model!AR317,Model!AW317,Model!BB317,Model!BG317,Model!BL317,Model!BQ317,Model!BV317),"") -> 0.087345401 | L41: =IFERROR(MAX(Model!C317,Model!D317,Model!E317,Model!F317,Model!G317,Model!H317,Model!I317,Model!N317,Model!S317,Model!X317,Model!AC317,Model!AH317,Model!AM317,Model!AR317,Model!AW317,Model!BB317,Model!BG317,Model!BL317,Model!BQ317,Model!BV317),"") -> 0.15902279 | N41: ROIC | O41: 0.12722348 | P41: 0.13639888 | Q41: 0.14293323 | R41: 0.14561408 | S41: 0.14502837 | T41: 0.14590456 | V41: 0.12116261 | W41: 0.087345401 | X41: 0.15902279 | Z41: ROIC | AA41: 0.12722348 | AB41: 0.13639888 | AC41: 0.13143166 | AD41: 0.13662242 | AE41: 0.13684743 | AF41: 0.13745841 | AH41: 0.12116261 | AI41: 0.087345401 | AJ41: 0.15902279
B42: RONTA | C42: =Model!BV328 -> 0.34060395 | D42: =Model!CA328 -> 0.36585045 | E42: =Model!CB328 -> 0.35009149 | F42: =Model!CC328 -> 0.38141037 | G42: =Model!CD328 -> 0.40497533 | H42: =Model!CE328 -> 0.41383009 | J42: =IFERROR(AVERAGE(Model!C328,Model!D328,Model!E328,Model!F328,Model!G328,Model!H328,Model!I328,Model!N328,Model!S328,Model!X328,Model!AC328,Model!AH328,Model!AM328,Model!AR328,Model!AW328,Model!BB328,Model!BG328,Model!BL328,Model!BQ328,Model!BV328),"") -> 0.30537876 | K42: =IFERROR(MIN(Model!C328,Model!D328,Model!E328,Model!F328,Model!G328,Model!H328,Model!I328,Model!N328,Model!S328,Model!X328,Model!AC328,Model!AH328,Model!AM328,Model!AR328,Model!AW328,Model!BB328,Model!BG328,Model!BL328,Model!BQ328,Model!BV328),"") -> 0.2318545 | L42: =IFERROR(MAX(Model!C328,Model!D328,Model!E328,Model!F328,Model!G328,Model!H328,Model!I328,Model!N328,Model!S328,Model!X328,Model!AC328,Model!AH328,Model!AM328,Model!AR328,Model!AW328,Model!BB328,Model!BG328,Model!BL328,Model!BQ328,Model!BV328),"") -> 0.44073179 | N42: RONTA | O42: 0.34060395 | P42: 0.36585045 | Q42: 0.41958767 | R42: 0.43678764 | S42: 0.44244272 | T42: 0.44720684 | V42: 0.30537876 | W42: 0.2318545 | X42: 0.44073179 | Z42: RONTA | AA42: 0.34060395 | AB42: 0.36585045 | AC42: 0.29507912 | AD42: 0.26554302 | AE42: 0.27264255 | AF42: 0.27981477 | AH42: 0.30537876 | AI42: 0.2318545 | AJ42: 0.44073179
B44: Implied Market Cap (USDm) | F44: =F27*F21 -> 48767.105 | G44: =G27*G21 -> 53596.453 | H44: =H27*H21 -> 58833.093 | N44: Implied Market Cap (USDm) | R44: 62526.822 | S44: 70457.955 | T44: 79311.244 | Z44: Implied Market Cap (USDm) | AD44: 34180.327 | AE44: 36159.494 | AF44: 38293.413
B45: (+) Net Debt, redeemable NCI & NCI | F45: =F38+Model!CC343 -> 2720.4212 | G45: =G38+Model!CD343 -> 2923.0595 | H45: =H38+Model!CE343 -> 3143.3577 | N45: (+) Net Debt, redeemable NCI & NCI | R45: 4072.7834 | S45: 4518.1567 | T45: 5008.8952 | Z45: (+) Net Debt, redeemable NCI & NCI | AD45: 1615.6928 | AE45: 1682.4524 | AF45: 1754.1194
B46: Implied Enterprise Value (USDm) | F46: =F44+F45 -> 51487.527 | G46: =G44+G45 -> 56519.512 | H46: =H44+H45 -> 61976.451 | N46: Implied Enterprise Value (USDm) | R46: 66599.606 | S46: 74976.112 | T46: 84320.139 | Z46: Implied Enterprise Value (USDm) | AD46: 35796.02 | AE46: 37841.946 | AF46: 40047.532
B47: Implied EV / Adjusted EBITDA (x) | F47: =IFERROR(F46/F35,"") -> 26.13634 | G47: =IFERROR(G46/G35,"") -> 26.367979 | H47: =IFERROR(H46/H35,"") -> 26.578373 | N47: Implied EV / Adjusted EBITDA (x) | R47: 30.120414 | S47: 30.162896 | T47: 30.246771 | Z47: Implied EV / Adjusted EBITDA (x) | AD47: 20.545807 | AE47: 20.709695 | AF47: 20.86665

Sheet DCF
B2: DCF VALUATION — HEICO CORPORATION (HEI)
B4: 1. WACC BUILD
B5: Risk-free rate (US 10Y govt) | C5: 0.045 | D5: Assumption (~US 10Y Treasury yield, Oct-2026); update to market
B6: Equity risk premium | C6: 0.05 | D6: US implied ERP ~4.5–5.5% (Damodaran)
B7: Levered beta | C7: 1.1 | D7: Aerospace aftermarket / defense-electronics peers (TransDigm, Howmet, Curtiss-Wright, Amphenol) ~0.9–1.3; commercial-aerospace cyclicality partly offset by defense / space mix
B8: Cost of equity | C8: =C5+C7*C6 -> 0.1
B9: Pre-tax cost of debt | C9: 0.054 | D9: Investment grade (BBB / Baa2); Jul-2026 notes priced at 4.95% (2031) and 5.40% (2036); marginal cost ~5.4%
B10: Tax rate | C10: 0.205 | D10: Model 2027E+ effective tax rate
B11: After-tax cost of debt | C11: =C9*(1-C10) -> 0.04293
B12: Target D/V | C12: 0.05 | D12: Net debt ~$2.3bn at FY2026E vs ~$43bn market cap ($302.45 × ~141m shares); HEICO runs ~1–2x net debt / EBITDA
B13: WACC | C13: =C8*(1-C12)+C11*C12 -> 0.0971465
B15: Valuation date (live) | C15: =TODAY() -> 46301 | D15: Periods = (31-Oct-Year − today) / 365.25 (HEICO fiscal year ends 31 October); cash flows assumed at fiscal year-end
B16: 2. UNLEVERED FREE CASH FLOW BUILD (USDm)
D17: 2027E | E17: 2028E | F17: 2029E | G17: 2030E | H17: 2031E | I17: 2032E | J17: 2033E | K17: 2034E | L17: 2035E | M17: 2036E | N17: Terminal | P17: CAGR 27–30E | Q17: CAGR 27–36E
B18: Adj. EBIT less acquisition costs | D18: =Model!CB145-Model!CB139 -> 1516.1688 | E18: =Model!CC145-Model!CC139 -> 1702.3759 | F18: =Model!CD145-Model!CD139 -> 1858.0072 | G18: =Model!CE145-Model!CE139 -> 2026.7639 | H18: =G18*(1+H$26) -> 2229.4403 | I18: =H18*(1+I$26) -> 2434.5488 | J18: =I18*(1+J$26) -> 2639.0509 | K18: =J18*(1+K$26) -> 2839.6188 | L18: =K18*(1+L$26) -> 3032.7128 | M18: =L18*(1+M$26) -> 3214.6756 | P18: =(G18/D18)^(1/(COLUMNS(D18:G18)-1))-1 -> 0.10158632 | Q18: =(M18/D18)^(1/(COLUMNS(D18:M18)-1))-1 -> 0.087090025
B19: × (1 − tax rate) | D19: =1-$C$10 -> 0.795 | E19: =1-$C$10 -> 0.795 | F19: =1-$C$10 -> 0.795 | G19: =1-$C$10 -> 0.795 | H19: =1-$C$10 -> 0.795 | I19: =1-$C$10 -> 0.795 | J19: =1-$C$10 -> 0.795 | K19: =1-$C$10 -> 0.795 | ... M19: =1-$C$10 -> 0.795
B20: NOPAT | D20: =D18*D19 -> 1205.3542 | E20: =E18*E19 -> 1353.3888 | F20: =F18*F19 -> 1477.1157 | G20: =G18*G19 -> 1611.2773 | H20: =H18*H19 -> 1772.405 | I20: =I18*I19 -> 1935.4663 | J20: =J18*J19 -> 2098.0455 | K20: =K18*K19 -> 2257.4969 | ... M20: =M18*M19 -> 2555.6671
B21: plus D&A (incl. acquired-intangible amortization) | D21: =Model!CB114 -> 251.95729 | E21: =Model!CC114 -> 267.58338 | F21: =Model!CD114 -> 285.48335 | G21: =Model!CE114 -> 305.07374 | H21: =G21*(1+H$26) -> 335.58111 | I21: =H21*(1+I$26) -> 366.45458 | J21: =I21*(1+J$26) -> 397.23676 | K21: =J21*(1+K$26) -> 427.42675 | L21: =K21*(1+L$26) -> 456.49177 | M21: =L21*(1+M$26) -> 483.88128
B22: − Capex and acquisitions (M&A lever 2027E–30E) | D22: =Model!CB194+Model!CB195 -> -899.14305 | E22: =Model!CC194+Model!CC195 -> -910.04184 | F22: =Model!CD194+Model!CD195 -> -1021.0809 | G22: =Model!CE194+Model!CE195 -> -1033.0954 | H22: =Model!CE194*(1+H$26) -> -146.40489 | I22: =H22*(1+I$26) -> -159.87414 | J22: =I22*(1+J$26) -> -173.30357 | K22: =J22*(1+K$26) -> -186.47464 | L22: =K22*(1+L$26) -> -199.15491 | M22: =L22*(1+M$26) -> -211.10421
B23: − Δ Working capital (CF statement) | D23: =Model!CB192 -> -190.60586 | E23: =Model!CC192 -> -173.05569 | F23: =Model!CD192 -> -175.28354 | G23: =Model!CE192 -> -190.7699 | H23: =G23*(1+H$26) -> -209.84689 | I23: =H23*(1+I$26) -> -229.15281 | J23: =I23*(1+J$26) -> -248.40164 | K23: =J23*(1+K$26) -> -267.28017 | L23: =K23*(1+L$26) -> -285.45522 | M23: =L23*(1+M$26) -> -302.58253
B24: Unlevered FCF | D24: =D20+D21+D22+D23 -> 367.56259 | E24: =E20+E21+E22+E23 -> 537.87469 | F24: =F20+F21+F22+F23 -> 566.23455 | G24: =G20+G21+G22+G23 -> 692.48579 | H24: =H20+H21+H22+H23 -> 1751.7344 | I24: =I20+I21+I22+I23 -> 1912.8939 | J24: =J20+J21+J22+J23 -> 2073.577 | K24: =K20+K21+K22+K23 -> 2231.1689 | ... M24: =M20+M21+M22+M23 -> 2525.8617 | N24: =M24*(1+$C$27) -> 2626.8961 | P24: =(G24/D24)^(1/(COLUMNS(D24:G24)-1))-1 -> 0.23507459 | Q24: =(M24/D24)^(1/(COLUMNS(D24:M24)-1))-1 -> 0.23882139
B25: Terminal Value (Gordon Growth) | N25: =N24/($C$13-$C$27) -> 45967.752
B26: Fade-period growth (2031E–36E; 10% → 6% linear) | H26: 0.1 | I26: =H26+($M$26-$H$26)/5 -> 0.092 | J26: =I26+($M$26-$H$26)/5 -> 0.084 | K26: =J26+($M$26-$H$26)/5 -> 0.076 | L26: =K26+($M$26-$H$26)/5 -> 0.068 | M26: 0.06
B27: Terminal growth rate | C27: 0.04
B29: Discount period (years) | D29: =(DATE(2027,10,31)-$C$15)/365.25 -> 1.0677618 | E29: =(DATE(2028,10,31)-$C$15)/365.25 -> 2.0698152 | F29: =(DATE(2029,10,31)-$C$15)/365.25 -> 3.0691307 | G29: =(DATE(2030,10,31)-$C$15)/365.25 -> 4.0684463 | H29: =(DATE(2031,10,31)-$C$15)/365.25 -> 5.0677618 | I29: =(DATE(2032,10,31)-$C$15)/365.25 -> 6.0698152 | J29: =(DATE(2033,10,31)-$C$15)/365.25 -> 7.0691307 | K29: =(DATE(2034,10,31)-$C$15)/365.25 -> 8.0684463 | L29: =(DATE(2035,10,31)-$C$15)/365.25 -> 9.0677618 | M29: =(DATE(2036,10,31)-$C$15)/365.25 -> 10.069815 | N29: =M29 -> 10.069815
B30: Discount factor | D30: =1/(1+$C$13)^D29 -> 0.90574715 | E30: =1/(1+$C$13)^E29 -> 0.82539089 | F30: =1/(1+$C$13)^F29 -> 0.75235465 | G30: =1/(1+$C$13)^G29 -> 0.68578116 | H30: =1/(1+$C$13)^H29 -> 0.62509854 | I30: =1/(1+$C$13)^I29 -> 0.56964093 | J30: =1/(1+$C$13)^J29 -> 0.5192352 | K30: =1/(1+$C$13)^K29 -> 0.47328971 | ... N30: =1/(1+$C$13)^N29 -> 0.39313589
B31: PV of UFCF | D31: =D24*D30 -> 332.91877 | E31: =E24*E30 -> 443.95687 | F31: =F24*F30 -> 426.0092 | G31: =G24*G30 -> 474.89371 | H31: =H24*H30 -> 1095.0066 | I31: =I24*I30 -> 1089.6627 | J31: =J24*J30 -> 1076.6742 | K31: =K24*K30 -> 1055.9893 | ... M31: =M24*M30 -> 993.00688 | N31: =N25*N30 -> 18071.573
D32: HEICO's EBITDA expenses share-based compensation; Adjusted EBIT deducts all D&A incl. ~$150–170m p.a. of acquired-intangible amortization (non-cash, added back in row 21). FY2026 is ~complete at the valuation date: its cash flows (incl. $1.0bn of 9M/26 acquisitions) sit in FY2026E year-end net debt, so the explicit period starts in FY2027E. Acquisition spend from the M&A lever is deducted in 2027E–30E (its earnings are in EBIT); the fade period and terminal value assume no new acquisitions.
B33: IMPLIED ROIC — invested capital roll-forward (USDm)
B34: Opening invested capital | D34: =Model!CA314 -> 7944.1317 | E34: =D38 -> 8781.9233 | F34: =E38 -> 9597.4374 | G34: =F38 -> 10508.319 | H34: =G38 -> 11427.11 | I34: =H38 -> 11447.781 | J34: =I38 -> 11470.353 | K34: =J38 -> 11494.822 | L34: =K38 -> 11521.15 | M34: =L38 -> 11549.268
B35: plus Capex and acquisitions | D35: =-D22 -> 899.14305 | E35: =-E22 -> 910.04184 | F35: =-F22 -> 1021.0809 | G35: =-G22 -> 1033.0954 | H35: =-H22 -> 146.40489 | I35: =-I22 -> 159.87414 | J35: =-J22 -> 173.30357 | K35: =-K22 -> 186.47464 | ... M35: =-M22 -> 211.10421
B36: less DD&A | D36: =-D21 -> -251.95729 | E36: =-E21 -> -267.58338 | F36: =-F21 -> -285.48335 | G36: =-G21 -> -305.07374 | H36: =-H21 -> -335.58111 | I36: =-I21 -> -366.45458 | J36: =-J21 -> -397.23676 | K36: =-K21 -> -427.42675 | ... M36: =-M21 -> -483.88128
B37: plus Δ Working capital investment | D37: =-D23 -> 190.60586 | E37: =-E23 -> 173.05569 | F37: =-F23 -> 175.28354 | G37: =-G23 -> 190.7699 | H37: =-H23 -> 209.84689 | I37: =-I23 -> 229.15281 | J37: =-J23 -> 248.40164 | K37: =-K23 -> 267.28017 | ... M37: =-M23 -> 302.58253
B38: Closing invested capital | D38: =SUM(D34:D37) -> 8781.9233 | E38: =SUM(E34:E37) -> 9597.4374 | F38: =SUM(F34:F37) -> 10508.319 | G38: =SUM(G34:G37) -> 11427.11 | H38: =SUM(H34:H37) -> 11447.781 | I38: =SUM(I34:I37) -> 11470.353 | J38: =SUM(J34:J37) -> 11494.822 | K38: =SUM(K34:K37) -> 11521.15 | ... M38: =SUM(M34:M37) -> 11579.073
B39: NOPAT (row 20) | D39: =D20 -> 1205.3542 | E39: =E20 -> 1353.3888 | F39: =F20 -> 1477.1157 | G39: =G20 -> 1611.2773 | H39: =H20 -> 1772.405 | I39: =I20 -> 1935.4663 | J39: =J20 -> 2098.0455 | K39: =K20 -> 2257.4969 | ... M39: =M20 -> 2555.6671
B40: Implied ROIC (NOPAT / avg. invested capital) | D40: =IFERROR(D39/AVERAGE(D34,D38),"") -> 0.14412893 | E40: =IFERROR(E39/AVERAGE(E34,E38),"") -> 0.14727268 | F40: =IFERROR(F39/AVERAGE(F34,F38),"") -> 0.14693461 | G40: =IFERROR(G39/AVERAGE(G34,G38),"") -> 0.14691095 | H40: =IFERROR(H39/AVERAGE(H34,H38),"") -> 0.15496511 | I40: =IFERROR(I39/AVERAGE(I34,I38),"") -> 0.16890261 | J40: =IFERROR(J39/AVERAGE(J34,J38),"") -> 0.18271539 | K40: =IFERROR(K39/AVERAGE(K34,K38),"") -> 0.19616786 | ... M40: =IFERROR(M39/AVERAGE(M34,M38),"") -> 0.22099874
B41: Reinvestment rate (net investment / NOPAT) | D41: =IFERROR(SUM(D35:D37)/D39,"") -> 0.69505844 | E41: =IFERROR(SUM(E35:E37)/E39,"") -> 0.60257195 | F41: =IFERROR(SUM(F35:F37)/F39,"") -> 0.61666202 | G41: =IFERROR(SUM(G35:G37)/G39,"") -> 0.57022557 | H41: =IFERROR(SUM(H35:H37)/H39,"") -> 0.011662496 | I41: =IFERROR(SUM(I35:I37)/I39,"") -> 0.011662496 | J41: =IFERROR(SUM(J35:J37)/J39,"") -> 0.011662496 | K41: =IFERROR(SUM(K35:K37)/K39,"") -> 0.011662496 | ... M41: =IFERROR(SUM(M35:M37)/M39,"") -> 0.011662496
B42: Implied terminal RONIC (g / reinvestment rate) | N42: =IFERROR($C$27/M41,"") -> 3.4297975
D43: Opening IC = Model FY2026E book invested capital (equity incl. NCI + redeemable NCI + net debt), rolled forward with capex + M&A − D&A + ΔWC.
B44: 3. VALUATION SUMMARY
B45: Sum of PV (explicit + fade) | C45: =SUM(D31:M31) -> 8016.1195
B46: PV of Terminal Value | C46: =N31 -> 18071.573
B47: Enterprise Value | C47: =C45+C46 -> 26087.693
B48: Less: Net debt + redeemable NCI + NCI (Model FY2026E year end) | C48: =Model!CA342+Model!CA343 -> 2742.7121 | D48: HEICO-specific: redeemable NCI (put rights at redemption value, ~$0.6bn) and NCI deducted alongside net debt (~7% of consolidated net income accrues to minority owners).
B49: Equity Value | C49: =C47-C48 -> 23344.981
B50: Diluted shares (m, Model FY2026E) | C50: =Model!CA340 -> 141.3744
B51: Implied share price ($) | C51: =C49/C50 -> 165.12876
B52: Current share price ($) | C52: =Model!CA339 -> 302.45
B53: Implied upside / (downside) | C53: =C51/C52-1 -> -0.45402955
B54: Required discount to DCF value for target IRR | C54: =1-((1+C13)/(1+H54))^H55 -> 0.13163893 | D54: vs. current | E54: Target IRR | H54: 0.15
B55: Max entry price for target IRR ($) | C55: =C51*(1-C54) -> 143.39139 | D55: =C55/C52-1 -> -0.52590052 | E55: Years for discount to close | H55: 3
B58: 4. SENSITIVITY: IMPLIED PRICE ($) — WACC × Terminal Growth
D60: WACC →
B61: Terminal growth ↓ | D61: =F61-0.01 -> 0.0871465 | E61: =F61-0.005 -> 0.0921465 | F61: =$C$13 -> 0.0971465 | G61: =F61+0.005 -> 0.1021465 | H61: =F61+0.01 -> 0.1071465
B62: =B64-0.01 -> 0.03 | D62: {=IFERROR((SUMPRODUCT($D$24:$M$24/(1+D$61)^$D$29:$M$29)+($M$24*(1+$B62)/(D$61-$B62))/(1+D$61)^$M$29-$C$48)/$C$50,"")} -> 179.62231 | E62: {=IFERROR((SUMPRODUCT($D$24:$M$24/(1+E$61)^$D$29:$M$29)+($M$24*(1+$B62)/(E$61-$B62))/(1+E$61)^$M$29-$C$48)/$C$50,"")} -> 160.90714 | F62: {=IFERROR((SUMPRODUCT($D$24:$M$24/(1+F$61)^$D$29:$M$29)+($M$24*(1+$B62)/(F$61-$B62))/(1+F$61)^$M$29-$C$48)/$C$50,"")} -> 145.04556 | G62: {=IFERROR((SUMPRODUCT($D$24:$M$24/(1+G$61)^$D$29:$M$29)+($M$24*(1+$B62)/(G$61-$B62))/(1+G$61)^$M$29-$C$48)/$C$50,"")} -> 131.44222 | H62: {=IFERROR((SUMPRODUCT($D$24:$M$24/(1+H$61)^$D$29:$M$29)+($M$24*(1+$B62)/(H$61-$B62))/(1+H$61)^$M$29-$C$48)/$C$50,"")} -> 119.65619
B63: =B64-0.005 -> 0.035 | D63: {=IFERROR((SUMPRODUCT($D$24:$M$24/(1+D$61)^$D$29:$M$29)+($M$24*(1+$B63)/(D$61-$B63))/(1+D$61)^$M$29-$C$48)/$C$50,"")} -> 193.67203 | E63: {=IFERROR((SUMPRODUCT($D$24:$M$24/(1+E$61)^$D$29:$M$29)+($M$24*(1+$B63)/(E$61-$B63))/(1+E$61)^$M$29-$C$48)/$C$50,"")} -> 172.21555 | F63: {=IFERROR((SUMPRODUCT($D$24:$M$24/(1+F$61)^$D$29:$M$29)+($M$24*(1+$B63)/(F$61-$B63))/(1+F$61)^$M$29-$C$48)/$C$50,"")} -> 154.27926 | G63: {=IFERROR((SUMPRODUCT($D$24:$M$24/(1+G$61)^$D$29:$M$29)+($M$24*(1+$B63)/(G$61-$B63))/(1+G$61)^$M$29-$C$48)/$C$50,"")} -> 139.07473 | H63: {=IFERROR((SUMPRODUCT($D$24:$M$24/(1+H$61)^$D$29:$M$29)+($M$24*(1+$B63)/(H$61-$B63))/(1+H$61)^$M$29-$C$48)/$C$50,"")} -> 126.03215
B64: =$C$27 -> 0.04 | D64: {=IFERROR((SUMPRODUCT($D$24:$M$24/(1+D$61)^$D$29:$M$29)+($M$24*(1+$B64)/(D$61-$B64))/(1+D$61)^$M$29-$C$48)/$C$50,"")} -> 210.70178 | E64: {=IFERROR((SUMPRODUCT($D$24:$M$24/(1+E$61)^$D$29:$M$29)+($M$24*(1+$B64)/(E$61-$B64))/(1+E$61)^$M$29-$C$48)/$C$50,"")} -> 185.69255 | F64: {=IFERROR((SUMPRODUCT($D$24:$M$24/(1+F$61)^$D$29:$M$29)+($M$24*(1+$B64)/(F$61-$B64))/(1+F$61)^$M$29-$C$48)/$C$50,"")} -> 165.12876 | G64: {=IFERROR((SUMPRODUCT($D$24:$M$24/(1+G$61)^$D$29:$M$29)+($M$24*(1+$B64)/(G$61-$B64))/(1+G$61)^$M$29-$C$48)/$C$50,"")} -> 147.93538 | H64: {=IFERROR((SUMPRODUCT($D$24:$M$24/(1+H$61)^$D$29:$M$29)+($M$24*(1+$B64)/(H$61-$B64))/(1+H$61)^$M$29-$C$48)/$C$50,"")} -> 133.35766
B65: =B64+0.005 -> 0.045 | D65: {=IFERROR((SUMPRODUCT($D$24:$M$24/(1+D$61)^$D$29:$M$29)+($M$24*(1+$B65)/(D$61-$B65))/(1+D$61)^$M$29-$C$48)/$C$50,"")} -> 231.77212 | E65: {=IFERROR((SUMPRODUCT($D$24:$M$24/(1+E$61)^$D$29:$M$29)+($M$24*(1+$B65)/(E$61-$B65))/(1+E$61)^$M$29-$C$48)/$C$50,"")} -> 202.02809 | F65: {=IFERROR((SUMPRODUCT($D$24:$M$24/(1+F$61)^$D$29:$M$29)+($M$24*(1+$B65)/(F$61-$B65))/(1+F$61)^$M$29-$C$48)/$C$50,"")} -> 178.05885 | G65: {=IFERROR((SUMPRODUCT($D$24:$M$24/(1+G$61)^$D$29:$M$29)+($M$24*(1+$B65)/(G$61-$B65))/(1+G$61)^$M$29-$C$48)/$C$50,"")} -> 158.34655 | H65: {=IFERROR((SUMPRODUCT($D$24:$M$24/(1+H$61)^$D$29:$M$29)+($M$24*(1+$B65)/(H$61-$B65))/(1+H$61)^$M$29-$C$48)/$C$50,"")} -> 141.86192
B66: =B64+0.01 -> 0.05 | D66: {=IFERROR((SUMPRODUCT($D$24:$M$24/(1+D$61)^$D$29:$M$29)+($M$24*(1+$B66)/(D$61-$B66))/(1+D$61)^$M$29-$C$48)/$C$50,"")} -> 258.5147 | E66: {=IFERROR((SUMPRODUCT($D$24:$M$24/(1+E$61)^$D$29:$M$29)+($M$24*(1+$B66)/(E$61-$B66))/(1+E$61)^$M$29-$C$48)/$C$50,"")} -> 222.23953 | F66: {=IFERROR((SUMPRODUCT($D$24:$M$24/(1+F$61)^$D$29:$M$29)+($M$24*(1+$B66)/(F$61-$B66))/(1+F$61)^$M$29-$C$48)/$C$50,"")} -> 193.73146 | G66: {=IFERROR((SUMPRODUCT($D$24:$M$24/(1+G$61)^$D$29:$M$29)+($M$24*(1+$B66)/(G$61-$B66))/(1+G$61)^$M$29-$C$48)/$C$50,"")} -> 170.75425 | H66: {=IFERROR((SUMPRODUCT($D$24:$M$24/(1+H$61)^$D$29:$M$29)+($M$24*(1+$B66)/(H$61-$B66))/(1+H$61)^$M$29-$C$48)/$C$50,"")} -> 151.85434
B69: 5. REVERSE DCF
B70: To solve for the market-implied path: Data ▸ What-If Analysis ▸ Goal Seek — set C51 to the current price (C52) by changing C27 (terminal growth) or the fade-period growth inputs (H26 / M26).
B72: 6. MAUBOUSSIN EV / NOPAT — TWO-STAGE FRAMEWORK
B73: EV/NOPAT = 1/r + [g × (1 − r/ROIIC) / (r × (r − g))] × [1 − ((1+g)/(1+r))^N]
B74: Formula source: Mauboussin & Rappaport, "Expectations Investing" (2021); Counterpoint Global, "What Does a Price-Earnings Multiple Mean?" (2020).
B76: Input | C76: Value | D76: Rationale (HEICO characteristics)
B77: r (Cost of capital / WACC) | C77: =$C$13 -> 0.0971465 | D77: Linked from Section 1 WACC build
B78: g (NOPAT growth, Stage 1) | C78: 0.1 | D78: Model Adjusted EBIT CAGR FY2026–30E (~11%; 10% used, below WACC): high-single-digit organic growth at both segments plus ~$0.8–0.9bn p.a. of acquisitions
B79: ROIIC (Return on incremental invested capital) | C79: 0.15 | D79: Organic reinvestment (PMA parts, repair capabilities, niche electronics R&D) earns very high returns on small capital (capex ~1.6% of sales); acquisitions at ~16x EBITDA earn ~7–9% after tax → blended ~15%
B80: N (Years of value creation / CAP) | C80: 15 | D80: Durable niche positions: FAA-approved PMA parts and DER repairs (~50% below OEM prices), sole-source defense / space electronics, decentralised acquisition engine with >100 subsidiaries and a 30+ year compounding record
B82: Calculation | C82: Value
B83: Steady-state component: 1 / r | C83: =1/C77 -> 10.293732
B84: Value-creation factor: 1 − r / ROIIC | C84: =1-C77/C79 -> 0.35235667
B85: Growth multiplier: g × (1 − r/ROIIC) / (r × (r − g)) | C85: =C78*C84/(C77*(C77-C78)) -> -127.10934
B86: Time decay: 1 − ((1+g)/(1+r))^N | C86: =1-((1+C78)/(1+C77))^C80 -> -0.039730891
B87: PVGO component (growth value) | C87: =C85*C86 -> 5.0501672
B88: Mauboussin EV / NOPAT (steady-state + PVGO) | C88: =C83+C87 -> 15.343899
B90: VALUATION — Applied to 2028E NOPAT | C90: USDm
B91: 2028E Adj. EBIT less acquisition costs | C91: =Model!CC145-Model!CC139 -> 1702.3759
B92: Tax rate (from WACC build) | C92: =$C$10 -> 0.205
B93: 2028E NOPAT | C93: =C91*(1-C92) -> 1353.3888
B94: × Mauboussin EV/NOPAT multiple | C94: =C88 -> 15.343899
B95: Implied Enterprise Value (2028E basis) | C95: =C93*C94 -> 20766.262
B96: Less: FY2027E net debt + redeemable NCI + NCI (Model) | C96: =Model!CB342+Model!CB343 -> 2545.1333
B97: Implied Equity Value | C97: =C95-C96 -> 18221.128
B98: Diluted shares 2028E (m, Model) | C98: =Model!CC340 -> 140.51235
B99: Implied share price 2028 ($) | C99: =C97/C98 -> 129.67635
B101: Current share price ($) | C101: =C52 -> 302.45
B102: Implied upside / (downside) | C102: =C99/C101-1 -> -0.57124699
B104: MARKET-IMPLIED EV/NOPAT TODAY | C104: USDm
B105: Current market cap (spot × diluted shares) | C105: =C52*C50 -> 42758.689
B106: Plus: FY2026E net debt + redeemable NCI + NCI | C106: =C48 -> 2742.7121
B107: Implied Enterprise Value (today) | C107: =C105+C106 -> 45501.401
B108: HEI market-implied EV/NOPAT (on 2028E NOPAT) | C108: =C107/C93 -> 33.620346
B110: Multiple gap (Mauboussin − Market) | C110: =C88-C108 -> -18.276447
B111: Implied re-rating headroom | C111: =C88/C108-1 -> -0.5436127

Sheet Charts
B2: HEICO Corporation — Historical Operating Performance (FY2006–FY2025)
B3: All historicals · USDm · fiscal years ending 31 October · Linked to Model. Segment growth = reported net sales y/y (organic + acquired). Adjusted EBITDA = company EBITDA + acquisition costs, contingent-consideration remeasurement and intangible impairments (model definition).
C7: 2006 | D7: 2007 | E7: 2008 | F7: 2009 | G7: 2010 | H7: 2011 | I7: 2012 | J7: 2013 | K7: 2014 | L7: 2015 | M7: 2016 | N7: 2017 | O7: 2018 | P7: 2019 | Q7: 2020 | R7: 2021 | S7: 2022 | T7: 2023 | U7: 2024 | V7: 2025
B8: FSG net sales y/y % | C8: =IFERROR(Model!C12+0,0) -> 0 | D8: =IFERROR(Model!D12+0,0) -> 0.38468558 | E8: =IFERROR(Model!E12+0,0) -> 0.13778975 | F8: =IFERROR(Model!F12+0,0) -> -0.094748289 | G8: =IFERROR(Model!G12+0,0) -> 0.042774447 | H8: =IFERROR(Model!H12+0,0) -> 0.30854859 | I8: =IFERROR(Model!I12+0,0) -> 0.057012805 | J8: =IFERROR(Model!N12+0,0) -> 0.16626134 | K8: =IFERROR(Model!S12+0,0) -> 0.14681394 | L8: =IFERROR(Model!X12+0,0) -> 0.061482615 | M8: =IFERROR(Model!AC12+0,0) -> 0.081721625 | N8: =IFERROR(Model!AH12+0,0) -> 0.10466165 | O8: =IFERROR(Model!AM12+0,0) -> 0.13477169 | P8: =IFERROR(Model!AR12+0,0) -> 0.12955752 | Q8: =IFERROR(Model!AW12+0,0) -> -0.25429392 | R8: =IFERROR(Model!BB12+0,0) -> 0.002462122 | S8: =IFERROR(Model!BG12+0,0) -> 0.35392826 | T8: =IFERROR(Model!BL12+0,0) -> 0.41026775 | U8: =IFERROR(Model!BQ12+0,0) -> 0.49100461 | V8: =IFERROR(Model!BV12+0,0) -> 0.18107575
B9: ETG net sales y/y % | C9: =IFERROR(Model!C31+0,0) -> 0 | D9: =IFERROR(Model!D31+0,0) -> 0.078368298 | E9: =IFERROR(Model!E31+0,0) -> 0.17744185 | F9: =IFERROR(Model!F31+0,0) -> -0.018295856 | G9: =IFERROR(Model!G31+0,0) -> 0.43436654 | H9: =IFERROR(Model!H31+0,0) -> 0.10757702 | I9: =IFERROR(Model!I31+0,0) -> 0.45583942 | J9: =IFERROR(Model!N31+0,0) -> 0.055594425 | K9: =IFERROR(Model!S31+0,0) -> 0.083909231 | L9: =IFERROR(Model!X31+0,0) -> 0.030516283 | M9: =IFERROR(Model!AC31+0,0) -> 0.30766122 | N9: =IFERROR(Model!AH31+0,0) -> 0.12320057 | O9: =IFERROR(Model!AM31+0,0) -> 0.22213941 | P9: =IFERROR(Model!AR31+0,0) -> 0.18907081 | Q9: =IFERROR(Model!AW31+0,0) -> 0.048488836 | R9: =IFERROR(Model!BB31+0,0) -> 0.096210572 | S9: =IFERROR(Model!BG31+0,0) -> 0.013871368 | T9: =IFERROR(Model!BL31+0,0) -> 0.25990077 | U9: =IFERROR(Model!BQ31+0,0) -> 0.031344524 | V9: =IFERROR(Model!BV31+0,0) -> 0.11830557
C11: =C7 -> 2006 | D11: =D7 -> 2007 | E11: =E7 -> 2008 | F11: =F7 -> 2009 | G11: =G7 -> 2010 | H11: =H7 -> 2011 | I11: =I7 -> 2012 | J11: =J7 -> 2013 | ... V11: =V7 -> 2025
B12: Adjusted EBITDA | C12: =Model!C140 -> 78.071 | D12: =Model!D140 -> 98.276 | E12: =Model!E140 -> 122.038 | F12: =Model!F140 -> 103.727 | G12: =Model!G140 -> 128.598 | H12: =Model!H140 -> 160.875 | I12: =Model!I140 -> 194.382 | J12: =Model!N140 -> 219.628 | K12: =Model!S140 -> 238.644 | L12: =Model!X140 -> 277.79 | M12: =Model!AC140 -> 331.762 | N12: =Model!AH140 -> 373.673 | O12: =Model!AM140 -> 453.378 | P12: =Model!AR140 -> 545.663 | Q12: =Model!AW140 -> 467.09 | R12: =Model!BB140 -> 488.608 | S12: =Model!BG140 -> 586.111 | T12: =Model!BL140 -> 770.167 | U12: =Model!BQ140 -> 999.846 | V12: =Model!BV140 -> 1232.427
B13: Operating Income (GAAP) | C13: =Model!C102 -> 66.867 | D13: =Model!D102 -> 86.014 | E13: =Model!E102 -> 105.788 | F13: =Model!F102 -> 88.255 | G13: =Model!G102 -> 109.173 | H13: =Model!H102 -> 138.431 | I13: =Model!I102 -> 163.294 | J13: =Model!N102 -> 183.59 | K13: =Model!S102 -> 203.388 | L13: =Model!X102 -> 229.656 | M13: =Model!AC102 -> 265.345 | N13: =Model!AH102 -> 306.658 | O13: =Model!AM102 -> 376.245 | P13: =Model!AR102 -> 457.097 | Q13: =Model!AW102 -> 376.648 | R13: =Model!BB102 -> 392.9 | S13: =Model!BG102 -> 496.844 | T13: =Model!BL102 -> 625.339 | U13: =Model!BQ102 -> 824.455 | V13: =Model!BV102 -> 1018.998
B14: Adj. EBITDA Margin % | C14: =Model!C141 -> 0.19906423 | D14: =Model!D141 -> 0.19348564 | E14: =Model!E141 -> 0.20956234 | F14: =Model!F141 -> 0.1926951 | G14: =Model!G141 -> 0.20841788 | H14: =Model!H141 -> 0.21032409 | I14: =Model!I141 -> 0.21661854 | J14: =Model!N141 -> 0.21772141 | K14: =Model!S141 -> 0.21075835 | L14: =Model!X141 -> 0.23370249 | M14: =Model!AC141 -> 0.24106091 | N14: =Model!AH141 -> 0.24506153 | O14: =Model!AM141 -> 0.25503327 | P14: =Model!AR141 -> 0.26544587 | Q14: =Model!AW141 -> 0.26138089 | R14: =Model!BB141 -> 0.26189243 | S14: =Model!BG141 -> 0.26541012 | T14: =Model!BL141 -> 0.25948105 | U14: =Model!BQ141 -> 0.25918398 | V14: =Model!BV141 -> 0.27478593
B15: GAAP Op. Margin % | C15: =Model!C179 -> 0.17049644 | D15: =Model!D179 -> 0.16934423 | E15: =Model!E179 -> 0.18165801 | F15: =Model!F179 -> 0.16395255 | G15: =Model!G179 -> 0.17693592 | H15: =Model!H179 -> 0.18098134 | I15: =Model!I179 -> 0.1819742 | J15: =Model!N179 -> 0.18199626 | K15: =Model!S179 -> 0.17962203 | L15: =Model!X179 -> 0.19320775 | M15: =Model!AC179 -> 0.19280179 | N15: =Model!AH179 -> 0.20111187 | O15: =Model!AM179 -> 0.21164457 | P15: =Model!AR179 -> 0.22236162 | Q15: =Model!AW179 -> 0.21077006 | R15: =Model!BB179 -> 0.21059323 | S15: =Model!BG179 -> 0.22498712 | T15: =Model!BL179 -> 0.21068628 | U15: =Model!BQ179 -> 0.21371844 | V15: =Model!BV179 -> 0.22719911
C17: =C7 -> 2006 | D17: =D7 -> 2007 | E17: =E7 -> 2008 | F17: =F7 -> 2009 | G17: =G7 -> 2010 | H17: =H7 -> 2011 | I17: =I7 -> 2012 | J17: =J7 -> 2013 | ... V17: =V7 -> 2025
B18: ROIC | C18: =IFERROR(Model!C317+0,NA()) -> 0.10555736 | D18: =IFERROR(Model!D317+0,NA()) -> 0.11600247 | E18: =IFERROR(Model!E317+0,NA()) -> 0.13308431 | F18: =IFERROR(Model!F317+0,NA()) -> 0.10148097 | G18: =IFERROR(Model!G317+0,NA()) -> 0.11925493 | H18: =IFERROR(Model!H317+0,NA()) -> 0.13865064 | I18: =IFERROR(Model!I317+0,NA()) -> 0.12076688 | J18: =IFERROR(Model!N317+0,NA()) -> 0.11008795 | K18: =IFERROR(Model!S317+0,NA()) -> 0.11874098 | L18: =IFERROR(Model!X317+0,NA()) -> 0.11901105 | M18: =IFERROR(Model!AC317+0,NA()) -> 0.11906875 | N18: =IFERROR(Model!AH317+0,NA()) -> 0.10755342 | O18: =IFERROR(Model!AM317+0,NA()) -> 0.14309974 | P18: =IFERROR(Model!AR317+0,NA()) -> 0.15902279 | Q18: =IFERROR(Model!AW317+0,NA()) -> 0.1358558 | R18: =IFERROR(Model!BB317+0,NA()) -> 0.12586279 | S18: =IFERROR(Model!BG317+0,NA()) -> 0.12461555 | T18: =IFERROR(Model!BL317+0,NA()) -> 0.087345401 | U18: =IFERROR(Model!BQ317+0,NA()) -> 0.11096685 | V18: =IFERROR(Model!BV317+0,NA()) -> 0.12722348
B19: RONTA | C19: =IFERROR(Model!C328+0,NA()) -> 0.26393078 | D19: =IFERROR(Model!D328+0,NA()) -> 0.28696823 | E19: =IFERROR(Model!E328+0,NA()) -> 0.28364753 | F19: =IFERROR(Model!F328+0,NA()) -> 0.2318545 | G19: =IFERROR(Model!G328+0,NA()) -> 0.27743248 | H19: =IFERROR(Model!H328+0,NA()) -> 0.33124152 | I19: =IFERROR(Model!I328+0,NA()) -> 0.29646367 | J19: =IFERROR(Model!N328+0,NA()) -> 0.28480612 | K19: =IFERROR(Model!S328+0,NA()) -> 0.29622953 | L19: =IFERROR(Model!X328+0,NA()) -> 0.29656846 | M19: =IFERROR(Model!AC328+0,NA()) -> 0.31379095 | N19: =IFERROR(Model!AH328+0,NA()) -> 0.33420851 | O19: =IFERROR(Model!AM328+0,NA()) -> 0.40185165 | P19: =IFERROR(Model!AR328+0,NA()) -> 0.44073179 | Q19: =IFERROR(Model!AW328+0,NA()) -> 0.25899027 | R19: =IFERROR(Model!BB328+0,NA()) -> 0.28748151 | S19: =IFERROR(Model!BG328+0,NA()) -> 0.30666714 | T19: =IFERROR(Model!BL328+0,NA()) -> 0.26738138 | U19: =IFERROR(Model!BQ328+0,NA()) -> 0.30672519 | V19: =IFERROR(Model!BV328+0,NA()) -> 0.34060395
B20: Adj. EBITDA margin % | C20: =IFERROR(Model!C141+0,NA()) -> 0.19906423 | D20: =IFERROR(Model!D141+0,NA()) -> 0.19348564 | E20: =IFERROR(Model!E141+0,NA()) -> 0.20956234 | F20: =IFERROR(Model!F141+0,NA()) -> 0.1926951 | G20: =IFERROR(Model!G141+0,NA()) -> 0.20841788 | H20: =IFERROR(Model!H141+0,NA()) -> 0.21032409 | I20: =IFERROR(Model!I141+0,NA()) -> 0.21661854 | J20: =IFERROR(Model!N141+0,NA()) -> 0.21772141 | K20: =IFERROR(Model!S141+0,NA()) -> 0.21075835 | L20: =IFERROR(Model!X141+0,NA()) -> 0.23370249 | M20: =IFERROR(Model!AC141+0,NA()) -> 0.24106091 | N20: =IFERROR(Model!AH141+0,NA()) -> 0.24506153 | O20: =IFERROR(Model!AM141+0,NA()) -> 0.25503327 | P20: =IFERROR(Model!AR141+0,NA()) -> 0.26544587 | Q20: =IFERROR(Model!AW141+0,NA()) -> 0.26138089 | R20: =IFERROR(Model!BB141+0,NA()) -> 0.26189243 | S20: =IFERROR(Model!BG141+0,NA()) -> 0.26541012 | T20: =IFERROR(Model!BL141+0,NA()) -> 0.25948105 | U20: =IFERROR(Model!BQ141+0,NA()) -> 0.25918398 | V20: =IFERROR(Model!BV141+0,NA()) -> 0.27478593
B21: FCF margin % | C21: =IFERROR(Model!C216+0,NA()) -> 0.09419924 | D21: =IFERROR(Model!D216+0,NA()) -> 0.087737536 | E21: =IFERROR(Model!E216+0,NA()) -> 0.10252822 | F21: =IFERROR(Model!F216+0,NA()) -> 0.12179916 | G21: =IFERROR(Model!G216+0,NA()) -> 0.15046514 | H21: =IFERROR(Model!H216+0,NA()) -> 0.15174973 | I21: =IFERROR(Model!I216+0,NA()) -> 0.13743067 | J21: =IFERROR(Model!N216+0,NA()) -> 0.11252264 | K21: =IFERROR(Model!S216+0,NA()) -> 0.15391443 | L21: =IFERROR(Model!X216+0,NA()) -> 0.13007551 | M21: =IFERROR(Model!AC216+0,NA()) -> 0.15863377 | N21: =IFERROR(Model!AH216+0,NA()) -> 0.16322461 | O21: =IFERROR(Model!AM216+0,NA()) -> 0.16122665 | P21: =IFERROR(Model!AR216+0,NA()) -> 0.1986917 | Q21: =IFERROR(Model!AW216+0,NA()) -> 0.21610691 | R21: =IFERROR(Model!BB216+0,NA()) -> 0.21863372 | S21: =IFERROR(Model!BG216+0,NA()) -> 0.19737792 | T21: =IFERROR(Model!BL216+0,NA()) -> 0.13453062 | U21: =IFERROR(Model!BQ216+0,NA()) -> 0.15919173 | V21: =IFERROR(Model!BV216+0,NA()) -> 0.19205609
