Workbook

Sheet Model
CA1: SCENARIO SWITCH ▼ (Bull / Base / Bear) — drives all scenario-linked forecast drivers
B2: Huntington Ingalls Industries, Inc. (NYSE: HII) — 3-Statement Financial Model | CA2: Base
B3: US GAAP as reported · USD millions (per-share data in USD) · Source: HII Forms 10-K / 10-Q (XBRL financial data) and Form 8-K earnings releases (Ex. 99.1), SEC EDGAR CIK 0001501585
B4: Basis notes: FY2015–16 as originally reported; FY2017+ as recast in the 2018 10-K for ASU 2017-07 (non-service pension moved below operating income). Technical Solutions formed Dec-2016 (renamed Mission Technologies 2022); Q1–Q3/15 shown on the original segment basis ("Other"), Q4/15 and FY2015 recast. Q3/26E–Q4/26E = FY26 guidance less 1H/26 actuals.
CC5: Forecast | CD5: Historical | CE5: Historical
B6: (USDm) | C6: Q1/15 | D6: Q2/15 | E6: 1H/15 | F6: Q3/15 | G6: Q4/15 | H6: 2015 | I6: Q1/16 | J6: Q2/16 | K6: 1H/16 | L6: Q3/16 | M6: Q4/16 | N6: 2016 | O6: Q1/17 | P6: Q2/17 | Q6: 1H/17 | R6: Q3/17 | S6: Q4/17 | T6: 2017 | U6: Q1/18 | V6: Q2/18 | W6: 1H/18 | X6: Q3/18 | Y6: Q4/18 | Z6: 2018 | AA6: Q1/19 | AB6: Q2/19 | AC6: 1H/19 | AD6: Q3/19 | AE6: Q4/19 | AF6: 2019 | AG6: Q1/20 | AH6: Q2/20 | AI6: 1H/20 | AJ6: Q3/20 | AK6: Q4/20 | AL6: 2020 | AM6: Q1/21 | AN6: Q2/21 | AO6: 1H/21 | AP6: Q3/21 | AQ6: Q4/21 | AR6: 2021 | AS6: Q1/22 | AT6: Q2/22 | AU6: 1H/22 | AV6: Q3/22 | AW6: Q4/22 | AX6: 2022 | AY6: Q1/23 | AZ6: Q2/23 | BA6: 1H/23 | BB6: Q3/23 | BC6: Q4/23 | BD6: 2023 | BE6: Q1/24 | BF6: Q2/24 | BG6: 1H/24 | BH6: Q3/24 | BI6: Q4/24 | BJ6: 2024 | BK6: Q1/25 | BL6: Q2/25 | BM6: 1H/25 | BN6: Q3/25 | BO6: Q4/25 | BP6: 2025 | BQ6: Q1/26 | BR6: Q2/26 | BS6: 1H/26 | BT6: Q3/26E | BU6: Q4/26E | BV6: 2026E | BW6: 2027E | BX6: 2028E | BY6: 2029E | BZ6: 2030E | CA6: Modelling Notes | CC6: 5Y CAGR | CD6: 5Y CAGR | CE6: 10Y CAGR
CC7: 25-'30 | CD7: 20-'25 | CE7: 15-'25
B8: SEGMENT P&L — BY DIVISION
CH9: SCENARIO INPUT TABLE — driver assumptions per Bull / Base / Bear | CI9: Bull | CJ9: Base | CK9: Bear | CL9: Bull / Bear = Base + Δ (Δ inputs on each block header). Guidance block = high / mid / low end of FY26 ranges.
B10: Ingalls Shipbuilding | CA10: INGALLS SHIPBUILDING — modelling logic
B11: Revenue (external) | C11: =IF(ISNUMBER(C12),C13-C12,"n/d") -> n/d | D11: =IF(ISNUMBER(D12),D13-D12,"n/d") -> n/d | E11: =IF(ISNUMBER(E12),E13-E12,"n/d") -> n/d | F11: =IF(ISNUMBER(F12),F13-F12,"n/d") -> n/d | G11: =IF(ISNUMBER(G12),G13-G12,"n/d") -> n/d | H11: =IF(ISNUMBER(H12),H13-H12,"n/d") -> n/d | I11: =IF(ISNUMBER(I12),I13-I12,"n/d") -> n/d | J11: =IF(ISNUMBER(J12),J13-J12,"n/d") -> n/d | ... BZ11: =IF(ISNUMBER(BZ12),BZ13-BZ12,"n/d") -> 3887.7541 | CA11: External revenue = segment revenue less intersegment sales. Intersegment sales by segment not disclosed before FY2018 (n/d). | CH11: FY26 guidance — Q2-26 release (30-Jul-26) | CI11: High | CJ11: Mid | CK11: Low
B12: Intersegment revenue | X12: 2 | Y12: 0 | Z12: 2 | AB12: 1 | AC12: =AA12+AB12 -> 1 | AD12: 1 | AE12: 1 | AF12: 3 | AG12: 1 | AH12: 1 | AI12: =AG12+AH12 -> 2 | AJ12: 0 | AK12: 2 | AL12: 4 | AM12: 3 | AN12: 5 | AO12: =AM12+AN12 -> 8 | AP12: 4 | AQ12: 3 | AR12: 15 | AS12: 3 | AU12: =AS12+AT12 -> 3 | AV12: 5 | AW12: 2 | AX12: 12 | AY12: 2 | AZ12: 3 | BA12: =AY12+AZ12 -> 5 | BB12: 1 | BC12: 3 | BD12: 9 | BE12: 2 | BF12: 1 | BG12: =BE12+BF12 -> 3 | BH12: 2 | BI12: 3 | BJ12: 8 | BK12: 4 | BL12: 3 | BM12: =BK12+BL12 -> 7 | BN12: 3 | BO12: 2 | BP12: 12 | BQ12: 3 | BR12: 2 | BS12: =BQ12+BR12 -> 5 | BT12: =BS12/2 -> 2.5 | BU12: =BS12/2 -> 2.5 | BV12: =SUM(BQ12,BR12,BT12,BU12) -> 10 | BW12: =BW13*BW31 -> 13.144674 | BX12: =BX13*BX31 -> 13.867631 | BY12: =BY13*BY31 -> 14.561013 | BZ12: =BZ13*BZ31 -> 15.216259 | CA12: Q3/Q4-26E at 1H/26 run-rate; 2027E+ = segment revenue × intersegment % (held at FY2025 level). | CH12: Shipbuilding revenue ($m) | CI12: 10400 | CJ12: 10300 | CK12: 10200
B13: Segment revenue (as reported, incl. intersegment) | C13: 469 | D13: 546 | E13: =C13+D13 -> 1015 | F13: 593 | G13: 580 | H13: 2188 | I13: 586 | J13: 585 | K13: =I13+J13 -> 1171 | L13: 577 | M13: 641 | N13: 2389 | O13: 550 | P13: 639 | Q13: =O13+P13 -> 1189 | R13: 593 | S13: 638 | T13: 2420 | U13: 585 | V13: 629 | W13: =U13+V13 -> 1214 | X13: 694 | Y13: 699 | Z13: 2607 | AA13: 584 | AB13: 622 | AC13: =AA13+AB13 -> 1206 | AD13: 647 | AE13: 702 | AF13: 2555 | AG13: 629 | AH13: 622 | AI13: =AG13+AH13 -> 1251 | AJ13: 675 | AK13: 752 | AL13: 2678 | AM13: 649 | AN13: 670 | AO13: =AM13+AN13 -> 1319 | AP13: 628 | AQ13: 581 | AR13: 2528 | AS13: 631 | AT13: 658 | AU13: =AS13+AT13 -> 1289 | AV13: 623 | AW13: 658 | AX13: 2570 | AY13: 577 | AZ13: 664 | BA13: =AY13+AZ13 -> 1241 | BB13: 711 | BC13: 800 | BD13: 2752 | BE13: 655 | BF13: 712 | BG13: =BE13+BF13 -> 1367 | BH13: 664 | BI13: 736 | BJ13: 2767 | BK13: 637 | BL13: 724 | BM13: =BK13+BL13 -> 1361 | BN13: 828 | BO13: 889 | BP13: 3078 | BQ13: 725 | BR13: 845 | BS13: =BQ13+BR13 -> 1570 | BT13: =(CHOOSE(MATCH($CA$2,{"Bull","Base","Bear"},0),$CI$12,$CJ$12,$CK$12)-BS13-BS39)*BS13/(BS13+BS39)/2 -> 805.38159 | BU13: =(CHOOSE(MATCH($CA$2,{"Bull","Base","Bear"},0),$CI$12,$CJ$12,$CK$12)-BS13-BS39)*BS13/(BS13+BS39)/2 -> 805.38159 | BV13: =SUM(BQ13,BR13,BT13,BU13) -> 3180.7632 | BW13: =BV13*(1+BW17) -> 3371.609 | BX13: =BW13*(1+BX17) -> 3557.0475 | BY13: =BX13*(1+BY17) -> 3734.8998 | BZ13: =BY13*(1+BZ17) -> 3902.9703 | CA13: Q3/26E–Q4/26E: FY26 guidance (scenario: high / mid / low end) less 1H/26 actuals, split evenly across Q3 and Q4. Shipbuilding guidance allocated between Ingalls and Newport News by 1H/26 revenue mix; 2H shipbuilding OI allocated by 2H revenue × 1H margin weights. 2027E+: prior year × (1 + scenario revenue growth). | CC13: =IFERROR((BZ13/BP13)^(1/5)-1,"n/m") -> 0.048637361 | CD13: =IFERROR((BP13/AL13)^(1/5)-1,"n/m") -> 0.028233167 | CE13: =IFERROR((BP13/H13)^(1/10)-1,"n/m") -> 0.034718299 | CH13: Shipbuilding OI margin | CI13: 0.065 | CJ13: 0.0625 | CK13: 0.06
B14: Segment operating income | C14: 45 | D14: 198 | E14: =C14+D14 -> 243 | F14: 77 | G14: 59 | H14: 379 | I14: 82 | J14: 88 | K14: =I14+J14 -> 170 | L14: 66 | M14: 85 | N14: 321 | O14: 66 | P14: 98 | Q14: =O14+P14 -> 164 | R14: 74 | S14: 75 | T14: 313 | U14: 64 | V14: 83 | W14: =U14+V14 -> 147 | X14: 82 | Y14: 84 | Z14: 313 | AA14: 46 | AB14: 69 | AC14: =AA14+AB14 -> 115 | AD14: 61 | AE14: 59 | AF14: 235 | AG14: 68 | AH14: 55 | AI14: =AG14+AH14 -> 123 | AJ14: 62 | AK14: 96 | AL14: 281 | AM14: 91 | AN14: 80 | AO14: =AM14+AN14 -> 171 | AP14: 62 | AQ14: 48 | AR14: 281 | AS14: 86 | AT14: 106 | AU14: =AS14+AT14 -> 192 | AV14: 50 | AW14: 50 | AX14: 292 | AY14: 55 | AZ14: 65 | BA14: =AY14+AZ14 -> 120 | BB14: 73 | BC14: 169 | BD14: 362 | BE14: 60 | BF14: 56 | BG14: =BE14+BF14 -> 116 | BH14: 49 | BI14: 46 | BJ14: 211 | BK14: 46 | BL14: 54 | BM14: =BK14+BL14 -> 100 | BN14: 65 | BO14: 68 | BP14: 233 | BQ14: 49 | BR14: 58 | BS14: =BQ14+BR14 -> 107 | BT14: =(CHOOSE(MATCH($CA$2,{"Bull","Base","Bear"},0),$CI$12,$CJ$12,$CK$12)*CHOOSE(MATCH($CA$2,{"Bull","Base","Bear"},0),$CI$13,$CJ$13,$CK$13)-BS14-BS40)*BT13*BS14/BS13/(BT13*BS14/BS13+BT39*BS40/BS39)/2 -> 59.051062 | BU14: =(CHOOSE(MATCH($CA$2,{"Bull","Base","Bear"},0),$CI$12,$CJ$12,$CK$12)*CHOOSE(MATCH($CA$2,{"Bull","Base","Bear"},0),$CI$13,$CJ$13,$CK$13)-BS14-BS40)*BU13*BS14/BS13/(BU13*BS14/BS13+BU39*BS40/BS39)/2 -> 59.051062 | BV14: =SUM(BQ14,BR14,BT14,BU14) -> 225.10212 | BW14: =BW13*BW20 -> 244.44165 | BX14: =BX13*BX20 -> 266.77856 | BY14: =BY13*BY20 -> 289.45474 | BZ14: =BZ13*BZ20 -> 312.23763 | CA14: Q3/26E–Q4/26E: FY26 guidance (scenario: high / mid / low end) less 1H/26 actuals, split evenly across Q3 and Q4. Shipbuilding guidance allocated between Ingalls and Newport News by 1H/26 revenue mix; 2H shipbuilding OI allocated by 2H revenue × 1H margin weights. 2027E+: segment revenue × scenario segment operating margin. | CC14: =IFERROR((BZ14/BP14)^(1/5)-1,"n/m") -> 0.060292924 | CD14: =IFERROR((BP14/AL14)^(1/5)-1,"n/m") -> -0.036770178 | CE14: =IFERROR((BP14/H14)^(1/10)-1,"n/m") -> -0.047485334 | CH14: MT revenue ($m) | CI14: 3200 | CJ14: 3100 | CK14: 3000
B15: Depreciation & amortization | H15: 65 | N15: 68 | T15: 73 | Z15: 69 | AF15: 70 | AL15: 73 | AR15: 74 | AX15: 79 | BD15: 76 | BE15: 19 | BF15: 19 | BG15: =BE15+BF15 -> 38 | BH15: 20 | BI15: 20 | BJ15: 78 | BK15: 20 | BL15: 20 | BM15: =BK15+BL15 -> 40 | BN15: 20 | BO15: 21 | BP15: 81 | BQ15: 20 | BR15: 20 | BS15: =BQ15+BR15 -> 40 | BT15: =BS15/2*($CJ$24-BS102)/BS102 -> 22.580645 | BU15: =BS15/2*($CJ$24-BS102)/BS102 -> 22.580645 | BV15: =SUM(BQ15,BR15,BT15,BU15) -> 85.16129 | BW15: =BW13*BW32 -> 87.661833 | BX15: =BX13*BX32 -> 92.483234 | BY15: =BY13*BY32 -> 97.107396 | BZ15: =BZ13*BZ32 -> 101.47723 | CA15: FY D&A by segment from 10-K segment note (quarterly disclosure from FY2024 under ASU 2023-07). Q3/Q4-26E: 1H/26 run-rate scaled to FY26 D&A guidance (~$330m). 2027E+: revenue × D&A %. | CH15: MT segment OI margin | CI15: 0.0525 | CJ15: 0.05 | CK15: 0.0475
B16: Segment EBITDA (segment OI + D&A) | C16: =IF(ISNUMBER(C15),C14+C15,"") | D16: =IF(ISNUMBER(D15),D14+D15,"") | E16: =IF(ISNUMBER(E15),E14+E15,"") | F16: =IF(ISNUMBER(F15),F14+F15,"") | G16: =IF(ISNUMBER(G15),G14+G15,"") | H16: =IF(ISNUMBER(H15),H14+H15,"") -> 444 | I16: =IF(ISNUMBER(I15),I14+I15,"") | J16: =IF(ISNUMBER(J15),J14+J15,"") | ... BZ16: =IF(ISNUMBER(BZ15),BZ14+BZ15,"") -> 413.71485 | CA16: Segment EBITDA = segment operating income + segment D&A (HII publishes MT EBITDA incl. state tax add-back; shown here on a simple OI + D&A basis for all segments). | CC16: =IFERROR((BZ16/BP16)^(1/5)-1,"n/m") -> 0.056706292 | CD16: =IFERROR((BP16/AL16)^(1/5)-1,"n/m") -> -0.023695531 | CE16: =IFERROR((BP16/H16)^(1/10)-1,"n/m") -> -0.034049953 | CH16: Free cash flow ($m) | CI16: 600 | CJ16: 550 | CK16: 500
B17: Revenue y/y % | I17: =IFERROR(I13/C13-1,"") -> 0.24946695 | J17: =IFERROR(J13/D13-1,"") -> 0.071428571 | K17: =IFERROR(K13/E13-1,"") -> 0.15369458 | L17: =IFERROR(L13/F13-1,"") -> -0.02698145 | M17: =IFERROR(M13/G13-1,"") -> 0.10517241 | N17: =IFERROR(N13/H13-1,"") -> 0.091864717 | O17: =IFERROR(O13/I13-1,"") -> -0.061433447 | P17: =IFERROR(P13/J13-1,"") -> 0.092307692 | ... BV17: =IFERROR(BV13/BP13-1,"") -> 0.033386348 | BW17: =CHOOSE(MATCH($CA$2,{"Bull","Base","Bear"},0),$CI$28,$CJ$28,$CK$28) -> 0.06 | BX17: =CHOOSE(MATCH($CA$2,{"Bull","Base","Bear"},0),$CI$29,$CJ$29,$CK$29) -> 0.055 | BY17: =CHOOSE(MATCH($CA$2,{"Bull","Base","Bear"},0),$CI$30,$CJ$30,$CK$30) -> 0.05 | BZ17: =CHOOSE(MATCH($CA$2,{"Bull","Base","Bear"},0),$CI$31,$CJ$31,$CK$31) -> 0.045 | CA17: 2027E–2030E revenue growth: scenario lever (ING_revGrowth, Bull/Base/Bear table →). 2026E growth is an output of FY26 guidance.
B18: Segment OI y/y % | I18: =IFERROR(I14/C14-1,"") -> 0.82222222 | J18: =IFERROR(J14/D14-1,"") -> -0.55555556 | K18: =IFERROR(K14/E14-1,"") -> -0.30041152 | L18: =IFERROR(L14/F14-1,"") -> -0.14285714 | M18: =IFERROR(M14/G14-1,"") -> 0.44067797 | N18: =IFERROR(N14/H14-1,"") -> -0.1530343 | O18: =IFERROR(O14/I14-1,"") -> -0.19512195 | P18: =IFERROR(P14/J14-1,"") -> 0.11363636 | ... BV18: =IFERROR(BV14/BP14-1,"") -> -0.033896463 | BW18: =IFERROR(BW14/BV14-1,"") -> 0.085914454 | BX18: =IFERROR(BX14/BW14-1,"") -> 0.09137931 | BY18: =IFERROR(BY14/BX14-1,"") -> 0.085 | BZ18: =IFERROR(BZ14/BY14-1,"") -> 0.078709677 | CH18: FY26 guidance — point estimates (all cases)
B19: Segment EBITDA y/y % | I19: =IFERROR(I16/C16-1,"") | J19: =IFERROR(J16/D16-1,"") | K19: =IFERROR(K16/E16-1,"") | L19: =IFERROR(L16/F16-1,"") | M19: =IFERROR(M16/G16-1,"") | N19: =IFERROR(N16/H16-1,"") -> -0.12387387 | O19: =IFERROR(O16/I16-1,"") | P19: =IFERROR(P16/J16-1,"") | ... BV19: =IFERROR(BV16/BP16-1,"") -> -0.011899954 | BW19: =IFERROR(BW16/BV16-1,"") -> 0.070392022 | BX19: =IFERROR(BX16/BW16-1,"") -> 0.08177665 | BY19: =IFERROR(BY16/BX16-1,"") -> 0.075990099 | BZ19: =IFERROR(BZ16/BY16-1,"") -> 0.070241546 | CH19: Operating FAS/CAS adjustment ($m) | CJ19: 44
B20: Segment operating margin % | C20: =IFERROR(C14/C13,"") -> 0.095948827 | D20: =IFERROR(D14/D13,"") -> 0.36263736 | E20: =IFERROR(E14/E13,"") -> 0.23940887 | F20: =IFERROR(F14/F13,"") -> 0.12984823 | G20: =IFERROR(G14/G13,"") -> 0.10172414 | H20: =IFERROR(H14/H13,"") -> 0.17321755 | I20: =IFERROR(I14/I13,"") -> 0.13993174 | J20: =IFERROR(J14/J13,"") -> 0.15042735 | ... BV20: =IFERROR(BV14/BV13,"") -> 0.070769847 | BW20: =CHOOSE(MATCH($CA$2,{"Bull","Base","Bear"},0),$CI$46,$CJ$46,$CK$46) -> 0.0725 | BX20: =CHOOSE(MATCH($CA$2,{"Bull","Base","Bear"},0),$CI$47,$CJ$47,$CK$47) -> 0.075 | BY20: =CHOOSE(MATCH($CA$2,{"Bull","Base","Bear"},0),$CI$48,$CJ$48,$CK$48) -> 0.0775 | BZ20: =CHOOSE(MATCH($CA$2,{"Bull","Base","Bear"},0),$CI$49,$CJ$49,$CK$49) -> 0.08 | CA20: 2027E–2030E segment operating margin: scenario lever (ING_margin). 2026E margin is an output of FY26 guidance. | CC20: =IFERROR(AVERAGE(BV20,BW20,BX20,BY20,BZ20),"n/m") -> 0.075153969 | CD20: =IFERROR(AVERAGE(AR20,AX20,BD20,BJ20,BP20),"n/m") -> 0.10165376 | CE20: =IFERROR(AVERAGE(N20,T20,Z20,AF20,AL20,AR20,AX20,BD20,BJ20,BP20),"n/m") -> 0.10889404 | CH20: Non-current state income taxes ($m) | CJ20: 20
B21: Segment EBITDA margin % | C21: =IFERROR(C16/C13,"") | D21: =IFERROR(D16/D13,"") | E21: =IFERROR(E16/E13,"") | F21: =IFERROR(F16/F13,"") | G21: =IFERROR(G16/G13,"") | H21: =IFERROR(H16/H13,"") -> 0.20292505 | I21: =IFERROR(I16/I13,"") | J21: =IFERROR(J16/J13,"") | ... BZ21: =IFERROR(BZ16/BZ13,"") -> 0.106 | CC21: =IFERROR(AVERAGE(BV21,BW21,BX21,BY21,BZ21),"n/m") -> 0.10130874 | CD21: =IFERROR(AVERAGE(AR21,AX21,BD21,BJ21,BP21),"n/m") -> 0.13008034 | CE21: =IFERROR(AVERAGE(N21,T21,Z21,AF21,AL21,AR21,AX21,BD21,BJ21,BP21),"n/m") -> 0.1370826 | CH21: Interest expense ($m) | CJ21: 105
B22: Incremental OI margin (ΔOI / ΔRev) | I22: =IFERROR((I14-C14)/(I13-C13),"") -> 0.31623932 | J22: =IFERROR((J14-D14)/(J13-D13),"") -> -2.8205128 | K22: =IFERROR((K14-E14)/(K13-E13),"") -> -0.46794872 | L22: =IFERROR((L14-F14)/(L13-F13),"") -> 0.6875 | M22: =IFERROR((M14-G14)/(M13-G13),"") -> 0.42622951 | N22: =IFERROR((N14-H14)/(N13-H13),"") -> -0.28855721 | O22: =IFERROR((O14-I14)/(O13-I13),"") -> 0.44444444 | P22: =IFERROR((P14-J14)/(P13-J13),"") -> 0.18518519 | ... BV22: =IFERROR((BV14-BP14)/(BV13-BP13),"") -> -0.076855114 | BW22: =IFERROR((BW14-BV14)/(BW13-BV13),"") -> 0.10133588 | BX22: =IFERROR((BX14-BW14)/(BX13-BW13),"") -> 0.12045455 | BY22: =IFERROR((BY14-BX14)/(BY13-BX13),"") -> 0.1275 | BZ22: =IFERROR((BZ14-BY14)/(BZ13-BY13),"") -> 0.13555556 | CH22: Non-operating retirement benefit ($m) | CJ22: 213
B23: Operating metrics — Ingalls | CH23: Effective tax rate | CJ23: 0.17
B24: Funded backlog | C24: 6356 | D24: 5842 | E24: =D24 -> 5842 | F24: 5458 | G24: 5153 | H24: =G24 -> 5153 | I24: 5327 | J24: 5088 | K24: =J24 -> 5088 | L24: 4834 | M24: 6033 | N24: =M24 -> 6033 | O24: 5593 | P24: 6894 | Q24: =P24 -> 6894 | R24: 6472 | S24: 5920 | T24: =S24 -> 5920 | U24: 7090 | V24: 6564 | W24: =V24 -> 6564 | X24: 8694 | Y24: 9943 | Z24: =Y24 -> 9943 | AA24: 10825 | AB24: 10340 | AC24: =AB24 -> 10340 | AD24: 9712 | AE24: 9062 | AF24: =AE24 -> 9062 | AG24: 9457 | AH24: 10085 | AI24: =AH24 -> 10085 | AJ24: 11186 | AK24: 10443 | AL24: =AK24 -> 10443 | AM24: 10516 | AN24: 11077 | AO24: =AN24 -> 11077 | AP24: 10561 | AQ24: 10216 | AR24: =AQ24 -> 10216 | AS24: 10515 | AT24: 10208 | AU24: =AT24 -> 10208 | AV24: 9698 | AW24: 9231 | AX24: =AW24 -> 9231 | AY24: 10852 | AZ24: 10345 | BA24: =AZ24 -> 10345 | BB24: 13100 | BC24: 12546 | BD24: =BC24 -> 12546 | BE24: 13133 | BF24: 13917 | BG24: =BF24 -> 13917 | BH24: 14143 | BI24: 13519 | BJ24: =BI24 -> 13519 | BK24: 12993 | BL24: 15783 | BM24: =BL24 -> 15783 | BN24: 15640 | BO24: 14925 | BP24: =BO24 -> 14925 | BQ24: 15775 | BR24: 16883 | BS24: =BR24 -> 16883 | CH24: D&A ($m) | CJ24: 330
B25: Unfunded backlog | C25: 1287 | D25: 1294 | E25: =D25 -> 1294 | F25: 1303 | G25: 1290 | H25: =G25 -> 1290 | I25: 720 | J25: 695 | K25: =J25 -> 695 | L25: 791 | M25: 692 | N25: =M25 -> 692 | O25: 679 | P25: 1699 | Q25: =P25 -> 1699 | R25: 1627 | S25: 2071 | T25: =S25 -> 2071 | U25: 2155 | V25: 2165 | W25: =V25 -> 2165 | X25: 1261 | Y25: 1422 | Z25: =Y25 -> 1422 | AA25: 1541 | AB25: 1626 | AC25: =AB25 -> 1626 | AD25: 1677 | AE25: 1693 | AF25: =AE25 -> 1693 | AG25: 1510 | AH25: 2216 | AI25: =AH25 -> 2216 | AJ25: 1792 | AK25: 1758 | AL25: =AK25 -> 1758 | AM25: 1687 | AN25: 660 | AO25: =AN25 -> 660 | AP25: 661 | AQ25: 792 | AR25: =AQ25 -> 792 | AS25: 815 | AT25: 940 | AU25: =AT25 -> 940 | AV25: 1028 | AW25: 3546 | AX25: =AW25 -> 3546 | AY25: 2786 | AZ25: 3157 | BA25: =AZ25 -> 3157 | BB25: 2968 | BC25: 3201 | BD25: =BC25 -> 3201 | BE25: 2059 | BF25: 2232 | BG25: =BF25 -> 2232 | BH25: 2244 | BI25: 2333 | BJ25: =BI25 -> 2333 | BK25: 2407 | BL25: 3308 | BM25: =BL25 -> 3308 | BN25: 2906 | BO25: 2856 | BP25: =BO25 -> 2856 | BQ25: 2477 | BR25: 2470 | BS25: =BR25 -> 2470 | CH25: Capex % of sales | CJ25: 0.045
B26: Total backlog | C26: =C24+C25 -> 7643 | D26: =D24+D25 -> 7136 | E26: =E24+E25 -> 7136 | F26: =F24+F25 -> 6761 | G26: =G24+G25 -> 6443 | H26: =H24+H25 -> 6443 | I26: =I24+I25 -> 6047 | J26: =J24+J25 -> 5783 | ... BS26: =BS24+BS25 -> 19353 | BT26: =BR26+BT27-BT13 -> 19353 | BU26: =BT26+BU27-BU13 -> 19353 | BV26: =BU26 -> 19353 | BW26: =BV26+BW27-BW13 -> 19353 | BX26: =BW26+BX27-BX13 -> 19353 | BY26: =BX26+BY27-BY13 -> 19353 | BZ26: =BY26+BZ27-BZ13 -> 19353 | CA26: Forecast backlog = prior backlog + new awards − segment revenue; awards = revenue × book-to-bill assumption. | CC26: =IFERROR((BZ26/BP26)^(1/5)-1,"n/m") -> 0.017087748 | CD26: =IFERROR((BP26/AL26)^(1/5)-1,"n/m") -> 0.078231837 | CE26: =IFERROR((BP26/H26)^(1/10)-1,"n/m") -> 0.10684499
B27: Implied new awards (ΔBacklog + Revenue) | D27: =IF(AND(ISNUMBER(D26),ISNUMBER(C26)),D26-C26+D13,"") -> 39 | E27: =IF(AND(ISNUMBER(C27),ISNUMBER(D27)),C27+D27,"") | F27: =IF(AND(ISNUMBER(F26),ISNUMBER(D26)),F26-D26+F13,"") -> 218 | G27: =IF(AND(ISNUMBER(G26),ISNUMBER(F26)),G26-F26+G13,"") -> 262 | I27: =IF(AND(ISNUMBER(I26),ISNUMBER(G26)),I26-G26+I13,"") -> 190 | J27: =IF(AND(ISNUMBER(J26),ISNUMBER(I26)),J26-I26+J13,"") -> 321 | K27: =IF(AND(ISNUMBER(I27),ISNUMBER(J27)),I27+J27,"") -> 511 | L27: =IF(AND(ISNUMBER(L26),ISNUMBER(J26)),L26-J26+L13,"") -> 419 | M27: =IF(AND(ISNUMBER(M26),ISNUMBER(L26)),M26-L26+M13,"") -> 1741 | N27: =IF(AND(ISNUMBER(N26),ISNUMBER(H26)),N26-H26+N13,"") -> 2671 | O27: =IF(AND(ISNUMBER(O26),ISNUMBER(M26)),O26-M26+O13,"") -> 97 | P27: =IF(AND(ISNUMBER(P26),ISNUMBER(O26)),P26-O26+P13,"") -> 2960 | Q27: =IF(AND(ISNUMBER(O27),ISNUMBER(P27)),O27+P27,"") -> 3057 | R27: =IF(AND(ISNUMBER(R26),ISNUMBER(P26)),R26-P26+R13,"") -> 99 | S27: =IF(AND(ISNUMBER(S26),ISNUMBER(R26)),S26-R26+S13,"") -> 530 | T27: =IF(AND(ISNUMBER(T26),ISNUMBER(N26)),T26-N26+T13,"") -> 3686 | U27: =IF(AND(ISNUMBER(U26),ISNUMBER(S26)),U26-S26+U13,"") -> 1839 | V27: =IF(AND(ISNUMBER(V26),ISNUMBER(U26)),V26-U26+V13,"") -> 113 | W27: =IF(AND(ISNUMBER(U27),ISNUMBER(V27)),U27+V27,"") -> 1952 | X27: =IF(AND(ISNUMBER(X26),ISNUMBER(V26)),X26-V26+X13,"") -> 1920 | Y27: =IF(AND(ISNUMBER(Y26),ISNUMBER(X26)),Y26-X26+Y13,"") -> 2109 | Z27: =IF(AND(ISNUMBER(Z26),ISNUMBER(T26)),Z26-T26+Z13,"") -> 5981 | AA27: =IF(AND(ISNUMBER(AA26),ISNUMBER(Y26)),AA26-Y26+AA13,"") -> 1585 | AB27: =IF(AND(ISNUMBER(AB26),ISNUMBER(AA26)),AB26-AA26+AB13,"") -> 222 | AC27: =IF(AND(ISNUMBER(AA27),ISNUMBER(AB27)),AA27+AB27,"") -> 1807 | AD27: =IF(AND(ISNUMBER(AD26),ISNUMBER(AB26)),AD26-AB26+AD13,"") -> 70 | AE27: =IF(AND(ISNUMBER(AE26),ISNUMBER(AD26)),AE26-AD26+AE13,"") -> 68 | AF27: =IF(AND(ISNUMBER(AF26),ISNUMBER(Z26)),AF26-Z26+AF13,"") -> 1945 | AG27: =IF(AND(ISNUMBER(AG26),ISNUMBER(AE26)),AG26-AE26+AG13,"") -> 841 | AH27: =IF(AND(ISNUMBER(AH26),ISNUMBER(AG26)),AH26-AG26+AH13,"") -> 1956 | AI27: =IF(AND(ISNUMBER(AG27),ISNUMBER(AH27)),AG27+AH27,"") -> 2797 | AJ27: =IF(AND(ISNUMBER(AJ26),ISNUMBER(AH26)),AJ26-AH26+AJ13,"") -> 1352 | AK27: =IF(AND(ISNUMBER(AK26),ISNUMBER(AJ26)),AK26-AJ26+AK13,"") -> -25 | AL27: =IF(AND(ISNUMBER(AL26),ISNUMBER(AF26)),AL26-AF26+AL13,"") -> 4124 | AM27: =IF(AND(ISNUMBER(AM26),ISNUMBER(AK26)),AM26-AK26+AM13,"") -> 651 | AN27: =IF(AND(ISNUMBER(AN26),ISNUMBER(AM26)),AN26-AM26+AN13,"") -> 204 | AO27: =IF(AND(ISNUMBER(AM27),ISNUMBER(AN27)),AM27+AN27,"") -> 855 | AP27: =IF(AND(ISNUMBER(AP26),ISNUMBER(AN26)),AP26-AN26+AP13,"") -> 113 | AQ27: =IF(AND(ISNUMBER(AQ26),ISNUMBER(AP26)),AQ26-AP26+AQ13,"") -> 367 | AR27: =IF(AND(ISNUMBER(AR26),ISNUMBER(AL26)),AR26-AL26+AR13,"") -> 1335 | AS27: =IF(AND(ISNUMBER(AS26),ISNUMBER(AQ26)),AS26-AQ26+AS13,"") -> 953 | AT27: =IF(AND(ISNUMBER(AT26),ISNUMBER(AS26)),AT26-AS26+AT13,"") -> 476 | AU27: =IF(AND(ISNUMBER(AS27),ISNUMBER(AT27)),AS27+AT27,"") -> 1429 | AV27: =IF(AND(ISNUMBER(AV26),ISNUMBER(AT26)),AV26-AT26+AV13,"") -> 201 | AW27: =IF(AND(ISNUMBER(AW26),ISNUMBER(AV26)),AW26-AV26+AW13,"") -> 2709 | AX27: =IF(AND(ISNUMBER(AX26),ISNUMBER(AR26)),AX26-AR26+AX13,"") -> 4339 | AY27: =IF(AND(ISNUMBER(AY26),ISNUMBER(AW26)),AY26-AW26+AY13,"") -> 1438 | AZ27: =IF(AND(ISNUMBER(AZ26),ISNUMBER(AY26)),AZ26-AY26+AZ13,"") -> 528 | BA27: =IF(AND(ISNUMBER(AY27),ISNUMBER(AZ27)),AY27+AZ27,"") -> 1966 | BB27: =IF(AND(ISNUMBER(BB26),ISNUMBER(AZ26)),BB26-AZ26+BB13,"") -> 3277 | BC27: =IF(AND(ISNUMBER(BC26),ISNUMBER(BB26)),BC26-BB26+BC13,"") -> 479 | BD27: =IF(AND(ISNUMBER(BD26),ISNUMBER(AX26)),BD26-AX26+BD13,"") -> 5722 | BE27: =IF(AND(ISNUMBER(BE26),ISNUMBER(BC26)),BE26-BC26+BE13,"") -> 100 | BF27: =IF(AND(ISNUMBER(BF26),ISNUMBER(BE26)),BF26-BE26+BF13,"") -> 1669 | BG27: =IF(AND(ISNUMBER(BE27),ISNUMBER(BF27)),BE27+BF27,"") -> 1769 | BH27: =IF(AND(ISNUMBER(BH26),ISNUMBER(BF26)),BH26-BF26+BH13,"") -> 902 | BI27: =IF(AND(ISNUMBER(BI26),ISNUMBER(BH26)),BI26-BH26+BI13,"") -> 201 | BJ27: =IF(AND(ISNUMBER(BJ26),ISNUMBER(BD26)),BJ26-BD26+BJ13,"") -> 2872 | BK27: =IF(AND(ISNUMBER(BK26),ISNUMBER(BI26)),BK26-BI26+BK13,"") -> 185 | BL27: =IF(AND(ISNUMBER(BL26),ISNUMBER(BK26)),BL26-BK26+BL13,"") -> 4415 | BM27: =IF(AND(ISNUMBER(BK27),ISNUMBER(BL27)),BK27+BL27,"") -> 4600 | BN27: =IF(AND(ISNUMBER(BN26),ISNUMBER(BL26)),BN26-BL26+BN13,"") -> 283 | BO27: =IF(AND(ISNUMBER(BO26),ISNUMBER(BN26)),BO26-BN26+BO13,"") -> 124 | BP27: =IF(AND(ISNUMBER(BP26),ISNUMBER(BJ26)),BP26-BJ26+BP13,"") -> 5007 | BQ27: =IF(AND(ISNUMBER(BQ26),ISNUMBER(BO26)),BQ26-BO26+BQ13,"") -> 1196 | BR27: =IF(AND(ISNUMBER(BR26),ISNUMBER(BQ26)),BR26-BQ26+BR13,"") -> 1946 | BS27: =IF(AND(ISNUMBER(BQ27),ISNUMBER(BR27)),BQ27+BR27,"") -> 3142 | BT27: =BT13*BT28 -> 805.38159 | BU27: =BU13*BU28 -> 805.38159 | BV27: =SUM(BQ27,BR27,BT27,BU27) -> 4752.7632 | BW27: =BW13*BW28 -> 3371.609 | BX27: =BX13*BX28 -> 3557.0475 | BY27: =BY13*BY28 -> 3734.8998 | BZ27: =BZ13*BZ28 -> 3902.9703 | CA27: Implied awards = change in total backlog + segment revenue (backlog also moves for de-obligations/adjustments; not separately disclosed). | CH27: ING_revGrowth | CI27: 0.02 | CJ27: Δ → | CK27: -0.03
B28: Book-to-bill (x) | C28: =IF(ISNUMBER(C27),IFERROR(C27/C13,""),"") | D28: =IF(ISNUMBER(D27),IFERROR(D27/D13,""),"") -> 0.071428571 | E28: =IF(ISNUMBER(E27),IFERROR(E27/E13,""),"") | F28: =IF(ISNUMBER(F27),IFERROR(F27/F13,""),"") -> 0.36762226 | G28: =IF(ISNUMBER(G27),IFERROR(G27/G13,""),"") -> 0.45172414 | H28: =IF(ISNUMBER(H27),IFERROR(H27/H13,""),"") | I28: =IF(ISNUMBER(I27),IFERROR(I27/I13,""),"") -> 0.32423208 | J28: =IF(ISNUMBER(J27),IFERROR(J27/J13,""),"") -> 0.54871795 | ... BS28: =IF(ISNUMBER(BS27),IFERROR(BS27/BS13,""),"") -> 2.0012739 | BT28: =$BV$28 -> 1 | BU28: =$BV$28 -> 1 | BV28: 1 | BW28: 1 | BX28: 1 | BY28: 1 | BZ28: 1 | CA28: Book-to-bill input (blue): 2026E cell = 2H/26 assumption applied to Q3/Q4-26E; 2027E+ held at 1.0x (backlog stable in $). Shipbuilding awards are lumpy (multi-ship / multi-year contracts) — adjust for known awards. | CH28: 2027E | CI28: =CJ28+$CI$27 -> 0.08 | CJ28: 0.06 | CK28: =CJ28+$CK$27 -> 0.03
B29: Backlog / revenue (years) | H29: =IFERROR(H26/H13,"") -> 2.9446984 | N29: =IFERROR(N26/N13,"") -> 2.8149853 | T29: =IFERROR(T26/T13,"") -> 3.3020661 | Z29: =IFERROR(Z26/Z13,"") -> 4.359417 | AF29: =IFERROR(AF26/AF13,"") -> 4.2093933 | AL29: =IFERROR(AL26/AL13,"") -> 4.5560119 | AR29: =IFERROR(AR26/AR13,"") -> 4.3544304 | AX29: =IFERROR(AX26/AX13,"") -> 4.9715953 | BD29: =IFERROR(BD26/BD13,"") -> 5.7220203 | BJ29: =IFERROR(BJ26/BJ13,"") -> 5.7289483 | BP29: =IFERROR(BP26/BP13,"") -> 5.7768031 | BV29: =IFERROR(BV26/BV13,"") -> 6.0843888 | BW29: =IFERROR(BW26/BW13,"") -> 5.7399895 | BX29: =IFERROR(BX26/BX13,"") -> 5.4407483 | BY29: =IFERROR(BY26/BY13,"") -> 5.1816651 | BZ29: =IFERROR(BZ26/BZ13,"") -> 4.9585312 | CH29: 2028E | CI29: =CJ29+$CI$27 -> 0.075 | CJ29: 0.055 | CK29: =CJ29+$CK$27 -> 0.025
B30: % of Revenue — Ingalls | CA30: % OF REVENUE drivers — hardcoded inputs that drive forecast segment cost / capital intensity | CH30: 2029E | CI30: =CJ30+$CI$27 -> 0.07 | CJ30: 0.05 | CK30: =CJ30+$CK$27 -> 0.02
B31: Intersegment revenue % of segment revenue | C31: =IFERROR(C12/C13,"n/d") -> 0 | D31: =IFERROR(D12/D13,"n/d") -> 0 | E31: =IFERROR(E12/E13,"n/d") -> 0 | F31: =IFERROR(F12/F13,"n/d") -> 0 | G31: =IFERROR(G12/G13,"n/d") -> 0 | H31: =IFERROR(H12/H13,"n/d") -> 0 | I31: =IFERROR(I12/I13,"n/d") -> 0 | J31: =IFERROR(J12/J13,"n/d") -> 0 | ... BS31: =IFERROR(BS12/BS13,"n/d") -> 0.0031847134 | BT31: =IFERROR(BT12/BT13,"") -> 0.0031041186 | BU31: =IFERROR(BU12/BU13,"") -> 0.0031041186 | BV31: =IFERROR(BV12/BV13,"") -> 0.0031438996 | BW31: =$BP$31 -> 0.0038986355 | BX31: =$BP$31 -> 0.0038986355 | BY31: =$BP$31 -> 0.0038986355 | BZ31: =$BP$31 -> 0.0038986355 | CA31: Held at FY2025 actual level (linked). | CH31: 2030E | CI31: =CJ31+$CI$27 -> 0.065 | CJ31: 0.045 | CK31: =CJ31+$CK$27 -> 0.015
B32: D&A % of revenue | C32: =IFERROR(C15/C13,"") -> 0 | D32: =IFERROR(D15/D13,"") -> 0 | E32: =IFERROR(E15/E13,"") -> 0 | F32: =IFERROR(F15/F13,"") -> 0 | G32: =IFERROR(G15/G13,"") -> 0 | H32: =IFERROR(H15/H13,"") -> 0.029707495 | I32: =IFERROR(I15/I13,"") -> 0 | J32: =IFERROR(J15/J13,"") -> 0 | ... BV32: =IFERROR(BV15/BV13,"") -> 0.026773854 | BW32: 0.026 | BX32: 0.026 | BY32: 0.026 | BZ32: 0.026 | CA32: Ingalls D&A ~2.6% of revenue (FY25 2.6%); held flat — capex step-up offsets revenue growth.
B33: Capital expenditures (segment) | H33: 53 | N33: 97 | T33: 131 | Z33: 134 | AF33: 182 | AL33: 104 | AR33: 72 | AX33: 69 | BD33: 65 | BE33: 11 | BF33: 13 | BG33: =BE33+BF33 -> 24 | BH33: 16 | BI33: 20 | BJ33: 60 | BK33: 14 | BL33: 16 | BM33: =BK33+BL33 -> 30 | BN33: 19 | BO33: 25 | BP33: 74 | BQ33: 10 | BV33: =BV13*BV34 -> 106.8648 | BW33: =BW13*BW34 -> 106.98353 | BX33: =BX13*BX34 -> 106.22836 | BY33: =BY13*BY34 -> 104.56854 | BZ33: =BZ13*BZ34 -> 101.98918 | CA33: Segment capex = revenue × segment capex %. Illustrative allocation of group capex (group capex in the CF statement is driven by the group capex % of revenue line). | CH33: NNS_revGrowth | CI33: 0.02 | CJ33: Δ → | CK33: -0.03
B34: Capex % of revenue | H34: =IFERROR(H33/H13,"") -> 0.024223035 | N34: =IFERROR(N33/N13,"") -> 0.040602763 | T34: =IFERROR(T33/T13,"") -> 0.054132231 | Z34: =IFERROR(Z33/Z13,"") -> 0.051400077 | AF34: =IFERROR(AF33/AF13,"") -> 0.071232877 | AL34: =IFERROR(AL33/AL13,"") -> 0.038834951 | AR34: =IFERROR(AR33/AR13,"") -> 0.028481013 | AX34: =IFERROR(AX33/AX13,"") -> 0.026848249 | BD34: =IFERROR(BD33/BD13,"") -> 0.023619186 | BJ34: =IFERROR(BJ33/BJ13,"") -> 0.021684134 | BP34: =IFERROR(BP33/BP13,"") -> 0.024041585 | BV34: =IFERROR($BP$34/$BP$227*BV227,0) -> 0.033597219 | BW34: =IFERROR($BP$34/$BP$227*BW227,0) -> 0.031730706 | BX34: =IFERROR($BP$34/$BP$227*BX227,0) -> 0.029864194 | BY34: =IFERROR($BP$34/$BP$227*BY227,0) -> 0.027997682 | BZ34: =IFERROR($BP$34/$BP$227*BZ227,0) -> 0.02613117 | CA34: Segment capex % = group capex % (CF memo) × FY2025 segment capex intensity relative to group. | CH34: 2027E | CI34: =CJ34+$CI$33 -> 0.09 | CJ34: 0.07 | CK34: =CJ34+$CK$33 -> 0.04
CH35: 2028E | CI35: =CJ35+$CI$33 -> 0.08 | CJ35: 0.06 | CK35: =CJ35+$CK$33 -> 0.03
B36: Newport News Shipbuilding | CA36: NEWPORT NEWS SHIPBUILDING — modelling logic | CH36: 2029E | CI36: =CJ36+$CI$33 -> 0.075 | CJ36: 0.055 | CK36: =CJ36+$CK$33 -> 0.025
B37: Revenue (external) | C37: =IF(ISNUMBER(C38),C39-C38,"n/d") -> n/d | D37: =IF(ISNUMBER(D38),D39-D38,"n/d") -> n/d | E37: =IF(ISNUMBER(E38),E39-E38,"n/d") -> n/d | F37: =IF(ISNUMBER(F38),F39-F38,"n/d") -> n/d | G37: =IF(ISNUMBER(G38),G39-G38,"n/d") -> n/d | H37: =IF(ISNUMBER(H38),H39-H38,"n/d") -> n/d | I37: =IF(ISNUMBER(I38),I39-I38,"n/d") -> n/d | J37: =IF(ISNUMBER(J38),J39-J38,"n/d") -> n/d | ... BZ37: =IF(ISNUMBER(BZ38),BZ39-BZ38,"n/d") -> 8943.3061 | CA37: External revenue = segment revenue less intersegment sales. Intersegment sales by segment not disclosed before FY2018 (n/d). | CH37: 2030E | CI37: =CJ37+$CI$33 -> 0.07 | CJ37: 0.05 | CK37: =CJ37+$CK$33 -> 0.02
B38: Intersegment revenue | V38: 3 | W38: =U38+V38 -> 3 | X38: 2 | Y38: 3 | Z38: 8 | AB38: 3 | AC38: =AA38+AB38 -> 3 | AD38: 1 | AE38: 4 | AF38: 8 | AG38: 2 | AH38: 2 | AI38: =AG38+AH38 -> 4 | AJ38: 3 | AK38: 5 | AL38: 12 | AM38: 2 | AN38: 4 | AO38: =AM38+AN38 -> 6 | AP38: 3 | AQ38: 2 | AR38: 11 | AS38: 2 | AU38: =AS38+AT38 -> 2 | AV38: 1 | AW38: 1 | AX38: 5 | AY38: 1 | AZ38: 0 | BA38: =AY38+AZ38 -> 1 | BB38: 2 | BC38: 0 | BD38: 3 | BE38: 1 | BF38: 1 | BG38: =BE38+BF38 -> 2 | BH38: 0 | BI38: 1 | BJ38: 3 | BL38: 1 | BM38: =BK38+BL38 -> 1 | BN38: 0 | BO38: 0 | BP38: 1 | BS38: =BQ38+BR38 -> 0 | BT38: =BS38/2 -> 0 | BU38: =BS38/2 -> 0 | BV38: =SUM(BQ38,BR38,BT38,BU38) -> 0 | BW38: =BW39*BW57 -> 1.1706752 | BX38: =BX39*BX57 -> 1.2409157 | BY38: =BY39*BY57 -> 1.3091661 | BZ38: =BZ39*BZ57 -> 1.3746244 | CA38: Q3/Q4-26E at 1H/26 run-rate; 2027E+ = segment revenue × intersegment % (held at FY2025 level).
B39: Segment revenue (as reported, incl. intersegment) | C39: 1061 | D39: 1166 | E39: =C39+D39 -> 2227 | F39: 1177 | G39: 1194 | H39: 4298 | I39: 993 | J39: 999 | K39: =I39+J39 -> 1992 | L39: 978 | M39: 1119 | N39: 4089 | O39: 971 | P39: 1001 | Q39: =O39+P39 -> 1972 | R39: 1053 | S39: 1139 | T39: 4164 | U39: 1082 | V39: 1183 | W39: =U39+V39 -> 2265 | X39: 1179 | Y39: 1352 | Z39: 4796 | AA39: 1279 | AB39: 1279 | AC39: =AA39+AB39 -> 2558 | AD39: 1274 | AE39: 1399 | AF39: 5231 | AG39: 1341 | AH39: 1122 | AI39: =AG39+AH39 -> 2463 | AJ39: 1358 | AK39: 1750 | AL39: 5571 | AM39: 1407 | AN39: 1363 | AO39: =AM39+AN39 -> 2770 | AP39: 1354 | AQ39: 1539 | AR39: 5663 | AS39: 1390 | AT39: 1433 | AU39: =AS39+AT39 -> 2823 | AV39: 1445 | AW39: 1584 | AX39: 5852 | AY39: 1506 | AZ39: 1509 | BA39: =AY39+AZ39 -> 3015 | BB39: 1453 | BC39: 1665 | BD39: 6133 | BE39: 1434 | BF39: 1535 | BG39: =BE39+BF39 -> 2969 | BH39: 1412 | BI39: 1588 | BJ39: 5969 | BK39: 1396 | BL39: 1603 | BM39: =BK39+BL39 -> 2999 | BN39: 1617 | BO39: 1891 | BP39: 6507 | BQ39: 1665 | BR39: 1849 | BS39: =BQ39+BR39 -> 3514 | BT39: =(CHOOSE(MATCH($CA$2,{"Bull","Base","Bear"},0),$CI$12,$CJ$12,$CK$12)-BS39-BS13)*BS39/(BS39+BS13)/2 -> 1802.6184 | BU39: =(CHOOSE(MATCH($CA$2,{"Bull","Base","Bear"},0),$CI$12,$CJ$12,$CK$12)-BS39-BS13)*BS39/(BS39+BS13)/2 -> 1802.6184 | BV39: =SUM(BQ39,BR39,BT39,BU39) -> 7119.2368 | BW39: =BV39*(1+BW43) -> 7617.5834 | BX39: =BW39*(1+BX43) -> 8074.6384 | BY39: =BX39*(1+BY43) -> 8518.7435 | BZ39: =BY39*(1+BZ43) -> 8944.6807 | CA39: Q3/26E–Q4/26E: FY26 guidance (scenario: high / mid / low end) less 1H/26 actuals, split evenly across Q3 and Q4. Shipbuilding guidance allocated between Ingalls and Newport News by 1H/26 revenue mix; 2H shipbuilding OI allocated by 2H revenue × 1H margin weights. 2027E+: prior year × (1 + scenario revenue growth). | CC39: =IFERROR((BZ39/BP39)^(1/5)-1,"n/m") -> 0.065704518 | CD39: =IFERROR((BP39/AL39)^(1/5)-1,"n/m") -> 0.03154821 | CE39: =IFERROR((BP39/H39)^(1/10)-1,"n/m") -> 0.042344885 | CH39: MT_revGrowth | CI39: 0.02 | CJ39: Δ → | CK39: -0.03
B40: Segment operating income | C40: 93 | D40: 109 | E40: =C40+D40 -> 202 | F40: 100 | G40: 116 | H40: 401 | I40: 81 | J40: 98 | K40: =I40+J40 -> 179 | L40: 68 | M40: 139 | N40: 386 | O40: 72 | P40: 80 | Q40: =O40+P40 -> 152 | R40: 96 | S40: 106 | T40: 354 | U40: 51 | V40: 91 | W40: =U40+V40 -> 142 | X40: 119 | Y40: 69 | Z40: 330 | AA40: 81 | AB40: 71 | AC40: =AA40+AB40 -> 152 | AD40: 121 | AE40: 137 | AF40: 410 | AG40: 95 | AH40: -69 | AI40: =AG40+AH40 -> 26 | AJ40: 79 | AK40: 128 | AL40: 233 | AM40: 93 | AN40: 76 | AO40: =AM40+AN40 -> 169 | AP40: 88 | AQ40: 95 | AR40: 352 | AS40: 81 | AT40: 94 | AU40: =AS40+AT40 -> 175 | AV40: 102 | AW40: 80 | AX40: 357 | AY40: 84 | AZ40: 95 | BA40: =AY40+AZ40 -> 179 | BB40: 90 | BC40: 110 | BD40: 379 | BE40: 82 | BF40: 111 | BG40: =BE40+BF40 -> 193 | BH40: 15 | BI40: 38 | BJ40: 246 | BK40: 85 | BL40: 82 | BM40: =BK40+BL40 -> 167 | BN40: 80 | BO40: 84 | BP40: 331 | BQ40: 88 | BR40: 111 | BS40: =BQ40+BR40 -> 199 | BT40: =(CHOOSE(MATCH($CA$2,{"Bull","Base","Bear"},0),$CI$12,$CJ$12,$CK$12)*CHOOSE(MATCH($CA$2,{"Bull","Base","Bear"},0),$CI$13,$CJ$13,$CK$13)-BS40-BS14)*BT39*BS40/BS39/(BT39*BS40/BS39+BT13*BS14/BS13)/2 -> 109.82394 | BU40: =(CHOOSE(MATCH($CA$2,{"Bull","Base","Bear"},0),$CI$12,$CJ$12,$CK$12)*CHOOSE(MATCH($CA$2,{"Bull","Base","Bear"},0),$CI$13,$CJ$13,$CK$13)-BS40-BS14)*BU39*BS40/BS39/(BU39*BS40/BS39+BU13*BS14/BS13)/2 -> 109.82394 | BV40: =SUM(BQ40,BR40,BT40,BU40) -> 418.64788 | BW40: =BW39*BW46 -> 514.18688 | BX40: =BX39*BX46 -> 565.22469 | BY40: =BY39*BY46 -> 617.6089 | BZ40: =BZ39*BZ46 -> 670.85105 | CA40: Q3/26E–Q4/26E: FY26 guidance (scenario: high / mid / low end) less 1H/26 actuals, split evenly across Q3 and Q4. Shipbuilding guidance allocated between Ingalls and Newport News by 1H/26 revenue mix; 2H shipbuilding OI allocated by 2H revenue × 1H margin weights. 2027E+: segment revenue × scenario segment operating margin. | CC40: =IFERROR((BZ40/BP40)^(1/5)-1,"n/m") -> 0.15175372 | CD40: =IFERROR((BP40/AL40)^(1/5)-1,"n/m") -> 0.072739851 | CE40: =IFERROR((BP40/H40)^(1/10)-1,"n/m") -> -0.019001458 | CH40: 2027E | CI40: =CJ40+$CI$39 -> 0.06 | CJ40: 0.04 | CK40: =CJ40+$CK$39 -> 0.01
B41: Depreciation & amortization | H41: 102 | N41: 109 | T41: 107 | Z41: 114 | AF41: 124 | AL41: 133 | AR41: 146 | AX41: 148 | BD41: 150 | BE41: 34 | BF41: 33 | BG41: =BE41+BF41 -> 67 | BH41: 34 | BI41: 35 | BJ41: 136 | BK41: 33 | BL41: 36 | BM41: =BK41+BL41 -> 69 | BN41: 34 | BO41: 38 | BP41: 141 | BQ41: 35 | BR41: 36 | BS41: =BQ41+BR41 -> 71 | BT41: =BS41/2*($CJ$24-BS102)/BS102 -> 40.080645 | BU41: =BS41/2*($CJ$24-BS102)/BS102 -> 40.080645 | BV41: =SUM(BQ41,BR41,BT41,BU41) -> 151.16129 | BW41: =BW39*BW58 -> 163.77804 | BX41: =BX39*BX58 -> 173.60473 | BY41: =BY39*BY58 -> 183.15299 | BZ41: =BZ39*BZ58 -> 192.31063 | CA41: FY D&A by segment from 10-K segment note (quarterly disclosure from FY2024 under ASU 2023-07). Q3/Q4-26E: 1H/26 run-rate scaled to FY26 D&A guidance (~$330m). 2027E+: revenue × D&A %. | CH41: 2028E | CI41: =CJ41+$CI$39 -> 0.06 | CJ41: 0.04 | CK41: =CJ41+$CK$39 -> 0.01
B42: Segment EBITDA (segment OI + D&A) | C42: =IF(ISNUMBER(C41),C40+C41,"") | D42: =IF(ISNUMBER(D41),D40+D41,"") | E42: =IF(ISNUMBER(E41),E40+E41,"") | F42: =IF(ISNUMBER(F41),F40+F41,"") | G42: =IF(ISNUMBER(G41),G40+G41,"") | H42: =IF(ISNUMBER(H41),H40+H41,"") -> 503 | I42: =IF(ISNUMBER(I41),I40+I41,"") | J42: =IF(ISNUMBER(J41),J40+J41,"") | ... BZ42: =IF(ISNUMBER(BZ41),BZ40+BZ41,"") -> 863.16169 | CA42: Segment EBITDA = segment operating income + segment D&A (HII publishes MT EBITDA incl. state tax add-back; shown here on a simple OI + D&A basis for all segments). | CC42: =IFERROR((BZ42/BP42)^(1/5)-1,"n/m") -> 0.12831414 | CD42: =IFERROR((BP42/AL42)^(1/5)-1,"n/m") -> 0.052185185 | CE42: =IFERROR((BP42/H42)^(1/10)-1,"n/m") -> -0.0063409294 | CH42: 2029E | CI42: =CJ42+$CI$39 -> 0.065 | CJ42: 0.045 | CK42: =CJ42+$CK$39 -> 0.015
B43: Revenue y/y % | I43: =IFERROR(I39/C39-1,"") -> -0.064090481 | J43: =IFERROR(J39/D39-1,"") -> -0.1432247 | K43: =IFERROR(K39/E39-1,"") -> -0.10552313 | L43: =IFERROR(L39/F39-1,"") -> -0.16907392 | M43: =IFERROR(M39/G39-1,"") -> -0.06281407 | N43: =IFERROR(N39/H39-1,"") -> -0.048627268 | O43: =IFERROR(O39/I39-1,"") -> -0.022155086 | P43: =IFERROR(P39/J39-1,"") -> 0.002002002 | ... BV43: =IFERROR(BV39/BP39-1,"") -> 0.094088954 | BW43: =CHOOSE(MATCH($CA$2,{"Bull","Base","Bear"},0),$CI$34,$CJ$34,$CK$34) -> 0.07 | BX43: =CHOOSE(MATCH($CA$2,{"Bull","Base","Bear"},0),$CI$35,$CJ$35,$CK$35) -> 0.06 | BY43: =CHOOSE(MATCH($CA$2,{"Bull","Base","Bear"},0),$CI$36,$CJ$36,$CK$36) -> 0.055 | BZ43: =CHOOSE(MATCH($CA$2,{"Bull","Base","Bear"},0),$CI$37,$CJ$37,$CK$37) -> 0.05 | CA43: 2027E–2030E revenue growth: scenario lever (NNS_revGrowth, Bull/Base/Bear table →). 2026E growth is an output of FY26 guidance. | CH43: 2030E | CI43: =CJ43+$CI$39 -> 0.065 | CJ43: 0.045 | CK43: =CJ43+$CK$39 -> 0.015
B44: Segment OI y/y % | I44: =IFERROR(I40/C40-1,"") -> -0.12903226 | J44: =IFERROR(J40/D40-1,"") -> -0.10091743 | K44: =IFERROR(K40/E40-1,"") -> -0.11386139 | L44: =IFERROR(L40/F40-1,"") -> -0.32 | M44: =IFERROR(M40/G40-1,"") -> 0.19827586 | N44: =IFERROR(N40/H40-1,"") -> -0.037406484 | O44: =IFERROR(O40/I40-1,"") -> -0.11111111 | P44: =IFERROR(P40/J40-1,"") -> -0.18367347 | ... BV44: =IFERROR(BV40/BP40-1,"") -> 0.26479721 | BW44: =IFERROR(BW40/BV40-1,"") -> 0.2282085 | BX44: =IFERROR(BX40/BW40-1,"") -> 0.099259259 | BY44: =IFERROR(BY40/BX40-1,"") -> 0.092678571 | BZ44: =IFERROR(BZ40/BY40-1,"") -> 0.086206897
B45: Segment EBITDA y/y % | I45: =IFERROR(I42/C42-1,"") | J45: =IFERROR(J42/D42-1,"") | K45: =IFERROR(K42/E42-1,"") | L45: =IFERROR(L42/F42-1,"") | M45: =IFERROR(M42/G42-1,"") | N45: =IFERROR(N42/H42-1,"") -> -0.015904573 | O45: =IFERROR(O42/I42-1,"") | P45: =IFERROR(P42/J42-1,"") | ... BV45: =IFERROR(BV42/BP42-1,"") -> 0.20722281 | BW45: =IFERROR(BW42/BV42-1,"") -> 0.18981049 | BX45: =IFERROR(BX42/BW42-1,"") -> 0.089775281 | BY45: =IFERROR(BY42/BX42-1,"") -> 0.083825137 | BZ45: =IFERROR(BZ42/BY42-1,"") -> 0.077925532 | CH45: ING_margin | CI45: 0.005 | CJ45: Δ → | CK45: -0.0125
B46: Segment operating margin % | C46: =IFERROR(C40/C39,"") -> 0.087653157 | D46: =IFERROR(D40/D39,"") -> 0.09348199 | E46: =IFERROR(E40/E39,"") -> 0.090704984 | F46: =IFERROR(F40/F39,"") -> 0.084961767 | G46: =IFERROR(G40/G39,"") -> 0.097152429 | H46: =IFERROR(H40/H39,"") -> 0.093299209 | I46: =IFERROR(I40/I39,"") -> 0.081570997 | J46: =IFERROR(J40/J39,"") -> 0.098098098 | ... BV46: =IFERROR(BV40/BV39,"") -> 0.058805162 | BW46: =CHOOSE(MATCH($CA$2,{"Bull","Base","Bear"},0),$CI$52,$CJ$52,$CK$52) -> 0.0675 | BX46: =CHOOSE(MATCH($CA$2,{"Bull","Base","Bear"},0),$CI$53,$CJ$53,$CK$53) -> 0.07 | BY46: =CHOOSE(MATCH($CA$2,{"Bull","Base","Bear"},0),$CI$54,$CJ$54,$CK$54) -> 0.0725 | BZ46: =CHOOSE(MATCH($CA$2,{"Bull","Base","Bear"},0),$CI$55,$CJ$55,$CK$55) -> 0.075 | CA46: 2027E–2030E segment operating margin: scenario lever (NNS_margin). 2026E margin is an output of FY26 guidance. | CC46: =IFERROR(AVERAGE(BV46,BW46,BX46,BY46,BZ46),"n/m") -> 0.068761032 | CD46: =IFERROR(AVERAGE(AR46,AX46,BD46,BJ46,BP46),"n/m") -> 0.055408143 | CE46: =IFERROR(AVERAGE(N46,T46,Z46,AF46,AL46,AR46,AX46,BD46,BJ46,BP46),"n/m") -> 0.06454647 | CH46: 2027E | CI46: =CJ46+$CI$45 -> 0.0775 | CJ46: 0.0725 | CK46: =CJ46+$CK$45 -> 0.06
B47: Segment EBITDA margin % | C47: =IFERROR(C42/C39,"") | D47: =IFERROR(D42/D39,"") | E47: =IFERROR(E42/E39,"") | F47: =IFERROR(F42/F39,"") | G47: =IFERROR(G42/G39,"") | H47: =IFERROR(H42/H39,"") -> 0.11703118 | I47: =IFERROR(I42/I39,"") | J47: =IFERROR(J42/J39,"") | ... BZ47: =IFERROR(BZ42/BZ39,"") -> 0.0965 | CC47: =IFERROR(AVERAGE(BV47,BW47,BX47,BY47,BZ47),"n/m") -> 0.090207591 | CD47: =IFERROR(AVERAGE(AR47,AX47,BD47,BJ47,BP47),"n/m") -> 0.079404763 | CE47: =IFERROR(AVERAGE(N47,T47,Z47,AF47,AL47,AR47,AX47,BD47,BJ47,BP47),"n/m") -> 0.08891494 | CH47: 2028E | CI47: =CJ47+$CI$45 -> 0.08 | CJ47: 0.075 | CK47: =CJ47+$CK$45 -> 0.0625
B48: Incremental OI margin (ΔOI / ΔRev) | I48: =IFERROR((I40-C40)/(I39-C39),"") -> 0.17647059 | J48: =IFERROR((J40-D40)/(J39-D39),"") -> 0.065868263 | K48: =IFERROR((K40-E40)/(K39-E39),"") -> 0.09787234 | L48: =IFERROR((L40-F40)/(L39-F39),"") -> 0.16080402 | M48: =IFERROR((M40-G40)/(M39-G39),"") -> -0.30666667 | N48: =IFERROR((N40-H40)/(N39-H39),"") -> 0.071770335 | O48: =IFERROR((O40-I40)/(O39-I39),"") -> 0.40909091 | P48: =IFERROR((P40-J40)/(P39-J39),"") -> -9 | ... BV48: =IFERROR((BV40-BP40)/(BV39-BP39),"") -> 0.14316009 | BW48: =IFERROR((BW40-BV40)/(BW39-BV39),"") -> 0.19171197 | BX48: =IFERROR((BX40-BW40)/(BX39-BW39),"") -> 0.11166667 | BY48: =IFERROR((BY40-BX40)/(BY39-BX39),"") -> 0.11795455 | BZ48: =IFERROR((BZ40-BY40)/(BZ39-BY39),"") -> 0.125 | CH48: 2029E | CI48: =CJ48+$CI$45 -> 0.0825 | CJ48: 0.0775 | CK48: =CJ48+$CK$45 -> 0.065
B49: Operating metrics — Newport News | CH49: 2030E | CI49: =CJ49+$CI$45 -> 0.085 | CJ49: 0.08 | CK49: =CJ49+$CK$45 -> 0.0675
B50: Funded backlog | C50: 7724 | D50: 7779 | E50: =D50 -> 7779 | F50: 6935 | G50: 6026 | H50: =G50 -> 6026 | I50: 8032 | J50: 7447 | K50: =J50 -> 7447 | L50: 7106 | M50: 5799 | N50: =M50 -> 5799 | O50: 6475 | P50: 6471 | Q50: =P50 -> 6471 | R50: 7682 | S50: 6976 | T50: =S50 -> 6976 | U50: 7474 | V50: 8004 | W50: =V50 -> 8004 | X50: 7529 | Y50: 6767 | Z50: =Y50 -> 6767 | AA50: 8615 | AB50: 8285 | AC50: =AB50 -> 8285 | AD50: 7570 | AE50: 8414 | AF50: =AE50 -> 8414 | AG50: 10537 | AH50: 10610 | AI50: =AH50 -> 10610 | AJ50: 10164 | AK50: 9536 | AL50: =AK50 -> 9536 | AM50: 13321 | AN50: 12330 | AO50: =AN50 -> 12330 | AP50: 11715 | AQ50: 11121 | AR50: =AQ50 -> 11121 | AS50: 12954 | AT50: 13025 | AU50: =AT50 -> 13025 | AV50: 11914 | AW50: 11665 | AX50: =AW50 -> 11665 | AY50: 13579 | AZ50: 12632 | BA50: =AZ50 -> 12632 | BB50: 11931 | BC50: 11890 | BD50: =BC50 -> 11890 | BE50: 12132 | BF50: 12006 | BG50: =BF50 -> 12006 | BH50: 11636 | BI50: 12079 | BJ50: =BI50 -> 12079 | BK50: 12827 | BL50: 16557 | BM50: =BL50 -> 16557 | BN50: 15586 | BO50: 15337 | BP50: =BO50 -> 15337 | BQ50: 14523 | BR50: 15849 | BS50: =BR50 -> 15849
B51: Unfunded backlog | C51: 6065 | D51: 9307 | E51: =D51 -> 9307 | F51: 9464 | G51: 9513 | H51: =G51 -> 9513 | I51: 7098 | J51: 7183 | K51: =J51 -> 7183 | L51: 7195 | M51: 7127 | N51: =M51 -> 7127 | O51: 5901 | P51: 5056 | Q51: =P51 -> 5056 | R51: 5974 | S51: 5608 | T51: =S51 -> 5608 | U51: 4602 | V51: 3751 | W51: =V51 -> 3751 | X51: 3671 | Y51: 4144 | Z51: =Y51 -> 4144 | AA51: 18607 | AB51: 17995 | AC51: =AB51 -> 17995 | AD51: 19179 | AE51: 26352 | AF51: =AE51 -> 26352 | AG51: 22407 | AH51: 21946 | AI51: =AH51 -> 21946 | AJ51: 21088 | AK51: 23132 | AL51: =AK51 -> 23132 | AM51: 22247 | AN51: 22649 | AO51: =AN51 -> 22649 | AP51: 21741 | AQ51: 21198 | AR51: =AQ51 -> 21198 | AS51: 18859 | AT51: 18386 | AU51: =AT51 -> 18386 | AV51: 18675 | AW51: 17742 | AX51: =AW51 -> 17742 | AY51: 15069 | AZ51: 16251 | BA51: =AZ51 -> 16251 | BB51: 16012 | BC51: 15349 | BD51: =BC51 -> 15349 | BE51: 16075 | BF51: 15468 | BG51: =BF51 -> 15468 | BH51: 15627 | BI51: 14666 | BJ51: =BI51 -> 14666 | BK51: 13880 | BL51: 15276 | BM51: =BL51 -> 15276 | BN51: 15420 | BO51: 14588 | BP51: =BO51 -> 14588 | BQ51: 15949 | BR51: 16639 | BS51: =BR51 -> 16639 | CH51: NNS_margin | CI51: 0.005 | CJ51: Δ → | CK51: -0.0125
B52: Total backlog | C52: =C50+C51 -> 13789 | D52: =D50+D51 -> 17086 | E52: =E50+E51 -> 17086 | F52: =F50+F51 -> 16399 | G52: =G50+G51 -> 15539 | H52: =H50+H51 -> 15539 | I52: =I50+I51 -> 15130 | J52: =J50+J51 -> 14630 | ... BS52: =BS50+BS51 -> 32488 | BT52: =BR52+BT53-BT39 -> 32488 | BU52: =BT52+BU53-BU39 -> 32488 | BV52: =BU52 -> 32488 | BW52: =BV52+BW53-BW39 -> 32488 | BX52: =BW52+BX53-BX39 -> 32488 | BY52: =BX52+BY53-BY39 -> 32488 | BZ52: =BY52+BZ53-BZ39 -> 32488 | CA52: Forecast backlog = prior backlog + new awards − segment revenue; awards = revenue × book-to-bill assumption. | CC52: =IFERROR((BZ52/BP52)^(1/5)-1,"n/m") -> 0.01657111 | CD52: =IFERROR((BP52/AL52)^(1/5)-1,"n/m") -> -0.017387414 | CE52: =IFERROR((BP52/H52)^(1/10)-1,"n/m") -> 0.067729174 | CH52: 2027E | CI52: =CJ52+$CI$51 -> 0.0725 | CJ52: 0.0675 | CK52: =CJ52+$CK$51 -> 0.055
B53: Implied new awards (ΔBacklog + Revenue) | D53: =IF(AND(ISNUMBER(D52),ISNUMBER(C52)),D52-C52+D39,"") -> 4463 | E53: =IF(AND(ISNUMBER(C53),ISNUMBER(D53)),C53+D53,"") | F53: =IF(AND(ISNUMBER(F52),ISNUMBER(D52)),F52-D52+F39,"") -> 490 | G53: =IF(AND(ISNUMBER(G52),ISNUMBER(F52)),G52-F52+G39,"") -> 334 | I53: =IF(AND(ISNUMBER(I52),ISNUMBER(G52)),I52-G52+I39,"") -> 584 | J53: =IF(AND(ISNUMBER(J52),ISNUMBER(I52)),J52-I52+J39,"") -> 499 | K53: =IF(AND(ISNUMBER(I53),ISNUMBER(J53)),I53+J53,"") -> 1083 | L53: =IF(AND(ISNUMBER(L52),ISNUMBER(J52)),L52-J52+L39,"") -> 649 | M53: =IF(AND(ISNUMBER(M52),ISNUMBER(L52)),M52-L52+M39,"") -> -256 | N53: =IF(AND(ISNUMBER(N52),ISNUMBER(H52)),N52-H52+N39,"") -> 1476 | O53: =IF(AND(ISNUMBER(O52),ISNUMBER(M52)),O52-M52+O39,"") -> 421 | P53: =IF(AND(ISNUMBER(P52),ISNUMBER(O52)),P52-O52+P39,"") -> 152 | Q53: =IF(AND(ISNUMBER(O53),ISNUMBER(P53)),O53+P53,"") -> 573 | R53: =IF(AND(ISNUMBER(R52),ISNUMBER(P52)),R52-P52+R39,"") -> 3182 | S53: =IF(AND(ISNUMBER(S52),ISNUMBER(R52)),S52-R52+S39,"") -> 67 | T53: =IF(AND(ISNUMBER(T52),ISNUMBER(N52)),T52-N52+T39,"") -> 3822 | U53: =IF(AND(ISNUMBER(U52),ISNUMBER(S52)),U52-S52+U39,"") -> 574 | V53: =IF(AND(ISNUMBER(V52),ISNUMBER(U52)),V52-U52+V39,"") -> 862 | W53: =IF(AND(ISNUMBER(U53),ISNUMBER(V53)),U53+V53,"") -> 1436 | X53: =IF(AND(ISNUMBER(X52),ISNUMBER(V52)),X52-V52+X39,"") -> 624 | Y53: =IF(AND(ISNUMBER(Y52),ISNUMBER(X52)),Y52-X52+Y39,"") -> 1063 | Z53: =IF(AND(ISNUMBER(Z52),ISNUMBER(T52)),Z52-T52+Z39,"") -> 3123 | AA53: =IF(AND(ISNUMBER(AA52),ISNUMBER(Y52)),AA52-Y52+AA39,"") -> 17590 | AB53: =IF(AND(ISNUMBER(AB52),ISNUMBER(AA52)),AB52-AA52+AB39,"") -> 337 | AC53: =IF(AND(ISNUMBER(AA53),ISNUMBER(AB53)),AA53+AB53,"") -> 17927 | AD53: =IF(AND(ISNUMBER(AD52),ISNUMBER(AB52)),AD52-AB52+AD39,"") -> 1743 | AE53: =IF(AND(ISNUMBER(AE52),ISNUMBER(AD52)),AE52-AD52+AE39,"") -> 9416 | AF53: =IF(AND(ISNUMBER(AF52),ISNUMBER(Z52)),AF52-Z52+AF39,"") -> 29086 | AG53: =IF(AND(ISNUMBER(AG52),ISNUMBER(AE52)),AG52-AE52+AG39,"") -> -481 | AH53: =IF(AND(ISNUMBER(AH52),ISNUMBER(AG52)),AH52-AG52+AH39,"") -> 734 | AI53: =IF(AND(ISNUMBER(AG53),ISNUMBER(AH53)),AG53+AH53,"") -> 253 | AJ53: =IF(AND(ISNUMBER(AJ52),ISNUMBER(AH52)),AJ52-AH52+AJ39,"") -> 54 | AK53: =IF(AND(ISNUMBER(AK52),ISNUMBER(AJ52)),AK52-AJ52+AK39,"") -> 3166 | AL53: =IF(AND(ISNUMBER(AL52),ISNUMBER(AF52)),AL52-AF52+AL39,"") -> 3473 | AM53: =IF(AND(ISNUMBER(AM52),ISNUMBER(AK52)),AM52-AK52+AM39,"") -> 4307 | AN53: =IF(AND(ISNUMBER(AN52),ISNUMBER(AM52)),AN52-AM52+AN39,"") -> 774 | AO53: =IF(AND(ISNUMBER(AM53),ISNUMBER(AN53)),AM53+AN53,"") -> 5081 | AP53: =IF(AND(ISNUMBER(AP52),ISNUMBER(AN52)),AP52-AN52+AP39,"") -> -169 | AQ53: =IF(AND(ISNUMBER(AQ52),ISNUMBER(AP52)),AQ52-AP52+AQ39,"") -> 402 | AR53: =IF(AND(ISNUMBER(AR52),ISNUMBER(AL52)),AR52-AL52+AR39,"") -> 5314 | AS53: =IF(AND(ISNUMBER(AS52),ISNUMBER(AQ52)),AS52-AQ52+AS39,"") -> 884 | AT53: =IF(AND(ISNUMBER(AT52),ISNUMBER(AS52)),AT52-AS52+AT39,"") -> 1031 | AU53: =IF(AND(ISNUMBER(AS53),ISNUMBER(AT53)),AS53+AT53,"") -> 1915 | AV53: =IF(AND(ISNUMBER(AV52),ISNUMBER(AT52)),AV52-AT52+AV39,"") -> 623 | AW53: =IF(AND(ISNUMBER(AW52),ISNUMBER(AV52)),AW52-AV52+AW39,"") -> 402 | AX53: =IF(AND(ISNUMBER(AX52),ISNUMBER(AR52)),AX52-AR52+AX39,"") -> 2940 | AY53: =IF(AND(ISNUMBER(AY52),ISNUMBER(AW52)),AY52-AW52+AY39,"") -> 747 | AZ53: =IF(AND(ISNUMBER(AZ52),ISNUMBER(AY52)),AZ52-AY52+AZ39,"") -> 1744 | BA53: =IF(AND(ISNUMBER(AY53),ISNUMBER(AZ53)),AY53+AZ53,"") -> 2491 | BB53: =IF(AND(ISNUMBER(BB52),ISNUMBER(AZ52)),BB52-AZ52+BB39,"") -> 513 | BC53: =IF(AND(ISNUMBER(BC52),ISNUMBER(BB52)),BC52-BB52+BC39,"") -> 961 | BD53: =IF(AND(ISNUMBER(BD52),ISNUMBER(AX52)),BD52-AX52+BD39,"") -> 3965 | BE53: =IF(AND(ISNUMBER(BE52),ISNUMBER(BC52)),BE52-BC52+BE39,"") -> 2402 | BF53: =IF(AND(ISNUMBER(BF52),ISNUMBER(BE52)),BF52-BE52+BF39,"") -> 802 | BG53: =IF(AND(ISNUMBER(BE53),ISNUMBER(BF53)),BE53+BF53,"") -> 3204 | BH53: =IF(AND(ISNUMBER(BH52),ISNUMBER(BF52)),BH52-BF52+BH39,"") -> 1201 | BI53: =IF(AND(ISNUMBER(BI52),ISNUMBER(BH52)),BI52-BH52+BI39,"") -> 1070 | BJ53: =IF(AND(ISNUMBER(BJ52),ISNUMBER(BD52)),BJ52-BD52+BJ39,"") -> 5475 | BK53: =IF(AND(ISNUMBER(BK52),ISNUMBER(BI52)),BK52-BI52+BK39,"") -> 1358 | BL53: =IF(AND(ISNUMBER(BL52),ISNUMBER(BK52)),BL52-BK52+BL39,"") -> 6729 | BM53: =IF(AND(ISNUMBER(BK53),ISNUMBER(BL53)),BK53+BL53,"") -> 8087 | BN53: =IF(AND(ISNUMBER(BN52),ISNUMBER(BL52)),BN52-BL52+BN39,"") -> 790 | BO53: =IF(AND(ISNUMBER(BO52),ISNUMBER(BN52)),BO52-BN52+BO39,"") -> 810 | BP53: =IF(AND(ISNUMBER(BP52),ISNUMBER(BJ52)),BP52-BJ52+BP39,"") -> 9687 | BQ53: =IF(AND(ISNUMBER(BQ52),ISNUMBER(BO52)),BQ52-BO52+BQ39,"") -> 2212 | BR53: =IF(AND(ISNUMBER(BR52),ISNUMBER(BQ52)),BR52-BQ52+BR39,"") -> 3865 | BS53: =IF(AND(ISNUMBER(BQ53),ISNUMBER(BR53)),BQ53+BR53,"") -> 6077 | BT53: =BT39*BT54 -> 1802.6184 | BU53: =BU39*BU54 -> 1802.6184 | BV53: =SUM(BQ53,BR53,BT53,BU53) -> 9682.2368 | BW53: =BW39*BW54 -> 7617.5834 | BX53: =BX39*BX54 -> 8074.6384 | BY53: =BY39*BY54 -> 8518.7435 | BZ53: =BZ39*BZ54 -> 8944.6807 | CA53: Implied awards = change in total backlog + segment revenue (backlog also moves for de-obligations/adjustments; not separately disclosed). | CH53: 2028E | CI53: =CJ53+$CI$51 -> 0.075 | CJ53: 0.07 | CK53: =CJ53+$CK$51 -> 0.0575
B54: Book-to-bill (x) | C54: =IF(ISNUMBER(C53),IFERROR(C53/C39,""),"") | D54: =IF(ISNUMBER(D53),IFERROR(D53/D39,""),"") -> 3.8276158 | E54: =IF(ISNUMBER(E53),IFERROR(E53/E39,""),"") | F54: =IF(ISNUMBER(F53),IFERROR(F53/F39,""),"") -> 0.41631266 | G54: =IF(ISNUMBER(G53),IFERROR(G53/G39,""),"") -> 0.27973199 | H54: =IF(ISNUMBER(H53),IFERROR(H53/H39,""),"") | I54: =IF(ISNUMBER(I53),IFERROR(I53/I39,""),"") -> 0.58811682 | J54: =IF(ISNUMBER(J53),IFERROR(J53/J39,""),"") -> 0.4994995 | ... BS54: =IF(ISNUMBER(BS53),IFERROR(BS53/BS39,""),"") -> 1.7293682 | BT54: =$BV$54 -> 1 | BU54: =$BV$54 -> 1 | BV54: 1 | BW54: 1 | BX54: 1 | BY54: 1 | BZ54: 1 | CA54: Book-to-bill input (blue): 2026E cell = 2H/26 assumption applied to Q3/Q4-26E; 2027E+ held at 1.0x (backlog stable in $). Shipbuilding awards are lumpy (multi-ship / multi-year contracts) — adjust for known awards. | CH54: 2029E | CI54: =CJ54+$CI$51 -> 0.0775 | CJ54: 0.0725 | CK54: =CJ54+$CK$51 -> 0.06
B55: Backlog / revenue (years) | H55: =IFERROR(H52/H39,"") -> 3.6154025 | N55: =IFERROR(N52/N39,"") -> 3.1611641 | T55: =IFERROR(T52/T39,"") -> 3.0220941 | Z55: =IFERROR(Z52/Z39,"") -> 2.2750209 | AF55: =IFERROR(AF52/AF39,"") -> 6.646148 | AL55: =IFERROR(AL52/AL39,"") -> 5.8639383 | AR55: =IFERROR(AR52/AR39,"") -> 5.7070457 | AX55: =IFERROR(AX52/AX39,"") -> 5.0251196 | BD55: =IFERROR(BD52/BD39,"") -> 4.4413827 | BJ55: =IFERROR(BJ52/BJ39,"") -> 4.48065 | BP55: =IFERROR(BP52/BP39,"") -> 4.5988935 | BV55: =IFERROR(BV52/BV39,"") -> 4.5634105 | BW55: =IFERROR(BW52/BW39,"") -> 4.2648696 | BX55: =IFERROR(BX52/BX39,"") -> 4.0234619 | BY55: =IFERROR(BY52/BY39,"") -> 3.813708 | BZ55: =IFERROR(BZ52/BZ39,"") -> 3.6321028 | CH55: 2030E | CI55: =CJ55+$CI$51 -> 0.08 | CJ55: 0.075 | CK55: =CJ55+$CK$51 -> 0.0625
B56: % of Revenue — Newport News | CA56: % OF REVENUE drivers — hardcoded inputs that drive forecast segment cost / capital intensity
B57: Intersegment revenue % of segment revenue | C57: =IFERROR(C38/C39,"n/d") -> 0 | D57: =IFERROR(D38/D39,"n/d") -> 0 | E57: =IFERROR(E38/E39,"n/d") -> 0 | F57: =IFERROR(F38/F39,"n/d") -> 0 | G57: =IFERROR(G38/G39,"n/d") -> 0 | H57: =IFERROR(H38/H39,"n/d") -> 0 | I57: =IFERROR(I38/I39,"n/d") -> 0 | J57: =IFERROR(J38/J39,"n/d") -> 0 | ... BS57: =IFERROR(BS38/BS39,"n/d") -> 0 | BT57: =IFERROR(BT38/BT39,"") -> 0 | BU57: =IFERROR(BU38/BU39,"") -> 0 | BV57: =IFERROR(BV38/BV39,"") -> 0 | BW57: =$BP$57 -> 0.00015368065 | BX57: =$BP$57 -> 0.00015368065 | BY57: =$BP$57 -> 0.00015368065 | BZ57: =$BP$57 -> 0.00015368065 | CA57: Held at FY2025 actual level (linked). | CH57: MT_margin | CI57: 0.005 | CJ57: Δ → | CK57: -0.0075
B58: D&A % of revenue | C58: =IFERROR(C41/C39,"") -> 0 | D58: =IFERROR(D41/D39,"") -> 0 | E58: =IFERROR(E41/E39,"") -> 0 | F58: =IFERROR(F41/F39,"") -> 0 | G58: =IFERROR(G41/G39,"") -> 0 | H58: =IFERROR(H41/H39,"") -> 0.023731968 | I58: =IFERROR(I41/I39,"") -> 0 | J58: =IFERROR(J41/J39,"") -> 0 | ... BV58: =IFERROR(BV41/BV39,"") -> 0.021232794 | BW58: 0.0215 | BX58: 0.0215 | BY58: 0.0215 | BZ58: 0.0215 | CA58: NNS D&A ~2.15% of revenue (FY25 2.2%); facilities investment (CVN/SSN capacity) keeps ratio broadly stable. | CH58: 2027E | CI58: =CJ58+$CI$57 -> 0.0575 | CJ58: 0.0525 | CK58: =CJ58+$CK$57 -> 0.045
B59: Capital expenditures (segment) | H59: 130 | N59: 176 | T59: 224 | Z59: 261 | AF59: 244 | AL59: 212 | AR59: 201 | AX59: 182 | BD59: 196 | BE59: 56 | BF59: 70 | BG59: =BE59+BF59 -> 126 | BH59: 55 | BI59: 87 | BJ59: 268 | BK59: 49 | BL59: 74 | BM59: =BK59+BL59 -> 123 | BN59: 80 | BO59: 100 | BP59: 303 | BQ59: 57 | BV59: =BV39*BV60 -> 463.27139 | BW59: =BW39*BW60 -> 468.16148 | BX59: =BX39*BX60 -> 467.05992 | BY59: =BY39*BY60 -> 461.95145 | BZ59: =BZ39*BZ60 -> 452.71243 | CA59: Segment capex = revenue × segment capex %. Illustrative allocation of group capex (group capex in the CF statement is driven by the group capex % of revenue line). | CH59: 2028E | CI59: =CJ59+$CI$57 -> 0.06 | CJ59: 0.055 | CK59: =CJ59+$CK$57 -> 0.0475
B60: Capex % of revenue | H60: =IFERROR(H59/H39,"") -> 0.030246626 | N60: =IFERROR(N59/N39,"") -> 0.043042309 | T60: =IFERROR(T59/T39,"") -> 0.053794428 | Z60: =IFERROR(Z59/Z39,"") -> 0.05442035 | AF60: =IFERROR(AF59/AF39,"") -> 0.046645001 | AL60: =IFERROR(AL59/AL39,"") -> 0.038054209 | AR60: =IFERROR(AR59/AR39,"") -> 0.035493555 | AX60: =IFERROR(AX59/AX39,"") -> 0.031100478 | BD60: =IFERROR(BD59/BD39,"") -> 0.031958259 | BJ60: =IFERROR(BJ59/BJ39,"") -> 0.044898643 | BP60: =IFERROR(BP59/BP39,"") -> 0.046565237 | BV60: =IFERROR($BP$60/$BP$227*BV227,0) -> 0.065073182 | BW60: =IFERROR($BP$60/$BP$227*BW227,0) -> 0.061458005 | BX60: =IFERROR($BP$60/$BP$227*BX227,0) -> 0.057842828 | BY60: =IFERROR($BP$60/$BP$227*BY227,0) -> 0.054227652 | BZ60: =IFERROR($BP$60/$BP$227*BZ227,0) -> 0.050612475 | CA60: Segment capex % = group capex % (CF memo) × FY2025 segment capex intensity relative to group. | CH60: 2029E | CI60: =CJ60+$CI$57 -> 0.0625 | CJ60: 0.0575 | CK60: =CJ60+$CK$57 -> 0.05
CH61: 2030E | CI61: =CJ61+$CI$57 -> 0.065 | CJ61: 0.06 | CK61: =CJ61+$CK$57 -> 0.0525
B62: Mission Technologies (Technical Solutions pre-2022) | CA62: MISSION TECHNOLOGIES (TECHNICAL SOLUTIONS PRE-2022) — modelling logic
B63: Revenue (external) | C63: =IF(ISNUMBER(C64),C65-C64,"n/d") -> n/d | D63: =IF(ISNUMBER(D64),D65-D64,"n/d") -> n/d | E63: =IF(ISNUMBER(E64),E65-E64,"n/d") -> n/d | F63: =IF(ISNUMBER(F64),F65-F64,"n/d") -> n/d | G63: =IF(ISNUMBER(G64),G65-G64,"n/d") -> n/d | H63: =IF(ISNUMBER(H64),H65-H64,"n/d") -> n/d | I63: =IF(ISNUMBER(I64),I65-I64,"n/d") -> n/d | J63: =IF(ISNUMBER(J64),J65-J64,"n/d") -> n/d | ... BZ63: =IF(ISNUMBER(BZ64),BZ65-BZ64,"n/d") -> 3502.7382 | CA63: External revenue = segment revenue less intersegment sales. Intersegment sales by segment not disclosed before FY2018 (n/d). | CH63: Buybacks ($m) | CI63: 150 | CJ63: Δ → | CK63: -200
B64: Intersegment revenue | U64: 26 | V64: 32 | W64: =U64+V64 -> 58 | X64: 31 | Y64: 34 | Z64: 123 | AA64: 23 | AB64: 30 | AC64: =AA64+AB64 -> 53 | AD64: 26 | AE64: 34 | AF64: 113 | AG64: 21 | AH64: 34 | AI64: =AG64+AH64 -> 55 | AJ64: 36 | AK64: 49 | AL64: 140 | AM64: 32 | AN64: 30 | AO64: =AM64+AN64 -> 62 | AP64: 31 | AQ64: 24 | AR64: 117 | AS64: 30 | AU64: =AS64+AT64 -> 30 | AV64: 31 | AW64: 29 | AX64: 116 | AY64: 30 | AZ64: 28 | BA64: =AY64+AZ64 -> 58 | BB64: 30 | BC64: 30 | BD64: 118 | BE64: 31 | BF64: 33 | BG64: =BE64+BF64 -> 64 | BH64: 34 | BI64: 29 | BJ64: 127 | BK64: 30 | BL64: 32 | BM64: =BK64+BL64 -> 62 | BN64: 37 | BO64: 33 | BP64: 132 | BQ64: 36 | BR64: 34 | BS64: =BQ64+BR64 -> 70 | BT64: =BS64/2 -> 35 | BU64: =BS64/2 -> 35 | BV64: =SUM(BQ64,BR64,BT64,BU64) -> 140 | BW64: =BW65*BW83 -> 139.80552 | BX64: =BX65*BX83 -> 145.39774 | BY64: =BY65*BY83 -> 151.94064 | BZ64: =BZ65*BZ83 -> 158.77797 | CA64: Q3/Q4-26E at 1H/26 run-rate; 2027E+ = segment revenue × intersegment % (held at FY2025 level). | CH64: 2026E | CI64: =MAX(0,CJ64+$CI$63) -> 150 | CJ64: 0 | CK64: =MAX(0,CJ64+$CK$63) -> 0
B65: Segment revenue (as reported, incl. intersegment) | C65: 40 | D65: 35 | E65: =C65+D65 -> 75 | F65: 30 | G65: 154 | H65: 616 | I65: 208 | J65: 143 | K65: =I65+J65 -> 351 | L65: 154 | M65: 186 | N65: 691 | O65: 225 | P65: 244 | Q65: =O65+P65 -> 469 | R65: 241 | S65: 242 | T65: 952 | U65: 233 | V65: 243 | W65: =U65+V65 -> 476 | X65: 245 | Y65: 185 | Z65: 906 | AA65: 240 | AB65: 321 | AC65: =AA65+AB65 -> 561 | AD65: 326 | AE65: 350 | AF65: 1237 | AG65: 317 | AH65: 320 | AI65: =AG65+AH65 -> 637 | AJ65: 320 | AK65: 311 | AL65: 1268 | AM65: 259 | AN65: 237 | AO65: =AM65+AN65 -> 496 | AP65: 394 | AQ65: 586 | AR65: 1476 | AS65: 590 | AT65: 600 | AU65: =AS65+AT65 -> 1190 | AV65: 595 | AW65: 602 | AX65: 2387 | AY65: 624 | AZ65: 645 | BA65: =AY65+AZ65 -> 1269 | BB65: 685 | BC65: 745 | BD65: 2699 | BE65: 750 | BF65: 765 | BG65: =BE65+BF65 -> 1515 | BH65: 709 | BI65: 713 | BJ65: 2937 | BK65: 735 | BL65: 791 | BM65: =BK65+BL65 -> 1526 | BN65: 787 | BO65: 731 | BP65: 3044 | BQ65: 748 | BR65: 760 | BS65: =BQ65+BR65 -> 1508 | BT65: =(CHOOSE(MATCH($CA$2,{"Bull","Base","Bear"},0),$CI$14,$CJ$14,$CK$14)-BS65)/2 -> 796 | BU65: =(CHOOSE(MATCH($CA$2,{"Bull","Base","Bear"},0),$CI$14,$CJ$14,$CK$14)-BS65)/2 -> 796 | BV65: =SUM(BQ65,BR65,BT65,BU65) -> 3100 | BW65: =BV65*(1+BW69) -> 3224 | BX65: =BW65*(1+BX69) -> 3352.96 | BY65: =BX65*(1+BY69) -> 3503.8432 | BZ65: =BY65*(1+BZ69) -> 3661.5161 | CA65: Q3/26E–Q4/26E: FY26 guidance (scenario: high / mid / low end) less 1H/26 actuals, split evenly across Q3 and Q4. Shipbuilding guidance allocated between Ingalls and Newport News by 1H/26 revenue mix; 2H shipbuilding OI allocated by 2H revenue × 1H margin weights. 2027E+: prior year × (1 + scenario revenue growth). | CC65: =IFERROR((BZ65/BP65)^(1/5)-1,"n/m") -> 0.037631771 | CD65: =IFERROR((BP65/AL65)^(1/5)-1,"n/m") -> 0.19142053 | CE65: =IFERROR((BP65/H65)^(1/10)-1,"n/m") -> 0.17323874 | CH65: 2027E | CI65: =MAX(0,CJ65+$CI$63) -> 350 | CJ65: 200 | CK65: =MAX(0,CJ65+$CK$63) -> 0
B66: Segment operating income | C66: -10 | D66: -64 | E66: =C66+D66 -> -74 | F66: -5 | G66: -51 | H66: -113 | I66: 3 | J66: -2 | K66: =I66+J66 -> 1 | L66: 6 | M66: 1 | N66: 8 | O66: -18 | P66: 9 | Q66: =O66+P66 -> -9 | R66: 22 | S66: 8 | T66: 21 | U66: 2 | V66: 7 | W66: =U66+V66 -> 9 | X66: 16 | Y66: -5 | Z66: 20 | AA66: 2 | AB66: -2 | AC66: =AA66+AB66 -> 0 | AD66: 9 | AE66: -23 | AF66: -14 | AG66: -7 | AH66: 9 | AI66: =AG66+AH66 -> 2 | AJ66: 21 | AK66: 18 | AL66: 41 | AM66: 7 | AN66: 13 | AO66: =AM66+AN66 -> 20 | AP66: 13 | AQ66: 17 | AR66: 50 | AS66: 9 | AT66: 25 | AU66: =AS66+AT66 -> 34 | AV66: 14 | AW66: 15 | AX66: 63 | AY66: 17 | AZ66: 9 | BA66: =AY66+AZ66 -> 26 | BB66: 24 | BC66: 51 | BD66: 101 | BE66: 28 | BF66: 36 | BG66: =BE66+BF66 -> 64 | BH66: 33 | BI66: 19 | BJ66: 116 | BK66: 40 | BL66: 36 | BM66: =BK66+BL66 -> 76 | BN66: 34 | BO66: 43 | BP66: 153 | BQ66: 35 | BR66: 55 | BS66: =BQ66+BR66 -> 90 | BT66: =(CHOOSE(MATCH($CA$2,{"Bull","Base","Bear"},0),$CI$14,$CJ$14,$CK$14)*CHOOSE(MATCH($CA$2,{"Bull","Base","Bear"},0),$CI$15,$CJ$15,$CK$15)-BS66)/2 -> 32.5 | BU66: =(CHOOSE(MATCH($CA$2,{"Bull","Base","Bear"},0),$CI$14,$CJ$14,$CK$14)*CHOOSE(MATCH($CA$2,{"Bull","Base","Bear"},0),$CI$15,$CJ$15,$CK$15)-BS66)/2 -> 32.5 | BV66: =SUM(BQ66,BR66,BT66,BU66) -> 155 | BW66: =BW65*BW72 -> 169.26 | BX66: =BX65*BX72 -> 184.4128 | BY66: =BY65*BY72 -> 201.47098 | BZ66: =BZ65*BZ72 -> 219.69097 | CA66: Q3/26E–Q4/26E: FY26 guidance (scenario: high / mid / low end) less 1H/26 actuals, split evenly across Q3 and Q4. Shipbuilding guidance allocated between Ingalls and Newport News by 1H/26 revenue mix; 2H shipbuilding OI allocated by 2H revenue × 1H margin weights. 2027E+: segment revenue × scenario segment operating margin. | CC66: =IFERROR((BZ66/BP66)^(1/5)-1,"n/m") -> 0.075038839 | CD66: =IFERROR((BP66/AL66)^(1/5)-1,"n/m") -> 0.30131224 | CE66: =IFERROR((BP66/H66)^(1/10)-1,"n/m") -> n/m | CH66: 2028E | CI66: =MAX(0,CJ66+$CI$63) -> 400 | CJ66: 250 | CK66: =MAX(0,CJ66+$CK$63) -> 50
B67: Depreciation & amortization | H67: 13 | N67: 9 | T67: 25 | Z67: 20 | AF67: 32 | AL67: 40 | AR67: 72 | AX67: 130 | BD67: 120 | BE67: 27 | BF67: 28 | BG67: =BE67+BF67 -> 55 | BH67: 27 | BI67: 28 | BJ67: 110 | BK67: 25 | BL67: 26 | BM67: =BK67+BL67 -> 51 | BN67: 25 | BO67: 27 | BP67: 103 | BQ67: 20 | BR67: 21 | BS67: =BQ67+BR67 -> 41 | BT67: =BS67/2*($CJ$24-BS102)/BS102 -> 23.145161 | BU67: =BS67/2*($CJ$24-BS102)/BS102 -> 23.145161 | BV67: =SUM(BQ67,BR67,BT67,BU67) -> 87.290323 | BW67: =BW65*BW84 -> 83.824 | BX67: =BX65*BX84 -> 87.17696 | BY67: =BY65*BY84 -> 91.099923 | BZ67: =BZ65*BZ84 -> 95.19942 | CA67: FY D&A by segment from 10-K segment note (quarterly disclosure from FY2024 under ASU 2023-07). Q3/Q4-26E: 1H/26 run-rate scaled to FY26 D&A guidance (~$330m). 2027E+: revenue × D&A %. | CH67: 2029E | CI67: =MAX(0,CJ67+$CI$63) -> 450 | CJ67: 300 | CK67: =MAX(0,CJ67+$CK$63) -> 100
B68: Segment EBITDA (segment OI + D&A) | C68: =IF(ISNUMBER(C67),C66+C67,"") | D68: =IF(ISNUMBER(D67),D66+D67,"") | E68: =IF(ISNUMBER(E67),E66+E67,"") | F68: =IF(ISNUMBER(F67),F66+F67,"") | G68: =IF(ISNUMBER(G67),G66+G67,"") | H68: =IF(ISNUMBER(H67),H66+H67,"") -> -100 | I68: =IF(ISNUMBER(I67),I66+I67,"") | J68: =IF(ISNUMBER(J67),J66+J67,"") | ... BZ68: =IF(ISNUMBER(BZ67),BZ66+BZ67,"") -> 314.89039 | CA68: Segment EBITDA = segment operating income + segment D&A (HII publishes MT EBITDA incl. state tax add-back; shown here on a simple OI + D&A basis for all segments). | CC68: =IFERROR((BZ68/BP68)^(1/5)-1,"n/m") -> 0.042278761 | CD68: =IFERROR((BP68/AL68)^(1/5)-1,"n/m") -> 0.25878335 | CE68: =IFERROR((BP68/H68)^(1/10)-1,"n/m") -> n/m | CH68: 2030E | CI68: =MAX(0,CJ68+$CI$63) -> 500 | CJ68: 350 | CK68: =MAX(0,CJ68+$CK$63) -> 150
B69: Revenue y/y % | I69: =IFERROR(I65/C65-1,"") -> 4.2 | J69: =IFERROR(J65/D65-1,"") -> 3.0857143 | K69: =IFERROR(K65/E65-1,"") -> 3.68 | L69: =IFERROR(L65/F65-1,"") -> 4.1333333 | M69: =IFERROR(M65/G65-1,"") -> 0.20779221 | N69: =IFERROR(N65/H65-1,"") -> 0.12175325 | O69: =IFERROR(O65/I65-1,"") -> 0.081730769 | P69: =IFERROR(P65/J65-1,"") -> 0.70629371 | ... BV69: =IFERROR(BV65/BP65-1,"") -> 0.018396846 | BW69: =CHOOSE(MATCH($CA$2,{"Bull","Base","Bear"},0),$CI$40,$CJ$40,$CK$40) -> 0.04 | BX69: =CHOOSE(MATCH($CA$2,{"Bull","Base","Bear"},0),$CI$41,$CJ$41,$CK$41) -> 0.04 | BY69: =CHOOSE(MATCH($CA$2,{"Bull","Base","Bear"},0),$CI$42,$CJ$42,$CK$42) -> 0.045 | BZ69: =CHOOSE(MATCH($CA$2,{"Bull","Base","Bear"},0),$CI$43,$CJ$43,$CK$43) -> 0.045 | CA69: 2027E–2030E revenue growth: scenario lever (MT_revGrowth, Bull/Base/Bear table →). 2026E growth is an output of FY26 guidance.
B70: Segment OI y/y % | I70: =IFERROR(I66/C66-1,"") -> -1.3 | J70: =IFERROR(J66/D66-1,"") -> -0.96875 | K70: =IFERROR(K66/E66-1,"") -> -1.0135135 | L70: =IFERROR(L66/F66-1,"") -> -2.2 | M70: =IFERROR(M66/G66-1,"") -> -1.0196078 | N70: =IFERROR(N66/H66-1,"") -> -1.0707965 | O70: =IFERROR(O66/I66-1,"") -> -7 | P70: =IFERROR(P66/J66-1,"") -> -5.5 | ... BV70: =IFERROR(BV66/BP66-1,"") -> 0.013071895 | BW70: =IFERROR(BW66/BV66-1,"") -> 0.092 | BX70: =IFERROR(BX66/BW66-1,"") -> 0.08952381 | BY70: =IFERROR(BY66/BX66-1,"") -> 0.0925 | BZ70: =IFERROR(BZ66/BY66-1,"") -> 0.090434783
B71: Segment EBITDA y/y % | I71: =IFERROR(I68/C68-1,"") | J71: =IFERROR(J68/D68-1,"") | K71: =IFERROR(K68/E68-1,"") | L71: =IFERROR(L68/F68-1,"") | M71: =IFERROR(M68/G68-1,"") | N71: =IFERROR(N68/H68-1,"") -> -1.17 | O71: =IFERROR(O68/I68-1,"") | P71: =IFERROR(P68/J68-1,"") | ... BV71: =IFERROR(BV68/BP68-1,"") -> -0.053553427 | BW71: =IFERROR(BW68/BV68-1,"") -> 0.044548529 | BX71: =IFERROR(BX68/BW68-1,"") -> 0.073121019 | BY71: =IFERROR(BY68/BX68-1,"") -> 0.077253086 | BZ71: =IFERROR(BZ68/BY68-1,"") -> 0.076287425
B72: Segment operating margin % | C72: =IFERROR(C66/C65,"") -> -0.25 | D72: =IFERROR(D66/D65,"") -> -1.8285714 | E72: =IFERROR(E66/E65,"") -> -0.98666667 | F72: =IFERROR(F66/F65,"") -> -0.16666667 | G72: =IFERROR(G66/G65,"") -> -0.33116883 | H72: =IFERROR(H66/H65,"") -> -0.18344156 | I72: =IFERROR(I66/I65,"") -> 0.014423077 | J72: =IFERROR(J66/J65,"") -> -0.013986014 | ... BV72: =IFERROR(BV66/BV65,"") -> 0.05 | BW72: =CHOOSE(MATCH($CA$2,{"Bull","Base","Bear"},0),$CI$58,$CJ$58,$CK$58) -> 0.0525 | BX72: =CHOOSE(MATCH($CA$2,{"Bull","Base","Bear"},0),$CI$59,$CJ$59,$CK$59) -> 0.055 | BY72: =CHOOSE(MATCH($CA$2,{"Bull","Base","Bear"},0),$CI$60,$CJ$60,$CK$60) -> 0.0575 | BZ72: =CHOOSE(MATCH($CA$2,{"Bull","Base","Bear"},0),$CI$61,$CJ$61,$CK$61) -> 0.06 | CA72: 2027E–2030E segment operating margin: scenario lever (MT_margin). 2026E margin is an output of FY26 guidance. | CC72: =IFERROR(AVERAGE(BV72,BW72,BX72,BY72,BZ72),"n/m") -> 0.055 | CD72: =IFERROR(AVERAGE(AR72,AX72,BD72,BJ72,BP72),"n/m") -> 0.037489693 | CE72: =IFERROR(AVERAGE(N72,T72,Z72,AF72,AL72,AR72,AX72,BD72,BJ72,BP72),"n/m") -> 0.026417645
B73: Segment EBITDA margin % | C73: =IFERROR(C68/C65,"") | D73: =IFERROR(D68/D65,"") | E73: =IFERROR(E68/E65,"") | F73: =IFERROR(F68/F65,"") | G73: =IFERROR(G68/G65,"") | H73: =IFERROR(H68/H65,"") -> -0.16233766 | I73: =IFERROR(I68/I65,"") | J73: =IFERROR(J68/J65,"") | ... BZ73: =IFERROR(BZ68/BZ65,"") -> 0.086 | CC73: =IFERROR(AVERAGE(BV73,BW73,BX73,BY73,BZ73),"n/m") -> 0.081431634 | CD73: =IFERROR(AVERAGE(AR73,AX73,BD73,BJ73,BP73),"n/m") -> 0.081288354 | CE73: =IFERROR(AVERAGE(N73,T73,Z73,AF73,AL73,AR73,AX73,BD73,BJ73,BP73),"n/m") -> 0.06019447
B74: Incremental OI margin (ΔOI / ΔRev) | I74: =IFERROR((I66-C66)/(I65-C65),"") -> 0.077380952 | J74: =IFERROR((J66-D66)/(J65-D65),"") -> 0.57407407 | K74: =IFERROR((K66-E66)/(K65-E65),"") -> 0.27173913 | L74: =IFERROR((L66-F66)/(L65-F65),"") -> 0.088709677 | M74: =IFERROR((M66-G66)/(M65-G65),"") -> 1.625 | N74: =IFERROR((N66-H66)/(N65-H65),"") -> 1.6133333 | O74: =IFERROR((O66-I66)/(O65-I65),"") -> -1.2352941 | P74: =IFERROR((P66-J66)/(P65-J65),"") -> 0.10891089 | ... BV74: =IFERROR((BV66-BP66)/(BV65-BP65),"") -> 0.035714286 | BW74: =IFERROR((BW66-BV66)/(BW65-BV65),"") -> 0.115 | BX74: =IFERROR((BX66-BW66)/(BX65-BW65),"") -> 0.1175 | BY74: =IFERROR((BY66-BX66)/(BY65-BX65),"") -> 0.11305556 | BZ74: =IFERROR((BZ66-BY66)/(BZ65-BY65),"") -> 0.11555556
B75: Operating metrics — Mission Technologies
B76: Funded backlog | C76: 59 | D76: 38 | E76: =D76 -> 38 | F76: 105 | G76: 80 | H76: =G76 -> 80 | I76: 103 | J76: 108 | K76: =J76 -> 108 | L76: 98 | M76: 712 | N76: =M76 -> 712 | O76: 671 | P76: 631 | Q76: =P76 -> 631 | R76: 335 | S76: 478 | T76: =S76 -> 478 | U76: 365 | V76: 405 | W76: =V76 -> 405 | X76: 425 | Y76: 339 | Z76: =Y76 -> 339 | AA76: 513 | AB76: 275 | AC76: =AB76 -> 275 | AD76: 520 | AE76: 435 | AF76: =AE76 -> 435 | AG76: 763 | AH76: 655 | AI76: =AH76 -> 655 | AJ76: 562 | AK76: 502 | AL76: =AK76 -> 502 | AM76: 754 | AN76: 592 | AO76: =AN76 -> 592 | AP76: 1499 | AQ76: 1334 | AR76: =AQ76 -> 1334 | AS76: 1369 | AT76: 1361 | AU76: =AT76 -> 1361 | AV76: 1600 | AW76: 1317 | AX76: =AW76 -> 1317 | AY76: 1332 | AZ76: 1466 | BA76: =AZ76 -> 1466 | BB76: 1905 | BC76: 1545 | BD76: =BC76 -> 1545 | BE76: 1692 | BF76: 1521 | BG76: =BF76 -> 1521 | BH76: 1887 | BI76: 1824 | BJ76: =BI76 -> 1824 | BK76: 1866 | BL76: 1838 | BM76: =BL76 -> 1838 | BN76: 1970 | BO76: 1723 | BP76: =BO76 -> 1723 | BQ76: 1672 | BR76: 1862 | BS76: =BR76 -> 1862
B77: Unfunded backlog | C77: 0 | D77: 0 | E77: =D77 -> 0 | F77: 0 | G77: 0 | H77: =G77 -> 0 | I77: 0 | J77: 0 | K77: =J77 -> 0 | L77: 0 | M77: 661 | N77: =M77 -> 661 | O77: 633 | P77: 315 | Q77: =P77 -> 315 | R77: 518 | S77: 314 | T77: =S77 -> 314 | U77: 394 | V77: 327 | W77: =V77 -> 327 | X77: 321 | Y77: 380 | Z77: =Y77 -> 380 | AA77: 500 | AB77: 855 | AC77: =AB77 -> 855 | AD77: 570 | AE77: 538 | AF77: =AE77 -> 538 | AG77: 483 | AH77: 554 | AI77: =AH77 -> 554 | AJ77: 556 | AK77: 646 | AL77: =AK77 -> 646 | AM77: 304 | AN77: 432 | AO77: =AN77 -> 432 | AP77: 3967 | AQ77: 3789 | AR77: =AQ77 -> 3789 | AS77: 3415 | AT77: 3289 | AU77: =AT77 -> 3289 | AV77: 3746 | AW77: 3622 | AX77: =AW77 -> 3622 | AY77: 3390 | AZ77: 3004 | BA77: =AZ77 -> 3004 | BB77: 3499 | BC77: 3590 | BD77: =BC77 -> 3590 | BE77: 3328 | BF77: 3392 | BG77: =BF77 -> 3392 | BH77: 3882 | BI77: 4292 | BJ77: =BI77 -> 4292 | BK77: 4075 | BL77: 4093 | BM77: =BL77 -> 4093 | BN77: 4157 | BO77: 3710 | BP77: =BO77 -> 3710 | BQ77: 3637 | BR77: 3619 | BS77: =BR77 -> 3619
B78: Total backlog | C78: =C76+C77 -> 59 | D78: =D76+D77 -> 38 | E78: =E76+E77 -> 38 | F78: =F76+F77 -> 105 | G78: =G76+G77 -> 80 | H78: =H76+H77 -> 80 | I78: =I76+I77 -> 103 | J78: =J76+J77 -> 108 | ... BS78: =BS76+BS77 -> 5481 | BT78: =BR78+BT79-BT65 -> 5481 | BU78: =BT78+BU79-BU65 -> 5481 | BV78: =BU78 -> 5481 | BW78: =BV78+BW79-BW65 -> 5481 | BX78: =BW78+BX79-BX65 -> 5481 | BY78: =BX78+BY79-BY65 -> 5481 | BZ78: =BY78+BZ79-BZ65 -> 5481 | CA78: Forecast backlog = prior backlog + new awards − segment revenue; awards = revenue × book-to-bill assumption. | CC78: =IFERROR((BZ78/BP78)^(1/5)-1,"n/m") -> 0.001760768 | CD78: =IFERROR((BP78/AL78)^(1/5)-1,"n/m") -> 0.36464461 | CE78: =IFERROR((BP78/H78)^(1/10)-1,"n/m") -> 0.52473711
B79: Implied new awards (ΔBacklog + Revenue) | D79: =IF(AND(ISNUMBER(D78),ISNUMBER(C78)),D78-C78+D65,"") -> 14 | E79: =IF(AND(ISNUMBER(C79),ISNUMBER(D79)),C79+D79,"") | F79: =IF(AND(ISNUMBER(F78),ISNUMBER(D78)),F78-D78+F65,"") -> 97 | G79: =IF(AND(ISNUMBER(G78),ISNUMBER(F78)),G78-F78+G65,"") -> 129 | I79: =IF(AND(ISNUMBER(I78),ISNUMBER(G78)),I78-G78+I65,"") -> 231 | J79: =IF(AND(ISNUMBER(J78),ISNUMBER(I78)),J78-I78+J65,"") -> 148 | K79: =IF(AND(ISNUMBER(I79),ISNUMBER(J79)),I79+J79,"") -> 379 | L79: =IF(AND(ISNUMBER(L78),ISNUMBER(J78)),L78-J78+L65,"") -> 144 | M79: =IF(AND(ISNUMBER(M78),ISNUMBER(L78)),M78-L78+M65,"") -> 1461 | N79: =IF(AND(ISNUMBER(N78),ISNUMBER(H78)),N78-H78+N65,"") -> 1984 | O79: =IF(AND(ISNUMBER(O78),ISNUMBER(M78)),O78-M78+O65,"") -> 156 | P79: =IF(AND(ISNUMBER(P78),ISNUMBER(O78)),P78-O78+P65,"") -> -114 | Q79: =IF(AND(ISNUMBER(O79),ISNUMBER(P79)),O79+P79,"") -> 42 | R79: =IF(AND(ISNUMBER(R78),ISNUMBER(P78)),R78-P78+R65,"") -> 148 | S79: =IF(AND(ISNUMBER(S78),ISNUMBER(R78)),S78-R78+S65,"") -> 181 | T79: =IF(AND(ISNUMBER(T78),ISNUMBER(N78)),T78-N78+T65,"") -> 371 | U79: =IF(AND(ISNUMBER(U78),ISNUMBER(S78)),U78-S78+U65,"") -> 200 | V79: =IF(AND(ISNUMBER(V78),ISNUMBER(U78)),V78-U78+V65,"") -> 216 | W79: =IF(AND(ISNUMBER(U79),ISNUMBER(V79)),U79+V79,"") -> 416 | X79: =IF(AND(ISNUMBER(X78),ISNUMBER(V78)),X78-V78+X65,"") -> 259 | Y79: =IF(AND(ISNUMBER(Y78),ISNUMBER(X78)),Y78-X78+Y65,"") -> 158 | Z79: =IF(AND(ISNUMBER(Z78),ISNUMBER(T78)),Z78-T78+Z65,"") -> 833 | AA79: =IF(AND(ISNUMBER(AA78),ISNUMBER(Y78)),AA78-Y78+AA65,"") -> 534 | AB79: =IF(AND(ISNUMBER(AB78),ISNUMBER(AA78)),AB78-AA78+AB65,"") -> 438 | AC79: =IF(AND(ISNUMBER(AA79),ISNUMBER(AB79)),AA79+AB79,"") -> 972 | AD79: =IF(AND(ISNUMBER(AD78),ISNUMBER(AB78)),AD78-AB78+AD65,"") -> 286 | AE79: =IF(AND(ISNUMBER(AE78),ISNUMBER(AD78)),AE78-AD78+AE65,"") -> 233 | AF79: =IF(AND(ISNUMBER(AF78),ISNUMBER(Z78)),AF78-Z78+AF65,"") -> 1491 | AG79: =IF(AND(ISNUMBER(AG78),ISNUMBER(AE78)),AG78-AE78+AG65,"") -> 590 | AH79: =IF(AND(ISNUMBER(AH78),ISNUMBER(AG78)),AH78-AG78+AH65,"") -> 283 | AI79: =IF(AND(ISNUMBER(AG79),ISNUMBER(AH79)),AG79+AH79,"") -> 873 | AJ79: =IF(AND(ISNUMBER(AJ78),ISNUMBER(AH78)),AJ78-AH78+AJ65,"") -> 229 | AK79: =IF(AND(ISNUMBER(AK78),ISNUMBER(AJ78)),AK78-AJ78+AK65,"") -> 341 | AL79: =IF(AND(ISNUMBER(AL78),ISNUMBER(AF78)),AL78-AF78+AL65,"") -> 1443 | AM79: =IF(AND(ISNUMBER(AM78),ISNUMBER(AK78)),AM78-AK78+AM65,"") -> 169 | AN79: =IF(AND(ISNUMBER(AN78),ISNUMBER(AM78)),AN78-AM78+AN65,"") -> 203 | AO79: =IF(AND(ISNUMBER(AM79),ISNUMBER(AN79)),AM79+AN79,"") -> 372 | AP79: =IF(AND(ISNUMBER(AP78),ISNUMBER(AN78)),AP78-AN78+AP65,"") -> 4836 | AQ79: =IF(AND(ISNUMBER(AQ78),ISNUMBER(AP78)),AQ78-AP78+AQ65,"") -> 243 | AR79: =IF(AND(ISNUMBER(AR78),ISNUMBER(AL78)),AR78-AL78+AR65,"") -> 5451 | AS79: =IF(AND(ISNUMBER(AS78),ISNUMBER(AQ78)),AS78-AQ78+AS65,"") -> 251 | AT79: =IF(AND(ISNUMBER(AT78),ISNUMBER(AS78)),AT78-AS78+AT65,"") -> 466 | AU79: =IF(AND(ISNUMBER(AS79),ISNUMBER(AT79)),AS79+AT79,"") -> 717 | AV79: =IF(AND(ISNUMBER(AV78),ISNUMBER(AT78)),AV78-AT78+AV65,"") -> 1291 | AW79: =IF(AND(ISNUMBER(AW78),ISNUMBER(AV78)),AW78-AV78+AW65,"") -> 195 | AX79: =IF(AND(ISNUMBER(AX78),ISNUMBER(AR78)),AX78-AR78+AX65,"") -> 2203 | AY79: =IF(AND(ISNUMBER(AY78),ISNUMBER(AW78)),AY78-AW78+AY65,"") -> 407 | AZ79: =IF(AND(ISNUMBER(AZ78),ISNUMBER(AY78)),AZ78-AY78+AZ65,"") -> 393 | BA79: =IF(AND(ISNUMBER(AY79),ISNUMBER(AZ79)),AY79+AZ79,"") -> 800 | BB79: =IF(AND(ISNUMBER(BB78),ISNUMBER(AZ78)),BB78-AZ78+BB65,"") -> 1619 | BC79: =IF(AND(ISNUMBER(BC78),ISNUMBER(BB78)),BC78-BB78+BC65,"") -> 476 | BD79: =IF(AND(ISNUMBER(BD78),ISNUMBER(AX78)),BD78-AX78+BD65,"") -> 2895 | BE79: =IF(AND(ISNUMBER(BE78),ISNUMBER(BC78)),BE78-BC78+BE65,"") -> 635 | BF79: =IF(AND(ISNUMBER(BF78),ISNUMBER(BE78)),BF78-BE78+BF65,"") -> 658 | BG79: =IF(AND(ISNUMBER(BE79),ISNUMBER(BF79)),BE79+BF79,"") -> 1293 | BH79: =IF(AND(ISNUMBER(BH78),ISNUMBER(BF78)),BH78-BF78+BH65,"") -> 1565 | BI79: =IF(AND(ISNUMBER(BI78),ISNUMBER(BH78)),BI78-BH78+BI65,"") -> 1060 | BJ79: =IF(AND(ISNUMBER(BJ78),ISNUMBER(BD78)),BJ78-BD78+BJ65,"") -> 3918 | BK79: =IF(AND(ISNUMBER(BK78),ISNUMBER(BI78)),BK78-BI78+BK65,"") -> 560 | BL79: =IF(AND(ISNUMBER(BL78),ISNUMBER(BK78)),BL78-BK78+BL65,"") -> 781 | BM79: =IF(AND(ISNUMBER(BK79),ISNUMBER(BL79)),BK79+BL79,"") -> 1341 | BN79: =IF(AND(ISNUMBER(BN78),ISNUMBER(BL78)),BN78-BL78+BN65,"") -> 983 | BO79: =IF(AND(ISNUMBER(BO78),ISNUMBER(BN78)),BO78-BN78+BO65,"") -> 37 | BP79: =IF(AND(ISNUMBER(BP78),ISNUMBER(BJ78)),BP78-BJ78+BP65,"") -> 2361 | BQ79: =IF(AND(ISNUMBER(BQ78),ISNUMBER(BO78)),BQ78-BO78+BQ65,"") -> 624 | BR79: =IF(AND(ISNUMBER(BR78),ISNUMBER(BQ78)),BR78-BQ78+BR65,"") -> 932 | BS79: =IF(AND(ISNUMBER(BQ79),ISNUMBER(BR79)),BQ79+BR79,"") -> 1556 | BT79: =BT65*BT80 -> 796 | BU79: =BU65*BU80 -> 796 | BV79: =SUM(BQ79,BR79,BT79,BU79) -> 3148 | BW79: =BW65*BW80 -> 3224 | BX79: =BX65*BX80 -> 3352.96 | BY79: =BY65*BY80 -> 3503.8432 | BZ79: =BZ65*BZ80 -> 3661.5161 | CA79: Implied awards = change in total backlog + segment revenue (backlog also moves for de-obligations/adjustments; not separately disclosed).
B80: Book-to-bill (x) | C80: =IF(ISNUMBER(C79),IFERROR(C79/C65,""),"") | D80: =IF(ISNUMBER(D79),IFERROR(D79/D65,""),"") -> 0.4 | E80: =IF(ISNUMBER(E79),IFERROR(E79/E65,""),"") | F80: =IF(ISNUMBER(F79),IFERROR(F79/F65,""),"") -> 3.2333333 | G80: =IF(ISNUMBER(G79),IFERROR(G79/G65,""),"") -> 0.83766234 | H80: =IF(ISNUMBER(H79),IFERROR(H79/H65,""),"") | I80: =IF(ISNUMBER(I79),IFERROR(I79/I65,""),"") -> 1.1105769 | J80: =IF(ISNUMBER(J79),IFERROR(J79/J65,""),"") -> 1.034965 | ... BS80: =IF(ISNUMBER(BS79),IFERROR(BS79/BS65,""),"") -> 1.0318302 | BT80: =$BV$80 -> 1 | BU80: =$BV$80 -> 1 | BV80: 1 | BW80: 1 | BX80: 1 | BY80: 1 | BZ80: 1 | CA80: Book-to-bill input (blue): 2026E cell = 2H/26 assumption applied to Q3/Q4-26E; 2027E+ held at 1.0x (backlog stable in $). Shipbuilding awards are lumpy (multi-ship / multi-year contracts) — adjust for known awards.
B81: Backlog / revenue (years) | H81: =IFERROR(H78/H65,"") -> 0.12987013 | N81: =IFERROR(N78/N65,"") -> 1.9869754 | T81: =IFERROR(T78/T65,"") -> 0.83193277 | Z81: =IFERROR(Z78/Z65,"") -> 0.79359823 | AF81: =IFERROR(AF78/AF65,"") -> 0.78658044 | AL81: =IFERROR(AL78/AL65,"") -> 0.90536278 | AR81: =IFERROR(AR78/AR65,"") -> 3.4708672 | AX81: =IFERROR(AX78/AX65,"") -> 2.0691244 | BD81: =IFERROR(BD78/BD65,"") -> 1.9025565 | BJ81: =IFERROR(BJ78/BJ65,"") -> 2.082397 | BP81: =IFERROR(BP78/BP65,"") -> 1.7848226 | BV81: =IFERROR(BV78/BV65,"") -> 1.7680645 | BW81: =IFERROR(BW78/BW65,"") -> 1.700062 | BX81: =IFERROR(BX78/BX65,"") -> 1.634675 | BY81: =IFERROR(BY78/BY65,"") -> 1.5642823 | BZ81: =IFERROR(BZ78/BZ65,"") -> 1.4969209
B82: % of Revenue — Mission Technologies | CA82: % OF REVENUE drivers — hardcoded inputs that drive forecast segment cost / capital intensity
B83: Intersegment revenue % of segment revenue | C83: =IFERROR(C64/C65,"n/d") -> 0 | D83: =IFERROR(D64/D65,"n/d") -> 0 | E83: =IFERROR(E64/E65,"n/d") -> 0 | F83: =IFERROR(F64/F65,"n/d") -> 0 | G83: =IFERROR(G64/G65,"n/d") -> 0 | H83: =IFERROR(H64/H65,"n/d") -> 0 | I83: =IFERROR(I64/I65,"n/d") -> 0 | J83: =IFERROR(J64/J65,"n/d") -> 0 | ... BS83: =IFERROR(BS64/BS65,"n/d") -> 0.046419098 | BT83: =IFERROR(BT64/BT65,"") -> 0.043969849 | BU83: =IFERROR(BU64/BU65,"") -> 0.043969849 | BV83: =IFERROR(BV64/BV65,"") -> 0.04516129 | BW83: =$BP$83 -> 0.043363995 | BX83: =$BP$83 -> 0.043363995 | BY83: =$BP$83 -> 0.043363995 | BZ83: =$BP$83 -> 0.043363995 | CA83: Held at FY2025 actual level (linked).
B84: D&A % of revenue | C84: =IFERROR(C67/C65,"") -> 0 | D84: =IFERROR(D67/D65,"") -> 0 | E84: =IFERROR(E67/E65,"") -> 0 | F84: =IFERROR(F67/F65,"") -> 0 | G84: =IFERROR(G67/G65,"") -> 0 | H84: =IFERROR(H67/H65,"") -> 0.021103896 | I84: =IFERROR(I67/I65,"") -> 0 | J84: =IFERROR(J67/J65,"") -> 0 | ... BV84: =IFERROR(BV67/BV65,"") -> 0.028158169 | BW84: 0.026 | BX84: 0.026 | BY84: 0.026 | BZ84: 0.026 | CA84: MT D&A 2.6% of revenue (FY25 3.4%, 1H26 2.7%) — purchased-intangible amortization (Alion) rolling off per 10-K amortization schedule.
B85: Capital expenditures (segment) | H85: 5 | N85: 8 | T85: 6 | Z85: 6 | AF85: 9 | AL85: 20 | AR85: 38 | AX85: 20 | BD85: 11 | BE85: 2 | BF85: 3 | BG85: =BE85+BF85 -> 5 | BH85: 6 | BI85: 7 | BJ85: 18 | BK85: 1 | BL85: 1 | BM85: =BK85+BL85 -> 2 | BN85: 2 | BO85: 9 | BP85: 13 | BQ85: 3 | BV85: =BV65*BV86 -> 18.501231 | BW85: =BW65*BW86 -> 18.17232 | BX85: =BX65*BX86 -> 17.787494 | BY85: =BY65*BY86 -> 17.426186 | BZ85: =BZ65*BZ86 -> 16.99634 | CA85: Segment capex = revenue × segment capex %. Illustrative allocation of group capex (group capex in the CF statement is driven by the group capex % of revenue line).
B86: Capex % of revenue | H86: =IFERROR(H85/H65,"") -> 0.0081168831 | N86: =IFERROR(N85/N65,"") -> 0.011577424 | T86: =IFERROR(T85/T65,"") -> 0.006302521 | Z86: =IFERROR(Z85/Z65,"") -> 0.0066225166 | AF86: =IFERROR(AF85/AF65,"") -> 0.0072756669 | AL86: =IFERROR(AL85/AL65,"") -> 0.015772871 | AR86: =IFERROR(AR85/AR65,"") -> 0.025745257 | AX86: =IFERROR(AX85/AX65,"") -> 0.0083787181 | BD86: =IFERROR(BD85/BD65,"") -> 0.0040755835 | BJ86: =IFERROR(BJ85/BJ65,"") -> 0.0061287028 | BP86: =IFERROR(BP85/BP65,"") -> 0.0042706965 | BV86: =IFERROR($BP$86/$BP$227*BV227,0) -> 0.0059681389 | BW86: =IFERROR($BP$86/$BP$227*BW227,0) -> 0.0056365757 | BX86: =IFERROR($BP$86/$BP$227*BX227,0) -> 0.0053050124 | BY86: =IFERROR($BP$86/$BP$227*BY227,0) -> 0.0049734491 | BZ86: =IFERROR($BP$86/$BP$227*BZ227,0) -> 0.0046418858 | CA86: Segment capex % = group capex % (CF memo) × FY2025 segment capex intensity relative to group.
B88: Corporate, eliminations & non-segment items | CA88: NON-SEGMENT ITEMS — modelling logic
B89: Intersegment eliminations | D89: -2 | E89: =C89+D89 -> -2 | F89: 0 | G89: -23 | H89: -82 | I89: -24 | J89: -27 | K89: =I89+J89 -> -51 | L89: -26 | M89: -24 | N89: -101 | O89: -22 | P89: -26 | Q89: =O89+P89 -> -48 | R89: -24 | S89: -23 | T89: -95 | U89: -26 | V89: -35 | W89: =U89+V89 -> -61 | X89: -35 | Y89: -37 | Z89: -133 | AA89: -23 | AB89: -34 | AC89: =AA89+AB89 -> -57 | AD89: -28 | AE89: -39 | AF89: -124 | AG89: -24 | AH89: -37 | AI89: =AG89+AH89 -> -61 | AJ89: -39 | AK89: -56 | AL89: -156 | AM89: -37 | AN89: -39 | AO89: =AM89+AN89 -> -76 | AP89: -38 | AQ89: -29 | AR89: -143 | AS89: -35 | AT89: -29 | AU89: =AS89+AT89 -> -64 | AV89: -37 | AW89: -32 | AX89: -133 | AY89: -33 | AZ89: -31 | BA89: =AY89+AZ89 -> -64 | BB89: -33 | BC89: -33 | BD89: -130 | BE89: -34 | BF89: -35 | BG89: =BE89+BF89 -> -69 | BH89: -36 | BI89: -33 | BJ89: -138 | BK89: -34 | BL89: -36 | BM89: =BK89+BL89 -> -70 | BN89: -40 | BO89: -35 | BP89: -145 | BQ89: -39 | BR89: -36 | BS89: =BQ89+BR89 -> -75 | BT89: =-(BT12+BT38+BT64) -> -37.5 | BU89: =-(BU12+BU38+BU64) -> -37.5 | BV89: =SUM(BQ89,BR89,BT89,BU89) -> -150 | BW89: =-(BW12+BW38+BW64) -> -154.12087 | BX89: =-(BX12+BX38+BX64) -> -160.50629 | BY89: =-(BY12+BY38+BY64) -> -167.81082 | BZ89: =-(BZ12+BZ38+BZ64) -> -175.36885 | CA89: Forecast = −(sum of segment intersegment revenue).
B90: Operating FAS/CAS adjustment (charge / (credit) to operating income) | C90: -27 | D90: -28 | E90: =C90+D90 -> -55 | F90: -27 | G90: -22 | H90: -104 | I90: -35 | J90: -35 | K90: =I90+J90 -> -70 | L90: -37 | M90: -38 | N90: -145 | O90: -53 | P90: -53 | Q90: =O90+P90 -> -106 | R90: -50 | S90: -49 | T90: -205 | U90: -72 | V90: -73 | W90: =U90+V90 -> -145 | X90: -73 | Y90: -72 | Z90: -290 | AA90: -34 | AB90: -37 | AC90: =AA90+AB90 -> -71 | AD90: -23 | AE90: -30 | AF90: -124 | AG90: -63 | AH90: -63 | AI90: =AG90+AH90 -> -126 | AJ90: -60 | AK90: -62 | AL90: -248 | AM90: 40 | AN90: 37 | AO90: =AM90+AN90 -> 77 | AP90: 41 | AQ90: 39 | AR90: 157 | AS90: 37 | AT90: 35 | AU90: =AS90+AT90 -> 72 | AV90: 36 | AW90: 37 | AX90: 145 | AY90: 19 | AZ90: 17 | BA90: =AY90+AZ90 -> 36 | BB90: 19 | BC90: 17 | BD90: 72 | BE90: 17 | BF90: 15 | BG90: =BE90+BF90 -> 32 | BH90: 16 | BI90: 14 | BJ90: 62 | BK90: 10 | BL90: 6 | BM90: =BK90+BL90 -> 16 | BN90: 9 | BO90: 10 | BP90: 35 | BQ90: 9 | BR90: 8 | BS90: =BQ90+BR90 -> 17 | BT90: =($CJ$19-BS90)/2 -> 13.5 | BU90: =($CJ$19-BS90)/2 -> 13.5 | BV90: =SUM(BQ90,BR90,BT90,BU90) -> 44 | BW90: =BV90 -> 44 | BX90: =BW90 -> 44 | BY90: =BX90 -> 44 | BZ90: =BY90 -> 44 | CA90: Operating FAS/CAS adjustment = GAAP pension service cost less CAS pension cost recovered in segment OI. FY26 guidance: ($44m) to operating income → Q3/Q4-26E = (44 − 1H)/2. 2027E+ held at FY26 level (HII has not guided beyond 2026).
B91: Non-current state income taxes (charge / (credit) to operating income) | C91: -1 | D91: 2 | E91: =C91+D91 -> 1 | F91: -1 | G91: 2 | H91: 2 | I91: 3 | J91: 2 | K91: =I91+J91 -> 5 | L91: 2 | M91: -5 | N91: 2 | O91: 5 | P91: -1 | Q91: =O91+P91 -> 4 | R91: 1 | S91: 7 | T91: 12 | U91: -2 | V91: -3 | W91: =U91+V91 -> -5 | X91: 0 | Y91: 7 | Z91: 2 | AA91: 2 | AB91: 0 | AC91: =AA91+AB91 -> 2 | AD91: 0 | AE91: 17 | AF91: 19 | AG91: 4 | AH91: 1 | AI91: =AG91+AH91 -> 5 | AJ91: 0 | AK91: -1 | AL91: 4 | AM91: 4 | AN91: 4 | AO91: =AM91+AN91 -> 8 | AP91: 4 | AQ91: 1 | AR91: 13 | AS91: 1 | AT91: -1 | AU91: =AS91+AT91 -> 0 | AV91: -1 | AW91: 3 | AX91: 2 | AY91: -4 | AZ91: -4 | BA91: =AY91+AZ91 -> -8 | BB91: -4 | BC91: 1 | BD91: -11 | BE91: -1 | BF91: -1 | BG91: =BE91+BF91 -> -2 | BH91: -1 | BI91: -21 | BJ91: -24 | BK91: 0 | BL91: 3 | BM91: =BK91+BL91 -> 3 | BN91: 9 | BO91: 13 | BP91: 25 | BQ91: 8 | BR91: 6 | BS91: =BQ91+BR91 -> 14 | BT91: =($CJ$20-BS91)/2 -> 3 | BU91: =($CJ$20-BS91)/2 -> 3 | BV91: =SUM(BQ91,BR91,BT91,BU91) -> 20 | BW91: =BV91 -> 20 | BX91: =BW91 -> 20 | BY91: =BX91 -> 20 | BZ91: =BY91 -> 20 | CA91: Deferred state income tax expense recorded in operating income. FY26 guidance ~($20m) → Q3/Q4-26E = (20 − 1H)/2; held flat thereafter.
B92: Corporate D&A (total D&A less segment D&A) | C92: =IF(COUNT(C15,C41,C67)=3,C102-C15-C41-C67,"") | D92: =IF(COUNT(D15,D41,D67)=3,D102-D15-D41-D67,"") | E92: =IF(COUNT(E15,E41,E67)=3,E102-E15-E41-E67,"") | F92: =IF(COUNT(F15,F41,F67)=3,F102-F15-F41-F67,"") | G92: =IF(COUNT(G15,G41,G67)=3,G102-G15-G41-G67,"") | H92: =IF(COUNT(H15,H41,H67)=3,H102-H15-H41-H67,"") -> 0 | I92: =IF(COUNT(I15,I41,I67)=3,I102-I15-I41-I67,"") | J92: =IF(COUNT(J15,J41,J67)=3,J102-J15-J41-J67,"") | ... BS92: =IF(COUNT(BS15,BS41,BS67)=3,BS102-BS15-BS41-BS67,"") -> 3 | BT92: =BS92/2*($CJ$24-BS102)/BS102 -> 1.6935484 | BU92: =BS92/2*($CJ$24-BS102)/BS102 -> 1.6935484 | BV92: =SUM(BQ92,BR92,BT92,BU92) -> 6.3870968 | BW92: 4 | BX92: 4 | BY92: 4 | BZ92: 4 | CA92: Corporate D&A ~$4m p.a. (FY25 actual).
B94: Group Total (consolidated) | CA94: GROUP TOTAL (CONSOLIDATED) — modelling logic
B95: Sales and service revenues | C95: =C13+C39+C65+C89 -> 1570 | D95: =D13+D39+D65+D89 -> 1745 | E95: =E13+E39+E65+E89 -> 3315 | F95: =F13+F39+F65+F89 -> 1800 | G95: =G13+G39+G65+G89 -> 1905 | H95: =H13+H39+H65+H89 -> 7020 | I95: =I13+I39+I65+I89 -> 1763 | J95: =J13+J39+J65+J89 -> 1700 | ... BZ95: =BZ13+BZ39+BZ65+BZ89 -> 16333.798 | CA95: Group revenue = sum of segment revenue + intersegment eliminations (ties to the consolidated income statement; see check row). | CC95: =IFERROR((BZ95/BP95)^(1/5)-1,"n/m") -> 0.055228921 | CD95: =IFERROR((BP95/AL95)^(1/5)-1,"n/m") -> 0.059269098 | CE95: =IFERROR((BP95/H95)^(1/10)-1,"n/m") -> 0.059257786
B96: Shipbuilding revenue (Ingalls + Newport News) | C96: =C13+C39 -> 1530 | D96: =D13+D39 -> 1712 | E96: =E13+E39 -> 3242 | F96: =F13+F39 -> 1770 | G96: =G13+G39 -> 1774 | H96: =H13+H39 -> 6486 | I96: =I13+I39 -> 1579 | J96: =J13+J39 -> 1584 | ... BZ96: =BZ13+BZ39 -> 12847.651 | CA96: HII non-GAAP "shipbuilding revenue". FY26 guidance $10.2–10.4bn (raised with Q2-26 results). | CC96: =IFERROR((BZ96/BP96)^(1/5)-1,"n/m") -> 0.060342876 | CD96: =IFERROR((BP96/AL96)^(1/5)-1,"n/m") -> 0.030476667 | CE96: =IFERROR((BP96/H96)^(1/10)-1,"n/m") -> 0.039828023
B97: Segment operating income (HII non-GAAP) | C97: =C14+C40+C66 -> 128 | D97: =D14+D40+D66 -> 243 | E97: =E14+E40+E66 -> 371 | F97: =F14+F40+F66 -> 172 | G97: =G14+G40+G66 -> 124 | H97: =H14+H40+H66 -> 667 | I97: =I14+I40+I66 -> 166 | J97: =J14+J40+J66 -> 184 | ... BZ97: =BZ14+BZ40+BZ66 -> 1202.7796 | CC97: =IFERROR((BZ97/BP97)^(1/5)-1,"n/m") -> 0.10900469 | CD97: =IFERROR((BP97/AL97)^(1/5)-1,"n/m") -> 0.052556056 | CE97: =IFERROR((BP97/H97)^(1/10)-1,"n/m") -> 0.0072547687
B98: Shipbuilding segment operating income | C98: =C14+C40 -> 138 | D98: =D14+D40 -> 307 | E98: =E14+E40 -> 445 | F98: =F14+F40 -> 177 | G98: =G14+G40 -> 175 | H98: =H14+H40 -> 780 | I98: =I14+I40 -> 163 | J98: =J14+J40 -> 186 | ... BZ98: =BZ14+BZ40 -> 983.08868 | CC98: =IFERROR((BZ98/BP98)^(1/5)-1,"n/m") -> 0.11753908 | CD98: =IFERROR((BP98/AL98)^(1/5)-1,"n/m") -> 0.018739621 | CE98: =IFERROR((BP98/H98)^(1/10)-1,"n/m") -> -0.031903946
B99: (−) Operating FAS/CAS adjustment | C99: =-C90 -> 27 | D99: =-D90 -> 28 | E99: =-E90 -> 55 | F99: =-F90 -> 27 | G99: =-G90 -> 22 | H99: =-H90 -> 104 | I99: =-I90 -> 35 | J99: =-J90 -> 35 | ... BZ99: =-BZ90 -> -44
B100: (−) Non-current state income taxes | C100: =-C91 -> 1 | D100: =-D91 -> -2 | E100: =-E91 -> -1 | F100: =-F91 -> 1 | G100: =-G91 -> -2 | H100: =-H91 -> -2 | I100: =-I91 -> -3 | J100: =-J91 -> -2 | ... BZ100: =-BZ91 -> -20
B101: Operating income (GAAP) | C101: =C97+C99+C100 -> 156 | D101: =D97+D99+D100 -> 269 | E101: =E97+E99+E100 -> 425 | F101: =F97+F99+F100 -> 200 | G101: =G97+G99+G100 -> 144 | H101: =H97+H99+H100 -> 769 | I101: =I97+I99+I100 -> 198 | J101: =J97+J99+J100 -> 217 | ... BZ101: =BZ97+BZ99+BZ100 -> 1138.7796 | CC101: =IFERROR((BZ101/BP101)^(1/5)-1,"n/m") -> 0.11628443 | CD101: =IFERROR((BP101/AL101)^(1/5)-1,"n/m") -> -0.038379489 | CE101: =IFERROR((BP101/H101)^(1/10)-1,"n/m") -> -0.015617458
B102: Depreciation & amortization (total) | H102: 180 | N102: 186 | T102: 205 | Z102: 203 | AF102: 227 | AL102: 247 | AR102: 293 | AX102: 358 | BD102: 347 | BE102: 80 | BF102: 80 | BG102: =BE102+BF102 -> 160 | BH102: 82 | BI102: 84 | BJ102: 326 | BK102: 79 | BL102: 83 | BM102: =BK102+BL102 -> 162 | BN102: 80 | BO102: 87 | BP102: 329 | BQ102: 76 | BR102: 79 | BS102: =BQ102+BR102 -> 155 | BT102: =($CJ$24-BS102)/2 -> 87.5 | BU102: =($CJ$24-BS102)/2 -> 87.5 | BV102: =SUM(BQ102,BR102,BT102,BU102) -> 330 | BW102: =BW15+BW41+BW67+BW92 -> 339.26388 | BX102: =BX15+BX41+BX67+BX92 -> 357.26492 | BY102: =BY15+BY41+BY67+BY92 -> 375.3603 | BZ102: =BZ15+BZ41+BZ67+BZ92 -> 392.98728 | CA102: FY26 guidance D&A ~$330m → Q3/Q4-26E = (330 − 1H)/2. 2027E+ = sum of segment D&A + corporate.
...

Sheet Bull-Base-Bear
B2: Huntington Ingalls Industries (HII) — Bull / Base / Bear Case P&L Summary | J2: Share price ($): | K2: =Model!$BV$350 -> 275
B3: Adjusted figures · USD millions · Live panel linked to Model — toggle scenario via Model!CA2. Bull and Bear panels are value snapshots generated from the Model with the switch set to each case. | J3: As of: | K3: =TODAY() -> 46297
B5: Scenario: | C5: =Model!CA2 -> Base | N5: Scenario: | O5: Bull | P5: Snapshot (values) — Model run with switch = Bull | Z5: Scenario: | AA5: Bear | AB5: Snapshot (values) — Model run with switch = Bear
B7: (USDm, except EPS and shares) | C7: 2025A | D7: 2026E | E7: 2027E | F7: 2028E | G7: 2029E | H7: 2030E | I7: 25-'30 CAGR | J7: LT Hist Avg | K7: LT Hist Min | L7: LT Hist Max | N7: (USDm, except EPS and shares) | O7: 2025A | P7: 2026E | Q7: 2027E | R7: 2028E | S7: 2029E | T7: 2030E | U7: 25-'30 CAGR | V7: LT Hist Avg | W7: LT Hist Min | X7: LT Hist Max | Z7: (USDm, except EPS and shares) | AA7: 2025A | AB7: 2026E | AC7: 2027E | AD7: 2028E | AE7: 2029E | AF7: 2030E | AG7: 25-'30 CAGR | AH7: LT Hist Avg | AI7: LT Hist Min | AJ7: LT Hist Max
B9: Revenue | C9: =Model!BP119 -> 12484 | D9: =Model!BV119 -> 13250 | E9: =Model!BW119 -> 14059.071 | F9: =Model!BX119 -> 14824.14 | G9: =Model!BY119 -> 15589.676 | H9: =Model!BZ119 -> 16333.798 | I9: =IFERROR((H9/C9)^(1/5)-1,"n/m") -> 0.055228921 | N9: Revenue | O9: 12484 | P9: 13450 | Q9: 14534.066 | R9: 15614.618 | S9: 16732.747 | T9: 17865.853 | U9: 0.074320835 | Z9: Revenue | AA9: 12484 | AB9: 13050 | AC9: 13461.333 | AD9: 13791.042 | AE9: 14089.98 | AF9: 14340.028 | AG9: 0.028109202
B10: Revenue y/y % | D10: =IFERROR(D9/C9-1,"") -> 0.061358539 | E10: =IFERROR(E9/D9-1,"") -> 0.061062 | F10: =IFERROR(F9/E9-1,"") -> 0.054418109 | G10: =IFERROR(G9/F9-1,"") -> 0.051641186 | H10: =IFERROR(H9/G9-1,"") -> 0.047731755 | N10: Revenue y/y % | P10: 0.077379045 | Q10: 0.080599705 | R10: 0.074346148 | S10: 0.071607861 | T10: 0.067717842 | Z10: Revenue y/y % | AB10: 0.045338033 | AC10: 0.031519756 | AD10: 0.024493057 | AE10: 0.021676209 | AF10: 0.017746526
B12: Segment Operating Income (Adj. EBIT) | C12: =Model!BP97 -> 717 | D12: =Model!BV97 -> 798.75 | E12: =Model!BW97 -> 927.88853 | F12: =Model!BX97 -> 1016.416 | G12: =Model!BY97 -> 1108.5346 | H12: =Model!BZ97 -> 1202.7796 | I12: =IFERROR((H12/C12)^(1/5)-1,"n/m") -> 0.10900469 | N12: Segment Operating Income (Adj. EBIT) | O12: 717 | P12: 844 | Q12: 1031.9144 | R12: 1148.6886 | S12: 1273.4809 | T12: 1404.934 | U12: 0.14400351 | Z12: Segment Operating Income (Adj. EBIT) | AA12: 717 | AB12: 754.5 | AC12: 734.27946 | AD12: 787.45221 | AE12: 840.24339 | AF12: 891.39776 | AG12: 0.044504887
B13: Segment operating margin % | C13: =IFERROR(C12/C9,"") -> 0.057433515 | D13: =IFERROR(D12/D9,"") -> 0.060283019 | E13: =IFERROR(E12/E9,"") -> 0.065999275 | F13: =IFERROR(F12/F9,"") -> 0.068564927 | G13: =IFERROR(G12/G9,"") -> 0.071106971 | H13: =IFERROR(H12/H9,"") -> 0.073637474 | J13: =AVERAGE(Model!H107,Model!N107,Model!T107,Model!Z107,Model!AF107,Model!AL107,Model!AR107,Model!AX107,Model!BD107,Model!BJ107,Model!BP107) -> 0.074449685 | K13: =MIN(Model!H107,Model!N107,Model!T107,Model!Z107,Model!AF107,Model!AL107,Model!AR107,Model!AX107,Model!BD107,Model!BJ107,Model!BP107) -> 0.049674902 | L13: =MAX(Model!H107,Model!N107,Model!T107,Model!Z107,Model!AF107,Model!AL107,Model!AR107,Model!AX107,Model!BD107,Model!BJ107,Model!BP107) -> 0.10116016 | N13: Segment operating margin % | O13: 0.057433515 | P13: 0.062750929 | Q13: 0.070999707 | R13: 0.073564954 | S13: 0.0761071 | T13: 0.07863795 | V13: 0.074449685 | W13: 0.049674902 | X13: 0.10116016 | Z13: Segment operating margin % | AA13: 0.057433515 | AB13: 0.057816092 | AC13: 0.054547307 | AD13: 0.057098819 | AE13: 0.05963411 | AF13: 0.062161509 | AH13: 0.074449685 | AI13: 0.049674902 | AJ13: 0.10116016
B15: Operating Income (GAAP) | C15: =Model!BP126 -> 657 | D15: =Model!BV126 -> 734.75 | E15: =Model!BW126 -> 863.88853 | F15: =Model!BX126 -> 952.41605 | G15: =Model!BY126 -> 1044.5346 | H15: =Model!BZ126 -> 1138.7796 | I15: =IFERROR((H15/C15)^(1/5)-1,"n/m") -> 0.11628443 | N15: Operating Income (GAAP) | O15: 657 | P15: 780 | Q15: 967.91444 | R15: 1084.6886 | S15: 1209.4809 | T15: 1340.934 | U15: 0.15336936 | Z15: Operating Income (GAAP) | AA15: 657 | AB15: 690.5 | AC15: 670.27946 | AD15: 723.45221 | AE15: 776.24339 | AF15: 827.39776 | AG15: 0.047200387
B16: Operating income y/y % | D16: =IFERROR(D15/C15-1,"") -> 0.11834094 | E16: =IFERROR(E15/D15-1,"") -> 0.17575846 | F16: =IFERROR(F15/E15-1,"") -> 0.10247563 | G16: =IFERROR(G15/F15-1,"") -> 0.096720943 | H16: =IFERROR(H15/G15-1,"") -> 0.090226804 | N16: Operating income y/y % | P16: 0.18721461 | Q16: 0.24091595 | R16: 0.12064518 | S16: 0.11504889 | T16: 0.1086856 | Z16: Operating income y/y % | AB16: 0.050989346 | AC16: -0.029283914 | AD16: 0.079329234 | AE16: 0.072971198 | AF16: 0.065899912
B17: Operating margin (GAAP) % | C17: =IFERROR(C15/C9,"") -> 0.052627363 | D17: =IFERROR(D15/D9,"") -> 0.05545283 | E17: =IFERROR(E15/E9,"") -> 0.061447054 | F17: =IFERROR(F15/F9,"") -> 0.064247644 | G17: =IFERROR(G15/G9,"") -> 0.06700169 | H17: =IFERROR(H15/H9,"") -> 0.069719218 | J17: =AVERAGE(Model!H180,Model!N180,Model!T180,Model!Z180,Model!AF180,Model!AL180,Model!AR180,Model!AX180,Model!BD180,Model!BJ180,Model!BP180) -> 0.082517328 | K17: =MIN(Model!H180,Model!N180,Model!T180,Model!Z180,Model!AF180,Model!AL180,Model!AR180,Model!AX180,Model!BD180,Model!BJ180,Model!BP180) -> 0.046380581 | L17: =MAX(Model!H180,Model!N180,Model!T180,Model!Z180,Model!AF180,Model!AL180,Model!AR180,Model!AX180,Model!BD180,Model!BJ180,Model!BP180) -> 0.12139219 | N17: Operating margin (GAAP) % | O17: 0.052627363 | P17: 0.057992565 | Q17: 0.06659626 | R17: 0.069466231 | S17: 0.072282265 | T17: 0.075055697 | V17: 0.082517328 | W17: 0.046380581 | X17: 0.12139219 | Z17: Operating margin (GAAP) % | AA17: 0.052627363 | AB17: 0.052911877 | AC17: 0.049792949 | AD17: 0.052458126 | AE17: 0.055091875 | AF17: 0.057698477 | AH17: 0.082517328 | AI17: 0.046380581 | AJ17: 0.12139219
B19: Net Income (Adjusted, model) | C19: =Model!BP164 -> 502.3 | D19: =Model!BV164 -> 598.3725 | E19: =Model!BW164 -> 676.77859 | F19: =Model!BX164 -> 749.37116 | G19: =Model!BY164 -> 824.90839 | H19: =Model!BZ164 -> 902.18931 | I19: =IFERROR((H19/C19)^(1/5)-1,"n/m") -> 0.12426036 | N19: Net Income (Adjusted, model) | O19: 502.3 | P19: 635.93 | Q19: 762.07984 | R19: 857.83469 | S19: 960.16432 | T19: 1067.9559 | U19: 0.16283482 | Z19: Net Income (Adjusted, model) | AA19: 502.3 | AB19: 561.645 | AC19: 518.01915 | AD19: 561.62081 | AE19: 604.90958 | AF19: 646.85616 | AG19: 0.051886565
B21: FDSO (m) | C21: =Model!BP137 -> 39.3 | D21: =Model!BV137 -> 39.45 | E21: =Model!BW137 -> 39.485153 | F21: =Model!BX137 -> 38.898288 | G21: =Model!BY137 -> 38.206017 | H21: =Model!BZ137 -> 37.425285 | I21: =IFERROR((H21/C21)^(1/5)-1,"n/m") -> -0.0097279683 | N21: FDSO (m) | O21: 39.3 | P21: 39.45 | Q21: 38.684813 | R21: 37.604853 | S21: 36.451744 | T21: 35.240323 | U21: -0.021570662 | Z21: FDSO (m) | AA21: 39.3 | AB21: 39.45 | AC21: 39.825 | AD21: 39.895596 | AE21: 39.817775 | AF21: 39.611295 | AG21: 0.001579203
B23: Adjusted EPS — Diluted ($) | C23: =Model!BP166 -> 12.78117 | D23: =Model!BV166 -> 15.167871 | E23: =Model!BW166 -> 17.140078 | F23: =Model!BX166 -> 19.264888 | G23: =Model!BY166 -> 21.59106 | H23: =Model!BZ166 -> 24.106411 | I23: =IFERROR((H23/C23)^(1/5)-1,"n/m") -> 0.13530457 | N23: Adjusted EPS — Diluted ($) | O23: 12.78117 | P23: 16.119899 | Q23: 19.699716 | R23: 22.811808 | S23: 26.340696 | T23: 30.304941 | U23: 0.18847093 | Z23: Adjusted EPS — Diluted ($) | AA23: 12.78117 | AB23: 14.236882 | AC23: 13.007386 | AD23: 14.077263 | AE23: 15.191948 | AF23: 16.330094 | AG23: 0.050228042
B24: EPS y/y % | D24: =IFERROR(D23/C23-1,"") -> 0.18673565 | E24: =IFERROR(E23/D23-1,"") -> 0.13002531 | F24: =IFERROR(F23/E23-1,"") -> 0.12396735 | G24: =IFERROR(G23/F23-1,"") -> 0.12074671 | H24: =IFERROR(H23/G23-1,"") -> 0.11649968 | N24: EPS y/y % | P24: 0.26122241 | Q24: 0.22207445 | R24: 0.1579765 | S24: 0.15469565 | T24: 0.15049886 | Z24: EPS y/y % | AB24: 0.11389502 | AC24: -0.086359916 | AD24: 0.082251504 | AE24: 0.079183356 | AF24: 0.074917683
B26: P / E (x) — assumed | E26: 16.5 | F26: =E26 -> 16.5 | G26: =F26 -> 16.5 | H26: =G26 -> 16.5 | N26: P / E (x) — assumed | Q26: 19 | R26: 19 | S26: 19 | T26: 19 | Z26: P / E (x) — assumed | AC26: 14 | AD26: 14 | AE26: 14 | AF26: 14
B27: Price Target ($) | E27: =E26*E23 -> 282.81128 | F27: =F26*F23 -> 317.87065 | G27: =G26*G23 -> 356.25248 | H27: =H26*H23 -> 397.75578 | N27: Price Target ($) | Q27: 374.29461 | R27: 433.42436 | S27: 500.47322 | T27: 575.79388 | Z27: Price Target ($) | AC27: 182.10341 | AD27: 197.08169 | AE27: 212.68727 | AF27: 228.62131
B28: Upside / (Downside) vs current | E28: =IFERROR(E27/$K$2-1,"") -> 0.02840467 | F28: =IFERROR(F27/$K$2-1,"") -> 0.15589327 | G28: =IFERROR(G27/$K$2-1,"") -> 0.29546357 | H28: =IFERROR(H27/$K$2-1,"") -> 0.44638467 | N28: Upside / (Downside) vs current | Q28: 0.3610713 | R28: 0.57608858 | S28: 0.81990263 | T28: 1.0937959 | Z28: Upside / (Downside) vs current | AC28: -0.33780579 | AD28: -0.28333932 | AE28: -0.22659173 | AF28: -0.16864977
B29: IRR (to Dec-Y-1) | F29: =IFERROR((F27/$K$2)^(1/((DATE(VALUE(LEFT(F$7,4))-1,12,31)-$K$3)/365.25))-1,"") -> 0.12332918 | G29: =IFERROR((G27/$K$2)^(1/((DATE(VALUE(LEFT(G$7,4))-1,12,31)-$K$3)/365.25))-1,"") -> 0.12206033 | H29: =IFERROR((H27/$K$2)^(1/((DATE(VALUE(LEFT(H$7,4))-1,12,31)-$K$3)/365.25))-1,"") -> 0.12037208 | N29: IRR (to Dec-Y-1) | R29: 0.44081195 | S29: 0.30524289 | T29: 0.25556007 | Z29: IRR (to Dec-Y-1) | AD29: -0.23466184 | AE29: -0.10802058 | AF29: -0.05529536
B31: Free Cash Flow | C31: =Model!BP221 -> 800 | D31: =Model!BV221 -> 550 | E31: =Model!BW221 -> 416.48627 | F31: =Model!BX221 -> 577.77523 | G31: =Model!BY221 -> 671.64027 | H31: =Model!BZ221 -> 781.51157 | I31: =IFERROR((H31/C31)^(1/5)-1,"n/m") -> -0.0046654374 | N31: Free Cash Flow | O31: 800 | P31: 600 | Q31: 490.65185 | R31: 673.10027 | S31: 790.66309 | T31: 929.26664 | U31: 0.030410017 | Z31: Free Cash Flow | AA31: 800 | AB31: 500 | AC31: 275.82468 | AD31: 409.15287 | AE31: 474.90789 | AF31: 551.56894 | AG31: -0.071670903
B32: FCF % | C32: =IFERROR(C31/C9,"") -> 0.064082025 | D32: =IFERROR(D31/D9,"") -> 0.041509434 | E32: =IFERROR(E31/E9,"") -> 0.029624024 | F32: =IFERROR(F31/F9,"") -> 0.038975296 | G32: =IFERROR(G31/G9,"") -> 0.043082376 | H32: =IFERROR(H31/H9,"") -> 0.047846285 | J32: =AVERAGE(Model!H223,Model!N223,Model!T223,Model!Z223,Model!AF223,Model!AL223,Model!AR223,Model!AX223,Model!BD223,Model!BJ223,Model!BP223) -> 0.059026037 | K32: =MIN(Model!H223,Model!N223,Model!T223,Model!Z223,Model!AF223,Model!AL223,Model!AR223,Model!AX223,Model!BD223,Model!BJ223,Model!BP223) -> 0.003467707 | L32: =MAX(Model!H223,Model!N223,Model!T223,Model!Z223,Model!AF223,Model!AL223,Model!AR223,Model!AX223,Model!BD223,Model!BJ223,Model!BP223) -> 0.095868946 | N32: FCF % | O32: 0.064082025 | P32: 0.044609665 | Q32: 0.033758746 | R32: 0.04310706 | S32: 0.047252437 | T32: 0.052013562 | V32: 0.059026037 | W32: 0.003467707 | X32: 0.095868946 | Z32: FCF % | AA32: 0.064082025 | AB32: 0.038314176 | AC32: 0.020490146 | AD32: 0.029668017 | AE32: 0.033705364 | AF32: 0.038463589 | AH32: 0.059026037 | AI32: 0.003467707 | AJ32: 0.095868946
B33: FCF / share ($) | C33: =IFERROR(C31/C21,"") -> 20.356234 | D33: =IFERROR(D31/D21,"") -> 13.941698 | E33: =IFERROR(E31/E21,"") -> 10.547921 | F33: =IFERROR(F31/F21,"") -> 14.853487 | G33: =IFERROR(G31/G21,"") -> 17.579437 | H33: =IFERROR(H31/H21,"") -> 20.881914 | N33: FCF / share ($) | O33: 20.356234 | P33: 15.209125 | Q33: 12.68332 | R33: 17.899293 | S33: 21.690679 | T33: 26.369413 | Z33: FCF / share ($) | AA33: 20.356234 | AB33: 12.674271 | AC33: 6.9259179 | AD33: 10.25559 | AE33: 11.927032 | AF33: 13.924537
B34: FCF Yield (on PT) | E34: =IFERROR(E33/E$27,"") -> 0.037296676 | F34: =IFERROR(F33/F$27,"") -> 0.046728087 | G34: =IFERROR(G33/G$27,"") -> 0.049345444 | H34: =IFERROR(H33/H$27,"") -> 0.052499334 | N34: FCF Yield (on PT) | Q34: 0.033885927 | R34: 0.041297385 | S34: 0.043340339 | T34: 0.04579662 | Z34: FCF Yield (on PT) | AC34: 0.038032885 | AD34: 0.052037254 | AE34: 0.05607779 | AF34: 0.060906556
B35: Segment EBITDA | C35: =Model!BP103 -> 1046 | D35: =Model!BV103 -> 1128.75 | E35: =Model!BW103 -> 1267.1524 | F35: =Model!BX103 -> 1373.681 | G35: =Model!BY103 -> 1483.8949 | H35: =Model!BZ103 -> 1595.7669 | I35: =IFERROR((H35/C35)^(1/5)-1,"n/m") -> 0.088146965 | N35: Segment EBITDA | O35: 1046 | P35: 1174 | Q35: 1382.7485 | R35: 1525.0547 | S35: 1676.3548 | T35: 1834.7127 | U35: 0.11894123 | Z35: Segment EBITDA | AA35: 1046 | AB35: 1084.5 | AC35: 1059.0539 | AD35: 1119.8526 | AE35: 1179.6257 | AF35: 1236.643 | AG35: 0.034052364
B36: Segment EBITDA margin % | C36: =IFERROR(C35/C9,"") -> 0.083787248 | D36: =IFERROR(D35/D9,"") -> 0.085188679 | E36: =IFERROR(E35/E9,"") -> 0.09013059 | F36: =IFERROR(F35/F9,"") -> 0.09266514 | G36: =IFERROR(G35/G9,"") -> 0.095184464 | H36: =IFERROR(H35/H9,"") -> 0.097697235 | J36: =AVERAGE(Model!H110,Model!N110,Model!T110,Model!Z110,Model!AF110,Model!AL110,Model!AR110,Model!AX110,Model!BD110,Model!BJ110,Model!BP110) -> 0.10221681 | K36: =MIN(Model!H110,Model!N110,Model!T110,Model!Z110,Model!AF110,Model!AL110,Model!AR110,Model!AX110,Model!BD110,Model!BJ110,Model!BP110) -> 0.077936714 | L36: =MAX(Model!H110,Model!N110,Model!T110,Model!Z110,Model!AF110,Model!AL110,Model!AR110,Model!AX110,Model!BD110,Model!BJ110,Model!BP110) -> 0.12747595 | N36: Segment EBITDA margin % | O36: 0.083787248 | P36: 0.087286245 | Q36: 0.095138451 | R36: 0.097668398 | S36: 0.10018408 | T36: 0.10269382 | V36: 0.10221681 | W36: 0.077936714 | X36: 0.12747595 | Z36: Segment EBITDA margin % | AA36: 0.083787248 | AB36: 0.083103448 | AC36: 0.07867378 | AD36: 0.081201446 | AE36: 0.083720899 | AF36: 0.086237142 | AH36: 0.10221681 | AI36: 0.077936714 | AJ36: 0.12747595
B38: Net Debt | C38: =Model!BP324 -> 1926 | D38: =Model!BV324 -> 1638.764 | E38: =Model!BW324 -> 1666.206 | F38: =Model!BX324 -> 1585.64 | G38: =Model!BY324 -> 1463.8496 | H38: =Model!BZ324 -> 1284.2329 | N38: Net Debt | O38: 1926 | P38: 1738.764 | Q38: 1837.49 | R38: 1804.0244 | S38: 1702.6297 | T38: 1511.6832 | Z38: Net Debt | AA38: 1926 | AB38: 1688.764 | AC38: 1658.7998 | AD38: 1552.6966 | AE38: 1437.3605 | AF38: 1301.2677
B39: Net Debt / Segment EBITDA (x) | C39: =IFERROR(C38/C35,"") -> 1.8413002 | D39: =IFERROR(D38/D35,"") -> 1.4518396 | E39: =IFERROR(E38/E35,"") -> 1.3149215 | F39: =IFERROR(F38/F35,"") -> 1.1543001 | G39: =IFERROR(G38/G35,"") -> 0.98649144 | H39: =IFERROR(H38/H35,"") -> 0.80477475 | N39: Net Debt / Segment EBITDA (x) | O39: 1.8413002 | P39: 1.4810596 | Q39: 1.3288678 | R39: 1.1829244 | S39: 1.0156738 | T39: 0.82393454 | Z39: Net Debt / Segment EBITDA (x) | AA39: 1.8413002 | AB39: 1.5571821 | AC39: 1.5663034 | AD39: 1.3865188 | AE39: 1.2184886 | AF39: 1.0522581
B41: ROIC | C41: =Model!BP325 -> 0.079765946 | D41: =Model!BV325 -> 0.091758468 | E41: =Model!BW325 -> 0.099290118 | F41: =Model!BX325 -> 0.10399557 | G41: =Model!BY325 -> 0.10887031 | H41: =Model!BZ325 -> 0.11397123 | J41: =AVERAGE(Model!H325,Model!N325,Model!T325,Model!Z325,Model!AF325,Model!AL325,Model!AR325,Model!AX325,Model!BD325,Model!BJ325,Model!BP325) -> 0.15198199 | K41: =MIN(Model!H325,Model!N325,Model!T325,Model!Z325,Model!AF325,Model!AL325,Model!AR325,Model!AX325,Model!BD325,Model!BJ325,Model!BP325) -> 0.06963973 | L41: =MAX(Model!H325,Model!N325,Model!T325,Model!Z325,Model!AF325,Model!AL325,Model!AR325,Model!AX325,Model!BD325,Model!BJ325,Model!BP325) -> 0.23635014 | N41: ROIC | O41: 0.079765946 | P41: 0.097123938 | Q41: 0.1104404 | R41: 0.11735592 | S41: 0.12465086 | T41: 0.13242161 | V41: 0.15198199 | W41: 0.06963973 | X41: 0.23635014 | Z41: ROIC | AA41: 0.079765946 | AB41: 0.086516204 | AC41: 0.078622193 | AD41: 0.080810446 | AE41: 0.082990509 | AF41: 0.08518048 | AH41: 0.15198199 | AI41: 0.06963973 | AJ41: 0.23635014
B42: RONTA | C42: =Model!BP337 -> 0.087780166 | D42: =Model!BV337 -> 0.09367425 | E42: =Model!BW337 -> 0.099984324 | F42: =Model!BX337 -> 0.1022934 | G42: =Model!BY337 -> 0.10454844 | H42: =Model!BZ337 -> 0.10651512 | J42: =AVERAGE(Model!H337,Model!N337,Model!T337,Model!Z337,Model!AF337,Model!AL337,Model!AR337,Model!AX337,Model!BD337,Model!BJ337,Model!BP337) -> 0.1333038 | K42: =MIN(Model!H337,Model!N337,Model!T337,Model!Z337,Model!AF337,Model!AL337,Model!AR337,Model!AX337,Model!BD337,Model!BJ337,Model!BP337) -> 0.078382283 | L42: =MAX(Model!H337,Model!N337,Model!T337,Model!Z337,Model!AF337,Model!AL337,Model!AR337,Model!AX337,Model!BD337,Model!BJ337,Model!BP337) -> 0.20393778 | N42: RONTA | O42: 0.087780166 | P42: 0.10057896 | Q42: 0.11377398 | R42: 0.11861242 | S42: 0.12308798 | T42: 0.12690316 | V42: 0.1333038 | W42: 0.078382283 | X42: 0.20393778 | Z42: RONTA | AA42: 0.087780166 | AB42: 0.088946368 | AC42: 0.079095217 | AD42: 0.079162846 | AE42: 0.079434675 | AF42: 0.079711651 | AH42: 0.1333038 | AI42: 0.078382283 | AJ42: 0.20393778
B44: Implied Market Cap (USDm) | E44: =E27*E21 -> 11166.847 | F44: =F27*F21 -> 12364.624 | G44: =G27*G21 -> 13610.988 | H44: =H27*H21 -> 14886.124 | N44: Implied Market Cap (USDm) | Q44: 14479.517 | R44: 16298.859 | S44: 18243.122 | T44: 20291.162 | Z44: Implied Market Cap (USDm) | AC44: 7252.2682 | AD44: 7862.6914 | AE44: 8468.7341 | AF44: 9055.9863
B45: (+) Net Debt | E45: =E38 -> 1666.206 | F45: =F38 -> 1585.64 | G45: =G38 -> 1463.8496 | H45: =H38 -> 1284.2329 | N45: (+) Net Debt | Q45: 1837.49 | R45: 1804.0244 | S45: 1702.6297 | T45: 1511.6832 | Z45: (+) Net Debt | AC45: 1658.7998 | AD45: 1552.6966 | AE45: 1437.3605 | AF45: 1301.2677
B46: Implied Enterprise Value (USDm) | E46: =E44+E45 -> 12833.053 | F46: =F44+F45 -> 13950.264 | G46: =G44+G45 -> 15074.838 | H46: =H44+H45 -> 16170.357 | N46: Implied Enterprise Value (USDm) | Q46: 16317.007 | R46: 18102.884 | S46: 19945.752 | T46: 21802.845 | Z46: Implied Enterprise Value (USDm) | AC46: 8911.0679 | AD46: 9415.388 | AE46: 9906.0946 | AF46: 10357.254
B47: Implied EV / Segment EBITDA (x) | E47: =IFERROR(E46/E35,"") -> 10.127474 | F47: =IFERROR(F46/F35,"") -> 10.155389 | G47: =IFERROR(G46/G35,"") -> 10.158966 | H47: =IFERROR(H46/H35,"") -> 10.133282 | N47: Implied EV / Segment EBITDA (x) | Q47: 11.800415 | R47: 11.870317 | S47: 11.898288 | T47: 11.88352 | Z47: Implied EV / Segment EBITDA (x) | AC47: 8.4141776 | AD47: 8.4077033 | AE47: 8.3976588 | AF47: 8.3752982

Sheet DCF
B2: DCF VALUATION — HUNTINGTON INGALLS INDUSTRIES (HII)
B4: 1. WACC BUILD
B5: Risk-free rate (US 10Y govt) | C5: 0.0425 | D5: Assumption (~US 10Y Treasury yield); update to market
B6: Equity risk premium | C6: 0.055 | D6: Damodaran-style US ERP estimate
B7: Levered beta | C7: 0.65 | D7: Defense prime / shipbuilder beta range ~0.5–0.8 (US-government-funded, long-cycle backlog)
B8: Cost of equity | C8: =C5+C7*C6 -> 0.07825
B9: Pre-tax cost of debt | C9: 0.05 | D9: HII senior notes (BBB- / Baa3) — FY26 interest guidance $105m on $2.7bn debt ≈ 3.9% coupon; marginal cost ~5%
B10: Tax rate | C10: 0.21 | D10: US federal statutory rate
B11: After-tax cost of debt | C11: =C9*(1-C10) -> 0.0395
B12: Target D/V | C12: 0.15 | D12: Target leverage; net debt / total capital
B13: WACC | C13: =C8*(1-C12)+C11*C12 -> 0.0724375
B15: Valuation date (live) | C15: =TODAY() -> 46297 | D15: Periods = (Dec-31-Year − today) / 365.25; cash flows assumed at year-end
B16: 2. UNLEVERED FREE CASH FLOW BUILD (USDm)
D17: 2026E | E17: 2027E | F17: 2028E | G17: 2029E | H17: 2030E | I17: 2031E | J17: 2032E | K17: 2033E | L17: 2034E | M17: 2035E | N17: Terminal
B18: Segment operating income (Adj. EBIT) | D18: =Model!BV97 -> 798.75 | E18: =Model!BW97 -> 927.88853 | F18: =Model!BX97 -> 1016.416 | G18: =Model!BY97 -> 1108.5346 | H18: =Model!BZ97 -> 1202.7796 | I18: =H18*(1+I$26) -> 1250.8908 | J18: =I18*(1+J$26) -> 1294.672 | K18: =J18*(1+K$26) -> 1333.5122 | L18: =K18*(1+L$26) -> 1370.1838 | M18: =L18*(1+M$26) -> 1404.4384
B19: × (1 − tax rate) | D19: =1-$C$10 -> 0.79 | E19: =1-$C$10 -> 0.79 | F19: =1-$C$10 -> 0.79 | G19: =1-$C$10 -> 0.79 | H19: =1-$C$10 -> 0.79 | I19: =1-$C$10 -> 0.79 | J19: =1-$C$10 -> 0.79 | K19: =1-$C$10 -> 0.79 | ... M19: =1-$C$10 -> 0.79
B20: NOPAT | D20: =D18*D19 -> 631.0125 | E20: =E18*E19 -> 733.03194 | F20: =F18*F19 -> 802.96868 | G20: =G18*G19 -> 875.74235 | H20: =H18*H19 -> 950.19592 | I20: =I18*I19 -> 988.20376 | J20: =J18*J19 -> 1022.7909 | K20: =K18*K19 -> 1053.4746 | ... M20: =M18*M19 -> 1109.5063
B21: plus D&A | D21: =Model!BV102 -> 330 | E21: =Model!BW102 -> 339.26388 | F21: =Model!BX102 -> 357.26492 | G21: =Model!BY102 -> 375.3603 | H21: =Model!BZ102 -> 392.98728 | I21: =H21*(1+I$26) -> 408.70677 | J21: =I21*(1+J$26) -> 423.01151 | K21: =J21*(1+K$26) -> 435.70186 | L21: =K21*(1+L$26) -> 447.68366 | M21: =L21*(1+M$26) -> 458.87575
B22: − Capex (net of grant proceeds) | D22: =Model!BV204+Model!BV205 -> -590.25 | E22: =Model!BW204+Model!BW205 -> -587.51054 | F22: =Model!BX204+Model!BX205 -> -582.96558 | G22: =Model!BY204+Model!BY205 -> -574.61284 | H22: =Model!BZ204+Model!BZ205 -> -561.68294 | I22: =H22*(1+I$26) -> -584.15026 | J22: =I22*(1+J$26) -> -604.59552 | K22: =J22*(1+K$26) -> -622.73338 | L22: =K22*(1+L$26) -> -639.85855 | M22: =L22*(1+M$26) -> -655.85502
B23: − Δ Working capital (CF statement) | D23: =SUM(Model!BV197:BV201) -> 83.1675 | E23: =SUM(Model!BW197:BW201) -> -80.755666 | F23: =SUM(Model!BX197:BX201) -> -6.6052624 | G23: =SUM(Model!BY197:BY201) -> -6.7255851 | H23: =SUM(Model!BZ197:BZ201) -> -6.6920823 | I23: =H23*(1+I$26) -> -6.9597656 | J23: =I23*(1+J$26) -> -7.2033574 | K23: =J23*(1+K$26) -> -7.4194581 | L23: =K23*(1+L$26) -> -7.6234932 | M23: =L23*(1+M$26) -> -7.8140805
B24: Unlevered FCF | D24: =D20+D21+D22+D23 -> 453.93 | E24: =E20+E21+E22+E23 -> 404.02961 | F24: =F20+F21+F22+F23 -> 570.66275 | G24: =G20+G21+G22+G23 -> 669.76423 | H24: =H20+H21+H22+H23 -> 774.80818 | I24: =I20+I21+I22+I23 -> 805.80051 | J24: =J20+J21+J22+J23 -> 834.00353 | K24: =K20+K21+K22+K23 -> 859.02363 | ... M24: =M20+M21+M22+M23 -> 904.71295 | N24: =M24*(1+$C$27) -> 927.33077
B25: Terminal Value (Gordon Growth) | N25: =N24/($C$13-$C$27) -> 19548.475
B26: Fade-period growth (2031E–35E) | I26: 0.04 | J26: 0.035 | K26: 0.03 | L26: 0.0275 | M26: 0.025
B27: Terminal growth rate | C27: 0.025
B29: Discount period (years) | D29: =(DATE(2026,12,31)-$C$15)/365.25 -> 0.24640657 | E29: =(DATE(2027,12,31)-$C$15)/365.25 -> 1.2457221 | F29: =(DATE(2028,12,31)-$C$15)/365.25 -> 2.2477755 | G29: =(DATE(2029,12,31)-$C$15)/365.25 -> 3.247091 | H29: =(DATE(2030,12,31)-$C$15)/365.25 -> 4.2464066 | I29: =(DATE(2031,12,31)-$C$15)/365.25 -> 5.2457221 | J29: =(DATE(2032,12,31)-$C$15)/365.25 -> 6.2477755 | K29: =(DATE(2033,12,31)-$C$15)/365.25 -> 7.247091 | L29: =(DATE(2034,12,31)-$C$15)/365.25 -> 8.2464066 | M29: =(DATE(2035,12,31)-$C$15)/365.25 -> 9.2457221 | N29: =M29 -> 9.2457221
B30: Discount factor | D30: =1/(1+$C$13)^D29 -> 0.9829154 | E30: =1/(1+$C$13)^E29 -> 0.91656852 | F30: =1/(1+$C$13)^F29 -> 0.85453643 | G30: =1/(1+$C$13)^G29 -> 0.79685514 | H30: =1/(1+$C$13)^H29 -> 0.74306734 | I30: =1/(1+$C$13)^I29 -> 0.69291023 | J30: =1/(1+$C$13)^J29 -> 0.64601502 | K30: =1/(1+$C$13)^K29 -> 0.60240895 | ... N30: =1/(1+$C$13)^N29 -> 0.52382836
B31: PV of UFCF | D31: =D24*D30 -> 446.17479 | E31: =E24*E30 -> 370.32082 | F31: =F24*F30 -> 487.65211 | G31: =G24*G30 -> 533.70507 | H31: =H24*H30 -> 575.73466 | I31: =I24*I30 -> 558.34741 | J31: =J24*J30 -> 538.7788 | K31: =K24*K30 -> 517.48352 | ... M31: =M24*M30 -> 473.9143 | N31: =N25*N30 -> 10240.045
D32: Pension: HII carries a net pension asset (Model BS); CAS pension recovery is embedded in segment OI and the non-cash FAS income is excluded from UFCF — no pension adjustment to net debt.
B34: 3. VALUATION SUMMARY
B35: Sum of PV (explicit + fade) | C35: =SUM(D31:M31) -> 4997.935
B36: PV of Terminal Value | C36: =N31 -> 10240.045
B37: Enterprise Value | C37: =C35+C36 -> 15237.981
B38: Less: Net debt (Model 2026E YE) | C38: =Model!BV324 -> 1638.764
B39: Equity Value | C39: =C37-C38 -> 13599.217
B40: Diluted shares (m, Model 2026E) | C40: =Model!BV137 -> 39.45
B41: Implied share price ($) | C41: =C39/C40 -> 344.72032
B42: Current share price ($) | C42: =Model!BV350 -> 275
B43: Implied upside / (downside) | C43: =C41/C42-1 -> 0.25352843
B46: 4. SENSITIVITY: IMPLIED PRICE ($) — WACC × Terminal Growth
B48: WACC (across):
B49: g (down) / WACC | D49: 0.06 | E49: 0.065 | F49: 0.07 | G49: 0.075 | H49: 0.08
B50: 0.015 | D50: =IFERROR((SUMPRODUCT($D$24:$M$24/(1+D$49)^$D$29:$M$29)+($M$24*(1+$B50)/(D$49-$B50))/(1+D$49)^$M$29-$C$38)/$C$40,"") -> 394.45067 | E50: =IFERROR((SUMPRODUCT($D$24:$M$24/(1+E$49)^$D$29:$M$29)+($M$24*(1+$B50)/(E$49-$B50))/(1+E$49)^$M$29-$C$38)/$C$40,"") -> 349.61711 | F50: =IFERROR((SUMPRODUCT($D$24:$M$24/(1+F$49)^$D$29:$M$29)+($M$24*(1+$B50)/(F$49-$B50))/(1+F$49)^$M$29-$C$38)/$C$40,"") -> 312.97416 | G50: =IFERROR((SUMPRODUCT($D$24:$M$24/(1+G$49)^$D$29:$M$29)+($M$24*(1+$B50)/(G$49-$B50))/(1+G$49)^$M$29-$C$38)/$C$40,"") -> 282.47309 | H50: =IFERROR((SUMPRODUCT($D$24:$M$24/(1+H$49)^$D$29:$M$29)+($M$24*(1+$B50)/(H$49-$B50))/(1+H$49)^$M$29-$C$38)/$C$40,"") -> 256.69559
B51: 0.02 | D51: =IFERROR((SUMPRODUCT($D$24:$M$24/(1+D$49)^$D$29:$M$29)+($M$24*(1+$B51)/(D$49-$B51))/(1+D$49)^$M$29-$C$38)/$C$40,"") -> 433.85066 | E51: =IFERROR((SUMPRODUCT($D$24:$M$24/(1+E$49)^$D$29:$M$29)+($M$24*(1+$B51)/(E$49-$B51))/(1+E$49)^$M$29-$C$38)/$C$40,"") -> 379.93745 | F51: =IFERROR((SUMPRODUCT($D$24:$M$24/(1+F$49)^$D$29:$M$29)+($M$24*(1+$B51)/(F$49-$B51))/(1+F$49)^$M$29-$C$38)/$C$40,"") -> 336.84186 | G51: =IFERROR((SUMPRODUCT($D$24:$M$24/(1+G$49)^$D$29:$M$29)+($M$24*(1+$B51)/(G$49-$B51))/(1+G$49)^$M$29-$C$38)/$C$40,"") -> 301.61276 | H51: =IFERROR((SUMPRODUCT($D$24:$M$24/(1+H$49)^$D$29:$M$29)+($M$24*(1+$B51)/(H$49-$B51))/(1+H$49)^$M$29-$C$38)/$C$40,"") -> 272.28272
B52: 0.025 | D52: =IFERROR((SUMPRODUCT($D$24:$M$24/(1+D$49)^$D$29:$M$29)+($M$24*(1+$B52)/(D$49-$B52))/(1+D$49)^$M$29-$C$38)/$C$40,"") -> 484.5078 | E52: =IFERROR((SUMPRODUCT($D$24:$M$24/(1+E$49)^$D$29:$M$29)+($M$24*(1+$B52)/(E$49-$B52))/(1+E$49)^$M$29-$C$38)/$C$40,"") -> 417.83787 | F52: =IFERROR((SUMPRODUCT($D$24:$M$24/(1+F$49)^$D$29:$M$29)+($M$24*(1+$B52)/(F$49-$B52))/(1+F$49)^$M$29-$C$38)/$C$40,"") -> 366.0135 | G52: =IFERROR((SUMPRODUCT($D$24:$M$24/(1+G$49)^$D$29:$M$29)+($M$24*(1+$B52)/(G$49-$B52))/(1+G$49)^$M$29-$C$38)/$C$40,"") -> 324.58036 | H52: =IFERROR((SUMPRODUCT($D$24:$M$24/(1+H$49)^$D$29:$M$29)+($M$24*(1+$B52)/(H$49-$B52))/(1+H$49)^$M$29-$C$38)/$C$40,"") -> 290.70388
B53: 0.03 | D53: =IFERROR((SUMPRODUCT($D$24:$M$24/(1+D$49)^$D$29:$M$29)+($M$24*(1+$B53)/(D$49-$B53))/(1+D$49)^$M$29-$C$38)/$C$40,"") -> 552.05065 | E53: =IFERROR((SUMPRODUCT($D$24:$M$24/(1+E$49)^$D$29:$M$29)+($M$24*(1+$B53)/(E$49-$B53))/(1+E$49)^$M$29-$C$38)/$C$40,"") -> 466.56698 | F53: =IFERROR((SUMPRODUCT($D$24:$M$24/(1+F$49)^$D$29:$M$29)+($M$24*(1+$B53)/(F$49-$B53))/(1+F$49)^$M$29-$C$38)/$C$40,"") -> 402.47805 | G53: =IFERROR((SUMPRODUCT($D$24:$M$24/(1+G$49)^$D$29:$M$29)+($M$24*(1+$B53)/(G$49-$B53))/(1+G$49)^$M$29-$C$38)/$C$40,"") -> 352.65187 | H53: =IFERROR((SUMPRODUCT($D$24:$M$24/(1+H$49)^$D$29:$M$29)+($M$24*(1+$B53)/(H$49-$B53))/(1+H$49)^$M$29-$C$38)/$C$40,"") -> 312.80926
B54: 0.035 | D54: =IFERROR((SUMPRODUCT($D$24:$M$24/(1+D$49)^$D$29:$M$29)+($M$24*(1+$B54)/(D$49-$B54))/(1+D$49)^$M$29-$C$38)/$C$40,"") -> 646.61063 | E54: =IFERROR((SUMPRODUCT($D$24:$M$24/(1+E$49)^$D$29:$M$29)+($M$24*(1+$B54)/(E$49-$B54))/(1+E$49)^$M$29-$C$38)/$C$40,"") -> 531.53913 | F54: =IFERROR((SUMPRODUCT($D$24:$M$24/(1+F$49)^$D$29:$M$29)+($M$24*(1+$B54)/(F$49-$B54))/(1+F$49)^$M$29-$C$38)/$C$40,"") -> 449.36104 | G54: =IFERROR((SUMPRODUCT($D$24:$M$24/(1+G$49)^$D$29:$M$29)+($M$24*(1+$B54)/(G$49-$B54))/(1+G$49)^$M$29-$C$38)/$C$40,"") -> 387.74126 | H54: =IFERROR((SUMPRODUCT($D$24:$M$24/(1+H$49)^$D$29:$M$29)+($M$24*(1+$B54)/(H$49-$B54))/(1+H$49)^$M$29-$C$38)/$C$40,"") -> 339.82696
B57: 5. REVERSE DCF
B58: To solve for the market-implied path: Data ▸ What-If Analysis ▸ Goal Seek — set C41 to the current price (C42) by changing C27 (terminal growth) or the fade-period growth inputs (I26:M26).
B60: 6. MAUBOUSSIN EV / NOPAT — TWO-STAGE FRAMEWORK
B61: EV/NOPAT = 1/r + [g × (1 − r/ROIIC) / (r × (r − g))] × [1 − ((1+g)/(1+r))^N]
B62: Formula source: Mauboussin & Rappaport, "Expectations Investing" (2021); Counterpoint Global, "What Does a Price-Earnings Multiple Mean?" (2020).
B64: Input | C64: Value | D64: Rationale (HII characteristics)
B65: r (Cost of capital / WACC) | C65: =$C$13 -> 0.0724375 | D65: Linked from Section 1 WACC build
B66: g (NOPAT growth, Stage 1) | C66: 0.06 | D66: Model segment OI CAGR 2025–30E ~11% (margin recovery from depressed FY24–25); normalised to ~6% (Navy shipbuilding budget growth + throughput gains)
B67: ROIIC (Return on incremental invested capital) | C67: 0.12 | D67: Capital-intensive shipyards: historical ROIC 7–24%; incremental returns constrained by cost-plus / fixed-price-incentive pricing and capex cycle
B68: N (Years of value creation / CAP) | C68: 12 | D68: Sole builder of US nuclear carriers & amphibs; one of two nuclear submarine builders — long competitive-advantage period, multi-decade programs
B70: Calculation | C70: Value
B71: Steady-state component: 1 / r | C71: =1/C65 -> 13.805004
B72: Value-creation factor: 1 − r / ROIIC | C72: =1-C65/C67 -> 0.39635417
B73: Growth multiplier: g × (1 − r/ROIIC) / (r × (r − g)) | C73: =C66*C72/(C65*(C65-C66)) -> 26.396001
B74: Time decay: 1 − ((1+g)/(1+r))^N | C74: =1-((1+C66)/(1+C65))^C68 -> 0.13062633
B75: PVGO component (growth value) | C75: =C73*C74 -> 3.4480126
B76: Mauboussin EV / NOPAT (steady-state + PVGO) | C76: =C71+C75 -> 17.253017
B78: VALUATION — Applied to 2028E NOPAT | C78: USDm
B79: 2028E Segment OI (Model) | C79: =Model!BX97 -> 1016.416
B80: Tax rate (from WACC build) | C80: =$C$10 -> 0.21
B81: 2028E NOPAT = EBIT × (1 − t) | C81: =C79*(1-C80) -> 802.96868
B82: × Mauboussin EV/NOPAT multiple | C82: =C76 -> 17.253017
B83: Implied Enterprise Value (2028E basis) | C83: =C81*C82 -> 13853.632
B84: Less: YE2027 net debt (Model) | C84: =Model!BW324 -> 1666.206
B85: Implied Equity Value | C85: =C83-C84 -> 12187.426
B86: Diluted shares 2028E (m, Model) | C86: =Model!BX137 -> 38.898288
B87: Implied share price 2028 ($) | C87: =C85/C86 -> 313.31523
B89: Current share price ($) | C89: =C42 -> 275
B90: Implied upside / (downside) | C90: =C87/C89-1 -> 0.13932812
B92: MARKET-IMPLIED EV/NOPAT TODAY | C92: USDm
B93: Current market cap (spot × diluted shares) | C93: =C42*C40 -> 10848.75
B94: Plus: YE2026 net debt | C94: =C38 -> 1638.764
B95: Implied Enterprise Value (today) | C95: =C93+C94 -> 12487.514
B96: HII's market-implied EV/NOPAT (on 2028E NOPAT) | C96: =C95/C81 -> 15.551683
B98: Multiple gap (Mauboussin − Market) | C98: =C76-C96 -> 1.7013344
B99: Implied re-rating headroom | C99: =C76/C96-1 -> 0.10939873

Sheet Charts
B2: HII — Historical Operating Performance (2015–2025)
B3: All historicals · USDm · Linked to Model. M&A % reflects disclosed acquired revenue only (Camber FY2017, Alion FY2021).
C7: 2015 | D7: 2016 | E7: 2017 | F7: 2018 | G7: 2019 | H7: 2020 | I7: 2021 | J7: 2022 | K7: 2023 | L7: 2024 | M7: 2025
B8: Organic % | C8: =0 -> 0 | D8: =IFERROR(Model!N172+0,0) -> 0.0068376068 | E8: =IFERROR(Model!T172+0,0) -> 0.0090548953 | F8: =IFERROR(Model!Z172+0,0) -> 0.098777046 | G8: =IFERROR(Model!AF172+0,0) -> 0.08842955 | H8: =IFERROR(Model!AL172+0,0) -> 0.051915946 | I8: =IFERROR(Model!AR172+0,0) -> -0.036641384 | J8: =IFERROR(Model!AX172+0,0) -> 0.12095758 | K8: =IFERROR(Model!BD172+0,0) -> 0.072873735 | L8: =IFERROR(Model!BJ172+0,0) -> 0.0070717653 | M8: =IFERROR(Model!BP172+0,0) -> 0.082271348
B9: M&A % | C9: =0 -> 0 | D9: =IFERROR(Model!N173+0,0) -> 0 | E9: =IFERROR(Model!T173+0,0) -> 0.043718166 | F9: =IFERROR(Model!Z173+0,0) -> 0 | G9: =IFERROR(Model!AF173+0,0) -> 0 | H9: =IFERROR(Model!AL173+0,0) -> 0 | I9: =IFERROR(Model!AR173+0,0) -> 0.054054054 | J9: =IFERROR(Model!AX173+0,0) -> 0 | K9: =IFERROR(Model!BD173+0,0) -> 0 | L9: =IFERROR(Model!BJ173+0,0) -> 0 | M9: =IFERROR(Model!BP173+0,0) -> 0
C11: =C7 -> 2015 | D11: =D7 -> 2016 | E11: =E7 -> 2017 | F11: =F7 -> 2018 | G11: =G7 -> 2019 | H11: =H7 -> 2020 | I11: =I7 -> 2021 | J11: =J7 -> 2022 | ... M11: =M7 -> 2025
B12: Segment Operating Income | C12: =Model!H97 -> 667 | D12: =Model!N97 -> 715 | E12: =Model!T97 -> 688 | F12: =Model!Z97 -> 663 | G12: =Model!AF97 -> 631 | H12: =Model!AL97 -> 555 | I12: =Model!AR97 -> 683 | J12: =Model!AX97 -> 712 | K12: =Model!BD97 -> 842 | L12: =Model!BJ97 -> 573 | M12: =Model!BP97 -> 717
B13: Operating Income (GAAP) | C13: =Model!H126 -> 769 | D13: =Model!N126 -> 858 | E13: =Model!T126 -> 881 | F13: =Model!Z126 -> 951 | G13: =Model!AF126 -> 736 | H13: =Model!AL126 -> 799 | I13: =Model!AR126 -> 513 | J13: =Model!AX126 -> 565 | K13: =Model!BD126 -> 781 | L13: =Model!BJ126 -> 535 | M13: =Model!BP126 -> 657
B14: Segment Op. Margin % | C14: =Model!H107 -> 0.095014245 | D14: =Model!N107 -> 0.10116016 | E14: =Model!T107 -> 0.092460691 | F14: =Model!Z107 -> 0.081090998 | G14: =Model!AF107 -> 0.070906843 | H14: =Model!AL107 -> 0.059288538 | I14: =Model!AR107 -> 0.071713566 | J14: =Model!AX107 -> 0.066691645 | K14: =Model!BD107 -> 0.073511437 | L14: =Model!BJ107 -> 0.049674902 | M14: =Model!BP107 -> 0.057433515
B15: GAAP Op. Margin % | C15: =Model!H180 -> 0.10954416 | D15: =Model!N180 -> 0.12139219 | E15: =Model!T180 -> 0.11839806 | F15: =Model!Z180 -> 0.11631605 | G15: =Model!AF180 -> 0.082705922 | H15: =Model!AL180 -> 0.085354129 | I15: =Model!AR180 -> 0.053863923 | J15: =Model!AX180 -> 0.052922443 | K15: =Model!BD180 -> 0.068185787 | L15: =Model!BJ180 -> 0.046380581 | M15: =Model!BP180 -> 0.052627363
C17: =C7 -> 2015 | D17: =D7 -> 2016 | E17: =E7 -> 2017 | F17: =F7 -> 2018 | G17: =G7 -> 2019 | H17: =H7 -> 2020 | I17: =I7 -> 2021 | J17: =J7 -> 2022 | ... M17: =M7 -> 2025
B18: ROIC | C18: =IFERROR(Model!H325,NA()) -> 0.22812917 | D18: =IFERROR(Model!N325,NA()) -> 0.23635014 | E18: =IFERROR(Model!T325,NA()) -> 0.18274008 | F18: =IFERROR(Model!Z325,NA()) -> 0.22306441 | G18: =IFERROR(Model!AF325,NA()) -> 0.18120831 | H18: =IFERROR(Model!AL325,NA()) -> 0.15508582 | I18: =IFERROR(Model!AR325,NA()) -> 0.10902546 | J18: =IFERROR(Model!AX325,NA()) -> 0.096737473 | K18: =IFERROR(Model!BD325,NA()) -> 0.11005535 | L18: =IFERROR(Model!BJ325,NA()) -> 0.06963973 | M18: =IFERROR(Model!BP325,NA()) -> 0.079765946
B19: RONTA | C19: =IFERROR(Model!H337,NA()) -> 0.12924323 | D19: =IFERROR(Model!N337,NA()) -> 0.16193683 | E19: =IFERROR(Model!T337,NA()) -> 0.13102542 | F19: =IFERROR(Model!Z337,NA()) -> 0.20393778 | G19: =IFERROR(Model!AF337,NA()) -> 0.15482358 | H19: =IFERROR(Model!AL337,NA()) -> 0.12543106 | I19: =IFERROR(Model!AR337,NA()) -> 0.13536154 | J19: =IFERROR(Model!AX337,NA()) -> 0.12137235 | K19: =IFERROR(Model!BD337,NA()) -> 0.13704751 | L19: =IFERROR(Model!BJ337,NA()) -> 0.078382283 | M19: =IFERROR(Model!BP337,NA()) -> 0.087780166
B20: Segment EBITDA margin % | C20: =IFERROR(Model!H110,NA()) -> 0.12065527 | D20: =IFERROR(Model!N110,NA()) -> 0.12747595 | E20: =IFERROR(Model!T110,NA()) -> 0.12001075 | F20: =IFERROR(Model!Z110,NA()) -> 0.10591977 | G20: =IFERROR(Model!AF110,NA()) -> 0.096415328 | H20: =IFERROR(Model!AL110,NA()) -> 0.085674607 | I20: =IFERROR(Model!AR110,NA()) -> 0.10247795 | J20: =IFERROR(Model!AX110,NA()) -> 0.1002248 | K20: =IFERROR(Model!BD110,NA()) -> 0.10380653 | L20: =IFERROR(Model!BJ110,NA()) -> 0.077936714 | M20: =IFERROR(Model!BP110,NA()) -> 0.083787248
B21: Shipbuilding op. margin % | C21: =IFERROR(Model!H108,NA()) -> 0.12025902 | D21: =IFERROR(Model!N108,NA()) -> 0.10913862 | E21: =IFERROR(Model!T108,NA()) -> 0.1013062 | F21: =IFERROR(Model!Z108,NA()) -> 0.08685668 | G21: =IFERROR(Model!AF108,NA()) -> 0.082840997 | H21: =IFERROR(Model!AL108,NA()) -> 0.062310583 | I21: =IFERROR(Model!AR108,NA()) -> 0.077279941 | J21: =IFERROR(Model!AX108,NA()) -> 0.077060081 | K21: =IFERROR(Model!BD108,NA()) -> 0.083398987 | L21: =IFERROR(Model!BJ108,NA()) -> 0.052312271 | M21: =IFERROR(Model!BP108,NA()) -> 0.058841941

Sheet Sheet1
