Workbook

Sheet Model
CF1: SCENARIO SWITCH ▼ (Bull / Base / Bear) — drives all scenario-linked forecast drivers
B2: Lincoln Electric Holdings, Inc. (Nasdaq: LECO) — 3-Statement Financial Model | CF2: Base
B3: US GAAP as reported · USD millions (per-share data in USD; shares in millions) · Source: Lincoln Electric Forms 10-K / 10-Q and Form 8-K earnings releases (Ex. 99.1), segment-recast 8-K (10-Feb-2016), SEC EDGAR CIK 0000059527 (investor-relations releases are the same documents as filed on EDGAR); XBRL company facts used to cross-check totals
B4: Basis notes: calendar fiscal year. Three reportable segments (Americas Welding, International Welding, The Harris Products Group) from Q1/16, recast for FY2013 and 2014–15 quarters (no 2013 quarterly recast); five legacy segments (North America / Europe / Asia Pacific / South America Welding + Harris) 2009–2015 and North America / Europe / Other Countries 2006–2008 shown as memo. Per-share data 2006–2010 restated for the 2-for-1 split (May-2011). Venezuela deconsolidated Q4/15. Adjusted measures = company definitions (special items: rationalization & asset impairments, acquisition costs & inventory step-up, pension settlements, Venezuela, disposal gains, discrete tax items). FY26 outlook per the Q2-26 call (30-Jul-2026).
CH5: Forecast | CI5: Historical | CJ5: Historical | CK5: Historical
B6: (USDm) | C6: 2006 | D6: 2007 | E6: 2008 | F6: 2009 | G6: 2010 | H6: 2011 | I6: 2012 | J6: Q1/13 | K6: Q2/13 | L6: Q3/13 | M6: Q4/13 | N6: 2013 | O6: Q1/14 | P6: Q2/14 | Q6: Q3/14 | R6: Q4/14 | S6: 2014 | T6: Q1/15 | U6: Q2/15 | V6: Q3/15 | W6: Q4/15 | X6: 2015 | Y6: Q1/16 | Z6: Q2/16 | AA6: Q3/16 | AB6: Q4/16 | AC6: 2016 | AD6: Q1/17 | AE6: Q2/17 | AF6: Q3/17 | AG6: Q4/17 | AH6: 2017 | AI6: Q1/18 | AJ6: Q2/18 | AK6: Q3/18 | AL6: Q4/18 | AM6: 2018 | AN6: Q1/19 | AO6: Q2/19 | AP6: Q3/19 | AQ6: Q4/19 | AR6: 2019 | AS6: Q1/20 | AT6: Q2/20 | AU6: Q3/20 | AV6: Q4/20 | AW6: 2020 | AX6: Q1/21 | AY6: Q2/21 | AZ6: Q3/21 | BA6: Q4/21 | BB6: 2021 | BC6: Q1/22 | BD6: Q2/22 | BE6: Q3/22 | BF6: Q4/22 | BG6: 2022 | BH6: Q1/23 | BI6: Q2/23 | BJ6: Q3/23 | BK6: Q4/23 | BL6: 2023 | BM6: Q1/24 | BN6: Q2/24 | BO6: Q3/24 | BP6: Q4/24 | BQ6: 2024 | BR6: Q1/25 | BS6: Q2/25 | BT6: Q3/25 | BU6: Q4/25 | BV6: 2025 | BW6: Q1/26 | BX6: Q2/26 | BY6: Q3/26E | BZ6: Q4/26E | CA6: 2026E | CB6: 2027E | CC6: 2028E | CD6: 2029E | CE6: 2030E | CF6: Modelling Notes | CH6: 5Y CAGR | CI6: 5Y CAGR | CJ6: 10Y CAGR | CK6: 19Y CAGR
CH7: 25-'30 | CI7: 20-'25 | CJ7: 15-'25 | CK7: 06-'25
B8: SEGMENT P&L — AMERICAS WELDING · INTERNATIONAL WELDING · THE HARRIS PRODUCTS GROUP (volume × price × acquisitions × FX build) | CF8: SEGMENT BUILD — modelling logic (prior-year net sales × (1 + volume + price + acquisitions + FX) → total segment sales × adjusted EBIT margin → group adjusted EBIT)
CN9: SCENARIO INPUT TABLE — driver assumptions per Bull / Base / Bear | CO9: Bull | CP9: Base | CQ9: Bear | CR9: Bull / Bear = Base + Δ (Δ inputs on each lever header). Outlook block = high / mid / low end of the FY26 ranges.
B10: Americas Welding (arc-welding equipment, consumables, automation & cutting — North and South America) | CF10: AMERICAS WELDING — modelling logic
B11: Net sales (external customers) | N11: 1848.663 | O11: 441.849 | P11: 465.524 | Q11: 469.39 | R11: 460.907 | S11: 1837.67 | T11: 448.837 | U11: 451.001 | V11: 454.172 | W11: 387.34 | X11: 1741.35 | Y11: 359.008 | Z11: 388.372 | AA11: 377.52 | AB11: 370.082 | AC11: 1494.982 | AD11: 383.324 | AE11: 405.147 | AF11: 398.289 | AG11: 423.019 | AH11: 1609.779 | AI11: 434.772 | AJ11: 462.515 | AK11: 454.01 | AL11: 455.217 | AM11: 1806.514 | AN11: 457.719 | AO11: 476.607 | AP11: 443.521 | AQ11: 437.899 | AR11: 1815.746 | AS11: 418.535 | AT11: 333.229 | AU11: 371.535 | AV11: 386.571 | AW11: 1509.87 | AX11: 425.242 | AY11: 457.468 | AZ11: 461.508 | BA11: 480.263 | BB11: 1824.481 | BC11: 534.055 | BD11: 595.659 | BE11: 585.628 | BF11: 573.592 | BG11: 2288.934 | BH11: 658.645 | BI11: 676.966 | BJ11: 665.228 | BK11: 654.707 | BL11: 2655.546 | BM11: 624.099 | BN11: 648.936 | BO11: 637.026 | BP11: 654.786 | BQ11: 2564.847 | BR11: 653.107 | BS11: 696.73 | BT11: 691.794 | BU11: 681.93 | BV11: 2723.561 | BW11: 706.225 | BX11: 774.438 | BY11: =BT11*(1+BY12) -> 774.64165 | BZ11: =BU11*(1+BZ12) -> 763.59636 | CA11: =SUM(BW11,BX11,BY11,BZ11) -> 3018.901 | CB11: =CA11*(1+CB12) -> 3200.0351 | CC11: =CB11*(1+CC12) -> 3376.037 | CD11: =CC11*(1+CD12) -> 3544.8389 | CE11: =CD11*(1+CE12) -> 3722.0808 | CF11: Historical: segment table of the earnings release (current 3-segment basis from FY2013 / Q1-14, per the Feb-2016 recast 8-K). Q3/Q4-26E: prior-year quarter × (1 + volume + price + acquisitions + FX). 2027E+: prior year × (1 + scenario levers AW_vol + AW_price (+ FX)). | CH11: =IFERROR((CE11/BV11)^(1/5)-1,"n/m") -> 0.06446096 | CI11: =IFERROR((BV11/AW11)^(1/5)-1,"n/m") -> 0.12522536 | CJ11: =IFERROR((BV11/X11)^(1/10)-1,"n/m") -> 0.045743331 | CK11: =IFERROR((BV11/C11)^(1/19)-1,"n/m") -> n/m | CN11: FY26 outlook — Q2-26 earnings call (30-Jul-26); company assumptions | CO11: High | CP11: Mid | CQ11: Low | CR11: Lincoln Electric gives qualitative / range outlook on its earnings call (not in the 8-K). Captured from call coverage; IR site & slides not reachable from this environment — verify against the Q2-26 presentation.
B12: Net sales y/y % | S12: =IF(AND(ISNUMBER(S11),ISNUMBER(N11)),IFERROR(S11/N11-1,""),"") -> -0.0059464597 | T12: =IF(AND(ISNUMBER(T11),ISNUMBER(O11)),IFERROR(T11/O11-1,""),"") -> 0.015815358 | U12: =IF(AND(ISNUMBER(U11),ISNUMBER(P11)),IFERROR(U11/P11-1,""),"") -> -0.031197103 | V12: =IF(AND(ISNUMBER(V11),ISNUMBER(Q11)),IFERROR(V11/Q11-1,""),"") -> -0.032420801 | W12: =IF(AND(ISNUMBER(W11),ISNUMBER(R11)),IFERROR(W11/R11-1,""),"") -> -0.15961354 | X12: =IF(AND(ISNUMBER(X11),ISNUMBER(S11)),IFERROR(X11/S11-1,""),"") -> -0.052414198 | Y12: =IF(AND(ISNUMBER(Y11),ISNUMBER(T11)),IFERROR(Y11/T11-1,""),"") -> -0.20013724 | Z12: =IF(AND(ISNUMBER(Z11),ISNUMBER(U11)),IFERROR(Z11/U11-1,""),"") -> -0.13886665 | ... BX12: =IF(AND(ISNUMBER(BX11),ISNUMBER(BS11)),IFERROR(BX11/BS11-1,""),"") -> 0.11153244 | BY12: =BY13+BY14+BY15+BY16 -> 0.11975769 | BZ12: =BZ13+BZ14+BZ15+BZ16 -> 0.11975769 | CA12: =IFERROR(CA11/BV11-1,"") -> 0.10843892 | CB12: =CB13+CB14+CB15+CB16 -> 0.06 | CC12: =CC13+CC14+CC15+CC16 -> 0.055 | CD12: =CD13+CD14+CD15+CD16 -> 0.05 | CE12: =CE13+CE14+CE15+CE16 -> 0.05 | CN12: FY26 net sales growth — "low double-digit %" | CO12: 0.13 | CP12: 0.115 | CQ12: 0.1 | CR12: Raised on the Q2-26 call to low double-digit (from mid-to-high single digit). 1H/26 +11.9%. Drives the Q3/Q4-26E volume calibration.
B13: Volume % (company "change in net sales due to volume") | Y13: -0.19 | Z13: -0.133 | AA13: -0.179 | AB13: -0.058 | AC13: -0.143 | AD13: 0.041 | AE13: 0.017 | AF13: 0.022 | AG13: 0.101 | AH13: 0.045 | AI13: 0.075 | AJ13: 0.077 | AK13: 0.058 | AL13: -0.001 | AM13: 0.051 | AN13: -0.029 | AO13: -0.036 | AP13: -0.045 | AQ13: -0.065 | AR13: -0.044 | AS13: -0.082 | AT13: -0.292 | AU13: -0.156 | AV13: -0.124 | AW13: -0.165 | AX13: -0.009 | AY13: 0.271 | AZ13: 0.114 | BA13: 0.093 | BB13: 0.109 | BC13: 0.052 | BD13: 0.099 | BE13: 0.114 | BF13: 0.077 | BG13: 0.086 | BH13: 0.11 | BI13: 0.058 | BJ13: 0.004 | BK13: 0.026 | BL13: 0.048 | BM13: -0.065 | BN13: -0.067 | BO13: -0.086 | BP13: -0.072 | BQ13: -0.072 | BR13: -0.04 | BS13: -0.034 | BT13: -0.024 | BU13: -0.069 | BV13: -0.042 | BW13: -0.004 | BX13: 0.071 | BY13: =$BX$13+BY139 -> 0.082757692 | BZ13: =$BX$13+BZ139 -> 0.082757692 | CA13: =IFERROR(CA18/BV11,"") -> 0.059023913 | CB13: =CHOOSE(MATCH($CF$2,{"Bull","Base","Bear"},0),$CO$23,$CP$23,$CQ$23) -> 0.03 | CC13: =CHOOSE(MATCH($CF$2,{"Bull","Base","Bear"},0),$CO$24,$CP$24,$CQ$24) -> 0.03 | CD13: =CHOOSE(MATCH($CF$2,{"Bull","Base","Bear"},0),$CO$25,$CP$25,$CQ$25) -> 0.025 | CE13: =CHOOSE(MATCH($CF$2,{"Bull","Base","Bear"},0),$CO$26,$CP$26,$CQ$26) -> 0.025 | CF13: Q3/Q4-26E: Q2/26 y/y volume + outlook calibration Δ (Group block). 2027E–2030E: scenario lever AW_vol (Bull/Base/Bear table →). | CN13: FY26 organic sales growth — "high single-digit to low double-digit" (memo) | CO13: 0.11 | CP13: 0.095 | CQ13: 0.08 | CR13: ~1/3 volume, ~2/3 price per management. Memo / cross-check only.
B14: Price % | Y14: 0.179 | Z14: 0.43 | AA14: -0.012 | AB14: 0 | AC14: 0.154 | AD14: 0.015 | AE14: 0.027 | AF14: 0.024 | AG14: 0.029 | AH14: 0.024 | AI14: 0.046 | AJ14: 0.054 | AK14: 0.091 | AL14: 0.083 | AM14: 0.069 | AN14: 0.063 | AO14: 0.025 | AP14: -0.012 | AQ14: -0.017 | AR14: 0.014 | AS14: -0.012 | AT14: -0.003 | AU14: -0.002 | AV14: 0.012 | AW14: -0.001 | AX14: 0.022 | AY14: 0.082 | AZ14: 0.118 | BA14: 0.146 | BB14: 0.091 | BC14: 0.198 | BD14: 0.196 | BE14: 0.151 | BF14: 0.114 | BG14: 0.164 | BH14: 0.046 | BI14: 0.01 | BJ14: 0.006 | BK14: 0.005 | BL14: 0.016 | BM14: 0.003 | BN14: 0.01 | BO14: 0.004 | BP14: -0.001 | BQ14: 0.004 | BR14: 0.021 | BS14: 0.065 | BT14: 0.096 | BU14: 0.104 | BV14: 0.072 | BW14: 0.076 | BX14: 0.037 | BY14: =$BX$14 -> 0.037 | BZ14: =$BX$14 -> 0.037 | CA14: =IFERROR(CA19/BV11,"") -> 0.046258479 | CB14: =CHOOSE(MATCH($CF$2,{"Bull","Base","Bear"},0),$CO$28,$CP$28,$CQ$28) -> 0.03 | CC14: =CHOOSE(MATCH($CF$2,{"Bull","Base","Bear"},0),$CO$29,$CP$29,$CQ$29) -> 0.025 | CD14: =CHOOSE(MATCH($CF$2,{"Bull","Base","Bear"},0),$CO$30,$CP$30,$CQ$30) -> 0.025 | CE14: =CHOOSE(MATCH($CF$2,{"Bull","Base","Bear"},0),$CO$31,$CP$31,$CQ$31) -> 0.025 | CF14: Q3/Q4-26E: Q2/26 y/y price held (carry-over of the 2025–26 increases; HPG includes metals pass-through). 2027E+: scenario lever. Note: 2016 Americas Welding as published includes Venezuela hyperinflationary price (+15.4%) offset by FX (−17.7%); ex-Venezuela price −0.5%, FX −1.0%. | CN14: 2H/26 incremental adjusted operating income margin — "mid-20%" | CO14: 0.275 | CP14: 0.25 | CQ14: 0.225 | CR14: Q2-26 call: adjusted operating margin to improve y/y at mid-20% incrementals in 2H; price/cost neutral in 2H. Drives the Q3/Q4-26E margin calibration.
B15: Acquisitions % | Y15: 0.016 | Z15: 0.036 | AA15: 0.027 | AB15: 0.019 | AC15: 0.025 | AD15: 0.009 | AE15: 0.003 | AF15: 0.003 | AG15: 0.007 | AH15: 0.006 | AI15: 0.009 | AJ15: 0.01 | AK15: 0.003 | AL15: 0.007 | AM15: 0.007 | AN15: 0.029 | AO15: 0.047 | AP15: 0.038 | AQ15: 0.043 | AR15: 0.039 | AS15: 0.014 | AT15: 0 | AU15: 0 | AV15: 0 | AW15: 0.003 | AX15: 0 | AY15: 0 | AZ15: 0 | BA15: 0 | BB15: 0 | BC15: 0.004 | BD15: 0.012 | BE15: 0.01 | BF15: 0.012 | BG15: 0.01 | BH15: 0.085 | BI15: 0.074 | BJ15: 0.123 | BK15: 0.107 | BL15: 0.097 | BM15: 0.006 | BN15: 0.018 | BO15: 0.045 | BP15: 0.083 | BQ15: 0.038 | BR15: 0.076 | BS15: 0.047 | BT15: 0.014 | BU15: 0 | BV15: 0.034 | BW15: 0 | BX15: 0 | BY15: 0 | BZ15: 0 | CA15: =IFERROR(CA20/BV11,"") -> 0 | CB15: 0 | CC15: 0 | CD15: 0 | CE15: 0 | CF15: No Americas Welding acquisitions in the last 12 months (Vanair Jul-24 and RedViking Apr-24 fully anniversaried). 2027E+: future deals in the M&A lever. | CN15: FY26 interest expense, net ($m) | CO15: 50 | CP15: 52.5 | CQ15: 55 | CR15: Company assumption $50–55m (maintained on the Q2-26 call).
B16: Foreign exchange % | Y16: -0.205 | Z16: -0.472 | AA16: -0.004 | AB16: -0.005 | AC16: -0.177 | AD16: 0.002 | AE16: -0.005 | AF16: 0.005 | AG16: 0.006 | AH16: 0.002 | AI16: 0.004 | AJ16: 0.001 | AK16: -0.012 | AL16: -0.013 | AM16: -0.005 | AN16: -0.011 | AO16: -0.005 | AP16: -0.004 | AQ16: 0.001 | AR16: -0.005 | AS16: -0.005 | AT16: -0.006 | AU16: -0.005 | AV16: -0.005 | AW16: -0.005 | AX16: 0.003 | AY16: 0.02 | AZ16: 0.01 | BA16: 0.003 | BB16: 0.009 | BC16: 0.002 | BD16: -0.005 | BE16: -0.007 | BF16: -0.009 | BG16: -0.005 | BH16: -0.008 | BI16: -0.005 | BJ16: 0.003 | BK16: 0.004 | BL16: -0.001 | BM16: 0.003 | BN16: -0.002 | BO16: -0.005 | BP16: -0.01 | BQ16: -0.004 | BR16: -0.011 | BS16: -0.004 | BT16: 0 | BU16: 0.006 | BV16: -0.002 | BW16: 0.009 | BX16: 0.004 | BY16: 0 | BZ16: 0 | CA16: =IFERROR(CA21/BV11,"") -> 0.0031565293 | CB16: 0 | CC16: 0 | CD16: 0 | CE16: 0 | CF16: Q3/Q4-26E: FX input (spot-rate translation vs prior-year quarter). 2027E+: International Welding FX lever; Americas & Harris 0%. | CN16: FY26 effective tax rate — "low-to-mid 20%" | CO16: 0.22 | CP16: 0.23 | CQ16: 0.24 | CR16: Company assumption (adjusted ETR). 1H/26 22.7% adjusted.
B17: Organic growth % (volume + price) | Y17: =Y13+Y14 -> -0.011 | Z17: =Z13+Z14 -> 0.297 | AA17: =AA13+AA14 -> -0.191 | AB17: =AB13+AB14 -> -0.058 | AC17: =AC13+AC14 -> 0.011 | AD17: =AD13+AD14 -> 0.056 | AE17: =AE13+AE14 -> 0.044 | AF17: =AF13+AF14 -> 0.046 | ... CE17: =CE13+CE14 -> 0.05 | CN17: FY26 capital expenditures ($m) | CO17: 130 | CP17: 120 | CQ17: 110 | CR17: Company assumption $110–130m.
B18: Δ Net sales — volume ($) | Y18: -85.063 | Z18: -59.999 | AA18: -81.338 | AB18: -22.315 | AC18: -248.715 | AD18: 14.761 | AE18: 6.766 | AF18: 8.401 | AG18: 37.378 | AH18: 67.306 | AI18: 28.562 | AJ18: 31.023 | AK18: 23.084 | AL18: -0.411 | AM18: 82.258 | AN18: -12.395 | AO18: -16.756 | AP18: -20.605 | AQ18: -29.529 | AR18: -79.285 | AS18: -37.692 | AT18: -139.035 | AU18: -69.028 | AV18: -54.412 | AW18: -300.167 | AX18: -3.79 | AY18: 90.285 | AZ18: 42.341 | BA18: 35.759 | BB18: 164.595 | BC18: 22.004 | BD18: 45.284 | BE18: 52.521 | BF18: 36.752 | BG18: 156.561 | BH18: 58.65 | BI18: 34.384 | BJ18: 2.072 | BK18: 14.754 | BL18: 109.86 | BM18: -42.653 | BN18: -45.665 | BO18: -57.292 | BP18: -46.844 | BQ18: -192.454 | BR18: -24.74 | BS18: -22.346 | BT18: -15.011 | BU18: -45.383 | BV18: -107.48 | BW18: -2.635 | BX18: 49.704 | BY18: =BT11*BY13 -> 57.251275 | BZ18: =BU11*BZ13 -> 56.434953 | CA18: =SUM(BW18,BX18,BY18,BZ18) -> 160.75523 | CB18: =CA11*CB13 -> 90.56703 | CC18: =CB11*CC13 -> 96.001052 | CD18: =CC11*CD13 -> 84.400925 | CE18: =CD11*CE13 -> 88.620971 | CN18: FY26 cash conversion (FCF / adjusted net income; memo) | CO18: 1 | CP18: 1 | CQ18: 1 | CR18: Company target ~100% cash conversion.
B19: Δ Net sales — price ($) | Y19: 80.32 | Z19: 193.706 | AA19: -5.645 | AB19: -0.176 | AC19: 268.205 | AD19: 5.52 | AE19: 10.508 | AF19: 9.197 | AG19: 10.784 | AH19: 36.009 | AI19: 17.682 | AJ19: 21.958 | AK19: 36.128 | AL19: 35.27 | AM19: 111.038 | AN19: 27.428 | AO19: 11.599 | AP19: -5.603 | AQ19: -7.719 | AR19: 25.705 | AS19: -5.392 | AT19: -1.405 | AU19: -0.682 | AV19: 5.164 | AW19: -2.315 | AX19: 9.065 | AY19: 27.33 | AZ19: 43.957 | BA19: 56.615 | BB19: 136.967 | BC19: 84.218 | BD19: 89.854 | BE19: 69.888 | BF19: 54.968 | BG19: 298.928 | BH19: 24.699 | BI19: 5.974 | BJ19: 3.488 | BK19: 2.964 | BL19: 37.125 | BM19: 2.284 | BN19: 6.522 | BO19: 2.505 | BP19: -0.541 | BQ19: 10.77 | BR19: 13.369 | BS19: 42.265 | BT19: 60.885 | BU19: 67.964 | BV19: 184.483 | BW19: 49.479 | BX19: 25.681 | BY19: =BT11*BY14 -> 25.596378 | BZ19: =BU11*BZ14 -> 25.23141 | CA19: =SUM(BW19,BX19,BY19,BZ19) -> 125.98779 | CB19: =CA11*CB14 -> 90.56703 | CC19: =CB11*CC14 -> 80.000877 | CD19: =CC11*CD14 -> 84.400925 | CE19: =CD11*CE14 -> 88.620971 | CN19: Capital returns | CO19: Bull | CP19: Base | CQ19: Bear
B20: Δ Net sales — acquisitions ($) | Y20: 6.977 | Z20: 16.323 | AA20: 12.3 | AB20: 7.232 | AC20: 42.832 | AD20: 3.338 | AE20: 1.354 | AF20: 1.14 | AG20: 2.638 | AH20: 8.47 | AI20: 3.606 | AJ20: 4.059 | AK20: 1.148 | AL20: 2.831 | AM20: 11.644 | AN20: 12.72 | AO20: 21.512 | AP20: 17.38 | AQ20: 19.45 | AR20: 71.062 | AS20: 6.19 | AT20: 0 | AU20: 0 | AV20: 0 | AW20: 6.19 | AX20: 0 | AY20: 0 | AZ20: 0 | BA20: 0 | BB20: 0 | BC20: 1.745 | BD20: 5.437 | BE20: 4.724 | BF20: 5.696 | BG20: 17.602 | BH20: 45.249 | BI20: 43.947 | BJ20: 72.159 | BK20: 61.138 | BL20: 222.493 | BM20: 4.164 | BN20: 12.42 | BO20: 30.212 | BP20: 54.301 | BQ20: 101.097 | BR20: 47.327 | BS20: 30.192 | BT20: 8.842 | BU20: 0 | BV20: 86.361 | BW20: 0 | BX20: 0 | BY20: =BT11*BY15 -> 0 | BZ20: =BU11*BZ15 -> 0 | CA20: =SUM(BW20,BX20,BY20,BZ20) -> 0 | CB20: =CA11*CB15 -> 0 | CC20: =CB11*CC15 -> 0 | CD20: =CC11*CD15 -> 0 | CE20: =CD11*CE15 -> 0 | CN20: 2H/26 share repurchases ($m) | CO20: 160 | CP20: 130 | CQ20: 100 | CR20: 1H/26 repurchases $133m (Q1 $57m, Q2 $76m). Base keeps the 1H pace.
B21: Δ Net sales — foreign exchange ($) | Y21: -92.063 | Z21: -212.659 | AA21: -1.969 | AB21: -1.999 | AC21: -308.69 | AD21: 0.697 | AE21: -1.853 | AF21: 2.031 | AG21: 2.137 | AH21: 3.012 | AI21: 1.598 | AJ21: 0.328 | AK21: -4.639 | AL21: -5.492 | AM21: -8.205 | AN21: -4.806 | AO21: -2.263 | AP21: -1.661 | AQ21: 0.48 | AR21: -8.25 | AS21: -2.29 | AT21: -2.938 | AU21: -2.276 | AV21: -2.08 | AW21: -9.584 | AX21: 1.432 | AY21: 6.624 | AZ21: 3.675 | BA21: 1.318 | BB21: 13.049 | BC21: 0.846 | BD21: -2.384 | BE21: -3.013 | BF21: -4.087 | BG21: -8.638 | BH21: -4.008 | BI21: -2.998 | BJ21: 1.881 | BK21: 2.259 | BL21: -2.866 | BM21: 1.659 | BN21: -1.307 | BO21: -3.627 | BP21: -6.837 | BQ21: -10.112 | BR21: -6.948 | BS21: -2.317 | BT21: 0.052 | BU21: 4.563 | BV21: -4.65 | BW21: 6.274 | BX21: 2.323 | BY21: =BT11*BY16 -> 0 | BZ21: =BU11*BZ16 -> 0 | CA21: =SUM(BW21,BX21,BY21,BZ21) -> 8.597 | CB21: =CA11*CB16 -> 0 | CC21: =CB11*CC16 -> 0 | CD21: =CC11*CD16 -> 0 | CE21: =CD11*CE16 -> 0 | CN21: Minimum net debt / Adjusted EBITDA (x) — buyback floor 2027E+ | CO21: 1.25 | CP21: 1 | CQ21: 0.75 | CR21: LECO runs ~0.5–1.0x net leverage; surplus cash above the floor is returned through repurchases.
B22: Inter-segment sales | N22: 105.811 | O22: 28.217 | P22: 28.989 | Q22: 27.244 | R22: 26.074 | S22: 110.524 | T22: 23.023 | U22: 23.902 | V22: 25.571 | W22: 20.042 | X22: 92.538 | Y22: 23.831 | Z22: 23.456 | AA22: 22.386 | AB22: 23.939 | AC22: 93.612 | AD22: 22.46 | AE22: 27.374 | AF22: 25.546 | AG22: 22.002 | AH22: 97.382 | AI22: 26.586 | AJ22: 31.24 | AK22: 31.845 | AL22: 29.265 | AM22: 118.936 | AN22: 29.388 | AO22: 34.811 | AP22: 31.101 | AQ22: 28.042 | AR22: 123.342 | AS22: 24.783 | AT22: 27.493 | AU22: 29.368 | AV22: 27.734 | AW22: 109.378 | AX22: 32.748 | AY22: 39.765 | AZ22: 37.48 | BA22: 30.657 | BB22: 140.65 | BC22: 28.156 | BD22: 29.031 | BE22: 35.353 | BF22: 29.479 | BG22: 122.019 | BH22: 32.318 | BI22: 30.85 | BJ22: 28.875 | BK22: 35.493 | BL22: 127.536 | BM22: 29.978 | BN22: 37.8 | BO22: 30.845 | BP22: 37.134 | BQ22: 135.758 | BR22: 30.372 | BS22: 43.391 | BT22: 30.058 | BU22: 25.101 | BV22: 128.922 | BW22: 36.709 | BX22: 28.904 | BY22: =BY11*BT22/BT11 -> 33.657677 | BZ22: =BZ11*BU22/BU11 -> 28.107038 | CA22: =SUM(BW22,BX22,BY22,BZ22) -> 127.37771 | CB22: =CB11*CA22/CA11 -> 135.02038 | CC22: =CC11*CB22/CB11 -> 142.4465 | CD22: =CD11*CC22/CC11 -> 149.56882 | CE22: =CE11*CD22/CD11 -> 157.04726 | CF22: Forecast: prior-year inter-segment sales ratio to external net sales. | CN22: AW_vol (Americas Welding volume y/y) | CO22: 0.02 | CP22: Δ → | CQ22: -0.02 | CR22: Americas industrial capex, fabrication & automation demand; volume inflected +7.1% in Q2/26 after nine quarters of declines (2025 −4.2%).
B23: Total segment sales (incl. inter-segment) | N23: =N11+N(N22) -> 1954.474 | O23: =O11+N(O22) -> 470.066 | P23: =P11+N(P22) -> 494.513 | Q23: =Q11+N(Q22) -> 496.634 | R23: =R11+N(R22) -> 486.981 | S23: =S11+N(S22) -> 1948.194 | T23: =T11+N(T22) -> 471.86 | U23: =U11+N(U22) -> 474.903 | ... BX23: =BX11+N(BX22) -> 803.342 | BY23: =BY11+BY22 -> 808.29933 | BZ23: =BZ11+BZ22 -> 791.7034 | CA23: =CA11+CA22 -> 3146.2787 | CB23: =CB11+CB22 -> 3335.0555 | CC23: =CC11+CC22 -> 3518.4835 | CD23: =CD11+CD22 -> 3694.4077 | CE23: =CE11+CE22 -> 3879.1281 | CN23: 2027E | CO23: =CP23+$CO$22 -> 0.05 | CP23: 0.03 | CQ23: =CP23+$CQ$22 -> 0.01
B24: Adjusted EBIT (segment profit, company definition) | N24: 377.436 | O24: 83.688 | P24: 95.941 | Q24: 84.026 | R24: 89.6 | S24: 353.255 | T24: 75.415 | U24: 79.421 | V24: 82.765 | W24: 79.088 | X24: 316.689 | Y24: 61.438 | Z24: 65.201 | AA24: 68.285 | AB24: 71.709 | AC24: 266.633 | AD24: 68.723 | AE24: 74.498 | AF24: 74.096 | AG24: 74.549 | AH24: 291.866 | AI24: 77.439 | AJ24: 88.158 | AK24: 89.253 | AL24: 85.894 | AM24: 340.744 | AN24: 81.752 | AO24: 84.851 | AP24: 74.11 | AQ24: 75.006 | AR24: 315.719 | AS24: 70.702 | AT24: 46.702 | AU24: 59.12 | AV24: 69.204 | AW24: 245.728 | AX24: 76.617 | AY24: 84.134 | AZ24: 84.557 | BA24: 83.708 | BB24: 329.016 | BC24: 111.568 | BD24: 118.067 | BE24: 118.804 | BF24: 114.38 | BG24: 462.819 | BH24: 132.453 | BI24: 139.87 | BJ24: 136.476 | BK24: 129.469 | BL24: 538.269 | BM24: 136.1 | BN24: 136.651 | BO24: 125.515 | BP24: 131.923 | BQ24: 530.188 | BR24: 124.198 | BS24: 137.915 | BT24: 131.615 | BU24: 141.111 | BV24: 534.839 | BW24: 127.468 | BX24: 158.095 | BY24: =BY23*BY26 -> 152.20207 | BZ24: =BZ23*BZ26 -> 162.73622 | CA24: =SUM(BW24,BX24,BY24,BZ24) -> 600.50129 | CB24: =CA24+CB30 -> 659.36986 | CC24: =CB24+CC30 -> 716.97049 | CD24: =CC24+CD30 -> 771.83109 | CE24: =CD24+CE30 -> 829.43472 | CF24: 2027E+: prior-year adjusted EBIT + Δ bridge (price $ × fall-through + volume $ × incremental margin + (acquisitions + FX) $ × prior-year margin). 2026E = sum of quarters. | CH24: =IFERROR((CE24/BV24)^(1/5)-1,"n/m") -> 0.091721413 | CI24: =IFERROR((BV24/AW24)^(1/5)-1,"n/m") -> 0.16829814 | CJ24: =IFERROR((BV24/X24)^(1/10)-1,"n/m") -> 0.053801977 | CK24: =IFERROR((BV24/C24)^(1/19)-1,"n/m") -> n/m | CN24: 2028E | CO24: =CP24+$CO$22 -> 0.05 | CP24: 0.03 | CQ24: =CP24+$CQ$22 -> 0.01
B25: Adjusted EBIT margin before outlook calibration % (Q3/Q4-26E helper) | BY25: =BT26+($BW$24+$BX$24)/($BW$23+$BX$23)-($BR$24+$BS$24)/($BR$23+$BS$23) -> 0.18288768 | BZ25: =BU26+($BW$24+$BX$24)/($BW$23+$BX$23)-($BR$24+$BS$24)/($BR$23+$BS$23) -> 0.20014054 | CF25: Q3/Q4-26E: prior-year quarter margin + (1H/26 − 1H/25 margin drift). | CN25: 2029E | CO25: =CP25+$CO$22 -> 0.045 | CP25: 0.025 | CQ25: =CP25+$CQ$22 -> 0.005
B26: Adjusted EBIT margin % (on total segment sales) | N26: =IF(AND(ISNUMBER(N24),ISNUMBER(N23)),IFERROR(N24/N23,""),"") -> 0.19311385 | O26: =IF(AND(ISNUMBER(O24),ISNUMBER(O23)),IFERROR(O24/O23,""),"") -> 0.17803457 | P26: =IF(AND(ISNUMBER(P24),ISNUMBER(P23)),IFERROR(P24/P23,""),"") -> 0.19401108 | Q26: =IF(AND(ISNUMBER(Q24),ISNUMBER(Q23)),IFERROR(Q24/Q23,""),"") -> 0.16919099 | R26: =IF(AND(ISNUMBER(R24),ISNUMBER(R23)),IFERROR(R24/R23,""),"") -> 0.18399075 | S26: =IF(AND(ISNUMBER(S24),ISNUMBER(S23)),IFERROR(S24/S23,""),"") -> 0.18132434 | T26: =IF(AND(ISNUMBER(T24),ISNUMBER(T23)),IFERROR(T24/T23,""),"") -> 0.15982495 | U26: =IF(AND(ISNUMBER(U24),ISNUMBER(U23)),IFERROR(U24/U23,""),"") -> 0.16723626 | ... BX26: =IF(AND(ISNUMBER(BX24),ISNUMBER(BX23)),IFERROR(BX24/BX23,""),"") -> 0.19679663 | BY26: =BY25+BY144 -> 0.18829914 | BZ26: =BZ25+BZ144 -> 0.205552 | CA26: =IFERROR(CA24/CA23,"") -> 0.1908608 | CB26: =IFERROR(CB24/CB23,"") -> 0.19770881 | CC26: =IFERROR(CC24/CC23,"") -> 0.20377259 | CD26: =IFERROR(CD24/CD23,"") -> 0.20891876 | CE26: =IFERROR(CE24/CE23,"") -> 0.21381989 | CF26: Q3/Q4-26E: margin before calibration + outlook calibration Δ. 2027E+: output of the Δ adjusted EBIT bridge. | CH26: =IFERROR(AVERAGE(CA26,CB26,CC26,CD26,CE26),"n/m") -> 0.20301617 | CI26: =IFERROR(AVERAGE(AW26,BB26,BG26,BL26,BQ26,BV26),"n/m") -> 0.18139591 | CJ26: =IFERROR(AVERAGE(X26,AC26,AH26,AM26,AR26,AW26,BB26,BG26,BL26,BQ26,BV26),"n/m") -> 0.17633248 | CK26: =IFERROR(AVERAGE(C26,D26,E26,F26,G26,H26,I26,N26,S26,X26,AC26,AH26,AM26,AR26,AW26,BB26,BG26,BL26,BQ26,BV26),"n/m") -> 0.17800735 | CN26: 2030E | CO26: =CP26+$CO$22 -> 0.045 | CP26: 0.025 | CQ26: =CP26+$CQ$22 -> 0.005
B27: Incremental adjusted EBIT margin (Δ adj. EBIT / Δ total sales) | S27: =IFERROR((S24-N24)/(S23-N23),"") -> 3.8504777 | T27: =IFERROR((T24-O24)/(T23-O23),"") -> -4.6114827 | U27: =IFERROR((U24-P24)/(U23-P23),"") -> 0.84242733 | V27: =IFERROR((V24-Q24)/(V23-Q23),"") -> 0.074655142 | W27: =IFERROR((W24-R24)/(W23-R23),"") -> 0.13206196 | X27: =IFERROR((X24-S24)/(X23-S23),"") -> 0.31989572 | Y27: =IFERROR((Y24-T24)/(Y23-T23),"") -> 0.1570079 | Z27: =IFERROR((Z24-U24)/(Z23-U23),"") -> 0.2254459 | ... CA27: =IFERROR((CA24-BV24)/(CA23-BV23),"") -> 0.22349639 | CB27: =IFERROR((CB24-CA24)/(CB23-CA23),"") -> 0.31184231 | CC27: =IFERROR((CC24-CB24)/(CC23-CB23),"") -> 0.31402303 | CD27: =IFERROR((CD24-CC24)/(CD23-CC23),"") -> 0.31184231 | CE27: =IFERROR((CE24-CD24)/(CE23-CD23),"") -> 0.31184231 | CN27: AW_price (Americas Welding price y/y) | CO27: 0.01 | CP27: Δ → | CQ27: -0.01 | CR27: Pricing to offset steel / tariff-driven inflation; 2025 +7.2%, 1H/26 +5.6%. Normalises to low-single-digit.
B28: Price fall-through to adjusted EBIT % | CB28: 0.3 | CC28: 0.3 | CD28: 0.3 | CE28: 0.3 | CF28: Input: share of price-driven sales growth that falls through to adjusted EBIT (price/cost broadly neutral — LECO prices to offset inflation; HPG price is largely metals pass-through). | CN28: 2027E | CO28: =CP28+$CO$27 -> 0.04 | CP28: 0.03 | CQ28: =CP28+$CQ$27 -> 0.02
B29: Volume incremental adjusted EBIT margin % | CB29: 0.35 | CC29: 0.35 | CD29: 0.35 | CE29: 0.35 | CF29: Input: incremental margin on volume-driven sales (company targets mid-20s–30s% incrementals through the cycle). | CN29: 2028E | CO29: =CP29+$CO$27 -> 0.035 | CP29: 0.025 | CQ29: =CP29+$CQ$27 -> 0.015
B30: Δ Adjusted EBIT (price × fall-through + volume × incremental + (acq. + FX) × prior margin) | CB30: =CB19*CB28+CB18*CB29+(CB20+CB21)*CA26 -> 58.86857 | CC30: =CC19*CC28+CC18*CC29+(CC20+CC21)*CB26 -> 57.600631 | CD30: =CD19*CD28+CD18*CD29+(CD20+CD21)*CC26 -> 54.860601 | CE30: =CE19*CE28+CE18*CE29+(CE20+CE21)*CD26 -> 57.603631 | CN30: 2029E | CO30: =CP30+$CO$27 -> 0.035 | CP30: 0.025 | CQ30: =CP30+$CQ$27 -> 0.015
B31: Special items (pre-tax, charged to the segment) | N31: 13.25 | O31: 17.618 | P31: 3.447 | Q31: 0.582 | R31: 0 | S31: 21.647 | T31: 0 | U31: 0 | V31: 166.178 | W31: 7.061 | X31: 173.239 | Y31: 0 | Z31: 0 | AA31: 0 | AB31: 0 | AC31: 0 | AD31: 0 | AE31: 0 | AF31: 5.283 | AG31: 3.959 | AH31: 9.242 | AI31: 0.758 | AJ31: 0 | AK31: 4.232 | AL31: 1.696 | AM31: 6.686 | AN31: 1.336 | AO31: 1.779 | AP31: 0 | AQ31: 0 | AR31: 3.115 | AS31: 1.19 | AT31: 26.007 | AU31: 7.044 | AV31: 0.748 | AW31: 34.989 | AX31: 4.44 | AY31: 1.65 | AZ31: 73.574 | BA31: 43.45 | BB31: 123.114 | BC31: -3.735 | BD31: 0.461 | BE31: -0.353 | BF31: 0.567 | BG31: -3.06 | BH31: 2.785 | BI31: 2.957 | BJ31: 4.056 | BK31: 0.06 | BL31: 9.858 | BM31: 0 | BN31: 0.354 | BO31: 23.357 | BP31: 4.11 | BQ31: 27.821 | BR31: 2.135 | BS31: 0.905 | BT31: 4.375 | BU31: 3.295 | BV31: 10.71 | BW31: 0.573 | BX31: 1.012 | CF31: Historical disclosure only; forecast special items are modelled at the consolidated level. | CN31: 2030E | CO31: =CP31+$CO$27 -> 0.035 | CP31: 0.025 | CQ31: =CP31+$CQ$27 -> 0.015
B32: EBIT (GAAP, as reported in the segment table) | N32: 364.186 | O32: 66.07 | P32: 92.494 | Q32: 83.444 | R32: 89.6 | S32: 331.608 | T32: 75.415 | U32: 79.421 | V32: -83.413 | W32: 72.027 | X32: 143.45 | Y32: 61.438 | Z32: 65.201 | AA32: 68.285 | AB32: 71.709 | AC32: 266.633 | AD32: 68.723 | AE32: 74.498 | AF32: 68.813 | AG32: 70.59 | AH32: 282.624 | AI32: 76.681 | AJ32: 88.158 | AK32: 85.021 | AL32: 84.198 | AM32: 334.058 | AN32: 80.416 | AO32: 83.072 | AP32: 74.11 | AQ32: 75.006 | AR32: 312.604 | AS32: 69.512 | AT32: 20.695 | AU32: 52.076 | AV32: 68.456 | AW32: 210.739 | AX32: 72.177 | AY32: 82.484 | AZ32: 10.983 | BA32: 40.258 | BB32: 205.902 | BC32: 115.303 | BD32: 117.606 | BE32: 119.157 | BF32: 113.813 | BG32: 465.879 | BH32: 129.668 | BI32: 136.913 | BJ32: 132.42 | BK32: 129.409 | BL32: 528.411 | BM32: 136.1 | BN32: 136.297 | BO32: 102.158 | BP32: 127.813 | BQ32: 502.367 | BR32: 122.063 | BS32: 137.01 | BT32: 127.24 | BU32: 137.816 | BV32: 524.129 | BW32: 126.895 | BX32: 157.083 | CN32: IW_vol (International Welding volume y/y) | CO32: 0.02 | CP32: Δ → | CQ32: -0.02 | CR32: Europe weak (2024–1H/26 volumes −4% to −10% p.a.); Asia Pacific improving. Base assumes a gradual recovery.
CN33: 2027E | CO33: =CP33+$CO$32 -> 0.04 | CP33: 0.02 | CQ33: =CP33+$CQ$32 -> 0
B34: International Welding (welding & cutting — Europe, Middle East, Africa, Asia Pacific) | CF34: INTERNATIONAL WELDING — modelling logic | CN34: 2028E | CO34: =CP34+$CO$32 -> 0.045 | CP34: 0.025 | CQ34: =CP34+$CQ$32 -> 0.005
B35: Net sales (external customers) | N35: 695.831 | O35: 170.742 | P35: 185.588 | Q35: 168.004 | R35: 157.09 | S35: 681.424 | T35: 139.247 | U35: 141.927 | V35: 128.072 | W35: 121.214 | X35: 530.46 | Y35: 124.305 | Z35: 132.815 | AA35: 119.564 | AB35: 130.605 | AC35: 507.289 | AD35: 128.888 | AE35: 141.498 | AF35: 197.617 | AG35: 256.021 | AH35: 724.024 | AI35: 247.32 | AJ35: 243.373 | AK35: 209.622 | AL35: 219.456 | AM35: 919.771 | AN35: 218.086 | AO35: 212.306 | AP35: 205.378 | AQ35: 218.606 | AR35: 854.376 | AS35: 197.923 | AT35: 177.167 | AU35: 196.937 | AV35: 214.782 | AW35: 786.809 | AX35: 223.079 | AY35: 252.352 | AZ35: 227.165 | BA35: 245.529 | BB35: 948.125 | BC35: 258.041 | BD35: 236.629 | BE35: 216.497 | BF35: 243.114 | BG35: 954.281 | BH35: 252.416 | BI35: 253.403 | BJ35: 242.01 | BK35: 292.177 | BL35: 1040.006 | BM35: 235.761 | BN35: 238.758 | BO35: 216.224 | BP35: 242.979 | BQ35: 933.722 | BR35: 219.061 | BS35: 232.824 | BT35: 219.629 | BU35: 259.351 | BV35: 930.865 | BW35: 227.035 | BX35: 243.292 | BY35: =BT35*(1+BY36) -> 220.8057 | BZ35: =BU35*(1+BZ36) -> 254.36049 | CA35: =SUM(BW35,BX35,BY35,BZ35) -> 945.49319 | CB35: =CA35*(1+CB36) -> 978.58545 | CC35: =CB35*(1+CC36) -> 1017.7289 | CD35: =CC35*(1+CD36) -> 1058.438 | CE35: =CD35*(1+CE36) -> 1100.7755 | CF35: Historical: segment table of the earnings release (current 3-segment basis from FY2013 / Q1-14, per the Feb-2016 recast 8-K). Q3/Q4-26E: prior-year quarter × (1 + volume + price + acquisitions + FX). 2027E+: prior year × (1 + scenario levers IW_vol + IW_price (+ FX)). | CH35: =IFERROR((CE35/BV35)^(1/5)-1,"n/m") -> 0.034099706 | CI35: =IFERROR((BV35/AW35)^(1/5)-1,"n/m") -> 0.034197483 | CJ35: =IFERROR((BV35/X35)^(1/10)-1,"n/m") -> 0.057848333 | CK35: =IFERROR((BV35/C35)^(1/19)-1,"n/m") -> n/m | CN35: 2029E | CO35: =CP35+$CO$32 -> 0.045 | CP35: 0.025 | CQ35: =CP35+$CQ$32 -> 0.005
B36: Net sales y/y % | S36: =IF(AND(ISNUMBER(S35),ISNUMBER(N35)),IFERROR(S35/N35-1,""),"") -> -0.02070474 | T36: =IF(AND(ISNUMBER(T35),ISNUMBER(O35)),IFERROR(T35/O35-1,""),"") -> -0.18445959 | U36: =IF(AND(ISNUMBER(U35),ISNUMBER(P35)),IFERROR(U35/P35-1,""),"") -> -0.23525767 | V36: =IF(AND(ISNUMBER(V35),ISNUMBER(Q35)),IFERROR(V35/Q35-1,""),"") -> -0.23768482 | W36: =IF(AND(ISNUMBER(W35),ISNUMBER(R35)),IFERROR(W35/R35-1,""),"") -> -0.22837864 | X36: =IF(AND(ISNUMBER(X35),ISNUMBER(S35)),IFERROR(X35/S35-1,""),"") -> -0.22154195 | Y36: =IF(AND(ISNUMBER(Y35),ISNUMBER(T35)),IFERROR(Y35/T35-1,""),"") -> -0.10730572 | Z36: =IF(AND(ISNUMBER(Z35),ISNUMBER(U35)),IFERROR(Z35/U35-1,""),"") -> -0.064202019 | ... BX36: =IF(AND(ISNUMBER(BX35),ISNUMBER(BS35)),IFERROR(BX35/BS35-1,""),"") -> 0.044961001 | BY36: =BY37+BY38+BY39+BY40 -> 0.0053576923 | BZ36: =BZ37+BZ38+BZ39+BZ40 -> -0.019242308 | CA36: =IFERROR(CA35/BV35-1,"") -> 0.015714623 | CB36: =CB37+CB38+CB39+CB40 -> 0.035 | CC36: =CC37+CC38+CC39+CC40 -> 0.04 | CD36: =CD37+CD38+CD39+CD40 -> 0.04 | CE36: =CE37+CE38+CE39+CE40 -> 0.04 | CN36: 2030E | CO36: =CP36+$CO$32 -> 0.045 | CP36: 0.025 | CQ36: =CP36+$CQ$32 -> 0.005
B37: Volume % (company "change in net sales due to volume") | Y37: -0.071 | Z37: -0.036 | AA37: -0.049 | AB37: 0.104 | AC37: -0.016 | AD37: 0.027 | AE37: 0.033 | AF37: 0.067 | AG37: -0.025 | AH37: 0.025 | AI37: -0.037 | AJ37: -0.045 | AK37: -0.105 | AL37: -0.137 | AM37: -0.092 | AN37: -0.072 | AO37: -0.097 | AP37: -0.062 | AQ37: -0.078 | AR37: -0.078 | AS37: -0.14 | AT37: -0.209 | AU37: -0.053 | AV37: -0.034 | AW37: -0.109 | AX37: 0.057 | AY37: 0.255 | AZ37: 0.038 | BA37: -0.008 | BB37: 0.079 | BC37: -0.005 | BD37: -0.067 | BE37: 0.024 | BF37: 0.014 | BG37: -0.01 | BH37: -0.057 | BI37: 0.038 | BJ37: 0.029 | BK37: 0.049 | BL37: 0.013 | BM37: -0.049 | BN37: -0.038 | BO37: -0.119 | BP37: -0.157 | BQ37: -0.093 | BR37: -0.058 | BS37: -0.068 | BT37: -0.042 | BU37: -0.036 | BV37: -0.051 | BW37: -0.099 | BX37: -0.047 | BY37: =$BX$37+BY139 -> -0.035242308 | BZ37: =$BX$37+BZ139 -> -0.035242308 | CA37: =IFERROR(CA42/BV35,"") -> -0.053114426 | CB37: =CHOOSE(MATCH($CF$2,{"Bull","Base","Bear"},0),$CO$33,$CP$33,$CQ$33) -> 0.02 | CC37: =CHOOSE(MATCH($CF$2,{"Bull","Base","Bear"},0),$CO$34,$CP$34,$CQ$34) -> 0.025 | CD37: =CHOOSE(MATCH($CF$2,{"Bull","Base","Bear"},0),$CO$35,$CP$35,$CQ$35) -> 0.025 | CE37: =CHOOSE(MATCH($CF$2,{"Bull","Base","Bear"},0),$CO$36,$CP$36,$CQ$36) -> 0.025 | CF37: Q3/Q4-26E: Q2/26 y/y volume + outlook calibration Δ (Group block). 2027E–2030E: scenario lever IW_vol (Bull/Base/Bear table →). | CN37: IW_price (International Welding price y/y) | CO37: 0.01 | CP37: Δ → | CQ37: -0.01 | CR37: Limited pricing power in Europe; 1H/26 +0.9%.
B38: Price % | Y38: -0.022 | Z38: -0.027 | AA38: -0.01 | AB38: -0.002 | AC38: -0.016 | AD38: 0.026 | AE38: 0.033 | AF38: 0.029 | AG38: 0.056 | AH38: 0.036 | AI38: 0.054 | AJ38: 0.055 | AK38: 0.052 | AL38: 0.038 | AM38: 0.048 | AN38: 0.026 | AO38: 0.012 | AP38: 0.003 | AQ38: -0.003 | AR38: 0.01 | AS38: -0.008 | AT38: -0.006 | AU38: 0 | AV38: 0.005 | AW38: -0.002 | AX38: 0.023 | AY38: 0.083 | AZ38: 0.108 | BA38: 0.139 | BB38: 0.09 | BC38: 0.234 | BD38: 0.186 | BE38: 0.138 | BF38: 0.117 | BG38: 0.168 | BH38: 0.058 | BI38: 0.004 | BJ38: 0.002 | BK38: -0.007 | BL38: 0.015 | BM38: -0.016 | BN38: -0.012 | BO38: -0.006 | BP38: 0 | BQ38: -0.008 | BR38: 0.004 | BS38: 0.004 | BT38: 0 | BU38: 0.005 | BV38: 0.003 | BW38: 0.001 | BX38: 0.016 | BY38: =$BX$38 -> 0.016 | BZ38: =$BX$38 -> 0.016 | CA38: =IFERROR(CA43/BV35,"") -> 0.012608359 | CB38: =CHOOSE(MATCH($CF$2,{"Bull","Base","Bear"},0),$CO$38,$CP$38,$CQ$38) -> 0.015 | CC38: =CHOOSE(MATCH($CF$2,{"Bull","Base","Bear"},0),$CO$39,$CP$39,$CQ$39) -> 0.015 | CD38: =CHOOSE(MATCH($CF$2,{"Bull","Base","Bear"},0),$CO$40,$CP$40,$CQ$40) -> 0.015 | CE38: =CHOOSE(MATCH($CF$2,{"Bull","Base","Bear"},0),$CO$41,$CP$41,$CQ$41) -> 0.015 | CF38: Q3/Q4-26E: Q2/26 y/y price held (carry-over of the 2025–26 increases; HPG includes metals pass-through). 2027E+: scenario lever. Note: 2016 Americas Welding as published includes Venezuela hyperinflationary price (+15.4%) offset by FX (−17.7%); ex-Venezuela price −0.5%, FX −1.0%. | CN38: 2027E | CO38: =CP38+$CO$37 -> 0.025 | CP38: 0.015 | CQ38: =CP38+$CQ$37 -> 0.005
B39: Acquisitions % | Y39: 0.025 | Z39: 0.026 | AA39: 0.011 | AB39: 0 | AC39: 0.016 | AD39: 0 | AE39: 0 | AF39: 0.515 | AG39: 0.857 | AH39: 0.342 | AI39: 0.799 | AJ39: 0.681 | AK39: 0.143 | AL39: 0 | AM39: 0.314 | AN39: 0 | AO39: 0 | AP39: 0.083 | AQ39: 0.09 | AR39: 0.04 | AS39: 0.084 | AT39: 0.072 | AU39: 0 | AV39: 0 | AW39: 0.039 | AX39: 0 | AY39: 0.02 | AZ39: 0.017 | BA39: 0.082 | BB39: 0.031 | BC39: 0.079 | BD39: 0 | BE39: 0 | BF39: 0 | BG39: 0.019 | BH39: 0.029 | BI39: 0.025 | BJ39: 0.049 | BK39: 0.124 | BL39: 0.057 | BM39: 0 | BN39: 0 | BO39: 0.004 | BP39: 0.002 | BQ39: 0.002 | BR39: 0.003 | BS39: 0.001 | BT39: 0.037 | BU39: 0.047 | BV39: 0.022 | BW39: 0.072 | BX39: 0.07 | BY39: 0.0246 | BZ39: 0 | CA39: =IFERROR(CA44/BV35,"") -> 0.040166805 | CB39: 0 | CC39: 0 | CD39: 0 | CE39: 0 | CF39: Alloy Steel (Australia; ~$48m sales; 100% consolidated from 1-Aug-2025) anniversaries on 1-Aug-2026: Q3/26E = one month (Q2/26 acquisition sales $16.2m ÷ 3 ÷ Q3/25 IW sales = 2.5%); Q4/26E 0%. | CN39: 2028E | CO39: =CP39+$CO$37 -> 0.025 | CP39: 0.015 | CQ39: =CP39+$CQ$37 -> 0.005
B40: Foreign exchange % | Y40: -0.039 | Z40: -0.027 | AA40: -0.019 | AB40: -0.025 | AC40: -0.028 | AD40: -0.016 | AE40: -0.001 | AF40: 0.043 | AG40: 0.072 | AH40: 0.025 | AI40: 0.102 | AJ40: 0.029 | AK40: -0.031 | AL40: -0.043 | AM40: 0 | AN40: -0.072 | AO40: -0.043 | AP40: -0.044 | AQ40: -0.012 | AR40: -0.044 | AS40: -0.029 | AT40: -0.022 | AU40: 0.012 | AV40: 0.011 | AW40: -0.007 | AX40: 0.047 | AY40: 0.067 | AZ40: -0.009 | BA40: -0.069 | BB40: 0.006 | BC40: -0.152 | BD40: -0.181 | BE40: -0.21 | BF40: -0.14 | BG40: -0.17 | BH40: -0.051 | BI40: 0.003 | BJ40: 0.038 | BK40: 0.036 | BL40: 0.005 | BM40: -0.001 | BN40: -0.008 | BO40: 0.014 | BP40: -0.013 | BQ40: -0.003 | BR40: -0.02 | BS40: 0.038 | BT40: 0.021 | BU40: 0.051 | BV40: 0.023 | BW40: 0.062 | BX40: 0.006 | BY40: 0 | BZ40: 0 | CA40: =IFERROR(CA45/BV35,"") -> 0.016053885 | CB40: =CHOOSE(MATCH($CF$2,{"Bull","Base","Bear"},0),$CO$53,$CP$53,$CQ$53) -> 0 | CC40: =CHOOSE(MATCH($CF$2,{"Bull","Base","Bear"},0),$CO$54,$CP$54,$CQ$54) -> 0 | CD40: =CHOOSE(MATCH($CF$2,{"Bull","Base","Bear"},0),$CO$55,$CP$55,$CQ$55) -> 0 | CE40: =CHOOSE(MATCH($CF$2,{"Bull","Base","Bear"},0),$CO$56,$CP$56,$CQ$56) -> 0 | CF40: Q3/Q4-26E: FX input (spot-rate translation vs prior-year quarter). 2027E+: International Welding FX lever; Americas & Harris 0%. | CN40: 2029E | CO40: =CP40+$CO$37 -> 0.025 | CP40: 0.015 | CQ40: =CP40+$CQ$37 -> 0.005
B41: Organic growth % (volume + price) | Y41: =Y37+Y38 -> -0.093 | Z41: =Z37+Z38 -> -0.063 | AA41: =AA37+AA38 -> -0.059 | AB41: =AB37+AB38 -> 0.102 | AC41: =AC37+AC38 -> -0.032 | AD41: =AD37+AD38 -> 0.053 | AE41: =AE37+AE38 -> 0.066 | AF41: =AF37+AF38 -> 0.096 | ... CE41: =CE37+CE38 -> 0.04 | CN41: 2030E | CO41: =CP41+$CO$37 -> 0.025 | CP41: 0.015 | CQ41: =CP41+$CQ$37 -> 0.005
B42: Δ Net sales — volume ($) | Y42: -9.822 | Z42: -5.112 | AA42: -6.322 | AB42: 12.627 | AC42: -8.629 | AD42: 3.347 | AE42: 4.377 | AF42: 7.988 | AG42: -3.209 | AH42: 12.503 | AI42: -4.737 | AJ42: -6.369 | AK42: -20.659 | AL42: -35.198 | AM42: -66.963 | AN42: -17.917 | AO42: -23.55 | AP42: -12.966 | AQ42: -17.076 | AR42: -71.509 | AS42: -30.507 | AT42: -44.452 | AU42: -10.964 | AV42: -7.341 | AW42: -93.264 | AX42: 11.25 | AY42: 45.095 | AZ42: 7.452 | BA42: -1.764 | BB42: 62.033 | BC42: -1.024 | BD42: -16.862 | BE42: 5.538 | BF42: 3.329 | BG42: -9.019 | BH42: -14.657 | BI42: 9.006 | BJ42: 6.296 | BK42: 11.874 | BL42: 12.519 | BM42: -12.272 | BN42: -9.557 | BO42: -28.899 | BP42: -45.93 | BQ42: -96.658 | BR42: -13.648 | BS42: -16.172 | BT42: -9.174 | BU42: -8.635 | BV42: -47.629 | BW42: -21.631 | BX42: -10.931 | BY42: =BT35*BY37 -> -7.7402328 | BZ42: =BU35*BZ37 -> -9.1401277 | CA42: =SUM(BW42,BX42,BY42,BZ42) -> -49.442361 | CB42: =CA35*CB37 -> 18.909864 | CC42: =CB35*CC37 -> 24.464636 | CD42: =CC35*CD37 -> 25.443222 | CE42: =CD35*CE37 -> 26.460951 | CN42: HPG_vol (Harris Products volume y/y) | CO42: 0.02 | CP42: Δ → | CQ42: -0.02 | CR42: HVAC/R, retail & specialty gas equipment; 1H/26 volume −4.9% against metals-driven price.
B43: Δ Net sales — price ($) | Y43: -3.105 | Z43: -3.883 | AA43: -1.255 | AB43: -0.185 | AC43: -8.428 | AD43: 3.199 | AE43: 4.423 | AF43: 3.446 | AG43: 7.259 | AH43: 18.327 | AI43: 7.019 | AJ43: 7.772 | AK43: 10.36 | AL43: 9.626 | AM43: 34.777 | AN43: 6.475 | AO43: 2.837 | AP43: 0.607 | AQ43: -0.76 | AR43: 9.159 | AS43: -1.691 | AT43: -1.28 | AU43: 0.07 | AV43: 1.101 | AW43: -1.8 | AX43: 4.62 | AY43: 14.712 | AZ43: 21.205 | BA43: 29.92 | BB43: 70.457 | BC43: 52.19 | BD43: 46.813 | BE43: 31.43 | BF43: 28.697 | BG43: 159.13 | BH43: 14.869 | BI43: 0.999 | BJ43: 0.477 | BK43: -1.654 | BL43: 14.691 | BM43: -4.01 | BN43: -3.149 | BO43: -1.349 | BP43: 0.095 | BQ43: -8.413 | BR43: 0.828 | BS43: 0.852 | BT43: 0.093 | BU43: 1.289 | BV43: 3.062 | BW43: 0.297 | BX43: 3.776 | BY43: =BT35*BY38 -> 3.514064 | BZ43: =BU35*BZ38 -> 4.149616 | CA43: =SUM(BW43,BX43,BY43,BZ43) -> 11.73668 | CB43: =CA35*CB38 -> 14.182398 | CC43: =CB35*CC38 -> 14.678782 | CD43: =CC35*CD38 -> 15.265933 | CE43: =CD35*CE38 -> 15.87657 | CN43: 2027E | CO43: =CP43+$CO$42 -> 0.05 | CP43: 0.03 | CQ43: =CP43+$CQ$42 -> 0.01
B44: Δ Net sales — acquisitions ($) | Y44: 3.465 | Z44: 3.702 | AA44: 1.454 | AB44: 0 | AC44: 8.622 | AD44: 0 | AE44: 0 | AF44: 61.52 | AG44: 111.91 | AH44: 173.43 | AI44: 102.946 | AJ44: 96.318 | AK44: 28.334 | AL44: 0 | AM44: 227.598 | AN44: 0 | AO44: 0 | AP44: 17.413 | AQ44: 19.648 | AR44: 37.061 | AS44: 18.302 | AT44: 15.219 | AU44: 0 | AV44: 0 | AW44: 33.521 | AX44: 0 | AY44: 3.585 | AZ44: 3.371 | BA44: 17.517 | BB44: 24.473 | BC44: 17.632 | BD44: 0 | BE44: 0 | BF44: 0 | BG44: 17.632 | BH44: 7.356 | BI44: 6.009 | BJ44: 10.564 | BK44: 30.149 | BL44: 54.078 | BM44: 0 | BN44: 0.057 | BO44: 1.064 | BP44: 0.539 | BQ44: 1.66 | BR44: 0.815 | BS44: 0.315 | BT44: 7.868 | BU44: 11.119 | BV44: 20.117 | BW44: 15.794 | BX44: 16.193 | BY44: =BT35*BY39 -> 5.4028734 | BZ44: =BU35*BZ39 -> 0 | CA44: =SUM(BW44,BX44,BY44,BZ44) -> 37.389873 | CB44: =CA35*CB39 -> 0 | CC44: =CB35*CC39 -> 0 | CD44: =CC35*CD39 -> 0 | CE44: =CD35*CE39 -> 0 | CN44: 2028E | CO44: =CP44+$CO$42 -> 0.05 | CP44: 0.03 | CQ44: =CP44+$CQ$42 -> 0.01
B45: Δ Net sales — foreign exchange ($) | Y45: -5.48 | Z45: -3.819 | AA45: -2.385 | AB45: -3.051 | AC45: -14.736 | AD45: -1.963 | AE45: -0.117 | AF45: 5.099 | AG45: 9.456 | AH45: 12.475 | AI45: 13.204 | AJ45: 4.154 | AK45: -6.03 | AL45: -10.993 | AM45: 0.335 | AN45: -17.792 | AO45: -10.354 | AP45: -9.298 | AQ45: -2.662 | AR45: -40.106 | AS45: -6.267 | AT45: -4.626 | AU45: 2.453 | AV45: 2.416 | AW45: -6.024 | AX45: 9.286 | AY45: 11.793 | AZ45: -1.8 | BA45: -14.926 | BB45: 4.353 | BC45: -33.836 | BD45: -45.674 | BE45: -47.636 | BF45: -34.441 | BG45: -161.587 | BH45: -13.193 | BI45: 0.76 | BJ45: 8.176 | BK45: 8.694 | BL45: 4.437 | BM45: -0.373 | BN45: -1.996 | BO45: 3.398 | BP45: -3.902 | BQ45: -2.873 | BR45: -4.695 | BS45: 9.071 | BT45: 4.618 | BU45: 12.599 | BV45: 21.593 | BW45: 13.514 | BX45: 1.43 | BY45: =BT35*BY40 -> 0 | BZ45: =BU35*BZ40 -> 0 | CA45: =SUM(BW45,BX45,BY45,BZ45) -> 14.944 | CB45: =CA35*CB40 -> 0 | CC45: =CB35*CC40 -> 0 | CD45: =CC35*CD40 -> 0 | CE45: =CD35*CE40 -> 0 | CN45: 2029E | CO45: =CP45+$CO$42 -> 0.05 | CP45: 0.03 | CQ45: =CP45+$CQ$42 -> 0.01
B46: Inter-segment sales | N46: 22.668 | O46: 5.988 | P46: 6.08 | Q46: 4.715 | R46: 4.825 | S46: 21.608 | T46: 5.027 | U46: 5.311 | V46: 5.4 | W46: 3.009 | X46: 18.747 | Y46: 4.426 | Z46: 3.841 | AA46: 3.688 | AB46: 4.02 | AC46: 15.975 | AD46: 4.285 | AE46: 5.478 | AF46: 5.451 | AG46: 3.646 | AH46: 18.86 | AI46: 4.509 | AJ46: 5.497 | AK46: 3.663 | AL46: 4.907 | AM46: 18.576 | AN46: 4.209 | AO46: 4.188 | AP46: 4.441 | AQ46: 4.853 | AR46: 17.691 | AS46: 4.483 | AT46: 4.286 | AU46: 4.898 | AV46: 4.827 | AW46: 18.494 | AX46: 4.285 | AY46: 6.897 | AZ46: 7.078 | BA46: 8.071 | BB46: 26.331 | BC46: 6.228 | BD46: 9.527 | BE46: 9.994 | BF46: 5.754 | BG46: 31.503 | BH46: 6.753 | BI46: 8.292 | BJ46: 4.896 | BK46: 11.557 | BL46: 31.498 | BM46: 8.408 | BN46: 8.849 | BO46: 7.371 | BP46: 11.233 | BQ46: 35.861 | BR46: 6.832 | BS46: 7.641 | BT46: 9.83 | BU46: 5.857 | BV46: 30.16 | BW46: 5.807 | BX46: 7.564 | BY46: =BY35*BT46/BT35 -> 9.8826661 | BZ46: =BZ35*BU46/BU35 -> 5.7442978 | CA46: =SUM(BW46,BX46,BY46,BZ46) -> 28.997964 | CB46: =CB35*CA46/CA35 -> 30.012893 | CC46: =CC35*CB46/CB35 -> 31.213408 | CD46: =CD35*CC46/CC35 -> 32.461945 | CE46: =CE35*CD46/CD35 -> 33.760422 | CF46: Forecast: prior-year inter-segment sales ratio to external net sales. | CN46: 2030E | CO46: =CP46+$CO$42 -> 0.05 | CP46: 0.03 | CQ46: =CP46+$CQ$42 -> 0.01
B47: Total segment sales (incl. inter-segment) | N47: =N35+N(N46) -> 718.499 | O47: =O35+N(O46) -> 176.73 | P47: =P35+N(P46) -> 191.668 | Q47: =Q35+N(Q46) -> 172.719 | R47: =R35+N(R46) -> 161.915 | S47: =S35+N(S46) -> 703.032 | T47: =T35+N(T46) -> 144.274 | U47: =U35+N(U46) -> 147.238 | ... BX47: =BX35+N(BX46) -> 250.856 | BY47: =BY35+BY46 -> 230.68837 | BZ47: =BZ35+BZ46 -> 260.10479 | CA47: =CA35+CA46 -> 974.49116 | CB47: =CB35+CB46 -> 1008.5983 | CC47: =CC35+CC46 -> 1048.9423 | CD47: =CD35+CD46 -> 1090.9 | CE47: =CE35+CE46 -> 1134.536 | CN47: HPG_price (Harris Products price y/y, incl. metals pass-through) | CO47: 0.015 | CP47: Δ → | CQ47: -0.015 | CR47: Silver / copper alloy pass-through drove +37.5% price in 1H/26; Base assumes normalised low-single-digit price from 2027 (metals flat).
B48: Adjusted EBIT (segment profit, company definition) | N48: 38.037 | O48: 8.314 | P48: 15.328 | Q48: 14.729 | R48: 10.349 | S48: 48.72 | T48: 10.934 | U48: 11.017 | V48: 9.268 | W48: 3.292 | X48: 34.511 | Y48: 6.233 | Z48: 9.67 | AA48: 5.796 | AB48: 7.447 | AC48: 29.146 | AD48: 9.605 | AE48: 9.496 | AF48: 10.612 | AG48: 12.008 | AH48: 41.721 | AI48: 14.973 | AJ48: 16.276 | AK48: 10.721 | AL48: 12.303 | AM48: 54.273 | AN48: 13.337 | AO48: 15.178 | AP48: 10.184 | AQ48: 11.582 | AR48: 50.281 | AS48: 6.615 | AT48: 9.682 | AU48: 13.432 | AV48: 15.25 | AW48: 44.979 | AX48: 18.816 | AY48: 29.997 | AZ48: 29.032 | BA48: 28.363 | BB48: 106.208 | BC48: 37.087 | BD48: 35.009 | BE48: 25.225 | BF48: 22.836 | BG48: 120.157 | BH48: 29.598 | BI48: 33.774 | BJ48: 30.239 | BK48: 42.888 | BL48: 136.497 | BM48: 27.776 | BN48: 25.709 | BO48: 20.101 | BP48: 32.53 | BQ48: 106.117 | BR48: 23.012 | BS48: 30.55 | BT48: 25.821 | BU48: 31.202 | BV48: 110.585 | BW48: 22.662 | BX48: 26.595 | BY48: =BY47*BY50 -> 24.204721 | BZ48: =BZ47*BZ50 -> 28.62324 | CA48: =SUM(BW48,BX48,BY48,BZ48) -> 102.08496 | CB48: =CA48+CB54 -> 111.30352 | CC48: =CB48+CC54 -> 122.31261 | CD48: =CC48+CD54 -> 133.76206 | CE48: =CD48+CE54 -> 145.66948 | CF48: 2027E+: prior-year adjusted EBIT + Δ bridge (price $ × fall-through + volume $ × incremental margin + (acquisitions + FX) $ × prior-year margin). 2026E = sum of quarters. | CH48: =IFERROR((CE48/BV48)^(1/5)-1,"n/m") -> 0.056658064 | CI48: =IFERROR((BV48/AW48)^(1/5)-1,"n/m") -> 0.19711889 | CJ48: =IFERROR((BV48/X48)^(1/10)-1,"n/m") -> 0.12350205 | CK48: =IFERROR((BV48/C48)^(1/19)-1,"n/m") -> n/m | CN48: 2027E | CO48: =CP48+$CO$47 -> 0.045 | CP48: 0.03 | CQ48: =CP48+$CQ$47 -> 0.015
B49: Adjusted EBIT margin before outlook calibration % (Q3/Q4-26E helper) | BY49: =BT50+($BW$48+$BX$48)/($BW$47+$BX$47)-($BR$48+$BS$48)/($BR$47+$BS$47) -> 0.099512429 | BZ49: =BU50+($BW$48+$BX$48)/($BW$47+$BX$47)-($BR$48+$BS$48)/($BR$47+$BS$47) -> 0.10463357 | CF49: Q3/Q4-26E: prior-year quarter margin + (1H/26 − 1H/25 margin drift). | CN49: 2028E | CO49: =CP49+$CO$47 -> 0.04 | CP49: 0.025 | CQ49: =CP49+$CQ$47 -> 0.01
B50: Adjusted EBIT margin % (on total segment sales) | N50: =IF(AND(ISNUMBER(N48),ISNUMBER(N47)),IFERROR(N48/N47,""),"") -> 0.052939531 | O50: =IF(AND(ISNUMBER(O48),ISNUMBER(O47)),IFERROR(O48/O47,""),"") -> 0.047043513 | P50: =IF(AND(ISNUMBER(P48),ISNUMBER(P47)),IFERROR(P48/P47,""),"") -> 0.079971618 | Q50: =IF(AND(ISNUMBER(Q48),ISNUMBER(Q47)),IFERROR(Q48/Q47,""),"") -> 0.085277242 | R50: =IF(AND(ISNUMBER(R48),ISNUMBER(R47)),IFERROR(R48/R47,""),"") -> 0.063916252 | S50: =IF(AND(ISNUMBER(S48),ISNUMBER(S47)),IFERROR(S48/S47,""),"") -> 0.069299833 | T50: =IF(AND(ISNUMBER(T48),ISNUMBER(T47)),IFERROR(T48/T47,""),"") -> 0.075786351 | U50: =IF(AND(ISNUMBER(U48),ISNUMBER(U47)),IFERROR(U48/U47,""),"") -> 0.074824434 | ... BX50: =IF(AND(ISNUMBER(BX48),ISNUMBER(BX47)),IFERROR(BX48/BX47,""),"") -> 0.106017 | BY50: =BY49+BY144 -> 0.10492389 | BZ50: =BZ49+BZ144 -> 0.11004503 | CA50: =IFERROR(CA48/CA47,"") -> 0.1047572 | CB50: =IFERROR(CB48/CB47,"") -> 0.11035465 | CC50: =IFERROR(CC48/CC47,"") -> 0.11660566 | CD50: =IFERROR(CD48/CD47,"") -> 0.12261624 | CE50: =IFERROR(CE48/CE47,"") -> 0.12839565 | CF50: Q3/Q4-26E: margin before calibration + outlook calibration Δ. 2027E+: output of the Δ adjusted EBIT bridge. | CH50: =IFERROR(AVERAGE(CA50,CB50,CC50,CD50,CE50),"n/m") -> 0.11654588 | CI50: =IFERROR(AVERAGE(AW50,BB50,BG50,BL50,BQ50,BV50),"n/m") -> 0.10643991 | CJ50: =IFERROR(AVERAGE(X50,AC50,AH50,AM50,AR50,AW50,BB50,BG50,BL50,BQ50,BV50),"n/m") -> 0.084439527 | CK50: =IFERROR(AVERAGE(C50,D50,E50,F50,G50,H50,I50,N50,S50,X50,AC50,AH50,AM50,AR50,AW50,BB50,BG50,BL50,BQ50,BV50),"n/m") -> 0.080851859 | CN50: 2029E | CO50: =CP50+$CO$47 -> 0.04 | CP50: 0.025 | CQ50: =CP50+$CQ$47 -> 0.01
B51: Incremental adjusted EBIT margin (Δ adj. EBIT / Δ total sales) | S51: =IFERROR((S48-N48)/(S47-N47),"") -> -0.69069632 | T51: =IFERROR((T48-O48)/(T47-O47),"") -> -0.080724673 | U51: =IFERROR((U48-P48)/(U47-P47),"") -> 0.097029034 | V51: =IFERROR((V48-Q48)/(V47-Q47),"") -> 0.13914439 | W51: =IFERROR((W48-R48)/(W47-R47),"") -> 0.18722806 | X51: =IFERROR((X48-S48)/(X47-S47),"") -> 0.092371201 | Y51: =IFERROR((Y48-T48)/(Y47-T47),"") -> 0.30245126 | Z51: =IFERROR((Z48-U48)/(Z47-U47),"") -> 0.12729163 | ... CA51: =IFERROR((CA48-BV48)/(CA47-BV47),"") -> -0.6312149 | CB51: =IFERROR((CB48-CA48)/(CB47-CA47),"") -> 0.27028197 | CC51: =IFERROR((CC48-CB48)/(CC47-CB47),"") -> 0.27288083 | CD51: =IFERROR((CD48-CC48)/(CD47-CC47),"") -> 0.27288083 | CE51: =IFERROR((CE48-CD48)/(CE47-CD47),"") -> 0.27288083 | CN51: 2030E | CO51: =CP51+$CO$47 -> 0.04 | CP51: 0.025 | CQ51: =CP51+$CQ$47 -> 0.01
B52: Price fall-through to adjusted EBIT % | CB52: 0.25 | CC52: 0.25 | CD52: 0.25 | CE52: 0.25 | CF52: Input: share of price-driven sales growth that falls through to adjusted EBIT (price/cost broadly neutral — LECO prices to offset inflation; HPG price is largely metals pass-through). | CN52: IW_fx (International Welding FX translation y/y) | CO52: 0.01 | CP52: Δ → | CQ52: -0.01 | CR52: Base 0% (constant currency); Bull assumes a weaker USD, Bear a stronger USD.
B53: Volume incremental adjusted EBIT margin % | CB53: 0.3 | CC53: 0.3 | CD53: 0.3 | CE53: 0.3 | CF53: Input: incremental margin on volume-driven sales (company targets mid-20s–30s% incrementals through the cycle). | CN53: 2027E | CO53: =CP53+$CO$52 -> 0.01 | CP53: 0 | CQ53: =CP53+$CQ$52 -> -0.01
B54: Δ Adjusted EBIT (price × fall-through + volume × incremental + (acq. + FX) × prior margin) | CB54: =CB43*CB52+CB42*CB53+(CB44+CB45)*CA50 -> 9.2185586 | CC54: =CC43*CC52+CC42*CC53+(CC44+CC45)*CB50 -> 11.009086 | CD54: =CD43*CD52+CD42*CD53+(CD44+CD45)*CC50 -> 11.44945 | CE54: =CE43*CE52+CE42*CE53+(CE44+CE45)*CD50 -> 11.907428 | CN54: 2028E | CO54: =CP54+$CO$52 -> 0.01 | CP54: 0 | CQ54: =CP54+$CQ$52 -> -0.01
B55: Special items (pre-tax, charged to the segment) | N55: 8.116 | O55: 0.03 | P55: 0.857 | Q55: 28.486 | R55: 0.166 | S55: 29.539 | T55: 0 | U55: 1.239 | V55: 14.944 | W55: 0.488 | X55: 16.671 | Y55: 0 | Z55: 0 | AA55: 0 | AB55: 0 | AC55: 0 | AD55: 0 | AE55: 0 | AF55: 2.314 | AG55: 7.762 | AH55: 10.076 | AI55: 10.175 | AJ55: 11.542 | AK55: 2.636 | AL55: 0.932 | AM55: 25.285 | AN55: 2.199 | AO55: -2.627 | AP55: -4.497 | AQ55: 7.081 | AR55: 2.156 | AS55: 6.137 | AT55: 0.565 | AU55: 2.401 | AV55: 10.301 | AW55: 19.404 | AX55: 4.609 | AY55: 2.471 | AZ55: 6.615 | BA55: 1.539 | BB55: 15.234 | BC55: 1.347 | BD55: 0.154 | BE55: 8.364 | BF55: 1.816 | BG55: 11.681 | BH55: 0.302 | BI55: 3.255 | BJ55: 7.87 | BK55: -21.147 | BL55: -9.721 | BM55: 3.069 | BN55: 31.234 | BO55: 2.926 | BP55: 0.517 | BQ55: 37.747 | BR55: 1.412 | BS55: 1.551 | BT55: 2.762 | BU55: 5.717 | BV55: 11.442 | BW55: 1.772 | BX55: 2.282 | CF55: Historical disclosure only; forecast special items are modelled at the consolidated level. | CN55: 2029E | CO55: =CP55+$CO$52 -> 0.01 | CP55: 0 | CQ55: =CP55+$CQ$52 -> -0.01
B56: EBIT (GAAP, as reported in the segment table) | N56: 29.921 | O56: 8.284 | P56: 14.471 | Q56: -13.757 | R56: 10.183 | S56: 19.181 | T56: 10.934 | U56: 9.778 | V56: -5.676 | W56: 2.804 | X56: 17.84 | Y56: 6.233 | Z56: 9.67 | AA56: 5.796 | AB56: 7.447 | AC56: 29.146 | AD56: 9.605 | AE56: 9.496 | AF56: 8.298 | AG56: 4.246 | AH56: 31.645 | AI56: 4.798 | AJ56: 4.734 | AK56: 8.085 | AL56: 11.371 | AM56: 28.988 | AN56: 11.138 | AO56: 17.805 | AP56: 14.681 | AQ56: 4.501 | AR56: 48.125 | AS56: 0.478 | AT56: 9.117 | AU56: 11.031 | AV56: 4.949 | AW56: 25.575 | AX56: 14.207 | AY56: 27.526 | AZ56: 22.417 | BA56: 26.824 | BB56: 90.974 | BC56: 35.74 | BD56: 34.855 | BE56: 16.861 | BF56: 21.02 | BG56: 108.476 | BH56: 29.296 | BI56: 30.519 | BJ56: 22.369 | BK56: 64.035 | BL56: 146.218 | BM56: 24.707 | BN56: -5.525 | BO56: 17.175 | BP56: 32.013 | BQ56: 68.37 | BR56: 21.6 | BS56: 28.999 | BT56: 23.059 | BU56: 25.485 | BV56: 99.143 | BW56: 20.89 | BX56: 24.313 | CN56: 2030E | CO56: =CP56+$CO$52 -> 0.01 | CP56: 0 | CQ56: =CP56+$CQ$52 -> -0.01
CN57: MA_spend (bolt-on acquisitions, $m) | CO57: 150 | CP57: Δ → | CQ57: -150 | CR57: LECO deployed $33–436m p.a. on acquisitions in 2016–25 (avg ~$150m); RISE strategy prioritises automation and growth bolt-ons.
B58: The Harris Products Group (brazing & soldering alloys, oxy-fuel cutting, gas regulators; US retail channel) | CF58: HARRIS PRODUCTS GROUP — modelling logic | CN58: 2027E | CO58: =CP58+$CO$57 -> 350 | CP58: 200 | CQ58: =CP58+$CQ$57 -> 50
B59: Net sales (external customers) | N59: 308.177 | O59: 72.471 | P59: 77.419 | Q59: 78.383 | R59: 65.957 | S59: 294.23 | T59: 69.816 | U59: 71.812 | V59: 62.922 | W59: 59.431 | X59: 263.981 | Y59: 67.409 | Z59: 71.231 | AA59: 70.562 | AB59: 63.141 | AC59: 272.343 | AD59: 68.685 | AE59: 80.213 | AF59: 73.585 | AG59: 68.145 | AH59: 290.628 | AI59: 75.604 | AJ59: 84.164 | AK59: 73.467 | AL59: 69.154 | AM59: 302.389 | AN59: 83.369 | AO59: 88.095 | AP59: 81.884 | AQ59: 79.802 | AR59: 333.15 | AS59: 85.533 | AT59: 80.331 | AU59: 100.416 | AV59: 92.441 | AW59: 358.721 | AX59: 108.7 | AY59: 116.634 | AZ59: 117.781 | BA59: 118.459 | BB59: 461.574 | BC59: 133.352 | BD59: 137.301 | BE59: 133.115 | BF59: 114.228 | BG59: 517.996 | BH59: 128.282 | BI59: 130.196 | BJ59: 125.976 | BK59: 111.63 | BL59: 496.084 | BM59: 121.337 | BN59: 133.989 | BO59: 130.509 | BP59: 124.266 | BQ59: 510.101 | BR59: 132.22 | BS59: 159.119 | BT59: 149.804 | BU59: 137.434 | BV59: 578.577 | BW59: 188.174 | BX59: 201.933 | BY59: =BT59*(1+BY60) -> 190.51439 | BZ59: =BU59*(1+BZ60) -> 174.78275 | CA59: =SUM(BW59,BX59,BY59,BZ59) -> 755.40414 | CB59: =CA59*(1+CB60) -> 800.72838 | CC59: =CB59*(1+CC60) -> 844.76845 | CD59: =CC59*(1+CD60) -> 891.23071 | CE59: =CD59*(1+CE60) -> 940.2484 | CF59: Historical: segment table of the earnings release (current 3-segment basis from FY2013 / Q1-14, per the Feb-2016 recast 8-K). Q3/Q4-26E: prior-year quarter × (1 + volume + price + acquisitions + FX). 2027E+: prior year × (1 + scenario levers HPG_vol + HPG_price (+ FX)). | CH59: =IFERROR((CE59/BV59)^(1/5)-1,"n/m") -> 0.10198653 | CI59: =IFERROR((BV59/AW59)^(1/5)-1,"n/m") -> 0.10032473 | CJ59: =IFERROR((BV59/X59)^(1/10)-1,"n/m") -> 0.081630312 | CK59: =IFERROR((BV59/C59)^(1/19)-1,"n/m") -> n/m | CN59: 2028E | CO59: =CP59+$CO$57 -> 400 | CP59: 250 | CQ59: =CP59+$CQ$57 -> 100
B60: Net sales y/y % | S60: =IF(AND(ISNUMBER(S59),ISNUMBER(N59)),IFERROR(S59/N59-1,""),"") -> -0.04525646 | T60: =IF(AND(ISNUMBER(T59),ISNUMBER(O59)),IFERROR(T59/O59-1,""),"") -> -0.036635344 | U60: =IF(AND(ISNUMBER(U59),ISNUMBER(P59)),IFERROR(U59/P59-1,""),"") -> -0.072424082 | V60: =IF(AND(ISNUMBER(V59),ISNUMBER(Q59)),IFERROR(V59/Q59-1,""),"") -> -0.1972494 | W60: =IF(AND(ISNUMBER(W59),ISNUMBER(R59)),IFERROR(W59/R59-1,""),"") -> -0.098943251 | X60: =IF(AND(ISNUMBER(X59),ISNUMBER(S59)),IFERROR(X59/S59-1,""),"") -> -0.10280733 | Y60: =IF(AND(ISNUMBER(Y59),ISNUMBER(T59)),IFERROR(Y59/T59-1,""),"") -> -0.034476338 | Z60: =IF(AND(ISNUMBER(Z59),ISNUMBER(U59)),IFERROR(Z59/U59-1,""),"") -> -0.0080905698 | ... BX60: =IF(AND(ISNUMBER(BX59),ISNUMBER(BS59)),IFERROR(BX59/BS59-1,""),"") -> 0.26906906 | BY60: =BY61+BY62+BY63+BY64 -> 0.27175769 | BZ60: =BZ61+BZ62+BZ63+BZ64 -> 0.27175769 | CA60: =IFERROR(CA59/BV59-1,"") -> 0.30562421 | CB60: =CB61+CB62+CB63+CB64 -> 0.06 | CC60: =CC61+CC62+CC63+CC64 -> 0.055 | CD60: =CD61+CD62+CD63+CD64 -> 0.055 | CE60: =CE61+CE62+CE63+CE64 -> 0.055 | CN60: 2029E | CO60: =CP60+$CO$57 -> 400 | CP60: 250 | CQ60: =CP60+$CQ$57 -> 100
B61: Volume % (company "change in net sales due to volume") | Y61: 0.02 | Z61: 0.01 | AA61: 0.083 | AB61: 0.039 | AC61: 0.037 | AD61: -0.029 | AE61: 0.111 | AF61: 0.072 | AG61: 0.069 | AH61: 0.056 | AI61: 0.093 | AJ61: 0.035 | AK61: 0.002 | AL61: 0.046 | AM61: 0.043 | AN61: 0.039 | AO61: -0.005 | AP61: 0.047 | AQ61: 0.057 | AR61: 0.033 | AS61: 0.034 | AT61: -0.078 | AU61: 0.128 | AV61: 0.074 | AW61: 0.037 | AX61: 0.136 | AY61: 0.229 | AZ61: -0.013 | BA61: 0.054 | BB61: 0.094 | BC61: 0.029 | BD61: -0.005 | BE61: 0.111 | BF61: -0.024 | BG61: 0.028 | BH61: -0.038 | BI61: -0.064 | BJ61: -0.112 | BK61: -0.069 | BL61: -0.071 | BM61: -0.069 | BN61: -0.019 | BO61: -0.03 | BP61: 0.027 | BQ61: -0.024 | BR61: 0.006 | BS61: 0.11 | BT61: 0.023 | BU61: -0.089 | BV61: 0.015 | BW61: -0.01 | BX61: -0.082 | BY61: =$BX$61+BY139 -> -0.070242308 | BZ61: =$BX$61+BZ139 -> -0.070242308 | CA61: =IFERROR(CA66/BV59,"") -> -0.05968827 | CB61: =CHOOSE(MATCH($CF$2,{"Bull","Base","Bear"},0),$CO$43,$CP$43,$CQ$43) -> 0.03 | CC61: =CHOOSE(MATCH($CF$2,{"Bull","Base","Bear"},0),$CO$44,$CP$44,$CQ$44) -> 0.03 | CD61: =CHOOSE(MATCH($CF$2,{"Bull","Base","Bear"},0),$CO$45,$CP$45,$CQ$45) -> 0.03 | CE61: =CHOOSE(MATCH($CF$2,{"Bull","Base","Bear"},0),$CO$46,$CP$46,$CQ$46) -> 0.03 | CF61: Q3/Q4-26E: Q2/26 y/y volume + outlook calibration Δ (Group block). 2027E–2030E: scenario lever HPG_vol (Bull/Base/Bear table →). | CN61: 2030E | CO61: =CP61+$CO$57 -> 400 | CP61: 250 | CQ61: =CP61+$CQ$57 -> 100
B62: Price % | Y62: -0.034 | Z62: -0.011 | AA62: 0.035 | AB62: 0.015 | AC62: 0 | AD62: 0.04 | AE62: 0.01 | AF62: -0.037 | AG62: -0.001 | AH62: 0.003 | AI62: -0.007 | AJ62: 0.015 | AK62: 0.01 | AL62: -0.015 | AM62: 0.001 | AN62: 0.006 | AO62: -0.008 | AP62: 0.01 | AQ62: 0.033 | AR62: 0.009 | AS62: 0.004 | AT62: 0.003 | AU62: 0.116 | AV62: 0.106 | AW62: 0.056 | AX62: 0.145 | AY62: 0.211 | AZ62: 0.086 | BA62: 0.07 | BB62: 0.124 | BC62: 0.062 | BD62: 0.041 | BE62: -0.005 | BF62: -0.001 | BG62: 0.024 | BH62: 0.004 | BI62: 0.01 | BJ62: 0.047 | BK62: 0.036 | BL62: 0.024 | BM62: 0.011 | BN62: 0.052 | BO62: 0.071 | BP62: 0.098 | BQ62: 0.057 | BR62: 0.095 | BS62: 0.074 | BT62: 0.118 | BU62: 0.178 | BV62: 0.116 | BW62: 0.414 | BX62: 0.342 | BY62: =$BX$62 -> 0.342 | BZ62: =$BX$62 -> 0.342 | CA62: =IFERROR(CA67/BV59,"") -> 0.35858908 | CB62: =CHOOSE(MATCH($CF$2,{"Bull","Base","Bear"},0),$CO$48,$CP$48,$CQ$48) -> 0.03 | CC62: =CHOOSE(MATCH($CF$2,{"Bull","Base","Bear"},0),$CO$49,$CP$49,$CQ$49) -> 0.025 | CD62: =CHOOSE(MATCH($CF$2,{"Bull","Base","Bear"},0),$CO$50,$CP$50,$CQ$50) -> 0.025 | CE62: =CHOOSE(MATCH($CF$2,{"Bull","Base","Bear"},0),$CO$51,$CP$51,$CQ$51) -> 0.025 | CF62: Q3/Q4-26E: Q2/26 y/y price held (carry-over of the 2025–26 increases; HPG includes metals pass-through). 2027E+: scenario lever. Note: 2016 Americas Welding as published includes Venezuela hyperinflationary price (+15.4%) offset by FX (−17.7%); ex-Venezuela price −0.5%, FX −1.0%.
B63: Acquisitions % | Y63: 0 | Z63: 0 | AA63: 0 | AB63: 0 | AC63: 0 | AD63: 0 | AE63: 0 | AF63: 0 | AG63: 0 | AH63: 0 | AI63: 0 | AJ63: 0 | AK63: 0 | AL63: 0 | AM63: 0 | AN63: 0.076 | AO63: 0.067 | AP63: 0.065 | AQ63: 0.07 | AR63: 0.07 | AS63: 0 | AT63: 0 | AU63: 0 | AV63: 0 | AW63: 0 | AX63: 0 | AY63: 0 | AZ63: 0.098 | BA63: 0.163 | BB63: 0.07 | BC63: 0.142 | BD63: 0.158 | BE63: 0.047 | BF63: 0 | BG63: 0.085 | BH63: 0 | BI63: 0 | BJ63: 0 | BK63: 0 | BL63: 0 | BM63: 0 | BN63: 0 | BO63: 0 | BP63: 0 | BQ63: 0 | BR63: 0 | BS63: 0 | BT63: 0 | BU63: 0 | BV63: 0 | BW63: 0 | BX63: 0 | BY63: 0 | BZ63: 0 | CA63: =IFERROR(CA68/BV59,"") -> 0 | CB63: 0 | CC63: 0 | CD63: 0 | CE63: 0 | CF63: No Harris acquisitions in the last 12 months.
B64: Foreign exchange % | Y64: -0.02 | Z64: -0.007 | AA64: 0.003 | AB64: 0.008 | AC64: -0.005 | AD64: 0.008 | AE64: 0.005 | AF64: 0.008 | AG64: 0.011 | AH64: 0.008 | AI64: 0.015 | AJ64: -0.001 | AK64: -0.014 | AL64: -0.016 | AM64: -0.004 | AN64: -0.019 | AO64: -0.008 | AP64: -0.007 | AQ64: -0.006 | AR64: -0.01 | AS64: -0.012 | AT64: -0.013 | AU64: -0.017 | AV64: -0.022 | AW64: -0.016 | AX64: -0.011 | AY64: 0.011 | AZ64: 0.002 | BA64: -0.005 | BB64: -0.001 | BC64: -0.006 | BD64: -0.017 | BE64: -0.023 | BF64: -0.011 | BG64: -0.014 | BH64: -0.005 | BI64: 0.002 | BJ64: 0.012 | BK64: 0.01 | BL64: 0.005 | BM64: 0.004 | BN64: -0.003 | BO64: -0.005 | BP64: -0.012 | BQ64: -0.004 | BR64: -0.012 | BS64: 0.004 | BT64: 0.007 | BU64: 0.017 | BV64: 0.003 | BW64: 0.019 | BX64: 0.009 | BY64: 0 | BZ64: 0 | CA64: =IFERROR(CA69/BV59,"") -> 0.006723392 | CB64: 0 | CC64: 0 | CD64: 0 | CE64: 0 | CF64: Q3/Q4-26E: FX input (spot-rate translation vs prior-year quarter). 2027E+: International Welding FX lever; Americas & Harris 0%.
B65: Organic growth % (volume + price) | Y65: =Y61+Y62 -> -0.014 | Z65: =Z61+Z62 -> -0.001 | AA65: =AA61+AA62 -> 0.118 | AB65: =AB61+AB62 -> 0.054 | AC65: =AC61+AC62 -> 0.037 | AD65: =AD61+AD62 -> 0.011 | AE65: =AE61+AE62 -> 0.121 | AF65: =AF61+AF62 -> 0.035 | ... CE65: =CE61+CE62 -> 0.055
B66: Δ Net sales — volume ($) | Y66: 1.39 | Z66: 0.736 | AA66: 5.235 | AB66: 2.322 | AC66: 9.683 | AD66: -1.984 | AE66: 7.916 | AF66: 5.05 | AG66: 4.38 | AH66: 15.362 | AI66: 6.38 | AJ66: 2.823 | AK66: 0.174 | AL66: 3.12 | AM66: 12.497 | AN66: 2.961 | AO66: -0.417 | AP66: 3.429 | AQ66: 3.925 | AR66: 9.898 | AS66: 2.8 | AT66: -6.891 | AU66: 10.461 | AV66: 5.872 | AW66: 12.242 | AX66: 11.641 | AY66: 18.421 | AZ66: -1.287 | BA66: 4.997 | BB66: 33.772 | BC66: 3.142 | BD66: -0.574 | BE66: 13.089 | BF66: -2.837 | BG66: 12.82 | BH66: -5.017 | BI66: -8.853 | BJ66: -14.919 | BK66: -7.904 | BL66: -36.693 | BM66: -8.856 | BN66: -2.523 | BO66: -3.727 | BP66: 3.057 | BQ66: -12.049 | BR66: 0.787 | BS66: 14.671 | BT66: 2.998 | BU66: -11.029 | BV66: 7.427 | BW66: -1.375 | BX66: -12.983 | BY66: =BT59*BY61 -> -10.522579 | BZ66: =BU59*BZ61 -> -9.6536813 | CA66: =SUM(BW66,BX66,BY66,BZ66) -> -34.53426 | CB66: =CA59*CB61 -> 22.662124 | CC66: =CB59*CC61 -> 24.021852 | CD66: =CC59*CD61 -> 25.343053 | CE66: =CD59*CE61 -> 26.736921
B67: Δ Net sales — price ($) | Y67: -2.404 | Z67: -0.809 | AA67: 2.226 | AB67: 0.902 | AC67: -0.085 | AD67: 2.718 | AE67: 0.692 | AF67: -2.604 | AG67: -0.064 | AH67: 0.742 | AI67: -0.496 | AJ67: 1.174 | AK67: 0.753 | AL67: -1.053 | AM67: 0.378 | AN67: 0.45 | AO67: -0.635 | AP67: 0.761 | AQ67: 2.276 | AR67: 2.852 | AS67: 0.323 | AT67: 0.278 | AU67: 9.472 | AV67: 8.498 | AW67: 18.571 | AX67: 12.443 | AY67: 16.979 | AZ67: 8.609 | BA67: 6.428 | BB67: 44.459 | BC67: 6.723 | BD67: 4.82 | BE67: -0.579 | BF67: -0.097 | BG67: 10.867 | BH67: 0.565 | BI67: 1.408 | BJ67: 6.231 | BK67: 4.126 | BL67: 12.33 | BM67: 1.443 | BN67: 6.728 | BO67: 8.898 | BP67: 10.972 | BQ67: 28.041 | BR67: 11.534 | BS67: 9.858 | BT67: 15.432 | BU67: 22.171 | BV67: 58.995 | BW67: 54.782 | BX67: 54.454 | BY67: =BT59*BY62 -> 51.232968 | BZ67: =BU59*BZ62 -> 47.002428 | CA67: =SUM(BW67,BX67,BY67,BZ67) -> 207.4714 | CB67: =CA59*CB62 -> 22.662124 | CC67: =CB59*CC62 -> 20.01821 | CD67: =CC59*CD62 -> 21.119211 | CE67: =CD59*CE62 -> 22.280768
B68: Δ Net sales — acquisitions ($) | Y68: 0 | Z68: 0 | AA68: 0 | AB68: 0 | AC68: 0 | AD68: 0 | AE68: 0 | AF68: 0 | AG68: 0 | AH68: 0 | AI68: 0 | AJ68: 0 | AK68: 0 | AL68: 0 | AM68: 0 | AN68: 5.774 | AO68: 5.656 | AP68: 4.766 | AQ68: 4.836 | AR68: 21.032 | AS68: 0 | AT68: 0 | AU68: 0 | AV68: 0 | AW68: 0 | AX68: 0 | AY68: 0 | AZ68: 9.88 | BA68: 15.073 | BB68: 24.953 | BC68: 15.452 | BD68: 18.407 | BE68: 5.552 | BF68: 0 | BG68: 39.411 | BH68: 0 | BI68: 0 | BJ68: 0 | BK68: 0 | BL68: 0 | BM68: 0 | BN68: 0 | BO68: 0 | BP68: 0 | BQ68: 0 | BR68: 0 | BS68: 0 | BT68: 0 | BU68: 0 | BV68: 0 | BW68: 0 | BX68: 0 | BY68: =BT59*BY63 -> 0 | BZ68: =BU59*BZ63 -> 0 | CA68: =SUM(BW68,BX68,BY68,BZ68) -> 0 | CB68: =CA59*CB63 -> 0 | CC68: =CB59*CC63 -> 0 | CD68: =CC59*CD63 -> 0 | CE68: =CD59*CE63 -> 0
B69: Δ Net sales — foreign exchange ($) | Y69: -1.393 | Z69: -0.508 | AA69: 0.179 | AB69: 0.486 | AC69: -1.236 | AD69: 0.542 | AE69: 0.374 | AF69: 0.577 | AG69: 0.688 | AH69: 2.181 | AI69: 1.035 | AJ69: -0.046 | AK69: -1.045 | AL69: -1.058 | AM69: -1.114 | AN69: -1.42 | AO69: -0.673 | AP69: -0.539 | AQ69: -0.389 | AR69: -3.021 | AS69: -0.959 | AT69: -1.151 | AU69: -1.401 | AV69: -1.731 | AW69: -5.242 | AX69: -0.917 | AY69: 0.903 | AZ69: 0.163 | BA69: -0.48 | BB69: -0.331 | BC69: -0.665 | BD69: -1.986 | BE69: -2.728 | BF69: -1.297 | BG69: -6.676 | BH69: -0.618 | BI69: 0.34 | BJ69: 1.549 | BK69: 1.18 | BL69: 2.451 | BM69: 0.468 | BN69: -0.412 | BO69: -0.638 | BP69: -1.393 | BQ69: -1.975 | BR69: -1.438 | BS69: 0.601 | BT69: 0.865 | BU69: 2.026 | BV69: 2.054 | BW69: 2.547 | BX69: 1.343 | BY69: =BT59*BY64 -> 0 | BZ69: =BU59*BZ64 -> 0 | CA69: =SUM(BW69,BX69,BY69,BZ69) -> 3.89 | CB69: =CA59*CB64 -> 0 | CC69: =CB59*CC64 -> 0 | CD69: =CC59*CD64 -> 0 | CE69: =CD59*CE64 -> 0
B70: Inter-segment sales | N70: 9.605 | O70: 2.118 | P70: 2.262 | Q70: 2.009 | R70: 1.821 | S70: 8.21 | T70: 2.011 | U70: 2.716 | V70: 2.307 | W70: 2.278 | X70: 9.312 | Y70: 2.303 | Z70: 2.824 | AA70: 1.856 | AB70: 1.726 | AC70: 8.709 | AD70: 2.3 | AE70: 2.399 | AF70: 2.064 | AG70: 1.427 | AH70: 8.19 | AI70: 1.907 | AJ70: 2.003 | AK70: 1.537 | AL70: 1.522 | AM70: 6.969 | AN70: 1.867 | AO70: 2.113 | AP70: 1.857 | AQ70: 1.65 | AR70: 7.487 | AS70: 1.725 | AT70: 1.753 | AU70: 1.898 | AV70: 1.658 | AW70: 7.034 | AX70: 2.147 | AY70: 2.284 | AZ70: 1.945 | BA70: 1.72 | BB70: 8.096 | BC70: 3.062 | BD70: 2.866 | BE70: 2.642 | BF70: 2.47 | BG70: 11.04 | BH70: 2.897 | BI70: 2.867 | BJ70: 2.299 | BK70: 2.578 | BL70: 10.641 | BM70: 3.093 | BN70: 3.272 | BO70: 3.155 | BP70: 2.801 | BQ70: 12.321 | BR70: 3.984 | BS70: 5.11 | BT70: 3.441 | BU70: 2.549 | BV70: 15.084 | BW70: 4.664 | BX70: 4.972 | BY70: =BY59*BT70/BT59 -> 4.3761182 | BZ70: =BZ59*BU70/BU59 -> 3.2417104 | CA70: =SUM(BW70,BX70,BY70,BZ70) -> 17.253829 | CB70: =CB59*CA70/CA59 -> 18.289058 | CC70: =CC59*CB70/CB59 -> 19.294956 | CD70: =CD59*CC70/CC59 -> 20.356179 | CE70: =CE59*CD70/CD59 -> 21.475769 | CF70: Forecast: prior-year inter-segment sales ratio to external net sales.
B71: Total segment sales (incl. inter-segment) | N71: =N59+N(N70) -> 317.782 | O71: =O59+N(O70) -> 74.589 | P71: =P59+N(P70) -> 79.681 | Q71: =Q59+N(Q70) -> 80.392 | R71: =R59+N(R70) -> 67.778 | S71: =S59+N(S70) -> 302.44 | T71: =T59+N(T70) -> 71.827 | U71: =U59+N(U70) -> 74.528 | ... BX71: =BX59+N(BX70) -> 206.905 | BY71: =BY59+BY70 -> 194.89051 | BZ71: =BZ59+BZ70 -> 178.02446 | CA71: =CA59+CA70 -> 772.65796 | CB71: =CB59+CB70 -> 819.01744 | CC71: =CC59+CC70 -> 864.0634 | CD71: =CD59+CD70 -> 911.58689 | CE71: =CE59+CE70 -> 961.72417
B72: Adjusted EBIT (segment profit, company definition) | N72: 27.826 | O72: 6.058 | P72: 7.178 | Q72: 8.947 | R72: 6.38 | S72: 28.563 | T72: 7.549 | U72: 8.25 | V72: 6.422 | W72: 5.661 | X72: 27.882 | Y72: 7.711 | Z72: 9.284 | AA72: 8.757 | AB72: 6.628 | AC72: 32.38 | AD72: 8.46 | AE72: 9.787 | AF72: 9.244 | AG72: 8.951 | AH72: 36.442 | AI72: 9.225 | AJ72: 10.157 | AK72: 8.676 | AL72: 8.506 | AM72: 36.564 | AN72: 10.519 | AO72: 13.488 | AP72: 11.038 | AQ72: 10.656 | AR72: 45.701 | AS72: 12.492 | AT72: 11.713 | AU72: 17.587 | AV72: 13.362 | AW72: 55.154 | AX72: 18.697 | AY72: 18.212 | AZ72: 15.98 | BA72: 15.558 | BB72: 68.447 | BC72: 19.598 | BD72: 17.922 | BE72: 14.432 | BF72: 12.056 | BG72: 64.008 | BH72: 18.983 | BI72: 19.51 | BJ72: 20.405 | BK72: 15.246 | BL72: 74.144 | BM72: 19.878 | BN72: 24.923 | BO72: 21.959 | BP72: 21.567 | BQ72: 88.328 | BR72: 24.329 | BS72: 31.884 | BT72: 28.078 | BU72: 23.317 | BV72: 107.608 | BW72: 40.809 | BX72: 42.253 | BY72: =BY71*BY74 -> 40.79376 | BZ72: =BZ71*BZ74 -> 34.29883 | CA72: =SUM(BW72,BX72,BY72,BZ72) -> 158.15459 | CB72: =CA72+CB78 -> 169.48565 | CC72: =CB72+CC78 -> 180.69585 | CD72: =CC72+CD78 -> 192.52261 | CE72: =CD72+CE78 -> 204.99984 | CF72: 2027E+: prior-year adjusted EBIT + Δ bridge (price $ × fall-through + volume $ × incremental margin + (acquisitions + FX) $ × prior-year margin). 2026E = sum of quarters. | CH72: =IFERROR((CE72/BV72)^(1/5)-1,"n/m") -> 0.13757959 | CI72: =IFERROR((BV72/AW72)^(1/5)-1,"n/m") -> 0.14301916 | CJ72: =IFERROR((BV72/X72)^(1/10)-1,"n/m") -> 0.14459558 | CK72: =IFERROR((BV72/C72)^(1/19)-1,"n/m") -> n/m
B73: Adjusted EBIT margin before outlook calibration % (Q3/Q4-26E helper) | BY73: =BT74+($BW$72+$BX$72)/($BW$71+$BX$71)-($BR$72+$BS$72)/($BR$71+$BS$71) -> 0.20390484 | BZ73: =BU74+($BW$72+$BX$72)/($BW$71+$BX$71)-($BR$72+$BS$72)/($BR$71+$BS$71) -> 0.18725212 | CF73: Q3/Q4-26E: prior-year quarter margin + (1H/26 − 1H/25 margin drift).
B74: Adjusted EBIT margin % (on total segment sales) | N74: =IF(AND(ISNUMBER(N72),ISNUMBER(N71)),IFERROR(N72/N71,""),"") -> 0.087563172 | O74: =IF(AND(ISNUMBER(O72),ISNUMBER(O71)),IFERROR(O72/O71,""),"") -> 0.08121841 | P74: =IF(AND(ISNUMBER(P72),ISNUMBER(P71)),IFERROR(P72/P71,""),"") -> 0.090084211 | Q74: =IF(AND(ISNUMBER(Q72),ISNUMBER(Q71)),IFERROR(Q72/Q71,""),"") -> 0.11129217 | R74: =IF(AND(ISNUMBER(R72),ISNUMBER(R71)),IFERROR(R72/R71,""),"") -> 0.094130839 | S74: =IF(AND(ISNUMBER(S72),ISNUMBER(S71)),IFERROR(S72/S71,""),"") -> 0.094441873 | T74: =IF(AND(ISNUMBER(T72),ISNUMBER(T71)),IFERROR(T72/T71,""),"") -> 0.10509975 | U74: =IF(AND(ISNUMBER(U72),ISNUMBER(U71)),IFERROR(U72/U71,""),"") -> 0.11069665 | ... BX74: =IF(AND(ISNUMBER(BX72),ISNUMBER(BX71)),IFERROR(BX72/BX71,""),"") -> 0.20421449 | BY74: =BY73+BY144 -> 0.2093163 | BZ74: =BZ73+BZ144 -> 0.19266358 | CA74: =IFERROR(CA72/CA71,"") -> 0.204689 | CB74: =IFERROR(CB72/CB71,"") -> 0.20693778 | CC74: =IFERROR(CC72/CC71,"") -> 0.20912337 | CD74: =IFERROR(CD72/CD71,"") -> 0.21119502 | CE74: =IFERROR(CE72/CE71,"") -> 0.21315866 | CF74: Q3/Q4-26E: margin before calibration + outlook calibration Δ. 2027E+: output of the Δ adjusted EBIT bridge. | CH74: =IFERROR(AVERAGE(CA74,CB74,CC74,CD74,CE74),"n/m") -> 0.20902077 | CI74: =IFERROR(AVERAGE(AW74,BB74,BG74,BL74,BQ74,BV74),"n/m") -> 0.15236246 | CJ74: =IFERROR(AVERAGE(X74,AC74,AH74,AM74,AR74,AW74,BB74,BG74,BL74,BQ74,BV74),"n/m") -> 0.13688341 | CK74: =IFERROR(AVERAGE(C74,D74,E74,F74,G74,H74,I74,N74,S74,X74,AC74,AH74,AM74,AR74,AW74,BB74,BG74,BL74,BQ74,BV74),"n/m") -> 0.12982481
B75: Incremental adjusted EBIT margin (Δ adj. EBIT / Δ total sales) | S75: =IFERROR((S72-N72)/(S71-N71),"") -> -0.048038065 | T75: =IFERROR((T72-O72)/(T71-O71),"") -> -0.53982621 | U75: =IFERROR((U72-P72)/(U71-P71),"") -> -0.20803415 | V75: =IFERROR((V72-Q72)/(V71-Q71),"") -> 0.16652377 | W75: =IFERROR((W72-R72)/(W71-R71),"") -> 0.11847092 | X75: =IFERROR((X72-S72)/(X71-S71),"") -> 0.023364326 | Y75: =IFERROR((Y72-T72)/(Y71-T71),"") -> -0.076595745 | Z75: =IFERROR((Z72-U72)/(Z71-U71),"") -> -2.1860465 | ... CA75: =IFERROR((CA72-BV72)/(CA71-BV71),"") -> 0.28238797 | CB75: =IFERROR((CB72-CA72)/(CB71-CA71),"") -> 0.24441738 | CC75: =IFERROR((CC72-CB72)/(CC71-CB71),"") -> 0.24886133 | CD75: =IFERROR((CD72-CC72)/(CD71-CC71),"") -> 0.24886133 | CE75: =IFERROR((CE72-CD72)/(CE71-CD71),"") -> 0.24886133
B76: Price fall-through to adjusted EBIT % | CB76: 0.2 | CC76: 0.2 | CD76: 0.2 | CE76: 0.2 | CF76: Input: share of price-driven sales growth that falls through to adjusted EBIT (price/cost broadly neutral — LECO prices to offset inflation; HPG price is largely metals pass-through).
B77: Volume incremental adjusted EBIT margin % | CB77: 0.3 | CC77: 0.3 | CD77: 0.3 | CE77: 0.3 | CF77: Input: incremental margin on volume-driven sales (company targets mid-20s–30s% incrementals through the cycle).
B78: Δ Adjusted EBIT (price × fall-through + volume × incremental + (acq. + FX) × prior margin) | CB78: =CB67*CB76+CB66*CB77+(CB68+CB69)*CA74 -> 11.331062 | CC78: =CC67*CC76+CC66*CC77+(CC68+CC69)*CB74 -> 11.210197 | CD78: =CD67*CD76+CD66*CD77+(CD68+CD69)*CC74 -> 11.826758 | CE78: =CE67*CE76+CE66*CE77+(CE68+CE69)*CD74 -> 12.47723
B79: Special items (pre-tax, charged to the segment) | N79: 0 | O79: 0 | P79: 0 | Q79: 0 | R79: 0 | S79: 0 | T79: 0 | U79: 0 | V79: 0 | W79: 0 | X79: 0 | Y79: 0 | Z79: 0 | AA79: 0 | AB79: 0 | AC79: 0 | AD79: 0 | AE79: 0 | AF79: 0 | AG79: 0 | AH79: 0 | AI79: 0 | AJ79: 0 | AK79: 0 | AL79: 0 | AM79: 0 | AN79: 0 | AO79: 0 | AP79: 0 | AQ79: 1.77 | AR79: 1.77 | AS79: 0 | AT79: 0 | AU79: 0 | AV79: 0 | AW79: 0 | AX79: 0 | AY79: 0 | AZ79: 0.547 | BA79: 3.238 | BB79: 3.785 | BC79: 0 | BD79: 0 | BE79: 0 | BF79: 0 | BG79: 0 | BH79: 0 | BI79: 0 | BJ79: 0 | BK79: 0 | BL79: 0 | BM79: 1.536 | BN79: -0.14 | BO79: 1.269 | BP79: 1.289 | BQ79: 3.955 | BR79: 0.178 | BS79: 0.086 | BT79: 0.316 | BU79: 0.488 | BV79: 1.068 | BW79: -0.182 | BX79: 0.187 | CF79: Historical disclosure only; forecast special items are modelled at the consolidated level.
B80: EBIT (GAAP, as reported in the segment table) | N80: 27.826 | O80: 6.058 | P80: 7.178 | Q80: 8.947 | R80: 6.38 | S80: 28.563 | T80: 7.549 | U80: 8.25 | V80: 6.422 | W80: 5.661 | X80: 27.882 | Y80: 7.711 | Z80: 9.284 | AA80: 8.757 | AB80: 6.628 | AC80: 32.38 | AD80: 8.46 | AE80: 9.787 | AF80: 9.244 | AG80: 8.951 | AH80: 36.442 | AI80: 9.225 | AJ80: 10.157 | AK80: 8.676 | AL80: 8.506 | AM80: 36.564 | AN80: 10.519 | AO80: 13.488 | AP80: 11.038 | AQ80: 8.886 | AR80: 43.931 | AS80: 12.492 | AT80: 11.713 | AU80: 17.587 | AV80: 13.362 | AW80: 55.154 | AX80: 18.697 | AY80: 18.212 | AZ80: 15.433 | BA80: 12.32 | BB80: 64.662 | BC80: 19.598 | BD80: 17.922 | BE80: 14.432 | BF80: 12.056 | BG80: 64.008 | BH80: 18.983 | BI80: 19.51 | BJ80: 20.405 | BK80: 15.246 | BL80: 74.144 | BM80: 18.342 | BN80: 25.063 | BO80: 20.69 | BP80: 20.278 | BQ80: 84.373 | BR80: 24.151 | BS80: 31.798 | BT80: 27.762 | BU80: 22.829 | BV80: 106.54 | BW80: 40.991 | BX80: 42.066
B82: Corporate / eliminations | CF82: CORPORATE & ELIMINATIONS
B83: Inter-segment eliminations | N83: -138.084 | O83: -36.323 | P83: -37.331 | Q83: -33.968 | R83: -32.72 | S83: -140.342 | T83: -30.061 | U83: -31.929 | V83: -33.278 | W83: -25.329 | X83: -120.597 | Y83: -30.56 | Z83: -30.121 | AA83: -27.93 | AB83: -29.685 | AC83: -118.296 | AD83: -29.045 | AE83: -35.251 | AF83: -33.061 | AG83: -27.075 | AH83: -124.432 | AI83: -33.002 | AJ83: -38.74 | AK83: -37.045 | AL83: -35.694 | AM83: -144.481 | AN83: -35.464 | AO83: -41.112 | AP83: -37.399 | AQ83: -34.545 | AR83: -148.52 | AS83: -30.991 | AT83: -33.532 | AU83: -36.164 | AV83: -34.219 | AW83: -134.906 | AX83: -39.18 | AY83: -48.946 | AZ83: -46.503 | BA83: -40.448 | BB83: -175.077 | BC83: -37.446 | BD83: -41.424 | BE83: -47.989 | BF83: -37.703 | BG83: -164.562 | BH83: -41.968 | BI83: -42.009 | BJ83: -36.07 | BK83: -49.628 | BL83: -169.675 | BM83: -41.479 | BN83: -49.921 | BO83: -41.371 | BP83: -51.168 | BQ83: -183.94 | BR83: -41.188 | BS83: -56.142 | BT83: -43.329 | BU83: -33.507 | BV83: -174.166 | BW83: -47.18 | BX83: -41.44 | BY83: =-(BY22+BY46+BY70) -> -47.916461 | BZ83: =-(BZ22+BZ46+BZ70) -> -37.093046 | CA83: =-(CA22+CA46+CA70) -> -173.62951 | CB83: =-(CB22+CB46+CB70) -> -183.32233 | CC83: =-(CC22+CC46+CC70) -> -192.95486 | CD83: =-(CD22+CD46+CD70) -> -202.38695 | CE83: =-(CE22+CE46+CE70) -> -212.28346
B84: Corporate / eliminations adjusted EBIT | N84: -5.948 | O84: 2.67 | P84: 0.785 | Q84: -0.302 | R84: 0.649 | S84: 3.802 | T84: 0.06 | U84: 0.634 | V84: -0.748 | W84: -0.221 | X84: -0.275 | Y84: 1.197 | Z84: -0.298 | AA84: 0.913 | AB84: -1.248 | AC84: 0.564 | AD84: 0.064 | AE84: -0.265 | AF84: 0.57 | AG84: -0.06 | AH84: 0.309 | AI84: -0.158 | AJ84: -3.186 | AK84: -1.099 | AL84: -4.444 | AM84: -8.887 | AN84: -3.042 | AO84: -3.969 | AP84: -1.632 | AQ84: -2.305 | AR84: -10.948 | AS84: -1.099 | AT84: -1.964 | AU84: -1.839 | AV84: -0.553 | AW84: -5.455 | AX84: -1.456 | AY84: -3.888 | AZ84: -4.704 | BA84: -2.355 | BB84: -12.403 | BC84: -4.801 | BD84: -3.984 | BE84: -1.685 | BF84: 0.437 | BG84: -10.033 | BH84: -9.374 | BI84: -2.183 | BJ84: -2.952 | BK84: -2.997 | BL84: -17.536 | BM84: -10.078 | BN84: -6.264 | BO84: 4.503 | BP84: 0.812 | BQ84: -11.028 | BR84: -1.65 | BS84: -1.2 | BT84: 2.034 | BU84: 0.416 | BV84: -0.4 | BW84: -1.395 | BX84: -3.044 | BY84: =($BW$84+$BX$84)/2 -> -2.2195 | BZ84: =($BW$84+$BX$84)/2 -> -2.2195 | CA84: =SUM(BW84,BX84,BY84,BZ84) -> -8.878 | CB84: -8 | CC84: -8 | CD84: -8 | CE84: -8 | CF84: Q3/Q4-26E: 1H/26 run-rate. 2027E+: -8 p.a. input (unallocated corporate costs net of inter-segment profit eliminations).
B85: Corporate special items (pre-tax) | N85: 0 | O85: 0 | P85: 0 | Q85: 0 | R85: 0 | S85: 0 | T85: 0 | U85: 0 | V85: 0 | W85: 0 | X85: 0 | Y85: 0 | Z85: 34.348 | AA85: 0 | AB85: 0 | AC85: 34.348 | AD85: 3.615 | AE85: 4.498 | AF85: -48.312 | AG85: 5.551 | AH85: -34.648 | AI85: 1.907 | AJ85: 0.788 | AK85: 0.97 | AL85: 0.833 | AM85: 4.498 | AN85: 0.79 | AO85: 1.014 | AP85: 0 | AQ85: 0 | AR85: 1.804 | AS85: 0 | AT85: 0 | AU85: 0 | AV85: 0 | AW85: 0 | AX85: 1.113 | AY85: 0.81 | AZ85: 0 | BA85: 0 | BB85: 1.923 | BC85: 0 | BD85: 0 | BE85: 3.068 | BF85: 2.935 | BG85: 6.003 | BH85: 0 | BI85: 0 | BJ85: 0 | BK85: 0 | BL85: 0 | BM85: 1.762 | BN85: 2.286 | BO85: 0.61 | BP85: 2.491 | BQ85: 7.147 | BR85: 0.802 | BS85: 0.429 | BT85: 0.452 | BU85: 0.718 | BV85: 2.401 | BW85: 0.653 | BX85: 0.015
B86: Corporate / eliminations EBIT (GAAP) | N86: -5.948 | O86: 2.67 | P86: 0.785 | Q86: -0.302 | R86: 0.649 | S86: 3.802 | T86: 0.06 | U86: 0.634 | V86: -0.748 | W86: -0.221 | X86: -0.275 | Y86: 1.197 | Z86: -34.646 | AA86: 0.913 | AB86: -1.248 | AC86: -33.784 | AD86: -3.551 | AE86: -4.763 | AF86: 48.882 | AG86: -5.611 | AH86: 34.957 | AI86: -2.065 | AJ86: -3.974 | AK86: -2.069 | AL86: -5.277 | AM86: -13.385 | AN86: -3.832 | AO86: -4.983 | AP86: -1.632 | AQ86: -2.305 | AR86: -12.752 | AS86: -1.099 | AT86: -1.964 | AU86: -1.839 | AV86: -0.553 | AW86: -5.455 | AX86: -2.569 | AY86: -4.698 | AZ86: -4.704 | BA86: -2.355 | BB86: -14.326 | BC86: -4.801 | BD86: -3.984 | BE86: -4.753 | BF86: -2.498 | BG86: -16.036 | BH86: -9.374 | BI86: -2.183 | BJ86: -2.952 | BK86: -2.997 | BL86: -17.536 | BM86: -11.84 | BN86: -8.55 | BO86: 3.893 | BP86: -1.679 | BQ86: -18.175 | BR86: -2.452 | BS86: -1.629 | BT86: 1.582 | BU86: -0.302 | BV86: -2.801 | BW86: -2.048 | BX86: -3.059
B88: Legacy segments (memo; as originally reported — North America / Europe / Other Countries to 2008; five welding & Harris segments 2009–Q4/15) | CF88: LEGACY SEGMENTS — historical disclosure only (not forecast)
B89: North America (to 2008) / North America Welding (2009–Q4/15) — net sales | C89: 1305.472 | D89: 1401.393 | E89: 1451.333 | F89: 858.18 | G89: 1013.193 | H89: 1309.499 | I89: 1580.818 | J89: 419.554 | K89: 419.069 | L89: 404.113 | M89: 410.033 | N89: 1652.769 | O89: 401.906 | P89: 429.49 | Q89: 439.621 | R89: 429.907 | S89: 1700.924 | T89: 412.988 | U89: 415.075 | V89: 408.416 | W89: 373.878 | X89: 1610.357
B90: North America (to 2008) / North America Welding (2009–Q4/15) — EBIT as adjusted | C90: 172.613 | D90: 211.092 | E90: 226.025 | F90: 134.544 | G90: 162.192 | H90: 227.924 | I90: 293.07 | J90: 76.66 | K90: 82.777 | L90: 75.225 | M90: 83.845 | N90: 318.507 | O90: 71.364 | P90: 91.195 | Q90: 84.45 | R90: 88.456 | S90: 335.465 | T90: 71.184 | U90: 77.494 | V90: 79.743 | W90: 78.325 | X90: 306.746
B91: Europe (to 2008) / Europe Welding (2009–Q4/15) — net sales | C91: 372.308 | D91: 510.514 | E91: 576.945 | F91: 346.383 | G91: 359.925 | H91: 508.692 | I91: 452.227 | J91: 110.491 | K91: 108.661 | L91: 98.522 | M91: 111.874 | N91: 429.548 | O91: 105.406 | P91: 115.574 | Q91: 107.507 | R91: 97.288 | S91: 425.775 | T91: 88.416 | U91: 90.903 | V91: 80.596 | W91: 76.909 | X91: 336.824
B92: Europe (to 2008) / Europe Welding (2009–Q4/15) — EBIT as adjusted | C92: 41.131 | D92: 62.982 | E92: 57.877 | F92: -2.196 | G92: 17.023 | H92: 36.171 | I92: 37.299 | J92: 10.701 | K92: 9.532 | L92: 7.881 | M92: 8.133 | N92: 36.247 | O92: 9.292 | P92: 14.899 | Q92: 15.221 | R92: 9.41 | S92: 48.822 | T92: 8.748 | U92: 9.481 | V92: 8.337 | W92: 4.751 | X92: 31.317
B93: Other Countries (to 2008) — net sales | C93: 294.135 | D93: 368.877 | E93: 450.853
B94: Other Countries (to 2008) — EBIT as adjusted | C94: 25.851 | D94: 18.578 | E94: 38.173
B95: Asia Pacific Welding (2009–Q4/15) — net sales | F95: 208.28 | G95: 324.092 | H95: 376.276 | I95: 324.482 | J95: 70.039 | K95: 69.239 | L95: 63.834 | M95: 63.17 | N95: 266.282 | O95: 61.286 | P95: 66.997 | Q95: 57.404 | R95: 58.113 | S95: 243.8 | T95: 49.25 | U95: 49.043 | V95: 45.505 | W95: 42.817 | X95: 186.615
B96: Asia Pacific Welding (2009–Q4/15) — EBIT as adjusted | F96: -18.37 | G96: 1.752 | H96: 2.629 | I96: 7.247 | J96: 2.293 | K96: 0.653 | L96: -0.979 | M96: -0.152 | N96: 1.815 | O96: -0.64 | P96: 0.365 | Q96: -0.304 | R96: 1.9 | S96: 1.321 | T96: 3.128 | U96: 2.244 | V96: 2.006 | W96: 0.014 | X96: 7.392
B97: South America Welding (2009–Q4/15) — net sales | F97: 99.171 | G97: 117.419 | H97: 156.684 | I97: 161.483 | J97: 36.374 | K97: 44.503 | L97: 51.715 | M97: 63.303 | N97: 195.895 | O97: 43.993 | P97: 39.051 | Q97: 32.862 | R97: 32.689 | S97: 148.595 | T97: 37.43 | U97: 37.907 | V97: 47.727 | W97: 14.95 | X97: 138.014
B98: South America Welding (2009–Q4/15) — EBIT as adjusted | F98: 10.648 | G98: 7.554 | H98: 12.895 | I98: 18.301 | J98: 5.112 | K98: 11.065 | L98: 15.942 | M98: 25.187 | N98: 57.306 | O98: 11.765 | P98: 4.995 | Q98: -0.59 | R98: -0.217 | S98: 15.953 | T98: 3.15 | U98: 1.378 | V98: 1.845 | W98: -0.804 | X98: 5.569
B99: The Harris Products Group (separate segment 2009–Q4/15) — net sales | F99: 217.271 | G99: 255.543 | H99: 343.458 | I99: 334.357 | J99: 82.115 | K99: 85.96 | L99: 73.691 | M99: 66.411 | N99: 308.177 | O99: 72.471 | P99: 77.419 | Q99: 78.383 | R99: 65.957 | S99: 294.23 | T99: 69.816 | U99: 71.812 | V99: 62.922 | W99: 59.431 | X99: 263.981
B100: The Harris Products Group (separate segment 2009–Q4/15) — EBIT as adjusted | F100: 0.888 | G100: 12.311 | H100: 25.151 | I100: 29.477 | J100: 7.151 | K100: 7.343 | L100: 6.917 | M100: 6.415 | N100: 27.826 | O100: 6.058 | P100: 7.178 | Q100: 8.947 | R100: 6.38 | S100: 28.563 | T100: 7.549 | U100: 8.25 | V100: 6.422 | W100: 5.661 | X100: 27.882
B101: Corporate / eliminations (legacy basis) — net sales | C101: 0 | D101: 0 | E101: 0 | F101: 0 | G101: 0 | H101: 0 | I101: 0 | J101: 0 | K101: 0 | L101: 0 | M101: 0 | N101: 0 | O101: 0 | P101: 0 | Q101: 0 | R101: 0 | S101: 0 | T101: 0 | U101: 0 | V101: 0 | W101: 0 | X101: 0
B102: Corporate / eliminations (legacy basis) — EBIT as adjusted | C102: -2.674 | D102: -2.547 | E102: 0.415 | F102: -3.344 | G102: -6.675 | H102: 0.426 | I102: -4.886 | J102: -0.603 | K102: -1.538 | L102: -0.822 | M102: -1.387 | N102: -4.35 | O102: 2.891 | P102: 0.6 | Q102: -0.324 | R102: 1.049 | S102: 4.216 | T102: 0.199 | U102: 0.475 | V102: -0.646 | W102: -0.127 | X102: -0.099
...

Sheet Bull-Base-Bear
B2: Lincoln Electric (LECO) — Bull / Base / Bear Case P&L Summary | J2: Share price ($): | K2: =Model!$CA$424 -> 275.54
B3: Adjusted figures (company definitions: adjusted EBIT / adjusted net income / adjusted diluted EPS) · USD millions · Live panel linked to Model — toggle scenario via Model!CF2. Bull and Bear panels are value snapshots generated from the Model with the switch set to each case. Adjusted EBITDA is a model measure (adjusted EBIT + D&A). | J3: As of: | K3: =TODAY() -> 2026-10-07 00:00:00
B5: Scenario: | C5: =Model!$CF$2 -> Base | N5: Scenario: | O5: Bull | P5: Snapshot (values) — Model run with switch = Bull | Z5: Scenario: | AA5: Bear | AB5: Snapshot (values) — Model run with switch = Bear
B7: (USDm, except EPS and shares) | C7: 2025A | D7: 2026E | E7: 2027E | F7: 2028E | G7: 2029E | H7: 2030E | I7: 25-'30 CAGR | J7: LT Hist Avg | K7: LT Hist Min | L7: LT Hist Max | N7: (USDm, except EPS and shares) | O7: 2025A | P7: 2026E | Q7: 2027E | R7: 2028E | S7: 2029E | T7: 2030E | U7: 25-'30 CAGR | V7: LT Hist Avg | W7: LT Hist Min | X7: LT Hist Max | Z7: (USDm, except EPS and shares) | AA7: 2025A | AB7: 2026E | AC7: 2027E | AD7: 2028E | AE7: 2029E | AF7: 2030E | AG7: 25-'30 CAGR | AH7: LT Hist Avg | AI7: LT Hist Min | AJ7: LT Hist Max
B9: Net sales | C9: =Model!BV154 -> 4233.003 | D9: =Model!CA154 -> 4719.7983 | E9: =Model!CB154 -> 5029.3489 | F9: =Model!CC154 -> 5405.0343 | G9: =Model!CD154 -> 5795.1676 | H9: =Model!CE154 -> 6203.2911 | I9: =IFERROR((H9/C9)^(1/5)-1,"n/m") -> 0.079430581 | N9: Net sales | O9: 4233.003 | P9: 4783.2934 | Q9: 5290.7139 | R9: 5926.5111 | S9: 6602.4699 | T9: 7324.7147 | U9: 0.11590809 | Z9: Net sales | AA9: 4233.003 | AB9: 4656.3033 | AC9: 4772.1632 | AD9: 4902.6613 | AE9: 5034.2021 | AF9: 5169.4344 | AG9: 0.040779887
B10: Net sales y/y % | D10: =IFERROR(D9/C9-1,"") -> 0.115 | E10: =IFERROR(E9/D9-1,"") -> 0.06558555 | F10: =IFERROR(F9/E9-1,"") -> 0.074698617 | G10: =IFERROR(G9/F9-1,"") -> 0.07217961 | H10: =IFERROR(H9/G9-1,"") -> 0.070424806 | N10: Net sales y/y % | P10: 0.13 | Q10: 0.10608182 | R10: 0.1201723 | S10: 0.11405677 | T10: 0.1093901 | Z10: Net sales y/y % | AB10: 0.1 | AC10: 0.024882368 | AD10: 0.027345711 | AE10: 0.026830475 | AF10: 0.026862717
B11: Organic sales growth % (volume + price) | C11: =Model!BV252 -> 0.025 | D11: =Model!CA252 -> 0.099686788 | E11: =Model!CB252 -> 0.054991877 | F11: =Model!CC252 -> 0.051534585 | G11: =Model!CD252 -> 0.047358306 | H11: =Model!CE252 -> 0.04634847 | N11: Organic sales growth % (volume + price) | O11: 0.025 | P11: 0.11468679 | Q11: 0.085782614 | R11: 0.081459788 | S11: 0.075851804 | T11: 0.073657298 | Z11: Organic sales growth % (volume + price) | AA11: 0.025 | AB11: 0.084686788 | AC11: 0.024197879 | AD11: 0.021219819 | AE11: 0.017901905 | AF11: 0.017746009
B12: Adjusted EBIT (company definition) | C12: =Model!BV222 -> 752.632 | D12: =Model!CA222 -> 851.86284 | E12: =Model!CB222 -> 939.65903 | F12: =Model!CC222 -> 1036.9539 | G12: =Model!CD222 -> 1135.2148 | H12: =Model!CE222 -> 1238.132 | I12: =IFERROR((H12/C12)^(1/5)-1,"n/m") -> 0.10468092 | N12: Adjusted EBIT (company definition) | O12: 752.632 | P12: 875.29296 | Q12: 1016.4334 | R12: 1179.813 | S12: 1351.4855 | T12: 1535.9238 | U12: 0.15334012 | Z12: Adjusted EBIT (company definition) | AA12: 752.632 | AB12: 831.60747 | AC12: 867.33955 | AD12: 903.06978 | AE12: 936.15335 | AF12: 970.01102 | AG12: 0.052055855
B13: Adjusted EBIT margin % | C13: =IFERROR(C12/C9,"") -> 0.17780096 | D13: =IFERROR(D12/D9,"") -> 0.18048713 | E13: =IFERROR(E12/E9,"") -> 0.18683512 | F13: =IFERROR(F12/F9,"") -> 0.19184965 | G13: =IFERROR(G12/G9,"") -> 0.19588989 | H13: =IFERROR(H12/H9,"") -> 0.19959276 | J13: =IFERROR(AVERAGE(Model!C223,Model!D223,Model!E223,Model!F223,Model!G223,Model!H223,Model!I223,Model!N223,Model!S223,Model!X223,Model!AC223,Model!AH223,Model!AM223,Model!AR223,Model!AW223,Model!BB223,Model!BG223,Model!BL223,Model!BQ223,Model!BV223),"") -> 0.13919665 | K13: =IFERROR(MIN(Model!C223,Model!D223,Model!E223,Model!F223,Model!G223,Model!H223,Model!I223,Model!N223,Model!S223,Model!X223,Model!AC223,Model!AH223,Model!AM223,Model!AR223,Model!AW223,Model!BB223,Model!BG223,Model!BL223,Model!BQ223,Model!BV223),"") -> 0.070647695 | L13: =IFERROR(MAX(Model!C223,Model!D223,Model!E223,Model!F223,Model!G223,Model!H223,Model!I223,Model!N223,Model!S223,Model!X223,Model!AC223,Model!AH223,Model!AM223,Model!AR223,Model!AW223,Model!BB223,Model!BG223,Model!BL223,Model!BQ223,Model!BV223),"") -> 0.1780154 | N13: Adjusted EBIT margin % | O13: 0.17780096 | P13: 0.1829896 | Q13: 0.19211649 | R13: 0.19907378 | S13: 0.20469394 | T13: 0.2096906 | V13: 0.13919665 | W13: 0.070647695 | X13: 0.1780154 | Z13: Adjusted EBIT margin % | AA13: 0.17780096 | AB13: 0.17859822 | AC13: 0.18174977 | AD13: 0.18419991 | AE13: 0.18595864 | AF13: 0.18764355 | AH13: 0.13919665 | AI13: 0.070647695 | AJ13: 0.1780154
B15: Operating income (GAAP) | C15: =Model!BV162 -> 718.059 | D15: =Model!CA162 -> 838.58084 | E15: =Model!CB162 -> 918.65903 | F15: =Model!CC162 -> 1015.4539 | G15: =Model!CD162 -> 1113.7148 | H15: =Model!CE162 -> 1216.632 | I15: =IFERROR((H15/C15)^(1/5)-1,"n/m") -> 0.11121942 | N15: Operating income (GAAP) | O15: 718.059 | P15: 862.01096 | Q15: 993.93339 | R15: 1156.813 | S15: 1328.4855 | T15: 1512.9238 | U15: 0.16073047 | Z15: Operating income (GAAP) | AA15: 718.059 | AB15: 818.32547 | AC15: 846.33955 | AD15: 882.06978 | AE15: 915.15335 | AF15: 949.01102 | AG15: 0.057358413
B16: Operating income y/y % | D16: =IFERROR(D15/C15-1,"") -> 0.16784392 | E16: =IFERROR(E15/D15-1,"") -> 0.095492512 | F16: =IFERROR(F15/E15-1,"") -> 0.10536544 | G16: =IFERROR(G15/F15-1,"") -> 0.096765403 | H16: =IFERROR(H15/G15-1,"") -> 0.092408984 | N16: Operating income y/y % | P16: 0.20047372 | Q16: 0.15304032 | R16: 0.16387373 | S16: 0.14840133 | T16: 0.13883346 | Z16: Operating income y/y % | AB16: 0.13963542 | AC16: 0.034233424 | AD16: 0.042217367 | AE16: 0.037506754 | AF16: 0.036996715
B17: Operating margin (GAAP) % | C17: =IFERROR(C15/C9,"") -> 0.16963347 | D17: =IFERROR(D15/D9,"") -> 0.17767302 | E17: =IFERROR(E15/E9,"") -> 0.18265963 | F17: =IFERROR(F15/F9,"") -> 0.18787188 | G17: =IFERROR(G15/G9,"") -> 0.1921799 | H17: =IFERROR(H15/H9,"") -> 0.19612686 | J17: =IFERROR(AVERAGE(Model!C264,Model!D264,Model!E264,Model!F264,Model!G264,Model!H264,Model!I264,Model!N264,Model!S264,Model!X264,Model!AC264,Model!AH264,Model!AM264,Model!AR264,Model!AW264,Model!BB264,Model!BG264,Model!BL264,Model!BQ264,Model!BV264),"") -> 0.12583033 | K17: =IFERROR(MIN(Model!C264,Model!D264,Model!E264,Model!F264,Model!G264,Model!H264,Model!I264,Model!N264,Model!S264,Model!X264,Model!AC264,Model!AH264,Model!AM264,Model!AR264,Model!AW264,Model!BB264,Model!BG264,Model!BL264,Model!BQ264,Model!BV264),"") -> 0.053765574 | L17: =IFERROR(MAX(Model!C264,Model!D264,Model!E264,Model!F264,Model!G264,Model!H264,Model!I264,Model!N264,Model!S264,Model!X264,Model!AC264,Model!AH264,Model!AM264,Model!AR264,Model!AW264,Model!BB264,Model!BG264,Model!BL264,Model!BQ264,Model!BV264),"") -> 0.17125748 | N17: Operating margin (GAAP) % | O17: 0.16963347 | P17: 0.18021285 | Q17: 0.18786376 | R17: 0.19519291 | S17: 0.20121039 | T17: 0.20655054 | V17: 0.12583033 | W17: 0.053765574 | X17: 0.17125748 | Z17: Operating margin (GAAP) % | AA17: 0.16963347 | AB17: 0.17574574 | AC17: 0.17734925 | AD17: 0.17991652 | AE17: 0.18178717 | AF17: 0.18358121 | AH17: 0.12583033 | AI17: 0.053765574 | AJ17: 0.17125748
B19: Adjusted net income (attributable to Lincoln Electric) | C19: =Model!BV240 -> 551.331 | D19: =Model!CA240 -> 616.79554 | E19: =Model!CB240 -> 684.53279 | F19: =Model!CC240 -> 752.98508 | G19: =Model!CD240 -> 823.94264 | H19: =Model!CE240 -> 898.38767 | I19: =IFERROR((H19/C19)^(1/5)-1,"n/m") -> 0.10258041 | N19: Adjusted net income (attributable to Lincoln Electric) | O19: 551.331 | P19: 641.07607 | Q19: 742.39053 | R19: 848.16754 | S19: 970.65276 | T19: 1102.4268 | U19: 0.14864934 | Z19: Adjusted net income (attributable to Lincoln Electric) | AA19: 551.331 | AB19: 595.44644 | AC19: 629.73856 | AD19: 659.70549 | AE19: 684.43909 | AF19: 709.79468 | AG19: 0.051826397
B21: FDSO (m) | C21: =Model!BV182 -> 55.875 | D21: =Model!CA182 -> 55.0378 | E21: =Model!CB182 -> 54.025826 | F21: =Model!CC182 -> 53.043562 | G21: =Model!CD182 -> 52.109948 | H21: =Model!CE182 -> 51.04691 | I21: =IFERROR((H21/C21)^(1/5)-1,"n/m") -> -0.017912046 | N21: FDSO (m) | O21: 55.875 | P21: 55.010581 | Q21: 53.53954 | R21: 52.127954 | S21: 51.001888 | T21: 49.569621 | U21: -0.023663306 | Z21: FDSO (m) | AA21: 55.875 | AB21: 55.065019 | AC21: 54.427595 | AD21: 53.725732 | AE21: 52.843762 | AF21: 51.981826 | AG21: -0.014340758
B23: Adjusted EPS — Diluted ($) | C23: =Model!BV244 -> 9.8672215 | D23: =Model!CA244 -> 11.208023 | E23: =Model!CB244 -> 12.670473 | F23: =Model!CC244 -> 14.195598 | G23: =Model!CD244 -> 15.811619 | H23: =Model!CE244 -> 17.599257 | I23: =IFERROR((H23/C23)^(1/5)-1,"n/m") -> 0.12269009 | N23: Adjusted EPS — Diluted ($) | O23: 9.8672215 | P23: 11.656834 | Q23: 13.86621 | R23: 16.270877 | S23: 19.031702 | T23: 22.239968 | U23: 0.17648896 | Z23: Adjusted EPS — Diluted ($) | AA23: 9.8672215 | AB23: 10.813488 | AC23: 11.570207 | AD23: 12.279134 | AE23: 12.952126 | AF23: 13.65467 | AG23: 0.067129848
B24: EPS y/y % | D24: =IFERROR(D23/C23-1,"") -> 0.13588443 | E24: =IFERROR(E23/D23-1,"") -> 0.13048242 | F24: =IFERROR(F23/E23-1,"") -> 0.12036841 | G24: =IFERROR(G23/F23-1,"") -> 0.11383959 | H24: =IFERROR(H23/G23-1,"") -> 0.11305848 | N24: EPS y/y % | P24: 0.18136947 | Q24: 0.18953484 | R24: 0.17341918 | S24: 0.16967894 | T24: 0.16857478 | Z24: EPS y/y % | AB24: 0.095899998 | AC24: 0.069979215 | AD24: 0.061271767 | AE24: 0.054807772 | AF24: 0.05424157
B26: P / E (x) — assumed (adjusted EPS) | G26: 22 | H26: 22 | N26: P / E (x) — assumed (adjusted EPS) | S26: 25 | T26: 25 | Z26: P / E (x) — assumed (adjusted EPS) | AD26: 18 | AE26: 18 | AF26: 18
B27: Price Target ($) | G27: =G26*G23 -> 347.85562 | H27: =H26*H23 -> 387.18365 | N27: Price Target ($) | S27: =S26*S23 -> 475.79256 | T27: =T26*T23 -> 555.99919 | Z27: Price Target ($) | AD27: =AD26*AD23 -> 221.02442 | AE27: =AE26*AE23 -> 233.13828 | AF27: =AF26*AF23 -> 245.78406
B28: Upside / (Downside) vs current | G28: =IFERROR(G27/$K$2-1,"") -> 0.26245052 | H28: =IFERROR(H27/$K$2-1,"") -> 0.40518127 | N28: Upside / (Downside) vs current | S28: =IFERROR(S27/$K$2-1,"") -> 0.72676403 | T28: =IFERROR(T27/$K$2-1,"") -> 1.0178529 | Z28: Upside / (Downside) vs current | AD28: =IFERROR(AD27/$K$2-1,"") -> -0.19784997 | AE28: =IFERROR(AE27/$K$2-1,"") -> -0.15388591 | AF28: =IFERROR(AF27/$K$2-1,"") -> -0.10799135
B29: IRR (to Dec-Y-1) | G29: =IFERROR((G27/$K$2)^(1/((DATE(2029-1,12,31)-$K$3)/365.25))-1,"") -> 0.10995301 | H29: =IFERROR((H27/$K$2)^(1/((DATE(2030-1,12,31)-$K$3)/365.25))-1,"") -> 0.11093705 | N29: IRR (to Dec-Y-1) | S29: =IFERROR((S27/$K$2)^(1/((DATE(2029-1,12,31)-$K$3)/365.25))-1,"") -> 0.27699128 | T29: =IFERROR((T27/$K$2)^(1/((DATE(2030-1,12,31)-$K$3)/365.25))-1,"") -> 0.24249236 | Z29: IRR (to Dec-Y-1) | AD29: =IFERROR((AD27/$K$2)^(1/((DATE(2028-1,12,31)-$K$3)/365.25))-1,"") -> -0.1638437 | AE29: =IFERROR((AE27/$K$2)^(1/((DATE(2029-1,12,31)-$K$3)/365.25))-1,"") -> -0.072067383 | AF29: =IFERROR((AF27/$K$2)^(1/((DATE(2030-1,12,31)-$K$3)/365.25))-1,"") -> -0.034726128
B31: Free Cash Flow | C31: =Model!BV298 -> 534.199 | D31: =Model!CA298 -> 514.23245 | E31: =Model!CB298 -> 635.62039 | F31: =Model!CC298 -> 695.52003 | G31: =Model!CD298 -> 769.61802 | H31: =Model!CE298 -> 847.11167 | I31: =IFERROR((H31/C31)^(1/5)-1,"n/m") -> 0.096598176 | N31: Free Cash Flow | O31: 534.199 | P31: 519.67497 | Q31: 663.5142 | R31: 754.11973 | S31: 879.28816 | T31: 1013.4279 | U31: 0.13662697 | Z31: Free Cash Flow | AA31: 534.199 | AB31: 512.04316 | AC31: 608.86746 | AD31: 635.88476 | AE31: 662.34701 | AF31: 689.38192 | AG31: 0.052328576
B32: FCF % | C32: =IFERROR(C31/C9,"") -> 0.12619859 | D32: =IFERROR(D31/D9,"") -> 0.10895221 | E32: =IFERROR(E31/E9,"") -> 0.12638224 | F32: =IFERROR(F31/F9,"") -> 0.12868004 | G32: =IFERROR(G31/G9,"") -> 0.13280341 | H32: =IFERROR(H31/H9,"") -> 0.13655843 | J32: =IFERROR(AVERAGE(Model!C300,Model!D300,Model!E300,Model!F300,Model!G300,Model!H300,Model!I300,Model!N300,Model!S300,Model!X300,Model!AC300,Model!AH300,Model!AM300,Model!AR300,Model!AW300,Model!BB300,Model!BG300,Model!BL300,Model!BQ300,Model!BV300),"") -> 0.094282002 | K32: =IFERROR(MIN(Model!C300,Model!D300,Model!E300,Model!F300,Model!G300,Model!H300,Model!I300,Model!N300,Model!S300,Model!X300,Model!AC300,Model!AH300,Model!AM300,Model!AR300,Model!AW300,Model!BB300,Model!BG300,Model!BL300,Model!BQ300,Model!BV300),"") -> 0.021642921 | L32: =IFERROR(MAX(Model!C300,Model!D300,Model!E300,Model!F300,Model!G300,Model!H300,Model!I300,Model!N300,Model!S300,Model!X300,Model!AC300,Model!AH300,Model!AM300,Model!AR300,Model!AW300,Model!BB300,Model!BG300,Model!BL300,Model!BQ300,Model!BV300),"") -> 0.13754892 | N32: FCF % | O32: 0.12619859 | P32: 0.10864376 | Q32: 0.12541109 | R32: 0.12724514 | S32: 0.13317564 | T32: 0.13835732 | V32: 0.094282002 | W32: 0.021642921 | X32: 0.13754892 | Z32: FCF % | AA32: 0.12619859 | AB32: 0.10996774 | AC32: 0.12758731 | AD32: 0.12970195 | AE32: 0.13156941 | AF32: 0.13335732 | AH32: 0.094282002 | AI32: 0.021642921 | AJ32: 0.13754892
B33: FCF / share ($) | C33: =IFERROR(C31/C21,"") -> 9.5606085 | D33: =IFERROR(D31/D21,"") -> 9.3432596 | E33: =IFERROR(E31/E21,"") -> 11.765121 | F33: =IFERROR(F31/F21,"") -> 13.112242 | G33: =IFERROR(G31/G21,"") -> 14.769119 | H33: =IFERROR(H31/H21,"") -> 16.594769 | N33: FCF / share ($) | O33: 9.5606085 | P33: 9.4468186 | Q33: 12.392975 | R33: 14.466705 | S33: 17.240306 | T33: 20.444536 | Z33: FCF / share ($) | AA33: 9.5606085 | AB33: 9.2988829 | AC33: 11.186742 | AD33: 11.835758 | AE33: 12.534062 | AF33: 13.26198
B34: FCF Yield (on PT) | F34: =IFERROR(F33/F$27,"") | G34: =IFERROR(G33/G$27,"") -> 0.042457613 | H34: =IFERROR(H33/H$27,"") -> 0.042860201 | N34: FCF Yield (on PT) | R34: =IFERROR(R33/R$27,"") | S34: =IFERROR(S33/S$27,"") -> 0.036234921 | T34: =IFERROR(T33/T$27,"") -> 0.036770802 | Z34: FCF Yield (on PT) | AD34: =IFERROR(AD33/AD$27,"") -> 0.053549548 | AE34: =IFERROR(AE33/AE$27,"") -> 0.053762353 | AF34: =IFERROR(AF33/AF$27,"") -> 0.053957851
B35: Adjusted EBITDA (model: adjusted EBIT + D&A) | C35: =Model!BV229 -> 851.178 | D35: =Model!CA229 -> 955.81884 | E35: =Model!CB229 -> 1054.6944 | F35: =Model!CC229 -> 1164.811 | G35: =Model!CD229 -> 1276.8808 | H35: =Model!CE229 -> 1394.213 | I35: =IFERROR((H35/C35)^(1/5)-1,"n/m") -> 0.10372721 | N35: Adjusted EBITDA (model: adjusted EBIT + D&A) | O35: 851.178 | P35: 979.24896 | Q35: 1138.7557 | R35: 1323.7345 | S35: 1518.6891 | T35: 1727.7738 | U35: 0.15210828 | Z35: Adjusted EBITDA (model: adjusted EBIT + D&A) | AA35: 851.178 | AB35: 935.56347 | AC35: 975.18197 | AD35: 1015.2922 | AE35: 1053.3244 | AF35: 1092.2934 | AG35: 0.051147787
B36: Adjusted EBITDA % of net sales | C36: =IFERROR(C35/C9,"") -> 0.20108136 | D36: =IFERROR(D35/D9,"") -> 0.20251264 | E36: =IFERROR(E35/E9,"") -> 0.20970794 | F36: =IFERROR(F35/F9,"") -> 0.21550482 | G36: =IFERROR(G35/G9,"") -> 0.22033543 | H36: =IFERROR(H35/H9,"") -> 0.22475377 | J36: =IFERROR(AVERAGE(Model!C230,Model!D230,Model!E230,Model!F230,Model!G230,Model!H230,Model!I230,Model!N230,Model!S230,Model!X230,Model!AC230,Model!AH230,Model!AM230,Model!AR230,Model!AW230,Model!BB230,Model!BG230,Model!BL230,Model!BQ230,Model!BV230),"") -> 0.16412065 | K36: =IFERROR(MIN(Model!C230,Model!D230,Model!E230,Model!F230,Model!G230,Model!H230,Model!I230,Model!N230,Model!S230,Model!X230,Model!AC230,Model!AH230,Model!AM230,Model!AR230,Model!AW230,Model!BB230,Model!BG230,Model!BL230,Model!BQ230,Model!BV230),"") -> 0.10337683 | L36: =IFERROR(MAX(Model!C230,Model!D230,Model!E230,Model!F230,Model!G230,Model!H230,Model!I230,Model!N230,Model!S230,Model!X230,Model!AC230,Model!AH230,Model!AM230,Model!AR230,Model!AW230,Model!BB230,Model!BG230,Model!BL230,Model!BQ230,Model!BV230),"") -> 0.20108136 | N36: Adjusted EBITDA % of net sales | O36: 0.20108136 | P36: 0.20472275 | Q36: 0.21523668 | R36: 0.22335813 | S36: 0.23001833 | T36: 0.23588274 | V36: 0.16412065 | W36: 0.10337683 | X36: 0.20108136 | Z36: Adjusted EBITDA % of net sales | AA36: 0.20108136 | AB36: 0.20092408 | AC36: 0.20434799 | AD36: 0.20709 | AE36: 0.20923363 | AF36: 0.21129843 | AH36: 0.16412065 | AI36: 0.10337683 | AJ36: 0.20108136
B38: Net Debt | C38: =Model!BV419 -> 985.219 | D38: =Model!CA419 -> 896.79696 | E38: =Model!CB419 -> 1054.6944 | F38: =Model!CC419 -> 1164.811 | G38: =Model!CD419 -> 1276.8808 | H38: =Model!CE419 -> 1394.213 | N38: Net Debt | O38: 985.219 | P38: 921.2652 | Q38: 1423.4446 | R38: 1654.6681 | S38: 1898.3614 | T38: 2159.7172 | Z38: Net Debt | AA38: 985.219 | AB38: 869.07548 | AC38: 731.38648 | AD38: 761.46912 | AE38: 789.9933 | AF38: 819.22002
B39: Net Debt / Adjusted EBITDA (x) | C39: =IFERROR(C38/C35,"") -> 1.157477 | D39: =IFERROR(D38/D35,"") -> 0.93824993 | E39: =IFERROR(E38/E35,"") -> 1 | F39: =IFERROR(F38/F35,"") -> 1 | G39: =IFERROR(G38/G35,"") -> 1 | H39: =IFERROR(H38/H35,"") -> 1 | N39: Net Debt / Adjusted EBITDA (x) | O39: 1.157477 | P39: 0.94078752 | Q39: 1.25 | R39: 1.25 | S39: 1.25 | T39: 1.25 | Z39: Net Debt / Adjusted EBITDA (x) | AA39: 1.157477 | AB39: 0.92893268 | AC39: 0.75 | AD39: 0.75 | AE39: 0.75 | AF39: 0.75
B40: Share repurchases ($m) | D40: =Model!CA311 -> 130 | E40: =Model!CB311 -> 411.65614 | F40: =Model!CC311 -> 368.54886 | G40: =Model!CD311 -> 438.4616 | H40: =Model!CE311 -> 515.44136 | N40: Share repurchases ($m) | P40: 160 | Q40: 634.19773 | R40: 401.30207 | S40: 533.33877 | T40: 680.63699
B41: Implied avg buyback price ($) | D41: =Model!CA310 -> 275.54 | E41: =Model!CB310 -> 294.8278 | F41: =Model!CC310 -> 315.46575 | G41: =Model!CD310 -> 337.54835 | H41: =Model!CE310 -> 361.17673 | N41: Implied avg buyback price ($) | P41: 275.54 | Q41: 294.8278 | R41: 315.46575 | S41: 337.54835 | T41: 361.17673
B42: Shares repurchased (m) | D42: =Model!CA312 -> 0.47180083 | E42: =Model!CB312 -> 1.3962596 | F42: =Model!CC312 -> 1.168269 | G42: =Model!CD312 -> 1.2989594 | H42: =Model!CE312 -> 1.4271167 | N42: Shares repurchased (m) | P42: 0.58067794 | Q42: 2.1510784 | R42: 1.2720939 | S42: 1.5800367 | T42: 1.8844984
B44: ROIC | C44: =Model!BV401 -> 0.2362566 | D44: =Model!CA401 -> 0.25681884 | E44: =Model!CB401 -> 0.25438012 | F44: =Model!CC401 -> 0.2516436 | G44: =Model!CD401 -> 0.24969055 | H44: =Model!CE401 -> 0.24904773 | J44: =IFERROR(AVERAGE(Model!C401,Model!D401,Model!E401,Model!F401,Model!G401,Model!H401,Model!I401,Model!N401,Model!S401,Model!X401,Model!AC401,Model!AH401,Model!AM401,Model!AR401,Model!AW401,Model!BB401,Model!BG401,Model!BL401,Model!BQ401,Model!BV401),"") -> 0.23179876 | K44: =IFERROR(MIN(Model!C401,Model!D401,Model!E401,Model!F401,Model!G401,Model!H401,Model!I401,Model!N401,Model!S401,Model!X401,Model!AC401,Model!AH401,Model!AM401,Model!AR401,Model!AW401,Model!BB401,Model!BG401,Model!BL401,Model!BQ401,Model!BV401),"") -> 0.083557813 | L44: =IFERROR(MAX(Model!C401,Model!D401,Model!E401,Model!F401,Model!G401,Model!H401,Model!I401,Model!N401,Model!S401,Model!X401,Model!AC401,Model!AH401,Model!AM401,Model!AR401,Model!AW401,Model!BB401,Model!BG401,Model!BL401,Model!BQ401,Model!BV401),"") -> 0.29017761 | N44: ROIC | O44: 0.2362566 | P44: 0.26369813 | Q44: 0.25700927 | R44: 0.2549212 | S44: 0.25484156 | T44: 0.25680474 | V44: 0.23179876 | W44: 0.083557813 | X44: 0.29017761 | Z44: ROIC | AA44: 0.2362566 | AB44: 0.25101859 | AC44: 0.25260296 | AD44: 0.2496794 | AE44: 0.24642107 | AF44: 0.24372468 | AH44: 0.23179876 | AI44: 0.083557813 | AJ44: 0.29017761
B45: RONTA | C45: =Model!BV413 -> 0.27912348 | D45: =Model!CA413 -> 0.30593875 | E45: =Model!CB413 -> 0.30962273 | F45: =Model!CC413 -> 0.31284435 | G45: =Model!CD413 -> 0.31592508 | H45: =Model!CE413 -> 0.31982968 | J45: =IFERROR(AVERAGE(Model!C413,Model!D413,Model!E413,Model!F413,Model!G413,Model!H413,Model!I413,Model!N413,Model!S413,Model!X413,Model!AC413,Model!AH413,Model!AM413,Model!AR413,Model!AW413,Model!BB413,Model!BG413,Model!BL413,Model!BQ413,Model!BV413),"") -> 0.19908104 | K45: =IFERROR(MIN(Model!C413,Model!D413,Model!E413,Model!F413,Model!G413,Model!H413,Model!I413,Model!N413,Model!S413,Model!X413,Model!AC413,Model!AH413,Model!AM413,Model!AR413,Model!AW413,Model!BB413,Model!BG413,Model!BL413,Model!BQ413,Model!BV413),"") -> 0.048889066 | L45: =IFERROR(MAX(Model!C413,Model!D413,Model!E413,Model!F413,Model!G413,Model!H413,Model!I413,Model!N413,Model!S413,Model!X413,Model!AC413,Model!AH413,Model!AM413,Model!AR413,Model!AW413,Model!BB413,Model!BG413,Model!BL413,Model!BQ413,Model!BV413),"") -> 0.3007133 | N45: RONTA | O45: 0.27912348 | P45: 0.31415055 | Q45: 0.31688774 | R45: 0.32363074 | S45: 0.33081271 | T45: 0.33922689 | V45: 0.19908104 | W45: 0.048889066 | X45: 0.3007133 | Z45: RONTA | AA45: 0.27912348 | AB45: 0.29562115 | AC45: 0.28131259 | AD45: 0.28502842 | AE45: 0.28766469 | AF45: 0.29057559 | AH45: 0.19908104 | AI45: 0.048889066 | AJ45: 0.3007133
B47: Implied Market Cap (USDm) | F47: =F27*F21 -> 0 | G47: =G27*G21 -> 18126.738 | H47: =H27*H21 -> 19764.529 | N47: Implied Market Cap (USDm) | R47: =R27*R21 -> 0 | S47: =S27*S21 -> 24266.319 | T47: =T27*T21 -> 27560.669 | Z47: Implied Market Cap (USDm) | AD47: =AD27*AD21 -> 11874.699 | AE47: =AE27*AE21 -> 12319.904 | AF47: =AF27*AF21 -> 12776.304
B48: (+) Net Debt & NCI | F48: =F38+Model!CC345 -> 1164.811 | G48: =G38+Model!CD345 -> 1276.8808 | H48: =H38+Model!CE345 -> 1394.213 | N48: (+) Net Debt & NCI | R48: =R38+Model!CC345 -> 1654.6681 | S48: =S38+Model!CD345 -> 1898.3614 | T48: =T38+Model!CE345 -> 2159.7172 | Z48: (+) Net Debt & NCI | AD48: =AD38+Model!CC345 -> 761.46912 | AE48: =AE38+Model!CD345 -> 789.9933 | AF48: =AF38+Model!CE345 -> 819.22002
B49: Implied Enterprise Value (USDm) | F49: =F47+F48 -> 1164.811 | G49: =G47+G48 -> 19403.619 | H49: =H47+H48 -> 21158.742 | N49: Implied Enterprise Value (USDm) | R49: =R47+R48 -> 1654.6681 | S49: =S47+S48 -> 26164.68 | T49: =T47+T48 -> 29720.386 | Z49: Implied Enterprise Value (USDm) | AD49: =AD47+AD48 -> 12636.168 | AE49: =AE47+AE48 -> 13109.897 | AF49: =AF47+AF48 -> 13595.524
B50: Implied EV / Adjusted EBITDA (x) | F50: =IFERROR(F49/F35,"") -> 1 | G50: =IFERROR(G49/G35,"") -> 15.196109 | H50: =IFERROR(H49/H35,"") -> 15.176118 | N50: Implied EV / Adjusted EBITDA (x) | R50: =IFERROR(R49/R35,"") -> 1.25 | S50: =IFERROR(S49/S35,"") -> 17.228464 | T50: =IFERROR(T49/T35,"") -> 17.201549 | Z50: Implied EV / Adjusted EBITDA (x) | AD50: =IFERROR(AD49/AD35,"") -> 12.445844 | AE50: =IFERROR(AE49/AE35,"") -> 12.44621 | AF50: =IFERROR(AF49/AF35,"") -> 12.44677

Sheet DCF
B2: DCF VALUATION — LINCOLN ELECTRIC HOLDINGS (LECO)
B4: 1. WACC BUILD
B5: Risk-free rate (US 10Y govt) | C5: 0.055 | D5: Assumption (~US 10Y Treasury yield); update to market
B6: Equity risk premium | C6: 0.05 | D6: US implied ERP ~4.5–5.5% (Damodaran)
B7: Levered beta | C7: 1.1 | D7: Diversified industrials / welding peers (ESAB, ITW, Kennametal, Snap-on) ~1.0–1.2; short-cycle industrial capex exposure, partly offset by consumables (~2/3 of welding sales) and automation growth
B8: Cost of equity | C8: =C5+C7*C6 -> 0.11
B9: Pre-tax cost of debt | C9: 0.055 | D9: Investment-grade private-placement notes (2024 Notes priced at 5.55%–5.74%); marginal cost ~5.5%
B10: Tax rate | C10: 0.235 | D10: Model 2027E+ effective tax rate
B11: After-tax cost of debt | C11: =C9*(1-C10) -> 0.042075
B12: Target D/V | C12: 0.08 | D12: Net debt ~$0.9bn at YE2026E vs ~$15bn market cap ($275.54 × ~54m shares); LECO runs ~0.5–1.0x net leverage
B13: WACC | C13: =C8*(1-C12)+C11*C12 -> 0.104566
B15: Valuation date (live) | C15: =TODAY() -> 2026-10-07 00:00:00 | D15: Periods = (Dec-31-Year − today) / 365.25; cash flows assumed at year-end
B16: 2. UNLEVERED FREE CASH FLOW BUILD (USDm)
D17: 2026E | E17: 2027E | F17: 2028E | G17: 2029E | H17: 2030E | I17: 2031E | J17: 2032E | K17: 2033E | L17: 2034E | M17: 2035E | N17: Terminal | P17: CAGR 26–30E | Q17: CAGR 26–35E
B18: Adj. EBIT less rationalization & transaction costs (cash special items) | D18: =Model!CA222-Model!CA214-Model!CA215 -> 839.23884 | E18: =Model!CB222-Model!CB214-Model!CB215 -> 922.65903 | F18: =Model!CC222-Model!CC214-Model!CC215 -> 1019.4539 | G18: =Model!CD222-Model!CD214-Model!CD215 -> 1117.7148 | H18: =Model!CE222-Model!CE214-Model!CE215 -> 1220.632 | I18: =H18*(1+I$26) -> 1293.8699 | J18: =I18*(1+J$26) -> 1366.6501 | K18: =J18*(1+K$26) -> 1438.3992 | L18: =K18*(1+L$26) -> 1508.5212 | M18: =L18*(1+M$26) -> 1576.4047 | P18: =(H18/D18)^(1/(COLUMNS(D18:H18)-1))-1 -> 0.098183198 | Q18: =(M18/D18)^(1/(COLUMNS(D18:M18)-1))-1 -> 0.072556643
B19: × (1 − tax rate) | D19: =1-$C$10 -> 0.765 | E19: =1-$C$10 -> 0.765 | F19: =1-$C$10 -> 0.765 | G19: =1-$C$10 -> 0.765 | H19: =1-$C$10 -> 0.765 | I19: =1-$C$10 -> 0.765 | J19: =1-$C$10 -> 0.765 | K19: =1-$C$10 -> 0.765 | ... M19: =1-$C$10 -> 0.765
B20: NOPAT | D20: =D18*D19 -> 642.01771 | E20: =E18*E19 -> 705.83416 | F20: =F18*F19 -> 779.88227 | G20: =G18*G19 -> 855.05178 | H20: =H18*H19 -> 933.78348 | I20: =I18*I19 -> 989.81049 | J20: =J18*J19 -> 1045.4873 | K20: =K18*K19 -> 1100.3754 | ... M20: =M18*M19 -> 1205.9496
B21: plus D&A | D21: =Model!CA148 -> 103.956 | E21: =Model!CB148 -> 115.03535 | F21: =Model!CC148 -> 127.85702 | G21: =Model!CD148 -> 141.66602 | H21: =Model!CE148 -> 156.08104 | I21: =H21*(1+I$26) -> 165.4459 | J21: =I21*(1+J$26) -> 174.75224 | K21: =J21*(1+K$26) -> 183.92673 | L21: =K21*(1+L$26) -> 192.89316 | M21: =L21*(1+M$26) -> 201.57335
B22: − Capex and acquisitions (M&A 2027E–30E) | D22: =Model!CA278 -> -120 | E22: =Model!CB278+Model!CB279 -> -335.79242 | F22: =Model!CC278+Model!CC279 -> -395.93593 | G22: =Model!CD278+Model!CD279 -> -406.46953 | H22: =Model!CE278+Model!CE279 -> -417.48886 | I22: =Model!CE278*(1+I$26) -> -177.53819 | J22: =I22*(1+J$26) -> -187.52472 | K22: =J22*(1+K$26) -> -197.36976 | L22: =K22*(1+L$26) -> -206.99154 | M22: =L22*(1+M$26) -> -216.30616
B23: − Δ Working capital (CF statement) | D23: =Model!CA276 -> -122.75992 | E23: =Model!CB276 -> -45.32642 | F23: =Model!CC276 -> -58.428851 | G23: =Model!CD276 -> -60.904619 | H23: =Model!CE276 -> -63.70042 | I23: =H23*(1+I$26) -> -67.522445 | J23: =I23*(1+J$26) -> -71.320583 | K23: =J23*(1+K$26) -> -75.064913 | L23: =K23*(1+L$26) -> -78.724328 | M23: =L23*(1+M$26) -> -82.266923
B24: Unlevered FCF | D24: =D20+D21+D22+D23 -> 503.21379 | E24: =E20+E21+E22+E23 -> 439.75067 | F24: =F20+F21+F22+F23 -> 453.37451 | G24: =G20+G21+G22+G23 -> 529.34366 | H24: =H20+H21+H22+H23 -> 608.67524 | I24: =I20+I21+I22+I23 -> 910.19575 | J24: =J20+J21+J22+J23 -> 961.39427 | K24: =K20+K21+K22+K23 -> 1011.8675 | ... M24: =M20+M21+M22+M23 -> 1108.9498 | N24: =M24*(1+$C$27) -> 1147.7631 | P24: =(H24/D24)^(1/(COLUMNS(D24:H24)-1))-1 -> 0.048716921 | Q24: =(M24/D24)^(1/(COLUMNS(D24:M24)-1))-1 -> 0.091764122
B25: Terminal Value (Gordon Growth) | N25: =N24/($C$13-$C$27) -> 16498.908
B26: Fade-period growth (2031E–35E; 6% → 4.5% linear) | I26: 0.06 | J26: =I26+($M$26-$I$26)/4 -> 0.05625 | K26: =J26+($M$26-$I$26)/4 -> 0.0525 | L26: =K26+($M$26-$I$26)/4 -> 0.04875 | M26: 0.045
B27: Terminal growth rate | C27: 0.035
B29: Discount period (years) | D29: =(DATE(2026,12,31)-$C$15)/365.25 -> 0.23271732 | E29: =(DATE(2027,12,31)-$C$15)/365.25 -> 1.2320329 | F29: =(DATE(2028,12,31)-$C$15)/365.25 -> 2.2340862 | G29: =(DATE(2029,12,31)-$C$15)/365.25 -> 3.2334018 | H29: =(DATE(2030,12,31)-$C$15)/365.25 -> 4.2327173 | I29: =(DATE(2031,12,31)-$C$15)/365.25 -> 5.2320329 | J29: =(DATE(2032,12,31)-$C$15)/365.25 -> 6.2340862 | K29: =(DATE(2033,12,31)-$C$15)/365.25 -> 7.2334018 | L29: =(DATE(2034,12,31)-$C$15)/365.25 -> 8.2327173 | M29: =(DATE(2035,12,31)-$C$15)/365.25 -> 9.2320329 | N29: =M29 -> 9.2320329
B30: Discount factor | D30: =1/(1+$C$13)^D29 -> 0.97712146 | E30: =1/(1+$C$13)^E29 -> 0.88468047 | F30: =1/(1+$C$13)^F29 -> 0.80076684 | G30: =1/(1+$C$13)^G29 -> 0.72500996 | H30: =1/(1+$C$13)^H29 -> 0.65642009 | I30: =1/(1+$C$13)^I29 -> 0.5943192 | J30: =1/(1+$C$13)^J29 -> 0.53794689 | K30: =1/(1+$C$13)^K29 -> 0.4870542 | ... N30: =1/(1+$C$13)^N29 -> 0.39925749
B31: PV of UFCF | D31: =D24*D30 -> 491.70099 | E31: =E24*E30 -> 389.03883 | F31: =F24*F30 -> 363.04727 | G31: =G24*G30 -> 383.77943 | H31: =H24*H30 -> 399.54666 | I31: =I24*I30 -> 540.94681 | J31: =J24*J30 -> 517.17905 | K31: =K24*K30 -> 492.8343 | ... M31: =M24*M30 -> 442.75653 | N31: =N25*N30 -> 6587.3128
D32: LECO-specific: Lincoln Electric's adjusted EBIT expenses stock-based compensation and includes all amortization of acquired intangibles (no amortization add-back in the company's adjusted measures). Rationalization and acquisition transaction costs are cash costs and are deducted in row 18 (Model adjusted EBIT less those special items). Acquisition spend from the M&A lever is deducted in 2027E–30E; the fade period and terminal value assume no new acquisitions. Pension non-service items sit in other income (outside adjusted EBIT). Operating-lease costs are inside operating income.
B33: IMPLIED ROIC — invested capital roll-forward (USDm)
B34: Opening invested capital | D34: =Model!BV398 -> 2455.013 | E34: =D38 -> 2593.8169 | F34: =E38 -> 2859.9004 | G34: =F38 -> 3186.4082 | H34: =G38 -> 3512.1163 | I34: =H38 -> 3837.2245 | J34: =I38 -> 3916.8393 | K34: =J38 -> 4000.9323 | L34: =K38 -> 4089.4403 | M34: =L38 -> 4182.263
B35: plus Capex and acquisitions | D35: =-D22 -> 120 | E35: =-E22 -> 335.79242 | F35: =-F22 -> 395.93593 | G35: =-G22 -> 406.46953 | H35: =-H22 -> 417.48886 | I35: =-I22 -> 177.53819 | J35: =-J22 -> 187.52472 | K35: =-K22 -> 197.36976 | ... M35: =-M22 -> 216.30616
B36: less DD&A | D36: =-D21 -> -103.956 | E36: =-E21 -> -115.03535 | F36: =-F21 -> -127.85702 | G36: =-G21 -> -141.66602 | H36: =-H21 -> -156.08104 | I36: =-I21 -> -165.4459 | J36: =-J21 -> -174.75224 | K36: =-K21 -> -183.92673 | ... M36: =-M21 -> -201.57335
B37: plus Δ Working capital investment | D37: =-D23 -> 122.75992 | E37: =-E23 -> 45.32642 | F37: =-F23 -> 58.428851 | G37: =-G23 -> 60.904619 | H37: =-H23 -> 63.70042 | I37: =-I23 -> 67.522445 | J37: =-J23 -> 71.320583 | K37: =-K23 -> 75.064913 | ... M37: =-M23 -> 82.266923
B38: Closing invested capital | D38: =SUM(D34:D37) -> 2593.8169 | E38: =SUM(E34:E37) -> 2859.9004 | F38: =SUM(F34:F37) -> 3186.4082 | G38: =SUM(G34:G37) -> 3512.1163 | H38: =SUM(H34:H37) -> 3837.2245 | I38: =SUM(I34:I37) -> 3916.8393 | J38: =SUM(J34:J37) -> 4000.9323 | K38: =SUM(K34:K37) -> 4089.4403 | ... M38: =SUM(M34:M37) -> 4279.2627
B39: NOPAT (row 20) | D39: =D20 -> 642.01771 | E39: =E20 -> 705.83416 | F39: =F20 -> 779.88227 | G39: =G20 -> 855.05178 | H39: =H20 -> 933.78348 | I39: =I20 -> 989.81049 | J39: =J20 -> 1045.4873 | K39: =K20 -> 1100.3754 | ... M39: =M20 -> 1205.9496
B40: Implied ROIC (NOPAT / avg. invested capital) | D40: =IFERROR(D39/AVERAGE(D34,D38),"") -> 0.25432337 | E40: =IFERROR(E39/AVERAGE(E34,E38),"") -> 0.25884516 | F40: =IFERROR(F39/AVERAGE(F34,F38),"") -> 0.25796972 | G40: =IFERROR(G39/AVERAGE(G34,G38),"") -> 0.25529556 | H40: =IFERROR(H39/AVERAGE(H34,H38),"") -> 0.25411353 | I40: =IFERROR(I39/AVERAGE(I34,I38),"") -> 0.2553011 | J40: =IFERROR(J39/AVERAGE(J34,J38),"") -> 0.26408626 | K40: =IFERROR(K39/AVERAGE(K34,K38),"") -> 0.27202095 | ... M40: =IFERROR(M39/AVERAGE(M34,M38),"") -> 0.28504305
B41: Reinvestment rate (net investment / NOPAT) | D41: =IFERROR(SUM(D35:D37)/D39,"") -> 0.21619952 | E41: =IFERROR(SUM(E35:E37)/E39,"") -> 0.37697735 | F41: =IFERROR(SUM(F35:F37)/F39,"") -> 0.41866288 | G41: =IFERROR(SUM(G35:G37)/G39,"") -> 0.3809221 | H41: =IFERROR(SUM(H35:H37)/H39,"") -> 0.34816234 | I41: =IFERROR(SUM(I35:I37)/I39,"") -> 0.080434321 | J41: =IFERROR(SUM(J35:J37)/J39,"") -> 0.080434321 | K41: =IFERROR(SUM(K35:K37)/K39,"") -> 0.080434321 | ... M41: =IFERROR(SUM(M35:M37)/M39,"") -> 0.080434321
B42: Implied terminal RONIC (g / reinvestment rate) | N42: =IFERROR($C$27/M41,"") -> 0.43513763
D43: Opening IC = Model 2025A book invested capital (total equity + net debt), rolled forward with capex + M&A − D&A + ΔWC.
B44: 3. VALUATION SUMMARY
B45: Sum of PV (explicit + fade) | C45: =SUM(D31:M31) -> 4488.7921
B46: PV of Terminal Value | C46: =N31 -> 6587.3128
B47: Enterprise Value | C47: =C45+C46 -> 11076.105
B48: Less: Net debt + NCI (Model 2026E YE) | C48: =Model!CA419+Model!CA345 -> 896.79696 | D48: LECO has no noncontrolling interests since 2023 (Model row shown for completeness).
B49: Equity Value | C49: =C47-C48 -> 10179.308
B50: Diluted shares (m, Model 2026E) | C50: =Model!CA425 -> 54.587706
B51: Implied share price ($) | C51: =C49/C50 -> 186.4762
B52: Current share price ($) | C52: =Model!CA424 -> 275.54
B53: Implied upside / (downside) | C53: =C51/C52-1 -> -0.32323365
B54: Required discount to DCF value for target IRR | C54: =1-((1+C13)/(1+H54))^H55 -> 0.11390254 | D54: vs. current | E54: Target IRR | H54: 0.15
B55: Max entry price for target IRR ($) | C55: =C51*(1-C54) -> 165.23609 | D55: =C55/C52-1 -> -0.40031906 | E55: Years for discount to close | H55: 3
B58: 4. SENSITIVITY: IMPLIED PRICE ($) — WACC × Terminal Growth
D60: WACC →
B61: Terminal growth ↓ | D61: =F61-0.01 -> 0.094566 | E61: =F61-0.005 -> 0.099566 | F61: =$C$13 -> 0.104566 | G61: =F61+0.005 -> 0.109566 | H61: =F61+0.01 -> 0.114566
B62: =B64-0.01 -> 0.025 | D62: {=IFERROR((SUMPRODUCT($D$24:$M$24/(1+D$61)^$D$29:$M$29)+($M$24*(1+$B62)/(D$61-$B62))/(1+D$61)^$M$29-$C$48)/$C$50,"")} -> 199.53696 | E62: {=IFERROR((SUMPRODUCT($D$24:$M$24/(1+E$61)^$D$29:$M$29)+($M$24*(1+$B62)/(E$61-$B62))/(1+E$61)^$M$29-$C$48)/$C$50,"")} -> 183.91311 | F62: {=IFERROR((SUMPRODUCT($D$24:$M$24/(1+F$61)^$D$29:$M$29)+($M$24*(1+$B62)/(F$61-$B62))/(1+F$61)^$M$29-$C$48)/$C$50,"")} -> 170.29028 | G62: {=IFERROR((SUMPRODUCT($D$24:$M$24/(1+G$61)^$D$29:$M$29)+($M$24*(1+$B62)/(G$61-$B62))/(1+G$61)^$M$29-$C$48)/$C$50,"")} -> 158.31245 | H62: {=IFERROR((SUMPRODUCT($D$24:$M$24/(1+H$61)^$D$29:$M$29)+($M$24*(1+$B62)/(H$61-$B62))/(1+H$61)^$M$29-$C$48)/$C$50,"")} -> 147.70312
B63: =B64-0.005 -> 0.03 | D63: {=IFERROR((SUMPRODUCT($D$24:$M$24/(1+D$61)^$D$29:$M$29)+($M$24*(1+$B63)/(D$61-$B63))/(1+D$61)^$M$29-$C$48)/$C$50,"")} -> 210.28539 | E63: {=IFERROR((SUMPRODUCT($D$24:$M$24/(1+E$61)^$D$29:$M$29)+($M$24*(1+$B63)/(E$61-$B63))/(1+E$61)^$M$29-$C$48)/$C$50,"")} -> 192.87736 | F63: {=IFERROR((SUMPRODUCT($D$24:$M$24/(1+F$61)^$D$29:$M$29)+($M$24*(1+$B63)/(F$61-$B63))/(1+F$61)^$M$29-$C$48)/$C$50,"")} -> 177.84057 | G63: {=IFERROR((SUMPRODUCT($D$24:$M$24/(1+G$61)^$D$29:$M$29)+($M$24*(1+$B63)/(G$61-$B63))/(1+G$61)^$M$29-$C$48)/$C$50,"")} -> 164.72693 | H63: {=IFERROR((SUMPRODUCT($D$24:$M$24/(1+H$61)^$D$29:$M$29)+($M$24*(1+$B63)/(H$61-$B63))/(1+H$61)^$M$29-$C$48)/$C$50,"")} -> 153.19437
B64: =$C$27 -> 0.035 | D64: {=IFERROR((SUMPRODUCT($D$24:$M$24/(1+D$61)^$D$29:$M$29)+($M$24*(1+$B64)/(D$61-$B64))/(1+D$61)^$M$29-$C$48)/$C$50,"")} -> 222.83828 | E64: {=IFERROR((SUMPRODUCT($D$24:$M$24/(1+E$61)^$D$29:$M$29)+($M$24*(1+$B64)/(E$61-$B64))/(1+E$61)^$M$29-$C$48)/$C$50,"")} -> 203.23 | F64: {=IFERROR((SUMPRODUCT($D$24:$M$24/(1+F$61)^$D$29:$M$29)+($M$24*(1+$B64)/(F$61-$B64))/(1+F$61)^$M$29-$C$48)/$C$50,"")} -> 186.4762 | G64: {=IFERROR((SUMPRODUCT($D$24:$M$24/(1+G$61)^$D$29:$M$29)+($M$24*(1+$B64)/(G$61-$B64))/(1+G$61)^$M$29-$C$48)/$C$50,"")} -> 172.00166 | H64: {=IFERROR((SUMPRODUCT($D$24:$M$24/(1+H$61)^$D$29:$M$29)+($M$24*(1+$B64)/(H$61-$B64))/(1+H$61)^$M$29-$C$48)/$C$50,"")} -> 159.37578
B65: =B64+0.005 -> 0.04 | D65: {=IFERROR((SUMPRODUCT($D$24:$M$24/(1+D$61)^$D$29:$M$29)+($M$24*(1+$B65)/(D$61-$B65))/(1+D$61)^$M$29-$C$48)/$C$50,"")} -> 237.69167 | E65: {=IFERROR((SUMPRODUCT($D$24:$M$24/(1+E$61)^$D$29:$M$29)+($M$24*(1+$B65)/(E$61-$B65))/(1+E$61)^$M$29-$C$48)/$C$50,"")} -> 215.32065 | F65: {=IFERROR((SUMPRODUCT($D$24:$M$24/(1+F$61)^$D$29:$M$29)+($M$24*(1+$B65)/(F$61-$B65))/(1+F$61)^$M$29-$C$48)/$C$50,"")} -> 196.44932 | G65: {=IFERROR((SUMPRODUCT($D$24:$M$24/(1+G$61)^$D$29:$M$29)+($M$24*(1+$B65)/(G$61-$B65))/(1+G$61)^$M$29-$C$48)/$C$50,"")} -> 180.32211 | H65: {=IFERROR((SUMPRODUCT($D$24:$M$24/(1+H$61)^$D$29:$M$29)+($M$24*(1+$B65)/(H$61-$B65))/(1+H$61)^$M$29-$C$48)/$C$50,"")} -> 166.38617
B66: =B64+0.01 -> 0.045 | D66: {=IFERROR((SUMPRODUCT($D$24:$M$24/(1+D$61)^$D$29:$M$29)+($M$24*(1+$B66)/(D$61-$B66))/(1+D$61)^$M$29-$C$48)/$C$50,"")} -> 255.54174 | E66: {=IFERROR((SUMPRODUCT($D$24:$M$24/(1+E$61)^$D$29:$M$29)+($M$24*(1+$B66)/(E$61-$B66))/(1+E$61)^$M$29-$C$48)/$C$50,"")} -> 229.62708 | F66: {=IFERROR((SUMPRODUCT($D$24:$M$24/(1+F$61)^$D$29:$M$29)+($M$24*(1+$B66)/(F$61-$B66))/(1+F$61)^$M$29-$C$48)/$C$50,"")} -> 208.09673 | G66: {=IFERROR((SUMPRODUCT($D$24:$M$24/(1+G$61)^$D$29:$M$29)+($M$24*(1+$B66)/(G$61-$B66))/(1+G$61)^$M$29-$C$48)/$C$50,"")} -> 189.93124 | H66: {=IFERROR((SUMPRODUCT($D$24:$M$24/(1+H$61)^$D$29:$M$29)+($M$24*(1+$B66)/(H$61-$B66))/(1+H$61)^$M$29-$C$48)/$C$50,"")} -> 174.40429
B69: 5. REVERSE DCF
B70: To solve for the market-implied path: Data ▸ What-If Analysis ▸ Goal Seek — set C51 to the current price (C52) by changing C27 (terminal growth) or the fade-period growth inputs (I26:M26).
B72: 6. MAUBOUSSIN EV / NOPAT — TWO-STAGE FRAMEWORK
B73: EV/NOPAT = 1/r + [g × (1 − r/ROIIC) / (r × (r − g))] × [1 − ((1+g)/(1+r))^N]
B74: Formula source: Mauboussin & Rappaport, "Expectations Investing" (2021); Counterpoint Global, "What Does a Price-Earnings Multiple Mean?" (2020).
B76: Input | C76: Value | D76: Rationale (Lincoln Electric characteristics)
B77: r (Cost of capital / WACC) | C77: =$C$13 -> 0.104566 | D77: Linked from Section 1 WACC build
B78: g (NOPAT growth, Stage 1) | C78: 0.07 | D78: Model adjusted EBIT CAGR 2026–30E: low/mid-single-digit organic growth (volume recovery + price), automation mix, bolt-on M&A and buybacks → ~7% NOPAT growth
B79: ROIIC (Return on incremental invested capital) | C79: 0.25 | D79: Consumables franchise and distribution reach earn high returns on organic investment (company adjusted ROIC ~22–23%); acquired growth earns lower returns on purchase price
B80: N (Years of value creation / CAP) | C80: 12 | D80: #1 global arc-welding brand; consumables razor/razor-blade model; installed base, distributor network and application know-how; welding automation and cobot growth; RISE 2030 strategy
B82: Calculation | C82: Value
B83: Steady-state component: 1 / r | C83: =1/C77 -> 9.563338
B84: Value-creation factor: 1 − r / ROIIC | C84: =1-C77/C79 -> 0.581736
B85: Growth multiplier: g × (1 − r/ROIIC) / (r × (r − g)) | C85: =C78*C84/(C77*(C77-C78)) -> 11.266379
B86: Time decay: 1 − ((1+g)/(1+r))^N | C86: =1-((1+C78)/(1+C77))^C80 -> 0.3171815
B87: PVGO component (growth value) | C87: =C85*C86 -> 3.573487
B88: Mauboussin EV / NOPAT (steady-state + PVGO) | C88: =C83+C87 -> 13.136825
B90: VALUATION — Applied to 2028E NOPAT | C90: USDm
B91: 2028E Adj. EBIT less rationalization & transaction costs | C91: =Model!CC222-Model!CC214-Model!CC215 -> 1019.4539
B92: Tax rate (from WACC build) | C92: =$C$10 -> 0.235
B93: 2028E NOPAT | C93: =C91*(1-C92) -> 779.88227
B94: × Mauboussin EV/NOPAT multiple | C94: =C88 -> 13.136825
B95: Implied Enterprise Value (2028E basis) | C95: =C93*C94 -> 10245.177
B96: Less: YE2027 net debt + NCI (Model) | C96: =Model!CB419+Model!CB345 -> 1054.6944
B97: Implied Equity Value | C97: =C95-C96 -> 9190.4824
B98: Diluted shares 2028E (m, Model) | C98: =Model!CC425 -> 52.609428
B99: Implied share price 2028 ($) | C99: =C97/C98 -> 174.69269
B101: Current share price ($) | C101: =C52 -> 275.54
B102: Implied upside / (downside) | C102: =C99/C101-1 -> -0.3659988
B104: MARKET-IMPLIED EV/NOPAT TODAY | C104: USDm
B105: Current market cap (spot × diluted shares) | C105: =C52*C50 -> 15041.097
B106: Plus: YE2026 net debt + NCI | C106: =C48 -> 896.79696
B107: Implied Enterprise Value (today) | C107: =C105+C106 -> 15937.894
B108: LECO market-implied EV/NOPAT (on 2028E NOPAT) | C108: =C107/C93 -> 20.436282
B110: Multiple gap (Mauboussin − Market) | C110: =C88-C108 -> -7.2994565
B111: Implied re-rating headroom | C111: =C88/C108-1 -> -0.35718125

Sheet Charts
B2: Lincoln Electric — Historical Operating Performance (2006–2025)
B3: All historicals · USDm · Linked to Model. Volume / price = company "change in net sales" table (consolidated; 2006–08 from the 10-K MD&A). Adjusted EBIT as reconciled by Lincoln Electric in each period ("EBIT, as adjusted" to 2019).
C7: 2006 | D7: 2007 | E7: 2008 | F7: 2009 | G7: 2010 | H7: 2011 | I7: 2012 | J7: 2013 | K7: 2014 | L7: 2015 | M7: 2016 | N7: 2017 | O7: 2018 | P7: 2019 | Q7: 2020 | R7: 2021 | S7: 2022 | T7: 2023 | U7: 2024 | V7: 2025
B8: Organic volume % | C8: =IFERROR(Model!C105+0,0) -> 0.155 | D8: =IFERROR(Model!D105+0,0) -> 0.068 | E8: =IFERROR(Model!E105+0,0) -> -0.039 | F8: =IFERROR(Model!F105+0,0) -> -0.298 | G8: =IFERROR(Model!G105+0,0) -> 0.141 | H8: =IFERROR(Model!H105+0,0) -> 0.148 | I8: =IFERROR(Model!I105+0,0) -> 0.013 | J8: =IFERROR(Model!N105+0,0) -> -0.027 | K8: =IFERROR(Model!S105+0,0) -> -0.02 | L8: =IFERROR(Model!X105+0,0) -> -0.08 | M8: =IFERROR(Model!AC105+0,0) -> -0.098 | N8: =IFERROR(Model!AH105+0,0) -> 0.042 | O8: =IFERROR(Model!AM105+0,0) -> 0.011 | P8: =IFERROR(Model!AR105+0,0) -> -0.047 | Q8: =IFERROR(Model!AW105+0,0) -> -0.127 | R8: =IFERROR(Model!BB105+0,0) -> 0.098 | S8: =IFERROR(Model!BG105+0,0) -> 0.05 | T8: =IFERROR(Model!BL105+0,0) -> 0.023 | U8: =IFERROR(Model!BQ105+0,0) -> -0.072 | V8: =IFERROR(Model!BV105+0,0) -> -0.037
B9: Price % | C9: =IFERROR(Model!C106+0,0) -> 0.029 | D9: =IFERROR(Model!D106+0,0) -> 0.038 | E9: =IFERROR(Model!E106+0,0) -> 0.077 | F9: =IFERROR(Model!F106+0,0) -> -0.005 | G9: =IFERROR(Model!G106+0,0) -> 0.004 | H9: =IFERROR(Model!H106+0,0) -> 0.069 | I9: =IFERROR(Model!I106+0,0) -> 0.017 | J9: =IFERROR(Model!N106+0,0) -> 0.001 | K9: =IFERROR(Model!S106+0,0) -> 0.018 | L9: =IFERROR(Model!X106+0,0) -> 0.04 | M9: =IFERROR(Model!AC106+0,0) -> 0.102 | N9: =IFERROR(Model!AH106+0,0) -> 0.024 | O9: =IFERROR(Model!AM106+0,0) -> 0.056 | P9: =IFERROR(Model!AR106+0,0) -> 0.012 | Q9: =IFERROR(Model!AW106+0,0) -> 0.005 | R9: =IFERROR(Model!BB106+0,0) -> 0.095 | S9: =IFERROR(Model!BG106+0,0) -> 0.145 | T9: =IFERROR(Model!BL106+0,0) -> 0.017 | U9: =IFERROR(Model!BQ106+0,0) -> 0.007 | V9: =IFERROR(Model!BV106+0,0) -> 0.062
C11: =C7 -> 2006 | D11: =D7 -> 2007 | E11: =E7 -> 2008 | F11: =F7 -> 2009 | G11: =G7 -> 2010 | H11: =H7 -> 2011 | I11: =I7 -> 2012 | J11: =J7 -> 2013 | ... V11: =V7 -> 2025
B12: Adjusted EBIT | C12: =Model!C222 -> 236.921 | D12: =Model!D222 -> 290.105 | E12: =Model!E222 -> 322.49 | F12: =Model!F222 -> 122.17 | G12: =Model!G222 -> 194.157 | H12: =Model!H222 -> 305.196 | I12: =Model!I222 -> 380.508 | J12: =Model!N222 -> 437.351 | K12: =Model!S222 -> 434.34 | L12: =Model!X222 -> 378.807 | M12: =Model!AC222 -> 328.723 | N12: =Model!AH222 -> 370.338 | O12: =Model!AM222 -> 422.694 | P12: =Model!AR222 -> 400.753 | Q12: =Model!AW222 -> 340.406 | R12: =Model!BB222 -> 491.268 | S12: =Model!BG222 -> 636.951 | T12: =Model!BL222 -> 731.374 | U12: =Model!BQ222 -> 713.605 | V12: =Model!BV222 -> 752.632
B13: Operating income (GAAP) | C13: =Model!C162 -> 232.97 | D13: =Model!D162 -> 277.632 | E13: =Model!E162 -> 295.404 | F13: =Model!F162 -> 92.976 | G13: =Model!G162 -> 186.43 | H13: =Model!H162 -> 296.68 | I13: =Model!I162 -> 362.081 | J13: =Model!N162 -> 406.985 | K13: =Model!S162 -> 373.747 | L13: =Model!X162 -> 181.7 | M13: =Model!AC162 -> 288.274 | N13: =Model!AH162 -> 377.711 | O13: =Model!AM162 -> 375.539 | P13: =Model!AR162 -> 370.91 | Q13: =Model!AW162 -> 282.071 | R13: =Model!BB162 -> 461.669 | S13: =Model!BG162 -> 612.336 | T13: =Model!BL162 -> 717.849 | U13: =Model!BQ162 -> 636.462 | V13: =Model!BV162 -> 718.059
B14: Adj. EBIT margin % | C14: =Model!C223 -> 0.12014767 | D14: =Model!D223 -> 0.1271953 | E14: =Model!E223 -> 0.13008187 | F14: =Model!F223 -> 0.070647695 | G14: =Model!G223 -> 0.093787859 | H14: =Model!H223 -> 0.1132617 | I14: =Model!I223 -> 0.13335403 | J14: =Model!N223 -> 0.15331281 | K14: =Model!S223 -> 0.15438677 | L14: =Model!X223 -> 0.14938416 | M14: =Model!AC223 -> 0.14451815 | N14: =Model!AH223 -> 0.14111173 | O14: =Model!AM223 -> 0.13956405 | P14: =Model!AR223 -> 0.1334388 | Q14: =Model!AW223 -> 0.12819387 | R14: =Model!BB223 -> 0.15189878 | S14: =Model!BG223 -> 0.16934732 | T14: =Model!BL223 -> 0.17448414 | U14: =Model!BQ223 -> 0.1780154 | V14: =Model!BV223 -> 0.17780096
B15: GAAP Op. margin % | C15: =Model!C264 -> 0.11814404 | D15: =Model!D264 -> 0.12172656 | E15: =Model!E264 -> 0.11915627 | F15: =Model!F264 -> 0.053765574 | G15: =Model!G264 -> 0.090055319 | H15: =Model!H264 -> 0.11010132 | I15: =Model!I264 -> 0.12689605 | J15: =Model!N264 -> 0.14266805 | K15: =Model!S264 -> 0.1328489 | L15: =Model!X264 -> 0.07165417 | M15: =Model!AC264 -> 0.12673535 | N15: =Model!AH264 -> 0.1439211 | O15: =Model!AM264 -> 0.12399453 | P15: =Model!AR264 -> 0.12350197 | Q15: =Model!AW264 -> 0.10622543 | R15: =Model!BB264 -> 0.14274685 | S15: =Model!BG264 -> 0.16280288 | T15: =Model!BL264 -> 0.17125748 | U15: =Model!BQ264 -> 0.15877136 | V15: =Model!BV264 -> 0.16963347
C17: =C7 -> 2006 | D17: =D7 -> 2007 | E17: =E7 -> 2008 | F17: =F7 -> 2009 | G17: =G7 -> 2010 | H17: =H7 -> 2011 | I17: =I7 -> 2012 | J17: =J7 -> 2013 | ... V17: =V7 -> 2025
B18: ROIC | C18: =IFERROR(Model!C401+0,NA()) -> 0.19476001 | D18: =IFERROR(Model!D401+0,NA()) -> 0.20488842 | E18: =IFERROR(Model!E401+0,NA()) -> 0.26763136 | F18: =IFERROR(Model!F401+0,NA()) -> 0.083557813 | G18: =IFERROR(Model!G401+0,NA()) -> 0.15572345 | H18: =IFERROR(Model!H401+0,NA()) -> 0.23494606 | I18: =IFERROR(Model!I401+0,NA()) -> 0.24248782 | J18: =IFERROR(Model!N401+0,NA()) -> 0.24507617 | K18: =IFERROR(Model!S401+0,NA()) -> 0.2721731 | L18: =IFERROR(Model!X401+0,NA()) -> 0.28921378 | M18: =IFERROR(Model!AC401+0,NA()) -> 0.22634364 | N18: =IFERROR(Model!AH401+0,NA()) -> 0.19073415 | O18: =IFERROR(Model!AM401+0,NA()) -> 0.26722135 | P18: =IFERROR(Model!AR401+0,NA()) -> 0.23320506 | Q18: =IFERROR(Model!AW401+0,NA()) -> 0.2124149 | R18: =IFERROR(Model!BB401+0,NA()) -> 0.29017761 | S18: =IFERROR(Model!BG401+0,NA()) -> 0.2486177 | T18: =IFERROR(Model!BL401+0,NA()) -> 0.28737639 | U18: =IFERROR(Model!BQ401+0,NA()) -> 0.25316987 | V18: =IFERROR(Model!BV401+0,NA()) -> 0.2362566
B19: RONTA | C19: =IFERROR(Model!C413+0,NA()) -> 0.16297135 | D19: =IFERROR(Model!D413+0,NA()) -> 0.15717288 | E19: =IFERROR(Model!E413+0,NA()) -> 0.16586831 | F19: =IFERROR(Model!F413+0,NA()) -> 0.048889066 | G19: =IFERROR(Model!G413+0,NA()) -> 0.096932574 | H19: =IFERROR(Model!H413+0,NA()) -> 0.14253517 | I19: =IFERROR(Model!I413+0,NA()) -> 0.17248538 | J19: =IFERROR(Model!N413+0,NA()) -> 0.19949643 | K19: =IFERROR(Model!S413+0,NA()) -> 0.21971541 | L19: =IFERROR(Model!X413+0,NA()) -> 0.23095549 | M19: =IFERROR(Model!AC413+0,NA()) -> 0.17738251 | N19: =IFERROR(Model!AH413+0,NA()) -> 0.152093 | O19: =IFERROR(Model!AM413+0,NA()) -> 0.21500541 | P19: =IFERROR(Model!AR413+0,NA()) -> 0.21165596 | Q19: =IFERROR(Model!AW413+0,NA()) -> 0.18557146 | R19: =IFERROR(Model!BB413+0,NA()) -> 0.28655778 | S19: =IFERROR(Model!BG413+0,NA()) -> 0.28895653 | T19: =IFERROR(Model!BL413+0,NA()) -> 0.3007133 | U19: =IFERROR(Model!BQ413+0,NA()) -> 0.28753927 | V19: =IFERROR(Model!BV413+0,NA()) -> 0.27912348
B20: Adj. EBIT margin % | C20: =IFERROR(Model!C223+0,NA()) -> 0.12014767 | D20: =IFERROR(Model!D223+0,NA()) -> 0.1271953 | E20: =IFERROR(Model!E223+0,NA()) -> 0.13008187 | F20: =IFERROR(Model!F223+0,NA()) -> 0.070647695 | G20: =IFERROR(Model!G223+0,NA()) -> 0.093787859 | H20: =IFERROR(Model!H223+0,NA()) -> 0.1132617 | I20: =IFERROR(Model!I223+0,NA()) -> 0.13335403 | J20: =IFERROR(Model!N223+0,NA()) -> 0.15331281 | K20: =IFERROR(Model!S223+0,NA()) -> 0.15438677 | L20: =IFERROR(Model!X223+0,NA()) -> 0.14938416 | M20: =IFERROR(Model!AC223+0,NA()) -> 0.14451815 | N20: =IFERROR(Model!AH223+0,NA()) -> 0.14111173 | O20: =IFERROR(Model!AM223+0,NA()) -> 0.13956405 | P20: =IFERROR(Model!AR223+0,NA()) -> 0.1334388 | Q20: =IFERROR(Model!AW223+0,NA()) -> 0.12819387 | R20: =IFERROR(Model!BB223+0,NA()) -> 0.15189878 | S20: =IFERROR(Model!BG223+0,NA()) -> 0.16934732 | T20: =IFERROR(Model!BL223+0,NA()) -> 0.17448414 | U20: =IFERROR(Model!BQ223+0,NA()) -> 0.1780154 | V20: =IFERROR(Model!BV223+0,NA()) -> 0.17780096
B21: FCF margin % | C21: =IFERROR(Model!C300+0,NA()) -> 0.021642921 | D21: =IFERROR(Model!D300+0,NA()) -> 0.082515047 | E21: =IFERROR(Model!E300+0,NA()) -> 0.0746322 | F21: =IFERROR(Model!F300+0,NA()) -> 0.12268018 | G21: =IFERROR(Model!G300+0,NA()) -> 0.046572459 | H21: =IFERROR(Model!H300+0,NA()) -> 0.047392776 | I21: =IFERROR(Model!I300+0,NA()) -> 0.096296411 | J21: =IFERROR(Model!N300+0,NA()) -> 0.092151882 | K21: =IFERROR(Model!S300+0,NA()) -> 0.11684115 | L21: =IFERROR(Model!X300+0,NA()) -> 0.10267053 | M21: =IFERROR(Model!AC300+0,NA()) -> 0.11145891 | N21: =IFERROR(Model!AH300+0,NA()) -> 0.10409456 | O21: =IFERROR(Model!AM300+0,NA()) -> 0.085154757 | P21: =IFERROR(Model!AR300+0,NA()) -> 0.11106886 | Q21: =IFERROR(Model!AW300+0,NA()) -> 0.11002523 | R21: =IFERROR(Model!BB300+0,NA()) -> 0.093542103 | S21: =IFERROR(Model!BG300+0,NA()) -> 0.082819868 | T21: =IFERROR(Model!BL300+0,NA()) -> 0.13754892 | U21: =IFERROR(Model!BQ300+0,NA()) -> 0.12033268 | V21: =IFERROR(Model!BV300+0,NA()) -> 0.12619859
