Workbook

Sheet Model
AP1: SCENARIO SWITCH ▼ (Bull / Base / Bear) — drives all scenario-linked forecast drivers
B2: Loar Holdings Inc. (NYSE: LOAR) — 3-Statement Financial Model | AP2: Base
B3: US GAAP as reported · USD millions (per-share data in USD; shares in millions) · Source: Loar Forms 10-K / 10-Q, Form 8-K earnings releases (Ex. 99.1), deal 8-Ks and the IPO prospectus (424B4, 26-Apr-2024), SEC EDGAR CIK 0002000178 (investor-relations releases at ir.loargroup.com are the same documents as filed on EDGAR)
B4: Basis notes: calendar fiscal year; single reportable segment; all periods as originally reported. FY2012–21: prospectus net income → Adjusted EBITDA reconciliation only (FY2017 = predecessor Jan–Oct + successor Oct–Dec: acquisition of Loar Group Inc. by Loar Holdings, LLC, 2-Oct-2017). Loar Holdings, LLC to the IPO (29-Apr-2024; follow-on Dec-2024) — per-share data from Q2-24. Acquisitions: SCHROTH Jul-22, DAC Jul-23, CAV Sep-23, Applied Avionics Aug-24, Beadlight Jul-25, LMB Dec-25, Harper Engineering Jan-26. Adjusted EPS on the current definition (adds back amortization of acquired intangibles, from Q1-26) for all periods. Q3/26E–Q4/26E calibrated to FY26 sales and Adjusted EBITDA guidance.
AR5: Forecast | AS5: Historical | AT5: Historical | AU5: Historical
B6: (USDm) | C6: 2012 | D6: 2013 | E6: 2014 | F6: 2015 | G6: 2016 | H6: 2017 | I6: 2018 | J6: 2019 | K6: 2020 | L6: 2021 | M6: Q1/22 | N6: Q2/22 | O6: Q3/22 | P6: Q4/22 | Q6: 2022 | R6: Q1/23 | S6: Q2/23 | T6: Q3/23 | U6: Q4/23 | V6: 2023 | W6: Q1/24 | X6: Q2/24 | Y6: Q3/24 | Z6: Q4/24 | AA6: 2024 | AB6: Q1/25 | AC6: Q2/25 | AD6: Q3/25 | AE6: Q4/25 | AF6: 2025 | AG6: Q1/26 | AH6: Q2/26 | AI6: Q3/26E | AJ6: Q4/26E | AK6: 2026E | AL6: 2027E | AM6: 2028E | AN6: 2029E | AO6: 2030E | AP6: Modelling Notes | AR6: 5Y CAGR | AS6: 5Y CAGR | AT6: 10Y CAGR | AU6: 13Y CAGR
AR7: 25-'30 | AS7: 20-'25 | AT7: 15-'25 | AU7: 12-'25
B8: END-MARKET P&L — COMMERCIAL AEROSPACE · BUSINESS JET & GA · DEFENSE · OTHER (OEM × aftermarket build) | AP8: END-MARKET BUILD — modelling logic (OEM / aftermarket net sales by end market → net sales × Adjusted EBITDA margin → Adjusted EBITDA → GAAP P&L)
AX9: SCENARIO INPUT TABLE — driver assumptions per Bull / Base / Bear | AY9: Bull | AZ9: Base | BA9: Bear | BB9: Bull / Bear = Base + Δ (Δ inputs on each block header). Outlook block = high / mid / low end of the FY26 guidance ranges.
B10: Commercial aerospace (seat-belt & airbag restraints, interiors latches, fluid & ice protection, avionics interface) | AP10: COMMERCIAL AEROSPACE — modelling logic
B11: OEM net sales | Q11: 40.792 | R11: 12.211 | S11: 13.702 | T11: 14.574 | U11: 14.239 | V11: 54.726 | W11: 16.193 | X11: 14.299 | Y11: 15.824 | Z11: 18.695 | AA11: 65.011 | AB11: 16.064 | AC11: 19.44 | AD11: 20.659 | AE11: 21.228 | AF11: 77.391 | AG11: 31.521 | AH11: 37.16 | AI11: =AD11*(1+AI12) | AJ11: =AE11*(1+AJ12) | AK11: =SUM(AG11,AH11,AI11,AJ11) | AL11: =AK11*(1+AL12) | AM11: =AL11*(1+AM12) | AN11: =AM11*(1+AN12) | AO11: =AN11*(1+AO12) | AP11: End-market sales as published (release Table 5; FY2022-23 prospectus note; Q1-23 = 1H-23 − Q2-23). Not published before 2022 or for 2022 quarters. Q3/Q4-26E: prior-year quarter × (1 + growth). 2027E+: prior year × (1 + scenario lever). | AX11: FY26 outlook — Q2-26 release (6-Aug-26) | AY11: High | AZ11: Mid | BA11: Low | BB11: Raised in the Q2-26 release (from $645–655m sales / $257–262m Adjusted EBITDA / $1.26–1.30 Adjusted EPS in Q1-26). Includes LMB (Dec-25) and Harper Engineering (Jan-26).
B12: y/y % | D12: =IF(AND(ISNUMBER(D11),ISNUMBER(C11)),IFERROR(D11/C11-1,""),"") | E12: =IF(AND(ISNUMBER(E11),ISNUMBER(D11)),IFERROR(E11/D11-1,""),"") | F12: =IF(AND(ISNUMBER(F11),ISNUMBER(E11)),IFERROR(F11/E11-1,""),"") | G12: =IF(AND(ISNUMBER(G11),ISNUMBER(F11)),IFERROR(G11/F11-1,""),"") | H12: =IF(AND(ISNUMBER(H11),ISNUMBER(G11)),IFERROR(H11/G11-1,""),"") | I12: =IF(AND(ISNUMBER(I11),ISNUMBER(H11)),IFERROR(I11/H11-1,""),"") | J12: =IF(AND(ISNUMBER(J11),ISNUMBER(I11)),IFERROR(J11/I11-1,""),"") | K12: =IF(AND(ISNUMBER(K11),ISNUMBER(J11)),IFERROR(K11/J11-1,""),"") | L12: =IF(AND(ISNUMBER(L11),ISNUMBER(K11)),IFERROR(L11/K11-1,""),"") | Q12: =IF(AND(ISNUMBER(Q11),ISNUMBER(L11)),IFERROR(Q11/L11-1,""),"") | R12: =IF(AND(ISNUMBER(R11),ISNUMBER(M11)),IFERROR(R11/M11-1,""),"") | S12: =IF(AND(ISNUMBER(S11),ISNUMBER(N11)),IFERROR(S11/N11-1,""),"") | T12: =IF(AND(ISNUMBER(T11),ISNUMBER(O11)),IFERROR(T11/O11-1,""),"") | U12: =IF(AND(ISNUMBER(U11),ISNUMBER(P11)),IFERROR(U11/P11-1,""),"") | V12: =IF(AND(ISNUMBER(V11),ISNUMBER(Q11)),IFERROR(V11/Q11-1,""),"") | W12: =IF(AND(ISNUMBER(W11),ISNUMBER(R11)),IFERROR(W11/R11-1,""),"") | X12: =IF(AND(ISNUMBER(X11),ISNUMBER(S11)),IFERROR(X11/S11-1,""),"") | ... AH12: =IF(AND(ISNUMBER(AH11),ISNUMBER(AC11)),IFERROR(AH11/AC11-1,""),"") | AI12: =AI13+$AI$101 | AJ12: =AJ13+$AI$101 | AK12: =IF(AND(ISNUMBER(AK11),ISNUMBER(AF11)),IFERROR(AK11/AF11-1,""),"") | AL12: =CHOOSE(MATCH($AP$2,{"Bull","Base","Bear"},0),$AY$29,$AZ$29,$BA$29) | AM12: =CHOOSE(MATCH($AP$2,{"Bull","Base","Bear"},0),$AY$30,$AZ$30,$BA$30) | AN12: =CHOOSE(MATCH($AP$2,{"Bull","Base","Bear"},0),$AY$31,$AZ$31,$BA$31) | AO12: =CHOOSE(MATCH($AP$2,{"Bull","Base","Bear"},0),$AY$32,$AZ$32,$BA$32) | AP12: Q3/Q4-26E: growth before calibration (row below) + revenue-outlook calibration Δ (Group block). 2027E–2030E: scenario lever (Bull/Base/Bear table →). | AX12: FY26 net sales ($m) | AY12: 675 | AZ12: 670 | BA12: 665 | BB12: Guided $665–675m (+35% y/y at mid). Drives the Q3/Q4-26E revenue calibration.
B13: Q3/Q4-26E growth before revenue calibration (1H/26 y/y) | AI13: =IFERROR((AG11+AH11)/(AB11+AC11)-1,0) | AJ13: =IFERROR((AG11+AH11)/(AB11+AC11)-1,0) | AP13: 1H/26 y/y growth of the line: includes LMB (closed 23-Dec-2025) and Harper Engineering (21-Jan-2026), which stay inorganic through Q4/26E; Beadlight anniversaries 28-Jul-2026. | AX13: FY26 Adjusted EBITDA ($m) | AY13: 270 | AZ13: 267.5 | BA13: 265 | BB13: Guided $265–270m (~40% margin). Drives the Q3/Q4-26E margin calibration.
B14: Aftermarket net sales | Q14: 66.697 | R14: 22.919 | S14: 20.211 | T14: 23.886 | U14: 22.188 | V14: 89.204 | W14: 25.149 | X14: 26.894 | Y14: 29.058 | Z14: 28.204 | AA14: 109.305 | AB14: 32.403 | AC14: 34.836 | AD14: 38.169 | AE14: 39.06 | AF14: 144.468 | AG14: 43.515 | AH14: 46.256 | AI14: =AD14*(1+AI15) | AJ14: =AE14*(1+AJ15) | AK14: =SUM(AG14,AH14,AI14,AJ14) | AL14: =AK14*(1+AL15) | AM14: =AL14*(1+AM15) | AN14: =AM14*(1+AN15) | AO14: =AN14*(1+AO15) | AX14: FY26 net income ($m) — memo | AY14: 60 | AZ14: 58 | BA14: 56 | BB14: Guided $56–60m (memo; compared with the model, not forced).
B15: y/y % | D15: =IF(AND(ISNUMBER(D14),ISNUMBER(C14)),IFERROR(D14/C14-1,""),"") | E15: =IF(AND(ISNUMBER(E14),ISNUMBER(D14)),IFERROR(E14/D14-1,""),"") | F15: =IF(AND(ISNUMBER(F14),ISNUMBER(E14)),IFERROR(F14/E14-1,""),"") | G15: =IF(AND(ISNUMBER(G14),ISNUMBER(F14)),IFERROR(G14/F14-1,""),"") | H15: =IF(AND(ISNUMBER(H14),ISNUMBER(G14)),IFERROR(H14/G14-1,""),"") | I15: =IF(AND(ISNUMBER(I14),ISNUMBER(H14)),IFERROR(I14/H14-1,""),"") | J15: =IF(AND(ISNUMBER(J14),ISNUMBER(I14)),IFERROR(J14/I14-1,""),"") | K15: =IF(AND(ISNUMBER(K14),ISNUMBER(J14)),IFERROR(K14/J14-1,""),"") | L15: =IF(AND(ISNUMBER(L14),ISNUMBER(K14)),IFERROR(L14/K14-1,""),"") | Q15: =IF(AND(ISNUMBER(Q14),ISNUMBER(L14)),IFERROR(Q14/L14-1,""),"") | R15: =IF(AND(ISNUMBER(R14),ISNUMBER(M14)),IFERROR(R14/M14-1,""),"") | S15: =IF(AND(ISNUMBER(S14),ISNUMBER(N14)),IFERROR(S14/N14-1,""),"") | T15: =IF(AND(ISNUMBER(T14),ISNUMBER(O14)),IFERROR(T14/O14-1,""),"") | U15: =IF(AND(ISNUMBER(U14),ISNUMBER(P14)),IFERROR(U14/P14-1,""),"") | V15: =IF(AND(ISNUMBER(V14),ISNUMBER(Q14)),IFERROR(V14/Q14-1,""),"") | W15: =IF(AND(ISNUMBER(W14),ISNUMBER(R14)),IFERROR(W14/R14-1,""),"") | X15: =IF(AND(ISNUMBER(X14),ISNUMBER(S14)),IFERROR(X14/S14-1,""),"") | ... AH15: =IF(AND(ISNUMBER(AH14),ISNUMBER(AC14)),IFERROR(AH14/AC14-1,""),"") | AI15: =AI16+$AI$101 | AJ15: =AJ16+$AI$101 | AK15: =IF(AND(ISNUMBER(AK14),ISNUMBER(AF14)),IFERROR(AK14/AF14-1,""),"") | AL15: =CHOOSE(MATCH($AP$2,{"Bull","Base","Bear"},0),$AY$34,$AZ$34,$BA$34) | AM15: =CHOOSE(MATCH($AP$2,{"Bull","Base","Bear"},0),$AY$35,$AZ$35,$BA$35) | AN15: =CHOOSE(MATCH($AP$2,{"Bull","Base","Bear"},0),$AY$36,$AZ$36,$BA$36) | AO15: =CHOOSE(MATCH($AP$2,{"Bull","Base","Bear"},0),$AY$37,$AZ$37,$BA$37) | AX15: FY26 Adjusted EPS ($, current definition) — memo | AY15: 1.36 | AZ15: 1.34 | BA15: 1.32 | BB15: Guided $1.32–1.36 (diluted EPS $0.57–0.62).
B16: Q3/Q4-26E growth before revenue calibration (1H/26 y/y) | AI16: =IFERROR((AG14+AH14)/(AB14+AC14)-1,0) | AJ16: =IFERROR((AG14+AH14)/(AB14+AC14)-1,0) | AX16: 2H/26 share repurchases ($m) | AY16: 0 | AZ16: 0 | BA16: 0 | BB16: No repurchase authorization; capital deployed to M&A / deleveraging.
B17: Commercial aerospace — net sales | C17: =IF(ISNUMBER(C11),C11+C14,"") | D17: =IF(ISNUMBER(D11),D11+D14,"") | E17: =IF(ISNUMBER(E11),E11+E14,"") | F17: =IF(ISNUMBER(F11),F11+F14,"") | G17: =IF(ISNUMBER(G11),G11+G14,"") | H17: =IF(ISNUMBER(H11),H11+H14,"") | I17: =IF(ISNUMBER(I11),I11+I14,"") | J17: =IF(ISNUMBER(J11),J11+J14,"") | ... AO17: =IF(ISNUMBER(AO11),AO11+AO14,"") | AR17: =IFERROR((AO17/AF17)^(1/5)-1,"n/m") | AS17: =IFERROR((AF17/K17)^(1/5)-1,"n/m") | AT17: =IFERROR((AF17/F17)^(1/10)-1,"n/m") | AU17: =IFERROR((AF17/C17)^(1/13)-1,"n/m")
B18: Net sales y/y % | D18: =IF(AND(ISNUMBER(D17),ISNUMBER(C17)),IFERROR(D17/C17-1,""),"") | E18: =IF(AND(ISNUMBER(E17),ISNUMBER(D17)),IFERROR(E17/D17-1,""),"") | F18: =IF(AND(ISNUMBER(F17),ISNUMBER(E17)),IFERROR(F17/E17-1,""),"") | G18: =IF(AND(ISNUMBER(G17),ISNUMBER(F17)),IFERROR(G17/F17-1,""),"") | H18: =IF(AND(ISNUMBER(H17),ISNUMBER(G17)),IFERROR(H17/G17-1,""),"") | I18: =IF(AND(ISNUMBER(I17),ISNUMBER(H17)),IFERROR(I17/H17-1,""),"") | J18: =IF(AND(ISNUMBER(J17),ISNUMBER(I17)),IFERROR(J17/I17-1,""),"") | K18: =IF(AND(ISNUMBER(K17),ISNUMBER(J17)),IFERROR(K17/J17-1,""),"") | L18: =IF(AND(ISNUMBER(L17),ISNUMBER(K17)),IFERROR(L17/K17-1,""),"") | Q18: =IF(AND(ISNUMBER(Q17),ISNUMBER(L17)),IFERROR(Q17/L17-1,""),"") | R18: =IF(AND(ISNUMBER(R17),ISNUMBER(M17)),IFERROR(R17/M17-1,""),"") | S18: =IF(AND(ISNUMBER(S17),ISNUMBER(N17)),IFERROR(S17/N17-1,""),"") | T18: =IF(AND(ISNUMBER(T17),ISNUMBER(O17)),IFERROR(T17/O17-1,""),"") | U18: =IF(AND(ISNUMBER(U17),ISNUMBER(P17)),IFERROR(U17/P17-1,""),"") | V18: =IF(AND(ISNUMBER(V17),ISNUMBER(Q17)),IFERROR(V17/Q17-1,""),"") | W18: =IF(AND(ISNUMBER(W17),ISNUMBER(R17)),IFERROR(W17/R17-1,""),"") | X18: =IF(AND(ISNUMBER(X17),ISNUMBER(S17)),IFERROR(X17/S17-1,""),"") | ... AK18: =IF(AND(ISNUMBER(AK17),ISNUMBER(AF17)),IFERROR(AK17/AF17-1,""),"") | AL18: =IF(AND(ISNUMBER(AL17),ISNUMBER(AK17)),IFERROR(AL17/AK17-1,""),"") | AM18: =IF(AND(ISNUMBER(AM17),ISNUMBER(AL17)),IFERROR(AM17/AL17-1,""),"") | AN18: =IF(AND(ISNUMBER(AN17),ISNUMBER(AM17)),IFERROR(AN17/AM17-1,""),"") | AO18: =IF(AND(ISNUMBER(AO17),ISNUMBER(AN17)),IFERROR(AO17/AN17-1,""),"") | AX18: FY26 point estimates (all cases)
B19: % of total net sales | C19: =IF(AND(ISNUMBER(C17),ISNUMBER(C90)),IFERROR(C17/C90,""),"") | D19: =IF(AND(ISNUMBER(D17),ISNUMBER(D90)),IFERROR(D17/D90,""),"") | E19: =IF(AND(ISNUMBER(E17),ISNUMBER(E90)),IFERROR(E17/E90,""),"") | F19: =IF(AND(ISNUMBER(F17),ISNUMBER(F90)),IFERROR(F17/F90,""),"") | G19: =IF(AND(ISNUMBER(G17),ISNUMBER(G90)),IFERROR(G17/G90,""),"") | H19: =IF(AND(ISNUMBER(H17),ISNUMBER(H90)),IFERROR(H17/H90,""),"") | I19: =IF(AND(ISNUMBER(I17),ISNUMBER(I90)),IFERROR(I17/I90,""),"") | J19: =IF(AND(ISNUMBER(J17),ISNUMBER(J90)),IFERROR(J17/J90,""),"") | ... AO19: =IF(AND(ISNUMBER(AO17),ISNUMBER(AO90)),IFERROR(AO17/AO90,""),"") | AX19: Interest expense, net ($m) | AZ19: 80 | BB19: FY26 guidance: ~$80m (1H/26 $38.7m).
B20: Aftermarket % of end-market sales | C20: =IF(AND(ISNUMBER(C14),ISNUMBER(C17)),IFERROR(C14/C17,""),"") | D20: =IF(AND(ISNUMBER(D14),ISNUMBER(D17)),IFERROR(D14/D17,""),"") | E20: =IF(AND(ISNUMBER(E14),ISNUMBER(E17)),IFERROR(E14/E17,""),"") | F20: =IF(AND(ISNUMBER(F14),ISNUMBER(F17)),IFERROR(F14/F17,""),"") | G20: =IF(AND(ISNUMBER(G14),ISNUMBER(G17)),IFERROR(G14/G17,""),"") | H20: =IF(AND(ISNUMBER(H14),ISNUMBER(H17)),IFERROR(H14/H17,""),"") | I20: =IF(AND(ISNUMBER(I14),ISNUMBER(I17)),IFERROR(I14/I17,""),"") | J20: =IF(AND(ISNUMBER(J14),ISNUMBER(J17)),IFERROR(J14/J17,""),"") | ... AO20: =IF(AND(ISNUMBER(AO14),ISNUMBER(AO17)),IFERROR(AO14/AO17,""),"") | AX20: Depreciation ($m) | AZ20: 15 | BB20: FY26 guidance: ~$15m (1H/26 $6.6m).
AX21: Amortization ($m) | AZ21: 65 | BB21: FY26 guidance: ~$65m (1H/26 $32.3m).
B22: Business jet & general aviation (auto-throttles, brakes, actuation, restraints) | AP22: BUSINESS JET & GENERAL AVIATION — modelling logic | AX22: Tax rate (GAAP & adjusted) | AZ22: 0.24 | BB22: 1H/26 effective rate 23.9% (Q2-26 23.3%); not guided. Net income guidance mid-point implies ~24%.
B23: OEM net sales | Q23: 31.207 | R23: 9.26 | S23: 10.43 | T23: 11.701 | U23: 15.625 | V23: 47.016 | W23: 16.207 | X23: 17.438 | Y23: 19.911 | Z23: 16.542 | AA23: 70.098 | AB23: 19.423 | AC23: 17.895 | AD23: 19.859 | AE23: 17.568 | AF23: 74.745 | AG23: 19.633 | AH23: 20.304 | AI23: =AD23*(1+AI24) | AJ23: =AE23*(1+AJ24) | AK23: =SUM(AG23,AH23,AI23,AJ23) | AL23: =AK23*(1+AL24) | AM23: =AL23*(1+AM24) | AN23: =AM23*(1+AN24) | AO23: =AN23*(1+AO24) | AP23: End-market sales as published (release Table 5; FY2022-23 prospectus note; Q1-23 = 1H-23 − Q2-23). Not published before 2022 or for 2022 quarters. Q3/Q4-26E: prior-year quarter × (1 + growth). 2027E+: prior year × (1 + scenario lever). | AX23: Capital expenditures ($m) | AZ23: 16 | BB23: Not guided; 1H/26 $7.0m, FY25 $13.0m; ~2.4% of FY26E sales.
B24: y/y % | D24: =IF(AND(ISNUMBER(D23),ISNUMBER(C23)),IFERROR(D23/C23-1,""),"") | E24: =IF(AND(ISNUMBER(E23),ISNUMBER(D23)),IFERROR(E23/D23-1,""),"") | F24: =IF(AND(ISNUMBER(F23),ISNUMBER(E23)),IFERROR(F23/E23-1,""),"") | G24: =IF(AND(ISNUMBER(G23),ISNUMBER(F23)),IFERROR(G23/F23-1,""),"") | H24: =IF(AND(ISNUMBER(H23),ISNUMBER(G23)),IFERROR(H23/G23-1,""),"") | I24: =IF(AND(ISNUMBER(I23),ISNUMBER(H23)),IFERROR(I23/H23-1,""),"") | J24: =IF(AND(ISNUMBER(J23),ISNUMBER(I23)),IFERROR(J23/I23-1,""),"") | K24: =IF(AND(ISNUMBER(K23),ISNUMBER(J23)),IFERROR(K23/J23-1,""),"") | L24: =IF(AND(ISNUMBER(L23),ISNUMBER(K23)),IFERROR(L23/K23-1,""),"") | Q24: =IF(AND(ISNUMBER(Q23),ISNUMBER(L23)),IFERROR(Q23/L23-1,""),"") | R24: =IF(AND(ISNUMBER(R23),ISNUMBER(M23)),IFERROR(R23/M23-1,""),"") | S24: =IF(AND(ISNUMBER(S23),ISNUMBER(N23)),IFERROR(S23/N23-1,""),"") | T24: =IF(AND(ISNUMBER(T23),ISNUMBER(O23)),IFERROR(T23/O23-1,""),"") | U24: =IF(AND(ISNUMBER(U23),ISNUMBER(P23)),IFERROR(U23/P23-1,""),"") | V24: =IF(AND(ISNUMBER(V23),ISNUMBER(Q23)),IFERROR(V23/Q23-1,""),"") | W24: =IF(AND(ISNUMBER(W23),ISNUMBER(R23)),IFERROR(W23/R23-1,""),"") | X24: =IF(AND(ISNUMBER(X23),ISNUMBER(S23)),IFERROR(X23/S23-1,""),"") | ... AH24: =IF(AND(ISNUMBER(AH23),ISNUMBER(AC23)),IFERROR(AH23/AC23-1,""),"") | AI24: =AI25+$AI$101 | AJ24: =AJ25+$AI$101 | AK24: =IF(AND(ISNUMBER(AK23),ISNUMBER(AF23)),IFERROR(AK23/AF23-1,""),"") | AL24: =CHOOSE(MATCH($AP$2,{"Bull","Base","Bear"},0),$AY$39,$AZ$39,$BA$39) | AM24: =CHOOSE(MATCH($AP$2,{"Bull","Base","Bear"},0),$AY$40,$AZ$40,$BA$40) | AN24: =CHOOSE(MATCH($AP$2,{"Bull","Base","Bear"},0),$AY$41,$AZ$41,$BA$41) | AO24: =CHOOSE(MATCH($AP$2,{"Bull","Base","Bear"},0),$AY$42,$AZ$42,$BA$42) | AP24: Q3/Q4-26E: growth before calibration (row below) + revenue-outlook calibration Δ (Group block). 2027E–2030E: scenario lever (Bull/Base/Bear table →). | AX24: Transaction expenses ($m) | AZ24: 4 | BB24: 1H/26 $2.8m (Harper Engineering); analyst point estimate for ongoing deal activity.
B25: Q3/Q4-26E growth before revenue calibration (1H/26 y/y) | AI25: =IFERROR((AG23+AH23)/(AB23+AC23)-1,0) | AJ25: =IFERROR((AG23+AH23)/(AB23+AC23)-1,0) | AP25: 1H/26 y/y growth of the line: includes LMB (closed 23-Dec-2025) and Harper Engineering (21-Jan-2026), which stay inorganic through Q4/26E; Beadlight anniversaries 28-Jul-2026.
B26: Aftermarket net sales | Q26: 17.053 | R26: 6.479 | S26: 6.308 | T26: 7.729 | U26: 8.512 | V26: 29.028 | W26: 9.407 | X26: 9.725 | Y26: 10.121 | Z26: 9.853 | AA26: 39.106 | AB26: 11.435 | AC26: 12.267 | AD26: 12.738 | AE26: 12.936 | AF26: 49.376 | AG26: 11.066 | AH26: 13.099 | AI26: =AD26*(1+AI27) | AJ26: =AE26*(1+AJ27) | AK26: =SUM(AG26,AH26,AI26,AJ26) | AL26: =AK26*(1+AL27) | AM26: =AL26*(1+AM27) | AN26: =AM26*(1+AN27) | AO26: =AN26*(1+AO27) | AX26: Minimum net debt / Adjusted EBITDA (x) — buyback floor 2027E+ | AY26: 3 | AZ26: 2.5 | BA26: 2 | BB26: Net debt $830m at 30-Jun-26 = ~3.6x LTM Adjusted EBITDA (~3.1x FY26E guidance mid-point) after LMB / Harper; < 5.5x keeps the SOFR + 4.25% margin. Floor = leverage at which surplus cash is returned via buybacks; until then free cash flow prepays term loans. Bull keeps more firepower deployed (higher floor).
B27: y/y % | D27: =IF(AND(ISNUMBER(D26),ISNUMBER(C26)),IFERROR(D26/C26-1,""),"") | E27: =IF(AND(ISNUMBER(E26),ISNUMBER(D26)),IFERROR(E26/D26-1,""),"") | F27: =IF(AND(ISNUMBER(F26),ISNUMBER(E26)),IFERROR(F26/E26-1,""),"") | G27: =IF(AND(ISNUMBER(G26),ISNUMBER(F26)),IFERROR(G26/F26-1,""),"") | H27: =IF(AND(ISNUMBER(H26),ISNUMBER(G26)),IFERROR(H26/G26-1,""),"") | I27: =IF(AND(ISNUMBER(I26),ISNUMBER(H26)),IFERROR(I26/H26-1,""),"") | J27: =IF(AND(ISNUMBER(J26),ISNUMBER(I26)),IFERROR(J26/I26-1,""),"") | K27: =IF(AND(ISNUMBER(K26),ISNUMBER(J26)),IFERROR(K26/J26-1,""),"") | L27: =IF(AND(ISNUMBER(L26),ISNUMBER(K26)),IFERROR(L26/K26-1,""),"") | Q27: =IF(AND(ISNUMBER(Q26),ISNUMBER(L26)),IFERROR(Q26/L26-1,""),"") | R27: =IF(AND(ISNUMBER(R26),ISNUMBER(M26)),IFERROR(R26/M26-1,""),"") | S27: =IF(AND(ISNUMBER(S26),ISNUMBER(N26)),IFERROR(S26/N26-1,""),"") | T27: =IF(AND(ISNUMBER(T26),ISNUMBER(O26)),IFERROR(T26/O26-1,""),"") | U27: =IF(AND(ISNUMBER(U26),ISNUMBER(P26)),IFERROR(U26/P26-1,""),"") | V27: =IF(AND(ISNUMBER(V26),ISNUMBER(Q26)),IFERROR(V26/Q26-1,""),"") | W27: =IF(AND(ISNUMBER(W26),ISNUMBER(R26)),IFERROR(W26/R26-1,""),"") | X27: =IF(AND(ISNUMBER(X26),ISNUMBER(S26)),IFERROR(X26/S26-1,""),"") | ... AH27: =IF(AND(ISNUMBER(AH26),ISNUMBER(AC26)),IFERROR(AH26/AC26-1,""),"") | AI27: =AI28+$AI$101 | AJ27: =AJ28+$AI$101 | AK27: =IF(AND(ISNUMBER(AK26),ISNUMBER(AF26)),IFERROR(AK26/AF26-1,""),"") | AL27: =CHOOSE(MATCH($AP$2,{"Bull","Base","Bear"},0),$AY$44,$AZ$44,$BA$44) | AM27: =CHOOSE(MATCH($AP$2,{"Bull","Base","Bear"},0),$AY$45,$AZ$45,$BA$45) | AN27: =CHOOSE(MATCH($AP$2,{"Bull","Base","Bear"},0),$AY$46,$AZ$46,$BA$46) | AO27: =CHOOSE(MATCH($AP$2,{"Bull","Base","Bear"},0),$AY$47,$AZ$47,$BA$47)
B28: Q3/Q4-26E growth before revenue calibration (1H/26 y/y) | AI28: =IFERROR((AG26+AH26)/(AB26+AC26)-1,0) | AJ28: =IFERROR((AG26+AH26)/(AB26+AC26)-1,0) | AX28: COM_OEM (commercial aerospace OEM sales y/y) | AY28: 0.03 | AZ28: Δ → | BA28: -0.06 | BB28: Boeing 737 / 787 and Airbus A320 / A350 rate ramps; Harper interiors latches; FY26 commercial + BJ OEM outlook +17–20%.
B29: Business jet & general aviation — net sales | C29: =IF(ISNUMBER(C23),C23+C26,"") | D29: =IF(ISNUMBER(D23),D23+D26,"") | E29: =IF(ISNUMBER(E23),E23+E26,"") | F29: =IF(ISNUMBER(F23),F23+F26,"") | G29: =IF(ISNUMBER(G23),G23+G26,"") | H29: =IF(ISNUMBER(H23),H23+H26,"") | I29: =IF(ISNUMBER(I23),I23+I26,"") | J29: =IF(ISNUMBER(J23),J23+J26,"") | ... AO29: =IF(ISNUMBER(AO23),AO23+AO26,"") | AR29: =IFERROR((AO29/AF29)^(1/5)-1,"n/m") | AS29: =IFERROR((AF29/K29)^(1/5)-1,"n/m") | AT29: =IFERROR((AF29/F29)^(1/10)-1,"n/m") | AU29: =IFERROR((AF29/C29)^(1/13)-1,"n/m") | AX29: 2027E | AY29: =AZ29+$AY$28 | AZ29: 0.14 | BA29: =AZ29+$BA$28
B30: Net sales y/y % | D30: =IF(AND(ISNUMBER(D29),ISNUMBER(C29)),IFERROR(D29/C29-1,""),"") | E30: =IF(AND(ISNUMBER(E29),ISNUMBER(D29)),IFERROR(E29/D29-1,""),"") | F30: =IF(AND(ISNUMBER(F29),ISNUMBER(E29)),IFERROR(F29/E29-1,""),"") | G30: =IF(AND(ISNUMBER(G29),ISNUMBER(F29)),IFERROR(G29/F29-1,""),"") | H30: =IF(AND(ISNUMBER(H29),ISNUMBER(G29)),IFERROR(H29/G29-1,""),"") | I30: =IF(AND(ISNUMBER(I29),ISNUMBER(H29)),IFERROR(I29/H29-1,""),"") | J30: =IF(AND(ISNUMBER(J29),ISNUMBER(I29)),IFERROR(J29/I29-1,""),"") | K30: =IF(AND(ISNUMBER(K29),ISNUMBER(J29)),IFERROR(K29/J29-1,""),"") | L30: =IF(AND(ISNUMBER(L29),ISNUMBER(K29)),IFERROR(L29/K29-1,""),"") | Q30: =IF(AND(ISNUMBER(Q29),ISNUMBER(L29)),IFERROR(Q29/L29-1,""),"") | R30: =IF(AND(ISNUMBER(R29),ISNUMBER(M29)),IFERROR(R29/M29-1,""),"") | S30: =IF(AND(ISNUMBER(S29),ISNUMBER(N29)),IFERROR(S29/N29-1,""),"") | T30: =IF(AND(ISNUMBER(T29),ISNUMBER(O29)),IFERROR(T29/O29-1,""),"") | U30: =IF(AND(ISNUMBER(U29),ISNUMBER(P29)),IFERROR(U29/P29-1,""),"") | V30: =IF(AND(ISNUMBER(V29),ISNUMBER(Q29)),IFERROR(V29/Q29-1,""),"") | W30: =IF(AND(ISNUMBER(W29),ISNUMBER(R29)),IFERROR(W29/R29-1,""),"") | X30: =IF(AND(ISNUMBER(X29),ISNUMBER(S29)),IFERROR(X29/S29-1,""),"") | ... AK30: =IF(AND(ISNUMBER(AK29),ISNUMBER(AF29)),IFERROR(AK29/AF29-1,""),"") | AL30: =IF(AND(ISNUMBER(AL29),ISNUMBER(AK29)),IFERROR(AL29/AK29-1,""),"") | AM30: =IF(AND(ISNUMBER(AM29),ISNUMBER(AL29)),IFERROR(AM29/AL29-1,""),"") | AN30: =IF(AND(ISNUMBER(AN29),ISNUMBER(AM29)),IFERROR(AN29/AM29-1,""),"") | AO30: =IF(AND(ISNUMBER(AO29),ISNUMBER(AN29)),IFERROR(AO29/AN29-1,""),"") | AX30: 2028E | AY30: =AZ30+$AY$28 | AZ30: 0.12 | BA30: =AZ30+$BA$28
B31: % of total net sales | C31: =IF(AND(ISNUMBER(C29),ISNUMBER(C90)),IFERROR(C29/C90,""),"") | D31: =IF(AND(ISNUMBER(D29),ISNUMBER(D90)),IFERROR(D29/D90,""),"") | E31: =IF(AND(ISNUMBER(E29),ISNUMBER(E90)),IFERROR(E29/E90,""),"") | F31: =IF(AND(ISNUMBER(F29),ISNUMBER(F90)),IFERROR(F29/F90,""),"") | G31: =IF(AND(ISNUMBER(G29),ISNUMBER(G90)),IFERROR(G29/G90,""),"") | H31: =IF(AND(ISNUMBER(H29),ISNUMBER(H90)),IFERROR(H29/H90,""),"") | I31: =IF(AND(ISNUMBER(I29),ISNUMBER(I90)),IFERROR(I29/I90,""),"") | J31: =IF(AND(ISNUMBER(J29),ISNUMBER(J90)),IFERROR(J29/J90,""),"") | ... AO31: =IF(AND(ISNUMBER(AO29),ISNUMBER(AO90)),IFERROR(AO29/AO90,""),"") | AX31: 2029E | AY31: =AZ31+$AY$28 | AZ31: 0.1 | BA31: =AZ31+$BA$28
B32: Aftermarket % of end-market sales | C32: =IF(AND(ISNUMBER(C26),ISNUMBER(C29)),IFERROR(C26/C29,""),"") | D32: =IF(AND(ISNUMBER(D26),ISNUMBER(D29)),IFERROR(D26/D29,""),"") | E32: =IF(AND(ISNUMBER(E26),ISNUMBER(E29)),IFERROR(E26/E29,""),"") | F32: =IF(AND(ISNUMBER(F26),ISNUMBER(F29)),IFERROR(F26/F29,""),"") | G32: =IF(AND(ISNUMBER(G26),ISNUMBER(G29)),IFERROR(G26/G29,""),"") | H32: =IF(AND(ISNUMBER(H26),ISNUMBER(H29)),IFERROR(H26/H29,""),"") | I32: =IF(AND(ISNUMBER(I26),ISNUMBER(I29)),IFERROR(I26/I29,""),"") | J32: =IF(AND(ISNUMBER(J26),ISNUMBER(J29)),IFERROR(J26/J29,""),"") | ... AO32: =IF(AND(ISNUMBER(AO26),ISNUMBER(AO29)),IFERROR(AO26/AO29,""),"") | AX32: 2030E | AY32: =AZ32+$AY$28 | AZ32: 0.09 | BA32: =AZ32+$BA$28
AX33: COM_AM (commercial aerospace aftermarket y/y) | AY33: 0.02 | AZ33: Δ → | BA33: -0.04 | BB33: Installed-base growth, aging fleets and price (proprietary, sole-source parts); FY26 outlook low-double digits.
B34: Defense (military aircraft components, restraints, sensors; LMB fans & motors from Dec-2025) | AP34: DEFENSE — modelling logic | AX34: 2027E | AY34: =AZ34+$AY$33 | AZ34: 0.1 | BA34: =AZ34+$BA$33
B35: OEM net sales | Q35: 26.631 | R35: 7.392 | S35: 7.15 | T35: 8.004 | U35: 7.853 | V35: 30.399 | W35: 7.786 | X35: 8.855 | Y35: 10.152 | Z35: 11.523 | AA35: 38.316 | AB35: 11.726 | AC35: 14.332 | AD35: 13.752 | AE35: 16.16 | AF35: 55.97 | AG35: 23.042 | AH35: 26.971 | AI35: =AD35*(1+AI36) | AJ35: =AE35*(1+AJ36) | AK35: =SUM(AG35,AH35,AI35,AJ35) | AL35: =AK35*(1+AL36) | AM35: =AL35*(1+AM36) | AN35: =AM35*(1+AN36) | AO35: =AN35*(1+AO36) | AP35: End-market sales as published (release Table 5; FY2022-23 prospectus note; Q1-23 = 1H-23 − Q2-23). Not published before 2022 or for 2022 quarters. Q3/Q4-26E: prior-year quarter × (1 + growth). 2027E+: prior year × (1 + scenario lever). | AX35: 2028E | AY35: =AZ35+$AY$33 | AZ35: 0.09 | BA35: =AZ35+$BA$33
B36: y/y % | D36: =IF(AND(ISNUMBER(D35),ISNUMBER(C35)),IFERROR(D35/C35-1,""),"") | E36: =IF(AND(ISNUMBER(E35),ISNUMBER(D35)),IFERROR(E35/D35-1,""),"") | F36: =IF(AND(ISNUMBER(F35),ISNUMBER(E35)),IFERROR(F35/E35-1,""),"") | G36: =IF(AND(ISNUMBER(G35),ISNUMBER(F35)),IFERROR(G35/F35-1,""),"") | H36: =IF(AND(ISNUMBER(H35),ISNUMBER(G35)),IFERROR(H35/G35-1,""),"") | I36: =IF(AND(ISNUMBER(I35),ISNUMBER(H35)),IFERROR(I35/H35-1,""),"") | J36: =IF(AND(ISNUMBER(J35),ISNUMBER(I35)),IFERROR(J35/I35-1,""),"") | K36: =IF(AND(ISNUMBER(K35),ISNUMBER(J35)),IFERROR(K35/J35-1,""),"") | L36: =IF(AND(ISNUMBER(L35),ISNUMBER(K35)),IFERROR(L35/K35-1,""),"") | Q36: =IF(AND(ISNUMBER(Q35),ISNUMBER(L35)),IFERROR(Q35/L35-1,""),"") | R36: =IF(AND(ISNUMBER(R35),ISNUMBER(M35)),IFERROR(R35/M35-1,""),"") | S36: =IF(AND(ISNUMBER(S35),ISNUMBER(N35)),IFERROR(S35/N35-1,""),"") | T36: =IF(AND(ISNUMBER(T35),ISNUMBER(O35)),IFERROR(T35/O35-1,""),"") | U36: =IF(AND(ISNUMBER(U35),ISNUMBER(P35)),IFERROR(U35/P35-1,""),"") | V36: =IF(AND(ISNUMBER(V35),ISNUMBER(Q35)),IFERROR(V35/Q35-1,""),"") | W36: =IF(AND(ISNUMBER(W35),ISNUMBER(R35)),IFERROR(W35/R35-1,""),"") | X36: =IF(AND(ISNUMBER(X35),ISNUMBER(S35)),IFERROR(X35/S35-1,""),"") | ... AH36: =IF(AND(ISNUMBER(AH35),ISNUMBER(AC35)),IFERROR(AH35/AC35-1,""),"") | AI36: =AI37+$AI$101 | AJ36: =AJ37+$AI$101 | AK36: =IF(AND(ISNUMBER(AK35),ISNUMBER(AF35)),IFERROR(AK35/AF35-1,""),"") | AL36: =CHOOSE(MATCH($AP$2,{"Bull","Base","Bear"},0),$AY$49,$AZ$49,$BA$49) | AM36: =CHOOSE(MATCH($AP$2,{"Bull","Base","Bear"},0),$AY$50,$AZ$50,$BA$50) | AN36: =CHOOSE(MATCH($AP$2,{"Bull","Base","Bear"},0),$AY$51,$AZ$51,$BA$51) | AO36: =CHOOSE(MATCH($AP$2,{"Bull","Base","Bear"},0),$AY$52,$AZ$52,$BA$52) | AP36: Q3/Q4-26E: growth before calibration (row below) + revenue-outlook calibration Δ (Group block). 2027E–2030E: scenario lever (Bull/Base/Bear table →). | AX36: 2029E | AY36: =AZ36+$AY$33 | AZ36: 0.08 | BA36: =AZ36+$BA$33
B37: Q3/Q4-26E growth before revenue calibration (1H/26 y/y) | AI37: =IFERROR((AG35+AH35)/(AB35+AC35)-1,0) | AJ37: =IFERROR((AG35+AH35)/(AB35+AC35)-1,0) | AP37: 1H/26 y/y growth of the line: includes LMB (closed 23-Dec-2025) and Harper Engineering (21-Jan-2026), which stay inorganic through Q4/26E; Beadlight anniversaries 28-Jul-2026. | AX37: 2030E | AY37: =AZ37+$AY$33 | AZ37: 0.08 | BA37: =AZ37+$BA$33
B38: Aftermarket net sales | Q38: 31.554 | R38: 7.842 | S38: 5.996 | T38: 7.218 | U38: 7.783 | V38: 28.839 | W38: 8.849 | X38: 12.022 | Y38: 11.81 | Z38: 17.951 | AA38: 50.632 | AB38: 17.056 | AC38: 17.139 | AD38: 15.032 | AE38: 17.442 | AF38: 66.669 | AG38: 17.607 | AH38: 18.062 | AI38: =AD38*(1+AI39) | AJ38: =AE38*(1+AJ39) | AK38: =SUM(AG38,AH38,AI38,AJ38) | AL38: =AK38*(1+AL39) | AM38: =AL38*(1+AM39) | AN38: =AM38*(1+AN39) | AO38: =AN38*(1+AO39) | AX38: BJ_OEM (business jet & GA OEM y/y) | AY38: 0.02 | AZ38: Δ → | BA38: -0.05 | BB38: Business-jet deliveries (Gulfstream G700/G800, Bombardier Global 8000, Textron); auto-throttle content.
B39: y/y % | D39: =IF(AND(ISNUMBER(D38),ISNUMBER(C38)),IFERROR(D38/C38-1,""),"") | E39: =IF(AND(ISNUMBER(E38),ISNUMBER(D38)),IFERROR(E38/D38-1,""),"") | F39: =IF(AND(ISNUMBER(F38),ISNUMBER(E38)),IFERROR(F38/E38-1,""),"") | G39: =IF(AND(ISNUMBER(G38),ISNUMBER(F38)),IFERROR(G38/F38-1,""),"") | H39: =IF(AND(ISNUMBER(H38),ISNUMBER(G38)),IFERROR(H38/G38-1,""),"") | I39: =IF(AND(ISNUMBER(I38),ISNUMBER(H38)),IFERROR(I38/H38-1,""),"") | J39: =IF(AND(ISNUMBER(J38),ISNUMBER(I38)),IFERROR(J38/I38-1,""),"") | K39: =IF(AND(ISNUMBER(K38),ISNUMBER(J38)),IFERROR(K38/J38-1,""),"") | L39: =IF(AND(ISNUMBER(L38),ISNUMBER(K38)),IFERROR(L38/K38-1,""),"") | Q39: =IF(AND(ISNUMBER(Q38),ISNUMBER(L38)),IFERROR(Q38/L38-1,""),"") | R39: =IF(AND(ISNUMBER(R38),ISNUMBER(M38)),IFERROR(R38/M38-1,""),"") | S39: =IF(AND(ISNUMBER(S38),ISNUMBER(N38)),IFERROR(S38/N38-1,""),"") | T39: =IF(AND(ISNUMBER(T38),ISNUMBER(O38)),IFERROR(T38/O38-1,""),"") | U39: =IF(AND(ISNUMBER(U38),ISNUMBER(P38)),IFERROR(U38/P38-1,""),"") | V39: =IF(AND(ISNUMBER(V38),ISNUMBER(Q38)),IFERROR(V38/Q38-1,""),"") | W39: =IF(AND(ISNUMBER(W38),ISNUMBER(R38)),IFERROR(W38/R38-1,""),"") | X39: =IF(AND(ISNUMBER(X38),ISNUMBER(S38)),IFERROR(X38/S38-1,""),"") | ... AH39: =IF(AND(ISNUMBER(AH38),ISNUMBER(AC38)),IFERROR(AH38/AC38-1,""),"") | AI39: =AI40+$AI$101 | AJ39: =AJ40+$AI$101 | AK39: =IF(AND(ISNUMBER(AK38),ISNUMBER(AF38)),IFERROR(AK38/AF38-1,""),"") | AL39: =CHOOSE(MATCH($AP$2,{"Bull","Base","Bear"},0),$AY$54,$AZ$54,$BA$54) | AM39: =CHOOSE(MATCH($AP$2,{"Bull","Base","Bear"},0),$AY$55,$AZ$55,$BA$55) | AN39: =CHOOSE(MATCH($AP$2,{"Bull","Base","Bear"},0),$AY$56,$AZ$56,$BA$56) | AO39: =CHOOSE(MATCH($AP$2,{"Bull","Base","Bear"},0),$AY$57,$AZ$57,$BA$57) | AX39: 2027E | AY39: =AZ39+$AY$38 | AZ39: 0.07 | BA39: =AZ39+$BA$38
B40: Q3/Q4-26E growth before revenue calibration (1H/26 y/y) | AI40: =IFERROR((AG38+AH38)/(AB38+AC38)-1,0) | AJ40: =IFERROR((AG38+AH38)/(AB38+AC38)-1,0) | AX40: 2028E | AY40: =AZ40+$AY$38 | AZ40: 0.06 | BA40: =AZ40+$BA$38
B41: Defense — net sales | C41: =IF(ISNUMBER(C35),C35+C38,"") | D41: =IF(ISNUMBER(D35),D35+D38,"") | E41: =IF(ISNUMBER(E35),E35+E38,"") | F41: =IF(ISNUMBER(F35),F35+F38,"") | G41: =IF(ISNUMBER(G35),G35+G38,"") | H41: =IF(ISNUMBER(H35),H35+H38,"") | I41: =IF(ISNUMBER(I35),I35+I38,"") | J41: =IF(ISNUMBER(J35),J35+J38,"") | ... AO41: =IF(ISNUMBER(AO35),AO35+AO38,"") | AR41: =IFERROR((AO41/AF41)^(1/5)-1,"n/m") | AS41: =IFERROR((AF41/K41)^(1/5)-1,"n/m") | AT41: =IFERROR((AF41/F41)^(1/10)-1,"n/m") | AU41: =IFERROR((AF41/C41)^(1/13)-1,"n/m") | AX41: 2029E | AY41: =AZ41+$AY$38 | AZ41: 0.06 | BA41: =AZ41+$BA$38
B42: Net sales y/y % | D42: =IF(AND(ISNUMBER(D41),ISNUMBER(C41)),IFERROR(D41/C41-1,""),"") | E42: =IF(AND(ISNUMBER(E41),ISNUMBER(D41)),IFERROR(E41/D41-1,""),"") | F42: =IF(AND(ISNUMBER(F41),ISNUMBER(E41)),IFERROR(F41/E41-1,""),"") | G42: =IF(AND(ISNUMBER(G41),ISNUMBER(F41)),IFERROR(G41/F41-1,""),"") | H42: =IF(AND(ISNUMBER(H41),ISNUMBER(G41)),IFERROR(H41/G41-1,""),"") | I42: =IF(AND(ISNUMBER(I41),ISNUMBER(H41)),IFERROR(I41/H41-1,""),"") | J42: =IF(AND(ISNUMBER(J41),ISNUMBER(I41)),IFERROR(J41/I41-1,""),"") | K42: =IF(AND(ISNUMBER(K41),ISNUMBER(J41)),IFERROR(K41/J41-1,""),"") | L42: =IF(AND(ISNUMBER(L41),ISNUMBER(K41)),IFERROR(L41/K41-1,""),"") | Q42: =IF(AND(ISNUMBER(Q41),ISNUMBER(L41)),IFERROR(Q41/L41-1,""),"") | R42: =IF(AND(ISNUMBER(R41),ISNUMBER(M41)),IFERROR(R41/M41-1,""),"") | S42: =IF(AND(ISNUMBER(S41),ISNUMBER(N41)),IFERROR(S41/N41-1,""),"") | T42: =IF(AND(ISNUMBER(T41),ISNUMBER(O41)),IFERROR(T41/O41-1,""),"") | U42: =IF(AND(ISNUMBER(U41),ISNUMBER(P41)),IFERROR(U41/P41-1,""),"") | V42: =IF(AND(ISNUMBER(V41),ISNUMBER(Q41)),IFERROR(V41/Q41-1,""),"") | W42: =IF(AND(ISNUMBER(W41),ISNUMBER(R41)),IFERROR(W41/R41-1,""),"") | X42: =IF(AND(ISNUMBER(X41),ISNUMBER(S41)),IFERROR(X41/S41-1,""),"") | ... AK42: =IF(AND(ISNUMBER(AK41),ISNUMBER(AF41)),IFERROR(AK41/AF41-1,""),"") | AL42: =IF(AND(ISNUMBER(AL41),ISNUMBER(AK41)),IFERROR(AL41/AK41-1,""),"") | AM42: =IF(AND(ISNUMBER(AM41),ISNUMBER(AL41)),IFERROR(AM41/AL41-1,""),"") | AN42: =IF(AND(ISNUMBER(AN41),ISNUMBER(AM41)),IFERROR(AN41/AM41-1,""),"") | AO42: =IF(AND(ISNUMBER(AO41),ISNUMBER(AN41)),IFERROR(AO41/AN41-1,""),"") | AX42: 2030E | AY42: =AZ42+$AY$38 | AZ42: 0.05 | BA42: =AZ42+$BA$38
B43: % of total net sales | C43: =IF(AND(ISNUMBER(C41),ISNUMBER(C90)),IFERROR(C41/C90,""),"") | D43: =IF(AND(ISNUMBER(D41),ISNUMBER(D90)),IFERROR(D41/D90,""),"") | E43: =IF(AND(ISNUMBER(E41),ISNUMBER(E90)),IFERROR(E41/E90,""),"") | F43: =IF(AND(ISNUMBER(F41),ISNUMBER(F90)),IFERROR(F41/F90,""),"") | G43: =IF(AND(ISNUMBER(G41),ISNUMBER(G90)),IFERROR(G41/G90,""),"") | H43: =IF(AND(ISNUMBER(H41),ISNUMBER(H90)),IFERROR(H41/H90,""),"") | I43: =IF(AND(ISNUMBER(I41),ISNUMBER(I90)),IFERROR(I41/I90,""),"") | J43: =IF(AND(ISNUMBER(J41),ISNUMBER(J90)),IFERROR(J41/J90,""),"") | ... AO43: =IF(AND(ISNUMBER(AO41),ISNUMBER(AO90)),IFERROR(AO41/AO90,""),"") | AX43: BJ_AM (business jet & GA aftermarket y/y) | AY43: 0.02 | AZ43: Δ → | BA43: -0.03 | BB43: Flight hours of the business-jet fleet; brakes and replacement parts.
B44: Aftermarket % of end-market sales | C44: =IF(AND(ISNUMBER(C38),ISNUMBER(C41)),IFERROR(C38/C41,""),"") | D44: =IF(AND(ISNUMBER(D38),ISNUMBER(D41)),IFERROR(D38/D41,""),"") | E44: =IF(AND(ISNUMBER(E38),ISNUMBER(E41)),IFERROR(E38/E41,""),"") | F44: =IF(AND(ISNUMBER(F38),ISNUMBER(F41)),IFERROR(F38/F41,""),"") | G44: =IF(AND(ISNUMBER(G38),ISNUMBER(G41)),IFERROR(G38/G41,""),"") | H44: =IF(AND(ISNUMBER(H38),ISNUMBER(H41)),IFERROR(H38/H41,""),"") | I44: =IF(AND(ISNUMBER(I38),ISNUMBER(I41)),IFERROR(I38/I41,""),"") | J44: =IF(AND(ISNUMBER(J38),ISNUMBER(J41)),IFERROR(J38/J41,""),"") | ... AO44: =IF(AND(ISNUMBER(AO38),ISNUMBER(AO41)),IFERROR(AO38/AO41,""),"") | AX44: 2027E | AY44: =AZ44+$AY$43 | AZ44: 0.08 | BA44: =AZ44+$BA$43
AX45: 2028E | AY45: =AZ45+$AY$43 | AZ45: 0.07 | BA45: =AZ45+$BA$43
B46: Other (industrial / non-aerospace; "Non-Aerospace" in the Q2-25 and Q3-25 releases) | AP46: OTHER / NON-AEROSPACE — modelling logic | AX46: 2029E | AY46: =AZ46+$AY$43 | AZ46: 0.07 | BA46: =AZ46+$BA$43
B47: OEM net sales | Q47: 12.626 | R47: 4.59 | S47: 5.066 | T47: 5.667 | U47: 5.722 | V47: 21.045 | W47: 4.3 | X47: 3.451 | Y47: 2.976 | Z47: 3.269 | AA47: 13.996 | AB47: 2.866 | AC47: 2.655 | AD47: 3.315 | AE47: 3.947 | AF47: 12.783 | AG47: 4.768 | AH47: 5.001 | AI47: =AD47*(1+AI48) | AJ47: =AE47*(1+AJ48) | AK47: =SUM(AG47,AH47,AI47,AJ47) | AL47: =AK47*(1+AL48) | AM47: =AL47*(1+AM48) | AN47: =AM47*(1+AN48) | AO47: =AN47*(1+AO48) | AP47: End-market sales as published (release Table 5; FY2022-23 prospectus note; Q1-23 = 1H-23 − Q2-23). Not published before 2022 or for 2022 quarters. Q3/Q4-26E: prior-year quarter × (1 + growth). 2027E+: prior year × (1 + scenario lever). | AX47: 2030E | AY47: =AZ47+$AY$43 | AZ47: 0.06 | BA47: =AZ47+$BA$43
B48: y/y % | D48: =IF(AND(ISNUMBER(D47),ISNUMBER(C47)),IFERROR(D47/C47-1,""),"") | E48: =IF(AND(ISNUMBER(E47),ISNUMBER(D47)),IFERROR(E47/D47-1,""),"") | F48: =IF(AND(ISNUMBER(F47),ISNUMBER(E47)),IFERROR(F47/E47-1,""),"") | G48: =IF(AND(ISNUMBER(G47),ISNUMBER(F47)),IFERROR(G47/F47-1,""),"") | H48: =IF(AND(ISNUMBER(H47),ISNUMBER(G47)),IFERROR(H47/G47-1,""),"") | I48: =IF(AND(ISNUMBER(I47),ISNUMBER(H47)),IFERROR(I47/H47-1,""),"") | J48: =IF(AND(ISNUMBER(J47),ISNUMBER(I47)),IFERROR(J47/I47-1,""),"") | K48: =IF(AND(ISNUMBER(K47),ISNUMBER(J47)),IFERROR(K47/J47-1,""),"") | L48: =IF(AND(ISNUMBER(L47),ISNUMBER(K47)),IFERROR(L47/K47-1,""),"") | Q48: =IF(AND(ISNUMBER(Q47),ISNUMBER(L47)),IFERROR(Q47/L47-1,""),"") | R48: =IF(AND(ISNUMBER(R47),ISNUMBER(M47)),IFERROR(R47/M47-1,""),"") | S48: =IF(AND(ISNUMBER(S47),ISNUMBER(N47)),IFERROR(S47/N47-1,""),"") | T48: =IF(AND(ISNUMBER(T47),ISNUMBER(O47)),IFERROR(T47/O47-1,""),"") | U48: =IF(AND(ISNUMBER(U47),ISNUMBER(P47)),IFERROR(U47/P47-1,""),"") | V48: =IF(AND(ISNUMBER(V47),ISNUMBER(Q47)),IFERROR(V47/Q47-1,""),"") | W48: =IF(AND(ISNUMBER(W47),ISNUMBER(R47)),IFERROR(W47/R47-1,""),"") | X48: =IF(AND(ISNUMBER(X47),ISNUMBER(S47)),IFERROR(X47/S47-1,""),"") | ... AH48: =IF(AND(ISNUMBER(AH47),ISNUMBER(AC47)),IFERROR(AH47/AC47-1,""),"") | AI48: =AI49+$AI$101 | AJ48: =AJ49+$AI$101 | AK48: =IF(AND(ISNUMBER(AK47),ISNUMBER(AF47)),IFERROR(AK47/AF47-1,""),"") | AL48: =CHOOSE(MATCH($AP$2,{"Bull","Base","Bear"},0),$AY$59,$AZ$59,$BA$59) | AM48: =CHOOSE(MATCH($AP$2,{"Bull","Base","Bear"},0),$AY$60,$AZ$60,$BA$60) | AN48: =CHOOSE(MATCH($AP$2,{"Bull","Base","Bear"},0),$AY$61,$AZ$61,$BA$61) | AO48: =CHOOSE(MATCH($AP$2,{"Bull","Base","Bear"},0),$AY$62,$AZ$62,$BA$62) | AP48: Q3/Q4-26E: growth before calibration (row below) + revenue-outlook calibration Δ (Group block). 2027E–2030E: scenario lever (Bull/Base/Bear table →). | AX48: DEF_OEM (defense OEM y/y) | AY48: 0.02 | AZ48: Δ → | BA48: -0.04 | BB48: Military aircraft and systems build (LMB fans & motors from Dec-25); FY26 defense outlook mid-single digits.
B49: Q3/Q4-26E growth before revenue calibration (1H/26 y/y) | AI49: =IFERROR((AG47+AH47)/(AB47+AC47)-1,0) | AJ49: =IFERROR((AG47+AH47)/(AB47+AC47)-1,0) | AP49: 1H/26 y/y growth of the line: includes LMB (closed 23-Dec-2025) and Harper Engineering (21-Jan-2026), which stay inorganic through Q4/26E; Beadlight anniversaries 28-Jul-2026. | AX49: 2027E | AY49: =AZ49+$AY$48 | AZ49: 0.08 | BA49: =AZ49+$BA$48
B50: Aftermarket net sales | Q50: 12.874 | R50: 3.553 | S50: 5.126 | T50: 4.028 | U50: 4.513 | V50: 17.22 | W50: 3.953 | X50: 4.331 | Y50: 3.667 | Z50: 4.404 | AA50: 16.355 | AB50: 3.686 | AC50: 4.559 | AD50: 3.227 | AE50: 3.409 | AF50: 14.881 | AG50: 4.936 | AH50: 4.726 | AI50: =AD50*(1+AI51) | AJ50: =AE50*(1+AJ51) | AK50: =SUM(AG50,AH50,AI50,AJ50) | AL50: =AK50*(1+AL51) | AM50: =AL50*(1+AM51) | AN50: =AM50*(1+AN51) | AO50: =AN50*(1+AO51) | AX50: 2028E | AY50: =AZ50+$AY$48 | AZ50: 0.07 | BA50: =AZ50+$BA$48
B51: y/y % | D51: =IF(AND(ISNUMBER(D50),ISNUMBER(C50)),IFERROR(D50/C50-1,""),"") | E51: =IF(AND(ISNUMBER(E50),ISNUMBER(D50)),IFERROR(E50/D50-1,""),"") | F51: =IF(AND(ISNUMBER(F50),ISNUMBER(E50)),IFERROR(F50/E50-1,""),"") | G51: =IF(AND(ISNUMBER(G50),ISNUMBER(F50)),IFERROR(G50/F50-1,""),"") | H51: =IF(AND(ISNUMBER(H50),ISNUMBER(G50)),IFERROR(H50/G50-1,""),"") | I51: =IF(AND(ISNUMBER(I50),ISNUMBER(H50)),IFERROR(I50/H50-1,""),"") | J51: =IF(AND(ISNUMBER(J50),ISNUMBER(I50)),IFERROR(J50/I50-1,""),"") | K51: =IF(AND(ISNUMBER(K50),ISNUMBER(J50)),IFERROR(K50/J50-1,""),"") | L51: =IF(AND(ISNUMBER(L50),ISNUMBER(K50)),IFERROR(L50/K50-1,""),"") | Q51: =IF(AND(ISNUMBER(Q50),ISNUMBER(L50)),IFERROR(Q50/L50-1,""),"") | R51: =IF(AND(ISNUMBER(R50),ISNUMBER(M50)),IFERROR(R50/M50-1,""),"") | S51: =IF(AND(ISNUMBER(S50),ISNUMBER(N50)),IFERROR(S50/N50-1,""),"") | T51: =IF(AND(ISNUMBER(T50),ISNUMBER(O50)),IFERROR(T50/O50-1,""),"") | U51: =IF(AND(ISNUMBER(U50),ISNUMBER(P50)),IFERROR(U50/P50-1,""),"") | V51: =IF(AND(ISNUMBER(V50),ISNUMBER(Q50)),IFERROR(V50/Q50-1,""),"") | W51: =IF(AND(ISNUMBER(W50),ISNUMBER(R50)),IFERROR(W50/R50-1,""),"") | X51: =IF(AND(ISNUMBER(X50),ISNUMBER(S50)),IFERROR(X50/S50-1,""),"") | ... AH51: =IF(AND(ISNUMBER(AH50),ISNUMBER(AC50)),IFERROR(AH50/AC50-1,""),"") | AI51: =AI52+$AI$101 | AJ51: =AJ52+$AI$101 | AK51: =IF(AND(ISNUMBER(AK50),ISNUMBER(AF50)),IFERROR(AK50/AF50-1,""),"") | AL51: =CHOOSE(MATCH($AP$2,{"Bull","Base","Bear"},0),$AY$64,$AZ$64,$BA$64) | AM51: =CHOOSE(MATCH($AP$2,{"Bull","Base","Bear"},0),$AY$65,$AZ$65,$BA$65) | AN51: =CHOOSE(MATCH($AP$2,{"Bull","Base","Bear"},0),$AY$66,$AZ$66,$BA$66) | AO51: =CHOOSE(MATCH($AP$2,{"Bull","Base","Bear"},0),$AY$67,$AZ$67,$BA$67) | AX51: 2029E | AY51: =AZ51+$AY$48 | AZ51: 0.07 | BA51: =AZ51+$BA$48
B52: Q3/Q4-26E growth before revenue calibration (1H/26 y/y) | AI52: =IFERROR((AG50+AH50)/(AB50+AC50)-1,0) | AJ52: =IFERROR((AG50+AH50)/(AB50+AC50)-1,0) | AX52: 2030E | AY52: =AZ52+$AY$48 | AZ52: 0.06 | BA52: =AZ52+$BA$48
B53: Other / non-aerospace — net sales | C53: =IF(ISNUMBER(C47),C47+C50,"") | D53: =IF(ISNUMBER(D47),D47+D50,"") | E53: =IF(ISNUMBER(E47),E47+E50,"") | F53: =IF(ISNUMBER(F47),F47+F50,"") | G53: =IF(ISNUMBER(G47),G47+G50,"") | H53: =IF(ISNUMBER(H47),H47+H50,"") | I53: =IF(ISNUMBER(I47),I47+I50,"") | J53: =IF(ISNUMBER(J47),J47+J50,"") | ... AO53: =IF(ISNUMBER(AO47),AO47+AO50,"") | AR53: =IFERROR((AO53/AF53)^(1/5)-1,"n/m") | AS53: =IFERROR((AF53/K53)^(1/5)-1,"n/m") | AT53: =IFERROR((AF53/F53)^(1/10)-1,"n/m") | AU53: =IFERROR((AF53/C53)^(1/13)-1,"n/m") | AX53: DEF_AM (defense aftermarket y/y) | AY53: 0.02 | AZ53: Δ → | BA53: -0.03 | BB53: Readiness / sustainment spares.
B54: Net sales y/y % | D54: =IF(AND(ISNUMBER(D53),ISNUMBER(C53)),IFERROR(D53/C53-1,""),"") | E54: =IF(AND(ISNUMBER(E53),ISNUMBER(D53)),IFERROR(E53/D53-1,""),"") | F54: =IF(AND(ISNUMBER(F53),ISNUMBER(E53)),IFERROR(F53/E53-1,""),"") | G54: =IF(AND(ISNUMBER(G53),ISNUMBER(F53)),IFERROR(G53/F53-1,""),"") | H54: =IF(AND(ISNUMBER(H53),ISNUMBER(G53)),IFERROR(H53/G53-1,""),"") | I54: =IF(AND(ISNUMBER(I53),ISNUMBER(H53)),IFERROR(I53/H53-1,""),"") | J54: =IF(AND(ISNUMBER(J53),ISNUMBER(I53)),IFERROR(J53/I53-1,""),"") | K54: =IF(AND(ISNUMBER(K53),ISNUMBER(J53)),IFERROR(K53/J53-1,""),"") | L54: =IF(AND(ISNUMBER(L53),ISNUMBER(K53)),IFERROR(L53/K53-1,""),"") | Q54: =IF(AND(ISNUMBER(Q53),ISNUMBER(L53)),IFERROR(Q53/L53-1,""),"") | R54: =IF(AND(ISNUMBER(R53),ISNUMBER(M53)),IFERROR(R53/M53-1,""),"") | S54: =IF(AND(ISNUMBER(S53),ISNUMBER(N53)),IFERROR(S53/N53-1,""),"") | T54: =IF(AND(ISNUMBER(T53),ISNUMBER(O53)),IFERROR(T53/O53-1,""),"") | U54: =IF(AND(ISNUMBER(U53),ISNUMBER(P53)),IFERROR(U53/P53-1,""),"") | V54: =IF(AND(ISNUMBER(V53),ISNUMBER(Q53)),IFERROR(V53/Q53-1,""),"") | W54: =IF(AND(ISNUMBER(W53),ISNUMBER(R53)),IFERROR(W53/R53-1,""),"") | X54: =IF(AND(ISNUMBER(X53),ISNUMBER(S53)),IFERROR(X53/S53-1,""),"") | ... AK54: =IF(AND(ISNUMBER(AK53),ISNUMBER(AF53)),IFERROR(AK53/AF53-1,""),"") | AL54: =IF(AND(ISNUMBER(AL53),ISNUMBER(AK53)),IFERROR(AL53/AK53-1,""),"") | AM54: =IF(AND(ISNUMBER(AM53),ISNUMBER(AL53)),IFERROR(AM53/AL53-1,""),"") | AN54: =IF(AND(ISNUMBER(AN53),ISNUMBER(AM53)),IFERROR(AN53/AM53-1,""),"") | AO54: =IF(AND(ISNUMBER(AO53),ISNUMBER(AN53)),IFERROR(AO53/AN53-1,""),"") | AX54: 2027E | AY54: =AZ54+$AY$53 | AZ54: 0.06 | BA54: =AZ54+$BA$53
B55: % of total net sales | C55: =IF(AND(ISNUMBER(C53),ISNUMBER(C90)),IFERROR(C53/C90,""),"") | D55: =IF(AND(ISNUMBER(D53),ISNUMBER(D90)),IFERROR(D53/D90,""),"") | E55: =IF(AND(ISNUMBER(E53),ISNUMBER(E90)),IFERROR(E53/E90,""),"") | F55: =IF(AND(ISNUMBER(F53),ISNUMBER(F90)),IFERROR(F53/F90,""),"") | G55: =IF(AND(ISNUMBER(G53),ISNUMBER(G90)),IFERROR(G53/G90,""),"") | H55: =IF(AND(ISNUMBER(H53),ISNUMBER(H90)),IFERROR(H53/H90,""),"") | I55: =IF(AND(ISNUMBER(I53),ISNUMBER(I90)),IFERROR(I53/I90,""),"") | J55: =IF(AND(ISNUMBER(J53),ISNUMBER(J90)),IFERROR(J53/J90,""),"") | ... AO55: =IF(AND(ISNUMBER(AO53),ISNUMBER(AO90)),IFERROR(AO53/AO90,""),"") | AX55: 2028E | AY55: =AZ55+$AY$53 | AZ55: 0.06 | BA55: =AZ55+$BA$53
B56: Aftermarket % of end-market sales | C56: =IF(AND(ISNUMBER(C50),ISNUMBER(C53)),IFERROR(C50/C53,""),"") | D56: =IF(AND(ISNUMBER(D50),ISNUMBER(D53)),IFERROR(D50/D53,""),"") | E56: =IF(AND(ISNUMBER(E50),ISNUMBER(E53)),IFERROR(E50/E53,""),"") | F56: =IF(AND(ISNUMBER(F50),ISNUMBER(F53)),IFERROR(F50/F53,""),"") | G56: =IF(AND(ISNUMBER(G50),ISNUMBER(G53)),IFERROR(G50/G53,""),"") | H56: =IF(AND(ISNUMBER(H50),ISNUMBER(H53)),IFERROR(H50/H53,""),"") | I56: =IF(AND(ISNUMBER(I50),ISNUMBER(I53)),IFERROR(I50/I53,""),"") | J56: =IF(AND(ISNUMBER(J50),ISNUMBER(J53)),IFERROR(J50/J53,""),"") | ... AO56: =IF(AND(ISNUMBER(AO50),ISNUMBER(AO53)),IFERROR(AO50/AO53,""),"") | AX56: 2029E | AY56: =AZ56+$AY$53 | AZ56: 0.05 | BA56: =AZ56+$BA$53
AX57: 2030E | AY57: =AZ57+$AY$53 | AZ57: 0.05 | BA57: =AZ57+$BA$53
B58: OEM / aftermarket mix (all end markets) | AP58: MIX — outputs | AX58: OTH_OEM (other / non-aerospace OEM y/y) | AY58: 0.02 | AZ58: Δ → | BA58: -0.04 | BB58: Industrial applications (~6% of sales).
B59: Total OEM net sales | C59: =IF(ISNUMBER(C11),C11+C23+C35+C47,"") | D59: =IF(ISNUMBER(D11),D11+D23+D35+D47,"") | E59: =IF(ISNUMBER(E11),E11+E23+E35+E47,"") | F59: =IF(ISNUMBER(F11),F11+F23+F35+F47,"") | G59: =IF(ISNUMBER(G11),G11+G23+G35+G47,"") | H59: =IF(ISNUMBER(H11),H11+H23+H35+H47,"") | I59: =IF(ISNUMBER(I11),I11+I23+I35+I47,"") | J59: =IF(ISNUMBER(J11),J11+J23+J35+J47,"") | ... AO59: =IF(ISNUMBER(AO11),AO11+AO23+AO35+AO47,"") | AR59: =IFERROR((AO59/AF59)^(1/5)-1,"n/m") | AS59: =IFERROR((AF59/K59)^(1/5)-1,"n/m") | AT59: =IFERROR((AF59/F59)^(1/10)-1,"n/m") | AU59: =IFERROR((AF59/C59)^(1/13)-1,"n/m") | AX59: 2027E | AY59: =AZ59+$AY$58 | AZ59: 0.04 | BA59: =AZ59+$BA$58
B60: Total aftermarket net sales | C60: =IF(ISNUMBER(C14),C14+C26+C38+C50,"") | D60: =IF(ISNUMBER(D14),D14+D26+D38+D50,"") | E60: =IF(ISNUMBER(E14),E14+E26+E38+E50,"") | F60: =IF(ISNUMBER(F14),F14+F26+F38+F50,"") | G60: =IF(ISNUMBER(G14),G14+G26+G38+G50,"") | H60: =IF(ISNUMBER(H14),H14+H26+H38+H50,"") | I60: =IF(ISNUMBER(I14),I14+I26+I38+I50,"") | J60: =IF(ISNUMBER(J14),J14+J26+J38+J50,"") | ... AO60: =IF(ISNUMBER(AO14),AO14+AO26+AO38+AO50,"") | AR60: =IFERROR((AO60/AF60)^(1/5)-1,"n/m") | AS60: =IFERROR((AF60/K60)^(1/5)-1,"n/m") | AT60: =IFERROR((AF60/F60)^(1/10)-1,"n/m") | AU60: =IFERROR((AF60/C60)^(1/13)-1,"n/m") | AX60: 2028E | AY60: =AZ60+$AY$58 | AZ60: 0.04 | BA60: =AZ60+$BA$58
B61: Aftermarket % of net sales | C61: =IF(AND(ISNUMBER(C60),ISNUMBER(C90)),IFERROR(C60/C90,""),"") | D61: =IF(AND(ISNUMBER(D60),ISNUMBER(D90)),IFERROR(D60/D90,""),"") | E61: =IF(AND(ISNUMBER(E60),ISNUMBER(E90)),IFERROR(E60/E90,""),"") | F61: =IF(AND(ISNUMBER(F60),ISNUMBER(F90)),IFERROR(F60/F90,""),"") | G61: =IF(AND(ISNUMBER(G60),ISNUMBER(G90)),IFERROR(G60/G90,""),"") | H61: =IF(AND(ISNUMBER(H60),ISNUMBER(H90)),IFERROR(H60/H90,""),"") | I61: =IF(AND(ISNUMBER(I60),ISNUMBER(I90)),IFERROR(I60/I90,""),"") | J61: =IF(AND(ISNUMBER(J60),ISNUMBER(J90)),IFERROR(J60/J90,""),"") | ... AO61: =IF(AND(ISNUMBER(AO60),ISNUMBER(AO90)),IFERROR(AO60/AO90,""),"") | AR61: =IFERROR(AVERAGE(AK61,AL61,AM61,AN61,AO61),"n/m") | AS61: =IFERROR(AVERAGE(L61,Q61,V61,AA61,AF61),"n/m") | AT61: =IFERROR(AVERAGE(G61,H61,I61,J61,K61,L61,Q61,V61,AA61,AF61),"n/m") | AU61: =IFERROR(AVERAGE(C61,D61,E61,F61,G61,H61,I61,J61,K61,L61,Q61,V61,AA61,AF61),"n/m") | AX61: 2029E | AY61: =AZ61+$AY$58 | AZ61: 0.04 | BA61: =AZ61+$BA$58
B62: Commercial + business jet & GA OEM y/y % (company outlook metric) | D62: =IFERROR((D11+D23)/(C11+C23)-1,"") | E62: =IFERROR((E11+E23)/(D11+D23)-1,"") | F62: =IFERROR((F11+F23)/(E11+E23)-1,"") | G62: =IFERROR((G11+G23)/(F11+F23)-1,"") | H62: =IFERROR((H11+H23)/(G11+G23)-1,"") | I62: =IFERROR((I11+I23)/(H11+H23)-1,"") | J62: =IFERROR((J11+J23)/(I11+I23)-1,"") | K62: =IFERROR((K11+K23)/(J11+J23)-1,"") | L62: =IFERROR((L11+L23)/(K11+K23)-1,"") | Q62: =IFERROR((Q11+Q23)/(L11+L23)-1,"") | R62: =IFERROR((R11+R23)/(M11+M23)-1,"") | S62: =IFERROR((S11+S23)/(N11+N23)-1,"") | T62: =IFERROR((T11+T23)/(O11+O23)-1,"") | U62: =IFERROR((U11+U23)/(P11+P23)-1,"") | V62: =IFERROR((V11+V23)/(Q11+Q23)-1,"") | W62: =IFERROR((W11+W23)/(R11+R23)-1,"") | X62: =IFERROR((X11+X23)/(S11+S23)-1,"") | ... AK62: =IFERROR((AK11+AK23)/(AF11+AF23)-1,"") | AL62: =IFERROR((AL11+AL23)/(AK11+AK23)-1,"") | AM62: =IFERROR((AM11+AM23)/(AL11+AL23)-1,"") | AN62: =IFERROR((AN11+AN23)/(AM11+AM23)-1,"") | AO62: =IFERROR((AO11+AO23)/(AN11+AN23)-1,"") | AP62: FY26 outlook (Q2-26 release): commercial, business jet & GA OEM growth 17–20%; aftermarket low-double digits; defense mid-single digits. | AX62: 2030E | AY62: =AZ62+$AY$58 | AZ62: 0.04 | BA62: =AZ62+$BA$58
B63: Commercial + business jet & GA aftermarket y/y % | D63: =IFERROR((D14+D26)/(C14+C26)-1,"") | E63: =IFERROR((E14+E26)/(D14+D26)-1,"") | F63: =IFERROR((F14+F26)/(E14+E26)-1,"") | G63: =IFERROR((G14+G26)/(F14+F26)-1,"") | H63: =IFERROR((H14+H26)/(G14+G26)-1,"") | I63: =IFERROR((I14+I26)/(H14+H26)-1,"") | J63: =IFERROR((J14+J26)/(I14+I26)-1,"") | K63: =IFERROR((K14+K26)/(J14+J26)-1,"") | L63: =IFERROR((L14+L26)/(K14+K26)-1,"") | Q63: =IFERROR((Q14+Q26)/(L14+L26)-1,"") | R63: =IFERROR((R14+R26)/(M14+M26)-1,"") | S63: =IFERROR((S14+S26)/(N14+N26)-1,"") | T63: =IFERROR((T14+T26)/(O14+O26)-1,"") | U63: =IFERROR((U14+U26)/(P14+P26)-1,"") | V63: =IFERROR((V14+V26)/(Q14+Q26)-1,"") | W63: =IFERROR((W14+W26)/(R14+R26)-1,"") | X63: =IFERROR((X14+X26)/(S14+S26)-1,"") | ... AK63: =IFERROR((AK14+AK26)/(AF14+AF26)-1,"") | AL63: =IFERROR((AL14+AL26)/(AK14+AK26)-1,"") | AM63: =IFERROR((AM14+AM26)/(AL14+AL26)-1,"") | AN63: =IFERROR((AN14+AN26)/(AM14+AM26)-1,"") | AO63: =IFERROR((AO14+AO26)/(AN14+AN26)-1,"") | AX63: OTH_AM (other / non-aerospace aftermarket y/y) | AY63: 0.02 | AZ63: Δ → | BA63: -0.04 | BB63: Industrial aftermarket.
B64: Defense y/y % | D64: =IFERROR(D41/C41-1,"") | E64: =IFERROR(E41/D41-1,"") | F64: =IFERROR(F41/E41-1,"") | G64: =IFERROR(G41/F41-1,"") | H64: =IFERROR(H41/G41-1,"") | I64: =IFERROR(I41/H41-1,"") | J64: =IFERROR(J41/I41-1,"") | K64: =IFERROR(K41/J41-1,"") | L64: =IFERROR(L41/K41-1,"") | Q64: =IFERROR(Q41/L41-1,"") | R64: =IFERROR(R41/M41-1,"") | S64: =IFERROR(S41/N41-1,"") | T64: =IFERROR(T41/O41-1,"") | U64: =IFERROR(U41/P41-1,"") | V64: =IFERROR(V41/Q41-1,"") | W64: =IFERROR(W41/R41-1,"") | X64: =IFERROR(X41/S41-1,"") | ... AK64: =IFERROR(AK41/AF41-1,"") | AL64: =IFERROR(AL41/AK41-1,"") | AM64: =IFERROR(AM41/AL41-1,"") | AN64: =IFERROR(AN41/AM41-1,"") | AO64: =IFERROR(AO41/AN41-1,"") | AX64: 2027E | AY64: =AZ64+$AY$63 | AZ64: 0.04 | BA64: =AZ64+$BA$63
B65: Net sales not split by end market (pre-2022 annual; 2022 quarters) | C65: =IF(ISNUMBER(C127),C127-N(C59)-N(C60),"") | D65: =IF(ISNUMBER(D127),D127-N(D59)-N(D60),"") | E65: =IF(ISNUMBER(E127),E127-N(E59)-N(E60),"") | F65: =IF(ISNUMBER(F127),F127-N(F59)-N(F60),"") | G65: =IF(ISNUMBER(G127),G127-N(G59)-N(G60),"") | H65: =IF(ISNUMBER(H127),H127-N(H59)-N(H60),"") | I65: =IF(ISNUMBER(I127),I127-N(I59)-N(I60),"") | J65: =IF(ISNUMBER(J127),J127-N(J59)-N(J60),"") | ... AH65: =IF(ISNUMBER(AH127),AH127-N(AH59)-N(AH60),"") | AP65: Net sales less the end-market split: end-market sales were first disclosed for FY2022 (prospectus). | AX65: 2028E | AY65: =AZ65+$AY$63 | AZ65: 0.04 | BA65: =AZ65+$BA$63
AX66: 2029E | AY66: =AZ66+$AY$63 | AZ66: 0.04 | BA66: =AZ66+$BA$63
B67: Organic vs acquired net sales (company definition: acquisitions organic from the 13th month) | AP67: ORGANIC / ACQUIRED — as published in each release; acquisitions: SCHROTH Jul-22, DAC Jul-23, CAV Sep-23, AAI Aug-24, Beadlight Jul-25, LMB Dec-25, Harper Jan-26 | AX67: 2030E | AY67: =AZ67+$AY$63 | AZ67: 0.04 | BA67: =AZ67+$BA$63
B68: Organic net sales (as published) | V68: 272.9 | W68: 82.5 | X68: 86.6 | Y68: 96.5 | Z68: 99.3 | AA68: 364.9 | AB68: 102 | AC68: 108 | AD68: 115 | AE68: 129.1 | AF68: 454.2 | AG68: 127.7 | AH68: 138.3 | AI68: =AI127-AI69 | AJ68: =AJ127-AJ69 | AK68: =SUM(AG68,AH68,AI68,AJ68) | AP68: Net sales of businesses owned in both periods (company definition). Q3/Q4-26E = net sales − acquisition sales input. | AR68: =IFERROR((AO68/AF68)^(1/5)-1,"n/m") | AS68: =IFERROR((AF68/K68)^(1/5)-1,"n/m") | AT68: =IFERROR((AF68/F68)^(1/10)-1,"n/m") | AU68: =IFERROR((AF68/C68)^(1/13)-1,"n/m") | AX68: EBM (Adjusted EBITDA margin, current portfolio) | AY68: 0.01 | AZ68: Δ → | BA68: -0.025 | BB68: FY25 38.1%; 1H/26 40.5%; FY26 guidance ~40%. Strategic value drivers (pricing, cost, productivity) + mix towards aftermarket; ~50 bps p.a. expansion.
B69: Net acquisition sales (net sales − organic) | V69: 44.577 | W69: 9.344 | X69: 10.415 | Y69: 7.019 | Z69: 11.141 | AA69: 37.919 | AB69: 12.659 | AC69: 15.123 | AD69: 11.751 | AE69: 2.65 | AF69: 42.083 | AG69: 28.388 | AH69: 33.279 | AI69: 31 | AJ69: 30 | AK69: =SUM(AG69,AH69,AI69,AJ69) | AP69: Q3/Q4-26E inputs: LMB (~$15m a quarter; ~$60m FY26 per the company) + Harper Engineering (~$16m a quarter) not in the prior-year quarter. Q2-26 net acquisition sales $33.3m incl. Beadlight (anniversaries 28-Jul-26). Q4: LMB consolidated from 23-Dec-25 (≈ one week in Q4-25). | AX69: 2027E | AY69: =AZ69+$AY$68 | AZ69: 0.405 | BA69: =AZ69+$BA$68
B70: Organic growth % (organic sales ÷ prior-period net sales − 1) | V70: 0.14 | W70: 0.111 | X70: 0.17 | Y70: 0.165 | Z70: 0.149 | AA70: 0.15 | AB70: 0.111 | AC70: 0.113 | AD70: 0.111 | AE70: 0.169 | AF70: 0.127 | AG70: 0.114 | AH70: 0.123 | AI70: =IFERROR(AI68/AD127-1,"") | AJ70: =IFERROR(AJ68/AE127-1,"") | AK70: =IFERROR(AK68/AF127-1,"") | AL70: =IFERROR((AL127-AL80)/(AK127-AK80)-1,"") | AM70: =IFERROR((AM127-AM80)/(AL127-AL80)-1,"") | AN70: =IFERROR((AN127-AN80)/(AM127-AM80)-1,"") | AO70: =IFERROR((AO127-AO80)/(AN127-AN80)-1,"") | AP70: Historical as published. 2027E+: growth of the current portfolio excluding future acquisitions (LMB / Harper organic from 2027). | AR70: =IFERROR(AVERAGE(AK70,AL70,AM70,AN70,AO70),"n/m") | AS70: =IFERROR(AVERAGE(L70,Q70,V70,AA70,AF70),"n/m") | AT70: =IFERROR(AVERAGE(G70,H70,I70,J70,K70,L70,Q70,V70,AA70,AF70),"n/m") | AU70: =IFERROR(AVERAGE(C70,D70,E70,F70,G70,H70,I70,J70,K70,L70,Q70,V70,AA70,AF70),"n/m") | AX70: 2028E | AY70: =AZ70+$AY$68 | AZ70: 0.41 | BA70: =AZ70+$BA$68
B71: Acquisition contribution to growth % | D71: =IF(AND(ISNUMBER(D69),ISNUMBER(C127)),IFERROR(D69/C127,""),"") | E71: =IF(AND(ISNUMBER(E69),ISNUMBER(D127)),IFERROR(E69/D127,""),"") | F71: =IF(AND(ISNUMBER(F69),ISNUMBER(E127)),IFERROR(F69/E127,""),"") | G71: =IF(AND(ISNUMBER(G69),ISNUMBER(F127)),IFERROR(G69/F127,""),"") | H71: =IF(AND(ISNUMBER(H69),ISNUMBER(G127)),IFERROR(H69/G127,""),"") | I71: =IF(AND(ISNUMBER(I69),ISNUMBER(H127)),IFERROR(I69/H127,""),"") | J71: =IF(AND(ISNUMBER(J69),ISNUMBER(I127)),IFERROR(J69/I127,""),"") | K71: =IF(AND(ISNUMBER(K69),ISNUMBER(J127)),IFERROR(K69/J127,""),"") | L71: =IF(AND(ISNUMBER(L69),ISNUMBER(K127)),IFERROR(L69/K127,""),"") | Q71: =IF(AND(ISNUMBER(Q69),ISNUMBER(L127)),IFERROR(Q69/L127,""),"") | R71: =IF(AND(ISNUMBER(R69),ISNUMBER(M127)),IFERROR(R69/M127,""),"") | S71: =IF(AND(ISNUMBER(S69),ISNUMBER(N127)),IFERROR(S69/N127,""),"") | T71: =IF(AND(ISNUMBER(T69),ISNUMBER(O127)),IFERROR(T69/O127,""),"") | U71: =IF(AND(ISNUMBER(U69),ISNUMBER(P127)),IFERROR(U69/P127,""),"") | V71: =IF(AND(ISNUMBER(V69),ISNUMBER(Q127)),IFERROR(V69/Q127,""),"") | W71: =IF(AND(ISNUMBER(W69),ISNUMBER(R127)),IFERROR(W69/R127,""),"") | X71: =IF(AND(ISNUMBER(X69),ISNUMBER(S127)),IFERROR(X69/S127,""),"") | ... AK71: =IF(AND(ISNUMBER(AK69),ISNUMBER(AF127)),IFERROR(AK69/AF127,""),"") | AL71: =IFERROR(AL80/AK127,"") | AM71: =IFERROR(AM80/AL127,"") | AN71: =IFERROR(AN80/AM127,"") | AO71: =IFERROR(AO80/AN127,"") | AR71: =IFERROR(AVERAGE(AK71,AL71,AM71,AN71,AO71),"n/m") | AS71: =IFERROR(AVERAGE(L71,Q71,V71,AA71,AF71),"n/m") | AT71: =IFERROR(AVERAGE(G71,H71,I71,J71,K71,L71,Q71,V71,AA71,AF71),"n/m") | AU71: =IFERROR(AVERAGE(C71,D71,E71,F71,G71,H71,I71,J71,K71,L71,Q71,V71,AA71,AF71),"n/m") | AX71: 2029E | AY71: =AZ71+$AY$68 | AZ71: 0.415 | BA71: =AZ71+$BA$68
B72: Check: published organic growth vs organic sales ÷ prior net sales (should be 0.0%) | D72: =IF(AND(ISNUMBER(D70),ISNUMBER(D68),ISNUMBER(C127)),IF(ABS(D68/C127-1-D70)<0.0015,0,ROUND(D68/C127-1-D70,3)),"n/p") | E72: =IF(AND(ISNUMBER(E70),ISNUMBER(E68),ISNUMBER(D127)),IF(ABS(E68/D127-1-E70)<0.0015,0,ROUND(E68/D127-1-E70,3)),"n/p") | F72: =IF(AND(ISNUMBER(F70),ISNUMBER(F68),ISNUMBER(E127)),IF(ABS(F68/E127-1-F70)<0.0015,0,ROUND(F68/E127-1-F70,3)),"n/p") | G72: =IF(AND(ISNUMBER(G70),ISNUMBER(G68),ISNUMBER(F127)),IF(ABS(G68/F127-1-G70)<0.0015,0,ROUND(G68/F127-1-G70,3)),"n/p") | H72: =IF(AND(ISNUMBER(H70),ISNUMBER(H68),ISNUMBER(G127)),IF(ABS(H68/G127-1-H70)<0.0015,0,ROUND(H68/G127-1-H70,3)),"n/p") | I72: =IF(AND(ISNUMBER(I70),ISNUMBER(I68),ISNUMBER(H127)),IF(ABS(I68/H127-1-I70)<0.0015,0,ROUND(I68/H127-1-I70,3)),"n/p") | J72: =IF(AND(ISNUMBER(J70),ISNUMBER(J68),ISNUMBER(I127)),IF(ABS(J68/I127-1-J70)<0.0015,0,ROUND(J68/I127-1-J70,3)),"n/p") | K72: =IF(AND(ISNUMBER(K70),ISNUMBER(K68),ISNUMBER(J127)),IF(ABS(K68/J127-1-K70)<0.0015,0,ROUND(K68/J127-1-K70,3)),"n/p") | L72: =IF(AND(ISNUMBER(L70),ISNUMBER(L68),ISNUMBER(K127)),IF(ABS(L68/K127-1-L70)<0.0015,0,ROUND(L68/K127-1-L70,3)),"n/p") | Q72: =IF(AND(ISNUMBER(Q70),ISNUMBER(Q68),ISNUMBER(L127)),IF(ABS(Q68/L127-1-Q70)<0.0015,0,ROUND(Q68/L127-1-Q70,3)),"n/p") | R72: =IF(AND(ISNUMBER(R70),ISNUMBER(R68),ISNUMBER(M127)),IF(ABS(R68/M127-1-R70)<0.0015,0,ROUND(R68/M127-1-R70,3)),"n/p") | S72: =IF(AND(ISNUMBER(S70),ISNUMBER(S68),ISNUMBER(N127)),IF(ABS(S68/N127-1-S70)<0.0015,0,ROUND(S68/N127-1-S70,3)),"n/p") | T72: =IF(AND(ISNUMBER(T70),ISNUMBER(T68),ISNUMBER(O127)),IF(ABS(T68/O127-1-T70)<0.0015,0,ROUND(T68/O127-1-T70,3)),"n/p") | U72: =IF(AND(ISNUMBER(U70),ISNUMBER(U68),ISNUMBER(P127)),IF(ABS(U68/P127-1-U70)<0.0015,0,ROUND(U68/P127-1-U70,3)),"n/p") | V72: =IF(AND(ISNUMBER(V70),ISNUMBER(V68),ISNUMBER(Q127)),IF(ABS(V68/Q127-1-V70)<0.0015,0,ROUND(V68/Q127-1-V70,3)),"n/p") | W72: =IF(AND(ISNUMBER(W70),ISNUMBER(W68),ISNUMBER(R127)),IF(ABS(W68/R127-1-W70)<0.0015,0,ROUND(W68/R127-1-W70,3)),"n/p") | X72: =IF(AND(ISNUMBER(X70),ISNUMBER(X68),ISNUMBER(S127)),IF(ABS(X68/S127-1-X70)<0.0015,0,ROUND(X68/S127-1-X70,3)),"n/p") | ... AH72: =IF(AND(ISNUMBER(AH70),ISNUMBER(AH68),ISNUMBER(AC127)),IF(ABS(AH68/AC127-1-AH70)<0.0015,0,ROUND(AH68/AC127-1-AH70,3)),"n/p") | AX72: 2030E | AY72: =AZ72+$AY$68 | AZ72: 0.42 | BA72: =AZ72+$BA$68
AX73: M&A_spend (bolt-on acquisitions, $m) | AY73: 200 | AZ73: Δ → | BA73: -300 | BB73: Loar deployed $60m (2023), $384m (2024), $508m (2025) and $250m (1H/26) on acquisitions; ~$750m pipeline. Base ~$300m p.a.
B74: Future acquisitions (M&A lever — bolt-ons, unallocated; deals closed from 2027E) | AP74: M&A LEVER — acquired sales = spend ÷ EV/sales; mid-year convention | AX74: 2027E | AY74: =MAX(0,AZ74+$AY$73) | AZ74: 300 | BA74: =MAX(0,AZ74+$BA$73)
B75: Acquisition spend (USDm, scenario) | AK75: 0 | AL75: =MAX(0,CHOOSE(MATCH($AP$2,{"Bull","Base","Bear"},0),$AY$74,$AZ$74,$BA$74)) | AM75: =MAX(0,CHOOSE(MATCH($AP$2,{"Bull","Base","Bear"},0),$AY$75,$AZ$75,$BA$75)) | AN75: =MAX(0,CHOOSE(MATCH($AP$2,{"Bull","Base","Bear"},0),$AY$76,$AZ$76,$BA$76)) | AO75: =MAX(0,CHOOSE(MATCH($AP$2,{"Bull","Base","Bear"},0),$AY$77,$AZ$77,$BA$77)) | AP75: Scenario lever M&A_spend (Base ~$300m p.a.; Loar acquired $508m in 2025 incl. LMB and $250m in 1H/26). Spend funded from cash / term-loan draws (debt schedule). | AX75: 2028E | AY75: =MAX(0,AZ75+$AY$73) | AZ75: 300 | BA75: =MAX(0,AZ75+$BA$73)
B76: Purchase multiple — EV / sales (x) | AK76: 0 | AL76: 6 | AM76: 6 | AN76: 6 | AO76: 6 | AP76: Loar deals: AAI $383.5m, LMB $474.8m on ~$60m 2026E sales (~7.9x), Harper $249.8m (+ up to $55m earn-out); 6.0x input. | AX76: 2029E | AY76: =MAX(0,AZ76+$AY$73) | AZ76: 300 | BA76: =MAX(0,AZ76+$BA$73)
B77: Annualised sales acquired in the year | AK77: 0 | AL77: =IFERROR(AL75/AL76,0) | AM77: =IFERROR(AM75/AM76,0) | AN77: =IFERROR(AN75/AN76,0) | AO77: =IFERROR(AO75/AO76,0) | AX77: 2030E | AY77: =MAX(0,AZ77+$AY$73) | AZ77: 300 | BA77: =MAX(0,AZ77+$BA$73)
B78: Growth of acquired businesses after acquisition % | AK78: 0 | AL78: 0.07 | AM78: 0.07 | AN78: 0.07 | AO78: 0.07
B79: Run-rate sales of businesses acquired (year end) | AK79: 0 | AL79: =AK79*(1+AL78)+AL77 | AM79: =AL79*(1+AM78)+AM77 | AN79: =AM79*(1+AN78)+AN77 | AO79: =AN79*(1+AO78)+AO77
B80: Net sales from future acquisitions | AK80: 0 | AL80: =AK79*(1+AL78)+0.5*AL77 | AM80: =AL79*(1+AM78)+0.5*AM77 | AN80: =AM79*(1+AN78)+0.5*AN77 | AO80: =AN79*(1+AO78)+0.5*AO77 | AP80: Mid-year convention: half a year of sales in the year of acquisition. Unallocated to end markets (separate line in the Group build).
B81: Adjusted EBITDA margin of acquired businesses % | AK81: 0 | AL81: 0.4 | AM81: 0.4 | AN81: 0.4 | AO81: 0.4 | AP81: LMB: ~$30m Adjusted EBITDA on ~$60m sales (2026E, company); Loar targets niche proprietary businesses with ≥35–40% margins post value drivers.
B82: Adjusted EBITDA from future acquisitions | AK82: 0 | AL82: =AL80*AL81 | AM82: =AM80*AM81 | AN82: =AN80*AN81 | AO82: =AO80*AO81
B83: PP&E % of spend | AK83: 0 | AL83: 0.02 | AM83: 0.02 | AN83: 0.02 | AO83: 0.02
B84: Acquired intangibles % of spend | AK84: 0 | AL84: 0.5 | AM84: 0.5 | AN84: 0.5 | AO84: 0.5 | AP84: Recent PPAs: AAI 40%, LMB 45%, Harper 61% of consideration in intangibles (customer relationships, trade names, technology).
B85: Intangible amortization life (years) | AK85: 0 | AL85: 15 | AM85: 15 | AN85: 15 | AO85: 15
B86: Cumulative acquired intangibles (gross) | AK86: 0 | AL86: =AK86+AL75*AL84 | AM86: =AL86+AM75*AM84 | AN86: =AM86+AN75*AN84 | AO86: =AN86+AO75*AO84
B87: Amortization of future-acquisition intangibles | AK87: 0 | AL87: =IFERROR((AK86+0.5*AL75*AL84)/AL85,0) | AM87: =IFERROR((AL86+0.5*AM75*AM84)/AM85,0) | AN87: =IFERROR((AM86+0.5*AN75*AN84)/AN85,0) | AO87: =IFERROR((AN86+0.5*AO75*AO84)/AO85,0) | AP87: Non-cash; added back in Adjusted EPS (current company definition) and excluded from Adjusted EBITDA.
B89: Group Total — net sales & Adjusted EBITDA (end-market build) → FY26 outlook calibration | AP89: GROUP TOTAL (CONSOLIDATED) — modelling logic
B90: Net sales (end-market build) | C90: =IF(ISNUMBER(C11),N(C11)+N(C14)+N(C23)+N(C26)+N(C35)+N(C38)+N(C47)+N(C50),C127) | D90: =IF(ISNUMBER(D11),N(D11)+N(D14)+N(D23)+N(D26)+N(D35)+N(D38)+N(D47)+N(D50),D127) | E90: =IF(ISNUMBER(E11),N(E11)+N(E14)+N(E23)+N(E26)+N(E35)+N(E38)+N(E47)+N(E50),E127) | F90: =IF(ISNUMBER(F11),N(F11)+N(F14)+N(F23)+N(F26)+N(F35)+N(F38)+N(F47)+N(F50),F127) | G90: =IF(ISNUMBER(G11),N(G11)+N(G14)+N(G23)+N(G26)+N(G35)+N(G38)+N(G47)+N(G50),G127) | H90: =IF(ISNUMBER(H11),N(H11)+N(H14)+N(H23)+N(H26)+N(H35)+N(H38)+N(H47)+N(H50),H127) | I90: =IF(ISNUMBER(I11),N(I11)+N(I14)+N(I23)+N(I26)+N(I35)+N(I38)+N(I47)+N(I50),I127) | J90: =IF(ISNUMBER(J11),N(J11)+N(J14)+N(J23)+N(J26)+N(J35)+N(J38)+N(J47)+N(J50),J127) | ... AH90: =IF(ISNUMBER(AH11),N(AH11)+N(AH14)+N(AH23)+N(AH26)+N(AH35)+N(AH38)+N(AH47)+N(AH50),AH127) | AI90: =AI11+AI14+AI23+AI26+AI35+AI38+AI47+AI50+N(AI80) | AJ90: =AJ11+AJ14+AJ23+AJ26+AJ35+AJ38+AJ47+AJ50+N(AJ80) | AK90: =AK11+AK14+AK23+AK26+AK35+AK38+AK47+AK50+N(AK80) | AL90: =AL11+AL14+AL23+AL26+AL35+AL38+AL47+AL50+N(AL80) | AM90: =AM11+AM14+AM23+AM26+AM35+AM38+AM47+AM50+N(AM80) | AN90: =AN11+AN14+AN23+AN26+AN35+AN38+AN47+AN50+N(AN80) | AO90: =AO11+AO14+AO23+AO26+AO35+AO38+AO47+AO50+N(AO80) | AP90: Σ end-market OEM + aftermarket sales (+ future acquisitions from 2027E). Before 2022 (and 2022 quarters) = reported net sales (no split). | AR90: =IFERROR((AO90/AF90)^(1/5)-1,"n/m") | AS90: =IFERROR((AF90/K90)^(1/5)-1,"n/m") | AT90: =IFERROR((AF90/F90)^(1/10)-1,"n/m") | AU90: =IFERROR((AF90/C90)^(1/13)-1,"n/m")
B91: Net sales y/y % | D91: =IF(AND(ISNUMBER(D90),ISNUMBER(C90)),IFERROR(D90/C90-1,""),"") | E91: =IF(AND(ISNUMBER(E90),ISNUMBER(D90)),IFERROR(E90/D90-1,""),"") | F91: =IF(AND(ISNUMBER(F90),ISNUMBER(E90)),IFERROR(F90/E90-1,""),"") | G91: =IF(AND(ISNUMBER(G90),ISNUMBER(F90)),IFERROR(G90/F90-1,""),"") | H91: =IF(AND(ISNUMBER(H90),ISNUMBER(G90)),IFERROR(H90/G90-1,""),"") | I91: =IF(AND(ISNUMBER(I90),ISNUMBER(H90)),IFERROR(I90/H90-1,""),"") | J91: =IF(AND(ISNUMBER(J90),ISNUMBER(I90)),IFERROR(J90/I90-1,""),"") | K91: =IF(AND(ISNUMBER(K90),ISNUMBER(J90)),IFERROR(K90/J90-1,""),"") | L91: =IF(AND(ISNUMBER(L90),ISNUMBER(K90)),IFERROR(L90/K90-1,""),"") | Q91: =IF(AND(ISNUMBER(Q90),ISNUMBER(L90)),IFERROR(Q90/L90-1,""),"") | R91: =IF(AND(ISNUMBER(R90),ISNUMBER(M90)),IFERROR(R90/M90-1,""),"") | S91: =IF(AND(ISNUMBER(S90),ISNUMBER(N90)),IFERROR(S90/N90-1,""),"") | T91: =IF(AND(ISNUMBER(T90),ISNUMBER(O90)),IFERROR(T90/O90-1,""),"") | U91: =IF(AND(ISNUMBER(U90),ISNUMBER(P90)),IFERROR(U90/P90-1,""),"") | V91: =IF(AND(ISNUMBER(V90),ISNUMBER(Q90)),IFERROR(V90/Q90-1,""),"") | W91: =IF(AND(ISNUMBER(W90),ISNUMBER(R90)),IFERROR(W90/R90-1,""),"") | X91: =IF(AND(ISNUMBER(X90),ISNUMBER(S90)),IFERROR(X90/S90-1,""),"") | ... AK91: =IF(AND(ISNUMBER(AK90),ISNUMBER(AF90)),IFERROR(AK90/AF90-1,""),"") | AL91: =IF(AND(ISNUMBER(AL90),ISNUMBER(AK90)),IFERROR(AL90/AK90-1,""),"") | AM91: =IF(AND(ISNUMBER(AM90),ISNUMBER(AL90)),IFERROR(AM90/AL90-1,""),"") | AN91: =IF(AND(ISNUMBER(AN90),ISNUMBER(AM90)),IFERROR(AN90/AM90-1,""),"") | AO91: =IF(AND(ISNUMBER(AO90),ISNUMBER(AN90)),IFERROR(AO90/AN90-1,""),"")
B92: Check: end-market build vs consolidated net sales (should be 0) | C92: =IF(ISNUMBER(C90),IF(ABS(C90-C127)<=0.15,0,ROUND(C90-C127,1)),"") | D92: =IF(ISNUMBER(D90),IF(ABS(D90-D127)<=0.15,0,ROUND(D90-D127,1)),"") | E92: =IF(ISNUMBER(E90),IF(ABS(E90-E127)<=0.15,0,ROUND(E90-E127,1)),"") | F92: =IF(ISNUMBER(F90),IF(ABS(F90-F127)<=0.15,0,ROUND(F90-F127,1)),"") | G92: =IF(ISNUMBER(G90),IF(ABS(G90-G127)<=0.15,0,ROUND(G90-G127,1)),"") | H92: =IF(ISNUMBER(H90),IF(ABS(H90-H127)<=0.15,0,ROUND(H90-H127,1)),"") | I92: =IF(ISNUMBER(I90),IF(ABS(I90-I127)<=0.15,0,ROUND(I90-I127,1)),"") | J92: =IF(ISNUMBER(J90),IF(ABS(J90-J127)<=0.15,0,ROUND(J90-J127,1)),"") | ... AO92: =IF(ISNUMBER(AO90),IF(ABS(AO90-AO127)<=0.15,0,ROUND(AO90-AO127,1)),"")
B93: Adjusted EBITDA margin % (current portfolio, before future M&A) | C93: =IF(ISNUMBER(C176),IFERROR(C176/C127,""),"") | D93: =IF(ISNUMBER(D176),IFERROR(D176/D127,""),"") | E93: =IF(ISNUMBER(E176),IFERROR(E176/E127,""),"") | F93: =IF(ISNUMBER(F176),IFERROR(F176/F127,""),"") | G93: =IF(ISNUMBER(G176),IFERROR(G176/G127,""),"") | H93: =IF(ISNUMBER(H176),IFERROR(H176/H127,""),"") | I93: =IF(ISNUMBER(I176),IFERROR(I176/I127,""),"") | J93: =IF(ISNUMBER(J176),IFERROR(J176/J127,""),"") | ... AH93: =IF(ISNUMBER(AH176),IFERROR(AH176/AH127,""),"") | AI93: =AI94+$AI$105 | AJ93: =AJ94+$AI$105 | AK93: =IFERROR((AK95)/AK127,"") | AL93: =CHOOSE(MATCH($AP$2,{"Bull","Base","Bear"},0),$AY$69,$AZ$69,$BA$69) | AM93: =CHOOSE(MATCH($AP$2,{"Bull","Base","Bear"},0),$AY$70,$AZ$70,$BA$70) | AN93: =CHOOSE(MATCH($AP$2,{"Bull","Base","Bear"},0),$AY$71,$AZ$71,$BA$71) | AO93: =CHOOSE(MATCH($AP$2,{"Bull","Base","Bear"},0),$AY$72,$AZ$72,$BA$72) | AP93: Historical = published Adjusted EBITDA ÷ net sales. Q3/Q4-26E: margin before calibration + Adjusted-EBITDA-outlook calibration Δ. 2027E–2030E: scenario lever (current portfolio). | AR93: =IFERROR(AVERAGE(AK93,AL93,AM93,AN93,AO93),"n/m") | AS93: =IFERROR(AVERAGE(L93,Q93,V93,AA93,AF93),"n/m") | AT93: =IFERROR(AVERAGE(G93,H93,I93,J93,K93,L93,Q93,V93,AA93,AF93),"n/m") | AU93: =IFERROR(AVERAGE(C93,D93,E93,F93,G93,H93,I93,J93,K93,L93,Q93,V93,AA93,AF93),"n/m")
B94: Adjusted EBITDA margin before outlook calibration % (Q3/Q4-26E helper) | AI94: =AD93+((AG176+AH176)/(AG127+AH127)-(AB176+AC176)/(AB127+AC127)) | AJ94: =AE93+((AG176+AH176)/(AG127+AH127)-(AB176+AC176)/(AB127+AC127)) | AP94: Prior-year quarter margin + (1H/26 − 1H/25 Adjusted EBITDA margin drift: +2.5pts, LMB / Harper mix and value drivers).
B95: Adjusted EBITDA (end-market build) | C95: =C176 | D95: =D176 | E95: =E176 | F95: =F176 | G95: =G176 | H95: =H176 | I95: =I176 | J95: =J176 | ... AH95: =AH176 | AI95: =AI127*AI93 | AJ95: =AJ127*AJ93 | AK95: =SUM(AG95,AH95,AI95,AJ95) | AL95: =(AL127-AL80)*AL93+AL82 | AM95: =(AM127-AM80)*AM93+AM82 | AN95: =(AN127-AN80)*AN93+AN82 | AO95: =(AO127-AO80)*AO93+AO82 | AP95: Loar's primary profit KPI and guidance metric. Forecast = net sales × Adjusted EBITDA margin (+ future acquisitions' EBITDA). Drives the GAAP P&L below. | AR95: =IFERROR((AO95/AF95)^(1/5)-1,"n/m") | AS95: =IFERROR((AF95/K95)^(1/5)-1,"n/m") | AT95: =IFERROR((AF95/F95)^(1/10)-1,"n/m") | AU95: =IFERROR((AF95/C95)^(1/13)-1,"n/m")
B96: Adjusted EBITDA y/y % | D96: =IF(AND(ISNUMBER(D95),ISNUMBER(C95)),IFERROR(D95/C95-1,""),"") | E96: =IF(AND(ISNUMBER(E95),ISNUMBER(D95)),IFERROR(E95/D95-1,""),"") | F96: =IF(AND(ISNUMBER(F95),ISNUMBER(E95)),IFERROR(F95/E95-1,""),"") | G96: =IF(AND(ISNUMBER(G95),ISNUMBER(F95)),IFERROR(G95/F95-1,""),"") | H96: =IF(AND(ISNUMBER(H95),ISNUMBER(G95)),IFERROR(H95/G95-1,""),"") | I96: =IF(AND(ISNUMBER(I95),ISNUMBER(H95)),IFERROR(I95/H95-1,""),"") | J96: =IF(AND(ISNUMBER(J95),ISNUMBER(I95)),IFERROR(J95/I95-1,""),"") | K96: =IF(AND(ISNUMBER(K95),ISNUMBER(J95)),IFERROR(K95/J95-1,""),"") | L96: =IF(AND(ISNUMBER(L95),ISNUMBER(K95)),IFERROR(L95/K95-1,""),"") | Q96: =IF(AND(ISNUMBER(Q95),ISNUMBER(L95)),IFERROR(Q95/L95-1,""),"") | R96: =IF(AND(ISNUMBER(R95),ISNUMBER(M95)),IFERROR(R95/M95-1,""),"") | S96: =IF(AND(ISNUMBER(S95),ISNUMBER(N95)),IFERROR(S95/N95-1,""),"") | T96: =IF(AND(ISNUMBER(T95),ISNUMBER(O95)),IFERROR(T95/O95-1,""),"") | U96: =IF(AND(ISNUMBER(U95),ISNUMBER(P95)),IFERROR(U95/P95-1,""),"") | V96: =IF(AND(ISNUMBER(V95),ISNUMBER(Q95)),IFERROR(V95/Q95-1,""),"") | W96: =IF(AND(ISNUMBER(W95),ISNUMBER(R95)),IFERROR(W95/R95-1,""),"") | X96: =IF(AND(ISNUMBER(X95),ISNUMBER(S95)),IFERROR(X95/S95-1,""),"") | ... AK96: =IF(AND(ISNUMBER(AK95),ISNUMBER(AF95)),IFERROR(AK95/AF95-1,""),"") | AL96: =IF(AND(ISNUMBER(AL95),ISNUMBER(AK95)),IFERROR(AL95/AK95-1,""),"") | AM96: =IF(AND(ISNUMBER(AM95),ISNUMBER(AL95)),IFERROR(AM95/AL95-1,""),"") | AN96: =IF(AND(ISNUMBER(AN95),ISNUMBER(AM95)),IFERROR(AN95/AM95-1,""),"") | AO96: =IF(AND(ISNUMBER(AO95),ISNUMBER(AN95)),IFERROR(AO95/AN95-1,""),"")
B97: Check: build vs Adjusted EBITDA bridge (should be 0) | C97: =IF(AND(ISNUMBER(C95),ISNUMBER(C174)),ROUND(C95-C174,1),"") | D97: =IF(AND(ISNUMBER(D95),ISNUMBER(D174)),ROUND(D95-D174,1),"") | E97: =IF(AND(ISNUMBER(E95),ISNUMBER(E174)),ROUND(E95-E174,1),"") | F97: =IF(AND(ISNUMBER(F95),ISNUMBER(F174)),ROUND(F95-F174,1),"") | G97: =IF(AND(ISNUMBER(G95),ISNUMBER(G174)),ROUND(G95-G174,1),"") | H97: =IF(AND(ISNUMBER(H95),ISNUMBER(H174)),ROUND(H95-H174,1),"") | I97: =IF(AND(ISNUMBER(I95),ISNUMBER(I174)),ROUND(I95-I174,1),"") | J97: =IF(AND(ISNUMBER(J95),ISNUMBER(J174)),ROUND(J95-J174,1),"") | ... AO97: =IF(AND(ISNUMBER(AO95),ISNUMBER(AO174)),ROUND(AO95-AO174,1),"")
B98: Memo: FY26 net sales guidance (scenario end-point) | AK98: =CHOOSE(MATCH($AP$2,{"Bull","Base","Bear"},0),$AY$12,$AZ$12,$BA$12) | AP98: Company FY26 net sales guidance $665–675m (raised in the Q2-26 release, 6-Aug-2026). Drives the revenue-outlook calibration.
B99: Net sales before revenue calibration (Q3/Q4-26E helper) | AI99: =AD11*(1+AI13)+AD14*(1+AI16)+AD23*(1+AI25)+AD26*(1+AI28)+AD35*(1+AI37)+AD38*(1+AI40)+AD47*(1+AI49)+AD50*(1+AI52) | AJ99: =AE11*(1+AJ13)+AE14*(1+AJ16)+AE23*(1+AJ25)+AE26*(1+AJ28)+AE35*(1+AJ37)+AE38*(1+AJ40)+AE47*(1+AJ49)+AE50*(1+AJ52)
B100: Net sales sensitivity to +1.00 of growth (Q3/Q4-26E helper) | AI100: =AD11+AD14+AD23+AD26+AD35+AD38+AD47+AD50 | AJ100: =AE11+AE14+AE23+AE26+AE35+AE38+AE47+AE50
B101: Outlook calibration: Δ y/y growth applied to all end-market lines (Q3/Q4-26E) | AI101: =(AK98-AG90-AH90-AI99-AJ99)/(AI100+AJ100) | AJ101: =$AI$101 | AP101: Solves the uniform growth shift (vs 1H/26 y/y rates) so that FY26 net sales = the FY26 guidance end-point for the active scenario.
...

Sheet Bull-Base-Bear
B2: Loar Holdings (LOAR) — Bull / Base / Bear Case P&L Summary | J2: Share price ($): | K2: =Model!$AK$393
B3: Adjusted figures (company definitions: Adjusted EBITDA; Adjusted EPS on the current definition, adding back amortization of acquired intangibles) · USD millions · Live panel linked to Model — toggle scenario via Model!AP2. Bull and Bear panels are value snapshots generated from the Model with the switch set to each case. 2026E includes LMB (from 23-Dec-2025) and Harper Engineering (from 21-Jan-2026). | J3: As of: | K3: =TODAY()
B5: Scenario: | C5: =Model!$AP$2 | N5: Scenario: | O5: Bull | P5: Snapshot (values) — Model run with switch = Bull | Z5: Scenario: | AA5: Bear | AB5: Snapshot (values) — Model run with switch = Bear
B7: (USDm, except EPS and shares) | C7: 2025A | D7: 2026E | E7: 2027E | F7: 2028E | G7: 2029E | H7: 2030E | I7: 25-'30 CAGR | J7: LT Hist Avg | K7: LT Hist Min | L7: LT Hist Max | N7: (USDm, except EPS and shares) | O7: 2025A | P7: 2026E | Q7: 2027E | R7: 2028E | S7: 2029E | T7: 2030E | U7: 25-'30 CAGR | V7: LT Hist Avg | W7: LT Hist Min | X7: LT Hist Max | Z7: (USDm, except EPS and shares) | AA7: 2025A | AB7: 2026E | AC7: 2027E | AD7: 2028E | AE7: 2029E | AF7: 2030E | AG7: 25-'30 CAGR | AH7: LT Hist Avg | AI7: LT Hist Min | AJ7: LT Hist Max
B9: Net Sales | C9: =Model!AF127 | D9: =Model!AK127 | E9: =Model!AL127 | F9: =Model!AM127 | G9: =Model!AN127 | H9: =Model!AO127 | I9: =IFERROR((H9/C9)^(1/5)-1,"n/m") | N9: Net Sales | O9: 496.283 | P9: 675 | Q9: 794.54342 | R9: 963.20177 | S9: 1139.9748 | T9: 1326.5022 | U9: 0.21729466 | Z9: Net Sales | AA9: 496.283 | AB9: 665 | AC9: 697.87358 | AD9: 725.24344 | AE9: 747.81509 | AF9: 766.97823 | AG9: 0.090964773
B10: Net sales y/y % | D10: =IFERROR(D9/C9-1,"") | E10: =IFERROR(E9/D9-1,"") | F10: =IFERROR(F9/E9-1,"") | G10: =IFERROR(G9/F9-1,"") | H10: =IFERROR(H9/G9-1,"") | N10: Net sales y/y % | P10: 0.36011107 | Q10: 0.17710137 | R10: 0.21227077 | S10: 0.18352653 | T10: 0.16362411 | Z10: Net sales y/y % | AB10: 0.33996127 | AC10: 0.049433959 | AD10: 0.039218938 | AE10: 0.031122861 | AF10: 0.025625499
B11: Organic growth % | C11: =Model!AF220 | D11: =Model!AK220 | E11: =Model!AL220 | F11: =Model!AM220 | G11: =Model!AN220 | H11: =Model!AO220 | N11: Organic growth % | O11: 0.127 | P11: 0.11293959 | Q11: 0.11537297 | R11: 0.10558392 | S11: 0.09775088 | T11: 0.092412591 | Z11: Organic growth % | AA11: 0.127 | AB11: 0.092789799 | AC11: 0.049433959 | AD11: 0.039218938 | AE11: 0.031122861 | AF11: 0.025625499
B12: Adjusted EBITDA | C12: =Model!AF174 | D12: =Model!AK174 | E12: =Model!AL174 | F12: =Model!AM174 | G12: =Model!AN174 | H12: =Model!AO174 | I12: =IFERROR((H12/C12)^(1/5)-1,"n/m") | N12: Adjusted EBITDA | O12: 189.124 | P12: 270 | Q12: 329.11052 | R12: 401.92807 | S12: 478.83327 | T12: 560.54609 | U12: 0.242719 | Z12: Adjusted EBITDA | AA12: 189.124 | AB12: 265 | AC12: 265.19196 | AD12: 279.21873 | AE12: 291.64789 | AF12: 302.9564 | AG12: 0.098820359
B13: Adjusted EBITDA margin % | C13: =IFERROR(C12/C9,"") | D13: =IFERROR(D12/D9,"") | E13: =IFERROR(E12/E9,"") | F13: =IFERROR(F12/F9,"") | G13: =IFERROR(G12/G9,"") | H13: =IFERROR(H12/H9,"") | J13: =IFERROR(AVERAGE(Model!C175,Model!D175,Model!E175,Model!F175,Model!G175,Model!H175,Model!I175,Model!N175,Model!S175,Model!X175,Model!AC175,Model!AH175,Model!AM175,Model!AR175,Model!AW175,Model!BB175,Model!BG175,Model!BL175,Model!BQ175,Model!AF175),"") | K13: =IFERROR(MIN(Model!C175,Model!D175,Model!E175,Model!F175,Model!G175,Model!H175,Model!I175,Model!N175,Model!S175,Model!X175,Model!AC175,Model!AH175,Model!AM175,Model!AR175,Model!AW175,Model!BB175,Model!BG175,Model!BL175,Model!BQ175,Model!AF175),"") | L13: =IFERROR(MAX(Model!C175,Model!D175,Model!E175,Model!F175,Model!G175,Model!H175,Model!I175,Model!N175,Model!S175,Model!X175,Model!AC175,Model!AH175,Model!AM175,Model!AR175,Model!AW175,Model!BB175,Model!BG175,Model!BL175,Model!BQ175,Model!AF175),"") | N13: Adjusted EBITDA margin % | O13: 0.38108096 | P13: 0.4 | Q13: 0.41421338 | R13: 0.41728337 | S13: 0.42003845 | T13: 0.42257456 | V13: 0.32168135 | W13: 0.16764565 | X13: 0.41728337 | Z13: Adjusted EBITDA margin % | AA13: 0.38108096 | AB13: 0.39849624 | AC13: 0.38 | AD13: 0.385 | AE13: 0.39 | AF13: 0.395 | AH13: 0.31785428 | AI13: 0.16764565 | AJ13: 0.40476399
B15: Operating Income (GAAP) | C15: =Model!AF134 | D15: =Model!AK134 | E15: =Model!AL134 | F15: =Model!AM134 | G15: =Model!AN134 | H15: =Model!AO134 | I15: =IFERROR((H15/C15)^(1/5)-1,"n/m") | N15: Operating Income (GAAP) | O15: 106.243 | P15: 160.414 | Q15: 207.9391 | R15: 256.09439 | S15: 307.84781 | T15: 366.54065 | U15: 0.28104494 | Z15: Operating Income (GAAP) | AA15: 106.243 | AB15: 155.414 | AC15: 164.49403 | AD15: 177.30704 | AE15: 188.65276 | AF15: 201.64145 | AG15: 0.13672627
B16: Operating income y/y % | D16: =IFERROR(D15/C15-1,"") | E16: =IFERROR(E15/D15-1,"") | F16: =IFERROR(F15/E15-1,"") | G16: =IFERROR(G15/F15-1,"") | H16: =IFERROR(H15/G15-1,"") | N16: Operating income y/y % | P16: 0.5098783 | Q16: 0.29626531 | R16: 0.23158361 | S16: 0.20208728 | T16: 0.1906554 | Z16: Operating income y/y % | AB16: 0.46281637 | AC16: 0.058424785 | AD16: 0.077893471 | AE16: 0.063989122 | AF16: 0.068849685
B17: Operating margin (GAAP) % | C17: =IFERROR(C15/C9,"") | D17: =IFERROR(D15/D9,"") | E17: =IFERROR(E15/E9,"") | F17: =IFERROR(F15/F9,"") | G17: =IFERROR(G15/G9,"") | H17: =IFERROR(H15/H9,"") | J17: =IFERROR(AVERAGE(Model!C231,Model!D231,Model!E231,Model!F231,Model!G231,Model!H231,Model!I231,Model!N231,Model!S231,Model!X231,Model!AC231,Model!AH231,Model!AM231,Model!AR231,Model!AW231,Model!BB231,Model!BG231,Model!BL231,Model!BQ231,Model!AF231),"") | K17: =IFERROR(MIN(Model!C231,Model!D231,Model!E231,Model!F231,Model!G231,Model!H231,Model!I231,Model!N231,Model!S231,Model!X231,Model!AC231,Model!AH231,Model!AM231,Model!AR231,Model!AW231,Model!BB231,Model!BG231,Model!BL231,Model!BQ231,Model!AF231),"") | L17: =IFERROR(MAX(Model!C231,Model!D231,Model!E231,Model!F231,Model!G231,Model!H231,Model!I231,Model!N231,Model!S231,Model!X231,Model!AC231,Model!AH231,Model!AM231,Model!AR231,Model!AW231,Model!BB231,Model!BG231,Model!BL231,Model!BQ231,Model!AF231),"") | N17: Operating margin (GAAP) % | O17: 0.21407745 | P17: 0.23765037 | Q17: 0.26170892 | R17: 0.26587824 | S17: 0.2700479 | T17: 0.27632118 | V17: 0.12499872 | W17: -0.24991595 | X17: 0.26587824 | Z17: Operating margin (GAAP) % | AA17: 0.21407745 | AB17: 0.23370526 | AC17: 0.23570749 | AD17: 0.24447934 | AE17: 0.25227194 | AF17: 0.26290374 | AH17: 0.12247161 | AI17: -0.24991595 | AJ17: 0.24581355
B19: Adjusted Net Income | C19: =Model!AF202 | D19: =Model!AK202 | E19: =Model!AL202 | F19: =Model!AM202 | G19: =Model!AN202 | H19: =Model!AO202 | I19: =IFERROR((H19/C19)^(1/5)-1,"n/m") | N19: Adjusted Net Income | O19: 131.19987 | P19: 137.59084 | Q19: 193.17193 | R19: 228.47467 | S19: 266.666 | T19: 310.85746 | U19: 0.18829858 | Z19: Adjusted Net Income | AA19: 131.19987 | AB19: 133.79084 | AC19: 143.67701 | AD19: 164.39548 | AE19: 177.04488 | AF19: 183.92714 | AG19: 0.069898262
B21: FDSO (m) | C21: =Model!AF148 | D21: =Model!AK148 | E21: =Model!AL148 | F21: =Model!AM148 | G21: =Model!AN148 | H21: =Model!AO148 | I21: =IFERROR((H21/C21)^(1/5)-1,"n/m") | N21: FDSO (m) | O21: 95.893 | P21: 95.5785 | Q21: 95.834471 | R21: 96.134471 | S21: 96.434471 | T21: 96.734471 | U21: 0.0017488927 | Z21: FDSO (m) | AA21: 95.893 | AB21: 95.5785 | AC21: 95.834471 | AD21: 95.480576 | AE21: 94.017563 | AF21: 92.15394 | AG21: -0.0079229568
B23: Adjusted EPS — Diluted ($) | C23: =Model!AF204 | D23: =Model!AK204 | E23: =Model!AL204 | F23: =Model!AM204 | G23: =Model!AN204 | H23: =Model!AO204 | I23: =IFERROR((H23/C23)^(1/5)-1,"n/m") | N23: Adjusted EPS — Diluted ($) | O23: 1.3681903 | P23: 1.4395585 | Q23: 2.0156831 | R23: 2.3766155 | S23: 2.765256 | T23: 3.2135128 | U23: 0.186224 | Z23: Adjusted EPS — Diluted ($) | AA23: 1.3681903 | AB23: 1.3998006 | AC23: 1.4992205 | AD23: 1.7217689 | AE23: 1.8831044 | AF23: 1.9958684 | AG23: 0.078442717
B24: EPS y/y % | D24: =IFERROR(D23/C23-1,"") | E24: =IFERROR(E23/D23-1,"") | F24: =IFERROR(F23/E23-1,"") | G24: =IFERROR(G23/F23-1,"") | H24: =IFERROR(H23/G23-1,"") | N24: EPS y/y % | P24: 0.052162484 | Q24: 0.40020927 | R24: 0.17906206 | S24: 0.16352686 | T24: 0.16210321 | Z24: EPS y/y % | AB24: 0.023103737 | AC24: 0.071024369 | AD24: 0.1484427 | AE24: 0.093703336 | AF24: 0.059882004
B26: P / E (x) — assumed (adjusted EPS) | G26: 45 | H26: 45 | N26: P / E (x) — assumed (adjusted EPS) | S26: 52 | T26: 52 | Z26: P / E (x) — assumed (adjusted EPS) | AD26: 35 | AE26: 35 | AF26: 35
B27: Price Target ($) | G27: =G26*G23 | H27: =H26*H23 | N27: Price Target ($) | S27: =S26*S23 | T27: =T26*T23 | Z27: Price Target ($) | AD27: =AD26*AD23 | AE27: =AE26*AE23 | AF27: =AF26*AF23
B28: Upside / (Downside) vs current | G28: =IFERROR(G27/$K$2-1,"") | H28: =IFERROR(H27/$K$2-1,"") | N28: Upside / (Downside) vs current | S28: =IFERROR(S27/$K$2-1,"") | T28: =IFERROR(T27/$K$2-1,"") | Z28: Upside / (Downside) vs current | AD28: =IFERROR(AD27/$K$2-1,"") | AE28: =IFERROR(AE27/$K$2-1,"") | AF28: =IFERROR(AF27/$K$2-1,"")
B29: IRR (to Dec-Y-1) | G29: =IFERROR((G27/$K$2)^(1/((DATE(2029-1,12,31)-$K$3)/365.25))-1,"") | H29: =IFERROR((H27/$K$2)^(1/((DATE(2030-1,12,31)-$K$3)/365.25))-1,"") | N29: IRR (to Dec-Y-1) | S29: =IFERROR((S27/$K$2)^(1/((DATE(2029-1,12,31)-$K$3)/365.25))-1,"") | T29: =IFERROR((T27/$K$2)^(1/((DATE(2030-1,12,31)-$K$3)/365.25))-1,"") | Z29: IRR (to Dec-Y-1) | AD29: =IFERROR((AD27/$K$2)^(1/((DATE(2028-1,12,31)-$K$3)/365.25))-1,"") | AE29: =IFERROR((AE27/$K$2)^(1/((DATE(2029-1,12,31)-$K$3)/365.25))-1,"") | AF29: =IFERROR((AF27/$K$2)^(1/((DATE(2030-1,12,31)-$K$3)/365.25))-1,"")
B31: Free Cash Flow | C31: =Model!AF261 | D31: =Model!AK261 | E31: =Model!AL261 | F31: =Model!AM261 | G31: =Model!AN261 | H31: =Model!AO261 | I31: =IFERROR((H31/C31)^(1/5)-1,"n/m") | N31: Free Cash Flow | O31: 99.257 | P31: 125.11873 | Q31: 175.50475 | R31: 199.30195 | S31: 239.57443 | T31: 285.70382 | U31: 0.23546652 | Z31: Free Cash Flow | AA31: 99.257 | AB31: 123.04674 | AC31: 146.09834 | AD31: 172.98095 | AE31: 186.71697 | AF31: 194.57957 | AG31: 0.14410852
B32: FCF % | C32: =IFERROR(C31/C9,"") | D32: =IFERROR(D31/D9,"") | E32: =IFERROR(E31/E9,"") | F32: =IFERROR(F31/F9,"") | G32: =IFERROR(G31/G9,"") | H32: =IFERROR(H31/H9,"") | J32: =IFERROR(AVERAGE(Model!C263,Model!D263,Model!E263,Model!F263,Model!G263,Model!H263,Model!I263,Model!N263,Model!S263,Model!X263,Model!AC263,Model!AH263,Model!AM263,Model!AR263,Model!AW263,Model!BB263,Model!BG263,Model!BL263,Model!BQ263,Model!AF263),"") | K32: =IFERROR(MIN(Model!C263,Model!D263,Model!E263,Model!F263,Model!G263,Model!H263,Model!I263,Model!N263,Model!S263,Model!X263,Model!AC263,Model!AH263,Model!AM263,Model!AR263,Model!AW263,Model!BB263,Model!BG263,Model!BL263,Model!BQ263,Model!AF263),"") | L32: =IFERROR(MAX(Model!C263,Model!D263,Model!E263,Model!F263,Model!G263,Model!H263,Model!I263,Model!N263,Model!S263,Model!X263,Model!AC263,Model!AH263,Model!AM263,Model!AR263,Model!AW263,Model!BB263,Model!BG263,Model!BL263,Model!BQ263,Model!AF263),"") | N32: FCF % | O32: 0.20000081 | P32: 0.18536109 | Q32: 0.22088754 | R32: 0.20691609 | S32: 0.21015765 | T32: 0.21538134 | V32: 0.11558704 | W32: -0.088499642 | X32: 0.20774074 | Z32: FCF % | AA32: 0.20000081 | AB32: 0.1850327 | AC32: 0.20934786 | AD32: 0.23851432 | AE32: 0.24968335 | AF32: 0.25369634 | AH32: 0.12197609 | AI32: -0.088499642 | AJ32: 0.23851432
B33: FCF / share ($) | C33: =IFERROR(C31/C21,"") | D33: =IFERROR(D31/D21,"") | E33: =IFERROR(E31/E21,"") | F33: =IFERROR(F31/F21,"") | G33: =IFERROR(G31/G21,"") | H33: =IFERROR(H31/H21,"") | N33: FCF / share ($) | O33: 1.0350808 | P33: 1.3090678 | Q33: 1.8313321 | R33: 2.073158 | S33: 2.4843236 | T33: 2.9534851 | Z33: FCF / share ($) | AA33: 1.0350808 | AB33: 1.2873894 | AC33: 1.5244863 | AD33: 1.8116873 | AE33: 1.9859797 | AF33: 2.1114623
B34: FCF Yield (on PT) | F34: =IFERROR(F33/F$27,"") | G34: =IFERROR(G33/G$27,"") | H34: =IFERROR(H33/H$27,"") | N34: FCF Yield (on PT) | R34: =IFERROR(R33/R$27,"") | S34: =IFERROR(S33/S$27,"") | T34: =IFERROR(T33/T$27,"") | Z34: FCF Yield (on PT) | AD34: =IFERROR(AD33/AD$27,"") | AE34: =IFERROR(AE33/AE$27,"") | AF34: =IFERROR(AF33/AF$27,"")
B35: Adjusted EBITDA (leverage basis) | C35: =Model!AF174 | D35: =Model!AK174 | E35: =Model!AL174 | F35: =Model!AM174 | G35: =Model!AN174 | H35: =Model!AO174 | I35: =IFERROR((H35/C35)^(1/5)-1,"n/m") | N35: Adjusted EBITDA (leverage basis) | O35: 189.124 | P35: 270 | Q35: 329.11052 | R35: 401.92807 | S35: 478.83327 | T35: 560.54609 | U35: 0.242719 | Z35: Adjusted EBITDA (leverage basis) | AA35: 189.124 | AB35: 265 | AC35: 265.19196 | AD35: 279.21873 | AE35: 291.64789 | AF35: 302.9564 | AG35: 0.098820359
B36: Adjusted EBITDA % of net sales | C36: =IFERROR(C35/C9,"") | D36: =IFERROR(D35/D9,"") | E36: =IFERROR(E35/E9,"") | F36: =IFERROR(F35/F9,"") | G36: =IFERROR(G35/G9,"") | H36: =IFERROR(H35/H9,"") | J36: =IFERROR(AVERAGE(Model!C228,Model!D228,Model!E228,Model!F228,Model!G228,Model!H228,Model!I228,Model!N228,Model!S228,Model!X228,Model!AC228,Model!AH228,Model!AM228,Model!AR228,Model!AW228,Model!BB228,Model!BG228,Model!BL228,Model!BQ228,Model!AF228),"") | K36: =IFERROR(MIN(Model!C228,Model!D228,Model!E228,Model!F228,Model!G228,Model!H228,Model!I228,Model!N228,Model!S228,Model!X228,Model!AC228,Model!AH228,Model!AM228,Model!AR228,Model!AW228,Model!BB228,Model!BG228,Model!BL228,Model!BQ228,Model!AF228),"") | L36: =IFERROR(MAX(Model!C228,Model!D228,Model!E228,Model!F228,Model!G228,Model!H228,Model!I228,Model!N228,Model!S228,Model!X228,Model!AC228,Model!AH228,Model!AM228,Model!AR228,Model!AW228,Model!BB228,Model!BG228,Model!BL228,Model!BQ228,Model!AF228),"") | N36: Adjusted EBITDA % of net sales | O36: 0.38108096 | P36: 0.4 | Q36: 0.41421338 | R36: 0.41728337 | S36: 0.42003845 | T36: 0.42257456 | V36: 0.32168135 | W36: 0.16764565 | X36: 0.41728337 | Z36: Adjusted EBITDA % of net sales | AA36: 0.38108096 | AB36: 0.39849624 | AC36: 0.38 | AD36: 0.385 | AE36: 0.39 | AF36: 0.395 | AH36: 0.31785428 | AI36: 0.16764565 | AJ36: 0.40476399
B38: Net Debt | C38: =Model!AF388 | D38: =Model!AK388 | E38: =Model!AL388 | F38: =Model!AM388 | G38: =Model!AN388 | H38: =Model!AO388 | N38: Net Debt | O38: 634.043 | P38: 761.03927 | Q38: 1087.5345 | R38: 1390.2326 | S38: 1652.6581 | T38: 1868.9543 | Z38: Net Debt | AA38: 634.043 | AB38: 763.11126 | AC38: 619.01292 | AD38: 562.43745 | AE38: 587.29577 | AF38: 609.9128
B39: Net Debt / Adjusted EBITDA (x) | C39: =IFERROR(C38/C35,"") | D39: =IFERROR(D38/D35,"") | E39: =IFERROR(E38/E35,"") | F39: =IFERROR(F38/F35,"") | G39: =IFERROR(G38/G35,"") | H39: =IFERROR(H38/H35,"") | N39: Net Debt / Adjusted EBITDA (x) | O39: 3.3525253 | P39: 2.8186639 | Q39: 3.304466 | R39: 3.4589088 | S39: 3.4514271 | T39: 3.3341671 | Z39: Net Debt / Adjusted EBITDA (x) | AA39: 3.3525253 | AB39: 2.8796651 | AC39: 2.3342069 | AD39: 2.0143257 | AE39: 2.0137152 | AF39: 2.0132032
B41: ROIC | C41: =Model!AF371 | D41: =Model!AK371 | E41: =Model!AL371 | F41: =Model!AM371 | G41: =Model!AN371 | H41: =Model!AO371 | J41: =IFERROR(AVERAGE(Model!C371,Model!D371,Model!E371,Model!F371,Model!G371,Model!H371,Model!I371,Model!N371,Model!S371,Model!X371,Model!AC371,Model!AH371,Model!AM371,Model!AR371,Model!AW371,Model!BB371,Model!BG371,Model!BL371,Model!BQ371,Model!AF371),"") | K41: =IFERROR(MIN(Model!C371,Model!D371,Model!E371,Model!F371,Model!G371,Model!H371,Model!I371,Model!N371,Model!S371,Model!X371,Model!AC371,Model!AH371,Model!AM371,Model!AR371,Model!AW371,Model!BB371,Model!BG371,Model!BL371,Model!BQ371,Model!AF371),"") | L41: =IFERROR(MAX(Model!C371,Model!D371,Model!E371,Model!F371,Model!G371,Model!H371,Model!I371,Model!N371,Model!S371,Model!X371,Model!AC371,Model!AH371,Model!AM371,Model!AR371,Model!AW371,Model!BB371,Model!BG371,Model!BL371,Model!BQ371,Model!AF371),"") | N41: ROIC | O41: 0.068371535 | P41: 0.072144773 | Q41: 0.073575466 | R41: 0.075772324 | S41: 0.078577842 | T41: 0.082445739 | V41: 0.073549029 | W41: 0.068371535 | X41: 0.076503229 | Z41: ROIC | AA41: 0.068371535 | AB41: 0.070309544 | AC41: 0.07190832 | AD41: 0.079438109 | AE41: 0.086816519 | AF41: 0.095273552 | AH41: 0.076186284 | AI41: 0.068371535 | AJ41: 0.080749209
B42: RONTA | C42: =Model!AF382 | D42: =Model!AK382 | E42: =Model!AL382 | F42: =Model!AM382 | G42: =Model!AN382 | H42: =Model!AO382 | J42: =IFERROR(AVERAGE(Model!C382,Model!D382,Model!E382,Model!F382,Model!G382,Model!H382,Model!I382,Model!N382,Model!S382,Model!X382,Model!AC382,Model!AH382,Model!AM382,Model!AR382,Model!AW382,Model!BB382,Model!BG382,Model!BL382,Model!BQ382,Model!AF382),"") | K42: =IFERROR(MIN(Model!C382,Model!D382,Model!E382,Model!F382,Model!G382,Model!H382,Model!I382,Model!N382,Model!S382,Model!X382,Model!AC382,Model!AH382,Model!AM382,Model!AR382,Model!AW382,Model!BB382,Model!BG382,Model!BL382,Model!BQ382,Model!AF382),"") | L42: =IFERROR(MAX(Model!C382,Model!D382,Model!E382,Model!F382,Model!G382,Model!H382,Model!I382,Model!N382,Model!S382,Model!X382,Model!AC382,Model!AH382,Model!AM382,Model!AR382,Model!AW382,Model!BB382,Model!BG382,Model!BL382,Model!BQ382,Model!AF382),"") | N42: RONTA | O42: 0.34743884 | P42: 0.36545608 | Q42: 0.41825233 | R42: 0.45503848 | S42: 0.48824816 | T42: 0.52327581 | V42: 0.4175105 | W42: 0.34743884 | X42: 0.45503848 | Z42: RONTA | AA42: 0.34743884 | AB42: 0.35741445 | AC42: 0.34535156 | AD42: 0.36479598 | AE42: 0.38173985 | AF42: 0.40256154 | AH42: 0.36086917 | AI42: 0.34743884 | AJ42: 0.37037268
B44: Implied Market Cap (USDm) | F44: =F27*F21 | G44: =G27*G21 | H44: =H27*H21 | N44: Implied Market Cap (USDm) | R44: =R27*R21 | S44: =S27*S21 | T44: =T27*T21 | Z44: Implied Market Cap (USDm) | AD44: =AD27*AD21 | AE44: =AE27*AE21 | AF44: =AF27*AF21
B45: (+) Net Debt & NCI | F45: =F38+Model!AM397 | G45: =G38+Model!AN397 | H45: =H38+Model!AO397 | N45: (+) Net Debt & NCI | R45: =R38+Model!AM397 | S45: =S38+Model!AN397 | T45: =T38+Model!AO397 | Z45: (+) Net Debt & NCI | AD45: =AD38+Model!AM397 | AE45: =AE38+Model!AN397 | AF45: =AF38+Model!AO397
B46: Implied Enterprise Value (USDm) | F46: =F44+F45 | G46: =G44+G45 | H46: =H44+H45 | N46: Implied Enterprise Value (USDm) | R46: =R44+R45 | S46: =S44+S45 | T46: =T44+T45 | Z46: Implied Enterprise Value (USDm) | AD46: =AD44+AD45 | AE46: =AE44+AE45 | AF46: =AF44+AF45
B47: Implied EV / Adjusted EBITDA (x) | F47: =IFERROR(F46/F35,"") | G47: =IFERROR(G46/G35,"") | H47: =IFERROR(H46/H35,"") | N47: Implied EV / Adjusted EBITDA (x) | R47: =IFERROR(R46/R35,"") | S47: =IFERROR(S46/S35,"") | T47: =IFERROR(T46/T35,"") | Z47: Implied EV / Adjusted EBITDA (x) | AD47: =IFERROR(AD46/AD35,"") | AE47: =IFERROR(AE46/AE35,"") | AF47: =IFERROR(AF46/AF35,"")

Sheet DCF
B2: DCF VALUATION — LOAR HOLDINGS (LOAR)
B4: 1. WACC BUILD
B5: Risk-free rate (US 10Y govt) | C5: 0.042 | D5: Assumption (~US 10Y Treasury yield); update to market
B6: Equity risk premium | C6: 0.05 | D6: US implied ERP ~4.5–5.5% (Damodaran)
B7: Levered beta | C7: 1.1 | D7: Aerospace components peers (TransDigm, HEICO, Ducommun, Karman) ~1.0–1.2; proprietary, sole-source content and ~50% aftermarket mix dampen cyclicality
B8: Cost of equity | C8: =C5+C7*C6
B9: Pre-tax cost of debt | C9: 0.082 | D9: Term loans at SOFR + 4.25% (B-rated, secured; ~8.2% all-in at 30-Jun-2026)
B10: Tax rate | C10: 0.24 | D10: Model 2027E+ effective tax rate
B11: After-tax cost of debt | C11: =C9*(1-C10)
B12: Target D/V | C12: 0.12 | D12: Net debt ~$0.83bn at 30-Jun-26 vs ~$7.2bn market cap ($75 × ~95.6m diluted shares); D/V ~10–15%
B13: WACC | C13: =C8*(1-C12)+C11*C12
B15: Valuation date (live) | C15: =TODAY() | D15: Periods = (Dec-31-Year − today) / 365.25; cash flows assumed at year-end
B16: 2. UNLEVERED FREE CASH FLOW BUILD (USDm)
D17: 2026E | E17: 2027E | F17: 2028E | G17: 2029E | H17: 2030E | I17: 2031E | J17: 2032E | K17: 2033E | L17: 2034E | M17: 2035E | N17: Terminal | P17: CAGR 26–30E | Q17: CAGR 26–35E
B18: Adjusted EBIT (Model; Adjusted EBITDA − DD&A) | D18: =Model!AK183 | E18: =Model!AL183 | F18: =Model!AM183 | G18: =Model!AN183 | H18: =Model!AO183 | I18: =H18*(1+I$31) | J18: =I18*(1+J$31) | K18: =J18*(1+K$31) | L18: =K18*(1+L$31) | M18: =L18*(1+M$31) | P18: =IFERROR(($H18/$D18)^(1/(VALUE(LEFT($H$17,4))-VALUE(LEFT($D$17,4))))-1,"n/m") | Q18: =IFERROR(($M18/$D18)^(1/(VALUE(LEFT($M$17,4))-VALUE(LEFT($D$17,4))))-1,"n/m")
B19: y/y % | E19: =IFERROR(E18/D18-1,"") | F19: =IFERROR(F18/E18-1,"") | G19: =IFERROR(G18/F18-1,"") | H19: =IFERROR(H18/G18-1,"") | I19: =IFERROR(I18/H18-1,"") | J19: =IFERROR(J18/I18-1,"") | K19: =IFERROR(K18/J18-1,"") | L19: =IFERROR(L18/K18-1,"") | M19: =IFERROR(M18/L18-1,"")
B20: (−) Transaction & integration costs (cash; added back in Adjusted EBITDA) | D20: =-(Model!AK120+Model!AK122) | E20: =-(Model!AL120+Model!AL122) | F20: =-(Model!AM120+Model!AM122) | G20: =-(Model!AN120+Model!AN122) | H20: =-(Model!AO120+Model!AO122) | I20: =H20*(1+I$31) | J20: =I20*(1+J$31) | K20: =J20*(1+K$31) | L20: =K20*(1+L$31) | M20: =L20*(1+M$31)
B21: × (1 − tax rate) | D21: =1-$C$10 | E21: =1-$C$10 | F21: =1-$C$10 | G21: =1-$C$10 | H21: =1-$C$10 | I21: =1-$C$10 | J21: =1-$C$10 | K21: =1-$C$10 | ... M21: =1-$C$10
B22: NOPAT = (Adjusted EBIT − transaction & integration costs) × (1 − t) | D22: =(D18+D20)*D21 | E22: =(E18+E20)*E21 | F22: =(F18+F20)*F21 | G22: =(G18+G20)*G21 | H22: =(H18+H20)*H21 | I22: =(I18+I20)*I21 | J22: =(J18+J20)*J21 | K22: =(K18+K20)*K21 | ... M22: =(M18+M20)*M21
B23: plus depreciation & amortization (total, incl. acquired-intangible amortization) | D23: =Model!AK144 | E23: =Model!AL144 | F23: =Model!AM144 | G23: =Model!AN144 | H23: =Model!AO144 | I23: =H23*(1+I$31) | J23: =I23*(1+J$31) | K23: =J23*(1+K$31) | L23: =K23*(1+L$31) | M23: =L23*(1+M$31)
B24: − Capex (PP&E) and acquisitions (M&A lever, 2027E+) | D24: =D29 | E24: =E29+Model!AL245 | F24: =F29+Model!AM245 | G24: =G29+Model!AN245 | H24: =H29+Model!AO245 | I24: =I29 | J24: =J29 | K24: =K29 | L24: =L29 | M24: =M29
B25: − Δ Working capital (CF statement) | D25: =Model!AK242 | E25: =Model!AL242 | F25: =Model!AM242 | G25: =Model!AN242 | H25: =Model!AO242 | I25: =H25*(1+I$31) | J25: =I25*(1+J$31) | K25: =J25*(1+K$31) | L25: =K25*(1+L$31) | M25: =L25*(1+M$31)
B26: Unlevered FCF | D26: =D22+D23+D24+D25 | E26: =E22+E23+E24+E25 | F26: =F22+F23+F24+F25 | G26: =G22+G23+G24+G25 | H26: =H22+H23+H24+H25 | I26: =I22+I23+I24+I25 | J26: =J22+J23+J24+J25 | K26: =K22+K23+K24+K25 | ... M26: =M22+M23+M24+M25 | N26: =M26*(1+$C$32) | P26: =IFERROR(($H26/$D26)^(1/(VALUE(LEFT($H$17,4))-VALUE(LEFT($D$17,4))))-1,"n/m") | Q26: =IFERROR(($M26/$D26)^(1/(VALUE(LEFT($M$17,4))-VALUE(LEFT($D$17,4))))-1,"n/m")
B27: y/y % | E27: =IFERROR(E26/D26-1,"") | F27: =IFERROR(F26/E26-1,"") | G27: =IFERROR(G26/F26-1,"") | H27: =IFERROR(H26/G26-1,"") | I27: =IFERROR(I26/H26-1,"") | J27: =IFERROR(J26/I26-1,"") | K27: =IFERROR(K26/J26-1,"") | L27: =IFERROR(L26/K26-1,"") | M27: =IFERROR(M26/L26-1,"")
B28: Terminal Value (Gordon Growth) | N28: =N26/($C$13-$C$32)
B29: memo: PP&E capex only (fade years carry no new acquisitions) | D29: =Model!AK244 | E29: =Model!AL244 | F29: =Model!AM244 | G29: =Model!AN244 | H29: =Model!AO244 | I29: =H29*(1+I$31) | J29: =I29*(1+J$31) | K29: =J29*(1+K$31) | L29: =K29*(1+L$31) | M29: =L29*(1+M$31)
B31: Fade-period growth (2031E–35E) | I31: 0.08 | J31: =I31+($M$31-$I$31)/(COLUMNS($I$31:$M$31)-1) | K31: =J31+($M$31-$I$31)/(COLUMNS($I$31:$M$31)-1) | L31: =K31+($M$31-$I$31)/(COLUMNS($I$31:$M$31)-1) | M31: 0.05
B32: Terminal growth rate | C32: 0.035
B34: Discount period (years) | D34: =(DATE(2026,12,31)-$C$15)/365.25 | E34: =(DATE(2027,12,31)-$C$15)/365.25 | F34: =(DATE(2028,12,31)-$C$15)/365.25 | G34: =(DATE(2029,12,31)-$C$15)/365.25 | H34: =(DATE(2030,12,31)-$C$15)/365.25 | I34: =(DATE(2031,12,31)-$C$15)/365.25 | J34: =(DATE(2032,12,31)-$C$15)/365.25 | K34: =(DATE(2033,12,31)-$C$15)/365.25 | L34: =(DATE(2034,12,31)-$C$15)/365.25 | M34: =(DATE(2035,12,31)-$C$15)/365.25 | N34: =M34
B35: Discount factor | D35: =1/(1+$C$13)^D34 | E35: =1/(1+$C$13)^E34 | F35: =1/(1+$C$13)^F34 | G35: =1/(1+$C$13)^G34 | H35: =1/(1+$C$13)^H34 | I35: =1/(1+$C$13)^I34 | J35: =1/(1+$C$13)^J34 | K35: =1/(1+$C$13)^K34 | ... N35: =1/(1+$C$13)^N34
B36: PV of UFCF | D36: =D26*D35 | E36: =E26*E35 | F36: =F26*F35 | G36: =G26*G35 | H36: =H26*H35 | I36: =I26*I35 | J36: =J26*J35 | K36: =K26*K35 | ... M36: =M26*M35 | N36: =N28*N35
D37: Loar's Adjusted EBITDA excludes stock-based compensation (~2.6% of sales), which is a real cost; Adjusted EBIT here deducts all D&A incl. ~$65m p.a. of acquired-intangible amortization (non-cash, added back in row 23). The 1H/26 Harper Engineering consideration ($249.8m) is excluded from 2026E UFCF and added to opening invested capital.
B39: Implied ROIC & incremental ROIC (USDm) | D39: =D17 | E39: =E17 | F39: =F17 | G39: =G17 | H39: =H17 | I39: =I17 | J39: =J17 | K39: =K17 | ... M39: =M17 | N39: Terminal
B40: NOPAT (row 22) | D40: =D22 | E40: =E22 | F40: =F22 | G40: =G22 | H40: =H22 | I40: =I22 | J40: =J22 | K40: =K22 | ... M40: =M22 | N40: =M40*(1+$C$32)
B41: Net investment = NOPAT − UFCF | D41: =D40-D26 | E41: =E40-E26 | F41: =F40-F26 | G41: =G40-G26 | H41: =H40-H26 | I41: =I40-I26 | J41: =J40-J26 | K41: =K40-K26 | ... N41: =N40-N26
B42: Opening invested capital | D42: =Model!AF368-Model!AK245 | E42: =D43 | F42: =E43 | G42: =F43 | H42: =G43 | I42: =H43 | J42: =I43 | K42: =J43 | L42: =K43 | ... N42: =M43
B43: Closing invested capital | D43: =D42+D41 | E43: =E42+E41 | F43: =F42+F41 | G43: =G42+G41 | H43: =H42+H41 | I43: =I42+I41 | J43: =J42+J41 | K43: =K42+K41 | ... M43: =M42+M41
B44: Implied ROIC = NOPAT / opening IC | D44: =IFERROR(D40/D42,"") | E44: =IFERROR(E40/E42,"") | F44: =IFERROR(F40/F42,"") | G44: =IFERROR(G40/G42,"") | H44: =IFERROR(H40/H42,"") | I44: =IFERROR(I40/I42,"") | J44: =IFERROR(J40/J42,"") | K44: =IFERROR(K40/K42,"") | ... N44: =IFERROR(N40/N42,"")
B45: Reinvestment rate = net inv. / NOPAT | D45: =IFERROR(D41/D40,"") | E45: =IFERROR(E41/E40,"") | F45: =IFERROR(F41/F40,"") | G45: =IFERROR(G41/G40,"") | H45: =IFERROR(H41/H40,"") | I45: =IFERROR(I41/I40,"") | J45: =IFERROR(J41/J40,"") | K45: =IFERROR(K41/K40,"") | ... N45: =IFERROR(N41/N40,"")
B46: Incremental ROIC = Δ NOPAT / prior-yr net inv. | E46: =IFERROR((E40-D40)/D41,"") | F46: =IFERROR((F40-E40)/E41,"") | G46: =IFERROR((G40-F40)/F41,"") | H46: =IFERROR((H40-G40)/G41,"") | I46: =IFERROR((I40-H40)/H41,"") | J46: =IFERROR((J40-I40)/I41,"") | K46: =IFERROR((K40-J40)/J41,"") | L46: =IFERROR((L40-K40)/K41,"") | M46: =IFERROR((M40-L40)/L41,"") | N46: =IFERROR($C$32/N45,"")
B47: Cumulative incremental ROIC 2026E–35E | C47: =IFERROR((M40-D40)/SUM(D41:L41),"")
D48: Opening IC = Model 2025A book IC (equity + net debt) + 2026 acquisitions (Harper Engineering, $249.8m cash), rolled forward with DCF net investment (capex + M&A − D&A + ΔWC). Terminal incremental ROIC = g / reinvestment rate.
B49: 3. VALUATION SUMMARY
B50: Sum of PV (explicit + fade) | C50: =SUM(D36:M36)
B51: PV of Terminal Value | C51: =N36
B52: Enterprise Value | C52: =C50+C51
B53: Less: net debt incl. finance leases (Model 2026E YE) | C53: =Model!AK388
B54: Less: non-controlling interests (none) | C54: =Model!AK397
B55: Equity Value | C55: =C52-C53-C54
B56: Diluted shares (m, Model 2026E period end) | C56: =Model!AK394
B57: Implied share price ($) | C57: =C55/C56
B58: Current share price ($) | C58: =Model!AK393
B59: Implied upside / (downside) | C59: =C57/C58-1
B60: Required discount to DCF value for target IRR (discount closes over horizon; value compounds at WACC) | C60: =1-((1+C13)/(1+F60))^F61 | E60: Target IRR | F60: 0.15
B61: Max entry price for target IRR ($) — % vs. current share price shown right | C61: =C57*(1-C60) | D61: =C61/C58-1 | E61: Years for discount to close | F61: 3
B64: 4. SENSITIVITY: IMPLIED PRICE ($) — WACC × Terminal Growth
B65: WACC step (across) | C65: 0.005
B66: Terminal growth step (down) | C66: 0.005
B67: g (down) / WACC | D67: =E67-$C$65 | E67: =F67-$C$65 | F67: =$C$13 | G67: =F67+$C$65 | H67: =G67+$C$65
B68: =B69-$C$66 | D68: =IFERROR((SUMPRODUCT($D$26:$M$26/(1+D$67)^$D$34:$M$34)+($M$26*(1+$B68)/(D$67-$B68))/(1+D$67)^$M$34-$C$53-$C$54)/$C$56,"") | E68: =IFERROR((SUMPRODUCT($D$26:$M$26/(1+E$67)^$D$34:$M$34)+($M$26*(1+$B68)/(E$67-$B68))/(1+E$67)^$M$34-$C$53-$C$54)/$C$56,"") | F68: =IFERROR((SUMPRODUCT($D$26:$M$26/(1+F$67)^$D$34:$M$34)+($M$26*(1+$B68)/(F$67-$B68))/(1+F$67)^$M$34-$C$53-$C$54)/$C$56,"") | G68: =IFERROR((SUMPRODUCT($D$26:$M$26/(1+G$67)^$D$34:$M$34)+($M$26*(1+$B68)/(G$67-$B68))/(1+G$67)^$M$34-$C$53-$C$54)/$C$56,"") | H68: =IFERROR((SUMPRODUCT($D$26:$M$26/(1+H$67)^$D$34:$M$34)+($M$26*(1+$B68)/(H$67-$B68))/(1+H$67)^$M$34-$C$53-$C$54)/$C$56,"")
B69: =B70-$C$66 | D69: =IFERROR((SUMPRODUCT($D$26:$M$26/(1+D$67)^$D$34:$M$34)+($M$26*(1+$B69)/(D$67-$B69))/(1+D$67)^$M$34-$C$53-$C$54)/$C$56,"") | E69: =IFERROR((SUMPRODUCT($D$26:$M$26/(1+E$67)^$D$34:$M$34)+($M$26*(1+$B69)/(E$67-$B69))/(1+E$67)^$M$34-$C$53-$C$54)/$C$56,"") | F69: =IFERROR((SUMPRODUCT($D$26:$M$26/(1+F$67)^$D$34:$M$34)+($M$26*(1+$B69)/(F$67-$B69))/(1+F$67)^$M$34-$C$53-$C$54)/$C$56,"") | G69: =IFERROR((SUMPRODUCT($D$26:$M$26/(1+G$67)^$D$34:$M$34)+($M$26*(1+$B69)/(G$67-$B69))/(1+G$67)^$M$34-$C$53-$C$54)/$C$56,"") | H69: =IFERROR((SUMPRODUCT($D$26:$M$26/(1+H$67)^$D$34:$M$34)+($M$26*(1+$B69)/(H$67-$B69))/(1+H$67)^$M$34-$C$53-$C$54)/$C$56,"")
B70: =$C$32 | D70: =IFERROR((SUMPRODUCT($D$26:$M$26/(1+D$67)^$D$34:$M$34)+($M$26*(1+$B70)/(D$67-$B70))/(1+D$67)^$M$34-$C$53-$C$54)/$C$56,"") | E70: =IFERROR((SUMPRODUCT($D$26:$M$26/(1+E$67)^$D$34:$M$34)+($M$26*(1+$B70)/(E$67-$B70))/(1+E$67)^$M$34-$C$53-$C$54)/$C$56,"") | F70: =IFERROR((SUMPRODUCT($D$26:$M$26/(1+F$67)^$D$34:$M$34)+($M$26*(1+$B70)/(F$67-$B70))/(1+F$67)^$M$34-$C$53-$C$54)/$C$56,"") | G70: =IFERROR((SUMPRODUCT($D$26:$M$26/(1+G$67)^$D$34:$M$34)+($M$26*(1+$B70)/(G$67-$B70))/(1+G$67)^$M$34-$C$53-$C$54)/$C$56,"") | H70: =IFERROR((SUMPRODUCT($D$26:$M$26/(1+H$67)^$D$34:$M$34)+($M$26*(1+$B70)/(H$67-$B70))/(1+H$67)^$M$34-$C$53-$C$54)/$C$56,"")
B71: =B70+$C$66 | D71: =IFERROR((SUMPRODUCT($D$26:$M$26/(1+D$67)^$D$34:$M$34)+($M$26*(1+$B71)/(D$67-$B71))/(1+D$67)^$M$34-$C$53-$C$54)/$C$56,"") | E71: =IFERROR((SUMPRODUCT($D$26:$M$26/(1+E$67)^$D$34:$M$34)+($M$26*(1+$B71)/(E$67-$B71))/(1+E$67)^$M$34-$C$53-$C$54)/$C$56,"") | F71: =IFERROR((SUMPRODUCT($D$26:$M$26/(1+F$67)^$D$34:$M$34)+($M$26*(1+$B71)/(F$67-$B71))/(1+F$67)^$M$34-$C$53-$C$54)/$C$56,"") | G71: =IFERROR((SUMPRODUCT($D$26:$M$26/(1+G$67)^$D$34:$M$34)+($M$26*(1+$B71)/(G$67-$B71))/(1+G$67)^$M$34-$C$53-$C$54)/$C$56,"") | H71: =IFERROR((SUMPRODUCT($D$26:$M$26/(1+H$67)^$D$34:$M$34)+($M$26*(1+$B71)/(H$67-$B71))/(1+H$67)^$M$34-$C$53-$C$54)/$C$56,"")
B72: =B71+$C$66 | D72: =IFERROR((SUMPRODUCT($D$26:$M$26/(1+D$67)^$D$34:$M$34)+($M$26*(1+$B72)/(D$67-$B72))/(1+D$67)^$M$34-$C$53-$C$54)/$C$56,"") | E72: =IFERROR((SUMPRODUCT($D$26:$M$26/(1+E$67)^$D$34:$M$34)+($M$26*(1+$B72)/(E$67-$B72))/(1+E$67)^$M$34-$C$53-$C$54)/$C$56,"") | F72: =IFERROR((SUMPRODUCT($D$26:$M$26/(1+F$67)^$D$34:$M$34)+($M$26*(1+$B72)/(F$67-$B72))/(1+F$67)^$M$34-$C$53-$C$54)/$C$56,"") | G72: =IFERROR((SUMPRODUCT($D$26:$M$26/(1+G$67)^$D$34:$M$34)+($M$26*(1+$B72)/(G$67-$B72))/(1+G$67)^$M$34-$C$53-$C$54)/$C$56,"") | H72: =IFERROR((SUMPRODUCT($D$26:$M$26/(1+H$67)^$D$34:$M$34)+($M$26*(1+$B72)/(H$67-$B72))/(1+H$67)^$M$34-$C$53-$C$54)/$C$56,"")
B75: 5. REVERSE DCF
B76: To solve for the market-implied path: Data ▸ What-If Analysis ▸ Goal Seek — set C57 (implied price) to the current price (C58) by changing C32 (terminal growth) or the Model scenario levers (end-market growth, Adjusted EBITDA margin, M&A spend).
B78: 6. MAUBOUSSIN EV / NOPAT — TWO-STAGE FRAMEWORK
B79: EV/NOPAT = 1/r + [g × (1 − r/ROIIC) / (r × (r − g))] × [1 − ((1+g)/(1+r))^N]
B80: Formula source: Mauboussin & Rappaport, "Expectations Investing" (2021); Counterpoint Global, "What Does a Price-Earnings Multiple Mean?" (2020).
B82: Input | C82: Value | D82: Rationale (Loar characteristics)
B83: r (Cost of capital / WACC) | C83: =$C$13 | D83: Linked from Section 1 WACC build
B84: g (NOPAT growth, Stage 1) | C84: 0.15 | D84: Model Adjusted EBIT CAGR 2026–30E: high-single-digit organic growth, ~50 bps p.a. margin expansion, ~$300m p.a. of bolt-on M&A and deleveraging → ~15% NOPAT growth
B85: ROIIC (Return on incremental invested capital) | C85: 0.2 | D85: Proprietary, mostly sole-source components (~50% aftermarket) earn very high returns on organic capital (capex ~2.5% of sales); acquisitions at 6–8x sales earn ~8–10% after tax, rising with value drivers
B86: N (Years of value creation / CAP) | C86: 12 | D86: Niche positions on long-lived platforms (20–30-year aircraft lives), FAA / OEM qualification barriers and a TransDigm-style value-driver model; growth reliant on continued M&A
B88: Calculation | C88: Value
B89: Steady-state component: 1 / r | C89: =1/C83
B90: Value-creation factor: 1 − r / ROIIC | C90: =1-C83/C85
B91: Growth multiplier: g × (1 − r/ROIIC) / (r × (r − g)) | C91: =C84*C90/(C83*(C83-C84))
B92: Time decay: 1 − ((1+g)/(1+r))^N | C92: =1-((1+C84)/(1+C83))^C86
B93: PVGO component (growth value) | C93: =C91*C92
B94: Mauboussin EV / NOPAT (steady-state + PVGO) | C94: =C89+C93
B96: VALUATION — Applied to 2028E NOPAT | C96: USDm
B97: 2028E Adjusted EBIT (Model) | C97: =Model!AM183
B98: (−) 2028E transaction & integration costs | C98: =-(Model!AM120+Model!AM122)
B99: Tax rate (from WACC build) | C99: =$C$10
B100: 2028E NOPAT = (Adj. EBIT − transaction & integration costs) × (1 − t) | C100: =(C97+C98)*(1-C99)
B101: × Mauboussin EV/NOPAT multiple | C101: =C94
B102: Implied Enterprise Value (2028E basis) | C102: =C100*C101
B103: Less: YE2027 net debt (Model) | C103: =Model!AL388+Model!AL397
B104: Implied Equity Value | C104: =C102-C103
B105: Diluted shares 2028E (m, Model) | C105: =Model!AM394
B106: Implied share price 2028 ($) | C106: =C104/C105
B108: Current share price ($) | C108: =C58
B109: Implied upside / (downside) | C109: =C106/C108-1
B111: MARKET-IMPLIED EV/NOPAT TODAY | C111: USDm
B112: Current market cap (spot × diluted shares) | C112: =C58*C56
B113: Plus: YE2026 net debt & NCI | C113: =C53+C54
B114: Implied Enterprise Value (today) | C114: =C112+C113
B115: LOAR's market-implied EV/NOPAT (on 2028E NOPAT) | C115: =C114/C100
B117: Multiple gap (Mauboussin − Market) | C117: =C94-C115
...

Sheet Charts
B2: Loar Holdings — Operating Performance (2012–2025) and Model Forecast (2026E–2030E)
B3: USDm · Linked to Model. Bars = organic growth vs acquisition contribution (as published from 2023; earlier years: total growth shown as organic where no split is available). Adjusted EBITDA as reconciled by Loar in each period (prospectus for FY2012–23). ROIC / RONTA on Adjusted EBIT (balance sheets from FY2022).
C7: 2012 | D7: 2013 | E7: 2014 | F7: 2015 | G7: 2016 | H7: 2017 | I7: 2018 | J7: 2019 | K7: 2020 | L7: 2021 | M7: 2022 | N7: 2023 | O7: 2024 | P7: 2025 | Q7: 2026E | R7: 2027E | S7: 2028E | T7: 2029E | U7: 2030E
B8: Organic growth % | C8: =IFERROR(Model!C70+0,IFERROR(Model!C219+0,0)) | D8: =IFERROR(Model!D70+0,IFERROR(Model!D219+0,0)) | E8: =IFERROR(Model!E70+0,IFERROR(Model!E219+0,0)) | F8: =IFERROR(Model!F70+0,IFERROR(Model!F219+0,0)) | G8: =IFERROR(Model!G70+0,IFERROR(Model!G219+0,0)) | H8: =IFERROR(Model!H70+0,IFERROR(Model!H219+0,0)) | I8: =IFERROR(Model!I70+0,IFERROR(Model!I219+0,0)) | J8: =IFERROR(Model!J70+0,IFERROR(Model!J219+0,0)) | ... L8: =IFERROR(Model!L70+0,IFERROR(Model!L219+0,0)) | M8: =IFERROR(Model!Q70+0,IFERROR(Model!Q219+0,0)) | N8: =IFERROR(Model!V70+0,IFERROR(Model!V219+0,0)) | O8: =IFERROR(Model!AA70+0,IFERROR(Model!AA219+0,0)) | P8: =IFERROR(Model!AF70+0,IFERROR(Model!AF219+0,0)) | Q8: =IFERROR(Model!AK70+0,IFERROR(Model!AK219+0,0)) | R8: =IFERROR(Model!AL70+0,IFERROR(Model!AL219+0,0)) | S8: =IFERROR(Model!AM70+0,IFERROR(Model!AM219+0,0)) | T8: =IFERROR(Model!AN70+0,IFERROR(Model!AN219+0,0)) | U8: =IFERROR(Model!AO70+0,IFERROR(Model!AO219+0,0))
B9: Acquisition contribution % | C9: =IFERROR(Model!C71+0,0) | D9: =IFERROR(Model!D71+0,0) | E9: =IFERROR(Model!E71+0,0) | F9: =IFERROR(Model!F71+0,0) | G9: =IFERROR(Model!G71+0,0) | H9: =IFERROR(Model!H71+0,0) | I9: =IFERROR(Model!I71+0,0) | J9: =IFERROR(Model!J71+0,0) | ... L9: =IFERROR(Model!L71+0,0) | M9: =IFERROR(Model!Q71+0,0) | N9: =IFERROR(Model!V71+0,0) | O9: =IFERROR(Model!AA71+0,0) | P9: =IFERROR(Model!AF71+0,0) | Q9: =IFERROR(Model!AK71+0,0) | R9: =IFERROR(Model!AL71+0,0) | S9: =IFERROR(Model!AM71+0,0) | T9: =IFERROR(Model!AN71+0,0) | U9: =IFERROR(Model!AO71+0,0)
C11: =C7 | D11: =D7 | E11: =E7 | F11: =F7 | G11: =G7 | H11: =H7 | I11: =I7 | J11: =J7 | ... U11: =U7
B12: Adjusted EBITDA | C12: =Model!C174 | D12: =Model!D174 | E12: =Model!E174 | F12: =Model!F174 | G12: =Model!G174 | H12: =Model!H174 | I12: =Model!I174 | J12: =Model!J174 | ... L12: =Model!L174 | M12: =Model!Q174 | N12: =Model!V174 | O12: =Model!AA174 | P12: =Model!AF174 | Q12: =Model!AK174 | R12: =Model!AL174 | S12: =Model!AM174 | T12: =Model!AN174 | U12: =Model!AO174
B13: Operating Income (GAAP) | C13: =Model!C134 | D13: =Model!D134 | E13: =Model!E134 | F13: =Model!F134 | G13: =Model!G134 | H13: =Model!H134 | I13: =Model!I134 | J13: =Model!J134 | ... L13: =Model!L134 | M13: =Model!Q134 | N13: =Model!V134 | O13: =Model!AA134 | P13: =Model!AF134 | Q13: =Model!AK134 | R13: =Model!AL134 | S13: =Model!AM134 | T13: =Model!AN134 | U13: =Model!AO134
B14: Adj. EBITDA Margin % | C14: =Model!C228 | D14: =Model!D228 | E14: =Model!E228 | F14: =Model!F228 | G14: =Model!G228 | H14: =Model!H228 | I14: =Model!I228 | J14: =Model!J228 | ... L14: =Model!L228 | M14: =Model!Q228 | N14: =Model!V228 | O14: =Model!AA228 | P14: =Model!AF228 | Q14: =Model!AK228 | R14: =Model!AL228 | S14: =Model!AM228 | T14: =Model!AN228 | U14: =Model!AO228
B15: GAAP Op. Margin % | C15: =Model!C231 | D15: =Model!D231 | E15: =Model!E231 | F15: =Model!F231 | G15: =Model!G231 | H15: =Model!H231 | I15: =Model!I231 | J15: =Model!J231 | ... L15: =Model!L231 | M15: =Model!Q231 | N15: =Model!V231 | O15: =Model!AA231 | P15: =Model!AF231 | Q15: =Model!AK231 | R15: =Model!AL231 | S15: =Model!AM231 | T15: =Model!AN231 | U15: =Model!AO231
C17: =C7 | D17: =D7 | E17: =E7 | F17: =F7 | G17: =G7 | H17: =H7 | I17: =I7 | J17: =J7 | ... U17: =U7
B18: ROIC | C18: =IFERROR(Model!C371+0,NA()) | D18: =IFERROR(Model!D371+0,NA()) | E18: =IFERROR(Model!E371+0,NA()) | F18: =IFERROR(Model!F371+0,NA()) | G18: =IFERROR(Model!G371+0,NA()) | H18: =IFERROR(Model!H371+0,NA()) | I18: =IFERROR(Model!I371+0,NA()) | J18: =IFERROR(Model!J371+0,NA()) | ... L18: =IFERROR(Model!L371+0,NA()) | M18: =IFERROR(Model!Q371+0,NA()) | N18: =IFERROR(Model!V371+0,NA()) | O18: =IFERROR(Model!AA371+0,NA()) | P18: =IFERROR(Model!AF371+0,NA()) | Q18: =IFERROR(Model!AK371+0,NA()) | R18: =IFERROR(Model!AL371+0,NA()) | S18: =IFERROR(Model!AM371+0,NA()) | T18: =IFERROR(Model!AN371+0,NA()) | U18: =IFERROR(Model!AO371+0,NA())
B19: RONTA | C19: =IFERROR(Model!C382+0,NA()) | D19: =IFERROR(Model!D382+0,NA()) | E19: =IFERROR(Model!E382+0,NA()) | F19: =IFERROR(Model!F382+0,NA()) | G19: =IFERROR(Model!G382+0,NA()) | H19: =IFERROR(Model!H382+0,NA()) | I19: =IFERROR(Model!I382+0,NA()) | J19: =IFERROR(Model!J382+0,NA()) | ... L19: =IFERROR(Model!L382+0,NA()) | M19: =IFERROR(Model!Q382+0,NA()) | N19: =IFERROR(Model!V382+0,NA()) | O19: =IFERROR(Model!AA382+0,NA()) | P19: =IFERROR(Model!AF382+0,NA()) | Q19: =IFERROR(Model!AK382+0,NA()) | R19: =IFERROR(Model!AL382+0,NA()) | S19: =IFERROR(Model!AM382+0,NA()) | T19: =IFERROR(Model!AN382+0,NA()) | U19: =IFERROR(Model!AO382+0,NA())
B20: Adj. EBITDA margin % | C20: =IFERROR(Model!C228+0,NA()) | D20: =IFERROR(Model!D228+0,NA()) | E20: =IFERROR(Model!E228+0,NA()) | F20: =IFERROR(Model!F228+0,NA()) | G20: =IFERROR(Model!G228+0,NA()) | H20: =IFERROR(Model!H228+0,NA()) | I20: =IFERROR(Model!I228+0,NA()) | J20: =IFERROR(Model!J228+0,NA()) | ... L20: =IFERROR(Model!L228+0,NA()) | M20: =IFERROR(Model!Q228+0,NA()) | N20: =IFERROR(Model!V228+0,NA()) | O20: =IFERROR(Model!AA228+0,NA()) | P20: =IFERROR(Model!AF228+0,NA()) | Q20: =IFERROR(Model!AK228+0,NA()) | R20: =IFERROR(Model!AL228+0,NA()) | S20: =IFERROR(Model!AM228+0,NA()) | T20: =IFERROR(Model!AN228+0,NA()) | U20: =IFERROR(Model!AO228+0,NA())
B21: FCF margin % | C21: =IFERROR(Model!C263+0,NA()) | D21: =IFERROR(Model!D263+0,NA()) | E21: =IFERROR(Model!E263+0,NA()) | F21: =IFERROR(Model!F263+0,NA()) | G21: =IFERROR(Model!G263+0,NA()) | H21: =IFERROR(Model!H263+0,NA()) | I21: =IFERROR(Model!I263+0,NA()) | J21: =IFERROR(Model!J263+0,NA()) | ... L21: =IFERROR(Model!L263+0,NA()) | M21: =IFERROR(Model!Q263+0,NA()) | N21: =IFERROR(Model!V263+0,NA()) | O21: =IFERROR(Model!AA263+0,NA()) | P21: =IFERROR(Model!AF263+0,NA()) | Q21: =IFERROR(Model!AK263+0,NA()) | R21: =IFERROR(Model!AL263+0,NA()) | S21: =IFERROR(Model!AM263+0,NA()) | T21: =IFERROR(Model!AN263+0,NA()) | U21: =IFERROR(Model!AO263+0,NA())
