Workbook

Sheet Model
CF1: SCENARIO SWITCH ▼ (Bull / Base / Bear) — drives all scenario-linked forecast drivers
B2: Mastercard Incorporated (NYSE: MA) — 3-Statement Financial Model | CF2: Base
B3: US GAAP as reported · USD millions (per-share data in USD; shares in millions; GDV in USD billions) · Fiscal years ended 31 December · Source: Mastercard Forms 10-K / 10-Q, Form 8-K earnings releases (Ex. 99.1), SEC EDGAR (CIK 1141391); XBRL company facts for cross-checks · FY26 outlook from the Q2-26 call is UNVERIFIED (not in an SEC filing)
B4: Basis notes: as originally reported in each release (2014 net revenue re-presented in 2015 kept as memo; 2018 cost reclassification; Q1-26 ending cash per the 10-Q). One reportable segment; net revenue = payment network + value-added services and solutions (presentation from the FY2022 10-K; legacy categories in memo). 10-for-1 split Jan-2014. Cash flow includes restricted cash and security deposits from 2018. Acquisitions: Vocalink 2017, Finicity / Nets A2A / Ekata 2020–21, Recorded Future Dec-2024; BVNK pending (assumed 30-Sep-2026).
CH5: Forecast | CI5: Historical | CJ5: Historical | CK5: Historical
B6: (USDm) | C6: 2006 | D6: 2007 | E6: 2008 | F6: 2009 | G6: 2010 | H6: 2011 | I6: 2012 | J6: Q1/13 | K6: Q2/13 | L6: Q3/13 | M6: Q4/13 | N6: 2013 | O6: Q1/14 | P6: Q2/14 | Q6: Q3/14 | R6: Q4/14 | S6: 2014 | T6: Q1/15 | U6: Q2/15 | V6: Q3/15 | W6: Q4/15 | X6: 2015 | Y6: Q1/16 | Z6: Q2/16 | AA6: Q3/16 | AB6: Q4/16 | AC6: 2016 | AD6: Q1/17 | AE6: Q2/17 | AF6: Q3/17 | AG6: Q4/17 | AH6: 2017 | AI6: Q1/18 | AJ6: Q2/18 | AK6: Q3/18 | AL6: Q4/18 | AM6: 2018 | AN6: Q1/19 | AO6: Q2/19 | AP6: Q3/19 | AQ6: Q4/19 | AR6: 2019 | AS6: Q1/20 | AT6: Q2/20 | AU6: Q3/20 | AV6: Q4/20 | AW6: 2020 | AX6: Q1/21 | AY6: Q2/21 | AZ6: Q3/21 | BA6: Q4/21 | BB6: 2021 | BC6: Q1/22 | BD6: Q2/22 | BE6: Q3/22 | BF6: Q4/22 | BG6: 2022 | BH6: Q1/23 | BI6: Q2/23 | BJ6: Q3/23 | BK6: Q4/23 | BL6: 2023 | BM6: Q1/24 | BN6: Q2/24 | BO6: Q3/24 | BP6: Q4/24 | BQ6: 2024 | BR6: Q1/25 | BS6: Q2/25 | BT6: Q3/25 | BU6: Q4/25 | BV6: 2025 | BW6: Q1/26 | BX6: Q2/26 | BY6: Q3/26E | BZ6: Q4/26E | CA6: 2026E | CB6: 2027E | CC6: 2028E | CD6: 2029E | CE6: 2030E | CF6: Modelling Notes | CH6: 5Y CAGR | CI6: 5Y CAGR | CJ6: 10Y CAGR | CK6: 19Y CAGR
CH7: 25-'30 | CI7: 20-'25 | CJ7: 15-'25 | CK7: 06-'25
B8: NET REVENUE BUILD — PAYMENT NETWORK (GDV × YIELD) · VALUE-ADDED SERVICES & SOLUTIONS (single reportable segment) | CF8: REVENUE BUILD — modelling logic (GDV → payment network net revenue at the network yield; value-added services and solutions by growth; Σ = net revenue → adjusted opex → adjusted operating income → GAAP P&L)
CN9: SCENARIO INPUT TABLE — driver assumptions per Bull / Base / Bear | CO9: Bull | CP9: Base | CQ9: Bear | CR9: Bull / Bear = Base + Δ (Δ inputs on each block header). Outlook block = high / mid / low end of the FY26 guidance (UNVERIFIED: call commentary, not in an SEC filing).
B10: Network volume drivers (Mastercard-branded programs, worldwide; operating-performance tables in each release) | CF10: VOLUME DRIVERS — GDV in USD = prior year × (1 + local-currency growth) × (1 + FX translation)
B11: Gross dollar volume (GDV), USD bn | C11: 1956 | D11: 2276 | E11: 2533 | F11: 2454 | G11: 2727 | H11: 3249 | I11: 3647 | J11: 947 | K11: 1007 | L11: 1045 | M11: 1104 | N11: 4103 | O11: 1045 | P11: 1124 | Q11: 1157 | R11: 1172 | S11: 4499 | T11: 1063 | U11: 1141 | V11: 1159 | W11: 1199 | X11: 4564 | Y11: 1141 | Z11: 1228 | AA11: 1221 | AB11: 1232 | AC11: 4827 | AD11: 1181 | AE11: 1282 | AF11: 1353 | AG11: 1420 | AH11: 5242 | AI11: 1415 | AJ11: 1475 | AK11: 1468 | AL11: 1550 | AM11: 5901 | AN11: 1484 | AO11: 1598 | AP11: 1652 | AQ11: 1726 | AR11: 6461 | AS11: 1565 | AT11: 1383 | AU11: 1648 | AV11: 1747 | AW11: 6337 | AX11: 1711 | AY11: 1904 | AZ11: 1993 | BA11: 2113 | BB11: 7720 | BC11: 1919 | BD11: 2054 | BE11: 2069 | BF11: 2133 | BG11: 8177 | BH11: 2108 | BI11: 2267 | BJ11: 2305 | BK11: 2352 | BL11: 9030 | BM11: 2290 | BN11: 2403 | BO11: 2502 | BP11: 2561 | BQ11: 9757 | BR11: 2417 | BS11: 2631 | BT11: 2747 | BU11: 2819 | BV11: 10632 | BW11: 2703 | BX11: 2881 | BY11: =BT11*(1+BY14) -> 2971.9312 | BZ11: =BU11*(1+BZ14) -> 3034.6535 | CA11: =SUM(BW11:BZ11) -> 11590.585 | CB11: =CA11*(1+CB14) -> 12575.784 | CC11: =CB11*(1+CC14) -> 13581.847 | CD11: =CC11*(1+CD14) -> 14668.395 | CE11: =CD11*(1+CE14) -> 15768.525 | CF11: Release "Mastercard Incorporated Operating Performance" table, all programs, worldwide (three months; annual = full-year table). GDV = purchase + cash volume; customer-reported and revised over time. | CH11: =IFERROR((CE11/BV11)^(1/5)-1,"n/m") -> 0.082019826 | CI11: =IFERROR((BV11/AW11)^(1/5)-1,"n/m") -> 0.10903755 | CJ11: =IFERROR((BV11/X11)^(1/10)-1,"n/m") -> 0.088245633 | CK11: =IFERROR((BV11/C11)^(1/19)-1,"n/m") -> 0.09319381 | CN11: FY26 outlook — Q2-26 earnings call (30-Jul-2026) — UNVERIFIED (not in an SEC filing) | CO11: High | CP11: Mid | CQ11: Low | CR11: Net revenue growth at the high end of a low-double-digits rate (currency-neutral, ex-acquisitions; raised), FX ~+1 ppt; adjusted opex growth low double digits (currency-neutral, ex-acquisitions), FX 0.5–1 ppt headwind; Q3 other expense ~$(125)m; non-GAAP tax rate 20–21% in Q3 and Q4. Source: third-party call transcripts (web search); Mastercard's 8-K release has no outlook. Numeric end-points are model translations of the wording.
B12: GDV growth, local currency % | C12: 14.17 | D12: 0.144 | E12: 0.107 | F12: 0.014 | G12: 0.091 | H12: 0.161 | I12: 0.154 | J12: 0.121 | K12: 0.133 | L12: 0.152 | M12: 0.138 | N12: 0.136 | O12: 0.138 | P12: 0.129 | Q12: 0.119 | R12: 0.129 | S12: 0.128 | T12: 0.121 | U12: 0.128 | V12: 0.13 | W12: 0.125 | X12: 0.126 | Y12: 0.132 | Z12: 0.114 | AA12: 0.073 | AB12: 0.053 | AC12: 0.092 | AD12: 0.047 | AE12: 0.061 | AF12: 0.101 | AG12: 0.127 | AH12: 0.086 | AI12: 0.141 | AJ12: 0.142 | AK12: 0.133 | AL12: 0.143 | AM12: 0.14 | AN12: 0.116 | AO12: 0.129 | AP12: 0.144 | AQ12: 0.123 | AR12: 0.13 | AS12: 0.081 | AT12: -0.1 | AU12: 0.012 | AV12: 0.014 | AW12: 0.001 | AX12: 0.075 | AY12: 0.328 | AZ12: 0.199 | BA12: 0.23 | BB12: 0.205 | BC12: 0.173 | BD12: 0.136 | BE12: 0.114 | BF12: 0.076 | BG12: 0.123 | BH12: 0.15 | BI12: 0.125 | BJ12: 0.108 | BK12: 0.099 | BL12: 0.119 | BM12: 0.104 | BN12: 0.094 | BO12: 0.105 | BP12: 0.116 | BQ12: 0.105 | BR12: 0.093 | BS12: 0.09 | BT12: 0.087 | BU12: 0.074 | BV12: 0.086 | BW12: 0.073 | BX12: 0.08 | BY12: =AVERAGE(BW12:BX12) -> 0.0765 | BZ12: =AVERAGE(BW12:BX12) -> 0.0765 | CA12: =AVERAGE(BW12:BZ12) -> 0.0765 | CB12: =CHOOSE(MATCH($CF$2,{"Bull","Base","Bear"},0),$CO$28,$CP$28,$CQ$28) -> 0.085 | CC12: =CHOOSE(MATCH($CF$2,{"Bull","Base","Bear"},0),$CO$29,$CP$29,$CQ$29) -> 0.08 | CD12: =CHOOSE(MATCH($CF$2,{"Bull","Base","Bear"},0),$CO$30,$CP$30,$CQ$30) -> 0.08 | CE12: =CHOOSE(MATCH($CF$2,{"Bull","Base","Bear"},0),$CO$31,$CP$31,$CQ$31) -> 0.075 | CF12: As published (EU-rule-adjusted figures 2016–17 are in the transcription notes, not used). Q3/Q4-26E: H1-26 average (8.0%, 7.3%→8.0%); 2027E+: scenario lever. | CH12: =IFERROR(AVERAGE(CA12,CB12,CC12,CD12,CE12),"n/m") -> 0.0793 | CI12: =IFERROR(AVERAGE(BB12,BG12,BL12,BQ12,BV12),"n/m") -> 0.1276 | CJ12: =IFERROR(AVERAGE(AC12,AH12,AM12,AR12,AW12,BB12,BG12,BL12,BQ12,BV12),"n/m") -> 0.1087 | CK12: =IFERROR(AVERAGE(C12,D12,E12,F12,G12,H12,I12,N12,S12,X12,AC12,AH12,AM12,AR12,AW12,BB12,BG12,BL12,BQ12,BV12),"n/m") -> 0.8159 | CN12: FY26 net revenue growth, reported (UNVERIFIED) | CO12: 0.14 | CP12: 0.135 | CQ12: 0.13 | CR12: Model end-points (reported USD growth): currency-neutral 13.0 / 12.5 / 12.0% (high end of low double digits) + ~1 ppt FX = 14.0 / 13.5 / 13.0% (Bull / Base / Bear). H1-26 actual +15% reported, +12% currency-neutral.
B13: FX translation (USD growth − local-currency growth), pp | C13: =IF(AND(ISNUMBER(C14),ISNUMBER(C12)),C14-C12,"") -> -14.021 | D13: =IF(AND(ISNUMBER(D14),ISNUMBER(D12)),D14-D12,"") -> 0.04 | E13: =IF(AND(ISNUMBER(E14),ISNUMBER(E12)),E14-E12,"") -> 0.008 | F13: =IF(AND(ISNUMBER(F14),ISNUMBER(F12)),F14-F12,"") -> -0.047 | G13: =IF(AND(ISNUMBER(G14),ISNUMBER(G12)),G14-G12,"") -> 0.016 | H13: =IF(AND(ISNUMBER(H14),ISNUMBER(H12)),H14-H12,"") -> 0.032 | I13: =IF(AND(ISNUMBER(I14),ISNUMBER(I12)),I14-I12,"") -> -0.033 | J13: =IF(AND(ISNUMBER(J14),ISNUMBER(J12)),J14-J12,"") -> -0.007 | ... BX13: =IF(AND(ISNUMBER(BX14),ISNUMBER(BX12)),BX14-BX12,"") -> 0.012 | BY13: 0.005 | BZ13: 0 | CA13: =CA14-CA12 -> 0.013660339 | CB13: 0 | CC13: 0 | CD13: 0 | CE13: 0 | CF13: Q3/Q4-26E: point estimates consistent with the ~1 ppt FY26 FX tailwind in the (unverified) outlook after +2.6 ppt in H1-26; 2027E+: constant currency (0). | CN13: FY26 adjusted operating expense growth, reported (UNVERIFIED; Bull = low end) | CO13: 0.11 | CP13: 0.115 | CQ13: 0.12 | CR13: Model end-points for adjusted operating expense growth (reported USD): low double digits currency-neutral (~10–11%) + 0.5–1 ppt FX headwind = 11.0 / 11.5 / 12.0% (Bull = low end). H1-26 actual +11% reported, +9% currency-neutral.
B14: GDV growth, USD % | C14: 0.149 | D14: 0.184 | E14: 0.115 | F14: -0.033 | G14: 0.107 | H14: 0.193 | I14: 0.121 | J14: 0.114 | K14: 0.128 | L14: 0.136 | M14: 0.118 | N14: 0.124 | O14: 0.103 | P14: 0.114 | Q14: 0.106 | R14: 0.06 | S14: 0.095 | T14: 0.018 | U14: 0.014 | V14: 0 | W14: 0.022 | X14: 0.014 | Y14: 0.072 | Z14: 0.076 | AA14: 0.054 | AB14: 0.026 | AC14: 0.056 | AD14: 0.034 | AE14: 0.042 | AF14: 0.11 | AG14: 0.155 | AH14: 0.087 | AI14: 0.193 | AJ14: 0.153 | AK14: 0.089 | AL14: 0.094 | AM14: 0.13 | AN14: 0.054 | AO14: 0.084 | AP14: 0.124 | AQ14: 0.115 | AR14: 0.096 | AS14: 0.055 | AT14: -0.137 | AU14: -0.003 | AV14: 0.01 | AW14: -0.02 | AX14: 0.093 | AY14: 0.383 | AZ14: 0.211 | BA14: 0.21 | BB14: 0.219 | BC14: 0.123 | BD14: 0.077 | BE14: 0.038 | BF14: 0.008 | BG14: 0.059 | BH14: 0.1 | BI14: 0.101 | BJ14: 0.112 | BK14: 0.103 | BL14: 0.104 | BM14: 0.086 | BN14: 0.061 | BO14: 0.086 | BP14: 0.089 | BQ14: 0.081 | BR14: 0.055 | BS14: 0.094 | BT14: 0.098 | BU14: 0.098 | BV14: 0.087 | BW14: 0.115 | BX14: 0.092 | BY14: =(1+BY12)*(1+BY13)-1 -> 0.0818825 | BZ14: =(1+BZ12)*(1+BZ13)-1 -> 0.0765 | CA14: =IF(AND(ISNUMBER(CA11),ISNUMBER(BV11)),IFERROR(CA11/BV11-1,""),"") -> 0.090160339 | CB14: =(1+CB12)*(1+CB13)-1 -> 0.085 | CC14: =(1+CC12)*(1+CC13)-1 -> 0.08 | CD14: =(1+CD12)*(1+CD13)-1 -> 0.08 | CE14: =(1+CE12)*(1+CE13)-1 -> 0.075 | CF14: 2026E = 2026E GDV ÷ 2025 GDV − 1; local-currency 2026E = average of the quarters (approximation). | CN14: H2-26E share repurchases ($m) | CO14: 7800 | CP14: 7000 | CQ14: 6000 | CR14: H1-26 $8,933m (Q2 $4.9bn); $0.7bn repurchased 1–27 Jul; $7.8bn of authorization left at 27-Jul-2026 (a new program is usually approved in December). Assumption.
B15: Memo: cross-border volume growth, local currency % (release text) | G15: 0.152 | H15: 0.187 | I15: 0.16 | J15: 0.16 | K15: 0.17 | L15: 0.19 | M15: 0.18 | N15: 0.18 | O15: 0.17 | P15: 0.16 | Q15: 0.15 | R15: 0.19 | S15: 0.16 | T15: 0.19 | U15: 0.17 | V15: 0.16 | W15: 0.12 | X15: 0.16 | Y15: 0.12 | Z15: 0.1 | AA15: 0.12 | AB15: 0.13 | AC15: 0.12 | AD15: 0.13 | AE15: 0.14 | AF15: 0.15 | AG15: 0.17 | AH15: 0.15 | AI15: 0.21 | AJ15: 0.19 | AK15: 0.17 | AL15: 0.17 | AM15: 0.18 | AN15: 0.13 | AO15: 0.16 | AP15: 0.17 | AQ15: 0.16 | AR15: 0.16 | AS15: -0.01 | AT15: -0.45 | AU15: -0.36 | AV15: -0.29 | AW15: -0.29 | AX15: -0.17 | AY15: 0.58 | AZ15: 0.52 | BA15: 0.53 | BB15: 0.32 | BC15: 0.53 | BD15: 0.58 | BE15: 0.44 | BF15: 0.31 | BG15: 0.45 | BH15: 0.35 | BI15: 0.24 | BJ15: 0.21 | BK15: 0.18 | BL15: 0.24 | BM15: 0.18 | BN15: 0.17 | BO15: 0.17 | BP15: 0.2 | BQ15: 0.18 | BR15: 0.15 | BS15: 0.15 | BT15: 0.15 | BU15: 0.14 | BV15: 0.15 | BW15: 0.13 | BX15: 0.12 | CF15: Release narrative ("cross-border volume growth of x% on a local currency basis"); 2006–09 not stated. Drives cross-border assessments inside payment network yield. | CH15: =IFERROR(AVERAGE(CA15,CB15,CC15,CD15,CE15),"n/m") -> n/m | CI15: =IFERROR(AVERAGE(BB15,BG15,BL15,BQ15,BV15),"n/m") -> 0.268 | CJ15: =IFERROR(AVERAGE(AC15,AH15,AM15,AR15,AW15,BB15,BG15,BL15,BQ15,BV15),"n/m") -> 0.166 | CK15: =IFERROR(AVERAGE(C15,D15,E15,F15,G15,H15,I15,N15,S15,X15,AC15,AH15,AM15,AR15,AW15,BB15,BG15,BL15,BQ15,BV15),"n/m") -> 0.1661875
B16: Memo: switched transactions growth % ("processed transactions" to Q3-16; release text) | F16: 0.069 | H16: 0.183 | I16: 0.25 | J16: 0.12 | K16: 0.11 | L16: 0.16 | M16: 0.13 | N16: 0.13 | O16: 0.14 | P16: 0.12 | Q16: 0.1 | R16: 0.11 | S16: 0.12 | T16: 0.12 | U16: 0.13 | V16: 0.12 | W16: 0.12 | X16: 0.12 | Y16: 0.14 | Z16: 0.14 | AA16: 0.18 | AB16: 0.17 | AC16: 0.16 | AD16: 0.17 | AE16: 0.17 | AF16: 0.17 | AG16: 0.17 | AH16: 0.17 | AI16: 0.17 | AJ16: 0.17 | AK16: 0.16 | AL16: 0.17 | AM16: 0.17 | AN16: 0.17 | AO16: 0.18 | AP16: 0.2 | AQ16: 0.19 | AR16: 0.19 | AS16: 0.13 | AT16: -0.1 | AU16: 0.05 | AV16: 0.04 | AW16: 0.03 | AX16: 0.09 | AY16: 0.41 | AZ16: 0.25 | BA16: 0.27 | BB16: 0.25 | BC16: 0.22 | BD16: 0.12 | BE16: 0.09 | BF16: 0.08 | BG16: 0.12 | BH16: 0.12 | BI16: 0.17 | BJ16: 0.15 | BK16: 0.12 | BL16: 0.14 | BM16: 0.13 | BN16: 0.11 | BO16: 0.11 | BP16: 0.11 | BQ16: 0.11 | BR16: 0.09 | BS16: 0.1 | BT16: 0.1 | BU16: 0.1 | BV16: 0.1 | BW16: 0.09 | BX16: 0.09 | CH16: =IFERROR(AVERAGE(CA16,CB16,CC16,CD16,CE16),"n/m") -> n/m | CI16: =IFERROR(AVERAGE(BB16,BG16,BL16,BQ16,BV16),"n/m") -> 0.144 | CJ16: =IFERROR(AVERAGE(AC16,AH16,AM16,AR16,AW16,BB16,BG16,BL16,BQ16,BV16),"n/m") -> 0.144 | CK16: =IFERROR(AVERAGE(C16,D16,E16,F16,G16,H16,I16,N16,S16,X16,AC16,AH16,AM16,AR16,AW16,BB16,BG16,BL16,BQ16,BV16),"n/m") -> 0.1445 | CN16: Q3/26E – Q4/26E and FY26 point estimates (all cases)
B17: Memo: Mastercard and Maestro-branded cards issued (bn; period end, release text) | C17: 0.817 | D17: 0.916 | E17: 0.981 | F17: 0.966 | G17: 1.6 | H17: 1.8 | I17: 1.9 | J17: 1.9 | K17: 1.9 | L17: 2 | M17: 2 | N17: 2 | O17: 2 | P17: 2 | Q17: 2.1 | R17: 2.1 | S17: 2.1 | T17: 2.2 | U17: 2.2 | V17: 2.2 | W17: 2.3 | X17: 2.3 | Y17: 2.3 | Z17: 2.3 | AA17: 2.3 | AB17: 2.3 | AC17: 2.3 | AD17: 2.4 | AE17: 2.4 | AF17: 2.4 | AG17: 2.4 | AH17: 2.4 | AI17: 2.4 | AJ17: 2.4 | AK17: 2.5 | AL17: 2.5 | AM17: 2.5 | AN17: 2.5 | AO17: 2.6 | AP17: 2.6 | AQ17: 2.6 | AR17: 2.6 | AS17: 2.6 | AT17: 2.6 | AU17: 2.7 | AV17: 2.8 | AW17: 2.8 | AX17: 2.8 | AY17: 2.9 | AZ17: 2.9 | BA17: 3 | BB17: 3 | BC17: 2.9 | BD17: 3 | BE17: 3 | BF17: 3.1 | BG17: 3.1 | BH17: 3.2 | BI17: 3.2 | BJ17: 3.3 | BK17: 3.3 | BL17: 3.3 | BM17: 3.4 | BN17: 3.4 | BO17: 3.4 | BP17: 3.5 | BQ17: 3.5 | BR17: 3.5 | BS17: 3.6 | BT17: 3.6 | BU17: 3.7 | BV17: 3.7 | BW17: 3.7 | BX17: 3.7 | CF17: Mastercard-branded only to 2009 (0.8–1.0bn); including Maestro from 2010. | CH17: =IFERROR((CE17/BV17)^(1/5)-1,"n/m") -> -1 | CI17: =IFERROR((BV17/AW17)^(1/5)-1,"n/m") -> 0.057325578 | CJ17: =IFERROR((BV17/X17)^(1/10)-1,"n/m") -> 0.048690633 | CK17: =IFERROR((BV17/C17)^(1/19)-1,"n/m") -> 0.082742653 | CN17: FY26 FX effect on net revenue growth (pp; memo) | CP17: 0.01 | CR17: Outlook: ~1 ppt FX tailwind for the year (H1-26: +2.6 ppt) — UNVERIFIED.
CN18: Q3/Q4-26E depreciation & amortization ($m per quarter) | CP18: 325 | CR18: Q2-26 $309m, Q1-26 $299m; rising with capitalized software and the June-2026 property additions.
B19: Payment network (assessments for switching, cross-border, scheme fees, less payment network rebates & incentives) | CF19: PAYMENT NETWORK — modelling logic (2027E+: GDV × yield; 2026E H2: prior-year quarter × (1 + H1-26 y/y + calibration Δ)) | CN19: Q3/Q4-26E investment income ($m per quarter) | CP19: 85 | CR19: Q2-26 $88m, Q1-26 $81m.
B20: Payment network net revenue | AW20: 9897 | AX20: 2648 | AY20: 2875 | AZ20: 3234 | BA20: 3186 | BB20: 11943 | BC20: 3399 | BD20: 3609 | BE20: 3765 | BF20: 3585 | BG20: 14358 | BH20: 3650 | BI20: 4073 | BJ20: 4210 | BK20: 3891 | BL20: 15824 | BM20: 3920 | BN20: 4375 | BO20: 4629 | BP20: 4411 | BQ20: 17335 | BR20: 4432 | BS20: 4945 | BT20: 5179 | BU20: 4920 | BV20: 19476 | BW20: 4948 | BX20: 5451 | BY20: =BT20*(1+BY21) -> 5591.3051 | BZ20: =BU20*(1+BZ21) -> 5311.6859 | CA20: =SUM(BW20:BZ20) -> 21301.991 | CB20: =CB11*CB23/10 -> 23459.35 | CC20: =CC11*CC23/10 -> 25716.14 | CD20: =CD11*CD23/10 -> 28051.165 | CE20: =CE11*CE23/10 -> 30456.552 | CF20: 10-Q / 10-K revenue tables (current presentation from the FY2022 10-K; FY2020–21 and 2021–22 quarters from the next filings' comparatives, Q4 = FY − 9M). Before 2020 net revenue is not split this way (legacy categories in memo below). | CH20: =IFERROR((CE20/BV20)^(1/5)-1,"n/m") -> 0.093543831 | CI20: =IFERROR((BV20/AW20)^(1/5)-1,"n/m") -> 0.14498353 | CJ20: =IFERROR((BV20/X20)^(1/10)-1,"n/m") -> n/m | CK20: =IFERROR((BV20/C20)^(1/19)-1,"n/m") -> n/m | CN20: Q3/Q4-26E interest expense ($m per quarter) | CP20: 255 | CR20: Q2-26 $218m; + a full quarter of the $5.0bn June-2026 notes (~4.5%, ~$55m) less the Nov-2026 $750m maturity.
B21: y/y % | D21: =IF(AND(ISNUMBER(D20),ISNUMBER(C20)),IFERROR(D20/C20-1,""),"") | E21: =IF(AND(ISNUMBER(E20),ISNUMBER(D20)),IFERROR(E20/D20-1,""),"") | F21: =IF(AND(ISNUMBER(F20),ISNUMBER(E20)),IFERROR(F20/E20-1,""),"") | G21: =IF(AND(ISNUMBER(G20),ISNUMBER(F20)),IFERROR(G20/F20-1,""),"") | H21: =IF(AND(ISNUMBER(H20),ISNUMBER(G20)),IFERROR(H20/G20-1,""),"") | I21: =IF(AND(ISNUMBER(I20),ISNUMBER(H20)),IFERROR(I20/H20-1,""),"") | N21: =IF(AND(ISNUMBER(N20),ISNUMBER(I20)),IFERROR(N20/I20-1,""),"") | O21: =IF(AND(ISNUMBER(O20),ISNUMBER(J20)),IFERROR(O20/J20-1,""),"") | P21: =IF(AND(ISNUMBER(P20),ISNUMBER(K20)),IFERROR(P20/K20-1,""),"") | Q21: =IF(AND(ISNUMBER(Q20),ISNUMBER(L20)),IFERROR(Q20/L20-1,""),"") | R21: =IF(AND(ISNUMBER(R20),ISNUMBER(M20)),IFERROR(R20/M20-1,""),"") | S21: =IF(AND(ISNUMBER(S20),ISNUMBER(N20)),IFERROR(S20/N20-1,""),"") | T21: =IF(AND(ISNUMBER(T20),ISNUMBER(O20)),IFERROR(T20/O20-1,""),"") | U21: =IF(AND(ISNUMBER(U20),ISNUMBER(P20)),IFERROR(U20/P20-1,""),"") | ... BX21: =IF(AND(ISNUMBER(BX20),ISNUMBER(BS20)),IFERROR(BX20/BS20-1,""),"") -> 0.10232558 | BY21: =BY22+$CA$95 -> 0.079610947 | BZ21: =BZ22+$CA$95 -> 0.079610947 | CA21: =IF(AND(ISNUMBER(CA20),ISNUMBER(BV20)),IFERROR(CA20/BV20-1,""),"") -> 0.093755954 | CB21: =IF(AND(ISNUMBER(CB20),ISNUMBER(CA20)),IFERROR(CB20/CA20-1,""),"") -> 0.101275 | CC21: =IF(AND(ISNUMBER(CC20),ISNUMBER(CB20)),IFERROR(CC20/CB20-1,""),"") -> 0.0962 | CD21: =IF(AND(ISNUMBER(CD20),ISNUMBER(CC20)),IFERROR(CD20/CC20-1,""),"") -> 0.0908 | CE21: =IF(AND(ISNUMBER(CE20),ISNUMBER(CD20)),IFERROR(CE20/CD20-1,""),"") -> 0.08575 | CF21: Q3/Q4-26E: H1-26 y/y growth + net revenue calibration Δ (Group block). | CN21: Q3/Q4-26E other income (expense), net ($m per quarter) | CP21: 45 | CR21: Set so total other income (expense) ≈ −$125m in Q3 (85 − 255 + 45), per the UNVERIFIED call guidance; H1-26 $106m incl. government grants.
B22: Q3/Q4-26E growth before revenue calibration (H1-26 y/y) | BY22: =IFERROR(SUM(BW20:BX20)/SUM(BR20:BS20)-1,0) -> 0.10899008 | BZ22: =IFERROR(SUM(BW20:BX20)/SUM(BR20:BS20)-1,0) -> 0.10899008 | CN22: Q3/Q4-26E tax rate (GAAP & adjusted) | CP22: 0.205 | CR22: Non-GAAP tax rate guided 20–21% for Q3 and Q4 (UNVERIFIED); H1-26 19.7%.
B23: Payment network yield (net revenue ÷ GDV, bps) | C23: =IF(AND(ISNUMBER(C20),ISNUMBER(C11)),IFERROR(C20/C11*10,""),"") | D23: =IF(AND(ISNUMBER(D20),ISNUMBER(D11)),IFERROR(D20/D11*10,""),"") | E23: =IF(AND(ISNUMBER(E20),ISNUMBER(E11)),IFERROR(E20/E11*10,""),"") | F23: =IF(AND(ISNUMBER(F20),ISNUMBER(F11)),IFERROR(F20/F11*10,""),"") | G23: =IF(AND(ISNUMBER(G20),ISNUMBER(G11)),IFERROR(G20/G11*10,""),"") | H23: =IF(AND(ISNUMBER(H20),ISNUMBER(H11)),IFERROR(H20/H11*10,""),"") | I23: =IF(AND(ISNUMBER(I20),ISNUMBER(I11)),IFERROR(I20/I11*10,""),"") | J23: =IF(AND(ISNUMBER(J20),ISNUMBER(J11)),IFERROR(J20/J11*10,""),"") | ... CA23: =IF(AND(ISNUMBER(CA20),ISNUMBER(CA11)),IFERROR(CA20/CA11*10,""),"") -> 18.378703 | CB23: =CA23*(1+CB24) -> 18.654383 | CC23: =CB23*(1+CC24) -> 18.934199 | CD23: =CC23*(1+CD24) -> 19.123541 | CE23: =CD23*(1+CE24) -> 19.314776 | CF23: bps of GDV (USD m ÷ USD bn × 10). Mix of cross-border (higher yield), switching, pricing, less rebates & incentives on new and renewed deals. 2027E+: prior year × (1 + yield change lever). | CH23: =IFERROR(AVERAGE(CA23,CB23,CC23,CD23,CE23),"n/m") -> 18.88112 | CI23: =IFERROR(AVERAGE(BB23,BG23,BL23,BQ23,BV23),"n/m") -> 17.327608 | CJ23: =IFERROR(AVERAGE(AC23,AH23,AM23,AR23,AW23,BB23,BG23,BL23,BQ23,BV23),"n/m") -> 17.04264 | CK23: =IFERROR(AVERAGE(C23,D23,E23,F23,G23,H23,I23,N23,S23,X23,AC23,AH23,AM23,AR23,AW23,BB23,BG23,BL23,BQ23,BV23),"n/m") -> 17.04264 | CN23: H2-26E capital expenditures incl. capitalized software ($m) | CP23: 700 | CR23: H1-26 $813m (property $445m, software $368m); FY2025 $1,215m.
B24: Payment network yield change y/y % (scenario lever 2027E+) | D24: =IF(AND(ISNUMBER(D23),ISNUMBER(C23)),IFERROR(D23/C23-1,""),"") | E24: =IF(AND(ISNUMBER(E23),ISNUMBER(D23)),IFERROR(E23/D23-1,""),"") | F24: =IF(AND(ISNUMBER(F23),ISNUMBER(E23)),IFERROR(F23/E23-1,""),"") | G24: =IF(AND(ISNUMBER(G23),ISNUMBER(F23)),IFERROR(G23/F23-1,""),"") | H24: =IF(AND(ISNUMBER(H23),ISNUMBER(G23)),IFERROR(H23/G23-1,""),"") | I24: =IF(AND(ISNUMBER(I23),ISNUMBER(H23)),IFERROR(I23/H23-1,""),"") | N24: =IF(AND(ISNUMBER(N23),ISNUMBER(I23)),IFERROR(N23/I23-1,""),"") | O24: =IF(AND(ISNUMBER(O23),ISNUMBER(J23)),IFERROR(O23/J23-1,""),"") | P24: =IF(AND(ISNUMBER(P23),ISNUMBER(K23)),IFERROR(P23/K23-1,""),"") | Q24: =IF(AND(ISNUMBER(Q23),ISNUMBER(L23)),IFERROR(Q23/L23-1,""),"") | R24: =IF(AND(ISNUMBER(R23),ISNUMBER(M23)),IFERROR(R23/M23-1,""),"") | S24: =IF(AND(ISNUMBER(S23),ISNUMBER(N23)),IFERROR(S23/N23-1,""),"") | T24: =IF(AND(ISNUMBER(T23),ISNUMBER(O23)),IFERROR(T23/O23-1,""),"") | U24: =IF(AND(ISNUMBER(U23),ISNUMBER(P23)),IFERROR(U23/P23-1,""),"") | ... CA24: =IF(AND(ISNUMBER(CA23),ISNUMBER(BV23)),IFERROR(CA23/BV23-1,""),"") -> 0.0032982437 | CB24: =CHOOSE(MATCH($CF$2,{"Bull","Base","Bear"},0),$CO$33,$CP$33,$CQ$33) -> 0.015 | CC24: =CHOOSE(MATCH($CF$2,{"Bull","Base","Bear"},0),$CO$34,$CP$34,$CQ$34) -> 0.015 | CD24: =CHOOSE(MATCH($CF$2,{"Bull","Base","Bear"},0),$CO$35,$CP$35,$CQ$35) -> 0.01 | CE24: =CHOOSE(MATCH($CF$2,{"Bull","Base","Bear"},0),$CO$36,$CP$36,$CQ$36) -> 0.01
B25: Memo: payment network rebates & incentives growth % (release text, from 2020) | AT25: -0.1 | AU25: 0 | AV25: 0 | AW25: 0.03 | AX25: 0.06 | AY25: 0.53 | AZ25: 0.35 | BA25: 0.37 | BB25: 0.32 | BC25: 0.26 | BD25: 0.19 | BE25: 0.2 | BF25: 0.14 | BG25: 0.19 | BH25: 0.25 | BI25: 0.22 | BJ25: 0.22 | BK25: 0.19 | BL25: 0.22 | BM25: 0.2 | BN25: 0.14 | BO25: 0.17 | BP25: 0.14 | BQ25: 0.16 | BR25: 0.12 | BS25: 0.17 | BT25: 0.16 | BU25: 0.2 | BV25: 0.16 | BW25: 0.23 | BX25: 0.22 | CN25: Target net debt / adjusted EBITDA (x) — buyback plug 2027E+ | CO25: 0.7 | CP25: 0.5 | CQ25: 0.3 | CR25: Net debt (total debt − unrestricted cash − investments) $13.0bn at 30-Jun-2026 ≈ 0.6x LTM adjusted EBITDA (model); FY2023–25 0.3–0.4x. Mastercard has no stated leverage target; it returns excess capital through buybacks (FY2025 $11.7bn). Target = leverage up to which surplus cash is returned (assumption).
B26: Memo: payment network growth, currency-neutral % (release text) | BH26: 0.1 | BI26: 0.14 | BJ26: 0.1 | BK26: 0.07 | BL26: 0.1 | BM26: 0.08 | BN26: 0.09 | BO26: 0.11 | BP26: 0.15 | BQ26: 0.11 | BR26: 0.16 | BS26: 0.13 | BT26: 0.1 | BU26: 0.09 | BV26: 0.12 | BW26: 0.08 | BX26: 0.08
CN27: GDV (gross dollar volume growth, local currency) | CO27: 0.015 | CP27: Δ → | CQ27: -0.025 | CR27: H1-26 +7.7% local (FY2025 +8.6%, FY2024 +9.2%); purchase volume +9–10%. Secular cash-to-card and tokenized / e-commerce shift; Bear = consumer slowdown / U.S. debit share loss.
B28: Value-added services and solutions (cyber & intelligence, data & services, open banking, loyalty, processing) | CF28: VALUE-ADDED SERVICES — prior year × (1 + growth); includes acquisitions (Recorded Future Dec-2024) — the company reports VAS growth incl. M&A | CN28: 2027E | CO28: =CP28+$CO$27 -> 0.1 | CP28: 0.085 | CQ28: =CP28+$CQ$27 -> 0.06
B29: Value-added services and solutions net revenue | AW29: 5404 | AX29: 1507 | AY29: 1653 | AZ29: 1751 | BA29: 2030 | BB29: 6941 | BC29: 1768 | BD29: 1888 | BE29: 1991 | BF29: 2232 | BG29: 7879 | BH29: 2098 | BI29: 2196 | BJ29: 2323 | BK29: 2657 | BL29: 9274 | BM29: 2428 | BN29: 2586 | BO29: 2740 | BP29: 3078 | BQ29: 10832 | BR29: 2818 | BS29: 3188 | BT29: 3423 | BU29: 3886 | BV29: 13315 | BW29: 3450 | BX29: 3826 | BY29: =BT29*(1+BY30) -> 4046.2464 | BZ29: =BU29*(1+BZ30) -> 4593.5476 | CA29: =SUM(BW29:BZ29) -> 15915.794 | CB29: =CA29*(1+CB30) -> 18303.163 | CC29: =CB29*(1+CC30) -> 20865.606 | CD29: =CC29*(1+CD30) -> 23578.135 | CE29: =CD29*(1+CE30) -> 26407.511 | CF29: Same sources as payment network. Q3/Q4-26E: prior-year quarter × (1 + H1-26 y/y + calibration Δ); 2027E+: scenario lever. | CH29: =IFERROR((CE29/BV29)^(1/5)-1,"n/m") -> 0.14677247 | CI29: =IFERROR((BV29/AW29)^(1/5)-1,"n/m") -> 0.19763689 | CJ29: =IFERROR((BV29/X29)^(1/10)-1,"n/m") -> n/m | CK29: =IFERROR((BV29/C29)^(1/19)-1,"n/m") -> n/m | CN29: 2028E | CO29: =CP29+$CO$27 -> 0.095 | CP29: 0.08 | CQ29: =CP29+$CQ$27 -> 0.055
B30: y/y % | D30: =IF(AND(ISNUMBER(D29),ISNUMBER(C29)),IFERROR(D29/C29-1,""),"") | E30: =IF(AND(ISNUMBER(E29),ISNUMBER(D29)),IFERROR(E29/D29-1,""),"") | F30: =IF(AND(ISNUMBER(F29),ISNUMBER(E29)),IFERROR(F29/E29-1,""),"") | G30: =IF(AND(ISNUMBER(G29),ISNUMBER(F29)),IFERROR(G29/F29-1,""),"") | H30: =IF(AND(ISNUMBER(H29),ISNUMBER(G29)),IFERROR(H29/G29-1,""),"") | I30: =IF(AND(ISNUMBER(I29),ISNUMBER(H29)),IFERROR(I29/H29-1,""),"") | N30: =IF(AND(ISNUMBER(N29),ISNUMBER(I29)),IFERROR(N29/I29-1,""),"") | O30: =IF(AND(ISNUMBER(O29),ISNUMBER(J29)),IFERROR(O29/J29-1,""),"") | P30: =IF(AND(ISNUMBER(P29),ISNUMBER(K29)),IFERROR(P29/K29-1,""),"") | Q30: =IF(AND(ISNUMBER(Q29),ISNUMBER(L29)),IFERROR(Q29/L29-1,""),"") | R30: =IF(AND(ISNUMBER(R29),ISNUMBER(M29)),IFERROR(R29/M29-1,""),"") | S30: =IF(AND(ISNUMBER(S29),ISNUMBER(N29)),IFERROR(S29/N29-1,""),"") | T30: =IF(AND(ISNUMBER(T29),ISNUMBER(O29)),IFERROR(T29/O29-1,""),"") | U30: =IF(AND(ISNUMBER(U29),ISNUMBER(P29)),IFERROR(U29/P29-1,""),"") | ... BX30: =IF(AND(ISNUMBER(BX29),ISNUMBER(BS29)),IFERROR(BX29/BS29-1,""),"") -> 0.20012547 | BY30: =BY31+$CA$95 -> 0.18207608 | BZ30: =BZ31+$CA$95 -> 0.18207608 | CA30: =IF(AND(ISNUMBER(CA29),ISNUMBER(BV29)),IFERROR(CA29/BV29-1,""),"") -> 0.19532813 | CB30: =CHOOSE(MATCH($CF$2,{"Bull","Base","Bear"},0),$CO$38,$CP$38,$CQ$38) -> 0.15 | CC30: =CHOOSE(MATCH($CF$2,{"Bull","Base","Bear"},0),$CO$39,$CP$39,$CQ$39) -> 0.14 | CD30: =CHOOSE(MATCH($CF$2,{"Bull","Base","Bear"},0),$CO$40,$CP$40,$CQ$40) -> 0.13 | CE30: =CHOOSE(MATCH($CF$2,{"Bull","Base","Bear"},0),$CO$41,$CP$41,$CQ$41) -> 0.12 | CN30: 2029E | CO30: =CP30+$CO$27 -> 0.095 | CP30: 0.08 | CQ30: =CP30+$CQ$27 -> 0.055
B31: Q3/Q4-26E growth before revenue calibration (H1-26 y/y) | BY31: =IFERROR(SUM(BW29:BX29)/SUM(BR29:BS29)-1,0) -> 0.21145521 | BZ31: =IFERROR(SUM(BW29:BX29)/SUM(BR29:BS29)-1,0) -> 0.21145521 | CN31: 2030E | CO31: =CP31+$CO$27 -> 0.09 | CP31: 0.075 | CQ31: =CP31+$CQ$27 -> 0.05
B32: Memo: value-added services growth, currency-neutral % (release text) | BH32: 0.21 | BI32: 0.16 | BJ32: 0.14 | BK32: 0.17 | BL32: 0.17 | BM32: 0.15 | BN32: 0.19 | BO32: 0.19 | BP32: 0.17 | BQ32: 0.17 | BR32: 0.18 | BS32: 0.22 | BT32: 0.22 | BU32: 0.22 | BV32: 0.21 | BW32: 0.18 | BX32: 0.18 | CN32: YLD (payment network yield change y/y) | CO32: 0.01 | CP32: Δ → | CQ32: -0.015 | CR32: Yield 15.5 bps (2021) → 18.3 bps (2025): cross-border recovery (higher-yield), pricing and switching, partly offset by rising rebates & incentives (+22% in H1-26). Bear = rebate pressure / regulation (interchange / CCCA).
B33: Value-added services % of net revenue | C33: =IF(AND(ISNUMBER(C29),ISNUMBER(C77)),IFERROR(C29/C77,""),"") | D33: =IF(AND(ISNUMBER(D29),ISNUMBER(D77)),IFERROR(D29/D77,""),"") | E33: =IF(AND(ISNUMBER(E29),ISNUMBER(E77)),IFERROR(E29/E77,""),"") | F33: =IF(AND(ISNUMBER(F29),ISNUMBER(F77)),IFERROR(F29/F77,""),"") | G33: =IF(AND(ISNUMBER(G29),ISNUMBER(G77)),IFERROR(G29/G77,""),"") | H33: =IF(AND(ISNUMBER(H29),ISNUMBER(H77)),IFERROR(H29/H77,""),"") | I33: =IF(AND(ISNUMBER(I29),ISNUMBER(I77)),IFERROR(I29/I77,""),"") | J33: =IF(AND(ISNUMBER(J29),ISNUMBER(J77)),IFERROR(J29/J77,""),"") | ... CE33: =IF(AND(ISNUMBER(CE29),ISNUMBER(CE77)),IFERROR(CE29/CE77,""),"") -> 0.46006935 | CH33: =IFERROR(AVERAGE(CA33,CB33,CC33,CD33,CE33),"n/m") -> 0.44496864 | CI33: =IFERROR(AVERAGE(BB33,BG33,BL33,BQ33,BV33),"n/m") -> 0.37640215 | CJ33: =IFERROR(AVERAGE(AC33,AH33,AM33,AR33,AW33,BB33,BG33,BL33,BQ33,BV33),"n/m") -> 0.37253172 | CK33: =IFERROR(AVERAGE(C33,D33,E33,F33,G33,H33,I33,N33,S33,X33,AC33,AH33,AM33,AR33,AW33,BB33,BG33,BL33,BQ33,BV33),"n/m") -> 0.37253172 | CN33: 2027E | CO33: =CP33+$CO$32 -> 0.025 | CP33: 0.015 | CQ33: =CP33+$CQ$32 -> 0
CN34: 2028E | CO34: =CP34+$CO$32 -> 0.025 | CP34: 0.015 | CQ34: =CP34+$CQ$32 -> 0
B35: Net revenue not split into payment network / value-added services (FY2006–19, Q1-13 – Q4-20) | C35: =IF(ISNUMBER(C20),0,C123) -> 3326.074 | D35: =IF(ISNUMBER(D20),0,D123) -> 4067.599 | E35: =IF(ISNUMBER(E20),0,E123) -> 4991.6 | F35: =IF(ISNUMBER(F20),0,F123) -> 5098.684 | G35: =IF(ISNUMBER(G20),0,G123) -> 5539 | H35: =IF(ISNUMBER(H20),0,H123) -> 6714 | I35: =IF(ISNUMBER(I20),0,I123) -> 7391 | J35: =IF(ISNUMBER(J20),0,J123) -> 1906 | ... BX35: =IF(ISNUMBER(BX20),0,BX123) -> 0 | BY35: =0 -> 0 | BZ35: =0 -> 0 | CA35: =SUM(BW35:BZ35) -> 0 | CB35: =0 -> 0 | CC35: =0 -> 0 | CD35: =0 -> 0 | CE35: =0 -> 0 | CF35: History before the current presentation (first presented in the FY2022 10-K, with FY2020–21 comparatives): consolidated net revenue. The legacy categories are in the memo block below. | CN35: 2029E | CO35: =CP35+$CO$32 -> 0.02 | CP35: 0.01 | CQ35: =CP35+$CQ$32 -> -0.005
B36: Legacy revenue categories (as presented FY2006–Q3-22; FY2006 not published; 2007–08 recast in the FY2009 10-K) — memo: | CN36: 2030E | CO36: =CP36+$CO$32 -> 0.02 | CP36: 0.01 | CQ36: =CP36+$CQ$32 -> -0.005
B37: Domestic assessments | D37: 2099 | E37: 2386 | F37: 2382 | G37: 2642 | H37: 3246 | I37: 3586 | J37: 901 | K37: 940 | L37: 963 | M37: 1001 | N37: 3805 | O37: 938 | P37: 1008 | Q37: 1003 | R37: 1018 | S37: 3967 | T37: 963 | U37: 1028 | V37: 1028 | W37: 1067 | X37: 4086 | Y37: 1027 | Z37: 1110 | AA37: 1132 | AB37: 1142 | AC37: 4411 | AD37: 1189 | AE37: 1260 | AF37: 1302 | AG37: 1379 | AH37: 5130 | AI37: 1458 | AJ37: 1537 | AK37: 1564 | AL37: 1579 | AM37: 6138 | AN37: 1605 | AO37: 1680 | AP37: 1722 | AQ37: 1774 | AR37: 6781 | AS37: 1683 | AT37: 1474 | AU37: 1750 | AV37: 1749 | AW37: 6656 | AX37: 1798 | AY37: 2056 | AZ37: 2139 | BA37: 2165 | BB37: 8158 | BC37: 2134 | BD37: 2283 | BE37: 2252 | CH37: =IFERROR((CE37/BV37)^(1/5)-1,"n/m") -> n/m | CI37: =IFERROR((BV37/AW37)^(1/5)-1,"n/m") -> -1 | CJ37: =IFERROR((BV37/X37)^(1/10)-1,"n/m") -> -1 | CK37: =IFERROR((BV37/C37)^(1/19)-1,"n/m") -> n/m | CN37: VAS (value-added services and solutions growth) | CO37: 0.03 | CP37: Δ → | CQ37: -0.05 | CR37: FY2025 +23% (incl. Recorded Future from Dec-2024), H1-26 +21% (+18% currency-neutral). Security, digital & authentication, consumer engagement, data & insights, open banking.
B38: Cross-border volume fees | D38: 1180 | E38: 1547 | F38: 1509 | G38: 1927 | H38: 2094 | I38: 2343 | J38: 607 | K38: 677 | L38: 760 | M38: 749 | N38: 2793 | O38: 695 | P38: 750 | Q38: 835 | R38: 774 | S38: 3054 | T38: 724 | U38: 777 | V38: 880 | W38: 844 | X38: 3225 | Y38: 796 | Z38: 866 | AA38: 996 | AB38: 910 | AC38: 3568 | AD38: 916 | AE38: 984 | AF38: 1157 | AG38: 1117 | AH38: 4174 | AI38: 1157 | AJ38: 1198 | AK38: 1338 | AL38: 1261 | AM38: 4954 | AN38: 1263 | AO38: 1374 | AP38: 1517 | AQ38: 1452 | AR38: 5606 | AS38: 1217 | AT38: 637 | AU38: 791 | AV38: 867 | AW38: 3512 | AX38: 932 | AY38: 1076 | AZ38: 1276 | BA38: 1380 | BB38: 4664 | BC38: 1395 | BD38: 1615 | BE38: 1803 | CH38: =IFERROR((CE38/BV38)^(1/5)-1,"n/m") -> n/m | CI38: =IFERROR((BV38/AW38)^(1/5)-1,"n/m") -> -1 | CJ38: =IFERROR((BV38/X38)^(1/10)-1,"n/m") -> -1 | CK38: =IFERROR((BV38/C38)^(1/19)-1,"n/m") -> n/m | CN38: 2027E | CO38: =CP38+$CO$37 -> 0.18 | CP38: 0.15 | CQ38: =CP38+$CQ$37 -> 0.1
B39: Transaction processing fees | D39: 1490 | E39: 1777 | F39: 2042 | G39: 2198 | H39: 2595 | I39: 3017 | J39: 775 | K39: 818 | L39: 865 | M39: 901 | N39: 3359 | O39: 936 | P39: 995 | Q39: 1041 | R39: 1063 | S39: 4035 | T39: 1006 | U39: 1051 | V39: 1140 | W39: 1148 | X39: 4345 | Y39: 1165 | Z39: 1271 | AA39: 1357 | AB39: 1350 | AC39: 5143 | AD39: 1347 | AE39: 1496 | AF39: 1662 | AG39: 1683 | AH39: 6188 | AI39: 1707 | AJ39: 1830 | AK39: 1912 | AL39: 1942 | AM39: 7391 | AN39: 1922 | AO39: 2053 | AP39: 2231 | AQ39: 2263 | AR39: 8469 | AS39: 2200 | AT39: 1901 | AU39: 2251 | AV39: 2379 | AW39: 8731 | AX39: 2351 | AY39: 2612 | AZ39: 2849 | BA39: 2987 | BB39: 10799 | BC39: 2912 | BD39: 3061 | BE39: 3288 | CH39: =IFERROR((CE39/BV39)^(1/5)-1,"n/m") -> n/m | CI39: =IFERROR((BV39/AW39)^(1/5)-1,"n/m") -> -1 | CJ39: =IFERROR((BV39/X39)^(1/10)-1,"n/m") -> -1 | CK39: =IFERROR((BV39/C39)^(1/19)-1,"n/m") -> n/m | CN39: 2028E | CO39: =CP39+$CO$37 -> 0.17 | CP39: 0.14 | CQ39: =CP39+$CQ$37 -> 0.09
B40: Other revenues | D40: 622 | E40: 751 | F40: 784 | G40: 791 | H40: 1000 | I40: 1154 | J40: 280 | K40: 315 | L40: 336 | M40: 400 | N40: 1331 | O40: 341 | P40: 392 | Q40: 460 | R40: 495 | S40: 1688 | T40: 418 | U40: 474 | V40: 501 | W40: 598 | X40: 1991 | Y40: 497 | Z40: 590 | AA40: 620 | AB40: 724 | AC40: 2431 | AD40: 561 | AE40: 694 | AF40: 747 | AG40: 851 | AH40: 2853 | AI40: 748 | AJ40: 785 | AK40: 819 | AL40: 996 | AM40: 3348 | AN40: 842 | AO40: 962 | AP40: 1087 | AQ40: 1233 | AR40: 4124 | AS40: 1062 | AT40: 1081 | AU40: 1143 | AV40: 1431 | AW40: 4717 | AX40: 1347 | AY40: 1475 | AZ40: 1562 | BA40: 1840 | BB40: 6224 | BC40: 1584 | BD40: 1745 | BE40: 1824 | CH40: =IFERROR((CE40/BV40)^(1/5)-1,"n/m") -> n/m | CI40: =IFERROR((BV40/AW40)^(1/5)-1,"n/m") -> -1 | CJ40: =IFERROR((BV40/X40)^(1/10)-1,"n/m") -> -1 | CK40: =IFERROR((BV40/C40)^(1/19)-1,"n/m") -> n/m | CN40: 2029E | CO40: =CP40+$CO$37 -> 0.16 | CP40: 0.13 | CQ40: =CP40+$CQ$37 -> 0.08
B41: Rebates and incentives (contra-revenue) | D41: -1324 | E41: -1469 | F41: -1618 | G41: -2019 | H41: -2221 | I41: -2709 | J41: -657 | K41: -654 | L41: -706 | M41: -925 | N41: -2942 | O41: -733 | P41: -768 | Q41: -836 | R41: -934 | S41: -3271 | T41: -881 | U41: -940 | V41: -1019 | W41: -1140 | X41: -3980 | Y41: -1039 | Z41: -1143 | AA41: -1225 | AB41: -1370 | AC41: -4777 | AD41: -1279 | AE41: -1381 | AF41: -1470 | AG41: -1718 | AH41: -5848 | AI41: -1490 | AJ41: -1685 | AK41: -1735 | AL41: -1971 | AM41: -6881 | AN41: -1743 | AO41: -1956 | AP41: -2090 | AQ41: -2308 | AR41: -8097 | AS41: -2153 | AT41: -1758 | AU41: -2098 | AV41: -2306 | AW41: -8315 | AX41: -2273 | AY41: -2691 | AZ41: -2841 | BA41: -3156 | BB41: -10961 | BC41: -2858 | BD41: -3207 | BE41: -3411 | CH41: =IFERROR((CE41/BV41)^(1/5)-1,"n/m") -> n/m | CI41: =IFERROR((BV41/AW41)^(1/5)-1,"n/m") -> -1 | CJ41: =IFERROR((BV41/X41)^(1/10)-1,"n/m") -> -1 | CK41: =IFERROR((BV41/C41)^(1/19)-1,"n/m") -> n/m | CN41: 2030E | CO41: =CP41+$CO$37 -> 0.15 | CP41: 0.12 | CQ41: =CP41+$CQ$37 -> 0.07
B42: Check: legacy categories vs net revenue (should be 0) | C42: =IF(ISNUMBER(C37),IF(ABS(N(C37)+N(C38)+N(C39)+N(C40)+N(C41)-C123)<=1.1,0,ROUND(N(C37)+N(C38)+N(C39)+N(C40)+N(C41)-C123,0)),"") | D42: =IF(ISNUMBER(D37),IF(ABS(N(D37)+N(D38)+N(D39)+N(D40)+N(D41)-D123)<=1.1,0,ROUND(N(D37)+N(D38)+N(D39)+N(D40)+N(D41)-D123,0)),"") -> 0 | E42: =IF(ISNUMBER(E37),IF(ABS(N(E37)+N(E38)+N(E39)+N(E40)+N(E41)-E123)<=1.1,0,ROUND(N(E37)+N(E38)+N(E39)+N(E40)+N(E41)-E123,0)),"") -> 0 | F42: =IF(ISNUMBER(F37),IF(ABS(N(F37)+N(F38)+N(F39)+N(F40)+N(F41)-F123)<=1.1,0,ROUND(N(F37)+N(F38)+N(F39)+N(F40)+N(F41)-F123,0)),"") -> 0 | G42: =IF(ISNUMBER(G37),IF(ABS(N(G37)+N(G38)+N(G39)+N(G40)+N(G41)-G123)<=1.1,0,ROUND(N(G37)+N(G38)+N(G39)+N(G40)+N(G41)-G123,0)),"") -> 0 | H42: =IF(ISNUMBER(H37),IF(ABS(N(H37)+N(H38)+N(H39)+N(H40)+N(H41)-H123)<=1.1,0,ROUND(N(H37)+N(H38)+N(H39)+N(H40)+N(H41)-H123,0)),"") -> 0 | I42: =IF(ISNUMBER(I37),IF(ABS(N(I37)+N(I38)+N(I39)+N(I40)+N(I41)-I123)<=1.1,0,ROUND(N(I37)+N(I38)+N(I39)+N(I40)+N(I41)-I123,0)),"") -> 0 | J42: =IF(ISNUMBER(J37),IF(ABS(N(J37)+N(J38)+N(J39)+N(J40)+N(J41)-J123)<=1.1,0,ROUND(N(J37)+N(J38)+N(J39)+N(J40)+N(J41)-J123,0)),"") -> 0 | ... BX42: =IF(ISNUMBER(BX37),IF(ABS(N(BX37)+N(BX38)+N(BX39)+N(BX40)+N(BX41)-BX123)<=1.1,0,ROUND(N(BX37)+N(BX38)+N(BX39)+N(BX40)+N(BX41)-BX123,0)),"") | CN42: OM (adjusted operating margin) | CO42: 0.01 | CP42: Δ → | CQ42: -0.015 | CR42: Adjusted operating margin 57.0% (2022) → 59.2% (2025) → 61.0% (H1-26). Modest annual expansion; investment in VAS / talent offsets operating leverage.
B43: Cross-border volume fees y/y % | D43: =IF(AND(ISNUMBER(D38),ISNUMBER(C38)),IFERROR(D38/C38-1,""),"") | E43: =IF(AND(ISNUMBER(E38),ISNUMBER(D38)),IFERROR(E38/D38-1,""),"") -> 0.31101695 | F43: =IF(AND(ISNUMBER(F38),ISNUMBER(E38)),IFERROR(F38/E38-1,""),"") -> -0.024563672 | G43: =IF(AND(ISNUMBER(G38),ISNUMBER(F38)),IFERROR(G38/F38-1,""),"") -> 0.27700464 | H43: =IF(AND(ISNUMBER(H38),ISNUMBER(G38)),IFERROR(H38/G38-1,""),"") -> 0.086663207 | I43: =IF(AND(ISNUMBER(I38),ISNUMBER(H38)),IFERROR(I38/H38-1,""),"") -> 0.11891117 | N43: =IF(AND(ISNUMBER(N38),ISNUMBER(I38)),IFERROR(N38/I38-1,""),"") -> 0.19206146 | O43: =IF(AND(ISNUMBER(O38),ISNUMBER(J38)),IFERROR(O38/J38-1,""),"") -> 0.14497529 | P43: =IF(AND(ISNUMBER(P38),ISNUMBER(K38)),IFERROR(P38/K38-1,""),"") -> 0.10782866 | Q43: =IF(AND(ISNUMBER(Q38),ISNUMBER(L38)),IFERROR(Q38/L38-1,""),"") -> 0.098684211 | R43: =IF(AND(ISNUMBER(R38),ISNUMBER(M38)),IFERROR(R38/M38-1,""),"") -> 0.033377837 | S43: =IF(AND(ISNUMBER(S38),ISNUMBER(N38)),IFERROR(S38/N38-1,""),"") -> 0.093447905 | T43: =IF(AND(ISNUMBER(T38),ISNUMBER(O38)),IFERROR(T38/O38-1,""),"") -> 0.041726619 | U43: =IF(AND(ISNUMBER(U38),ISNUMBER(P38)),IFERROR(U38/P38-1,""),"") -> 0.036 | ... CA43: =IF(AND(ISNUMBER(CA38),ISNUMBER(BV38)),IFERROR(CA38/BV38-1,""),"") | CB43: =IF(AND(ISNUMBER(CB38),ISNUMBER(CA38)),IFERROR(CB38/CA38-1,""),"") | CC43: =IF(AND(ISNUMBER(CC38),ISNUMBER(CB38)),IFERROR(CC38/CB38-1,""),"") | CD43: =IF(AND(ISNUMBER(CD38),ISNUMBER(CC38)),IFERROR(CD38/CC38-1,""),"") | CE43: =IF(AND(ISNUMBER(CE38),ISNUMBER(CD38)),IFERROR(CE38/CD38-1,""),"") | CN43: 2027E | CO43: =CP43+$CO$42 -> 0.613 | CP43: 0.603 | CQ43: =CP43+$CQ$42 -> 0.588
B44: Rebates & incentives % of gross revenue | C44: =IF(ISNUMBER(C41),IFERROR(-C41/(C123-C41),""),"") | D44: =IF(ISNUMBER(D41),IFERROR(-D41/(D123-D41),""),"") -> 0.24556722 | E44: =IF(ISNUMBER(E41),IFERROR(-E41/(E123-E41),""),"") -> 0.22737826 | F44: =IF(ISNUMBER(F41),IFERROR(-F41/(F123-F41),""),"") -> 0.24089268 | G44: =IF(ISNUMBER(G41),IFERROR(-G41/(G123-G41),""),"") -> 0.26713416 | H44: =IF(ISNUMBER(H41),IFERROR(-H41/(H123-H41),""),"") -> 0.24857303 | I44: =IF(ISNUMBER(I41),IFERROR(-I41/(I123-I41),""),"") -> 0.26821782 | J44: =IF(ISNUMBER(J41),IFERROR(-J41/(J123-J41),""),"") -> 0.25634023 | ... CE44: =IF(ISNUMBER(CE41),IFERROR(-CE41/(CE123-CE41),""),"") | CN44: 2028E | CO44: =CP44+$CO$42 -> 0.618 | CP44: 0.608 | CQ44: =CP44+$CQ$42 -> 0.593
B45: Payment network key metrics (current presentation, from FY2022; assessments are gross of rebates) — memo: | CN45: 2029E | CO45: =CP45+$CO$42 -> 0.623 | CP45: 0.613 | CQ45: =CP45+$CQ$42 -> 0.598
B46: Domestic assessments | BG46: 8794 | BH46: 2254 | BI46: 2468 | BJ46: 2460 | BK46: 2384 | BL46: 9566 | BM46: 2470 | BN46: 2596 | BO46: 2641 | BP46: 2538 | BQ46: 10245 | BR46: 2658 | BS46: 2789 | BT46: 2809 | BU46: 2773 | BV46: 11029 | BW46: 2896 | BX46: 3154 | CN46: 2030E | CO46: =CP46+$CO$42 -> 0.628 | CP46: 0.618 | CQ46: =CP46+$CQ$42 -> 0.603
B47: Cross-border assessments | BG47: 6597 | BH47: 1849 | BI47: 2050 | BJ47: 2313 | BK47: 2198 | BL47: 8409 | BM47: 2238 | BN47: 2433 | BO47: 2804 | BP47: 2706 | BQ47: 10181 | BR47: 2595 | BS47: 2848 | BT47: 3313 | BU47: 3265 | BV47: 12021 | BW47: 3190 | BX47: 3460 | CN47: M&A_spend (acquisitions, $m) | CO47: 500 | CP47: Δ → | CQ47: -500 | CR47: Recorded Future $2.65bn (2024), none in 2025, BVNK $1.5bn (2026); Finicity, Ekata, Nets A2A (2020–21). Base $1.0bn p.a. (assumption).
B48: Transaction processing assessments | BG48: 10646 | BH48: 2752 | BI48: 2979 | BJ48: 3172 | BK48: 3165 | BL48: 12067 | BM48: 3086 | BN48: 3324 | BO48: 3587 | BP48: 3605 | BQ48: 13602 | BR48: 3527 | BS48: 3971 | BT48: 4191 | BU48: 4241 | BV48: 15930 | BW48: 4224 | BX48: 4508 | CN48: 2027E | CO48: =MAX(0,CP48+$CO$47) -> 1500 | CP48: 1000 | CQ48: =MAX(0,CP48+$CQ$47) -> 500
B49: Other network assessments | BG49: 766 | BH49: 212 | BI49: 270 | BJ49: 229 | BK49: 251 | BL49: 963 | BM49: 226 | BN49: 244 | BO49: 227 | BP49: 239 | BQ49: 936 | BR49: 231 | BS49: 260 | BT49: 255 | BU49: 272 | BV49: 1018 | BW49: 277 | BX49: 326 | CN49: 2028E | CO49: =MAX(0,CP49+$CO$47) -> 1500 | CP49: 1000 | CQ49: =MAX(0,CP49+$CQ$47) -> 500
B50: Payment network rebates & incentives (MD&A text) | BM50: -4100 | BN50: -4222 | BO50: -4630 | BP50: -4677 | BQ50: -17629 | BR50: -4579 | BS50: -4923 | BT50: -5389 | BU50: -5631 | BV50: -20522 | BW50: -5639 | BX50: -5997 | CN50: 2029E | CO50: =MAX(0,CP50+$CO$47) -> 1500 | CP50: 1000 | CQ50: =MAX(0,CP50+$CQ$47) -> 500
B51: Check: key metrics vs payment network net revenue (should be 0) | C51: =IF(AND(ISNUMBER(C46),ISNUMBER(C50)),IF(ABS(N(C46)+N(C47)+N(C48)+N(C49)+N(C50)-C20)<=1.1,0,ROUND(N(C46)+N(C47)+N(C48)+N(C49)+N(C50)-C20,0)),"") | D51: =IF(AND(ISNUMBER(D46),ISNUMBER(D50)),IF(ABS(N(D46)+N(D47)+N(D48)+N(D49)+N(D50)-D20)<=1.1,0,ROUND(N(D46)+N(D47)+N(D48)+N(D49)+N(D50)-D20,0)),"") | E51: =IF(AND(ISNUMBER(E46),ISNUMBER(E50)),IF(ABS(N(E46)+N(E47)+N(E48)+N(E49)+N(E50)-E20)<=1.1,0,ROUND(N(E46)+N(E47)+N(E48)+N(E49)+N(E50)-E20,0)),"") | F51: =IF(AND(ISNUMBER(F46),ISNUMBER(F50)),IF(ABS(N(F46)+N(F47)+N(F48)+N(F49)+N(F50)-F20)<=1.1,0,ROUND(N(F46)+N(F47)+N(F48)+N(F49)+N(F50)-F20,0)),"") | G51: =IF(AND(ISNUMBER(G46),ISNUMBER(G50)),IF(ABS(N(G46)+N(G47)+N(G48)+N(G49)+N(G50)-G20)<=1.1,0,ROUND(N(G46)+N(G47)+N(G48)+N(G49)+N(G50)-G20,0)),"") | H51: =IF(AND(ISNUMBER(H46),ISNUMBER(H50)),IF(ABS(N(H46)+N(H47)+N(H48)+N(H49)+N(H50)-H20)<=1.1,0,ROUND(N(H46)+N(H47)+N(H48)+N(H49)+N(H50)-H20,0)),"") | I51: =IF(AND(ISNUMBER(I46),ISNUMBER(I50)),IF(ABS(N(I46)+N(I47)+N(I48)+N(I49)+N(I50)-I20)<=1.1,0,ROUND(N(I46)+N(I47)+N(I48)+N(I49)+N(I50)-I20,0)),"") | J51: =IF(AND(ISNUMBER(J46),ISNUMBER(J50)),IF(ABS(N(J46)+N(J47)+N(J48)+N(J49)+N(J50)-J20)<=1.1,0,ROUND(N(J46)+N(J47)+N(J48)+N(J49)+N(J50)-J20,0)),"") | ... BX51: =IF(AND(ISNUMBER(BX46),ISNUMBER(BX50)),IF(ABS(N(BX46)+N(BX47)+N(BX48)+N(BX49)+N(BX50)-BX20)<=1.1,0,ROUND(N(BX46)+N(BX47)+N(BX48)+N(BX49)+N(BX50)-BX20,0)),"") -> 0 | CN51: 2030E | CO51: =MAX(0,CP51+$CO$47) -> 1500 | CP51: 1000 | CQ51: =MAX(0,CP51+$CQ$47) -> 500
B53: Pending acquisition — BVNK (stablecoin payments infrastructure): $1.5bn + up to $300m contingent; expected to close by end-Q3-2026 | CF53: BVNK — closing assumed 30-Sep-2026 (Q2-26 10-Q: "expected to complete before the end of the third quarter"); revenue and PPA not disclosed (flagged inputs)
B54: Deal switch (1 = include BVNK from 30-Sep-2026; 0 = exclude) | CA54: 1 | CB54: =CA54 -> 1 | CC54: =CB54 -> 1 | CD54: =CC54 -> 1 | CE54: =CD54 -> 1
B55: Cash consideration at closing (USDm) | CA55: =1500.0*CA54 -> 1500 | CB55: 0 | CC55: 0 | CD55: 0 | CE55: 0 | CF55: Pending at 30-Jun-2026: agreement March 2026, 100% for $1.5bn plus up to $300m contingent consideration; expected to complete before the end of Q3-2026 (Q2-26 10-Q Note 2). Closing not yet reported in an SEC filing; the model assumes 30-Sep-2026 (assumption). Revenue, profit and PPA not disclosed.
B56: BVNK net revenue (not disclosed — input 0; flag) | BY56: 0 | BZ56: 0 | CB56: 0 | CC56: 0 | CD56: 0 | CE56: 0 | CF56: Not disclosed by Mastercard; outlook excludes acquisitions. Enter an estimate here to add BVNK revenue on top of the organic build (adjusted opex below).
B57: BVNK adjusted operating expenses (not disclosed — input 0; flag) | BY57: 0 | BZ57: 0 | CB57: 0 | CC57: 0 | CD57: 0 | CE57: 0
B58: Acquired intangibles % of consideration (assumption) | CA58: 0.25 | CB58: =CA58 -> 0.25 | CC58: =CB58 -> 0.25 | CD58: =CC58 -> 0.25 | CE58: =CD58 -> 0.25 | CF58: Assumption: Recorded Future (Dec-2024) — $2.65bn with ~$1.7bn goodwill, i.e. ~35% to intangibles and other net assets; 25% assumed for an early-stage platform.
B59: Intangible amortization life (years, assumption) | CA59: 8 | CB59: =CA59 -> 8 | CC59: =CB59 -> 8 | CD59: =CC59 -> 8 | CE59: =CD59 -> 8
B60: Amortization of BVNK intangibles (in D&A) | CA60: =0 -> 0 | CB60: =IFERROR($CA$55*$CA$58/CB59,0) -> 46.875 | CC60: =IFERROR($CA$55*$CA$58/CC59,0) -> 46.875 | CD60: =IFERROR($CA$55*$CA$58/CD59,0) -> 46.875 | CE60: =IFERROR($CA$55*$CA$58/CE59,0) -> 46.875
B62: Future acquisitions (M&A lever — value-added services bolt-ons; deals closed from 2027E) | CF62: M&A LEVER — acquired revenue = spend ÷ EV/sales; mid-year convention
B63: Acquisition spend (USDm, scenario) | CA63: 0 | CB63: =MAX(0,CHOOSE(MATCH($CF$2,{"Bull","Base","Bear"},0),$CO$48,$CP$48,$CQ$48)) -> 1000 | CC63: =MAX(0,CHOOSE(MATCH($CF$2,{"Bull","Base","Bear"},0),$CO$49,$CP$49,$CQ$49)) -> 1000 | CD63: =MAX(0,CHOOSE(MATCH($CF$2,{"Bull","Base","Bear"},0),$CO$50,$CP$50,$CQ$50)) -> 1000 | CE63: =MAX(0,CHOOSE(MATCH($CF$2,{"Bull","Base","Bear"},0),$CO$51,$CP$51,$CQ$51)) -> 1000 | CF63: Scenario lever M&A_spend (Base $1.0bn p.a. of bolt-ons). Funded from cash / commercial paper (debt schedule).
B64: Purchase multiple — EV / sales (x) | CA64: 0 | CB64: 8 | CC64: 8 | CD64: 8 | CE64: 8 | CF64: Assumption: Recorded Future $2.65bn (~9x sales at announcement), Finicity $825m, Ekata $850m — high-growth software / data assets at high-single-digit sales multiples.
B65: Annualised revenue acquired in the year | CA65: 0 | CB65: =IFERROR(CB63/CB64,0) -> 125 | CC65: =IFERROR(CC63/CC64,0) -> 125 | CD65: =IFERROR(CD63/CD64,0) -> 125 | CE65: =IFERROR(CE63/CE64,0) -> 125
B66: Growth of acquired businesses after acquisition % | CA66: 0 | CB66: 0.12 | CC66: 0.12 | CD66: 0.12 | CE66: 0.12
B67: Run-rate revenue of businesses acquired (year end) | CA67: 0 | CB67: =CA67*(1+CB66)+CB65 -> 125 | CC67: =CB67*(1+CC66)+CC65 -> 265 | CD67: =CC67*(1+CD66)+CD65 -> 421.8 | CE67: =CD67*(1+CE66)+CE65 -> 597.416
B68: Revenue from future acquisitions | CA68: 0 | CB68: =CA67*(1+CB66)+0.5*CB65 -> 62.5 | CC68: =CB67*(1+CC66)+0.5*CC65 -> 202.5 | CD68: =CC67*(1+CD66)+0.5*CD65 -> 359.3 | CE68: =CD67*(1+CE66)+0.5*CE65 -> 534.916 | CF68: Mid-year convention.
B69: Adjusted operating margin of acquired businesses (after amortization) % | CA69: 0 | CB69: 0.15 | CC69: 0.15 | CD69: 0.15 | CE69: 0.15 | CF69: Assumption: acquired data / security businesses are margin-dilutive versus the ~60% group adjusted operating margin.
B70: Adjusted operating income from future acquisitions | CA70: 0 | CB70: =CB68*CB69 -> 9.375 | CC70: =CC68*CC69 -> 30.375 | CD70: =CD68*CD69 -> 53.895 | CE70: =CE68*CE69 -> 80.2374
B71: Acquired intangibles % of spend | CA71: 0 | CB71: 0.3 | CC71: 0.3 | CD71: 0.3 | CE71: 0.3
B72: Intangible amortization life (years) | CA72: 0 | CB72: 8 | CC72: 8 | CD72: 8 | CE72: 8
B73: Cumulative acquired intangibles (gross) | CA73: 0 | CB73: =CA73+CB63*CB71 -> 300 | CC73: =CB73+CC63*CC71 -> 600 | CD73: =CC73+CD63*CD71 -> 900 | CE73: =CD73+CE63*CE71 -> 1200
B74: Amortization of future-acquisition intangibles (inside adjusted operating income) | CA74: 0 | CB74: =IFERROR((CA73+0.5*CB63*CB71)/CB72,0) -> 18.75 | CC74: =IFERROR((CB73+0.5*CC63*CC71)/CC72,0) -> 56.25 | CD74: =IFERROR((CC73+0.5*CD63*CD71)/CD72,0) -> 93.75 | CE74: =IFERROR((CD73+0.5*CE63*CE71)/CE72,0) -> 131.25 | CF74: Mastercard does not adjust out amortization of acquired intangibles; the acquired-business margin above is after amortization.
B76: Group Total — net revenue & adjusted operating income → FY26 guidance calibration (guidance UNVERIFIED: earnings-call commentary) | CF76: GROUP TOTAL (CONSOLIDATED) — modelling logic
B77: Net revenue (build) | C77: =N(C20)+N(C29)+N(C35) -> 3326.074 | D77: =N(D20)+N(D29)+N(D35) -> 4067.599 | E77: =N(E20)+N(E29)+N(E35) -> 4991.6 | F77: =N(F20)+N(F29)+N(F35) -> 5098.684 | G77: =N(G20)+N(G29)+N(G35) -> 5539 | H77: =N(H20)+N(H29)+N(H35) -> 6714 | I77: =N(I20)+N(I29)+N(I35) -> 7391 | J77: =N(J20)+N(J29)+N(J35) -> 1906 | ... BX77: =N(BX20)+N(BX29)+N(BX35) -> 9277 | BY77: =BY20+BY29+N(BY35)+N(BY68)+N(BY56)*N($CA$54) -> 9637.5515 | BZ77: =BZ20+BZ29+N(BZ35)+N(BZ68)+N(BZ56)*N($CA$54) -> 9905.2335 | CA77: =CA20+CA29+N(CA35)+N(CA68)+N(CA56)*N($CA$54) -> 37217.785 | CB77: =CB20+CB29+N(CB35)+N(CB68)+N(CB56)*N($CA$54) -> 41825.013 | CC77: =CC20+CC29+N(CC35)+N(CC68)+N(CC56)*N($CA$54) -> 46784.246 | CD77: =CD20+CD29+N(CD35)+N(CD68)+N(CD56)*N($CA$54) -> 51988.6 | CE77: =CE20+CE29+N(CE35)+N(CE68)+N(CE56)*N($CA$54) -> 57398.979 | CF77: Payment network + value-added services (+ not split, history) (+ future acquisitions and BVNK from 2026E). | CH77: =IFERROR((CE77/BV77)^(1/5)-1,"n/m") -> 0.11848432 | CI77: =IFERROR((BV77/AW77)^(1/5)-1,"n/m") -> 0.16468094 | CJ77: =IFERROR((BV77/X77)^(1/10)-1,"n/m") -> 0.12991635 | CK77: =IFERROR((BV77/C77)^(1/19)-1,"n/m") -> 0.12799315
B78: Net revenue y/y % | D78: =IF(AND(ISNUMBER(D77),ISNUMBER(C77)),IFERROR(D77/C77-1,""),"") -> 0.22294303 | E78: =IF(AND(ISNUMBER(E77),ISNUMBER(D77)),IFERROR(E77/D77-1,""),"") -> 0.22716128 | F78: =IF(AND(ISNUMBER(F77),ISNUMBER(E77)),IFERROR(F77/E77-1,""),"") -> 0.021452841 | G78: =IF(AND(ISNUMBER(G77),ISNUMBER(F77)),IFERROR(G77/F77-1,""),"") -> 0.086358755 | H78: =IF(AND(ISNUMBER(H77),ISNUMBER(G77)),IFERROR(H77/G77-1,""),"") -> 0.21213215 | I78: =IF(AND(ISNUMBER(I77),ISNUMBER(H77)),IFERROR(I77/H77-1,""),"") -> 0.10083408 | N78: =IF(AND(ISNUMBER(N77),ISNUMBER(I77)),IFERROR(N77/I77-1,""),"") -> 0.1292112 | O78: =IF(AND(ISNUMBER(O77),ISNUMBER(J77)),IFERROR(O77/J77-1,""),"") -> 0.14218258 | P78: =IF(AND(ISNUMBER(P77),ISNUMBER(K77)),IFERROR(P77/K77-1,""),"") -> 0.13406489 | Q78: =IF(AND(ISNUMBER(Q77),ISNUMBER(L77)),IFERROR(Q77/L77-1,""),"") -> 0.12849414 | R78: =IF(AND(ISNUMBER(R77),ISNUMBER(M77)),IFERROR(R77/M77-1,""),"") -> 0.1364064 | S78: =IF(AND(ISNUMBER(S77),ISNUMBER(N77)),IFERROR(S77/N77-1,""),"") -> 0.13503475 | T78: =IF(AND(ISNUMBER(T77),ISNUMBER(O77)),IFERROR(T77/O77-1,""),"") -> 0.024345429 | U78: =IF(AND(ISNUMBER(U77),ISNUMBER(P77)),IFERROR(U77/P77-1,""),"") -> 0.0054690787 | ... CA78: =IF(AND(ISNUMBER(CA77),ISNUMBER(BV77)),IFERROR(CA77/BV77-1,""),"") -> 0.135 | CB78: =IF(AND(ISNUMBER(CB77),ISNUMBER(CA77)),IFERROR(CB77/CA77-1,""),"") -> 0.12379104 | CC78: =IF(AND(ISNUMBER(CC77),ISNUMBER(CB77)),IFERROR(CC77/CB77-1,""),"") -> 0.11857097 | CD78: =IF(AND(ISNUMBER(CD77),ISNUMBER(CC77)),IFERROR(CD77/CC77-1,""),"") -> 0.1112416 | CE78: =IF(AND(ISNUMBER(CE77),ISNUMBER(CD77)),IFERROR(CE77/CD77-1,""),"") -> 0.10406858
B79: Check: build vs consolidated net revenue (should be 0) | C79: =IF(ISNUMBER(C77),IF(ABS(C77-C123)<=1.1,0,ROUND(C77-C123,0)),"") -> 0 | D79: =IF(ISNUMBER(D77),IF(ABS(D77-D123)<=1.1,0,ROUND(D77-D123,0)),"") -> 0 | E79: =IF(ISNUMBER(E77),IF(ABS(E77-E123)<=1.1,0,ROUND(E77-E123,0)),"") -> 0 | F79: =IF(ISNUMBER(F77),IF(ABS(F77-F123)<=1.1,0,ROUND(F77-F123,0)),"") -> 0 | G79: =IF(ISNUMBER(G77),IF(ABS(G77-G123)<=1.1,0,ROUND(G77-G123,0)),"") -> 0 | H79: =IF(ISNUMBER(H77),IF(ABS(H77-H123)<=1.1,0,ROUND(H77-H123,0)),"") -> 0 | I79: =IF(ISNUMBER(I77),IF(ABS(I77-I123)<=1.1,0,ROUND(I77-I123,0)),"") -> 0 | J79: =IF(ISNUMBER(J77),IF(ABS(J77-J123)<=1.1,0,ROUND(J77-J123,0)),"") -> 0 | ... CE79: =IF(ISNUMBER(CE77),IF(ABS(CE77-CE123)<=1.1,0,ROUND(CE77-CE123,0)),"") -> 0
B80: Memo: company currency-neutral net revenue growth % (release; 2006–08: currency effect given only in points) | F80: 0.039 | G80: 0.095 | H80: 0.195 | I80: 0.13 | J80: 0.09 | K80: 0.15 | L80: 0.15 | M80: 0.11 | N80: 0.13 | O80: 0.14 | P80: 0.13 | Q80: 0.13 | R80: 0.17 | S80: 0.14 | T80: 0.08 | U80: 0.07 | V80: 0.08 | W80: 0.09 | X80: 0.08 | Y80: 0.14 | Z80: 0.14 | AA80: 0.14 | AB80: 0.1 | AC80: 0.13 | AD80: 0.12 | AE80: 0.14 | AF80: 0.17 | AG80: 0.18 | AH80: 0.15 | AI80: 0.27 | AJ80: 0.18 | AK80: 0.17 | AL80: 0.17 | AM80: 0.2 | AN80: 0.13 | AO80: 0.15 | AP80: 0.16 | AQ80: 0.17 | AR80: 0.16 | AS80: 0.05 | AT80: -0.17 | AU80: -0.14 | AV80: -0.07 | AW80: -0.08 | AX80: 0.02 | AY80: 0.31 | AZ80: 0.29 | BA80: 0.28 | BB80: 0.22 | BC80: 0.28 | BD80: 0.27 | BE80: 0.23 | BF80: 0.17 | BG80: 0.23 | BH80: 0.14 | BI80: 0.15 | BJ80: 0.11 | BK80: 0.11 | BL80: 0.13 | BM80: 0.11 | BN80: 0.13 | BO80: 0.14 | BP80: 0.16 | BQ80: 0.13 | BR80: 0.17 | BS80: 0.16 | BT80: 0.15 | BU80: 0.15 | BV80: 0.15 | BW80: 0.12 | BX80: 0.12 | CH80: =IFERROR(AVERAGE(CA80,CB80,CC80,CD80,CE80),"n/m") -> n/m | CI80: =IFERROR(AVERAGE(BB80,BG80,BL80,BQ80,BV80),"n/m") -> 0.172 | CJ80: =IFERROR(AVERAGE(AC80,AH80,AM80,AR80,AW80,BB80,BG80,BL80,BQ80,BV80),"n/m") -> 0.142 | CK80: =IFERROR(AVERAGE(C80,D80,E80,F80,G80,H80,I80,N80,S80,X80,AC80,AH80,AM80,AR80,AW80,BB80,BG80,BL80,BQ80,BV80),"n/m") -> 0.13111765
B81: Memo: currency effect on net revenue growth (reported − currency-neutral), pp | C81: =IF(AND(ISNUMBER(C80),ISNUMBER(C78)),C78-C80,"") | D81: =IF(AND(ISNUMBER(D80),ISNUMBER(D78)),D78-D80,"") | E81: =IF(AND(ISNUMBER(E80),ISNUMBER(E78)),E78-E80,"") | F81: =IF(AND(ISNUMBER(F80),ISNUMBER(F78)),F78-F80,"") -> -0.017547159 | G81: =IF(AND(ISNUMBER(G80),ISNUMBER(G78)),G78-G80,"") -> -0.0086412455 | H81: =IF(AND(ISNUMBER(H80),ISNUMBER(H78)),H78-H80,"") -> 0.017132154 | I81: =IF(AND(ISNUMBER(I80),ISNUMBER(I78)),I78-I80,"") -> -0.029165922 | J81: =IF(AND(ISNUMBER(J80),ISNUMBER(J78)),J78-J80,"") | ... BX81: =IF(AND(ISNUMBER(BX80),ISNUMBER(BX78)),BX78-BX80,"") -> 0.020661503
B82: Adjusted operating expenses (build) | C82: =IF(ISNUMBER(C165),C165,"") -> 2676.579 | D82: =IF(ISNUMBER(D165),D165,"") -> 2956.487 | E82: =IF(ISNUMBER(E165),E165,"") -> 3043.105 | F82: =IF(ISNUMBER(F165),F165,"") -> 2831.576 | G82: =IF(ISNUMBER(G165),G165,"") -> 2787 | H82: =IF(ISNUMBER(H165),H165,"") -> 3231 | I82: =IF(ISNUMBER(I165),I165,"") -> 3434 | J82: =IF(ISNUMBER(J165),J165,"") -> 799 | ... BX82: =IF(ISNUMBER(BX165),BX165,"") -> 3608 | BY82: =BT82*(1+BY83)+N(BY57)*N($CA$54) -> 3868.7459 | BZ82: =BU82*(1+BZ83)+N(BZ57)*N($CA$54) -> 4164.1041 | CA82: =SUM(BW82:BZ82) -> 14929.85 | CB82: =CB85*(1-CB87) -> 16632.843 | CC82: =CC85*(1-CC87) -> 18432.169 | CD82: =CD85*(1-CD87) -> 20285.944 | CE82: =CE85*(1-CE87) -> 22176.751 | CF82: Company adjusted operating expenses (GAAP less litigation provisions, restructuring and other special items). Q3/Q4-26E: prior-year quarter × (1 + H1-26 y/y + opex calibration Δ) (+ BVNK). 2027E+: adjusted net revenue × (1 − adjusted operating margin lever). | CH82: =IFERROR((CE82/BV82)^(1/5)-1,"n/m") -> 0.10617405 | CI82: =IFERROR((BV82/AW82)^(1/5)-1,"n/m") -> 0.1337867 | CJ82: =IFERROR((BV82/X82)^(1/10)-1,"n/m") -> 0.11648223 | CK82: =IFERROR((BV82/C82)^(1/19)-1,"n/m") -> 0.088428805
B83: Adjusted operating expenses y/y % | D83: =IF(AND(ISNUMBER(D82),ISNUMBER(C82)),IFERROR(D82/C82-1,""),"") -> 0.10457678 | E83: =IF(AND(ISNUMBER(E82),ISNUMBER(D82)),IFERROR(E82/D82-1,""),"") -> 0.029297609 | F83: =IF(AND(ISNUMBER(F82),ISNUMBER(E82)),IFERROR(F82/E82-1,""),"") -> -0.069510911 | G83: =IF(AND(ISNUMBER(G82),ISNUMBER(F82)),IFERROR(G82/F82-1,""),"") -> -0.01574247 | H83: =IF(AND(ISNUMBER(H82),ISNUMBER(G82)),IFERROR(H82/G82-1,""),"") -> 0.15931109 | I83: =IF(AND(ISNUMBER(I82),ISNUMBER(H82)),IFERROR(I82/H82-1,""),"") -> 0.062828846 | N83: =IF(AND(ISNUMBER(N82),ISNUMBER(I82)),IFERROR(N82/I82-1,""),"") -> 0.091438556 | O83: =IF(AND(ISNUMBER(O82),ISNUMBER(J82)),IFERROR(O82/J82-1,""),"") -> 0.11639549 | P83: =IF(AND(ISNUMBER(P82),ISNUMBER(K82)),IFERROR(P82/K82-1,""),"") -> 0.14516129 | Q83: =IF(AND(ISNUMBER(Q82),ISNUMBER(L82)),IFERROR(Q82/L82-1,""),"") -> 0.11649485 | R83: =IF(AND(ISNUMBER(R82),ISNUMBER(M82)),IFERROR(R82/M82-1,""),"") -> 0.25832583 | S83: =IF(AND(ISNUMBER(S82),ISNUMBER(N82)),IFERROR(S82/N82-1,""),"") -> 0.16515475 | T83: =IF(AND(ISNUMBER(T82),ISNUMBER(O82)),IFERROR(T82/O82-1,""),"") -> -0.014573991 | U83: =IF(AND(ISNUMBER(U82),ISNUMBER(P82)),IFERROR(U82/P82-1,""),"") -> 0.084507042 | ... BX83: =IF(AND(ISNUMBER(BX82),ISNUMBER(BS82)),IFERROR(BX82/BS82-1,""),"") -> 0.10674847 | BY83: =BY84+$CA$100 -> 0.11878134 | BZ83: =BZ84+$CA$100 -> 0.11878134 | CA83: =IF(AND(ISNUMBER(CA82),ISNUMBER(BV82)),IFERROR(CA82/BV82-1,""),"") -> 0.115 | CB83: =IF(AND(ISNUMBER(CB82),ISNUMBER(CA82)),IFERROR(CB82/CA82-1,""),"") -> 0.1140663 | CC83: =IF(AND(ISNUMBER(CC82),ISNUMBER(CB82)),IFERROR(CC82/CB82-1,""),"") -> 0.10817913 | CD83: =IF(AND(ISNUMBER(CD82),ISNUMBER(CC82)),IFERROR(CD82/CC82-1,""),"") -> 0.10057279 | CE83: =IF(AND(ISNUMBER(CE82),ISNUMBER(CD82)),IFERROR(CE82/CD82-1,""),"") -> 0.09320773
B84: Q3/Q4-26E adjusted opex growth before calibration (H1-26 y/y) | BY84: =IFERROR(SUM(BW82:BX82)/SUM(BR82:BS82)-1,0) -> 0.11062802 | BZ84: =IFERROR(SUM(BW82:BX82)/SUM(BR82:BS82)-1,0) -> 0.11062802
B85: Adjusted net revenue (net revenue + revenue special items) | C85: =IF(ISNUMBER(C123),C123+N(C117),"") -> 3326.074 | D85: =IF(ISNUMBER(D123),D123+N(D117),"") -> 4067.599 | E85: =IF(ISNUMBER(E123),E123+N(E117),"") -> 4991.6 | F85: =IF(ISNUMBER(F123),F123+N(F117),"") -> 5098.684 | G85: =IF(ISNUMBER(G123),G123+N(G117),"") -> 5539 | H85: =IF(ISNUMBER(H123),H123+N(H117),"") -> 6714 | I85: =IF(ISNUMBER(I123),I123+N(I117),"") -> 7391 | J85: =IF(ISNUMBER(J123),J123+N(J117),"") -> 1906 | ... BX85: =IF(ISNUMBER(BX123),BX123+N(BX117),"") -> 9277 | BY85: =BY77 -> 9637.5515 | BZ85: =BZ77 -> 9905.2335 | CA85: =SUM(BW85:BZ85) -> 37217.785 | CB85: =CB77 -> 41825.013 | CC85: =CC77 -> 46784.246 | CD85: =CD77 -> 51988.6 | CE85: =CE77 -> 57398.979
B86: Adjusted operating income (build) | C86: =IF(ISNUMBER(C82),C85-C82,"") -> 649.495 | D86: =IF(ISNUMBER(D82),D85-D82,"") -> 1111.112 | E86: =IF(ISNUMBER(E82),E85-E82,"") -> 1948.495 | F86: =IF(ISNUMBER(F82),F85-F82,"") -> 2267.108 | G86: =IF(ISNUMBER(G82),G85-G82,"") -> 2752 | H86: =IF(ISNUMBER(H82),H85-H82,"") -> 3483 | I86: =IF(ISNUMBER(I82),I85-I82,"") -> 3957 | J86: =IF(ISNUMBER(J82),J85-J82,"") -> 1107 | ... CE86: =IF(ISNUMBER(CE82),CE85-CE82,"") -> 35222.229 | CF86: Adjusted net revenue − adjusted operating expenses (company definition); drives the GAAP P&L below. | CH86: =IFERROR((CE86/BV86)^(1/5)-1,"n/m") -> 0.1266747 | CI86: =IFERROR((BV86/AW86)^(1/5)-1,"n/m") -> 0.18929798 | CJ86: =IFERROR((BV86/X86)^(1/10)-1,"n/m") -> 0.14033382 | CK86: =IFERROR((BV86/C86)^(1/19)-1,"n/m") -> 0.19576172
B87: Adjusted operating margin % | C87: =IF(AND(ISNUMBER(C86),ISNUMBER(C85)),IFERROR(C86/C85,""),"") -> 0.19527377 | D87: =IF(AND(ISNUMBER(D86),ISNUMBER(D85)),IFERROR(D86/D85,""),"") -> 0.27316164 | E87: =IF(AND(ISNUMBER(E86),ISNUMBER(E85)),IFERROR(E86/E85,""),"") -> 0.3903548 | F87: =IF(AND(ISNUMBER(F86),ISNUMBER(F85)),IFERROR(F86/F85,""),"") -> 0.44464572 | G87: =IF(AND(ISNUMBER(G86),ISNUMBER(G85)),IFERROR(G86/G85,""),"") -> 0.49684058 | H87: =IF(AND(ISNUMBER(H86),ISNUMBER(H85)),IFERROR(H86/H85,""),"") -> 0.51876676 | I87: =IF(AND(ISNUMBER(I86),ISNUMBER(I85)),IFERROR(I86/I85,""),"") -> 0.53538087 | J87: =IF(AND(ISNUMBER(J86),ISNUMBER(J85)),IFERROR(J86/J85,""),"") -> 0.58079748 | ... CA87: =IF(AND(ISNUMBER(CA86),ISNUMBER(CA85)),IFERROR(CA86/CA85,""),"") -> 0.59885173 | CB87: =CHOOSE(MATCH($CF$2,{"Bull","Base","Bear"},0),$CO$43,$CP$43,$CQ$43)+IFERROR(N(CB70)/CB85-N(CB68)/CB85*CHOOSE(MATCH($CF$2,{"Bull","Base","Bear"},0),$CO$43,$CP$43,$CQ$43),0) -> 0.60232307 | CC87: =CHOOSE(MATCH($CF$2,{"Bull","Base","Bear"},0),$CO$44,$CP$44,$CQ$44)+IFERROR(N(CC70)/CC85-N(CC68)/CC85*CHOOSE(MATCH($CF$2,{"Bull","Base","Bear"},0),$CO$44,$CP$44,$CQ$44),0) -> 0.6060176 | CD87: =CHOOSE(MATCH($CF$2,{"Bull","Base","Bear"},0),$CO$45,$CP$45,$CQ$45)+IFERROR(N(CD70)/CD85-N(CD68)/CD85*CHOOSE(MATCH($CF$2,{"Bull","Base","Bear"},0),$CO$45,$CP$45,$CQ$45),0) -> 0.60980015 | CE87: =CHOOSE(MATCH($CF$2,{"Bull","Base","Bear"},0),$CO$46,$CP$46,$CQ$46)+IFERROR(N(CE70)/CE85-N(CE68)/CE85*CHOOSE(MATCH($CF$2,{"Bull","Base","Bear"},0),$CO$46,$CP$46,$CQ$46),0) -> 0.61363859 | CF87: 2027E+: scenario margin lever on the organic business, blended with the future-acquisition margin. | CH87: =IFERROR(AVERAGE(CA87,CB87,CC87,CD87,CE87),"n/m") -> 0.60612623 | CI87: =IFERROR(AVERAGE(BB87,BG87,BL87,BQ87,BV87),"n/m") -> 0.57367659 | CJ87: =IFERROR(AVERAGE(AC87,AH87,AM87,AR87,AW87,BB87,BG87,BL87,BQ87,BV87),"n/m") -> 0.56261633 | CK87: =IFERROR(AVERAGE(C87,D87,E87,F87,G87,H87,I87,N87,S87,X87,AC87,AH87,AM87,AR87,AW87,BB87,BG87,BL87,BQ87,BV87),"n/m") -> 0.50551451
B88: Adjusted operating income y/y % | D88: =IF(AND(ISNUMBER(D86),ISNUMBER(C86)),IFERROR(D86/C86-1,""),"") -> 0.71073218 | E88: =IF(AND(ISNUMBER(E86),ISNUMBER(D86)),IFERROR(E86/D86-1,""),"") -> 0.7536441 | F88: =IF(AND(ISNUMBER(F86),ISNUMBER(E86)),IFERROR(F86/E86-1,""),"") -> 0.16351748 | G88: =IF(AND(ISNUMBER(G86),ISNUMBER(F86)),IFERROR(G86/F86-1,""),"") -> 0.2138813 | H88: =IF(AND(ISNUMBER(H86),ISNUMBER(G86)),IFERROR(H86/G86-1,""),"") -> 0.265625 | I88: =IF(AND(ISNUMBER(I86),ISNUMBER(H86)),IFERROR(I86/H86-1,""),"") -> 0.13608958 | N88: =IF(AND(ISNUMBER(N86),ISNUMBER(I86)),IFERROR(N86/I86-1,""),"") -> 0.16199141 | O88: =IF(AND(ISNUMBER(O86),ISNUMBER(J86)),IFERROR(O86/J86-1,""),"") -> 0.16079494 | P88: =IF(AND(ISNUMBER(P86),ISNUMBER(K86)),IFERROR(P86/K86-1,""),"") -> 0.1262215 | Q88: =IF(AND(ISNUMBER(Q86),ISNUMBER(L86)),IFERROR(Q86/L86-1,""),"") -> 0.13782051 | R88: =IF(AND(ISNUMBER(R86),ISNUMBER(M86)),IFERROR(R86/M86-1,""),"") -> 0.002955665 | S88: =IF(AND(ISNUMBER(S86),ISNUMBER(N86)),IFERROR(S86/N86-1,""),"") -> 0.11048282 | T88: =IF(AND(ISNUMBER(T86),ISNUMBER(O86)),IFERROR(T86/O86-1,""),"") -> 0.051361868 | U88: =IF(AND(ISNUMBER(U86),ISNUMBER(P86)),IFERROR(U86/P86-1,""),"") -> -0.051337672 | ... CA88: =IF(AND(ISNUMBER(CA86),ISNUMBER(BV86)),IFERROR(CA86/BV86-1,""),"") -> 0.14880341 | CB88: =IF(AND(ISNUMBER(CB86),ISNUMBER(CA86)),IFERROR(CB86/CA86-1,""),"") -> 0.13030527 | CC88: =IF(AND(ISNUMBER(CC86),ISNUMBER(CB86)),IFERROR(CC86/CB86-1,""),"") -> 0.12543206 | CD88: =IF(AND(ISNUMBER(CD86),ISNUMBER(CC86)),IFERROR(CD86/CC86-1,""),"") -> 0.11817757 | CE88: =IF(AND(ISNUMBER(CE86),ISNUMBER(CD86)),IFERROR(CE86/CD86-1,""),"") -> 0.11101823
B89: Incremental adjusted operating margin (Δ adj. OI / Δ adj. net revenue) | D89: =IFERROR((D86-C86)/(D85-C85),"") -> 0.62252385 | E89: =IFERROR((E86-D86)/(E85-D85),"") -> 0.90625768 | F89: =IFERROR((F86-E86)/(F85-E85),"") -> 2.9753558 | G89: =IFERROR((G86-F86)/(G85-F85),"") -> 1.1012364 | H89: =IFERROR((H86-G86)/(H85-G85),"") -> 0.62212766 | I89: =IFERROR((I86-H86)/(I85-H85),"") -> 0.70014771 | N89: =IFERROR((N86-I86)/(N85-I85),"") -> 0.67120419 | O89: =IFERROR((O86-J86)/(O85-J85),"") -> 0.65682657 | P89: =IFERROR((P86-K86)/(P85-K85),"") -> 0.55160142 | Q89: =IFERROR((Q86-L86)/(Q85-L85),"") -> 0.60350877 | R89: =IFERROR((R86-M86)/(R85-M85),"") -> 0.010344828 | S89: =IFERROR((S86-N86)/(S85-N85),"") -> 0.45075421 | T89: =IFERROR((T86-O86)/(T85-O85),"") -> 1.245283 | U89: =IFERROR((U86-P86)/(U85-P85),"") -> -5.4615385 | ... CA89: =IFERROR((CA86-BV86)/(CA85-BV85),"") -> 0.65215162 | CB89: =IFERROR((CB86-CA86)/(CB85-CA85),"") -> 0.63036501 | CC89: =IFERROR((CC86-CB86)/(CC85-CB85),"") -> 0.6371764 | CD89: =IFERROR((CD86-CC86)/(CD85-CC85),"") -> 0.64380312 | CE89: =IFERROR((CE86-CD86)/(CE85-CD85),"") -> 0.65052234
B90: Check: build vs adjusted operating income bridge (should be 0) | C90: =IF(AND(ISNUMBER(C86),ISNUMBER(C170)),IF(ABS(C86-C170)<=1.1,0,ROUND(C86-C170,0)),"") -> 0 | D90: =IF(AND(ISNUMBER(D86),ISNUMBER(D170)),IF(ABS(D86-D170)<=1.1,0,ROUND(D86-D170,0)),"") -> 0 | E90: =IF(AND(ISNUMBER(E86),ISNUMBER(E170)),IF(ABS(E86-E170)<=1.1,0,ROUND(E86-E170,0)),"") -> 0 | F90: =IF(AND(ISNUMBER(F86),ISNUMBER(F170)),IF(ABS(F86-F170)<=1.1,0,ROUND(F86-F170,0)),"") -> 0 | G90: =IF(AND(ISNUMBER(G86),ISNUMBER(G170)),IF(ABS(G86-G170)<=1.1,0,ROUND(G86-G170,0)),"") -> 0 | H90: =IF(AND(ISNUMBER(H86),ISNUMBER(H170)),IF(ABS(H86-H170)<=1.1,0,ROUND(H86-H170,0)),"") -> 0 | I90: =IF(AND(ISNUMBER(I86),ISNUMBER(I170)),IF(ABS(I86-I170)<=1.1,0,ROUND(I86-I170,0)),"") -> 0 | J90: =IF(AND(ISNUMBER(J86),ISNUMBER(J170)),IF(ABS(J86-J170)<=1.1,0,ROUND(J86-J170,0)),"") -> 0 | ... CE90: =IF(AND(ISNUMBER(CE86),ISNUMBER(CE170)),IF(ABS(CE86-CE170)<=1.1,0,ROUND(CE86-CE170,0)),"") -> 0
B91: FY26 calibration (Q3/Q4-26E; deltas in the 2026E column):
B92: Memo: FY26 net revenue end-point (FY2025 × (1 + guided reported growth); scenario) — UNVERIFIED guidance | CA92: =BV123*(1+CHOOSE(MATCH($CF$2,{"Bull","Base","Bear"},0),$CO$12,$CP$12,$CQ$12)) -> 37217.785 | CF92: FY26 net revenue growth at the high end of a low-double-digits rate (raised: higher within the range than prior expectations), currency-neutral, excluding acquisitions; FX ~1 ppt tailwind. Q3-26: high end of low double digits currency-neutral ex-acquisitions. UNVERIFIED — given on the Q2-26 earnings call (30-Jul-2026), not in any SEC filing (the 8-K Ex. 99.1 release has no outlook; slide decks are no longer furnished). Wording from third-party call transcripts (Yahoo Finance / Motley Fool / Globe and Mail / Investing.com) found by web search; investor.mastercard.com is not reachable from the build environment.
B93: Net revenue before calibration (Q3/Q4-26E helper; 2026E = Σ) | BY93: =BT20*(1+BY22)+BT29*(1+BY31) -> 9890.2708 | BZ93: =BU20*(1+BZ22)+BU29*(1+BZ31) -> 10163.946 | CA93: =(BY93+BZ93) -> 20054.217
B94: Net revenue sensitivity to +1.00 of growth (Q3/Q4-26E helper; 2026E = Σ) | BY94: =BT20+BT29 -> 8602 | BZ94: =BU20+BU29 -> 8806 | CA94: =(BY94+BZ94) -> 17408
B95: Calibration: Δ y/y growth applied to payment network and value-added services (Q3/Q4-26E) | CA95: =(CA92-SUM(BW77:BX77)-CA93)/CA94 -> -0.029379135 | CF95: Closed-form solve: the uniform growth shift (vs H1-26 y/y rates) so that FY26 organic net revenue = the guidance end-point for the active scenario.
B96: Check: FY26 organic net revenue vs guidance end-point (should be 0) | CA96: =ROUND(CA77-N((BY56+BZ56))*N(CA54)-CA92,0) -> 0
B97: Memo: FY26 adjusted operating expenses end-point (FY2025 × (1 + guided growth); scenario) — UNVERIFIED guidance | CA97: =BV82*(1+CHOOSE(MATCH($CF$2,{"Bull","Base","Bear"},0),$CO$13,$CP$13,$CQ$13)) -> 14929.85 | CF97: FY26 operating expense growth (adjusted, currency-neutral, ex-acquisitions) at a low-double-digits rate; FX 0.5–1 ppt headwind. Q3-26: low double digits. UNVERIFIED — given on the Q2-26 earnings call (30-Jul-2026), not in any SEC filing (the 8-K Ex. 99.1 release has no outlook; slide decks are no longer furnished). Wording from third-party call transcripts (Yahoo Finance / Motley Fool / Globe and Mail / Investing.com) found by web search; investor.mastercard.com is not reachable from the build environment.
B98: Adjusted opex before calibration (Q3/Q4-26E helper; 2026E = Σ) | BY98: =BT82*(1+BY84) -> 3840.5517 | BZ98: =BU82*(1+BZ84) -> 4133.7575 | CA98: =(BY98+BZ98) -> 7974.3092
B99: Adjusted opex sensitivity to +1.00 of growth (helper; 2026E = Σ) | BY99: =BT82 -> 3458 | BZ99: =BU82 -> 3722 | CA99: =(BY99+BZ99) -> 7180
B100: Calibration: Δ adjusted opex growth (Q3/Q4-26E) | CA100: =(CA97-SUM(BW82:BX82)-CA98)/CA99 -> 0.0081533177 | CF100: Solves the uniform shift in adjusted opex growth so that FY26 organic adjusted opex = the guidance end-point (scenario).
B101: Check: FY26 organic adjusted opex vs guidance end-point (should be 0) | CA101: =ROUND(CA82-N((BY57+BZ57))*N(CA54)-CA97,0) -> 0
B102: Memo: implied FY26 currency-neutral net revenue growth (end-point − FX point estimate) — guided "high end of low double digits" | CA102: =CHOOSE(MATCH($CF$2,{"Bull","Base","Bear"},0),$CO$12,$CP$12,$CQ$12)-$CP$17 -> 0.125
B103: Memo: FY26 adjusted EPS (model output; not guided) | CA103: =CA201 -> 19.88864
...

Sheet Bull-Base-Bear
B2: Mastercard Incorporated (MA) — Bull / Base / Bear Case P&L Summary | J2: Share price ($): | K2: =Model!$CA$392 -> 595
B3: Adjusted figures (company definitions: adjusted operating income, adjusted EPS; adjusted EBITDA is a model definition) · USD millions · Live panel linked to Model — toggle the scenario on the Model sheet (cell CF2). Bull and Bear panels are value snapshots generated from the Model with the switch set to each case. 2026E = Q1–Q2 actual + Q3/Q4 calibrated to the FY26 outlook (net revenue growth high end of low double digits; adjusted opex growth low double digits) — outlook UNVERIFIED (earnings call, not an SEC filing). | J3: As of: | K3: =TODAY() -> 2026-10-13 00:00:00
B5: Scenario: | C5: =Model!$CF$2 -> Base | N5: Scenario: | O5: Bull | P5: Snapshot (values) — Model run with switch = Bull | Z5: Scenario: | AA5: Bear | AB5: Snapshot (values) — Model run with switch = Bear
B7: (USDm, except EPS and shares) | C7: 2025A | D7: 2026E | E7: 2027E | F7: 2028E | G7: 2029E | H7: 2030E | I7: 25-'30 CAGR | J7: LT Hist Avg | K7: LT Hist Min | L7: LT Hist Max | N7: (USDm, except EPS and shares) | O7: 2025A | P7: 2026E | Q7: 2027E | R7: 2028E | S7: 2029E | T7: 2030E | U7: 25-'30 CAGR | V7: LT Hist Avg | W7: LT Hist Min | X7: LT Hist Max | Z7: (USDm, except EPS and shares) | AA7: 2025A | AB7: 2026E | AC7: 2027E | AD7: 2028E | AE7: 2029E | AF7: 2030E | AG7: 25-'30 CAGR | AH7: LT Hist Avg | AI7: LT Hist Min | AJ7: LT Hist Max
B9: Net revenue | C9: =Model!BV123 -> 32791 | D9: =Model!CA123 -> 37217.785 | E9: =Model!CB123 -> 41825.013 | F9: =Model!CC123 -> 46784.246 | G9: =Model!CD123 -> 51988.6 | H9: =Model!CE123 -> 57398.979 | I9: =IFERROR((H9/C9)^(1/5)-1,"n/m") -> 0.11848432 | N9: Net revenue | O9: 32791 | P9: 37381.74 | Q9: 43080.855 | R9: 49449.698 | S9: 56381.207 | T9: 63865.69 | U9: 0.14262202 | Z9: Net revenue | AA9: 32791 | AB9: 37053.83 | AC9: 39942.188 | AD9: 42817.397 | AE9: 45595.098 | AF9: 48233.391 | AG9: 0.08023595
B10: Net revenue y/y % | D10: =IFERROR(D9/C9-1,"") -> 0.135 | E10: =IFERROR(E9/D9-1,"") -> 0.12379104 | F10: =IFERROR(F9/E9-1,"") -> 0.11857097 | G10: =IFERROR(G9/F9-1,"") -> 0.1112416 | H10: =IFERROR(H9/G9-1,"") -> 0.10406858 | N10: Net revenue y/y % | P10: 0.14 | Q10: 0.15245719 | R10: 0.14783466 | S10: 0.14017292 | T10: 0.13274782 | Z10: Net revenue y/y % | AB10: 0.13 | AC10: 0.077950323 | AD10: 0.071984273 | AE10: 0.064873176 | AF10: 0.057863521
B11: Payment network y/y % | C11: =Model!BV212 -> 0.12350736 | D11: =Model!CA212 -> 0.093755954 | E11: =Model!CB212 -> 0.101275 | F11: =Model!CC212 -> 0.0962 | G11: =Model!CD212 -> 0.0908 | H11: =Model!CE212 -> 0.08575 | N11: Payment network y/y % | O11: 0.12350736 | P11: 0.098639715 | Q11: 0.1275 | R11: 0.122375 | S11: 0.1169 | T11: 0.1118 | Z11: Payment network y/y % | AA11: 0.12350736 | AB11: 0.088872193 | AC11: 0.06 | AD11: 0.055 | AE11: 0.049725 | AF11: 0.04475
B12: Adjusted EBITDA (model) | C12: =Model!BV185 -> 20544 | D12: =Model!CA185 -> 23545.935 | E12: =Model!CB185 -> 26679.846 | F12: =Model!CC185 -> 30045.866 | G12: =Model!CD185 -> 33610.893 | H12: =Model!CE185 -> 37351.919 | I12: =IFERROR((H12/C12)^(1/5)-1,"n/m") -> 0.12700432 | N12: Adjusted EBITDA (model) | O12: 20544 | P12: 23776.84 | Q12: 27904.907 | R12: 32230.298 | S12: 36975.03 | T12: 42139.302 | U12: 0.15451736 | Z12: Adjusted EBITDA (model) | AA12: 20544 | AB12: 23315.03 | AC12: 24886.603 | AD12: 26876.654 | AE12: 28829.369 | AF12: 30716.011 | AG12: 0.0837671
B13: Adjusted EBITDA margin % | C13: =IFERROR(C12/C9,"") -> 0.62651337 | D13: =IFERROR(D12/D9,"") -> 0.63265278 | E13: =IFERROR(E12/E9,"") -> 0.63789211 | F13: =IFERROR(F12/F9,"") -> 0.64222187 | G13: =IFERROR(G12/G9,"") -> 0.64650507 | H13: =IFERROR(H12/H9,"") -> 0.65074186 | J13: =IFERROR(AVERAGE(Model!C186,Model!D186,Model!E186,Model!F186,Model!G186,Model!H186,Model!I186,Model!N186,Model!S186,Model!X186,Model!AC186,Model!AH186,Model!AM186,Model!AR186,Model!AW186,Model!BB186,Model!BG186,Model!BL186,Model!BQ186,Model!BV186),"") -> 0.53713235 | K13: =IFERROR(MIN(Model!C186,Model!D186,Model!E186,Model!F186,Model!G186,Model!H186,Model!I186,Model!N186,Model!S186,Model!X186,Model!AC186,Model!AH186,Model!AM186,Model!AR186,Model!AW186,Model!BB186,Model!BG186,Model!BL186,Model!BQ186,Model!BV186),"") -> 0.2252737 | L13: =IFERROR(MAX(Model!C186,Model!D186,Model!E186,Model!F186,Model!G186,Model!H186,Model!I186,Model!N186,Model!S186,Model!X186,Model!AC186,Model!AH186,Model!AM186,Model!AR186,Model!AW186,Model!BB186,Model!BG186,Model!BL186,Model!BQ186,Model!BV186),"") -> 0.62651337 | N13: Adjusted EBITDA margin % | O13: 0.62651337 | P13: 0.63605493 | Q13: 0.64773336 | R13: 0.65177947 | S13: 0.65580415 | T13: 0.65981127 | V13: 0.53713235 | W13: 0.2252737 | X13: 0.62651337 | Z13: Adjusted EBITDA margin % | AA13: 0.62651337 | AB13: 0.62922052 | AC13: 0.6230656 | AD13: 0.62770407 | AE13: 0.63229097 | AF13: 0.63682049 | AH13: 0.53713235 | AI13: 0.2252737 | AJ13: 0.62651337
B15: Operating income (GAAP) | C15: =Model!BV130 -> 18897 | D15: =Model!CA130 -> 21803.935 | E15: =Model!CB130 -> 24742.17 | F15: =Model!CC130 -> 27902.076 | G15: =Model!CD130 -> 31252.656 | H15: =Model!CE130 -> 34772.229 | I15: =IFERROR((H15/C15)^(1/5)-1,"n/m") -> 0.1297125 | N15: Operating income (GAAP) | O15: 18897 | P15: 22034.84 | Q15: 25915.158 | R15: 29967.759 | S15: 34420.569 | T15: 39274.118 | U15: 0.15755788 | Z15: Operating income (GAAP) | AA15: 18897 | AB15: 21573.03 | AC15: 23022.319 | AD15: 24895.863 | AE15: 26735.385 | AF15: 28513.576 | AG15: 0.085754819
B16: Operating income y/y % | D16: =IFERROR(D15/C15-1,"") -> 0.1538305 | E16: =IFERROR(E15/D15-1,"") -> 0.13475712 | F16: =IFERROR(F15/E15-1,"") -> 0.12771336 | G16: =IFERROR(G15/F15-1,"") -> 0.12008352 | H16: =IFERROR(H15/G15-1,"") -> 0.11261676 | N16: Operating income y/y % | P16: 0.16604964 | Q16: 0.17609921 | R16: 0.15637955 | S16: 0.14858669 | T16: 0.14100725 | Z16: Operating income y/y % | AB16: 0.14161137 | AC16: 0.067180598 | AD16: 0.081379458 | AE16: 0.073888681 | AF16: 0.066510762
B17: Operating margin (GAAP) % | C17: =IFERROR(C15/C9,"") -> 0.57628618 | D17: =IFERROR(D15/D9,"") -> 0.5858472 | E17: =IFERROR(E15/E9,"") -> 0.59156396 | F17: =IFERROR(F15/F9,"") -> 0.59639898 | G17: =IFERROR(G15/G9,"") -> 0.6011444 | H17: =IFERROR(H15/H9,"") -> 0.60579873 | J17: =IFERROR(AVERAGE(Model!C225,Model!D225,Model!E225,Model!F225,Model!G225,Model!H225,Model!I225,Model!N225,Model!S225,Model!X225,Model!AC225,Model!AH225,Model!AM225,Model!AR225,Model!AW225,Model!BB225,Model!BG225,Model!BL225,Model!BQ225,Model!BV225),"") -> 0.45701046 | K17: =IFERROR(MIN(Model!C225,Model!D225,Model!E225,Model!F225,Model!G225,Model!H225,Model!I225,Model!N225,Model!S225,Model!X225,Model!AC225,Model!AH225,Model!AM225,Model!AR225,Model!AW225,Model!BB225,Model!BG225,Model!BL225,Model!BQ225,Model!BV225),"") -> -0.1070809 | L17: =IFERROR(MAX(Model!C225,Model!D225,Model!E225,Model!F225,Model!G225,Model!H225,Model!I225,Model!N225,Model!S225,Model!X225,Model!AC225,Model!AH225,Model!AM225,Model!AR225,Model!AW225,Model!BB225,Model!BG225,Model!BL225,Model!BQ225,Model!BV225),"") -> 0.57628618 | N17: Operating margin (GAAP) % | O17: 0.57628618 | P17: 0.58945464 | Q17: 0.60154697 | R17: 0.6060251 | S17: 0.61049719 | T17: 0.61494863 | V17: 0.45701046 | W17: -0.1070809 | X17: 0.57628618 | Z17: Operating margin (GAAP) % | AA17: 0.57628618 | AB17: 0.58220783 | AC17: 0.57639103 | AD17: 0.58144269 | AE17: 0.58636535 | AF17: 0.59115844 | AH17: 0.45701046 | AI17: -0.1070809 | AJ17: 0.57628618
B19: Adjusted Net Income | C19: =Model!BV198 -> 15415 | D19: =Model!CA198 -> 17507.648 | E19: =Model!CB198 -> 19686.972 | F19: =Model!CC198 -> 22159.558 | G19: =Model!CD198 -> 24756.254 | H19: =Model!CE198 -> 27480.942 | I19: =IFERROR((H19/C19)^(1/5)-1,"n/m") -> 0.12258082 | N19: Adjusted Net Income | O19: 15415 | P19: 17691.218 | Q19: 20605.266 | R19: 23616.242 | S19: 27039.932 | T19: 30771.294 | U19: 0.14826055 | Z19: Adjusted Net Income | AA19: 15415 | AB19: 17324.079 | AC19: 18338.367 | AD19: 19900.373 | AE19: 21319.953 | AF19: 22689.489 | AG19: 0.080379255
B21: FDSO (m) | C21: =Model!BV152 -> 906 | D21: =Model!CA152 -> 880.28382 | E21: =Model!CB152 -> 856.33569 | F21: =Model!CC152 -> 833.74802 | G21: =Model!CD152 -> 809.29611 | H21: =Model!CE152 -> 784.00495 | I21: =IFERROR((H21/C21)^(1/5)-1,"n/m") -> -0.028510477 | N21: FDSO (m) | O21: 906 | P21: 879.94769 | Q21: 850.47719 | R21: 821.80707 | S21: 793.6735 | T21: 763.59132 | U21: -0.033623063 | Z21: FDSO (m) | AA21: 906 | AB21: 880.70399 | AC21: 862.40428 | AD21: 846.10548 | AE21: 826.15156 | AF21: 806.73753 | AG21: -0.022940947
B23: Adjusted EPS — Diluted ($) | C23: =Model!BV201 -> 17.014349 | D23: =Model!CA201 -> 19.88864 | E23: =Model!CB201 -> 22.989783 | F23: =Model!CC201 -> 26.578244 | G23: =Model!CD201 -> 30.58986 | H23: =Model!CE201 -> 35.052001 | I23: =IFERROR((H23/C23)^(1/5)-1,"n/m") -> 0.1555254 | N23: Adjusted EPS — Diluted ($) | O23: 17.014349 | P23: 20.104852 | Q23: 24.227887 | R23: 28.736967 | S23: 34.06934 | T23: 40.298119 | U23: 0.18821187 | Z23: Adjusted EPS — Diluted ($) | AA23: 17.014349 | AB23: 19.670717 | AC23: 21.264234 | AD23: 23.519967 | AE23: 25.806346 | AF23: 28.124995 | AG23: 0.10574612
B24: EPS y/y % | D24: =IFERROR(D23/C23-1,"") -> 0.16893338 | E24: =IFERROR(E23/D23-1,"") -> 0.15592533 | F24: =IFERROR(F23/E23-1,"") -> 0.15608938 | G24: =IFERROR(G23/F23-1,"") -> 0.15093606 | H24: =IFERROR(H23/G23-1,"") -> 0.14586994 | N24: EPS y/y % | P24: 0.18164098 | Q24: 0.20507665 | R24: 0.18611113 | S24: 0.18555796 | T24: 0.18282653 | Z24: EPS y/y % | AB24: 0.15612517 | AC24: 0.081009624 | AD24: 0.10608106 | AE24: 0.097210117 | AF24: 0.089848022
B26: P / E (x) — assumed (adjusted EPS) | G26: 33 | H26: 33 | N26: P / E (x) — assumed (adjusted EPS) | S26: 37 | T26: 37 | Z26: P / E (x) — assumed (adjusted EPS) | AD26: 26 | AE26: 26 | AF26: 26
B27: Price Target ($) | G27: =G26*G23 -> 1009.4654 | H27: =H26*H23 -> 1156.716 | N27: Price Target ($) | S27: =S26*S23 -> 1260.5656 | T27: =T26*T23 -> 1491.0304 | Z27: Price Target ($) | AD27: =AD26*AD23 -> 611.51914 | AE27: =AE26*AE23 -> 670.96498 | AF27: =AF26*AF23 -> 731.24986
B28: Upside / (Downside) vs current | G28: =IFERROR(G27/$K$2-1,"") -> 0.69658045 | H28: =IFERROR(H27/$K$2-1,"") -> 0.94406055 | N28: Upside / (Downside) vs current | S28: =IFERROR(S27/$K$2-1,"") -> 1.1185976 | T28: =IFERROR(T27/$K$2-1,"") -> 1.5059334 | Z28: Upside / (Downside) vs current | AD28: =IFERROR(AD27/$K$2-1,"") -> 0.027763257 | AE28: =IFERROR(AE27/$K$2-1,"") -> 0.12767224 | AF28: =IFERROR(AF27/$K$2-1,"") -> 0.22899136
B29: IRR (to Dec-Y-1) | G29: =IFERROR((G27/$K$2)^(1/((DATE(2029-1,12,31)-$K$3)/365.25))-1,"") -> 0.26917373 | H29: =IFERROR((H27/$K$2)^(1/((DATE(2030-1,12,31)-$K$3)/365.25))-1,"") -> 0.22954873 | N29: IRR (to Dec-Y-1) | S29: =IFERROR((S27/$K$2)^(1/((DATE(2029-1,12,31)-$K$3)/365.25))-1,"") -> 0.40289029 | T29: =IFERROR((T27/$K$2)^(1/((DATE(2030-1,12,31)-$K$3)/365.25))-1,"") -> 0.330516 | Z29: IRR (to Dec-Y-1) | AD29: =IFERROR((AD27/$K$2)^(1/((DATE(2028-1,12,31)-$K$3)/365.25))-1,"") -> 0.022783402 | AE29: =IFERROR((AE27/$K$2)^(1/((DATE(2029-1,12,31)-$K$3)/365.25))-1,"") -> 0.055675927 | AF29: =IFERROR((AF27/$K$2)^(1/((DATE(2030-1,12,31)-$K$3)/365.25))-1,"") -> 0.066194283
B31: Free Cash Flow | C31: =Model!BV256 -> 16433 | D31: =Model!CA256 -> 16244.423 | E31: =Model!CB256 -> 19293.651 | F31: =Model!CC256 -> 21813.145 | G31: =Model!CD256 -> 24479.783 | H31: =Model!CE256 -> 27277.671 | I31: =IFERROR((H31/C31)^(1/5)-1,"n/m") -> 0.10666987 | N31: Free Cash Flow | O31: 16433 | P31: 16403.936 | Q31: 20089.048 | R31: 23138.294 | S31: 26627.369 | T31: 30427.326 | U31: 0.13112183 | Z31: Free Cash Flow | AA31: 16433 | AB31: 16084.91 | AC31: 18143.838 | AD31: 19759.568 | AE31: 21248.287 | AF31: 22686.529 | AG31: 0.066621274
B32: FCF % | C32: =IFERROR(C31/C9,"") -> 0.50114361 | D32: =IFERROR(D31/D9,"") -> 0.43646938 | E32: =IFERROR(E31/E9,"") -> 0.46129457 | F32: =IFERROR(F31/F9,"") -> 0.46624979 | G32: =IFERROR(G31/G9,"") -> 0.47086829 | H32: =IFERROR(H31/H9,"") -> 0.4752292 | J32: =IFERROR(AVERAGE(Model!C258,Model!D258,Model!E258,Model!F258,Model!G258,Model!H258,Model!I258,Model!N258,Model!S258,Model!X258,Model!AC258,Model!AH258,Model!AM258,Model!AR258,Model!AW258,Model!BB258,Model!BG258,Model!BL258,Model!BQ258,Model!BV258),"") -> 0.3584562 | K32: =IFERROR(MIN(Model!C258,Model!D258,Model!E258,Model!F258,Model!G258,Model!H258,Model!I258,Model!N258,Model!S258,Model!X258,Model!AC258,Model!AH258,Model!AM258,Model!AR258,Model!AW258,Model!BB258,Model!BG258,Model!BL258,Model!BQ258,Model!BV258),"") -> 0.04867277 | L32: =IFERROR(MAX(Model!C258,Model!D258,Model!E258,Model!F258,Model!G258,Model!H258,Model!I258,Model!N258,Model!S258,Model!X258,Model!AC258,Model!AH258,Model!AM258,Model!AR258,Model!AW258,Model!BB258,Model!BG258,Model!BL258,Model!BQ258,Model!BV258),"") -> 0.50114361 | N32: FCF % | O32: 0.50114361 | P32: 0.43882218 | Q32: 0.46631033 | R32: 0.46791577 | S32: 0.47227383 | T32: 0.47642679 | V32: 0.3584562 | W32: 0.04867277 | X32: 0.50114361 | Z32: FCF % | AA32: 0.50114361 | AB32: 0.43409576 | AC32: 0.45425248 | AD32: 0.46148456 | AE32: 0.46602131 | AF32: 0.47034905 | AH32: 0.3584562 | AI32: 0.04867277 | AJ32: 0.50114361
B33: FCF / share ($) | C33: =IFERROR(C31/C21,"") -> 18.137969 | D33: =IFERROR(D31/D21,"") -> 18.45362 | E33: =IFERROR(E31/E21,"") -> 22.530477 | F33: =IFERROR(F31/F21,"") -> 26.162754 | G33: =IFERROR(G31/G21,"") -> 30.24824 | H33: =IFERROR(H31/H21,"") -> 34.792728 | N33: FCF / share ($) | O33: 18.137969 | P33: 18.641945 | Q33: 23.620913 | R33: 28.155384 | S33: 33.549525 | T33: 39.847658 | Z33: FCF / share ($) | AA33: 18.137969 | AB33: 18.263697 | AC33: 21.038669 | AD33: 23.353551 | AE33: 25.719599 | AF33: 28.121326
B34: FCF Yield (on PT) | F34: =IFERROR(F33/F$27,"") | G34: =IFERROR(G33/G$27,"") -> 0.029964614 | H34: =IFERROR(H33/H$27,"") -> 0.030078885 | N34: FCF Yield (on PT) | R34: =IFERROR(R33/R$27,"") | S34: =IFERROR(S33/S$27,"") -> 0.026614661 | T34: =IFERROR(T33/T$27,"") -> 0.026724913 | Z34: FCF Yield (on PT) | AD34: =IFERROR(AD33/AD$27,"") -> 0.038189404 | AE34: =IFERROR(AE33/AE$27,"") -> 0.038332253 | AF34: =IFERROR(AF33/AF$27,"") -> 0.038456522
B35: Adjusted EBITDA (leverage basis) | C35: =Model!BV185 -> 20544 | D35: =Model!CA185 -> 23545.935 | E35: =Model!CB185 -> 26679.846 | F35: =Model!CC185 -> 30045.866 | G35: =Model!CD185 -> 33610.893 | H35: =Model!CE185 -> 37351.919 | I35: =IFERROR((H35/C35)^(1/5)-1,"n/m") -> 0.12700432 | N35: Adjusted EBITDA (leverage basis) | O35: 20544 | P35: 23776.84 | Q35: 27904.907 | R35: 32230.298 | S35: 36975.03 | T35: 42139.302 | U35: 0.15451736 | Z35: Adjusted EBITDA (leverage basis) | AA35: 20544 | AB35: 23315.03 | AC35: 24886.603 | AD35: 26876.654 | AE35: 28829.369 | AF35: 30716.011 | AG35: 0.0837671
B36: Adjusted EBITDA % of net revenue | C36: =IFERROR(C35/C9,"") -> 0.62651337 | D36: =IFERROR(D35/D9,"") -> 0.63265278 | E36: =IFERROR(E35/E9,"") -> 0.63789211 | F36: =IFERROR(F35/F9,"") -> 0.64222187 | G36: =IFERROR(G35/G9,"") -> 0.64650507 | H36: =IFERROR(H35/H9,"") -> 0.65074186 | J36: =IFERROR(AVERAGE(Model!C224,Model!D224,Model!E224,Model!F224,Model!G224,Model!H224,Model!I224,Model!N224,Model!S224,Model!X224,Model!AC224,Model!AH224,Model!AM224,Model!AR224,Model!AW224,Model!BB224,Model!BG224,Model!BL224,Model!BQ224,Model!BV224),"") -> 0.53713235 | K36: =IFERROR(MIN(Model!C224,Model!D224,Model!E224,Model!F224,Model!G224,Model!H224,Model!I224,Model!N224,Model!S224,Model!X224,Model!AC224,Model!AH224,Model!AM224,Model!AR224,Model!AW224,Model!BB224,Model!BG224,Model!BL224,Model!BQ224,Model!BV224),"") -> 0.2252737 | L36: =IFERROR(MAX(Model!C224,Model!D224,Model!E224,Model!F224,Model!G224,Model!H224,Model!I224,Model!N224,Model!S224,Model!X224,Model!AC224,Model!AH224,Model!AM224,Model!AR224,Model!AW224,Model!BB224,Model!BG224,Model!BL224,Model!BQ224,Model!BV224),"") -> 0.62651337 | N36: Adjusted EBITDA % of net revenue | O36: 0.62651337 | P36: 0.63605493 | Q36: 0.64773336 | R36: 0.65177947 | S36: 0.65580415 | T36: 0.65981127 | V36: 0.53713235 | W36: 0.2252737 | X36: 0.62651337 | Z36: Adjusted EBITDA % of net revenue | AA36: 0.62651337 | AB36: 0.62922052 | AC36: 0.6230656 | AD36: 0.62770407 | AE36: 0.63229097 | AF36: 0.63682049 | AH36: 0.53713235 | AI36: 0.2252737 | AJ36: 0.62651337
B38: Net Debt | C38: =Model!BV386 -> 8102 | D38: =Model!CA386 -> 12815.104 | E38: =Model!CB386 -> 13339.923 | F38: =Model!CC386 -> 15022.933 | G38: =Model!CD386 -> 16805.447 | H38: =Model!CE386 -> 18675.959 | N38: Net Debt | O38: 8102 | P38: 13454.421 | Q38: 19533.435 | R38: 22561.209 | S38: 25882.521 | T38: 29497.511 | Z38: Net Debt | AA38: 8102 | AB38: 11976.079 | AC38: 7465.981 | AD38: 8062.9963 | AE38: 8648.8106 | AF38: 9214.8034
B39: Net Debt / Adjusted EBITDA (x) | C39: =IFERROR(C38/C35,"") -> 0.39437305 | D39: =IFERROR(D38/D35,"") -> 0.54425973 | E39: =IFERROR(E38/E35,"") -> 0.5 | F39: =IFERROR(F38/F35,"") -> 0.5 | G39: =IFERROR(G38/G35,"") -> 0.5 | H39: =IFERROR(H38/H35,"") -> 0.5 | N39: Net Debt / Adjusted EBITDA (x) | O39: 0.39437305 | P39: 0.56586247 | Q39: 0.7 | R39: 0.7 | S39: 0.7 | T39: 0.7 | Z39: Net Debt / Adjusted EBITDA (x) | AA39: 0.39437305 | AB39: 0.51366348 | AC39: 0.3 | AD39: 0.3 | AE39: 0.3 | AF39: 0.3
B40: Share repurchases ($m; 2026E = H2) | D40: =Model!CA269 -> 7000 | E40: =Model!CB269 -> 15045.845 | F40: =Model!CC269 -> 18363.038 | G40: =Model!CD269 -> 20748.917 | H40: =Model!CE269 -> 23226.883 | N40: Share repurchases ($m; 2026E = H2) | P40: 7800 | Q40: 20900.906 | R40: 20580.632 | S40: 24005.475 | T40: 27725.119 | AB40: 6000 | AC40: 9354.2776 | AD40: 15675.399 | AE40: 16746.658 | AF40: 17717.041
B41: Implied avg buyback price ($) | D41: =Model!CA268 -> 595 | E41: =Model!CB268 -> 648.55 | F41: =Model!CC268 -> 706.9195 | G41: =Model!CD268 -> 770.54225 | H41: =Model!CE268 -> 839.89106 | N41: Implied avg buyback price ($) | P41: 595 | Q41: 648.55 | R41: 706.9195 | S41: 770.54225 | T41: 839.89106 | AB41: 595 | AC41: 648.55 | AD41: 706.9195 | AE41: 770.54225 | AF41: 839.89106
B42: Shares repurchased (m) | D42: =Model!CA270 -> 11.764706 | E42: =Model!CB270 -> 23.199207 | F42: =Model!CC270 -> 25.976137 | G42: =Model!CD270 -> 26.927683 | H42: =Model!CE270 -> 27.654638 | N42: Shares repurchased (m) | P42: 13.109244 | Q42: 32.227131 | R42: 29.113119 | S42: 31.154002 | T42: 33.010376 | AB42: 10.084034 | AC42: 14.423372 | AD42: 22.174235 | AE42: 21.733601 | AF42: 21.094452
B44: ROIC | C44: =Model!BV369 -> 0.98439879 | D44: =Model!CA369 -> 0.93967132 | E44: =Model!CB369 -> 0.96558791 | F44: =Model!CC369 -> 0.99856396 | G44: =Model!CD369 -> 1.0318003 | H44: =Model!CE369 -> 1.0644783 | J44: =IFERROR(AVERAGE(Model!C369,Model!D369,Model!E369,Model!F369,Model!G369,Model!H369,Model!I369,Model!N369,Model!S369,Model!X369,Model!AC369,Model!AH369,Model!AM369,Model!AR369,Model!AW369,Model!BB369,Model!BG369,Model!BL369,Model!BQ369,Model!BV369),"") -> 9.5416715 | K44: =IFERROR(MIN(Model!C369,Model!D369,Model!E369,Model!F369,Model!G369,Model!H369,Model!I369,Model!N369,Model!S369,Model!X369,Model!AC369,Model!AH369,Model!AM369,Model!AR369,Model!AW369,Model!BB369,Model!BG369,Model!BL369,Model!BQ369,Model!BV369),"") -> 0.64710137 | L44: =IFERROR(MAX(Model!C369,Model!D369,Model!E369,Model!F369,Model!G369,Model!H369,Model!I369,Model!N369,Model!S369,Model!X369,Model!AC369,Model!AH369,Model!AM369,Model!AR369,Model!AW369,Model!BB369,Model!BG369,Model!BL369,Model!BQ369,Model!BV369),"") -> 159.25146 | N44: ROIC | O44: 0.98439879 | P44: 0.94815247 | Q44: 0.97894579 | R44: 1.0108995 | S44: 1.04647 | T44: 1.0842456 | V44: 9.5416715 | W44: 0.64710137 | X44: 159.25146 | Z44: ROIC | AA44: 0.98439879 | AB44: 0.93116863 | AC44: 0.9337345 | AD44: 0.95776311 | AE44: 0.97912352 | AF44: 0.99737687 | AH44: 9.5416715 | AI44: 0.64710137 | AJ44: 159.25146
B45: RONTA | C45: =Model!BV380 -> 0.91607469 | D45: =Model!CA380 -> 1.0006567 | E45: =Model!CB380 -> 1.0467311 | F45: =Model!CC380 -> 1.161544 | G45: =Model!CD380 -> 1.2659362 | H45: =Model!CE380 -> 1.3339749 | J45: =IFERROR(AVERAGE(Model!C380,Model!D380,Model!E380,Model!F380,Model!G380,Model!H380,Model!I380,Model!N380,Model!S380,Model!X380,Model!AC380,Model!AH380,Model!AM380,Model!AR380,Model!AW380,Model!BB380,Model!BG380,Model!BL380,Model!BQ380,Model!BV380),"") -> 0.55050691 | K45: =IFERROR(MIN(Model!C380,Model!D380,Model!E380,Model!F380,Model!G380,Model!H380,Model!I380,Model!N380,Model!S380,Model!X380,Model!AC380,Model!AH380,Model!AM380,Model!AR380,Model!AW380,Model!BB380,Model!BG380,Model!BL380,Model!BQ380,Model!BV380),"") -> 0.15084563 | L45: =IFERROR(MAX(Model!C380,Model!D380,Model!E380,Model!F380,Model!G380,Model!H380,Model!I380,Model!N380,Model!S380,Model!X380,Model!AC380,Model!AH380,Model!AM380,Model!AR380,Model!AW380,Model!BB380,Model!BG380,Model!BL380,Model!BQ380,Model!BV380),"") -> 0.92159376 | N45: RONTA | O45: 0.91607469 | P45: 1.0471695 | Q45: 1.1570017 | R45: 1.2543015 | S45: 1.3482638 | T45: 1.4375118 | V45: 0.55050691 | W45: 0.15084563 | X45: 0.92159376 | Z45: RONTA | AA45: 0.91607469 | AB45: 0.94698143 | AC45: 0.75424459 | AD45: 0.78127174 | AE45: 0.80496466 | AF45: 0.82356469 | AH45: 0.55050691 | AI45: 0.15084563 | AJ45: 0.92159376
B47: Implied Market Cap (USDm) | F47: =F27*F21 -> 0 | G47: =G27*G21 -> 816956.4 | H47: =H27*H21 -> 906871.09 | N47: Implied Market Cap (USDm) | R47: =R27*R21 -> 0 | S47: =S27*S21 -> 1000477.5 | T47: =T27*T21 -> 1138537.9 | Z47: Implied Market Cap (USDm) | AD47: =AD27*AD21 -> 517409.69 | AE47: =AE27*AE21 -> 554318.77 | AF47: =AF27*AF21 -> 589926.71
B48: (+) Net Debt & NCI | F48: =F38+Model!CC306 -> 15017.933 | G48: =G38+Model!CD306 -> 16800.447 | H48: =H38+Model!CE306 -> 18670.959 | N48: (+) Net Debt & NCI | R48: =R38+Model!CC306 -> 22556.209 | S48: =S38+Model!CD306 -> 25877.521 | T48: =T38+Model!CE306 -> 29492.511 | Z48: (+) Net Debt & NCI | AD48: =AD38+Model!CC306 -> 8057.9963 | AE48: =AE38+Model!CD306 -> 8643.8106 | AF48: =AF38+Model!CE306 -> 9209.8034
B49: Implied Enterprise Value (USDm) | F49: =F47+F48 -> 15017.933 | G49: =G47+G48 -> 833756.84 | H49: =H47+H48 -> 925542.05 | N49: Implied Enterprise Value (USDm) | R49: =R47+R48 -> 22556.209 | S49: =S47+S48 -> 1026355 | T49: =T47+T48 -> 1168030.4 | Z49: Implied Enterprise Value (USDm) | AD49: =AD47+AD48 -> 525467.69 | AE49: =AE47+AE48 -> 562962.58 | AF49: =AF47+AF48 -> 599136.51
B50: Implied EV / Adjusted EBITDA (x) | F50: =IFERROR(F49/F35,"") -> 0.49983359 | G50: =IFERROR(G49/G35,"") -> 24.80615 | H50: =IFERROR(H49/H35,"") -> 24.778969 | N50: Implied EV / Adjusted EBITDA (x) | R50: =IFERROR(R49/R35,"") -> 0.69984487 | S50: =IFERROR(S49/S35,"") -> 27.758058 | T50: =IFERROR(T49/T35,"") -> 27.718313 | Z50: Implied EV / Adjusted EBITDA (x) | AD50: =IFERROR(AD49/AD35,"") -> 19.551083 | AE50: =IFERROR(AE49/AE35,"") -> 19.527399 | AF50: =IFERROR(AF49/AF35,"") -> 19.505674

Sheet DCF
B2: DCF VALUATION — MASTERCARD INCORPORATED (MA)
B4: 1. WACC BUILD
B5: Risk-free rate (US 10Y govt) | C5: 0.0425 | D5: Assumption (~US 10Y Treasury yield, Oct-2026; government rate sources are not reachable from the build environment); update to market
B6: Equity risk premium | C6: 0.05 | D6: Assumption: US implied ERP ~4.5–5.5%
B7: Levered beta | C7: 1 | D7: Assumption: payment networks (V, AXP, PYPL) ~0.9–1.2; volume-linked, recurring network revenue with consumer-spending cyclicality
B8: Cost of equity | C8: =C5+C7*C6 -> 0.0925
B9: Pre-tax cost of debt | C9: 0.047 | D9: June-2026 notes priced at 4.325%–5.0% (SOFR + 0.39% floaters); A+/Aa3-rated; commercial paper 3.84% (Q2-26 10-Q Note 9)
B10: Tax rate | C10: 0.205 | D10: Model 2027E+ effective tax rate (non-GAAP rate guided 20–21% for H2-26, UNVERIFIED)
B11: After-tax cost of debt | C11: =C9*(1-C10) -> 0.037365
B12: Target D/V | C12: 0.03 | D12: Net debt ~$13bn at 30-Jun-2026 vs ~$520bn market cap ($595 × ~879m diluted shares)
B13: WACC | C13: =C8*(1-C12)+C11*C12 -> 0.09084595
B15: Valuation date (live) | C15: =TODAY() -> 2026-10-13 00:00:00 | D15: Periods = (31-Dec of the year − today) / 365.25; cash flows assumed at year end. 2026E UFCF excluded (its cash flows sit in YE2026E net debt; valuation date Oct-2026).
B16: 2. UNLEVERED FREE CASH FLOW BUILD (USDm)
D17: 2026E | E17: 2027E | F17: 2028E | G17: 2029E | H17: 2030E | I17: 2031E | J17: 2032E | K17: 2033E | L17: 2034E | M17: 2035E | N17: Terminal | P17: CAGR 26–30E | Q17: CAGR 26–35E
B18: Adj. EBIT (adjusted operating income, full-cost) less litigation provisions & restructuring (cash) | D18: =Model!CA189-Model!CA191 -> 21803.935 | E18: =Model!CB189-Model!CB191 -> 24742.17 | F18: =Model!CC189-Model!CC191 -> 27902.076 | G18: =Model!CD189-Model!CD191 -> 31252.656 | H18: =Model!CE189-Model!CE191 -> 34772.229 | I18: =H18*(1+I$26) -> 37901.729 | J18: =I18*(1+J$26) -> 41028.622 | K18: =J18*(1+K$26) -> 44105.768 | L18: =K18*(1+L$26) -> 47082.908 | M18: =L18*(1+M$26) -> 49907.882 | P18: =(H18/D18)^(1/(COLUMNS(D18:H18)-1))-1 -> 0.12376218 | Q18: =(M18/D18)^(1/(COLUMNS(D18:M18)-1))-1 -> 0.096375602
B19: × (1 − tax rate) | D19: =1-$C$10 -> 0.795 | E19: =1-$C$10 -> 0.795 | F19: =1-$C$10 -> 0.795 | G19: =1-$C$10 -> 0.795 | H19: =1-$C$10 -> 0.795 | I19: =1-$C$10 -> 0.795 | J19: =1-$C$10 -> 0.795 | K19: =1-$C$10 -> 0.795 | ... M19: =1-$C$10 -> 0.795
B20: NOPAT | D20: =D18*D19 -> 17334.128 | E20: =E18*E19 -> 19670.026 | F20: =F18*F19 -> 22182.151 | G20: =G18*G19 -> 24845.861 | H20: =H18*H19 -> 27643.922 | I20: =I18*I19 -> 30131.875 | J20: =J18*J19 -> 32617.754 | K20: =K18*K19 -> 35064.086 | ... M20: =M18*M19 -> 39676.766
B21: plus D&A (depreciation + amortization of capitalized software and acquired intangibles) | D21: =Model!CA148 -> 1258 | E21: =Model!CB148 -> 1487.6755 | F21: =Model!CC148 -> 1693.7893 | G21: =Model!CD148 -> 1908.2374 | H21: =Model!CE148 -> 2129.6903 | I21: =H21*(1+I$26) -> 2321.3624 | J21: =I21*(1+J$26) -> 2512.8748 | K21: =J21*(1+K$26) -> 2701.3404 | L21: =K21*(1+L$26) -> 2883.6809 | M21: =L21*(1+M$26) -> 3056.7018
B22: − Capex (property, equipment & capitalized software) and acquisitions (M&A lever 2027E–30E) | D22: =Model!CA240 -> -1513 | E22: =Model!CB240+Model!CB241 -> -2673.0005 | F22: =Model!CC240+Model!CC241 -> -2871.3698 | G22: =Model!CD240+Model!CD241 -> -3079.544 | H22: =Model!CE240+Model!CE241 -> -3295.9592 | I22: =Model!CE240*(1+I$26) -> -2502.5955 | J22: =I22*(1+J$26) -> -2709.0596 | K22: =J22*(1+K$26) -> -2912.2391 | L22: =K22*(1+L$26) -> -3108.8152 | M22: =L22*(1+M$26) -> -3295.3442
B23: − Δ Working capital (CF statement) | D23: =Model!CA238 -> -1373.1145 | E23: =Model!CB238 -> -603.09552 | F23: =Model!CC238 -> -653.19981 | G23: =Model!CD238 -> -683.20969 | H23: =Model!CE238 -> -712.43391 | I23: =H23*(1+I$26) -> -776.55296 | J23: =I23*(1+J$26) -> -840.61858 | K23: =J23*(1+K$26) -> -903.66497 | L23: =K23*(1+L$26) -> -964.66236 | M23: =L23*(1+M$26) -> -1022.5421
B24: Unlevered FCF | D24: =D20+D21+D22+D23 -> 15706.014 | E24: =E20+E21+E22+E23 -> 17881.605 | F24: =F20+F21+F22+F23 -> 20351.37 | G24: =G20+G21+G22+G23 -> 22991.345 | H24: =H20+H21+H22+H23 -> 25765.219 | I24: =I20+I21+I22+I23 -> 29174.089 | J24: =J20+J21+J22+J23 -> 31580.951 | K24: =K20+K21+K22+K23 -> 33949.522 | ... M24: =M20+M21+M22+M23 -> 38415.582 | N24: =M24*(1+$C$27) -> 39952.205 | P24: =(H24/D24)^(1/(COLUMNS(D24:H24)-1))-1 -> 0.13172775 | Q24: =(M24/D24)^(1/(COLUMNS(D24:M24)-1))-1 -> 0.10448586
B25: Terminal Value (Gordon Growth) | N25: =N24/($C$13-$C$27) -> 785750
B26: Fade-period growth (2031E–35E; 9.0% → 6.0% linear) | I26: 0.09 | J26: =I26+($M$26-$I$26)/4 -> 0.0825 | K26: =J26+($M$26-$I$26)/4 -> 0.075 | L26: =K26+($M$26-$I$26)/4 -> 0.0675 | M26: 0.06
B27: Terminal growth rate | C27: 0.04
B29: Discount period (years) | D29: =(DATE(2026,12,31)-$C$15)/365.25 -> 0.21629021 | E29: =(DATE(2027,12,31)-$C$15)/365.25 -> 1.2156057 | F29: =(DATE(2028,12,31)-$C$15)/365.25 -> 2.2176591 | G29: =(DATE(2029,12,31)-$C$15)/365.25 -> 3.2169747 | H29: =(DATE(2030,12,31)-$C$15)/365.25 -> 4.2162902 | I29: =(DATE(2031,12,31)-$C$15)/365.25 -> 5.2156057 | J29: =(DATE(2032,12,31)-$C$15)/365.25 -> 6.2176591 | K29: =(DATE(2033,12,31)-$C$15)/365.25 -> 7.2169747 | L29: =(DATE(2034,12,31)-$C$15)/365.25 -> 8.2162902 | M29: =(DATE(2035,12,31)-$C$15)/365.25 -> 9.2156057 | N29: =M29 -> 9.2156057
B30: Discount factor | D30: =1/(1+$C$13)^D29 -> 0.98136856 | E30: =1/(1+$C$13)^E29 -> 0.89969346 | F30: =1/(1+$C$13)^F29 -> 0.8246195 | G30: =1/(1+$C$13)^G29 -> 0.75598995 | H30: =1/(1+$C$13)^H29 -> 0.69307215 | I30: =1/(1+$C$13)^I29 -> 0.63539072 | J30: =1/(1+$C$13)^J29 -> 0.58237122 | K30: =1/(1+$C$13)^K29 -> 0.53390296 | ... N30: =1/(1+$C$13)^N29 -> 0.44873214
B31: PV of UFCF (2026E excluded: in YE2026E net debt) | D31: =0*D24*D30 -> 0 | E31: =E24*E30 -> 16087.963 | F31: =F24*F30 -> 16782.137 | G31: =G24*G30 -> 17381.226 | H31: =H24*H30 -> 17857.156 | I31: =I24*I30 -> 18536.945 | J31: =J24*J30 -> 18391.837 | K31: =K24*K30 -> 18125.75 | L31: =L24*L30 -> 17738.884 | M31: =M24*M30 -> 17238.306 | N31: =N25*N30 -> 352591.28
D32: Mastercard's adjusted operating income expenses share-based compensation and the amortization of acquired intangibles and capitalized software (neither is adjusted out); D&A is added back in row 21 and capex (incl. capitalized software) deducted in row 22, so the basis is consistent full cost. Litigation provisions and restructuring (cash; excluded from adjusted results) are deducted inside row 18 ($450m a year assumed from 2027E). Row 22 includes acquisitions from the M&A lever in 2027E–30E; the fade period and terminal value assume no new acquisitions. The 2026E column (incl. the BVNK consideration) is excluded: those cash flows are in YE2026E net debt.
B33: IMPLIED ROIC — invested capital roll-forward (USDm)
B34: Opening invested capital | D34: =Model!BV366+Model!CA55 -> 17348 | E34: =D38 -> 18976.114 | F34: =E38 -> 20764.535 | G34: =F38 -> 22595.315 | H34: =G38 -> 24449.832 | I34: =H38 -> 26328.534 | J34: =I38 -> 27286.32 | K34: =J38 -> 28323.124 | L34: =K38 -> 29437.687 | M34: =L38 -> 30627.484
B35: plus Capex and acquisitions | D35: =-D22 -> 1513 | E35: =-E22 -> 2673.0005 | F35: =-F22 -> 2871.3698 | G35: =-G22 -> 3079.544 | H35: =-H22 -> 3295.9592 | I35: =-I22 -> 2502.5955 | J35: =-J22 -> 2709.0596 | K35: =-K22 -> 2912.2391 | ... M35: =-M22 -> 3295.3442
B36: less DD&A | D36: =-D21 -> -1258 | E36: =-E21 -> -1487.6755 | F36: =-F21 -> -1693.7893 | G36: =-G21 -> -1908.2374 | H36: =-H21 -> -2129.6903 | I36: =-I21 -> -2321.3624 | J36: =-J21 -> -2512.8748 | K36: =-K21 -> -2701.3404 | ... M36: =-M21 -> -3056.7018
B37: plus Δ Working capital investment | D37: =-D23 -> 1373.1145 | E37: =-E23 -> 603.09552 | F37: =-F23 -> 653.19981 | G37: =-G23 -> 683.20969 | H37: =-H23 -> 712.43391 | I37: =-I23 -> 776.55296 | J37: =-J23 -> 840.61858 | K37: =-K23 -> 903.66497 | ... M37: =-M23 -> 1022.5421
B38: Closing invested capital | D38: =SUM(D34:D37) -> 18976.114 | E38: =SUM(E34:E37) -> 20764.535 | F38: =SUM(F34:F37) -> 22595.315 | G38: =SUM(G34:G37) -> 24449.832 | H38: =SUM(H34:H37) -> 26328.534 | I38: =SUM(I34:I37) -> 27286.32 | J38: =SUM(J34:J37) -> 28323.124 | K38: =SUM(K34:K37) -> 29437.687 | ... M38: =SUM(M34:M37) -> 31888.669
B39: NOPAT (row 20) | D39: =D20 -> 17334.128 | E39: =E20 -> 19670.026 | F39: =F20 -> 22182.151 | G39: =G20 -> 24845.861 | H39: =H20 -> 27643.922 | I39: =I20 -> 30131.875 | J39: =J20 -> 32617.754 | K39: =K20 -> 35064.086 | ... M39: =M20 -> 39676.766
B40: Implied ROIC (NOPAT / avg. invested capital) | D40: =IFERROR(D39/AVERAGE(D34,D38),"") -> 0.95441437 | E40: =IFERROR(E39/AVERAGE(E34,E38),"") -> 0.98991968 | F40: =IFERROR(F39/AVERAGE(F34,F38),"") -> 1.0231655 | G40: =IFERROR(G39/AVERAGE(G34,G38),"") -> 1.0562561 | H40: =IFERROR(H39/AVERAGE(H34,H38),"") -> 1.0888071 | I40: =IFERROR(I39/AVERAGE(I34,I38),"") -> 1.1240122 | J40: =IFERROR(J39/AVERAGE(J34,J38),"") -> 1.1731013 | K40: =IFERROR(K39/AVERAGE(K34,K38),"") -> 1.2141133 | ... M40: =IFERROR(M39/AVERAGE(M34,M38),"") -> 1.2693285
B41: Reinvestment rate (net investment / NOPAT) | D41: =IFERROR(SUM(D35:D37)/D39,"") -> 0.093925373 | E41: =IFERROR(SUM(E35:E37)/E39,"") -> 0.090921112 | F41: =IFERROR(SUM(F35:F37)/F39,"") -> 0.08253394 | G41: =IFERROR(SUM(G35:G37)/G39,"") -> 0.074640853 | H41: =IFERROR(SUM(H35:H37)/H39,"") -> 0.067960791 | I41: =IFERROR(SUM(I35:I37)/I39,"") -> 0.031786474 | J41: =IFERROR(SUM(J35:J37)/J39,"") -> 0.031786474 | K41: =IFERROR(SUM(K35:K37)/K39,"") -> 0.031786474 | ... M41: =IFERROR(SUM(M35:M37)/M39,"") -> 0.031786474
B42: Implied terminal RONIC (g / reinvestment rate) | N42: =IFERROR($C$27/M41,"") -> 1.2583969
D43: Opening IC = Model 2025A book IC (equity + net debt) + the BVNK consideration (2026E), rolled forward with capex + M&A − D&A + ΔWC.
B44: 3. VALUATION SUMMARY
B45: Sum of PV (explicit + fade) | C45: =SUM(D31:M31) -> 158140.2
B46: PV of Terminal Value | C46: =N31 -> 352591.28
B47: Enterprise Value | C47: =C45+C46 -> 510731.48
B48: Less: Net debt + NCI (Model 2026E year end) | C48: =Model!CA386+Model!CA306+Model!CA304 -> 12810.104 | D48: Net debt = total debt − unrestricted cash − investments (restricted cash and customer security deposits excluded); NCI and redeemable NCI deducted (nil at YE2026E).
B49: Equity Value | C49: =C47-C48 -> 497921.38
B50: Diluted shares (m, Model 2026E year end) | C50: =Model!CA393 -> 866.93529
B51: Implied share price ($) | C51: =C49/C50 -> 574.34665
B52: Current share price ($) | C52: =Model!CA392 -> 595
B53: Implied upside / (downside) | C53: =C51/C52-1 -> -0.034711517
B54: Required discount to DCF value for target IRR | C54: =1-((1+C13)/(1+H54))^H55 -> 0.14651332 | D54: vs. current | E54: Target IRR | H54: 0.15
B55: Max entry price for target IRR ($) | C55: =C51*(1-C54) -> 490.19722 | D55: =C55/C52-1 -> -0.17613913 | E55: Years for discount to close | H55: 3
B58: 4. SENSITIVITY: IMPLIED PRICE ($) — WACC × Terminal Growth
D60: WACC →
B61: Terminal growth ↓ | D61: =F61-0.01 -> 0.08084595 | E61: =F61-0.005 -> 0.08584595 | F61: =$C$13 -> 0.09084595 | G61: =F61+0.005 -> 0.09584595 | H61: =F61+0.01 -> 0.10084595
B62: =B64-0.01 -> 0.03 | D62: {=IFERROR((SUMPRODUCT($D$24:$M$24/(1+D$61)^$D$29:$M$29)+($M$24*(1+$B62)/(D$61-$B62))/(1+D$61)^$M$29-$C$48)/$C$50,"")} -> 633.06476 | E62: {=IFERROR((SUMPRODUCT($D$24:$M$24/(1+E$61)^$D$29:$M$29)+($M$24*(1+$B62)/(E$61-$B62))/(1+E$61)^$M$29-$C$48)/$C$50,"")} -> 572.51822 | F62: {=IFERROR((SUMPRODUCT($D$24:$M$24/(1+F$61)^$D$29:$M$29)+($M$24*(1+$B62)/(F$61-$B62))/(1+F$61)^$M$29-$C$48)/$C$50,"")} -> 522.01528 | G62: {=IFERROR((SUMPRODUCT($D$24:$M$24/(1+G$61)^$D$29:$M$29)+($M$24*(1+$B62)/(G$61-$B62))/(1+G$61)^$M$29-$C$48)/$C$50,"")} -> 479.26497 | H62: {=IFERROR((SUMPRODUCT($D$24:$M$24/(1+H$61)^$D$29:$M$29)+($M$24*(1+$B62)/(H$61-$B62))/(1+H$61)^$M$29-$C$48)/$C$50,"")} -> 442.6232
B63: =B64-0.005 -> 0.035 | D63: {=IFERROR((SUMPRODUCT($D$24:$M$24/(1+D$61)^$D$29:$M$29)+($M$24*(1+$B63)/(D$61-$B63))/(1+D$61)^$M$29-$C$48)/$C$50,"")} -> 683.24622 | E63: {=IFERROR((SUMPRODUCT($D$24:$M$24/(1+E$61)^$D$29:$M$29)+($M$24*(1+$B63)/(E$61-$B63))/(1+E$61)^$M$29-$C$48)/$C$50,"")} -> 612.18118 | F63: {=IFERROR((SUMPRODUCT($D$24:$M$24/(1+F$61)^$D$29:$M$29)+($M$24*(1+$B63)/(F$61-$B63))/(1+F$61)^$M$29-$C$48)/$C$50,"")} -> 553.93198 | G63: {=IFERROR((SUMPRODUCT($D$24:$M$24/(1+G$61)^$D$29:$M$29)+($M$24*(1+$B63)/(G$61-$B63))/(1+G$61)^$M$29-$C$48)/$C$50,"")} -> 505.33634 | H63: {=IFERROR((SUMPRODUCT($D$24:$M$24/(1+H$61)^$D$29:$M$29)+($M$24*(1+$B63)/(H$61-$B63))/(1+H$61)^$M$29-$C$48)/$C$50,"")} -> 464.19258
B64: =$C$27 -> 0.04 | D64: {=IFERROR((SUMPRODUCT($D$24:$M$24/(1+D$61)^$D$29:$M$29)+($M$24*(1+$B64)/(D$61-$B64))/(1+D$61)^$M$29-$C$48)/$C$50,"")} -> 745.71323 | E64: {=IFERROR((SUMPRODUCT($D$24:$M$24/(1+E$61)^$D$29:$M$29)+($M$24*(1+$B64)/(E$61-$B64))/(1+E$61)^$M$29-$C$48)/$C$50,"")} -> 660.49549 | F64: {=IFERROR((SUMPRODUCT($D$24:$M$24/(1+F$61)^$D$29:$M$29)+($M$24*(1+$B64)/(F$61-$B64))/(1+F$61)^$M$29-$C$48)/$C$50,"")} -> 592.12582 | G64: {=IFERROR((SUMPRODUCT($D$24:$M$24/(1+G$61)^$D$29:$M$29)+($M$24*(1+$B64)/(G$61-$B64))/(1+G$61)^$M$29-$C$48)/$C$50,"")} -> 536.07614 | H64: {=IFERROR((SUMPRODUCT($D$24:$M$24/(1+H$61)^$D$29:$M$29)+($M$24*(1+$B64)/(H$61-$B64))/(1+H$61)^$M$29-$C$48)/$C$50,"")} -> 489.30688
B65: =B64+0.005 -> 0.045 | D65: {=IFERROR((SUMPRODUCT($D$24:$M$24/(1+D$61)^$D$29:$M$29)+($M$24*(1+$B65)/(D$61-$B65))/(1+D$61)^$M$29-$C$48)/$C$50,"")} -> 825.60675 | E65: {=IFERROR((SUMPRODUCT($D$24:$M$24/(1+E$61)^$D$29:$M$29)+($M$24*(1+$B65)/(E$61-$B65))/(1+E$61)^$M$29-$C$48)/$C$50,"")} -> 720.63823 | F65: {=IFERROR((SUMPRODUCT($D$24:$M$24/(1+F$61)^$D$29:$M$29)+($M$24*(1+$B65)/(F$61-$B65))/(1+F$61)^$M$29-$C$48)/$C$50,"")} -> 638.65056 | G65: {=IFERROR((SUMPRODUCT($D$24:$M$24/(1+G$61)^$D$29:$M$29)+($M$24*(1+$B65)/(G$61-$B65))/(1+G$61)^$M$29-$C$48)/$C$50,"")} -> 572.86162 | H65: {=IFERROR((SUMPRODUCT($D$24:$M$24/(1+H$61)^$D$29:$M$29)+($M$24*(1+$B65)/(H$61-$B65))/(1+H$61)^$M$29-$C$48)/$C$50,"")} -> 518.91825
B66: =B64+0.01 -> 0.05 | D66: {=IFERROR((SUMPRODUCT($D$24:$M$24/(1+D$61)^$D$29:$M$29)+($M$24*(1+$B66)/(D$61-$B66))/(1+D$61)^$M$29-$C$48)/$C$50,"")} -> 931.40109 | E66: {=IFERROR((SUMPRODUCT($D$24:$M$24/(1+E$61)^$D$29:$M$29)+($M$24*(1+$B66)/(E$61-$B66))/(1+E$61)^$M$29-$C$48)/$C$50,"")} -> 797.55908 | F66: {=IFERROR((SUMPRODUCT($D$24:$M$24/(1+F$61)^$D$29:$M$29)+($M$24*(1+$B66)/(F$61-$B66))/(1+F$61)^$M$29-$C$48)/$C$50,"")} -> 696.5656 | G66: {=IFERROR((SUMPRODUCT($D$24:$M$24/(1+G$61)^$D$29:$M$29)+($M$24*(1+$B66)/(G$61-$B66))/(1+G$61)^$M$29-$C$48)/$C$50,"")} -> 617.67081 | H66: {=IFERROR((SUMPRODUCT($D$24:$M$24/(1+H$61)^$D$29:$M$29)+($M$24*(1+$B66)/(H$61-$B66))/(1+H$61)^$M$29-$C$48)/$C$50,"")} -> 554.35337
B69: 5. REVERSE DCF
B70: To solve for the market-implied path: Data ▸ What-If Analysis ▸ Goal Seek — set C51 to the current price (C52) by changing C27 (terminal growth) or the fade-period growth inputs (I26:M26).
B72: 6. MAUBOUSSIN EV / NOPAT — TWO-STAGE FRAMEWORK
B73: EV/NOPAT = 1/r + [g × (1 − r/ROIIC) / (r × (r − g))] × [1 − ((1+g)/(1+r))^N]
B74: Formula source: Mauboussin & Rappaport, "Expectations Investing" (2021); Counterpoint Global, "What Does a Price-Earnings Multiple Mean?" (2020).
B76: Input | C76: Value | D76: Rationale (Mastercard characteristics)
B77: r (Cost of capital / WACC) | C77: =$C$13 -> 0.09084595 | D77: Linked from Section 1 WACC build
B78: g (NOPAT growth, Stage 1) | C78: 0.11 | D78: Model adjusted EBIT CAGR 2026–30E: high-single-digit GDV growth, rising yield and mid-teens value-added services growth with modest margin expansion → ~11% NOPAT growth
B79: ROIIC (Return on incremental invested capital) | C79: 0.4 | D79: A two-sided network with ~60% adjusted operating margins and capex of ~4% of revenue earns very high returns on organic investment; acquired VAS businesses (Recorded Future, BVNK) earn far less on their purchase price
B80: N (Years of value creation / CAP) | C80: 15 | D80: Global acceptance network, brand and issuer relationships sustain a long competitive-advantage period; risks are regulation (interchange, routing — CCCA), account-to-account and stablecoin rails, and rebate competition
B82: Calculation | C82: Value
B83: Steady-state component: 1 / r | C83: =1/C77 -> 11.007645
B84: Value-creation factor: 1 − r / ROIIC | C84: =1-C77/C79 -> 0.77288512
B85: Growth multiplier: g × (1 − r/ROIIC) / (r × (r − g)) | C85: =C78*C84/(C77*(C77-C78)) -> -48.858648
B86: Time decay: 1 − ((1+g)/(1+r))^N | C86: =1-((1+C78)/(1+C77))^C80 -> -0.29835462
B87: PVGO component (growth value) | C87: =C85*C86 -> 14.577204
B88: Mauboussin EV / NOPAT (steady-state + PVGO) | C88: =C83+C87 -> 25.584849
B90: VALUATION — Applied to 2028E NOPAT | C90: USDm
B91: 2028E Adj. EBIT less litigation provisions & restructuring | C91: =Model!CC189-Model!CC191 -> 27902.076
B92: Tax rate (from WACC build) | C92: =$C$10 -> 0.205
B93: 2028E NOPAT | C93: =C91*(1-C92) -> 22182.151
B94: × Mauboussin EV/NOPAT multiple | C94: =C88 -> 25.584849
B95: Implied Enterprise Value (2028E basis) | C95: =C93*C94 -> 567526.97
B96: Less: YE2027 net debt + NCI (Model) | C96: =Model!CB386+Model!CB306 -> 13334.923
B97: Implied Equity Value | C97: =C95-C96 -> 554192.05
B98: Diluted shares 2028E (m, Model) | C98: =Model!CC393 -> 821.75995
B99: Implied share price 2028 ($) | C99: =C97/C98 -> 674.39652
B101: Current share price ($) | C101: =C52 -> 595
B102: Implied upside / (downside) | C102: =C99/C101-1 -> 0.13343953
B104: MARKET-IMPLIED EV/NOPAT TODAY | C104: USDm
B105: Current market cap (spot × diluted shares) | C105: =C52*C50 -> 515826.5
B106: Plus: YE2026 net debt + NCI | C106: =C48 -> 12810.104
B107: Implied Enterprise Value (today) | C107: =C105+C106 -> 528636.6
B108: MA market-implied EV/NOPAT (on 2028E NOPAT) | C108: =C107/C93 -> 23.831621
B110: Multiple gap (Mauboussin − Market) | C110: =C88-C108 -> 1.753228
B111: Implied re-rating headroom | C111: =C88/C108-1 -> 0.073567301

Sheet Charts
B2: Mastercard Incorporated — Operating Performance (2011–2025) and Model Forecast (2026E–2030E)
B3: USDm · Linked to Model. Bars = contribution to net revenue growth (pp): payment network vs value-added services (from 2021; earlier years = total net revenue growth). Adjusted EBITDA is a model definition (adjusted operating income + D&A). ROIC on adjusted EBIT (full-cost).
C7: 2011 | D7: 2012 | E7: 2013 | F7: 2014 | G7: 2015 | H7: 2016 | I7: 2017 | J7: 2018 | K7: 2019 | L7: 2020 | M7: 2021 | N7: 2022 | O7: 2023 | P7: 2024 | Q7: 2025 | R7: 2026E | S7: 2027E | T7: 2028E | U7: 2029E | V7: 2030E
B8: Payment network contribution to growth (pp) | C8: =IFERROR(Model!H215+0,0) -> 0.21213215 | D8: =IFERROR(Model!I215+0,0) -> 0.10083408 | E8: =IFERROR(Model!N215+0,0) -> 0.1292112 | F8: =IFERROR(Model!S215+0,0) -> 0.13503475 | G8: =IFERROR(Model!X215+0,0) -> 0.020479257 | H8: =IFERROR(Model!AC215+0,0) -> 0.11472018 | I8: =IFERROR(Model!AH215+0,0) -> 0.15970676 | J8: =IFERROR(Model!AM215+0,0) -> 0.19628711 | K8: =IFERROR(Model!AR215+0,0) -> 0.12929766 | L8: =IFERROR(Model!AW215+0,0) -> -0.093703726 | M8: =IFERROR(Model!BB215+0,0) -> 0.13371675 | N8: =IFERROR(Model!BG215+0,0) -> 0.12788604 | O8: =IFERROR(Model!BL215+0,0) -> 0.065926159 | P8: =IFERROR(Model!BQ215+0,0) -> 0.060204 | Q8: =IFERROR(Model!BV215+0,0) -> 0.076010935 | R8: =IFERROR(Model!CA215+0,0) -> 0.055685736 | S8: =IFERROR(Model!CB215+0,0) -> 0.057965812 | T8: =IFERROR(Model!CC215+0,0) -> 0.05395789 | U8: =IFERROR(Model!CD215+0,0) -> 0.049910508 | V8: =IFERROR(Model!CE215+0,0) -> 0.046267593
B9: Value-added services contribution to growth (pp) | C9: =IFERROR(Model!H216+0,0) -> 0 | D9: =IFERROR(Model!I216+0,0) -> 0 | E9: =IFERROR(Model!N216+0,0) -> 0 | F9: =IFERROR(Model!S216+0,0) -> 0 | G9: =IFERROR(Model!X216+0,0) -> 0 | H9: =IFERROR(Model!AC216+0,0) -> 0 | I9: =IFERROR(Model!AH216+0,0) -> 0 | J9: =IFERROR(Model!AM216+0,0) -> 0 | K9: =IFERROR(Model!AR216+0,0) -> 0 | L9: =IFERROR(Model!AW216+0,0) -> 0 | M9: =IFERROR(Model!BB216+0,0) -> 0.10045095 | N9: =IFERROR(Model!BG216+0,0) -> 0.04967168 | O9: =IFERROR(Model!BL216+0,0) -> 0.062733282 | P9: =IFERROR(Model!BQ216+0,0) -> 0.062076659 | Q9: =IFERROR(Model!BV216+0,0) -> 0.088152803 | R9: =IFERROR(Model!CA216+0,0) -> 0.079314264 | S9: =IFERROR(Model!CB216+0,0) -> 0.065825226 | T9: =IFERROR(Model!CC216+0,0) -> 0.064613078 | U9: =IFERROR(Model!CD216+0,0) -> 0.06133109 | V9: =IFERROR(Model!CE216+0,0) -> 0.057800983
C11: =C7 -> 2011 | D11: =D7 -> 2012 | E11: =E7 -> 2013 | F11: =F7 -> 2014 | G11: =G7 -> 2015 | H11: =H7 -> 2016 | I11: =I7 -> 2017 | J11: =J7 -> 2018 | ... V11: =V7 -> 2030E
B12: Adjusted EBITDA (model) | C12: =Model!H185 -> 3677 | D12: =Model!I185 -> 4187 | E12: =Model!N185 -> 4856 | F12: =Model!S185 -> 5427 | G12: =Model!X185 -> 5584 | H12: =Model!AC185 -> 6251 | I12: =Model!AH185 -> 7240 | J12: =Model!AM185 -> 8869 | K12: =Model!AR185 -> 10186 | L12: =Model!AW185 -> 8734 | M12: =Model!BB185 -> 10984 | N12: =Model!BG185 -> 13400 | O12: =Model!BL185 -> 15346 | P12: =Model!BQ185 -> 17349 | Q12: =Model!BV185 -> 20544 | R12: =Model!CA185 -> 23545.935 | S12: =Model!CB185 -> 26679.846 | T12: =Model!CC185 -> 30045.866 | U12: =Model!CD185 -> 33610.893 | V12: =Model!CE185 -> 37351.919
B13: Operating income (GAAP) | C13: =Model!H130 -> 2713 | D13: =Model!I130 -> 3937 | E13: =Model!N130 -> 4503 | F13: =Model!S130 -> 5106 | G13: =Model!X130 -> 5078 | H13: =Model!AC130 -> 5761 | I13: =Model!AH130 -> 6622 | J13: =Model!AM130 -> 7282 | K13: =Model!AR130 -> 9664 | L13: =Model!AW130 -> 8081 | M13: =Model!BB130 -> 10082 | N13: =Model!BG130 -> 12264 | O13: =Model!BL130 -> 14008 | P13: =Model!BQ130 -> 15582 | Q13: =Model!BV130 -> 18897 | R13: =Model!CA130 -> 21803.935 | S13: =Model!CB130 -> 24742.17 | T13: =Model!CC130 -> 27902.076 | U13: =Model!CD130 -> 31252.656 | V13: =Model!CE130 -> 34772.229
B14: Adj. EBITDA Margin % | C14: =Model!H224 -> 0.5476616 | D14: =Model!I224 -> 0.5664998 | E14: =Model!N224 -> 0.58183561 | F14: =Model!S224 -> 0.57289138 | G14: =Model!X224 -> 0.57763525 | H14: =Model!AC224 -> 0.58008537 | I14: =Model!AH224 -> 0.57933904 | J14: =Model!AM224 -> 0.59324415 | K14: =Model!AR224 -> 0.60332879 | L14: =Model!AW224 -> 0.57081237 | M14: =Model!BB224 -> 0.58165643 | N14: =Model!BG224 -> 0.60259927 | O14: =Model!BL224 -> 0.61144314 | P14: =Model!BQ224 -> 0.61593354 | Q14: =Model!BV224 -> 0.62651337 | R14: =Model!CA224 -> 0.63265278 | S14: =Model!CB224 -> 0.63789211 | T14: =Model!CC224 -> 0.64222187 | U14: =Model!CD224 -> 0.64650507 | V14: =Model!CE224 -> 0.65074186
B15: Operating Margin % | C15: =Model!H225 -> 0.40408102 | D15: =Model!I225 -> 0.53267487 | E15: =Model!N225 -> 0.5395399 | F15: =Model!S225 -> 0.53900559 | G15: =Model!X225 -> 0.52529223 | H15: =Model!AC225 -> 0.53461396 | I15: =Model!AH225 -> 0.52988717 | J15: =Model!AM225 -> 0.4870903 | K15: =Model!AR225 -> 0.57241012 | L15: =Model!AW225 -> 0.52813542 | M15: =Model!BB225 -> 0.53389112 | N15: =Model!BG225 -> 0.55151324 | O15: =Model!BL225 -> 0.55813212 | P15: =Model!BQ225 -> 0.55320055 | Q15: =Model!BV225 -> 0.57628618 | R15: =Model!CA225 -> 0.5858472 | S15: =Model!CB225 -> 0.59156396 | T15: =Model!CC225 -> 0.59639898 | U15: =Model!CD225 -> 0.6011444 | V15: =Model!CE225 -> 0.60579873
C17: =C7 -> 2011 | D17: =D7 -> 2012 | E17: =E7 -> 2013 | F17: =F7 -> 2014 | G17: =G7 -> 2015 | H17: =H7 -> 2016 | I17: =I7 -> 2017 | J17: =J7 -> 2018 | ... V17: =V7 -> 2030E
B18: ROIC | C18: =IFERROR(Model!H369+0,NA()) -> 2.5608662 | D18: =IFERROR(Model!I369+0,NA()) -> 1.4405534 | E18: =IFERROR(Model!N369+0,NA()) -> 2.6492285 | F18: =IFERROR(Model!S369+0,NA()) -> 1.8063726 | G18: =IFERROR(Model!X369+0,NA()) -> 1.5300158 | H18: =IFERROR(Model!AC369+0,NA()) -> 1.6712902 | I18: =IFERROR(Model!AH369+0,NA()) -> 1.5511465 | J18: =IFERROR(Model!AM369+0,NA()) -> 1.9900097 | K18: =IFERROR(Model!AR369+0,NA()) -> 1.1721702 | L18: =IFERROR(Model!AW369+0,NA()) -> 0.78595638 | M18: =IFERROR(Model!BB369+0,NA()) -> 0.64710137 | N18: =IFERROR(Model!BG369+0,NA()) -> 0.82114966 | O18: =IFERROR(Model!BL369+0,NA()) -> 0.87850555 | P18: =IFERROR(Model!BQ369+0,NA()) -> 0.86365149 | Q18: =IFERROR(Model!BV369+0,NA()) -> 0.98439879 | R18: =IFERROR(Model!CA369+0,NA()) -> 0.93967132 | S18: =IFERROR(Model!CB369+0,NA()) -> 0.96558791 | T18: =IFERROR(Model!CC369+0,NA()) -> 0.99856396 | U18: =IFERROR(Model!CD369+0,NA()) -> 1.0318003 | V18: =IFERROR(Model!CE369+0,NA()) -> 1.0644783
B19: RONTA | C19: =IFERROR(Model!H380+0,NA()) -> 0.49541042 | D19: =IFERROR(Model!I380+0,NA()) -> 0.47902379 | E19: =IFERROR(Model!N380+0,NA()) -> 0.49549162 | F19: =IFERROR(Model!S380+0,NA()) -> 0.5292138 | G19: =IFERROR(Model!X380+0,NA()) -> 0.54679323 | H19: =IFERROR(Model!AC380+0,NA()) -> 0.47010266 | I19: =IFERROR(Model!AH380+0,NA()) -> 0.59410335 | J19: =IFERROR(Model!AM380+0,NA()) -> 0.69444725 | K19: =IFERROR(Model!AR380+0,NA()) -> 0.67428857 | L19: =IFERROR(Model!AW380+0,NA()) -> 0.43091451 | M19: =IFERROR(Model!BB380+0,NA()) -> 0.62175664 | N19: =IFERROR(Model!BG380+0,NA()) -> 0.7934238 | O19: =IFERROR(Model!BL380+0,NA()) -> 0.75170003 | P19: =IFERROR(Model!BQ380+0,NA()) -> 0.92159376 | Q19: =IFERROR(Model!BV380+0,NA()) -> 0.91607469 | R19: =IFERROR(Model!CA380+0,NA()) -> 1.0006567 | S19: =IFERROR(Model!CB380+0,NA()) -> 1.0467311 | T19: =IFERROR(Model!CC380+0,NA()) -> 1.161544 | U19: =IFERROR(Model!CD380+0,NA()) -> 1.2659362 | V19: =IFERROR(Model!CE380+0,NA()) -> 1.3339749
B20: Adj. EBITDA margin % | C20: =IFERROR(Model!H224+0,NA()) -> 0.5476616 | D20: =IFERROR(Model!I224+0,NA()) -> 0.5664998 | E20: =IFERROR(Model!N224+0,NA()) -> 0.58183561 | F20: =IFERROR(Model!S224+0,NA()) -> 0.57289138 | G20: =IFERROR(Model!X224+0,NA()) -> 0.57763525 | H20: =IFERROR(Model!AC224+0,NA()) -> 0.58008537 | I20: =IFERROR(Model!AH224+0,NA()) -> 0.57933904 | J20: =IFERROR(Model!AM224+0,NA()) -> 0.59324415 | K20: =IFERROR(Model!AR224+0,NA()) -> 0.60332879 | L20: =IFERROR(Model!AW224+0,NA()) -> 0.57081237 | M20: =IFERROR(Model!BB224+0,NA()) -> 0.58165643 | N20: =IFERROR(Model!BG224+0,NA()) -> 0.60259927 | O20: =IFERROR(Model!BL224+0,NA()) -> 0.61144314 | P20: =IFERROR(Model!BQ224+0,NA()) -> 0.61593354 | Q20: =IFERROR(Model!BV224+0,NA()) -> 0.62651337 | R20: =IFERROR(Model!CA224+0,NA()) -> 0.63265278 | S20: =IFERROR(Model!CB224+0,NA()) -> 0.63789211 | T20: =IFERROR(Model!CC224+0,NA()) -> 0.64222187 | U20: =IFERROR(Model!CD224+0,NA()) -> 0.64650507 | V20: =IFERROR(Model!CE224+0,NA()) -> 0.65074186
B21: FCF margin % | C21: =IFERROR(Model!H258+0,NA()) -> 0.37339887 | D21: =IFERROR(Model!I258+0,NA()) -> 0.36936815 | E21: =IFERROR(Model!N258+0,NA()) -> 0.45962138 | F21: =IFERROR(Model!S258+0,NA()) -> 0.32439565 | G21: =IFERROR(Model!X258+0,NA()) -> 0.38284887 | H21: =IFERROR(Model!AC258+0,NA()) -> 0.38066073 | I21: =IFERROR(Model!AH258+0,NA()) -> 0.41065856 | J21: =IFERROR(Model!AM258+0,NA()) -> 0.38254181 | K21: =IFERROR(Model!AR258+0,NA()) -> 0.44156844 | L21: =IFERROR(Model!AW258+0,NA()) -> 0.42585452 | M21: =IFERROR(Model!BB258+0,NA()) -> 0.45800678 | N21: =IFERROR(Model!BG258+0,NA()) -> 0.45410802 | O21: =IFERROR(Model!BL258+0,NA()) -> 0.4339788 | P21: =IFERROR(Model!BQ258+0,NA()) -> 0.48233749 | Q21: =IFERROR(Model!BV258+0,NA()) -> 0.50114361 | R21: =IFERROR(Model!CA258+0,NA()) -> 0.43646938 | S21: =IFERROR(Model!CB258+0,NA()) -> 0.46129457 | T21: =IFERROR(Model!CC258+0,NA()) -> 0.46624979 | U21: =IFERROR(Model!CD258+0,NA()) -> 0.47086829 | V21: =IFERROR(Model!CE258+0,NA()) -> 0.4752292
