Workbook

Sheet Model
AC1: SCENARIO SWITCH ▼ (Bull / Base / Bear) — drives all scenario-linked forecast drivers
B2: Mobility Global Inc. (NYSE: MBGL) — 3-Statement Financial Model | AC2: Base
B3: US GAAP · USD millions (whole millions as published; per-share data in USD; shares in millions) · calendar fiscal year · Source: Mobility Global Form 10 (information statement, 10-12B/A, 27-May-2026; first draft DRS 23-Oct-2025), Form 10-Q (Q2-26), Form 8-K (earnings release Ex. 99.1 and FY2025 quarterly data Ex. 99.2, 7-Aug-2026; separation 2-Jul-2026), SEC EDGAR CIK 0002090312 ("S&P Global Mobility Holding Co" to Jan-2026); S&P Global Inc. earnings releases (CIK 0000064040) for the Mobility segment memo; investor-relations sites are blocked — the releases are the documents filed on EDGAR
B4: Basis notes: spun off from S&P Global on 1-Jul-2026 (one MBGL share per SPGI share; 294.8m shares). History to 30-Jun-2026 = carve-out (combined) statements incl. S&P Global corporate allocations: FY2023–25 annual, 2025 quarters (Q3/Q4 "unaudited and preliminary"), Q1/Q2-26. Pre-2025 quarters and FY2022 = S&P Global "Mobility" segment memo (revenue comparable within $0–4m; profit not comparable). Segments: CARFAX, B2B (2025 realignment; recast by the company). Acquisition: Market Scan Feb-2023. $2.0bn senior notes (May-2026) funded a $2.0bn dividend to S&P Global. Q3/Q4-26E calibrated to FY26 revenue and Adjusted EBITDA guidance (7-Aug-2026).
AE5: Forecast | AF5: Historical | AG5: Historical | AH5: Historical
B6: (USDm) | C6: 2022 | D6: Q1/23 | E6: Q2/23 | F6: Q3/23 | G6: Q4/23 | H6: 2023 | I6: Q1/24 | J6: Q2/24 | K6: Q3/24 | L6: Q4/24 | M6: 2024 | N6: Q1/25 | O6: Q2/25 | P6: Q3/25 | Q6: Q4/25 | R6: 2025 | S6: Q1/26 | T6: Q2/26 | U6: Q3/26E | V6: Q4/26E | W6: 2026E | X6: 2027E | Y6: 2028E | Z6: 2029E | AA6: 2030E | AB6: 2031E | AC6: Modelling Notes | AE6: 5Y CAGR | AF6: 2Y CAGR | AG6: 1Y | AH6: 3Y CAGR
AE7: 26-'31 | AF7: 23-'25 | AG7: 24-'25 | AH7: 22-'25
B8: SEGMENT P&L — CARFAX · B2B · CORPORATE (revenue × Segment Adjusted EBITDA margin) | AC8: SEGMENT BUILD — modelling logic (segment revenue → Segment Adjusted EBITDA margin → Adjusted EBITDA → GAAP P&L). Carve-out basis to 30-Jun-2026; consolidated from Q3-26.
AK9: SCENARIO INPUT TABLE — driver assumptions per Bull / Base / Bear | AL9: Bull | AM9: Base | AN9: Bear | AO9: Bull / Bear = Base + Δ (Δ inputs on each block header). Outlook block = high / mid / low end of the FY26 guidance ranges.
B10: CARFAX | AC10: CFX — modelling logic
B11: Segment revenue | H11: 928 | M11: 1039 | N11: 275 | O11: 289 | P11: 291 | Q11: 287 | R11: 1142 | S11: 298 | T11: 312 | U11: =P11*(1+U12) -> 313.83911 | V11: =Q11*(1+V12) -> 309.52517 | W11: =SUM(S11:V11) -> 1233.3643 | X11: =W11*(1+X12) -> 1332.0334 | Y11: =X11*(1+Y12) -> 1435.932 | Z11: =Y11*(1+Z12) -> 1543.6269 | AA11: =Z11*(1+AA12) -> 1654.7681 | AB11: =AA11*(1+AB12) -> 1770.6018 | AC11: Carve-out segment revenue as published (Form 10 MD&A FY2023–25, Q1-25 / Q1-26; 10-Q / release Q2; FY2025 quarterly data Ex. 99.2 for Q3-25 / Q4-25). Q3/Q4-26E: prior-year quarter × (1 + growth). 2027E+: prior year × (1 + scenario lever). | AE11: =IFERROR((AB11/W11)^(1/5)-1,"n/m") -> 0.074993674 | AF11: =IFERROR((R11/H11)^(1/2)-1,"n/m") -> 0.10932567 | AG11: =IFERROR(R11/M11-1,"n/m") -> 0.099133782 | AH11: =IFERROR((R11/C11)^(1/3)-1,"n/m") -> n/m | AK11: FY26 outlook — Q2-26 release (7-Aug-2026) | AL11: High | AM11: Mid | AN11: Low | AO11: First guidance as a public company: revenue $1,870–1,885m (+6.9–7.7%), Adjusted EBITDA $745–760m (~40% margin); 1H carve-out + 2H consolidated. No EPS / interest / tax / capex / FCF guidance. "Medium-term financial targets" referenced in the release are not filed on EDGAR (unverified; not used).
B12: y/y % | H12: =IF(AND(ISNUMBER(H11),ISNUMBER(C11)),IFERROR(H11/C11-1,""),"") | I12: =IF(AND(ISNUMBER(I11),ISNUMBER(D11)),IFERROR(I11/D11-1,""),"") | J12: =IF(AND(ISNUMBER(J11),ISNUMBER(E11)),IFERROR(J11/E11-1,""),"") | K12: =IF(AND(ISNUMBER(K11),ISNUMBER(F11)),IFERROR(K11/F11-1,""),"") | L12: =IF(AND(ISNUMBER(L11),ISNUMBER(G11)),IFERROR(L11/G11-1,""),"") | M12: =IF(AND(ISNUMBER(M11),ISNUMBER(H11)),IFERROR(M11/H11-1,""),"") -> 0.11961207 | N12: =IF(AND(ISNUMBER(N11),ISNUMBER(I11)),IFERROR(N11/I11-1,""),"") | O12: =IF(AND(ISNUMBER(O11),ISNUMBER(J11)),IFERROR(O11/J11-1,""),"") | ... T12: =IF(AND(ISNUMBER(T11),ISNUMBER(O11)),IFERROR(T11/O11-1,""),"") -> 0.079584775 | U12: =U13+$U$94 -> 0.07848492 | V12: =V13+$U$94 -> 0.07848492 | W12: =IF(AND(ISNUMBER(W11),ISNUMBER(R11)),IFERROR(W11/R11-1,""),"") -> 0.080003751 | X12: =CHOOSE(MATCH($AC$2,{"Bull","Base","Bear"},0),$AL$24,$AM$24,$AN$24) -> 0.08 | Y12: =CHOOSE(MATCH($AC$2,{"Bull","Base","Bear"},0),$AL$25,$AM$25,$AN$25) -> 0.078 | Z12: =CHOOSE(MATCH($AC$2,{"Bull","Base","Bear"},0),$AL$26,$AM$26,$AN$26) -> 0.075 | AA12: =CHOOSE(MATCH($AC$2,{"Bull","Base","Bear"},0),$AL$27,$AM$27,$AN$27) -> 0.072 | AB12: =CHOOSE(MATCH($AC$2,{"Bull","Base","Bear"},0),$AL$28,$AM$28,$AN$28) -> 0.07 | AC12: Q3/Q4-26E: growth before calibration (row below) + revenue-outlook calibration Δ (Group block). 2027E–2031E: scenario lever. | AK12: FY26 revenue ($m) | AL12: 1885 | AM12: 1877.5 | AN12: 1870 | AO12: Guided $1,870–1,885m. Drives the Q3/Q4-26E revenue calibration.
B13: Q3/Q4-26E growth before revenue calibration (1H/26 y/y) | U13: =IFERROR((S11+T11)/(N11+O11)-1,0) -> 0.081560284 | V13: =IFERROR((S11+T11)/(N11+O11)-1,0) -> 0.081560284 | AK13: FY26 Adjusted EBITDA ($m) | AL13: 760 | AM13: 752.5 | AN13: 745 | AO13: Guided $745–760m. Drives the Q3/Q4-26E segment-margin calibration.
B14: Subscription revenue | H14: 748 | M14: 843 | N14: 225 | O14: 234 | P14: 235 | Q14: 233 | R14: 927 | S14: 242 | T14: 252 | AK14: 2H/26 share repurchases ($m) | AL14: 0 | AM14: 0 | AN14: 0 | AO14: No repurchase authorization announced (10-Q, 8-Ks). Dividend $0.06 a quarter.
B15: Non-subscription revenue | H15: 180 | M15: 196 | N15: 50 | O15: 55 | P15: 56 | Q15: 54 | R15: 215 | S15: 56 | T15: 60
B16: Subscription % of segment revenue | C16: =IF(AND(ISNUMBER(C14),ISNUMBER(C11)),IFERROR(C14/C11,""),"") | D16: =IF(AND(ISNUMBER(D14),ISNUMBER(D11)),IFERROR(D14/D11,""),"") | E16: =IF(AND(ISNUMBER(E14),ISNUMBER(E11)),IFERROR(E14/E11,""),"") | F16: =IF(AND(ISNUMBER(F14),ISNUMBER(F11)),IFERROR(F14/F11,""),"") | G16: =IF(AND(ISNUMBER(G14),ISNUMBER(G11)),IFERROR(G14/G11,""),"") | H16: =IF(AND(ISNUMBER(H14),ISNUMBER(H11)),IFERROR(H14/H11,""),"") -> 0.80603448 | I16: =IF(AND(ISNUMBER(I14),ISNUMBER(I11)),IFERROR(I14/I11,""),"") | J16: =IF(AND(ISNUMBER(J14),ISNUMBER(J11)),IFERROR(J14/J11,""),"") | ... AB16: =IF(AND(ISNUMBER(AB14),ISNUMBER(AB11)),IFERROR(AB14/AB11,""),"") | AE16: =IFERROR(AVERAGE(X16,Y16,Z16,AA16,AB16),"n/m") -> n/m | AF16: =IFERROR(AVERAGE(H16,M16,R16),"n/m") -> 0.80970845 | AG16: =IFERROR(AVERAGE(M16,R16),"n/m") -> 0.81154544 | AH16: =IFERROR(AVERAGE(C16,H16,M16,R16),"n/m") -> 0.80970845 | AK16: FY26 point estimates (all cases; not guided — assumptions unless stated)
B17: International revenue (memo) | H17: 137 | M17: 155 | N17: 39 | O17: 43 | R17: 168 | S17: 45 | T17: 47 | AK17: 2H/26 interest expense, net ($m) | AM17: 54 | AO17: Assumption: coupons on $2.0bn notes $27.7m a quarter + ~$0.8m accretion/fees − interest on ~$250m cash. Form 10 pro forma: $114m p.a. gross (5.74% incl. amortization).
B18: Segment Adjusted EBITDA | H18: 422 | M18: 476 | N18: 130 | O18: 142 | P18: 146 | Q18: 118 | R18: 536 | S18: 140 | T18: 153 | U18: =U11*U19 -> 154.69458 | V18: =V11*V19 -> 124.535 | W18: =SUM(S18:V18) -> 572.22959 | X18: =X11*X19 -> 639.37604 | Y18: =Y11*Y19 -> 696.42704 | Z18: =Z11*Z19 -> 756.3772 | AA18: =AA11*AA19 -> 819.1102 | AB18: =AB11*AB19 -> 885.30092 | AC18: Company measure: segment operating profit + D&A + SBC + transaction costs + severance & other. Forecast = revenue × margin. | AE18: =IFERROR((AB18/W18)^(1/5)-1,"n/m") -> 0.091199408 | AF18: =IFERROR((R18/H18)^(1/2)-1,"n/m") -> 0.12700585 | AG18: =IFERROR(R18/M18-1,"n/m") -> 0.12605042 | AH18: =IFERROR((R18/C18)^(1/3)-1,"n/m") -> n/m | AK18: 2H/26 effective tax rate | AM18: 0.29 | AO18: Assumption: 1H/26 29.4% (Q2 29.3%); not guided.
B19: Segment Adjusted EBITDA margin % | C19: =IF(AND(ISNUMBER(C18),ISNUMBER(C11)),IFERROR(C18/C11,""),"") | D19: =IF(AND(ISNUMBER(D18),ISNUMBER(D11)),IFERROR(D18/D11,""),"") | E19: =IF(AND(ISNUMBER(E18),ISNUMBER(E11)),IFERROR(E18/E11,""),"") | F19: =IF(AND(ISNUMBER(F18),ISNUMBER(F11)),IFERROR(F18/F11,""),"") | G19: =IF(AND(ISNUMBER(G18),ISNUMBER(G11)),IFERROR(G18/G11,""),"") | H19: =IF(AND(ISNUMBER(H18),ISNUMBER(H11)),IFERROR(H18/H11,""),"") -> 0.45474138 | I19: =IF(AND(ISNUMBER(I18),ISNUMBER(I11)),IFERROR(I18/I11,""),"") | J19: =IF(AND(ISNUMBER(J18),ISNUMBER(J11)),IFERROR(J18/J11,""),"") | ... T19: =IF(AND(ISNUMBER(T18),ISNUMBER(T11)),IFERROR(T18/T11,""),"") -> 0.49038462 | U19: =U20+$U$98 -> 0.49291047 | V19: =V20+$U$98 -> 0.40234208 | W19: =IF(AND(ISNUMBER(W18),ISNUMBER(W11)),IFERROR(W18/W11,""),"") -> 0.46395829 | X19: =CHOOSE(MATCH($AC$2,{"Bull","Base","Bear"},0),$AL$36,$AM$36,$AN$36) -> 0.48 | Y19: =CHOOSE(MATCH($AC$2,{"Bull","Base","Bear"},0),$AL$37,$AM$37,$AN$37) -> 0.485 | Z19: =CHOOSE(MATCH($AC$2,{"Bull","Base","Bear"},0),$AL$38,$AM$38,$AN$38) -> 0.49 | AA19: =CHOOSE(MATCH($AC$2,{"Bull","Base","Bear"},0),$AL$39,$AM$39,$AN$39) -> 0.495 | AB19: =CHOOSE(MATCH($AC$2,{"Bull","Base","Bear"},0),$AL$40,$AM$40,$AN$40) -> 0.5 | AC19: Q3/Q4-26E: margin before calibration + Adjusted-EBITDA-outlook calibration Δ. 2027E–2031E: scenario lever. | AE19: =IFERROR(AVERAGE(X19,Y19,Z19,AA19,AB19),"n/m") -> 0.49 | AF19: =IFERROR(AVERAGE(H19,M19,R19),"n/m") -> 0.46074207 | AG19: =IFERROR(AVERAGE(M19,R19),"n/m") -> 0.46374242 | AH19: =IFERROR(AVERAGE(C19,H19,M19,R19),"n/m") -> 0.46074207 | AK19: FY26 capital expenditures ($m) | AM19: 26 | AO19: Assumption: 1H/26 $12m; FY2025 $24m.
B20: Q3/Q4-26E margin before calibration (prior-year quarter + 1H/26 y/y drift) | U20: =P19+((S18+T18)/(S11+T11)-(N18+O18)/(N11+O11)) -> 0.49977658 | V20: =Q19+((S18+T18)/(S11+T11)-(N18+O18)/(N11+O11)) -> 0.40920819
B21: Segment operating profit (GAAP) | H21: 210 | M21: 259 | N21: 77 | O21: 89 | P21: 92 | Q21: 64 | R21: 322 | S21: 89 | T21: 101 | AK21: Target net debt / Adjusted EBITDA (x) — buyback plug 2027E+ | AL21: 2.5 | AM21: 2 | AN21: 1.5 | AO21: Assumption — no leverage target published. Net debt ~$1.8bn at 30-Jun-26 ≈ 2.5x LTM Adjusted EBITDA ($740m); covenant ≤ 3.50x; notes rated investment grade (change-of-control put on a downgrade below IG). Target = leverage at which surplus cash is returned via buybacks; Bull = more buybacks (higher target).
B22: Segment D&A (memo) | H22: 198 | M22: 199 | N22: 50 | O22: 50 | P22: 50 | Q22: 48 | R22: 198 | S22: 50 | T22: 50
B23: Segment stock-based compensation (memo) | H23: 14 | M23: 18 | N23: 3 | O23: 2 | P23: 4 | Q23: 4 | R23: 13 | S23: 1 | T23: 2 | AK23: CFX_G (CARFAX revenue y/y) | AL23: 0.02 | AM23: Δ → | AN23: -0.03 | AO23: FY2024 +12%, FY2025 +10%, 1H/26 +8%: dealer subscriptions (Advantage, Listings, CARFAX for Life), BIG data customers, Showroom / Homegrown launches, CARFAX Germany.
B24: Segment transaction costs, severance & other items (memo) | H24: 0 | M24: 0 | N24: 0 | O24: 1 | P24: 0 | Q24: 2 | R24: 3 | S24: 0 | T24: 0 | AK24: 2027E | AL24: =AM24+$AL$23 -> 0.1 | AM24: 0.08 | AN24: =AM24+$AN$23 -> 0.05
B25: Check: segment OP + D&A + SBC + items vs Segment Adjusted EBITDA (should be 0; ±1 rounding) | C25: =IF(AND(ISNUMBER(C21),ISNUMBER(C18)),IF(ABS(C21+C22+N(C23)+N(C24)-C18)<=1,0,C21+C22+N(C23)+N(C24)-C18),"") | D25: =IF(AND(ISNUMBER(D21),ISNUMBER(D18)),IF(ABS(D21+D22+N(D23)+N(D24)-D18)<=1,0,D21+D22+N(D23)+N(D24)-D18),"") | E25: =IF(AND(ISNUMBER(E21),ISNUMBER(E18)),IF(ABS(E21+E22+N(E23)+N(E24)-E18)<=1,0,E21+E22+N(E23)+N(E24)-E18),"") | F25: =IF(AND(ISNUMBER(F21),ISNUMBER(F18)),IF(ABS(F21+F22+N(F23)+N(F24)-F18)<=1,0,F21+F22+N(F23)+N(F24)-F18),"") | G25: =IF(AND(ISNUMBER(G21),ISNUMBER(G18)),IF(ABS(G21+G22+N(G23)+N(G24)-G18)<=1,0,G21+G22+N(G23)+N(G24)-G18),"") | H25: =IF(AND(ISNUMBER(H21),ISNUMBER(H18)),IF(ABS(H21+H22+N(H23)+N(H24)-H18)<=1,0,H21+H22+N(H23)+N(H24)-H18),"") -> 0 | I25: =IF(AND(ISNUMBER(I21),ISNUMBER(I18)),IF(ABS(I21+I22+N(I23)+N(I24)-I18)<=1,0,I21+I22+N(I23)+N(I24)-I18),"") | J25: =IF(AND(ISNUMBER(J21),ISNUMBER(J18)),IF(ABS(J21+J22+N(J23)+N(J24)-J18)<=1,0,J21+J22+N(J23)+N(J24)-J18),"") | ... T25: =IF(AND(ISNUMBER(T21),ISNUMBER(T18)),IF(ABS(T21+T22+N(T23)+N(T24)-T18)<=1,0,T21+T22+N(T23)+N(T24)-T18),"") -> 0 | AK25: 2028E | AL25: =AM25+$AL$23 -> 0.098 | AM25: 0.078 | AN25: =AM25+$AN$23 -> 0.048
B26: Segment Adjusted operating profit (company; Form 10 periods) | H26: 400 | M26: 449 | N26: 124 | R26: 514 | S26: 136 | AK26: 2029E | AL26: =AM26+$AL$23 -> 0.095 | AM26: 0.075 | AN26: =AM26+$AN$23 -> 0.045
AK27: 2030E | AL27: =AM27+$AL$23 -> 0.092 | AM27: 0.072 | AN27: =AM27+$AN$23 -> 0.042
B28: B2B (automotiveMastermind, Polk Automotive Solutions, Market Scan, OEM & supplier data) | AC28: B2B — modelling logic | AK28: 2031E | AL28: =AM28+$AL$23 -> 0.09 | AM28: 0.07 | AN28: =AM28+$AN$23 -> 0.04
B29: Segment revenue | H29: 557 | M29: 574 | N29: 145 | O29: 150 | P29: 154 | Q29: 159 | R29: 608 | S29: 157 | T29: 156 | U29: =P29*(1+U30) -> 162.923 | V29: =Q29*(1+V30) -> 168.21271 | W29: =SUM(S29:V29) -> 644.13572 | X29: =W29*(1+X30) -> 676.3425 | Y29: =X29*(1+Y30) -> 710.15963 | Z29: =Y29*(1+Z30) -> 742.11681 | AA29: =Z29*(1+AA30) -> 775.51207 | AB29: =AA29*(1+AB30) -> 806.53255 | AE29: =IFERROR((AB29/W29)^(1/5)-1,"n/m") -> 0.045993302 | AF29: =IFERROR((R29/H29)^(1/2)-1,"n/m") -> 0.044778416 | AG29: =IFERROR(R29/M29-1,"n/m") -> 0.059233449 | AH29: =IFERROR((R29/C29)^(1/3)-1,"n/m") -> n/m | AK29: B2B_G (B2B revenue y/y) | AL29: 0.02 | AM29: Δ → | AN29: -0.03 | AO29: FY2024 +3%, FY2025 +6%, 1H/26 +6% (Q2 +4%): OEM / dealer marketing (automotiveMastermind), Polk data, Market Scan; non-subscription (recalls, marketing) cyclical.
B30: y/y % | H30: =IF(AND(ISNUMBER(H29),ISNUMBER(C29)),IFERROR(H29/C29-1,""),"") | I30: =IF(AND(ISNUMBER(I29),ISNUMBER(D29)),IFERROR(I29/D29-1,""),"") | J30: =IF(AND(ISNUMBER(J29),ISNUMBER(E29)),IFERROR(J29/E29-1,""),"") | K30: =IF(AND(ISNUMBER(K29),ISNUMBER(F29)),IFERROR(K29/F29-1,""),"") | L30: =IF(AND(ISNUMBER(L29),ISNUMBER(G29)),IFERROR(L29/G29-1,""),"") | M30: =IF(AND(ISNUMBER(M29),ISNUMBER(H29)),IFERROR(M29/H29-1,""),"") -> 0.030520646 | N30: =IF(AND(ISNUMBER(N29),ISNUMBER(I29)),IFERROR(N29/I29-1,""),"") | O30: =IF(AND(ISNUMBER(O29),ISNUMBER(J29)),IFERROR(O29/J29-1,""),"") | ... T30: =IF(AND(ISNUMBER(T29),ISNUMBER(O29)),IFERROR(T29/O29-1,""),"") -> 0.04 | U30: =U31+$U$94 -> 0.057941585 | V30: =V31+$U$94 -> 0.057941585 | W30: =IF(AND(ISNUMBER(W29),ISNUMBER(R29)),IFERROR(W29/R29-1,""),"") -> 0.059433744 | X30: =CHOOSE(MATCH($AC$2,{"Bull","Base","Bear"},0),$AL$30,$AM$30,$AN$30) -> 0.05 | Y30: =CHOOSE(MATCH($AC$2,{"Bull","Base","Bear"},0),$AL$31,$AM$31,$AN$31) -> 0.05 | Z30: =CHOOSE(MATCH($AC$2,{"Bull","Base","Bear"},0),$AL$32,$AM$32,$AN$32) -> 0.045 | AA30: =CHOOSE(MATCH($AC$2,{"Bull","Base","Bear"},0),$AL$33,$AM$33,$AN$33) -> 0.045 | AB30: =CHOOSE(MATCH($AC$2,{"Bull","Base","Bear"},0),$AL$34,$AM$34,$AN$34) -> 0.04 | AK30: 2027E | AL30: =AM30+$AL$29 -> 0.07 | AM30: 0.05 | AN30: =AM30+$AN$29 -> 0.02
B31: Q3/Q4-26E growth before revenue calibration (1H/26 y/y) | U31: =IFERROR((S29+T29)/(N29+O29)-1,0) -> 0.061016949 | V31: =IFERROR((S29+T29)/(N29+O29)-1,0) -> 0.061016949 | AK31: 2028E | AL31: =AM31+$AL$29 -> 0.07 | AM31: 0.05 | AN31: =AM31+$AN$29 -> 0.02
B32: Subscription revenue | H32: 422 | M32: 460 | N32: 118 | O32: 124 | P32: 127 | Q32: 130 | R32: 499 | S32: 130 | T32: 131 | AK32: 2029E | AL32: =AM32+$AL$29 -> 0.065 | AM32: 0.045 | AN32: =AM32+$AN$29 -> 0.015
B33: Non-subscription revenue | H33: 135 | M33: 114 | N33: 27 | O33: 26 | P33: 27 | Q33: 29 | R33: 109 | S33: 27 | T33: 25 | AK33: 2030E | AL33: =AM33+$AL$29 -> 0.065 | AM33: 0.045 | AN33: =AM33+$AN$29 -> 0.015
B34: Subscription % of segment revenue | C34: =IF(AND(ISNUMBER(C32),ISNUMBER(C29)),IFERROR(C32/C29,""),"") | D34: =IF(AND(ISNUMBER(D32),ISNUMBER(D29)),IFERROR(D32/D29,""),"") | E34: =IF(AND(ISNUMBER(E32),ISNUMBER(E29)),IFERROR(E32/E29,""),"") | F34: =IF(AND(ISNUMBER(F32),ISNUMBER(F29)),IFERROR(F32/F29,""),"") | G34: =IF(AND(ISNUMBER(G32),ISNUMBER(G29)),IFERROR(G32/G29,""),"") | H34: =IF(AND(ISNUMBER(H32),ISNUMBER(H29)),IFERROR(H32/H29,""),"") -> 0.75763016 | I34: =IF(AND(ISNUMBER(I32),ISNUMBER(I29)),IFERROR(I32/I29,""),"") | J34: =IF(AND(ISNUMBER(J32),ISNUMBER(J29)),IFERROR(J32/J29,""),"") | ... AB34: =IF(AND(ISNUMBER(AB32),ISNUMBER(AB29)),IFERROR(AB32/AB29,""),"") | AE34: =IFERROR(AVERAGE(X34,Y34,Z34,AA34,AB34),"n/m") -> n/m | AF34: =IFERROR(AVERAGE(H34,M34,R34),"n/m") -> 0.79324919 | AG34: =IFERROR(AVERAGE(M34,R34),"n/m") -> 0.81105871 | AH34: =IFERROR(AVERAGE(C34,H34,M34,R34),"n/m") -> 0.79324919 | AK34: 2031E | AL34: =AM34+$AL$29 -> 0.06 | AM34: 0.04 | AN34: =AM34+$AN$29 -> 0.01
B35: International revenue (memo) | H35: 124 | M35: 129 | N35: 31 | O35: 31 | R35: 128 | S35: 34 | T35: 32 | AK35: CFX_M (CARFAX Segment Adjusted EBITDA margin) | AL35: 0.01 | AM35: Δ → | AN35: -0.025 | AO35: FY2023 45.5%, FY2024 45.8%, FY2025 46.9%, 1H/26 48.0%; operating leverage on the data estate vs advertising / strategic investment.
B36: Segment Adjusted EBITDA | H36: 191 | M36: 203 | N36: 44 | O36: 49 | P36: 55 | Q36: 49 | R36: 197 | S36: 49 | T36: 53 | U36: =U29*U37 -> 58.799092 | V36: =V29*V37 -> 52.471323 | W36: =SUM(S36:V36) -> 213.27041 | X36: =X29*X37 -> 226.57474 | Y36: =Y29*Y37 -> 241.45427 | Z36: =Z29*Z37 -> 256.0303 | AA36: =AA29*AA37 -> 271.42922 | AB36: =AB29*AB37 -> 286.31906 | AE36: =IFERROR((AB36/W36)^(1/5)-1,"n/m") -> 0.060678896 | AF36: =IFERROR((R36/H36)^(1/2)-1,"n/m") -> 0.015585355 | AG36: =IFERROR(R36/M36-1,"n/m") -> -0.02955665 | AH36: =IFERROR((R36/C36)^(1/3)-1,"n/m") -> n/m | AK36: 2027E | AL36: =AM36+$AL$35 -> 0.49 | AM36: 0.48 | AN36: =AM36+$AN$35 -> 0.455
B37: Segment Adjusted EBITDA margin % | C37: =IF(AND(ISNUMBER(C36),ISNUMBER(C29)),IFERROR(C36/C29,""),"") | D37: =IF(AND(ISNUMBER(D36),ISNUMBER(D29)),IFERROR(D36/D29,""),"") | E37: =IF(AND(ISNUMBER(E36),ISNUMBER(E29)),IFERROR(E36/E29,""),"") | F37: =IF(AND(ISNUMBER(F36),ISNUMBER(F29)),IFERROR(F36/F29,""),"") | G37: =IF(AND(ISNUMBER(G36),ISNUMBER(G29)),IFERROR(G36/G29,""),"") | H37: =IF(AND(ISNUMBER(H36),ISNUMBER(H29)),IFERROR(H36/H29,""),"") -> 0.34290844 | I37: =IF(AND(ISNUMBER(I36),ISNUMBER(I29)),IFERROR(I36/I29,""),"") | J37: =IF(AND(ISNUMBER(J36),ISNUMBER(J29)),IFERROR(J36/J29,""),"") | ... T37: =IF(AND(ISNUMBER(T36),ISNUMBER(T29)),IFERROR(T36/T29,""),"") -> 0.33974359 | U37: =U38+$U$98 -> 0.3609011 | V37: =V38+$U$98 -> 0.31193435 | W37: =IF(AND(ISNUMBER(W36),ISNUMBER(W29)),IFERROR(W36/W29,""),"") -> 0.33109547 | X37: =CHOOSE(MATCH($AC$2,{"Bull","Base","Bear"},0),$AL$42,$AM$42,$AN$42) -> 0.335 | Y37: =CHOOSE(MATCH($AC$2,{"Bull","Base","Bear"},0),$AL$43,$AM$43,$AN$43) -> 0.34 | Z37: =CHOOSE(MATCH($AC$2,{"Bull","Base","Bear"},0),$AL$44,$AM$44,$AN$44) -> 0.345 | AA37: =CHOOSE(MATCH($AC$2,{"Bull","Base","Bear"},0),$AL$45,$AM$45,$AN$45) -> 0.35 | AB37: =CHOOSE(MATCH($AC$2,{"Bull","Base","Bear"},0),$AL$46,$AM$46,$AN$46) -> 0.355 | AE37: =IFERROR(AVERAGE(X37,Y37,Z37,AA37,AB37),"n/m") -> 0.345 | AF37: =IFERROR(AVERAGE(H37,M37,R37),"n/m") -> 0.34019338 | AG37: =IFERROR(AVERAGE(M37,R37),"n/m") -> 0.33883585 | AH37: =IFERROR(AVERAGE(C37,H37,M37,R37),"n/m") -> 0.34019338 | AK37: 2028E | AL37: =AM37+$AL$35 -> 0.495 | AM37: 0.485 | AN37: =AM37+$AN$35 -> 0.46
B38: Q3/Q4-26E margin before calibration (prior-year quarter + 1H/26 y/y drift) | U38: =P37+((S36+T36)/(S29+T29)-(N36+O36)/(N29+O29)) -> 0.36776721 | V38: =Q37+((S36+T36)/(S29+T29)-(N36+O36)/(N29+O29)) -> 0.31880046 | AK38: 2029E | AL38: =AM38+$AL$35 -> 0.5 | AM38: 0.49 | AN38: =AM38+$AN$35 -> 0.465
B39: Segment operating profit (GAAP) | H39: 61 | M39: 69 | N39: 14 | O39: 16 | P39: 23 | Q39: 9 | R39: 62 | S39: 5 | T39: 3 | AK39: 2030E | AL39: =AM39+$AL$35 -> 0.505 | AM39: 0.495 | AN39: =AM39+$AN$35 -> 0.47
B40: Segment D&A (memo) | H40: 110 | M40: 111 | N40: 28 | O40: 27 | P40: 27 | Q40: 30 | R40: 112 | S40: 28 | T40: 27 | AK40: 2031E | AL40: =AM40+$AL$35 -> 0.51 | AM40: 0.5 | AN40: =AM40+$AN$35 -> 0.475
B41: Segment stock-based compensation (memo) | H41: 6 | M41: 10 | N41: 2 | O41: 2 | P41: 3 | Q41: 2 | R41: 9 | S41: 3 | T41: 3 | AK41: B2B_M (B2B Segment Adjusted EBITDA margin) | AL41: 0.015 | AM41: Δ → | AN41: -0.03 | AO41: FY2023 34.3%, FY2024 35.4%, FY2025 32.4% (2025 allocation refinement), 1H/26 32.6%; "One Mobility Global" integration and AI workflow savings.
B42: Segment transaction costs, severance & other items (memo) | H42: 14 | M42: 13 | N42: 0 | O42: 4 | P42: 2 | Q42: 8 | R42: 14 | S42: 13 | T42: 20 | AK42: 2027E | AL42: =AM42+$AL$41 -> 0.35 | AM42: 0.335 | AN42: =AM42+$AN$41 -> 0.305
B43: Check: segment OP + D&A + SBC + items vs Segment Adjusted EBITDA (should be 0; ±1 rounding) | C43: =IF(AND(ISNUMBER(C39),ISNUMBER(C36)),IF(ABS(C39+C40+N(C41)+N(C42)-C36)<=1,0,C39+C40+N(C41)+N(C42)-C36),"") | D43: =IF(AND(ISNUMBER(D39),ISNUMBER(D36)),IF(ABS(D39+D40+N(D41)+N(D42)-D36)<=1,0,D39+D40+N(D41)+N(D42)-D36),"") | E43: =IF(AND(ISNUMBER(E39),ISNUMBER(E36)),IF(ABS(E39+E40+N(E41)+N(E42)-E36)<=1,0,E39+E40+N(E41)+N(E42)-E36),"") | F43: =IF(AND(ISNUMBER(F39),ISNUMBER(F36)),IF(ABS(F39+F40+N(F41)+N(F42)-F36)<=1,0,F39+F40+N(F41)+N(F42)-F36),"") | G43: =IF(AND(ISNUMBER(G39),ISNUMBER(G36)),IF(ABS(G39+G40+N(G41)+N(G42)-G36)<=1,0,G39+G40+N(G41)+N(G42)-G36),"") | H43: =IF(AND(ISNUMBER(H39),ISNUMBER(H36)),IF(ABS(H39+H40+N(H41)+N(H42)-H36)<=1,0,H39+H40+N(H41)+N(H42)-H36),"") -> 0 | I43: =IF(AND(ISNUMBER(I39),ISNUMBER(I36)),IF(ABS(I39+I40+N(I41)+N(I42)-I36)<=1,0,I39+I40+N(I41)+N(I42)-I36),"") | J43: =IF(AND(ISNUMBER(J39),ISNUMBER(J36)),IF(ABS(J39+J40+N(J41)+N(J42)-J36)<=1,0,J39+J40+N(J41)+N(J42)-J36),"") | ... T43: =IF(AND(ISNUMBER(T39),ISNUMBER(T36)),IF(ABS(T39+T40+N(T41)+N(T42)-T36)<=1,0,T39+T40+N(T41)+N(T42)-T36),"") -> 0 | AK43: 2028E | AL43: =AM43+$AL$41 -> 0.355 | AM43: 0.34 | AN43: =AM43+$AN$41 -> 0.31
B44: Segment Adjusted operating profit (company; Form 10 periods) | H44: 181 | M44: 189 | N44: 41 | R44: 183 | S44: 45 | AK44: 2029E | AL44: =AM44+$AL$41 -> 0.36 | AM44: 0.345 | AN44: =AM44+$AN$41 -> 0.315
AK45: 2030E | AL45: =AM45+$AL$41 -> 0.365 | AM45: 0.35 | AN45: =AM45+$AN$41 -> 0.32
B46: Corporate (unallocated expense: corporate functions, select initiatives, unoccupied space; separation costs) | AC46: CORPORATE — modelling logic (carve-out allocations to 30-Jun-2026; standalone public-company costs from Q3-26) | AK46: 2031E | AL46: =AM46+$AL$41 -> 0.37 | AM46: 0.355 | AN46: =AM46+$AN$41 -> 0.325
B47: Corporate operating profit (GAAP) | H47: -32 | M47: -30 | N47: -7 | O47: -9 | P47: -11 | Q47: -18 | R47: -45 | S47: -13 | T47: -22 | AK47: M&A_spend (tuck-in acquisitions, $m) | AL47: 100 | AM47: Δ → | AN47: 0 | AO47: None announced; the Form 10 cites inorganic opportunities in a fragmented industry (Market Scan Feb-2023, $214m). Base nil; Bull $100m p.a. (assumption).
B48: Corporate transaction costs, severance & other items (memo) | H48: 16 | M48: 10 | N48: 2 | O48: 6 | P48: 1 | Q48: 14 | R48: 23 | S48: 8 | T48: 18 | AK48: 2027E | AL48: =MAX(0,AM48+$AL$47) -> 100 | AM48: 0 | AN48: =MAX(0,AM48+$AN$47) -> 0
B49: Corporate Adjusted EBITDA | H49: -16 | M49: -20 | N49: -5 | O49: -3 | P49: -10 | Q49: -4 | R49: -22 | S49: -5 | T49: -4 | U49: -12 | V49: -12 | W49: =SUM(S49:V49) -> -33 | X49: =X85*X50 -> -48.201022 | Y49: =Y85*Y50 -> -49.360108 | Z49: =Z85*Z50 -> -50.286362 | AA49: =AA85*AA50 -> -51.035883 | AB49: =AB85*AB50 -> -51.542688 | AC49: History: corporate unallocated (S&P Global allocations; FY2025 −$22m, 1H/26 −$9m). Q3/Q4-26E input (assumption): −$12m a quarter = 1H/26 run-rate (−$4.5m) + standalone public-company costs. The Form 10 pro forma quantifies only $12m p.a. (TSA $3m + new corporate leases $9m); the rest (board, audit, investor relations, treasury, insurance) is an assumption. 2027E+: % of revenue. | AK49: 2028E | AL49: =MAX(0,AM49+$AL$47) -> 100 | AM49: 0 | AN49: =MAX(0,AM49+$AN$47) -> 0
B50: Corporate Adjusted EBITDA % of revenue | C50: =IF(AND(ISNUMBER(C49),ISNUMBER(C85)),IFERROR(C49/C85,""),"") | D50: =IF(AND(ISNUMBER(D49),ISNUMBER(D85)),IFERROR(D49/D85,""),"") | E50: =IF(AND(ISNUMBER(E49),ISNUMBER(E85)),IFERROR(E49/E85,""),"") | F50: =IF(AND(ISNUMBER(F49),ISNUMBER(F85)),IFERROR(F49/F85,""),"") | G50: =IF(AND(ISNUMBER(G49),ISNUMBER(G85)),IFERROR(G49/G85,""),"") | H50: =IF(AND(ISNUMBER(H49),ISNUMBER(H85)),IFERROR(H49/H85,""),"") -> -0.010774411 | I50: =IF(AND(ISNUMBER(I49),ISNUMBER(I85)),IFERROR(I49/I85,""),"") | J50: =IF(AND(ISNUMBER(J49),ISNUMBER(J85)),IFERROR(J49/J85,""),"") | ... W50: =IF(AND(ISNUMBER(W49),ISNUMBER(W85)),IFERROR(W49/W85,""),"") -> -0.017576565 | X50: -0.024 | Y50: -0.023 | Z50: -0.022 | AA50: -0.021 | AB50: -0.02 | AC50: 2027E+: input (assumption) — full-year standalone corporate cost base. | AE50: =IFERROR(AVERAGE(X50,Y50,Z50,AA50,AB50),"n/m") -> -0.022 | AF50: =IFERROR(AVERAGE(H50,M50,R50),"n/m") -> -0.011915032 | AG50: =IFERROR(AVERAGE(M50,R50),"n/m") -> -0.012485342 | AH50: =IFERROR(AVERAGE(C50,H50,M50,R50),"n/m") -> -0.011915032 | AK50: 2029E | AL50: =MAX(0,AM50+$AL$47) -> 100 | AM50: 0 | AN50: =MAX(0,AM50+$AN$47) -> 0
AK51: 2030E | AL51: =MAX(0,AM51+$AL$47) -> 100 | AM51: 0 | AN51: =MAX(0,AM51+$AN$47) -> 0
B52: S&P Global "Mobility" segment as reported by the former parent (memo; S&P Global CIK 64040) — revenue comparable, profit not | AC52: S&P GLOBAL MOBILITY SEGMENT — memo. Fills the pre-2025 quarters the carve-out never published. Revenue ties to the carve-out within $0–4m (≤0.25%) in every overlapping period → spliced revenue history below. Profit is NOT comparable: S&P Global segment results exclude corporate allocations and stand-up costs, and carry S&P Global's deal amortization ($303m vs $296m). | AK52: 2031E | AL52: =MAX(0,AM52+$AL$47) -> 100 | AM52: 0 | AN52: =MAX(0,AM52+$AN$47) -> 0
B53: S&P Global Mobility revenue (2022 = S&P Global non-GAAP pro forma, full year) | C53: 1351 | D53: 358 | E53: 369 | F53: 379 | G53: 377 | H53: 1484 | I53: 386 | J53: 400 | K53: 412 | L53: 411 | M53: 1609 | N53: 420 | O53: 438 | P53: 445 | Q53: 444 | R53: 1747 | S53: 454 | T53: 468 | AE53: =IFERROR((AB53/W53)^(1/5)-1,"n/m") -> n/m | AF53: =IFERROR((R53/H53)^(1/2)-1,"n/m") -> 0.08499941 | AG53: =IFERROR(R53/M53-1,"n/m") -> 0.085767557 | AH53: =IFERROR((R53/C53)^(1/3)-1,"n/m") -> 0.089463083
B54: y/y % | H54: =IF(AND(ISNUMBER(H53),ISNUMBER(C53)),IFERROR(H53/C53-1,""),"") -> 0.098445596 | I54: =IF(AND(ISNUMBER(I53),ISNUMBER(D53)),IFERROR(I53/D53-1,""),"") -> 0.078212291 | J54: =IF(AND(ISNUMBER(J53),ISNUMBER(E53)),IFERROR(J53/E53-1,""),"") -> 0.08401084 | K54: =IF(AND(ISNUMBER(K53),ISNUMBER(F53)),IFERROR(K53/F53-1,""),"") -> 0.08707124 | L54: =IF(AND(ISNUMBER(L53),ISNUMBER(G53)),IFERROR(L53/G53-1,""),"") -> 0.090185676 | M54: =IF(AND(ISNUMBER(M53),ISNUMBER(H53)),IFERROR(M53/H53-1,""),"") -> 0.084231806 | N54: =IF(AND(ISNUMBER(N53),ISNUMBER(I53)),IFERROR(N53/I53-1,""),"") -> 0.088082902 | O54: =IF(AND(ISNUMBER(O53),ISNUMBER(J53)),IFERROR(O53/J53-1,""),"") -> 0.095 | ... W54: =IF(AND(ISNUMBER(W53),ISNUMBER(R53)),IFERROR(W53/R53-1,""),"") | X54: =IF(AND(ISNUMBER(X53),ISNUMBER(W53)),IFERROR(X53/W53-1,""),"") | Y54: =IF(AND(ISNUMBER(Y53),ISNUMBER(X53)),IFERROR(Y53/X53-1,""),"") | Z54: =IF(AND(ISNUMBER(Z53),ISNUMBER(Y53)),IFERROR(Z53/Y53-1,""),"") | AA54: =IF(AND(ISNUMBER(AA53),ISNUMBER(Z53)),IFERROR(AA53/Z53-1,""),"") | AB54: =IF(AND(ISNUMBER(AB53),ISNUMBER(AA53)),IFERROR(AB53/AA53-1,""),"") | AE54: =IFERROR(AVERAGE(X54,Y54,Z54,AA54,AB54),"n/m") -> n/m | AF54: =IFERROR(AVERAGE(H54,M54,R54),"n/m") -> 0.089481653 | AG54: =IFERROR(AVERAGE(M54,R54),"n/m") -> 0.084999682 | AH54: =IFERROR(AVERAGE(C54,H54,M54,R54),"n/m") -> 0.089481653
B55: Subscription revenue | D55: 281 | E55: 292 | F55: 296 | G55: 299 | H55: 1169 | I55: 311 | J55: 323 | K55: 331 | L55: 333 | M55: 1299 | N55: 343 | O55: 357 | P55: 362 | Q55: 361 | R55: 1422 | S55: 372 | T55: 383
B56: Non-subscription revenue | D56: 77 | E56: 77 | F56: 83 | G56: 78 | H56: 315 | I56: 75 | J56: 77 | K56: 81 | L56: 78 | M56: 310 | N56: 77 | O56: 81 | P56: 83 | Q56: 83 | R56: 325 | S56: 82 | T56: 85
B57: S&P Global Mobility operating profit (GAAP segment; 2022 pro forma) | C57: 250 | D57: 64 | E57: 68 | F57: 80 | G57: 46 | H57: 260 | I57: 70 | J57: 80 | K57: 97 | L57: 65 | M57: 312 | N57: 86 | O57: 104 | P57: 117 | Q57: 71 | R57: 378 | S57: 93 | T57: 104
B58: + Non-GAAP adjustments (excl. deal amortization) | D58: 2 | E58: 4 | F58: 4 | G58: 5 | H58: 15 | I58: 1 | J58: 8 | K58: 1 | L58: 2 | M58: 12 | N58: 0 | O58: 5 | P58: 0 | Q58: 10 | R58: 15 | S58: 13
B59: + Deal-related amortization | D59: 74 | E59: 76 | F59: 76 | G59: 76 | H59: 301 | I59: 76 | J59: 76 | K59: 76 | L59: 76 | M59: 303 | N59: 76 | O59: 76 | P59: 76 | Q59: 76 | R59: 303 | S59: 76
B60: S&P Global Mobility adjusted operating profit | D60: 140 | E60: 149 | F60: 160 | G60: 127 | H60: 576 | I60: 147 | J60: 164 | K60: 174 | L60: 143 | M60: 627 | N60: 162 | O60: 185 | P60: 193 | Q60: 157 | R60: 697 | S60: 182 | AE60: =IFERROR((AB60/W60)^(1/5)-1,"n/m") -> n/m | AF60: =IFERROR((R60/H60)^(1/2)-1,"n/m") -> 0.10003157 | AG60: =IFERROR(R60/M60-1,"n/m") -> 0.11164274 | AH60: =IFERROR((R60/C60)^(1/3)-1,"n/m") -> n/m
B61: Adjusted operating margin % | C61: =IF(AND(ISNUMBER(C60),ISNUMBER(C53)),IFERROR(C60/C53,""),"") | D61: =IF(AND(ISNUMBER(D60),ISNUMBER(D53)),IFERROR(D60/D53,""),"") -> 0.39106145 | E61: =IF(AND(ISNUMBER(E60),ISNUMBER(E53)),IFERROR(E60/E53,""),"") -> 0.40379404 | F61: =IF(AND(ISNUMBER(F60),ISNUMBER(F53)),IFERROR(F60/F53,""),"") -> 0.42216359 | G61: =IF(AND(ISNUMBER(G60),ISNUMBER(G53)),IFERROR(G60/G53,""),"") -> 0.33687003 | H61: =IF(AND(ISNUMBER(H60),ISNUMBER(H53)),IFERROR(H60/H53,""),"") -> 0.38814016 | I61: =IF(AND(ISNUMBER(I60),ISNUMBER(I53)),IFERROR(I60/I53,""),"") -> 0.38082902 | J61: =IF(AND(ISNUMBER(J60),ISNUMBER(J53)),IFERROR(J60/J53,""),"") -> 0.41 | ... AB61: =IF(AND(ISNUMBER(AB60),ISNUMBER(AB53)),IFERROR(AB60/AB53,""),"") | AE61: =IFERROR(AVERAGE(X61,Y61,Z61,AA61,AB61),"n/m") -> n/m | AF61: =IFERROR(AVERAGE(H61,M61,R61),"n/m") -> 0.39226429 | AG61: =IFERROR(AVERAGE(M61,R61),"n/m") -> 0.39432635 | AH61: =IFERROR(AVERAGE(C61,H61,M61,R61),"n/m") -> 0.39226429
B62: Check: S&P Global OP + adjustments + amortization vs adjusted OP (should be 0; ±1 S&P Global rounding) | C62: =IF(AND(ISNUMBER(C58),ISNUMBER(C60)),IF(ABS(C57+C58+C59-C60)<=1,0,C57+C58+C59-C60),"") | D62: =IF(AND(ISNUMBER(D58),ISNUMBER(D60)),IF(ABS(D57+D58+D59-D60)<=1,0,D57+D58+D59-D60),"") -> 0 | E62: =IF(AND(ISNUMBER(E58),ISNUMBER(E60)),IF(ABS(E57+E58+E59-E60)<=1,0,E57+E58+E59-E60),"") -> 0 | F62: =IF(AND(ISNUMBER(F58),ISNUMBER(F60)),IF(ABS(F57+F58+F59-F60)<=1,0,F57+F58+F59-F60),"") -> 0 | G62: =IF(AND(ISNUMBER(G58),ISNUMBER(G60)),IF(ABS(G57+G58+G59-G60)<=1,0,G57+G58+G59-G60),"") -> 0 | H62: =IF(AND(ISNUMBER(H58),ISNUMBER(H60)),IF(ABS(H57+H58+H59-H60)<=1,0,H57+H58+H59-H60),"") -> 0 | I62: =IF(AND(ISNUMBER(I58),ISNUMBER(I60)),IF(ABS(I57+I58+I59-I60)<=1,0,I57+I58+I59-I60),"") -> 0 | J62: =IF(AND(ISNUMBER(J58),ISNUMBER(J60)),IF(ABS(J57+J58+J59-J60)<=1,0,J57+J58+J59-J60),"") -> 0 | ... T62: =IF(AND(ISNUMBER(T58),ISNUMBER(T60)),IF(ABS(T57+T58+T59-T60)<=1,0,T57+T58+T59-T60),"")
B63: Basis difference: carve-out revenue − S&P Global segment revenue (information) | C63: =IF(AND(ISNUMBER(C115),ISNUMBER(C53)),C115-C53,"") | D63: =IF(AND(ISNUMBER(D115),ISNUMBER(D53)),D115-D53,"") | E63: =IF(AND(ISNUMBER(E115),ISNUMBER(E53)),E115-E53,"") | F63: =IF(AND(ISNUMBER(F115),ISNUMBER(F53)),F115-F53,"") | G63: =IF(AND(ISNUMBER(G115),ISNUMBER(G53)),G115-G53,"") | H63: =IF(AND(ISNUMBER(H115),ISNUMBER(H53)),H115-H53,"") -> 1 | I63: =IF(AND(ISNUMBER(I115),ISNUMBER(I53)),I115-I53,"") | J63: =IF(AND(ISNUMBER(J115),ISNUMBER(J53)),J115-J53,"") | ... T63: =IF(AND(ISNUMBER(T115),ISNUMBER(T53)),T115-T53,"") -> 0 | AC63: Carve-out revenue exceeds the S&P Global segment by $0–4m (FY23 +1, FY24 +4, FY25 +3; Q4-25 +2): rounding and minor intercompany items.
B64: as % of revenue | C64: =IF(ISNUMBER(C63),C63/C115,"") | D64: =IF(ISNUMBER(D63),D63/D115,"") | E64: =IF(ISNUMBER(E63),E63/E115,"") | F64: =IF(ISNUMBER(F63),F63/F115,"") | G64: =IF(ISNUMBER(G63),G63/G115,"") | H64: =IF(ISNUMBER(H63),H63/H115,"") -> 0.00067340067 | I64: =IF(ISNUMBER(I63),I63/I115,"") | J64: =IF(ISNUMBER(J63),J63/J115,"") | ... T64: =IF(ISNUMBER(T63),T63/T115,"") -> 0
B65: Carve-out segment Adjusted OP (CARFAX + B2B, before corporate) − S&P Global adjusted OP (information) | C65: =IF(AND(ISNUMBER(C26),ISNUMBER(C60)),C26+C44-C60,"") | D65: =IF(AND(ISNUMBER(D26),ISNUMBER(D60)),D26+D44-D60,"") | E65: =IF(AND(ISNUMBER(E26),ISNUMBER(E60)),E26+E44-E60,"") | F65: =IF(AND(ISNUMBER(F26),ISNUMBER(F60)),F26+F44-F60,"") | G65: =IF(AND(ISNUMBER(G26),ISNUMBER(G60)),G26+G44-G60,"") | H65: =IF(AND(ISNUMBER(H26),ISNUMBER(H60)),H26+H44-H60,"") -> 5 | I65: =IF(AND(ISNUMBER(I26),ISNUMBER(I60)),I26+I44-I60,"") | J65: =IF(AND(ISNUMBER(J26),ISNUMBER(J60)),J26+J44-J60,"") | ... T65: =IF(AND(ISNUMBER(T26),ISNUMBER(T60)),T26+T44-T60,"") | AC65: FY2025: 0 (514 + 183 = 697, the 2025 allocation methodology matches); FY2023 +5 and FY2024 +11 (segment cost allocations refined in 2025). Corporate unallocated cost sits outside both.
B66: Revenue — spliced history (carve-out where filed, S&P Global segment otherwise) | C66: =IF(ISNUMBER(C115),C115,IF(ISNUMBER(C53),C53,"")) -> 1351 | D66: =IF(ISNUMBER(D115),D115,IF(ISNUMBER(D53),D53,"")) -> 358 | E66: =IF(ISNUMBER(E115),E115,IF(ISNUMBER(E53),E53,"")) -> 369 | F66: =IF(ISNUMBER(F115),F115,IF(ISNUMBER(F53),F53,"")) -> 379 | G66: =IF(ISNUMBER(G115),G115,IF(ISNUMBER(G53),G53,"")) -> 377 | H66: =IF(ISNUMBER(H115),H115,IF(ISNUMBER(H53),H53,"")) -> 1485 | I66: =IF(ISNUMBER(I115),I115,IF(ISNUMBER(I53),I53,"")) -> 386 | J66: =IF(ISNUMBER(J115),J115,IF(ISNUMBER(J53),J53,"")) -> 400 | ... T66: =IF(ISNUMBER(T115),T115,IF(ISNUMBER(T53),T53,"")) -> 468 | U66: =U115 -> 476.76212 | V66: =V115 -> 477.73788 | W66: =W115 -> 1877.5 | X66: =X115 -> 2008.3759 | Y66: =Y115 -> 2146.0917 | Z66: =Z115 -> 2285.7437 | AA66: =AA115 -> 2430.2801 | AB66: =AB115 -> 2577.1344 | AC66: Comparable revenue series for growth analysis: FY2022 (pro forma) and Q1-23 – Q4-24 from S&P Global (black = formula on the memo rows); carve-out thereafter. | AE66: =IFERROR((AB66/W66)^(1/5)-1,"n/m") -> 0.065396889 | AF66: =IFERROR((R66/H66)^(1/2)-1,"n/m") -> 0.085564912 | AG66: =IFERROR(R66/M66-1,"n/m") -> 0.084934904 | AH66: =IFERROR((R66/C66)^(1/3)-1,"n/m") -> 0.090086346
B67: y/y % (spliced) | H67: =IF(AND(ISNUMBER(H66),ISNUMBER(C66)),IFERROR(H66/C66-1,""),"") -> 0.099185788 | I67: =IF(AND(ISNUMBER(I66),ISNUMBER(D66)),IFERROR(I66/D66-1,""),"") -> 0.078212291 | J67: =IF(AND(ISNUMBER(J66),ISNUMBER(E66)),IFERROR(J66/E66-1,""),"") -> 0.08401084 | K67: =IF(AND(ISNUMBER(K66),ISNUMBER(F66)),IFERROR(K66/F66-1,""),"") -> 0.08707124 | L67: =IF(AND(ISNUMBER(L66),ISNUMBER(G66)),IFERROR(L66/G66-1,""),"") -> 0.090185676 | M67: =IF(AND(ISNUMBER(M66),ISNUMBER(H66)),IFERROR(M66/H66-1,""),"") -> 0.086195286 | N67: =IF(AND(ISNUMBER(N66),ISNUMBER(I66)),IFERROR(N66/I66-1,""),"") -> 0.088082902 | O67: =IF(AND(ISNUMBER(O66),ISNUMBER(J66)),IFERROR(O66/J66-1,""),"") -> 0.0975 | ... W67: =IF(AND(ISNUMBER(W66),ISNUMBER(R66)),IFERROR(W66/R66-1,""),"") -> 0.072857143 | X67: =IF(AND(ISNUMBER(X66),ISNUMBER(W66)),IFERROR(X66/W66-1,""),"") -> 0.069707552 | Y67: =IF(AND(ISNUMBER(Y66),ISNUMBER(X66)),IFERROR(Y66/X66-1,""),"") -> 0.068570695 | Z67: =IF(AND(ISNUMBER(Z66),ISNUMBER(Y66)),IFERROR(Z66/Y66-1,""),"") -> 0.06507275 | AA67: =IF(AND(ISNUMBER(AA66),ISNUMBER(Z66)),IFERROR(AA66/Z66-1,""),"") -> 0.063233858 | AB67: =IF(AND(ISNUMBER(AB66),ISNUMBER(AA66)),IFERROR(AB66/AA66-1,""),"") -> 0.060426881 | AE67: =IFERROR(AVERAGE(X67,Y67,Z67,AA67,AB67),"n/m") -> 0.065402347 | AF67: =IFERROR(AVERAGE(H67,M67,R67),"n/m") -> 0.090105326 | AG67: =IFERROR(AVERAGE(M67,R67),"n/m") -> 0.085565095 | AH67: =IFERROR(AVERAGE(C67,H67,M67,R67),"n/m") -> 0.090105326
B68: Basis of the spliced series | C68: S&P Global pro forma (full year) | D68: S&P Global segment (2023–24 quarters) | H68: Carve-out (Form 10) | N68: Carve-out (Form 10 / 10-Q / Ex. 99.2)
B70: Future acquisitions (M&A lever — tuck-ins; none announced) | AC70: M&A LEVER — acquired revenue = spend ÷ EV/sales; mid-year convention
B71: Acquisition spend (USDm, scenario) | W71: 0 | X71: =MAX(0,CHOOSE(MATCH($AC$2,{"Bull","Base","Bear"},0),$AL$48,$AM$48,$AN$48)) -> 0 | Y71: =MAX(0,CHOOSE(MATCH($AC$2,{"Bull","Base","Bear"},0),$AL$49,$AM$49,$AN$49)) -> 0 | Z71: =MAX(0,CHOOSE(MATCH($AC$2,{"Bull","Base","Bear"},0),$AL$50,$AM$50,$AN$50)) -> 0 | AA71: =MAX(0,CHOOSE(MATCH($AC$2,{"Bull","Base","Bear"},0),$AL$51,$AM$51,$AN$51)) -> 0 | AB71: =MAX(0,CHOOSE(MATCH($AC$2,{"Bull","Base","Bear"},0),$AL$52,$AM$52,$AN$52)) -> 0 | AC71: Scenario lever M&A_spend (Base nil; no acquisitions announced). Funded from cash / revolver (debt schedule).
B72: Purchase multiple — EV / revenue (x) | W72: 0 | X72: 5 | Y72: 5 | Z72: 5 | AA72: 5 | AB72: 5 | AC72: Assumption: data / software tuck-ins at ~5x revenue (Market Scan, Feb-2023: $214m cash).
B73: Annualised revenue acquired in the year | W73: 0 | X73: =IFERROR(X71/X72,0) -> 0 | Y73: =IFERROR(Y71/Y72,0) -> 0 | Z73: =IFERROR(Z71/Z72,0) -> 0 | AA73: =IFERROR(AA71/AA72,0) -> 0 | AB73: =IFERROR(AB71/AB72,0) -> 0
B74: Growth of acquired businesses after acquisition % | W74: 0 | X74: 0.06 | Y74: 0.06 | Z74: 0.06 | AA74: 0.06 | AB74: 0.06
B75: Run-rate revenue of businesses acquired (year end) | W75: 0 | X75: =W75*(1+X74)+X73 -> 0 | Y75: =X75*(1+Y74)+Y73 -> 0 | Z75: =Y75*(1+Z74)+Z73 -> 0 | AA75: =Z75*(1+AA74)+AA73 -> 0 | AB75: =AA75*(1+AB74)+AB73 -> 0
B76: Revenue from future acquisitions | W76: 0 | X76: =W75*(1+X74)+0.5*X73 -> 0 | Y76: =X75*(1+Y74)+0.5*Y73 -> 0 | Z76: =Y75*(1+Z74)+0.5*Z73 -> 0 | AA76: =Z75*(1+AA74)+0.5*AA73 -> 0 | AB76: =AA75*(1+AB74)+0.5*AB73 -> 0 | AC76: Mid-year convention. Unallocated to segments (separate line in the group build).
B77: Adjusted EBITDA margin of acquired businesses % | W77: 0 | X77: 0.3 | Y77: 0.3 | Z77: 0.3 | AA77: 0.3 | AB77: 0.3 | AC77: Assumption (B2B-like margin).
B78: Adjusted EBITDA from future acquisitions | W78: 0 | X78: =X76*X77 -> 0 | Y78: =Y76*Y77 -> 0 | Z78: =Z76*Z77 -> 0 | AA78: =AA76*AA77 -> 0 | AB78: =AB76*AB77 -> 0
B79: Acquired intangibles % of spend | W79: 0 | X79: 0.4 | Y79: 0.4 | Z79: 0.4 | AA79: 0.4 | AB79: 0.4 | AC79: Market Scan: $87m intangibles (customer relationships $81m / 20y, trade names $6m / 7y).
B80: Intangible amortization life (years) | W80: 0 | X80: 15 | Y80: 15 | Z80: 15 | AA80: 15 | AB80: 15
B81: Cumulative acquired intangibles (gross) | W81: 0 | X81: =W81+X71*X79 -> 0 | Y81: =X81+Y71*Y79 -> 0 | Z81: =Y81+Z71*Z79 -> 0 | AA81: =Z81+AA71*AA79 -> 0 | AB81: =AA81+AB71*AB79 -> 0
B82: Amortization of future-acquisition intangibles | W82: 0 | X82: =IFERROR((W81+0.5*X71*X79)/X80,0) -> 0 | Y82: =IFERROR((X81+0.5*Y71*Y79)/Y80,0) -> 0 | Z82: =IFERROR((Y81+0.5*Z71*Z79)/Z80,0) -> 0 | AA82: =IFERROR((Z81+0.5*AA71*AA79)/AA80,0) -> 0 | AB82: =IFERROR((AA81+0.5*AB71*AB79)/AB80,0) -> 0
B84: Group total — revenue & Adjusted EBITDA (segment build) → FY26 outlook calibration | AC84: GROUP TOTAL — modelling logic
B85: Revenue (segment build) | C85: =IF(ISNUMBER(C11),C11+C29,"") | D85: =IF(ISNUMBER(D11),D11+D29,"") | E85: =IF(ISNUMBER(E11),E11+E29,"") | F85: =IF(ISNUMBER(F11),F11+F29,"") | G85: =IF(ISNUMBER(G11),G11+G29,"") | H85: =IF(ISNUMBER(H11),H11+H29,"") -> 1485 | I85: =IF(ISNUMBER(I11),I11+I29,"") | J85: =IF(ISNUMBER(J11),J11+J29,"") | ... T85: =IF(ISNUMBER(T11),T11+T29,"") -> 468 | U85: =U11+U29+N(U76) -> 476.76212 | V85: =V11+V29+N(V76) -> 477.73788 | W85: =W11+W29+N(W76) -> 1877.5 | X85: =X11+X29+N(X76) -> 2008.3759 | Y85: =Y11+Y29+N(Y76) -> 2146.0917 | Z85: =Z11+Z29+N(Z76) -> 2285.7437 | AA85: =AA11+AA29+N(AA76) -> 2430.2801 | AB85: =AB11+AB29+N(AB76) -> 2577.1344 | AC85: CARFAX + B2B (+ future acquisitions from 2027E). | AE85: =IFERROR((AB85/W85)^(1/5)-1,"n/m") -> 0.065396889 | AF85: =IFERROR((R85/H85)^(1/2)-1,"n/m") -> 0.085564912 | AG85: =IFERROR(R85/M85-1,"n/m") -> 0.084934904 | AH85: =IFERROR((R85/C85)^(1/3)-1,"n/m") -> n/m
B86: Revenue y/y % | H86: =IF(AND(ISNUMBER(H85),ISNUMBER(C85)),IFERROR(H85/C85-1,""),"") | I86: =IF(AND(ISNUMBER(I85),ISNUMBER(D85)),IFERROR(I85/D85-1,""),"") | J86: =IF(AND(ISNUMBER(J85),ISNUMBER(E85)),IFERROR(J85/E85-1,""),"") | K86: =IF(AND(ISNUMBER(K85),ISNUMBER(F85)),IFERROR(K85/F85-1,""),"") | L86: =IF(AND(ISNUMBER(L85),ISNUMBER(G85)),IFERROR(L85/G85-1,""),"") | M86: =IF(AND(ISNUMBER(M85),ISNUMBER(H85)),IFERROR(M85/H85-1,""),"") -> 0.086195286 | N86: =IF(AND(ISNUMBER(N85),ISNUMBER(I85)),IFERROR(N85/I85-1,""),"") | O86: =IF(AND(ISNUMBER(O85),ISNUMBER(J85)),IFERROR(O85/J85-1,""),"") | ... W86: =IF(AND(ISNUMBER(W85),ISNUMBER(R85)),IFERROR(W85/R85-1,""),"") -> 0.072857143 | X86: =IF(AND(ISNUMBER(X85),ISNUMBER(W85)),IFERROR(X85/W85-1,""),"") -> 0.069707552 | Y86: =IF(AND(ISNUMBER(Y85),ISNUMBER(X85)),IFERROR(Y85/X85-1,""),"") -> 0.068570695 | Z86: =IF(AND(ISNUMBER(Z85),ISNUMBER(Y85)),IFERROR(Z85/Y85-1,""),"") -> 0.06507275 | AA86: =IF(AND(ISNUMBER(AA85),ISNUMBER(Z85)),IFERROR(AA85/Z85-1,""),"") -> 0.063233858 | AB86: =IF(AND(ISNUMBER(AB85),ISNUMBER(AA85)),IFERROR(AB85/AA85-1,""),"") -> 0.060426881
B87: Check: segment build vs consolidated revenue (should be 0) | C87: =IF(AND(ISNUMBER(C85),ISNUMBER(C115)),ROUND(C85-C115,1),"") | D87: =IF(AND(ISNUMBER(D85),ISNUMBER(D115)),ROUND(D85-D115,1),"") | E87: =IF(AND(ISNUMBER(E85),ISNUMBER(E115)),ROUND(E85-E115,1),"") | F87: =IF(AND(ISNUMBER(F85),ISNUMBER(F115)),ROUND(F85-F115,1),"") | G87: =IF(AND(ISNUMBER(G85),ISNUMBER(G115)),ROUND(G85-G115,1),"") | H87: =IF(AND(ISNUMBER(H85),ISNUMBER(H115)),ROUND(H85-H115,1),"") -> 0 | I87: =IF(AND(ISNUMBER(I85),ISNUMBER(I115)),ROUND(I85-I115,1),"") | J87: =IF(AND(ISNUMBER(J85),ISNUMBER(J115)),ROUND(J85-J115,1),"") | ... AB87: =IF(AND(ISNUMBER(AB85),ISNUMBER(AB115)),ROUND(AB85-AB115,1),"") -> 0
B88: Adjusted EBITDA (segment build) | C88: =IF(ISNUMBER(C18),C18+C36+C49,"") | D88: =IF(ISNUMBER(D18),D18+D36+D49,"") | E88: =IF(ISNUMBER(E18),E18+E36+E49,"") | F88: =IF(ISNUMBER(F18),F18+F36+F49,"") | G88: =IF(ISNUMBER(G18),G18+G36+G49,"") | H88: =IF(ISNUMBER(H18),H18+H36+H49,"") -> 597 | I88: =IF(ISNUMBER(I18),I18+I36+I49,"") | J88: =IF(ISNUMBER(J18),J18+J36+J49,"") | ... T88: =IF(ISNUMBER(T18),T18+T36+T49,"") -> 202 | U88: =U18+U36+U49+N(U78) -> 201.49368 | V88: =V18+V36+V49+N(V78) -> 165.00632 | W88: =W18+W36+W49+N(W78) -> 752.5 | X88: =X18+X36+X49+N(X78) -> 817.74976 | Y88: =Y18+Y36+Y49+N(Y78) -> 888.5212 | Z88: =Z18+Z36+Z49+N(Z78) -> 962.12114 | AA88: =AA18+AA36+AA49+N(AA78) -> 1039.5035 | AB88: =AB18+AB36+AB49+N(AB78) -> 1120.0773 | AC88: Mobility Global's guided profit KPI. CARFAX + B2B + Corporate Segment Adjusted EBITDA (+ future acquisitions). Drives the GAAP P&L below. | AE88: =IFERROR((AB88/W88)^(1/5)-1,"n/m") -> 0.082800125 | AF88: =IFERROR((R88/H88)^(1/2)-1,"n/m") -> 0.091308744 | AG88: =IFERROR(R88/M88-1,"n/m") -> 0.078907436 | AH88: =IFERROR((R88/C88)^(1/3)-1,"n/m") -> n/m
B89: Adjusted EBITDA margin % | C89: =IF(AND(ISNUMBER(C88),ISNUMBER(C85)),IFERROR(C88/C85,""),"") | D89: =IF(AND(ISNUMBER(D88),ISNUMBER(D85)),IFERROR(D88/D85,""),"") | E89: =IF(AND(ISNUMBER(E88),ISNUMBER(E85)),IFERROR(E88/E85,""),"") | F89: =IF(AND(ISNUMBER(F88),ISNUMBER(F85)),IFERROR(F88/F85,""),"") | G89: =IF(AND(ISNUMBER(G88),ISNUMBER(G85)),IFERROR(G88/G85,""),"") | H89: =IF(AND(ISNUMBER(H88),ISNUMBER(H85)),IFERROR(H88/H85,""),"") -> 0.4020202 | I89: =IF(AND(ISNUMBER(I88),ISNUMBER(I85)),IFERROR(I88/I85,""),"") | J89: =IF(AND(ISNUMBER(J88),ISNUMBER(J85)),IFERROR(J88/J85,""),"") | ... AB89: =IF(AND(ISNUMBER(AB88),ISNUMBER(AB85)),IFERROR(AB88/AB85,""),"") -> 0.43462122 | AE89: =IFERROR(AVERAGE(X89,Y89,Z89,AA89,AB89),"n/m") -> 0.42089233 | AF89: =IFERROR(AVERAGE(H89,M89,R89),"n/m") -> 0.40562047 | AG89: =IFERROR(AVERAGE(M89,R89),"n/m") -> 0.4074206 | AH89: =IFERROR(AVERAGE(C89,H89,M89,R89),"n/m") -> 0.40562047
B90: Check: segment build vs company-published Adjusted EBITDA (should be 0; ±1 rounding) | C90: =IF(AND(ISNUMBER(C88),ISNUMBER(C155)),IF(ABS(C88-C155)<=1,0,C88-C155),"") | D90: =IF(AND(ISNUMBER(D88),ISNUMBER(D155)),IF(ABS(D88-D155)<=1,0,D88-D155),"") | E90: =IF(AND(ISNUMBER(E88),ISNUMBER(E155)),IF(ABS(E88-E155)<=1,0,E88-E155),"") | F90: =IF(AND(ISNUMBER(F88),ISNUMBER(F155)),IF(ABS(F88-F155)<=1,0,F88-F155),"") | G90: =IF(AND(ISNUMBER(G88),ISNUMBER(G155)),IF(ABS(G88-G155)<=1,0,G88-G155),"") | H90: =IF(AND(ISNUMBER(H88),ISNUMBER(H155)),IF(ABS(H88-H155)<=1,0,H88-H155),"") -> 0 | I90: =IF(AND(ISNUMBER(I88),ISNUMBER(I155)),IF(ABS(I88-I155)<=1,0,I88-I155),"") | J90: =IF(AND(ISNUMBER(J88),ISNUMBER(J155)),IF(ABS(J88-J155)<=1,0,J88-J155),"") | ... T90: =IF(AND(ISNUMBER(T88),ISNUMBER(T155)),IF(ABS(T88-T155)<=1,0,T88-T155),"") -> 0 | U90: =ROUND(U88-U153,1) -> 0 | V90: =ROUND(V88-V153,1) -> 0 | W90: =ROUND(W88-W153,1) -> 0 | X90: =ROUND(X88-X153,1) -> 0 | Y90: =ROUND(Y88-Y153,1) -> 0 | Z90: =ROUND(Z88-Z153,1) -> 0 | AA90: =ROUND(AA88-AA153,1) -> 0 | AB90: =ROUND(AB88-AB153,1) -> 0
B91: Memo: FY26 revenue guidance (scenario end-point) | W91: =CHOOSE(MATCH($AC$2,{"Bull","Base","Bear"},0),$AL$12,$AM$12,$AN$12) -> 1877.5 | AC91: Company FY26 revenue guidance $1,870–1,885m (Q2-26 release, 7-Aug-2026). Drives the revenue calibration.
B92: Revenue before calibration (Q3/Q4-26E helper) | U92: =P11*(1+U13)+P29*(1+U31) -> 478.13065 | V92: =Q11*(1+V13)+Q29*(1+V31) -> 479.1095
B93: Revenue sensitivity to +1.00 of growth (Q3/Q4-26E helper) | U93: =P11+P29 -> 445 | V93: =Q11+Q29 -> 446
B94: Outlook calibration: Δ y/y growth applied to both segments (Q3/Q4-26E) | U94: =(W91-S85-T85-U92-V92)/(U93+V93) -> -0.0030753637 | V94: =$U$94 -> -0.0030753637 | AC94: Closed-form solve: uniform growth shift (vs 1H/26 y/y rates) so FY26 revenue = the guidance end-point for the active scenario.
B95: Check: FY26 revenue vs guidance end-point (should be 0) | W95: =ROUND(W85-W91,1) -> 0
B96: Memo: FY26 Adjusted EBITDA guidance (scenario end-point) | W96: =CHOOSE(MATCH($AC$2,{"Bull","Base","Bear"},0),$AL$13,$AM$13,$AN$13) -> 752.5 | AC96: Company FY26 Adjusted EBITDA guidance $745–760m (Q2-26 release). Drives the segment-margin calibration.
B97: Adjusted EBITDA before margin calibration (Q3/Q4-26E helper) | U97: =U11*U20+U29*U38+U49 -> 204.76718 | V97: =V11*V20+V29*V38+V49 -> 168.28653
B98: Outlook calibration: Δ Segment Adjusted EBITDA margin (both segments, Q3/Q4-26E) | U98: =(W96-S88-T88-U97-V97)/(U11+U29+V11+V29) -> -0.0068661101 | V98: =$U$98 -> -0.0068661101 | AC98: Solves the uniform segment-margin shift so FY26 Adjusted EBITDA = the guidance end-point (after the corporate-cost input). Negative = standalone dis-synergies beyond the corporate input.
B99: Check: FY26 Adjusted EBITDA vs guidance end-point (should be 0) | W99: =ROUND(W88-W96,1) -> 0
B100: Memo: FY26 revenue growth guidance (+6.9–7.7%) vs model | W100: =W85/R115-1 -> 0.072857143
B102: Cost drivers, D&A and adjusting items | AC102: COST DRIVERS — inputs that drive forecast cost lines
B103: Operating-related expenses % of revenue | C103: =IF(AND(ISNUMBER(C116),ISNUMBER(C115)),IFERROR(C116/C115,""),"") | D103: =IF(AND(ISNUMBER(D116),ISNUMBER(D115)),IFERROR(D116/D115,""),"") | E103: =IF(AND(ISNUMBER(E116),ISNUMBER(E115)),IFERROR(E116/E115,""),"") | F103: =IF(AND(ISNUMBER(F116),ISNUMBER(F115)),IFERROR(F116/F115,""),"") | G103: =IF(AND(ISNUMBER(G116),ISNUMBER(G115)),IFERROR(G116/G115,""),"") | H103: =IF(AND(ISNUMBER(H116),ISNUMBER(H115)),IFERROR(H116/H115,""),"") -> 0.3016835 | I103: =IF(AND(ISNUMBER(I116),ISNUMBER(I115)),IFERROR(I116/I115,""),"") | J103: =IF(AND(ISNUMBER(J116),ISNUMBER(J115)),IFERROR(J116/J115,""),"") | ... T103: =IF(AND(ISNUMBER(T116),ISNUMBER(T115)),IFERROR(T116/T115,""),"") -> 0.28632479 | U103: =P103 -> 0.28988764 | V103: =Q103 -> 0.28699552 | W103: =IF(AND(ISNUMBER(W116),ISNUMBER(W115)),IFERROR(W116/W115,""),"") -> 0.29044798 | X103: 0.295 | Y103: 0.295 | Z103: 0.295 | AA103: 0.295 | AB103: 0.295 | AC103: Q3/Q4-26E: prior-year quarter ratio. 2027E+: input (FY2023–25: 30.2% / 29.4% / 29.5%). Selling & general expenses is the balancing line to the Adjusted EBITDA build. | AE103: =IFERROR(AVERAGE(X103,Y103,Z103,AA103,AB103),"n/m") -> 0.295 | AF103: =IFERROR(AVERAGE(H103,M103,R103),"n/m") -> 0.29700766 | AG103: =IFERROR(AVERAGE(M103,R103),"n/m") -> 0.29466974 | AH103: =IFERROR(AVERAGE(C103,H103,M103,R103),"n/m") -> 0.29700766
...

Sheet Bull-Base-Bear
B2: Mobility Global Inc. (MBGL) — Bull / Base / Bear Case P&L Summary | J2: Share price ($): | K2: =Model!$X$351 -> 18
B3: Company definitions: Adjusted EBITDA (company), Adjusted EPS = model definition (Mobility Global publishes none: + amortization of intangibles, transaction and other items, tax-effected) · USD millions · Live panel linked to Model — toggle scenario via Model!AC2. Bull and Bear panels are value snapshots generated from the Model with the switch set to each case. 2026E = 1H carve-out actual + 2H calibrated to the FY26 outlook (revenue $1,870–1,885m, Adjusted EBITDA $745–760m). | J3: As of: | K3: =TODAY() -> 2026-10-13 00:00:00
B5: Scenario: | C5: =Model!$AC$2 -> Base | N5: Scenario: | O5: Bull | P5: Snapshot (values) — Model run with switch = Bull | Z5: Scenario: | AA5: Bear | AB5: Snapshot (values) — Model run with switch = Bear
B7: (USDm, except EPS and shares) | C7: 2026E | D7: 2027E | E7: 2028E | F7: 2029E | G7: 2030E | H7: 2031E | I7: 26-'31 CAGR | J7: LT Hist Avg | K7: LT Hist Min | L7: LT Hist Max | N7: (USDm, except EPS and shares) | O7: 2026E | P7: 2027E | Q7: 2028E | R7: 2029E | S7: 2030E | T7: 2031E | U7: 26-'31 CAGR | V7: LT Hist Avg | W7: LT Hist Min | X7: LT Hist Max | Z7: (USDm, except EPS and shares) | AA7: 2026E | AB7: 2027E | AC7: 2028E | AD7: 2029E | AE7: 2030E | AF7: 2031E | AG7: 26-'31 CAGR | AH7: LT Hist Avg | AI7: LT Hist Min | AJ7: LT Hist Max
B9: Revenue | C9: =Model!W115 -> 1877.5 | D9: =Model!X115 -> 2008.3759 | E9: =Model!Y115 -> 2146.0917 | F9: =Model!Z115 -> 2285.7437 | G9: =Model!AA115 -> 2430.2801 | H9: =Model!AB115 -> 2577.1344 | I9: =IFERROR((H9/C9)^(1/5)-1,"n/m") -> 0.065396889 | N9: Revenue | O9: 1885 | P9: 2064.0969 | Q9: 2267.2211 | R9: 2479.9005 | S9: 2705.6412 | T9: 2942.2277 | U9: 0.09313295 | Z9: Revenue | AA9: 1870 | AB9: 1944.255 | AC9: 2019.2579 | AD9: 2090.102 | AE9: 2159.5957 | AF9: 2225.3518 | AG9: 0.03540776
B10: Revenue y/y % | D10: =IFERROR(D9/C9-1,"") -> 0.069707552 | E10: =IFERROR(E9/D9-1,"") -> 0.068570695 | F10: =IFERROR(F9/E9-1,"") -> 0.06507275 | G10: =IFERROR(G9/F9-1,"") -> 0.063233858 | H10: =IFERROR(H9/G9-1,"") -> 0.060426881 | N10: Revenue y/y % | P10: 0.095011612 | Q10: 0.098408294 | R10: 0.093806194 | S10: 0.091028098 | T10: 0.087441956 | Z10: Revenue y/y % | AB10: 0.03970854 | AC10: 0.038576715 | AD10: 0.035084214 | AE10: 0.033248953 | AF10: 0.030448346
B11: CARFAX revenue y/y % | C11: =Model!W192 -> 0.080003751 | D11: =Model!X192 -> 0.08 | E11: =Model!Y192 -> 0.078 | F11: =Model!Z192 -> 0.075 | G11: =Model!AA192 -> 0.072 | H11: =Model!AB192 -> 0.07 | N11: CARFAX revenue y/y % | O11: 0.084264101 | P11: 0.1 | Q11: 0.098 | R11: 0.095 | S11: 0.092 | T11: 0.09 | Z11: CARFAX revenue y/y % | AA11: 0.075743401 | AB11: 0.05 | AC11: 0.048 | AD11: 0.045 | AE11: 0.042 | AF11: 0.04
B12: Adjusted EBITDA | C12: =Model!W153 -> 752.5 | D12: =Model!X153 -> 817.74976 | E12: =Model!Y153 -> 888.5212 | F12: =Model!Z153 -> 962.12114 | G12: =Model!AA153 -> 1039.5035 | H12: =Model!AB153 -> 1120.0773 | I12: =IFERROR((H12/C12)^(1/5)-1,"n/m") -> 0.082800125 | N12: Adjusted EBITDA | O12: 760 | P12: 863.08294 | Q12: 960.37614 | R12: 1064.2514 | S12: 1176.0613 | T12: 1295.4777 | U12: 0.11255956 | Z12: Adjusted EBITDA | AA12: 745 | AB12: 739.82423 | AC12: 782.30307 | AD12: 824.30085 | AE12: 866.51992 | AF12: 908.36514 | AG12: 0.040449097
B13: Adjusted EBITDA margin % | C13: =IFERROR(C12/C9,"") -> 0.40079893 | D13: =IFERROR(D12/D9,"") -> 0.40716967 | E13: =IFERROR(E12/E9,"") -> 0.41401829 | F13: =IFERROR(F12/F9,"") -> 0.42092257 | G13: =IFERROR(G12/G9,"") -> 0.42772992 | H13: =IFERROR(H12/H9,"") -> 0.43462122 | J13: =IFERROR(AVERAGE(Model!H154,Model!M154,Model!R154),"") -> 0.40584493 | K13: =IFERROR(MIN(Model!H154,Model!M154,Model!R154),"") -> 0.4026936 | L13: =IFERROR(MAX(Model!H154,Model!M154,Model!R154),"") -> 0.40855549 | N13: Adjusted EBITDA margin % | O13: 0.40318302 | P13: 0.41814071 | Q13: 0.42359174 | R13: 0.42915083 | S13: 0.43467009 | T13: 0.44030504 | V13: 0.40584493 | W13: 0.4026936 | X13: 0.40855549 | Z13: Adjusted EBITDA margin % | AA13: 0.39839572 | AB13: 0.38051811 | AC13: 0.38742107 | AD13: 0.39438307 | AE13: 0.40124173 | AF13: 0.40818945 | AH13: 0.40584493 | AI13: 0.4026936 | AJ13: 0.40855549
B15: Operating Profit (GAAP) | C15: =Model!W119 -> 338.5 | D15: =Model!X119 -> 461.57387 | E15: =Model!Y119 -> 539.45328 | F15: =Model!Z119 -> 610.12052 | G15: =Model!AA119 -> 687.46765 | H15: =Model!AB119 -> 767.95747 | I15: =IFERROR((H15/C15)^(1/5)-1,"n/m") -> 0.17802823 | N15: Operating Profit (GAAP) | O15: 346 | P15: 504.40358 | Q15: 604.7645 | R15: 701.5068 | S15: 808.90949 | T15: 923.69091 | U15: 0.2169987 | Z15: Operating Profit (GAAP) | AA15: 331 | AB15: 384.99488 | AC15: 435.89865 | AD15: 476.40871 | AE15: 520.16841 | AF15: 563.63275 | AG15: 0.11232999
B16: Operating profit y/y % | D16: =IFERROR(D15/C15-1,"") -> 0.36358602 | E16: =IFERROR(E15/D15-1,"") -> 0.16872578 | F16: =IFERROR(F15/E15-1,"") -> 0.13099789 | G16: =IFERROR(G15/F15-1,"") -> 0.12677354 | H16: =IFERROR(H15/G15-1,"") -> 0.1170816 | N16: Operating profit y/y % | P16: 0.4578138 | Q16: 0.19896948 | R16: 0.1599669 | S16: 0.15310285 | T16: 0.1418965 | Z16: Operating profit y/y % | AB16: 0.16312652 | AC16: 0.13221935 | AD16: 0.092934581 | AE16: 0.091853279 | AF16: 0.083558215
B17: Operating margin (GAAP) % | C17: =IFERROR(C15/C9,"") -> 0.18029294 | D17: =IFERROR(D15/D9,"") -> 0.22982444 | E17: =IFERROR(E15/E9,"") -> 0.25136544 | F17: =IFERROR(F15/F9,"") -> 0.26692429 | G17: =IFERROR(G15/G9,"") -> 0.28287589 | H17: =IFERROR(H15/H9,"") -> 0.29798891 | J17: =IFERROR(AVERAGE(Model!H201,Model!M201,Model!R201),"") -> 0.17980199 | K17: =IFERROR(MIN(Model!H201,Model!M201,Model!R201),"") -> 0.16094276 | L17: =IFERROR(MAX(Model!H201,Model!M201,Model!R201),"") -> 0.19371429 | N17: Operating margin (GAAP) % | O17: 0.18355438 | P17: 0.24437011 | Q17: 0.26674261 | R17: 0.28287699 | S17: 0.29897146 | T17: 0.3139427 | V17: 0.17980199 | W17: 0.16094276 | X17: 0.19371429 | Z17: Operating margin (GAAP) % | AA17: 0.17700535 | AB17: 0.19801666 | AC17: 0.21587071 | AD17: 0.22793562 | AE17: 0.24086379 | AF17: 0.25327804 | AH17: 0.17980199 | AI17: 0.16094276 | AJ17: 0.19371429
B19: Adjusted Net Income (model definition) | C19: =Model!W183 -> 462.48516 | D19: =Model!X183 -> 480.45345 | E19: =Model!Y183 -> 528.6376 | F19: =Model!Z183 -> 576.19294 | G19: =Model!AA183 -> 621.74028 | H19: =Model!AB183 -> 671.17735 | I19: =IFERROR((H19/C19)^(1/5)-1,"n/m") -> 0.077327875 | N19: Adjusted Net Income (model definition) | O19: 467.8333 | P19: 512.14809 | Q19: 560.34056 | R19: 621.97081 | S19: 686.28614 | T19: 757.24219 | U19: 0.101105 | Z19: Adjusted Net Income (model definition) | AA19: 457.13573 | AB19: 425.5814 | AC19: 462.6494 | AD19: 493.53595 | AE19: 519.24721 | AF19: 546.88517 | AG19: 0.036502121
B21: FDSO (m) | C21: =Model!W133 -> 295.58799 | D21: =Model!X133 -> 285.66545 | E21: =Model!Y133 -> 260.48561 | F21: =Model!Z133 -> 231.64119 | G21: =Model!AA133 -> 202.51682 | H21: =Model!AB133 -> 173.25637 | I21: =IFERROR((H21/C21)^(1/5)-1,"n/m") -> -0.1013295 | N21: FDSO (m) | O21: 295.58799 | P21: 273.79994 | Q21: 235.7323 | R21: 204.31997 | S21: 171.52949 | T21: 137.47839 | U21: -0.14195605 | Z21: FDSO (m) | AA21: 295.58799 | AB21: 296.92132 | AC21: 290.194 | AD21: 272.50747 | AE21: 251.63355 | AF21: 231.24969 | AG21: -0.047908084
B23: Adjusted EPS — Diluted ($) | C23: =Model!W185 -> 1.5646277 | D23: =Model!X185 -> 1.6818746 | E23: =Model!Y185 -> 2.0294311 | F23: =Model!Z185 -> 2.4874373 | G23: =Model!AA185 -> 3.0700673 | H23: =Model!AB185 -> 3.8738971 | I23: =IFERROR((H23/C23)^(1/5)-1,"n/m") -> 0.19880187 | N23: Adjusted EPS — Diluted ($) | O23: 1.5827209 | P23: 1.8705194 | Q23: 2.3770207 | R23: 3.0441019 | S23: 4.0009804 | T23: 5.5080814 | U23: 0.28327342 | Z23: Adjusted EPS — Diluted ($) | AA23: 1.5465301 | AB23: 1.4333137 | AC23: 1.5942763 | AD23: 1.8110915 | AE23: 2.0635055 | AF23: 2.3649119 | AG23: 0.088657621
B24: EPS y/y % | D24: =IFERROR(D23/C23-1,"") -> 0.074935919 | E24: =IFERROR(E23/D23-1,"") -> 0.2066483 | F24: =IFERROR(F23/E23-1,"") -> 0.22568206 | G24: =IFERROR(G23/F23-1,"") -> 0.23422903 | H24: =IFERROR(H23/G23-1,"") -> 0.26182806 | N24: EPS y/y % | P24: 0.18183778 | Q24: 0.2707811 | R24: 0.28063753 | S24: 0.31433852 | T24: 0.37668292 | Z24: EPS y/y % | AB24: -0.07320674 | AC24: 0.11230099 | AD24: 0.13599601 | AE24: 0.13937122 | AF24: 0.14606524
B26: P / E (x) — assumed (adjusted EPS) | G26: 13 | H26: 13 | N26: P / E (x) — assumed (adjusted EPS) | S26: 15 | T26: 15 | Z26: P / E (x) — assumed (adjusted EPS) | AD26: 10 | AE26: 10 | AF26: 10
B27: Price Target ($) | G27: =G26*G23 -> 39.910875 | H27: =H26*H23 -> 50.360662 | N27: Price Target ($) | S27: =S26*S23 -> 60.014706 | T27: =T26*T23 -> 82.621221 | Z27: Price Target ($) | AD27: =AD26*AD23 -> 18.110915 | AE27: =AE26*AE23 -> 20.635055 | AF27: =AF26*AF23 -> 23.649119
B28: Upside / (Downside) vs current | G28: =IFERROR(G27/$K$2-1,"") -> 1.2172708 | H28: =IFERROR(H27/$K$2-1,"") -> 1.7978146 | N28: Upside / (Downside) vs current | S28: =IFERROR(S27/$K$2-1,"") -> 2.3341503 | T28: =IFERROR(T27/$K$2-1,"") -> 3.5900678 | Z28: Upside / (Downside) vs current | AD28: =IFERROR(AD27/$K$2-1,"") -> 0.0061619345 | AE28: =IFERROR(AE27/$K$2-1,"") -> 0.14639195 | AF28: =IFERROR(AF27/$K$2-1,"") -> 0.31383997
B29: IRR (to 31-Dec of Y-1) | G29: =IFERROR((G27/$K$2)^(1/((DATE(2030-1,12,31)-$K$3)/365.25))-1,"") -> 0.28084956 | H29: =IFERROR((H27/$K$2)^(1/((DATE(2031-1,12,31)-$K$3)/365.25))-1,"") -> 0.27636364 | N29: IRR (to 31-Dec of Y-1) | S29: =IFERROR((S27/$K$2)^(1/((DATE(2030-1,12,31)-$K$3)/365.25))-1,"") -> 0.4540204 | T29: =IFERROR((T27/$K$2)^(1/((DATE(2031-1,12,31)-$K$3)/365.25))-1,"") -> 0.43538089 | Z29: IRR (to 31-Dec of Y-1) | AD29: =IFERROR((AD27/$K$2)^(1/((DATE(2029-1,12,31)-$K$3)/365.25))-1,"") -> 0.0027738904 | AE29: =IFERROR((AE27/$K$2)^(1/((DATE(2030-1,12,31)-$K$3)/365.25))-1,"") -> 0.043383023 | AF29: =IFERROR((AF27/$K$2)^(1/((DATE(2031-1,12,31)-$K$3)/365.25))-1,"") -> 0.066879447
B31: Free Cash Flow | C31: =Model!W232 -> 392.6964 | D31: =Model!X232 -> 492.13414 | E31: =Model!Y232 -> 548.59599 | F31: =Model!Z232 -> 597.17523 | G31: =Model!AA232 -> 642.99622 | H31: =Model!AB232 -> 692.66173 | I31: =IFERROR((H31/C31)^(1/5)-1,"n/m") -> 0.120193 | N31: Free Cash Flow | O31: 398.20089 | P31: 525.75283 | Q31: 583.85218 | R31: 647.95985 | S31: 714.07294 | T31: 786.84965 | U31: 0.14592952 | Z31: Free Cash Flow | AA31: 387.19192 | AB31: 435.45822 | AC31: 480.21914 | AD31: 511.50207 | AE31: 536.81247 | AF31: 563.96627 | AG31: 0.078115698
B32: FCF % | C32: =IFERROR(C31/C9,"") -> 0.2091592 | D32: =IFERROR(D31/D9,"") -> 0.24504085 | E32: =IFERROR(E31/E9,"") -> 0.25562561 | F32: =IFERROR(F31/F9,"") -> 0.26126079 | G32: =IFERROR(G31/G9,"") -> 0.264577 | H32: =IFERROR(H31/H9,"") -> 0.26877206 | J32: =IFERROR(AVERAGE(Model!H236,Model!M236,Model!R236),"") -> 0.25712617 | K32: =IFERROR(MIN(Model!H236,Model!M236,Model!R236),"") -> 0.25252525 | L32: =IFERROR(MAX(Model!H236,Model!M236,Model!R236),"") -> 0.26342857 | N32: FCF % | O32: 0.21124716 | P32: 0.25471325 | Q32: 0.25751885 | R32: 0.26128461 | S32: 0.26392005 | T32: 0.2674333 | V32: 0.25712617 | W32: 0.25252525 | X32: 0.26342857 | Z32: FCF % | AA32: 0.2070545 | AB32: 0.22397176 | AC32: 0.23781961 | AD32: 0.24472589 | AE32: 0.24857082 | AF32: 0.25342791 | AH32: 0.25712617 | AI32: 0.25252525 | AJ32: 0.26342857
B33: FCF / share ($) | C33: =IFERROR(C31/C21,"") -> 1.3285263 | D33: =IFERROR(D31/D21,"") -> 1.722764 | E33: =IFERROR(E31/E21,"") -> 2.106051 | F33: =IFERROR(F31/F21,"") -> 2.5780183 | G33: =IFERROR(G31/G21,"") -> 3.1750262 | H33: =IFERROR(H31/H21,"") -> 3.9979005 | N33: FCF / share ($) | O33: 1.3471484 | P33: 1.920208 | Q33: 2.4767593 | R33: 3.1712997 | S33: 4.1629747 | T33: 5.7234423 | Z33: FCF / share ($) | AA33: 1.3099041 | AB33: 1.4665778 | AC33: 1.6548211 | AD33: 1.8770204 | AE33: 2.1333104 | AF33: 2.4387763
B34: FCF Yield (on PT) | F34: =IFERROR(F33/F$27,"") | G34: =IFERROR(G33/G$27,"") -> 0.079552908 | H34: =IFERROR(H33/H$27,"") -> 0.079385384 | N34: FCF Yield (on PT) | R34: =IFERROR(R33/R$27,"") | S34: =IFERROR(S33/S$27,"") -> 0.06936591 | T34: =IFERROR(T33/T$27,"") -> 0.069273271 | Z34: FCF Yield (on PT) | AD34: =IFERROR(AD33/AD$27,"") -> 0.10364029 | AE34: =IFERROR(AE33/AE$27,"") -> 0.10338283 | AF34: =IFERROR(AF33/AF$27,"") -> 0.10312334
B35: Adjusted EBITDA (leverage basis) | C35: =Model!W153 -> 752.5 | D35: =Model!X153 -> 817.74976 | E35: =Model!Y153 -> 888.5212 | F35: =Model!Z153 -> 962.12114 | G35: =Model!AA153 -> 1039.5035 | H35: =Model!AB153 -> 1120.0773 | I35: =IFERROR((H35/C35)^(1/5)-1,"n/m") -> 0.082800125 | N35: Adjusted EBITDA (leverage basis) | O35: 760 | P35: 863.08294 | Q35: 960.37614 | R35: 1064.2514 | S35: 1176.0613 | T35: 1295.4777 | U35: 0.11255956 | Z35: Adjusted EBITDA (leverage basis) | AA35: 745 | AB35: 739.82423 | AC35: 782.30307 | AD35: 824.30085 | AE35: 866.51992 | AF35: 908.36514 | AG35: 0.040449097
B36: Adjusted EBITDA % of revenue | C36: =IFERROR(C35/C9,"") -> 0.40079893 | D36: =IFERROR(D35/D9,"") -> 0.40716967 | E36: =IFERROR(E35/E9,"") -> 0.41401829 | F36: =IFERROR(F35/F9,"") -> 0.42092257 | G36: =IFERROR(G35/G9,"") -> 0.42772992 | H36: =IFERROR(H35/H9,"") -> 0.43462122 | J36: =IFERROR(AVERAGE(Model!H198,Model!M198,Model!R198),"") -> 0.40584493 | K36: =IFERROR(MIN(Model!H198,Model!M198,Model!R198),"") -> 0.4026936 | L36: =IFERROR(MAX(Model!H198,Model!M198,Model!R198),"") -> 0.40855549 | N36: Adjusted EBITDA % of revenue | O36: 0.40318302 | P36: 0.41814071 | Q36: 0.42359174 | R36: 0.42915083 | S36: 0.43467009 | T36: 0.44030504 | V36: 0.40584493 | W36: 0.4026936 | X36: 0.40855549 | Z36: Adjusted EBITDA % of revenue | AA36: 0.39839572 | AB36: 0.38051811 | AC36: 0.38742107 | AD36: 0.39438307 | AE36: 0.40124173 | AF36: 0.40818945 | AH36: 0.40584493 | AI36: 0.4026936 | AJ36: 0.40855549
B38: Net Debt | C38: =Model!W346 -> 1616.2002 | D38: =Model!X346 -> 1635.4995 | E38: =Model!Y346 -> 1777.0424 | F38: =Model!Z346 -> 1924.2423 | G38: =Model!AA346 -> 2079.0071 | H38: =Model!AB346 -> 2240.1546 | N38: Net Debt | O38: 1610.6957 | P38: 2157.7074 | Q38: 2400.9403 | R38: 2660.6284 | S38: 2940.1532 | T38: 3238.6942 | Z38: Net Debt | AA38: 1621.7046 | AB38: 1260.0515 | AC38: 1173.4546 | AD38: 1236.4513 | AE38: 1299.7799 | AF38: 1362.5477
B39: Net Debt / Adjusted EBITDA (x) | C39: =IFERROR(C38/C35,"") -> 2.1477743 | D39: =IFERROR(D38/D35,"") -> 2 | E39: =IFERROR(E38/E35,"") -> 2 | F39: =IFERROR(F38/F35,"") -> 2 | G39: =IFERROR(G38/G35,"") -> 2 | H39: =IFERROR(H38/H35,"") -> 2 | N39: Net Debt / Adjusted EBITDA (x) | O39: 2.1193364 | P39: 2.5 | Q39: 2.5 | R39: 2.5 | S39: 2.5 | T39: 2.5 | Z39: Net Debt / Adjusted EBITDA (x) | AA39: 2.1767848 | AB39: 1.7031769 | AC39: 1.5 | AD39: 1.5 | AE39: 1.5 | AF39: 1.5
B40: Share repurchases ($m; 2026E = 2H) | D40: =Model!X246 -> 437.62839 | E40: =Model!Y246 -> 618.26486 | F40: =Model!Z246 -> 676.63762 | G40: =Model!AA246 -> 734.85512 | H40: =Model!AB246 -> 796.42857 | N40: Share repurchases ($m; 2026E = 2H) | P40: 898.95941 | Q40: 661.19137 | R40: 746.7307 | S40: 838.71188 | T40: 937.66828 | AB40: 0 | AC40: 316.07523 | AD40: 496.9962 | AE40: 524.78073 | AF40: 553.77379
B41: Implied avg buyback price ($) | D41: =Model!X245 -> 19.44 | E41: =Model!Y245 -> 20.9952 | F41: =Model!Z245 -> 22.674816 | G41: =Model!AA245 -> 24.488801 | H41: =Model!AB245 -> 26.447905 | N41: Implied avg buyback price ($) | P41: 19.44 | Q41: 20.9952 | R41: 22.674816 | S41: 24.488801 | T41: 26.447905 | AB41: 19.44 | AC41: 20.9952 | AD41: 22.674816 | AE41: 24.488801 | AF41: 26.447905
B42: Shares repurchased (m) | D42: =Model!X247 -> 22.511748 | E42: =Model!Y247 -> 29.447915 | F42: =Model!Z247 -> 29.840931 | G42: =Model!AA247 -> 30.007803 | H42: =Model!AB247 -> 30.113106 | N42: Shares repurchased (m) | P42: 46.242768 | Q42: 31.492502 | R42: 32.932161 | S42: 34.248793 | T42: 35.453404 | AB42: 0 | AC42: 15.054643 | AD42: 21.918423 | AE42: 21.429417 | AF42: 20.938286
B44: ROIC | C44: =Model!W329 -> 0.027197982 | D44: =Model!X329 -> 0.031976969 | E44: =Model!Y329 -> 0.037059097 | F44: =Model!Z329 -> 0.042515347 | G44: =Model!AA329 -> 0.048615522 | H44: =Model!AB329 -> 0.055146588 | J44: =IFERROR(AVERAGE(Model!H329,Model!M329,Model!R329),"") -> 0.021215496 | K44: =IFERROR(MIN(Model!H329,Model!M329,Model!R329),"") -> 0.018013991 | L44: =IFERROR(MAX(Model!H329,Model!M329,Model!R329),"") -> 0.023640561 | N44: ROIC | O44: 0.027661781 | P44: 0.034433691 | Q44: 0.040660968 | R44: 0.047435008 | S44: 0.055040043 | T44: 0.063281907 | V44: 0.021215496 | W44: 0.018013991 | X44: 0.023640561 | Z44: ROIC | AA44: 0.026734147 | AB44: 0.027079014 | AC44: 0.03027767 | AD44: 0.03356608 | AE44: 0.037184821 | AF44: 0.04090566 | AH44: 0.021215496 | AI44: 0.018013991 | AJ44: 0.023640561
B45: RONTA | C45: =Model!W340 -> 0.62460937 | D45: =Model!X340 -> 0.73192811 | E45: =Model!Y340 -> 1.1269825 | F45: =Model!Z340 -> 1.2727433 | G45: =Model!AA340 -> 1.3860319 | H45: =Model!AB340 -> 1.4954717 | J45: =IFERROR(AVERAGE(Model!H340,Model!M340,Model!R340),"") -> 2.4457308 | K45: =IFERROR(MIN(Model!H340,Model!M340,Model!R340),"") -> 2.138934 | L45: =IFERROR(MAX(Model!H340,Model!M340,Model!R340),"") -> 2.7334697 | N45: RONTA | O45: 0.62857471 | P45: 1.1449519 | Q45: 1.3055485 | R45: 1.4669968 | S45: 1.6361956 | T45: 1.8043981 | V45: 2.4457308 | W45: 2.138934 | X45: 2.7334697 | Z45: RONTA | AA45: 0.62055774 | AB45: 0.35173266 | AC45: 0.34637366 | AD45: 0.39700361 | AE45: 0.45592813 | AF45: 0.52091189 | AH45: 2.4457308 | AI45: 2.138934 | AJ45: 2.7334697
B47: Implied Market Cap (USDm) | F47: =F27*F21 -> 0 | G47: =G27*G21 -> 8082.6237 | H47: =H27*H21 -> 8725.3055 | N47: Implied Market Cap (USDm) | R47: =R27*R21 -> 0 | S47: =S27*S21 -> 10294.292 | T47: =T27*T21 -> 11358.633 | Z47: Implied Market Cap (USDm) | AD47: =AD27*AD21 -> 4935.3595 | AE47: =AE27*AE21 -> 5192.4721 | AF47: =AF27*AF21 -> 5468.8517
B48: (+) Net Debt & NCI | F48: =F38+Model!Z355 -> 1924.2423 | G48: =G38+Model!AA355 -> 2079.0071 | H48: =H38+Model!AB355 -> 2240.1546 | N48: (+) Net Debt & NCI | R48: =R38+Model!Z355 -> 2660.6284 | S48: =S38+Model!AA355 -> 2940.1532 | T48: =T38+Model!AB355 -> 3238.6942 | Z48: (+) Net Debt & NCI | AD48: =AD38+Model!Z355 -> 1236.4513 | AE48: =AE38+Model!AA355 -> 1299.7799 | AF48: =AF38+Model!AB355 -> 1362.5477
B49: Implied Enterprise Value (USDm) | F49: =F47+F48 -> 1924.2423 | G49: =G47+G48 -> 10161.631 | H49: =H47+H48 -> 10965.46 | N49: Implied Enterprise Value (USDm) | R49: =R47+R48 -> 2660.6284 | S49: =S47+S48 -> 13234.445 | T49: =T47+T48 -> 14597.327 | Z49: Implied Enterprise Value (USDm) | AD49: =AD47+AD48 -> 6171.8108 | AE49: =AE47+AE48 -> 6492.252 | AF49: =AF47+AF48 -> 6831.3994
B50: Implied EV / Adjusted EBITDA (x) | F50: =IFERROR(F49/F35,"") -> 2 | G50: =IFERROR(G49/G35,"") -> 9.7754653 | H50: =IFERROR(H49/H35,"") -> 9.7899138 | N50: Implied EV / Adjusted EBITDA (x) | R50: =IFERROR(R49/R35,"") -> 2.5 | S50: =IFERROR(S49/S35,"") -> 11.253194 | T50: =IFERROR(T49/T35,"") -> 11.267911 | Z50: Implied EV / Adjusted EBITDA (x) | AD50: =IFERROR(AD49/AD35,"") -> 7.4873279 | AE50: =IFERROR(AE49/AE35,"") -> 7.4923286 | AF50: =IFERROR(AF49/AF35,"") -> 7.5205433

Sheet DCF
B2: DCF VALUATION — MOBILITY GLOBAL INC. (MBGL)
B4: 1. WACC BUILD
B5: Risk-free rate (US 10Y govt) | C5: 0.0425 | D5: Assumption (~US 10Y Treasury yield, Oct-2026; rate sources not reachable from the build environment); update to market
B6: Equity risk premium | C6: 0.05 | D6: Assumption: US implied ERP ~4.5–5.5%
B7: Levered beta | C7: 1.15 | D7: Assumption: no trading history before Jul-2026; data / information-services peers ~0.9–1.2, raised for a newly levered spin (~2.2x) with auto-dealer and OEM end-market exposure; ~81% subscription revenue dampens cyclicality
B8: Cost of equity | C8: =C5+C7*C6 -> 0.1
B9: Pre-tax cost of debt | C9: 0.0575 | D9: Senior notes 5.050% 2029 / 5.450% 2031 / 6.050% 2036 (May-2026; 5.74% all-in per the Form 10 pro forma); revolver SOFR + 1.0–1.625%
B10: Tax rate | C10: 0.27 | D10: Assumption: normalised tax rate on adjusted EBIT (model 2027E+ GAAP effective rate 28.5%; amortization is largely non-deductible)
B11: After-tax cost of debt | C11: =C9*(1-C10) -> 0.041975
B12: Target D/V | C12: 0.25 | D12: Net debt ~$1.8bn at 30-Jun-2026 vs ~$5.3bn market cap ($18.00 × ~296m diluted shares); D/V ~25%
B13: WACC | C13: =C8*(1-C12)+C11*C12 -> 0.08549375
B15: Valuation date (live) | C15: =TODAY() -> 2026-10-13 00:00:00 | D15: Periods = (31-Dec of the year − today) / 365.25; cash flows assumed at year-end; 2026E (valuation date in Q4) is the base year and its cash flow sits in YE2026E net debt
B16: 2. UNLEVERED FREE CASH FLOW BUILD (USDm)
D17: 2027E | E17: 2028E | F17: 2029E | G17: 2030E | H17: 2031E | I17: 2032E | J17: 2033E | K17: 2034E | L17: 2035E | M17: 2036E | N17: Terminal | P17: CAGR 27–31E | Q17: CAGR 27–36E
B18: Adj. EBITA (Adjusted EBITDA − depreciation) less SBC and cash transaction / severance / other costs | D18: =Model!X161-Model!X158-Model!X109 -> 757.57387 | E18: =Model!Y161-Model!Y158-Model!Y109 -> 835.45328 | F18: =Model!Z161-Model!Z158-Model!Z109 -> 906.12052 | G18: =Model!AA161-Model!AA158-Model!AA109 -> 980.46765 | H18: =Model!AB161-Model!AB158-Model!AB109 -> 1057.9575 | I18: =H18*(1+I$26) -> 1121.4349 | J18: =I18*(1+J$26) -> 1183.1138 | K18: =J18*(1+K$26) -> 1242.2695 | L18: =K18*(1+L$26) -> 1298.1717 | M18: =L18*(1+M$26) -> 1350.0985 | P18: =(H18/D18)^(1/(COLUMNS(D18:H18)-1))-1 -> 0.087078248 | Q18: =(M18/D18)^(1/(COLUMNS(D18:M18)-1))-1 -> 0.066307037
B19: × (1 − tax rate) | D19: =1-$C$10 -> 0.73 | E19: =1-$C$10 -> 0.73 | F19: =1-$C$10 -> 0.73 | G19: =1-$C$10 -> 0.73 | H19: =1-$C$10 -> 0.73 | I19: =1-$C$10 -> 0.73 | J19: =1-$C$10 -> 0.73 | K19: =1-$C$10 -> 0.73 | ... M19: =1-$C$10 -> 0.73
B20: NOPAT | D20: =D18*D19 -> 553.02892 | E20: =E18*E19 -> 609.88089 | F20: =F18*F19 -> 661.46798 | G20: =G18*G19 -> 715.74139 | H20: =H18*H19 -> 772.30895 | I20: =I18*I19 -> 818.64749 | J20: =J18*J19 -> 863.6731 | K20: =K18*K19 -> 906.85675 | ... M20: =M18*M19 -> 985.57192
B21: plus depreciation (amortization of acquired intangibles is excluded above, not added back) | D21: =Model!X104 -> 16.067007 | E21: =Model!Y104 -> 17.168733 | F21: =Model!Z104 -> 18.28595 | G21: =Model!AA104 -> 19.442241 | H21: =Model!AB104 -> 20.617075 | I21: =H21*(1+I$26) -> 21.8541 | J21: =I21*(1+J$26) -> 23.056075 | K21: =J21*(1+K$26) -> 24.208879 | L21: =K21*(1+L$26) -> 25.298278 | M21: =L21*(1+M$26) -> 26.31021
B22: − Capex and acquisitions (M&A lever 2027E–31E) | D22: =Model!X214+Model!X215 -> -28.117263 | E22: =Model!Y214+Model!Y215 -> -30.045283 | F22: =Model!Z214+Model!Z215 -> -32.000412 | G22: =Model!AA214+Model!AA215 -> -34.023922 | H22: =Model!AB214+Model!AB215 -> -36.079881 | I22: =Model!AB214*(1+I$26) -> -38.244674 | J22: =I22*(1+J$26) -> -40.348131 | K22: =J22*(1+K$26) -> -42.365538 | L22: =K22*(1+L$26) -> -44.271987 | M22: =L22*(1+M$26) -> -46.042867
B23: − Δ Working capital (CF statement) | D23: =Model!X212 -> 3.1320582 | E23: =Model!Y212 -> 3.295745 | F23: =Model!Z212 -> 3.3420848 | G23: =Model!AA212 -> 3.4589737 | H23: =Model!AB212 -> 3.5144434 | I23: =H23*(1+I$26) -> 3.72531 | J23: =I23*(1+J$26) -> 3.9302021 | K23: =J23*(1+K$26) -> 4.1267122 | L23: =K23*(1+L$26) -> 4.3124143 | M23: =L23*(1+M$26) -> 4.4849108
B24: Unlevered FCF | D24: =D20+D21+D22+D23 -> 544.11072 | E24: =E20+E21+E22+E23 -> 600.30009 | F24: =F20+F21+F22+F23 -> 651.0956 | G24: =G20+G21+G22+G23 -> 704.61868 | H24: =H20+H21+H22+H23 -> 760.36059 | I24: =I20+I21+I22+I23 -> 805.98222 | J24: =J20+J21+J22+J23 -> 850.31124 | K24: =K20+K21+K22+K23 -> 892.82681 | ... M24: =M20+M21+M22+M23 -> 970.32417 | N24: =M24*(1+$C$27) -> 999.4339 | P24: =(H24/D24)^(1/(COLUMNS(D24:H24)-1))-1 -> 0.087259166 | Q24: =(M24/D24)^(1/(COLUMNS(D24:M24)-1))-1 -> 0.066385905
B25: Terminal Value (Gordon Growth) | N25: =N24/($C$13-$C$27) -> 18009.846
B26: Fade-period growth (2032E–36E; 6.0% → 4.0% linear) | I26: 0.06 | J26: =I26+($M$26-$I$26)/4 -> 0.055 | K26: =J26+($M$26-$I$26)/4 -> 0.05 | L26: =K26+($M$26-$I$26)/4 -> 0.045 | M26: 0.04
B27: Terminal growth rate | C27: 0.03
B29: Discount period (years) | D29: =(DATE(2027,12,31)-$C$15)/365.25 -> 1.2156057 | E29: =(DATE(2028,12,31)-$C$15)/365.25 -> 2.2176591 | F29: =(DATE(2029,12,31)-$C$15)/365.25 -> 3.2169747 | G29: =(DATE(2030,12,31)-$C$15)/365.25 -> 4.2162902 | H29: =(DATE(2031,12,31)-$C$15)/365.25 -> 5.2156057 | I29: =(DATE(2032,12,31)-$C$15)/365.25 -> 6.2176591 | J29: =(DATE(2033,12,31)-$C$15)/365.25 -> 7.2169747 | K29: =(DATE(2034,12,31)-$C$15)/365.25 -> 8.2162902 | L29: =(DATE(2035,12,31)-$C$15)/365.25 -> 9.2156057 | M29: =(DATE(2036,12,31)-$C$15)/365.25 -> 10.217659 | N29: =M29 -> 10.217659
B30: Discount factor | D30: =1/(1+$C$13)^D29 -> 0.90508885 | E30: =1/(1+$C$13)^E29 -> 0.83366339 | F30: =1/(1+$C$13)^F29 -> 0.76804699 | G30: =1/(1+$C$13)^G29 -> 0.70759515 | H30: =1/(1+$C$13)^H29 -> 0.65190139 | I30: =1/(1+$C$13)^I29 -> 0.60045632 | J30: =1/(1+$C$13)^J29 -> 0.5531953 | K30: =1/(1+$C$13)^K29 -> 0.50965412 | ... N30: =1/(1+$C$13)^N29 -> 0.43248606
B31: PV of UFCF | D31: =D24*D30 -> 492.46855 | E31: =E24*E30 -> 500.44821 | F31: =F24*F30 -> 500.07201 | G31: =G24*G30 -> 498.58476 | H31: =H24*H30 -> 495.68012 | I31: =I24*I30 -> 483.95712 | J31: =J24*J30 -> 470.38818 | K31: =K24*K30 -> 455.03286 | ... M31: =M24*M30 -> 419.65168 | N31: =N25*N30 -> 7789.0074
D32: NOPAT basis (standard): taxed on pre-amortization Adjusted EBITA with a depreciation-only add-back. The ~$296m p.a. of acquired-intangible amortization (IHS Markit purchase accounting) is non-cash and largely non-deductible (deferred-tax liability $967m at 30-Jun-2026), so taxing EBIT after amortization would overstate the cash tax shield. Mobility Global's Adjusted EBITDA adds back stock-based compensation, a real cost: row 18 deducts SBC and the cash transaction (separation stand-up), severance and other items the company excludes. Base year 2026E: valuation date (Oct-2026) inside the year; YE2026E net debt captures 2H/26 cash flow.
B33: IMPLIED ROIC — invested capital roll-forward (USDm)
B34: Opening invested capital | D34: =Model!W326 -> 11514.069 | E34: =D38 -> 11522.987 | F34: =E38 -> 11532.568 | G34: =F38 -> 11542.94 | H34: =G38 -> 11554.063 | I34: =H38 -> 11566.011 | J34: =I38 -> 11578.676 | K34: =J38 -> 11592.038 | L34: =K38 -> 11606.068 | M34: =L38 -> 11620.729
B35: plus Capex and acquisitions | D35: =-D22 -> 28.117263 | E35: =-E22 -> 30.045283 | F35: =-F22 -> 32.000412 | G35: =-G22 -> 34.023922 | H35: =-H22 -> 36.079881 | I35: =-I22 -> 38.244674 | J35: =-J22 -> 40.348131 | K35: =-K22 -> 42.365538 | ... M35: =-M22 -> 46.042867
B36: less DD&A | D36: =-D21 -> -16.067007 | E36: =-E21 -> -17.168733 | F36: =-F21 -> -18.28595 | G36: =-G21 -> -19.442241 | H36: =-H21 -> -20.617075 | I36: =-I21 -> -21.8541 | J36: =-J21 -> -23.056075 | K36: =-K21 -> -24.208879 | ... M36: =-M21 -> -26.31021
B37: plus Δ Working capital investment | D37: =-D23 -> -3.1320582 | E37: =-E23 -> -3.295745 | F37: =-F23 -> -3.3420848 | G37: =-G23 -> -3.4589737 | H37: =-H23 -> -3.5144434 | I37: =-I23 -> -3.72531 | J37: =-J23 -> -3.9302021 | K37: =-K23 -> -4.1267122 | ... M37: =-M23 -> -4.4849108
B38: Closing invested capital | D38: =SUM(D34:D37) -> 11522.987 | E38: =SUM(E34:E37) -> 11532.568 | F38: =SUM(F34:F37) -> 11542.94 | G38: =SUM(G34:G37) -> 11554.063 | H38: =SUM(H34:H37) -> 11566.011 | I38: =SUM(I34:I37) -> 11578.676 | J38: =SUM(J34:J37) -> 11592.038 | K38: =SUM(K34:K37) -> 11606.068 | ... M38: =SUM(M34:M37) -> 11635.977
B39: NOPAT (row 20) | D39: =D20 -> 553.02892 | E39: =E20 -> 609.88089 | F39: =F20 -> 661.46798 | G39: =G20 -> 715.74139 | H39: =H20 -> 772.30895 | I39: =I20 -> 818.64749 | J39: =J20 -> 863.6731 | K39: =K20 -> 906.85675 | ... M39: =M20 -> 985.57192
B40: Implied ROIC (NOPAT / avg. invested capital) | D40: =IFERROR(D39/AVERAGE(D34,D38),"") -> 0.048012119 | E40: =IFERROR(E39/AVERAGE(E34,E38),"") -> 0.052905333 | F40: =IFERROR(F39/AVERAGE(F34,F38),"") -> 0.057330741 | G40: =IFERROR(G39/AVERAGE(G34,G38),"") -> 0.061976993 | H40: =IFERROR(H39/AVERAGE(H34,H38),"") -> 0.06680852 | I40: =IFERROR(I39/AVERAGE(I34,I38),"") -> 0.070741719 | J40: =IFERROR(J39/AVERAGE(J34,J38),"") -> 0.074548681 | K40: =IFERROR(K39/AVERAGE(K34,K38),"") -> 0.078183688 | ... M40: =IFERROR(M39/AVERAGE(M34,M38),"") -> 0.084755932
B41: Reinvestment rate (net investment / NOPAT) | D41: =IFERROR(SUM(D35:D37)/D39,"") -> 0.016126096 | E41: =IFERROR(SUM(E35:E37)/E39,"") -> 0.015709305 | F41: =IFERROR(SUM(F35:F37)/F39,"") -> 0.015680846 | G41: =IFERROR(SUM(G35:G37)/G39,"") -> 0.01554012 | H41: =IFERROR(SUM(H35:H37)/H39,"") -> 0.015470963 | I41: =IFERROR(SUM(I35:I37)/I39,"") -> 0.015470963 | J41: =IFERROR(SUM(J35:J37)/J39,"") -> 0.015470963 | K41: =IFERROR(SUM(K35:K37)/K39,"") -> 0.015470963 | ... M41: =IFERROR(SUM(M35:M37)/M39,"") -> 0.015470963
B42: Implied terminal RONIC (g / reinvestment rate) | N42: =IFERROR($C$27/M41,"") -> 1.9391166
D43: Opening IC = Model 2026E book IC (equity + net debt at 31-Dec-2026; equity carries the IHS Markit purchase goodwill and intangibles), rolled forward with capex + M&A − D&A + ΔWC.
B44: 3. VALUATION SUMMARY
B45: Sum of PV (explicit + fade) | C45: =SUM(D31:M31) -> 4754.3662
B46: PV of Terminal Value | C46: =N31 -> 7789.0074
B47: Enterprise Value | C47: =C45+C46 -> 12543.374
B48: Less: Net debt + NCI (Model 2026E year end, 31-Dec-2026) | C48: =Model!W346+Model!W355 -> 1616.2002 | D48: MBGL: no noncontrolling interests; net debt = senior notes (carrying value) + revolver − cash at the base-year end.
B49: Equity Value | C49: =C47-C48 -> 10927.173
B50: Diluted shares (m, Model 2026E period end) | C50: =Model!W352 -> 296.02132
B51: Implied share price ($) | C51: =C49/C50 -> 36.913468
B52: Current share price ($) | C52: =Model!W351 -> 18
B53: Implied upside / (downside) | C53: =C51/C52-1 -> 1.0507482
B54: Required discount to DCF value for target IRR | C54: =1-((1+C13)/(1+H54))^H55 -> 0.15901459 | D54: vs. current | E54: Target IRR | H54: 0.15
B55: Max entry price for target IRR ($) | C55: =C51*(1-C54) -> 31.043688 | D55: =C55/C52-1 -> 0.72464932 | E55: Years for discount to close | H55: 3
B58: 4. SENSITIVITY: IMPLIED PRICE ($) — WACC × Terminal Growth
D60: WACC →
B61: Terminal growth ↓ | D61: =F61-0.01 -> 0.07549375 | E61: =F61-0.005 -> 0.08049375 | F61: =$C$13 -> 0.08549375 | G61: =F61+0.005 -> 0.09049375 | H61: =F61+0.01 -> 0.09549375
B62: =B64-0.01 -> 0.02 | D62: {=IFERROR((SUMPRODUCT($D$24:$M$24/(1+D$61)^$D$29:$M$29)+($M$24*(1+$B62)/(D$61-$B62))/(1+D$61)^$M$29-$C$48)/$C$50,"")} -> 40.097537 | E62: {=IFERROR((SUMPRODUCT($D$24:$M$24/(1+E$61)^$D$29:$M$29)+($M$24*(1+$B62)/(E$61-$B62))/(1+E$61)^$M$29-$C$48)/$C$50,"")} -> 36.078573 | F62: {=IFERROR((SUMPRODUCT($D$24:$M$24/(1+F$61)^$D$29:$M$29)+($M$24*(1+$B62)/(F$61-$B62))/(1+F$61)^$M$29-$C$48)/$C$50,"")} -> 32.679482 | G62: {=IFERROR((SUMPRODUCT($D$24:$M$24/(1+G$61)^$D$29:$M$29)+($M$24*(1+$B62)/(G$61-$B62))/(1+G$61)^$M$29-$C$48)/$C$50,"")} -> 29.768151 | H62: {=IFERROR((SUMPRODUCT($D$24:$M$24/(1+H$61)^$D$29:$M$29)+($M$24*(1+$B62)/(H$61-$B62))/(1+H$61)^$M$29-$C$48)/$C$50,"")} -> 27.247476
B63: =B64-0.005 -> 0.025 | D63: {=IFERROR((SUMPRODUCT($D$24:$M$24/(1+D$61)^$D$29:$M$29)+($M$24*(1+$B63)/(D$61-$B63))/(1+D$61)^$M$29-$C$48)/$C$50,"")} -> 43.087951 | E63: {=IFERROR((SUMPRODUCT($D$24:$M$24/(1+E$61)^$D$29:$M$29)+($M$24*(1+$B63)/(E$61-$B63))/(1+E$61)^$M$29-$C$48)/$C$50,"")} -> 38.470185 | F63: {=IFERROR((SUMPRODUCT($D$24:$M$24/(1+F$61)^$D$29:$M$29)+($M$24*(1+$B63)/(F$61-$B63))/(1+F$61)^$M$29-$C$48)/$C$50,"")} -> 34.621499 | G63: {=IFERROR((SUMPRODUCT($D$24:$M$24/(1+G$61)^$D$29:$M$29)+($M$24*(1+$B63)/(G$61-$B63))/(1+G$61)^$M$29-$C$48)/$C$50,"")} -> 31.365559 | H63: {=IFERROR((SUMPRODUCT($D$24:$M$24/(1+H$61)^$D$29:$M$29)+($M$24*(1+$B63)/(H$61-$B63))/(1+H$61)^$M$29-$C$48)/$C$50,"")} -> 28.576068
B64: =$C$27 -> 0.03 | D64: {=IFERROR((SUMPRODUCT($D$24:$M$24/(1+D$61)^$D$29:$M$29)+($M$24*(1+$B64)/(D$61-$B64))/(1+D$61)^$M$29-$C$48)/$C$50,"")} -> 46.73569 | E64: {=IFERROR((SUMPRODUCT($D$24:$M$24/(1+E$61)^$D$29:$M$29)+($M$24*(1+$B64)/(E$61-$B64))/(1+E$61)^$M$29-$C$48)/$C$50,"")} -> 41.335442 | F64: {=IFERROR((SUMPRODUCT($D$24:$M$24/(1+F$61)^$D$29:$M$29)+($M$24*(1+$B64)/(F$61-$B64))/(1+F$61)^$M$29-$C$48)/$C$50,"")} -> 36.913468 | G64: {=IFERROR((SUMPRODUCT($D$24:$M$24/(1+G$61)^$D$29:$M$29)+($M$24*(1+$B64)/(G$61-$B64))/(1+G$61)^$M$29-$C$48)/$C$50,"")} -> 33.227028 | H64: {=IFERROR((SUMPRODUCT($D$24:$M$24/(1+H$61)^$D$29:$M$29)+($M$24*(1+$B64)/(H$61-$B64))/(1+H$61)^$M$29-$C$48)/$C$50,"")} -> 30.107518
B65: =B64+0.005 -> 0.035 | D65: {=IFERROR((SUMPRODUCT($D$24:$M$24/(1+D$61)^$D$29:$M$29)+($M$24*(1+$B65)/(D$61-$B65))/(1+D$61)^$M$29-$C$48)/$C$50,"")} -> 51.284244 | E65: {=IFERROR((SUMPRODUCT($D$24:$M$24/(1+E$61)^$D$29:$M$29)+($M$24*(1+$B65)/(E$61-$B65))/(1+E$61)^$M$29-$C$48)/$C$50,"")} -> 44.830513 | F65: {=IFERROR((SUMPRODUCT($D$24:$M$24/(1+F$61)^$D$29:$M$29)+($M$24*(1+$B65)/(F$61-$B65))/(1+F$61)^$M$29-$C$48)/$C$50,"")} -> 39.659348 | G65: {=IFERROR((SUMPRODUCT($D$24:$M$24/(1+G$61)^$D$29:$M$29)+($M$24*(1+$B65)/(G$61-$B65))/(1+G$61)^$M$29-$C$48)/$C$50,"")} -> 35.423935 | H65: {=IFERROR((SUMPRODUCT($D$24:$M$24/(1+H$61)^$D$29:$M$29)+($M$24*(1+$B65)/(H$61-$B65))/(1+H$61)^$M$29-$C$48)/$C$50,"")} -> 31.892126
B66: =B64+0.01 -> 0.04 | D66: {=IFERROR((SUMPRODUCT($D$24:$M$24/(1+D$61)^$D$29:$M$29)+($M$24*(1+$B66)/(D$61-$B66))/(1+D$61)^$M$29-$C$48)/$C$50,"")} -> 57.114307 | E66: {=IFERROR((SUMPRODUCT($D$24:$M$24/(1+E$61)^$D$29:$M$29)+($M$24*(1+$B66)/(E$61-$B66))/(1+E$61)^$M$29-$C$48)/$C$50,"")} -> 49.188698 | F66: {=IFERROR((SUMPRODUCT($D$24:$M$24/(1+F$61)^$D$29:$M$29)+($M$24*(1+$B66)/(F$61-$B66))/(1+F$61)^$M$29-$C$48)/$C$50,"")} -> 43.008802 | G66: {=IFERROR((SUMPRODUCT($D$24:$M$24/(1+G$61)^$D$29:$M$29)+($M$24*(1+$B66)/(G$61-$B66))/(1+G$61)^$M$29-$C$48)/$C$50,"")} -> 38.055927 | H66: {=IFERROR((SUMPRODUCT($D$24:$M$24/(1+H$61)^$D$29:$M$29)+($M$24*(1+$B66)/(H$61-$B66))/(1+H$61)^$M$29-$C$48)/$C$50,"")} -> 33.998321
B69: 5. REVERSE DCF
B70: To solve for the market-implied path: Data ▸ What-If Analysis ▸ Goal Seek — set C51 to the current price (C52) by changing C27 (terminal growth) or the fade-period growth inputs (I26:M26).
B72: 6. MAUBOUSSIN EV / NOPAT — TWO-STAGE FRAMEWORK
B73: EV/NOPAT = 1/r + [g × (1 − r/ROIIC) / (r × (r − g))] × [1 − ((1+g)/(1+r))^N]
B74: Formula source: Mauboussin & Rappaport, "Expectations Investing" (2021); Counterpoint Global, "What Does a Price-Earnings Multiple Mean?" (2020).
B76: Input | C76: Value | D76: Rationale (Mobility Global characteristics)
B77: r (Cost of capital / WACC) | C77: =$C$13 -> 0.08549375 | D77: Linked from Section 1 WACC build
B78: g (NOPAT growth, Stage 1) | C78: 0.09 | D78: Model Adjusted EBIT CAGR 2026–31E: ~7% revenue growth (CARFAX ~8%, B2B ~5%) with modest margin expansion → high-single-digit NOPAT growth
B79: ROIIC (Return on incremental invested capital) | C79: 0.3 | D79: Asset-light data business (capex ~1.4% of revenue): incremental returns on organic capital are very high; book IC is inflated by IHS Markit purchase accounting
B80: N (Years of value creation / CAP) | C80: 12 | D80: CARFAX consumer brand and vehicle-history data estate (38bn records, 832m VINs) and dealer network effects; exposure to dealer / OEM budgets and AI-driven disruption
B82: Calculation | C82: Value
B83: Steady-state component: 1 / r | C83: =1/C77 -> 11.696761
B84: Value-creation factor: 1 − r / ROIIC | C84: =1-C77/C79 -> 0.71502083
B85: Growth multiplier: g × (1 − r/ROIIC) / (r × (r − g)) | C85: =C78*C84/(C77*(C77-C78)) -> -167.03657
B86: Time decay: 1 − ((1+g)/(1+r))^N | C86: =1-((1+C78)/(1+C77))^C80 -> -0.050969345
B87: PVGO component (growth value) | C87: =C85*C86 -> 8.5137444
B88: Mauboussin EV / NOPAT (steady-state + PVGO) | C88: =C83+C87 -> 20.210506
B90: VALUATION — Applied to 2029E NOPAT | C90: USDm
B91: 2029E Adj. EBITA less SBC and cash adjusting items | C91: =Model!Z161-Model!Z158-Model!Z109 -> 906.12052
B92: Tax rate (from WACC build) | C92: =$C$10 -> 0.27
B93: 2029E NOPAT | C93: =C91*(1-C92) -> 661.46798
B94: × Mauboussin EV/NOPAT multiple | C94: =C88 -> 20.210506
B95: Implied Enterprise Value (2029E basis) | C95: =C93*C94 -> 13368.602
B96: Less: YE2028E net debt + NCI (Model) | C96: =Model!Y346+Model!Y355 -> 1777.0424
B97: Implied Equity Value | C97: =C95-C96 -> 11591.56
B98: Diluted shares 2029E (m, Model) | C98: =Model!Z352 -> 217.12073
B99: Implied share price 2029 ($) | C99: =C97/C98 -> 53.387626
B101: Current share price ($) | C101: =C52 -> 18
B102: Implied upside / (downside) | C102: =C99/C101-1 -> 1.9659792
B104: MARKET-IMPLIED EV/NOPAT TODAY | C104: USDm
B105: Current market cap (spot × diluted shares) | C105: =C52*C50 -> 5328.3838
B106: Plus: YE2026E net debt + NCI | C106: =C48 -> 1616.2002
B107: Implied Enterprise Value (today) | C107: =C105+C106 -> 6944.5839
B108: MBGL market-implied EV/NOPAT (on 2029E NOPAT) | C108: =C107/C93 -> 10.498745
B110: Multiple gap (Mauboussin − Market) | C110: =C88-C108 -> 9.7117604
B111: Implied re-rating headroom | C111: =C88/C108-1 -> 0.92504009

Sheet Charts
B2: Mobility Global — Operating Performance (2023–2025) and Model Forecast (2026E–2031E)
B3: USDm · Linked to Model. Bars = CARFAX / B2B revenue growth (carve-out; 2023 growth n/a on the carve-out basis — see the S&P Global segment memo). Adjusted EBITDA = company definition. ROIC / RONTA on Adjusted EBIT (full-cost); returns are depressed by the IHS Markit purchase-accounting goodwill and intangibles in equity. Carve-out history starts in FY2023.
C7: 2023 | D7: 2024 | E7: 2025 | F7: 2026E | G7: 2027E | H7: 2028E | I7: 2029E | J7: 2030E | K7: 2031E
B8: CARFAX revenue y/y % | C8: =IFERROR(Model!H192+0,0) -> 0 | D8: =IFERROR(Model!M192+0,0) -> 0.11961207 | E8: =IFERROR(Model!R192+0,0) -> 0.099133782 | F8: =IFERROR(Model!W192+0,0) -> 0.080003751 | G8: =IFERROR(Model!X192+0,0) -> 0.08 | H8: =IFERROR(Model!Y192+0,0) -> 0.078 | I8: =IFERROR(Model!Z192+0,0) -> 0.075 | J8: =IFERROR(Model!AA192+0,0) -> 0.072 | K8: =IFERROR(Model!AB192+0,0) -> 0.07
B9: B2B revenue y/y % | C9: =IFERROR(Model!H193+0,0) -> 0 | D9: =IFERROR(Model!M193+0,0) -> 0.030520646 | E9: =IFERROR(Model!R193+0,0) -> 0.059233449 | F9: =IFERROR(Model!W193+0,0) -> 0.059433744 | G9: =IFERROR(Model!X193+0,0) -> 0.05 | H9: =IFERROR(Model!Y193+0,0) -> 0.05 | I9: =IFERROR(Model!Z193+0,0) -> 0.045 | J9: =IFERROR(Model!AA193+0,0) -> 0.045 | K9: =IFERROR(Model!AB193+0,0) -> 0.04
C11: =C7 -> 2023 | D11: =D7 -> 2024 | E11: =E7 -> 2025 | F11: =F7 -> 2026E | G11: =G7 -> 2027E | H11: =H7 -> 2028E | I11: =I7 -> 2029E | J11: =J7 -> 2030E | K11: =K7 -> 2031E
B12: Adjusted EBITDA | C12: =IFERROR(Model!H153+0,NA()) -> 598 | D12: =IFERROR(Model!M153+0,NA()) -> 659 | E12: =IFERROR(Model!R153+0,NA()) -> 711 | F12: =IFERROR(Model!W153+0,NA()) -> 752.5 | G12: =IFERROR(Model!X153+0,NA()) -> 817.74976 | H12: =IFERROR(Model!Y153+0,NA()) -> 888.5212 | I12: =IFERROR(Model!Z153+0,NA()) -> 962.12114 | J12: =IFERROR(Model!AA153+0,NA()) -> 1039.5035 | K12: =IFERROR(Model!AB153+0,NA()) -> 1120.0773
B13: Operating profit (GAAP) | C13: =IFERROR(Model!H119+0,NA()) -> 239 | D13: =IFERROR(Model!M119+0,NA()) -> 298 | E13: =IFERROR(Model!R119+0,NA()) -> 339 | F13: =IFERROR(Model!W119+0,NA()) -> 338.5 | G13: =IFERROR(Model!X119+0,NA()) -> 461.57387 | H13: =IFERROR(Model!Y119+0,NA()) -> 539.45328 | I13: =IFERROR(Model!Z119+0,NA()) -> 610.12052 | J13: =IFERROR(Model!AA119+0,NA()) -> 687.46765 | K13: =IFERROR(Model!AB119+0,NA()) -> 767.95747
B14: Adj. EBITDA Margin % | C14: =IFERROR(Model!H198+0,NA()) -> 0.4026936 | D14: =IFERROR(Model!M198+0,NA()) -> 0.40855549 | E14: =IFERROR(Model!R198+0,NA()) -> 0.40628571 | F14: =IFERROR(Model!W198+0,NA()) -> 0.40079893 | G14: =IFERROR(Model!X198+0,NA()) -> 0.40716967 | H14: =IFERROR(Model!Y198+0,NA()) -> 0.41401829 | I14: =IFERROR(Model!Z198+0,NA()) -> 0.42092257 | J14: =IFERROR(Model!AA198+0,NA()) -> 0.42772992 | K14: =IFERROR(Model!AB198+0,NA()) -> 0.43462122
B15: GAAP Op. Margin % | C15: =IFERROR(Model!H201+0,NA()) -> 0.16094276 | D15: =IFERROR(Model!M201+0,NA()) -> 0.18474892 | E15: =IFERROR(Model!R201+0,NA()) -> 0.19371429 | F15: =IFERROR(Model!W201+0,NA()) -> 0.18029294 | G15: =IFERROR(Model!X201+0,NA()) -> 0.22982444 | H15: =IFERROR(Model!Y201+0,NA()) -> 0.25136544 | I15: =IFERROR(Model!Z201+0,NA()) -> 0.26692429 | J15: =IFERROR(Model!AA201+0,NA()) -> 0.28287589 | K15: =IFERROR(Model!AB201+0,NA()) -> 0.29798891
C17: =C7 -> 2023 | D17: =D7 -> 2024 | E17: =E7 -> 2025 | F17: =F7 -> 2026E | G17: =G7 -> 2027E | H17: =H7 -> 2028E | I17: =I7 -> 2029E | J17: =J7 -> 2030E | K17: =K7 -> 2031E
B18: ROIC | C18: =IFERROR(Model!H329+0,NA()) -> 0.018013991 | D18: =IFERROR(Model!M329+0,NA()) -> 0.021991938 | E18: =IFERROR(Model!R329+0,NA()) -> 0.023640561 | F18: =IFERROR(Model!W329+0,NA()) -> 0.027197982 | G18: =IFERROR(Model!X329+0,NA()) -> 0.031976969 | H18: =IFERROR(Model!Y329+0,NA()) -> 0.037059097 | I18: =IFERROR(Model!Z329+0,NA()) -> 0.042515347 | J18: =IFERROR(Model!AA329+0,NA()) -> 0.048615522 | K18: =IFERROR(Model!AB329+0,NA()) -> 0.055146588
B19: RONTA | C19: =IFERROR(Model!H340+0,NA()) -> 2.138934 | D19: =IFERROR(Model!M340+0,NA()) -> 2.4647887 | E19: =IFERROR(Model!R340+0,NA()) -> 2.7334697 | F19: =IFERROR(Model!W340+0,NA()) -> 0.62460937 | G19: =IFERROR(Model!X340+0,NA()) -> 0.73192811 | H19: =IFERROR(Model!Y340+0,NA()) -> 1.1269825 | I19: =IFERROR(Model!Z340+0,NA()) -> 1.2727433 | J19: =IFERROR(Model!AA340+0,NA()) -> 1.3860319 | K19: =IFERROR(Model!AB340+0,NA()) -> 1.4954717
B20: Adj. EBITDA margin % | C20: =IFERROR(Model!H198+0,NA()) -> 0.4026936 | D20: =IFERROR(Model!M198+0,NA()) -> 0.40855549 | E20: =IFERROR(Model!R198+0,NA()) -> 0.40628571 | F20: =IFERROR(Model!W198+0,NA()) -> 0.40079893 | G20: =IFERROR(Model!X198+0,NA()) -> 0.40716967 | H20: =IFERROR(Model!Y198+0,NA()) -> 0.41401829 | I20: =IFERROR(Model!Z198+0,NA()) -> 0.42092257 | J20: =IFERROR(Model!AA198+0,NA()) -> 0.42772992 | K20: =IFERROR(Model!AB198+0,NA()) -> 0.43462122
B21: FCF margin % | C21: =IFERROR(Model!H236+0,NA()) -> 0.25252525 | D21: =IFERROR(Model!M236+0,NA()) -> 0.25542467 | E21: =IFERROR(Model!R236+0,NA()) -> 0.26342857 | F21: =IFERROR(Model!W236+0,NA()) -> 0.2091592 | G21: =IFERROR(Model!X236+0,NA()) -> 0.24504085 | H21: =IFERROR(Model!Y236+0,NA()) -> 0.25562561 | I21: =IFERROR(Model!Z236+0,NA()) -> 0.26126079 | J21: =IFERROR(Model!AA236+0,NA()) -> 0.264577 | K21: =IFERROR(Model!AB236+0,NA()) -> 0.26877206
