Workbook

Sheet Model
CF1: SCENARIO SWITCH ▼ (Bull / Base / Bear) — drives all scenario-linked forecast drivers
B2: Moody's Corporation (NYSE: MCO) — 3-Statement Financial Model | CF2: Base
B3: US GAAP as reported · USD millions (per-share data in USD; shares in millions) · Calendar fiscal year · Source: Moody's Forms 10-K / 10-Q, Form 8-K earnings releases (Ex. 99.1), SEC EDGAR (CIK 1059556); XBRL company facts; investor-relations releases (ir.moodys.com) are the same documents as filed on EDGAR
B4: Basis notes: as originally reported (10-K over the Q4 release for annual columns). Segments: MIS (ratings) and MA (analytics) since the Jan-2008 reorganisation (2006–07 revenue lines on the 2008 basis). MA lines on the current structure from 2021 (restated comparatives). Acquisitions: BvD Aug-17, Reis Oct-18, RDC Feb-20, RMS Sep-21; divestitures: MAKS Nov-19, Learning Solutions Q4-25, Regulatory Solutions Q2-26. Q3/Q4-26E calibrated to the FY26 guidance (22-Jul-2026). Share price $470.00 (user, 12-Oct-2026).
CH5: Forecast | CI5: Historical | CJ5: Historical | CK5: Historical
B6: (USDm) | C6: 2006 | D6: 2007 | E6: 2008 | F6: 2009 | G6: 2010 | H6: 2011 | I6: 2012 | J6: Q1/13 | K6: Q2/13 | L6: Q3/13 | M6: Q4/13 | N6: 2013 | O6: Q1/14 | P6: Q2/14 | Q6: Q3/14 | R6: Q4/14 | S6: 2014 | T6: Q1/15 | U6: Q2/15 | V6: Q3/15 | W6: Q4/15 | X6: 2015 | Y6: Q1/16 | Z6: Q2/16 | AA6: Q3/16 | AB6: Q4/16 | AC6: 2016 | AD6: Q1/17 | AE6: Q2/17 | AF6: Q3/17 | AG6: Q4/17 | AH6: 2017 | AI6: Q1/18 | AJ6: Q2/18 | AK6: Q3/18 | AL6: Q4/18 | AM6: 2018 | AN6: Q1/19 | AO6: Q2/19 | AP6: Q3/19 | AQ6: Q4/19 | AR6: 2019 | AS6: Q1/20 | AT6: Q2/20 | AU6: Q3/20 | AV6: Q4/20 | AW6: 2020 | AX6: Q1/21 | AY6: Q2/21 | AZ6: Q3/21 | BA6: Q4/21 | BB6: 2021 | BC6: Q1/22 | BD6: Q2/22 | BE6: Q3/22 | BF6: Q4/22 | BG6: 2022 | BH6: Q1/23 | BI6: Q2/23 | BJ6: Q3/23 | BK6: Q4/23 | BL6: 2023 | BM6: Q1/24 | BN6: Q2/24 | BO6: Q3/24 | BP6: Q4/24 | BQ6: 2024 | BR6: Q1/25 | BS6: Q2/25 | BT6: Q3/25 | BU6: Q4/25 | BV6: 2025 | BW6: Q1/26 | BX6: Q2/26 | BY6: Q3/26E | BZ6: Q4/26E | CA6: 2026E | CB6: 2027E | CC6: 2028E | CD6: 2029E | CE6: 2030E | CF6: Modelling Notes | CH6: 5Y CAGR | CI6: 5Y CAGR | CJ6: 10Y CAGR | CK6: 19Y CAGR
CH7: 25-'30 | CI7: 20-'25 | CJ7: 15-'25 | CK7: 06-'25
B8: SEGMENT P&L — MIS · MA (revenue by line of business × segment Adjusted Operating Margin) | CF8: SEGMENT BUILD — modelling logic (revenue by line → segment external revenue + intersegment revenue → × segment Adjusted Operating Margin = segment Adjusted Operating Income → Σ = Adjusted Operating Income (company measure) → GAAP P&L)
CN9: SCENARIO INPUT TABLE — driver assumptions per Bull / Base / Bear | CO9: Bull | CP9: Base | CQ9: Bear | CR9: Bull / Bear = Base + Δ (Δ inputs on each block header). Outlook block = high / mid / low of the FY26 guidance (22-Jul-2026).
B10: Moody's Investors Service (credit ratings; ratings revenue by line of business + MIS Other) | CF10: MIS — modelling logic
B11: Corporate Finance (CFG) | C11: 335.9 | D11: 411.5 | E11: 300.5 | F11: 408.2 | G11: 563.9 | H11: 652.1 | I11: 857.6 | J11: 258.3 | K11: 262.9 | L11: 233 | M11: 242.6 | N11: 996.8 | O11: 264.4 | P11: 320.9 | Q11: 260.7 | R11: 263.3 | S11: 1109.3 | T11: 298.7 | U11: 319.6 | V11: 248.3 | W11: 246.1 | X11: 1112.7 | Y11: 240.3 | Z11: 304.8 | AA11: 299.6 | AB11: 277.6 | AC11: 1122.3 | AD11: 352.8 | AE11: 355.8 | AF11: 350.2 | AG11: 333.9 | AH11: 1392.7 | AI11: 377.7 | AJ11: 377.6 | AK11: 296.1 | AL11: 282.7 | AM11: 1334.1 | AN11: 355.4 | AO11: 387.4 | AP11: 392 | AQ11: 362 | AR11: 1497 | AS11: 453 | AT11: 572 | AU11: 461 | AV11: 371 | AW11: 1857 | AX11: 605 | AY11: 550 | AZ11: 488 | BA11: 444 | BB11: 2087 | BC11: 417 | BD11: 322 | BE11: 277 | BF11: 253 | BG11: 1269 | BH11: 356 | BI11: 365 | BJ11: 346 | BK11: 337 | BL11: 1404 | BM11: 529 | BN11: 525 | BO11: 515 | BP11: 381 | BQ11: 1950 | BR11: 564 | BS11: 512 | BT11: 576 | BU11: 480 | BV11: 2132 | BW11: 633 | BX11: 651 | BY11: =BT11*(1+BY12) -> 591.97905 | BZ11: =BU11*(1+BZ12) -> 493.31588 | CA11: =SUM(BW11:BZ11) -> 2369.2949 | CB11: =CA11*(1+CB12) -> 2535.1456 | CC11: =CB11*(1+CC12) -> 2687.2543 | CD11: =CC11*(1+CD12) -> 2848.4896 | CE11: =CD11*(1+CE12) -> 2990.914 | CF11: External revenue by line as originally reported in each release. Q3/Q4-26E: prior-year quarter × (1 + growth). 2027E+: prior year × (1 + scenario lever). | CH11: =IFERROR((CE11/BV11)^(1/5)-1,"n/m") -> 0.070048214 | CI11: =IFERROR((BV11/AW11)^(1/5)-1,"n/m") -> 0.028004603 | CJ11: =IFERROR((BV11/X11)^(1/10)-1,"n/m") -> 0.067187946 | CK11: =IFERROR((BV11/C11)^(1/19)-1,"n/m") -> 0.10215051 | CN11: FY26 guidance — Q2-26 release (22-Jul-2026) | CO11: High | CP11: Mid | CQ11: Low | CR11: Revenue up high-single-digit %, adjusted operating margin 52–53%, adjusted diluted EPS $16.50–17.00 (raised from $16.40–17.00), diluted EPS $16.00–16.50, FCF $2.7–2.9bn, share repurchases up to $3.0bn, ETR 23–25%, net interest $220–240m; MIS revenue up high-single-digit % at ~65% margin; MA revenue up mid-single-digit % at 34–35%. Qualitative ranges are read as high-single-digit = 7–9% and mid-single-digit = 4–6% (model interpretation).
B12: y/y % | D12: =IF(AND(ISNUMBER(D11),ISNUMBER(C11)),IFERROR(D11/C11-1,""),"") -> 0.22506698 | E12: =IF(AND(ISNUMBER(E11),ISNUMBER(D11)),IFERROR(E11/D11-1,""),"") -> -0.26974484 | F12: =IF(AND(ISNUMBER(F11),ISNUMBER(E11)),IFERROR(F11/E11-1,""),"") -> 0.35840266 | G12: =IF(AND(ISNUMBER(G11),ISNUMBER(F11)),IFERROR(G11/F11-1,""),"") -> 0.38143067 | H12: =IF(AND(ISNUMBER(H11),ISNUMBER(G11)),IFERROR(H11/G11-1,""),"") -> 0.15641071 | I12: =IF(AND(ISNUMBER(I11),ISNUMBER(H11)),IFERROR(I11/H11-1,""),"") -> 0.31513572 | N12: =IF(AND(ISNUMBER(N11),ISNUMBER(I11)),IFERROR(N11/I11-1,""),"") -> 0.16231343 | O12: =IF(AND(ISNUMBER(O11),ISNUMBER(J11)),IFERROR(O11/J11-1,""),"") -> 0.02361595 | P12: =IF(AND(ISNUMBER(P11),ISNUMBER(K11)),IFERROR(P11/K11-1,""),"") -> 0.2206162 | Q12: =IF(AND(ISNUMBER(Q11),ISNUMBER(L11)),IFERROR(Q11/L11-1,""),"") -> 0.11888412 | R12: =IF(AND(ISNUMBER(R11),ISNUMBER(M11)),IFERROR(R11/M11-1,""),"") -> 0.085325639 | S12: =IF(AND(ISNUMBER(S11),ISNUMBER(N11)),IFERROR(S11/N11-1,""),"") -> 0.11286116 | T12: =IF(AND(ISNUMBER(T11),ISNUMBER(O11)),IFERROR(T11/O11-1,""),"") -> 0.12972769 | U12: =IF(AND(ISNUMBER(U11),ISNUMBER(P11)),IFERROR(U11/P11-1,""),"") -> -0.0040511063 | ... BX12: =IF(AND(ISNUMBER(BX11),ISNUMBER(BS11)),IFERROR(BX11/BS11-1,""),"") -> 0.27148438 | BY12: =BY13+$CA$120 -> 0.027741409 | BZ12: =BZ13+$CA$120 -> 0.027741409 | CA12: =IF(AND(ISNUMBER(CA11),ISNUMBER(BV11)),IFERROR(CA11/BV11-1,""),"") -> 0.11130156 | CB12: =CHOOSE(MATCH($CF$2,{"Bull","Base","Bear"},0),$CO$38,$CP$38,$CQ$38) -> 0.07 | CC12: =CHOOSE(MATCH($CF$2,{"Bull","Base","Bear"},0),$CO$39,$CP$39,$CQ$39) -> 0.06 | CD12: =CHOOSE(MATCH($CF$2,{"Bull","Base","Bear"},0),$CO$40,$CP$40,$CQ$40) -> 0.06 | CE12: =CHOOSE(MATCH($CF$2,{"Bull","Base","Bear"},0),$CO$41,$CP$41,$CQ$41) -> 0.05 | CF12: Q3/Q4-26E: 1H26 y/y growth of the line + MIS revenue-guidance calibration Δ (Group block). 2027E–2030E: scenario lever (table →). | CN12: FY26 MIS revenue growth | CO12: 0.09 | CP12: 0.08 | CQ12: 0.07 | CR12: Guided "increase in the high-single-digit percent range" (read as 7–9%). Drives the Q3/Q4-26E MIS revenue calibration.
B13: Q3/Q4-26E growth before calibration (1H26 y/y) | BY13: =IFERROR(SUM(BW11:BX11)/SUM(BR11:BS11)-1,0) -> 0.19330855 | BZ13: =IFERROR(SUM(BW11:BX11)/SUM(BR11:BS11)-1,0) -> 0.19330855 | CN13: FY26 MA revenue growth | CO13: 0.06 | CP13: 0.05 | CQ13: 0.04 | CR13: Guided "increase in the mid-single-digit percent range" (read as 4–6%; incl. ~4 pts inorganic drag from the Learning and Regulatory Solutions divestitures and ~(0.5) pts FX). Drives the MA calibration.
B14: Structured Finance (SFG) | C14: 872.6 | D14: 873.3 | E14: 411.2 | F14: 304.9 | G14: 290.8 | H14: 344.6 | I14: 381 | J14: 93 | K14: 97.2 | L14: 83.5 | M14: 108.8 | N14: 382.5 | O14: 95.3 | P14: 110.6 | Q14: 102.1 | R14: 118.5 | S14: 426.5 | T14: 101.3 | U14: 121.2 | V14: 112.5 | W14: 114.1 | X14: 449.1 | Y14: 90.6 | Z14: 111.5 | AA14: 104.2 | AB14: 130.5 | AC14: 436.8 | AD14: 100.2 | AE14: 119.2 | AF14: 128.3 | AG14: 147.8 | AH14: 495.5 | AI14: 129.7 | AJ14: 141.6 | AK14: 125.4 | AL14: 129.8 | AM14: 526.5 | AN14: 100.7 | AO14: 112.1 | AP14: 105.4 | AQ14: 109 | AR14: 427 | AS14: 96 | AT14: 81 | AU14: 88 | AV14: 97 | AW14: 362 | AX14: 116 | AY14: 140 | AZ14: 143 | BA14: 161 | BB14: 560 | BC14: 144 | BD14: 123 | BE14: 101 | BF14: 94 | BG14: 462 | BH14: 99 | BI14: 102 | BJ14: 102 | BK14: 102 | BL14: 405 | BM14: 114 | BN14: 131 | BO14: 135 | BP14: 138 | BQ14: 518 | BR14: 138 | BS14: 135 | BT14: 146 | BU14: 139 | BV14: 558 | BW14: 137 | BX14: 151 | BY14: =BT14*(1+BY15) -> 129.84918 | BZ14: =BU14*(1+BZ15) -> 123.62353 | CA14: =SUM(BW14:BZ14) -> 541.47271 | CB14: =CA14*(1+CB15) -> 568.54634 | CC14: =CB14*(1+CC15) -> 591.28819 | CD14: =CC14*(1+CD15) -> 614.93972 | CE14: =CD14*(1+CE15) -> 639.53731 | CH14: =IFERROR((CE14/BV14)^(1/5)-1,"n/m") -> 0.027652629 | CI14: =IFERROR((BV14/AW14)^(1/5)-1,"n/m") -> 0.090398199 | CJ14: =IFERROR((BV14/X14)^(1/10)-1,"n/m") -> 0.021948744 | CK14: =IFERROR((BV14/C14)^(1/19)-1,"n/m") -> -0.023257811 | CN14: FY26 adjusted diluted EPS ($) | CO14: 17 | CP14: 16.75 | CQ14: 16.5 | CR14: Guided $16.50–17.00. Drives the Q3/Q4-26E segment-margin calibration.
B15: y/y % | D15: =IF(AND(ISNUMBER(D14),ISNUMBER(C14)),IFERROR(D14/C14-1,""),"") -> 0.00080220032 | E15: =IF(AND(ISNUMBER(E14),ISNUMBER(D14)),IFERROR(E14/D14-1,""),"") -> -0.52914233 | F15: =IF(AND(ISNUMBER(F14),ISNUMBER(E14)),IFERROR(F14/E14-1,""),"") -> -0.25851167 | G15: =IF(AND(ISNUMBER(G14),ISNUMBER(F14)),IFERROR(G14/F14-1,""),"") -> -0.04624467 | H15: =IF(AND(ISNUMBER(H14),ISNUMBER(G14)),IFERROR(H14/G14-1,""),"") -> 0.18500688 | I15: =IF(AND(ISNUMBER(I14),ISNUMBER(H14)),IFERROR(I14/H14-1,""),"") -> 0.10562972 | N15: =IF(AND(ISNUMBER(N14),ISNUMBER(I14)),IFERROR(N14/I14-1,""),"") -> 0.0039370079 | O15: =IF(AND(ISNUMBER(O14),ISNUMBER(J14)),IFERROR(O14/J14-1,""),"") -> 0.024731183 | P15: =IF(AND(ISNUMBER(P14),ISNUMBER(K14)),IFERROR(P14/K14-1,""),"") -> 0.13786008 | Q15: =IF(AND(ISNUMBER(Q14),ISNUMBER(L14)),IFERROR(Q14/L14-1,""),"") -> 0.22275449 | R15: =IF(AND(ISNUMBER(R14),ISNUMBER(M14)),IFERROR(R14/M14-1,""),"") -> 0.089154412 | S15: =IF(AND(ISNUMBER(S14),ISNUMBER(N14)),IFERROR(S14/N14-1,""),"") -> 0.11503268 | T15: =IF(AND(ISNUMBER(T14),ISNUMBER(O14)),IFERROR(T14/O14-1,""),"") -> 0.062959077 | U15: =IF(AND(ISNUMBER(U14),ISNUMBER(P14)),IFERROR(U14/P14-1,""),"") -> 0.095840868 | ... BX15: =IF(AND(ISNUMBER(BX14),ISNUMBER(BS14)),IFERROR(BX14/BS14-1,""),"") -> 0.11851852 | BY15: =BY16+$CA$120 -> -0.11062209 | BZ15: =BZ16+$CA$120 -> -0.11062209 | CA15: =IF(AND(ISNUMBER(CA14),ISNUMBER(BV14)),IFERROR(CA14/BV14-1,""),"") -> -0.029618807 | CB15: =CHOOSE(MATCH($CF$2,{"Bull","Base","Bear"},0),$CO$43,$CP$43,$CQ$43) -> 0.05 | CC15: =CHOOSE(MATCH($CF$2,{"Bull","Base","Bear"},0),$CO$44,$CP$44,$CQ$44) -> 0.04 | CD15: =CHOOSE(MATCH($CF$2,{"Bull","Base","Bear"},0),$CO$45,$CP$45,$CQ$45) -> 0.04 | CE15: =CHOOSE(MATCH($CF$2,{"Bull","Base","Bear"},0),$CO$46,$CP$46,$CQ$46) -> 0.04 | CN15: FY26 MCO revenue growth — memo | CO15: 0.09 | CP15: 0.08 | CQ15: 0.07 | CR15: Guided "high-single-digit" (information row; the model total follows the segment end-points).
B16: Q3/Q4-26E growth before calibration (1H26 y/y) | BY16: =IFERROR(SUM(BW14:BX14)/SUM(BR14:BS14)-1,0) -> 0.054945055 | BZ16: =IFERROR(SUM(BW14:BX14)/SUM(BR14:BS14)-1,0) -> 0.054945055 | CN16: FY26 Adjusted Operating Margin — memo | CO16: 0.53 | CP16: 0.525 | CQ16: 0.52 | CR16: Guided 52–53% (information row).
B17: Financial Institutions (FIG) | C17: 233.1 | D17: 274.3 | E17: 263 | F17: 258.5 | G17: 278.7 | H17: 294.9 | I17: 325.5 | J17: 86.5 | K17: 84.5 | L17: 78.9 | M17: 88.9 | N17: 338.8 | O17: 85.4 | P17: 92.2 | Q17: 91.8 | R17: 85.3 | S17: 354.7 | T17: 93.8 | U17: 90.4 | V17: 89.5 | W17: 91.9 | X17: 365.6 | Y17: 94.9 | Z17: 89.7 | AA17: 95.8 | AB17: 88.5 | AC17: 368.9 | AD17: 112.3 | AE17: 102.4 | AF17: 102.1 | AG17: 119 | AH17: 435.8 | AI17: 114.3 | AJ17: 120.6 | AK17: 119.5 | AL17: 87.3 | AM17: 441.7 | AN17: 115.8 | AO17: 125.2 | AP17: 120.5 | AQ17: 115 | AR17: 476 | AS17: 125 | AT17: 142 | AU17: 134 | AV17: 129 | AW17: 530 | AX17: 162 | AY17: 150 | AZ17: 153 | BA17: 137 | BB17: 602 | BC17: 131 | BD17: 128 | BE17: 109 | BF17: 123 | BG17: 491 | BH17: 142 | BI17: 145 | BJ17: 126 | BK17: 132 | BL17: 545 | BM17: 195 | BN17: 195 | BO17: 170 | BP17: 167 | BQ17: 727 | BR17: 191 | BS17: 191 | BT17: 208 | BU17: 169 | BV17: 759 | BW17: 194 | BX17: 222 | BY17: =BT17*(1+BY18) -> 192.07512 | BZ17: =BU17*(1+BZ18) -> 156.06104 | CA17: =SUM(BW17:BZ17) -> 764.13616 | CB17: =CA17*(1+CB18) -> 809.98433 | CC17: =CB17*(1+CC18) -> 850.48355 | CD17: =CC17*(1+CD18) -> 893.00773 | CE17: =CD17*(1+CE18) -> 937.65811 | CH17: =IFERROR((CE17/BV17)^(1/5)-1,"n/m") -> 0.043183112 | CI17: =IFERROR((BV17/AW17)^(1/5)-1,"n/m") -> 0.074467247 | CJ17: =IFERROR((BV17/X17)^(1/10)-1,"n/m") -> 0.07578023 | CK17: =IFERROR((BV17/C17)^(1/19)-1,"n/m") -> 0.064104266 | CN17: FY26 MIS Adjusted Operating Margin — memo | CO17: 0.65 | CP17: 0.65 | CQ17: 0.65 | CR17: Guided ~65% (information row).
B18: y/y % | D18: =IF(AND(ISNUMBER(D17),ISNUMBER(C17)),IFERROR(D17/C17-1,""),"") -> 0.17674818 | E18: =IF(AND(ISNUMBER(E17),ISNUMBER(D17)),IFERROR(E17/D17-1,""),"") -> -0.041195771 | F18: =IF(AND(ISNUMBER(F17),ISNUMBER(E17)),IFERROR(F17/E17-1,""),"") -> -0.017110266 | G18: =IF(AND(ISNUMBER(G17),ISNUMBER(F17)),IFERROR(G17/F17-1,""),"") -> 0.078143133 | H18: =IF(AND(ISNUMBER(H17),ISNUMBER(G17)),IFERROR(H17/G17-1,""),"") -> 0.058127018 | I18: =IF(AND(ISNUMBER(I17),ISNUMBER(H17)),IFERROR(I17/H17-1,""),"") -> 0.10376399 | N18: =IF(AND(ISNUMBER(N17),ISNUMBER(I17)),IFERROR(N17/I17-1,""),"") -> 0.040860215 | O18: =IF(AND(ISNUMBER(O17),ISNUMBER(J17)),IFERROR(O17/J17-1,""),"") -> -0.012716763 | P18: =IF(AND(ISNUMBER(P17),ISNUMBER(K17)),IFERROR(P17/K17-1,""),"") -> 0.09112426 | Q18: =IF(AND(ISNUMBER(Q17),ISNUMBER(L17)),IFERROR(Q17/L17-1,""),"") -> 0.1634981 | R18: =IF(AND(ISNUMBER(R17),ISNUMBER(M17)),IFERROR(R17/M17-1,""),"") -> -0.040494938 | S18: =IF(AND(ISNUMBER(S17),ISNUMBER(N17)),IFERROR(S17/N17-1,""),"") -> 0.046930342 | T18: =IF(AND(ISNUMBER(T17),ISNUMBER(O17)),IFERROR(T17/O17-1,""),"") -> 0.098360656 | U18: =IF(AND(ISNUMBER(U17),ISNUMBER(P17)),IFERROR(U17/P17-1,""),"") -> -0.019522777 | ... BX18: =IF(AND(ISNUMBER(BX17),ISNUMBER(BS17)),IFERROR(BX17/BS17-1,""),"") -> 0.16230366 | BY18: =BY19+$CA$120 -> -0.076561906 | BZ18: =BZ19+$CA$120 -> -0.076561906 | CA18: =IF(AND(ISNUMBER(CA17),ISNUMBER(BV17)),IFERROR(CA17/BV17-1,""),"") -> 0.0067670113 | CB18: =CHOOSE(MATCH($CF$2,{"Bull","Base","Bear"},0),$CO$48,$CP$48,$CQ$48) -> 0.06 | CC18: =CHOOSE(MATCH($CF$2,{"Bull","Base","Bear"},0),$CO$49,$CP$49,$CQ$49) -> 0.05 | CD18: =CHOOSE(MATCH($CF$2,{"Bull","Base","Bear"},0),$CO$50,$CP$50,$CQ$50) -> 0.05 | CE18: =CHOOSE(MATCH($CF$2,{"Bull","Base","Bear"},0),$CO$51,$CP$51,$CQ$51) -> 0.05 | CN18: FY26 MA Adjusted Operating Margin — memo | CO18: 0.35 | CP18: 0.345 | CQ18: 0.34 | CR18: Guided 34–35% (information row).
B19: Q3/Q4-26E growth before calibration (1H26 y/y) | BY19: =IFERROR(SUM(BW17:BX17)/SUM(BR17:BS17)-1,0) -> 0.089005236 | BZ19: =IFERROR(SUM(BW17:BX17)/SUM(BR17:BS17)-1,0) -> 0.089005236 | CN19: FY26 diluted EPS ($) — memo | CO19: 16.5 | CP19: 16.25 | CQ19: 16 | CR19: Guided $16.00–16.50 (information row).
B20: Public, Project & Infrastructure Finance (PPIF) | C20: 198.2 | D20: 220.8 | E20: 230 | F20: 246.1 | G20: 271.6 | H20: 277.3 | I20: 322.7 | J20: 83.4 | K20: 92.7 | L20: 82.7 | M20: 82.5 | N20: 341.3 | O20: 80.7 | P20: 98 | Q20: 88.5 | R20: 90.1 | S20: 357.3 | T20: 100.7 | U20: 99.9 | V20: 90.6 | W20: 85.2 | X20: 376.4 | Y20: 91.5 | Z20: 112.3 | AA20: 105.2 | AB20: 103.2 | AC20: 412.2 | AD20: 98.1 | AE20: 104.7 | AF20: 109.2 | AG20: 119.3 | AH20: 431.3 | AI20: 93.2 | AJ20: 108.1 | AK20: 99 | AL20: 90.8 | AM20: 391.1 | AN20: 92.7 | AO20: 108.6 | AP20: 119.8 | AQ20: 125 | AR20: 446 | AS20: 109 | AT20: 133 | AU20: 133 | AV20: 121 | AW20: 496 | AX20: 143 | AY20: 130 | AZ20: 130 | BA20: 118 | BB20: 521 | BC20: 123 | BD20: 122 | BE20: 92 | BF20: 94 | BG20: 431 | BH20: 129 | BI20: 127 | BJ20: 115 | BK20: 105 | BL20: 476 | BM20: 141 | BN20: 154 | BO20: 154 | BP20: 115 | BQ20: 564 | BR20: 163 | BS20: 162 | BT20: 161 | BU20: 149 | BV20: 635 | BW20: 176 | BX20: 224 | BY20: =BT20*(1+BY21) -> 171.49754 | BZ20: =BU20*(1+BZ21) -> 158.71511 | CA20: =SUM(BW20:BZ20) -> 730.21265 | CB20: =CA20*(1+CB21) -> 774.02541 | CC20: =CB20*(1+CC21) -> 820.46693 | CD20: =CC20*(1+CD21) -> 861.49028 | CE20: =CD20*(1+CE21) -> 904.56479 | CH20: =IFERROR((CE20/BV20)^(1/5)-1,"n/m") -> 0.073329809 | CI20: =IFERROR((BV20/AW20)^(1/5)-1,"n/m") -> 0.050650834 | CJ20: =IFERROR((BV20/X20)^(1/10)-1,"n/m") -> 0.053688915 | CK20: =IFERROR((BV20/C20)^(1/19)-1,"n/m") -> 0.063198155 | CN20: FY26 Free Cash Flow ($m) — memo | CO20: 2900 | CP20: 2800 | CQ20: 2700 | CR20: Guided $2.7–2.9bn (operating cash flow $3.15–3.35bn less capex ~$450m) (information row).
B21: y/y % | D21: =IF(AND(ISNUMBER(D20),ISNUMBER(C20)),IFERROR(D20/C20-1,""),"") -> 0.11402624 | E21: =IF(AND(ISNUMBER(E20),ISNUMBER(D20)),IFERROR(E20/D20-1,""),"") -> 0.041666667 | F21: =IF(AND(ISNUMBER(F20),ISNUMBER(E20)),IFERROR(F20/E20-1,""),"") -> 0.07 | G21: =IF(AND(ISNUMBER(G20),ISNUMBER(F20)),IFERROR(G20/F20-1,""),"") -> 0.10361642 | H21: =IF(AND(ISNUMBER(H20),ISNUMBER(G20)),IFERROR(H20/G20-1,""),"") -> 0.020986745 | I21: =IF(AND(ISNUMBER(I20),ISNUMBER(H20)),IFERROR(I20/H20-1,""),"") -> 0.1637216 | N21: =IF(AND(ISNUMBER(N20),ISNUMBER(I20)),IFERROR(N20/I20-1,""),"") -> 0.057638674 | O21: =IF(AND(ISNUMBER(O20),ISNUMBER(J20)),IFERROR(O20/J20-1,""),"") -> -0.032374101 | P21: =IF(AND(ISNUMBER(P20),ISNUMBER(K20)),IFERROR(P20/K20-1,""),"") -> 0.057173679 | Q21: =IF(AND(ISNUMBER(Q20),ISNUMBER(L20)),IFERROR(Q20/L20-1,""),"") -> 0.070133011 | R21: =IF(AND(ISNUMBER(R20),ISNUMBER(M20)),IFERROR(R20/M20-1,""),"") -> 0.092121212 | S21: =IF(AND(ISNUMBER(S20),ISNUMBER(N20)),IFERROR(S20/N20-1,""),"") -> 0.046879578 | T21: =IF(AND(ISNUMBER(T20),ISNUMBER(O20)),IFERROR(T20/O20-1,""),"") -> 0.24783147 | U21: =IF(AND(ISNUMBER(U20),ISNUMBER(P20)),IFERROR(U20/P20-1,""),"") -> 0.019387755 | ... BX21: =IF(AND(ISNUMBER(BX20),ISNUMBER(BS20)),IFERROR(BX20/BS20-1,""),"") -> 0.38271605 | BY21: =BY22+$CA$120 -> 0.06520209 | BZ21: =BZ22+$CA$120 -> 0.06520209 | CA21: =IF(AND(ISNUMBER(CA20),ISNUMBER(BV20)),IFERROR(CA20/BV20-1,""),"") -> 0.14994118 | CB21: =CHOOSE(MATCH($CF$2,{"Bull","Base","Bear"},0),$CO$53,$CP$53,$CQ$53) -> 0.06 | CC21: =CHOOSE(MATCH($CF$2,{"Bull","Base","Bear"},0),$CO$54,$CP$54,$CQ$54) -> 0.06 | CD21: =CHOOSE(MATCH($CF$2,{"Bull","Base","Bear"},0),$CO$55,$CP$55,$CQ$55) -> 0.05 | CE21: =CHOOSE(MATCH($CF$2,{"Bull","Base","Bear"},0),$CO$56,$CP$56,$CQ$56) -> 0.05 | CN21: 2H26E share repurchases ($m) | CO21: 835 | CP21: 685 | CQ21: 535 | CR21: 1H26 $2,165m (treasury shares); FY26 guidance "up to $3.0bn" → 2H up to $835m (high), $2.85bn FY (mid), $2.7bn FY (low). $1.8bn authorization remaining at 30-Jun-2026.
B22: Q3/Q4-26E growth before calibration (1H26 y/y) | BY22: =IFERROR(SUM(BW20:BX20)/SUM(BR20:BS20)-1,0) -> 0.23076923 | BZ22: =IFERROR(SUM(BW20:BX20)/SUM(BR20:BS20)-1,0) -> 0.23076923
B23: MIS Other (ICRA non-ratings, data / research) | R23: 7.9 | S23: 18 | T23: 7.8 | U23: 8.1 | V23: 7.2 | W23: 7.3 | X23: 30.4 | Y23: 7.8 | Z23: 7.3 | AA23: 7.5 | AB23: 8 | AC23: 30.6 | AD23: 4.8 | AE23: 4.6 | AF23: 4.4 | AG23: 4.7 | AH23: 18.5 | AI23: 5 | AJ23: 4.4 | AK23: 4.8 | AL23: 4.8 | AM23: 19 | AN23: 5.5 | AO23: 5.1 | AP23: 8.9 | AQ23: 9 | AR23: 29 | AS23: 11 | AT23: 10 | AU23: 9 | AV23: 17 | AW23: 47 | AX23: 10 | AY23: 10 | AZ23: 11 | BA23: 11 | BB23: 42 | BC23: 12 | BD23: 11 | BE23: 11 | BF23: 12 | BG23: 46 | BH23: 7 | BI23: 8 | BJ23: 7 | BK23: 8 | BL23: 30 | BM23: 8 | BN23: 10 | BO23: 8 | BP23: 8 | BQ23: 34 | BR23: 9 | BS23: 10 | BT23: 7 | BU23: 9 | BV23: 35 | BW23: 13 | BX23: 12 | BY23: =BT23*(1+BY24) -> 8.0515563 | BZ23: =BU23*(1+BZ24) -> 10.352001 | CA23: =SUM(BW23:BZ23) -> 43.403557 | CB23: =CA23*(1+CB24) -> 46.007771 | CC23: =CB23*(1+CC24) -> 48.308159 | CD23: =CC23*(1+CD24) -> 50.723567 | CE23: =CD23*(1+CE24) -> 53.259746 | CN23: Q3/26E–Q4/26E and FY26 point estimates (all cases)
B24: y/y % | D24: =IF(AND(ISNUMBER(D23),ISNUMBER(C23)),IFERROR(D23/C23-1,""),"") | E24: =IF(AND(ISNUMBER(E23),ISNUMBER(D23)),IFERROR(E23/D23-1,""),"") | F24: =IF(AND(ISNUMBER(F23),ISNUMBER(E23)),IFERROR(F23/E23-1,""),"") | G24: =IF(AND(ISNUMBER(G23),ISNUMBER(F23)),IFERROR(G23/F23-1,""),"") | H24: =IF(AND(ISNUMBER(H23),ISNUMBER(G23)),IFERROR(H23/G23-1,""),"") | I24: =IF(AND(ISNUMBER(I23),ISNUMBER(H23)),IFERROR(I23/H23-1,""),"") | N24: =IF(AND(ISNUMBER(N23),ISNUMBER(I23)),IFERROR(N23/I23-1,""),"") | O24: =IF(AND(ISNUMBER(O23),ISNUMBER(J23)),IFERROR(O23/J23-1,""),"") | P24: =IF(AND(ISNUMBER(P23),ISNUMBER(K23)),IFERROR(P23/K23-1,""),"") | Q24: =IF(AND(ISNUMBER(Q23),ISNUMBER(L23)),IFERROR(Q23/L23-1,""),"") | R24: =IF(AND(ISNUMBER(R23),ISNUMBER(M23)),IFERROR(R23/M23-1,""),"") | S24: =IF(AND(ISNUMBER(S23),ISNUMBER(N23)),IFERROR(S23/N23-1,""),"") | T24: =IF(AND(ISNUMBER(T23),ISNUMBER(O23)),IFERROR(T23/O23-1,""),"") | U24: =IF(AND(ISNUMBER(U23),ISNUMBER(P23)),IFERROR(U23/P23-1,""),"") | ... BX24: =IF(AND(ISNUMBER(BX23),ISNUMBER(BS23)),IFERROR(BX23/BS23-1,""),"") -> 0.2 | BY24: =BY25+$CA$120 -> 0.15022233 | BZ24: =BZ25+$CA$120 -> 0.15022233 | CA24: =IF(AND(ISNUMBER(CA23),ISNUMBER(BV23)),IFERROR(CA23/BV23-1,""),"") -> 0.24010164 | CB24: =CHOOSE(MATCH($CF$2,{"Bull","Base","Bear"},0),$CO$58,$CP$58,$CQ$58) -> 0.06 | CC24: =CHOOSE(MATCH($CF$2,{"Bull","Base","Bear"},0),$CO$59,$CP$59,$CQ$59) -> 0.05 | CD24: =CHOOSE(MATCH($CF$2,{"Bull","Base","Bear"},0),$CO$60,$CP$60,$CQ$60) -> 0.05 | CE24: =CHOOSE(MATCH($CF$2,{"Bull","Base","Bear"},0),$CO$61,$CP$61,$CQ$61) -> 0.05 | CN24: Q3/Q4-26E interest expense, net (per quarter, $m; expense −) | CP24: -53 | CR24: FY26 guidance $220–240m (mid $230m) − 1H26 $124m = $106m for 2H.
B25: Q3/Q4-26E growth before calibration (1H26 y/y) | BY25: =IFERROR(SUM(BW23:BX23)/SUM(BR23:BS23)-1,0) -> 0.31578947 | BZ25: =IFERROR(SUM(BW23:BX23)/SUM(BR23:BS23)-1,0) -> 0.31578947 | CN25: Q3/Q4-26E other non-operating income, net (per quarter, $m) | CP25: 0 | CR25: Guided non-operating income $70–90m incl. interest and divestiture gains → other non-operating ≈ nil in 2H (1H26 +$16m).
B26: MIS revenue not split on the current lines (history before the current line structure; derived) | C26: =IF(ISNUMBER(C30),C30-(N(C11)+N(C14)+N(C17)+N(C20)+N(C23)),"") -> 0 | D26: =IF(ISNUMBER(D30),D30-(N(D11)+N(D14)+N(D17)+N(D20)+N(D23)),"") -> 0 | E26: =IF(ISNUMBER(E30),E30-(N(E11)+N(E14)+N(E17)+N(E20)+N(E23)),"") -> 0 | F26: =IF(ISNUMBER(F30),F30-(N(F11)+N(F14)+N(F17)+N(F20)+N(F23)),"") -> 0 | G26: =IF(ISNUMBER(G30),G30-(N(G11)+N(G14)+N(G17)+N(G20)+N(G23)),"") -> 0 | H26: =IF(ISNUMBER(H30),H30-(N(H11)+N(H14)+N(H17)+N(H20)+N(H23)),"") -> 0 | I26: =IF(ISNUMBER(I30),I30-(N(I11)+N(I14)+N(I17)+N(I20)+N(I23)),"") -> 0 | J26: =IF(ISNUMBER(J30),J30-(N(J11)+N(J14)+N(J17)+N(J20)+N(J23)),"") -> 0 | ... BX26: =IF(ISNUMBER(BX30),BX30-(N(BX11)+N(BX14)+N(BX17)+N(BX20)+N(BX23)),"") -> 0 | BY26: =0 -> 0 | BZ26: =0 -> 0 | CA26: =SUM(BW26:BZ26) -> 0 | CB26: =0 -> 0 | CC26: =0 -> 0 | CD26: =0 -> 0 | CE26: =0 -> 0 | CF26: Consolidated segment revenue less the current lines: carries the periods before each line was first published (MIS Other from 2013; MA lines on the 2022 / 2024 bases; legacy MA lines are memo rows below). | CN26: Q4/26E contingent gain on the Regulatory Solutions divestiture ($m) | CP26: 119 | CR26: Up to $119m of contingent consideration payable on post-closing conditions in 2H26 (Q2-26 10-Q); the FY26 EPS bridge gain of ~$(1.25) less the Q2 $(0.72) implies ~$0.53 net ≈ $119m pre-tax. Timing assumed Q4.
B27: MIS — external revenue | C27: =IF(ISNUMBER(C30),N(C11)+N(C14)+N(C17)+N(C20)+N(C23)+C26,"") -> 1639.8 | D27: =IF(ISNUMBER(D30),N(D11)+N(D14)+N(D17)+N(D20)+N(D23)+D26,"") -> 1779.9 | E27: =IF(ISNUMBER(E30),N(E11)+N(E14)+N(E17)+N(E20)+N(E23)+E26,"") -> 1204.7 | F27: =IF(ISNUMBER(F30),N(F11)+N(F14)+N(F17)+N(F20)+N(F23)+F26,"") -> 1217.7 | G27: =IF(ISNUMBER(G30),N(G11)+N(G14)+N(G17)+N(G20)+N(G23)+G26,"") -> 1405 | H27: =IF(ISNUMBER(H30),N(H11)+N(H14)+N(H17)+N(H20)+N(H23)+H26,"") -> 1568.9 | I27: =IF(ISNUMBER(I30),N(I11)+N(I14)+N(I17)+N(I20)+N(I23)+I26,"") -> 1886.8 | J27: =IF(ISNUMBER(J30),N(J11)+N(J14)+N(J17)+N(J20)+N(J23)+J26,"") -> 521.2 | ... BX27: =IF(ISNUMBER(BX30),N(BX11)+N(BX14)+N(BX17)+N(BX20)+N(BX23)+BX26,"") -> 1260 | BY27: =BY11+BY14+BY17+BY20+BY23 -> 1093.4524 | BZ27: =BZ11+BZ14+BZ17+BZ20+BZ23 -> 942.06756 | CA27: =SUM(BW27:BZ27) -> 4448.52 | CB27: =CB11+CB14+CB17+CB20+CB23 -> 4733.7094 | CC27: =CC11+CC14+CC17+CC20+CC23 -> 4997.8011 | CD27: =CD11+CD14+CD17+CD20+CD23 -> 5268.6509 | CE27: =CE11+CE14+CE17+CE20+CE23 -> 5525.934 | CF27: Σ lines (+ not-split residual in history) = segment external revenue as reported. | CH27: =IFERROR((CE27/BV27)^(1/5)-1,"n/m") -> 0.060529566 | CI27: =IFERROR((BV27/AW27)^(1/5)-1,"n/m") -> 0.045842757 | CJ27: =IFERROR((BV27/X27)^(1/10)-1,"n/m") -> 0.058437876 | CK27: =IFERROR((BV27/C27)^(1/19)-1,"n/m") -> 0.049669745 | CN27: Q3/Q4-26E acquired-intangible amortization (per quarter, $m) | CP27: 50.5 | CR27: FY2025 10-K schedule 2026 $207m − 1H26 $106m, split evenly.
B28: Segment revenue y/y % | D28: =IF(AND(ISNUMBER(D27),ISNUMBER(C27)),IFERROR(D27/C27-1,""),"") -> 0.085437248 | E28: =IF(AND(ISNUMBER(E27),ISNUMBER(D27)),IFERROR(E27/D27-1,""),"") -> -0.32316422 | F28: =IF(AND(ISNUMBER(F27),ISNUMBER(E27)),IFERROR(F27/E27-1,""),"") -> 0.010791068 | G28: =IF(AND(ISNUMBER(G27),ISNUMBER(F27)),IFERROR(G27/F27-1,""),"") -> 0.15381457 | H28: =IF(AND(ISNUMBER(H27),ISNUMBER(G27)),IFERROR(H27/G27-1,""),"") -> 0.1166548 | I28: =IF(AND(ISNUMBER(I27),ISNUMBER(H27)),IFERROR(I27/H27-1,""),"") -> 0.20262604 | N28: =IF(AND(ISNUMBER(N27),ISNUMBER(I27)),IFERROR(N27/I27-1,""),"") -> 0.091477634 | O28: =IF(AND(ISNUMBER(O27),ISNUMBER(J27)),IFERROR(O27/J27-1,""),"") -> 0.0088257866 | P28: =IF(AND(ISNUMBER(P27),ISNUMBER(K27)),IFERROR(P27/K27-1,""),"") -> 0.1570817 | Q28: =IF(AND(ISNUMBER(Q27),ISNUMBER(L27)),IFERROR(Q27/L27-1,""),"") -> 0.13595482 | R28: =IF(AND(ISNUMBER(R27),ISNUMBER(M27)),IFERROR(R27/M27-1,""),"") -> 0.080910482 | S28: =IF(AND(ISNUMBER(S27),ISNUMBER(N27)),IFERROR(S27/N27-1,""),"") -> 0.10022337 | T28: =IF(AND(ISNUMBER(T27),ISNUMBER(O27)),IFERROR(T27/O27-1,""),"") -> 0.14549258 | U28: =IF(AND(ISNUMBER(U27),ISNUMBER(P27)),IFERROR(U27/P27-1,""),"") -> 0.028148625 | ... CA28: =IF(AND(ISNUMBER(CA27),ISNUMBER(BV27)),IFERROR(CA27/BV27-1,""),"") -> 0.08 | CB28: =IF(AND(ISNUMBER(CB27),ISNUMBER(CA27)),IFERROR(CB27/CA27-1,""),"") -> 0.064108832 | CC28: =IF(AND(ISNUMBER(CC27),ISNUMBER(CB27)),IFERROR(CC27/CB27-1,""),"") -> 0.055789592 | CD28: =IF(AND(ISNUMBER(CD27),ISNUMBER(CC27)),IFERROR(CD27/CC27-1,""),"") -> 0.054193777 | CE28: =IF(AND(ISNUMBER(CE27),ISNUMBER(CD27)),IFERROR(CE27/CD27-1,""),"") -> 0.048832833 | CN28: Q3/Q4-26E other depreciation & amortization (per quarter, $m) | CP28: 68 | CR28: D&A guided ~6% of revenue; 1H26 other D&A $142m ($71m/qtr) → $68m/qtr with amortization ≈ 6.1% of FY revenue.
B29: % of total revenue | C29: =IF(AND(ISNUMBER(C27),ISNUMBER(C110)),IFERROR(C27/C110,""),"") -> 0.80496785 | D29: =IF(AND(ISNUMBER(D27),ISNUMBER(D110)),IFERROR(D27/D110,""),"") -> 0.78791501 | E29: =IF(AND(ISNUMBER(E27),ISNUMBER(E110)),IFERROR(E27/E110,""),"") -> 0.68628233 | F29: =IF(AND(ISNUMBER(F27),ISNUMBER(F110)),IFERROR(F27/F110,""),"") -> 0.67755397 | G29: =IF(AND(ISNUMBER(G27),ISNUMBER(G110)),IFERROR(G27/G110,""),"") -> 0.69143701 | H29: =IF(AND(ISNUMBER(H27),ISNUMBER(H110)),IFERROR(H27/H110,""),"") -> 0.68790284 | I29: =IF(AND(ISNUMBER(I27),ISNUMBER(I110)),IFERROR(I27/I110,""),"") -> 0.69105959 | J29: =IF(AND(ISNUMBER(J27),ISNUMBER(J110)),IFERROR(J27/J110,""),"") -> 0.71221645 | ... CE29: =IF(AND(ISNUMBER(CE27),ISNUMBER(CE110)),IFERROR(CE27/CE110,""),"") -> 0.51985742 | CH29: =IFERROR(AVERAGE(CA29,CB29,CC29,CD29,CE29),"n/m") -> 0.53065065 | CI29: =IFERROR(AVERAGE(BB29,BG29,BL29,BQ29,BV29),"n/m") -> 0.531782 | CJ29: =IFERROR(AVERAGE(AC29,AH29,AM29,AR29,AW29,BB29,BG29,BL29,BQ29,BV29),"n/m") -> 0.57952949 | CK29: =IFERROR(AVERAGE(C29,D29,E29,F29,G29,H29,I29,N29,S29,X29,AC29,AH29,AM29,AR29,AW29,BB29,BG29,BL29,BQ29,BV29),"n/m") -> 0.64323274 | CN29: Q3/Q4-26E restructuring (per quarter, $m) | CP29: 30 | CR29: Guided ~1.5% of revenue (≈ $118m) − 1H26 $59m ≈ $59m for 2H (programme expanded Jul-2026 to $300–350m total).
B30: Memo: MIS external revenue as reported | C30: 1639.8 | D30: 1779.9 | E30: 1204.7 | F30: 1217.7 | G30: 1405 | H30: 1568.9 | I30: 1886.8 | J30: 521.2 | K30: 537.3 | L30: 478.1 | M30: 522.8 | N30: 2059.4 | O30: 525.8 | P30: 621.7 | Q30: 543.1 | R30: 565.1 | S30: 2265.8 | T30: 602.3 | U30: 639.2 | V30: 548.1 | W30: 544.6 | X30: 2334.2 | Y30: 525.1 | Z30: 625.6 | AA30: 612.3 | AB30: 607.8 | AC30: 2370.8 | AD30: 668.2 | AE30: 686.7 | AF30: 694.2 | AG30: 724.7 | AH30: 2773.8 | AI30: 719.9 | AJ30: 752.3 | AK30: 644.8 | AL30: 595.4 | AM30: 2712.4 | AN30: 670.1 | AO30: 738.4 | AP30: 746.6 | AQ30: 720 | AR30: 2875 | AS30: 794 | AT30: 938 | AU30: 825 | AV30: 735 | AW30: 3292 | AX30: 1036 | AY30: 980 | AZ30: 925 | BA30: 871 | BB30: 3812 | BC30: 827 | BD30: 706 | BE30: 590 | BF30: 576 | BG30: 2699 | BH30: 733 | BI30: 747 | BJ30: 696 | BK30: 684 | BL30: 2860 | BM30: 987 | BN30: 1015 | BO30: 982 | BP30: 809 | BQ30: 3793 | BR30: 1065 | BS30: 1010 | BT30: 1098 | BU30: 946 | BV30: 4119 | BW30: 1153 | BX30: 1260 | CN30: Q3/Q4-26E other items excluded from Adjusted Operating Income (per quarter, $m) | CP30: 11.5 | CR30: Reserve for an international non-income tax obligation ~0.5% of revenue (1H26 $36m) and duplicate rent (NY HQ; EPS bridge ~$0.10 ≈ $22m pre-tax for FY; 1H26 $2m).
B31: Check: MIS line build vs reported (should be 0) | C31: =IF(AND(ISNUMBER(C27),ISNUMBER(C30)),IF(ABS(C27-C30)<=0.6,0,ROUND(C27-C30,1)),"") -> 0 | D31: =IF(AND(ISNUMBER(D27),ISNUMBER(D30)),IF(ABS(D27-D30)<=0.6,0,ROUND(D27-D30,1)),"") -> 0 | E31: =IF(AND(ISNUMBER(E27),ISNUMBER(E30)),IF(ABS(E27-E30)<=0.6,0,ROUND(E27-E30,1)),"") -> 0 | F31: =IF(AND(ISNUMBER(F27),ISNUMBER(F30)),IF(ABS(F27-F30)<=0.6,0,ROUND(F27-F30,1)),"") -> 0 | G31: =IF(AND(ISNUMBER(G27),ISNUMBER(G30)),IF(ABS(G27-G30)<=0.6,0,ROUND(G27-G30,1)),"") -> 0 | H31: =IF(AND(ISNUMBER(H27),ISNUMBER(H30)),IF(ABS(H27-H30)<=0.6,0,ROUND(H27-H30,1)),"") -> 0 | I31: =IF(AND(ISNUMBER(I27),ISNUMBER(I30)),IF(ABS(I27-I30)<=0.6,0,ROUND(I27-I30,1)),"") -> 0 | J31: =IF(AND(ISNUMBER(J27),ISNUMBER(J30)),IF(ABS(J27-J30)<=0.6,0,ROUND(J27-J30,1)),"") -> 0 | ... BX31: =IF(AND(ISNUMBER(BX27),ISNUMBER(BX30)),IF(ABS(BX27-BX30)<=0.6,0,ROUND(BX27-BX30,1)),"") -> 0 | CN31: Q3/Q4-26E tax rate (GAAP and on adjusting items) | CP31: 0.24 | CR31: FY26 guidance 23–25%; 1H26 24.5%.
B32: Memo: MIS recurring revenue (as reported) | P32: 218.9 | Q32: 216.6 | R32: 226.7 | S32: 882.5 | T32: 221.4 | U32: 227 | V32: 231.8 | W32: 222 | X32: 901.8 | Y32: 230.6 | Z32: 236.4 | AA32: 229.6 | AB32: 233.3 | AC32: 929.8 | AD32: 237.2 | AE32: 237.6 | AF32: 243.7 | AG32: 247.5 | AH32: 966 | AI32: 256.9 | AJ32: 256.4 | AK32: 254.3 | AL32: 258.7 | AM32: 1026.3 | AN32: 260.2 | AO32: 260.8 | AP32: 268 | AQ32: 277 | AR32: 1066 | AS32: 275 | AT32: 274 | AU32: 277 | AV32: 284 | AW32: 1110 | AX32: 291 | AY32: 294 | AZ32: 294 | BA32: 293 | BB32: 1172 | BC32: 298 | BD32: 294 | BE32: 294 | BF32: 299 | BG32: 1187 | BH32: 302 | BI32: 304 | BJ32: 308 | BK32: 309 | BL32: 1222 | BM32: 310 | BN32: 323 | BO32: 319 | BP32: 324 | BQ32: 1276 | BR32: 333 | BS32: 347 | BT32: 345 | BU32: 353 | BV32: 1378 | BW32: 363 | BX32: 369 | CH32: =IFERROR((CE32/BV32)^(1/5)-1,"n/m") -> -1 | CI32: =IFERROR((BV32/AW32)^(1/5)-1,"n/m") -> 0.044203748 | CJ32: =IFERROR((BV32/X32)^(1/10)-1,"n/m") -> 0.04331127 | CK32: =IFERROR((BV32/C32)^(1/19)-1,"n/m") -> n/m | CN32: Q3/Q4-26E net income attributable to NCI (per quarter, $m) | CP32: 1 | CR32: ICRA minority; 1H26 $1m.
B33: MIS recurring revenue % of segment revenue | C33: =IF(ISNUMBER(C32),IFERROR(C32/C27,""),"") | D33: =IF(ISNUMBER(D32),IFERROR(D32/D27,""),"") | E33: =IF(ISNUMBER(E32),IFERROR(E32/E27,""),"") | F33: =IF(ISNUMBER(F32),IFERROR(F32/F27,""),"") | G33: =IF(ISNUMBER(G32),IFERROR(G32/G27,""),"") | H33: =IF(ISNUMBER(H32),IFERROR(H32/H27,""),"") | I33: =IF(ISNUMBER(I32),IFERROR(I32/I27,""),"") | J33: =IF(ISNUMBER(J32),IFERROR(J32/J27,""),"") | ... BX33: =IF(ISNUMBER(BX32),IFERROR(BX32/BX27,""),"") -> 0.29285714 | CH33: =IFERROR(AVERAGE(CA33,CB33,CC33,CD33,CE33),"n/m") -> n/m | CI33: =IFERROR(AVERAGE(BB33,BG33,BL33,BQ33,BV33),"n/m") -> 0.36909436 | CJ33: =IFERROR(AVERAGE(AC33,AH33,AM33,AR33,AW33,BB33,BG33,BL33,BQ33,BV33),"n/m") -> 0.36722558 | CK33: =IFERROR(AVERAGE(C33,D33,E33,F33,G33,H33,I33,N33,S33,X33,AC33,AH33,AM33,AR33,AW33,BB33,BG33,BL33,BQ33,BV33),"n/m") -> 0.37067377 | CN33: FY26 capital additions ($m) | CP33: 450 | CR33: Guided ~$450m (incl. ~$100m of New York and London office relocations); 1H26 $186m.
B34: MIS intersegment revenue | E34: 63.6 | F34: 60 | G34: 61.3 | H34: 65.8 | I34: 71.5 | J34: 18.9 | K34: 19 | L34: 19.6 | M34: 21.1 | N34: 78.6 | O34: 21.5 | P34: 21.9 | Q34: 22.3 | R34: 21.9 | S34: 87.6 | T34: 22.3 | U34: 23.7 | V34: 23.5 | W34: 24 | X34: 93.5 | Y34: 24 | Z34: 24.6 | AA34: 25.3 | AB34: 26.3 | AC34: 100.2 | AD34: 26 | AE34: 27 | AF34: 29 | AG34: 29.7 | AH34: 111.7 | AI34: 29.8 | AJ34: 30.6 | AK34: 31.6 | AL34: 32 | AM34: 124 | AN34: 32.3 | AO34: 33 | AP34: 34.3 | AQ34: 35 | AR34: 134 | AS34: 37 | AT34: 35 | AU34: 38 | AV34: 38 | AW34: 148 | AX34: 40 | AY34: 42 | AZ34: 42 | BA34: 41 | BB34: 165 | BC34: 43 | BD34: 43 | BE34: 43 | BF34: 45 | BG34: 174 | BH34: 45 | BI34: 46 | BJ34: 47 | BK34: 48 | BL34: 186 | BM34: 47 | BN34: 49 | BO34: 48 | BP34: 49 | BQ34: 193 | BR34: 49 | BS34: 50 | BT34: 50 | BU34: 49 | BV34: 198 | BW34: 51 | BX34: 52 | BY34: =BY27*BY35 -> 46.674514 | BZ34: =BZ27*BZ35 -> 40.212581 | CA34: =SUM(BW34:BZ34) -> 189.88709 | CB34: =CB27*CB35 -> 202.06053 | CC34: =CC27*CC35 -> 213.33341 | CD34: =CD27*CD35 -> 224.89475 | CE34: =CE27*CE35 -> 235.877 | CF34: MIS: royalty / fees charged to MA for use of ratings content; MA: products and services sold to MIS. Eliminated on consolidation. Forecast: % of segment external revenue held at the 1H26 ratio.
B35: Intersegment revenue % of external revenue | C35: =IF(AND(ISNUMBER(C34),ISNUMBER(C27)),IFERROR(C34/C27,""),"") | D35: =IF(AND(ISNUMBER(D34),ISNUMBER(D27)),IFERROR(D34/D27,""),"") | E35: =IF(AND(ISNUMBER(E34),ISNUMBER(E27)),IFERROR(E34/E27,""),"") -> 0.052793227 | F35: =IF(AND(ISNUMBER(F34),ISNUMBER(F27)),IFERROR(F34/F27,""),"") -> 0.04927322 | G35: =IF(AND(ISNUMBER(G34),ISNUMBER(G27)),IFERROR(G34/G27,""),"") -> 0.043629893 | H35: =IF(AND(ISNUMBER(H34),ISNUMBER(H27)),IFERROR(H34/H27,""),"") -> 0.041940213 | I35: =IF(AND(ISNUMBER(I34),ISNUMBER(I27)),IFERROR(I34/I27,""),"") -> 0.037894848 | J35: =IF(AND(ISNUMBER(J34),ISNUMBER(J27)),IFERROR(J34/J27,""),"") -> 0.036262471 | ... BX35: =IF(AND(ISNUMBER(BX34),ISNUMBER(BX27)),IFERROR(BX34/BX27,""),"") -> 0.041269841 | BY35: =IFERROR(SUM(BW34:BX34)/SUM(BW27:BX27),0) -> 0.042685454 | BZ35: =IFERROR(SUM(BW34:BX34)/SUM(BW27:BX27),0) -> 0.042685454 | CA35: =IFERROR(SUM(BW34:BX34)/SUM(BW27:BX27),0) -> 0.042685454 | CB35: =$CA$35 -> 0.042685454 | CC35: =$CA$35 -> 0.042685454 | CD35: =$CA$35 -> 0.042685454 | CE35: =$CA$35 -> 0.042685454 | CN35: Target net debt / Adjusted Operating Income (x) — buyback plug 2027E+ | CO35: 1.5 | CP35: 1.25 | CQ35: 1 | CR35: Net debt / Adjusted Operating Income was ~1.2x at YE2025 (total debt $7.0bn less cash and short-term investments $2.4bn ÷ $4.0bn); FY2021–25 range 1.2–2.4x (2.4x after the RMS acquisition). Target = leverage up to which surplus cash is returned via buybacks (assumption; Moody's gives no numeric net-leverage target). Bull = more buybacks.
B36: MIS — total segment revenue (external + intersegment) | C36: =IF(AND(ISNUMBER(C27),ISNUMBER(C34)),C27+C34,"") | D36: =IF(AND(ISNUMBER(D27),ISNUMBER(D34)),D27+D34,"") | E36: =IF(AND(ISNUMBER(E27),ISNUMBER(E34)),E27+E34,"") -> 1268.3 | F36: =IF(AND(ISNUMBER(F27),ISNUMBER(F34)),F27+F34,"") -> 1277.7 | G36: =IF(AND(ISNUMBER(G27),ISNUMBER(G34)),G27+G34,"") -> 1466.3 | H36: =IF(AND(ISNUMBER(H27),ISNUMBER(H34)),H27+H34,"") -> 1634.7 | I36: =IF(AND(ISNUMBER(I27),ISNUMBER(I34)),I27+I34,"") -> 1958.3 | J36: =IF(AND(ISNUMBER(J27),ISNUMBER(J34)),J27+J34,"") -> 540.1 | ... CE36: =IF(AND(ISNUMBER(CE27),ISNUMBER(CE34)),CE27+CE34,"") -> 5761.811
B37: MIS Adjusted Operating Income (segment measure) | I37: 991.2 | J37: 255.8 | K37: 320.1 | L37: 262.1 | M37: 277.4 | N37: 1115.4 | O37: 301.6 | P37: 374.7 | Q37: 304.6 | R37: 294.4 | S37: 1277.2 | T37: 343.3 | U37: 375.9 | V37: 303.5 | W37: 284.7 | X37: 1307.4 | Y37: 270.5 | Z37: 368.9 | AA37: 364.8 | AB37: 348.6 | AC37: 1355.4 | AD37: 405.9 | AE37: 422.3 | AF37: 404 | AG37: 406.4 | AH37: 1638.6 | AI37: 439.3 | AJ37: 479.3 | AK37: 388.7 | AL37: 350.1 | AM37: 1657.4 | AN37: 385.6 | AO37: 464.4 | AP37: 468.3 | AQ37: 427 | AR37: 1745 | AS37: 503 | AT37: 623 | AU37: 554 | AV37: 373 | AW37: 2053 | AX37: 728 | AY37: 678 | AZ37: 580 | BA37: 489 | BB37: 2474 | BC37: 510 | BD37: 415 | BE37: 289 | BF37: 274 | BG37: 1488 | BH37: 442 | BI37: 443 | BJ37: 395 | BK37: 380 | BL37: 1660 | BM37: 668 | BN37: 672 | BO37: 614 | BP37: 440 | BQ37: 2394 | BR37: 735 | BS37: 680 | BT37: 749 | BU37: 582 | BV37: 2746 | BW37: 803 | BX37: 896 | BY37: =BY36*BY38 -> 749.30908 | BZ37: =BZ36*BZ38 -> 579.25165 | CA37: =SUM(BW37:BZ37) -> 3027.5607 | CB37: =CB36*CB38 -> 3232.9293 | CC37: =CC36*CC38 -> 3439.3488 | CD37: =CD36*CD38 -> 3653.2078 | CE37: =CE36*CE38 -> 3860.4134 | CF37: Company segment measure (operating income + D&A + restructuring + other items excluded by the company; includes intersegment revenue and expense). Forecast = total segment revenue × Adjusted Operating Margin. | CH37: =IFERROR((CE37/BV37)^(1/5)-1,"n/m") -> 0.070499961 | CI37: =IFERROR((BV37/AW37)^(1/5)-1,"n/m") -> 0.059893715 | CJ37: =IFERROR((BV37/X37)^(1/10)-1,"n/m") -> 0.077033484 | CK37: =IFERROR((BV37/C37)^(1/19)-1,"n/m") -> n/m | CN37: MIS_CFG (Corporate Finance y/y) | CO37: 0.03 | CP37: Δ → | CQ37: -0.05 | CR37: FY2015–25 CAGR 6.7%; 1H26 +19% on refinancing / M&A issuance; leveraged-finance refinancing walls 2027–28.
B38: MIS Adjusted Operating Margin % (company basis: on total segment revenue) | C38: =IF(AND(ISNUMBER(C37),ISNUMBER(C36)),IFERROR(C37/C36,""),"") | D38: =IF(AND(ISNUMBER(D37),ISNUMBER(D36)),IFERROR(D37/D36,""),"") | E38: =IF(AND(ISNUMBER(E37),ISNUMBER(E36)),IFERROR(E37/E36,""),"") | F38: =IF(AND(ISNUMBER(F37),ISNUMBER(F36)),IFERROR(F37/F36,""),"") | G38: =IF(AND(ISNUMBER(G37),ISNUMBER(G36)),IFERROR(G37/G36,""),"") | H38: =IF(AND(ISNUMBER(H37),ISNUMBER(H36)),IFERROR(H37/H36,""),"") | I38: =IF(AND(ISNUMBER(I37),ISNUMBER(I36)),IFERROR(I37/I36,""),"") -> 0.5061533 | J38: =IF(AND(ISNUMBER(J37),ISNUMBER(J36)),IFERROR(J37/J36,""),"") -> 0.473616 | ... BX38: =IF(AND(ISNUMBER(BX37),ISNUMBER(BX36)),IFERROR(BX37/BX36,""),"") -> 0.68292683 | BY38: =BY39+$CA$135 -> 0.65721547 | BZ38: =BZ39+$CA$135 -> 0.58970107 | CA38: =IF(AND(ISNUMBER(CA37),ISNUMBER(CA36)),IFERROR(CA37/CA36,""),"") -> 0.65271561 | CB38: =CHOOSE(MATCH($CF$2,{"Bull","Base","Bear"},0),$CO$88,$CP$88,$CQ$88) -> 0.655 | CC38: =CHOOSE(MATCH($CF$2,{"Bull","Base","Bear"},0),$CO$89,$CP$89,$CQ$89) -> 0.66 | CD38: =CHOOSE(MATCH($CF$2,{"Bull","Base","Bear"},0),$CO$90,$CP$90,$CQ$90) -> 0.665 | CE38: =CHOOSE(MATCH($CF$2,{"Bull","Base","Bear"},0),$CO$91,$CP$91,$CQ$91) -> 0.67 | CF38: Q3/Q4-26E: margin before calibration + adjusted-EPS-guidance calibration Δ (Group block). 2027E+: scenario lever. | CH38: =IFERROR(AVERAGE(CA38,CB38,CC38,CD38,CE38),"n/m") -> 0.66054312 | CI38: =IFERROR(AVERAGE(BB38,BG38,BL38,BQ38,BV38),"n/m") -> 0.58433429 | CJ38: =IFERROR(AVERAGE(AC38,AH38,AM38,AR38,AW38,BB38,BG38,BL38,BQ38,BV38),"n/m") -> 0.57991296 | CK38: =IFERROR(AVERAGE(C38,D38,E38,F38,G38,H38,I38,N38,S38,X38,AC38,AH38,AM38,AR38,AW38,BB38,BG38,BL38,BQ38,BV38),"n/m") -> 0.56487315 | CN38: 2027E | CO38: =CP38+$CO$37 -> 0.1 | CP38: 0.07 | CQ38: =CP38+$CQ$37 -> 0.02
B39: Q3/Q4-26E margin before EPS calibration (prior-year quarter + 1H26 y/y drift) | BY39: =BT38+IFERROR(SUM(BW37:BX37)/SUM(BW36:BX36)-SUM(BR37:BS37)/SUM(BR36:BS36),0) -> 0.67684328 | BZ39: =BU38+IFERROR(SUM(BW37:BX37)/SUM(BW36:BX36)-SUM(BR37:BS37)/SUM(BR36:BS36),0) -> 0.60932888 | CN39: 2028E | CO39: =CP39+$CO$37 -> 0.09 | CP39: 0.06 | CQ39: =CP39+$CQ$37 -> 0.01
B40: Memo: MIS Adjusted Operating Margin as published (%) | I40: 0.506 | J40: 0.474 | K40: 0.575 | L40: 0.527 | M40: 0.51 | N40: 0.522 | O40: 0.551 | P40: 0.582 | Q40: 0.539 | R40: 0.502 | S40: 0.543 | T40: 0.55 | U40: 0.567 | V40: 0.531 | W40: 0.501 | X40: 0.539 | Y40: 0.493 | Z40: 0.567 | AA40: 0.572 | AB40: 0.55 | AC40: 0.549 | AD40: 0.585 | AE40: 0.592 | AF40: 0.559 | AG40: 0.539 | AH40: 0.568 | AI40: 0.586 | AJ40: 0.612 | AK40: 0.575 | AL40: 0.558 | AM40: 0.584 | AN40: 0.549 | AO40: 0.602 | AP40: 0.6 | AQ40: 0.566 | AR40: 0.58 | AS40: 0.605 | AT40: 0.64 | AU40: 0.642 | AV40: 0.483 | AW40: 0.597 | AX40: 0.677 | AY40: 0.663 | AZ40: 0.6 | BA40: 0.536 | BB40: 0.622 | BC40: 0.586 | BD40: 0.554 | BE40: 0.457 | BF40: 0.441 | BG40: 0.518 | BH40: 0.568 | BI40: 0.559 | BJ40: 0.532 | BK40: 0.519 | BL40: 0.545 | BM40: 0.646 | BN40: 0.632 | BO40: 0.596 | BP40: 0.513 | BQ40: 0.601 | BR40: 0.66 | BS40: 0.642 | BT40: 0.652 | BU40: 0.585 | BV40: 0.636 | BW40: 0.667 | BX40: 0.683 | CN40: 2029E | CO40: =CP40+$CO$37 -> 0.09 | CP40: 0.06 | CQ40: =CP40+$CQ$37 -> 0.01
B41: Incremental Adjusted Operating Margin (Δ AOI / Δ total revenue) | D41: =IFERROR((D37-C37)/(D36-C36),"") | E41: =IFERROR((E37-D37)/(E36-D36),"") | F41: =IFERROR((F37-E37)/(F36-E36),"") -> 0 | G41: =IFERROR((G37-F37)/(G36-F36),"") -> 0 | H41: =IFERROR((H37-G37)/(H36-G36),"") -> 0 | I41: =IFERROR((I37-H37)/(I36-H36),"") -> 3.0630408 | N41: =IFERROR((N37-I37)/(N36-I36),"") -> 0.69115192 | O41: =IFERROR((O37-J37)/(O36-J36),"") -> 6.3611111 | P41: =IFERROR((P37-K37)/(P36-K36),"") -> 0.62542955 | Q41: =IFERROR((Q37-L37)/(Q36-L36),"") -> 0.62776957 | R41: =IFERROR((R37-M37)/(R36-M36),"") -> 0.39443155 | S41: =IFERROR((S37-N37)/(S36-N36),"") -> 0.75116063 | T41: =IFERROR((T37-O37)/(T36-O36),"") -> 0.53945666 | U41: =IFERROR((U37-P37)/(U36-P36),"") -> 0.062176166 | ... CA41: =IFERROR((CA37-BV37)/(CA36-BV36),"") -> 0.87602524 | CB41: =IFERROR((CB37-CA37)/(CB36-CA36),"") -> 0.69063296 | CC41: =IFERROR((CC37-CB37)/(CC36-CB36),"") -> 0.74962245 | CD41: =IFERROR((CD37-CC37)/(CD36-CC36),"") -> 0.75726152 | CE41: =IFERROR((CE37-CD37)/(CE36-CD36),"") -> 0.77239013 | CN41: 2030E | CO41: =CP41+$CO$37 -> 0.08 | CP41: 0.05 | CQ41: =CP41+$CQ$37 -> 0
CN42: MIS_SFG (Structured Finance y/y) | CO42: 0.03 | CP42: Δ → | CQ42: -0.05 | CR42: 1H26 +5%; private credit / CLO / ABS growth vs CMBS cyclicality.
B43: Moody's Analytics (data, research, analytics and software; recurring subscription / SaaS) | CF43: MA — modelling logic | CN43: 2027E | CO43: =CP43+$CO$42 -> 0.08 | CP43: 0.05 | CQ43: =CP43+$CQ$42 -> 0
B44: Decision Solutions — Banking | BI44: 123 | BJ44: 136 | BL44: 521 | BM44: 134 | BN44: 131 | BO44: 140 | BP44: 146 | BQ44: 551 | BR44: 141 | BS44: 138 | BT44: 140 | BU44: 150 | BV44: 569 | BW44: 133 | BX44: 119 | BY44: =BT44*(1+BY45) -> 123.72163 | BZ44: =BU44*(1+BZ45) -> 132.55889 | CA44: =SUM(BW44:BZ44) -> 508.28051 | CB44: =CA44*(1+CB45) -> 543.86015 | CC44: =CB44*(1+CC45) -> 581.93036 | CD44: =CC44*(1+CD45) -> 616.84618 | CE44: =CD44*(1+CE45) -> 653.85695 | CF44: External revenue by line as originally reported in each release. Q3/Q4-26E: prior-year quarter × (1 + growth). 2027E+: prior year × (1 + scenario lever). | CH44: =IFERROR((CE44/BV44)^(1/5)-1,"n/m") -> 0.028191706 | CI44: =IFERROR((BV44/AW44)^(1/5)-1,"n/m") -> n/m | CJ44: =IFERROR((BV44/X44)^(1/10)-1,"n/m") -> n/m | CK44: =IFERROR((BV44/C44)^(1/19)-1,"n/m") -> n/m | CN44: 2028E | CO44: =CP44+$CO$42 -> 0.07 | CP44: 0.04 | CQ44: =CP44+$CQ$42 -> -0.01
B45: y/y % | D45: =IF(AND(ISNUMBER(D44),ISNUMBER(C44)),IFERROR(D44/C44-1,""),"") | E45: =IF(AND(ISNUMBER(E44),ISNUMBER(D44)),IFERROR(E44/D44-1,""),"") | F45: =IF(AND(ISNUMBER(F44),ISNUMBER(E44)),IFERROR(F44/E44-1,""),"") | G45: =IF(AND(ISNUMBER(G44),ISNUMBER(F44)),IFERROR(G44/F44-1,""),"") | H45: =IF(AND(ISNUMBER(H44),ISNUMBER(G44)),IFERROR(H44/G44-1,""),"") | I45: =IF(AND(ISNUMBER(I44),ISNUMBER(H44)),IFERROR(I44/H44-1,""),"") | N45: =IF(AND(ISNUMBER(N44),ISNUMBER(I44)),IFERROR(N44/I44-1,""),"") | O45: =IF(AND(ISNUMBER(O44),ISNUMBER(J44)),IFERROR(O44/J44-1,""),"") | P45: =IF(AND(ISNUMBER(P44),ISNUMBER(K44)),IFERROR(P44/K44-1,""),"") | Q45: =IF(AND(ISNUMBER(Q44),ISNUMBER(L44)),IFERROR(Q44/L44-1,""),"") | R45: =IF(AND(ISNUMBER(R44),ISNUMBER(M44)),IFERROR(R44/M44-1,""),"") | S45: =IF(AND(ISNUMBER(S44),ISNUMBER(N44)),IFERROR(S44/N44-1,""),"") | T45: =IF(AND(ISNUMBER(T44),ISNUMBER(O44)),IFERROR(T44/O44-1,""),"") | U45: =IF(AND(ISNUMBER(U44),ISNUMBER(P44)),IFERROR(U44/P44-1,""),"") | ... BX45: =IF(AND(ISNUMBER(BX44),ISNUMBER(BS44)),IFERROR(BX44/BS44-1,""),"") -> -0.13768116 | BY45: =BY46+$CA$125 -> -0.11627409 | BZ45: =BZ46+$CA$125 -> -0.11627409 | CA45: =IF(AND(ISNUMBER(CA44),ISNUMBER(BV44)),IFERROR(CA44/BV44-1,""),"") -> -0.10671263 | CB45: =CHOOSE(MATCH($CF$2,{"Bull","Base","Bear"},0),$CO$63,$CP$63,$CQ$63) -> 0.07 | CC45: =CHOOSE(MATCH($CF$2,{"Bull","Base","Bear"},0),$CO$64,$CP$64,$CQ$64) -> 0.07 | CD45: =CHOOSE(MATCH($CF$2,{"Bull","Base","Bear"},0),$CO$65,$CP$65,$CQ$65) -> 0.06 | CE45: =CHOOSE(MATCH($CF$2,{"Bull","Base","Bear"},0),$CO$66,$CP$66,$CQ$66) -> 0.06 | CF45: Q3/Q4-26E: 1H26 y/y growth of the line + MA revenue-guidance calibration Δ (Group block). 2027E–2030E: scenario lever (table →). | CN45: 2029E | CO45: =CP45+$CO$42 -> 0.07 | CP45: 0.04 | CQ45: =CP45+$CQ$42 -> -0.01
B46: Q3/Q4-26E growth before calibration (1H26 y/y) | BY46: =IFERROR(SUM(BW44:BX44)/SUM(BR44:BS44)-1,0) -> -0.096774194 | BZ46: =IFERROR(SUM(BW44:BX44)/SUM(BR44:BS44)-1,0) -> -0.096774194 | CN46: 2030E | CO46: =CP46+$CO$42 -> 0.07 | CP46: 0.04 | CQ46: =CP46+$CQ$42 -> -0.01
B47: Decision Solutions — Insurance | BI47: 133 | BJ47: 138 | BL47: 550 | BM47: 144 | BN47: 147 | BO47: 148 | BP47: 159 | BQ47: 598 | BR47: 163 | BS47: 168 | BT47: 171 | BU47: 183 | BV47: 685 | BW47: 181 | BX47: 183 | BY47: =BT47*(1+BY48) -> 184.71386 | BZ47: =BU47*(1+BZ48) -> 197.67623 | CA47: =SUM(BW47:BZ47) -> 746.39009 | CB47: =CA47*(1+CB48) -> 813.5652 | CC47: =CB47*(1+CC48) -> 878.65041 | CD47: =CC47*(1+CD48) -> 948.94245 | CE47: =CD47*(1+CE48) -> 1015.3684 | CH47: =IFERROR((CE47/BV47)^(1/5)-1,"n/m") -> 0.081898742 | CI47: =IFERROR((BV47/AW47)^(1/5)-1,"n/m") -> n/m | CJ47: =IFERROR((BV47/X47)^(1/10)-1,"n/m") -> n/m | CK47: =IFERROR((BV47/C47)^(1/19)-1,"n/m") -> n/m | CN47: MIS_FIG (Financial Institutions y/y) | CO47: 0.02 | CP47: Δ → | CQ47: -0.04 | CR47: 1H26 +9%; bank / insurer issuance; private-credit fund ratings.
B48: y/y % | D48: =IF(AND(ISNUMBER(D47),ISNUMBER(C47)),IFERROR(D47/C47-1,""),"") | E48: =IF(AND(ISNUMBER(E47),ISNUMBER(D47)),IFERROR(E47/D47-1,""),"") | F48: =IF(AND(ISNUMBER(F47),ISNUMBER(E47)),IFERROR(F47/E47-1,""),"") | G48: =IF(AND(ISNUMBER(G47),ISNUMBER(F47)),IFERROR(G47/F47-1,""),"") | H48: =IF(AND(ISNUMBER(H47),ISNUMBER(G47)),IFERROR(H47/G47-1,""),"") | I48: =IF(AND(ISNUMBER(I47),ISNUMBER(H47)),IFERROR(I47/H47-1,""),"") | N48: =IF(AND(ISNUMBER(N47),ISNUMBER(I47)),IFERROR(N47/I47-1,""),"") | O48: =IF(AND(ISNUMBER(O47),ISNUMBER(J47)),IFERROR(O47/J47-1,""),"") | P48: =IF(AND(ISNUMBER(P47),ISNUMBER(K47)),IFERROR(P47/K47-1,""),"") | Q48: =IF(AND(ISNUMBER(Q47),ISNUMBER(L47)),IFERROR(Q47/L47-1,""),"") | R48: =IF(AND(ISNUMBER(R47),ISNUMBER(M47)),IFERROR(R47/M47-1,""),"") | S48: =IF(AND(ISNUMBER(S47),ISNUMBER(N47)),IFERROR(S47/N47-1,""),"") | T48: =IF(AND(ISNUMBER(T47),ISNUMBER(O47)),IFERROR(T47/O47-1,""),"") | U48: =IF(AND(ISNUMBER(U47),ISNUMBER(P47)),IFERROR(U47/P47-1,""),"") | ... BX48: =IF(AND(ISNUMBER(BX47),ISNUMBER(BS47)),IFERROR(BX47/BS47-1,""),"") -> 0.089285714 | BY48: =BY49+$CA$125 -> 0.080197991 | BZ48: =BZ49+$CA$125 -> 0.080197991 | CA48: =IF(AND(ISNUMBER(CA47),ISNUMBER(BV47)),IFERROR(CA47/BV47-1,""),"") -> 0.089620568 | CB48: =CHOOSE(MATCH($CF$2,{"Bull","Base","Bear"},0),$CO$68,$CP$68,$CQ$68) -> 0.09 | CC48: =CHOOSE(MATCH($CF$2,{"Bull","Base","Bear"},0),$CO$69,$CP$69,$CQ$69) -> 0.08 | CD48: =CHOOSE(MATCH($CF$2,{"Bull","Base","Bear"},0),$CO$70,$CP$70,$CQ$70) -> 0.08 | CE48: =CHOOSE(MATCH($CF$2,{"Bull","Base","Bear"},0),$CO$71,$CP$71,$CQ$71) -> 0.07 | CN48: 2027E | CO48: =CP48+$CO$47 -> 0.08 | CP48: 0.06 | CQ48: =CP48+$CQ$47 -> 0.02
B49: Q3/Q4-26E growth before calibration (1H26 y/y) | BY49: =IFERROR(SUM(BW47:BX47)/SUM(BR47:BS47)-1,0) -> 0.099697885 | BZ49: =IFERROR(SUM(BW47:BX47)/SUM(BR47:BS47)-1,0) -> 0.099697885 | CN49: 2028E | CO49: =CP49+$CO$47 -> 0.07 | CP49: 0.05 | CQ49: =CP49+$CQ$47 -> 0.01
B50: Decision Solutions — KYC | BI50: 78 | BJ50: 80 | BL50: 312 | BM50: 87 | BN50: 88 | BO50: 95 | BP50: 97 | BQ50: 367 | BR50: 101 | BS50: 107 | BT50: 113 | BU50: 117 | BV50: 438 | BW50: 118 | BX50: 121 | BY50: =BT50*(1+BY51) -> 127.63786 | BZ50: =BU50*(1+BZ51) -> 132.15601 | CA50: =SUM(BW50:BZ50) -> 498.79387 | CB50: =CA50*(1+CB51) -> 558.64913 | CC50: =CB50*(1+CC51) -> 620.10054 | CD50: =CC50*(1+CD51) -> 682.11059 | CE50: =CD50*(1+CE51) -> 743.50055 | CH50: =IFERROR((CE50/BV50)^(1/5)-1,"n/m") -> 0.11163301 | CI50: =IFERROR((BV50/AW50)^(1/5)-1,"n/m") -> n/m | CJ50: =IFERROR((BV50/X50)^(1/10)-1,"n/m") -> n/m | CK50: =IFERROR((BV50/C50)^(1/19)-1,"n/m") -> n/m | CN50: 2029E | CO50: =CP50+$CO$47 -> 0.07 | CP50: 0.05 | CQ50: =CP50+$CQ$47 -> 0.01
B51: y/y % | D51: =IF(AND(ISNUMBER(D50),ISNUMBER(C50)),IFERROR(D50/C50-1,""),"") | E51: =IF(AND(ISNUMBER(E50),ISNUMBER(D50)),IFERROR(E50/D50-1,""),"") | F51: =IF(AND(ISNUMBER(F50),ISNUMBER(E50)),IFERROR(F50/E50-1,""),"") | G51: =IF(AND(ISNUMBER(G50),ISNUMBER(F50)),IFERROR(G50/F50-1,""),"") | H51: =IF(AND(ISNUMBER(H50),ISNUMBER(G50)),IFERROR(H50/G50-1,""),"") | I51: =IF(AND(ISNUMBER(I50),ISNUMBER(H50)),IFERROR(I50/H50-1,""),"") | N51: =IF(AND(ISNUMBER(N50),ISNUMBER(I50)),IFERROR(N50/I50-1,""),"") | O51: =IF(AND(ISNUMBER(O50),ISNUMBER(J50)),IFERROR(O50/J50-1,""),"") | P51: =IF(AND(ISNUMBER(P50),ISNUMBER(K50)),IFERROR(P50/K50-1,""),"") | Q51: =IF(AND(ISNUMBER(Q50),ISNUMBER(L50)),IFERROR(Q50/L50-1,""),"") | R51: =IF(AND(ISNUMBER(R50),ISNUMBER(M50)),IFERROR(R50/M50-1,""),"") | S51: =IF(AND(ISNUMBER(S50),ISNUMBER(N50)),IFERROR(S50/N50-1,""),"") | T51: =IF(AND(ISNUMBER(T50),ISNUMBER(O50)),IFERROR(T50/O50-1,""),"") | U51: =IF(AND(ISNUMBER(U50),ISNUMBER(P50)),IFERROR(U50/P50-1,""),"") | ... BX51: =IF(AND(ISNUMBER(BX50),ISNUMBER(BS50)),IFERROR(BX50/BS50-1,""),"") -> 0.13084112 | BY51: =BY52+$CA$125 -> 0.12953857 | BZ51: =BZ52+$CA$125 -> 0.12953857 | CA51: =IF(AND(ISNUMBER(CA50),ISNUMBER(BV50)),IFERROR(CA50/BV50-1,""),"") -> 0.13879879 | CB51: =CHOOSE(MATCH($CF$2,{"Bull","Base","Bear"},0),$CO$73,$CP$73,$CQ$73) -> 0.12 | CC51: =CHOOSE(MATCH($CF$2,{"Bull","Base","Bear"},0),$CO$74,$CP$74,$CQ$74) -> 0.11 | CD51: =CHOOSE(MATCH($CF$2,{"Bull","Base","Bear"},0),$CO$75,$CP$75,$CQ$75) -> 0.1 | CE51: =CHOOSE(MATCH($CF$2,{"Bull","Base","Bear"},0),$CO$76,$CP$76,$CQ$76) -> 0.09 | CN51: 2030E | CO51: =CP51+$CO$47 -> 0.07 | CP51: 0.05 | CQ51: =CP51+$CQ$47 -> 0.01
B52: Q3/Q4-26E growth before calibration (1H26 y/y) | BY52: =IFERROR(SUM(BW50:BX50)/SUM(BR50:BS50)-1,0) -> 0.14903846 | BZ52: =IFERROR(SUM(BW50:BX50)/SUM(BR50:BS50)-1,0) -> 0.14903846 | CN52: MIS_PPIF (Public, Project & Infrastructure Finance y/y) | CO52: 0.03 | CP52: Δ → | CQ52: -0.05 | CR52: 1H26 +23%; infrastructure / energy-transition project finance and US public finance.
B53: Research & Insights | AX53: 171 | AY53: 175 | AZ53: 177 | BA53: 174 | BB53: 697 | BC53: 183 | BD53: 185 | BE53: 184 | BF53: 181 | BG53: 733 | BH53: 195 | BI53: 217 | BJ53: 222 | BK53: 230 | BL53: 884 | BM53: 222 | BN53: 226 | BO53: 235 | BP53: 243 | BQ53: 926 | BR53: 236 | BS53: 249 | BT53: 252 | BU53: 258 | BV53: 995 | BW53: 255 | BX53: 256 | BY53: =BT53*(1+BY54) -> 260.59531 | BZ53: =BU53*(1+BZ54) -> 266.79996 | CA53: =SUM(BW53:BZ53) -> 1038.3953 | CB53: =CA53*(1+CB54) -> 1090.315 | CC53: =CB53*(1+CC54) -> 1144.8308 | CD53: =CC53*(1+CD54) -> 1202.0723 | CE53: =CD53*(1+CE54) -> 1262.1759 | CH53: =IFERROR((CE53/BV53)^(1/5)-1,"n/m") -> 0.048719546 | CI53: =IFERROR((BV53/AW53)^(1/5)-1,"n/m") -> n/m | CJ53: =IFERROR((BV53/X53)^(1/10)-1,"n/m") -> n/m | CK53: =IFERROR((BV53/C53)^(1/19)-1,"n/m") -> n/m | CN53: 2027E | CO53: =CP53+$CO$52 -> 0.09 | CP53: 0.06 | CQ53: =CP53+$CQ$52 -> 0.01
B54: y/y % | D54: =IF(AND(ISNUMBER(D53),ISNUMBER(C53)),IFERROR(D53/C53-1,""),"") | E54: =IF(AND(ISNUMBER(E53),ISNUMBER(D53)),IFERROR(E53/D53-1,""),"") | F54: =IF(AND(ISNUMBER(F53),ISNUMBER(E53)),IFERROR(F53/E53-1,""),"") | G54: =IF(AND(ISNUMBER(G53),ISNUMBER(F53)),IFERROR(G53/F53-1,""),"") | H54: =IF(AND(ISNUMBER(H53),ISNUMBER(G53)),IFERROR(H53/G53-1,""),"") | I54: =IF(AND(ISNUMBER(I53),ISNUMBER(H53)),IFERROR(I53/H53-1,""),"") | N54: =IF(AND(ISNUMBER(N53),ISNUMBER(I53)),IFERROR(N53/I53-1,""),"") | O54: =IF(AND(ISNUMBER(O53),ISNUMBER(J53)),IFERROR(O53/J53-1,""),"") | P54: =IF(AND(ISNUMBER(P53),ISNUMBER(K53)),IFERROR(P53/K53-1,""),"") | Q54: =IF(AND(ISNUMBER(Q53),ISNUMBER(L53)),IFERROR(Q53/L53-1,""),"") | R54: =IF(AND(ISNUMBER(R53),ISNUMBER(M53)),IFERROR(R53/M53-1,""),"") | S54: =IF(AND(ISNUMBER(S53),ISNUMBER(N53)),IFERROR(S53/N53-1,""),"") | T54: =IF(AND(ISNUMBER(T53),ISNUMBER(O53)),IFERROR(T53/O53-1,""),"") | U54: =IF(AND(ISNUMBER(U53),ISNUMBER(P53)),IFERROR(U53/P53-1,""),"") | ... BX54: =IF(AND(ISNUMBER(BX53),ISNUMBER(BS53)),IFERROR(BX53/BS53-1,""),"") -> 0.02811245 | BY54: =BY55+$CA$125 -> 0.034108353 | BZ54: =BZ55+$CA$125 -> 0.034108353 | CA54: =IF(AND(ISNUMBER(CA53),ISNUMBER(BV53)),IFERROR(CA53/BV53-1,""),"") -> 0.043613327 | CB54: =CHOOSE(MATCH($CF$2,{"Bull","Base","Bear"},0),$CO$78,$CP$78,$CQ$78) -> 0.05 | CC54: =CHOOSE(MATCH($CF$2,{"Bull","Base","Bear"},0),$CO$79,$CP$79,$CQ$79) -> 0.05 | CD54: =CHOOSE(MATCH($CF$2,{"Bull","Base","Bear"},0),$CO$80,$CP$80,$CQ$80) -> 0.05 | CE54: =CHOOSE(MATCH($CF$2,{"Bull","Base","Bear"},0),$CO$81,$CP$81,$CQ$81) -> 0.05 | CN54: 2028E | CO54: =CP54+$CO$52 -> 0.09 | CP54: 0.06 | CQ54: =CP54+$CQ$52 -> 0.01
B55: Q3/Q4-26E growth before calibration (1H26 y/y) | BY55: =IFERROR(SUM(BW53:BX53)/SUM(BR53:BS53)-1,0) -> 0.053608247 | BZ55: =IFERROR(SUM(BW53:BX53)/SUM(BR53:BS53)-1,0) -> 0.053608247 | CN55: 2029E | CO55: =CP55+$CO$52 -> 0.08 | CP55: 0.05 | CQ55: =CP55+$CQ$52 -> 0
B56: Data & Information | AX56: 168 | AY56: 176 | AZ56: 174 | BA56: 180 | BB56: 698 | BC56: 178 | BD56: 178 | BE56: 176 | BF56: 180 | BG56: 712 | BH56: 188 | BI56: 196 | BJ56: 200 | BK56: 205 | BL56: 789 | BM56: 212 | BN56: 210 | BO56: 213 | BP56: 218 | BQ56: 853 | BR56: 218 | BS56: 226 | BT56: 233 | BU56: 235 | BV56: 912 | BW56: 239 | BX56: 246 | BY56: =BT56*(1+BY57) -> 249.97229 | BZ56: =BU56*(1+BZ57) -> 252.11798 | CA56: =SUM(BW56:BZ56) -> 987.09027 | CB56: =CA56*(1+CB57) -> 1066.0575 | CC56: =CB56*(1+CC57) -> 1151.3421 | CD56: =CC56*(1+CD57) -> 1231.936 | CE56: =CD56*(1+CE57) -> 1318.1716 | CH56: =IFERROR((CE56/BV56)^(1/5)-1,"n/m") -> 0.07645386 | CI56: =IFERROR((BV56/AW56)^(1/5)-1,"n/m") -> n/m | CJ56: =IFERROR((BV56/X56)^(1/10)-1,"n/m") -> n/m | CK56: =IFERROR((BV56/C56)^(1/19)-1,"n/m") -> n/m | CN56: 2030E | CO56: =CP56+$CO$52 -> 0.08 | CP56: 0.05 | CQ56: =CP56+$CQ$52 -> 0
B57: y/y % | D57: =IF(AND(ISNUMBER(D56),ISNUMBER(C56)),IFERROR(D56/C56-1,""),"") | E57: =IF(AND(ISNUMBER(E56),ISNUMBER(D56)),IFERROR(E56/D56-1,""),"") | F57: =IF(AND(ISNUMBER(F56),ISNUMBER(E56)),IFERROR(F56/E56-1,""),"") | G57: =IF(AND(ISNUMBER(G56),ISNUMBER(F56)),IFERROR(G56/F56-1,""),"") | H57: =IF(AND(ISNUMBER(H56),ISNUMBER(G56)),IFERROR(H56/G56-1,""),"") | I57: =IF(AND(ISNUMBER(I56),ISNUMBER(H56)),IFERROR(I56/H56-1,""),"") | N57: =IF(AND(ISNUMBER(N56),ISNUMBER(I56)),IFERROR(N56/I56-1,""),"") | O57: =IF(AND(ISNUMBER(O56),ISNUMBER(J56)),IFERROR(O56/J56-1,""),"") | P57: =IF(AND(ISNUMBER(P56),ISNUMBER(K56)),IFERROR(P56/K56-1,""),"") | Q57: =IF(AND(ISNUMBER(Q56),ISNUMBER(L56)),IFERROR(Q56/L56-1,""),"") | R57: =IF(AND(ISNUMBER(R56),ISNUMBER(M56)),IFERROR(R56/M56-1,""),"") | S57: =IF(AND(ISNUMBER(S56),ISNUMBER(N56)),IFERROR(S56/N56-1,""),"") | T57: =IF(AND(ISNUMBER(T56),ISNUMBER(O56)),IFERROR(T56/O56-1,""),"") | U57: =IF(AND(ISNUMBER(U56),ISNUMBER(P56)),IFERROR(U56/P56-1,""),"") | ... BX57: =IF(AND(ISNUMBER(BX56),ISNUMBER(BS56)),IFERROR(BX56/BS56-1,""),"") -> 0.088495575 | BY57: =BY58+$CA$125 -> 0.072842448 | BZ57: =BZ58+$CA$125 -> 0.072842448 | CA57: =IF(AND(ISNUMBER(CA56),ISNUMBER(BV56)),IFERROR(CA56/BV56-1,""),"") -> 0.082335818 | CB57: =CHOOSE(MATCH($CF$2,{"Bull","Base","Bear"},0),$CO$83,$CP$83,$CQ$83) -> 0.08 | CC57: =CHOOSE(MATCH($CF$2,{"Bull","Base","Bear"},0),$CO$84,$CP$84,$CQ$84) -> 0.08 | CD57: =CHOOSE(MATCH($CF$2,{"Bull","Base","Bear"},0),$CO$85,$CP$85,$CQ$85) -> 0.07 | CE57: =CHOOSE(MATCH($CF$2,{"Bull","Base","Bear"},0),$CO$86,$CP$86,$CQ$86) -> 0.07 | CN57: MIS_MOTH (MIS Other y/y) | CO57: 0.02 | CP57: Δ → | CQ57: -0.03 | CR57: ICRA non-ratings and other; small (~$50m p.a.).
B58: Q3/Q4-26E growth before calibration (1H26 y/y) | BY58: =IFERROR(SUM(BW56:BX56)/SUM(BR56:BS56)-1,0) -> 0.092342342 | BZ58: =IFERROR(SUM(BW56:BX56)/SUM(BR56:BS56)-1,0) -> 0.092342342 | CN58: 2027E | CO58: =CP58+$CO$57 -> 0.08 | CP58: 0.06 | CQ58: =CP58+$CQ$57 -> 0.03
B59: Memo: Decision Solutions — total (Banking + Insurance + KYC; as reported before the 2024 split) | C59: =IF(ISNUMBER(C44),C44+C47+C50,IF(ISNUMBER(C76),C76,"")) | D59: =IF(ISNUMBER(D44),D44+D47+D50,IF(ISNUMBER(D76),D76,"")) | E59: =IF(ISNUMBER(E44),E44+E47+E50,IF(ISNUMBER(E76),E76,"")) | F59: =IF(ISNUMBER(F44),F44+F47+F50,IF(ISNUMBER(F76),F76,"")) | G59: =IF(ISNUMBER(G44),G44+G47+G50,IF(ISNUMBER(G76),G76,"")) | H59: =IF(ISNUMBER(H44),H44+H47+H50,IF(ISNUMBER(H76),H76,"")) | I59: =IF(ISNUMBER(I44),I44+I47+I50,IF(ISNUMBER(I76),I76,"")) | J59: =IF(ISNUMBER(J44),J44+J47+J50,IF(ISNUMBER(J76),J76,"")) | ... BX59: =IF(ISNUMBER(BX44),BX44+BX47+BX50,IF(ISNUMBER(BX76),BX76,"")) -> 423 | BY59: =BY44+BY47+BY50 -> 436.07334 | BZ59: =BZ44+BZ47+BZ50 -> 462.39113 | CA59: =SUM(BW59:BZ59) -> 1753.4645 | CB59: =CB44+CB47+CB50 -> 1916.0745 | CC59: =CC44+CC47+CC50 -> 2080.6813 | CD59: =CD44+CD47+CD50 -> 2247.8992 | CE59: =CE44+CE47+CE50 -> 2412.7259 | CN59: 2028E | CO59: =CP59+$CO$57 -> 0.07 | CP59: 0.05 | CQ59: =CP59+$CQ$57 -> 0.02
B60: MA revenue not split on the current lines (history before the current line structure; derived) | C60: =IF(ISNUMBER(C64),C64-(N(C44)+N(C47)+N(C50)+N(C53)+N(C56))-IF(AND(NOT(ISNUMBER(C44)),ISNUMBER(C76)),C76,0),"") -> 397.3 | D60: =IF(ISNUMBER(D64),D64-(N(D44)+N(D47)+N(D50)+N(D53)+N(D56))-IF(AND(NOT(ISNUMBER(D44)),ISNUMBER(D76)),D76,0),"") -> 479.1 | E60: =IF(ISNUMBER(E64),E64-(N(E44)+N(E47)+N(E50)+N(E53)+N(E56))-IF(AND(NOT(ISNUMBER(E44)),ISNUMBER(E76)),E76,0),"") -> 550.7 | F60: =IF(ISNUMBER(F64),F64-(N(F44)+N(F47)+N(F50)+N(F53)+N(F56))-IF(AND(NOT(ISNUMBER(F44)),ISNUMBER(F76)),F76,0),"") -> 579.5 | G60: =IF(ISNUMBER(G64),G64-(N(G44)+N(G47)+N(G50)+N(G53)+N(G56))-IF(AND(NOT(ISNUMBER(G44)),ISNUMBER(G76)),G76,0),"") -> 627 | H60: =IF(ISNUMBER(H64),H64-(N(H44)+N(H47)+N(H50)+N(H53)+N(H56))-IF(AND(NOT(ISNUMBER(H44)),ISNUMBER(H76)),H76,0),"") -> 711.8 | I60: =IF(ISNUMBER(I64),I64-(N(I44)+N(I47)+N(I50)+N(I53)+N(I56))-IF(AND(NOT(ISNUMBER(I44)),ISNUMBER(I76)),I76,0),"") -> 843.5 | J60: =IF(ISNUMBER(J64),J64-(N(J44)+N(J47)+N(J50)+N(J53)+N(J56))-IF(AND(NOT(ISNUMBER(J44)),ISNUMBER(J76)),J76,0),"") -> 210.6 | ... BX60: =IF(ISNUMBER(BX64),BX64-(N(BX44)+N(BX47)+N(BX50)+N(BX53)+N(BX56))-IF(AND(NOT(ISNUMBER(BX44)),ISNUMBER(BX76)),BX76,0),"") -> 0 | BY60: =0 -> 0 | BZ60: =0 -> 0 | CA60: =SUM(BW60:BZ60) -> 0 | CB60: =0 -> 0 | CC60: =0 -> 0 | CD60: =0 -> 0 | CE60: =0 -> 0 | CN60: 2029E | CO60: =CP60+$CO$57 -> 0.07 | CP60: 0.05 | CQ60: =CP60+$CQ$57 -> 0.02
B61: MA — external revenue | C61: =IF(ISNUMBER(C64),N(C44)+N(C47)+N(C50)+N(C53)+N(C56)+C60+IF(AND(NOT(ISNUMBER(C44)),ISNUMBER(C76)),C76,0),"") -> 397.3 | D61: =IF(ISNUMBER(D64),N(D44)+N(D47)+N(D50)+N(D53)+N(D56)+D60+IF(AND(NOT(ISNUMBER(D44)),ISNUMBER(D76)),D76,0),"") -> 479.1 | E61: =IF(ISNUMBER(E64),N(E44)+N(E47)+N(E50)+N(E53)+N(E56)+E60+IF(AND(NOT(ISNUMBER(E44)),ISNUMBER(E76)),E76,0),"") -> 550.7 | F61: =IF(ISNUMBER(F64),N(F44)+N(F47)+N(F50)+N(F53)+N(F56)+F60+IF(AND(NOT(ISNUMBER(F44)),ISNUMBER(F76)),F76,0),"") -> 579.5 | G61: =IF(ISNUMBER(G64),N(G44)+N(G47)+N(G50)+N(G53)+N(G56)+G60+IF(AND(NOT(ISNUMBER(G44)),ISNUMBER(G76)),G76,0),"") -> 627 | H61: =IF(ISNUMBER(H64),N(H44)+N(H47)+N(H50)+N(H53)+N(H56)+H60+IF(AND(NOT(ISNUMBER(H44)),ISNUMBER(H76)),H76,0),"") -> 711.8 | I61: =IF(ISNUMBER(I64),N(I44)+N(I47)+N(I50)+N(I53)+N(I56)+I60+IF(AND(NOT(ISNUMBER(I44)),ISNUMBER(I76)),I76,0),"") -> 843.5 | J61: =IF(ISNUMBER(J64),N(J44)+N(J47)+N(J50)+N(J53)+N(J56)+J60+IF(AND(NOT(ISNUMBER(J44)),ISNUMBER(J76)),J76,0),"") -> 210.6 | ... BX61: =IF(ISNUMBER(BX64),N(BX44)+N(BX47)+N(BX50)+N(BX53)+N(BX56)+BX60+IF(AND(NOT(ISNUMBER(BX44)),ISNUMBER(BX76)),BX76,0),"") -> 925 | BY61: =BY44+BY47+BY50+BY53+BY56 -> 946.64094 | BZ61: =BZ44+BZ47+BZ50+BZ53+BZ56 -> 981.30906 | CA61: =SUM(BW61:BZ61) -> 3778.95 | CB61: =CB44+CB47+CB50+CB53+CB56 -> 4072.447 | CC61: =CC44+CC47+CC50+CC53+CC56 -> 4376.8542 | CD61: =CD44+CD47+CD50+CD53+CD56 -> 4681.9076 | CE61: =CE44+CE47+CE50+CE53+CE56 -> 4993.0734 | CH61: =IFERROR((CE61/BV61)^(1/5)-1,"n/m") -> 0.067670445 | CI61: =IFERROR((BV61/AW61)^(1/5)-1,"n/m") -> 0.11600328 | CJ61: =IFERROR((BV61/X61)^(1/10)-1,"n/m") -> 0.1208231 | CK61: =IFERROR((BV61/C61)^(1/19)-1,"n/m") -> 0.1229793 | CN61: 2030E | CO61: =CP61+$CO$57 -> 0.07 | CP61: 0.05 | CQ61: =CP61+$CQ$57 -> 0.02
B62: Segment revenue y/y % | D62: =IF(AND(ISNUMBER(D61),ISNUMBER(C61)),IFERROR(D61/C61-1,""),"") -> 0.20588976 | E62: =IF(AND(ISNUMBER(E61),ISNUMBER(D61)),IFERROR(E61/D61-1,""),"") -> 0.14944688 | F62: =IF(AND(ISNUMBER(F61),ISNUMBER(E61)),IFERROR(F61/E61-1,""),"") -> 0.052297076 | G62: =IF(AND(ISNUMBER(G61),ISNUMBER(F61)),IFERROR(G61/F61-1,""),"") -> 0.081967213 | H62: =IF(AND(ISNUMBER(H61),ISNUMBER(G61)),IFERROR(H61/G61-1,""),"") -> 0.13524721 | I62: =IF(AND(ISNUMBER(I61),ISNUMBER(H61)),IFERROR(I61/H61-1,""),"") -> 0.18502388 | N62: =IF(AND(ISNUMBER(N61),ISNUMBER(I61)),IFERROR(N61/I61-1,""),"") -> 0.082513337 | O62: =IF(AND(ISNUMBER(O61),ISNUMBER(J61)),IFERROR(O61/J61-1,""),"") -> 0.14624881 | P62: =IF(AND(ISNUMBER(P61),ISNUMBER(K61)),IFERROR(P61/K61-1,""),"") -> 0.15134888 | Q62: =IF(AND(ISNUMBER(Q61),ISNUMBER(L61)),IFERROR(Q61/L61-1,""),"") -> 0.2005277 | R62: =IF(AND(ISNUMBER(R61),ISNUMBER(M61)),IFERROR(R61/M61-1,""),"") -> 0.21840874 | S62: =IF(AND(ISNUMBER(S61),ISNUMBER(N61)),IFERROR(S61/N61-1,""),"") -> 0.17018946 | T62: =IF(AND(ISNUMBER(T61),ISNUMBER(O61)),IFERROR(T61/O61-1,""),"") -> 0.090720795 | U62: =IF(AND(ISNUMBER(U61),ISNUMBER(P61)),IFERROR(U61/P61-1,""),"") -> 0.1076251 | ... CA62: =IF(AND(ISNUMBER(CA61),ISNUMBER(BV61)),IFERROR(CA61/BV61-1,""),"") -> 0.05 | CB62: =IF(AND(ISNUMBER(CB61),ISNUMBER(CA61)),IFERROR(CB61/CA61-1,""),"") -> 0.077666281 | CC62: =IF(AND(ISNUMBER(CC61),ISNUMBER(CB61)),IFERROR(CC61/CB61-1,""),"") -> 0.074747979 | CD62: =IF(AND(ISNUMBER(CD61),ISNUMBER(CC61)),IFERROR(CD61/CC61-1,""),"") -> 0.069696952 | CE62: =IF(AND(ISNUMBER(CE61),ISNUMBER(CD61)),IFERROR(CE61/CD61-1,""),"") -> 0.066461336 | CN62: MA_BANK (Decision Solutions — Banking y/y) | CO62: 0.02 | CP62: Δ → | CQ62: -0.04 | CR62: 2026 depressed by the Learning (Q4-25) and Regulatory Solutions (Q2-26) divestitures; 2027E includes 1H anniversary; organic cc Banking +9% in 1H26; ARR +10%.
B63: % of total revenue | C63: =IF(AND(ISNUMBER(C61),ISNUMBER(C110)),IFERROR(C61/C110,""),"") -> 0.19503215 | D63: =IF(AND(ISNUMBER(D61),ISNUMBER(D110)),IFERROR(D61/D110,""),"") -> 0.21208499 | E63: =IF(AND(ISNUMBER(E61),ISNUMBER(E110)),IFERROR(E61/E110,""),"") -> 0.31371767 | F63: =IF(AND(ISNUMBER(F61),ISNUMBER(F110)),IFERROR(F61/F110,""),"") -> 0.32244603 | G63: =IF(AND(ISNUMBER(G61),ISNUMBER(G110)),IFERROR(G61/G110,""),"") -> 0.30856299 | H63: =IF(AND(ISNUMBER(H61),ISNUMBER(H110)),IFERROR(H61/H110,""),"") -> 0.31209716 | I63: =IF(AND(ISNUMBER(I61),ISNUMBER(I110)),IFERROR(I61/I110,""),"") -> 0.30894041 | J63: =IF(AND(ISNUMBER(J61),ISNUMBER(J110)),IFERROR(J61/J110,""),"") -> 0.28778355 | ... CE63: =IF(AND(ISNUMBER(CE61),ISNUMBER(CE110)),IFERROR(CE61/CE110,""),"") -> 0.46972806 | CH63: =IFERROR(AVERAGE(CA63,CB63,CC63,CD63,CE63),"n/m") -> 0.46446681 | CI63: =IFERROR(AVERAGE(BB63,BG63,BL63,BQ63,BV63),"n/m") -> 0.468218 | CJ63: =IFERROR(AVERAGE(AC63,AH63,AM63,AR63,AW63,BB63,BG63,BL63,BQ63,BV63),"n/m") -> 0.42047051 | CK63: =IFERROR(AVERAGE(C63,D63,E63,F63,G63,H63,I63,N63,S63,X63,AC63,AH63,AM63,AR63,AW63,BB63,BG63,BL63,BQ63,BV63),"n/m") -> 0.35676726 | CN63: 2027E | CO63: =CP63+$CO$62 -> 0.09 | CP63: 0.07 | CQ63: =CP63+$CQ$62 -> 0.03
B64: Memo: MA external revenue as reported | C64: 397.3 | D64: 479.1 | E64: 550.7 | F64: 579.5 | G64: 627 | H64: 711.8 | I64: 843.5 | J64: 210.6 | K64: 218.7 | L64: 227.4 | M64: 256.4 | N64: 913.1 | O64: 241.4 | P64: 251.8 | Q64: 273 | R64: 312.4 | S64: 1068.5 | T64: 263.3 | U64: 278.9 | V64: 286.8 | W64: 321.3 | X64: 1150.3 | Y64: 291 | Z64: 303.3 | AA64: 304.8 | AB64: 334.3 | AC64: 1233.4 | AD64: 307 | AE64: 313.8 | AF64: 368.7 | AG64: 440.8 | AH64: 1430.3 | AI64: 406.8 | AJ64: 422.8 | AK64: 436 | AL64: 464.7 | AM64: 1730.3 | AN64: 472 | AO64: 475.2 | AP64: 493.9 | AQ64: 513 | AR64: 1954 | AS64: 496 | AT64: 497 | AU64: 531 | AV64: 555 | AW64: 2079 | AX64: 564 | AY64: 573 | AZ64: 601 | BA64: 668 | BB64: 2406 | BC64: 695 | BD64: 675 | BE64: 685 | BF64: 714 | BG64: 2769 | BH64: 737 | BI64: 747 | BJ64: 776 | BK64: 796 | BL64: 3056 | BM64: 799 | BN64: 802 | BO64: 831 | BP64: 863 | BQ64: 3295 | BR64: 859 | BS64: 888 | BT64: 909 | BU64: 943 | BV64: 3599 | BW64: 926 | BX64: 925 | CN64: 2028E | CO64: =CP64+$CO$62 -> 0.09 | CP64: 0.07 | CQ64: =CP64+$CQ$62 -> 0.03
B65: Check: MA line build vs reported (should be 0) | C65: =IF(AND(ISNUMBER(C61),ISNUMBER(C64)),IF(ABS(C61-C64)<=0.6,0,ROUND(C61-C64,1)),"") -> 0 | D65: =IF(AND(ISNUMBER(D61),ISNUMBER(D64)),IF(ABS(D61-D64)<=0.6,0,ROUND(D61-D64,1)),"") -> 0 | E65: =IF(AND(ISNUMBER(E61),ISNUMBER(E64)),IF(ABS(E61-E64)<=0.6,0,ROUND(E61-E64,1)),"") -> 0 | F65: =IF(AND(ISNUMBER(F61),ISNUMBER(F64)),IF(ABS(F61-F64)<=0.6,0,ROUND(F61-F64,1)),"") -> 0 | G65: =IF(AND(ISNUMBER(G61),ISNUMBER(G64)),IF(ABS(G61-G64)<=0.6,0,ROUND(G61-G64,1)),"") -> 0 | H65: =IF(AND(ISNUMBER(H61),ISNUMBER(H64)),IF(ABS(H61-H64)<=0.6,0,ROUND(H61-H64,1)),"") -> 0 | I65: =IF(AND(ISNUMBER(I61),ISNUMBER(I64)),IF(ABS(I61-I64)<=0.6,0,ROUND(I61-I64,1)),"") -> 0 | J65: =IF(AND(ISNUMBER(J61),ISNUMBER(J64)),IF(ABS(J61-J64)<=0.6,0,ROUND(J61-J64,1)),"") -> 0 | ... BX65: =IF(AND(ISNUMBER(BX61),ISNUMBER(BX64)),IF(ABS(BX61-BX64)<=0.6,0,ROUND(BX61-BX64,1)),"") -> 0 | CN65: 2029E | CO65: =CP65+$CO$62 -> 0.08 | CP65: 0.06 | CQ65: =CP65+$CQ$62 -> 0.02
B66: Memo: MA recurring revenue (as reported) | P66: 193.1 | Q66: 198.7 | R66: 216.8 | S66: 785.3 | T66: 202.7 | U66: 211.8 | V66: 215.3 | W66: 223.6 | X66: 853.4 | Y66: 221.7 | Z66: 230.5 | AA66: 230.2 | AB66: 237 | AC66: 919.4 | AD66: 242.4 | AE66: 251 | AF66: 291.1 | AG66: 333.1 | AH66: 1117.6 | AI66: 346 | AJ66: 356.3 | AK66: 365 | AL66: 387.8 | AM66: 1455.1 | AN66: 400.5 | AO66: 406 | AP66: 415.4 | AQ66: 439 | AR66: 1661 | AS66: 446 | AT66: 455 | AU66: 480 | AV66: 506 | AW66: 1887 | AX66: 521 | AY66: 535 | AZ66: 565 | BA66: 618 | BB66: 2236 | BC66: 651 | BD66: 633 | BE66: 647 | BF66: 668 | BG66: 2599 | BH66: 692 | BI66: 700 | BJ66: 728 | BK66: 748 | BL66: 2868 | BM66: 757 | BN66: 763 | BO66: 793 | BP66: 821 | BQ66: 3134 | BR66: 822 | BS66: 852 | BT66: 875 | BU66: 913 | BV66: 3462 | BW66: 909 | BX66: 915 | CH66: =IFERROR((CE66/BV66)^(1/5)-1,"n/m") -> -1 | CI66: =IFERROR((BV66/AW66)^(1/5)-1,"n/m") -> 0.12904443 | CJ66: =IFERROR((BV66/X66)^(1/10)-1,"n/m") -> 0.15031675 | CK66: =IFERROR((BV66/C66)^(1/19)-1,"n/m") -> n/m | CN66: 2030E | CO66: =CP66+$CO$62 -> 0.08 | CP66: 0.06 | CQ66: =CP66+$CQ$62 -> 0.02
B67: MA recurring revenue % of segment revenue | C67: =IF(ISNUMBER(C66),IFERROR(C66/C61,""),"") | D67: =IF(ISNUMBER(D66),IFERROR(D66/D61,""),"") | E67: =IF(ISNUMBER(E66),IFERROR(E66/E61,""),"") | F67: =IF(ISNUMBER(F66),IFERROR(F66/F61,""),"") | G67: =IF(ISNUMBER(G66),IFERROR(G66/G61,""),"") | H67: =IF(ISNUMBER(H66),IFERROR(H66/H61,""),"") | I67: =IF(ISNUMBER(I66),IFERROR(I66/I61,""),"") | J67: =IF(ISNUMBER(J66),IFERROR(J66/J61,""),"") | ... BX67: =IF(ISNUMBER(BX66),IFERROR(BX66/BX61,""),"") -> 0.98918919 | CH67: =IFERROR(AVERAGE(CA67,CB67,CC67,CD67,CE67),"n/m") -> n/m | CI67: =IFERROR(AVERAGE(BB67,BG67,BL67,BQ67,BV67),"n/m") -> 0.94390059 | CJ67: =IFERROR(AVERAGE(AC67,AH67,AM67,AR67,AW67,BB67,BG67,BL67,BQ67,BV67),"n/m") -> 0.88449482 | CK67: =IFERROR(AVERAGE(C67,D67,E67,F67,G67,H67,I67,N67,S67,X67,AC67,AH67,AM67,AR67,AW67,BB67,BG67,BL67,BQ67,BV67),"n/m") -> 0.86014976 | CN67: MA_INS (Decision Solutions — Insurance y/y) | CO67: 0.02 | CP67: Δ → | CQ67: -0.04 | CR67: 1H26 +10% (CAPE Analytics, RMS cloud migration); ARR +9%.
B68: Memo: MA Annualized Recurring Revenue (ARR, period end; organic constant currency) | BC68: 2573 | BD68: 2608 | BE68: 2662 | BF68: 2773 | BG68: 2773 | BH68: 2752 | BI68: 2781 | BJ68: 2851 | BK68: 2962 | BL68: 2962 | BM68: 3059 | BN68: 3105 | BO68: 3147 | BP68: 3278 | BQ68: 3278 | BR68: 3266 | BS68: 3297 | BT68: 3361 | BU68: 3498 | BV68: 3498 | BW68: 3607 | BX68: 3661 | CH68: =IFERROR((CE68/BV68)^(1/5)-1,"n/m") -> -1 | CI68: =IFERROR((BV68/AW68)^(1/5)-1,"n/m") -> n/m | CJ68: =IFERROR((BV68/X68)^(1/10)-1,"n/m") -> n/m | CK68: =IFERROR((BV68/C68)^(1/19)-1,"n/m") -> n/m | CN68: 2027E | CO68: =CP68+$CO$67 -> 0.11 | CP68: 0.09 | CQ68: =CP68+$CQ$67 -> 0.05
B69: MA ARR growth y/y % (as published) | CN69: 2028E | CO69: =CP69+$CO$67 -> 0.1 | CP69: 0.08 | CQ69: =CP69+$CQ$67 -> 0.04
B70: Legacy line: Research, Data & Analytics (RD&A) | F70: 413.6 | G70: 425 | H70: 451.3 | I70: 491 | J70: 129.6 | K70: 130.3 | L70: 133.7 | M70: 138.4 | N70: 532 | O70: 140.9 | P70: 144.7 | Q70: 146.8 | R70: 149.5 | S70: 571.8 | T70: 149.6 | U70: 157.5 | V70: 157.9 | W70: 161.4 | X70: 626.4 | Y70: 164.9 | Z70: 168.3 | AA70: 167.7 | AB70: 166.7 | AC70: 667.6 | AD70: 175.4 | AE70: 180.9 | AF70: 218.4 | AG70: 258 | AH70: 832.7 | AI70: 269.2 | AJ70: 279.9 | AK70: 282.6 | AL70: 302.4 | AM70: 1134.1 | AN70: 307.7 | AO70: 315.3 | AP70: 317.5 | AQ70: 333 | AR70: 1273 | AS70: 358 | AT70: 366 | AU70: 386 | AV70: 404 | AW70: 1514 | AX70: 419 | AY70: 435 | AZ70: 445 | BA70: 454 | BB70: 1745 | CF70: Legacy MA revenue lines as originally reported (structure in force in each period; see row comments). | CN70: 2029E | CO70: =CP70+$CO$67 -> 0.1 | CP70: 0.08 | CQ70: =CP70+$CQ$67 -> 0.04
B71: Legacy line: Enterprise Risk Solutions (ERS) | I71: 242.6 | J71: 53 | K71: 60.2 | L71: 64.4 | M71: 84.9 | N71: 262.5 | O71: 59.8 | P71: 67.2 | Q71: 81.1 | R71: 120.4 | S71: 328.5 | T71: 77.1 | U71: 83.2 | V71: 92.2 | W71: 121.5 | X71: 374 | Y71: 89.5 | Z71: 97.5 | AA71: 101.5 | AB71: 130.3 | AC71: 418.8 | AD71: 95.9 | AE71: 97.3 | AF71: 112.6 | AG71: 142.8 | AH71: 448.6 | AI71: 100.1 | AJ71: 105.5 | AK71: 113 | AL71: 118.8 | AM71: 437.4 | AN71: 121.9 | AO71: 117.7 | AP71: 133.3 | AQ71: 149 | AR71: 522 | AS71: 138 | AT71: 131 | AU71: 145 | AV71: 151 | AW71: 565 | AX71: 145 | AY71: 138 | AZ71: 156 | BA71: 214 | BB71: 661 | CN71: 2030E | CO71: =CP71+$CO$67 -> 0.09 | CP71: 0.07 | CQ71: =CP71+$CQ$67 -> 0.03
B72: Legacy line: Professional Services (PS) | C72: 13.5 | D72: 18.1 | E72: 25.6 | F72: 20.8 | G72: 28.8 | H72: 77.1 | I72: 109.9 | J72: 28 | K72: 28.2 | L72: 29.3 | M72: 33.1 | N72: 118.6 | O72: 40.7 | P72: 39.9 | Q72: 45.1 | R72: 42.5 | S72: 168.2 | T72: 36.6 | U72: 38.2 | V72: 36.7 | W72: 38.4 | X72: 149.9 | Y72: 36.6 | Z72: 37.5 | AA72: 35.6 | AB72: 37.3 | AC72: 147 | AD72: 35.7 | AE72: 35.6 | AF72: 37.7 | AG72: 40 | AH72: 149 | AI72: 37.5 | AJ72: 37.4 | AK72: 40.4 | AL72: 43.5 | AM72: 158.8 | AN72: 42.4 | AO72: 42.2 | AP72: 43.1 | AQ72: 31 | AR72: 159 | AS72: 0 | AT72: 0 | AU72: 0 | AV72: 0 | AW72: 0 | CN72: MA_KYC (Decision Solutions — KYC y/y) | CO72: 0.03 | CP72: Δ → | CQ72: -0.04 | CR72: 1H26 +15% (cc +11%); ARR +13%; Orbis / Maxsight entity data.
B73: Legacy line: Subscriptions (2006–2008 basis) | C73: 347.5 | D73: 421.5 | E73: 475.9 | CN73: 2027E | CO73: =CP73+$CO$72 -> 0.15 | CP73: 0.12 | CQ73: =CP73+$CQ$72 -> 0.08
B74: Legacy line: Software (2006–2008 basis) | C74: 36.3 | D74: 39.5 | E74: 49.2 | CN74: 2028E | CO74: =CP74+$CO$72 -> 0.14 | CP74: 0.11 | CQ74: =CP74+$CQ$72 -> 0.07
B75: Legacy line: Risk Management Software (2009–2010) | F75: 145.1 | G75: 173.2 | H75: 183.4 | CN75: 2029E | CO75: =CP75+$CO$72 -> 0.13 | CP75: 0.1 | CQ75: =CP75+$CQ$72 -> 0.06
B76: Legacy line: Decision Solutions (total; sub-lines from 2024 basis) | AX76: 225 | AY76: 222 | AZ76: 250 | BA76: 314 | BB76: 1011 | BC76: 334 | BD76: 312 | BE76: 325 | BF76: 353 | BG76: 1324 | BH76: 354 | BK76: 361 | CN76: 2030E | CO76: =CP76+$CO$72 -> 0.12 | CP76: 0.09 | CQ76: =CP76+$CQ$72 -> 0.05
B77: MA intersegment revenue | H77: 10.6 | I77: 11.8 | J77: 2.8 | K77: 2.7 | L77: 3 | M77: 3.1 | N77: 11.6 | O77: 3.3 | P77: 3.3 | Q77: 3.4 | R77: 3.2 | S77: 13.3 | T77: 3.3 | U77: 3.1 | V77: 3.3 | W77: 3.4 | X77: 13.1 | Y77: 2.8 | Z77: 2.8 | AA77: 4.2 | AB77: 3.7 | AC77: 13.5 | AD77: 3.7 | AE77: 3.8 | AF77: 4.1 | AG77: 4.4 | AH77: 16 | AI77: 5 | AJ77: 2.4 | AK77: 2.6 | AL77: 2.3 | AM77: 12.3 | AN77: 2.4 | AO77: 2.2 | AP77: 2.1 | AQ77: 2 | AR77: 9 | AS77: 2 | AT77: 2 | AU77: 1 | AV77: 2 | AW77: 7 | AX77: 2 | AY77: 2 | AZ77: 2 | BA77: 1 | BB77: 7 | BC77: 2 | BD77: 1 | BE77: 2 | BF77: 3 | BG77: 8 | BH77: 3 | BI77: 4 | BJ77: 3 | BK77: 3 | BL77: 13 | BM77: 3 | BN77: 4 | BO77: 3 | BP77: 3 | BQ77: 13 | BR77: 3 | BS77: 3 | BT77: 3 | BU77: 3 | BV77: 12 | BW77: 3 | BX77: 3 | BY77: =BY61*BY78 -> 3.0685282 | BZ77: =BZ61*BZ78 -> 3.1809046 | CA77: =SUM(BW77:BZ77) -> 12.249433 | CB77: =CB61*CB78 -> 13.200801 | CC77: =CC61*CC78 -> 14.187534 | CD77: =CD61*CD78 -> 15.176362 | CE77: =CE61*CE78 -> 16.185003 | CN77: MA_RI (Research & Insights y/y) | CO77: 0.02 | CP77: Δ → | CQ77: -0.03 | CR77: 1H26 +5%; ARR +6%; mature research subscriptions.
B78: Intersegment revenue % of external revenue | C78: =IF(AND(ISNUMBER(C77),ISNUMBER(C61)),IFERROR(C77/C61,""),"") | D78: =IF(AND(ISNUMBER(D77),ISNUMBER(D61)),IFERROR(D77/D61,""),"") | E78: =IF(AND(ISNUMBER(E77),ISNUMBER(E61)),IFERROR(E77/E61,""),"") | F78: =IF(AND(ISNUMBER(F77),ISNUMBER(F61)),IFERROR(F77/F61,""),"") | G78: =IF(AND(ISNUMBER(G77),ISNUMBER(G61)),IFERROR(G77/G61,""),"") | H78: =IF(AND(ISNUMBER(H77),ISNUMBER(H61)),IFERROR(H77/H61,""),"") -> 0.014891824 | I78: =IF(AND(ISNUMBER(I77),ISNUMBER(I61)),IFERROR(I77/I61,""),"") -> 0.01398933 | J78: =IF(AND(ISNUMBER(J77),ISNUMBER(J61)),IFERROR(J77/J61,""),"") -> 0.013295347 | ... BX78: =IF(AND(ISNUMBER(BX77),ISNUMBER(BX61)),IFERROR(BX77/BX61,""),"") -> 0.0032432432 | BY78: =IFERROR(SUM(BW77:BX77)/SUM(BW61:BX61),0) -> 0.0032414911 | BZ78: =IFERROR(SUM(BW77:BX77)/SUM(BW61:BX61),0) -> 0.0032414911 | CA78: =IFERROR(SUM(BW77:BX77)/SUM(BW61:BX61),0) -> 0.0032414911 | CB78: =$CA$78 -> 0.0032414911 | CC78: =$CA$78 -> 0.0032414911 | CD78: =$CA$78 -> 0.0032414911 | CE78: =$CA$78 -> 0.0032414911 | CN78: 2027E | CO78: =CP78+$CO$77 -> 0.07 | CP78: 0.05 | CQ78: =CP78+$CQ$77 -> 0.02
B79: MA — total segment revenue (external + intersegment) | C79: =IF(AND(ISNUMBER(C61),ISNUMBER(C77)),C61+C77,"") | D79: =IF(AND(ISNUMBER(D61),ISNUMBER(D77)),D61+D77,"") | E79: =IF(AND(ISNUMBER(E61),ISNUMBER(E77)),E61+E77,"") | F79: =IF(AND(ISNUMBER(F61),ISNUMBER(F77)),F61+F77,"") | G79: =IF(AND(ISNUMBER(G61),ISNUMBER(G77)),G61+G77,"") | H79: =IF(AND(ISNUMBER(H61),ISNUMBER(H77)),H61+H77,"") -> 722.4 | I79: =IF(AND(ISNUMBER(I61),ISNUMBER(I77)),I61+I77,"") -> 855.3 | J79: =IF(AND(ISNUMBER(J61),ISNUMBER(J77)),J61+J77,"") -> 213.4 | ... CE79: =IF(AND(ISNUMBER(CE61),ISNUMBER(CE77)),CE61+CE77,"") -> 5009.2584 | CN79: 2028E | CO79: =CP79+$CO$77 -> 0.07 | CP79: 0.05 | CQ79: =CP79+$CQ$77 -> 0.02
B80: MA Adjusted Operating Income (segment measure) | I80: 191.9 | J80: 48.2 | K80: 53.8 | L80: 52.8 | M80: 57.8 | N80: 212.6 | O80: 54.5 | P80: 59.3 | Q80: 68.3 | R80: 77.3 | S80: 257.5 | T80: 56.6 | U80: 71.3 | V80: 74.5 | W80: 77.1 | X80: 279.5 | Y80: 63.5 | Z80: 72.5 | AA80: 73.8 | AB80: 75 | AC80: 285.8 | AD80: 70 | AE80: 74.7 | AF80: 94.5 | AG80: 112.1 | AH80: 351.3 | AI80: 101.4 | AJ80: 105.1 | AK80: 125.5 | AL80: 127.7 | AM80: 459.7 | AN80: 133.3 | AO80: 134.6 | AP80: 145.6 | AQ80: 132 | AR80: 546 | AS80: 146 | AT80: 143 | AU80: 167 | AV80: 158 | AW80: 614 | AX80: 186 | AY80: 183 | AZ80: 157 | BA80: 100 | BB80: 627 | BC80: 224 | BD80: 205 | BE80: 208 | BF80: 203 | BG80: 840 | BH80: 214 | BI80: 210 | BJ80: 262 | BK80: 251 | BL80: 937 | BM80: 238 | BN80: 230 | BO80: 253 | BP80: 293 | BQ80: 1014 | BR80: 259 | BS80: 286 | BT80: 313 | BU80: 338 | BV80: 1196 | BW80: 302 | BX80: 312 | BY80: =BY79*BY81 -> 326.05346 | BZ80: =BZ79*BZ81 -> 351.86781 | CA80: =SUM(BW80:BZ80) -> 1291.9213 | CB80: =CB79*CB81 -> 1450.405 | CC80: =CC79*CC81 -> 1602.7302 | CD80: =CD79*CD81 -> 1761.4065 | CE80: =CE79*CE81 -> 1928.5645 | CH80: =IFERROR((CE80/BV80)^(1/5)-1,"n/m") -> 0.10027336 | CI80: =IFERROR((BV80/AW80)^(1/5)-1,"n/m") -> 0.14264826 | CJ80: =IFERROR((BV80/X80)^(1/10)-1,"n/m") -> 0.15647151 | CK80: =IFERROR((BV80/C80)^(1/19)-1,"n/m") -> n/m | CN80: 2029E | CO80: =CP80+$CO$77 -> 0.07 | CP80: 0.05 | CQ80: =CP80+$CQ$77 -> 0.02
B81: MA Adjusted Operating Margin % (company basis: on total segment revenue) | C81: =IF(AND(ISNUMBER(C80),ISNUMBER(C79)),IFERROR(C80/C79,""),"") | D81: =IF(AND(ISNUMBER(D80),ISNUMBER(D79)),IFERROR(D80/D79,""),"") | E81: =IF(AND(ISNUMBER(E80),ISNUMBER(E79)),IFERROR(E80/E79,""),"") | F81: =IF(AND(ISNUMBER(F80),ISNUMBER(F79)),IFERROR(F80/F79,""),"") | G81: =IF(AND(ISNUMBER(G80),ISNUMBER(G79)),IFERROR(G80/G79,""),"") | H81: =IF(AND(ISNUMBER(H80),ISNUMBER(H79)),IFERROR(H80/H79,""),"") | I81: =IF(AND(ISNUMBER(I80),ISNUMBER(I79)),IFERROR(I80/I79,""),"") -> 0.22436572 | J81: =IF(AND(ISNUMBER(J80),ISNUMBER(J79)),IFERROR(J80/J79,""),"") -> 0.22586692 | ... BX81: =IF(AND(ISNUMBER(BX80),ISNUMBER(BX79)),IFERROR(BX80/BX79,""),"") -> 0.3362069 | BY81: =BY82+$CA$135 -> 0.34331916 | BZ81: =BZ82+$CA$135 -> 0.35741127 | CA81: =IF(AND(ISNUMBER(CA80),ISNUMBER(CA79)),IFERROR(CA80/CA79,""),"") -> 0.34076848 | CB81: =CHOOSE(MATCH($CF$2,{"Bull","Base","Bear"},0),$CO$93,$CP$93,$CQ$93) -> 0.355 | CC81: =CHOOSE(MATCH($CF$2,{"Bull","Base","Bear"},0),$CO$94,$CP$94,$CQ$94) -> 0.365 | CD81: =CHOOSE(MATCH($CF$2,{"Bull","Base","Bear"},0),$CO$95,$CP$95,$CQ$95) -> 0.375 | CE81: =CHOOSE(MATCH($CF$2,{"Bull","Base","Bear"},0),$CO$96,$CP$96,$CQ$96) -> 0.385 | CH81: =IFERROR(AVERAGE(CA81,CB81,CC81,CD81,CE81),"n/m") -> 0.3641537 | CI81: =IFERROR(AVERAGE(BB81,BG81,BL81,BQ81,BV81),"n/m") -> 0.30107564 | CJ81: =IFERROR(AVERAGE(AC81,AH81,AM81,AR81,AW81,BB81,BG81,BL81,BQ81,BV81),"n/m") -> 0.28137725 | CK81: =IFERROR(AVERAGE(C81,D81,E81,F81,G81,H81,I81,N81,S81,X81,AC81,AH81,AM81,AR81,AW81,BB81,BG81,BL81,BQ81,BV81),"n/m") -> 0.26759456 | CN81: 2030E | CO81: =CP81+$CO$77 -> 0.07 | CP81: 0.05 | CQ81: =CP81+$CQ$77 -> 0.02
B82: Q3/Q4-26E margin before EPS calibration (prior-year quarter + 1H26 y/y drift) | BY82: =BT81+IFERROR(SUM(BW80:BX80)/SUM(BW79:BX79)-SUM(BR80:BS80)/SUM(BR79:BS79),0) -> 0.36294697 | BZ82: =BU81+IFERROR(SUM(BW80:BX80)/SUM(BW79:BX79)-SUM(BR80:BS80)/SUM(BR79:BS79),0) -> 0.37703908 | CN82: MA_DI (Data & Information y/y) | CO82: 0.02 | CP82: Δ → | CQ82: -0.03 | CR82: 1H26 +9%; ARR +8%; Orbis company data.
B83: Memo: MA Adjusted Operating Margin as published (%) | I83: 0.224 | J83: 0.226 | K83: 0.243 | L83: 0.229 | M83: 0.223 | N83: 0.23 | O83: 0.223 | P83: 0.232 | Q83: 0.247 | R83: 0.245 | S83: 0.238 | T83: 0.212 | U83: 0.253 | V83: 0.257 | W83: 0.237 | X83: 0.24 | Y83: 0.216 | Z83: 0.237 | AA83: 0.239 | AB83: 0.222 | AC83: 0.229 | AD83: 0.225 | AE83: 0.235 | AF83: 0.253 | AG83: 0.252 | AH83: 0.243 | AI83: 0.246 | AJ83: 0.247 | AK83: 0.286 | AL83: 0.273 | AM83: 0.264 | AN83: 0.281 | AO83: 0.282 | AP83: 0.294 | AQ83: 0.256 | AR83: 0.278 | AS83: 0.293 | AT83: 0.287 | AU83: 0.314 | AV83: 0.284 | AW83: 0.294 | AX83: 0.329 | AY83: 0.318 | AZ83: 0.26 | BA83: 0.149 | BB83: 0.26 | BC83: 0.321 | BD83: 0.303 | BE83: 0.303 | BF83: 0.283 | BG83: 0.302 | BH83: 0.289 | BI83: 0.28 | BJ83: 0.336 | BK83: 0.314 | BL83: 0.305 | BM83: 0.297 | BN83: 0.285 | BO83: 0.303 | BP83: 0.338 | BQ83: 0.307 | BR83: 0.3 | BS83: 0.321 | BT83: 0.343 | BU83: 0.357 | BV83: 0.331 | BW83: 0.325 | BX83: 0.336 | CN83: 2027E | CO83: =CP83+$CO$82 -> 0.1 | CP83: 0.08 | CQ83: =CP83+$CQ$82 -> 0.05
B84: Incremental Adjusted Operating Margin (Δ AOI / Δ total revenue) | D84: =IFERROR((D80-C80)/(D79-C79),"") | E84: =IFERROR((E80-D80)/(E79-D79),"") | F84: =IFERROR((F80-E80)/(F79-E79),"") | G84: =IFERROR((G80-F80)/(G79-F79),"") | H84: =IFERROR((H80-G80)/(H79-G79),"") | I84: =IFERROR((I80-H80)/(I79-H79),"") -> 1.4439428 | N84: =IFERROR((N80-I80)/(N79-I79),"") -> 0.29827089 | O84: =IFERROR((O80-J80)/(O79-J79),"") -> 0.20127796 | P84: =IFERROR((P80-K80)/(P79-K79),"") -> 0.16320475 | Q84: =IFERROR((Q80-L80)/(Q79-L79),"") -> 0.33695652 | R84: =IFERROR((R80-M80)/(R79-M79),"") -> 0.34759358 | S84: =IFERROR((S80-N80)/(S79-N79),"") -> 0.28580522 | T84: =IFERROR((T80-O80)/(T79-O79),"") -> 0.095890411 | U84: =IFERROR((U80-P80)/(U79-P79),"") -> 0.44609665 | ... CA84: =IFERROR((CA80-BV80)/(CA79-BV79),"") -> 0.53230616 | CB84: =IFERROR((CB80-CA80)/(CB79-CA79),"") -> 0.53823936 | CC84: =IFERROR((CC80-CB80)/(CC79-CB79),"") -> 0.49878288 | CD84: =IFERROR((CD80-CC80)/(CD79-CC79),"") -> 0.5184783 | CE84: =IFERROR((CE80-CD80)/(CE79-CD79),"") -> 0.53546342 | CN84: 2028E | CO84: =CP84+$CO$82 -> 0.1 | CP84: 0.08 | CQ84: =CP84+$CQ$82 -> 0.05
CN85: 2029E | CO85: =CP85+$CO$82 -> 0.09 | CP85: 0.07 | CQ85: =CP85+$CQ$82 -> 0.04
B86: Eliminations and growth decomposition | CF86: ELIMINATIONS — intersegment revenue and expense net to zero in Adjusted Operating Income | CN86: 2030E | CO86: =CP86+$CO$82 -> 0.09 | CP86: 0.07 | CQ86: =CP86+$CQ$82 -> 0.04
B87: Eliminations (intersegment revenue) | C87: =IF(ISNUMBER(C34),-(C34+N(C77)),"") | D87: =IF(ISNUMBER(D34),-(D34+N(D77)),"") | E87: =IF(ISNUMBER(E34),-(E34+N(E77)),"") -> -63.6 | F87: =IF(ISNUMBER(F34),-(F34+N(F77)),"") -> -60 | G87: =IF(ISNUMBER(G34),-(G34+N(G77)),"") -> -61.3 | H87: =IF(ISNUMBER(H34),-(H34+N(H77)),"") -> -76.4 | I87: =IF(ISNUMBER(I34),-(I34+N(I77)),"") -> -83.3 | J87: =IF(ISNUMBER(J34),-(J34+N(J77)),"") -> -21.7 | ... CE87: =IF(ISNUMBER(CE34),-(CE34+N(CE77)),"") -> -252.062 | CN87: MIS_M (MIS Adjusted Operating Margin, company basis) | CO87: 0.01 | CP87: Δ → | CQ87: -0.03 | CR87: FY26 guided ~65% (1H26 67.5%, FY2025 63.6%, FY2021 62.2%, FY2022 51.8%); operating leverage on issuance.
B88: Memo: MCO organic constant-currency revenue growth % (as published) | BD88: -0.13 | BE88: -0.17 | BF88: -0.13 | BG88: -0.13 | BH88: -0.02 | BK88: 0.13 | BN88: 0.22 | BO88: 0.23 | BP88: 0.13 | BQ88: 0.2 | BR88: 0.08 | BS88: 0.02 | BT88: 0.09 | BU88: 0.11 | BV88: 0.07 | BW88: 0.06 | BX88: 0.16 | CN88: 2027E | CO88: =CP88+$CO$87 -> 0.665 | CP88: 0.655 | CQ88: =CP88+$CQ$87 -> 0.625
B89: Memo: MA organic constant-currency revenue growth % (as published) | AF89: 0.11 | AG89: 0.13 | AH89: 0.08 | BD89: 0.08 | BE89: 0.09 | BF89: 0.11 | BG89: 0.1 | BH89: 0.09 | BJ89: 0.11 | BK89: 0.1 | BN89: 0.08 | BO89: 0.06 | BP89: 0.08 | BQ89: 0.08 | BR89: 0.07 | BS89: 0.07 | BT89: 0.06 | BU89: 0.06 | BV89: 0.07 | BW89: 0.06 | BX89: 0.08 | CN89: 2028E | CO89: =CP89+$CO$87 -> 0.67 | CP89: 0.66 | CQ89: =CP89+$CQ$87 -> 0.63
B90: Memo: MIS organic constant-currency revenue growth % (as published) | BK90: 0.17 | BN90: 0.37 | BO90: 0.41 | BP90: 0.19 | BQ90: 0.33 | BR90: 0.08 | BS90: -0.02 | BW90: 0.06 | BX90: 0.24 | CN90: 2029E | CO90: =CP90+$CO$87 -> 0.675 | CP90: 0.665 | CQ90: =CP90+$CQ$87 -> 0.635
B91: Contribution to total revenue growth — MIS (pp) | D91: =IFERROR((D27-C27)/C110,"") -> 0.068774238 | E91: =IFERROR((E27-D27)/D110,"") -> -0.25462594 | F91: =IFERROR((F27-E27)/E110,"") -> 0.0074057195 | G91: =IFERROR((G27-F27)/F110,"") -> 0.10421767 | H91: =IFERROR((H27-G27)/G110,"") -> 0.080659449 | I91: =IFERROR((I27-H27)/H110,"") -> 0.13938703 | N91: =IFERROR((N27-I27)/I110,"") -> 0.063216496 | O91: =IFERROR((O27-J27)/J110,"") -> 0.0062858705 | P91: =IFERROR((P27-K27)/K110,"") -> 0.11164021 | Q91: =IFERROR((Q27-L27)/L110,"") -> 0.092133239 | R91: =IFERROR((R27-M27)/M110,"") -> 0.054286448 | S91: =IFERROR((S27-N27)/N110,"") -> 0.069436501 | T91: =IFERROR((T27-O27)/O110,"") -> 0.099713243 | U91: =IFERROR((U27-P27)/P110,"") -> 0.020034345 | ... CA91: =IFERROR((CA27-BV27)/BV110,"") -> 0.042694999 | CB91: =IFERROR((CB27-CA27)/CA110,"") -> 0.034663077 | CC91: =IFERROR((CC27-CB27)/CB110,"") -> 0.029940871 | CD91: =IFERROR((CD27-CC27)/CC110,"") -> 0.028754984 | CE91: =IFERROR((CE27-CD27)/CD110,"") -> 0.02565844 | CN91: 2030E | CO91: =CP91+$CO$87 -> 0.68 | CP91: 0.67 | CQ91: =CP91+$CQ$87 -> 0.64
B92: Contribution to total revenue growth — MA (pp) | D92: =IFERROR((D61-C61+N(D100)-N(C100))/C110,"") -> 0.040155122 | E92: =IFERROR((E61-D61+N(E100)-N(D100))/D110,"") -> 0.03169544 | F92: =IFERROR((F61-E61+N(F100)-N(E100))/E110,"") -> 0.016406517 | G92: =IFERROR((G61-F61+N(G100)-N(F100))/F110,"") -> 0.026430002 | H92: =IFERROR((H61-G61+N(H100)-N(G100))/G110,"") -> 0.041732283 | I92: =IFERROR((I61-H61+N(I100)-N(H100))/H110,"") -> 0.057745429 | N92: =IFERROR((N61-I61+N(N100)-N(I100))/I110,"") -> 0.025491704 | O92: =IFERROR((O61-J61+N(O100)-N(J100))/J110,"") -> 0.042088002 | P92: =IFERROR((P61-K61+N(P100)-N(K100))/K110,"") -> 0.043783069 | Q92: =IFERROR((Q61-L61+N(Q100)-N(L100))/L110,"") -> 0.064635011 | R92: =IFERROR((R61-M61+N(R100)-N(M100))/M110,"") -> 0.071868583 | S92: =IFERROR((S61-N61+N(S100)-N(N100))/N110,"") -> 0.052279226 | T92: =IFERROR((T61-O61+N(T100)-N(O100))/O110,"") -> 0.02854536 | U92: =IFERROR((U61-P61+N(U100)-N(P100))/P110,"") -> 0.031024614 | ... CA92: =IFERROR((CA61-BV61+N(CA100)-N(BV100))/BV110,"") -> 0.023315626 | CB92: =IFERROR((CB61-CA61+N(CB100)-N(CA100))/CA110,"") -> 0.037409156 | CC92: =IFERROR((CC61-CB61+N(CC100)-N(CB100))/CB110,"") -> 0.037945138 | CD92: =IFERROR((CD61-CC61+N(CD100)-N(CC100))/CC110,"") -> 0.035794472 | CE92: =IFERROR((CE61-CD61+N(CE100)-N(CD100))/CD110,"") -> 0.034425736 | CN92: MA_M (MA Adjusted Operating Margin, company basis) | CO92: 0.01 | CP92: Δ → | CQ92: -0.02 | CR92: FY26 guided 34–35% (FY2025 33.1%, FY2021 26.0%); restructuring savings ($300–350m p.a. company-wide) and SaaS mix; Moody's medium-term MA ambition is not quantified on EDGAR in 2026 filings.
CN93: 2027E | CO93: =CP93+$CO$92 -> 0.365 | CP93: 0.355 | CQ93: =CP93+$CQ$92 -> 0.335
B94: Future acquisitions (M&A lever — MA bolt-ons; deals closed from 2027E) | CF94: M&A LEVER — acquired revenue = spend ÷ EV/sales; mid-year convention | CN94: 2028E | CO94: =CP94+$CO$92 -> 0.375 | CP94: 0.365 | CQ94: =CP94+$CQ$92 -> 0.345
B95: Acquisition spend (USDm, scenario) | CA95: 0 | CB95: =MAX(0,CHOOSE(MATCH($CF$2,{"Bull","Base","Bear"},0),$CO$98,$CP$98,$CQ$98)) -> 200 | CC95: =MAX(0,CHOOSE(MATCH($CF$2,{"Bull","Base","Bear"},0),$CO$99,$CP$99,$CQ$99)) -> 200 | CD95: =MAX(0,CHOOSE(MATCH($CF$2,{"Bull","Base","Bear"},0),$CO$100,$CP$100,$CQ$100)) -> 200 | CE95: =MAX(0,CHOOSE(MATCH($CF$2,{"Bull","Base","Bear"},0),$CO$101,$CP$101,$CQ$101)) -> 200 | CF95: Scenario lever M&A_spend (Base $200m p.a. of MA bolt-ons). Funded from cash / commercial paper (debt schedule). | CN95: 2029E | CO95: =CP95+$CO$92 -> 0.385 | CP95: 0.375 | CQ95: =CP95+$CQ$92 -> 0.355
B96: Purchase multiple — EV / sales (x) | CA96: 0 | CB96: 7 | CC96: 7 | CD96: 7 | CE96: 7 | CF96: Analytics / data bolt-ons: RDC (2020) $702m, RMS (2021) $1,927m on ~$300m revenue (~6–7x); BvD (2017) $3.5bn on ~$280m (~12x). 7.0x input (assumption). | CN96: 2030E | CO96: =CP96+$CO$92 -> 0.395 | CP96: 0.385 | CQ96: =CP96+$CQ$92 -> 0.365
B97: Annualised revenue acquired in the year | CA97: 0 | CB97: =IFERROR(CB95/CB96,0) -> 28.571429 | CC97: =IFERROR(CC95/CC96,0) -> 28.571429 | CD97: =IFERROR(CD95/CD96,0) -> 28.571429 | CE97: =IFERROR(CE95/CE96,0) -> 28.571429 | CN97: M&A_spend (bolt-on acquisitions, $m) | CO97: 300 | CP97: Δ → | CQ97: -200 | CR97: Bolt-ons 2022–26 (kompany, GCR, Praedicat, Numerated, CAPE Analytics $223m, ICR Chile, Fintellix, MERIS) ran ~$0–250m p.a.; large deals (BvD $3.5bn 2017, RMS $1.9bn 2021) are not modelled. Base $200m p.a. (assumption).
B98: Growth of acquired businesses after acquisition % | CA98: 0 | CB98: 0.06 | CC98: 0.06 | CD98: 0.06 | CE98: 0.06 | CN98: 2027E | CO98: =MAX(0,CP98+$CO$97) -> 500 | CP98: 200 | CQ98: =MAX(0,CP98+$CQ$97) -> 0
B99: Run-rate revenue of businesses acquired (year end) | CA99: 0 | CB99: =CA99*(1+CB98)+CB97 -> 28.571429 | CC99: =CB99*(1+CC98)+CC97 -> 58.857143 | CD99: =CC99*(1+CD98)+CD97 -> 90.96 | CE99: =CD99*(1+CE98)+CE97 -> 124.98903 | CN99: 2028E | CO99: =MAX(0,CP99+$CO$97) -> 500 | CP99: 200 | CQ99: =MAX(0,CP99+$CQ$97) -> 0
B100: Revenue from future acquisitions (reported in MA) | CA100: 0 | CB100: =CA99*(1+CB98)+0.5*CB97 -> 14.285714 | CC100: =CB99*(1+CC98)+0.5*CC97 -> 44.571429 | CD100: =CC99*(1+CD98)+0.5*CD97 -> 76.674286 | CE100: =CD99*(1+CE98)+0.5*CE97 -> 110.70331 | CF100: Mid-year convention. | CN100: 2029E | CO100: =MAX(0,CP100+$CO$97) -> 500 | CP100: 200 | CQ100: =MAX(0,CP100+$CQ$97) -> 0
...

Sheet Bull-Base-Bear
B2: Moody's Corporation (MCO) — Bull / Base / Bear Case P&L Summary | J2: Share price ($): | K2: =Model!$CA$423 -> 470
B3: Adjusted figures (company definitions: Adjusted Operating Income = model Adjusted EBITDA; adjusted diluted EPS) · USD millions · Live panel linked to Model — toggle scenario via Model!CF2. Bull and Bear panels are value snapshots generated from the Model with the switch set to each case. 2026E = Q1–Q2 actual + Q3–Q4 calibrated to the FY26 guidance (MIS revenue up HSD, MA up MSD, adjusted EPS $16.50–17.00). | J3: As of: | K3: =TODAY() -> 2026-10-12 00:00:00
B5: Scenario: | C5: =Model!$CF$2 -> Base | N5: Scenario: | O5: Bull | P5: Snapshot (values) — Model run with switch = Bull | Z5: Scenario: | AA5: Bear | AB5: Snapshot (values) — Model run with switch = Bear
B7: (USDm, except EPS and shares) | C7: 2025A | D7: 2026E | E7: 2027E | F7: 2028E | G7: 2029E | H7: 2030E | I7: 25-'30 CAGR | J7: LT Hist Avg | K7: LT Hist Min | L7: LT Hist Max | N7: (USDm, except EPS and shares) | O7: 2025A | P7: 2026E | Q7: 2027E | R7: 2028E | S7: 2029E | T7: 2030E | U7: 25-'30 CAGR | V7: LT Hist Avg | W7: LT Hist Min | X7: LT Hist Max | Z7: (USDm, except EPS and shares) | AA7: 2025A | AB7: 2026E | AC7: 2027E | AD7: 2028E | AE7: 2029E | AF7: 2030E | AG7: 25-'30 CAGR | AH7: LT Hist Avg | AI7: LT Hist Min | AJ7: LT Hist Max
B9: Revenue | C9: =Model!BV163 -> 7718 | D9: =Model!CA163 -> 8227.47 | E9: =Model!CB163 -> 8820.4421 | F9: =Model!CC163 -> 9419.2267 | G9: =Model!CD163 -> 10027.233 | H9: =Model!CE163 -> 10629.711 | I9: =IFERROR((H9/C9)^(1/5)-1,"n/m") -> 0.066113234 | N9: Revenue | O9: 7718 | P9: 8304.65 | Q9: 9132.3187 | R9: 10023.117 | S9: 10960.66 | T9: 11930.637 | U9: 0.091017643 | Z9: Revenue | AA9: 7718 | AB9: 8150.29 | AC9: 8381.9835 | AD9: 8572.7801 | AE9: 8742.1364 | AF9: 8878.714 | AG9: 0.028416554
B10: Revenue y/y % | D10: =IFERROR(D9/C9-1,"") -> 0.066010625 | E10: =IFERROR(E9/D9-1,"") -> 0.072072232 | F10: =IFERROR(F9/E9-1,"") -> 0.067886009 | G10: =IFERROR(G9/F9-1,"") -> 0.064549457 | H10: =IFERROR(H9/G9-1,"") -> 0.060084175 | N10: Revenue y/y % | P10: 0.076010625 | Q10: 0.099663286 | R10: 0.097543477 | S10: 0.093538136 | T10: 0.088496201 | Z10: Revenue y/y % | AB10: 0.056010625 | AC10: 0.028427634 | AD10: 0.022762706 | AE10: 0.019755125 | AF10: 0.015622907
B11: MIS revenue y/y % | C11: =Model!BV247 -> 0.085947799 | D11: =Model!CA247 -> 0.08 | E11: =Model!CB247 -> 0.064108832 | F11: =Model!CC247 -> 0.055789592 | G11: =Model!CD247 -> 0.054193777 | H11: =Model!CE247 -> 0.048832833 | N11: MIS revenue y/y % | O11: 0.085947799 | P11: 0.09 | Q11: 0.092289457 | R11: 0.083998082 | S11: 0.082429634 | T11: 0.077071809 | Z11: MIS revenue y/y % | AA11: 0.085947799 | AB11: 0.07 | AC11: 0.016024025 | AD11: 0.0077063507 | AE11: 0.006112985 | AF11: 0.00078070649
B12: Adjusted Operating Income (= Adjusted EBITDA) | C12: =Model!BV219 -> 3942 | D12: =Model!CA219 -> 4319.482 | E12: =Model!CB219 -> 4686.9057 | F12: =Model!CC219 -> 5053.2219 | G12: =Model!CD219 -> 5433.7829 | H12: =Model!CE219 -> 5816.6537 | I12: =IFERROR((H12/C12)^(1/5)-1,"n/m") -> 0.080914437 | N12: Adjusted Operating Income (= Adjusted EBITDA) | O12: 3942 | P12: 4375.0815 | Q12: 4944.5743 | R12: 5470.5785 | S12: 6034.7439 | T12: 6625.69 | U12: 0.10943764 | Z12: Adjusted Operating Income (= Adjusted EBITDA) | AA12: 3942 | AB12: 4263.83 | AC12: 4230.2749 | AD12: 4369.5499 | AE12: 4502.5661 | AF12: 4619.4721 | AG12: 0.032226838
B13: Adjusted Operating Margin % | C13: =IFERROR(C12/C9,"") -> 0.51075408 | D13: =IFERROR(D12/D9,"") -> 0.52500732 | E13: =IFERROR(E12/E9,"") -> 0.53136857 | F13: =IFERROR(F12/F9,"") -> 0.53647948 | G13: =IFERROR(G12/G9,"") -> 0.54190254 | H13: =IFERROR(H12/H9,"") -> 0.54720715 | J13: =IFERROR(AVERAGE(Model!C220,Model!D220,Model!E220,Model!F220,Model!G220,Model!H220,Model!I220,Model!N220,Model!S220,Model!X220,Model!AC220,Model!AH220,Model!AM220,Model!AR220,Model!AW220,Model!BB220,Model!BG220,Model!BL220,Model!BQ220,Model!BV220),"") -> 0.46801913 | K13: =IFERROR(MIN(Model!C220,Model!D220,Model!E220,Model!F220,Model!G220,Model!H220,Model!I220,Model!N220,Model!S220,Model!X220,Model!AC220,Model!AH220,Model!AM220,Model!AR220,Model!AW220,Model!BB220,Model!BG220,Model!BL220,Model!BQ220,Model!BV220),"") -> 0.41299213 | L13: =IFERROR(MAX(Model!C220,Model!D220,Model!E220,Model!F220,Model!G220,Model!H220,Model!I220,Model!N220,Model!S220,Model!X220,Model!AC220,Model!AH220,Model!AM220,Model!AR220,Model!AW220,Model!BB220,Model!BG220,Model!BL220,Model!BQ220,Model!BV220),"") -> 0.55883364 | N13: Adjusted Operating Margin % | O13: 0.51075408 | P13: 0.52682311 | Q13: 0.5414369 | R13: 0.54579614 | S13: 0.55058214 | T13: 0.55535088 | V13: 0.46801913 | W13: 0.41299213 | X13: 0.55883364 | Z13: Adjusted Operating Margin % | AA13: 0.51075408 | AB13: 0.52315071 | AC13: 0.50468662 | AD13: 0.50970045 | AE13: 0.51504184 | AF13: 0.52028617 | AH13: 0.46801913 | AI13: 0.41299213 | AJ13: 0.55883364
B15: Operating Income (GAAP) | C15: =Model!BV170 -> 3351 | D15: =Model!CA170 -> 3654.482 | E15: =Model!CB170 -> 4091.7031 | F15: =Model!CC170 -> 4514.7105 | G15: =Model!CD170 -> 4889.4147 | H15: =Model!CE170 -> 5268.058 | I15: =IFERROR((H15/C15)^(1/5)-1,"n/m") -> 0.094700267 | N15: Operating Income (GAAP) | O15: 3351 | P15: 3710.0815 | Q15: 4334.1442 | R15: 4897.7232 | S15: 5434.9054 | T15: 5999.6591 | U15: 0.12354489 | Z15: Operating Income (GAAP) | AA15: 3351 | AB15: 3598.83 | AC15: 3653.5235 | AD15: 3870.357 | AE15: 4020.3649 | AF15: 4156.081 | AG15: 0.044003405
B16: Operating income y/y % | D16: =IFERROR(D15/C15-1,"") -> 0.090564606 | E16: =IFERROR(E15/D15-1,"") -> 0.1196397 | F16: =IFERROR(F15/E15-1,"") -> 0.10338173 | G16: =IFERROR(G15/F15-1,"") -> 0.082996287 | H16: =IFERROR(H15/G15-1,"") -> 0.07744144 | N16: Operating income y/y % | P16: 0.10715653 | Q16: 0.16820726 | R16: 0.13003237 | S16: 0.10967999 | T16: 0.10391232 | Z16: Operating income y/y % | AB16: 0.073957016 | AC16: 0.015197595 | AD16: 0.059349136 | AE16: 0.038758153 | AF16: 0.033757167
B17: Operating margin (GAAP) % | C17: =IFERROR(C15/C9,"") -> 0.43417984 | D17: =IFERROR(D15/D9,"") -> 0.44418053 | E17: =IFERROR(E15/E9,"") -> 0.46388867 | F17: =IFERROR(F15/F9,"") -> 0.47930797 | G17: =IFERROR(G15/G9,"") -> 0.48761357 | H17: =IFERROR(H15/H9,"") -> 0.4955975 | J17: =IFERROR(AVERAGE(Model!C256,Model!D256,Model!E256,Model!F256,Model!G256,Model!H256,Model!I256,Model!N256,Model!S256,Model!X256,Model!AC256,Model!AH256,Model!AM256,Model!AR256,Model!AW256,Model!BB256,Model!BG256,Model!BL256,Model!BQ256,Model!BV256),"") -> 0.41255603 | K17: =IFERROR(MIN(Model!C256,Model!D256,Model!E256,Model!F256,Model!G256,Model!H256,Model!I256,Model!N256,Model!S256,Model!X256,Model!AC256,Model!AH256,Model!AM256,Model!AR256,Model!AW256,Model!BB256,Model!BG256,Model!BL256,Model!BQ256,Model!BV256),"") -> 0.17720992 | L17: =IFERROR(MAX(Model!C256,Model!D256,Model!E256,Model!F256,Model!G256,Model!H256,Model!I256,Model!N256,Model!S256,Model!X256,Model!AC256,Model!AH256,Model!AM256,Model!AR256,Model!AW256,Model!BB256,Model!BG256,Model!BL256,Model!BQ256,Model!BV256),"") -> 0.61828089 | N17: Operating margin (GAAP) % | O17: 0.43417984 | P17: 0.44674749 | Q17: 0.47459406 | R17: 0.48864273 | S17: 0.49585565 | T17: 0.50287834 | V17: 0.41255603 | W17: 0.17720992 | X17: 0.61828089 | Z17: Operating margin (GAAP) % | AA17: 0.43417984 | AB17: 0.44155852 | AC17: 0.43587816 | AD17: 0.45147046 | AE17: 0.45988357 | AF17: 0.46809493 | AH17: 0.41255603 | AI17: 0.17720992 | AJ17: 0.61828089
B19: Adjusted Net Income (attributable to Moody's) | C19: =Model!BV235 -> 2687 | D19: =Model!CA235 -> 2922.0063 | E19: =Model!CB235 -> 3136.1109 | F19: =Model!CC235 -> 3361.5854 | G19: =Model!CD235 -> 3607.015 | H19: =Model!CE235 -> 3854.0686 | I19: =IFERROR((H19/C19)^(1/5)-1,"n/m") -> 0.074806677 | N19: Adjusted Net Income (attributable to Moody's) | O19: 2687 | P19: 2964.262 | Q19: 3321.8985 | R19: 3610.1636 | S19: 3974.6325 | T19: 4356.999 | U19: 0.10149862 | Z19: Adjusted Net Income (attributable to Moody's) | AA19: 2687 | AB19: 2879.7108 | AC19: 2802.5746 | AD19: 2890.5478 | AE19: 2965.9978 | AF19: 3029.5823 | AG19: 0.024290202
B21: FDSO (m) | C21: =Model!BV189 -> 179.9 | D21: =Model!CA189 -> 174.44814 | E21: =Model!CB189 -> 169.75645 | F21: =Model!CC189 -> 164.60191 | G21: =Model!CD189 -> 159.77157 | H21: =Model!CE189 -> 154.98752 | I21: =IFERROR((H21/C21)^(1/5)-1,"n/m") -> -0.029371335 | N21: FDSO (m) | O21: 179.9 | P21: 174.36835 | Q21: 168.08029 | R21: 161.25853 | S21: 155.68239 | T21: 149.9091 | U21: -0.035817233 | Z21: FDSO (m) | AA21: 179.9 | AB21: 174.52793 | AC21: 171.76105 | AD21: 168.9024 | AE21: 165.42983 | AF21: 162.26194 | AG21: -0.020426333
B23: Adjusted EPS — Diluted ($) | C23: =Model!BV238 -> 14.936076 | D23: =Model!CA238 -> 16.75 | E23: =Model!CB238 -> 18.474177 | F23: =Model!CC238 -> 20.422518 | G23: =Model!CD238 -> 22.576075 | H23: =Model!CE238 -> 24.866961 | I23: =IFERROR((H23/C23)^(1/5)-1,"n/m") -> 0.10733045 | N23: Adjusted EPS — Diluted ($) | O23: 14.936076 | P23: 17 | Q23: 19.763761 | R23: 22.387427 | S23: 25.530392 | T23: 29.064273 | U23: 0.14241683 | Z23: Adjusted EPS — Diluted ($) | AA23: 14.936076 | AB23: 16.5 | AC23: 16.316706 | AD23: 17.113717 | AE23: 17.929038 | AF23: 18.670936 | AG23: 0.045648975
B24: EPS y/y % | D24: =IFERROR(D23/C23-1,"") -> 0.12144585 | E24: =IFERROR(E23/D23-1,"") -> 0.10293597 | F24: =IFERROR(F23/E23-1,"") -> 0.10546292 | G24: =IFERROR(G23/F23-1,"") -> 0.10545011 | H24: =IFERROR(H23/G23-1,"") -> 0.10147407 | N24: EPS y/y % | P24: 0.13818385 | Q24: 0.16257416 | R24: 0.13275137 | S24: 0.14038975 | T24: 0.1384186 | Z24: EPS y/y % | AB24: 0.10470785 | AC24: -0.011108702 | AD24: 0.048846267 | AE24: 0.047641409 | AF24: 0.041379663
B26: P / E (x) — assumed (adjusted EPS) | F26: 31 | G26: 31 | H26: 31 | N26: P / E (x) — assumed (adjusted EPS) | R26: 35 | S26: 35 | T26: 35 | Z26: P / E (x) — assumed (adjusted EPS) | AD26: 24 | AE26: 24 | AF26: 24
B27: Price Target ($) | F27: =F26*F23 -> 633.09806 | G27: =G26*G23 -> 699.85832 | H27: =H26*H23 -> 770.8758 | N27: Price Target ($) | R27: =R26*R23 -> 783.55994 | S27: =S26*S23 -> 893.56373 | T27: =T26*T23 -> 1017.2496 | Z27: Price Target ($) | AD27: =AD26*AD23 -> 410.7292 | AE27: =AE26*AE23 -> 430.29692 | AF27: =AF26*AF23 -> 448.10246
B28: Upside / (Downside) vs current | F28: =IFERROR(F27/$K$2-1,"") -> 0.34701716 | G28: =IFERROR(G27/$K$2-1,"") -> 0.48906026 | H28: =IFERROR(H27/$K$2-1,"") -> 0.64016127 | N28: Upside / (Downside) vs current | R28: =IFERROR(R27/$K$2-1,"") -> 0.66714881 | S28: =IFERROR(S27/$K$2-1,"") -> 0.90119942 | T28: =IFERROR(T27/$K$2-1,"") -> 1.1643608 | Z28: Upside / (Downside) vs current | AD28: =IFERROR(AD27/$K$2-1,"") -> -0.12610809 | AE28: =IFERROR(AE27/$K$2-1,"") -> -0.084474646 | AF28: =IFERROR(AF27/$K$2-1,"") -> -0.046590516
B29: IRR (to Dec-Y-1) | F29: =IFERROR((F27/$K$2)^(1/((DATE(2028-1,12,31)-$K$3)/365.25))-1,"") -> 0.27699065 | G29: =IFERROR((G27/$K$2)^(1/((DATE(2029-1,12,31)-$K$3)/365.25))-1,"") -> 0.19639471 | H29: =IFERROR((H27/$K$2)^(1/((DATE(2030-1,12,31)-$K$3)/365.25))-1,"") -> 0.16611374 | N29: IRR (to Dec-Y-1) | R29: =IFERROR((R27/$K$2)^(1/((DATE(2028-1,12,31)-$K$3)/365.25))-1,"") -> 0.5212254 | S29: =IFERROR((S27/$K$2)^(1/((DATE(2029-1,12,31)-$K$3)/365.25))-1,"") -> 0.33556697 | T29: =IFERROR((T27/$K$2)^(1/((DATE(2030-1,12,31)-$K$3)/365.25))-1,"") -> 0.27100993 | Z29: IRR (to Dec-Y-1) | AD29: =IFERROR((AD27/$K$2)^(1/((DATE(2028-1,12,31)-$K$3)/365.25))-1,"") -> -0.10473978 | AE29: =IFERROR((AE27/$K$2)^(1/((DATE(2029-1,12,31)-$K$3)/365.25))-1,"") -> -0.038968793 | AF29: =IFERROR((AF27/$K$2)^(1/((DATE(2030-1,12,31)-$K$3)/365.25))-1,"") -> -0.014709087
B31: Free Cash Flow | C31: =Model!BV288 -> 2575 | D31: =Model!CA288 -> 2933.7428 | E31: =Model!CB288 -> 3296.0488 | F31: =Model!CC288 -> 3617.7692 | G31: =Model!CD288 -> 3878.1855 | H31: =Model!CE288 -> 4130.9902 | I31: =IFERROR((H31/C31)^(1/5)-1,"n/m") -> 0.099146008 | N31: Free Cash Flow | O31: 2575 | P31: 2984.5644 | Q31: 3513.2109 | R31: 3911.903 | S31: 4303.9789 | T31: 4704.8446 | U31: 0.12811561 | Z31: Free Cash Flow | AA31: 2575 | AB31: 2882.8813 | AC31: 2915.6372 | AD31: 3085.1408 | AE31: 3162.1525 | AF31: 3218.7974 | AG31: 0.045642633
B32: FCF % | C32: =IFERROR(C31/C9,"") -> 0.33363566 | D32: =IFERROR(D31/D9,"") -> 0.35657897 | E32: =IFERROR(E31/E9,"") -> 0.37368295 | F32: =IFERROR(F31/F9,"") -> 0.38408346 | G32: =IFERROR(G31/G9,"") -> 0.38676528 | H32: =IFERROR(H31/H9,"") -> 0.38862678 | J32: =IFERROR(AVERAGE(Model!C292,Model!D292,Model!E292,Model!F292,Model!G292,Model!H292,Model!I292,Model!N292,Model!S292,Model!X292,Model!AC292,Model!AH292,Model!AM292,Model!AR292,Model!AW292,Model!BB292,Model!BG292,Model!BL292,Model!BQ292,Model!BV292),"") -> 0.30304136 | K32: =IFERROR(MIN(Model!C292,Model!D292,Model!E292,Model!F292,Model!G292,Model!H292,Model!I292,Model!N292,Model!S292,Model!X292,Model!AC292,Model!AH292,Model!AM292,Model!AR292,Model!AW292,Model!BB292,Model!BG292,Model!BL292,Model!BQ292,Model!BV292),"") -> 0.15625223 | L32: =IFERROR(MAX(Model!C292,Model!D292,Model!E292,Model!F292,Model!G292,Model!H292,Model!I292,Model!N292,Model!S292,Model!X292,Model!AC292,Model!AH292,Model!AM292,Model!AR292,Model!AW292,Model!BB292,Model!BG292,Model!BL292,Model!BQ292,Model!BV292),"") -> 0.38037609 | N32: FCF % | O32: 0.33363566 | P32: 0.35938472 | Q32: 0.38470086 | R32: 0.39028808 | S32: 0.39267514 | T32: 0.39434981 | V32: 0.30304136 | W32: 0.15625223 | X32: 0.38037609 | Z32: FCF % | AA32: 0.33363566 | AB32: 0.35371518 | AC32: 0.34784573 | AD32: 0.35987635 | AE32: 0.36171393 | AF32: 0.36252969 | AH32: 0.30304136 | AI32: 0.15625223 | AJ32: 0.38037609
B33: FCF / share ($) | C33: =IFERROR(C31/C21,"") -> 14.313508 | D33: =IFERROR(D31/D21,"") -> 16.817278 | E33: =IFERROR(E31/E21,"") -> 19.416339 | F33: =IFERROR(F31/F21,"") -> 21.978902 | G33: =IFERROR(G31/G21,"") -> 24.273314 | H33: =IFERROR(H31/H21,"") -> 26.653696 | N33: FCF / share ($) | O33: 14.313508 | P33: 17.116434 | Q33: 20.901981 | R33: 24.25858 | S33: 27.645894 | T33: 31.38465 | Z33: FCF / share ($) | AA33: 14.313508 | AB33: 16.518166 | AC33: 16.974961 | AD33: 18.26582 | AE33: 19.114766 | AF33: 19.837045
B34: FCF Yield (on PT) | F34: =IFERROR(F33/F$27,"") -> 0.034716426 | G34: =IFERROR(G33/G$27,"") -> 0.034683182 | H34: =IFERROR(H33/H$27,"") -> 0.034575863 | N34: FCF Yield (on PT) | R34: =IFERROR(R33/R$27,"") -> 0.030959444 | S34: =IFERROR(S33/S$27,"") -> 0.030938917 | T34: =IFERROR(T33/T$27,"") -> 0.030852459 | Z34: FCF Yield (on PT) | AD34: =IFERROR(AD33/AD$27,"") -> 0.044471687 | AE34: =IFERROR(AE33/AE$27,"") -> 0.04442227 | AF34: =IFERROR(AF33/AF$27,"") -> 0.044268993
B35: Adjusted Operating Income (leverage basis) | C35: =Model!BV219 -> 3942 | D35: =Model!CA219 -> 4319.482 | E35: =Model!CB219 -> 4686.9057 | F35: =Model!CC219 -> 5053.2219 | G35: =Model!CD219 -> 5433.7829 | H35: =Model!CE219 -> 5816.6537 | I35: =IFERROR((H35/C35)^(1/5)-1,"n/m") -> 0.080914437 | N35: Adjusted Operating Income (leverage basis) | O35: 3942 | P35: 4375.0815 | Q35: 4944.5743 | R35: 5470.5785 | S35: 6034.7439 | T35: 6625.69 | U35: 0.10943764 | Z35: Adjusted Operating Income (leverage basis) | AA35: 3942 | AB35: 4263.83 | AC35: 4230.2749 | AD35: 4369.5499 | AE35: 4502.5661 | AF35: 4619.4721 | AG35: 0.032226838
B36: Adjusted Operating Income % of revenue | C36: =IFERROR(C35/C9,"") -> 0.51075408 | D36: =IFERROR(D35/D9,"") -> 0.52500732 | E36: =IFERROR(E35/E9,"") -> 0.53136857 | F36: =IFERROR(F35/F9,"") -> 0.53647948 | G36: =IFERROR(G35/G9,"") -> 0.54190254 | H36: =IFERROR(H35/H9,"") -> 0.54720715 | J36: =IFERROR(AVERAGE(Model!C255,Model!D255,Model!E255,Model!F255,Model!G255,Model!H255,Model!I255,Model!N255,Model!S255,Model!X255,Model!AC255,Model!AH255,Model!AM255,Model!AR255,Model!AW255,Model!BB255,Model!BG255,Model!BL255,Model!BQ255,Model!BV255),"") -> 0.46801913 | K36: =IFERROR(MIN(Model!C255,Model!D255,Model!E255,Model!F255,Model!G255,Model!H255,Model!I255,Model!N255,Model!S255,Model!X255,Model!AC255,Model!AH255,Model!AM255,Model!AR255,Model!AW255,Model!BB255,Model!BG255,Model!BL255,Model!BQ255,Model!BV255),"") -> 0.41299213 | L36: =IFERROR(MAX(Model!C255,Model!D255,Model!E255,Model!F255,Model!G255,Model!H255,Model!I255,Model!N255,Model!S255,Model!X255,Model!AC255,Model!AH255,Model!AM255,Model!AR255,Model!AW255,Model!BB255,Model!BG255,Model!BL255,Model!BQ255,Model!BV255),"") -> 0.55883364 | N36: Adjusted Operating Income % of revenue | O36: 0.51075408 | P36: 0.52682311 | Q36: 0.5414369 | R36: 0.54579614 | S36: 0.55058214 | T36: 0.55535088 | V36: 0.46801913 | W36: 0.41299213 | X36: 0.55883364 | Z36: Adjusted Operating Income % of revenue | AA36: 0.51075408 | AB36: 0.52315071 | AC36: 0.50468662 | AD36: 0.50970045 | AE36: 0.51504184 | AF36: 0.52028617 | AH36: 0.46801913 | AI36: 0.41299213 | AJ36: 0.55883364
B38: Net Debt | C38: =Model!BV417 -> 4546 | D38: =Model!CA417 -> 4991.0492 | E38: =Model!CB417 -> 5829.6321 | F38: =Model!CC417 -> 6287.5274 | G38: =Model!CD417 -> 6763.2286 | H38: =Model!CE417 -> 7241.8171 | N38: Net Debt | O38: 4546 | P38: 5090.2276 | Q38: 7387.8615 | R38: 8176.8678 | S38: 9023.1158 | T38: 9909.5349 | Z38: Net Debt | AA38: 4546 | AB38: 4891.9107 | AC38: 4201.2749 | AD38: 4340.5499 | AE38: 4473.5661 | AF38: 4590.4721
B39: Net Debt / Adjusted Operating Income (x) | C39: =IFERROR(C38/C35,"") -> 1.1532217 | D39: =IFERROR(D38/D35,"") -> 1.155474 | E39: =IFERROR(E38/E35,"") -> 1.2438125 | F39: =IFERROR(F38/F35,"") -> 1.2442611 | G39: =IFERROR(G38/G35,"") -> 1.244663 | H39: =IFERROR(H38/H35,"") -> 1.2450143 | N39: Net Debt / Adjusted Operating Income (x) | O39: 1.1532217 | P39: 1.1634589 | Q39: 1.494135 | R39: 1.4946989 | S39: 1.4951945 | T39: 1.4956231 | Z39: Net Debt / Adjusted Operating Income (x) | AA39: 1.1532217 | AB39: 1.1473044 | AC39: 0.99314465 | AD39: 0.99336316 | AE39: 0.99355923 | AF39: 0.99372223
B40: Share repurchases ($m; 2026E = 2H) | D40: =Model!CA302 -> 685 | E40: =Model!CB302 -> 3082.2476 | F40: =Model!CC302 -> 2980.5519 | G40: =Model!CD302 -> 3211.2215 | H40: =Model!CE302 -> 3417.3273 | N40: Share repurchases ($m; 2026E = 2H) | P40: 835 | Q40: 4459.8938 | R40: 3320.6442 | S40: 3727.0553 | T40: 4125.3273 | AB40: 535 | AC40: 1371.184 | AD40: 2311.2407 | AE40: 2326.3011 | AF40: 2306.199
B41: Implied avg buyback price ($) | D41: =Model!CA301 -> 470 | E41: =Model!CB301 -> 507.6 | F41: =Model!CC301 -> 548.208 | G41: =Model!CD301 -> 592.06464 | H41: =Model!CE301 -> 639.42981 | N41: Implied avg buyback price ($) | P41: 470 | Q41: 507.6 | R41: 548.208 | S41: 592.06464 | T41: 639.42981 | AB41: 470 | AC41: 507.6 | AD41: 548.208 | AE41: 592.06464 | AF41: 639.42981
B42: Shares repurchased (m) | D42: =Model!CA303 -> 1.4574468 | E42: =Model!CB303 -> 6.0721978 | F42: =Model!CC303 -> 5.4368996 | G42: =Model!CD303 -> 5.4237684 | H42: =Model!CE303 -> 5.3443353 | N42: Shares repurchased (m) | P42: 1.7765957 | Q42: 8.7862368 | R42: 6.0572706 | S42: 6.2950142 | T42: 6.4515717 | AB42: 1.1382979 | AC42: 2.7013081 | AD42: 4.2159922 | AE42: 3.9291336 | AF42: 3.6066492
B44: ROIC | C44: =Model!BV400 -> 0.32904969 | D44: =Model!CA400 -> 0.36176661 | E44: =Model!CB400 -> 0.38615226 | F44: =Model!CC400 -> 0.41167208 | G44: =Model!CD400 -> 0.43662086 | H44: =Model!CE400 -> 0.4606037 | J44: =IFERROR(AVERAGE(Model!C400,Model!D400,Model!E400,Model!F400,Model!G400,Model!H400,Model!I400,Model!N400,Model!S400,Model!X400,Model!AC400,Model!AH400,Model!AM400,Model!AR400,Model!AW400,Model!BB400,Model!BG400,Model!BL400,Model!BQ400,Model!BV400),"") -> 0.38734712 | K44: =IFERROR(MIN(Model!C400,Model!D400,Model!E400,Model!F400,Model!G400,Model!H400,Model!I400,Model!N400,Model!S400,Model!X400,Model!AC400,Model!AH400,Model!AM400,Model!AR400,Model!AW400,Model!BB400,Model!BG400,Model!BL400,Model!BQ400,Model!BV400),"") -> 0.208933 | L44: =IFERROR(MAX(Model!C400,Model!D400,Model!E400,Model!F400,Model!G400,Model!H400,Model!I400,Model!N400,Model!S400,Model!X400,Model!AC400,Model!AH400,Model!AM400,Model!AR400,Model!AW400,Model!BB400,Model!BG400,Model!BL400,Model!BQ400,Model!BV400),"") -> 1.0906407 | N44: ROIC | O44: 0.32904969 | P44: 0.3671063 | Q44: 0.39567567 | R44: 0.42058102 | S44: 0.4457308 | T44: 0.47087151 | V44: 0.38734712 | W44: 0.208933 | X44: 1.0906407 | Z44: ROIC | AA44: 0.32904969 | AB44: 0.35643298 | AC44: 0.353593 | AD44: 0.3678638 | AE44: 0.38057143 | AF44: 0.3914531 | AH44: 0.38734712 | AI44: 0.208933 | AJ44: 1.0906407
B45: RONTA (n/m where net tangible assets ≤ 0) | C45: =Model!BV411 -> 0.62394666 | D45: =Model!CA411 -> 0.72033351 | E45: =Model!CB411 -> 0.82799711 | F45: =Model!CC411 -> 0.86941138 | G45: =Model!CD411 -> 0.91566071 | H45: =Model!CE411 -> 0.96116252 | J45: =IFERROR(AVERAGE(Model!C411,Model!D411,Model!E411,Model!F411,Model!G411,Model!H411,Model!I411,Model!N411,Model!S411,Model!X411,Model!AC411,Model!AH411,Model!AM411,Model!AR411,Model!AW411,Model!BB411,Model!BG411,Model!BL411,Model!BQ411,Model!BV411),"") -> 0.60728083 | K45: =IFERROR(MIN(Model!C411,Model!D411,Model!E411,Model!F411,Model!G411,Model!H411,Model!I411,Model!N411,Model!S411,Model!X411,Model!AC411,Model!AH411,Model!AM411,Model!AR411,Model!AW411,Model!BB411,Model!BG411,Model!BL411,Model!BQ411,Model!BV411),"") -> 0.36751088 | L45: =IFERROR(MAX(Model!C411,Model!D411,Model!E411,Model!F411,Model!G411,Model!H411,Model!I411,Model!N411,Model!S411,Model!X411,Model!AC411,Model!AH411,Model!AM411,Model!AR411,Model!AW411,Model!BB411,Model!BG411,Model!BL411,Model!BQ411,Model!BV411),"") -> 1.4961731 | N45: RONTA (n/m where net tangible assets ≤ 0) | O45: 0.62394666 | P45: 0.74913278 | Q45: 0.89959403 | R45: 0.9834561 | S45: 1.0732441 | T45: 1.1657544 | V45: 0.60728083 | W45: 0.36751088 | X45: 1.4961731 | Z45: RONTA (n/m where net tangible assets ≤ 0) | AA45: 0.62394666 | AB45: 0.69294912 | AC45: 0.52596685 | AD45: 0.50261408 | AE45: 0.48163663 | AF45: 0.46127939 | AH45: 0.60728083 | AI45: 0.36751088 | AJ45: 1.4961731
B47: Implied Market Cap (USDm) | F47: =F27*F21 -> 104209.15 | G47: =G27*G21 -> 111817.46 | H47: =H27*H21 -> 119476.13 | N47: Implied Market Cap (USDm) | R47: =R27*R21 -> 126355.73 | S47: =S27*S21 -> 139112.14 | T47: =T27*T21 -> 152494.96 | Z47: Implied Market Cap (USDm) | AD47: =AD27*AD21 -> 69373.147 | AE47: =AE27*AE21 -> 71183.948 | AF47: =AF27*AF21 -> 72709.976
B48: (+) Net Debt & NCI | F48: =F38+Model!CC332 -> 6438.5274 | G48: =G38+Model!CD332 -> 6918.2286 | H48: =H38+Model!CE332 -> 7400.8171 | N48: (+) Net Debt & NCI | R48: =R38+Model!CC332 -> 8327.8678 | S48: =S38+Model!CD332 -> 9178.1158 | T48: =T38+Model!CE332 -> 10068.535 | Z48: (+) Net Debt & NCI | AD48: =AD38+Model!CC332 -> 4491.5499 | AE48: =AE38+Model!CD332 -> 4628.5661 | AF48: =AF38+Model!CE332 -> 4749.4721
B49: Implied Enterprise Value (USDm) | F49: =F47+F48 -> 110647.67 | G49: =G47+G48 -> 118735.69 | H49: =H47+H48 -> 126876.95 | N49: Implied Enterprise Value (USDm) | R49: =R47+R48 -> 134683.59 | S49: =S47+S48 -> 148290.25 | T49: =T47+T48 -> 162563.5 | Z49: Implied Enterprise Value (USDm) | AD49: =AD47+AD48 -> 73864.696 | AE49: =AE47+AE48 -> 75812.514 | AF49: =AF47+AF48 -> 77459.448
B50: Implied EV / Adjusted Operating Income (x) | F50: =IFERROR(F49/F35,"") -> 21.896461 | G50: =IFERROR(G49/G35,"") -> 21.851387 | H50: =IFERROR(H49/H35,"") -> 21.812704 | N50: Implied EV / Adjusted Operating Income (x) | R50: =IFERROR(R49/R35,"") -> 24.619625 | S50: =IFERROR(S49/S35,"") -> 24.57275 | T50: =IFERROR(T49/T35,"") -> 24.535331 | Z50: Implied EV / Adjusted Operating Income (x) | AD50: =IFERROR(AD49/AD35,"") -> 16.904418 | AE50: =IFERROR(AE49/AE35,"") -> 16.837624 | AF50: =IFERROR(AF49/AF35,"") -> 16.76803

Sheet DCF
B2: DCF VALUATION — MOODY'S CORPORATION (MCO)
B4: 1. WACC BUILD
B5: Risk-free rate (US 10Y govt) | C5: 0.0425 | D5: Assumption (~US 10Y Treasury yield, Oct-2026; government rate sources are not reachable from the build environment); update to market
B6: Equity risk premium | C6: 0.05 | D6: Assumption: US implied ERP ~4.5–5.5%
B7: Levered beta | C7: 1.1 | D7: Assumption: financial data / ratings peers (SPGI, MSCI, FDS, ICE) ~0.9–1.2; MIS issuance-driven revenue (~55% of total) adds cyclicality to the recurring MA base
B8: Cost of equity | C8: =C5+C7*C6 -> 0.0975
B9: Pre-tax cost of debt | C9: 0.05 | D9: Aug-2024 $500m 5.00% senior notes due 2034 (latest issue; Q2-26 10-Q Note 13); marginal 10-year cost ~5.0% (assumption)
B10: Tax rate | C10: 0.24 | D10: Model 2027E+ effective tax rate (FY26 ETR guidance 23–25%)
B11: After-tax cost of debt | C11: =C9*(1-C10) -> 0.038
B12: Target D/V | C12: 0.08 | D12: Total debt ~$6.9bn at 30-Jun-2026 vs ~$82bn market cap ($470 × ~174m diluted shares); net debt ~1.3x Adjusted Operating Income
B13: WACC | C13: =C8*(1-C12)+C11*C12 -> 0.09274
B15: Valuation date (live) | C15: =TODAY() -> 2026-10-12 00:00:00 | D15: Periods = (31-Dec-Year − today) / 365.25; cash flows assumed at year-end. 2026E UFCF is shown but excluded from the sum (YE2026E net debt already reflects it)
B16: 2. UNLEVERED FREE CASH FLOW BUILD (USDm)
D17: 2026E | E17: 2027E | F17: 2028E | G17: 2029E | H17: 2030E | I17: 2031E | J17: 2032E | K17: 2033E | L17: 2034E | M17: 2035E | N17: Terminal | P17: CAGR 26–30E | Q17: CAGR 26–35E
B18: Adj. EBITA less restructuring & other excluded cash items | D18: =Model!CA224-Model!CA226 -> 3861.482 | E18: =Model!CB224-Model!CB226 -> 4289.3698 | F18: =Model!CC224-Model!CC226 -> 4704.7105 | G18: =Model!CD224-Model!CD226 -> 5052.748 | H18: =Model!CE224-Model!CE226 -> 5412.7247 | I18: =H18*(1+I$26) -> 5791.6154 | J18: =I18*(1+J$26) -> 6168.0704 | K18: =J18*(1+K$26) -> 6538.1546 | L18: =K18*(1+L$26) -> 6897.7531 | M18: =L18*(1+M$26) -> 7242.6408 | P18: =(H18/D18)^(1/(COLUMNS(D18:H18)-1))-1 -> 0.088091658 | Q18: =(M18/D18)^(1/(COLUMNS(D18:M18)-1))-1 -> 0.072381257
B19: × (1 − tax rate) | D19: =1-$C$10 -> 0.76 | E19: =1-$C$10 -> 0.76 | F19: =1-$C$10 -> 0.76 | G19: =1-$C$10 -> 0.76 | H19: =1-$C$10 -> 0.76 | I19: =1-$C$10 -> 0.76 | J19: =1-$C$10 -> 0.76 | K19: =1-$C$10 -> 0.76 | ... M19: =1-$C$10 -> 0.76
B20: NOPAT | D20: =D18*D19 -> 2934.7263 | E20: =E18*E19 -> 3259.921 | F20: =F18*F19 -> 3575.58 | G20: =G18*G19 -> 3840.0885 | H20: =H18*H19 -> 4113.6708 | I20: =I18*I19 -> 4401.6277 | J20: =J18*J19 -> 4687.7335 | K20: =K18*K19 -> 4968.9975 | ... M20: =M18*M19 -> 5504.407
B21: plus depreciation & amortization excl. acquired intangibles | D21: =Model!CA152 -> 278 | E21: =Model!CB152 -> 317.53592 | F21: =Model!CC152 -> 348.51139 | G21: =Model!CD152 -> 381.03484 | H21: =Model!CE152 -> 403.92901 | I21: =H21*(1+I$26) -> 432.20404 | J21: =I21*(1+J$26) -> 460.2973 | K21: =J21*(1+K$26) -> 487.91514 | L21: =K21*(1+L$26) -> 514.75047 | M21: =L21*(1+M$26) -> 540.48799
B22: − Capex and acquisitions (M&A lever 2027E–30E) | D22: =Model!CA270 -> -450 | E22: =Model!CB270+Model!CB271 -> -658.66299 | F22: =Model!CC270+Model!CC271 -> -670.96134 | G22: =Model!CD270+Model!CD271 -> -701.36164 | H22: =Model!CE270+Model!CE271 -> -731.48554 | I22: =Model!CE270*(1+I$26) -> -568.68952 | J22: =I22*(1+J$26) -> -605.65434 | K22: =J22*(1+K$26) -> -641.9936 | L22: =K22*(1+L$26) -> -677.30325 | M22: =L22*(1+M$26) -> -711.16841
B23: − Δ Working capital (CF statement) | D23: =Model!CA268 -> -7.8635351 | E23: =Model!CB268 -> 65.811783 | F23: =Model!CC268 -> 66.45689 | G23: =Model!CD268 -> 67.480334 | H23: =Model!CE268 -> 66.866806 | I23: =H23*(1+I$26) -> 71.547482 | J23: =I23*(1+J$26) -> 76.198068 | K23: =J23*(1+K$26) -> 80.769953 | L23: =K23*(1+L$26) -> 85.2123 | M23: =L23*(1+M$26) -> 89.472915
B24: Unlevered FCF | D24: =D20+D21+D22+D23 -> 2754.8628 | E24: =E20+E21+E22+E23 -> 2984.6058 | F24: =F20+F21+F22+F23 -> 3319.5869 | G24: =G20+G21+G22+G23 -> 3587.242 | H24: =H20+H21+H22+H23 -> 3852.981 | I24: =I20+I21+I22+I23 -> 4336.6897 | J24: =J20+J21+J22+J23 -> 4618.5745 | K24: =K20+K21+K22+K23 -> 4895.689 | ... M24: =M20+M21+M22+M23 -> 5423.1995 | N24: =M24*(1+$C$27) -> 5640.1275 | P24: =(H24/D24)^(1/(COLUMNS(D24:H24)-1))-1 -> 0.087487378 | Q24: =(M24/D24)^(1/(COLUMNS(D24:M24)-1))-1 -> 0.07816184
B25: Terminal Value (Gordon Growth) | N25: =N24/($C$13-$C$27) -> 106942.12
B26: Fade-period growth (2031E–35E; 7% → 5% linear) | I26: 0.07 | J26: =I26+($M$26-$I$26)/4 -> 0.065 | K26: =J26+($M$26-$I$26)/4 -> 0.06 | L26: =K26+($M$26-$I$26)/4 -> 0.055 | M26: 0.05
B27: Terminal growth rate | C27: 0.04
B29: Discount period (years) | D29: =(DATE(2026,12,31)-$C$15)/365.25 -> 0.21902806 | E29: =(DATE(2027,12,31)-$C$15)/365.25 -> 1.2183436 | F29: =(DATE(2028,12,31)-$C$15)/365.25 -> 2.220397 | G29: =(DATE(2029,12,31)-$C$15)/365.25 -> 3.2197125 | H29: =(DATE(2030,12,31)-$C$15)/365.25 -> 4.2190281 | I29: =(DATE(2031,12,31)-$C$15)/365.25 -> 5.2183436 | J29: =(DATE(2032,12,31)-$C$15)/365.25 -> 6.220397 | K29: =(DATE(2033,12,31)-$C$15)/365.25 -> 7.2197125 | L29: =(DATE(2034,12,31)-$C$15)/365.25 -> 8.2190281 | M29: =(DATE(2035,12,31)-$C$15)/365.25 -> 9.2183436 | N29: =M29 -> 9.2183436
B30: Discount factor | D30: =1/(1+$C$13)^D29 -> 0.98076223 | E30: =1/(1+$C$13)^E29 -> 0.89758018 | F30: =1/(1+$C$13)^F29 -> 0.82125367 | G30: =1/(1+$C$13)^G29 -> 0.75160013 | H30: =1/(1+$C$13)^H29 -> 0.68785416 | I30: =1/(1+$C$13)^I29 -> 0.62951472 | J30: =1/(1+$C$13)^J29 -> 0.57598339 | K30: =1/(1+$C$13)^K29 -> 0.52713212 | ... N30: =1/(1+$C$13)^N29 -> 0.44150795
B31: PV of UFCF | D31: =D24*D30 -> 2701.8654 | E31: =E24*E30 -> 2678.923 | F31: =F24*F30 -> 2726.2229 | G31: =G24*G30 -> 2696.1716 | H31: =H24*H30 -> 2650.289 | I31: =I24*I30 -> 2730.01 | J31: =J24*J30 -> 2660.2222 | K31: =K24*K30 -> 2580.6749 | ... M31: =M24*M30 -> 2394.3857 | N31: =N25*N30 -> 47215.797
D32: NOPAT basis (playbook 5.7): Adjusted EBITA = Adjusted Operating Income (which excludes D&A, restructuring and other items) − depreciation and amortization of PP&E / software, i.e. before acquired-intangible amortization; stock-based compensation is already expensed. Restructuring and the other items Moody's excludes (reserves, duplicate rent, asset abandonment) are deducted as cash costs in row 18. Row 21 adds back depreciation only. Row 22 includes bolt-on M&A in 2027E–30E; the fade period and terminal value assume no new acquisitions. 2026E (column D) is excluded from the sum of PV because net debt is taken at YE2026E. Divestiture gains and contingent consideration (Regulatory Solutions) are excluded. Leases are treated as operating costs (not in net debt).
B33: IMPLIED ROIC — invested capital roll-forward (USDm)
B34: Opening invested capital | D34: =Model!BV397 -> 8751 | E34: =D38 -> 8930.8635 | F34: =E38 -> 9206.1788 | G34: =F38 -> 9462.1719 | H34: =G38 -> 9715.0183 | I34: =H38 -> 9975.7081 | J34: =I38 -> 10040.646 | K34: =J38 -> 10109.805 | L34: =K38 -> 10183.114 | M34: =L38 -> 10260.454
B35: plus Capex and acquisitions | D35: =-D22 -> 450 | E35: =-E22 -> 658.66299 | F35: =-F22 -> 670.96134 | G35: =-G22 -> 701.36164 | H35: =-H22 -> 731.48554 | I35: =-I22 -> 568.68952 | J35: =-J22 -> 605.65434 | K35: =-K22 -> 641.9936 | ... M35: =-M22 -> 711.16841
B36: less DD&A | D36: =-D21 -> -278 | E36: =-E21 -> -317.53592 | F36: =-F21 -> -348.51139 | G36: =-G21 -> -381.03484 | H36: =-H21 -> -403.92901 | I36: =-I21 -> -432.20404 | J36: =-J21 -> -460.2973 | K36: =-K21 -> -487.91514 | ... M36: =-M21 -> -540.48799
B37: plus Δ Working capital investment | D37: =-D23 -> 7.8635351 | E37: =-E23 -> -65.811783 | F37: =-F23 -> -66.45689 | G37: =-G23 -> -67.480334 | H37: =-H23 -> -66.866806 | I37: =-I23 -> -71.547482 | J37: =-J23 -> -76.198068 | K37: =-K23 -> -80.769953 | ... M37: =-M23 -> -89.472915
B38: Closing invested capital | D38: =SUM(D34:D37) -> 8930.8635 | E38: =SUM(E34:E37) -> 9206.1788 | F38: =SUM(F34:F37) -> 9462.1719 | G38: =SUM(G34:G37) -> 9715.0183 | H38: =SUM(H34:H37) -> 9975.7081 | I38: =SUM(I34:I37) -> 10040.646 | J38: =SUM(J34:J37) -> 10109.805 | K38: =SUM(K34:K37) -> 10183.114 | ... M38: =SUM(M34:M37) -> 10341.662
B39: NOPAT (row 20) | D39: =D20 -> 2934.7263 | E39: =E20 -> 3259.921 | F39: =F20 -> 3575.58 | G39: =G20 -> 3840.0885 | H39: =H20 -> 4113.6708 | I39: =I20 -> 4401.6277 | J39: =J20 -> 4687.7335 | K39: =K20 -> 4968.9975 | ... M39: =M20 -> 5504.407
B40: Implied ROIC (NOPAT / avg. invested capital) | D40: =IFERROR(D39/AVERAGE(D34,D38),"") -> 0.33194763 | E40: =IFERROR(E39/AVERAGE(E34,E38),"") -> 0.35947659 | F40: =IFERROR(F39/AVERAGE(F34,F38),"") -> 0.3830633 | G40: =IFERROR(G39/AVERAGE(G34,G38),"") -> 0.400485 | H40: =IFERROR(H39/AVERAGE(H34,H38),"") -> 0.41782824 | I40: =IFERROR(I39/AVERAGE(I34,I38),"") -> 0.43980314 | J40: =IFERROR(J39/AVERAGE(J34,J38),"") -> 0.46527331 | K40: =IFERROR(K39/AVERAGE(K34,K38),"") -> 0.48972724 | ... M40: =IFERROR(M39/AVERAGE(M34,M38),"") -> 0.53435357
B41: Reinvestment rate (net investment / NOPAT) | D41: =IFERROR(SUM(D35:D37)/D39,"") -> 0.06128801 | E41: =IFERROR(SUM(E35:E37)/E39,"") -> 0.084454588 | F41: =IFERROR(SUM(F35:F37)/F39,"") -> 0.071594835 | G41: =IFERROR(SUM(G35:G37)/G39,"") -> 0.065843914 | H41: =IFERROR(SUM(H35:H37)/H39,"") -> 0.063371558 | I41: =IFERROR(SUM(I35:I37)/I39,"") -> 0.014753179 | J41: =IFERROR(SUM(J35:J37)/J39,"") -> 0.014753179 | K41: =IFERROR(SUM(K35:K37)/K39,"") -> 0.014753179 | ... M41: =IFERROR(SUM(M35:M37)/M39,"") -> 0.014753179
B42: Implied terminal RONIC (g / reinvestment rate) | N42: =IFERROR($C$27/M41,"") -> 2.71128
D43: Opening IC = Model 2025A book IC (equity incl. NCI + net debt), rolled forward through 2026E with capex + M&A − depreciation + ΔWC.
B44: 3. VALUATION SUMMARY
B45: Sum of PV (explicit 2027E–30E + fade; 2026E excluded) | C45: =SUM(E31:M31) -> 23608.597
B46: PV of Terminal Value | C46: =N31 -> 47215.797
B47: Enterprise Value | C47: =C45+C46 -> 70824.393
B48: Less: Net debt + NCI (Model 2026E year end) | C48: =Model!CA417+Model!CA332 -> 5134.0492 | D48: MCO: noncontrolling interests (ICRA, ~$0.15bn) deducted alongside net debt (total debt − cash − short-term investments) at YE2026E.
B49: Equity Value | C49: =C47-C48 -> 65690.344
B50: Diluted shares (m, Model 2026E period end) | C50: =Model!CA424 -> 172.39255
B51: Implied share price ($) | C51: =C49/C50 -> 381.05094
B52: Current share price ($) | C52: =Model!CA423 -> 470
B53: Implied upside / (downside) | C53: =C51/C52-1 -> -0.18925332
B54: Required discount to DCF value for target IRR | C54: =1-((1+C13)/(1+H54))^H55 -> 0.14205983 | D54: vs. current | E54: Target IRR | H54: 0.15
B55: Max entry price for target IRR ($) | C55: =C51*(1-C54) -> 326.91891 | D55: =C55/C52-1 -> -0.30442786 | E55: Years for discount to close | H55: 3
B58: 4. SENSITIVITY: IMPLIED PRICE ($) — WACC × Terminal Growth
D60: WACC →
B61: Terminal growth ↓ | D61: =F61-0.01 -> 0.08274 | E61: =F61-0.005 -> 0.08774 | F61: =$C$13 -> 0.09274 | G61: =F61+0.005 -> 0.09774 | H61: =F61+0.01 -> 0.10274
B62: =B64-0.01 -> 0.03 | D62: {=IFERROR((SUMPRODUCT($D$24:$M$24/(1+D$61)^$D$29:$M$29)+($M$24*(1+$B62)/(D$61-$B62))/(1+D$61)^$M$29-$C$48)/$C$50,"")} -> 424.76774 | E62: {=IFERROR((SUMPRODUCT($D$24:$M$24/(1+E$61)^$D$29:$M$29)+($M$24*(1+$B62)/(E$61-$B62))/(1+E$61)^$M$29-$C$48)/$C$50,"")} -> 384.58702 | F62: {=IFERROR((SUMPRODUCT($D$24:$M$24/(1+F$61)^$D$29:$M$29)+($M$24*(1+$B62)/(F$61-$B62))/(1+F$61)^$M$29-$C$48)/$C$50,"")} -> 350.8559 | G62: {=IFERROR((SUMPRODUCT($D$24:$M$24/(1+G$61)^$D$29:$M$29)+($M$24*(1+$B62)/(G$61-$B62))/(1+G$61)^$M$29-$C$48)/$C$50,"")} -> 322.14474 | H62: {=IFERROR((SUMPRODUCT($D$24:$M$24/(1+H$61)^$D$29:$M$29)+($M$24*(1+$B62)/(H$61-$B62))/(1+H$61)^$M$29-$C$48)/$C$50,"")} -> 297.41706
B63: =B64-0.005 -> 0.035 | D63: {=IFERROR((SUMPRODUCT($D$24:$M$24/(1+D$61)^$D$29:$M$29)+($M$24*(1+$B63)/(D$61-$B63))/(1+D$61)^$M$29-$C$48)/$C$50,"")} -> 457.27295 | E63: {=IFERROR((SUMPRODUCT($D$24:$M$24/(1+E$61)^$D$29:$M$29)+($M$24*(1+$B63)/(E$61-$B63))/(1+E$61)^$M$29-$C$48)/$C$50,"")} -> 410.46405 | F63: {=IFERROR((SUMPRODUCT($D$24:$M$24/(1+F$61)^$D$29:$M$29)+($M$24*(1+$B63)/(F$61-$B63))/(1+F$61)^$M$29-$C$48)/$C$50,"")} -> 371.80383 | G63: {=IFERROR((SUMPRODUCT($D$24:$M$24/(1+G$61)^$D$29:$M$29)+($M$24*(1+$B63)/(G$61-$B63))/(1+G$61)^$M$29-$C$48)/$C$50,"")} -> 339.34277 | H63: {=IFERROR((SUMPRODUCT($D$24:$M$24/(1+H$61)^$D$29:$M$29)+($M$24*(1+$B63)/(H$61-$B63))/(1+H$61)^$M$29-$C$48)/$C$50,"")} -> 311.70698
B64: =$C$27 -> 0.04 | D64: {=IFERROR((SUMPRODUCT($D$24:$M$24/(1+D$61)^$D$29:$M$29)+($M$24*(1+$B64)/(D$61-$B64))/(1+D$61)^$M$29-$C$48)/$C$50,"")} -> 497.38349 | E64: {=IFERROR((SUMPRODUCT($D$24:$M$24/(1+E$61)^$D$29:$M$29)+($M$24*(1+$B64)/(E$61-$B64))/(1+E$61)^$M$29-$C$48)/$C$50,"")} -> 441.76148 | F64: {=IFERROR((SUMPRODUCT($D$24:$M$24/(1+F$61)^$D$29:$M$29)+($M$24*(1+$B64)/(F$61-$B64))/(1+F$61)^$M$29-$C$48)/$C$50,"")} -> 396.72369 | G64: {=IFERROR((SUMPRODUCT($D$24:$M$24/(1+G$61)^$D$29:$M$29)+($M$24*(1+$B64)/(G$61-$B64))/(1+G$61)^$M$29-$C$48)/$C$50,"")} -> 359.51933 | H64: {=IFERROR((SUMPRODUCT($D$24:$M$24/(1+H$61)^$D$29:$M$29)+($M$24*(1+$B64)/(H$61-$B64))/(1+H$61)^$M$29-$C$48)/$C$50,"")} -> 328.27455
B65: =B64+0.005 -> 0.045 | D65: {=IFERROR((SUMPRODUCT($D$24:$M$24/(1+D$61)^$D$29:$M$29)+($M$24*(1+$B65)/(D$61-$B65))/(1+D$61)^$M$29-$C$48)/$C$50,"")} -> 548.12216 | E65: {=IFERROR((SUMPRODUCT($D$24:$M$24/(1+E$61)^$D$29:$M$29)+($M$24*(1+$B65)/(E$61-$B65))/(1+E$61)^$M$29-$C$48)/$C$50,"")} -> 480.38167 | F65: {=IFERROR((SUMPRODUCT($D$24:$M$24/(1+F$61)^$D$29:$M$29)+($M$24*(1+$B65)/(F$61-$B65))/(1+F$61)^$M$29-$C$48)/$C$50,"")} -> 426.86346 | G65: {=IFERROR((SUMPRODUCT($D$24:$M$24/(1+G$61)^$D$29:$M$29)+($M$24*(1+$B65)/(G$61-$B65))/(1+G$61)^$M$29-$C$48)/$C$50,"")} -> 383.52155 | H65: {=IFERROR((SUMPRODUCT($D$24:$M$24/(1+H$61)^$D$29:$M$29)+($M$24*(1+$B65)/(H$61-$B65))/(1+H$61)^$M$29-$C$48)/$C$50,"")} -> 347.71145
B66: =B64+0.01 -> 0.05 | D66: {=IFERROR((SUMPRODUCT($D$24:$M$24/(1+D$61)^$D$29:$M$29)+($M$24*(1+$B66)/(D$61-$B66))/(1+D$61)^$M$29-$C$48)/$C$50,"")} -> 614.35829 | E66: {=IFERROR((SUMPRODUCT($D$24:$M$24/(1+E$61)^$D$29:$M$29)+($M$24*(1+$B66)/(E$61-$B66))/(1+E$61)^$M$29-$C$48)/$C$50,"")} -> 529.23507 | F66: {=IFERROR((SUMPRODUCT($D$24:$M$24/(1+F$61)^$D$29:$M$29)+($M$24*(1+$B66)/(F$61-$B66))/(1+F$61)^$M$29-$C$48)/$C$50,"")} -> 464.05511 | G66: {=IFERROR((SUMPRODUCT($D$24:$M$24/(1+G$61)^$D$29:$M$29)+($M$24*(1+$B66)/(G$61-$B66))/(1+G$61)^$M$29-$C$48)/$C$50,"")} -> 412.55147 | H66: {=IFERROR((SUMPRODUCT($D$24:$M$24/(1+H$61)^$D$29:$M$29)+($M$24*(1+$B66)/(H$61-$B66))/(1+H$61)^$M$29-$C$48)/$C$50,"")} -> 370.83377
B69: 5. REVERSE DCF
B70: To solve for the market-implied path: Data ▸ What-If Analysis ▸ Goal Seek — set C51 to the current price (C52) by changing C27 (terminal growth) or the fade-period growth inputs (I26:M26).
B72: 6. MAUBOUSSIN EV / NOPAT — TWO-STAGE FRAMEWORK
B73: EV/NOPAT = 1/r + [g × (1 − r/ROIIC) / (r × (r − g))] × [1 − ((1+g)/(1+r))^N]
B74: Formula source: Mauboussin & Rappaport, "Expectations Investing" (2021); Counterpoint Global, "What Does a Price-Earnings Multiple Mean?" (2020).
B76: Input | C76: Value | D76: Rationale (Moody's characteristics)
B77: r (Cost of capital / WACC) | C77: =$C$13 -> 0.09274 | D77: Linked from Section 1 WACC build
B78: g (NOPAT growth, Stage 1) | C78: 0.08 | D78: Model Adjusted EBITA CAGR 2025–30E: mid- to high-single-digit revenue growth (issuance cycle + recurring MA) with margin expansion → ~8% NOPAT growth
B79: ROIIC (Return on incremental invested capital) | C79: 0.4 | D79: Ratings duopoly with S&P (NRSRO certification, issuer-pays model) and data / analytics with high renewal rates; incremental capital needs are small (capex ~5% of revenue), so returns on incremental capital are very high; large acquisitions (BvD, RMS) earned much lower returns on purchase price
B80: N (Years of value creation / CAP) | C80: 20 | D80: Regulatory and reputational moat in ratings (decades of track record, investor mandates) and embedded MA workflow data; risks: regulation, issuance cyclicality, AI-driven disintermediation of research
B82: Calculation | C82: Value
B83: Steady-state component: 1 / r | C83: =1/C77 -> 10.782834
B84: Value-creation factor: 1 − r / ROIIC | C84: =1-C77/C79 -> 0.76815
B85: Growth multiplier: g × (1 − r/ROIIC) / (r × (r − g)) | C85: =C78*C84/(C77*(C77-C78)) -> 52.011515
B86: Time decay: 1 − ((1+g)/(1+r))^N | C86: =1-((1+C78)/(1+C77))^C80 -> 0.20906955
B87: PVGO component (growth value) | C87: =C85*C86 -> 10.874024
B88: Mauboussin EV / NOPAT (steady-state + PVGO) | C88: =C83+C87 -> 21.656858
B90: VALUATION — Applied to 2028E NOPAT | C90: USDm
B91: 2028E Adj. EBITA less restructuring & other excluded cash items | C91: =Model!CC224-Model!CC226 -> 4704.7105
B92: Tax rate (from WACC build) | C92: =$C$10 -> 0.24
B93: 2028E NOPAT | C93: =C91*(1-C92) -> 3575.58
B94: × Mauboussin EV/NOPAT multiple | C94: =C88 -> 21.656858
B95: Implied Enterprise Value (2028E basis) | C95: =C93*C94 -> 77435.828
B96: Less: YE2027 net debt + NCI (Model) | C96: =Model!CB417+Model!CB332 -> 5976.6321
B97: Implied Equity Value | C97: =C95-C96 -> 71459.195
B98: Diluted shares 2028E (m, Model) | C98: =Model!CC424 -> 162.18346
B99: Implied share price 2028 ($) | C99: =C97/C98 -> 440.60718
B101: Current share price ($) | C101: =C52 -> 470
B102: Implied upside / (downside) | C102: =C99/C101-1 -> -0.06253791
B104: MARKET-IMPLIED EV/NOPAT TODAY | C104: USDm
B105: Current market cap (spot × diluted shares) | C105: =C52*C50 -> 81024.5
B106: Plus: YE2026 net debt + NCI | C106: =C48 -> 5134.0492
B107: Implied Enterprise Value (today) | C107: =C105+C106 -> 86158.549
B108: MCO market-implied EV/NOPAT (on 2028E NOPAT) | C108: =C107/C93 -> 24.096384
B110: Multiple gap (Mauboussin − Market) | C110: =C88-C108 -> -2.4395264
B111: Implied re-rating headroom | C111: =C88/C108-1 -> -0.10124035

Sheet Charts
B2: Moody's Corporation — Operating Performance (2011–2025) and Model Forecast (2026E–2030E)
B3: USDm · Linked to Model. Bars = contribution of each segment to total revenue growth (pp). Adjusted Operating Income = company definition (Adjusted EBITDA; before 2012 the model applies the current definition). Book ROIC is not charted (invested capital is near zero or negative after debt-funded buybacks); FCF conversion is shown instead.
C7: 2011 | D7: 2012 | E7: 2013 | F7: 2014 | G7: 2015 | H7: 2016 | I7: 2017 | J7: 2018 | K7: 2019 | L7: 2020 | M7: 2021 | N7: 2022 | O7: 2023 | P7: 2024 | Q7: 2025 | R7: 2026E | S7: 2027E | T7: 2028E | U7: 2029E | V7: 2030E
B8: MIS contribution to growth (pp) | C8: =IFERROR(Model!H91+0,0) -> 0.080659449 | D8: =IFERROR(Model!I91+0,0) -> 0.13938703 | E8: =IFERROR(Model!N91+0,0) -> 0.063216496 | F8: =IFERROR(Model!S91+0,0) -> 0.069436501 | G8: =IFERROR(Model!X91+0,0) -> 0.020514051 | H8: =IFERROR(Model!AC91+0,0) -> 0.010503659 | I8: =IFERROR(Model!AH91+0,0) -> 0.11181399 | J8: =IFERROR(Model!AM91+0,0) -> -0.014604791 | K8: =IFERROR(Model!AR91+0,0) -> 0.036599365 | L8: =IFERROR(Model!AW91+0,0) -> 0.086353282 | M8: =IFERROR(Model!BB91+0,0) -> 0.096816235 | N8: =IFERROR(Model!BG91+0,0) -> -0.17899646 | O8: =IFERROR(Model!BL91+0,0) -> 0.029444038 | P8: =IFERROR(Model!BQ91+0,0) -> 0.15770791 | Q8: =IFERROR(Model!BV91+0,0) -> 0.045993228 | R8: =IFERROR(Model!CA91+0,0) -> 0.042694999 | S8: =IFERROR(Model!CB91+0,0) -> 0.034663077 | T8: =IFERROR(Model!CC91+0,0) -> 0.029940871 | U8: =IFERROR(Model!CD91+0,0) -> 0.028754984 | V8: =IFERROR(Model!CE91+0,0) -> 0.02565844
B9: MA contribution to growth (pp) | C9: =IFERROR(Model!H92+0,0) -> 0.041732283 | D9: =IFERROR(Model!I92+0,0) -> 0.057745429 | E9: =IFERROR(Model!N92+0,0) -> 0.025491704 | F9: =IFERROR(Model!S92+0,0) -> 0.052279226 | G9: =IFERROR(Model!X92+0,0) -> 0.024532885 | H9: =IFERROR(Model!AC92+0,0) -> 0.023848472 | I9: =IFERROR(Model!AH92+0,0) -> 0.054630709 | J9: =IFERROR(Model!AM92+0,0) -> 0.071358912 | K9: =IFERROR(Model!AR92+0,0) -> 0.050352263 | L9: =IFERROR(Model!AW92+0,0) -> 0.025885276 | M9: =IFERROR(Model!BB92+0,0) -> 0.060882517 | N9: =IFERROR(Model!BG92+0,0) -> 0.0583789 | O9: =IFERROR(Model!BL92+0,0) -> 0.052487198 | P9: =IFERROR(Model!BQ92+0,0) -> 0.040398918 | Q9: =IFERROR(Model!BV92+0,0) -> 0.042889391 | R9: =IFERROR(Model!CA92+0,0) -> 0.023315626 | S9: =IFERROR(Model!CB92+0,0) -> 0.037409156 | T9: =IFERROR(Model!CC92+0,0) -> 0.037945138 | U9: =IFERROR(Model!CD92+0,0) -> 0.035794472 | V9: =IFERROR(Model!CE92+0,0) -> 0.034425736
C11: =C7 -> 2011 | D11: =D7 -> 2012 | E11: =E7 -> 2013 | F11: =F7 -> 2014 | G11: =G7 -> 2015 | H11: =H7 -> 2016 | I11: =I7 -> 2017 | J11: =J7 -> 2018 | ... V11: =V7 -> 2030E
B12: Adjusted Operating Income | C12: =Model!H219 -> 967.6 | D12: =Model!I219 -> 1183.1 | E12: =Model!N219 -> 1328 | F12: =Model!S219 -> 1534.7 | G12: =Model!X219 -> 1586.9 | H12: =Model!AC219 -> 1641.2 | I12: =Model!AH219 -> 1989.9 | J12: =Model!AM219 -> 2117.1 | K12: =Model!AR219 -> 2291 | L12: =Model!AW219 -> 2667 | M12: =Model!BB219 -> 3101 | N12: =Model!BG219 -> 2328 | O12: =Model!BL219 -> 2597 | P12: =Model!BQ219 -> 3408 | Q12: =Model!BV219 -> 3942 | R12: =Model!CA219 -> 4319.482 | S12: =Model!CB219 -> 4686.9057 | T12: =Model!CC219 -> 5053.2219 | U12: =Model!CD219 -> 5433.7829 | V12: =Model!CE219 -> 5816.6537
B13: Operating income (GAAP) | C13: =Model!H170 -> 888.4 | D13: =Model!I170 -> 1077.4 | E13: =Model!N170 -> 1234.6 | F13: =Model!S170 -> 1439.1 | G13: =Model!X170 -> 1473.4 | H13: =Model!AC170 -> 638.7 | I13: =Model!AH170 -> 1809.1 | J13: =Model!AM170 -> 1868.2 | K13: =Model!AR170 -> 1998 | L13: =Model!AW170 -> 2388 | M13: =Model!BB170 -> 2844 | N13: =Model!BG170 -> 1883 | O13: =Model!BL170 -> 2137 | P13: =Model!BQ170 -> 2875 | Q13: =Model!BV170 -> 3351 | R13: =Model!CA170 -> 3654.482 | S13: =Model!CB170 -> 4091.7031 | T13: =Model!CC170 -> 4514.7105 | U13: =Model!CD170 -> 4889.4147 | V13: =Model!CE170 -> 5268.058
B14: Adj. Operating Margin % | C14: =Model!H255 -> 0.42425571 | D14: =Model!I255 -> 0.43332235 | E14: =Model!N255 -> 0.44676198 | F14: =Model!S255 -> 0.46027652 | G14: =Model!X255 -> 0.45541685 | H14: =Model!AC255 -> 0.45535764 | I14: =Model!AH255 -> 0.47332366 | J14: =Model!AM255 -> 0.47653454 | K14: =Model!AR255 -> 0.47442535 | L14: =Model!AW255 -> 0.49655558 | M14: =Model!BB255 -> 0.49871341 | N14: =Model!BG255 -> 0.42574982 | O14: =Model!BL255 -> 0.43897904 | P14: =Model!BQ255 -> 0.48081264 | Q14: =Model!BV255 -> 0.51075408 | R14: =Model!CA255 -> 0.52500732 | S14: =Model!CB255 -> 0.53136857 | T14: =Model!CC255 -> 0.53647948 | U14: =Model!CD255 -> 0.54190254 | V14: =Model!CE255 -> 0.54720715
B15: GAAP Op. Margin % | C15: =Model!H256 -> 0.38952953 | D15: =Model!I256 -> 0.39460865 | E15: =Model!N256 -> 0.41534062 | F15: =Model!S256 -> 0.43160483 | G15: =Model!X256 -> 0.42284402 | H15: =Model!AC256 -> 0.17720992 | I15: =Model!AH256 -> 0.43031802 | J15: =Model!AM256 -> 0.42051005 | K15: =Model!AR256 -> 0.41375026 | L15: =Model!AW256 -> 0.44460994 | M15: =Model!BB256 -> 0.45738179 | N15: =Model!BG256 -> 0.34436723 | O15: =Model!BL256 -> 0.3612238 | P15: =Model!BQ256 -> 0.40561512 | Q15: =Model!BV256 -> 0.43417984 | R15: =Model!CA256 -> 0.44418053 | S15: =Model!CB256 -> 0.46388867 | T15: =Model!CC256 -> 0.47930797 | U15: =Model!CD256 -> 0.48761357 | V15: =Model!CE256 -> 0.4955975
C17: =C7 -> 2011 | D17: =D7 -> 2012 | E17: =E7 -> 2013 | F17: =F7 -> 2014 | G17: =G7 -> 2015 | H17: =H7 -> 2016 | I17: =I7 -> 2017 | J17: =J7 -> 2018 | ... V17: =V7 -> 2030E
B18: FCF conversion (FCF / adj. net income) | C18: =IFERROR(Model!H293+0,0) -> 1.303331 | D18: =IFERROR(Model!I293+0,0) -> 1.1484295 | E18: =IFERROR(Model!N293+0,0) -> 1.084245 | F18: =IFERROR(Model!S293+0,0) -> 1.0443783 | G18: =IFERROR(Model!X293+0,0) -> 1.1378308 | H18: =IFERROR(Model!AC293+0,0) -> 1.1810546 | I18: =IFERROR(Model!AH293+0,0) -> 0.55749809 | J18: =IFERROR(Model!AM293+0,0) -> 0.95439354 | K18: =IFERROR(Model!AR293+0,0) -> 1.011335 | L18: =IFERROR(Model!AW293+0,0) -> 1.0635086 | M18: =IFERROR(Model!BB293+0,0) -> 0.80814205 | N18: =IFERROR(Model!BG293+0,0) -> 0.7528445 | O18: =IFERROR(Model!BL293+0,0) -> 1.0318332 | P18: =IFERROR(Model!BQ293+0,0) -> 1.1061869 | Q18: =IFERROR(Model!BV293+0,0) -> 0.95831783 | R18: =IFERROR(Model!CA293+0,0) -> 1.0040166 | S18: =IFERROR(Model!CB293+0,0) -> 1.0509988 | T18: =IFERROR(Model!CC293+0,0) -> 1.0762092 | U18: =IFERROR(Model!CD293+0,0) -> 1.0751787 | V18: =IFERROR(Model!CE293+0,0) -> 1.0718518
B19: Adj. EBITA margin % | C19: =IFERROR(Model!H225+0,0) -> 0.398518 | D19: =IFERROR(Model!I225+0,0) -> 0.41010145 | E19: =IFERROR(Model!N225+0,0) -> 0.4247603 | F19: =IFERROR(Model!S225+0,0) -> 0.44012236 | G19: =IFERROR(Model!X225+0,0) -> 0.43199885 | H19: =IFERROR(Model!AC225+0,0) -> 0.42969314 | I19: =IFERROR(Model!AH225+0,0) -> 0.45027473 | J19: =IFERROR(Model!AM225+0,0) -> 0.45623157 | K19: =IFERROR(Model!AR225+0,0) -> 0.45433837 | L19: =IFERROR(Model!AW225+0,0) -> 0.47868181 | M19: =IFERROR(Model!BB225+0,0) -> 0.48279189 | N19: =IFERROR(Model!BG225+0,0) -> 0.40179225 | O19: =IFERROR(Model!BL225+0,0) -> 0.40939824 | P19: =IFERROR(Model!BQ225+0,0) -> 0.44794018 | Q19: =IFERROR(Model!BV225+0,0) -> 0.47641876 | R19: =IFERROR(Model!CA225+0,0) -> 0.49121808 | S19: =IFERROR(Model!CB225+0,0) -> 0.49536857 | T19: =IFERROR(Model!CC225+0,0) -> 0.49947948 | U19: =IFERROR(Model!CD225+0,0) -> 0.50390254 | V19: =IFERROR(Model!CE225+0,0) -> 0.50920715
B20: Adj. Operating Margin % | C20: =IFERROR(Model!H255+0,0) -> 0.42425571 | D20: =IFERROR(Model!I255+0,0) -> 0.43332235 | E20: =IFERROR(Model!N255+0,0) -> 0.44676198 | F20: =IFERROR(Model!S255+0,0) -> 0.46027652 | G20: =IFERROR(Model!X255+0,0) -> 0.45541685 | H20: =IFERROR(Model!AC255+0,0) -> 0.45535764 | I20: =IFERROR(Model!AH255+0,0) -> 0.47332366 | J20: =IFERROR(Model!AM255+0,0) -> 0.47653454 | K20: =IFERROR(Model!AR255+0,0) -> 0.47442535 | L20: =IFERROR(Model!AW255+0,0) -> 0.49655558 | M20: =IFERROR(Model!BB255+0,0) -> 0.49871341 | N20: =IFERROR(Model!BG255+0,0) -> 0.42574982 | O20: =IFERROR(Model!BL255+0,0) -> 0.43897904 | P20: =IFERROR(Model!BQ255+0,0) -> 0.48081264 | Q20: =IFERROR(Model!BV255+0,0) -> 0.51075408 | R20: =IFERROR(Model!CA255+0,0) -> 0.52500732 | S20: =IFERROR(Model!CB255+0,0) -> 0.53136857 | T20: =IFERROR(Model!CC255+0,0) -> 0.53647948 | U20: =IFERROR(Model!CD255+0,0) -> 0.54190254 | V20: =IFERROR(Model!CE255+0,0) -> 0.54720715
B21: FCF margin % | C21: =IFERROR(Model!H292+0,0) -> 0.32253256 | D21: =IFERROR(Model!I292+0,0) -> 0.284987 | E21: =IFERROR(Model!N292+0,0) -> 0.29756098 | F21: =IFERROR(Model!S292+0,0) -> 0.2831179 | G21: =IFERROR(Model!X292+0,0) -> 0.30552447 | H21: =IFERROR(Model!AC292+0,0) -> 0.30822374 | I21: =IFERROR(Model!AH292+0,0) -> 0.15625223 | J21: =IFERROR(Model!AM292+0,0) -> 0.3085286 | K21: =IFERROR(Model!AR292+0,0) -> 0.33257403 | L21: =IFERROR(Model!AW292+0,0) -> 0.38037609 | M21: =IFERROR(Model!BB292+0,0) -> 0.30009649 | N21: =IFERROR(Model!BG292+0,0) -> 0.21781273 | O21: =IFERROR(Model!BL292+0,0) -> 0.31778229 | P21: =IFERROR(Model!BQ292+0,0) -> 0.35567156 | Q21: =IFERROR(Model!BV292+0,0) -> 0.33363566 | R21: =IFERROR(Model!CA292+0,0) -> 0.35657897 | S21: =IFERROR(Model!CB292+0,0) -> 0.37368295 | T21: =IFERROR(Model!CC292+0,0) -> 0.38408346 | U21: =IFERROR(Model!CD292+0,0) -> 0.38676528 | V21: =IFERROR(Model!CE292+0,0) -> 0.38862678
