Workbook

Sheet Model
CD1: SCENARIO SWITCH ▼ (Bull / Base / Bear) — drives all scenario-linked forecast drivers
B2: Meta Platforms, Inc. (NASDAQ: META) — 3-Statement Financial Model | CD2: Base
B3: US GAAP as reported · USD millions (per-share data in USD; shares and people in millions) · Fiscal years ended 31 December · Source: SEC EDGAR only (CIK 1326801): Forms 10-K / 10-Q, Form 8-K earnings releases (Ex. 99.1), IPO prospectus (424B4, 18-May-2012), notes-issue 8-Ks; XBRL company facts. Investor-relations releases are the same documents as filed on EDGAR; all guidance is from the 8-K releases (no unverified guidance used)
B4: Basis notes: as originally reported (FY2011 cost reclassification, FY2016 ASU 2016-09 and 2018 restricted-cash re-presentations not recast). Facebook, Inc. until 28-Oct-2021 (ticker FB until 9-Jun-2022); IPO 18-May-2012 (FY2009–11 from the prospectus; no FY2009 balance sheet). Segments FoA / RL from Q4-21 (2019–21 recast). Acquisitions: Instagram 2012, WhatsApp and Oculus 2014. Q3/26E calibrated to revenue guidance, 2H/26E to FY26 expense guidance (29-Jul-2026).
CF5: Forecast | CG5: Historical | CH5: Historical | CI5: Historical
B6: (USDm) | C6: 2009 | D6: 2010 | E6: 2011 | F6: 2012 | G6: Q1/13 | H6: Q2/13 | I6: Q3/13 | J6: Q4/13 | K6: 2013 | L6: Q1/14 | M6: Q2/14 | N6: Q3/14 | O6: Q4/14 | P6: 2014 | Q6: Q1/15 | R6: Q2/15 | S6: Q3/15 | T6: Q4/15 | U6: 2015 | V6: Q1/16 | W6: Q2/16 | X6: Q3/16 | Y6: Q4/16 | Z6: 2016 | AA6: Q1/17 | AB6: Q2/17 | AC6: Q3/17 | AD6: Q4/17 | AE6: 2017 | AF6: Q1/18 | AG6: Q2/18 | AH6: Q3/18 | AI6: Q4/18 | AJ6: 2018 | AK6: Q1/19 | AL6: Q2/19 | AM6: Q3/19 | AN6: Q4/19 | AO6: 2019 | AP6: Q1/20 | AQ6: Q2/20 | AR6: Q3/20 | AS6: Q4/20 | AT6: 2020 | AU6: Q1/21 | AV6: Q2/21 | AW6: Q3/21 | AX6: Q4/21 | AY6: 2021 | AZ6: Q1/22 | BA6: Q2/22 | BB6: Q3/22 | BC6: Q4/22 | BD6: 2022 | BE6: Q1/23 | BF6: Q2/23 | BG6: Q3/23 | BH6: Q4/23 | BI6: 2023 | BJ6: Q1/24 | BK6: Q2/24 | BL6: Q3/24 | BM6: Q4/24 | BN6: 2024 | BO6: Q1/25 | BP6: Q2/25 | BQ6: Q3/25 | BR6: Q4/25 | BS6: 2025 | BT6: Q1/26 | BU6: Q2/26 | BV6: Q3/26E | BW6: Q4/26E | BX6: 2026E | BY6: 2027E | BZ6: 2028E | CA6: 2029E | CB6: 2030E | CC6: 2031E | CD6: Modelling Notes | CF6: 5Y CAGR | CG6: 5Y CAGR | CH6: 10Y CAGR | CI6: 16Y CAGR
CF7: 26-'31 | CG7: 20-'25 | CH7: 15-'25 | CI7: 09-'25
B8: OPERATING BUILD — FAMILY OF APPS (ADVERTISING = AD IMPRESSIONS × PRICE PER AD; OTHER REVENUE) · REALITY LABS | CD8: OPERATING BUILD — modelling logic (advertising = prior-year period × (1 + impressions growth) × (1 + price-per-ad growth); other revenue by line; segment profit; costs built separately below)
CL9: SCENARIO INPUT TABLE — driver assumptions per Bull / Base / Bear | CM9: Bull | CN9: Base | CO9: Bear | CP9: Bull / Bear = Base + Δ (Δ inputs on each block header). Outlook block = high / mid / low end of the 2026 guidance ranges.
B10: Family of Apps — advertising (Facebook, Instagram, Messenger, WhatsApp, Threads) | CD10: ADVERTISING — modelling logic
B11: Advertising revenue | C11: 764 | D11: 1868 | E11: 3154 | F11: 4279 | G11: 1245 | H11: 1599 | I11: 1798 | J11: 2344 | K11: 6986 | L11: 2265 | M11: 2676 | N11: 2957 | O11: 3594 | P11: 11492 | Q11: 3317 | R11: 3827 | S11: 4299 | T11: 5637 | U11: 17079 | V11: 5201 | W11: 6239 | X11: 6816 | Y11: 8629 | Z11: 26885 | AA11: 7857 | AB11: 9164 | AC11: 10142 | AD11: 12779 | AE11: 39942 | AF11: 11795 | AG11: 13038 | AH11: 13539 | AI11: 16640 | AJ11: 55013 | AK11: 14912 | AL11: 16624 | AM11: 17383 | AN11: 20736 | AO11: 69655 | AP11: 17440 | AQ11: 18321 | AR11: 21221 | AS11: 27187 | AT11: 84169 | AU11: 25439 | AV11: 28580 | AW11: 28276 | AX11: 32639 | AY11: 114934 | AZ11: 26998 | BA11: 28152 | BB11: 27237 | BC11: 31254 | BD11: 113642 | BE11: 28101 | BF11: 31498 | BG11: 33643 | BH11: 38706 | BI11: 131948 | BJ11: 35635 | BK11: 38329 | BL11: 39885 | BM11: 46783 | BN11: 160633 | BO11: 41392 | BP11: 46563 | BQ11: 50082 | BR11: 58137 | BS11: 196175 | BT11: 55024 | BU11: 59363 | BV11: =BQ11*(1+BV12) -> 60804.947 | BW11: =BR11*(1+BW12) -> 70584.585 | BX11: =SUM(BT11:BW11) -> 245776.53 | BY11: =BX11*(1+BY12) -> 291982.52 | BZ11: =BY11*(1+BZ12) -> 337356.6 | CA11: =BZ11*(1+CA12) -> 382562.39 | CB11: =CA11*(1+CB12) -> 425715.43 | CC11: =CB11*(1+CC12) -> 469308.69 | CD11: History: release reconciliation ("GAAP advertising revenue"; 2009-11 prospectus; segment table from Q4-2021). Forecast: prior-year period × (1 + ad impressions growth) × (1 + price-per-ad growth). | CF11: =IFERROR((CC11/BX11)^(1/5)-1,"n/m") -> 0.13810842 | CG11: =IFERROR((BS11/AT11)^(1/5)-1,"n/m") -> 0.18439973 | CH11: =IFERROR((BS11/U11)^(1/10)-1,"n/m") -> 0.27649207 | CI11: =IFERROR((BS11/C11)^(1/16)-1,"n/m") -> 0.41448027 | CL11: Outlook — Q2-26 release (8-K Ex. 99.1, 29-Jul-2026) | CM11: High | CN11: Mid | CO11: Low | CP11: Q3/26 revenue $61–64bn (FX ~1% headwind); FY26 total expenses $165–169bn (low end raised for the $2.4bn Q2 legal charges); FY26 operating income above 2025; FY26 capital expenditures incl. principal payments on finance leases $130–145bn; tax rate 15–17% for the remaining quarters. All from the 8-K (SEC EDGAR).
B12: y/y % | D12: =IF(AND(ISNUMBER(D11),ISNUMBER(C11)),IFERROR(D11/C11-1,""),"") -> 1.4450262 | E12: =IF(AND(ISNUMBER(E11),ISNUMBER(D11)),IFERROR(E11/D11-1,""),"") -> 0.68843683 | F12: =IF(AND(ISNUMBER(F11),ISNUMBER(E11)),IFERROR(F11/E11-1,""),"") -> 0.35668992 | K12: =IF(AND(ISNUMBER(K11),ISNUMBER(F11)),IFERROR(K11/F11-1,""),"") -> 0.63262444 | L12: =IF(AND(ISNUMBER(L11),ISNUMBER(G11)),IFERROR(L11/G11-1,""),"") -> 0.81927711 | M12: =IF(AND(ISNUMBER(M11),ISNUMBER(H11)),IFERROR(M11/H11-1,""),"") -> 0.67354597 | N12: =IF(AND(ISNUMBER(N11),ISNUMBER(I11)),IFERROR(N11/I11-1,""),"") -> 0.64460512 | O12: =IF(AND(ISNUMBER(O11),ISNUMBER(J11)),IFERROR(O11/J11-1,""),"") -> 0.53327645 | P12: =IF(AND(ISNUMBER(P11),ISNUMBER(K11)),IFERROR(P11/K11-1,""),"") -> 0.64500429 | Q12: =IF(AND(ISNUMBER(Q11),ISNUMBER(L11)),IFERROR(Q11/L11-1,""),"") -> 0.46445916 | R12: =IF(AND(ISNUMBER(R11),ISNUMBER(M11)),IFERROR(R11/M11-1,""),"") -> 0.43011958 | ... BU12: =IF(AND(ISNUMBER(BU11),ISNUMBER(BP11)),IFERROR(BU11/BP11-1,""),"") -> 0.27489638 | BV12: =(1+BV13)*(1+BV14)-1 -> 0.21410781 | BW12: =(1+BW13)*(1+BW14)-1 -> 0.21410781 | BX12: =IF(AND(ISNUMBER(BX11),ISNUMBER(BS11)),IFERROR(BX11/BS11-1,""),"") -> 0.25284329 | BY12: =(1+BY13)*(1+BY14)-1 -> 0.188 | BZ12: =(1+BZ13)*(1+BZ14)-1 -> 0.1554 | CA12: =(1+CA13)*(1+CA14)-1 -> 0.134 | CB12: =(1+CB13)*(1+CB14)-1 -> 0.1128 | CC12: =(1+CC13)*(1+CC14)-1 -> 0.1024 | CF12: =IFERROR(AVERAGE(BY12,BZ12,CA12,CB12,CC12),"n/m") -> 0.13852 | CG12: =IFERROR(AVERAGE(AY12,BD12,BI12,BN12,BS12),"n/m") -> 0.19080331 | CH12: =IFERROR(AVERAGE(Z12,AE12,AJ12,AO12,AT12,AY12,BD12,BI12,BN12,BS12),"n/m") -> 0.28656803 | CI12: =IFERROR(AVERAGE(C12,D12,E12,F12,K12,P12,U12,Z12,AE12,AJ12,AO12,AT12,AY12,BD12,BI12,BN12,BS12),"n/m") -> 0.44497664 | CL12: Q3/26 total revenue ($m) | CM12: 64000 | CN12: 62500 | CO12: 61000 | CP12: Guided $61–64bn. Drives the Q3/26E price-per-ad calibration.
B13: Ad impressions delivered y/y % (company-reported, rounded) | L13: -0.17 | M13: -0.25 | N13: -0.56 | P13: -0.4 | Q13: -0.62 | R13: -0.55 | S13: -0.1 | U13: -0.38 | V13: 0.5 | W13: 0.49 | X13: 0.5 | Z13: 0.5 | AA13: 0.32 | AB13: 0.19 | AC13: 0.1 | AE13: 0.15 | AF13: 0.08 | AG13: 0.21 | AH13: 0.25 | AJ13: 0.22 | AK13: 0.32 | AL13: 0.33 | AM13: 0.37 | AO13: 0.33 | AP13: 0.39 | AQ13: 0.4 | AR13: 0.35 | AT13: 0.34 | AU13: 0.12 | AV13: 0.06 | AW13: 0.09 | AX13: 0.13 | AY13: 0.1 | AZ13: 0.15 | BA13: 0.15 | BB13: 0.17 | BC13: 0.23 | BD13: 0.18 | BE13: 0.26 | BF13: 0.34 | BG13: 0.31 | BH13: 0.21 | BI13: 0.28 | BJ13: 0.2 | BK13: 0.1 | BL13: 0.07 | BM13: 0.06 | BN13: 0.11 | BO13: 0.05 | BP13: 0.11 | BQ13: 0.14 | BR13: 0.18 | BS13: 0.12 | BT13: 0.19 | BU13: 0.14 | BV13: =BV15 -> 0.14 | BW13: =BW15 -> 0.14 | BY13: =CHOOSE(MATCH($CD$2,{"Bull","Base","Bear"},0),$CM$28,$CN$28,$CO$28) -> 0.1 | BZ13: =CHOOSE(MATCH($CD$2,{"Bull","Base","Bear"},0),$CM$29,$CN$29,$CO$29) -> 0.09 | CA13: =CHOOSE(MATCH($CD$2,{"Bull","Base","Bear"},0),$CM$30,$CN$30,$CO$30) -> 0.08 | CB13: =CHOOSE(MATCH($CD$2,{"Bull","Base","Bear"},0),$CM$31,$CN$31,$CO$31) -> 0.07 | CC13: =CHOOSE(MATCH($CD$2,{"Bull","Base","Bear"},0),$CM$32,$CN$32,$CO$32) -> 0.06 | CD13: Releases from Q4-2021; before that the 10-Q / 10-K MD&A ("number of ads delivered", 2014-21; Q4 not published, year from the 10-K). Q3/Q4-26E: Q2/26 y/y held. 2027E+: scenario lever. | CF13: =IFERROR(AVERAGE(BY13,BZ13,CA13,CB13,CC13),"n/m") -> 0.08 | CG13: =IFERROR(AVERAGE(AY13,BD13,BI13,BN13,BS13),"n/m") -> 0.158 | CH13: =IFERROR(AVERAGE(Z13,AE13,AJ13,AO13,AT13,AY13,BD13,BI13,BN13,BS13),"n/m") -> 0.233 | CI13: =IFERROR(AVERAGE(C13,D13,E13,F13,K13,P13,U13,Z13,AE13,AJ13,AO13,AT13,AY13,BD13,BI13,BN13,BS13),"n/m") -> 0.12916667 | CL13: FY26 total expenses ($m) — Bull = low end, Bear = high end | CM13: 165000 | CN13: 167000 | CO13: 169000 | CP13: Guided $165–169bn. Drives the 2H/26E other-operating-cost calibration (lower expenses in the Bull case).
B14: Average price per ad y/y % (company-reported, rounded) | L14: 1.18 | M14: 1.23 | N14: 2.74 | P14: 1.73 | Q14: 2.85 | R14: 2.2 | S14: 0.61 | U14: 1.4 | V14: 0.05 | W14: 0.09 | X14: 0.06 | Z14: 0.05 | AA14: 0.14 | AB14: 0.24 | AC14: 0.35 | AE14: 0.29 | AF14: 0.39 | AG14: 0.17 | AH14: 0.07 | AJ14: 0.13 | AK14: -0.04 | AL14: -0.04 | AM14: -0.06 | AO14: -0.05 | AP14: -0.16 | AQ14: -0.21 | AR14: -0.09 | AT14: -0.1 | AU14: 0.3 | AV14: 0.47 | AW14: 0.22 | AX14: 0.06 | AY14: 0.24 | AZ14: -0.08 | BA14: -0.14 | BB14: -0.18 | BC14: -0.22 | BD14: -0.16 | BE14: -0.17 | BF14: -0.16 | BG14: -0.06 | BH14: 0.02 | BI14: -0.09 | BJ14: 0.06 | BK14: 0.1 | BL14: 0.11 | BM14: 0.14 | BN14: 0.1 | BO14: 0.1 | BP14: 0.09 | BQ14: 0.1 | BR14: 0.06 | BS14: 0.09 | BT14: 0.12 | BU14: 0.12 | BV14: =BV16+$BV$77 -> 0.065006847 | BW14: =BW16+$BV$77 -> 0.065006847 | BY14: =CHOOSE(MATCH($CD$2,{"Bull","Base","Bear"},0),$CM$34,$CN$34,$CO$34) -> 0.08 | BZ14: =CHOOSE(MATCH($CD$2,{"Bull","Base","Bear"},0),$CM$35,$CN$35,$CO$35) -> 0.06 | CA14: =CHOOSE(MATCH($CD$2,{"Bull","Base","Bear"},0),$CM$36,$CN$36,$CO$36) -> 0.05 | CB14: =CHOOSE(MATCH($CD$2,{"Bull","Base","Bear"},0),$CM$37,$CN$37,$CO$37) -> 0.04 | CC14: =CHOOSE(MATCH($CD$2,{"Bull","Base","Bear"},0),$CM$38,$CN$38,$CO$38) -> 0.04 | CD14: Not disclosed 2019-Q3 2021 in some quarters. Q3/Q4-26E: Q2/26 y/y + revenue-guidance calibration Δ (solved in Q3, carried into Q4). 2027E+: scenario lever. | CF14: =IFERROR(AVERAGE(BY14,BZ14,CA14,CB14,CC14),"n/m") -> 0.054 | CG14: =IFERROR(AVERAGE(AY14,BD14,BI14,BN14,BS14),"n/m") -> 0.036 | CH14: =IFERROR(AVERAGE(Z14,AE14,AJ14,AO14,AT14,AY14,BD14,BI14,BN14,BS14),"n/m") -> 0.05 | CI14: =IFERROR(AVERAGE(C14,D14,E14,F14,K14,P14,U14,Z14,AE14,AJ14,AO14,AT14,AY14,BD14,BI14,BN14,BS14),"n/m") -> 0.3025 | CL14: 2H/26E share repurchases ($m) | CM14: 5000 | CN14: 0 | CO14: 0 | CP14: No repurchases in 1H/26 (Q4/25 none either) while capex is funded; $50bn+ authorization remaining (10-Q). Base / Bear nil, Bull $5bn (assumption).
B15: Q3/Q4-26E ad impressions growth (Q2/26 y/y, held) | BV15: =$BU$13 -> 0.14 | BW15: =$BU$13 -> 0.14
B16: Q3/Q4-26E price-per-ad growth before calibration (Q2/26 y/y, held) | BV16: =$BU$14 -> 0.12 | BW16: =$BU$14 -> 0.12 | CL16: Q3/26E, Q4/26E and FY26 point estimates (all cases)
B17: Memo: implied advertising growth = (1 + impressions) × (1 + price) − 1 | C17: =IF(AND(ISNUMBER(C13),ISNUMBER(C14)),(1+C13)*(1+C14)-1,"") | D17: =IF(AND(ISNUMBER(D13),ISNUMBER(D14)),(1+D13)*(1+D14)-1,"") | E17: =IF(AND(ISNUMBER(E13),ISNUMBER(E14)),(1+E13)*(1+E14)-1,"") | F17: =IF(AND(ISNUMBER(F13),ISNUMBER(F14)),(1+F13)*(1+F14)-1,"") | G17: =IF(AND(ISNUMBER(G13),ISNUMBER(G14)),(1+G13)*(1+G14)-1,"") | H17: =IF(AND(ISNUMBER(H13),ISNUMBER(H14)),(1+H13)*(1+H14)-1,"") | I17: =IF(AND(ISNUMBER(I13),ISNUMBER(I14)),(1+I13)*(1+I14)-1,"") | J17: =IF(AND(ISNUMBER(J13),ISNUMBER(J14)),(1+J13)*(1+J14)-1,"") | ... BU17: =IF(AND(ISNUMBER(BU13),ISNUMBER(BU14)),(1+BU13)*(1+BU14)-1,"") -> 0.2768 | CL17: Q3/Q4-26E D&A growth q/q | CN17: 0.07 | CP17: Q4/25 → Q1/26 +10.9%, Q1 → Q2/26 +6.0% (servers and data centers placed in service). Assumption.
B18: Memo: reported advertising growth − implied (rounding of the published whole-% figures; not a check) | D18: =IF(AND(ISNUMBER(D17),ISNUMBER(D12)),D12-D17,"") | E18: =IF(AND(ISNUMBER(E17),ISNUMBER(E12)),E12-E17,"") | F18: =IF(AND(ISNUMBER(F17),ISNUMBER(F12)),F12-F17,"") | K18: =IF(AND(ISNUMBER(K17),ISNUMBER(K12)),K12-K17,"") | L18: =IF(AND(ISNUMBER(L17),ISNUMBER(L12)),L12-L17,"") -> 0.0098771084 | M18: =IF(AND(ISNUMBER(M17),ISNUMBER(M12)),M12-M17,"") -> 0.0010459662 | N18: =IF(AND(ISNUMBER(N17),ISNUMBER(N12)),N12-N17,"") -> -0.0009948832 | O18: =IF(AND(ISNUMBER(O17),ISNUMBER(O12)),O12-O17,"") | P18: =IF(AND(ISNUMBER(P17),ISNUMBER(P12)),P12-P17,"") -> 0.0070042943 | Q18: =IF(AND(ISNUMBER(Q17),ISNUMBER(Q12)),Q12-Q17,"") -> 0.0014591611 | R18: =IF(AND(ISNUMBER(R17),ISNUMBER(R12)),R12-R17,"") -> -0.0098804185 | ... BU18: =IF(AND(ISNUMBER(BU17),ISNUMBER(BU12)),BU12-BU17,"") -> -0.001903623 | CL18: Q3/Q4-26E share-based compensation ($m) | CN18: 7658 | CP18: Q2/26 level held ($7,658m; Q1/26 $6,032m).
B19: Memo: advertising revenue excluding foreign-exchange effect (company non-GAAP) | F19: 4402 | H19: 1612 | I19: 1801 | J19: 2346 | K19: 7008 | M19: 2646 | N19: 2936 | O19: 3697 | P19: 11553 | Q19: 3505 | R19: 4159 | S19: 4641 | T19: 5959 | U19: 18264 | V19: 5403 | W19: 6240 | X19: 6847 | Y19: 8664 | Z19: 27154 | AA19: 7879 | AB19: 9305 | AC19: 10014 | AD19: 12452 | AE19: 39650 | AF19: 11260 | AG19: 12667 | AH19: 13698 | AI19: 16987 | AJ19: 54612 | AK19: 15415 | AL19: 17196 | AM19: 17678 | AN19: 21030 | AO19: 71319 | AP19: 17714 | AQ19: 18616 | AR19: 21112 | AS19: 26855 | AT19: 84298 | AU19: 24744 | AV19: 27605 | AW19: 28020 | AX19: 32945 | AY19: 113314 | AZ19: 27886 | BA19: 29407 | BB19: 29013 | BC19: 33231 | BD19: 119538 | BE19: 28907 | BF19: 31767 | BG19: 32998 | BH19: 37897 | BI19: 131569 | BJ19: 35530 | BK19: 38696 | BL19: 40423 | BM19: 46864 | BN19: 161513 | BO19: 42616 | BP19: 46643 | BQ19: 49673 | BR19: 57664 | BS19: 196595 | BT19: 53290 | BU19: 58670 | CL19: Q3/Q4-26E tax rate | CN19: 0.16 | CP19: Guided 15–17% for the remaining quarters of 2026 (mid-point).
B20: Advertising growth at constant currency % | D20: =IF(AND(ISNUMBER(D19),ISNUMBER(C11)),IFERROR(D19/C11-1,""),"") | E20: =IF(AND(ISNUMBER(E19),ISNUMBER(D11)),IFERROR(E19/D11-1,""),"") | F20: =IF(AND(ISNUMBER(F19),ISNUMBER(E11)),IFERROR(F19/E11-1,""),"") -> 0.39568802 | K20: =IF(AND(ISNUMBER(K19),ISNUMBER(F11)),IFERROR(K19/F11-1,""),"") -> 0.63776583 | L20: =IF(AND(ISNUMBER(L19),ISNUMBER(G11)),IFERROR(L19/G11-1,""),"") | M20: =IF(AND(ISNUMBER(M19),ISNUMBER(H11)),IFERROR(M19/H11-1,""),"") -> 0.65478424 | N20: =IF(AND(ISNUMBER(N19),ISNUMBER(I11)),IFERROR(N19/I11-1,""),"") -> 0.63292547 | O20: =IF(AND(ISNUMBER(O19),ISNUMBER(J11)),IFERROR(O19/J11-1,""),"") -> 0.57721843 | P20: =IF(AND(ISNUMBER(P19),ISNUMBER(K11)),IFERROR(P19/K11-1,""),"") -> 0.65373604 | Q20: =IF(AND(ISNUMBER(Q19),ISNUMBER(L11)),IFERROR(Q19/L11-1,""),"") -> 0.54746137 | R20: =IF(AND(ISNUMBER(R19),ISNUMBER(M11)),IFERROR(R19/M11-1,""),"") -> 0.55418535 | ... BU20: =IF(AND(ISNUMBER(BU19),ISNUMBER(BP11)),IFERROR(BU19/BP11-1,""),"") -> 0.26001332 | CL20: FY26 capital expenditures incl. finance-lease principal ($m) | CN20: 137500 | CP20: Guided $130–145bn (narrowed from $125–145bn); mid-point. 1H/26 $50.9bn.
B21: FX effect on advertising growth (pp) | D21: =IF(AND(ISNUMBER(D20),ISNUMBER(D12)),D12-D20,"") | E21: =IF(AND(ISNUMBER(E20),ISNUMBER(E12)),E12-E20,"") | F21: =IF(AND(ISNUMBER(F20),ISNUMBER(F12)),F12-F20,"") -> -0.038998098 | K21: =IF(AND(ISNUMBER(K20),ISNUMBER(K12)),K12-K20,"") -> -0.0051413882 | L21: =IF(AND(ISNUMBER(L20),ISNUMBER(L12)),L12-L20,"") | M21: =IF(AND(ISNUMBER(M20),ISNUMBER(M12)),M12-M20,"") -> 0.018761726 | N21: =IF(AND(ISNUMBER(N20),ISNUMBER(N12)),N12-N20,"") -> 0.011679644 | O21: =IF(AND(ISNUMBER(O20),ISNUMBER(O12)),O12-O20,"") -> -0.04394198 | P21: =IF(AND(ISNUMBER(P20),ISNUMBER(P12)),P12-P20,"") -> -0.0087317492 | Q21: =IF(AND(ISNUMBER(Q20),ISNUMBER(Q12)),Q12-Q20,"") -> -0.083002208 | R21: =IF(AND(ISNUMBER(R20),ISNUMBER(R12)),R12-R20,"") -> -0.12406577 | ... BU21: =IF(AND(ISNUMBER(BU20),ISNUMBER(BU12)),BU12-BU20,"") -> 0.014883062 | CL21: Q3/Q4-26E interest-income yield on cash and marketable securities | CN21: 0.04 | CP21: Q2/26 interest income $859m on ~$86bn average (~4.0%, 10-Q).
CL22: Q3/Q4-26E interest rate on debt, net of capitalized interest | CN22: 0.042 | CP22: Q2/26 interest expense $783m (notes $754m net of capitalized interest) on ~$71.5bn average notes (~4.2%, 10-Q).
B23: Other revenue — FoA other revenue (WhatsApp business messaging, Meta Verified; payments & other fees to 2017) · Reality Labs (Quest, AI glasses) | CD23: OTHER REVENUE — FoA other revenue and Reality Labs split from 2019 (segment recast in the Q4-2021 release); before that total non-advertising revenue only | CL23: Q3/Q4-26E dividend per share ($) | CN23: 0.525 | CP23: Quarterly $0.525 declared in 2025 and 2026 (XBRL).
B24: Family of Apps other revenue | AO24: 541 | AS24: 168 | AT24: 657 | AU24: 198 | AV24: 192 | AW24: 176 | AX24: 155 | AY24: 721 | AZ24: 215 | BA24: 218 | BB24: 192 | BC24: 184 | BD24: 808 | BE24: 205 | BF24: 225 | BG24: 293 | BH24: 334 | BI24: 1058 | BJ24: 380 | BK24: 389 | BL24: 434 | BM24: 519 | BN24: 1722 | BO24: 510 | BP24: 583 | BQ24: 690 | BR24: 801 | BS24: 2584 | BT24: 885 | BU24: 1007 | BV24: =BQ24*(1+BV25) -> 1194.4007 | BW24: =BR24*(1+BW25) -> 1386.5435 | BX24: =SUM(BT24:BW24) -> 4472.9442 | BY24: =BX24*(1+BY25) -> 6262.1219 | BZ24: =BY24*(1+BZ25) -> 8140.7584 | CA24: =BZ24*(1+CA25) -> 10175.948 | CB24: =CA24*(1+CB25) -> 12211.138 | CC24: =CB24*(1+CC25) -> 14042.808 | CF24: =IFERROR((CC24/BX24)^(1/5)-1,"n/m") -> 0.25710657 | CG24: =IFERROR((BS24/AT24)^(1/5)-1,"n/m") -> 0.31505958 | CH24: =IFERROR((BS24/U24)^(1/10)-1,"n/m") -> n/m | CI24: =IFERROR((BS24/C24)^(1/16)-1,"n/m") -> n/m
B25: y/y % | D25: =IF(AND(ISNUMBER(D24),ISNUMBER(C24)),IFERROR(D24/C24-1,""),"") | E25: =IF(AND(ISNUMBER(E24),ISNUMBER(D24)),IFERROR(E24/D24-1,""),"") | F25: =IF(AND(ISNUMBER(F24),ISNUMBER(E24)),IFERROR(F24/E24-1,""),"") | K25: =IF(AND(ISNUMBER(K24),ISNUMBER(F24)),IFERROR(K24/F24-1,""),"") | L25: =IF(AND(ISNUMBER(L24),ISNUMBER(G24)),IFERROR(L24/G24-1,""),"") | M25: =IF(AND(ISNUMBER(M24),ISNUMBER(H24)),IFERROR(M24/H24-1,""),"") | N25: =IF(AND(ISNUMBER(N24),ISNUMBER(I24)),IFERROR(N24/I24-1,""),"") | O25: =IF(AND(ISNUMBER(O24),ISNUMBER(J24)),IFERROR(O24/J24-1,""),"") | P25: =IF(AND(ISNUMBER(P24),ISNUMBER(K24)),IFERROR(P24/K24-1,""),"") | Q25: =IF(AND(ISNUMBER(Q24),ISNUMBER(L24)),IFERROR(Q24/L24-1,""),"") | R25: =IF(AND(ISNUMBER(R24),ISNUMBER(M24)),IFERROR(R24/M24-1,""),"") | ... BU25: =IF(AND(ISNUMBER(BU24),ISNUMBER(BP24)),IFERROR(BU24/BP24-1,""),"") -> 0.72727273 | BV25: =IFERROR(SUM(BT24:BU24)/SUM(BO24:BP24)-1,0) -> 0.73101555 | BW25: =IFERROR(SUM(BT24:BU24)/SUM(BO24:BP24)-1,0) -> 0.73101555 | BX25: =IF(AND(ISNUMBER(BX24),ISNUMBER(BS24)),IFERROR(BX24/BS24-1,""),"") -> 0.73101555 | BY25: =CHOOSE(MATCH($CD$2,{"Bull","Base","Bear"},0),$CM$40,$CN$40,$CO$40) -> 0.4 | BZ25: =CHOOSE(MATCH($CD$2,{"Bull","Base","Bear"},0),$CM$41,$CN$41,$CO$41) -> 0.3 | CA25: =CHOOSE(MATCH($CD$2,{"Bull","Base","Bear"},0),$CM$42,$CN$42,$CO$42) -> 0.25 | CB25: =CHOOSE(MATCH($CD$2,{"Bull","Base","Bear"},0),$CM$43,$CN$43,$CO$43) -> 0.2 | CC25: =CHOOSE(MATCH($CD$2,{"Bull","Base","Bear"},0),$CM$44,$CN$44,$CO$44) -> 0.15 | CD25: Q3/Q4-26E: 1H/26 y/y. 2027E+: scenario lever. | CL25: Maximum net debt / adjusted EBITDA before buybacks (x) — buyback ceiling 2027E+ | CM25: 0.5 | CN25: 0.25 | CO25: 0 | CP25: Meta moved from net cash ($22bn at YE2025, cash and marketable securities $81.6bn vs notes $58.7bn) to ~$6.6bn net cash at 30-Jun-2026 as capex outran operating cash flow. Ceiling (assumption) up to which surplus cash is returned via buybacks; above it, cash flow reduces debt. Bull = more buybacks.
B26: Reality Labs revenue | AO26: 501 | AS26: 717 | AT26: 1139 | AU26: 534 | AV26: 305 | AW26: 558 | AX26: 877 | AY26: 2274 | AZ26: 695 | BA26: 452 | BB26: 285 | BC26: 727 | BD26: 2159 | BE26: 339 | BF26: 276 | BG26: 210 | BH26: 1071 | BI26: 1896 | BJ26: 440 | BK26: 353 | BL26: 270 | BM26: 1083 | BN26: 2146 | BO26: 412 | BP26: 370 | BQ26: 470 | BR26: 955 | BS26: 2207 | BT26: 402 | BU26: 431 | BV26: =BQ26*(1+BV27) -> 500.65217 | BW26: =BR26*(1+BW27) -> 1017.2826 | BX26: =SUM(BT26:BW26) -> 2350.9348 | BY26: =BX26*(1+BY27) -> 2586.0283 | BZ26: =BY26*(1+BZ27) -> 2844.6311 | CA26: =BZ26*(1+CA27) -> 3129.0942 | CB26: =CA26*(1+CB27) -> 3442.0036 | CC26: =CB26*(1+CC27) -> 3786.204 | CF26: =IFERROR((CC26/BX26)^(1/5)-1,"n/m") -> 0.1 | CG26: =IFERROR((BS26/AT26)^(1/5)-1,"n/m") -> 0.14144692 | CH26: =IFERROR((BS26/U26)^(1/10)-1,"n/m") -> n/m | CI26: =IFERROR((BS26/C26)^(1/16)-1,"n/m") -> n/m
B27: y/y % | D27: =IF(AND(ISNUMBER(D26),ISNUMBER(C26)),IFERROR(D26/C26-1,""),"") | E27: =IF(AND(ISNUMBER(E26),ISNUMBER(D26)),IFERROR(E26/D26-1,""),"") | F27: =IF(AND(ISNUMBER(F26),ISNUMBER(E26)),IFERROR(F26/E26-1,""),"") | K27: =IF(AND(ISNUMBER(K26),ISNUMBER(F26)),IFERROR(K26/F26-1,""),"") | L27: =IF(AND(ISNUMBER(L26),ISNUMBER(G26)),IFERROR(L26/G26-1,""),"") | M27: =IF(AND(ISNUMBER(M26),ISNUMBER(H26)),IFERROR(M26/H26-1,""),"") | N27: =IF(AND(ISNUMBER(N26),ISNUMBER(I26)),IFERROR(N26/I26-1,""),"") | O27: =IF(AND(ISNUMBER(O26),ISNUMBER(J26)),IFERROR(O26/J26-1,""),"") | P27: =IF(AND(ISNUMBER(P26),ISNUMBER(K26)),IFERROR(P26/K26-1,""),"") | Q27: =IF(AND(ISNUMBER(Q26),ISNUMBER(L26)),IFERROR(Q26/L26-1,""),"") | R27: =IF(AND(ISNUMBER(R26),ISNUMBER(M26)),IFERROR(R26/M26-1,""),"") | ... BU27: =IF(AND(ISNUMBER(BU26),ISNUMBER(BP26)),IFERROR(BU26/BP26-1,""),"") -> 0.16486486 | BV27: =IFERROR(SUM(BT26:BU26)/SUM(BO26:BP26)-1,0) -> 0.065217391 | BW27: =IFERROR(SUM(BT26:BU26)/SUM(BO26:BP26)-1,0) -> 0.065217391 | BX27: =IF(AND(ISNUMBER(BX26),ISNUMBER(BS26)),IFERROR(BX26/BS26-1,""),"") -> 0.065217391 | BY27: =CHOOSE(MATCH($CD$2,{"Bull","Base","Bear"},0),$CM$46,$CN$46,$CO$46) -> 0.1 | BZ27: =CHOOSE(MATCH($CD$2,{"Bull","Base","Bear"},0),$CM$47,$CN$47,$CO$47) -> 0.1 | CA27: =CHOOSE(MATCH($CD$2,{"Bull","Base","Bear"},0),$CM$48,$CN$48,$CO$48) -> 0.1 | CB27: =CHOOSE(MATCH($CD$2,{"Bull","Base","Bear"},0),$CM$49,$CN$49,$CO$49) -> 0.1 | CC27: =CHOOSE(MATCH($CD$2,{"Bull","Base","Bear"},0),$CM$50,$CN$50,$CO$50) -> 0.1 | CD27: Q3/Q4-26E: 1H/26 y/y. 2027E+: scenario lever. | CL27: IMPR (ad impressions y/y) | CM27: 0.02 | CN27: Δ → | CO27: -0.04 | CP27: 1H/26 +19% / +14% (Q1 / Q2); FY25 +12%, FY24 +11%; Threads, WhatsApp Status and Reels add inventory; DAP growth ~3–4% p.a. Assumption.
B28: Total non-advertising revenue | C28: =IF(ISNUMBER(C24),C24+C26,IF(ISNUMBER(C11),C109-C11,"")) -> 13 | D28: =IF(ISNUMBER(D24),D24+D26,IF(ISNUMBER(D11),D109-D11,"")) -> 106 | E28: =IF(ISNUMBER(E24),E24+E26,IF(ISNUMBER(E11),E109-E11,"")) -> 557 | F28: =IF(ISNUMBER(F24),F24+F26,IF(ISNUMBER(F11),F109-F11,"")) -> 810 | G28: =IF(ISNUMBER(G24),G24+G26,IF(ISNUMBER(G11),G109-G11,"")) -> 213 | H28: =IF(ISNUMBER(H24),H24+H26,IF(ISNUMBER(H11),H109-H11,"")) -> 214 | I28: =IF(ISNUMBER(I24),I24+I26,IF(ISNUMBER(I11),I109-I11,"")) -> 218 | J28: =IF(ISNUMBER(J24),J24+J26,IF(ISNUMBER(J11),J109-J11,"")) -> 241 | ... BU28: =IF(ISNUMBER(BU24),BU24+BU26,IF(ISNUMBER(BU11),BU109-BU11,"")) -> 1438 | BV28: =BV24+BV26 -> 1695.0529 | BW28: =BW24+BW26 -> 2403.8261 | BX28: =SUM(BT28:BW28) -> 6823.879 | BY28: =BY24+BY26 -> 8848.1501 | BZ28: =BZ24+BZ26 -> 10985.39 | CA28: =CA24+CA26 -> 13305.042 | CB28: =CB24+CB26 -> 15653.141 | CC28: =CC24+CC26 -> 17829.012 | CD28: History: FoA other + Reality Labs where the segment split is published; otherwise revenue − advertising (payments and other fees, Oculus hardware). | CF28: =IFERROR((CC28/BX28)^(1/5)-1,"n/m") -> 0.2117672 | CG28: =IFERROR((BS28/AT28)^(1/5)-1,"n/m") -> 0.21681336 | CH28: =IFERROR((BS28/U28)^(1/10)-1,"n/m") -> 0.18891785 | CI28: =IFERROR((BS28/C28)^(1/16)-1,"n/m") -> 0.44678893 | CL28: 2027E | CM28: =CN28+$CM$27 -> 0.12 | CN28: 0.1 | CO28: =CN28+$CO$27 -> 0.06
B29: y/y % | D29: =IF(AND(ISNUMBER(D28),ISNUMBER(C28)),IFERROR(D28/C28-1,""),"") -> 7.1538462 | E29: =IF(AND(ISNUMBER(E28),ISNUMBER(D28)),IFERROR(E28/D28-1,""),"") -> 4.254717 | F29: =IF(AND(ISNUMBER(F28),ISNUMBER(E28)),IFERROR(F28/E28-1,""),"") -> 0.45421903 | K29: =IF(AND(ISNUMBER(K28),ISNUMBER(F28)),IFERROR(K28/F28-1,""),"") -> 0.09382716 | L29: =IF(AND(ISNUMBER(L28),ISNUMBER(G28)),IFERROR(L28/G28-1,""),"") -> 0.11267606 | M29: =IF(AND(ISNUMBER(M28),ISNUMBER(H28)),IFERROR(M28/H28-1,""),"") -> 0.093457944 | N29: =IF(AND(ISNUMBER(N28),ISNUMBER(I28)),IFERROR(N28/I28-1,""),"") -> 0.12844037 | O29: =IF(AND(ISNUMBER(O28),ISNUMBER(J28)),IFERROR(O28/J28-1,""),"") -> 0.066390041 | P29: =IF(AND(ISNUMBER(P28),ISNUMBER(K28)),IFERROR(P28/K28-1,""),"") -> 0.099322799 | Q29: =IF(AND(ISNUMBER(Q28),ISNUMBER(L28)),IFERROR(Q28/L28-1,""),"") -> -0.046413502 | R29: =IF(AND(ISNUMBER(R28),ISNUMBER(M28)),IFERROR(R28/M28-1,""),"") -> -0.081196581 | ... BX29: =IF(AND(ISNUMBER(BX28),ISNUMBER(BS28)),IFERROR(BX28/BS28-1,""),"") -> 0.42431204 | BY29: =IF(AND(ISNUMBER(BY28),ISNUMBER(BX28)),IFERROR(BY28/BX28-1,""),"") -> 0.29664523 | BZ29: =IF(AND(ISNUMBER(BZ28),ISNUMBER(BY28)),IFERROR(BZ28/BY28-1,""),"") -> 0.24154647 | CA29: =IF(AND(ISNUMBER(CA28),ISNUMBER(BZ28)),IFERROR(CA28/BZ28-1,""),"") -> 0.21115799 | CB29: =IF(AND(ISNUMBER(CB28),ISNUMBER(CA28)),IFERROR(CB28/CA28-1,""),"") -> 0.17648189 | CC29: =IF(AND(ISNUMBER(CC28),ISNUMBER(CB28)),IFERROR(CC28/CB28-1,""),"") -> 0.13900539 | CL29: 2028E | CM29: =CN29+$CM$27 -> 0.11 | CN29: 0.09 | CO29: =CN29+$CO$27 -> 0.05
B30: Contribution to revenue growth — advertising (pp) | D30: =IFERROR((D11-C11)/C109,"") -> 1.4208494 | E30: =IFERROR((E11-D11)/D109,"") -> 0.6514691 | F30: =IFERROR((F11-E11)/E109,"") -> 0.30315279 | K30: =IFERROR((K11-F11)/F109,"") -> 0.53193162 | L30: =IFERROR((L11-G11)/G109,"") -> 0.69958848 | M30: =IFERROR((M11-H11)/H109,"") -> 0.59404302 | N30: =IFERROR((N11-I11)/I109,"") -> 0.57490079 | O30: =IFERROR((O11-J11)/J109,"") -> 0.48355899 | P30: =IFERROR((P11-K11)/K109,"") -> 0.57240854 | Q30: =IFERROR((Q11-L11)/L109,"") -> 0.42046363 | R30: =IFERROR((R11-M11)/M109,"") -> 0.39553265 | ... BX30: =IFERROR((BX11-BS11)/BS109,"") -> 0.24681554 | BY30: =IFERROR((BY11-BX11)/BX109,"") -> 0.18292127 | BZ30: =IFERROR((BZ11-BY11)/BY109,"") -> 0.15082931 | CA30: =IFERROR((CA11-BZ11)/BZ109,"") -> 0.12977415 | CB30: =IFERROR((CB11-CA11)/CA109,"") -> 0.10900881 | CC30: =IFERROR((CC11-CB11)/CB109,"") -> 0.098768383 | CL30: 2029E | CM30: =CN30+$CM$27 -> 0.1 | CN30: 0.08 | CO30: =CN30+$CO$27 -> 0.04
B31: Contribution to revenue growth — other revenue (pp) | D31: =IFERROR((D28-C28)/C109,"") -> 0.11969112 | E31: =IFERROR((E28-D28)/D109,"") -> 0.22847011 | F31: =IFERROR((F28-E28)/E109,"") -> 0.068175694 | K31: =IFERROR((K28-F28)/F109,"") -> 0.014934172 | L31: =IFERROR((L28-G28)/G109,"") -> 0.016460905 | M31: =IFERROR((M28-H28)/H109,"") -> 0.01103144 | N31: =IFERROR((N28-I28)/I109,"") -> 0.013888889 | O31: =IFERROR((O28-J28)/J109,"") -> 0.0061895551 | P31: =IFERROR((P28-K28)/K109,"") -> 0.011178862 | Q31: =IFERROR((Q28-L28)/L109,"") -> -0.0043964828 | R31: =IFERROR((R28-M28)/M109,"") -> -0.0065292096 | ... BX31: =IFERROR((BX28-BS28)/BS109,"") -> 0.010115537 | BY31: =IFERROR((BY28-BX28)/BX109,"") -> 0.0080137286 | BZ31: =IFERROR((BZ28-BY28)/BY109,"") -> 0.0071044597 | CA31: =IFERROR((CA28-BZ28)/BZ109,"") -> 0.0066591245 | CB31: =IFERROR((CB28-CA28)/CA109,"") -> 0.0059315287 | CC31: =IFERROR((CC28-CB28)/CB109,"") -> 0.0049298277 | CL31: 2030E | CM31: =CN31+$CM$27 -> 0.09 | CN31: 0.07 | CO31: =CN31+$CO$27 -> 0.03
CL32: 2031E | CM32: =CN32+$CM$27 -> 0.08 | CN32: 0.06 | CO32: =CN32+$CO$27 -> 0.02
B33: Segment results — Family of Apps · Reality Labs (first presented in the Q4-2021 release; FY2019-20, Q4-2020 and 2021 quarters recast) | CD33: SEGMENTS — FoA income = consolidated income from operations − Reality Labs result (forecast) | CL33: PRICE (average price per ad y/y) | CM33: 0.02 | CN33: Δ → | CO33: -0.04 | CP33: 1H/26 +12% (both quarters); FY25 +9%, FY24 +10%; AI ranking and ad-format gains vs mix shift to lower-monetizing geographies. Assumption.
B34: Family of Apps revenue | AO34: 70196 | AS34: 27355 | AT34: 84826 | AU34: 25637 | AV34: 28772 | AW34: 28452 | AX34: 32794 | AY34: 115655 | AZ34: 27213 | BA34: 28370 | BB34: 27429 | BC34: 31438 | BD34: 114450 | BE34: 28306 | BF34: 31723 | BG34: 33936 | BH34: 39040 | BI34: 133006 | BJ34: 36015 | BK34: 38718 | BL34: 40319 | BM34: 47302 | BN34: 162355 | BO34: 41902 | BP34: 47146 | BQ34: 50772 | BR34: 58938 | BS34: 198759 | BT34: 55909 | BU34: 60370 | BV34: =BV11+BV24 -> 61999.348 | BW34: =BW11+BW24 -> 71971.129 | BX34: =SUM(BT34:BW34) -> 250249.48 | BY34: =BY11+BY24 -> 298244.64 | BZ34: =BZ11+BZ24 -> 345497.36 | CA34: =CA11+CA24 -> 392738.34 | CB34: =CB11+CB24 -> 437926.56 | CC34: =CC11+CC24 -> 483351.49 | CF34: =IFERROR((CC34/BX34)^(1/5)-1,"n/m") -> 0.14071717 | CG34: =IFERROR((BS34/AT34)^(1/5)-1,"n/m") -> 0.18565835 | CH34: =IFERROR((BS34/U34)^(1/10)-1,"n/m") -> n/m | CI34: =IFERROR((BS34/C34)^(1/16)-1,"n/m") -> n/m | CL34: 2027E | CM34: =CN34+$CM$33 -> 0.1 | CN34: 0.08 | CO34: =CN34+$CO$33 -> 0.04
B35: y/y % | D35: =IF(AND(ISNUMBER(D34),ISNUMBER(C34)),IFERROR(D34/C34-1,""),"") | E35: =IF(AND(ISNUMBER(E34),ISNUMBER(D34)),IFERROR(E34/D34-1,""),"") | F35: =IF(AND(ISNUMBER(F34),ISNUMBER(E34)),IFERROR(F34/E34-1,""),"") | K35: =IF(AND(ISNUMBER(K34),ISNUMBER(F34)),IFERROR(K34/F34-1,""),"") | L35: =IF(AND(ISNUMBER(L34),ISNUMBER(G34)),IFERROR(L34/G34-1,""),"") | M35: =IF(AND(ISNUMBER(M34),ISNUMBER(H34)),IFERROR(M34/H34-1,""),"") | N35: =IF(AND(ISNUMBER(N34),ISNUMBER(I34)),IFERROR(N34/I34-1,""),"") | O35: =IF(AND(ISNUMBER(O34),ISNUMBER(J34)),IFERROR(O34/J34-1,""),"") | P35: =IF(AND(ISNUMBER(P34),ISNUMBER(K34)),IFERROR(P34/K34-1,""),"") | Q35: =IF(AND(ISNUMBER(Q34),ISNUMBER(L34)),IFERROR(Q34/L34-1,""),"") | R35: =IF(AND(ISNUMBER(R34),ISNUMBER(M34)),IFERROR(R34/M34-1,""),"") | ... BX35: =IF(AND(ISNUMBER(BX34),ISNUMBER(BS34)),IFERROR(BX34/BS34-1,""),"") -> 0.25905985 | BY35: =IF(AND(ISNUMBER(BY34),ISNUMBER(BX34)),IFERROR(BY34/BX34-1,""),"") -> 0.19178928 | BZ35: =IF(AND(ISNUMBER(BZ34),ISNUMBER(BY34)),IFERROR(BZ34/BY34-1,""),"") -> 0.15843611 | CA35: =IF(AND(ISNUMBER(CA34),ISNUMBER(BZ34)),IFERROR(CA34/BZ34-1,""),"") -> 0.13673324 | CB35: =IF(AND(ISNUMBER(CB34),ISNUMBER(CA34)),IFERROR(CB34/CA34-1,""),"") -> 0.11505937 | CC35: =IF(AND(ISNUMBER(CC34),ISNUMBER(CB34)),IFERROR(CC34/CB34-1,""),"") -> 0.10372728 | CL35: 2028E | CM35: =CN35+$CM$33 -> 0.08 | CN35: 0.06 | CO35: =CN35+$CO$33 -> 0.02
B36: Family of Apps income from operations | AO36: 28489 | AS36: 14874 | AT36: 39294 | AU36: 13205 | AV36: 14799 | AW36: 13054 | AX36: 15889 | AY36: 56946 | AZ36: 11484 | BA36: 11164 | BB36: 9336 | BC36: 10678 | BD36: 42661 | BE36: 11219 | BF36: 13131 | BG36: 17490 | BH36: 21030 | BI36: 62871 | BJ36: 17664 | BK36: 19335 | BL36: 21778 | BM36: 28332 | BN36: 87109 | BO36: 21765 | BP36: 24971 | BQ36: 24967 | BR36: 30766 | BS36: 102469 | BT36: 26900 | BU36: 23394 | BV36: =BV116-BV38 -> 24203.719 | BW36: =BW116-BW38 -> 30091.465 | BX36: =SUM(BT36:BW36) -> 104589.18 | BY36: =BY116-BY38 -> 122233.46 | BZ36: =BZ116-BZ38 -> 138615.08 | CA36: =CA116-CA38 -> 153765.02 | CB36: =CB116-CB38 -> 173014.51 | CC36: =CC116-CC38 -> 192281.07 | CD36: Forecast: consolidated income from operations − Reality Labs operating loss (FoA carries all one-off items in the forecast). | CF36: =IFERROR((CC36/BX36)^(1/5)-1,"n/m") -> 0.12950966 | CG36: =IFERROR((BS36/AT36)^(1/5)-1,"n/m") -> 0.21130428 | CH36: =IFERROR((BS36/U36)^(1/10)-1,"n/m") -> n/m | CI36: =IFERROR((BS36/C36)^(1/16)-1,"n/m") -> n/m | CL36: 2029E | CM36: =CN36+$CM$33 -> 0.07 | CN36: 0.05 | CO36: =CN36+$CO$33 -> 0.01
B37: FoA operating margin % | C37: =IF(AND(ISNUMBER(C36),ISNUMBER(C34)),IFERROR(C36/C34,""),"") | D37: =IF(AND(ISNUMBER(D36),ISNUMBER(D34)),IFERROR(D36/D34,""),"") | E37: =IF(AND(ISNUMBER(E36),ISNUMBER(E34)),IFERROR(E36/E34,""),"") | F37: =IF(AND(ISNUMBER(F36),ISNUMBER(F34)),IFERROR(F36/F34,""),"") | G37: =IF(AND(ISNUMBER(G36),ISNUMBER(G34)),IFERROR(G36/G34,""),"") | H37: =IF(AND(ISNUMBER(H36),ISNUMBER(H34)),IFERROR(H36/H34,""),"") | I37: =IF(AND(ISNUMBER(I36),ISNUMBER(I34)),IFERROR(I36/I34,""),"") | J37: =IF(AND(ISNUMBER(J36),ISNUMBER(J34)),IFERROR(J36/J34,""),"") | ... CC37: =IF(AND(ISNUMBER(CC36),ISNUMBER(CC34)),IFERROR(CC36/CC34,""),"") -> 0.39780795 | CF37: =IFERROR(AVERAGE(BY37,BZ37,CA37,CB37,CC37),"n/m") -> 0.39909043 | CG37: =IFERROR(AVERAGE(AY37,BD37,BI37,BN37,BS37),"n/m") -> 0.47797943 | CH37: =IFERROR(AVERAGE(Z37,AE37,AJ37,AO37,AT37,AY37,BD37,BI37,BN37,BS37),"n/m") -> 0.46556816 | CI37: =IFERROR(AVERAGE(C37,D37,E37,F37,K37,P37,U37,Z37,AE37,AJ37,AO37,AT37,AY37,BD37,BI37,BN37,BS37),"n/m") -> 0.46556816 | CL37: 2030E | CM37: =CN37+$CM$33 -> 0.06 | CN37: 0.04 | CO37: =CN37+$CO$33 -> 0
B38: Reality Labs income (loss) from operations | AO38: -4503 | AS38: -2099 | AT38: -6623 | AU38: -1827 | AV38: -2432 | AW38: -2631 | AX38: -3304 | AY38: -10193 | AZ38: -2960 | BA38: -2806 | BB38: -3672 | BC38: -4279 | BD38: -13717 | BE38: -3992 | BF38: -3739 | BG38: -3742 | BH38: -4646 | BI38: -16120 | BJ38: -3846 | BK38: -4488 | BL38: -4428 | BM38: -4967 | BN38: -17729 | BO38: -4210 | BP38: -4530 | BQ38: -4432 | BR38: -6021 | BS38: -19193 | BT38: -4028 | BU38: -4619 | BV38: =BQ38*IFERROR(SUM(BT38:BU38)/SUM(BO38:BP38),1) -> -4384.8403 | BW38: =BR38*IFERROR(SUM(BT38:BU38)/SUM(BO38:BP38),1) -> -5956.9322 | BX38: =SUM(BT38:BW38) -> -18988.772 | BY38: =-CHOOSE(MATCH($CD$2,{"Bull","Base","Bear"},0),$CM$52,$CN$52,$CO$52) -> -20000 | BZ38: =-CHOOSE(MATCH($CD$2,{"Bull","Base","Bear"},0),$CM$53,$CN$53,$CO$53) -> -19500 | CA38: =-CHOOSE(MATCH($CD$2,{"Bull","Base","Bear"},0),$CM$54,$CN$54,$CO$54) -> -19000 | CB38: =-CHOOSE(MATCH($CD$2,{"Bull","Base","Bear"},0),$CM$55,$CN$55,$CO$55) -> -18000 | CC38: =-CHOOSE(MATCH($CD$2,{"Bull","Base","Bear"},0),$CM$56,$CN$56,$CO$56) -> -17000 | CD38: Q3/Q4-26E: prior-year quarter × 1H/26 ÷ 1H/25 loss ratio. 2027E+: scenario lever (operating loss, $m). | CL38: 2031E | CM38: =CN38+$CM$33 -> 0.06 | CN38: 0.04 | CO38: =CN38+$CO$33 -> 0
B39: y/y % | D39: =IF(AND(ISNUMBER(D38),ISNUMBER(C38)),IFERROR(D38/C38-1,""),"") | E39: =IF(AND(ISNUMBER(E38),ISNUMBER(D38)),IFERROR(E38/D38-1,""),"") | F39: =IF(AND(ISNUMBER(F38),ISNUMBER(E38)),IFERROR(F38/E38-1,""),"") | K39: =IF(AND(ISNUMBER(K38),ISNUMBER(F38)),IFERROR(K38/F38-1,""),"") | L39: =IF(AND(ISNUMBER(L38),ISNUMBER(G38)),IFERROR(L38/G38-1,""),"") | M39: =IF(AND(ISNUMBER(M38),ISNUMBER(H38)),IFERROR(M38/H38-1,""),"") | N39: =IF(AND(ISNUMBER(N38),ISNUMBER(I38)),IFERROR(N38/I38-1,""),"") | O39: =IF(AND(ISNUMBER(O38),ISNUMBER(J38)),IFERROR(O38/J38-1,""),"") | P39: =IF(AND(ISNUMBER(P38),ISNUMBER(K38)),IFERROR(P38/K38-1,""),"") | Q39: =IF(AND(ISNUMBER(Q38),ISNUMBER(L38)),IFERROR(Q38/L38-1,""),"") | R39: =IF(AND(ISNUMBER(R38),ISNUMBER(M38)),IFERROR(R38/M38-1,""),"") | ... BX39: =IF(AND(ISNUMBER(BX38),ISNUMBER(BS38)),IFERROR(BX38/BS38-1,""),"") -> -0.010640732 | BY39: =IF(AND(ISNUMBER(BY38),ISNUMBER(BX38)),IFERROR(BY38/BX38-1,""),"") -> 0.053253973 | BZ39: =IF(AND(ISNUMBER(BZ38),ISNUMBER(BY38)),IFERROR(BZ38/BY38-1,""),"") -> -0.025 | CA39: =IF(AND(ISNUMBER(CA38),ISNUMBER(BZ38)),IFERROR(CA38/BZ38-1,""),"") -> -0.025641026 | CB39: =IF(AND(ISNUMBER(CB38),ISNUMBER(CA38)),IFERROR(CB38/CA38-1,""),"") -> -0.052631579 | CC39: =IF(AND(ISNUMBER(CC38),ISNUMBER(CB38)),IFERROR(CC38/CB38-1,""),"") -> -0.055555556 | CL39: FOTH (FoA other revenue y/y) | CM39: 0.1 | CN39: Δ → | CO39: -0.15 | CP39: 1H/26 +73%; FY25 +50% (WhatsApp business messaging, Meta Verified subscriptions). Assumption.
B40: Check: segment revenue vs consolidated revenue (should be 0) | C40: =IF(ISNUMBER(C34),ROUND(C34+C26-C109,1),"") | D40: =IF(ISNUMBER(D34),ROUND(D34+D26-D109,1),"") | E40: =IF(ISNUMBER(E34),ROUND(E34+E26-E109,1),"") | F40: =IF(ISNUMBER(F34),ROUND(F34+F26-F109,1),"") | G40: =IF(ISNUMBER(G34),ROUND(G34+G26-G109,1),"") | H40: =IF(ISNUMBER(H34),ROUND(H34+H26-H109,1),"") | I40: =IF(ISNUMBER(I34),ROUND(I34+I26-I109,1),"") | J40: =IF(ISNUMBER(J34),ROUND(J34+J26-J109,1),"") | ... BU40: =IF(ISNUMBER(BU34),ROUND(BU34+BU26-BU109,1),"") -> 0 | CL40: 2027E | CM40: =CN40+$CM$39 -> 0.5 | CN40: 0.4 | CO40: =CN40+$CO$39 -> 0.25
B41: Check: segment results vs income from operations (should be 0) | C41: =IF(ISNUMBER(C36),ROUND(C36+C38-C116,1),"") | D41: =IF(ISNUMBER(D36),ROUND(D36+D38-D116,1),"") | E41: =IF(ISNUMBER(E36),ROUND(E36+E38-E116,1),"") | F41: =IF(ISNUMBER(F36),ROUND(F36+F38-F116,1),"") | G41: =IF(ISNUMBER(G36),ROUND(G36+G38-G116,1),"") | H41: =IF(ISNUMBER(H36),ROUND(H36+H38-H116,1),"") | I41: =IF(ISNUMBER(I36),ROUND(I36+I38-I116,1),"") | J41: =IF(ISNUMBER(J36),ROUND(J36+J38-J116,1),"") | ... BU41: =IF(ISNUMBER(BU36),ROUND(BU36+BU38-BU116,1),"") -> 0 | CL41: 2028E | CM41: =CN41+$CM$39 -> 0.4 | CN41: 0.3 | CO41: =CN41+$CO$39 -> 0.15
CL42: 2029E | CM42: =CN42+$CM$39 -> 0.35 | CN42: 0.25 | CO42: =CN42+$CO$39 -> 0.1
B43: People, engagement & productivity (company-reported KPIs) | CD43: KPIs — information rows (release text) | CL43: 2030E | CM43: =CN43+$CM$39 -> 0.3 | CN43: 0.2 | CO43: =CN43+$CO$39 -> 0.05
B44: Family daily active people (DAP), m (average for the last month of the quarter; from Q4-2019) | AN44: 2260 | AO44: 2260 | AP44: 2360 | AQ44: 2470 | AR44: 2540 | AS44: 2600 | AT44: 2600 | AU44: 2720 | AV44: 2760 | AW44: 2810 | AX44: 2820 | AY44: 2820 | AZ44: 2870 | BA44: 2880 | BB44: 2930 | BC44: 2960 | BD44: 2960 | BE44: 3020 | BF44: 3070 | BG44: 3140 | BH44: 3190 | BI44: 3190 | BJ44: 3240 | BK44: 3270 | BL44: 3290 | BM44: 3350 | BN44: 3350 | BO44: 3430 | BP44: 3480 | BQ44: 3540 | BR44: 3580 | BS44: 3580 | BT44: 3560 | BU44: 3600 | CF44: =IFERROR((CC44/BX44)^(1/5)-1,"n/m") -> n/m | CG44: =IFERROR((BS44/AT44)^(1/5)-1,"n/m") -> 0.066060705 | CH44: =IFERROR((BS44/U44)^(1/10)-1,"n/m") -> n/m | CI44: =IFERROR((BS44/C44)^(1/16)-1,"n/m") -> n/m | CL44: 2031E | CM44: =CN44+$CM$39 -> 0.25 | CN44: 0.15 | CO44: =CN44+$CO$39 -> 0
B45: DAP y/y % | D45: =IF(AND(ISNUMBER(D44),ISNUMBER(C44)),IFERROR(D44/C44-1,""),"") | E45: =IF(AND(ISNUMBER(E44),ISNUMBER(D44)),IFERROR(E44/D44-1,""),"") | F45: =IF(AND(ISNUMBER(F44),ISNUMBER(E44)),IFERROR(F44/E44-1,""),"") | K45: =IF(AND(ISNUMBER(K44),ISNUMBER(F44)),IFERROR(K44/F44-1,""),"") | L45: =IF(AND(ISNUMBER(L44),ISNUMBER(G44)),IFERROR(L44/G44-1,""),"") | M45: =IF(AND(ISNUMBER(M44),ISNUMBER(H44)),IFERROR(M44/H44-1,""),"") | N45: =IF(AND(ISNUMBER(N44),ISNUMBER(I44)),IFERROR(N44/I44-1,""),"") | O45: =IF(AND(ISNUMBER(O44),ISNUMBER(J44)),IFERROR(O44/J44-1,""),"") | P45: =IF(AND(ISNUMBER(P44),ISNUMBER(K44)),IFERROR(P44/K44-1,""),"") | Q45: =IF(AND(ISNUMBER(Q44),ISNUMBER(L44)),IFERROR(Q44/L44-1,""),"") | R45: =IF(AND(ISNUMBER(R44),ISNUMBER(M44)),IFERROR(R44/M44-1,""),"") | ... BX45: =IF(AND(ISNUMBER(BX44),ISNUMBER(BS44)),IFERROR(BX44/BS44-1,""),"") | BY45: =IF(AND(ISNUMBER(BY44),ISNUMBER(BX44)),IFERROR(BY44/BX44-1,""),"") | BZ45: =IF(AND(ISNUMBER(BZ44),ISNUMBER(BY44)),IFERROR(BZ44/BY44-1,""),"") | CA45: =IF(AND(ISNUMBER(CA44),ISNUMBER(BZ44)),IFERROR(CA44/BZ44-1,""),"") | CB45: =IF(AND(ISNUMBER(CB44),ISNUMBER(CA44)),IFERROR(CB44/CA44-1,""),"") | CC45: =IF(AND(ISNUMBER(CC44),ISNUMBER(CB44)),IFERROR(CC44/CB44-1,""),"") | CL45: RLREV (Reality Labs revenue y/y) | CM45: 0.1 | CN45: Δ → | CO45: -0.1 | CP45: 1H/26 +7%; FY25 −3% (Quest declines offset by AI glasses). Assumption.
B46: Family monthly active people (MAP), m (Q4-2019 to Q4-2023) | AN46: 2890 | AO46: 2890 | AP46: 2990 | AQ46: 3140 | AR46: 3210 | AS46: 3300 | AT46: 3300 | AU46: 3450 | AV46: 3510 | AW46: 3580 | AX46: 3590 | AY46: 3590 | AZ46: 3640 | BA46: 3650 | BB46: 3710 | BC46: 3740 | BD46: 3740 | BE46: 3810 | BF46: 3880 | BG46: 3960 | BH46: 3980 | BI46: 3980 | CL46: 2027E | CM46: =CN46+$CM$45 -> 0.2 | CN46: 0.1 | CO46: =CN46+$CO$45 -> 0
B47: Facebook daily active users (DAUs), m (to Q4-2023) | F47: 618 | G47: 665 | H47: 699 | I47: 728 | J47: 757 | K47: 757 | L47: 802 | M47: 829 | N47: 864 | O47: 890 | P47: 890 | Q47: 936 | R47: 968 | S47: 1010 | T47: 1040 | U47: 1040 | V47: 1090 | W47: 1130 | X47: 1180 | Y47: 1230 | Z47: 1230 | AA47: 1280 | AB47: 1320 | AC47: 1370 | AD47: 1400 | AE47: 1400 | AF47: 1450 | AG47: 1470 | AH47: 1490 | AI47: 1520 | AJ47: 1520 | AK47: 1560 | AL47: 1590 | AM47: 1620 | AN47: 1660 | AO47: 1660 | AP47: 1730 | AQ47: 1790 | AR47: 1820 | AS47: 1840 | AT47: 1840 | AU47: 1880 | AV47: 1910 | AW47: 1930 | AX47: 1930 | AY47: 1930 | AZ47: 1960 | BA47: 1970 | BB47: 1980 | BC47: 2000 | BD47: 2000 | BE47: 2040 | BF47: 2060 | BG47: 2090 | BH47: 2110 | BI47: 2110 | CL47: 2028E | CM47: =CN47+$CM$45 -> 0.2 | CN47: 0.1 | CO47: =CN47+$CO$45 -> 0
B48: Facebook monthly active users (MAUs), m (to Q4-2023) | F48: 1060 | G48: 1110 | H48: 1150 | I48: 1190 | J48: 1230 | K48: 1230 | L48: 1280 | M48: 1320 | N48: 1350 | O48: 1390 | P48: 1390 | Q48: 1440 | R48: 1490 | S48: 1550 | T48: 1590 | U48: 1590 | V48: 1650 | W48: 1710 | X48: 1790 | Y48: 1860 | Z48: 1860 | AA48: 1940 | AB48: 2010 | AC48: 2070 | AD48: 2130 | AE48: 2130 | AF48: 2200 | AG48: 2230 | AH48: 2270 | AI48: 2320 | AJ48: 2320 | AK48: 2380 | AL48: 2410 | AM48: 2450 | AN48: 2500 | AO48: 2500 | AP48: 2600 | AQ48: 2700 | AR48: 2740 | AS48: 2800 | AT48: 2800 | AU48: 2850 | AV48: 2900 | AW48: 2910 | AX48: 2910 | AY48: 2910 | AZ48: 2940 | BA48: 2930 | BB48: 2960 | BC48: 2960 | BD48: 2960 | BE48: 2990 | BF48: 3030 | BG48: 3050 | BH48: 3070 | BI48: 3070 | CL48: 2029E | CM48: =CN48+$CM$45 -> 0.2 | CN48: 0.1 | CO48: =CN48+$CO$45 -> 0
B49: Revenue per DAP — annualised, on period DAP ($) | C49: =IF(ISNUMBER(C44),IFERROR(C109*1/C44,""),"") | D49: =IF(ISNUMBER(D44),IFERROR(D109*1/D44,""),"") | E49: =IF(ISNUMBER(E44),IFERROR(E109*1/E44,""),"") | F49: =IF(ISNUMBER(F44),IFERROR(F109*1/F44,""),"") | G49: =IF(ISNUMBER(G44),IFERROR(G109*4/G44,""),"") | H49: =IF(ISNUMBER(H44),IFERROR(H109*4/H44,""),"") | I49: =IF(ISNUMBER(I44),IFERROR(I109*4/I44,""),"") | J49: =IF(ISNUMBER(J44),IFERROR(J109*4/J44,""),"") | K49: =IF(ISNUMBER(K44),IFERROR(K109*1/K44,""),"") | L49: =IF(ISNUMBER(L44),IFERROR(L109*4/L44,""),"") | M49: =IF(ISNUMBER(M44),IFERROR(M109*4/M44,""),"") | N49: =IF(ISNUMBER(N44),IFERROR(N109*4/N44,""),"") | O49: =IF(ISNUMBER(O44),IFERROR(O109*4/O44,""),"") | P49: =IF(ISNUMBER(P44),IFERROR(P109*1/P44,""),"") | Q49: =IF(ISNUMBER(Q44),IFERROR(Q109*4/Q44,""),"") | R49: =IF(ISNUMBER(R44),IFERROR(R109*4/R44,""),"") | S49: =IF(ISNUMBER(S44),IFERROR(S109*4/S44,""),"") | T49: =IF(ISNUMBER(T44),IFERROR(T109*4/T44,""),"") | U49: =IF(ISNUMBER(U44),IFERROR(U109*1/U44,""),"") | V49: =IF(ISNUMBER(V44),IFERROR(V109*4/V44,""),"") | W49: =IF(ISNUMBER(W44),IFERROR(W109*4/W44,""),"") | X49: =IF(ISNUMBER(X44),IFERROR(X109*4/X44,""),"") | Y49: =IF(ISNUMBER(Y44),IFERROR(Y109*4/Y44,""),"") | Z49: =IF(ISNUMBER(Z44),IFERROR(Z109*1/Z44,""),"") | AA49: =IF(ISNUMBER(AA44),IFERROR(AA109*4/AA44,""),"") | AB49: =IF(ISNUMBER(AB44),IFERROR(AB109*4/AB44,""),"") | AC49: =IF(ISNUMBER(AC44),IFERROR(AC109*4/AC44,""),"") | AD49: =IF(ISNUMBER(AD44),IFERROR(AD109*4/AD44,""),"") | AE49: =IF(ISNUMBER(AE44),IFERROR(AE109*1/AE44,""),"") | AF49: =IF(ISNUMBER(AF44),IFERROR(AF109*4/AF44,""),"") | AG49: =IF(ISNUMBER(AG44),IFERROR(AG109*4/AG44,""),"") | AH49: =IF(ISNUMBER(AH44),IFERROR(AH109*4/AH44,""),"") | AI49: =IF(ISNUMBER(AI44),IFERROR(AI109*4/AI44,""),"") | AJ49: =IF(ISNUMBER(AJ44),IFERROR(AJ109*1/AJ44,""),"") | AK49: =IF(ISNUMBER(AK44),IFERROR(AK109*4/AK44,""),"") | AL49: =IF(ISNUMBER(AL44),IFERROR(AL109*4/AL44,""),"") | AM49: =IF(ISNUMBER(AM44),IFERROR(AM109*4/AM44,""),"") | AN49: =IF(ISNUMBER(AN44),IFERROR(AN109*4/AN44,""),"") -> 37.313274 | AO49: =IF(ISNUMBER(AO44),IFERROR(AO109*1/AO44,""),"") -> 31.281858 | AP49: =IF(ISNUMBER(AP44),IFERROR(AP109*4/AP44,""),"") -> 30.062712 | AQ49: =IF(ISNUMBER(AQ44),IFERROR(AQ109*4/AQ44,""),"") -> 30.262348 | AR49: =IF(ISNUMBER(AR44),IFERROR(AR109*4/AR44,""),"") -> 33.811024 | AS49: =IF(ISNUMBER(AS44),IFERROR(AS109*4/AS44,""),"") -> 43.187692 | AT49: =IF(ISNUMBER(AT44),IFERROR(AT109*1/AT44,""),"") -> 33.063462 | AU49: =IF(ISNUMBER(AU44),IFERROR(AU109*4/AU44,""),"") -> 38.486765 | AV49: =IF(ISNUMBER(AV44),IFERROR(AV109*4/AV44,""),"") -> 42.14058 | AW49: =IF(ISNUMBER(AW44),IFERROR(AW109*4/AW44,""),"") -> 41.295374 | AX49: =IF(ISNUMBER(AX44),IFERROR(AX109*4/AX44,""),"") -> 47.760284 | AY49: =IF(ISNUMBER(AY44),IFERROR(AY109*1/AY44,""),"") -> 41.818794 | AZ49: =IF(ISNUMBER(AZ44),IFERROR(AZ109*4/AZ44,""),"") -> 38.896167 | BA49: =IF(ISNUMBER(BA44),IFERROR(BA109*4/BA44,""),"") -> 40.030556 | BB49: =IF(ISNUMBER(BB44),IFERROR(BB109*4/BB44,""),"") -> 37.834812 | BC49: =IF(ISNUMBER(BC44),IFERROR(BC109*4/BC44,""),"") -> 43.466216 | BD49: =IF(ISNUMBER(BD44),IFERROR(BD109*1/BD44,""),"") -> 39.394932 | BE49: =IF(ISNUMBER(BE44),IFERROR(BE109*4/BE44,""),"") -> 37.940397 | BF49: =IF(ISNUMBER(BF44),IFERROR(BF109*4/BF44,""),"") -> 41.692508 | BG49: =IF(ISNUMBER(BG44),IFERROR(BG109*4/BG44,""),"") -> 43.498089 | BH49: =IF(ISNUMBER(BH44),IFERROR(BH109*4/BH44,""),"") -> 50.295925 | BI49: =IF(ISNUMBER(BI44),IFERROR(BI109*1/BI44,""),"") -> 42.289028 | BJ49: =IF(ISNUMBER(BJ44),IFERROR(BJ109*4/BJ44,""),"") -> 45.006173 | BK49: =IF(ISNUMBER(BK44),IFERROR(BK109*4/BK44,""),"") -> 47.793272 | BL49: =IF(ISNUMBER(BL44),IFERROR(BL109*4/BL44,""),"") -> 49.348328 | BM49: =IF(ISNUMBER(BM44),IFERROR(BM109*4/BM44,""),"") -> 57.773134 | BN49: =IF(ISNUMBER(BN44),IFERROR(BN109*1/BN44,""),"") -> 49.104776 | BO49: =IF(ISNUMBER(BO44),IFERROR(BO109*4/BO44,""),"") -> 49.345773 | BP49: =IF(ISNUMBER(BP44),IFERROR(BP109*4/BP44,""),"") -> 54.616092 | BQ49: =IF(ISNUMBER(BQ44),IFERROR(BQ109*4/BQ44,""),"") -> 57.900565 | BR49: =IF(ISNUMBER(BR44),IFERROR(BR109*4/BR44,""),"") -> 66.919553 | BS49: =IF(ISNUMBER(BS44),IFERROR(BS109*1/BS44,""),"") -> 56.135754 | BT49: =IF(ISNUMBER(BT44),IFERROR(BT109*4/BT44,""),"") -> 63.270787 | BU49: =IF(ISNUMBER(BU44),IFERROR(BU109*4/BU44,""),"") -> 67.556667 | CL49: 2030E | CM49: =CN49+$CM$45 -> 0.2 | CN49: 0.1 | CO49: =CN49+$CO$45 -> 0
B50: Headcount (period end) | AA50: 18770 | AB50: 20658 | AC50: 23165 | AD50: 25105 | AE50: 25105 | AF50: 27742 | AG50: 30275 | AH50: 33606 | AI50: 35587 | AJ50: 35587 | AK50: 37773 | AL50: 39651 | AM50: 43030 | AN50: 44942 | AO50: 44942 | AP50: 48268 | AQ50: 52534 | AR50: 56653 | AS50: 58604 | AT50: 58604 | AU50: 60654 | AV50: 63404 | AW50: 68177 | AX50: 71970 | AY50: 71970 | AZ50: 77805 | BA50: 83553 | BB50: 87314 | BC50: 86482 | BD50: 86482 | BE50: 77114 | BF50: 71469 | BG50: 66185 | BH50: 67317 | BI50: 67317 | BJ50: 69329 | BK50: 70799 | BL50: 72404 | BM50: 74067 | BN50: 74067 | BO50: 76834 | BP50: 75945 | BQ50: 78450 | BR50: 78865 | BS50: 78865 | BT50: 77986 | BU50: 75472 | CF50: =IFERROR((CC50/BX50)^(1/5)-1,"n/m") -> n/m | CG50: =IFERROR((BS50/AT50)^(1/5)-1,"n/m") -> 0.06118575 | CH50: =IFERROR((BS50/U50)^(1/10)-1,"n/m") -> n/m | CI50: =IFERROR((BS50/C50)^(1/16)-1,"n/m") -> n/m | CL50: 2031E | CM50: =CN50+$CM$45 -> 0.2 | CN50: 0.1 | CO50: =CN50+$CO$45 -> 0
B51: Headcount y/y % | D51: =IF(AND(ISNUMBER(D50),ISNUMBER(C50)),IFERROR(D50/C50-1,""),"") | E51: =IF(AND(ISNUMBER(E50),ISNUMBER(D50)),IFERROR(E50/D50-1,""),"") | F51: =IF(AND(ISNUMBER(F50),ISNUMBER(E50)),IFERROR(F50/E50-1,""),"") | K51: =IF(AND(ISNUMBER(K50),ISNUMBER(F50)),IFERROR(K50/F50-1,""),"") | L51: =IF(AND(ISNUMBER(L50),ISNUMBER(G50)),IFERROR(L50/G50-1,""),"") | M51: =IF(AND(ISNUMBER(M50),ISNUMBER(H50)),IFERROR(M50/H50-1,""),"") | N51: =IF(AND(ISNUMBER(N50),ISNUMBER(I50)),IFERROR(N50/I50-1,""),"") | O51: =IF(AND(ISNUMBER(O50),ISNUMBER(J50)),IFERROR(O50/J50-1,""),"") | P51: =IF(AND(ISNUMBER(P50),ISNUMBER(K50)),IFERROR(P50/K50-1,""),"") | Q51: =IF(AND(ISNUMBER(Q50),ISNUMBER(L50)),IFERROR(Q50/L50-1,""),"") | R51: =IF(AND(ISNUMBER(R50),ISNUMBER(M50)),IFERROR(R50/M50-1,""),"") | ... BX51: =IF(AND(ISNUMBER(BX50),ISNUMBER(BS50)),IFERROR(BX50/BS50-1,""),"") | BY51: =IF(AND(ISNUMBER(BY50),ISNUMBER(BX50)),IFERROR(BY50/BX50-1,""),"") | BZ51: =IF(AND(ISNUMBER(BZ50),ISNUMBER(BY50)),IFERROR(BZ50/BY50-1,""),"") | CA51: =IF(AND(ISNUMBER(CA50),ISNUMBER(BZ50)),IFERROR(CA50/BZ50-1,""),"") | CB51: =IF(AND(ISNUMBER(CB50),ISNUMBER(CA50)),IFERROR(CB50/CA50-1,""),"") | CC51: =IF(AND(ISNUMBER(CC50),ISNUMBER(CB50)),IFERROR(CC50/CB50-1,""),"") | CL51: RLLOSS (Reality Labs operating loss, $m) | CM51: -3000 | CN51: Δ → | CO51: 4000 | CP51: FY25 loss $19.2bn; 1H/26 $8.6bn (−1% y/y). The company said 2026 Reality Labs losses would be similar to 2025. Assumption: gradual narrowing.
B52: Revenue per employee — annualised ($000) | C52: =IF(ISNUMBER(C50),IFERROR(C109*1/C50*1000,""),"") | D52: =IF(ISNUMBER(D50),IFERROR(D109*1/D50*1000,""),"") | E52: =IF(ISNUMBER(E50),IFERROR(E109*1/E50*1000,""),"") | F52: =IF(ISNUMBER(F50),IFERROR(F109*1/F50*1000,""),"") | G52: =IF(ISNUMBER(G50),IFERROR(G109*4/G50*1000,""),"") | H52: =IF(ISNUMBER(H50),IFERROR(H109*4/H50*1000,""),"") | I52: =IF(ISNUMBER(I50),IFERROR(I109*4/I50*1000,""),"") | J52: =IF(ISNUMBER(J50),IFERROR(J109*4/J50*1000,""),"") | K52: =IF(ISNUMBER(K50),IFERROR(K109*1/K50*1000,""),"") | L52: =IF(ISNUMBER(L50),IFERROR(L109*4/L50*1000,""),"") | M52: =IF(ISNUMBER(M50),IFERROR(M109*4/M50*1000,""),"") | N52: =IF(ISNUMBER(N50),IFERROR(N109*4/N50*1000,""),"") | O52: =IF(ISNUMBER(O50),IFERROR(O109*4/O50*1000,""),"") | P52: =IF(ISNUMBER(P50),IFERROR(P109*1/P50*1000,""),"") | Q52: =IF(ISNUMBER(Q50),IFERROR(Q109*4/Q50*1000,""),"") | R52: =IF(ISNUMBER(R50),IFERROR(R109*4/R50*1000,""),"") | S52: =IF(ISNUMBER(S50),IFERROR(S109*4/S50*1000,""),"") | T52: =IF(ISNUMBER(T50),IFERROR(T109*4/T50*1000,""),"") | U52: =IF(ISNUMBER(U50),IFERROR(U109*1/U50*1000,""),"") | V52: =IF(ISNUMBER(V50),IFERROR(V109*4/V50*1000,""),"") | W52: =IF(ISNUMBER(W50),IFERROR(W109*4/W50*1000,""),"") | X52: =IF(ISNUMBER(X50),IFERROR(X109*4/X50*1000,""),"") | Y52: =IF(ISNUMBER(Y50),IFERROR(Y109*4/Y50*1000,""),"") | Z52: =IF(ISNUMBER(Z50),IFERROR(Z109*1/Z50*1000,""),"") | AA52: =IF(ISNUMBER(AA50),IFERROR(AA109*4/AA50*1000,""),"") -> 1711.6676 | AB52: =IF(ISNUMBER(AB50),IFERROR(AB109*4/AB50*1000,""),"") -> 1804.8214 | AC52: =IF(ISNUMBER(AC50),IFERROR(AC109*4/AC50*1000,""),"") -> 1783.3801 | AD52: =IF(ISNUMBER(AD50),IFERROR(AD109*4/AD50*1000,""),"") -> 2066.8393 | AE52: =IF(ISNUMBER(AE50),IFERROR(AE109*1/AE50*1000,""),"") -> 1619.3189 | AF52: =IF(ISNUMBER(AF50),IFERROR(AF109*4/AF50*1000,""),"") -> 1725.3262 | AG52: =IF(ISNUMBER(AG50),IFERROR(AG109*4/AG50*1000,""),"") -> 1748.109 | AH52: =IF(ISNUMBER(AH50),IFERROR(AH109*4/AH50*1000,""),"") -> 1633.8749 | AI52: =IF(ISNUMBER(AI50),IFERROR(AI109*4/AI50*1000,""),"") -> 1901.1437 | AJ52: =IF(ISNUMBER(AJ50),IFERROR(AJ109*1/AJ50*1000,""),"") -> 1569.0561 | AK52: =IF(ISNUMBER(AK50),IFERROR(AK109*4/AK50*1000,""),"") -> 1596.5902 | AL52: =IF(ISNUMBER(AL50),IFERROR(AL109*4/AL50*1000,""),"") -> 1703.4627 | AM52: =IF(ISNUMBER(AM50),IFERROR(AM109*4/AM50*1000,""),"") -> 1640.9017 | AN52: =IF(ISNUMBER(AN50),IFERROR(AN109*4/AN50*1000,""),"") -> 1876.374 | AO52: =IF(ISNUMBER(AO50),IFERROR(AO109*1/AO50*1000,""),"") -> 1573.072 | AP52: =IF(ISNUMBER(AP50),IFERROR(AP109*4/AP50*1000,""),"") -> 1469.8765 | AQ52: =IF(ISNUMBER(AQ50),IFERROR(AQ109*4/AQ50*1000,""),"") -> 1422.85 | AR52: =IF(ISNUMBER(AR50),IFERROR(AR109*4/AR50*1000,""),"") -> 1515.895 | AS52: =IF(ISNUMBER(AS50),IFERROR(AS109*4/AS50*1000,""),"") -> 1916.0467 | AT52: =IF(ISNUMBER(AT50),IFERROR(AT109*1/AT50*1000,""),"") -> 1466.8794 | AU52: =IF(ISNUMBER(AU50),IFERROR(AU109*4/AU50*1000,""),"") -> 1725.9208 | AV52: =IF(ISNUMBER(AV50),IFERROR(AV109*4/AV50*1000,""),"") -> 1834.3953 | AW52: =IF(ISNUMBER(AW50),IFERROR(AW109*4/AW50*1000,""),"") -> 1702.0403 | AX52: =IF(ISNUMBER(AX50),IFERROR(AX109*4/AX50*1000,""),"") -> 1871.3909 | AY52: =IF(ISNUMBER(AY50),IFERROR(AY109*1/AY50*1000,""),"") -> 1638.5855 | AZ52: =IF(ISNUMBER(AZ50),IFERROR(AZ109*4/AZ50*1000,""),"") -> 1434.7664 | BA52: =IF(ISNUMBER(BA50),IFERROR(BA109*4/BA50*1000,""),"") -> 1379.8188 | BB52: =IF(ISNUMBER(BB50),IFERROR(BB109*4/BB50*1000,""),"") -> 1269.6246 | BC52: =IF(ISNUMBER(BC50),IFERROR(BC109*4/BC50*1000,""),"") -> 1487.7084 | BD52: =IF(ISNUMBER(BD50),IFERROR(BD109*1/BD50*1000,""),"") -> 1348.3615 | BE52: =IF(ISNUMBER(BE50),IFERROR(BE109*4/BE50*1000,""),"") -> 1485.8521 | BF52: =IF(ISNUMBER(BF50),IFERROR(BF109*4/BF50*1000,""),"") -> 1790.9303 | BG52: =IF(ISNUMBER(BG50),IFERROR(BG109*4/BG50*1000,""),"") -> 2063.67 | BH52: =IF(ISNUMBER(BH50),IFERROR(BH109*4/BH50*1000,""),"") -> 2383.4098 | BI52: =IF(ISNUMBER(BI50),IFERROR(BI109*1/BI50*1000,""),"") -> 2003.9812 | BJ52: =IF(ISNUMBER(BJ50),IFERROR(BJ109*4/BJ50*1000,""),"") -> 2103.3045 | BK52: =IF(ISNUMBER(BK50),IFERROR(BK109*4/BK50*1000,""),"") -> 2207.4323 | BL52: =IF(ISNUMBER(BL50),IFERROR(BL109*4/BL50*1000,""),"") -> 2242.3623 | BM52: =IF(ISNUMBER(BM50),IFERROR(BM109*4/BM50*1000,""),"") -> 2613.0395 | BN52: =IF(ISNUMBER(BN50),IFERROR(BN109*1/BN50*1000,""),"") -> 2220.9756 | BO52: =IF(ISNUMBER(BO50),IFERROR(BO109*4/BO50*1000,""),"") -> 2202.8789 | BP52: =IF(ISNUMBER(BP50),IFERROR(BP109*4/BP50*1000,""),"") -> 2502.6532 | BQ52: =IF(ISNUMBER(BQ50),IFERROR(BQ109*4/BQ50*1000,""),"") -> 2612.7215 | BR52: =IF(ISNUMBER(BR50),IFERROR(BR109*4/BR50*1000,""),"") -> 3037.7481 | BS52: =IF(ISNUMBER(BS50),IFERROR(BS109*1/BS50*1000,""),"") -> 2548.228 | BT52: =IF(ISNUMBER(BT50),IFERROR(BT109*4/BT50*1000,""),"") -> 2888.262 | BU52: =IF(ISNUMBER(BU50),IFERROR(BU109*4/BU50*1000,""),"") -> 3222.4401 | CL52: 2027E | CM52: =CN52+$CM$51 -> 17000 | CN52: 20000 | CO52: =CN52+$CO$51 -> 24000
CL53: 2028E | CM53: =CN53+$CM$51 -> 16500 | CN53: 19500 | CO53: =CN53+$CO$51 -> 23500
B54: Revenue by geography (billing address of the customer; 10-Q / 10-K revenue note from 2018; Q4 = year − nine months) | CD54: GEOGRAPHY — memo (customer billing address, not user location) | CL54: 2029E | CM54: =CN54+$CM$51 -> 16000 | CN54: 19000 | CO54: =CN54+$CO$51 -> 23000
B55: United States & Canada | AF55: 5442 | AG55: 5982 | AH55: 6325 | AI55: 7978 | AJ55: 25727 | AK55: 6777 | AL55: 7632 | AM55: 8026 | AN55: 9771 | AO55: 32206 | AP55: 8012 | AQ55: 8292 | AR55: 9229 | AS55: 12900 | AT55: 38433 | AU55: 11436 | AV55: 12612 | AW55: 12668 | AX55: 14825 | AY55: 51541 | AZ55: 11780 | BA55: 12186 | BB55: 11966 | BC55: 14218 | BD55: 50150 | BE55: 11449 | BF55: 12404 | BG55: 12908 | BH55: 16127 | BI55: 52888 | BJ55: 13646 | BK55: 14640 | BL55: 15619 | BM55: 19302 | BN55: 63207 | BO55: 16869 | BP55: 18454 | BQ55: 19708 | BR55: 23835 | BS55: 78866 | BT55: 21267 | BU55: 23863 | CF55: =IFERROR((CC55/BX55)^(1/5)-1,"n/m") -> n/m | CG55: =IFERROR((BS55/AT55)^(1/5)-1,"n/m") -> 0.15461476 | CH55: =IFERROR((BS55/U55)^(1/10)-1,"n/m") -> n/m | CI55: =IFERROR((BS55/C55)^(1/16)-1,"n/m") -> n/m | CL55: 2030E | CM55: =CN55+$CM$51 -> 15000 | CN55: 18000 | CO55: =CN55+$CO$51 -> 22000
B56: Europe (incl. Russia and Turkey) | AF56: 3027 | AG56: 3307 | AH56: 3234 | AI56: 4063 | AJ56: 13631 | AK56: 3624 | AL56: 4097 | AM56: 4053 | AN56: 5052 | AO56: 16826 | AP56: 4150 | AQ56: 4249 | AR56: 5055 | AS56: 6895 | AT56: 20349 | AU56: 6384 | AV56: 7220 | AW56: 7018 | AX56: 8435 | AY56: 29057 | AZ56: 6638 | BA56: 6650 | BB56: 5996 | BC56: 7397 | BD56: 26681 | BE56: 6759 | BF56: 7515 | BG56: 7578 | BH56: 9358 | BI56: 31210 | BJ56: 8404 | BK56: 9153 | BL56: 9205 | BM56: 11599 | BN56: 38361 | BO56: 9621 | BP56: 11128 | BQ56: 11566 | BR56: 14254 | BS56: 46569 | BT56: 13240 | BU56: 14009 | CF56: =IFERROR((CC56/BX56)^(1/5)-1,"n/m") -> n/m | CG56: =IFERROR((BS56/AT56)^(1/5)-1,"n/m") -> 0.18007815 | CH56: =IFERROR((BS56/U56)^(1/10)-1,"n/m") -> n/m | CI56: =IFERROR((BS56/C56)^(1/16)-1,"n/m") -> n/m | CL56: 2031E | CM56: =CN56+$CM$51 -> 14000 | CN56: 17000 | CO56: =CN56+$CO$51 -> 21000
B57: Asia-Pacific | AF57: 2475 | AG57: 2772 | AH57: 3007 | AI57: 3479 | AJ57: 11733 | AK57: 3337 | AL57: 3628 | AM57: 3958 | AN57: 4483 | AO57: 15406 | AP57: 3971 | AQ57: 4611 | AR57: 5311 | AS57: 5955 | AT57: 19848 | AU57: 6101 | AV57: 6677 | AW57: 6592 | AX57: 7369 | AY57: 26739 | AZ57: 6722 | BA57: 6960 | BB57: 6797 | BC57: 7281 | BD57: 27760 | BE57: 7292 | BF57: 8551 | BG57: 9790 | BH57: 10521 | BI57: 36154 | BJ57: 10312 | BK57: 10967 | BL57: 11243 | BM57: 12487 | BN57: 45009 | BO57: 11239 | BP57: 12858 | BQ57: 14304 | BR57: 15416 | BS57: 53817 | BT57: 15445 | BU57: 16073 | CF57: =IFERROR((CC57/BX57)^(1/5)-1,"n/m") -> n/m | CG57: =IFERROR((BS57/AT57)^(1/5)-1,"n/m") -> 0.22078883 | CH57: =IFERROR((BS57/U57)^(1/10)-1,"n/m") -> n/m | CI57: =IFERROR((BS57/C57)^(1/16)-1,"n/m") -> n/m | CL57: OPEX (other operating costs excl. D&A, SBC, one-offs; % of revenue) | CM57: -0.02 | CN57: Δ → | CO57: 0.03 | CP57: FY25 39.1%, 1H/26 39.4%, 2026E ~42% (guidance-implied 2H step-up: AI compute, cloud capacity, talent). Assumption: modest operating leverage.
B58: Rest of World (Africa, Latin America, Middle East) | AF58: 1022 | AG58: 1170 | AH58: 1161 | AI58: 1394 | AJ58: 4747 | AK58: 1339 | AL58: 1529 | AM58: 1615 | AN58: 1776 | AO58: 6259 | AP58: 1604 | AQ58: 1535 | AR58: 1875 | AS58: 2321 | AT58: 7335 | AU58: 2250 | AV58: 2568 | AW58: 2732 | AX58: 3042 | AY58: 10592 | AZ58: 2768 | BA58: 3026 | BB58: 2955 | BC58: 3269 | BD58: 12018 | BE58: 3145 | BF58: 3529 | BG58: 3870 | BH58: 4106 | BI58: 14650 | BJ58: 4093 | BK58: 4311 | BL58: 4522 | BM58: 4998 | BN58: 17924 | BO58: 4585 | BP58: 5076 | BQ58: 5664 | BR58: 6389 | BS58: 21714 | BT58: 6359 | BU58: 6856 | CF58: =IFERROR((CC58/BX58)^(1/5)-1,"n/m") -> n/m | CG58: =IFERROR((BS58/AT58)^(1/5)-1,"n/m") -> 0.2424186 | CH58: =IFERROR((BS58/U58)^(1/10)-1,"n/m") -> n/m | CI58: =IFERROR((BS58/C58)^(1/16)-1,"n/m") -> n/m | CL58: 2027E | CM58: =CN58+$CM$57 -> 0.39 | CN58: 0.41 | CO58: =CN58+$CO$57 -> 0.44
B59: Check: Σ geographies vs revenue (should be 0; ±1 where Q4 = year − nine months) | C59: =IF(ISNUMBER(C55),IF(ABS(C55+C56+C57+C58-C109)<=1.1,0,ROUND(C55+C56+C57+C58-C109,1)),"") | D59: =IF(ISNUMBER(D55),IF(ABS(D55+D56+D57+D58-D109)<=1.1,0,ROUND(D55+D56+D57+D58-D109,1)),"") | E59: =IF(ISNUMBER(E55),IF(ABS(E55+E56+E57+E58-E109)<=1.1,0,ROUND(E55+E56+E57+E58-E109,1)),"") | F59: =IF(ISNUMBER(F55),IF(ABS(F55+F56+F57+F58-F109)<=1.1,0,ROUND(F55+F56+F57+F58-F109,1)),"") | G59: =IF(ISNUMBER(G55),IF(ABS(G55+G56+G57+G58-G109)<=1.1,0,ROUND(G55+G56+G57+G58-G109,1)),"") | H59: =IF(ISNUMBER(H55),IF(ABS(H55+H56+H57+H58-H109)<=1.1,0,ROUND(H55+H56+H57+H58-H109,1)),"") | I59: =IF(ISNUMBER(I55),IF(ABS(I55+I56+I57+I58-I109)<=1.1,0,ROUND(I55+I56+I57+I58-I109,1)),"") | J59: =IF(ISNUMBER(J55),IF(ABS(J55+J56+J57+J58-J109)<=1.1,0,ROUND(J55+J56+J57+J58-J109,1)),"") | ... BU59: =IF(ISNUMBER(BU55),IF(ABS(BU55+BU56+BU57+BU58-BU109)<=1.1,0,ROUND(BU55+BU56+BU57+BU58-BU109,1)),"") -> 0 | CL59: 2028E | CM59: =CN59+$CM$57 -> 0.38 | CN59: 0.4 | CO59: =CN59+$CO$57 -> 0.43
B60: United States & Canada % of revenue | C60: =IF(ISNUMBER(C55),IFERROR(C55/C109,""),"") | D60: =IF(ISNUMBER(D55),IFERROR(D55/D109,""),"") | E60: =IF(ISNUMBER(E55),IFERROR(E55/E109,""),"") | F60: =IF(ISNUMBER(F55),IFERROR(F55/F109,""),"") | G60: =IF(ISNUMBER(G55),IFERROR(G55/G109,""),"") | H60: =IF(ISNUMBER(H55),IFERROR(H55/H109,""),"") | I60: =IF(ISNUMBER(I55),IFERROR(I55/I109,""),"") | J60: =IF(ISNUMBER(J55),IFERROR(J55/J109,""),"") | ... BU60: =IF(ISNUMBER(BU55),IFERROR(BU55/BU109,""),"") -> 0.3924771 | CL60: 2029E | CM60: =CN60+$CM$57 -> 0.37 | CN60: 0.39 | CO60: =CN60+$CO$57 -> 0.42
B61: United States & Canada y/y % | D61: =IF(AND(ISNUMBER(D55),ISNUMBER(C55)),IFERROR(D55/C55-1,""),"") | E61: =IF(AND(ISNUMBER(E55),ISNUMBER(D55)),IFERROR(E55/D55-1,""),"") | F61: =IF(AND(ISNUMBER(F55),ISNUMBER(E55)),IFERROR(F55/E55-1,""),"") | K61: =IF(AND(ISNUMBER(K55),ISNUMBER(F55)),IFERROR(K55/F55-1,""),"") | L61: =IF(AND(ISNUMBER(L55),ISNUMBER(G55)),IFERROR(L55/G55-1,""),"") | M61: =IF(AND(ISNUMBER(M55),ISNUMBER(H55)),IFERROR(M55/H55-1,""),"") | N61: =IF(AND(ISNUMBER(N55),ISNUMBER(I55)),IFERROR(N55/I55-1,""),"") | O61: =IF(AND(ISNUMBER(O55),ISNUMBER(J55)),IFERROR(O55/J55-1,""),"") | P61: =IF(AND(ISNUMBER(P55),ISNUMBER(K55)),IFERROR(P55/K55-1,""),"") | Q61: =IF(AND(ISNUMBER(Q55),ISNUMBER(L55)),IFERROR(Q55/L55-1,""),"") | R61: =IF(AND(ISNUMBER(R55),ISNUMBER(M55)),IFERROR(R55/M55-1,""),"") | ... BX61: =IF(AND(ISNUMBER(BX55),ISNUMBER(BS55)),IFERROR(BX55/BS55-1,""),"") | BY61: =IF(AND(ISNUMBER(BY55),ISNUMBER(BX55)),IFERROR(BY55/BX55-1,""),"") | BZ61: =IF(AND(ISNUMBER(BZ55),ISNUMBER(BY55)),IFERROR(BZ55/BY55-1,""),"") | CA61: =IF(AND(ISNUMBER(CA55),ISNUMBER(BZ55)),IFERROR(CA55/BZ55-1,""),"") | CB61: =IF(AND(ISNUMBER(CB55),ISNUMBER(CA55)),IFERROR(CB55/CA55-1,""),"") | CC61: =IF(AND(ISNUMBER(CC55),ISNUMBER(CB55)),IFERROR(CC55/CB55-1,""),"") | CL61: 2030E | CM61: =CN61+$CM$57 -> 0.365 | CN61: 0.385 | CO61: =CN61+$CO$57 -> 0.415
CL62: 2031E | CM62: =CN62+$CM$57 -> 0.36 | CN62: 0.38 | CO62: =CN62+$CO$57 -> 0.41
B63: Future acquisitions (M&A lever — technology and talent deals; no acquired revenue assumed) | CD63: M&A LEVER — spend → goodwill & intangibles; acquired intangibles amortised (inside D&A); mid-year convention | CL63: CAPEX (purchases of property and equipment % of revenue) | CM63: -0.04 | CN63: Δ → | CO63: 0.05 | CP63: FY25 34.7% ($69.7bn); 2026E ~53% (guidance mid-point $137.5bn incl. finance leases); 2019–21 16–21%. AI data-center build-out (Hyperion, Prometheus). Assumption: intensity fades toward ~23%, above the pre-AI level.
B64: Acquisition spend (USDm, scenario) | BX64: 0 | BY64: =MAX(0,CHOOSE(MATCH($CD$2,{"Bull","Base","Bear"},0),$CM$70,$CN$70,$CO$70)) -> 1000 | BZ64: =MAX(0,CHOOSE(MATCH($CD$2,{"Bull","Base","Bear"},0),$CM$71,$CN$71,$CO$71)) -> 1000 | CA64: =MAX(0,CHOOSE(MATCH($CD$2,{"Bull","Base","Bear"},0),$CM$72,$CN$72,$CO$72)) -> 1000 | CB64: =MAX(0,CHOOSE(MATCH($CD$2,{"Bull","Base","Bear"},0),$CM$73,$CN$73,$CO$73)) -> 1000 | CC64: =MAX(0,CHOOSE(MATCH($CD$2,{"Bull","Base","Bear"},0),$CM$74,$CN$74,$CO$74)) -> 1000 | CD64: Scenario lever MNA (Base $1bn p.a.). Funded from cash / debt (debt schedule). | CL64: 2027E | CM64: =CN64+$CM$63 -> 0.42 | CN64: 0.46 | CO64: =CN64+$CO$63 -> 0.51
B65: Acquired intangibles % of spend (rest goodwill) | BX65: 0 | BY65: 0.25 | BZ65: 0.25 | CA65: 0.25 | CB65: 0.25 | CC65: 0.25 | CD65: Assumption (Meta's purchase-price allocations are mostly goodwill: WhatsApp 2014, Oculus 2014, Giphy, Within, Kustomer). | CL65: 2028E | CM65: =CN65+$CM$63 -> 0.34 | CN65: 0.38 | CO65: =CN65+$CO$63 -> 0.43
B66: Intangible amortization life (years) | BX66: 0 | BY66: 5 | BZ66: 5 | CA66: 5 | CB66: 5 | CC66: 5 | CL66: 2029E | CM66: =CN66+$CM$63 -> 0.27 | CN66: 0.31 | CO66: =CN66+$CO$63 -> 0.36
B67: Cumulative acquired intangibles (gross) | BX67: 0 | BY67: =BX67+BY64*BY65 -> 250 | BZ67: =BY67+BZ64*BZ65 -> 500 | CA67: =BZ67+CA64*CA65 -> 750 | CB67: =CA67+CB64*CB65 -> 1000 | CC67: =CB67+CC64*CC65 -> 1250 | CL67: 2030E | CM67: =CN67+$CM$63 -> 0.22 | CN67: 0.26 | CO67: =CN67+$CO$63 -> 0.31
B68: Amortization of future-acquisition intangibles (inside D&A) | BX68: 0 | BY68: =IFERROR((BX67+0.5*BY64*BY65)/BY66,0) -> 25 | BZ68: =IFERROR((BY67+0.5*BZ64*BZ65)/BZ66,0) -> 75 | CA68: =IFERROR((BZ67+0.5*CA64*CA65)/CA66,0) -> 125 | CB68: =IFERROR((CA67+0.5*CB64*CB65)/CB66,0) -> 175 | CC68: =IFERROR((CB67+0.5*CC64*CC65)/CC66,0) -> 225 | CL68: 2031E | CM68: =CN68+$CM$63 -> 0.19 | CN68: 0.23 | CO68: =CN68+$CO$63 -> 0.28
CL69: MNA (acquisitions, $m) | CM69: 2000 | CN69: Δ → | CO69: -1000 | CP69: Acquisitions of businesses and intangible assets: FY25 $0.1bn, FY24 $0.3bn, FY22 $1.3bn (Within, Kustomer era). Base $1bn p.a. (assumption).
B70: Group total — revenue (build) → 2026 guidance calibration (Q3/26E revenue; FY26 total expenses) | CD70: GROUP TOTAL (CONSOLIDATED) — modelling logic | CL70: 2027E | CM70: =MAX(0,CN70+$CM$69) -> 3000 | CN70: 1000 | CO70: =MAX(0,CN70+$CO$69) -> 0
B71: Revenue (build) | C71: =IF(ISNUMBER(C11),C11+C28,C109) -> 777 | D71: =IF(ISNUMBER(D11),D11+D28,D109) -> 1974 | E71: =IF(ISNUMBER(E11),E11+E28,E109) -> 3711 | F71: =IF(ISNUMBER(F11),F11+F28,F109) -> 5089 | G71: =IF(ISNUMBER(G11),G11+G28,G109) -> 1458 | H71: =IF(ISNUMBER(H11),H11+H28,H109) -> 1813 | I71: =IF(ISNUMBER(I11),I11+I28,I109) -> 2016 | J71: =IF(ISNUMBER(J11),J11+J28,J109) -> 2585 | ... BU71: =IF(ISNUMBER(BU11),BU11+BU28,BU109) -> 60801 | BV71: =BV11+BV28 -> 62500 | BW71: =BW11+BW28 -> 72988.412 | BX71: =BX11+BX28 -> 252600.41 | BY71: =BY11+BY28 -> 300830.67 | BZ71: =BZ11+BZ28 -> 348341.99 | CA71: =CA11+CA28 -> 395867.43 | CB71: =CB11+CB28 -> 441368.57 | CC71: =CC11+CC28 -> 487137.7 | CD71: Advertising + non-advertising revenue. | CF71: =IFERROR((CC71/BX71)^(1/5)-1,"n/m") -> 0.1403641 | CG71: =IFERROR((BS71/AT71)^(1/5)-1,"n/m") -> 0.18511415 | CH71: =IFERROR((BS71/U71)^(1/10)-1,"n/m") -> 0.27338308 | CI71: =IFERROR((BS71/C71)^(1/16)-1,"n/m") -> 0.41512189 | CL71: 2028E | CM71: =MAX(0,CN71+$CM$69) -> 3000 | CN71: 1000 | CO71: =MAX(0,CN71+$CO$69) -> 0
B72: Revenue y/y % | D72: =IF(AND(ISNUMBER(D71),ISNUMBER(C71)),IFERROR(D71/C71-1,""),"") -> 1.5405405 | E72: =IF(AND(ISNUMBER(E71),ISNUMBER(D71)),IFERROR(E71/D71-1,""),"") -> 0.87993921 | F72: =IF(AND(ISNUMBER(F71),ISNUMBER(E71)),IFERROR(F71/E71-1,""),"") -> 0.37132848 | K72: =IF(AND(ISNUMBER(K71),ISNUMBER(F71)),IFERROR(K71/F71-1,""),"") -> 0.54686579 | L72: =IF(AND(ISNUMBER(L71),ISNUMBER(G71)),IFERROR(L71/G71-1,""),"") -> 0.71604938 | M72: =IF(AND(ISNUMBER(M71),ISNUMBER(H71)),IFERROR(M71/H71-1,""),"") -> 0.60507446 | N72: =IF(AND(ISNUMBER(N71),ISNUMBER(I71)),IFERROR(N71/I71-1,""),"") -> 0.58878968 | O72: =IF(AND(ISNUMBER(O71),ISNUMBER(J71)),IFERROR(O71/J71-1,""),"") -> 0.48974855 | P72: =IF(AND(ISNUMBER(P71),ISNUMBER(K71)),IFERROR(P71/K71-1,""),"") -> 0.5835874 | Q72: =IF(AND(ISNUMBER(Q71),ISNUMBER(L71)),IFERROR(Q71/L71-1,""),"") -> 0.41606715 | R72: =IF(AND(ISNUMBER(R71),ISNUMBER(M71)),IFERROR(R71/M71-1,""),"") -> 0.38900344 | ... BX72: =IF(AND(ISNUMBER(BX71),ISNUMBER(BS71)),IFERROR(BX71/BS71-1,""),"") -> 0.25693108 | BY72: =IF(AND(ISNUMBER(BY71),ISNUMBER(BX71)),IFERROR(BY71/BX71-1,""),"") -> 0.190935 | BZ72: =IF(AND(ISNUMBER(BZ71),ISNUMBER(BY71)),IFERROR(BZ71/BY71-1,""),"") -> 0.15793377 | CA72: =IF(AND(ISNUMBER(CA71),ISNUMBER(BZ71)),IFERROR(CA71/BZ71-1,""),"") -> 0.13643327 | CB72: =IF(AND(ISNUMBER(CB71),ISNUMBER(CA71)),IFERROR(CB71/CA71-1,""),"") -> 0.11494034 | CC72: =IF(AND(ISNUMBER(CC71),ISNUMBER(CB71)),IFERROR(CC71/CB71-1,""),"") -> 0.10369821 | CL72: 2029E | CM72: =MAX(0,CN72+$CM$69) -> 3000 | CN72: 1000 | CO72: =MAX(0,CN72+$CO$69) -> 0
B73: Check: build vs consolidated revenue (should be 0) | C73: =IF(ISNUMBER(C71),ROUND(C71-C109,1),"") -> 0 | D73: =IF(ISNUMBER(D71),ROUND(D71-D109,1),"") -> 0 | E73: =IF(ISNUMBER(E71),ROUND(E71-E109,1),"") -> 0 | F73: =IF(ISNUMBER(F71),ROUND(F71-F109,1),"") -> 0 | G73: =IF(ISNUMBER(G71),ROUND(G71-G109,1),"") -> 0 | H73: =IF(ISNUMBER(H71),ROUND(H71-H109,1),"") -> 0 | I73: =IF(ISNUMBER(I71),ROUND(I71-I109,1),"") -> 0 | J73: =IF(ISNUMBER(J71),ROUND(J71-J109,1),"") -> 0 | ... CC73: =IF(ISNUMBER(CC71),ROUND(CC71-CC109,1),"") -> 0 | CL73: 2030E | CM73: =MAX(0,CN73+$CM$69) -> 3000 | CN73: 1000 | CO73: =MAX(0,CN73+$CO$69) -> 0
B74: Memo: Q3/26 revenue guidance (scenario end-point: high / mid / low of $61–64bn) | BV74: =CHOOSE(MATCH($CD$2,{"Bull","Base","Bear"},0),$CM$12,$CN$12,$CO$12) -> 62500 | CD74: Company Q3/26 revenue guidance $61–64bn (Q2-26 release, 29-Jul-2026). Drives the price-per-ad calibration. | CL74: 2031E | CM74: =MAX(0,CN74+$CM$69) -> 3000 | CN74: 1000 | CO74: =MAX(0,CN74+$CO$69) -> 0
B75: Q3/26E revenue before calibration (helper) | BV75: =BQ11*(1+BV13)*(1+BV16)+BV24+BV26 -> 65639.751
B76: Q3/26E revenue sensitivity to +1.00 of price-per-ad growth (helper) | BV76: =BQ11*(1+BV13) -> 57093.48
B77: Guidance calibration: Δ price-per-ad growth (solved in Q3/26E; carried into Q4/26E) | BV77: =(BV74-BV75)/BV76 -> -0.054993153 | BW77: =$BV$77 -> -0.054993153 | CD77: Closed-form linear solve: Δ = (guidance end-point − revenue before calibration) ÷ sensitivity. No guidance for Q4: the Q3 Δ is carried forward.
B78: Check: Q3/26E revenue vs guidance end-point (should be 0) | BV78: =ROUND(BV109-BV74,1) -> 0
B79: Memo: FY26 total expenses guidance (scenario end-point: low / mid / high of $165–169bn) | BX79: =CHOOSE(MATCH($CD$2,{"Bull","Base","Bear"},0),$CM$13,$CN$13,$CO$13) -> 167000 | CD79: Company FY26 total expenses guidance $165–169bn (Q2-26 release; low end raised from $162bn for the Q2 legal charges). Drives the 2H cost calibration.
B80: 2H/26E total costs and expenses required (guidance − 1H/26 actual) | BX80: =BX79-SUM(BT114:BU114) -> 91535
B81: Q3 share of 2H costs (2H/25 pattern: Q3/25 ÷ (Q3/25 + Q4/25)) | BX81: =BQ114/(BQ114+BR114) -> 0.46628198
B82: Total costs and expenses target (Q3/26E, Q4/26E) | BV82: =$BX$80*$BX$81 -> 42681.121 | BW82: =$BX$80*(1-$BX$81) -> 48853.879 | CD82: Other operating costs (cash) are the balancing driver: target − D&A − share-based compensation − one-off items.
B83: Check: FY26 total costs and expenses vs guidance end-point (should be 0) | BX83: =ROUND(BX114-BX79,1) -> 0
B84: Memo: FY26 income from operations − FY25 ("above 2025 operating income" — information, should be > 0) | BX84: =BX116-BS116 -> 2324.4115
B85: Memo: FY26 capital expenditures incl. principal payments on finance leases — guidance mid-point ($130–145bn) | BX85: =$CN$20 -> 137500
B86: Model − guidance (information) | BX86: =BX246-BX85 -> 0
B88: Cost drivers — D&A (capex-driven), share-based compensation, other operating costs, one-off items; interest & other | CD88: COST DRIVERS — total costs = D&A + share-based compensation + other operating costs (cash) + company-quantified one-offs
B89: Depreciation & amortization (cash-flow statement) | C89: 78 | D89: 139 | E89: 323 | F89: 649 | G89: 241 | H89: 230 | I89: 274 | J89: 274 | K89: 1011 | L89: 264 | M89: 257 | N89: 289 | O89: 433 | P89: 1243 | Q89: 457 | R89: 459 | S89: 486 | T89: 543 | U89: 1945 | V89: 552 | W89: 585 | X89: 591 | Y89: 614 | Z89: 2342 | AA89: 671 | AB89: 728 | AC89: 773 | AD89: 853 | AE89: 3025 | AF89: 949 | AG89: 1034 | AH89: 1107 | AI89: 1225 | AJ89: 4315 | AK89: 1355 | AL89: 1502 | AM89: 1416 | AN89: 1468 | AO89: 5741 | AP89: 1597 | AQ89: 1704 | AR89: 1698 | AS89: 1863 | AT89: 6862 | AU89: 1972 | AV89: 1985 | AW89: 1995 | AX89: 2014 | AY89: 7967 | AZ89: 2156 | BA89: 1979 | BB89: 2175 | BC89: 2376 | BD89: 8686 | BE89: 2524 | BF89: 2623 | BG89: 2858 | BH89: 3172 | BI89: 11178 | BJ89: 3374 | BK89: 3637 | BL89: 4027 | BM89: 4460 | BN89: 15498 | BO89: 3900 | BP89: 4342 | BQ89: 4963 | BR89: 5411 | BS89: 18616 | BT89: 5999 | BU89: 6356 | BV89: =BU89*(1+$CN$17) -> 6800.92 | BW89: =BV89*(1+$CN$17) -> 7276.9844 | BX89: =SUM(BT89:BW89) -> 26432.904 | BY89: =(BX280+0.5*BY246)*BY90+N(BY68) -> 40661.106 | BZ89: =(BY280+0.5*BZ246)*BZ90+N(BZ68) -> 51572.498 | CA89: =(BZ280+0.5*CA246)*CA90+N(CA68) -> 63168.691 | CB89: =(CA280+0.5*CB246)*CB90+N(CB68) -> 70083.464 | CC89: =(CB280+0.5*CC246)*CC90+N(CC68) -> 75594.846 | CD89: Q3/Q4-26E: prior quarter × (1 + q/q growth point estimate). 2027E+: (opening net PP&E + ½ × capex incl. finance leases) × depreciation rate + acquired-intangible amortization. | CF89: =IFERROR((CC89/BX89)^(1/5)-1,"n/m") -> 0.23387016 | CG89: =IFERROR((BS89/AT89)^(1/5)-1,"n/m") -> 0.22091978 | CH89: =IFERROR((BS89/U89)^(1/10)-1,"n/m") -> 0.25342016 | CI89: =IFERROR((BS89/C89)^(1/16)-1,"n/m") -> 0.40803025
B90: D&A rate — D&A ÷ (opening net PP&E + ½ capex incl. finance leases) (annual) | F90: =IFERROR(F89/(E280+0.5*F246),"") -> 0.28521204 | K90: =IFERROR(K89/(F280+0.5*K246),"") -> 0.30941086 | P90: =IFERROR(P89/(K280+0.5*P246),"") -> 0.31717275 | U90: =IFERROR(U89/(P280+0.5*U246),"") -> 0.36781392 | Z90: =IFERROR(Z89/(U280+0.5*Z246),"") -> 0.28954689 | AE90: =IFERROR(AE89/(Z280+0.5*AE246),"") -> 0.2529793 | AJ90: =IFERROR(AJ89/(AE280+0.5*AJ246),"") -> 0.20867084 | AO90: =IFERROR(AO89/(AJ280+0.5*AO246),"") -> 0.17659182 | AT90: =IFERROR(AT89/(AO280+0.5*AT246),"") -> 0.15890696 | AY90: =IFERROR(AY89/(AT280+0.5*AY246),"") -> 0.14418605 | BD90: =IFERROR(BD89/(AY280+0.5*BD246),"") -> 0.11765343 | BI90: =IFERROR(BI89/(BD280+0.5*BI246),"") -> 0.119462 | BN90: =IFERROR(BN89/(BI280+0.5*BN246),"") -> 0.13337407 | BS90: =IFERROR(BS89/(BN280+0.5*BS246),"") -> 0.11823173 | BY90: 0.11 | BZ90: 0.11 | CA90: 0.115 | CB90: 0.115 | CC90: 0.115 | CD90: FY2025 11.8% (D&A $18.6bn on opening net PP&E $121.3bn + ½ × $72.2bn capex incl. finance leases); servers depreciated over 5.5 years from 2025, buildings and network over longer lives; 2026E implied ~10.8%. 2027E+ input (assumption).
B91: Share-based compensation (cash-flow statement) | C91: 27 | D91: 20 | E91: 217 | F91: 1572 | G91: 170 | H91: 224 | I91: 239 | J91: 273 | K91: 906 | L91: 274 | M91: 314 | N91: 353 | O91: 845 | P91: 1786 | Q91: 694 | R91: 763 | S91: 757 | T91: 746 | U91: 2960 | V91: 747 | W91: 805 | X91: 819 | Y91: 831 | Z91: 3218 | AA91: 867 | AB91: 1032 | AC91: 1010 | AD91: 814 | AE91: 3723 | AF91: 955 | AG91: 1186 | AH91: 1040 | AI91: 971 | AJ91: 4152 | AK91: 1010 | AL91: 1303 | AM91: 1249 | AN91: 1273 | AO91: 4836 | AP91: 1335 | AQ91: 1695 | AR91: 1722 | AS91: 1784 | AT91: 6536 | AU91: 1830 | AV91: 2548 | AW91: 2379 | AX91: 2406 | AY91: 9164 | AZ91: 2498 | BA91: 3351 | BB91: 3134 | BC91: 3008 | BD91: 11992 | BE91: 3051 | BF91: 4060 | BG91: 3492 | BH91: 3424 | BI91: 14027 | BJ91: 3562 | BK91: 4616 | BL91: 4250 | BM91: 4262 | BN91: 16690 | BO91: 4147 | BP91: 4834 | BQ91: 5555 | BR91: 5890 | BS91: 20427 | BT91: 6032 | BU91: 7658 | BV91: =$CN$18 -> 7658 | BW91: =$CN$18 -> 7658 | BX91: =SUM(BT91:BW91) -> 29006 | BY91: =BY109*BY92 -> 34595.527 | BZ91: =BZ109*BZ92 -> 38317.619 | CA91: =CA109*CA92 -> 43545.417 | CB91: =CB109*CB92 -> 46343.7 | CC91: =CC109*CC92 -> 51149.458 | CD91: Q3/Q4-26E: point estimate (Q2/26 level). 2027E+: % of revenue. | CF91: =IFERROR((CC91/BX91)^(1/5)-1,"n/m") -> 0.1201357 | CG91: =IFERROR((BS91/AT91)^(1/5)-1,"n/m") -> 0.25596781 | CH91: =IFERROR((BS91/U91)^(1/10)-1,"n/m") -> 0.21308515 | CI91: =IFERROR((BS91/C91)^(1/16)-1,"n/m") -> 0.51330878
B92: Share-based compensation % of revenue | C92: =IF(AND(ISNUMBER(C91),ISNUMBER(C109)),IFERROR(C91/C109,""),"") -> 0.034749035 | D92: =IF(AND(ISNUMBER(D91),ISNUMBER(D109)),IFERROR(D91/D109,""),"") -> 0.010131712 | E92: =IF(AND(ISNUMBER(E91),ISNUMBER(E109)),IFERROR(E91/E109,""),"") -> 0.058474805 | F92: =IF(AND(ISNUMBER(F91),ISNUMBER(F109)),IFERROR(F91/F109,""),"") -> 0.30890155 | G92: =IF(AND(ISNUMBER(G91),ISNUMBER(G109)),IFERROR(G91/G109,""),"") -> 0.11659808 | H92: =IF(AND(ISNUMBER(H91),ISNUMBER(H109)),IFERROR(H91/H109,""),"") -> 0.12355212 | I92: =IF(AND(ISNUMBER(I91),ISNUMBER(I109)),IFERROR(I91/I109,""),"") -> 0.11855159 | J92: =IF(AND(ISNUMBER(J91),ISNUMBER(J109)),IFERROR(J91/J109,""),"") -> 0.10560928 | ... BX92: =IF(AND(ISNUMBER(BX91),ISNUMBER(BX109)),IFERROR(BX91/BX109,""),"") -> 0.11482958 | BY92: 0.115 | BZ92: 0.11 | CA92: 0.11 | CB92: 0.105 | CC92: 0.105 | CF92: =IFERROR(AVERAGE(BY92,BZ92,CA92,CB92,CC92),"n/m") -> 0.109 | CG92: =IFERROR(AVERAGE(AY92,BD92,BI92,BN92,BS92),"n/m") -> 0.097525754 | CH92: =IFERROR(AVERAGE(Z92,AE92,AJ92,AO92,AT92,AY92,BD92,BI92,BN92,BS92),"n/m") -> 0.091443613 | CI92: =IFERROR(AVERAGE(C92,D92,E92,F92,K92,P92,U92,Z92,AE92,AJ92,AO92,AT92,AY92,BD92,BI92,BN92,BS92),"n/m") -> 0.10295054
B93: One-off: legal accruals and settlements (company-quantified; G&A) | C93: 0 | D93: 0 | E93: 0 | F93: 0 | G93: 0 | H93: 0 | I93: 0 | J93: 0 | K93: 0 | L93: 0 | M93: 0 | N93: 0 | O93: 0 | P93: 0 | Q93: 0 | R93: 0 | S93: 0 | T93: 0 | U93: 0 | V93: 0 | W93: 0 | X93: 0 | Y93: 0 | Z93: 0 | AA93: 0 | AB93: 0 | AC93: 0 | AD93: 0 | AE93: 0 | AF93: 0 | AG93: 0 | AH93: 0 | AI93: 0 | AJ93: 0 | AK93: 3000 | AL93: 2000 | AM93: 0 | AN93: 0 | AO93: 5000 | AP93: 0 | AQ93: 0 | AR93: 0 | AS93: 0 | AT93: 0 | AU93: 0 | AV93: 0 | AW93: 0 | AX93: 0 | AY93: 0 | AZ93: 0 | BA93: 0 | BB93: 0 | BC93: 0 | BD93: 0 | BE93: 0 | BF93: 1870 | BG93: 0 | BH93: 0 | BI93: 1870 | BJ93: 0 | BK93: 0 | BL93: 0 | BM93: -1550 | BN93: -1550 | BO93: 0 | BP93: 0 | BQ93: 0 | BR93: 0 | BS93: 0 | BT93: 0 | BU93: 2400 | BV93: =0 -> 0 | BW93: =0 -> 0 | BX93: =SUM(BT93:BW93) -> 2400 | BY93: =0 -> 0 | BZ93: =0 -> 0 | CA93: =0 -> 0 | CB93: =0 -> 0 | CC93: =0 -> 0 | CD93: Only items the company quantified in its releases (FTC 2019; Q2-23; Q4-24 release; Q2-26). The Q2-24 Texas settlement was named but not quantified (left in).
B94: One-off: restructuring and severance (company-quantified) | C94: 0 | D94: 0 | E94: 0 | F94: 0 | G94: 0 | H94: 0 | I94: 0 | J94: 0 | K94: 0 | L94: 0 | M94: 0 | N94: 0 | O94: 0 | P94: 0 | Q94: 0 | R94: 0 | S94: 0 | T94: 0 | U94: 0 | V94: 0 | W94: 0 | X94: 0 | Y94: 0 | Z94: 0 | AA94: 0 | AB94: 0 | AC94: 0 | AD94: 0 | AE94: 0 | AF94: 0 | AG94: 0 | AH94: 0 | AI94: 0 | AJ94: 0 | AK94: 0 | AL94: 0 | AM94: 0 | AN94: 0 | AO94: 0 | AP94: 0 | AQ94: 0 | AR94: 0 | AS94: 0 | AT94: 0 | AU94: 0 | AV94: 0 | AW94: 0 | AX94: 0 | AY94: 0 | AZ94: 0 | BA94: 0 | BB94: 413 | BC94: 4198 | BD94: 4611 | BE94: 1144 | BF94: 780 | BG94: 380 | BH94: 1150 | BI94: 3454 | BJ94: 0 | BK94: 0 | BL94: 0 | BM94: 0 | BN94: 0 | BO94: 0 | BP94: 0 | BQ94: 0 | BR94: 0 | BS94: 0 | BT94: 0 | BU94: 1180 | BV94: =0 -> 0 | BW94: =0 -> 0 | BX94: =SUM(BT94:BW94) -> 1180 | BY94: =0 -> 0 | BZ94: =0 -> 0 | CA94: =0 -> 0 | CB94: =0 -> 0 | CC94: =0 -> 0 | CD94: Q3-22 lease impairment; Q4-22–Q4-23 facilities consolidation, layoffs and data-center restructuring; Q2-26 severance (May-2026 headcount reduction). Forecast: none assumed.
B95: Other operating costs (cash; excl. D&A, share-based compensation and one-offs) | C95: =IF(ISNUMBER(C89),C114-C89-C91-N(C93)-N(C94),"") -> 410 | D95: =IF(ISNUMBER(D89),D114-D89-D91-N(D93)-N(D94),"") -> 783 | E95: =IF(ISNUMBER(E89),E114-E89-E91-N(E93)-N(E94),"") -> 1415 | F95: =IF(ISNUMBER(F89),F114-F89-F91-N(F93)-N(F94),"") -> 2330 | G95: =IF(ISNUMBER(G89),G114-G89-G91-N(G93)-N(G94),"") -> 674 | H95: =IF(ISNUMBER(H89),H114-H89-H91-N(H93)-N(H94),"") -> 797 | I95: =IF(ISNUMBER(I89),I114-I89-I91-N(I93)-N(I94),"") -> 767 | J95: =IF(ISNUMBER(J89),J114-J89-J91-N(J93)-N(J94),"") -> 905 | ... BU95: =IF(ISNUMBER(BU89),BU114-BU89-BU91-N(BU93)-N(BU94),"") -> 24432 | BV95: =BV82-BV89-BV91-BV93-BV94 -> 28222.201 | BW95: =BW82-BW89-BW91-BW93-BW94 -> 33918.894 | BX95: =SUM(BT95:BW95) -> 107981.1 | BY95: =BY109*BY96 -> 123340.58 | BZ95: =BZ109*BZ96 -> 139336.8 | CA95: =CA109*CA96 -> 154388.3 | CB95: =CB109*CB96 -> 169926.9 | CC95: =CC109*CC96 -> 185112.33 | CD95: Q3/Q4-26E: balancing driver to the FY26 expense guidance. 2027E+: % of revenue (scenario lever): AI compute (third-party cloud, data-center operations), people, content, marketing. | CF95: =IFERROR((CC95/BX95)^(1/5)-1,"n/m") -> 0.11382644 | CG95: =IFERROR((BS95/AT95)^(1/5)-1,"n/m") -> 0.14538255 | CH95: =IFERROR((BS95/U95)^(1/10)-1,"n/m") -> 0.27740938 | CI95: =IFERROR((BS95/C95)^(1/16)-1,"n/m") -> 0.38893251
B96: Other operating costs % of revenue | C96: =IF(AND(ISNUMBER(C95),ISNUMBER(C109)),IFERROR(C95/C109,""),"") -> 0.52767053 | D96: =IF(AND(ISNUMBER(D95),ISNUMBER(D109)),IFERROR(D95/D109,""),"") -> 0.39665653 | E96: =IF(AND(ISNUMBER(E95),ISNUMBER(E109)),IFERROR(E95/E109,""),"") -> 0.38129884 | F96: =IF(AND(ISNUMBER(F95),ISNUMBER(F109)),IFERROR(F95/F109,""),"") -> 0.45785027 | G96: =IF(AND(ISNUMBER(G95),ISNUMBER(G109)),IFERROR(G95/G109,""),"") -> 0.46227709 | H96: =IF(AND(ISNUMBER(H95),ISNUMBER(H109)),IFERROR(H95/H109,""),"") -> 0.43960287 | I96: =IF(AND(ISNUMBER(I95),ISNUMBER(I109)),IFERROR(I95/I109,""),"") -> 0.38045635 | J96: =IF(AND(ISNUMBER(J95),ISNUMBER(J109)),IFERROR(J95/J109,""),"") -> 0.35009671 | ... BX96: =IF(AND(ISNUMBER(BX95),ISNUMBER(BX109)),IFERROR(BX95/BX109,""),"") -> 0.42747791 | BY96: =CHOOSE(MATCH($CD$2,{"Bull","Base","Bear"},0),$CM$58,$CN$58,$CO$58) -> 0.41 | BZ96: =CHOOSE(MATCH($CD$2,{"Bull","Base","Bear"},0),$CM$59,$CN$59,$CO$59) -> 0.4 | CA96: =CHOOSE(MATCH($CD$2,{"Bull","Base","Bear"},0),$CM$60,$CN$60,$CO$60) -> 0.39 | CB96: =CHOOSE(MATCH($CD$2,{"Bull","Base","Bear"},0),$CM$61,$CN$61,$CO$61) -> 0.385 | CC96: =CHOOSE(MATCH($CD$2,{"Bull","Base","Bear"},0),$CM$62,$CN$62,$CO$62) -> 0.38 | CF96: =IFERROR(AVERAGE(BY96,BZ96,CA96,CB96,CC96),"n/m") -> 0.393 | CG96: =IFERROR(AVERAGE(AY96,BD96,BI96,BN96,BS96),"n/m") -> 0.44073522 | CH96: =IFERROR(AVERAGE(Z96,AE96,AJ96,AO96,AT96,AY96,BD96,BI96,BN96,BS96),"n/m") -> 0.41965984 | CI96: =IFERROR(AVERAGE(C96,D96,E96,F96,K96,P96,U96,Z96,AE96,AJ96,AO96,AT96,AY96,BD96,BI96,BN96,BS96),"n/m") -> 0.41740864
B97: y/y % | D97: =IF(AND(ISNUMBER(D95),ISNUMBER(C95)),IFERROR(D95/C95-1,""),"") -> 0.9097561 | E97: =IF(AND(ISNUMBER(E95),ISNUMBER(D95)),IFERROR(E95/D95-1,""),"") -> 0.80715198 | F97: =IF(AND(ISNUMBER(F95),ISNUMBER(E95)),IFERROR(F95/E95-1,""),"") -> 0.64664311 | K97: =IF(AND(ISNUMBER(K95),ISNUMBER(F95)),IFERROR(K95/F95-1,""),"") -> 0.35236052 | L97: =IF(AND(ISNUMBER(L95),ISNUMBER(G95)),IFERROR(L95/G95-1,""),"") -> 0.3189911 | M97: =IF(AND(ISNUMBER(M95),ISNUMBER(H95)),IFERROR(M95/H95-1,""),"") -> 0.19071518 | N97: =IF(AND(ISNUMBER(N95),ISNUMBER(I95)),IFERROR(N95/I95-1,""),"") -> 0.51760104 | O97: =IF(AND(ISNUMBER(O95),ISNUMBER(J95)),IFERROR(O95/J95-1,""),"") -> 0.59116022 | P97: =IF(AND(ISNUMBER(P95),ISNUMBER(K95)),IFERROR(P95/K95-1,""),"") -> 0.41002856 | Q97: =IF(AND(ISNUMBER(Q95),ISNUMBER(L95)),IFERROR(Q95/L95-1,""),"") -> 0.64116985 | R97: =IF(AND(ISNUMBER(R95),ISNUMBER(M95)),IFERROR(R95/M95-1,""),"") -> 0.63013699 | ... BX97: =IF(AND(ISNUMBER(BX95),ISNUMBER(BS95)),IFERROR(BX95/BS95-1,""),"") -> 0.37298429 | BY97: =IF(AND(ISNUMBER(BY95),ISNUMBER(BX95)),IFERROR(BY95/BX95-1,""),"") -> 0.1422423 | BZ97: =IF(AND(ISNUMBER(BZ95),ISNUMBER(BY95)),IFERROR(BZ95/BY95-1,""),"") -> 0.12969149 | CA97: =IF(AND(ISNUMBER(CA95),ISNUMBER(BZ95)),IFERROR(CA95/BZ95-1,""),"") -> 0.10802244 | CB97: =IF(AND(ISNUMBER(CB95),ISNUMBER(CA95)),IFERROR(CB95/CA95-1,""),"") -> 0.10064623 | CC97: =IF(AND(ISNUMBER(CC95),ISNUMBER(CB95)),IFERROR(CC95/CB95-1,""),"") -> 0.089364468
B98: Cost lines — share of total costs excluding one-offs (forecast presentation; one-offs booked in G&A):
B99: Cost of revenue % | C99: =IFERROR(C110/(C114-N(C93)-N(C94)),"") -> 0.43300971 | D99: =IFERROR(D110/(D114-N(D93)-N(D94)),"") -> 0.52335456 | E99: =IFERROR(E110/(E114-N(E93)-N(E94)),"") -> 0.4398977 | F99: =IFERROR(F110/(F114-N(F93)-N(F94)),"") -> 0.29971435 | G99: =IFERROR(G110/(G114-N(G93)-N(G94)),"") -> 0.38064516 | H99: =IFERROR(H110/(H114-N(H93)-N(H94)),"") -> 0.37170264 | I99: =IFERROR(I110/(I114-N(I93)-N(I94)),"") -> 0.39609375 | J99: =IFERROR(J110/(J114-N(J93)-N(J94)),"") -> 0.33815427 | ... BU99: =IFERROR(BU110/(BU114-N(BU93)-N(BU94)),"") -> 0.29469906 | BV99: =IFERROR(SUM(BT110:BU110)/(SUM(BT114:BU114)-SUM(BT93:BU93)-SUM(BT94:BU94)),0) -> 0.29975656 | BW99: =IFERROR(SUM(BT110:BU110)/(SUM(BT114:BU114)-SUM(BT93:BU93)-SUM(BT94:BU94)),0) -> 0.29975656 | BY99: =$BW$99 -> 0.29975656 | BZ99: =$BW$99 -> 0.29975656 | CA99: =$BW$99 -> 0.29975656 | CB99: =$BW$99 -> 0.29975656 | CC99: =$BW$99 -> 0.29975656 | CD99: Q3/Q4-26E: 1H/26 mix (G&A excluding the Q2 legal charges; the Q2 severance spread across the lines is not separable). 2027E+: held.
B100: Research & development % | C100: =IFERROR(C111/(C114-N(C93)-N(C94)),"") -> 0.16893204 | D100: =IFERROR(D111/(D114-N(D93)-N(D94)),"") -> 0.15286624 | E100: =IFERROR(E111/(E114-N(E93)-N(E94)),"") -> 0.19846547 | F100: =IFERROR(F111/(F114-N(F93)-N(F94)),"") -> 0.30740497 | G100: =IFERROR(G111/(G114-N(G93)-N(G94)),"") -> 0.27004608 | H100: =IFERROR(H111/(H114-N(H93)-N(H94)),"") -> 0.27498002 | I100: =IFERROR(I111/(I114-N(I93)-N(I94)),"") -> 0.28828125 | J100: =IFERROR(J111/(J114-N(J93)-N(J94)),"") -> 0.28099174 | ... BU100: =IFERROR(BU111/(BU114-N(BU93)-N(BU94)),"") -> 0.56328357 | BV100: =IFERROR(SUM(BT111:BU111)/(SUM(BT114:BU114)-SUM(BT93:BU93)-SUM(BT94:BU94)),0) -> 0.54747166 | BW100: =IFERROR(SUM(BT111:BU111)/(SUM(BT114:BU114)-SUM(BT93:BU93)-SUM(BT94:BU94)),0) -> 0.54747166 | BY100: =$BW$100 -> 0.54747166 | BZ100: =$BW$100 -> 0.54747166 | CA100: =$BW$100 -> 0.54747166 | CB100: =$BW$100 -> 0.54747166 | CC100: =$BW$100 -> 0.54747166
B101: Marketing & sales % | C101: =IFERROR(C112/(C114-N(C93)-N(C94)),"") -> 0.22330097 | D101: =IFERROR(D112/(D114-N(D93)-N(D94)),"") -> 0.19532909 | E101: =IFERROR(E112/(E114-N(E93)-N(E94)),"") -> 0.21841432 | F101: =IFERROR(F112/(F114-N(F93)-N(F94)),"") -> 0.19687981 | G101: =IFERROR(G112/(G114-N(G93)-N(G94)),"") -> 0.18709677 | H101: =IFERROR(H112/(H114-N(H93)-N(H94)),"") -> 0.21502798 | I101: =IFERROR(I112/(I114-N(I93)-N(I94)),"") -> 0.18203125 | J101: =IFERROR(J112/(J114-N(J93)-N(J94)),"") -> 0.20110193 | ... BU101: =IFERROR(BU112/(BU114-N(BU93)-N(BU94)),"") -> 0.089242054 | BV101: =IFERROR(SUM(BT112:BU112)/(SUM(BT114:BU114)-SUM(BT93:BU93)-SUM(BT94:BU94)),0) -> 0.088182514 | BW101: =IFERROR(SUM(BT112:BU112)/(SUM(BT114:BU114)-SUM(BT93:BU93)-SUM(BT94:BU94)),0) -> 0.088182514 | BY101: =$BW$101 -> 0.088182514 | BZ101: =$BW$101 -> 0.088182514 | CA101: =$BW$101 -> 0.088182514 | CB101: =$BW$101 -> 0.088182514 | CC101: =$BW$101 -> 0.088182514
...

Sheet Bull-Base-Bear
B2: Meta Platforms, Inc. (META) — Bull / Base / Bear Case P&L Summary | J2: Share price ($): | K2: =Model!$BY$371 -> 745
B3: Adjusted figures (current definition: GAAP + company-quantified one-offs, share-based compensation expensed; adjusted EBITDA = model definition) · USD millions · Live panel linked to Model — toggle scenario via Model!CD2. Bull and Bear panels are value snapshots generated from the Model with the switch set to each case. 2026E = Q1–Q2 actual + Q3 calibrated to revenue guidance ($61–64bn) and 2H to FY26 expense guidance ($165–169bn). | J3: As of: | K3: =TODAY() -> 2026-10-13 00:00:00
B5: Scenario: | C5: =Model!$CD$2 -> Base | N5: Scenario: | O5: Bull | P5: Snapshot (values) — Model run with switch = Bull | Z5: Scenario: | AA5: Bear | AB5: Snapshot (values) — Model run with switch = Bear
B7: (USDm, except EPS and shares) | C7: 2026E | D7: 2027E | E7: 2028E | F7: 2029E | G7: 2030E | H7: 2031E | I7: 26-'31 CAGR | J7: LT Hist Avg | K7: LT Hist Min | L7: LT Hist Max | N7: (USDm, except EPS and shares) | O7: 2026E | P7: 2027E | Q7: 2028E | R7: 2029E | S7: 2030E | T7: 2031E | U7: 26-'31 CAGR | V7: LT Hist Avg | W7: LT Hist Min | X7: LT Hist Max | Z7: (USDm, except EPS and shares) | AA7: 2026E | AB7: 2027E | AC7: 2028E | AD7: 2029E | AE7: 2030E | AF7: 2031E | AG7: 26-'31 CAGR | AH7: LT Hist Avg | AI7: LT Hist Min | AJ7: LT Hist Max
B9: Revenue | C9: =Model!BX109 -> 252600.41 | D9: =Model!BY109 -> 300830.67 | E9: =Model!BZ109 -> 348341.99 | F9: =Model!CA109 -> 395867.43 | G9: =Model!CB109 -> 441368.57 | H9: =Model!CC109 -> 487137.7 | I9: =IFERROR((H9/C9)^(1/5)-1,"n/m") -> 0.1403641 | N9: Revenue | O9: 255841.67 | P9: 316320.45 | Q9: 380558.28 | R9: 449619.98 | S9: 521505.75 | T9: 599023.1 | U9: 0.18548062 | Z9: Revenue | AA9: 249359.16 | AB9: 275313.01 | AC9: 295135.02 | AD9: 310210.25 | AE9: 319587.49 | AF9: 325783.69 | AG9: 0.054923104
B10: Revenue y/y % | D10: =IFERROR(D9/C9-1,"") -> 0.190935 | E10: =IFERROR(E9/D9-1,"") -> 0.15793377 | F10: =IFERROR(F9/E9-1,"") -> 0.13643327 | G10: =IFERROR(G9/F9-1,"") -> 0.11494034 | H10: =IFERROR(H9/G9-1,"") -> 0.10369821 | N10: Revenue y/y % | P10: 0.23639146 | Q10: 0.20307832 | R10: 0.1814747 | S10: 0.15988118 | T10: 0.14864142 | Z10: Revenue y/y % | AB10: 0.1040822 | AC10: 0.071998089 | AD10: 0.051079126 | AE10: 0.030228648 | AF10: 0.019388122
B11: Advertising revenue y/y % | C11: =Model!BX201 -> 0.25284329 | D11: =Model!BY201 -> 0.188 | E11: =Model!BZ201 -> 0.1554 | F11: =Model!CA201 -> 0.134 | G11: =Model!CB201 -> 0.1128 | H11: =Model!CC201 -> 0.1024 | N11: Advertising revenue y/y % | O11: 0.26936555 | P11: 0.232 | Q11: 0.1988 | R11: 0.177 | S11: 0.1554 | T11: 0.1448 | Z11: Advertising revenue y/y % | AA11: 0.23632103 | AB11: 0.1024 | AC11: 0.071 | AD11: 0.0504 | AE11: 0.03 | AF11: 0.02
B12: Adjusted EBITDA (model definition) | C12: =Model!BX168 -> 115613.32 | D12: =Model!BY168 -> 142894.57 | E12: =Model!BZ168 -> 170687.58 | F12: =Model!CA168 -> 197933.72 | G12: =Model!CB168 -> 225097.97 | H12: =Model!CC168 -> 250875.91 | I12: =IFERROR((H12/C12)^(1/5)-1,"n/m") -> 0.16758961 | N12: Adjusted EBITDA (model definition) | O12: 120854.57 | P12: 156578.62 | Q12: 194084.72 | R12: 233802.39 | S12: 276398.05 | T12: 320477.36 | U12: 0.21536536 | Z12: Adjusted EBITDA (model definition) | AA12: 110372.06 | AB12: 122514.29 | AC12: 135762.11 | AD12: 145798.82 | AE12: 153402 | AF12: 158005.09 | AG12: 0.074391058
B13: Adjusted EBITDA margin % | C13: =IFERROR(C12/C9,"") -> 0.45769251 | D13: =IFERROR(D12/D9,"") -> 0.475 | E13: =IFERROR(E12/E9,"") -> 0.49 | F13: =IFERROR(F12/F9,"") -> 0.5 | G13: =IFERROR(G12/G9,"") -> 0.51 | H13: =IFERROR(H12/H9,"") -> 0.515 | J13: =IFERROR(AVERAGE(Model!C169,Model!D169,Model!E169,Model!F169,Model!K169,Model!P169,Model!U169,Model!Z169,Model!AE169,Model!AJ169,Model!AO169,Model!AT169,Model!AY169,Model!BD169,Model!BI169,Model!BN169,Model!BS169),"") -> 0.47964081 | K13: =IFERROR(MIN(Model!C169,Model!D169,Model!E169,Model!F169,Model!K169,Model!P169,Model!U169,Model!Z169,Model!AE169,Model!AJ169,Model!AO169,Model!AT169,Model!AY169,Model!BD169,Model!BI169,Model!BN169,Model!BS169),"") -> 0.23324818 | L13: =IFERROR(MAX(Model!C169,Model!D169,Model!E169,Model!F169,Model!K169,Model!P169,Model!U169,Model!Z169,Model!AE169,Model!AJ169,Model!AO169,Model!AT169,Model!AY169,Model!BD169,Model!BI169,Model!BN169,Model!BS169),"") -> 0.59321175 | N13: Adjusted EBITDA margin % | O13: 0.47238033 | P13: 0.495 | Q13: 0.51 | R13: 0.52 | S13: 0.53 | T13: 0.535 | V13: 0.47964081 | W13: 0.23324818 | X13: 0.59321175 | Z13: Adjusted EBITDA margin % | AA13: 0.44262285 | AB13: 0.445 | AC13: 0.46 | AD13: 0.47 | AE13: 0.48 | AF13: 0.485 | AH13: 0.47964081 | AI13: 0.23324818 | AJ13: 0.59321175
B15: Income from operations (GAAP) | C15: =Model!BX116 -> 85600.412 | D15: =Model!BY116 -> 102233.46 | E15: =Model!BZ116 -> 119115.08 | F15: =Model!CA116 -> 134765.02 | G15: =Model!CB116 -> 155014.51 | H15: =Model!CC116 -> 175281.07 | I15: =IFERROR((H15/C15)^(1/5)-1,"n/m") -> 0.1541223 | N15: Income from operations (GAAP) | O15: 90841.666 | P15: 116171.53 | Q15: 143100.72 | R15: 171318.18 | S15: 206869 | T15: 245132.4 | U15: 0.21961603 | Z15: Income from operations (GAAP) | AA15: 80359.157 | AB15: 81766.667 | AC15: 84354.252 | AD15: 83787.582 | AE15: 85944.051 | AF15: 86903.045 | AG15: 0.015780624
B16: Income from operations y/y % | D16: =IFERROR(D15/C15-1,"") -> 0.1943104 | E16: =IFERROR(E15/D15-1,"") -> 0.16512809 | F16: =IFERROR(F15/E15-1,"") -> 0.1313851 | G16: =IFERROR(G15/F15-1,"") -> 0.15025769 | H16: =IFERROR(H15/G15-1,"") -> 0.13073978 | N16: Income from operations y/y % | P16: 0.27883532 | Q16: 0.23180538 | R16: 0.19718601 | S16: 0.20751342 | T16: 0.18496442 | Z16: Income from operations y/y % | AB16: 0.017515241 | AC16: 0.031645965 | AD16: -0.0067177477 | AE16: 0.025737336 | AF16: 0.011158356
B17: Operating margin (GAAP) % | C17: =IFERROR(C15/C9,"") -> 0.33887677 | D17: =IFERROR(D15/D9,"") -> 0.33983723 | E17: =IFERROR(E15/E9,"") -> 0.34194866 | F17: =IFERROR(F15/F9,"") -> 0.34042968 | G17: =IFERROR(G15/G9,"") -> 0.35121329 | H17: =IFERROR(H15/H9,"") -> 0.35981832 | J17: =IFERROR(AVERAGE(Model!C214,Model!D214,Model!E214,Model!F214,Model!K214,Model!P214,Model!U214,Model!Z214,Model!AE214,Model!AJ214,Model!AO214,Model!AT214,Model!AY214,Model!BD214,Model!BI214,Model!BN214,Model!BS214),"") -> 0.38131634 | K17: =IFERROR(MIN(Model!C214,Model!D214,Model!E214,Model!F214,Model!K214,Model!P214,Model!U214,Model!Z214,Model!AE214,Model!AJ214,Model!AO214,Model!AT214,Model!AY214,Model!BD214,Model!BI214,Model!BN214,Model!BS214),"") -> 0.10571822 | L17: =IFERROR(MAX(Model!C214,Model!D214,Model!E214,Model!F214,Model!K214,Model!P214,Model!U214,Model!Z214,Model!AE214,Model!AJ214,Model!AO214,Model!AT214,Model!AY214,Model!BD214,Model!BI214,Model!BN214,Model!BS214),"") -> 0.52279635 | N17: Operating margin (GAAP) % | O17: 0.35506987 | P17: 0.36725899 | Q17: 0.37602839 | R17: 0.38102884 | S17: 0.39667635 | T17: 0.40922028 | V17: 0.38131634 | W17: 0.10571822 | X17: 0.52279635 | Z17: Operating margin (GAAP) % | AA17: 0.32226271 | AB17: 0.29699529 | AC17: 0.28581581 | AD17: 0.27009933 | AE17: 0.26892182 | AF17: 0.26675075 | AH17: 0.38131634 | AI17: 0.10571822 | AJ17: 0.52279635
B19: Adjusted net income (current definition) | C19: =Model!BX192 -> 74577.344 | D19: =Model!BY192 -> 84127.364 | E19: =Model!BZ192 -> 97359.247 | F19: =Model!CA192 -> 110612.77 | G19: =Model!CB192 -> 126479.06 | H19: =Model!CC192 -> 143129.45 | I19: =IFERROR((H19/C19)^(1/5)-1,"n/m") -> 0.13926412 | N19: Adjusted net income (current definition) | O19: 78979.998 | P19: 95820.904 | Q19: 116349.77 | R19: 139170.87 | S19: 167075.45 | T19: 198171.78 | U19: 0.2020013 | Z19: Adjusted net income (current definition) | AA19: 70174.691 | AB19: 66760.827 | AC19: 67216.473 | AD19: 65995.435 | AE19: 67594.184 | AF19: 69501.906 | AG19: -0.0019248509
B21: Diluted shares (m) | C21: =Model!BX133 -> 2570 | D21: =Model!BY133 -> 2604 | E21: =Model!BZ133 -> 2630.4982 | F21: =Model!CA133 -> 2628.8759 | G21: =Model!CB133 -> 2589.5104 | H21: =Model!CC133 -> 2528.4359 | I21: =IFERROR((H21/C21)^(1/5)-1,"n/m") -> -0.0032556937 | N21: Diluted shares (m) | O21: 2568.3221 | P21: 2569.416 | Q21: 2541.7434 | R21: 2491.06 | S21: 2401.4499 | T21: 2280.6168 | U21: -0.0234813 | Z21: Diluted shares (m) | AA21: 2570 | AB21: 2604 | AC21: 2634 | AD21: 2664 | AE21: 2694 | AF21: 2724 | AG21: 0.011707096
B23: Adjusted EPS — Diluted ($) | C23: =Model!BX193 -> 29.018422 | D23: =Model!BY193 -> 32.306975 | E23: =Model!BZ193 -> 37.011713 | F23: =Model!CA193 -> 42.076071 | G23: =Model!CB193 -> 48.842847 | H23: =Model!CC193 -> 56.607904 | I23: =IFERROR((H23/C23)^(1/5)-1,"n/m") -> 0.14298533 | N23: Adjusted EPS — Diluted ($) | O23: 30.751593 | P23: 37.292873 | Q23: 45.775576 | R23: 55.868132 | S23: 69.572741 | T23: 86.89394 | U23: 0.23090454 | Z23: Adjusted EPS — Diluted ($) | AA23: 27.305327 | AB23: 25.637798 | AC23: 25.518782 | AD23: 24.773061 | AE23: 25.09064 | AF23: 25.51465 | AG23: -0.013474203
B24: EPS y/y % | D24: =IFERROR(D23/C23-1,"") -> 0.11332641 | E24: =IFERROR(E23/D23-1,"") -> 0.14562607 | F24: =IFERROR(F23/E23-1,"") -> 0.13683122 | G24: =IFERROR(G23/F23-1,"") -> 0.16082243 | H24: =IFERROR(H23/G23-1,"") -> 0.15898043 | N24: EPS y/y % | P24: 0.21271353 | Q24: 0.22746177 | R24: 0.22047906 | S24: 0.2453028 | T24: 0.24896531 | Z24: EPS y/y % | AB24: -0.061069722 | AC24: -0.0046422047 | AD24: -0.029222452 | AE24: 0.012819526 | AF24: 0.016899131
B26: P / E (x) — assumed (adjusted EPS) | G26: 24 | H26: 24 | N26: P / E (x) — assumed (adjusted EPS) | S26: 28 | T26: 28 | Z26: P / E (x) — assumed (adjusted EPS) | AD26: 18 | AE26: 18 | AF26: 18
B27: Price Target ($) | G27: =G26*G23 -> 1172.2283 | H27: =H26*H23 -> 1358.5897 | N27: Price Target ($) | S27: =S26*S23 -> 1948.0368 | T27: =T26*T23 -> 2433.0303 | Z27: Price Target ($) | AD27: =AD26*AD23 -> 445.9151 | AE27: =AE26*AE23 -> 451.63152 | AF27: =AF26*AF23 -> 459.2637
B28: Upside / (Downside) vs current | G28: =IFERROR(G27/$K$2-1,"") -> 0.57346084 | H28: =IFERROR(H27/$K$2-1,"") -> 0.82361032 | N28: Upside / (Downside) vs current | S28: =IFERROR(S27/$K$2-1,"") -> 1.6148144 | T28: =IFERROR(T27/$K$2-1,"") -> 2.2658125 | Z28: Upside / (Downside) vs current | AD28: =IFERROR(AD27/$K$2-1,"") -> -0.40145624 | AE28: =IFERROR(AE27/$K$2-1,"") -> -0.3937832 | AF28: =IFERROR(AF27/$K$2-1,"") -> -0.38353866
B29: IRR (to 31-Dec of Y-1) | G29: =IFERROR((G27/$K$2)^(1/((DATE(2030-1,12,31)-$K$3)/365.25))-1,"") -> 0.15131159 | H29: =IFERROR((H27/$K$2)^(1/((DATE(2031-1,12,31)-$K$3)/365.25))-1,"") -> 0.15315223 | N29: IRR (to 31-Dec of Y-1) | S29: =IFERROR((S27/$K$2)^(1/((DATE(2030-1,12,31)-$K$3)/365.25))-1,"") -> 0.34822364 | T29: =IFERROR((T27/$K$2)^(1/((DATE(2031-1,12,31)-$K$3)/365.25))-1,"") -> 0.32405505 | Z29: IRR (to 31-Dec of Y-1) | AD29: =IFERROR((AD27/$K$2)^(1/((DATE(2029-1,12,31)-$K$3)/365.25))-1,"") -> -0.20660992 | AE29: =IFERROR((AE27/$K$2)^(1/((DATE(2030-1,12,31)-$K$3)/365.25))-1,"") -> -0.1440869 | AF29: =IFERROR((AF27/$K$2)^(1/((DATE(2031-1,12,31)-$K$3)/365.25))-1,"") -> -0.10839838
B31: Free Cash Flow | C31: =Model!BX249 -> -8258.7406 | D31: =Model!BY249 -> 20755.194 | E31: =Model!BZ249 -> 53245.721 | F31: =Model!CA249 -> 92527.627 | G31: =Model!CB249 -> 126145.34 | H31: =Model!CC249 -> 156490.17 | I31: =IFERROR((H31/C31)^(1/5)-1,"n/m") -> -2.8010039 | N31: Free Cash Flow | O31: -3644.2066 | P31: 39624.364 | Q31: 79578.421 | R31: 129247.37 | S31: 176510.57 | T31: 223554.3 | U31: -3.278012 | Z31: Free Cash Flow | AA31: -12873.275 | AB31: -2693.7057 | AC31: 19816.191 | AD31: 45565.994 | AE31: 64599.443 | AF31: 79030.97 | AG31: -2.4375457
B32: FCF % | C32: =IFERROR(C31/C9,"") -> -0.032694882 | D32: =IFERROR(D31/D9,"") -> 0.068992945 | E32: =IFERROR(E31/E9,"") -> 0.15285473 | F32: =IFERROR(F31/F9,"") -> 0.23373387 | G32: =IFERROR(G31/G9,"") -> 0.28580499 | H32: =IFERROR(H31/H9,"") -> 0.32124422 | J32: =IFERROR(AVERAGE(Model!C254,Model!D254,Model!E254,Model!F254,Model!K254,Model!P254,Model!U254,Model!Z254,Model!AE254,Model!AJ254,Model!AO254,Model!AT254,Model!AY254,Model!BD254,Model!BI254,Model!BN254,Model!BS254),"") -> 0.27671393 | K32: =IFERROR(MIN(Model!C254,Model!D254,Model!E254,Model!F254,Model!K254,Model!P254,Model!U254,Model!Z254,Model!AE254,Model!AJ254,Model!AO254,Model!AT254,Model!AY254,Model!BD254,Model!BI254,Model!BN254,Model!BS254),"") -> 0.074081352 | L32: =IFERROR(MAX(Model!C254,Model!D254,Model!E254,Model!F254,Model!K254,Model!P254,Model!U254,Model!Z254,Model!AE254,Model!AJ254,Model!AO254,Model!AT254,Model!AY254,Model!BD254,Model!BI254,Model!BN254,Model!BS254),"") -> 0.43005436 | N32: FCF % | O32: -0.014243992 | P32: 0.12526652 | Q32: 0.20910968 | R32: 0.28745914 | S32: 0.33846333 | T32: 0.37319813 | V32: 0.27671393 | W32: 0.074081352 | X32: 0.43005436 | Z32: FCF % | AA32: -0.051625433 | AB32: -0.009784157 | AC32: 0.067142799 | AD32: 0.14688745 | AE32: 0.20213383 | AF32: 0.24258725 | AH32: 0.27671393 | AI32: 0.074081352 | AJ32: 0.43005436
B33: FCF / share ($) | C33: =IFERROR(C31/C21,"") -> -3.2135177 | D33: =IFERROR(D31/D21,"") -> 7.9705046 | E33: =IFERROR(E31/E21,"") -> 20.241687 | F33: =IFERROR(F31/F21,"") -> 35.19665 | G33: =IFERROR(G31/G21,"") -> 48.713973 | H33: =IFERROR(H31/H21,"") -> 61.892085 | N33: FCF / share ($) | O33: -1.4189056 | P33: 15.421545 | Q33: 31.308597 | R33: 51.884487 | S33: 73.501667 | T33: 98.023613 | Z33: FCF / share ($) | AA33: -5.0090563 | AB33: -1.0344492 | AC33: 7.5232312 | AD33: 17.104352 | AE33: 23.979006 | AF33: 29.012838
B34: FCF Yield (on PT) | F34: =IFERROR(F33/F$27,"") | G34: =IFERROR(G33/G$27,"") -> 0.041556728 | H34: =IFERROR(H33/H$27,"") -> 0.045556128 | N34: FCF Yield (on PT) | R34: =IFERROR(R33/R$27,"") | S34: =IFERROR(S33/S$27,"") -> 0.03773115 | T34: =IFERROR(T33/T$27,"") -> 0.040288693 | Z34: FCF Yield (on PT) | AD34: =IFERROR(AD33/AD$27,"") -> 0.038357867 | AE34: =IFERROR(AE33/AE$27,"") -> 0.053094182 | AF34: =IFERROR(AF33/AF$27,"") -> 0.063172504
B35: Adjusted EBITDA (leverage basis) | C35: =Model!BX168 -> 115613.32 | D35: =Model!BY168 -> 142894.57 | E35: =Model!BZ168 -> 170687.58 | F35: =Model!CA168 -> 197933.72 | G35: =Model!CB168 -> 225097.97 | H35: =Model!CC168 -> 250875.91 | I35: =IFERROR((H35/C35)^(1/5)-1,"n/m") -> 0.16758961 | N35: Adjusted EBITDA (leverage basis) | O35: 120854.57 | P35: 156578.62 | Q35: 194084.72 | R35: 233802.39 | S35: 276398.05 | T35: 320477.36 | U35: 0.21536536 | Z35: Adjusted EBITDA (leverage basis) | AA35: 110372.06 | AB35: 122514.29 | AC35: 135762.11 | AD35: 145798.82 | AE35: 153402 | AF35: 158005.09 | AG35: 0.074391058
B36: Adjusted EBITDA % of revenue | C36: =IFERROR(C35/C9,"") -> 0.45769251 | D36: =IFERROR(D35/D9,"") -> 0.475 | E36: =IFERROR(E35/E9,"") -> 0.49 | F36: =IFERROR(F35/F9,"") -> 0.5 | G36: =IFERROR(G35/G9,"") -> 0.51 | H36: =IFERROR(H35/H9,"") -> 0.515 | J36: =IFERROR(AVERAGE(Model!C213,Model!D213,Model!E213,Model!F213,Model!K213,Model!P213,Model!U213,Model!Z213,Model!AE213,Model!AJ213,Model!AO213,Model!AT213,Model!AY213,Model!BD213,Model!BI213,Model!BN213,Model!BS213),"") -> 0.47964081 | K36: =IFERROR(MIN(Model!C213,Model!D213,Model!E213,Model!F213,Model!K213,Model!P213,Model!U213,Model!Z213,Model!AE213,Model!AJ213,Model!AO213,Model!AT213,Model!AY213,Model!BD213,Model!BI213,Model!BN213,Model!BS213),"") -> 0.23324818 | L36: =IFERROR(MAX(Model!C213,Model!D213,Model!E213,Model!F213,Model!K213,Model!P213,Model!U213,Model!Z213,Model!AE213,Model!AJ213,Model!AO213,Model!AT213,Model!AY213,Model!BD213,Model!BI213,Model!BN213,Model!BS213),"") -> 0.59321175 | N36: Adjusted EBITDA % of revenue | O36: 0.47238033 | P36: 0.495 | Q36: 0.51 | R36: 0.52 | S36: 0.53 | T36: 0.535 | V36: 0.47964081 | W36: 0.23324818 | X36: 0.59321175 | Z36: Adjusted EBITDA % of revenue | AA36: 0.44262285 | AB36: 0.445 | AC36: 0.46 | AD36: 0.47 | AE36: 0.48 | AF36: 0.485 | AH36: 0.47964081 | AI36: 0.23324818 | AJ36: 0.59321175
B38: Net Debt | C38: =Model!BX365 -> 31296.741 | D38: =Model!BY365 -> 48335.551 | E38: =Model!BZ365 -> 42671.894 | F38: =Model!CA365 -> 49483.429 | G38: =Model!CB365 -> 56274.492 | H38: =Model!CC365 -> 62718.979 | N38: Net Debt | O38: 31678.683 | P38: 78289.312 | Q38: 97042.361 | R38: 116901.19 | S38: 138199.02 | T38: 160238.68 | Z38: Net Debt | AA38: 35911.275 | AB38: 72757.906 | AC38: 88170.471 | AD38: 79699.131 | AE38: 52080.313 | AF38: 11034.896
B39: Net Debt / Adjusted EBITDA (x) | C39: =IFERROR(C38/C35,"") -> 0.27070187 | D39: =IFERROR(D38/D35,"") -> 0.33826024 | E39: =IFERROR(E38/E35,"") -> 0.25 | F39: =IFERROR(F38/F35,"") -> 0.25 | G39: =IFERROR(G38/G35,"") -> 0.25 | H39: =IFERROR(H38/H35,"") -> 0.25 | N39: Net Debt / Adjusted EBITDA (x) | O39: 0.26212234 | P39: 0.5 | Q39: 0.5 | R39: 0.5 | S39: 0.5 | T39: 0.5 | Z39: Net Debt / Adjusted EBITDA (x) | AA39: 0.32536562 | AB39: 0.59387283 | AC39: 0.64944831 | AD39: 0.54663769 | AE39: 0.33950219 | AF39: 0.069838863
B40: Share repurchases ($m; 2026E = 2H) | D40: =Model!BY264 -> 0 | E40: =Model!BZ264 -> 6085.8177 | F40: =Model!CA264 -> 52781.473 | G40: =Model!CB264 -> 83608.902 | H40: =Model!CC264 -> 109091.74 | N40: Share repurchases ($m; 2026E = 2H) | P40: 44852.594 | Q40: 51790.414 | R40: 95506.71 | S40: 139317.82 | T40: 179755.57 | AB40: 0 | AC40: 0 | AD40: 0 | AE40: 0 | AF40: 0
B41: Implied avg buyback price ($) | D41: =Model!BY263 -> 804.6 | E41: =Model!BZ263 -> 868.968 | F41: =Model!CA263 -> 938.48544 | G41: =Model!CB263 -> 1013.5643 | H41: =Model!CC263 -> 1094.6494 | N41: Implied avg buyback price ($) | P41: 804.6 | Q41: 868.968 | R41: 938.48544 | S41: 1013.5643 | T41: 1094.6494 | AB41: 804.6 | AC41: 868.968 | AD41: 938.48544 | AE41: 1013.5643 | AF41: 1094.6494
B42: Shares repurchased (m) | D42: =Model!BY265 -> 0 | E42: =Model!BZ265 -> 7.0035004 | F42: =Model!CA265 -> 56.241121 | G42: =Model!CB265 -> 82.489985 | H42: =Model!CC265 -> 99.659071 | N42: Shares repurchased (m) | P42: 55.745208 | Q42: 59.599909 | R42: 101.76685 | S42: 137.45337 | T42: 164.21291 | AB42: 0 | AC42: 0 | AD42: 0 | AE42: 0 | AF42: 0
B44: ROIC | C44: =Model!BX347 -> 0.22995314 | D44: =Model!BY347 -> 0.20097435 | E44: =Model!BZ347 -> 0.19590913 | F44: =Model!CA347 -> 0.19743706 | G44: =Model!CB347 -> 0.20842061 | H44: =Model!CC347 -> 0.22181535 | J44: =IFERROR(AVERAGE(Model!C347,Model!D347,Model!E347,Model!F347,Model!K347,Model!P347,Model!U347,Model!Z347,Model!AE347,Model!AJ347,Model!AO347,Model!AT347,Model!AY347,Model!BD347,Model!BI347,Model!BN347,Model!BS347),"") -> 0.39499745 | K44: =IFERROR(MIN(Model!C347,Model!D347,Model!E347,Model!F347,Model!K347,Model!P347,Model!U347,Model!Z347,Model!AE347,Model!AJ347,Model!AO347,Model!AT347,Model!AY347,Model!BD347,Model!BI347,Model!BN347,Model!BS347),"") -> 0.01286971 | L44: =IFERROR(MAX(Model!C347,Model!D347,Model!E347,Model!F347,Model!K347,Model!P347,Model!U347,Model!Z347,Model!AE347,Model!AJ347,Model!AO347,Model!AT347,Model!AY347,Model!BD347,Model!BI347,Model!BN347,Model!BS347),"") -> 0.72991597 | N44: ROIC | O44: 0.24351824 | P44: 0.2303181 | Q44: 0.23787563 | R44: 0.25348858 | S44: 0.28040126 | T44: 0.31176165 | V44: 0.39499745 | W44: 0.01286971 | X44: 0.72991597 | Z44: ROIC | AA44: 0.21640569 | AB44: 0.15985717 | AC44: 0.1390663 | AD44: 0.12477315 | AE44: 0.11948048 | AF44: 0.11604567 | AH44: 0.39499745 | AI44: 0.01286971 | AJ44: 0.72991597
B45: RONTA | C45: =Model!BX359 -> 0.21350994 | D45: =Model!BY359 -> 0.19015553 | E45: =Model!BZ359 -> 0.18733135 | F45: =Model!CA359 -> 0.18997823 | G45: =Model!CB359 -> 0.20138834 | H45: =Model!CC359 -> 0.21500159 | J45: =IFERROR(AVERAGE(Model!C359,Model!D359,Model!E359,Model!F359,Model!K359,Model!P359,Model!U359,Model!Z359,Model!AE359,Model!AJ359,Model!AO359,Model!AT359,Model!AY359,Model!BD359,Model!BI359,Model!BN359,Model!BS359),"") -> 0.51428198 | K45: =IFERROR(MIN(Model!C359,Model!D359,Model!E359,Model!F359,Model!K359,Model!P359,Model!U359,Model!Z359,Model!AE359,Model!AJ359,Model!AO359,Model!AT359,Model!AY359,Model!BD359,Model!BI359,Model!BN359,Model!BS359),"") -> 0.016966681 | L45: =IFERROR(MAX(Model!C359,Model!D359,Model!E359,Model!F359,Model!K359,Model!P359,Model!U359,Model!Z359,Model!AE359,Model!AJ359,Model!AO359,Model!AT359,Model!AY359,Model!BD359,Model!BI359,Model!BN359,Model!BS359),"") -> 0.94249403 | N45: RONTA | O45: 0.22609461 | P45: 0.21877208 | Q45: 0.22899979 | R45: 0.24613497 | S45: 0.27395908 | T45: 0.30609199 | V45: 0.51428198 | W45: 0.016966681 | X45: 0.94249403 | Z45: RONTA | AA45: 0.20094049 | AB45: 0.15097225 | AC45: 0.13249119 | AD45: 0.11941988 | AE45: 0.11465364 | AF45: 0.11153542 | AH45: 0.51428198 | AI45: 0.016966681 | AJ45: 0.94249403
B47: Implied Market Cap (USDm) | F47: =F27*F21 -> 0 | G47: =G27*G21 -> 3035497.4 | H47: =H27*H21 -> 3435106.9 | N47: Implied Market Cap (USDm) | R47: =R27*R21 -> 0 | S47: =S27*S21 -> 4678112.7 | T47: =T27*T21 -> 5548809.8 | Z47: Implied Market Cap (USDm) | AD47: =AD27*AD21 -> 1187917.8 | AE47: =AE27*AE21 -> 1216695.3 | AF47: =AF27*AF21 -> 1251034.3
B48: (+) Net Debt & NCI | F48: =F38+Model!CA375 -> 49483.429 | G48: =G38+Model!CB375 -> 56274.492 | H48: =H38+Model!CC375 -> 62718.979 | N48: (+) Net Debt & NCI | R48: =R38+Model!CA375 -> 116901.19 | S48: =S38+Model!CB375 -> 138199.02 | T48: =T38+Model!CC375 -> 160238.68 | Z48: (+) Net Debt & NCI | AD48: =AD38+Model!CA375 -> 79699.131 | AE48: =AE38+Model!CB375 -> 52080.313 | AF48: =AF38+Model!CC375 -> 11034.896
B49: Implied Enterprise Value (USDm) | F49: =F47+F48 -> 49483.429 | G49: =G47+G48 -> 3091771.9 | H49: =H47+H48 -> 3497825.9 | N49: Implied Enterprise Value (USDm) | R49: =R47+R48 -> 116901.19 | S49: =S47+S48 -> 4816311.8 | T49: =T47+T48 -> 5709048.5 | Z49: Implied Enterprise Value (USDm) | AD49: =AD47+AD48 -> 1267617 | AE49: =AE47+AE48 -> 1268775.6 | AF49: =AF47+AF48 -> 1262069.2
B50: Implied EV / Adjusted EBITDA (x) | F50: =IFERROR(F49/F35,"") -> 0.25 | G50: =IFERROR(G49/G35,"") -> 13.735228 | H50: =IFERROR(H49/H35,"") -> 13.942454 | N50: Implied EV / Adjusted EBITDA (x) | R50: =IFERROR(R49/R35,"") -> 0.5 | S50: =IFERROR(S49/S35,"") -> 17.425274 | T50: =IFERROR(T49/T35,"") -> 17.814202 | Z50: Implied EV / Adjusted EBITDA (x) | AD50: =IFERROR(AD49/AD35,"") -> 8.6942882 | AE50: =IFERROR(AE49/AE35,"") -> 8.2709199 | AF50: =IFERROR(AF49/AF35,"") -> 7.9875225

Sheet DCF
B2: DCF VALUATION — META PLATFORMS, INC. (META)
B4: 1. WACC BUILD
B5: Risk-free rate (US 10Y govt) | C5: 0.0425 | D5: Assumption (~US 10Y Treasury yield, Oct-2026; government rate sources not reachable from the build environment); update to market
B6: Equity risk premium | C6: 0.05 | D6: Assumption: US implied ERP ~4.5–5.5%
B7: Levered beta | C7: 1.2 | D7: Assumption: mega-cap internet and advertising peers (GOOGL, AMZN, MSFT, SNAP, PINS) ~1.0–1.3; advertising is cyclical and the AI capex cycle raises operating leverage
B8: Cost of equity | C8: =C5+C7*C6 -> 0.1025
B9: Pre-tax cost of debt | C9: 0.05 | D9: May-2026 notes 4.55%–6.45% (effective 4.60%–6.48%); Nov-2025 notes 4.20%–5.75% (Q2-26 10-Q Note 8); AA- / Aa3 class issuer
B10: Tax rate | C10: 0.16 | D10: Model 2027E+ effective tax rate (2026 guidance 15–17% for the remaining quarters)
B11: After-tax cost of debt | C11: =C9*(1-C10) -> 0.042
B12: Target D/V | C12: 0.05 | D12: Notes ~$84bn at 30-Jun-2026 vs ~$1.9tn market cap ($745 × ~2.57bn diluted shares); net debt ≈ 0 (cash and marketable securities $90.3bn)
B13: WACC | C13: =C8*(1-C12)+C11*C12 -> 0.099475
B15: Valuation date (live) | C15: =TODAY() -> 2026-10-13 00:00:00 | D15: Periods = (31-Dec of the year − today) / 365.25; cash flows assumed at year-end; 2026E is the base year (its cash flows are in YE2026E net debt)
B16: 2. UNLEVERED FREE CASH FLOW BUILD (USDm)
D17: 2027E | E17: 2028E | F17: 2029E | G17: 2030E | H17: 2031E | I17: 2032E | J17: 2033E | K17: 2034E | L17: 2035E | M17: 2036E | N17: Terminal | P17: CAGR 27–31E | Q17: CAGR 27–36E
B18: Adj. EBIT (current definition, full-cost) less cash one-off items (legal, restructuring) | D18: =Model!BY173-Model!BY175 -> 102233.46 | E18: =Model!BZ173-Model!BZ175 -> 119115.08 | F18: =Model!CA173-Model!CA175 -> 134765.02 | G18: =Model!CB173-Model!CB175 -> 155014.51 | H18: =Model!CC173-Model!CC175 -> 175281.07 | I18: =H18*(1+I$26) -> 191056.36 | J18: =I18*(1+J$26) -> 206340.87 | K18: =J18*(1+K$26) -> 220784.73 | L18: =K18*(1+L$26) -> 234031.82 | M18: =L18*(1+M$26) -> 245733.41 | P18: =IFERROR(IF(D18<=0,"n/m",(H18/D18)^(1/(COLUMNS(D18:H18)-1))-1),"n/m") -> 0.14428837 | Q18: =IFERROR(IF(D18<=0,"n/m",(M18/D18)^(1/(COLUMNS(D18:M18)-1))-1),"n/m") -> 0.10234875
B19: × (1 − tax rate) | D19: =1-$C$10 -> 0.84 | E19: =1-$C$10 -> 0.84 | F19: =1-$C$10 -> 0.84 | G19: =1-$C$10 -> 0.84 | H19: =1-$C$10 -> 0.84 | I19: =1-$C$10 -> 0.84 | J19: =1-$C$10 -> 0.84 | K19: =1-$C$10 -> 0.84 | ... M19: =1-$C$10 -> 0.84
B20: NOPAT | D20: =D18*D19 -> 85876.108 | E20: =E18*E19 -> 100056.67 | F20: =F18*F19 -> 113202.62 | G20: =G18*G19 -> 130212.19 | H20: =H18*H19 -> 147236.1 | I20: =I18*I19 -> 160487.35 | J20: =J18*J19 -> 173326.33 | K20: =K18*K19 -> 185459.18 | ... M20: =M18*M19 -> 206416.06
B21: plus D&A | D21: =Model!BY129 -> 40661.106 | E21: =Model!BZ129 -> 51572.498 | F21: =Model!CA129 -> 63168.691 | G21: =Model!CB129 -> 70083.464 | H21: =Model!CC129 -> 75594.846 | I21: =H21*(1+I$26) -> 82398.383 | J21: =I21*(1+J$26) -> 88990.253 | K21: =J21*(1+K$26) -> 95219.571 | L21: =K21*(1+L$26) -> 100932.75 | M21: =L21*(1+M$26) -> 105979.38
B22: − Capex incl. principal payments on finance leases and acquisitions (M&A lever 2027E–31E) | D22: =Model!BY247 -> -142382.11 | E22: =Model!BZ247+Model!BZ228 -> -137369.96 | F22: =Model!CA247+Model!CA228 -> -127718.9 | G22: =Model!CB247+Model!CB228 -> -119755.83 | H22: =Model!CC247+Model!CC228 -> -117041.67 | I22: =Model!CC247*(1+I$26) -> -126485.42 | J22: =I22*(1+J$26) -> -136604.25 | K22: =J22*(1+K$26) -> -146166.55 | L22: =K22*(1+L$26) -> -154936.55 | M22: =L22*(1+M$26) -> -162683.37
B23: − Δ Working capital (CF statement) | D23: =Model!BY223 -> 3753.3048 | E23: =Model!BZ223 -> 2366.3141 | F23: =Model!CA223 -> 1919.6517 | G23: =Model!CB223 -> 1994.9447 | H23: =Model!CC223 -> 2658.0805 | I23: =H23*(1+I$26) -> 2897.3077 | J23: =I23*(1+J$26) -> 3129.0924 | K23: =J23*(1+K$26) -> 3348.1288 | L23: =K23*(1+L$26) -> 3549.0166 | M23: =L23*(1+M$26) -> 3726.4674
B24: Unlevered FCF | D24: =D20+D21+D22+D23 -> -12091.589 | E24: =E20+E21+E22+E23 -> 16625.521 | F24: =F20+F21+F22+F23 -> 50572.06 | G24: =G20+G21+G22+G23 -> 82534.766 | H24: =H20+H21+H22+H23 -> 108447.35 | I24: =I20+I21+I22+I23 -> 119297.62 | J24: =J20+J21+J22+J23 -> 128841.42 | K24: =K20+K21+K22+K23 -> 137860.32 | ... M24: =M20+M21+M22+M23 -> 153438.54 | N24: =M24*(1+$C$27) -> 158808.89 | P24: =IFERROR(IF(D24<=0,"n/m",(H24/D24)^(1/(COLUMNS(D24:H24)-1))-1),"n/m") -> n/m | Q24: =IFERROR(IF(D24<=0,"n/m",(M24/D24)^(1/(COLUMNS(D24:M24)-1))-1),"n/m") -> n/m
B25: Terminal Value (Gordon Growth) | N25: =N24/($C$13-$C$27) -> 2463108
B26: Fade-period growth (2032E–36E; 9.0% → 5.0% linear) | I26: 0.09 | J26: =I26+($M$26-$I$26)/4 -> 0.08 | K26: =J26+($M$26-$I$26)/4 -> 0.07 | L26: =K26+($M$26-$I$26)/4 -> 0.06 | M26: 0.05
B27: Terminal growth rate | C27: 0.035
B29: Discount period (years) | D29: =(DATE(2027,12,31)-$C$15)/365.25 -> 1.2156057 | E29: =(DATE(2028,12,31)-$C$15)/365.25 -> 2.2176591 | F29: =(DATE(2029,12,31)-$C$15)/365.25 -> 3.2169747 | G29: =(DATE(2030,12,31)-$C$15)/365.25 -> 4.2162902 | H29: =(DATE(2031,12,31)-$C$15)/365.25 -> 5.2156057 | I29: =(DATE(2032,12,31)-$C$15)/365.25 -> 6.2176591 | J29: =(DATE(2033,12,31)-$C$15)/365.25 -> 7.2169747 | K29: =(DATE(2034,12,31)-$C$15)/365.25 -> 8.2162902 | L29: =(DATE(2035,12,31)-$C$15)/365.25 -> 9.2156057 | M29: =(DATE(2036,12,31)-$C$15)/365.25 -> 10.217659 | N29: =M29 -> 10.217659
B30: Discount factor | D30: =1/(1+$C$13)^D29 -> 0.89111723 | E30: =1/(1+$C$13)^E29 -> 0.81033559 | F30: =1/(1+$C$13)^F29 -> 0.73706832 | G30: =1/(1+$C$13)^G29 -> 0.67042558 | H30: =1/(1+$C$13)^H29 -> 0.60980841 | I30: =1/(1+$C$13)^I29 -> 0.554528 | J30: =1/(1+$C$13)^J29 -> 0.50438982 | K30: =1/(1+$C$13)^K29 -> 0.45878493 | ... N30: =1/(1+$C$13)^N29 -> 0.37947402
B31: PV of UFCF | D31: =D24*D30 -> -10775.023 | E31: =E24*E30 -> 13472.251 | F31: =F24*F30 -> 37275.063 | G31: =G24*G30 -> 55333.418 | H31: =H24*H30 -> 66132.108 | I31: =I24*I30 -> 66153.868 | J31: =J24*J30 -> 64986.302 | K31: =K24*K30 -> 63248.239 | ... M31: =M24*M30 -> 58225.939 | N31: =N25*N30 -> 934685.49
D32: Meta's adjusted EBIT (current definition) expenses share-based compensation (a real cost: ~11% of revenue) and all D&A; only the one-off legal and restructuring items the company quantified are added back, and those are deducted again inside row 18 because they are cash costs. D&A is added back in row 21 (dominated by servers and data centers). Row 22 = purchases of property and equipment + principal payments on finance leases (the company's capex measure) + acquisitions; the fade period and terminal value carry capex (no new acquisitions). Taxes on net share settlement (~90% of SBC) are a financing flow and are not deducted. Operating and finance lease liabilities are excluded from net debt (lease costs sit in operating costs). 2026E is the base year: its cash flows are in YE2026E net debt.
B33: IMPLIED ROIC — invested capital roll-forward (USDm)
B34: Opening invested capital | D34: =Model!BX344 -> 328331.14 | E34: =D38 -> 426298.84 | F34: =E38 -> 509729.98 | G34: =F38 -> 572360.54 | H34: =G38 -> 620037.96 | I34: =H38 -> 658826.71 | J34: =I38 -> 700016.44 | K34: =J38 -> 744501.35 | L34: =K38 -> 792100.2 | M34: =L38 -> 842554.98
B35: plus Capex and acquisitions | D35: =-D22 -> 142382.11 | E35: =-E22 -> 137369.96 | F35: =-F22 -> 127718.9 | G35: =-G22 -> 119755.83 | H35: =-H22 -> 117041.67 | I35: =-I22 -> 126485.42 | J35: =-J22 -> 136604.25 | K35: =-K22 -> 146166.55 | ... M35: =-M22 -> 162683.37
B36: less DD&A | D36: =-D21 -> -40661.106 | E36: =-E21 -> -51572.498 | F36: =-F21 -> -63168.691 | G36: =-G21 -> -70083.464 | H36: =-H21 -> -75594.846 | I36: =-I21 -> -82398.383 | J36: =-J21 -> -88990.253 | K36: =-K21 -> -95219.571 | ... M36: =-M21 -> -105979.38
B37: plus Δ Working capital investment | D37: =-D23 -> -3753.3048 | E37: =-E23 -> -2366.3141 | F37: =-F23 -> -1919.6517 | G37: =-G23 -> -1994.9447 | H37: =-H23 -> -2658.0805 | I37: =-I23 -> -2897.3077 | J37: =-J23 -> -3129.0924 | K37: =-K23 -> -3348.1288 | ... M37: =-M23 -> -3726.4674
B38: Closing invested capital | D38: =SUM(D34:D37) -> 426298.84 | E38: =SUM(E34:E37) -> 509729.98 | F38: =SUM(F34:F37) -> 572360.54 | G38: =SUM(G34:G37) -> 620037.96 | H38: =SUM(H34:H37) -> 658826.71 | I38: =SUM(I34:I37) -> 700016.44 | J38: =SUM(J34:J37) -> 744501.35 | K38: =SUM(K34:K37) -> 792100.2 | ... M38: =SUM(M34:M37) -> 895532.51
B39: NOPAT (row 20) | D39: =D20 -> 85876.108 | E39: =E20 -> 100056.67 | F39: =F20 -> 113202.62 | G39: =G20 -> 130212.19 | H39: =H20 -> 147236.1 | I39: =I20 -> 160487.35 | J39: =J20 -> 173326.33 | K39: =K20 -> 185459.18 | ... M39: =M20 -> 206416.06
B40: Implied ROIC (NOPAT / avg. invested capital) | D40: =IFERROR(D39/AVERAGE(D34,D38),"") -> 0.22759792 | E40: =IFERROR(E39/AVERAGE(E34,E38),"") -> 0.21378971 | F40: =IFERROR(F39/AVERAGE(F34,F38),"") -> 0.20922948 | G40: =IFERROR(G39/AVERAGE(G34,G38),"") -> 0.2184038 | H40: =IFERROR(H39/AVERAGE(H34,H38),"") -> 0.23026064 | I40: =IFERROR(I39/AVERAGE(I34,I38),"") -> 0.23621173 | J40: =IFERROR(J39/AVERAGE(J34,J38),"") -> 0.23997812 | K40: =IFERROR(K39/AVERAGE(K34,K38),"") -> 0.24138877 | ... M40: =IFERROR(M39/AVERAGE(M34,M38),"") -> 0.23752091
B41: Reinvestment rate (net investment / NOPAT) | D41: =IFERROR(SUM(D35:D37)/D39,"") -> 1.1408027 | E41: =IFERROR(SUM(E35:E37)/E39,"") -> 0.83383895 | F41: =IFERROR(SUM(F35:F37)/F39,"") -> 0.5532607 | G41: =IFERROR(SUM(G35:G37)/G39,"") -> 0.36615175 | H41: =IFERROR(SUM(H35:H37)/H39,"") -> 0.26344588 | I41: =IFERROR(SUM(I35:I37)/I39,"") -> 0.25665407 | J41: =IFERROR(SUM(J35:J37)/J39,"") -> 0.25665407 | K41: =IFERROR(SUM(K35:K37)/K39,"") -> 0.25665407 | ... M41: =IFERROR(SUM(M35:M37)/M39,"") -> 0.25665407
B42: Implied terminal RONIC (g / reinvestment rate) | N42: =IFERROR($C$27/M41,"") -> 0.13637033
D43: Opening IC = Model 2026E book IC (equity + net debt at 31-Dec-2026E), rolled forward with capex + M&A − D&A + ΔWC.
B44: 3. VALUATION SUMMARY
B45: Sum of PV (explicit + fade) | C45: =SUM(D31:M31) -> 475033.53
B46: PV of Terminal Value | C46: =N31 -> 934685.49
B47: Enterprise Value | C47: =C45+C46 -> 1409719
B48: Less: Net debt + NCI (Model 2026E year end; net debt = notes + CP − cash − marketable securities) | C48: =Model!BX365+Model!BX375 -> 31296.741 | D48: META: no noncontrolling interests; non-marketable equity investments ($30bn at 30-Jun-2026) are not added back (conservative).
B49: Equity Value | C49: =C47-C48 -> 1378422.3
B50: Diluted shares (m, Model 2026E period end) | C50: =Model!BX372 -> 2589
B51: Implied share price ($) | C51: =C49/C50 -> 532.41494
B52: Current share price ($) | C52: =Model!BX371 -> 745
B53: Implied upside / (downside) | C53: =C51/C52-1 -> -0.28534907
B54: Required discount to DCF value for target IRR | C54: =1-((1+C13)/(1+H54))^H55 -> 0.12609836 | D54: vs. current | E54: Target IRR | H54: 0.15
B55: Max entry price for target IRR ($) | C55: =C51*(1-C54) -> 465.27829 | D55: =C55/C52-1 -> -0.37546538 | E55: Years for discount to close | H55: 3
B58: 4. SENSITIVITY: IMPLIED PRICE ($) — WACC × Terminal Growth
D60: WACC →
B61: Terminal growth ↓ | D61: =F61-0.01 -> 0.089475 | E61: =F61-0.005 -> 0.094475 | F61: =$C$13 -> 0.099475 | G61: =F61+0.005 -> 0.104475 | H61: =F61+0.01 -> 0.109475
B62: =B64-0.01 -> 0.025 | D62: {=IFERROR((SUMPRODUCT($D$24:$M$24/(1+D$61)^$D$29:$M$29)+($M$24*(1+$B62)/(D$61-$B62))/(1+D$61)^$M$29-$C$48)/$C$50,"")} -> 575.86758 | E62: {=IFERROR((SUMPRODUCT($D$24:$M$24/(1+E$61)^$D$29:$M$29)+($M$24*(1+$B62)/(E$61-$B62))/(1+E$61)^$M$29-$C$48)/$C$50,"")} -> 524.87432 | F62: {=IFERROR((SUMPRODUCT($D$24:$M$24/(1+F$61)^$D$29:$M$29)+($M$24*(1+$B62)/(F$61-$B62))/(1+F$61)^$M$29-$C$48)/$C$50,"")} -> 480.9196 | G62: {=IFERROR((SUMPRODUCT($D$24:$M$24/(1+G$61)^$D$29:$M$29)+($M$24*(1+$B62)/(G$61-$B62))/(1+G$61)^$M$29-$C$48)/$C$50,"")} -> 442.66925 | H62: {=IFERROR((SUMPRODUCT($D$24:$M$24/(1+H$61)^$D$29:$M$29)+($M$24*(1+$B62)/(H$61-$B62))/(1+H$61)^$M$29-$C$48)/$C$50,"")} -> 409.10519
B63: =B64-0.005 -> 0.03 | D63: {=IFERROR((SUMPRODUCT($D$24:$M$24/(1+D$61)^$D$29:$M$29)+($M$24*(1+$B63)/(D$61-$B63))/(1+D$61)^$M$29-$C$48)/$C$50,"")} -> 610.942 | E63: {=IFERROR((SUMPRODUCT($D$24:$M$24/(1+E$61)^$D$29:$M$29)+($M$24*(1+$B63)/(E$61-$B63))/(1+E$61)^$M$29-$C$48)/$C$50,"")} -> 553.65933 | F63: {=IFERROR((SUMPRODUCT($D$24:$M$24/(1+F$61)^$D$29:$M$29)+($M$24*(1+$B63)/(F$61-$B63))/(1+F$61)^$M$29-$C$48)/$C$50,"")} -> 504.81425 | G63: {=IFERROR((SUMPRODUCT($D$24:$M$24/(1+G$61)^$D$29:$M$29)+($M$24*(1+$B63)/(G$61-$B63))/(1+G$61)^$M$29-$C$48)/$C$50,"")} -> 462.70175 | H63: {=IFERROR((SUMPRODUCT($D$24:$M$24/(1+H$61)^$D$29:$M$29)+($M$24*(1+$B63)/(H$61-$B63))/(1+H$61)^$M$29-$C$48)/$C$50,"")} -> 426.04606
B64: =$C$27 -> 0.035 | D64: {=IFERROR((SUMPRODUCT($D$24:$M$24/(1+D$61)^$D$29:$M$29)+($M$24*(1+$B64)/(D$61-$B64))/(1+D$61)^$M$29-$C$48)/$C$50,"")} -> 652.45505 | E64: {=IFERROR((SUMPRODUCT($D$24:$M$24/(1+E$61)^$D$29:$M$29)+($M$24*(1+$B64)/(E$61-$B64))/(1+E$61)^$M$29-$C$48)/$C$50,"")} -> 587.28419 | F64: {=IFERROR((SUMPRODUCT($D$24:$M$24/(1+F$61)^$D$29:$M$29)+($M$24*(1+$B64)/(F$61-$B64))/(1+F$61)^$M$29-$C$48)/$C$50,"")} -> 532.41494 | G64: {=IFERROR((SUMPRODUCT($D$24:$M$24/(1+G$61)^$D$29:$M$29)+($M$24*(1+$B64)/(G$61-$B64))/(1+G$61)^$M$29-$C$48)/$C$50,"")} -> 485.61765 | H64: {=IFERROR((SUMPRODUCT($D$24:$M$24/(1+H$61)^$D$29:$M$29)+($M$24*(1+$B64)/(H$61-$B64))/(1+H$61)^$M$29-$C$48)/$C$50,"")} -> 445.26164
B65: =B64+0.005 -> 0.04 | D65: {=IFERROR((SUMPRODUCT($D$24:$M$24/(1+D$61)^$D$29:$M$29)+($M$24*(1+$B65)/(D$61-$B65))/(1+D$61)^$M$29-$C$48)/$C$50,"")} -> 702.35881 | E65: {=IFERROR((SUMPRODUCT($D$24:$M$24/(1+E$61)^$D$29:$M$29)+($M$24*(1+$B65)/(E$61-$B65))/(1+E$61)^$M$29-$C$48)/$C$50,"")} -> 627.08158 | F65: {=IFERROR((SUMPRODUCT($D$24:$M$24/(1+F$61)^$D$29:$M$29)+($M$24*(1+$B65)/(F$61-$B65))/(1+F$61)^$M$29-$C$48)/$C$50,"")} -> 564.65635 | G65: {=IFERROR((SUMPRODUCT($D$24:$M$24/(1+G$61)^$D$29:$M$29)+($M$24*(1+$B65)/(G$61-$B65))/(1+G$61)^$M$29-$C$48)/$C$50,"")} -> 512.08779 | H65: {=IFERROR((SUMPRODUCT($D$24:$M$24/(1+H$61)^$D$29:$M$29)+($M$24*(1+$B65)/(H$61-$B65))/(1+H$61)^$M$29-$C$48)/$C$50,"")} -> 467.24305
B66: =B64+0.01 -> 0.045 | D66: {=IFERROR((SUMPRODUCT($D$24:$M$24/(1+D$61)^$D$29:$M$29)+($M$24*(1+$B66)/(D$61-$B66))/(1+D$61)^$M$29-$C$48)/$C$50,"")} -> 763.4832 | E66: {=IFERROR((SUMPRODUCT($D$24:$M$24/(1+E$61)^$D$29:$M$29)+($M$24*(1+$B66)/(E$61-$B66))/(1+E$61)^$M$29-$C$48)/$C$50,"")} -> 674.92291 | F66: {=IFERROR((SUMPRODUCT($D$24:$M$24/(1+F$61)^$D$29:$M$29)+($M$24*(1+$B66)/(F$61-$B66))/(1+F$61)^$M$29-$C$48)/$C$50,"")} -> 602.81633 | G66: {=IFERROR((SUMPRODUCT($D$24:$M$24/(1+G$61)^$D$29:$M$29)+($M$24*(1+$B66)/(G$61-$B66))/(1+G$61)^$M$29-$C$48)/$C$50,"")} -> 543.00857 | H66: {=IFERROR((SUMPRODUCT($D$24:$M$24/(1+H$61)^$D$29:$M$29)+($M$24*(1+$B66)/(H$61-$B66))/(1+H$61)^$M$29-$C$48)/$C$50,"")} -> 492.63374
B69: 5. REVERSE DCF
B70: To solve for the market-implied path: Data ▸ What-If Analysis ▸ Goal Seek — set C51 to the current price (C52) by changing C27 (terminal growth) or the fade-period growth inputs (I26:M26).
B72: 6. MAUBOUSSIN EV / NOPAT — TWO-STAGE FRAMEWORK
B73: EV/NOPAT = 1/r + [g × (1 − r/ROIIC) / (r × (r − g))] × [1 − ((1+g)/(1+r))^N]
B74: Formula source: Mauboussin & Rappaport, "Expectations Investing" (2021); Counterpoint Global, "What Does a Price-Earnings Multiple Mean?" (2020).
B76: Input | C76: Value | D76: Rationale (Meta characteristics)
B77: r (Cost of capital / WACC) | C77: =$C$13 -> 0.099475 | D77: Linked from Section 1 WACC build
B78: g (NOPAT growth, Stage 1) | C78: 0.1 | D78: Model adjusted EBIT CAGR 2026–31E (~14%): high-teens revenue growth fading to ~10% (impressions + price), with D&A from the 2025–27 capex wave absorbing operating leverage
B79: ROIIC (Return on incremental invested capital) | C79: 0.18 | D79: Historical ROIC 25–35% (2015–25) on an asset-light ad platform; incremental returns on the AI data-center build-out are unproven, so ROIIC is set below history (assumption)
B80: N (Years of value creation / CAP) | C80: 15 | D80: Network effects across 3.6bn daily people, first-party data and ad-tech scale sustain a long competitive-advantage period; regulatory and youth-safety litigation risk
B82: Calculation | C82: Value
B83: Steady-state component: 1 / r | C83: =1/C77 -> 10.052777
B84: Value-creation factor: 1 − r / ROIIC | C84: =1-C77/C79 -> 0.44736111
B85: Growth multiplier: g × (1 − r/ROIIC) / (r × (r − g)) | C85: =C78*C84/(C77*(C77-C78)) -> -856.61362
B86: Time decay: 1 − ((1+g)/(1+r))^N | C86: =1-((1+C78)/(1+C77))^C80 -> -0.0071864997
B87: PVGO component (growth value) | C87: =C85*C86 -> 6.1560536
B88: Mauboussin EV / NOPAT (steady-state + PVGO) | C88: =C83+C87 -> 16.208831
B90: VALUATION — Applied to 2029E NOPAT | C90: USDm
B91: 2029E Adj. EBIT less cash one-off items | C91: =Model!CA173-Model!CA175 -> 134765.02
B92: Tax rate (from WACC build) | C92: =$C$10 -> 0.16
B93: 2029E NOPAT | C93: =C91*(1-C92) -> 113202.62
B94: × Mauboussin EV/NOPAT multiple | C94: =C88 -> 16.208831
B95: Implied Enterprise Value (2029E basis) | C95: =C93*C94 -> 1834882.1
B96: Less: YE2028E net debt + NCI (Model) | C96: =Model!BZ365+Model!BZ375 -> 42671.894
B97: Implied Equity Value | C97: =C95-C96 -> 1792210.2
B98: Diluted shares 2029E (m, Model) | C98: =Model!CA372 -> 2615.7554
B99: Implied share price 2029 ($) | C99: =C97/C98 -> 685.15972
B101: Current share price ($) | C101: =C52 -> 745
B102: Implied upside / (downside) | C102: =C99/C101-1 -> -0.080322528
B104: MARKET-IMPLIED EV/NOPAT TODAY | C104: USDm
B105: Current market cap (spot × diluted shares) | C105: =C52*C50 -> 1928805
B106: Plus: YE2026E net debt + NCI | C106: =C48 -> 31296.741
B107: Implied Enterprise Value (today) | C107: =C105+C106 -> 1960101.7
B108: META market-implied EV/NOPAT (on 2029E NOPAT) | C108: =C107/C93 -> 17.314986
B110: Multiple gap (Mauboussin − Market) | C110: =C88-C108 -> -1.1061549
B111: Implied re-rating headroom | C111: =C88/C108-1 -> -0.063884251

Sheet Charts
B2: Meta Platforms, Inc. — Operating Performance (2012–2025) and Model Forecast (2026E–2031E)
B3: USDm · Linked to Model. Bars = contribution of advertising and of other revenue to total revenue growth (pp). Adjusted EBITDA = model definition (Meta publishes none); income from operations GAAP. ROIC / RONTA on adjusted EBIT (current definition). 2012: no y/y growth in the model columns (FY2011 base).
C7: 2012 | D7: 2013 | E7: 2014 | F7: 2015 | G7: 2016 | H7: 2017 | I7: 2018 | J7: 2019 | K7: 2020 | L7: 2021 | M7: 2022 | N7: 2023 | O7: 2024 | P7: 2025 | Q7: 2026E | R7: 2027E | S7: 2028E | T7: 2029E | U7: 2030E | V7: 2031E
B8: Advertising contribution to growth (pp) | C8: =IFERROR(Model!F30+0,0) -> 0.30315279 | D8: =IFERROR(Model!K30+0,0) -> 0.53193162 | E8: =IFERROR(Model!P30+0,0) -> 0.57240854 | F8: =IFERROR(Model!U30+0,0) -> 0.44817905 | G8: =IFERROR(Model!Z30+0,0) -> 0.54696564 | H8: =IFERROR(Model!AE30+0,0) -> 0.47242926 | I8: =IFERROR(Model!AJ30+0,0) -> 0.37072295 | J8: =IFERROR(Model!AO30+0,0) -> 0.26222286 | K8: =IFERROR(Model!AT30+0,0) -> 0.20529867 | L8: =IFERROR(Model!AY30+0,0) -> 0.35787821 | M8: =IFERROR(Model!BD30+0,0) -> -0.010955745 | N8: =IFERROR(Model!BI30+0,0) -> 0.15698617 | O8: =IFERROR(Model!BN30+0,0) -> 0.21263584 | P8: =IFERROR(Model!BS30+0,0) -> 0.21605948 | Q8: =IFERROR(Model!BX30+0,0) -> 0.24681554 | R8: =IFERROR(Model!BY30+0,0) -> 0.18292127 | S8: =IFERROR(Model!BZ30+0,0) -> 0.15082931 | T8: =IFERROR(Model!CA30+0,0) -> 0.12977415 | U8: =IFERROR(Model!CB30+0,0) -> 0.10900881 | V8: =IFERROR(Model!CC30+0,0) -> 0.098768383
B9: Other revenue contribution to growth (pp) | C9: =IFERROR(Model!F31+0,0) -> 0.068175694 | D9: =IFERROR(Model!K31+0,0) -> 0.014934172 | E9: =IFERROR(Model!P31+0,0) -> 0.011178862 | F9: =IFERROR(Model!U31+0,0) -> -0.010027274 | G9: =IFERROR(Model!Z31+0,0) -> -0.0053547523 | H9: =IFERROR(Model!AE31+0,0) -> -0.0015196469 | I9: =IFERROR(Model!AJ31+0,0) -> 0.0028042211 | J9: =IFERROR(Model!AO31+0,0) -> 0.0038862423 | K9: =IFERROR(Model!AT31+0,0) -> 0.010665233 | L9: =IFERROR(Model!AY31+0,0) -> 0.013947537 | M9: =IFERROR(Model!BD31+0,0) -> -0.000237431 | N9: =IFERROR(Model!BI31+0,0) -> -0.00011148368 | O9: =IFERROR(Model!BN31+0,0) -> 0.0067752887 | P9: =IFERROR(Model!BS31+0,0) -> 0.0056109081 | Q9: =IFERROR(Model!BX31+0,0) -> 0.010115537 | R9: =IFERROR(Model!BY31+0,0) -> 0.0080137286 | S9: =IFERROR(Model!BZ31+0,0) -> 0.0071044597 | T9: =IFERROR(Model!CA31+0,0) -> 0.0066591245 | U9: =IFERROR(Model!CB31+0,0) -> 0.0059315287 | V9: =IFERROR(Model!CC31+0,0) -> 0.0049298277
C11: =C7 -> 2012 | D11: =D7 -> 2013 | E11: =E7 -> 2014 | F11: =F7 -> 2015 | G11: =G7 -> 2016 | H11: =H7 -> 2017 | I11: =I7 -> 2018 | J11: =J7 -> 2019 | ... V11: =V7 -> 2031E
B12: Adjusted EBITDA (model) | C12: =Model!F168 -> 1187 | D12: =Model!K168 -> 3815 | E12: =Model!P168 -> 6237 | F12: =Model!U168 -> 8170 | G12: =Model!Z168 -> 14769 | H12: =Model!AE168 -> 23228 | I12: =Model!AJ168 -> 29228 | J12: =Model!AO168 -> 34727 | K12: =Model!AT168 -> 39533 | L12: =Model!AY168 -> 54720 | M12: =Model!BD168 -> 42241 | N12: =Model!BI168 -> 63253 | O12: =Model!BN168 -> 83328 | P12: =Model!BS168 -> 101892 | Q12: =Model!BX168 -> 115613.32 | R12: =Model!BY168 -> 142894.57 | S12: =Model!BZ168 -> 170687.58 | T12: =Model!CA168 -> 197933.72 | U12: =Model!CB168 -> 225097.97 | V12: =Model!CC168 -> 250875.91
B13: Income from operations (GAAP) | C13: =Model!F116 -> 538 | D13: =Model!K116 -> 2804 | E13: =Model!P116 -> 4994 | F13: =Model!U116 -> 6225 | G13: =Model!Z116 -> 12427 | H13: =Model!AE116 -> 20203 | I13: =Model!AJ116 -> 24913 | J13: =Model!AO116 -> 23986 | K13: =Model!AT116 -> 32671 | L13: =Model!AY116 -> 46753 | M13: =Model!BD116 -> 28944 | N13: =Model!BI116 -> 46751 | O13: =Model!BN116 -> 69380 | P13: =Model!BS116 -> 83276 | Q13: =Model!BX116 -> 85600.412 | R13: =Model!BY116 -> 102233.46 | S13: =Model!BZ116 -> 119115.08 | T13: =Model!CA116 -> 134765.02 | U13: =Model!CB116 -> 155014.51 | V13: =Model!CC116 -> 175281.07
B14: Adj. EBITDA Margin % | C14: =Model!F213 -> 0.23324818 | D14: =Model!K213 -> 0.48462907 | E14: =Model!P213 -> 0.50032087 | F14: =Model!U213 -> 0.45571174 | G14: =Model!Z213 -> 0.53437296 | H14: =Model!AE213 -> 0.57137235 | I14: =Model!AJ213 -> 0.52344282 | J14: =Model!AO213 -> 0.49120896 | K14: =Model!AT213 -> 0.4598732 | L14: =Model!AY213 -> 0.464008 | M14: =Model!BD213 -> 0.36224477 | N14: =Model!BI213 -> 0.46888111 | O14: =Model!BN213 -> 0.50655011 | P14: =Model!BS213 -> 0.50701114 | Q14: =Model!BX213 -> 0.45769251 | R14: =Model!BY213 -> 0.475 | S14: =Model!BZ213 -> 0.49 | T14: =Model!CA213 -> 0.5 | U14: =Model!CB213 -> 0.51 | V14: =Model!CC213 -> 0.515
B15: Operating Margin (GAAP) % | C15: =Model!F214 -> 0.10571822 | D15: =Model!K214 -> 0.35619919 | E15: =Model!P214 -> 0.40060966 | F15: =Model!U214 -> 0.34722222 | G15: =Model!Z214 -> 0.44963456 | H15: =Model!AE214 -> 0.49696209 | I15: =Model!AJ214 -> 0.44616569 | J15: =Model!AO214 -> 0.33927889 | K15: =Model!AT214 -> 0.38005002 | L15: =Model!AY214 -> 0.39645041 | M15: =Model!BD214 -> 0.24821412 | N15: =Model!BI214 -> 0.34655528 | O15: =Model!BN214 -> 0.42176035 | P15: =Model!BS214 -> 0.41437855 | Q15: =Model!BX214 -> 0.33887677 | R15: =Model!BY214 -> 0.33983723 | S15: =Model!BZ214 -> 0.34194866 | T15: =Model!CA214 -> 0.34042968 | U15: =Model!CB214 -> 0.35121329 | V15: =Model!CC214 -> 0.35981832
C17: =C7 -> 2012 | D17: =D7 -> 2013 | E17: =E7 -> 2014 | F17: =F7 -> 2015 | G17: =G7 -> 2016 | H17: =H7 -> 2017 | I17: =I7 -> 2018 | J17: =J7 -> 2019 | ... V17: =V7 -> 2031E
B18: ROIC | C18: =IFERROR(Model!F347+0,NA()) -> 0.01286971 | D18: =IFERROR(Model!K347+0,NA()) -> 0.33961154 | E18: =IFERROR(Model!P347+0,NA()) -> 0.11899313 | F18: =IFERROR(Model!U347+0,NA()) -> 0.14311753 | G18: =IFERROR(Model!Z347+0,NA()) -> 0.34098932 | H18: =IFERROR(Model!AE347+0,NA()) -> 0.5471987 | I18: =IFERROR(Model!AJ347+0,NA()) -> 0.50499601 | J18: =IFERROR(Model!AO347+0,NA()) -> 0.51762045 | K18: =IFERROR(Model!AT347+0,NA()) -> 0.41907697 | L18: =IFERROR(Model!AY347+0,NA()) -> 0.50633933 | M18: =IFERROR(Model!BD347+0,NA()) -> 0.28464874 | N18: =IFERROR(Model!BI347+0,NA()) -> 0.40441663 | O18: =IFERROR(Model!BN347+0,NA()) -> 0.448262 | P18: =IFERROR(Model!BS347+0,NA()) -> 0.38080706 | Q18: =IFERROR(Model!BX347+0,NA()) -> 0.22995314 | R18: =IFERROR(Model!BY347+0,NA()) -> 0.20097435 | S18: =IFERROR(Model!BZ347+0,NA()) -> 0.19590913 | T18: =IFERROR(Model!CA347+0,NA()) -> 0.19743706 | U18: =IFERROR(Model!CB347+0,NA()) -> 0.20842061 | V18: =IFERROR(Model!CC347+0,NA()) -> 0.22181535
B19: RONTA | C19: =IFERROR(Model!F359+0,NA()) -> 0.016966681 | D19: =IFERROR(Model!K359+0,NA()) -> 0.39534898 | E19: =IFERROR(Model!P359+0,NA()) -> 0.51869859 | F19: =IFERROR(Model!U359+0,NA()) -> 0.47622483 | G19: =IFERROR(Model!Z359+0,NA()) -> 0.84663833 | H19: =IFERROR(Model!AE359+0,NA()) -> 0.94249403 | I19: =IFERROR(Model!AJ359+0,NA()) -> 0.73363258 | J19: =IFERROR(Model!AO359+0,NA()) -> 0.54523695 | K19: =IFERROR(Model!AT359+0,NA()) -> 0.44332286 | L19: =IFERROR(Model!AY359+0,NA()) -> 0.50540584 | M19: =IFERROR(Model!BD359+0,NA()) -> 0.2791711 | N19: =IFERROR(Model!BI359+0,NA()) -> 0.38738134 | O19: =IFERROR(Model!BN359+0,NA()) -> 0.41606872 | P19: =IFERROR(Model!BS359+0,NA()) -> 0.33948146 | Q19: =IFERROR(Model!BX359+0,NA()) -> 0.21350994 | R19: =IFERROR(Model!BY359+0,NA()) -> 0.19015553 | S19: =IFERROR(Model!BZ359+0,NA()) -> 0.18733135 | T19: =IFERROR(Model!CA359+0,NA()) -> 0.18997823 | U19: =IFERROR(Model!CB359+0,NA()) -> 0.20138834 | V19: =IFERROR(Model!CC359+0,NA()) -> 0.21500159
B20: Adj. EBITDA margin % | C20: =IFERROR(Model!F213+0,NA()) -> 0.23324818 | D20: =IFERROR(Model!K213+0,NA()) -> 0.48462907 | E20: =IFERROR(Model!P213+0,NA()) -> 0.50032087 | F20: =IFERROR(Model!U213+0,NA()) -> 0.45571174 | G20: =IFERROR(Model!Z213+0,NA()) -> 0.53437296 | H20: =IFERROR(Model!AE213+0,NA()) -> 0.57137235 | I20: =IFERROR(Model!AJ213+0,NA()) -> 0.52344282 | J20: =IFERROR(Model!AO213+0,NA()) -> 0.49120896 | K20: =IFERROR(Model!AT213+0,NA()) -> 0.4598732 | L20: =IFERROR(Model!AY213+0,NA()) -> 0.464008 | M20: =IFERROR(Model!BD213+0,NA()) -> 0.36224477 | N20: =IFERROR(Model!BI213+0,NA()) -> 0.46888111 | O20: =IFERROR(Model!BN213+0,NA()) -> 0.50655011 | P20: =IFERROR(Model!BS213+0,NA()) -> 0.50701114 | Q20: =IFERROR(Model!BX213+0,NA()) -> 0.45769251 | R20: =IFERROR(Model!BY213+0,NA()) -> 0.475 | S20: =IFERROR(Model!BZ213+0,NA()) -> 0.49 | T20: =IFERROR(Model!CA213+0,NA()) -> 0.5 | U20: =IFERROR(Model!CB213+0,NA()) -> 0.51 | V20: =IFERROR(Model!CC213+0,NA()) -> 0.515
B21: FCF margin % | C21: =IFERROR(Model!F254+0,NA()) -> 0.074081352 | D21: =IFERROR(Model!K254+0,NA()) -> 0.36191565 | E21: =IFERROR(Model!P254+0,NA()) -> 0.29087117 | F21: =IFERROR(Model!U254+0,NA()) -> 0.3389112 | G21: =IFERROR(Model!Z254+0,NA()) -> 0.42032709 | H21: =IFERROR(Model!AE254+0,NA()) -> 0.43005436 | I21: =IFERROR(Model!AJ254+0,NA()) -> 0.27506358 | J21: =IFERROR(Model!AO254+0,NA()) -> 0.29223305 | K21: =IFERROR(Model!AT254+0,NA()) -> 0.26787646 | L21: =IFERROR(Model!AY254+0,NA()) -> 0.32595036 | M21: =IFERROR(Model!BD254+0,NA()) -> 0.15812673 | N21: =IFERROR(Model!BI254+0,NA()) -> 0.31882404 | O21: =IFERROR(Model!BN254+0,NA()) -> 0.31673364 | P21: =IFERROR(Model!BS254+0,NA()) -> 0.21687748 | Q21: =IFERROR(Model!BX254+0,NA()) -> -0.032694882 | R21: =IFERROR(Model!BY254+0,NA()) -> 0.068992945 | S21: =IFERROR(Model!BZ254+0,NA()) -> 0.15285473 | T21: =IFERROR(Model!CA254+0,NA()) -> 0.23373387 | U21: =IFERROR(Model!CB254+0,NA()) -> 0.28580499 | V21: =IFERROR(Model!CC254+0,NA()) -> 0.32124422
