Workbook

Sheet Model
CF1: SCENARIO SWITCH ▼ (Bull / Base / Bear) — drives all scenario-linked forecast drivers
B2: Martin Marietta Materials, Inc. (NYSE: MLM) — 3-Statement Financial Model | CF2: Base
B3: US GAAP as reported · USD millions (per-share data in USD; shipments in millions of tons) · Source: Martin Marietta Forms 10-K (incl. Exhibit 13 annual reports to 2018) / 10-Q and Form 8-K earnings releases (Ex. 99.1), deal 8-Ks (LNA, Aug-2026), SEC EDGAR CIK 0000916076 (investor-relations releases are the same documents as filed on EDGAR)
B4: Basis notes: calendar fiscal year. Revenues incl. freight (net sales + freight & delivery revenues to 2017; ASC 606 from 2018). Product-line revenues: net sales basis to 2017, products & services (ex freight) 2018–22, total revenues from 2023. TXI from 1-Jul-2014 (cement); Bluegrass Apr-2018; Lehigh West Oct-2021; Blue Water Apr-2024; South Texas cement sold Feb-2024; Midlothian cement & Texas ready mix = discontinued operations from Q3/25 (2025 quarters shown on the recast continuing-ops basis; 2024 and earlier as originally reported); QUIKRETE asset exchange closed Feb-2026; NFM May-2026; LNA (Lhoist North America) closed 21-Aug-2026 — excluded from company FY26 guidance, modelled separately from Q3/26E.
CH5: Forecast | CI5: Historical | CJ5: Historical | CK5: Historical
B6: (USDm) | C6: 2006 | D6: 2007 | E6: 2008 | F6: 2009 | G6: 2010 | H6: 2011 | I6: 2012 | J6: Q1/13 | K6: Q2/13 | L6: Q3/13 | M6: Q4/13 | N6: 2013 | O6: Q1/14 | P6: Q2/14 | Q6: Q3/14 | R6: Q4/14 | S6: 2014 | T6: Q1/15 | U6: Q2/15 | V6: Q3/15 | W6: Q4/15 | X6: 2015 | Y6: Q1/16 | Z6: Q2/16 | AA6: Q3/16 | AB6: Q4/16 | AC6: 2016 | AD6: Q1/17 | AE6: Q2/17 | AF6: Q3/17 | AG6: Q4/17 | AH6: 2017 | AI6: Q1/18 | AJ6: Q2/18 | AK6: Q3/18 | AL6: Q4/18 | AM6: 2018 | AN6: Q1/19 | AO6: Q2/19 | AP6: Q3/19 | AQ6: Q4/19 | AR6: 2019 | AS6: Q1/20 | AT6: Q2/20 | AU6: Q3/20 | AV6: Q4/20 | AW6: 2020 | AX6: Q1/21 | AY6: Q2/21 | AZ6: Q3/21 | BA6: Q4/21 | BB6: 2021 | BC6: Q1/22 | BD6: Q2/22 | BE6: Q3/22 | BF6: Q4/22 | BG6: 2022 | BH6: Q1/23 | BI6: Q2/23 | BJ6: Q3/23 | BK6: Q4/23 | BL6: 2023 | BM6: Q1/24 | BN6: Q2/24 | BO6: Q3/24 | BP6: Q4/24 | BQ6: 2024 | BR6: Q1/25 | BS6: Q2/25 | BT6: Q3/25 | BU6: Q4/25 | BV6: 2025 | BW6: Q1/26 | BX6: Q2/26 | BY6: Q3/26E | BZ6: Q4/26E | CA6: 2026E | CB6: 2027E | CC6: 2028E | CD6: 2029E | CE6: 2030E | CF6: Modelling Notes | CH6: 5Y CAGR | CI6: 5Y CAGR | CJ6: 10Y CAGR | CK6: 19Y CAGR
CH7: 25-'30 | CI7: 20-'25 | CJ7: 15-'25 | CK7: 06-'25
B8: PRODUCT-LINE P&L — AGGREGATES · OTHER BUILDING MATERIALS · SPECIALTIES · LNA (volume × price build) | CF8: PRODUCT-LINE BUILD — modelling logic (shipments × ASP → revenues → gross profit → Adjusted EBITDA)
CN9: SCENARIO INPUT TABLE — driver assumptions per Bull / Base / Bear | CO9: Bull | CP9: Base | CQ9: Bear | CR9: Bull / Bear = Base + Δ (Δ inputs on each block header). Outlook block = high / mid / low end of FY26 ranges.
B10: Aggregates (crushed stone, sand & gravel; shipments incl. internal tons) — Building Materials business | CF10: AGGREGATES — modelling logic
B11: Shipments (million tons) | C11: 198.49 | D11: 182.326 | E11: 159.355 | F11: 123.401 | G11: 130.007 | H11: 125.074 | I11: 128.331 | J11: 22.779 | K11: 34.574 | L11: 39.631 | M11: 31.448 | N11: 128.433 | O11: 24.619 | P11: 38.974 | Q11: 45.107 | R11: 37.35 | S11: 146.05 | T11: 28.836 | U11: 42.003 | V11: 47.521 | W11: 38.001 | X11: 156.422 | Y11: 32.665 | Z11: 42.554 | AA11: 45.239 | AB11: 38.168 | AC11: 158.626 | AD11: 32.611 | AE11: 43.423 | AF11: 43.805 | AG11: 37.858 | AH11: 157.698 | AI11: 30.02 | AJ11: 48.319 | AK11: 50.324 | AL11: 42.173 | AM11: 170.836 | AN11: 37.286 | AO11: 53.153 | AP11: 56.669 | AQ11: 43.923 | AR11: 191.126 | AS11: 38.3 | AT11: 51.2 | AU11: 51.8 | AV11: 45.2 | AW11: 186.5 | AX11: 37.1 | AY11: 52.9 | AZ11: 57 | BA11: 54.2 | BB11: 201.2 | BC11: 42.1 | BD11: 57.8 | BE11: 60.2 | BF11: 47.7 | BG11: 207.7 | BH11: 41.7 | BI11: 54.5 | BJ11: 55.9 | BK11: 46.6 | BL11: 198.8 | BM11: 36.6 | BN11: 53 | BO11: 53.7 | BP11: 47.9 | BQ11: 191.1 | BR11: 39 | BS11: 52.7 | BT11: 57.9 | BU11: 48.9 | BV11: 198.5 | BW11: 43.9 | BX11: 61.6 | BY11: =BT11*(1+BY12) -> 70.412778 | BZ11: =BU11*(1+BZ12) -> 59.467787 | CA11: =SUM(BW11,BX11,BY11,BZ11) -> 235.38057 | CB11: =CA11*(1+CB12) -> 242.44198 | CC11: =CB11*(1+CC12) -> 249.71524 | CD11: =CC11*(1+CD12) -> 255.95812 | CE11: =CD11*(1+CE12) -> 262.35708 | CF11: Q3/26E–Q4/26E: prior-year quarter × (1 + Q2/26 y/y shipment growth, which includes the Feb-26 QUIKRETE aggregates sites and May-26 NFM). 2027E+: prior year × (1 + scenario volume lever AGG_vol). | CH11: =IFERROR((CE11/BV11)^(1/5)-1,"n/m") -> 0.057368709 | CI11: =IFERROR((BV11/AW11)^(1/5)-1,"n/m") -> 0.012549667 | CJ11: =IFERROR((BV11/X11)^(1/10)-1,"n/m") -> 0.0241092 | CK11: =IFERROR((BV11/C11)^(1/19)-1,"n/m") -> 2.6515352e-06 | CN11: FY26 outlook — Q2-26 release (30-Jul-26); legacy MLM, excludes LNA | CO11: High | CP11: Mid | CQ11: Low | CR11: Company guidance excludes the LNA acquisition (closed 21-Aug-26) — the model adds LNA separately.
B12: Shipments y/y % | D12: =IF(AND(ISNUMBER(D11),ISNUMBER(C11)),IFERROR(D11/C11-1,""),"") -> -0.081434833 | E12: =IF(AND(ISNUMBER(E11),ISNUMBER(D11)),IFERROR(E11/D11-1,""),"") -> -0.12598861 | F12: =IF(AND(ISNUMBER(F11),ISNUMBER(E11)),IFERROR(F11/E11-1,""),"") -> -0.22562204 | G12: =IF(AND(ISNUMBER(G11),ISNUMBER(F11)),IFERROR(G11/F11-1,""),"") -> 0.053532791 | H12: =IF(AND(ISNUMBER(H11),ISNUMBER(G11)),IFERROR(H11/G11-1,""),"") -> -0.037944111 | I12: =IF(AND(ISNUMBER(I11),ISNUMBER(H11)),IFERROR(I11/H11-1,""),"") -> 0.026040584 | N12: =IF(AND(ISNUMBER(N11),ISNUMBER(I11)),IFERROR(N11/I11-1,""),"") -> 0.00079481965 | O12: =IF(AND(ISNUMBER(O11),ISNUMBER(J11)),IFERROR(O11/J11-1,""),"") -> 0.080776153 | P12: =IF(AND(ISNUMBER(P11),ISNUMBER(K11)),IFERROR(P11/K11-1,""),"") -> 0.12726326 | Q12: =IF(AND(ISNUMBER(Q11),ISNUMBER(L11)),IFERROR(Q11/L11-1,""),"") -> 0.13817466 | R12: =IF(AND(ISNUMBER(R11),ISNUMBER(M11)),IFERROR(R11/M11-1,""),"") -> 0.18767489 | S12: =IF(AND(ISNUMBER(S11),ISNUMBER(N11)),IFERROR(S11/N11-1,""),"") -> 0.1371688 | T12: =IF(AND(ISNUMBER(T11),ISNUMBER(O11)),IFERROR(T11/O11-1,""),"") -> 0.17129047 | U12: =IF(AND(ISNUMBER(U11),ISNUMBER(P11)),IFERROR(U11/P11-1,""),"") -> 0.077718479 | ... BX12: =IF(AND(ISNUMBER(BX11),ISNUMBER(BS11)),IFERROR(BX11/BS11-1,""),"") -> 0.16888046 | BY12: =$BX$12+BY118 -> 0.21611016 | BZ12: =$BX$12+BZ118 -> 0.21611016 | CA12: =IFERROR(CA11/BV11-1,"") -> 0.1857963 | CB12: =CHOOSE(MATCH($CF$2,{"Bull","Base","Bear"},0),$CO$25,$CP$25,$CQ$25) -> 0.03 | CC12: =CHOOSE(MATCH($CF$2,{"Bull","Base","Bear"},0),$CO$26,$CP$26,$CQ$26) -> 0.03 | CD12: =CHOOSE(MATCH($CF$2,{"Bull","Base","Bear"},0),$CO$27,$CP$27,$CQ$27) -> 0.025 | CE12: =CHOOSE(MATCH($CF$2,{"Bull","Base","Bear"},0),$CO$28,$CP$28,$CQ$28) -> 0.025 | CF12: Q3/Q4-26E: Q2/26 y/y + revenue-outlook calibration Δ (Group block). 2027E–2030E: scenario lever AGG_vol (Bull/Base/Bear table →). | CN12: FY26 revenues ($m) | CO12: 7400 | CP12: 7300 | CQ12: 7200 | CR12: Raised to $7.2–7.4bn in the Q2-26 release (from $7.00–7.32bn).
B13: Average selling price — ASP ($ / ton, as reported) | I13: 10.33 | J13: 10.97 | K13: 10.48 | L13: 10.55 | M13: 10.67 | N13: 10.63 | O13: 10.82 | P13: 11 | Y13: 13.04 | Z13: 12.78 | AA13: 12.77 | AB13: 13.03 | AC13: 12.88 | AD13: 13.73 | AE13: 13.24 | AF13: 13.4 | AG13: 13.55 | AH13: 13.46 | AI13: 14.04 | AJ13: 13.7 | AK13: 13.6 | AL13: 13.61 | AM13: 13.71 | AN13: 14.36 | AO13: 14.18 | AP13: 14.37 | AQ13: 14.38 | AR13: 14.33 | AS13: 14.8 | AT13: 14.66 | AU13: 14.75 | AV13: 14.88 | AW13: 14.77 | AX13: 15.31 | AY13: 15.07 | AZ13: 14.93 | BA13: 15.09 | BB13: 15.08 | BC13: 16.17 | BD13: 16.34 | BE13: 16.65 | BF13: 17.58 | BG13: 16.68 | BH13: 19.83 | BI13: 19.37 | BJ13: 19.98 | BK13: 20.22 | BL13: 19.84 | BM13: 22.26 | BN13: 21.61 | BO13: 21.52 | BP13: 21.95 | BQ13: 21.8 | BR13: 23.77 | BS13: 23.21 | BT13: 23.24 | BU13: 23.11 | BV13: 23.3 | BW13: 23.7 | BX13: 22.74 | BY13: =BT13*(1+BY14) -> 22.769393 | BZ13: =BU13*(1+BZ14) -> 22.642025 | CA13: =IFERROR((BW11*BW13+BX11*BX13+BY11*BY13+BZ11*BZ13)/CA11,"") -> 22.903086 | CB13: =CA13*(1+CB14) -> 24.277271 | CC13: =CB13*(1+CC14) -> 25.612521 | CD13: =CC13*(1+CD14) -> 26.893147 | CE13: =CD13*(1+CE14) -> 28.237804 | CF13: Q3/26E–Q4/26E: prior-year quarter × (1 + Q2/26 y/y ASP change, which reflects acquisition mix). FY = shipment-weighted. 2027E+: scenario lever AGG_ASP. | CH13: =IFERROR((CE13/BV13)^(1/5)-1,"n/m") -> 0.0391901 | CI13: =IFERROR((BV13/AW13)^(1/5)-1,"n/m") -> 0.09545637 | CJ13: =IFERROR((BV13/X13)^(1/10)-1,"n/m") -> n/m | CK13: =IFERROR((BV13/C13)^(1/19)-1,"n/m") -> n/m | CN13: FY26 Adjusted EBITDA from continuing operations ($m) | CO13: 2500 | CP13: 2430 | CQ13: 2360 | CR13: Reaffirmed $2.36–2.50bn. Drives the Q3/Q4-26E margin calibration.
B14: ASP y/y % | D14: =IF(AND(ISNUMBER(D13),ISNUMBER(C13)),IFERROR(D13/C13-1,""),"") | E14: =IF(AND(ISNUMBER(E13),ISNUMBER(D13)),IFERROR(E13/D13-1,""),"") | F14: =IF(AND(ISNUMBER(F13),ISNUMBER(E13)),IFERROR(F13/E13-1,""),"") | G14: =IF(AND(ISNUMBER(G13),ISNUMBER(F13)),IFERROR(G13/F13-1,""),"") | H14: =IF(AND(ISNUMBER(H13),ISNUMBER(G13)),IFERROR(H13/G13-1,""),"") | I14: =IF(AND(ISNUMBER(I13),ISNUMBER(H13)),IFERROR(I13/H13-1,""),"") | N14: =IF(AND(ISNUMBER(N13),ISNUMBER(I13)),IFERROR(N13/I13-1,""),"") -> 0.029041626 | O14: =IF(AND(ISNUMBER(O13),ISNUMBER(J13)),IFERROR(O13/J13-1,""),"") -> -0.013673655 | P14: =IF(AND(ISNUMBER(P13),ISNUMBER(K13)),IFERROR(P13/K13-1,""),"") -> 0.049618321 | Q14: =IF(AND(ISNUMBER(Q13),ISNUMBER(L13)),IFERROR(Q13/L13-1,""),"") | R14: =IF(AND(ISNUMBER(R13),ISNUMBER(M13)),IFERROR(R13/M13-1,""),"") | S14: =IF(AND(ISNUMBER(S13),ISNUMBER(N13)),IFERROR(S13/N13-1,""),"") | T14: =IF(AND(ISNUMBER(T13),ISNUMBER(O13)),IFERROR(T13/O13-1,""),"") | U14: =IF(AND(ISNUMBER(U13),ISNUMBER(P13)),IFERROR(U13/P13-1,""),"") | ... BX14: =IF(AND(ISNUMBER(BX13),ISNUMBER(BS13)),IFERROR(BX13/BS13-1,""),"") -> -0.020249892 | BY14: =$BX$14 -> -0.020249892 | BZ14: =$BX$14 -> -0.020249892 | CA14: =IFERROR(CA13/BV13-1,"") -> -0.01703494 | CB14: =CHOOSE(MATCH($CF$2,{"Bull","Base","Bear"},0),$CO$30,$CP$30,$CQ$30) -> 0.06 | CC14: =CHOOSE(MATCH($CF$2,{"Bull","Base","Bear"},0),$CO$31,$CP$31,$CQ$31) -> 0.055 | CD14: =CHOOSE(MATCH($CF$2,{"Bull","Base","Bear"},0),$CO$32,$CP$32,$CQ$32) -> 0.05 | CE14: =CHOOSE(MATCH($CF$2,{"Bull","Base","Bear"},0),$CO$33,$CP$33,$CQ$33) -> 0.05 | CN14: FY26 net earnings from continuing ops attributable ($m, mid-point reconciliation) | CO14: 1043 | CP14: 1043 | CQ14: 1043 | CR14: Q2-26 release mid-point reconciliation (memo only).
B15: Revenue ÷ (shipments × ASP) — freight, internal & other (x) | C15: =IFERROR(C16/(C11*C13),"") | D15: =IFERROR(D16/(D11*D13),"") | E15: =IFERROR(E16/(E11*E13),"") | F15: =IFERROR(F16/(F11*F13),"") | G15: =IFERROR(G16/(G11*G13),"") | H15: =IFERROR(H16/(H11*H13),"") | I15: =IFERROR(I16/(I11*I13),"") -> 0.98366154 | J15: =IFERROR(J16/(J11*J13),"") -> 0.99165366 | ... BX15: =IFERROR(BX16/(BX11*BX13),"") -> 1.0943871 | BY15: =BT15 -> 1.0835347 | BZ15: =BU15 -> 1.083995 | CA15: =IFERROR(CA16/(CA11*CA13),"") -> 1.0891886 | CB15: =CA15 -> 1.0891886 | CC15: =CB15 -> 1.0891886 | CD15: =CC15 -> 1.0891886 | CE15: =CD15 -> 1.0891886 | CF15: Bridges shipments × ASP to product-line revenues (freight revenues included from 2018/2023 basis; internal sales). Forecast: prior-year quarter (Q3/Q4-26E) / prior year (2027E+). | CN15: FY26 point estimates (all cases)
B16: Revenues | H16: 1213.2 | I16: 1304 | J16: 247.8 | K16: 357.2 | L16: 411.2 | M16: 331.2 | N16: 1347.5 | O16: 263.9 | P16: 422 | Q16: 478.8 | R16: 405.4 | S16: 1570 | T16: 332.2 | U16: 481.5 | V16: 530 | W16: 449.9 | X16: 1793.7 | Y16: 406.5 | Z16: 516.3 | AA16: 542.7 | AB16: 501.2 | AC16: 2060.9 | AD16: 451.4 | AE16: 578.4 | AF16: 591.2 | AG16: 516.3 | AH16: 2137.2 | AI16: 425 | AJ16: 665.308 | AK16: 687.8 | AL16: 577.549 | AM16: 2355.673 | AN16: 541.473 | AO16: 757.802 | AP16: 818.693 | AQ16: 635.295 | AR16: 2756.738 | AS16: 570.3 | AT16: 754.9 | AU16: 766.9 | AV16: 677.2 | AW16: 2769.3 | AX16: 572.6 | AY16: 801.8 | AZ16: 857.1 | BA16: 827 | BB16: 3058.5 | BC16: 685.9 | BD16: 955.2 | BE16: 1015.7 | BF16: 849.2 | BG16: 3506 | BH16: 911.9 | BI16: 1151.4 | BJ16: 1216.3 | BK16: 1021.9 | BL16: 4301.6 | BM16: 885 | BN16: 1242 | BO16: 1250 | BP16: 1137 | BQ16: 4514 | BR16: 1002 | BS16: 1320 | BT16: 1458 | BU16: 1225 | BV16: 5004 | BW16: 1142 | BX16: 1533 | BY16: =BY11*BY13*BY15 -> 1737.1838 | BZ16: =BZ11*BZ13*BZ15 -> 1459.568 | CA16: =SUM(BW16,BX16,BY16,BZ16) -> 5871.7517 | CB16: =CB11*CB13*CB15 -> 6410.7786 | CC16: =CC11*CC13*CC15 -> 6966.2725 | CD16: =CD11*CD13*CD15 -> 7497.4508 | CE16: =CE11*CE13*CE15 -> 8069.1314 | CH16: =IFERROR((CE16/BV16)^(1/5)-1,"n/m") -> 0.10027665 | CI16: =IFERROR((BV16/AW16)^(1/5)-1,"n/m") -> 0.12561393 | CJ16: =IFERROR((BV16/X16)^(1/10)-1,"n/m") -> 0.10804334 | CK16: =IFERROR((BV16/C16)^(1/19)-1,"n/m") -> n/m | CN16: Interest expense, net of interest income ($m) | CP16: 223 | CR16: Q2-26 mid-point reconciliation (legacy; LNA financing added separately).
B17: Revenues y/y % | D17: =IF(AND(ISNUMBER(D16),ISNUMBER(C16)),IFERROR(D16/C16-1,""),"") | E17: =IF(AND(ISNUMBER(E16),ISNUMBER(D16)),IFERROR(E16/D16-1,""),"") | F17: =IF(AND(ISNUMBER(F16),ISNUMBER(E16)),IFERROR(F16/E16-1,""),"") | G17: =IF(AND(ISNUMBER(G16),ISNUMBER(F16)),IFERROR(G16/F16-1,""),"") | H17: =IF(AND(ISNUMBER(H16),ISNUMBER(G16)),IFERROR(H16/G16-1,""),"") | I17: =IF(AND(ISNUMBER(I16),ISNUMBER(H16)),IFERROR(I16/H16-1,""),"") -> 0.074843389 | N17: =IF(AND(ISNUMBER(N16),ISNUMBER(I16)),IFERROR(N16/I16-1,""),"") -> 0.033358896 | O17: =IF(AND(ISNUMBER(O16),ISNUMBER(J16)),IFERROR(O16/J16-1,""),"") -> 0.064971751 | P17: =IF(AND(ISNUMBER(P16),ISNUMBER(K16)),IFERROR(P16/K16-1,""),"") -> 0.18141097 | Q17: =IF(AND(ISNUMBER(Q16),ISNUMBER(L16)),IFERROR(Q16/L16-1,""),"") -> 0.16439689 | R17: =IF(AND(ISNUMBER(R16),ISNUMBER(M16)),IFERROR(R16/M16-1,""),"") -> 0.22403382 | S17: =IF(AND(ISNUMBER(S16),ISNUMBER(N16)),IFERROR(S16/N16-1,""),"") -> 0.16512059 | T17: =IF(AND(ISNUMBER(T16),ISNUMBER(O16)),IFERROR(T16/O16-1,""),"") -> 0.25881016 | U17: =IF(AND(ISNUMBER(U16),ISNUMBER(P16)),IFERROR(U16/P16-1,""),"") -> 0.14099526 | ... BX17: =IF(AND(ISNUMBER(BX16),ISNUMBER(BS16)),IFERROR(BX16/BS16-1,""),"") -> 0.16136364 | BY17: =IFERROR(BY16/BT16-1,"") -> 0.19148406 | BZ17: =IFERROR(BZ16/BU16-1,"") -> 0.19148406 | CA17: =IFERROR(CA16/BV16-1,"") -> 0.17341162 | CB17: =IFERROR(CB16/CA16-1,"") -> 0.0918 | CC17: =IFERROR(CC16/CB16-1,"") -> 0.08665 | CD17: =IFERROR(CD16/CC16-1,"") -> 0.07625 | CE17: =IFERROR(CE16/CD16-1,"") -> 0.07625 | CN17: Tax rate (GAAP) | CP17: =279/(1043+279) -> 0.21104387 | CR17: Implied by the Q2-26 mid-point reconciliation: tax $279m / pre-tax $1,322m.
B18: Gross profit (GAAP) | I18: 240.6 | J18: 2.1 | K18: 78.9 | L18: 108.2 | M18: 69.9 | N18: 259.1 | O18: 10.1 | P18: 100.1 | Q18: 119.3 | R18: 94.6 | S18: 324.1 | T18: 41.4 | U18: 137.2 | V18: 166.1 | W18: 122.2 | X18: 467 | Y18: 81.1 | Z18: 164.4 | AA18: 173 | AB18: 136.3 | AC18: 554.8 | AD18: 79.3 | AE18: 173.5 | AF18: 188 | AG18: 161.3 | AH18: 601.9 | AI18: 53 | AJ18: 198.54 | AK18: 209.082 | AL18: 146.133 | AM18: 606.759 | AN18: 97.562 | AO18: 251.422 | AP18: 287.024 | AQ18: 171.377 | AR18: 807.884 | AS18: 93.4 | AT18: 268 | AU18: 279.1 | AV18: 208.2 | AW18: 848.5 | AX18: 121.8 | AY18: 273 | AZ18: 292.9 | BA18: 217.1 | BB18: 904.8 | BC18: 101.9 | BD18: 309 | BE18: 330.3 | BF18: 239 | BG18: 980.3 | BH18: 238.1 | BI18: 370.9 | BJ18: 440.6 | BK18: 328.6 | BL18: 1378.1 | BM18: 239 | BN18: 392 | BO18: 438 | BP18: 379 | BQ18: 1449 | BR18: 297 | BS18: 430 | BT18: 531 | BU18: 420 | BV18: 1677 | BW18: 288 | BX18: 418 | BY18: =BY16*BY20 -> 588.09944 | BZ18: =BZ16*BZ20 -> 462.96873 | CA18: =SUM(BW18,BX18,BY18,BZ18) -> 1757.0682 | CB18: =CB16*CB20 -> 2115.5569 | CC18: =CC16*CC20 -> 2368.5327 | CD18: =CD16*CD20 -> 2624.1078 | CE18: =CE16*CE20 -> 2864.5417 | CF18: Forecast gross profit = revenues × gross margin. | CH18: =IFERROR((CE18/BV18)^(1/5)-1,"n/m") -> 0.11302371 | CI18: =IFERROR((BV18/AW18)^(1/5)-1,"n/m") -> 0.1459779 | CJ18: =IFERROR((BV18/X18)^(1/10)-1,"n/m") -> 0.13637486 | CK18: =IFERROR((BV18/C18)^(1/19)-1,"n/m") -> n/m | CN18: DD&A incl. equity-affiliate results ($m) | CP18: 800 | CR18: Q2-26 mid-point reconciliation.
B19: Gross margin before outlook calibration % (Q3/Q4-26E helper) | BY19: =BT20+(BW18+BX18)/(BW16+BX16)-(BR18+BS18)/(BR16+BS16) -> 0.3150306 | BZ19: =BU20+(BW18+BX18)/(BW16+BX16)-(BR18+BS18)/(BR16+BS16) -> 0.29369021 | CF19: Q3/Q4-26E: prior-year quarter margin + (1H/26 − 1H/25 margin drift). | CN19: Capital expenditures ($m) | CO19: 600 | CP19: 575 | CQ19: 550 | CR19: Latest published range $550–600m (Q1-26 release guidance table); Q2 release cites capex reductions without a new range.
B20: Gross margin % | C20: =IF(AND(ISNUMBER(C18),ISNUMBER(C16)),IFERROR(C18/C16,""),"") | D20: =IF(AND(ISNUMBER(D18),ISNUMBER(D16)),IFERROR(D18/D16,""),"") | E20: =IF(AND(ISNUMBER(E18),ISNUMBER(E16)),IFERROR(E18/E16,""),"") | F20: =IF(AND(ISNUMBER(F18),ISNUMBER(F16)),IFERROR(F18/F16,""),"") | G20: =IF(AND(ISNUMBER(G18),ISNUMBER(G16)),IFERROR(G18/G16,""),"") | H20: =IF(AND(ISNUMBER(H18),ISNUMBER(H16)),IFERROR(H18/H16,""),"") | I20: =IF(AND(ISNUMBER(I18),ISNUMBER(I16)),IFERROR(I18/I16,""),"") -> 0.1845092 | J20: =IF(AND(ISNUMBER(J18),ISNUMBER(J16)),IFERROR(J18/J16,""),"") -> 0.0084745763 | ... BX20: =IF(AND(ISNUMBER(BX18),ISNUMBER(BX16)),IFERROR(BX18/BX16,""),"") -> 0.27266797 | BY20: =BY19+BY121 -> 0.33853612 | BZ20: =BZ19+BZ121 -> 0.31719573 | CA20: =IFERROR(CA18/CA16,"") -> 0.29924088 | CB20: =CHOOSE(MATCH($CF$2,{"Bull","Base","Bear"},0),$CO$35,$CP$35,$CQ$35) -> 0.33 | CC20: =CHOOSE(MATCH($CF$2,{"Bull","Base","Bear"},0),$CO$36,$CP$36,$CQ$36) -> 0.34 | CD20: =CHOOSE(MATCH($CF$2,{"Bull","Base","Bear"},0),$CO$37,$CP$37,$CQ$37) -> 0.35 | CE20: =CHOOSE(MATCH($CF$2,{"Bull","Base","Bear"},0),$CO$38,$CP$38,$CQ$38) -> 0.355 | CF20: Q3/Q4-26E: margin before calibration + outlook calibration Δ (row "Outlook calibration"). 2027E+: scenario lever AGG_GM. | CH20: =IFERROR(AVERAGE(CA20,CB20,CC20,CD20,CE20),"n/m") -> 0.33484818 | CI20: =IFERROR(AVERAGE(BB20,BG20,BL20,BQ20,BV20),"n/m") -> 0.31038801 | CJ20: =IFERROR(AVERAGE(AC20,AH20,AM20,AR20,AW20,BB20,BG20,BL20,BQ20,BV20),"n/m") -> 0.29597996 | CK20: =IFERROR(AVERAGE(C20,D20,E20,F20,G20,H20,I20,N20,S20,X20,AC20,AH20,AM20,AR20,AW20,BB20,BG20,BL20,BQ20,BV20),"n/m") -> 0.27166997 | CN20: LNA run-rate cost synergies ($m) | CP20: 85 | CR20: Deal release (29-Jun-2026): ~$85m annual run-rate cost synergies.
B21: Gross profit per ton ($) | C21: =IF(AND(ISNUMBER(C18),ISNUMBER(C11)),IFERROR(C18/C11,""),"") | D21: =IF(AND(ISNUMBER(D18),ISNUMBER(D11)),IFERROR(D18/D11,""),"") | E21: =IF(AND(ISNUMBER(E18),ISNUMBER(E11)),IFERROR(E18/E11,""),"") | F21: =IF(AND(ISNUMBER(F18),ISNUMBER(F11)),IFERROR(F18/F11,""),"") | G21: =IF(AND(ISNUMBER(G18),ISNUMBER(G11)),IFERROR(G18/G11,""),"") | H21: =IF(AND(ISNUMBER(H18),ISNUMBER(H11)),IFERROR(H18/H11,""),"") | I21: =IF(AND(ISNUMBER(I18),ISNUMBER(I11)),IFERROR(I18/I11,""),"") -> 1.8748393 | J21: =IF(AND(ISNUMBER(J18),ISNUMBER(J11)),IFERROR(J18/J11,""),"") -> 0.092190175 | ... BX21: =IF(AND(ISNUMBER(BX18),ISNUMBER(BX11)),IFERROR(BX18/BX11,""),"") -> 6.7857143 | BY21: =IFERROR(BY18/BY11,"") -> 8.3521693 | BZ21: =IFERROR(BZ18/BZ11,"") -> 7.7852019 | CA21: =IFERROR(CA18/CA11,"") -> 7.4647971 | CB21: =IFERROR(CB18/CB11,"") -> 8.7260338 | CC21: =IFERROR(CC18/CC11,"") -> 9.4849343 | CD21: =IFERROR(CD18/CD11,"") -> 10.252098 | CE21: =IFERROR(CE18/CE11,"") -> 10.918484 | CH21: =IFERROR((CE21/BV21)^(1/5)-1,"n/m") -> 0.052635377 | CI21: =IFERROR((BV21/AW21)^(1/5)-1,"n/m") -> 0.13177451 | CJ21: =IFERROR((BV21/X21)^(1/10)-1,"n/m") -> 0.10962275 | CK21: =IFERROR((BV21/C21)^(1/19)-1,"n/m") -> n/m | CN21: 2H/26 share repurchases ($m) | CO21: 100 | CP21: 0 | CQ21: 0 | CR21: Post-LNA deleveraging: Base assumes no 2H buybacks (1H/26: $200m).
B22: DD&A in cost of revenues (where disclosed) | BR22: 113 | BS22: 125 | BW22: 131 | BX22: 166 | CN22: Minimum net debt / Adjusted EBITDA (x) — buyback floor 2027E+ | CO22: 2.5 | CP22: 2.25 | CQ22: 2 | CR22: MLM target: < 2.5x within 24 months of closing.
B23: Cash gross profit per ton ($) (where DD&A disclosed) | C23: =IFERROR(IF(ISNUMBER(C22),(C18+C22)/C11,""),"") | D23: =IFERROR(IF(ISNUMBER(D22),(D18+D22)/D11,""),"") | E23: =IFERROR(IF(ISNUMBER(E22),(E18+E22)/E11,""),"") | F23: =IFERROR(IF(ISNUMBER(F22),(F18+F22)/F11,""),"") | G23: =IFERROR(IF(ISNUMBER(G22),(G18+G22)/G11,""),"") | H23: =IFERROR(IF(ISNUMBER(H22),(H18+H22)/H11,""),"") | I23: =IFERROR(IF(ISNUMBER(I22),(I18+I22)/I11,""),"") | J23: =IFERROR(IF(ISNUMBER(J22),(J18+J22)/J11,""),"") | ... BX23: =IFERROR(IF(ISNUMBER(BX22),(BX18+BX22)/BX11,""),"") -> 9.4805195
B24: Memo: reported aggregates volume change % (company) | C24: -0.023 | D24: -0.081 | E24: -0.126 | F24: -0.226 | G24: 0.054 | H24: -0.038 | I24: 0.026 | J24: -0.088 | K24: -0.016 | L24: 0.081 | M24: -0.004 | N24: 0.001 | O24: 0.081 | P24: 0.127 | Q24: 0.138 | R24: 0.188 | S24: 0.137 | T24: 0.173 | U24: 0.078 | V24: 0.054 | W24: 0.017 | X24: 0.071 | Y24: 0.133 | Z24: 0.013 | AA24: -0.047 | AB24: 0.004 | AC24: 0.014 | AD24: -0.002 | AE24: 0.02 | AF24: -0.032 | AG24: -0.009 | AH24: -0.006 | AI24: -0.079 | AJ24: 0.113 | AK24: 0.149 | AL24: 0.114 | AM24: 0.083 | AN24: 0.242 | AO24: 0.099 | AP24: 0.124 | AQ24: 0.04 | AR24: 0.117 | AS24: 0.023 | AT24: -0.037 | AU24: -0.087 | AV24: 0.03 | AW24: -0.024 | AX24: -0.03 | AY24: 0.033 | AZ24: 0.102 | BA24: 0.197 | BB24: 0.079 | BC24: 0.134 | BD24: 0.093 | BE24: 0.056 | BF24: -0.12 | BG24: 0.033 | BH24: -0.008 | BI24: -0.057 | BJ24: -0.073 | BK24: -0.021 | BM24: -0.123 | BN24: -0.028 | BO24: -0.039 | BP24: 0.027 | BQ24: -0.04 | BT24: 0.08 | BU24: 0.02 | BV24: 0.04 | BW24: 0.124 | BX24: 0.17 | CN24: AGG_vol (aggregates shipments y/y) | CO24: 0.02 | CP24: Δ → | CQ24: -0.02 | CR24: Infrastructure (IIJA tail), data centers / heavy nonresidential vs. soft housing; 2026 organic guide +1–3%.
B25: Memo: reported aggregates ASP change % (company) | C25: 0.135 | D25: 0.104 | E25: 0.069 | F25: 0.021 | G25: -0.034 | H25: 0.027 | I25: 0.008 | J25: 0.057 | K25: 0.017 | L25: 0.023 | M25: 0.034 | N25: 0.03 | O25: -0.013 | P25: 0.05 | Q25: 0.058 | R25: 0.067 | S25: 0.045 | T25: 0.114 | U25: 0.085 | V25: 0.054 | W25: 0.084 | X25: 0.08 | Y25: 0.081 | Z25: 0.068 | AA25: 0.085 | AB25: 0.056 | AC25: 0.073 | AD25: 0.053 | AE25: 0.038 | AF25: 0.051 | AG25: 0.04 | AH25: 0.045 | AI25: 0.023 | AJ25: 0.035 | AK25: 0.015 | AL25: 0.005 | AM25: 0.019 | AN25: 0.023 | AO25: 0.034 | AP25: 0.053 | AQ25: 0.053 | AR25: 0.042 | AS25: 0.027 | AT25: 0.033 | AU25: 0.027 | AV25: 0.035 | AW25: 0.031 | AX25: 0.034 | AY25: 0.029 | AZ25: 0.012 | BA25: 0.014 | BB25: 0.021 | BC25: 0.056 | BD25: 0.084 | BE25: 0.116 | BF25: 0.165 | BG25: 0.106 | BH25: 0.226 | BI25: 0.186 | BJ25: 0.2 | BK25: 0.15 | BM25: 0.122 | BN25: 0.116 | BO25: 0.077 | BP25: 0.086 | BQ25: 0.099 | BT25: 0.08 | BU25: 0.053 | BV25: 0.07 | BW25: 0 | BX25: -0.02 | CN25: 2027E | CO25: =CP25+$CO$24 -> 0.05 | CP25: 0.03 | CQ25: =CP25+$CQ$24 -> 0.01
CN26: 2028E | CO26: =CP26+$CO$24 -> 0.05 | CP26: 0.03 | CQ26: =CP26+$CQ$24 -> 0.01
B27: Other Building Materials (ready mixed concrete · asphalt & paving; cement Jul-2014 → divested / discontinued 2024–26) | CF27: OTHER BUILDING MATERIALS — modelling logic | CN27: 2029E | CO27: =CP27+$CO$24 -> 0.045 | CP27: 0.025 | CQ27: =CP27+$CQ$24 -> 0.005
B28: Revenues | H28: =N(H33)+N(H36)+N(H39)+N(H42)+N(H44)+N(H46) -> 106.2 | I28: =N(I33)+N(I36)+N(I39)+N(I42)+N(I44)+N(I46) -> 332.5 | J28: =N(J33)+N(J36)+N(J39)+N(J42)+N(J44)+N(J46) -> 42.2 | K28: =N(K33)+N(K36)+N(K39)+N(K42)+N(K44)+N(K46) -> 94.9 | L28: =N(L33)+N(L36)+N(L39)+N(L42)+N(L44)+N(L46) -> 133.5 | M28: =N(M33)+N(M36)+N(M39)+N(M42)+N(M44)+N(M46) -> 102.1 | N28: =N(N33)+N(N36)+N(N39)+N(N42)+N(N44)+N(N46) -> 370.1 | O28: =N(O33)+N(O36)+N(O39)+N(O42)+N(O44)+N(O46) -> 58.4 | ... BX28: =N(BX33)+N(BX36)+N(BX39)+N(BX42)+N(BX44)+N(BX46) -> 303 | BY28: =BT28*(1+BY29) -> 409.02412 | BZ28: =BU28*(1+BZ29) -> 288.9971 | CA28: =SUM(BW28,BX28,BY28,BZ28) -> 1117.0212 | CB28: =CA28*(1+CB29) -> 1150.5319 | CC28: =CB28*(1+CC29) -> 1185.0478 | CD28: =CC28*(1+CD29) -> 1220.5992 | CE28: =CD28*(1+CE29) -> 1257.2172 | CF28: Historical = sum of the product lines reported in each period (memo rows below). Q3/Q4-26E: prior-year quarter × (1 + Q2/26 y/y). 2027E+: scenario lever OBM_growth. | CH28: =IFERROR((CE28/BV28)^(1/5)-1,"n/m") -> 0.04852727 | CI28: =IFERROR((BV28/AW28)^(1/5)-1,"n/m") -> -0.10591794 | CJ28: =IFERROR((BV28/X28)^(1/10)-1,"n/m") -> -0.022609745 | CK28: =IFERROR((BV28/C28)^(1/19)-1,"n/m") -> n/m | CN28: 2030E | CO28: =CP28+$CO$24 -> 0.045 | CP28: 0.025 | CQ28: =CP28+$CQ$24 -> 0.005
B29: Revenues y/y % | D29: =IF(AND(ISNUMBER(D28),ISNUMBER(C28)),IFERROR(D28/C28-1,""),"") | E29: =IF(AND(ISNUMBER(E28),ISNUMBER(D28)),IFERROR(E28/D28-1,""),"") | F29: =IF(AND(ISNUMBER(F28),ISNUMBER(E28)),IFERROR(F28/E28-1,""),"") | G29: =IF(AND(ISNUMBER(G28),ISNUMBER(F28)),IFERROR(G28/F28-1,""),"") | H29: =IF(AND(ISNUMBER(H28),ISNUMBER(G28)),IFERROR(H28/G28-1,""),"") | I29: =IF(AND(ISNUMBER(I28),ISNUMBER(H28)),IFERROR(I28/H28-1,""),"") -> 2.1308851 | N29: =IF(AND(ISNUMBER(N28),ISNUMBER(I28)),IFERROR(N28/I28-1,""),"") -> 0.11308271 | O29: =IF(AND(ISNUMBER(O28),ISNUMBER(J28)),IFERROR(O28/J28-1,""),"") -> 0.38388626 | P29: =IF(AND(ISNUMBER(P28),ISNUMBER(K28)),IFERROR(P28/K28-1,""),"") -> 0.24341412 | Q29: =IF(AND(ISNUMBER(Q28),ISNUMBER(L28)),IFERROR(Q28/L28-1,""),"") -> 1.8494382 | R29: =IF(AND(ISNUMBER(R28),ISNUMBER(M28)),IFERROR(R28/M28-1,""),"") -> 2.0940255 | S29: =IF(AND(ISNUMBER(S28),ISNUMBER(N28)),IFERROR(S28/N28-1,""),"") -> 1.3588219 | T29: =IF(AND(ISNUMBER(T28),ISNUMBER(O28)),IFERROR(T28/O28-1,""),"") -> 3.125 | U29: =IF(AND(ISNUMBER(U28),ISNUMBER(P28)),IFERROR(U28/P28-1,""),"") -> 1.6118644 | ... BX29: =IF(AND(ISNUMBER(BX28),ISNUMBER(BS28)),IFERROR(BX28/BS28-1,""),"") -> 0.11808118 | BY29: =$BX$29+BY118 -> 0.16531089 | BZ29: =$BX$29+BZ118 -> 0.16531089 | CA29: =IFERROR(CA28/BV28-1,"") -> 0.12602946 | CB29: =CHOOSE(MATCH($CF$2,{"Bull","Base","Bear"},0),$CO$40,$CP$40,$CQ$40) -> 0.03 | CC29: =CHOOSE(MATCH($CF$2,{"Bull","Base","Bear"},0),$CO$41,$CP$41,$CQ$41) -> 0.03 | CD29: =CHOOSE(MATCH($CF$2,{"Bull","Base","Bear"},0),$CO$42,$CP$42,$CQ$42) -> 0.03 | CE29: =CHOOSE(MATCH($CF$2,{"Bull","Base","Bear"},0),$CO$43,$CP$43,$CQ$43) -> 0.03 | CF29: Note: 2025 y/y compares the continuing-operations recast with 2024 as reported (2024 still includes Texas/California cement & ready mix). | CN29: AGG_ASP (aggregates ASP y/y) | CO29: 0.015 | CP29: Δ → | CQ29: -0.015 | CR29: Organic ASP guide +4–6% for 2026; mid-single-digit pricing through the cycle.
B30: Gross profit (GAAP) | I30: =N(I34)+N(I37)+N(I40)+N(I43)+N(I45)+N(I47) -> 13.5 | J30: =N(J34)+N(J37)+N(J40)+N(J43)+N(J45)+N(J47) -> -7.1 | K30: =N(K34)+N(K37)+N(K40)+N(K43)+N(K45)+N(K47) -> 6.3 | L30: =N(L34)+N(L37)+N(L40)+N(L43)+N(L45)+N(L47) -> 14.7 | M30: =N(M34)+N(M37)+N(M40)+N(M43)+N(M45)+N(M47) -> 8.3 | N30: =N(N34)+N(N37)+N(N40)+N(N43)+N(N45)+N(N47) -> 22.6 | O30: =N(O34)+N(O37)+N(O40)+N(O43)+N(O45)+N(O47) -> -2.5 | P30: =N(P34)+N(P37)+N(P40)+N(P43)+N(P45)+N(P47) -> 11.6 | ... BX30: =N(BX34)+N(BX37)+N(BX40)+N(BX43)+N(BX45)+N(BX47) -> 34 | BY30: =BY28*BY32 -> 69.297075 | BZ30: =BZ28*BZ32 -> 31.303094 | CA30: =SUM(BW30,BX30,BY30,BZ30) -> 118.60017 | CB30: =CB28*CB32 -> 115.05319 | CC30: =CC28*CC32 -> 124.43002 | CD30: =CD28*CD32 -> 134.26592 | CE30: =CE28*CE32 -> 138.29389 | CH30: =IFERROR((CE30/BV30)^(1/5)-1,"n/m") -> 0.071310562 | CI30: =IFERROR((BV30/AW30)^(1/5)-1,"n/m") -> -0.20618177 | CJ30: =IFERROR((BV30/X30)^(1/10)-1,"n/m") -> -0.060181606 | CK30: =IFERROR((BV30/C30)^(1/19)-1,"n/m") -> n/m | CN30: 2027E | CO30: =CP30+$CO$29 -> 0.075 | CP30: 0.06 | CQ30: =CP30+$CQ$29 -> 0.045
B31: Gross margin before outlook calibration % (Q3/Q4-26E helper) | BY31: =BT32+(BW30+BX30)/(BW28+BX28)-(BR30+BS30)/(BR28+BS28) -> 0.145915 | BZ31: =BU32+(BW30+BX30)/(BW28+BX28)-(BR30+BS30)/(BR28+BS28) -> 0.084810777 | CN31: 2028E | CO31: =CP31+$CO$29 -> 0.07 | CP31: 0.055 | CQ31: =CP31+$CQ$29 -> 0.04
B32: Gross margin % | C32: =IF(AND(ISNUMBER(C30),ISNUMBER(C28)),IFERROR(C30/C28,""),"") | D32: =IF(AND(ISNUMBER(D30),ISNUMBER(D28)),IFERROR(D30/D28,""),"") | E32: =IF(AND(ISNUMBER(E30),ISNUMBER(E28)),IFERROR(E30/E28,""),"") | F32: =IF(AND(ISNUMBER(F30),ISNUMBER(F28)),IFERROR(F30/F28,""),"") | G32: =IF(AND(ISNUMBER(G30),ISNUMBER(G28)),IFERROR(G30/G28,""),"") | H32: =IF(AND(ISNUMBER(H30),ISNUMBER(H28)),IFERROR(H30/H28,""),"") | I32: =IF(AND(ISNUMBER(I30),ISNUMBER(I28)),IFERROR(I30/I28,""),"") -> 0.040601504 | J32: =IF(AND(ISNUMBER(J30),ISNUMBER(J28)),IFERROR(J30/J28,""),"") -> -0.16824645 | ... BX32: =IF(AND(ISNUMBER(BX30),ISNUMBER(BX28)),IFERROR(BX30/BX28,""),"") -> 0.11221122 | BY32: =BY31+BY121 -> 0.16942051 | BZ32: =BZ31+BZ121 -> 0.10831629 | CA32: =IFERROR(CA30/CA28,"") -> 0.10617539 | CB32: =CHOOSE(MATCH($CF$2,{"Bull","Base","Bear"},0),$CO$45,$CP$45,$CQ$45) -> 0.1 | CC32: =CHOOSE(MATCH($CF$2,{"Bull","Base","Bear"},0),$CO$46,$CP$46,$CQ$46) -> 0.105 | CD32: =CHOOSE(MATCH($CF$2,{"Bull","Base","Bear"},0),$CO$47,$CP$47,$CQ$47) -> 0.11 | CE32: =CHOOSE(MATCH($CF$2,{"Bull","Base","Bear"},0),$CO$48,$CP$48,$CQ$48) -> 0.11 | CH32: =IFERROR(AVERAGE(CA32,CB32,CC32,CD32,CE32),"n/m") -> 0.10623508 | CI32: =IFERROR(AVERAGE(BB32,BG32,BL32,BQ32,BV32),"n/m") -> 0.15965129 | CJ32: =IFERROR(AVERAGE(AC32,AH32,AM32,AR32,AW32,BB32,BG32,BL32,BQ32,BV32),"n/m") -> 0.16366271 | CK32: =IFERROR(AVERAGE(C32,D32,E32,F32,G32,H32,I32,N32,S32,X32,AC32,AH32,AM32,AR32,AW32,BB32,BG32,BL32,BQ32,BV32),"n/m") -> 0.14373791 | CN32: 2029E | CO32: =CP32+$CO$29 -> 0.065 | CP32: 0.05 | CQ32: =CP32+$CQ$29 -> 0.035
B33: Memo: Cement revenues (TXI from Jul-2014) | Q33: 109.5 | R33: 100 | S33: 209.6 | T33: 96.6 | U33: 100.4 | V33: 110.5 | W33: 60.1 | X33: 367.6 | Y33: 69.9 | Z33: 59.8 | AA33: 60.1 | AB33: 85.4 | AC33: 364.4 | AD33: 93.7 | AE33: 99 | AF33: 88.6 | AG33: 90.2 | AH33: 371.5 | AI33: 89.2 | AJ33: 113.148 | AK33: 98.223 | AL33: 87.277 | AM33: 387.83 | AN33: 99.017 | AO33: 112.35 | AP33: 119.609 | AQ33: 108.136 | AR33: 439.112 | AS33: 106.6 | AT33: 109.5 | AU33: 115.6 | AV33: 120.8 | AW33: 452.5 | AX33: 109.6 | AY33: 116.5 | AZ33: 132.3 | BA33: 136.1 | BB33: 494.5 | BC33: 134.3 | BD33: 157.9 | BE33: 163.2 | BF33: 146.9 | BG33: 602.3 | BH33: 168.6 | BI33: 197.7 | BJ33: 199.1 | BK33: 160.2 | BL33: 725.5 | CN33: 2030E | CO33: =CP33+$CO$29 -> 0.065 | CP33: 0.05 | CQ33: =CP33+$CQ$29 -> 0.035
B34: Memo: Cement gross profit | Q34: 24.2 | R34: 28.3 | S34: 52.5 | T34: 19 | U34: 30.4 | V34: 38.2 | W34: 15.8 | X34: 103.5 | Y34: 32.6 | Z34: 24 | AA34: 29.7 | AB34: 26.7 | AC34: 120.1 | AD34: 30.9 | AE34: 29.4 | AF34: 27.6 | AG34: 29.4 | AH34: 117.3 | AI34: 23.7 | AJ34: 41.305 | AK34: 32.543 | AL34: 28.631 | AM34: 126.213 | AN34: 13.779 | AO34: 42.229 | AP34: 48.519 | AQ34: 38.895 | AR34: 143.421 | AS34: 27.3 | AT34: 43.4 | AU34: 46.5 | AV34: 53.7 | AW34: 170.9 | AX34: 15.3 | AY34: 36.1 | AZ34: 49.9 | BA34: 55.8 | BB34: 157 | BC34: 27.3 | BD34: 51.1 | BE34: 67.7 | BF34: 58.2 | BG34: 204.4 | BH34: 47.1 | BI34: 93.3 | BJ34: 108.7 | BK34: 84.5 | BL34: 333.6 | CN34: AGG_GM (aggregates gross margin) | CO34: 0.02 | CP34: Δ → | CQ34: -0.02 | CR34: FY25 33.5%; 1H/26 26.4% (inventory markup, acquired-site mix). Unit-margin expansion as pricing > cost.
B35: Memo: Cement shipments (million tons) | Q35: 1.525 | R35: 1.3 | S35: 2.824 | T35: 1.217 | U35: 1.203 | V35: 1.337 | W35: 0.802 | X35: 4.558 | Y35: 0.957 | Z35: 0.854 | AA35: 0.905 | AB35: 0.81 | AC35: 3.525 | AD35: 0.905 | AE35: 0.922 | AF35: 0.817 | AG35: 0.824 | AH35: 3.467 | AI35: 0.825 | AJ35: 1.028 | AK35: 0.879 | AL35: 0.775 | AM35: 3.508 | AN35: 0.885 | AO35: 0.978 | AP35: 1.06 | AQ35: 0.948 | AR35: 3.871 | AS35: 0.9 | AT35: 1 | AU35: 1 | AV35: 1.1 | AW35: 4 | AX35: 0.9 | AY35: 0.9 | AZ35: 1.1 | BA35: 1.1 | BB35: 4 | BC35: 1 | BD35: 1.1 | BE35: 1.1 | BF35: 0.9 | BG35: 4.2 | BH35: 1 | BI35: 1.1 | BJ35: 1.1 | BK35: 0.9 | BL35: 4 | BM35: 0.6 | BN35: 0.5 | BO35: 0.6 | BP35: 0.5 | BQ35: 2.3 | CN35: 2027E | CO35: =CP35+$CO$34 -> 0.35 | CP35: 0.33 | CQ35: =CP35+$CQ$34 -> 0.31
B36: Memo: Ready mixed concrete revenues | H36: 33 | I36: 116.3 | J36: 27.4 | K36: 36.7 | L36: 41.8 | M36: 42.7 | N36: 146.1 | O36: 38 | P36: 52.4 | Q36: 183.7 | R36: 156.3 | S36: 430.5 | T36: 127.6 | U36: 149.8 | V36: 209.6 | W36: 168.9 | X36: 655.8 | Y36: 186.8 | Z36: 214.9 | AA36: 263.7 | AB36: 237.1 | AC36: 902.6 | AD36: 222.4 | AE36: 241.9 | AF36: 240.2 | AG36: 231.6 | AH36: 936.1 | AI36: 218.5 | AJ36: 277.202 | AK36: 254.686 | AL36: 213.346 | AM36: 963.77 | AN36: 211.156 | AO36: 241.178 | AP36: 271.844 | AQ36: 223.873 | AR36: 948.052 | AS36: 189.7 | AT36: 245.1 | AU36: 254.6 | AV36: 262.7 | AW36: 952.1 | AX36: 235.3 | AY36: 268.4 | AZ36: 320.8 | BA36: 321.3 | BB36: 1145.8 | BC36: 290.1 | BD36: 226.1 | BE36: 227.4 | BF36: 207.7 | BG36: 951.3 | BH36: 220 | BI36: 271.4 | BJ36: 285.2 | BK36: 232.8 | BL36: 1009.3 | CN36: 2028E | CO36: =CP36+$CO$34 -> 0.36 | CP36: 0.34 | CQ36: =CP36+$CQ$34 -> 0.32
B37: Memo: Ready mixed concrete gross profit | I37: -1.2 | J37: -0.3 | K37: 1.6 | L37: 3.1 | M37: 3.4 | N37: 8.3 | O37: 2.9 | P37: 7 | Q37: 18.6 | R37: 10.5 | S37: 39.1 | T37: 2.1 | U37: 9.4 | V37: 23.6 | W37: 8 | X37: 43 | Y37: 18.1 | Z37: 25.3 | AA37: 39.9 | AB37: 23.1 | AC37: 99.1 | AD37: 19.8 | AE37: 26.9 | AF37: 23.9 | AG37: 21.1 | AH37: 91.7 | AI37: 15.6 | AJ37: 29.952 | AK37: 20.632 | AL37: 7.95 | AM37: 74.175 | AN37: 14.492 | AO37: 19.014 | AP37: 28.948 | AQ37: 16.324 | AR37: 78.778 | AS37: 5.9 | AT37: 26.1 | AU37: 24.7 | AV37: 22.9 | AW37: 79.6 | AX37: 19.4 | AY37: 19.1 | AZ37: 31.4 | BA37: 25.7 | BB37: 95.6 | BC37: 21.1 | BD37: 14.3 | BE37: 18.7 | BF37: 15.5 | BG37: 69.6 | BH37: 11.2 | BI37: 35.4 | BJ37: 34.1 | BK37: 21.3 | BL37: 102 | CN37: 2029E | CO37: =CP37+$CO$34 -> 0.37 | CP37: 0.35 | CQ37: =CP37+$CQ$34 -> 0.33
B38: Memo: Ready mixed concrete shipments (million cubic yards) | I38: 1.481 | J38: 0.329 | K38: 0.436 | L38: 0.496 | M38: 0.481 | N38: 1.742 | O38: 0.407 | P38: 0.552 | Q38: 2.046 | R38: 1.773 | S38: 4.779 | T38: 1.363 | U38: 1.613 | V38: 2.111 | W38: 1.618 | X38: 6.707 | Y38: 1.786 | Z38: 1.997 | AA38: 2.486 | AB38: 2.22 | AC38: 8.49 | AD38: 2.056 | AE38: 2.226 | AF38: 2.16 | AG38: 2.116 | AH38: 8.559 | AI38: 2.009 | AJ38: 2.559 | AK38: 2.232 | AL38: 1.886 | AM38: 8.685 | AN38: 1.932 | AO38: 2.162 | AP38: 2.433 | AQ38: 1.986 | AR38: 8.516 | AS38: 1.7 | AT38: 2.2 | AU38: 2.2 | AV38: 2.3 | AW38: 8.4 | AX38: 2.1 | AY38: 2.3 | AZ38: 2.7 | BA38: 2.8 | BB38: 10 | BC38: 2.4 | BD38: 1.8 | BE38: 1.7 | BF38: 1.5 | BG38: 7.4 | BH38: 1.5 | BI38: 1.8 | BJ38: 1.8 | BK38: 1.5 | BL38: 6.5 | BM38: 1.2 | BN38: 1.2 | BO38: 1.3 | BP38: 1.2 | BQ38: 5 | CN38: 2030E | CO38: =CP38+$CO$34 -> 0.375 | CP38: 0.355 | CQ38: =CP38+$CQ$34 -> 0.335
B39: Memo: Asphalt & paving revenues (asphalt + road paving before 2016) | H39: 72.6 | I39: 216.2 | J39: 14.8 | K39: 58.2 | L39: 91.7 | M39: 59.4 | N39: 224 | O39: 20.4 | P39: 65.6 | Q39: 87.2 | R39: 59.6 | S39: 232.9 | T39: 16.7 | U39: 58 | V39: 97.8 | W39: 50.9 | X39: 223.5 | Y39: 11.3 | Z39: 65.6 | AA39: 111.6 | AB39: 89.7 | AC39: 341.4 | AD39: 26.6 | AE39: 112 | AF39: 149.6 | AG39: 76.9 | AH39: 292.5 | AI39: 16.4 | AJ39: 83.14 | AK39: 99.983 | AL39: 69.19 | AM39: 268.679 | AN39: 15.846 | AO39: 82.198 | AP39: 131.099 | AQ39: 68.366 | AR39: 294.036 | AS39: 18.1 | AT39: 107 | AU39: 129.8 | AV39: 76.8 | AW39: 331.7 | AX39: 12.2 | AY39: 135.3 | AZ39: 195.9 | BA39: 170.7 | BB39: 514.2 | BC39: 54.8 | BD39: 212.3 | BE39: 309.8 | BF39: 198.6 | BG39: 775.4 | BH39: 58 | BI39: 240.9 | BJ39: 359.9 | BK39: 228.4 | BL39: 887.1 | BM39: 59 | BN39: 245 | BO39: 343 | BP39: 223 | BQ39: 869 | CN39: OBM_growth (Other Building Materials revenues y/y) | CO39: 0.03 | CP39: Δ → | CQ39: -0.03 | CR39: Ready mixed concrete & asphalt/paving (Texas ready mix divested).
B40: Memo: Asphalt & paving gross profit | I40: 14.7 | J40: -6.8 | K40: 4.7 | L40: 11.6 | M40: 4.9 | N40: 14.3 | O40: -5.4 | P40: 4.6 | Q40: 14.3 | R40: 6.6 | S40: 20 | T40: -4.8 | U40: 7.9 | V40: 22.1 | W40: 10.5 | X40: 35.8 | Y40: -6.2 | Z40: 12.8 | AA40: 30.4 | AB40: 16.5 | AC40: 53.6 | AD40: -4.8 | AE40: 20.4 | AF40: 28.8 | AG40: 20.2 | AH40: 64.7 | AI40: -7.6 | AJ40: 18.512 | AK40: 25.606 | AL40: 16.438 | AM40: 52.917 | AN40: -7.829 | AO40: 15.742 | AP40: 31.102 | AQ40: 12.168 | AR40: 50.687 | AS40: -8.1 | AT40: 21.9 | AU40: 32.6 | AV40: 13.9 | AW40: 60.4 | AX40: -8.2 | AY40: 28.7 | AZ40: 38.9 | BA40: 19.8 | BB40: 79.2 | BC40: -13.3 | BD40: 26.4 | BE40: 50.5 | BF40: 18.4 | BG40: 81.9 | BH40: -20.5 | BI40: 36.5 | BJ40: 66.1 | BK40: 26.9 | BL40: 109 | BM40: -22 | BN40: 37 | BO40: 61 | BP40: 25 | BQ40: 101 | CN40: 2027E | CO40: =CP40+$CO$39 -> 0.06 | CP40: 0.03 | CQ40: =CP40+$CQ$39 -> 0
B41: Memo: Asphalt shipments (million tons) | I41: 3.26 | J41: 0.261 | K41: 0.843 | L41: 1.225 | M41: 0.759 | N41: 3.089 | O41: 0.326 | P41: 0.95 | Q41: 1.253 | R41: 0.786 | S41: 3.315 | T41: 0.27 | U41: 0.812 | V41: 1.256 | W41: 0.579 | X41: 2.917 | Y41: 0.145 | Z41: 0.847 | AA41: 1.36 | AB41: 0.802 | AC41: 3.154 | AD41: 0.29 | AE41: 0.987 | AF41: 1.214 | AG41: 0.812 | AH41: 3.29 | AI41: 0.192 | AJ41: 0.928 | AK41: 1.103 | AL41: 0.709 | AM41: 2.933 | AN41: 0.193 | AO41: 0.814 | AP41: 1.336 | AQ41: 0.628 | AR41: 2.876 | AS41: 0.2 | AT41: 1.1 | AU41: 1.3 | AV41: 0.7 | AW41: 3.3 | AX41: 0.1 | AY41: 1.8 | AZ41: 2.8 | BA41: 2.3 | BB41: 7.1 | BC41: 0.7 | BD41: 2.6 | BE41: 3.7 | BF41: 2.1 | BG41: 9.1 | BH41: 0.5 | BI41: 2.6 | BJ41: 3.9 | BK41: 2.4 | BL41: 9.4 | BM41: 0.5 | BN41: 2.5 | BO41: 3.6 | BP41: 2.2 | BQ41: 8.8 | CN41: 2028E | CO41: =CP41+$CO$39 -> 0.06 | CP41: 0.03 | CQ41: =CP41+$CQ$39 -> 0
B42: Memo: Cement & ready mixed concrete (reported combined, Q1/24–Q2/25) | BM42: 265 | BN42: 261 | BO42: 296 | BP42: 261 | BQ42: 1083 | CN42: 2029E | CO42: =CP42+$CO$39 -> 0.06 | CP42: 0.03 | CQ42: =CP42+$CQ$39 -> 0
B43: Memo: Cement & ready mixed concrete gross profit (combined) | BM43: 31 | BN43: 72 | BO43: 89 | BP43: 68 | BQ43: 260 | CN43: 2030E | CO43: =CP43+$CO$39 -> 0.06 | CP43: 0.03 | CQ43: =CP43+$CQ$39 -> 0
B44: Memo: Ready mixed concrete and asphalt & paving (reported combined) | CN44: OBM_GM (Other Building Materials gross margin) | CO44: 0.02 | CP44: Δ → | CQ44: -0.02 | CR44: FY25 9.9%.
B45: Memo: Ready mixed concrete and asphalt & paving gross profit (combined) | CN45: 2027E | CO45: =CP45+$CO$44 -> 0.12 | CP45: 0.1 | CQ45: =CP45+$CQ$44 -> 0.08
B46: Memo: Other Building Materials as reported (continuing ops, Q3/25+ & recast Q1–Q2/25; "other" line 2011–12) | H46: 0.6 | BR46: 122 | BS46: 271 | BT46: 351 | BU46: 248 | BV46: 992 | BW46: 116 | BX46: 303 | CN46: 2028E | CO46: =CP46+$CO$44 -> 0.125 | CP46: 0.105 | CQ46: =CP46+$CQ$44 -> 0.085
B47: Memo: Other Building Materials gross profit as reported | BR47: -19 | BS47: 39 | BT47: 54 | BU47: 23 | BV47: 98 | BW47: -16 | BX47: 34 | CN47: 2029E | CO47: =CP47+$CO$44 -> 0.13 | CP47: 0.11 | CQ47: =CP47+$CQ$44 -> 0.09
CN48: 2030E | CO48: =CP48+$CO$44 -> 0.13 | CP48: 0.11 | CQ48: =CP48+$CQ$44 -> 0.09
B49: Less: interproduct / intersegment sales | H49: 0 | I49: 0 | J49: 0 | K49: 0 | L49: 0 | M49: 0 | N49: 0 | O49: 0 | P49: 0 | Q49: 0 | R49: 0 | S49: 0 | T49: 0 | U49: 0 | V49: 0 | W49: 0 | X49: 0 | Y49: 0 | Z49: 0 | AA49: 0 | AB49: -83.8 | AC49: -330.5 | AD49: -65.7 | AE49: -99.6 | AF49: -106 | AG49: -65.4 | AH49: -264 | AI49: -60.7 | AJ49: -78.178 | AK49: -66.839 | AL49: -58.557 | AM49: -264.237 | AN49: -58.361 | AO49: -67.772 | AP49: -77.419 | AQ49: -61.959 | AR49: -265.514 | AS49: -53.6 | AT49: -75.9 | AU49: -81.4 | AV49: -83.4 | AW49: -294.4 | AX49: -73.1 | AY49: -96.7 | AZ49: -115.3 | BA49: -117.8 | BB49: -403 | BC49: -88.1 | BD49: -102.3 | BE49: -104.6 | BF49: -87.5 | BG49: -382.5 | BH49: -87.8 | BI49: -121.1 | BJ49: -141.9 | BK49: -111.1 | BL49: -461.7 | BM49: -39 | BN49: -65 | BO49: -82 | BP49: -66 | BQ49: -250 | BR49: -49 | BS49: -72 | BT49: -94 | BU49: -72 | BV49: -287 | BW49: -39 | BX49: -41 | BY49: =-BY28*BY50 -> -109.53922 | BZ49: =-BZ28*BZ50 -> -83.902384 | CA49: =SUM(BW49,BX49,BY49,BZ49) -> -273.44161 | CB49: =-CB28*CB50 -> -281.64486 | CC49: =-CC28*CC50 -> -290.0942 | CD49: =-CD28*CD50 -> -298.79703 | CE49: =-CE28*CE50 -> -307.76094 | CN49: SPEC_growth (legacy Specialties revenues y/y) | CO49: 0.03 | CP49: Δ → | CQ49: -0.03 | CR49: Magnesia chemicals & dolomitic lime (steel, environmental).
B50: Interproduct sales % of Other Building Materials revenues | C50: =IFERROR(-C49/C28,"") | D50: =IFERROR(-D49/D28,"") | E50: =IFERROR(-E49/E28,"") | F50: =IFERROR(-F49/F28,"") | G50: =IFERROR(-G49/G28,"") | H50: =IFERROR(-H49/H28,"") -> 0 | I50: =IFERROR(-I49/I28,"") -> 0 | J50: =IFERROR(-J49/J28,"") -> 0 | ... BX50: =IFERROR(-BX49/BX28,"") -> 0.13531353 | BY50: =BT50 -> 0.26780627 | BZ50: =BU50 -> 0.29032258 | CA50: =IFERROR(-CA49/CA28,"") -> 0.24479536 | CB50: =$CA$50 -> 0.24479536 | CC50: =$CA$50 -> 0.24479536 | CD50: =$CA$50 -> 0.24479536 | CE50: =$CA$50 -> 0.24479536 | CF50: Forecast: prior-year quarter (Q3/Q4-26E); 2026E level held flat 2027E+. | CN50: 2027E | CO50: =CP50+$CO$49 -> 0.07 | CP50: 0.04 | CQ50: =CP50+$CQ$49 -> 0.01
CN51: 2028E | CO51: =CP51+$CO$49 -> 0.07 | CP51: 0.04 | CQ51: =CP51+$CQ$49 -> 0.01
B52: Specialties (Magnesia Specialties: magnesia-based chemicals & dolomitic lime; Premier Magnesia from 25-Jul-2025) | CF52: SPECIALTIES (legacy Magnesia Specialties) — modelling logic | CN52: 2029E | CO52: =CP52+$CO$49 -> 0.07 | CP52: 0.04 | CQ52: =CP52+$CQ$49 -> 0.01
B53: Revenues | C53: 150.7 | D53: 154.4 | E53: 167.2 | F53: 143.7 | G53: 176.4 | H53: 200.6 | I53: 202.2 | J53: 55.2 | K53: 56.6 | L53: 55.8 | M53: 58.1 | N53: 225.6 | O53: 57.4 | P53: 61.9 | Q53: 58.7 | R53: 58.2 | S53: 236.1 | T53: 58.8 | U53: 60.5 | V53: 57.3 | W53: 51 | X53: 227.5 | Y53: 59.5 | Z53: 58.8 | AA53: 60.2 | AB53: 59.4 | AC53: 238 | AD53: 63.3 | AE53: 64.6 | AF53: 58.5 | AG53: 61.7 | AH53: 248.1 | AI53: 64.9 | AJ53: 68.157 | AK53: 68.365 | AL53: 67.246 | AM53: 268.636 | AN53: 69.174 | AO53: 70.379 | AP53: 59.334 | AQ53: 51.008 | AR53: 249.894 | AS53: 59.9 | AT53: 48.9 | AU53: 55.2 | AV53: 56.8 | AW53: 220.9 | AX53: 65.3 | AY53: 70 | AZ53: 71.9 | BA53: 67.6 | BB53: 274.7 | BC53: 70.8 | BD53: 74.6 | BE53: 69 | BF53: 63.5 | BG53: 278 | BH53: 83.4 | BI53: 80.5 | BJ53: 75.5 | BK53: 76 | BL53: 315.4 | BM53: 81 | BN53: 81 | BO53: 82 | BP53: 77 | BQ53: 320 | BR53: 87 | BS53: 90 | BT53: 131 | BU53: 133 | BV53: 441 | BW53: 143 | BX53: 152 | BY53: =BT53*(1+BY54) -> 143.73709 | BZ53: =BU53*(1+BZ54) -> 145.93155 | CA53: =SUM(BW53,BX53,BY53,BZ53) -> 584.66864 | CB53: =CA53*(1+CB54) -> 608.05539 | CC53: =CB53*(1+CC54) -> 632.3776 | CD53: =CC53*(1+CD54) -> 657.67271 | CE53: =CD53*(1+CE54) -> 683.97962 | CH53: =IFERROR((CE53/BV53)^(1/5)-1,"n/m") -> 0.091744252 | CI53: =IFERROR((BV53/AW53)^(1/5)-1,"n/m") -> 0.14828205 | CJ53: =IFERROR((BV53/X53)^(1/10)-1,"n/m") -> 0.068429127 | CK53: =IFERROR((BV53/C53)^(1/19)-1,"n/m") -> 0.058140748 | CN53: 2030E | CO53: =CP53+$CO$49 -> 0.07 | CP53: 0.04 | CQ53: =CP53+$CQ$49 -> 0.01
B54: Revenues y/y % | D54: =IF(AND(ISNUMBER(D53),ISNUMBER(C53)),IFERROR(D53/C53-1,""),"") -> 0.02455209 | E54: =IF(AND(ISNUMBER(E53),ISNUMBER(D53)),IFERROR(E53/D53-1,""),"") -> 0.082901554 | F54: =IF(AND(ISNUMBER(F53),ISNUMBER(E53)),IFERROR(F53/E53-1,""),"") -> -0.14055024 | G54: =IF(AND(ISNUMBER(G53),ISNUMBER(F53)),IFERROR(G53/F53-1,""),"") -> 0.22755741 | H54: =IF(AND(ISNUMBER(H53),ISNUMBER(G53)),IFERROR(H53/G53-1,""),"") -> 0.13718821 | I54: =IF(AND(ISNUMBER(I53),ISNUMBER(H53)),IFERROR(I53/H53-1,""),"") -> 0.0079760718 | N54: =IF(AND(ISNUMBER(N53),ISNUMBER(I53)),IFERROR(N53/I53-1,""),"") -> 0.115727 | O54: =IF(AND(ISNUMBER(O53),ISNUMBER(J53)),IFERROR(O53/J53-1,""),"") -> 0.039855072 | P54: =IF(AND(ISNUMBER(P53),ISNUMBER(K53)),IFERROR(P53/K53-1,""),"") -> 0.093639576 | Q54: =IF(AND(ISNUMBER(Q53),ISNUMBER(L53)),IFERROR(Q53/L53-1,""),"") -> 0.051971326 | R54: =IF(AND(ISNUMBER(R53),ISNUMBER(M53)),IFERROR(R53/M53-1,""),"") -> 0.0017211704 | S54: =IF(AND(ISNUMBER(S53),ISNUMBER(N53)),IFERROR(S53/N53-1,""),"") -> 0.046542553 | T54: =IF(AND(ISNUMBER(T53),ISNUMBER(O53)),IFERROR(T53/O53-1,""),"") -> 0.024390244 | U54: =IF(AND(ISNUMBER(U53),ISNUMBER(P53)),IFERROR(U53/P53-1,""),"") -> -0.022617124 | ... BX54: =IF(AND(ISNUMBER(BX53),ISNUMBER(BS53)),IFERROR(BX53/BS53-1,""),"") -> 0.68888889 | BY54: =BY55+BY118 -> 0.097229708 | BZ54: =BZ55+BZ118 -> 0.097229708 | CA54: =IFERROR(CA53/BV53-1,"") -> 0.32577924 | CB54: =CHOOSE(MATCH($CF$2,{"Bull","Base","Bear"},0),$CO$50,$CP$50,$CQ$50) -> 0.04 | CC54: =CHOOSE(MATCH($CF$2,{"Bull","Base","Bear"},0),$CO$51,$CP$51,$CQ$51) -> 0.04 | CD54: =CHOOSE(MATCH($CF$2,{"Bull","Base","Bear"},0),$CO$52,$CP$52,$CQ$52) -> 0.04 | CE54: =CHOOSE(MATCH($CF$2,{"Bull","Base","Bear"},0),$CO$53,$CP$53,$CQ$53) -> 0.04 | CF54: Q3/Q4-26E: organic growth input (row below) + revenue-outlook calibration Δ. 2027E+: scenario lever SPEC_growth. | CN54: SPEC_GM (legacy Specialties gross margin) | CO54: 0.02 | CP54: Δ → | CQ54: -0.02 | CR54: FY25 31.1% (Premier Magnesia from Jul-25).
B55: Q3/Q4-26E organic growth input (before revenue calibration) | BY55: 0.05 | BZ55: 0.05 | CF55: +5% input: Q2/26 +69% y/y is inflated by Premier Magnesia (acquired 25-Jul-2025), which anniversaries in Q3. | CN55: 2027E | CO55: =CP55+$CO$54 -> 0.33 | CP55: 0.31 | CQ55: =CP55+$CQ$54 -> 0.29
B56: Gross profit (GAAP) | C56: 33.5 | D56: 43.4 | E56: 41.8 | F56: 45.6 | G56: 61.7 | H56: 75.4 | I56: 77.2 | J56: 19.6 | K56: 21.3 | L56: 19.9 | M56: 22.9 | N56: 83.7 | O56: 18.8 | P56: 23.4 | Q56: 20 | R56: 22.4 | S56: 84.6 | T56: 20.2 | U56: 21.2 | V56: 19.4 | W56: 17.9 | X56: 78.7 | Y56: 23 | Z56: 21.7 | AA56: 22.8 | AB56: 22 | AC56: 89.5 | AD56: 22.3 | AE56: 23.6 | AF56: 19.9 | AG56: 23.6 | AH56: 89.4 | AI56: 25.1 | AJ56: 24.87 | AK56: 26.823 | AL56: 26.151 | AM56: 102.905 | AN56: 26.607 | AO56: 29.212 | AP56: 23.997 | AQ56: 19.644 | AR56: 99.459 | AS56: 26.1 | AT56: 18.2 | AU56: 21 | AV56: 24.3 | AW56: 89.6 | AX56: 28.4 | AY56: 27.9 | AZ56: 28.1 | BA56: 25.9 | BB56: 110.4 | BC56: 26.8 | BD56: 25.8 | BE56: 21.6 | BF56: 21.3 | BG56: 95.5 | BH56: 25 | BI56: 27.7 | BJ56: 21.4 | BK56: 23 | BL56: 97.1 | BM56: 29 | BN56: 27 | BO56: 29 | BP56: 22 | BQ56: 107 | BR56: 38 | BS56: 36 | BT56: 34 | BU56: 29 | BV56: 137 | BW56: 45 | BX56: 50 | BY56: =BY53*BY58 -> 40.684424 | BZ56: =BZ53*BZ58 -> 35.249857 | CA56: =SUM(BW56,BX56,BY56,BZ56) -> 170.93428 | CB56: =CB53*CB58 -> 188.49717 | CC56: =CC53*CC58 -> 199.19895 | CD56: =CD53*CD58 -> 210.45527 | CE56: =CE53*CE58 -> 218.87348 | CH56: =IFERROR((CE56/BV56)^(1/5)-1,"n/m") -> 0.098233063 | CI56: =IFERROR((BV56/AW56)^(1/5)-1,"n/m") -> 0.088635548 | CJ56: =IFERROR((BV56/X56)^(1/10)-1,"n/m") -> 0.056999017 | CK56: =IFERROR((BV56/C56)^(1/19)-1,"n/m") -> 0.076944843 | CN56: 2028E | CO56: =CP56+$CO$54 -> 0.335 | CP56: 0.315 | CQ56: =CP56+$CQ$54 -> 0.295
B57: Gross margin before outlook calibration % (Q3/Q4-26E helper) | BY57: =BT58 -> 0.25954198 | BZ57: =BU58 -> 0.21804511 | CF57: Prior-year quarter margin (already includes Premier Magnesia); no 1H drift applied. | CN57: 2029E | CO57: =CP57+$CO$54 -> 0.34 | CP57: 0.32 | CQ57: =CP57+$CQ$54 -> 0.3
B58: Gross margin % | C58: =IF(AND(ISNUMBER(C56),ISNUMBER(C53)),IFERROR(C56/C53,""),"") -> 0.22229595 | D58: =IF(AND(ISNUMBER(D56),ISNUMBER(D53)),IFERROR(D56/D53,""),"") -> 0.28108808 | E58: =IF(AND(ISNUMBER(E56),ISNUMBER(E53)),IFERROR(E56/E53,""),"") -> 0.25 | F58: =IF(AND(ISNUMBER(F56),ISNUMBER(F53)),IFERROR(F56/F53,""),"") -> 0.31732777 | G58: =IF(AND(ISNUMBER(G56),ISNUMBER(G53)),IFERROR(G56/G53,""),"") -> 0.34977324 | H58: =IF(AND(ISNUMBER(H56),ISNUMBER(H53)),IFERROR(H56/H53,""),"") -> 0.37587238 | I58: =IF(AND(ISNUMBER(I56),ISNUMBER(I53)),IFERROR(I56/I53,""),"") -> 0.3818002 | J58: =IF(AND(ISNUMBER(J56),ISNUMBER(J53)),IFERROR(J56/J53,""),"") -> 0.35507246 | ... BX58: =IF(AND(ISNUMBER(BX56),ISNUMBER(BX53)),IFERROR(BX56/BX53,""),"") -> 0.32894737 | BY58: =BY57+BY121 -> 0.2830475 | BZ58: =BZ57+BZ121 -> 0.24155063 | CA58: =IFERROR(CA56/CA53,"") -> 0.29236095 | CB58: =CHOOSE(MATCH($CF$2,{"Bull","Base","Bear"},0),$CO$55,$CP$55,$CQ$55) -> 0.31 | CC58: =CHOOSE(MATCH($CF$2,{"Bull","Base","Bear"},0),$CO$56,$CP$56,$CQ$56) -> 0.315 | CD58: =CHOOSE(MATCH($CF$2,{"Bull","Base","Bear"},0),$CO$57,$CP$57,$CQ$57) -> 0.32 | CE58: =CHOOSE(MATCH($CF$2,{"Bull","Base","Bear"},0),$CO$58,$CP$58,$CQ$58) -> 0.32 | CH58: =IFERROR(AVERAGE(CA58,CB58,CC58,CD58,CE58),"n/m") -> 0.31147219 | CI58: =IFERROR(AVERAGE(BB58,BG58,BL58,BQ58,BV58),"n/m") -> 0.33966276 | CJ58: =IFERROR(AVERAGE(AC58,AH58,AM58,AR58,AW58,BB58,BG58,BL58,BQ58,BV58),"n/m") -> 0.36213857 | CK58: =IFERROR(AVERAGE(C58,D58,E58,F58,G58,H58,I58,N58,S58,X58,AC58,AH58,AM58,AR58,AW58,BB58,BG58,BL58,BQ58,BV58),"n/m") -> 0.34374054 | CN58: 2030E | CO58: =CP58+$CO$54 -> 0.34 | CP58: 0.32 | CQ58: =CP58+$CQ$54 -> 0.3
CN59: LNA_growth (LNA sales y/y) | CO59: 0.03 | CP59: Δ → | CQ59: -0.03 | CR59: LNA sales +5.0% (2025) and +4.8% (1H/26).
B60: LNA — Lhoist North America (high-calcium & dolomitic lime, industrial minerals; acquired 21-Aug-2026, Specialties) | CF60: LNA — modelling logic (closed 21-Aug-2026; NOT in company FY26 guidance) | CN60: 2027E | CO60: =CP60+$CO$59 -> 0.08 | CP60: 0.05 | CQ60: =CP60+$CQ$59 -> 0.02
B61: Memo: LNA standalone sales (pre-acquisition; not consolidated) | BQ61: 1670.314 | BV61: 1753.66 | CN61: 2028E | CO61: =CP61+$CO$59 -> 0.08 | CP61: 0.05 | CQ61: =CP61+$CQ$59 -> 0.02
B62: Memo: LNA standalone gross profit (pre-acquisition) | BQ62: 757.608 | BV62: 820.018 | CN62: 2029E | CO62: =CP62+$CO$59 -> 0.075 | CP62: 0.045 | CQ62: =CP62+$CQ$59 -> 0.015
B63: Memo: LNA standalone sales — six months (1H/25 in Q2/25 column; 1H/26 in Q2/26 column) | BS63: 863.419 | BX63: 904.568 | CN63: 2030E | CO63: =CP63+$CO$59 -> 0.075 | CP63: 0.045 | CQ63: =CP63+$CQ$59 -> 0.015
B64: Memo: LNA standalone gross profit — six months | BS64: 414.889 | BX64: 418.449 | CN64: LNA_GM (LNA standalone gross margin, pre-PPA) | CO64: 0.015 | CP64: Δ → | CQ64: -0.015 | CR64: LNA 46.8% (FY25), 46.3% (1H/26).
B65: Days consolidated in period (closing 21-Aug-2026) | BY65: 41 | BZ65: 92 | CA65: =SUM(BW65,BX65,BY65,BZ65) -> 133 | CB65: 365 | CC65: 365 | CD65: 365 | CE65: 365 | CF65: Closing 21-Aug-2026 (Form 8-K Item 2.01, filed 24-Aug-2026): 41 days in Q3/26, full Q4/26. | CN65: 2027E | CO65: =CP65+$CO$64 -> 0.48 | CP65: 0.465 | CQ65: =CP65+$CQ$64 -> 0.45
B66: Annual sales run-rate (standalone basis) | BY66: =$CA$66 -> 1837.2363 | BZ66: =$CA$66 -> 1837.2363 | CA66: =BV61*(1+CA67) -> 1837.2363 | CB66: =CA66*(1+CB67) -> 1929.0981 | CC66: =CB66*(1+CC67) -> 2025.553 | CD66: =CC66*(1+CD67) -> 2116.7029 | CE66: =CD66*(1+CE67) -> 2211.9545 | CF66: 2026E = FY2025 standalone sales × (1 + 1H/26 y/y growth). 2027E+: × (1 + scenario lever LNA_growth). | CN66: 2028E | CO66: =CP66+$CO$64 -> 0.485 | CP66: 0.47 | CQ66: =CP66+$CQ$64 -> 0.455
B67: Sales growth y/y % | BV67: =IF(AND(ISNUMBER(BV61),ISNUMBER(BQ61)),IFERROR(BV61/BQ61-1,""),"") -> 0.049898402 | CA67: =IFERROR(BX63/BS63-1,"") -> 0.047658205 | CB67: =CHOOSE(MATCH($CF$2,{"Bull","Base","Bear"},0),$CO$60,$CP$60,$CQ$60) -> 0.05 | CC67: =CHOOSE(MATCH($CF$2,{"Bull","Base","Bear"},0),$CO$61,$CP$61,$CQ$61) -> 0.05 | CD67: =CHOOSE(MATCH($CF$2,{"Bull","Base","Bear"},0),$CO$62,$CP$62,$CQ$62) -> 0.045 | CE67: =CHOOSE(MATCH($CF$2,{"Bull","Base","Bear"},0),$CO$63,$CP$63,$CQ$63) -> 0.045 | CN67: 2029E | CO67: =CP67+$CO$64 -> 0.485 | CP67: 0.47 | CQ67: =CP67+$CQ$64 -> 0.455
B68: Revenues (consolidated from closing) | BY68: =BY66*BY65/365 -> 206.37449 | BZ68: =BZ66*BZ65/365 -> 463.08422 | CA68: =SUM(BW68,BX68,BY68,BZ68) -> 669.4587 | CB68: =CB66*CB65/365 -> 1929.0981 | CC68: =CC66*CC65/365 -> 2025.553 | CD68: =CD66*CD65/365 -> 2116.7029 | CE68: =CE66*CE65/365 -> 2211.9545 | CN68: 2030E | CO68: =CP68+$CO$64 -> 0.485 | CP68: 0.47 | CQ68: =CP68+$CQ$64 -> 0.455
B69: Standalone gross margin % (before purchase accounting) | BQ69: =IF(AND(ISNUMBER(BQ62),ISNUMBER(BQ61)),IFERROR(BQ62/BQ61,""),"") -> 0.4535722 | BV69: =IF(AND(ISNUMBER(BV62),ISNUMBER(BV61)),IFERROR(BV62/BV61,""),"") -> 0.46760375 | BY69: =$CA$69 -> 0.4625954 | BZ69: =$CA$69 -> 0.4625954 | CA69: =IFERROR(BX64/BX63,"") -> 0.4625954 | CB69: =CHOOSE(MATCH($CF$2,{"Bull","Base","Bear"},0),$CO$65,$CP$65,$CQ$65) -> 0.465 | CC69: =CHOOSE(MATCH($CF$2,{"Bull","Base","Bear"},0),$CO$66,$CP$66,$CQ$66) -> 0.47 | CD69: =CHOOSE(MATCH($CF$2,{"Bull","Base","Bear"},0),$CO$67,$CP$67,$CQ$67) -> 0.47 | CE69: =CHOOSE(MATCH($CF$2,{"Bull","Base","Bear"},0),$CO$68,$CP$68,$CQ$68) -> 0.47 | CF69: 2026E = 1H/26 standalone gross margin (46.3%). 2027E+: scenario lever LNA_GM. | CN69: LNA_syn (synergy realisation % of $85m) | CO69: 0.25 | CP69: Δ → | CQ69: -0.25 | CR69: Company: run-rate synergies within ~2 years.
B70: (+) Cost synergies realised ($85m run-rate target) | BY70: 0 | BZ70: 0 | CA70: =SUM(BW70,BX70,BY70,BZ70) -> 0 | CB70: =$CP$20*CHOOSE(MATCH($CF$2,{"Bull","Base","Bear"},0),$CO$70,$CP$70,$CQ$70) -> 42.5 | CC70: =$CP$20*CHOOSE(MATCH($CF$2,{"Bull","Base","Bear"},0),$CO$71,$CP$71,$CQ$71) -> 85 | CD70: =$CP$20*CHOOSE(MATCH($CF$2,{"Bull","Base","Bear"},0),$CO$72,$CP$72,$CQ$72) -> 85 | CE70: =$CP$20*CHOOSE(MATCH($CF$2,{"Bull","Base","Bear"},0),$CO$73,$CP$73,$CQ$73) -> 85 | CF70: Company target: ~$85m annual run-rate cost synergies (deal release, 29-Jun-2026). Realisation % per scenario lever LNA_syn; booked in gross profit. | CN70: 2027E | CO70: =CP70+$CO$69 -> 0.75 | CP70: 0.5 | CQ70: =CP70+$CQ$69 -> 0.25
B71: (−) Purchase-accounting D&A (PP&E step-up + acquired intangibles) | BY71: =$CB$71*BY65/365 -> 42.684932 | BZ71: =$CB$71*BZ65/365 -> 95.780822 | CA71: =SUM(BW71,BX71,BY71,BZ71) -> 138.46575 | CB71: 380 | CC71: 380 | CD71: 380 | CE71: 380 | CF71: $380m p.a. per pro forma note (q) (Form 8-K 10-Aug-2026 Ex. 99.3): PP&E write-up (20-yr life) + $5.9bn intangibles (customer relationships $4.0bn/16y, permits $1.5bn/20y, technology $0.4bn/10y). Non-cash; added back in Adjusted EBITDA. | CN71: 2028E | CO71: =CP71+$CO$69 -> 1.25 | CP71: 1 | CQ71: =CP71+$CQ$69 -> 0.75
B72: of which: amortization of acquired intangibles | BY72: =$CB$72*BY65/365 -> 41 | BZ72: =$CB$72*BZ65/365 -> 92 | CA72: =SUM(BW72,BX72,BY72,BZ72) -> 133 | CB72: =4000/16+1500/20+400/10 -> 365 | CC72: =4000/16+1500/20+400/10 -> 365 | CD72: =4000/16+1500/20+400/10 -> 365 | CE72: =4000/16+1500/20+400/10 -> 365 | CF72: Straight-line: $4,000m/16y + $1,500m/20y + $400m/10y = $365m p.a. (pro forma note (f)). Drives the intangibles roll-forward. | CN72: 2029E | CO72: =CP72+$CO$69 -> 1.25 | CP72: 1 | CQ72: =CP72+$CQ$69 -> 0.75
B73: (−) Inventory fair-value markup expensed | BY73: 30 | BZ73: 29 | CA73: =SUM(BW73,BX73,BY73,BZ73) -> 59 | CB73: 0 | CC73: 0 | CD73: 0 | CE73: 0 | CF73: $59m step-up of acquired inventory ($152m fair value vs $93m book; pro forma note) expensed as the inventory turns (assumed Q3/Q4-26). Added back in Adjusted EBITDA (Specialties deal > $200m threshold). | CN73: 2030E | CO73: =CP73+$CO$69 -> 1.25 | CP73: 1 | CQ73: =CP73+$CQ$69 -> 0.75
B74: Gross profit (GAAP) | BY74: =BY68*BY69+BY70-BY71-BY73 -> 22.782958 | BZ74: =BZ68*BZ69+BZ70-BZ71-BZ73 -> 89.439808 | CA74: =SUM(BW74,BX74,BY74,BZ74) -> 112.22277 | CB74: =CB68*CB69+CB70-CB71-CB73 -> 559.53062 | CC74: =CC68*CC69+CC70-CC71-CC73 -> 657.00991 | CD74: =CD68*CD69+CD70-CD71-CD73 -> 699.85036 | CE74: =CE68*CE69+CE70-CE71-CE73 -> 744.61863 | CN74: M&A_spend (bolt-on acquisitions, $m) | CO74: 500 | CP74: Δ → | CQ74: -500 | CR74: Base: deleveraging pause in 2027E, bolt-ons resume 2028E.
B75: Gross margin % (GAAP) | BY75: =IFERROR(BY74/BY68,"") -> 0.11039619 | BZ75: =IFERROR(BZ74/BZ68,"") -> 0.1931394 | CA75: =IFERROR(CA74/CA68,"") -> 0.1676321 | CB75: =IFERROR(CB74/CB68,"") -> 0.29004778 | CC75: =IFERROR(CC74/CC68,"") -> 0.32436076 | CD75: =IFERROR(CD74/CD68,"") -> 0.33063231 | CE75: =IFERROR(CE74/CE68,"") -> 0.33663379 | CN75: 2027E | CO75: =CP75+$CO$74 -> 500 | CP75: 0 | CQ75: =CP75+$CQ$74 -> -500
B76: Standalone DD&A % of sales (in cost of sales) | BY76: =$CA$76 -> 0.043 | BZ76: =$CA$76 -> 0.043 | CA76: 0.043 | CB76: =CA76 -> 0.043 | CC76: =CB76 -> 0.043 | CD76: =CC76 -> 0.043 | CE76: =CD76 -> 0.043 | CF76: 1H/26 standalone DD&A $38.7m on sales $904.6m = 4.3% (Ex. 99.2 cash-flow statement). | CN76: 2028E | CO76: =CP76+$CO$74 -> 1000 | CP76: 500 | CQ76: =CP76+$CQ$74 -> 0
B77: Standalone DD&A (USDm) | BY77: =BY68*BY76 -> 8.8741029 | BZ77: =BZ68*BZ76 -> 19.912621 | CA77: =SUM(BW77,BX77,BY77,BZ77) -> 28.786724 | CB77: =CB68*CB76 -> 82.951218 | CC77: =CC68*CC76 -> 87.098779 | CD77: =CD68*CD76 -> 91.018224 | CE77: =CE68*CE76 -> 95.114045 | CN77: 2029E | CO77: =CP77+$CO$74 -> 1250 | CP77: 750 | CQ77: =CP77+$CQ$74 -> 250
B78: Standalone SG&A % of sales | BY78: =$CA$78 -> 0.088 | BZ78: =$CA$78 -> 0.088 | CA78: 0.088 | CB78: =CA78 -> 0.088 | CC78: =CB78 -> 0.088 | CD78: =CC78 -> 0.088 | CE78: =CD78 -> 0.088 | CF78: 1H/26 standalone SG&A $79.6m / sales $904.6m = 8.8%. | CN78: 2030E | CO78: =CP78+$CO$74 -> 1250 | CP78: 750 | CQ78: =CP78+$CQ$74 -> 250
B79: SG&A (USDm; consolidated in the SG&A line) | BY79: =BY68*BY78 -> 18.160955 | BZ79: =BZ68*BZ78 -> 40.751411 | CA79: =SUM(BW79,BX79,BY79,BZ79) -> 58.912366 | CB79: =CB68*CB78 -> 169.76063 | CC79: =CC68*CC78 -> 178.24866 | CD79: =CD68*CD78 -> 186.26985 | CE79: =CE68*CE78 -> 194.652
B80: Memo: LNA Adjusted EBITDA contribution (GP + PA D&A + markup + standalone D&A − SG&A) | BY80: =BY74+BY71+BY73+BY77-BY79 -> 86.181037 | BZ80: =BZ74+BZ71+BZ73+BZ77-BZ79 -> 193.38184 | CA80: =CA74+CA71+CA73+CA77-CA79 -> 279.56288 | CB80: =CB74+CB71+CB73+CB77-CB79 -> 852.7212 | CC80: =CC74+CC71+CC73+CC77-CC79 -> 945.86003 | CD80: =CD74+CD71+CD73+CD77-CD79 -> 984.59873 | CE80: =CE74+CE71+CE73+CE77-CE79 -> 1025.0807 | CF80: Deal release: LNA FY2025 Adjusted EBITDA $786m (44.8% margin) on $1.75bn gross sales; ~15x incl. run-rate synergies.
B81: Memo: LNA Adjusted EBITDA margin % | BY81: =IFERROR(BY80/BY68,"") -> 0.4175954 | BZ81: =IFERROR(BZ80/BZ68,"") -> 0.4175954 | CA81: =IFERROR(CA80/CA68,"") -> 0.4175954 | CB81: =IFERROR(CB80/CB68,"") -> 0.44203102 | CC81: =IFERROR(CC80/CC68,"") -> 0.46696385 | CD81: =IFERROR(CD80/CD68,"") -> 0.46515679 | CE81: =IFERROR(CE80/CE68,"") -> 0.46342755
B83: Corporate gross profit, freight outside product lines & unallocated Building Materials | CF83: CORPORATE & RECONCILING ITEMS
B84: Corporate gross profit (loss) | C84: -7.8 | D84: -4.6 | E84: -4.1 | F84: -3.7 | G84: -4.3 | H84: -3.4 | I84: -5.4 | J84: -2 | K84: 0.3 | L84: 0.3 | M84: -0.1 | N84: -1.4 | O84: -0.6 | P84: 0.5 | Q84: -0.8 | R84: 2.9 | S84: 2.1 | T84: -3.6 | U84: -5.9 | V84: -6.9 | W84: 10.4 | X84: -6.2 | Y84: -4 | Z84: -1.5 | AA84: -3.2 | AB84: 0.5 | AC84: -8.1 | AD84: -0.4 | AE84: 0.3 | AF84: 3.5 | AG84: 3.5 | AH84: 6.9 | AI84: 1.9 | AJ84: 3.168 | AK84: -0.579 | AL84: 3.098 | AM84: 7.572 | AN84: -0.474 | AO84: 0.195 | AP84: 1.725 | AQ84: 1.579 | AR84: 3.024 | AS84: -1 | AT84: 4.5 | AU84: 0.7 | AV84: 3.2 | AW84: 7.5 | AX84: -0.8 | AY84: 0.5 | AZ84: 0.5 | BA84: 1.8 | BB84: 2 | BC84: -7.9 | BD84: 1.6 | BE84: -2.1 | BF84: 2.8 | BG84: -5.8 | BH84: 1.9 | BI84: -3.4 | BJ84: 5.1 | BK84: -0.8 | BL84: 2.8 | BM84: -5 | BN84: -11 | BO84: -18 | BP84: -5 | BQ84: -39 | BR84: -1 | BS84: -9 | BT84: -8 | BU84: -4 | BV84: -23 | BW84: -7 | BX84: -7 | BY84: =(BW84+BX84)/2 -> -7 | BZ84: =(BW84+BX84)/2 -> -7 | CA84: =SUM(BW84,BX84,BY84,BZ84) -> -28 | CB84: -30 | CC84: -30 | CD84: -30 | CE84: -30 | CF84: Q3/Q4-26E: 1H/26 run-rate; 2027E+: −$30m p.a. input.
B85: Freight revenues outside product-line tables (net-sales basis to 2017; ex-freight basis 2018–22) | C85: 263.5 | D85: 239.5 | E85: 256.8 | F85: 206 | G85: 232 | H85: 193.9 | I85: 198.9 | J85: 39.8 | K85: 54 | L85: 64.8 | M85: 53.6 | N85: 212.3 | O85: 49 | P85: 67.3 | Q85: 85.8 | R85: 76.8 | S85: 278.9 | T85: 59.5 | U85: 71.2 | V85: 77 | W85: 63.8 | X85: 271.5 | Y85: 54.8 | Z85: 61.9 | AA85: 65.6 | AB85: 59.8 | AC85: 242 | AD85: 52.2 | AE85: 67.2 | AF85: 65.6 | AG85: 59.2 | AH85: 244.2 | AI85: 48.7 | AJ85: 73.626 | AK85: 77.422 | AL85: 64.167 | AM85: 263.914 | AN85: 60.65 | AO85: 83.333 | AP85: 97.086 | AQ85: 75.711 | AR85: 316.78 | AS85: 67.2 | AT85: 81.1 | AU85: 80.7 | AV85: 68.7 | AW85: 297.8 | AX85: 60.5 | AY85: 82.6 | AZ85: 94.6 | BA85: 91.5 | BB85: 329.3 | BC85: 83 | BD85: 117.9 | BE85: 131.2 | BF85: 98.1 | BG85: 430.2 | BH85: 0 | BI85: 0 | BJ85: 0 | BK85: 0 | BL85: 0 | BM85: 0 | BN85: 0 | BO85: 0 | BP85: 0 | BQ85: 0 | BR85: 0 | BS85: 0 | BT85: 0 | BU85: 0 | BV85: 0 | BW85: 0 | BX85: 0
B86: Freight gross profit outside product-line tables (2018–22) | C86: 0 | D86: 0 | E86: 0 | F86: 0 | G86: 0 | H86: 0 | I86: 0 | J86: 0 | K86: 0 | L86: 0 | M86: 0 | N86: 0 | O86: 0 | P86: 0 | Q86: 0 | R86: 0 | S86: 0 | T86: 0 | U86: 0 | V86: 0 | W86: 0 | X86: 0 | Y86: 0 | Z86: 0 | AA86: 0 | AB86: 0 | AC86: 0 | AD86: 0 | AE86: 0 | AF86: 0 | AG86: 0 | AH86: 0 | AI86: -1.3 | AJ86: -0.43 | AK86: -1.123 | AL86: -1.117 | AM86: -3.964 | AN86: -1.23 | AO86: -0.947 | AP86: -0.67 | AQ86: -1.398 | AR86: -4.246 | AS86: -1.2 | AT86: -1.6 | AU86: -0.1 | AV86: -0.8 | AW86: -3.7 | AX86: -1.2 | AY86: -0.2 | AZ86: 0.2 | BA86: 0.6 | BB86: -0.6 | BC86: 0.2 | BD86: -3 | BE86: 1.1 | BF86: -1 | BG86: -2.6 | BH86: 0 | BI86: 0 | BJ86: 0 | BK86: 0 | BL86: 0 | BM86: 0 | BN86: 0 | BO86: 0 | BP86: 0 | BQ86: 0 | BR86: 0 | BS86: 0 | BT86: 0 | BU86: 0 | BV86: 0 | BW86: 0 | BX86: 0
B87: Building Materials revenues not split by product line (to Q2/11; segment total) | C87: 1792.2 | D87: 1813.2 | E87: 1696.1 | F87: 1352.9 | G87: 1374.5
B88: Building Materials gross profit not split by product line (to Q3/12) | C88: 496.8 | D88: 532.2 | E88: 432.7 | F88: 295.8 | G88: 264.6 | H88: 230
B90: Future acquisitions (M&A lever — bolt-ons, unallocated; deals closed from 2027E) | CF90: M&A LEVER — acquired sales = spend ÷ EV/sales; mid-year convention
B91: Acquisition spend (USDm, scenario) | CA91: 0 | CB91: =MAX(0,CHOOSE(MATCH($CF$2,{"Bull","Base","Bear"},0),$CO$75,$CP$75,$CQ$75)) -> 0 | CC91: =MAX(0,CHOOSE(MATCH($CF$2,{"Bull","Base","Bear"},0),$CO$76,$CP$76,$CQ$76)) -> 500 | CD91: =MAX(0,CHOOSE(MATCH($CF$2,{"Bull","Base","Bear"},0),$CO$77,$CP$77,$CQ$77)) -> 750 | CE91: =MAX(0,CHOOSE(MATCH($CF$2,{"Bull","Base","Bear"},0),$CO$78,$CP$78,$CQ$78)) -> 750 | CF91: Scenario lever M&A_spend. MLM deployed ~$0.5–3.6bn p.a. on acquisitions in 2018–25 (Bluegrass, Lehigh West, Blue Water, Albert Frei, Premier Magnesia, NFM) plus LNA ($13.5bn) in 2026; Base assumes a deleveraging pause in 2027.
B92: Purchase multiple — EV / sales (x) | CA92: 0 | CB92: 3 | CC92: =CB92 -> 3 | CD92: =CC92 -> 3 | CE92: =CD92 -> 3
B93: Annualised sales acquired in the year | CA93: 0 | CB93: =IFERROR(CB91/CB92,0) -> 0 | CC93: =IFERROR(CC91/CC92,0) -> 166.66667 | CD93: =IFERROR(CD91/CD92,0) -> 250 | CE93: =IFERROR(CE91/CE92,0) -> 250
B94: Growth of acquired businesses after acquisition % | CA94: 0 | CB94: 0.05 | CC94: =CB94 -> 0.05 | CD94: =CC94 -> 0.05 | CE94: =CD94 -> 0.05
B95: Run-rate sales of businesses acquired (year end) | CA95: 0 | CB95: =CA95*(1+CB94)+CB93 -> 0 | CC95: =CB95*(1+CC94)+CC93 -> 166.66667 | CD95: =CC95*(1+CD94)+CD93 -> 425 | CE95: =CD95*(1+CE94)+CE93 -> 696.25
B96: Revenues from future acquisitions | CA96: 0 | CB96: =CA95*(1+CB94)+0.5*CB93 -> 0 | CC96: =CB95*(1+CC94)+0.5*CC93 -> 83.333333 | CD96: =CC95*(1+CD94)+0.5*CD93 -> 300 | CE96: =CD95*(1+CE94)+0.5*CE93 -> 571.25 | CF96: Mid-year convention: deals close evenly through the year (half a year of sales in year 1).
B97: Gross margin of acquired businesses % (after D&A) | CA97: 0 | CB97: 0.25 | CC97: =CB97 -> 0.25 | CD97: =CC97 -> 0.25 | CE97: =CD97 -> 0.25
B98: Gross profit from future acquisitions | CA98: 0 | CB98: =CB96*CB97 -> 0 | CC98: =CC96*CC97 -> 20.833333 | CD98: =CD96*CD97 -> 75 | CE98: =CE96*CE97 -> 142.8125
B99: D&A of acquired businesses % of sales (incl. step-ups) | CA99: 0 | CB99: 0.12 | CC99: =CB99 -> 0.12 | CD99: =CC99 -> 0.12 | CE99: =CD99 -> 0.12
B100: D&A from future acquisitions (in cost of revenues) | CA100: 0 | CB100: =CB96*CB99 -> 0 | CC100: =CC96*CC99 -> 10 | CD100: =CD96*CD99 -> 36 | CE100: =CE96*CE99 -> 68.55
B101: PP&E & mineral reserves % of spend | CA101: 0 | CB101: 0.55 | CC101: =CB101 -> 0.55 | CD101: =CC101 -> 0.55 | CE101: =CD101 -> 0.55 | CF101: Aggregates bolt-ons: consideration mostly allocated to PP&E / mineral reserves; balance to intangibles and goodwill.
B102: Acquired intangibles % of spend | CA102: 0 | CB102: 0.1 | CC102: =CB102 -> 0.1 | CD102: =CC102 -> 0.1 | CE102: =CD102 -> 0.1
...

Sheet Bull-Base-Bear
B2: Martin Marietta Materials (MLM) — Bull / Base / Bear Case P&L Summary | J2: Share price ($): | K2: =Model!$CA$426 -> 518.7
B3: Adjusted figures (company current definition: Adjusted EBITDA / adjusted EPS from continuing operations) · USD millions · Live panel linked to Model — toggle scenario via Model!CF2. Bull and Bear panels are value snapshots generated from the Model with the switch set to each case. 2026E includes LNA from 21-Aug-2026. | J3: As of: | K3: =TODAY() -> 46299
B5: Scenario: | C5: =Model!$CF$2 -> Base | N5: Scenario: | O5: Bull | P5: Snapshot (values) — Model run with switch = Bull | Z5: Scenario: | AA5: Bear | AB5: Snapshot (values) — Model run with switch = Bear
B7: (USDm, except EPS and shares) | C7: 2025A | D7: 2026E | E7: 2027E | F7: 2028E | G7: 2029E | H7: 2030E | I7: 25-'30 CAGR | J7: LT Hist Avg | K7: LT Hist Min | L7: LT Hist Max | N7: (USDm, except EPS and shares) | O7: 2025A | P7: 2026E | Q7: 2027E | R7: 2028E | S7: 2029E | T7: 2030E | U7: 25-'30 CAGR | V7: LT Hist Avg | W7: LT Hist Min | X7: LT Hist Max | Z7: (USDm, except EPS and shares) | AA7: 2025A | AB7: 2026E | AC7: 2027E | AD7: 2028E | AE7: 2029E | AF7: 2030E | AG7: 25-'30 CAGR | AH7: LT Hist Avg | AI7: LT Hist Min | AJ7: LT Hist Max
B9: Revenues | C9: =Model!BV152 -> 6150 | D9: =Model!CA152 -> 7969.4587 | E9: =Model!CB152 -> 9816.819 | F9: =Model!CC152 -> 10602.49 | G9: =Model!CD152 -> 11493.629 | H9: =Model!CE152 -> 12485.772 | I9: =IFERROR((H9/C9)^(1/5)-1,"n/m") -> 0.15214743 | N9: Revenues | O9: 6150 | P9: 8069.4587 | Q9: 10326.592 | R9: 11672.073 | S9: 13190.641 | T9: 14888.058 | U9: 0.19341801 | Z9: Revenues | AA9: 6150 | AB9: 7869.4587 | AC9: 9400.9541 | AD9: 9752.4 | AE9: 10086.628 | AF9: 10477.544 | AG9: 0.11244071
B10: Revenues y/y % | D10: =IFERROR(D9/C9-1,"") -> 0.29584694 | E10: =IFERROR(E9/D9-1,"") -> 0.231805 | F10: =IFERROR(F9/E9-1,"") -> 0.080033158 | G10: =IFERROR(G9/F9-1,"") -> 0.08404993 | H10: =IFERROR(H9/G9-1,"") -> 0.086321149 | N10: Revenues y/y % | P10: 0.31210711 | Q10: 0.27971306 | R10: 0.13029283 | S10: 0.13010275 | T10: 0.1286834 | Z10: Revenues y/y % | AB10: 0.27958678 | AC10: 0.19461254 | AD10: 0.037384072 | AE10: 0.034271353 | AF10: 0.038755825
B11: Aggregates shipments y/y % | C11: =Model!BV231 -> 0.038723182 | D11: =Model!CA231 -> 0.1857963 | E11: =Model!CB231 -> 0.03 | F11: =Model!CC231 -> 0.03 | G11: =Model!CD231 -> 0.025 | H11: =Model!CE231 -> 0.025 | N11: Aggregates shipments y/y % | O11: 0.038723182 | P11: 0.20197455 | Q11: 0.05 | R11: 0.05 | S11: 0.045 | T11: 0.045 | Z11: Aggregates shipments y/y % | AA11: 0.038723182 | AB11: 0.16961805 | AC11: 0.01 | AD11: 0.01 | AE11: 0.005 | AF11: 0.005
B12: Adjusted EBITDA (continuing operations) | C12: =Model!BV204 -> 2065 | D12: =Model!CA204 -> 2709.5629 | E12: =Model!CB204 -> 3592.3373 | F12: =Model!CC204 -> 4007.7658 | G12: =Model!CD204 -> 4411.5047 | H12: =Model!CE204 -> 4811.2674 | I12: =IFERROR((H12/C12)^(1/5)-1,"n/m") -> 0.18431679 | N12: Adjusted EBITDA (continuing operations) | O12: 2065 | P12: 2779.5629 | Q12: 3991.8064 | R12: 4627.5928 | S12: 5283.3716 | T12: 5966.5414 | U12: 0.23640434 | Z12: Adjusted EBITDA (continuing operations) | AA12: 2065 | AB12: 2639.5629 | AC12: 3238.4502 | AD12: 3488.1157 | AE12: 3682.491 | AF12: 3856.7328 | AG12: 0.13307824
B13: Adjusted EBITDA margin % | C13: =IFERROR(C12/C9,"") -> 0.33577236 | D13: =IFERROR(D12/D9,"") -> 0.33999334 | E13: =IFERROR(E12/E9,"") -> 0.365937 | F13: =IFERROR(F12/F9,"") -> 0.37800232 | G13: =IFERROR(G12/G9,"") -> 0.38382176 | H13: =IFERROR(H12/H9,"") -> 0.38534001 | J13: =IFERROR(AVERAGE(Model!C205,Model!D205,Model!E205,Model!F205,Model!G205,Model!H205,Model!I205,Model!N205,Model!S205,Model!X205,Model!AC205,Model!AH205,Model!AM205,Model!AR205,Model!AW205,Model!BB205,Model!BG205,Model!BL205,Model!BQ205,Model!BV205),"") -> 0.24703766 | K13: =IFERROR(MIN(Model!C205,Model!D205,Model!E205,Model!F205,Model!G205,Model!H205,Model!I205,Model!N205,Model!S205,Model!X205,Model!AC205,Model!AH205,Model!AM205,Model!AR205,Model!AW205,Model!BB205,Model!BG205,Model!BL205,Model!BQ205,Model!BV205),"") -> 0.16190616 | L13: =IFERROR(MAX(Model!C205,Model!D205,Model!E205,Model!F205,Model!G205,Model!H205,Model!I205,Model!N205,Model!S205,Model!X205,Model!AC205,Model!AH205,Model!AM205,Model!AR205,Model!AW205,Model!BB205,Model!BG205,Model!BL205,Model!BQ205,Model!BV205),"") -> 0.33577236 | N13: Adjusted EBITDA margin % | O13: 0.33577236 | P13: 0.34445469 | Q13: 0.38655604 | R13: 0.3964671 | S13: 0.4005394 | T13: 0.40076023 | V13: 0.24703766 | W13: 0.16190616 | X13: 0.33577236 | Z13: Adjusted EBITDA margin % | AA13: 0.33577236 | AB13: 0.33541861 | AC13: 0.34448102 | AD13: 0.35766742 | AE13: 0.36508643 | AF13: 0.36809513 | AH13: 0.24703766 | AI13: 0.16190616 | AJ13: 0.33577236
B15: Earnings from Operations (GAAP) | C15: =Model!BV160 -> 1437 | D15: =Model!CA160 -> 1487.3104 | E15: =Model!CB160 -> 2221.7368 | F15: =Model!CC160 -> 2571.3706 | G15: =Model!CD160 -> 2881.0247 | H15: =Model!CE160 -> 3175.3209 | I15: =IFERROR((H15/C15)^(1/5)-1,"n/m") -> 0.17183421 | N15: Earnings from Operations (GAAP) | O15: 1437 | P15: 1557.3104 | Q15: 2567.9904 | R15: 3078.826 | S15: 3574.3263 | T15: 4077.7144 | U15: 0.23194695 | Z15: Earnings from Operations (GAAP) | AA15: 1437 | AB15: 1417.3104 | AC15: 1909.902 | AD15: 2138.4196 | AE15: 2297.5341 | AF15: 2429.85 | AG15: 0.11077102
B16: Earnings from operations y/y % | D16: =IFERROR(D15/C15-1,"") -> 0.035010717 | E16: =IFERROR(E15/D15-1,"") -> 0.49379497 | F16: =IFERROR(F15/E15-1,"") -> 0.15736959 | G16: =IFERROR(G15/F15-1,"") -> 0.12042374 | H16: =IFERROR(H15/G15-1,"") -> 0.10214986 | N16: Earnings from operations y/y % | P16: 0.083723313 | Q16: 0.6489907 | R16: 0.19892427 | S16: 0.16093809 | T16: 0.1408344 | Z16: Earnings from operations y/y % | AB16: -0.013701879 | AC16: 0.34755378 | AD16: 0.11964885 | AE16: 0.074407551 | AF16: 0.057590386
B17: Operating margin (GAAP) % | C17: =IFERROR(C15/C9,"") -> 0.23365854 | D17: =IFERROR(D15/D9,"") -> 0.18662628 | E17: =IFERROR(E15/E9,"") -> 0.22631942 | F17: =IFERROR(F15/F9,"") -> 0.24252516 | G17: =IFERROR(G15/G9,"") -> 0.25066276 | H17: =IFERROR(H15/H9,"") -> 0.25431515 | J17: =IFERROR(AVERAGE(Model!C240,Model!D240,Model!E240,Model!F240,Model!G240,Model!H240,Model!I240,Model!N240,Model!S240,Model!X240,Model!AC240,Model!AH240,Model!AM240,Model!AR240,Model!AW240,Model!BB240,Model!BG240,Model!BL240,Model!BQ240,Model!BV240),"") -> 0.17151852 | K17: =IFERROR(MIN(Model!C240,Model!D240,Model!E240,Model!F240,Model!G240,Model!H240,Model!I240,Model!N240,Model!S240,Model!X240,Model!AC240,Model!AH240,Model!AM240,Model!AR240,Model!AW240,Model!BB240,Model!BG240,Model!BL240,Model!BQ240,Model!BV240),"") -> 0.076069886 | L17: =IFERROR(MAX(Model!C240,Model!D240,Model!E240,Model!F240,Model!G240,Model!H240,Model!I240,Model!N240,Model!S240,Model!X240,Model!AC240,Model!AH240,Model!AM240,Model!AR240,Model!AW240,Model!BB240,Model!BG240,Model!BL240,Model!BQ240,Model!BV240),"") -> 0.41416769 | N17: Operating margin (GAAP) % | O17: 0.23365854 | P17: 0.19298821 | Q17: 0.24867744 | R17: 0.26377714 | S17: 0.27097442 | T17: 0.27389163 | V17: 0.17151852 | W17: 0.076069886 | X17: 0.41416769 | Z17: Operating margin (GAAP) % | AA17: 0.23365854 | AB17: 0.18010265 | AC17: 0.20316044 | AD17: 0.21927111 | AE17: 0.2277802 | AF17: 0.23191028 | AH17: 0.17151852 | AI17: 0.076069886 | AJ17: 0.41416769
B19: Adjusted Net Earnings (continuing ops, attributable to MLM) | C19: =Model!BV222 -> 1020.6852 | D19: =Model!CA222 -> 1088.1684 | E19: =Model!CB222 -> 1307.885 | F19: =Model!CC222 -> 1617.8143 | G19: =Model!CD222 -> 1887.9942 | H19: =Model!CE222 -> 2108.0983 | I19: =IFERROR((H19/C19)^(1/5)-1,"n/m") -> 0.15611174 | N19: Adjusted Net Earnings (continuing ops, attributable to MLM) | O19: 1020.6852 | P19: 1143.3954 | Q19: 1575.7248 | R19: 2000.612 | S19: 2370.8108 | T19: 2695.3047 | U19: 0.21434814 | Z19: Adjusted Net Earnings (continuing ops, attributable to MLM) | AA19: 1020.6852 | AB19: 1032.9415 | AC19: 1062.9974 | AD19: 1270.102 | AE19: 1432.0514 | AF19: 1560.9968 | AG19: 0.088684505
B21: FDSO (m) | C21: =Model!BV180 -> 60.6 | D21: =Model!CA180 -> 64.208753 | E21: =Model!CB180 -> 71.329402 | F21: =Model!CC180 -> 71.479402 | G21: =Model!CD180 -> 70.543924 | H21: =Model!CE180 -> 67.941507 | I21: =IFERROR((H21/C21)^(1/5)-1,"n/m") -> 0.023133984 | N21: FDSO (m) | O21: 60.6 | P21: 64.160556 | Q21: 71.136612 | R21: 70.166257 | S21: 67.066573 | T21: 62.804938 | U21: 0.0071733669 | Z21: FDSO (m) | AA21: 60.6 | AB21: 64.208753 | AC21: 71.329402 | AD21: 71.479402 | AE21: 71.629402 | AF21: 71.308869 | AG21: 0.033080551
B23: Adjusted EPS — Diluted ($) | C23: =Model!BV224 -> 16.842989 | D23: =Model!CA224 -> 16.947354 | E23: =Model!CB224 -> 18.335847 | F23: =Model!CC224 -> 22.633294 | G23: =Model!CD224 -> 26.763385 | H23: =Model!CE224 -> 31.028136 | I23: =IFERROR((H23/C23)^(1/5)-1,"n/m") -> 0.12997101 | N23: Adjusted EPS — Diluted ($) | O23: 16.842989 | P23: 17.820846 | Q23: 22.150687 | R23: 28.512452 | S23: 35.350111 | T23: 42.91549 | U23: 0.20569922 | Z23: Adjusted EPS — Diluted ($) | AA23: 16.842989 | AB23: 16.087238 | AC23: 14.902654 | AD23: 17.768783 | AE23: 19.992508 | AF23: 21.89064 | AG23: 0.053823445
B24: EPS y/y % | D24: =IFERROR(D23/C23-1,"") -> 0.0061963014 | E24: =IFERROR(E23/D23-1,"") -> 0.081929834 | F24: =IFERROR(F23/E23-1,"") -> 0.23437401 | G24: =IFERROR(G23/F23-1,"") -> 0.18247858 | H24: =IFERROR(H23/G23-1,"") -> 0.15935022 | N24: EPS y/y % | P24: 0.058057181 | Q24: 0.24296496 | R24: 0.28720397 | S24: 0.23981307 | T24: 0.21401287 | Z24: EPS y/y % | AB24: -0.044870362 | AC24: -0.073635015 | AD24: 0.19232335 | AE24: 0.12514789 | AF24: 0.094942135
B26: P / E (x) — assumed (adjusted EPS) | F26: 26 | G26: 26 | H26: 26 | N26: P / E (x) — assumed (adjusted EPS) | R26: 30 | S26: 30 | T26: 30 | Z26: P / E (x) — assumed (adjusted EPS) | AD26: 21 | AE26: 21 | AF26: 21
B27: Price Target ($) | F27: =F26*F23 -> 588.46563 | G27: =G26*G23 -> 695.84801 | H27: =H26*H23 -> 806.73154 | N27: Price Target ($) | R27: =R26*R23 -> 855.37357 | S27: =S26*S23 -> 1060.5033 | T27: =T26*T23 -> 1287.4647 | Z27: Price Target ($) | AD27: =AD26*AD23 -> 373.14444 | AE27: =AE26*AE23 -> 419.84268 | AF27: =AF26*AF23 -> 459.70344
B28: Upside / (Downside) vs current | F28: =IFERROR(F27/$K$2-1,"") -> 0.13450093 | G28: =IFERROR(G27/$K$2-1,"") -> 0.34152305 | H28: =IFERROR(H27/$K$2-1,"") -> 0.55529504 | N28: Upside / (Downside) vs current | R28: =IFERROR(R27/$K$2-1,"") -> 0.64907185 | S28: =IFERROR(S27/$K$2-1,"") -> 1.0445408 | T28: =IFERROR(T27/$K$2-1,"") -> 1.4820989 | Z28: Upside / (Downside) vs current | AD28: =IFERROR(AD27/$K$2-1,"") -> -0.28061609 | AE28: =IFERROR(AE27/$K$2-1,"") -> -0.1905867 | AF28: =IFERROR(AF27/$K$2-1,"") -> -0.11373928
B29: IRR (to Dec-Y-1) | F29: =IFERROR((F27/$K$2)^(1/((DATE(2028-1,12,31)-$K$3)/365.25))-1,"") -> 0.10710467 | G29: =IFERROR((G27/$K$2)^(1/((DATE(2029-1,12,31)-$K$3)/365.25))-1,"") -> 0.14000047 | H29: =IFERROR((H27/$K$2)^(1/((DATE(2030-1,12,31)-$K$3)/365.25))-1,"") -> 0.14596665 | N29: IRR (to Dec-Y-1) | R29: =IFERROR((R27/$K$2)^(1/((DATE(2028-1,12,31)-$K$3)/365.25))-1,"") -> 0.49678148 | S29: =IFERROR((S27/$K$2)^(1/((DATE(2029-1,12,31)-$K$3)/365.25))-1,"") -> 0.37567746 | T29: =IFERROR((T27/$K$2)^(1/((DATE(2030-1,12,31)-$K$3)/365.25))-1,"") -> 0.3237227 | Z29: IRR (to Dec-Y-1) | AD29: =IFERROR((AD27/$K$2)^(1/((DATE(2028-1,12,31)-$K$3)/365.25))-1,"") -> -0.23322373 | AE29: =IFERROR((AE27/$K$2)^(1/((DATE(2029-1,12,31)-$K$3)/365.25))-1,"") -> -0.089988962 | AF29: =IFERROR((AF27/$K$2)^(1/((DATE(2030-1,12,31)-$K$3)/365.25))-1,"") -> -0.03656295
B31: Free Cash Flow | C31: =Model!BV273 -> 978 | D31: =Model!CA273 -> 937.96654 | E31: =Model!CB273 -> 1666.42 | F31: =Model!CC273 -> 1961.0007 | G31: =Model!CD273 -> 2225.1111 | H31: =Model!CE273 -> 2445.3569 | I31: =IFERROR((H31/C31)^(1/5)-1,"n/m") -> 0.2011595 | N31: Free Cash Flow | O31: 978 | P31: 980.41439 | Q31: 1889.3287 | R31: 2257.8324 | S31: 2626.1709 | T31: 2954.2639 | U31: 0.24744695 | Z31: Free Cash Flow | AA31: 978 | AB31: 895.49296 | AC31: 1452.2135 | AD31: 1682.6312 | AE31: 1849.2934 | AF31: 1971.0496 | AG31: 0.15046057
B32: FCF % | C32: =IFERROR(C31/C9,"") -> 0.15902439 | D32: =IFERROR(D31/D9,"") -> 0.11769514 | E32: =IFERROR(E31/E9,"") -> 0.16975152 | F32: =IFERROR(F31/F9,"") -> 0.18495661 | G32: =IFERROR(G31/G9,"") -> 0.19359518 | H32: =IFERROR(H31/H9,"") -> 0.19585148 | J32: =IFERROR(AVERAGE(Model!C275,Model!D275,Model!E275,Model!F275,Model!G275,Model!H275,Model!I275,Model!N275,Model!S275,Model!X275,Model!AC275,Model!AH275,Model!AM275,Model!AR275,Model!AW275,Model!BB275,Model!BG275,Model!BL275,Model!BQ275,Model!BV275),"") -> 0.084088729 | K32: =IFERROR(MIN(Model!C275,Model!D275,Model!E275,Model!F275,Model!G275,Model!H275,Model!I275,Model!N275,Model!S275,Model!X275,Model!AC275,Model!AH275,Model!AM275,Model!AR275,Model!AW275,Model!BB275,Model!BG275,Model!BL275,Model!BQ275,Model!BV275),"") -> 0.032730239 | L32: =IFERROR(MAX(Model!C275,Model!D275,Model!E275,Model!F275,Model!G275,Model!H275,Model!I275,Model!N275,Model!S275,Model!X275,Model!AC275,Model!AH275,Model!AM275,Model!AR275,Model!AW275,Model!BB275,Model!BG275,Model!BL275,Model!BQ275,Model!BV275),"") -> 0.15902439 | N32: FCF % | O32: 0.15902439 | P32: 0.12149692 | Q32: 0.18295763 | R32: 0.19343886 | S32: 0.1990935 | T32: 0.19843179 | V32: 0.084088729 | W32: 0.032730239 | X32: 0.15902439 | Z32: FCF % | AA32: 0.15902439 | AB32: 0.11379346 | AC32: 0.15447512 | AD32: 0.17253509 | AE32: 0.18334109 | AF32: 0.18812134 | AH32: 0.084088729 | AI32: 0.032730239 | AJ32: 0.15902439
B33: FCF / share ($) | C33: =IFERROR(C31/C21,"") -> 16.138614 | D33: =IFERROR(D31/D21,"") -> 14.608079 | E33: =IFERROR(E31/E21,"") -> 23.362315 | F33: =IFERROR(F31/F21,"") -> 27.434486 | G33: =IFERROR(G31/G21,"") -> 31.542208 | H33: =IFERROR(H31/H21,"") -> 35.992091 | N33: FCF / share ($) | O33: 16.138614 | P33: 15.280641 | Q33: 26.55916 | R33: 32.178321 | S33: 39.157672 | T33: 47.038721 | Z33: FCF / share ($) | AA33: 16.138614 | AB33: 13.946587 | AC33: 20.359255 | AD33: 23.540085 | AE33: 25.817518 | AF33: 27.641016
B34: FCF Yield (on PT) | F34: =IFERROR(F33/F$27,"") -> 0.046620371 | G34: =IFERROR(G33/G$27,"") -> 0.045329163 | H34: =IFERROR(H33/H$27,"") -> 0.044614706 | N34: FCF Yield (on PT) | R34: =IFERROR(R33/R$27,"") -> 0.037619027 | S34: =IFERROR(S33/S$27,"") -> 0.036923667 | T34: =IFERROR(T33/T$27,"") -> 0.036535931 | Z34: FCF Yield (on PT) | AD34: =IFERROR(AD33/AD$27,"") -> 0.06308572 | AE34: =IFERROR(AE33/AE$27,"") -> 0.061493316 | AF34: =IFERROR(AF33/AF$27,"") -> 0.060127929
B35: Adjusted EBITDA — pro forma (2026E incl. LNA full year) | C35: =Model!BV214 -> 2065 | D35: =Model!CA214 -> 3197.2214 | E35: =Model!CB214 -> 3592.3373 | F35: =Model!CC214 -> 4007.7658 | G35: =Model!CD214 -> 4411.5047 | H35: =Model!CE214 -> 4811.2674 | I35: =IFERROR((H35/C35)^(1/5)-1,"n/m") -> 0.18431679 | N35: Adjusted EBITDA — pro forma (2026E incl. LNA full year) | O35: 2065 | P35: 3267.2214 | Q35: 3991.8064 | R35: 4627.5928 | S35: 5283.3716 | T35: 5966.5414 | U35: 0.23640434 | Z35: Adjusted EBITDA — pro forma (2026E incl. LNA full year) | AA35: 2065 | AB35: 3127.2214 | AC35: 3238.4502 | AD35: 3488.1157 | AE35: 3682.491 | AF35: 3856.7328 | AG35: 0.13307824
B36: Adjusted EBITDA (pro forma) % of revenues | C36: =IFERROR(C35/C9,"") -> 0.33577236 | D36: =IFERROR(D35/D9,"") -> 0.40118426 | E36: =IFERROR(E35/E9,"") -> 0.365937 | F36: =IFERROR(F35/F9,"") -> 0.37800232 | G36: =IFERROR(G35/G9,"") -> 0.38382176 | H36: =IFERROR(H35/H9,"") -> 0.38534001 | J36: =IFERROR(AVERAGE(Model!C238,Model!D238,Model!E238,Model!F238,Model!G238,Model!H238,Model!I238,Model!N238,Model!S238,Model!X238,Model!AC238,Model!AH238,Model!AM238,Model!AR238,Model!AW238,Model!BB238,Model!BG238,Model!BL238,Model!BQ238,Model!BV238),"") -> 0.24703766 | K36: =IFERROR(MIN(Model!C238,Model!D238,Model!E238,Model!F238,Model!G238,Model!H238,Model!I238,Model!N238,Model!S238,Model!X238,Model!AC238,Model!AH238,Model!AM238,Model!AR238,Model!AW238,Model!BB238,Model!BG238,Model!BL238,Model!BQ238,Model!BV238),"") -> 0.16190616 | L36: =IFERROR(MAX(Model!C238,Model!D238,Model!E238,Model!F238,Model!G238,Model!H238,Model!I238,Model!N238,Model!S238,Model!X238,Model!AC238,Model!AH238,Model!AM238,Model!AR238,Model!AW238,Model!BB238,Model!BG238,Model!BL238,Model!BQ238,Model!BV238),"") -> 0.33577236 | N36: Adjusted EBITDA (pro forma) % of revenues | O36: 0.33577236 | P36: 0.40488731 | Q36: 0.38655604 | R36: 0.3964671 | S36: 0.4005394 | T36: 0.40076023 | V36: 0.24703766 | W36: 0.16190616 | X36: 0.33577236 | Z36: Adjusted EBITDA (pro forma) % of revenues | AA36: 0.33577236 | AB36: 0.39738711 | AC36: 0.34448102 | AD36: 0.35766742 | AE36: 0.36508643 | AF36: 0.36809513 | AH36: 0.24703766 | AI36: 0.16190616 | AJ36: 0.33577236
B38: Net Debt | C38: =Model!BV421 -> 5256 | D38: =Model!CA421 -> 12240.588 | E38: =Model!CB421 -> 10860.654 | F38: =Model!CC421 -> 9702.1028 | G38: =Model!CD421 -> 9925.8856 | H38: =Model!CE421 -> 10825.352 | N38: Net Debt | O38: 5256 | P38: 12297.972 | Q38: 11194.434 | R38: 11568.982 | S38: 13208.429 | T38: 14916.354 | Z38: Net Debt | AA38: 5256 | AB38: 12283.062 | AC38: 11117.334 | AD38: 9737.1523 | AE38: 8457.2629 | AF38: 7713.4655
B39: Net Debt / Adjusted EBITDA (x) | C39: =IFERROR(C38/C35,"") -> 2.5452785 | D39: =IFERROR(D38/D35,"") -> 3.828508 | E39: =IFERROR(E38/E35,"") -> 3.0232836 | F39: =IFERROR(F38/F35,"") -> 2.4208258 | G39: =IFERROR(G38/G35,"") -> 2.25 | H39: =IFERROR(H38/H35,"") -> 2.25 | N39: Net Debt / Adjusted EBITDA (x) | O39: 2.5452785 | P39: 3.7640461 | Q39: 2.8043531 | R39: 2.5 | S39: 2.5 | T39: 2.5 | Z39: Net Debt / Adjusted EBITDA (x) | AA39: 2.5452785 | AB39: 3.9277876 | AC39: 3.4329181 | AD39: 2.7915222 | AE39: 2.2966147 | AF39: 2
B41: ROIC | C41: =Model!BV404 -> 0.078373843 | D41: =Model!CA404 -> 0.044428423 | E41: =Model!CB404 -> 0.058228754 | F41: =Model!CC404 -> 0.066354824 | G41: =Model!CD404 -> 0.073105328 | H41: =Model!CE404 -> 0.07925012 | J41: =IFERROR(AVERAGE(Model!C404,Model!D404,Model!E404,Model!F404,Model!G404,Model!H404,Model!I404,Model!N404,Model!S404,Model!X404,Model!AC404,Model!AH404,Model!AM404,Model!AR404,Model!AW404,Model!BB404,Model!BG404,Model!BL404,Model!BQ404,Model!BV404),"") -> 0.08428637 | K41: =IFERROR(MIN(Model!C404,Model!D404,Model!E404,Model!F404,Model!G404,Model!H404,Model!I404,Model!N404,Model!S404,Model!X404,Model!AC404,Model!AH404,Model!AM404,Model!AR404,Model!AW404,Model!BB404,Model!BG404,Model!BL404,Model!BQ404,Model!BV404),"") -> 0.03361715 | L41: =IFERROR(MAX(Model!C404,Model!D404,Model!E404,Model!F404,Model!G404,Model!H404,Model!I404,Model!N404,Model!S404,Model!X404,Model!AC404,Model!AH404,Model!AM404,Model!AR404,Model!AW404,Model!BB404,Model!BG404,Model!BL404,Model!BQ404,Model!BV404),"") -> 0.14888392 | N41: ROIC | O41: 0.078373843 | P41: 0.046221187 | Q41: 0.065919196 | R41: 0.076428957 | S41: 0.085709904 | T41: 0.094557447 | V41: 0.08428637 | W41: 0.03361715 | X41: 0.14888392 | Z41: ROIC | AA41: 0.078373843 | AB41: 0.042632747 | AC41: 0.05027949 | AD41: 0.056441901 | AE41: 0.060805271 | AF41: 0.064473684 | AH41: 0.08428637 | AI41: 0.03361715 | AJ41: 0.14888392
B42: RONTA | C42: =Model!BV415 -> 0.087006175 | D42: =Model!CA415 -> 0.069373529 | E42: =Model!CB415 -> 0.09004483 | F42: =Model!CC415 -> 0.097158068 | G42: =Model!CD415 -> 0.10755667 | H42: =Model!CE415 -> 0.11994091 | J42: =IFERROR(AVERAGE(Model!C415,Model!D415,Model!E415,Model!F415,Model!G415,Model!H415,Model!I415,Model!N415,Model!S415,Model!X415,Model!AC415,Model!AH415,Model!AM415,Model!AR415,Model!AW415,Model!BB415,Model!BG415,Model!BL415,Model!BQ415,Model!BV415),"") -> 0.094662288 | K42: =IFERROR(MIN(Model!C415,Model!D415,Model!E415,Model!F415,Model!G415,Model!H415,Model!I415,Model!N415,Model!S415,Model!X415,Model!AC415,Model!AH415,Model!AM415,Model!AR415,Model!AW415,Model!BB415,Model!BG415,Model!BL415,Model!BQ415,Model!BV415),"") -> 0.039851224 | L42: =IFERROR(MAX(Model!C415,Model!D415,Model!E415,Model!F415,Model!G415,Model!H415,Model!I415,Model!N415,Model!S415,Model!X415,Model!AC415,Model!AH415,Model!AM415,Model!AR415,Model!AW415,Model!BB415,Model!BG415,Model!BL415,Model!BQ415,Model!BV415),"") -> 0.16330395 | N42: RONTA | O42: 0.087006175 | P42: 0.072154325 | Q42: 0.10206301 | R42: 0.1174961 | S42: 0.13097034 | T42: 0.14360784 | V42: 0.094662288 | W42: 0.039851224 | X42: 0.16330395 | Z42: RONTA | AA42: 0.087006175 | AB42: 0.066586741 | AC42: 0.07781899 | AD42: 0.0826806 | AE42: 0.083200725 | AF42: 0.084675586 | AH42: 0.094662288 | AI42: 0.039851224 | AJ42: 0.16330395
B44: Implied Market Cap (USDm) | F44: =F27*F21 -> 42063.172 | G44: =G27*G21 -> 49087.849 | H44: =H27*H21 -> 54810.557 | N44: Implied Market Cap (USDm) | R44: =R27*R21 -> 60018.361 | S44: =S27*S21 -> 71124.324 | T44: =T27*T21 -> 80859.14 | Z44: Implied Market Cap (USDm) | AD44: =AD27*AD21 -> 26672.141 | AE44: =AE27*AE21 -> 30073.08 | AF44: =AF27*AF21 -> 32780.932
B45: (+) Net Debt & NCI | F45: =F38+Model!CC324 -> 9704.1028 | G45: =G38+Model!CD324 -> 9927.8856 | H45: =H38+Model!CE324 -> 10827.352 | N45: (+) Net Debt & NCI | R45: =R38+Model!CC324 -> 11570.982 | S45: =S38+Model!CD324 -> 13210.429 | T45: =T38+Model!CE324 -> 14918.354 | Z45: (+) Net Debt & NCI | AD45: =AD38+Model!CC324 -> 9739.1523 | AE45: =AE38+Model!CD324 -> 8459.2629 | AF45: =AF38+Model!CE324 -> 7715.4655
B46: Implied Enterprise Value (USDm) | F46: =F44+F45 -> 51767.274 | G46: =G44+G45 -> 59015.735 | H46: =H44+H45 -> 65637.908 | N46: Implied Enterprise Value (USDm) | R46: =R44+R45 -> 71589.343 | S46: =S44+S45 -> 84334.753 | T46: =T44+T45 -> 95777.493 | Z46: Implied Enterprise Value (USDm) | AD46: =AD44+AD45 -> 36411.293 | AE46: =AE44+AE45 -> 38532.343 | AF46: =AF44+AF45 -> 40496.398
B47: Implied EV / Adjusted EBITDA (x) | F47: =IFERROR(F46/F35,"") -> 12.916741 | G47: =IFERROR(G46/G35,"") -> 13.377688 | H47: =IFERROR(H46/H35,"") -> 13.64254 | N47: Implied EV / Adjusted EBITDA (x) | R47: =IFERROR(R46/R35,"") -> 15.470104 | S47: =IFERROR(S46/S35,"") -> 15.962298 | T47: =IFERROR(T46/T35,"") -> 16.052431 | Z47: Implied EV / Adjusted EBITDA (x) | AD47: =IFERROR(AD46/AD35,"") -> 10.438671 | AE47: =IFERROR(AE46/AE35,"") -> 10.463662 | AF47: =IFERROR(AF46/AF35,"") -> 10.500183

Sheet DCF
B2: DCF VALUATION — MARTIN MARIETTA MATERIALS (MLM)
B4: 1. WACC BUILD
B5: Risk-free rate (US 10Y govt) | C5: 0.045 | D5: Assumption (~US 10Y Treasury yield); update to market
B6: Equity risk premium | C6: 0.05 | D6: US implied ERP ~4.5–5.5% (Damodaran)
B7: Levered beta | C7: 1 | D7: Construction-materials peers (VMC, CRH, EXP, Knife River) ~0.9–1.1; infrastructure-weighted demand and aggregates pricing power dampen cyclicality
B8: Cost of equity | C8: =C5+C7*C6 -> 0.095
B9: Pre-tax cost of debt | C9: 0.055 | D9: Investment grade (BBB+/Baa2); Aug-2026 LNA notes priced at 4.85%–6.375% (5.52% blended); marginal cost ~5.5%
B10: Tax rate | C10: 0.22 | D10: Model 2027E+ effective tax rate
B11: After-tax cost of debt | C11: =C9*(1-C10) -> 0.0429
B12: Target D/V | C12: 0.25 | D12: Net debt ~$12.2bn at YE2026E (post-LNA) vs ~$37bn market cap ($518.70 × ~71m shares); 3.8x pro forma leverage, targeted < 2.5x
B13: WACC | C13: =C8*(1-C12)+C11*C12 -> 0.081975
B15: Valuation date (live) | C15: =TODAY() -> 46299 | D15: Periods = (Dec-31-Year − today) / 365.25; cash flows assumed at year-end
B16: 2. UNLEVERED FREE CASH FLOW BUILD (USDm)
D17: 2026E | E17: 2027E | F17: 2028E | G17: 2029E | H17: 2030E | I17: 2031E | J17: 2032E | K17: 2033E | L17: 2034E | M17: 2035E | N17: Terminal | P17: CAGR 26–30E | Q17: CAGR 26–35E
B18: Adjusted EBIT (Model; Adjusted EBITDA − DD&A) | D18: =Model!CA212 -> 1742.3104 | E18: =Model!CB212 -> 2261.7368 | F18: =Model!CC212 -> 2596.3706 | G18: =Model!CD212 -> 2906.0247 | H18: =Model!CE212 -> 3200.3209 | I18: =H18*(1+I$31) -> 3424.3434 | J18: =I18*(1+J$31) -> 3646.9257 | K18: =J18*(1+K$31) -> 3865.7413 | L18: =K18*(1+L$31) -> 4078.357 | M18: =L18*(1+M$31) -> 4282.2749 | P18: =IFERROR(($H18/$D18)^(1/(VALUE(LEFT($H$17,4))-VALUE(LEFT($D$17,4))))-1,"n/m") -> 0.1641716 | Q18: =IFERROR(($M18/$D18)^(1/(VALUE(LEFT($M$17,4))-VALUE(LEFT($D$17,4))))-1,"n/m") -> 0.10508157
B19: y/y % | E19: =IFERROR(E18/D18-1,"") -> 0.29812506 | F19: =IFERROR(F18/E18-1,"") -> 0.14795436 | G19: =IFERROR(G18/F18-1,"") -> 0.1192642 | H19: =IFERROR(H18/G18-1,"") -> 0.10127109 | I19: =IFERROR(I18/H18-1,"") -> 0.07 | J19: =IFERROR(J18/I18-1,"") -> 0.065 | K19: =IFERROR(K18/J18-1,"") -> 0.06 | L19: =IFERROR(L18/K18-1,"") -> 0.055 | M19: =IFERROR(M18/L18-1,"") -> 0.05
B20: (−) Acquisition, divestiture & integration costs (cash; added back in Adjusted EBITDA) | D20: =-Model!CA158 -> -106 | E20: =-Model!CB158 -> -25 | F20: =-Model!CC158 -> -10 | G20: =-Model!CD158 -> -10 | H20: =-Model!CE158 -> -10 | I20: =H20*(1+I$31) -> -10.7 | J20: =I20*(1+J$31) -> -11.3955 | K20: =J20*(1+K$31) -> -12.07923 | L20: =K20*(1+L$31) -> -12.743588 | M20: =L20*(1+M$31) -> -13.380767
B21: × (1 − tax rate) | D21: =1-$C$10 -> 0.78 | E21: =1-$C$10 -> 0.78 | F21: =1-$C$10 -> 0.78 | G21: =1-$C$10 -> 0.78 | H21: =1-$C$10 -> 0.78 | I21: =1-$C$10 -> 0.78 | J21: =1-$C$10 -> 0.78 | K21: =1-$C$10 -> 0.78 | ... M21: =1-$C$10 -> 0.78
B22: NOPAT = (Adjusted EBIT − acquisition costs) × (1 − t) | D22: =(D18+D20)*D21 -> 1276.3221 | E22: =(E18+E20)*E21 -> 1744.6547 | F22: =(F18+F20)*F21 -> 2017.3691 | G22: =(G18+G20)*G21 -> 2258.8992 | H22: =(H18+H20)*H21 -> 2488.4503 | I22: =(I18+I20)*I21 -> 2662.6419 | J22: =(J18+J20)*J21 -> 2835.7136 | K22: =(K18+K20)*K21 -> 3005.8564 | ... M22: =(M18+M20)*M21 -> 3329.7374
B23: plus depreciation, depletion & amortization (total, incl. LNA purchase accounting) | D23: =Model!CA176 -> 971.25248 | E23: =Model!CB176 -> 1330.6005 | F23: =Model!CC176 -> 1411.3952 | G23: =Model!CD176 -> 1505.4801 | H23: =Model!CE176 -> 1610.9464 | I23: =H23*(1+I$31) -> 1723.7127 | J23: =I23*(1+J$31) -> 1835.754 | K23: =J23*(1+K$31) -> 1945.8993 | L23: =K23*(1+L$31) -> 2052.9237 | M23: =L23*(1+M$31) -> 2155.5699
B24: − Capex (PP&E) and acquisitions (M&A lever, 2027E+) | D24: =D29 -> -635.25128 | E24: =E29+Model!CB256 -> -834.42962 | F24: =F29+Model!CC256 -> -1401.2117 | G24: =G29+Model!CD256 -> -1726.9584 | H24: =H29+Model!CE256 -> -1811.2906 | I24: =I29 -> -1135.5809 | J24: =J29 -> -1209.3937 | K24: =K29 -> -1281.9573 | L24: =L29 -> -1352.465 | M24: =M29 -> -1420.0882
B25: − Δ Working capital (CF statement) | D25: =Model!CA253 -> -80.318304 | E25: =Model!CB253 -> -97.313706 | F25: =Model!CC253 -> -143.72459 | G25: =Model!CD253 -> -174.37011 | H25: =Model!CE253 -> -202.30768 | I25: =H25*(1+I$31) -> -216.46922 | J25: =I25*(1+J$31) -> -230.53972 | K25: =J25*(1+K$31) -> -244.3721 | L25: =K25*(1+L$31) -> -257.81257 | M25: =L25*(1+M$31) -> -270.7032
B26: Unlevered FCF | D26: =D22+D23+D24+D25 -> 1532.005 | E26: =E22+E23+E24+E25 -> 2143.5119 | F26: =F22+F23+F24+F25 -> 1883.828 | G26: =G22+G23+G24+G25 -> 1863.0508 | H26: =H22+H23+H24+H25 -> 2085.7985 | I26: =I22+I23+I24+I25 -> 3034.3044 | J26: =J22+J23+J24+J25 -> 3231.5342 | K26: =K22+K23+K24+K25 -> 3425.4262 | ... M26: =M22+M23+M24+M25 -> 3794.5159 | N26: =M26*(1+$C$32) -> 3946.2965 | P26: =IFERROR(($H26/$D26)^(1/(VALUE(LEFT($H$17,4))-VALUE(LEFT($D$17,4))))-1,"n/m") -> 0.080197186 | Q26: =IFERROR(($M26/$D26)^(1/(VALUE(LEFT($M$17,4))-VALUE(LEFT($D$17,4))))-1,"n/m") -> 0.10602831
B27: y/y % | E27: =IFERROR(E26/D26-1,"") -> 0.39915463 | F27: =IFERROR(F26/E26-1,"") -> -0.12114879 | G27: =IFERROR(G26/F26-1,"") -> -0.011029281 | H27: =IFERROR(H26/G26-1,"") -> 0.11956075 | I27: =IFERROR(I26/H26-1,"") -> 0.45474474 | J27: =IFERROR(J26/I26-1,"") -> 0.065 | K27: =IFERROR(K26/J26-1,"") -> 0.06 | L27: =IFERROR(L26/K26-1,"") -> 0.055 | M27: =IFERROR(M26/L26-1,"") -> 0.05
B28: Terminal Value (Gordon Growth) | N28: =N26/($C$13-$C$32) -> 94015.403
B29: memo: PP&E capex only (fade years carry no new acquisitions) | D29: =Model!CA255 -> -635.25128 | E29: =Model!CB255 -> -834.42962 | F29: =Model!CC255 -> -901.21166 | G29: =Model!CD255 -> -976.95843 | H29: =Model!CE255 -> -1061.2906 | I29: =H29*(1+I$31) -> -1135.5809 | J29: =I29*(1+J$31) -> -1209.3937 | K29: =J29*(1+K$31) -> -1281.9573 | L29: =K29*(1+L$31) -> -1352.465 | M29: =L29*(1+M$31) -> -1420.0882
B31: Fade-period growth (2031E–35E) | I31: 0.07 | J31: =I31+($M$31-$I$31)/(COLUMNS($I$31:$M$31)-1) -> 0.065 | K31: =J31+($M$31-$I$31)/(COLUMNS($I$31:$M$31)-1) -> 0.06 | L31: =K31+($M$31-$I$31)/(COLUMNS($I$31:$M$31)-1) -> 0.055 | M31: 0.05
B32: Terminal growth rate | C32: 0.04
B34: Discount period (years) | D34: =(DATE(2026,12,31)-$C$15)/365.25 -> 0.24093087 | E34: =(DATE(2027,12,31)-$C$15)/365.25 -> 1.2402464 | F34: =(DATE(2028,12,31)-$C$15)/365.25 -> 2.2422998 | G34: =(DATE(2029,12,31)-$C$15)/365.25 -> 3.2416153 | H34: =(DATE(2030,12,31)-$C$15)/365.25 -> 4.2409309 | I34: =(DATE(2031,12,31)-$C$15)/365.25 -> 5.2402464 | J34: =(DATE(2032,12,31)-$C$15)/365.25 -> 6.2422998 | K34: =(DATE(2033,12,31)-$C$15)/365.25 -> 7.2416153 | L34: =(DATE(2034,12,31)-$C$15)/365.25 -> 8.2409309 | M34: =(DATE(2035,12,31)-$C$15)/365.25 -> 9.2402464 | N34: =M34 -> 9.2402464
B35: Discount factor | D35: =1/(1+$C$13)^D34 -> 0.98119655 | E35: =1/(1+$C$13)^E34 -> 0.90690586 | F35: =1/(1+$C$13)^F34 -> 0.83805924 | G35: =1/(1+$C$13)^G34 -> 0.7746061 | H35: =1/(1+$C$13)^H34 -> 0.71595728 | I35: =1/(1+$C$13)^I34 -> 0.66174902 | J35: =1/(1+$C$13)^J34 -> 0.61151317 | K35: =1/(1+$C$13)^K34 -> 0.56521283 | ... N35: =1/(1+$C$13)^N34 -> 0.48286352
B36: PV of UFCF | D36: =D26*D35 -> 1503.198 | E36: =E26*E35 -> 1943.9635 | F36: =F26*F35 -> 1578.7595 | G36: =G26*G35 -> 1443.1305 | H36: =H26*H35 -> 1493.3426 | I36: =I26*I35 -> 2007.9479 | J36: =J26*J35 -> 1976.1257 | K36: =K26*K35 -> 1936.0948 | ... M36: =M26*M35 -> 1832.2333 | N36: =N28*N35 -> 45396.609
D37: MLM's Adjusted EBITDA expenses stock-based compensation; Adjusted EBIT deducts all DD&A incl. ~$380m p.a. of LNA purchase-accounting D&A (non-cash, added back in row 23). The LNA cash consideration (closed 21-Aug-2026) sits in YE2026E net debt, not in UFCF. Acquisition spend from the M&A lever is deducted in 2027E–30E; the fade period and terminal value assume no new acquisitions. LNA intangible amortization is largely non-deductible (a deferred tax liability was recorded), so NOPAT slightly overstates the tax shield. Operating-lease costs sit inside earnings from operations.
B39: Implied ROIC & incremental ROIC (USDm) | D39: =D17 -> 2026E | E39: =E17 -> 2027E | F39: =F17 -> 2028E | G39: =G17 -> 2029E | H39: =H17 -> 2030E | I39: =I17 -> 2031E | J39: =J17 -> 2032E | K39: =K17 -> 2033E | ... M39: =M17 -> 2035E | N39: Terminal
B40: NOPAT (row 22) | D40: =D22 -> 1276.3221 | E40: =E22 -> 1744.6547 | F40: =F22 -> 2017.3691 | G40: =G22 -> 2258.8992 | H40: =H22 -> 2488.4503 | I40: =I22 -> 2662.6419 | J40: =J22 -> 2835.7136 | K40: =K22 -> 3005.8564 | ... M40: =M22 -> 3329.7374 | N40: =M40*(1+$C$32) -> 3462.9269
B41: Net investment = NOPAT − UFCF | D41: =D40-D26 -> -255.68289 | E41: =E40-E26 -> -398.8572 | F41: =F40-F26 -> 133.54105 | G41: =G40-G26 -> 395.84849 | H41: =H40-H26 -> 402.65184 | I41: =I40-I26 -> -371.66253 | J41: =J40-J26 -> -395.8206 | K41: =K40-K26 -> -419.56983 | ... N41: =N40-N26 -> -483.36962
B42: Opening invested capital | D42: =Model!BV401+Model!CA346+Model!CA348 -> 28829 | E42: =D43 -> 28573.317 | F42: =E43 -> 28174.46 | G42: =F43 -> 28308.001 | H42: =G43 -> 28703.849 | I42: =H43 -> 29106.501 | J42: =I43 -> 28734.839 | K42: =J43 -> 28339.018 | L42: =K43 -> 27919.448 | ... N42: =M43 -> 27012.024
B43: Closing invested capital | D43: =D42+D41 -> 28573.317 | E43: =E42+E41 -> 28174.46 | F43: =F42+F41 -> 28308.001 | G43: =G42+G41 -> 28703.849 | H43: =H42+H41 -> 29106.501 | I43: =I42+I41 -> 28734.839 | J43: =J42+J41 -> 28339.018 | K43: =K42+K41 -> 27919.448 | ... M43: =M42+M41 -> 27012.024
B44: Implied ROIC = NOPAT / opening IC | D44: =IFERROR(D40/D42,"") -> 0.04427216 | E44: =IFERROR(E40/E42,"") -> 0.061058879 | F44: =IFERROR(F40/F42,"") -> 0.071602759 | G44: =IFERROR(G40/G42,"") -> 0.079797201 | H44: =IFERROR(H40/H42,"") -> 0.086693959 | I44: =IFERROR(I40/I42,"") -> 0.091479283 | J44: =IFERROR(J40/J42,"") -> 0.098685557 | K44: =IFERROR(K40/K42,"") -> 0.10606777 | ... N44: =IFERROR(N40/N42,"") -> 0.12819946
B45: Reinvestment rate = net inv. / NOPAT | D45: =IFERROR(D41/D40,"") -> -0.20032787 | E45: =IFERROR(E41/E40,"") -> -0.2286167 | F45: =IFERROR(F41/F40,"") -> 0.066195648 | G45: =IFERROR(G41/G40,"") -> 0.17523955 | H45: =IFERROR(H41/H40,"") -> 0.16180827 | I45: =IFERROR(I41/I40,"") -> -0.13958412 | J45: =IFERROR(J41/J40,"") -> -0.13958412 | K45: =IFERROR(K41/K40,"") -> -0.13958412 | ... N45: =IFERROR(N41/N40,"") -> -0.13958412
B46: Incremental ROIC = Δ NOPAT / prior-yr net inv. | E46: =IFERROR((E40-D40)/D41,"") -> -1.8316931 | F46: =IFERROR((F40-E40)/E41,"") -> -0.68373938 | G46: =IFERROR((G40-F40)/F41,"") -> 1.8086585 | H46: =IFERROR((H40-G40)/G41,"") -> 0.57989635 | I46: =IFERROR((I40-H40)/H41,"") -> 0.43261077 | J46: =IFERROR((J40-I40)/I41,"") -> -0.465669 | K46: =IFERROR((K40-J40)/J41,"") -> -0.42984831 | L46: =IFERROR((L40-K40)/K41,"") -> -0.39402762 | M46: =IFERROR((M40-L40)/L41,"") -> -0.35820692 | N46: =IFERROR($C$32/N45,"") -> -0.28656554
B47: Cumulative incremental ROIC 2026E–35E | C47: =IFERROR((M40-D40)/SUM(D41:L41),"") -> -1.5185761
D48: Opening IC = Model 2025A book IC (equity + net debt) + LNA total consideration ($13.5bn cash & shares), rolled forward with DCF net investment (capex + M&A − D&A + ΔWC). Terminal incremental ROIC = g ÷ reinvestment rate. Cumulative = (NOPAT 2035E − 2026E) / Σ net investment 2026E–34E.
B49: 3. VALUATION SUMMARY
B50: Sum of PV (explicit + fade) | C50: =SUM(D36:M36) -> 17602.723
B51: PV of Terminal Value | C51: =N36 -> 45396.609
B52: Enterprise Value | C52: =C50+C51 -> 62999.332
B53: Less: net debt (Model 2026E YE, post-LNA) | C53: =Model!CA421 -> 12240.588
B54: Less: non-controlling interests (Model 2026E) | C54: =Model!CA324 -> 2
B55: Equity Value | C55: =C52-C53-C54 -> 50756.744
B56: Diluted shares (m, Model 2026E period end incl. 10.95m LNA shares) | C56: =Model!CA427 -> 71.204402
B57: Implied share price ($) | C57: =C55/C56 -> 712.83155
B58: Current share price ($) | C58: =Model!CA426 -> 518.7
B59: Implied upside / (downside) | C59: =C57/C58-1 -> 0.37426556
B62: 4. SENSITIVITY: IMPLIED PRICE ($) — WACC × Terminal Growth
B63: WACC step (across) | C63: 0.005
B64: Terminal growth step (down) | C64: 0.005
B65: g (down) / WACC | D65: =E65-$C$63 -> 0.071975 | E65: =F65-$C$63 -> 0.076975 | F65: =$C$13 -> 0.081975 | G65: =F65+$C$63 -> 0.086975 | H65: =G65+$C$63 -> 0.091975
B66: =B67-$C$64 -> 0.03 | D66: =IFERROR((SUMPRODUCT($D$26:$M$26/(1+D$65)^$D$34:$M$34)+($M$26*(1+$B66)/(D$65-$B66))/(1+D$65)^$M$34-$C$53-$C$54)/$C$56,"") -> 774.92734 | E66: =IFERROR((SUMPRODUCT($D$26:$M$26/(1+E$65)^$D$34:$M$34)+($M$26*(1+$B66)/(E$65-$B66))/(1+E$65)^$M$34-$C$53-$C$54)/$C$56,"") -> 669.89168 | F66: =IFERROR((SUMPRODUCT($D$26:$M$26/(1+F$65)^$D$34:$M$34)+($M$26*(1+$B66)/(F$65-$B66))/(1+F$65)^$M$34-$C$53-$C$54)/$C$56,"") -> 585.2153 | G66: =IFERROR((SUMPRODUCT($D$26:$M$26/(1+G$65)^$D$34:$M$34)+($M$26*(1+$B66)/(G$65-$B66))/(1+G$65)^$M$34-$C$53-$C$54)/$C$56,"") -> 515.5335 | H66: =IFERROR((SUMPRODUCT($D$26:$M$26/(1+H$65)^$D$34:$M$34)+($M$26*(1+$B66)/(H$65-$B66))/(1+H$65)^$M$34-$C$53-$C$54)/$C$56,"") -> 457.21299
B67: =B68-$C$64 -> 0.035 | D67: =IFERROR((SUMPRODUCT($D$26:$M$26/(1+D$65)^$D$34:$M$34)+($M$26*(1+$B67)/(D$65-$B67))/(1+D$65)^$M$34-$C$53-$C$54)/$C$56,"") -> 871.75326 | E67: =IFERROR((SUMPRODUCT($D$26:$M$26/(1+E$65)^$D$34:$M$34)+($M$26*(1+$B67)/(E$65-$B67))/(1+E$65)^$M$34-$C$53-$C$54)/$C$56,"") -> 743.23825 | F67: =IFERROR((SUMPRODUCT($D$26:$M$26/(1+F$65)^$D$34:$M$34)+($M$26*(1+$B67)/(F$65-$B67))/(1+F$65)^$M$34-$C$53-$C$54)/$C$56,"") -> 642.23172 | G67: =IFERROR((SUMPRODUCT($D$26:$M$26/(1+G$65)^$D$34:$M$34)+($M$26*(1+$B67)/(G$65-$B67))/(1+G$65)^$M$34-$C$53-$C$54)/$C$56,"") -> 560.79018 | H67: =IFERROR((SUMPRODUCT($D$26:$M$26/(1+H$65)^$D$34:$M$34)+($M$26*(1+$B67)/(H$65-$B67))/(1+H$65)^$M$34-$C$53-$C$54)/$C$56,"") -> 493.75872
B68: =$C$32 -> 0.04 | D68: =IFERROR((SUMPRODUCT($D$26:$M$26/(1+D$65)^$D$34:$M$34)+($M$26*(1+$B68)/(D$65-$B68))/(1+D$65)^$M$34-$C$53-$C$54)/$C$56,"") -> 998.86094 | E68: =IFERROR((SUMPRODUCT($D$26:$M$26/(1+E$65)^$D$34:$M$34)+($M$26*(1+$B68)/(E$65-$B68))/(1+E$65)^$M$34-$C$53-$C$54)/$C$56,"") -> 836.42161 | F68: =IFERROR((SUMPRODUCT($D$26:$M$26/(1+F$65)^$D$34:$M$34)+($M$26*(1+$B68)/(F$65-$B68))/(1+F$65)^$M$34-$C$53-$C$54)/$C$56,"") -> 712.83155 | G68: =IFERROR((SUMPRODUCT($D$26:$M$26/(1+G$65)^$D$34:$M$34)+($M$26*(1+$B68)/(G$65-$B68))/(1+G$65)^$M$34-$C$53-$C$54)/$C$56,"") -> 615.68106 | H68: =IFERROR((SUMPRODUCT($D$26:$M$26/(1+H$65)^$D$34:$M$34)+($M$26*(1+$B68)/(H$65-$B68))/(1+H$65)^$M$34-$C$53-$C$54)/$C$56,"") -> 537.33586
B69: =B68+$C$64 -> 0.045 | D69: =IFERROR((SUMPRODUCT($D$26:$M$26/(1+D$65)^$D$34:$M$34)+($M$26*(1+$B69)/(D$65-$B69))/(1+D$65)^$M$34-$C$53-$C$54)/$C$56,"") -> 1173.0892 | E69: =IFERROR((SUMPRODUCT($D$26:$M$26/(1+E$65)^$D$34:$M$34)+($M$26*(1+$B69)/(E$65-$B69))/(1+E$65)^$M$34-$C$53-$C$54)/$C$56,"") -> 958.74755 | F69: =IFERROR((SUMPRODUCT($D$26:$M$26/(1+F$65)^$D$34:$M$34)+($M$26*(1+$B69)/(F$65-$B69))/(1+F$65)^$M$34-$C$53-$C$54)/$C$56,"") -> 802.52532 | G69: =IFERROR((SUMPRODUCT($D$26:$M$26/(1+G$65)^$D$34:$M$34)+($M$26*(1+$B69)/(G$65-$B69))/(1+G$65)^$M$34-$C$53-$C$54)/$C$56,"") -> 683.64898 | H69: =IFERROR((SUMPRODUCT($D$26:$M$26/(1+H$65)^$D$34:$M$34)+($M$26*(1+$B69)/(H$65-$B69))/(1+H$65)^$M$34-$C$53-$C$54)/$C$56,"") -> 590.18966
B70: =B69+$C$64 -> 0.05 | D70: =IFERROR((SUMPRODUCT($D$26:$M$26/(1+D$65)^$D$34:$M$34)+($M$26*(1+$B70)/(D$65-$B70))/(1+D$65)^$M$34-$C$53-$C$54)/$C$56,"") -> 1426.6021 | E70: =IFERROR((SUMPRODUCT($D$26:$M$26/(1+E$65)^$D$34:$M$34)+($M$26*(1+$B70)/(E$65-$B70))/(1+E$65)^$M$34-$C$53-$C$54)/$C$56,"") -> 1126.4214 | F70: =IFERROR((SUMPRODUCT($D$26:$M$26/(1+F$65)^$D$34:$M$34)+($M$26*(1+$B70)/(F$65-$B70))/(1+F$65)^$M$34-$C$53-$C$54)/$C$56,"") -> 920.2703 | G70: =IFERROR((SUMPRODUCT($D$26:$M$26/(1+G$65)^$D$34:$M$34)+($M$26*(1+$B70)/(G$65-$B70))/(1+G$65)^$M$34-$C$53-$C$54)/$C$56,"") -> 769.99903 | H70: =IFERROR((SUMPRODUCT($D$26:$M$26/(1+H$65)^$D$34:$M$34)+($M$26*(1+$B70)/(H$65-$B70))/(1+H$65)^$M$34-$C$53-$C$54)/$C$56,"") -> 655.63519
B73: 5. REVERSE DCF
B74: To solve for the market-implied path: Data ▸ What-If Analysis ▸ Goal Seek — set C57 (implied price) to the current price (C58) by changing C32 (terminal growth) or the Model scenario levers (aggregates volume / ASP / margins, LNA growth & synergies, M&A spend).
B76: 6. MAUBOUSSIN EV / NOPAT — TWO-STAGE FRAMEWORK
B77: EV/NOPAT = 1/r + [g × (1 − r/ROIIC) / (r × (r − g))] × [1 − ((1+g)/(1+r))^N]
B78: Formula source: Mauboussin & Rappaport, "Expectations Investing" (2021); Counterpoint Global, "What Does a Price-Earnings Multiple Mean?" (2020).
B80: Input | C80: Value | D80: Rationale (Martin Marietta characteristics)
B81: r (Cost of capital / WACC) | C81: =$C$13 -> 0.081975 | D81: Linked from Section 1 WACC build
B82: g (NOPAT growth, Stage 1) | C82: 0.09 | D82: Model Adjusted EBIT CAGR 2026–30E: mid-single-digit aggregates pricing + low-single-digit volume, LNA synergies and deleveraging → ~9% NOPAT growth
B83: ROIIC (Return on incremental invested capital) | C83: 0.15 | D83: Aggregates pricing power on a fixed, permitted reserve base earns high returns on organic investment (capex ~8% of sales); acquired growth earns ~6–8% after tax on purchase price (LNA ~15x EBITDA incl. synergies)
B84: N (Years of value creation / CAP) | C84: 15 | D84: Irreplaceable permitted reserves (~70–100 years) in Sun Belt growth markets; local scale plus rail/water logistics; #1 U.S. lime producer post-LNA; disciplined SOAR 2030 capital allocation
B86: Calculation | C86: Value
B87: Steady-state component: 1 / r | C87: =1/C81 -> 12.198841
B88: Value-creation factor: 1 − r / ROIIC | C88: =1-C81/C83 -> 0.4535
B89: Growth multiplier: g × (1 − r/ROIIC) / (r × (r − g)) | C89: =C82*C88/(C81*(C81-C82)) -> -62.043078
B90: Time decay: 1 − ((1+g)/(1+r))^N | C90: =1-((1+C82)/(1+C81))^C84 -> -0.11722097
B91: PVGO component (growth value) | C91: =C89*C90 -> 7.2727495
B92: Mauboussin EV / NOPAT (steady-state + PVGO) | C92: =C87+C91 -> 19.471591
B94: VALUATION — Applied to 2028E NOPAT | C94: USDm
B95: 2028E Adjusted EBIT (Model) | C95: =Model!CC212 -> 2596.3706
B96: (−) 2028E acquisition & integration costs | C96: =-Model!CC158 -> -10
B97: Tax rate (from WACC build) | C97: =$C$10 -> 0.22
B98: 2028E NOPAT = (Adj. EBIT − acquisition costs) × (1 − t) | C98: =(C95+C96)*(1-C97) -> 2017.3691
B99: × Mauboussin EV/NOPAT multiple | C99: =C92 -> 19.471591
B100: Implied Enterprise Value (2028E basis) | C100: =C98*C99 -> 39281.385
B101: Less: YE2027 net debt + NCI (Model) | C101: =Model!CB421+Model!CB324 -> 10862.654
B102: Implied Equity Value | C102: =C100-C101 -> 28418.73
B103: Diluted shares 2028E (m, Model) | C103: =Model!CC427 -> 71.554402
B104: Implied share price 2028 ($) | C104: =C102/C103 -> 397.16257
B106: Current share price ($) | C106: =C58 -> 518.7
B107: Implied upside / (downside) | C107: =C104/C106-1 -> -0.2343116
B109: MARKET-IMPLIED EV/NOPAT TODAY | C109: USDm
B110: Current market cap (spot × diluted shares) | C110: =C58*C56 -> 36933.723
B111: Plus: YE2026 net debt & NCI | C111: =C53+C54 -> 12242.588
B112: Implied Enterprise Value (today) | C112: =C110+C111 -> 49176.311
B113: MLM's market-implied EV/NOPAT (on 2028E NOPAT) | C113: =C112/C98 -> 24.376457
B115: Multiple gap (Mauboussin − Market) | C115: =C92-C113 -> -4.9048668
B116: Implied re-rating headroom | C116: =C92/C113-1 -> -0.20121327

Sheet Charts
B2: Martin Marietta Materials — Historical Operating Performance (2006–2025)
B3: All historicals · USDm · Linked to Model. Volume / price = aggregates shipments and ASP y/y (company-reported price change where the $ ASP was not disclosed: 2007–12, 2014–15). Adjusted EBITDA as reconciled by MLM in each period (EBITDA before 2018); 2025 on the continuing-operations basis.
C7: 2006 | D7: 2007 | E7: 2008 | F7: 2009 | G7: 2010 | H7: 2011 | I7: 2012 | J7: 2013 | K7: 2014 | L7: 2015 | M7: 2016 | N7: 2017 | O7: 2018 | P7: 2019 | Q7: 2020 | R7: 2021 | S7: 2022 | T7: 2023 | U7: 2024 | V7: 2025
B8: Aggregates volume % | C8: =IFERROR(Model!C12+0,IFERROR(Model!C24+0,0)) -> 0 | D8: =IFERROR(Model!D12+0,IFERROR(Model!D24+0,0)) -> -0.081434833 | E8: =IFERROR(Model!E12+0,IFERROR(Model!E24+0,0)) -> -0.12598861 | F8: =IFERROR(Model!F12+0,IFERROR(Model!F24+0,0)) -> -0.22562204 | G8: =IFERROR(Model!G12+0,IFERROR(Model!G24+0,0)) -> 0.053532791 | H8: =IFERROR(Model!H12+0,IFERROR(Model!H24+0,0)) -> -0.037944111 | I8: =IFERROR(Model!I12+0,IFERROR(Model!I24+0,0)) -> 0.026040584 | J8: =IFERROR(Model!N12+0,IFERROR(Model!N24+0,0)) -> 0.00079481965 | K8: =IFERROR(Model!S12+0,IFERROR(Model!S24+0,0)) -> 0.1371688 | L8: =IFERROR(Model!X12+0,IFERROR(Model!X24+0,0)) -> 0.071016775 | M8: =IFERROR(Model!AC12+0,IFERROR(Model!AC24+0,0)) -> 0.01409009 | N8: =IFERROR(Model!AH12+0,IFERROR(Model!AH24+0,0)) -> -0.0058502389 | O8: =IFERROR(Model!AM12+0,IFERROR(Model!AM24+0,0)) -> 0.083311139 | P8: =IFERROR(Model!AR12+0,IFERROR(Model!AR24+0,0)) -> 0.11876888 | Q8: =IFERROR(Model!AW12+0,IFERROR(Model!AW24+0,0)) -> -0.024203928 | R8: =IFERROR(Model!BB12+0,IFERROR(Model!BB24+0,0)) -> 0.078820375 | S8: =IFERROR(Model!BG12+0,IFERROR(Model!BG24+0,0)) -> 0.032306163 | T8: =IFERROR(Model!BL12+0,IFERROR(Model!BL24+0,0)) -> -0.042850265 | U8: =IFERROR(Model!BQ12+0,IFERROR(Model!BQ24+0,0)) -> -0.038732394 | V8: =IFERROR(Model!BV12+0,IFERROR(Model!BV24+0,0)) -> 0.038723182
B9: Aggregates price (ASP) % | C9: =IFERROR(Model!C14+0,IFERROR(Model!C25+0,0)) -> 0 | D9: =IFERROR(Model!D14+0,IFERROR(Model!D25+0,0)) -> 0.104 | E9: =IFERROR(Model!E14+0,IFERROR(Model!E25+0,0)) -> 0.069 | F9: =IFERROR(Model!F14+0,IFERROR(Model!F25+0,0)) -> 0.021 | G9: =IFERROR(Model!G14+0,IFERROR(Model!G25+0,0)) -> -0.034 | H9: =IFERROR(Model!H14+0,IFERROR(Model!H25+0,0)) -> 0.027 | I9: =IFERROR(Model!I14+0,IFERROR(Model!I25+0,0)) -> 0.008 | J9: =IFERROR(Model!N14+0,IFERROR(Model!N25+0,0)) -> 0.029041626 | K9: =IFERROR(Model!S14+0,IFERROR(Model!S25+0,0)) -> 0.045 | L9: =IFERROR(Model!X14+0,IFERROR(Model!X25+0,0)) -> 0.08 | M9: =IFERROR(Model!AC14+0,IFERROR(Model!AC25+0,0)) -> 0.073 | N9: =IFERROR(Model!AH14+0,IFERROR(Model!AH25+0,0)) -> 0.045031056 | O9: =IFERROR(Model!AM14+0,IFERROR(Model!AM25+0,0)) -> 0.018573551 | P9: =IFERROR(Model!AR14+0,IFERROR(Model!AR25+0,0)) -> 0.045222465 | Q9: =IFERROR(Model!AW14+0,IFERROR(Model!AW25+0,0)) -> 0.030704815 | R9: =IFERROR(Model!BB14+0,IFERROR(Model!BB25+0,0)) -> 0.02098849 | S9: =IFERROR(Model!BG14+0,IFERROR(Model!BG25+0,0)) -> 0.1061008 | T9: =IFERROR(Model!BL14+0,IFERROR(Model!BL25+0,0)) -> 0.18944844 | U9: =IFERROR(Model!BQ14+0,IFERROR(Model!BQ25+0,0)) -> 0.098790323 | V9: =IFERROR(Model!BV14+0,IFERROR(Model!BV25+0,0)) -> 0.068807339
C11: =C7 -> 2006 | D11: =D7 -> 2007 | E11: =E7 -> 2008 | F11: =F7 -> 2009 | G11: =G7 -> 2010 | H11: =H7 -> 2011 | I11: =I7 -> 2012 | J11: =J7 -> 2013 | ... V11: =V7 -> 2025
B12: Adjusted EBITDA | C12: =Model!C204 -> 535 | D12: =Model!D204 -> 590.6 | E12: =Model!E204 -> 497.7 | F12: =Model!F204 -> 364.1 | G12: =Model!G204 -> 374.7 | H12: =Model!H204 -> 335.9 | I12: =Model!I204 -> 329.9 | J12: =Model!N204 -> 390.2 | K12: =Model!S204 -> 537 | L12: =Model!X204 -> 766.7 | M12: =Model!AC204 -> 971.6 | N12: =Model!AH204 -> 1004.4 | O12: =Model!AM204 -> 1103.765 | P12: =Model!AR204 -> 1254.549 | Q12: =Model!AW204 -> 1392.8 | R12: =Model!BB204 -> 1528.5 | S12: =Model!BG204 -> 1600.3 | T12: =Model!BL204 -> 2127.7 | U12: =Model!BQ204 -> 2066 | V12: =Model!BV204 -> 2065
B13: Earnings from Operations (GAAP) | C13: =Model!C160 -> 388 | D13: =Model!D160 -> 433 | E13: =Model!E160 -> 323.3 | F13: =Model!F160 -> 187.6 | G13: =Model!G160 -> 196.4 | H13: =Model!H160 -> 161 | I13: =Model!I160 -> 155 | J13: =Model!N160 -> 218 | K13: =Model!S160 -> 314.9 | L13: =Model!X160 -> 479.4 | M13: =Model!AC160 -> 667.3 | N13: =Model!AH160 -> 700.4 | O13: =Model!AM160 -> 690.737 | P13: =Model!AR160 -> 884.934 | Q13: =Model!AW160 -> 1005.4 | R13: =Model!BB160 -> 973.8 | S13: =Model!BG160 -> 1206.7 | T13: =Model!BL160 -> 1596 | U13: =Model!BQ160 -> 2707 | V13: =Model!BV160 -> 1437
B14: Adj. EBITDA Margin % | C14: =Model!C238 -> 0.24247643 | D14: =Model!D238 -> 0.26759096 | E14: =Model!E238 -> 0.23475308 | F14: =Model!F238 -> 0.21384941 | G14: =Model!G238 -> 0.21016322 | H14: =Model!H238 -> 0.19598576 | I14: =Model!I238 -> 0.16190616 | J14: =Model!N238 -> 0.18102528 | K14: =Model!S238 -> 0.18154158 | L14: =Model!X238 -> 0.2166064 | M14: =Model!AC238 -> 0.25442547 | N14: =Model!AH238 -> 0.25327819 | O14: =Model!AM238 -> 0.26006034 | P14: =Model!AR238 -> 0.26472316 | Q14: =Model!AW238 -> 0.29446711 | R14: =Model!BB238 -> 0.28232361 | S14: =Model!BG238 -> 0.25975944 | T14: =Model!BL238 -> 0.31394971 | U14: =Model!BQ238 -> 0.31609547 | V14: =Model!BV238 -> 0.33577236
B15: GAAP Op. Margin % | C15: =Model!C240 -> 0.17585207 | D15: =Model!D240 -> 0.19618504 | E15: =Model!E240 -> 0.15249281 | F15: =Model!F240 -> 0.11018442 | G15: =Model!G240 -> 0.11015761 | H15: =Model!H240 -> 0.093937803 | I15: =Model!I240 -> 0.076069886 | J15: =Model!N240 -> 0.10113663 | K15: =Model!S240 -> 0.10645707 | L15: =Model!X240 -> 0.13543903 | M15: =Model!AC240 -> 0.17474076 | N15: =Model!AH240 -> 0.17661892 | O15: =Model!AM240 -> 0.16274596 | P15: =Model!AR240 -> 0.18673047 | Q15: =Model!AW240 -> 0.21256263 | R15: =Model!BB240 -> 0.17986701 | S15: =Model!BG240 -> 0.1958706 | T15: =Model!BL240 -> 0.23549548 | U15: =Model!BQ240 -> 0.41416769 | V15: =Model!BV240 -> 0.23365854
C17: =C7 -> 2006 | D17: =D7 -> 2007 | E17: =E7 -> 2008 | F17: =F7 -> 2009 | G17: =G7 -> 2010 | H17: =H7 -> 2011 | I17: =I7 -> 2012 | J17: =J7 -> 2013 | ... V17: =V7 -> 2025
B18: ROIC | C18: =IFERROR(Model!C404+0,NA()) -> 0.14210892 | D18: =IFERROR(Model!D404+0,NA()) -> 0.14888392 | E18: =IFERROR(Model!E404+0,NA()) -> 0.096542535 | F18: =IFERROR(Model!F404+0,NA()) -> 0.059397211 | G18: =IFERROR(Model!G404+0,NA()) -> 0.061867321 | H18: =IFERROR(Model!H404+0,NA()) -> 0.052294967 | I18: =IFERROR(Model!I404+0,NA()) -> 0.052185242 | J18: =IFERROR(Model!N404+0,NA()) -> 0.062340196 | K18: =IFERROR(Model!S404+0,NA()) -> 0.03361715 | L18: =IFERROR(Model!X404+0,NA()) -> 0.064646377 | M18: =IFERROR(Model!AC404+0,NA()) -> 0.083522916 | N18: =IFERROR(Model!AH404+0,NA()) -> 0.13074083 | O18: =IFERROR(Model!AM404+0,NA()) -> 0.077709273 | P18: =IFERROR(Model!AR404+0,NA()) -> 0.088493879 | Q18: =IFERROR(Model!AW404+0,NA()) -> 0.098218959 | R18: =IFERROR(Model!BB404+0,NA()) -> 0.0783412 | S18: =IFERROR(Model!BG404+0,NA()) -> 0.077645377 | T18: =IFERROR(Model!BL404+0,NA()) -> 0.11746405 | U18: =IFERROR(Model!BQ404+0,NA()) -> 0.08133323 | V18: =IFERROR(Model!BV404+0,NA()) -> 0.078373843
B19: RONTA | C19: =IFERROR(Model!C415+0,NA()) -> 0.15775686 | D19: =IFERROR(Model!D415+0,NA()) -> 0.16330395 | E19: =IFERROR(Model!E415+0,NA()) -> 0.10230041 | F19: =IFERROR(Model!F415+0,NA()) -> 0.057879715 | G19: =IFERROR(Model!G415+0,NA()) -> 0.065503105 | H19: =IFERROR(Model!H415+0,NA()) -> 0.056197882 | I19: =IFERROR(Model!I415+0,NA()) -> 0.055462961 | J19: =IFERROR(Model!N415+0,NA()) -> 0.066682737 | K19: =IFERROR(Model!S415+0,NA()) -> 0.039851224 | L19: =IFERROR(Model!X415+0,NA()) -> 0.078859899 | M19: =IFERROR(Model!AC415+0,NA()) -> 0.10256416 | N19: =IFERROR(Model!AH415+0,NA()) -> 0.12853746 | O19: =IFERROR(Model!AM415+0,NA()) -> 0.099709944 | P19: =IFERROR(Model!AR415+0,NA()) -> 0.10627788 | Q19: =IFERROR(Model!AW415+0,NA()) -> 0.114027 | R19: =IFERROR(Model!BB415+0,NA()) -> 0.098174524 | S19: =IFERROR(Model!BG415+0,NA()) -> 0.095704038 | T19: =IFERROR(Model!BL415+0,NA()) -> 0.12709608 | U19: =IFERROR(Model!BQ415+0,NA()) -> 0.090349753 | V19: =IFERROR(Model!BV415+0,NA()) -> 0.087006175
B20: Adj. EBITDA margin % | C20: =IFERROR(Model!C238+0,NA()) -> 0.24247643 | D20: =IFERROR(Model!D238+0,NA()) -> 0.26759096 | E20: =IFERROR(Model!E238+0,NA()) -> 0.23475308 | F20: =IFERROR(Model!F238+0,NA()) -> 0.21384941 | G20: =IFERROR(Model!G238+0,NA()) -> 0.21016322 | H20: =IFERROR(Model!H238+0,NA()) -> 0.19598576 | I20: =IFERROR(Model!I238+0,NA()) -> 0.16190616 | J20: =IFERROR(Model!N238+0,NA()) -> 0.18102528 | K20: =IFERROR(Model!S238+0,NA()) -> 0.18154158 | L20: =IFERROR(Model!X238+0,NA()) -> 0.2166064 | M20: =IFERROR(Model!AC238+0,NA()) -> 0.25442547 | N20: =IFERROR(Model!AH238+0,NA()) -> 0.25327819 | O20: =IFERROR(Model!AM238+0,NA()) -> 0.26006034 | P20: =IFERROR(Model!AR238+0,NA()) -> 0.26472316 | Q20: =IFERROR(Model!AW238+0,NA()) -> 0.29446711 | R20: =IFERROR(Model!BB238+0,NA()) -> 0.28232361 | S20: =IFERROR(Model!BG238+0,NA()) -> 0.25975944 | T20: =IFERROR(Model!BL238+0,NA()) -> 0.31394971 | U20: =IFERROR(Model!BQ238+0,NA()) -> 0.31609547 | V20: =IFERROR(Model!BV238+0,NA()) -> 0.33577236
B21: FCF margin % | C21: =IFERROR(Model!C275+0,NA()) -> 0.032730239 | D21: =IFERROR(Model!D275+0,NA()) -> 0.059193059 | E21: =IFERROR(Model!E275+0,NA()) -> 0.04121881 | F21: =IFERROR(Model!F275+0,NA()) -> 0.10521438 | G21: =IFERROR(Model!G275+0,NA()) -> 0.075097874 | H21: =IFERROR(Model!H275+0,NA()) -> 0.060523368 | I21: =IFERROR(Model!I275+0,NA()) -> 0.035171771 | J21: =IFERROR(Model!N275+0,NA()) -> 0.071314312 | K21: =IFERROR(Model!S275+0,NA()) -> 0.050532454 | L21: =IFERROR(Model!X275+0,NA()) -> 0.072019155 | M21: =IFERROR(Model!AC275+0,NA()) -> 0.076303289 | N21: =IFERROR(Model!AH275+0,NA()) -> 0.062425106 | O21: =IFERROR(Model!AM275+0,NA()) -> 0.077562075 | P21: =IFERROR(Model!AR275+0,NA()) -> 0.12082468 | Q21: =IFERROR(Model!AW275+0,NA()) -> 0.14596503 | R21: =IFERROR(Model!BB275+0,NA()) -> 0.13199113 | S21: =IFERROR(Model!BG275+0,NA()) -> 0.082685409 | T21: =IFERROR(Model!BL275+0,NA()) -> 0.12956678 | U21: =IFERROR(Model!BQ275+0,NA()) -> 0.092411261 | V21: =IFERROR(Model!BV275+0,NA()) -> 0.15902439
