Workbook

Sheet Model
CK1: SCENARIO SWITCH ▼ (Bull / Base / Bear) — drives all scenario-linked forecast drivers
B2: Microsoft Corporation (NASDAQ: MSFT) — 3-Statement Financial Model | CK2: Base
B3: US GAAP as reported · USD millions (per-share data in USD; shares in millions) · Fiscal years ended 30 June (2027 = Jul-2026 – Jun-2027) · Source: Microsoft Forms 10-K / 10-Q, Form 8-K earnings releases (Ex. 99.1) and the 8-K of 2-Sep-2026 (FY27 segments, restated history, Q1 FY27 outlook), SEC EDGAR (CIK 0000789019); XBRL company facts. FY27 full-year call commentary is UNVERIFIED (information rows only).
B4: Basis notes: as originally reported (FY2016–17 ASC 606 / 842 restatement and later segment recasts not applied; memo comments). Segment build on the FY27 structure (Agents and Infra / Devices and Consumer), restated history Q1/25–Q4/26 only; earlier structures as memo. Acquisitions: LinkedIn Dec-16, Nuance Mar-22, Activision Blizzard Oct-23. Q1/27E calibrated to the Q1 FY27 outlook; Q2–Q4/27E carry the Q1 calibration. Share price $541 (user, 12-Oct-2026).
CM5: Forecast | CN5: Historical | CO5: Historical | CP5: Historical
B6: (USDm) | C6: 2006 | D6: 2007 | E6: 2008 | F6: 2009 | G6: 2010 | H6: 2011 | I6: 2012 | J6: Q1/13 | K6: Q2/13 | L6: Q3/13 | M6: Q4/13 | N6: 2013 | O6: Q1/14 | P6: Q2/14 | Q6: Q3/14 | R6: Q4/14 | S6: 2014 | T6: Q1/15 | U6: Q2/15 | V6: Q3/15 | W6: Q4/15 | X6: 2015 | Y6: Q1/16 | Z6: Q2/16 | AA6: Q3/16 | AB6: Q4/16 | AC6: 2016 | AD6: Q1/17 | AE6: Q2/17 | AF6: Q3/17 | AG6: Q4/17 | AH6: 2017 | AI6: Q1/18 | AJ6: Q2/18 | AK6: Q3/18 | AL6: Q4/18 | AM6: 2018 | AN6: Q1/19 | AO6: Q2/19 | AP6: Q3/19 | AQ6: Q4/19 | AR6: 2019 | AS6: Q1/20 | AT6: Q2/20 | AU6: Q3/20 | AV6: Q4/20 | AW6: 2020 | AX6: Q1/21 | AY6: Q2/21 | AZ6: Q3/21 | BA6: Q4/21 | BB6: 2021 | BC6: Q1/22 | BD6: Q2/22 | BE6: Q3/22 | BF6: Q4/22 | BG6: 2022 | BH6: Q1/23 | BI6: Q2/23 | BJ6: Q3/23 | BK6: Q4/23 | BL6: 2023 | BM6: Q1/24 | BN6: Q2/24 | BO6: Q3/24 | BP6: Q4/24 | BQ6: 2024 | BR6: Q1/25 | BS6: Q2/25 | BT6: Q3/25 | BU6: Q4/25 | BV6: 2025 | BW6: Q1/26 | BX6: Q2/26 | BY6: Q3/26 | BZ6: Q4/26 | CA6: 2026 | CB6: Q1/27E | CC6: Q2/27E | CD6: Q3/27E | CE6: Q4/27E | CF6: 2027E | CG6: 2028E | CH6: 2029E | CI6: 2030E | CJ6: 2031E | CK6: Modelling Notes | CM6: 5Y CAGR | CN6: 5Y CAGR | CO6: 10Y CAGR | CP6: 20Y CAGR
CM7: 26-'31 | CN7: 21-'26 | CO7: 16-'26 | CP7: 06-'26
B8: SEGMENT P&L — AGENTS AND INFRA · DEVICES AND CONSUMER (FY27 structure: product & service lines × segment operating margin) | CK8: SEGMENT BUILD — modelling logic (product & service revenue → segment revenue → segment operating income at the segment margin → operating income → GAAP P&L)
CS9: SCENARIO INPUT TABLE — driver assumptions per Bull / Base / Bear | CT9: Bull | CU9: Base | CV9: Bear | CW9: Bull / Bear = Base + Δ (Δ inputs on each block header). Outlook block = high / mid / low end of the Q1 FY27 guidance ranges (costs: low / mid / high).
B10: Agents and Infra (Azure, Microsoft 365 cloud, productivity & server licensing, industry solutions — Dynamics 365, LinkedIn Talent / Sales, healthcare — and frontier & support services) | CK10: AGENTS AND INFRA — modelling logic (history: restated FY27 basis, 8-K 2-Sep-2026, Q1/25–Q4/26 only)
B11: Azure revenue | BR11: 16021 | BS11: 17337 | BT11: 18540 | BU11: 20712 | BV11: 72610 | BW11: 22384 | BX11: 24129 | BY11: 26008 | BZ11: 29417 | CA11: 101938 | CB11: =BW11*(1+CB12) -> 31523.127 | CC11: =BX11*(1+CC12) -> 33980.59 | CD11: =BY11*(1+CD12) -> 36626.764 | CE11: =BZ11*(1+CE12) -> 41427.619 | CF11: =SUM(CB11:CE11) -> 143558.1 | CG11: =CF11*(1+CG12) -> 189496.69 | CH11: =CG11*(1+CH12) -> 238765.83 | CI11: =CH11*(1+CI12) -> 288906.65 | CJ11: =CI11*(1+CJ12) -> 338020.79 | CK11: Restated product & service revenue (FY27 definitions; 8-K 2-Sep-2026, Ex. 99.1). Q1–Q4/27E: prior-year quarter × (1 + growth). 2028E+: prior year × (1 + scenario lever). | CM11: =IFERROR((CJ11/CA11)^(1/5)-1,"n/m") -> 0.2709295 | CN11: =IFERROR((CA11/BB11)^(1/5)-1,"n/m") -> n/m | CO11: =IFERROR((CA11/AC11)^(1/10)-1,"n/m") -> n/m | CP11: =IFERROR((CA11/C11)^(1/20)-1,"n/m") -> n/m | CS11: Q1 FY27 guidance — 29-Jul-2026 call, re-filed in 8-K 2-Sep-2026 (Item 7.01, Ex. 99.1; SEC-filed) | CT11: High | CU11: Mid | CV11: Low | CW11: Total revenue $89.85–90.95bn: Agents and Infra $75.15–75.75bn, Devices and Consumer $14.7–15.2bn (adjusted to the FY27 segments); COGS $29.6–29.8bn; operating expenses $16.8–16.9bn; other income ~$(100)m ex OpenAI; operating margin relatively flat y/y; ETR ~20%; capex over $50bn. Cost rows: Bull = low end, Bear = high end.
B12: y/y % | D12: =IF(AND(ISNUMBER(D11),ISNUMBER(C11)),IFERROR(D11/C11-1,""),"") | E12: =IF(AND(ISNUMBER(E11),ISNUMBER(D11)),IFERROR(E11/D11-1,""),"") | F12: =IF(AND(ISNUMBER(F11),ISNUMBER(E11)),IFERROR(F11/E11-1,""),"") | G12: =IF(AND(ISNUMBER(G11),ISNUMBER(F11)),IFERROR(G11/F11-1,""),"") | H12: =IF(AND(ISNUMBER(H11),ISNUMBER(G11)),IFERROR(H11/G11-1,""),"") | I12: =IF(AND(ISNUMBER(I11),ISNUMBER(H11)),IFERROR(I11/H11-1,""),"") | N12: =IF(AND(ISNUMBER(N11),ISNUMBER(I11)),IFERROR(N11/I11-1,""),"") | O12: =IF(AND(ISNUMBER(O11),ISNUMBER(J11)),IFERROR(O11/J11-1,""),"") | P12: =IF(AND(ISNUMBER(P11),ISNUMBER(K11)),IFERROR(P11/K11-1,""),"") | Q12: =IF(AND(ISNUMBER(Q11),ISNUMBER(L11)),IFERROR(Q11/L11-1,""),"") | R12: =IF(AND(ISNUMBER(R11),ISNUMBER(M11)),IFERROR(R11/M11-1,""),"") | S12: =IF(AND(ISNUMBER(S11),ISNUMBER(N11)),IFERROR(S11/N11-1,""),"") | T12: =IF(AND(ISNUMBER(T11),ISNUMBER(O11)),IFERROR(T11/O11-1,""),"") | U12: =IF(AND(ISNUMBER(U11),ISNUMBER(P11)),IFERROR(U11/P11-1,""),"") | ... CA12: =IF(AND(ISNUMBER(CA11),ISNUMBER(BV11)),IFERROR(CA11/BV11-1,""),"") -> 0.40391131 | CB12: =CB13+$CB$139 -> 0.40828836 | CC12: =CC13+$CB$139 -> 0.40828836 | CD12: =CD13+$CB$139 -> 0.40828836 | CE12: =CE13+$CB$139 -> 0.40828836 | CF12: =IF(AND(ISNUMBER(CF11),ISNUMBER(CA11)),IFERROR(CF11/CA11-1,""),"") -> 0.40828836 | CG12: =CHOOSE(MATCH($CK$2,{"Bull","Base","Bear"},0),$CT$27,$CU$27,$CV$27) -> 0.32 | CH12: =CHOOSE(MATCH($CK$2,{"Bull","Base","Bear"},0),$CT$28,$CU$28,$CV$28) -> 0.26 | CI12: =CHOOSE(MATCH($CK$2,{"Bull","Base","Bear"},0),$CT$29,$CU$29,$CV$29) -> 0.21 | CJ12: =CHOOSE(MATCH($CK$2,{"Bull","Base","Bear"},0),$CT$30,$CU$30,$CV$30) -> 0.17 | CK12: Q1–Q4/27E: Q4/26 y/y growth of the line + the segment calibration Δ solved in Q1/27E to the segment revenue guidance (carried to Q2–Q4). 2028E–2031E: scenario lever (Bull/Base/Bear table →). | CS12: Q1 FY27 Agents and Infra revenue ($m) | CT12: 75750 | CU12: 75450 | CV12: 75150 | CW12: Guided $75.15–75.75bn (8-K 2-Sep-2026). Drives the Agents and Infra growth calibration.
B13: Growth before calibration (Q4/26 y/y, latest actual quarter) | CB13: =IFERROR(BZ11/BU11-1,0) -> 0.42028776 | CC13: =IFERROR(BZ11/BU11-1,0) -> 0.42028776 | CD13: =IFERROR(BZ11/BU11-1,0) -> 0.42028776 | CE13: =IFERROR(BZ11/BU11-1,0) -> 0.42028776 | CS13: Q1 FY27 Devices and Consumer revenue ($m) | CT13: 15200 | CU13: 14950 | CV13: 14700 | CW13: Guided $14.7–15.2bn. Drives the Devices and Consumer growth calibration.
B14: Microsoft 365 cloud revenue | BR14: 20017 | BS14: 20686 | BT14: 20967 | BU14: 22935 | BV14: 84605 | BW14: 23694 | BX14: 24466 | BY14: 25418 | BZ14: 26721 | CA14: 100299 | CB14: =BW14*(1+CB15) -> 27320.978 | CC14: =BX14*(1+CC15) -> 28211.153 | CD14: =BY14*(1+CD15) -> 29308.881 | CE14: =BZ14*(1+CE15) -> 30811.339 | CF14: =SUM(CB14:CE14) -> 115652.35 | CG14: =CF14*(1+CG15) -> 131843.68 | CH14: =CG14*(1+CH15) -> 148983.36 | CI14: =CH14*(1+CI15) -> 166861.36 | CJ14: =CI14*(1+CJ15) -> 185216.11 | CM14: =IFERROR((CJ14/CA14)^(1/5)-1,"n/m") -> 0.13051527 | CN14: =IFERROR((CA14/BB14)^(1/5)-1,"n/m") -> n/m | CO14: =IFERROR((CA14/AC14)^(1/10)-1,"n/m") -> n/m | CP14: =IFERROR((CA14/C14)^(1/20)-1,"n/m") -> n/m | CS14: Q1 FY27 cost of revenue ($m; Bull = low end) | CT14: 29600 | CU14: 29700 | CV14: 29800 | CW14: Guided $29.6–29.8bn. With opex, sets the guided operating income for the margin calibration.
B15: y/y % | D15: =IF(AND(ISNUMBER(D14),ISNUMBER(C14)),IFERROR(D14/C14-1,""),"") | E15: =IF(AND(ISNUMBER(E14),ISNUMBER(D14)),IFERROR(E14/D14-1,""),"") | F15: =IF(AND(ISNUMBER(F14),ISNUMBER(E14)),IFERROR(F14/E14-1,""),"") | G15: =IF(AND(ISNUMBER(G14),ISNUMBER(F14)),IFERROR(G14/F14-1,""),"") | H15: =IF(AND(ISNUMBER(H14),ISNUMBER(G14)),IFERROR(H14/G14-1,""),"") | I15: =IF(AND(ISNUMBER(I14),ISNUMBER(H14)),IFERROR(I14/H14-1,""),"") | N15: =IF(AND(ISNUMBER(N14),ISNUMBER(I14)),IFERROR(N14/I14-1,""),"") | O15: =IF(AND(ISNUMBER(O14),ISNUMBER(J14)),IFERROR(O14/J14-1,""),"") | P15: =IF(AND(ISNUMBER(P14),ISNUMBER(K14)),IFERROR(P14/K14-1,""),"") | Q15: =IF(AND(ISNUMBER(Q14),ISNUMBER(L14)),IFERROR(Q14/L14-1,""),"") | R15: =IF(AND(ISNUMBER(R14),ISNUMBER(M14)),IFERROR(R14/M14-1,""),"") | S15: =IF(AND(ISNUMBER(S14),ISNUMBER(N14)),IFERROR(S14/N14-1,""),"") | T15: =IF(AND(ISNUMBER(T14),ISNUMBER(O14)),IFERROR(T14/O14-1,""),"") | U15: =IF(AND(ISNUMBER(U14),ISNUMBER(P14)),IFERROR(U14/P14-1,""),"") | ... CA15: =IF(AND(ISNUMBER(CA14),ISNUMBER(BV14)),IFERROR(CA14/BV14-1,""),"") -> 0.18549731 | CB15: =CB16+$CB$139 -> 0.15307582 | CC15: =CC16+$CB$139 -> 0.15307582 | CD15: =CD16+$CB$139 -> 0.15307582 | CE15: =CE16+$CB$139 -> 0.15307582 | CF15: =IF(AND(ISNUMBER(CF14),ISNUMBER(CA14)),IFERROR(CF14/CA14-1,""),"") -> 0.15307582 | CG15: =CHOOSE(MATCH($CK$2,{"Bull","Base","Bear"},0),$CT$32,$CU$32,$CV$32) -> 0.14 | CH15: =CHOOSE(MATCH($CK$2,{"Bull","Base","Bear"},0),$CT$33,$CU$33,$CV$33) -> 0.13 | CI15: =CHOOSE(MATCH($CK$2,{"Bull","Base","Bear"},0),$CT$34,$CU$34,$CV$34) -> 0.12 | CJ15: =CHOOSE(MATCH($CK$2,{"Bull","Base","Bear"},0),$CT$35,$CU$35,$CV$35) -> 0.11 | CS15: Q1 FY27 operating expenses ($m; Bull = low end) | CT15: 16800 | CU15: 16850 | CV15: 16900 | CW15: Guided $16.8–16.9bn. Drives Q1/27E R&D, S&M and G&A (prior-year mix).
B16: Growth before calibration (Q4/26 y/y, latest actual quarter) | CB16: =IFERROR(BZ14/BU14-1,0) -> 0.16507521 | CC16: =IFERROR(BZ14/BU14-1,0) -> 0.16507521 | CD16: =IFERROR(BZ14/BU14-1,0) -> 0.16507521 | CE16: =IFERROR(BZ14/BU14-1,0) -> 0.16507521
B17: Productivity and server licensing revenue | BR17: 8051 | BS17: 8307 | BT17: 8731 | BU17: 10302 | BV17: 35391 | BW17: 8678 | BX17: 8814 | BY17: 8760 | BZ17: 11033 | CA17: 37285 | CB17: =BW17*(1+CB18) -> 9189.6349 | CC17: =BX17*(1+CC18) -> 9333.6532 | CD17: =BY17*(1+CD18) -> 9276.4695 | CE17: =BZ17*(1+CE18) -> 11683.48 | CF17: =SUM(CB17:CE17) -> 39483.238 | CG17: =CF17*(1+CG18) -> 38693.573 | CH17: =CG17*(1+CH18) -> 37919.702 | CI17: =CH17*(1+CI18) -> 36782.111 | CJ17: =CI17*(1+CJ18) -> 35678.647 | CM17: =IFERROR((CJ17/CA17)^(1/5)-1,"n/m") -> -0.0087690663 | CN17: =IFERROR((CA17/BB17)^(1/5)-1,"n/m") -> n/m | CO17: =IFERROR((CA17/AC17)^(1/10)-1,"n/m") -> n/m | CP17: =IFERROR((CA17/C17)^(1/20)-1,"n/m") -> n/m | CS17: FY2027E point estimates (all cases)
B18: y/y % | D18: =IF(AND(ISNUMBER(D17),ISNUMBER(C17)),IFERROR(D17/C17-1,""),"") | E18: =IF(AND(ISNUMBER(E17),ISNUMBER(D17)),IFERROR(E17/D17-1,""),"") | F18: =IF(AND(ISNUMBER(F17),ISNUMBER(E17)),IFERROR(F17/E17-1,""),"") | G18: =IF(AND(ISNUMBER(G17),ISNUMBER(F17)),IFERROR(G17/F17-1,""),"") | H18: =IF(AND(ISNUMBER(H17),ISNUMBER(G17)),IFERROR(H17/G17-1,""),"") | I18: =IF(AND(ISNUMBER(I17),ISNUMBER(H17)),IFERROR(I17/H17-1,""),"") | N18: =IF(AND(ISNUMBER(N17),ISNUMBER(I17)),IFERROR(N17/I17-1,""),"") | O18: =IF(AND(ISNUMBER(O17),ISNUMBER(J17)),IFERROR(O17/J17-1,""),"") | P18: =IF(AND(ISNUMBER(P17),ISNUMBER(K17)),IFERROR(P17/K17-1,""),"") | Q18: =IF(AND(ISNUMBER(Q17),ISNUMBER(L17)),IFERROR(Q17/L17-1,""),"") | R18: =IF(AND(ISNUMBER(R17),ISNUMBER(M17)),IFERROR(R17/M17-1,""),"") | S18: =IF(AND(ISNUMBER(S17),ISNUMBER(N17)),IFERROR(S17/N17-1,""),"") | T18: =IF(AND(ISNUMBER(T17),ISNUMBER(O17)),IFERROR(T17/O17-1,""),"") | U18: =IF(AND(ISNUMBER(U17),ISNUMBER(P17)),IFERROR(U17/P17-1,""),"") | ... CA18: =IF(AND(ISNUMBER(CA17),ISNUMBER(BV17)),IFERROR(CA17/BV17-1,""),"") -> 0.053516431 | CB18: =CB19+$CB$139 -> 0.058957703 | CC18: =CC19+$CB$139 -> 0.058957703 | CD18: =CD19+$CB$139 -> 0.058957703 | CE18: =CE19+$CB$139 -> 0.058957703 | CF18: =IF(AND(ISNUMBER(CF17),ISNUMBER(CA17)),IFERROR(CF17/CA17-1,""),"") -> 0.058957703 | CG18: =CHOOSE(MATCH($CK$2,{"Bull","Base","Bear"},0),$CT$37,$CU$37,$CV$37) -> -0.02 | CH18: =CHOOSE(MATCH($CK$2,{"Bull","Base","Bear"},0),$CT$38,$CU$38,$CV$38) -> -0.02 | CI18: =CHOOSE(MATCH($CK$2,{"Bull","Base","Bear"},0),$CT$39,$CU$39,$CV$39) -> -0.03 | CJ18: =CHOOSE(MATCH($CK$2,{"Bull","Base","Bear"},0),$CT$40,$CU$40,$CV$40) -> -0.03 | CS18: Q1–Q4/27E other income (expense), net per quarter ($m) | CU18: -100 | CW18: Guided ~$(100)m for Q1 excluding any impact from investments in OpenAI; held for Q2–Q4 (assumption).
B19: Growth before calibration (Q4/26 y/y, latest actual quarter) | CB19: =IFERROR(BZ17/BU17-1,0) -> 0.070957096 | CC19: =IFERROR(BZ17/BU17-1,0) -> 0.070957096 | CD19: =IFERROR(BZ17/BU17-1,0) -> 0.070957096 | CE19: =IFERROR(BZ17/BU17-1,0) -> 0.070957096 | CS19: FY27E effective tax rate | CU19: 0.2 | CW19: Guided ~20% for Q1 (8-K 2-Sep-2026); held for the year (assumption). FY26 19.4%.
B20: Industry solutions revenue | BR20: 4459 | BS20: 4544 | BT20: 4579 | BU20: 4835 | BV20: 18417 | BW20: 4894 | BX20: 4994 | BY20: 5165 | BZ20: 5292 | CA20: 20345 | CB20: =BW20*(1+CB21) -> 5297.8516 | CC20: =BX20*(1+CC21) -> 5406.1036 | CD20: =BY20*(1+CD21) -> 5591.2145 | CE20: =BZ20*(1+CE21) -> 5728.6945 | CF20: =SUM(CB20:CE20) -> 22023.864 | CG20: =CF20*(1+CG21) -> 24006.012 | CH20: =CG20*(1+CH21) -> 26166.553 | CI20: =CH20*(1+CI21) -> 28259.877 | CJ20: =CI20*(1+CJ21) -> 30520.667 | CM20: =IFERROR((CJ20/CA20)^(1/5)-1,"n/m") -> 0.084494281 | CN20: =IFERROR((CA20/BB20)^(1/5)-1,"n/m") -> n/m | CO20: =IFERROR((CA20/AC20)^(1/10)-1,"n/m") -> n/m | CP20: =IFERROR((CA20/C20)^(1/20)-1,"n/m") -> n/m | CS20: FY27E quarterly dividend declared ($) | CU20: 1 | CW20: Assumption: $0.91 + ~10% (Sep-2025 raise +9.6%); the Sep-2026 declaration is not in the EDGAR filings reviewed. Update when filed.
B21: y/y % | D21: =IF(AND(ISNUMBER(D20),ISNUMBER(C20)),IFERROR(D20/C20-1,""),"") | E21: =IF(AND(ISNUMBER(E20),ISNUMBER(D20)),IFERROR(E20/D20-1,""),"") | F21: =IF(AND(ISNUMBER(F20),ISNUMBER(E20)),IFERROR(F20/E20-1,""),"") | G21: =IF(AND(ISNUMBER(G20),ISNUMBER(F20)),IFERROR(G20/F20-1,""),"") | H21: =IF(AND(ISNUMBER(H20),ISNUMBER(G20)),IFERROR(H20/G20-1,""),"") | I21: =IF(AND(ISNUMBER(I20),ISNUMBER(H20)),IFERROR(I20/H20-1,""),"") | N21: =IF(AND(ISNUMBER(N20),ISNUMBER(I20)),IFERROR(N20/I20-1,""),"") | O21: =IF(AND(ISNUMBER(O20),ISNUMBER(J20)),IFERROR(O20/J20-1,""),"") | P21: =IF(AND(ISNUMBER(P20),ISNUMBER(K20)),IFERROR(P20/K20-1,""),"") | Q21: =IF(AND(ISNUMBER(Q20),ISNUMBER(L20)),IFERROR(Q20/L20-1,""),"") | R21: =IF(AND(ISNUMBER(R20),ISNUMBER(M20)),IFERROR(R20/M20-1,""),"") | S21: =IF(AND(ISNUMBER(S20),ISNUMBER(N20)),IFERROR(S20/N20-1,""),"") | T21: =IF(AND(ISNUMBER(T20),ISNUMBER(O20)),IFERROR(T20/O20-1,""),"") | U21: =IF(AND(ISNUMBER(U20),ISNUMBER(P20)),IFERROR(U20/P20-1,""),"") | ... CA21: =IF(AND(ISNUMBER(CA20),ISNUMBER(BV20)),IFERROR(CA20/BV20-1,""),"") -> 0.10468589 | CB21: =CB22+$CB$139 -> 0.082519739 | CC21: =CC22+$CB$139 -> 0.082519739 | CD21: =CD22+$CB$139 -> 0.082519739 | CE21: =CE22+$CB$139 -> 0.082519739 | CF21: =IF(AND(ISNUMBER(CF20),ISNUMBER(CA20)),IFERROR(CF20/CA20-1,""),"") -> 0.082519739 | CG21: =CHOOSE(MATCH($CK$2,{"Bull","Base","Bear"},0),$CT$42,$CU$42,$CV$42) -> 0.09 | CH21: =CHOOSE(MATCH($CK$2,{"Bull","Base","Bear"},0),$CT$43,$CU$43,$CV$43) -> 0.09 | CI21: =CHOOSE(MATCH($CK$2,{"Bull","Base","Bear"},0),$CT$44,$CU$44,$CV$44) -> 0.08 | CJ21: =CHOOSE(MATCH($CK$2,{"Bull","Base","Bear"},0),$CT$45,$CU$45,$CV$45) -> 0.08 | CS21: FY27 revenue / operating-income growth "double-digit" — UNVERIFIED | CU21: 0.1 | CW21: UNVERIFIED: 29-Jul-2026 call commentary as reported by third parties (MarketBeat, Nasdaq, Motley Fool transcript); not in an SEC filing. Information row only — not used as a solve target.
B22: Growth before calibration (Q4/26 y/y, latest actual quarter) | CB22: =IFERROR(BZ20/BU20-1,0) -> 0.094519131 | CC22: =IFERROR(BZ20/BU20-1,0) -> 0.094519131 | CD22: =IFERROR(BZ20/BU20-1,0) -> 0.094519131 | CE22: =IFERROR(BZ20/BU20-1,0) -> 0.094519131
B23: Frontier and support services revenue | BR23: 1928 | BS23: 1892 | BT23: 1946 | BU23: 1994 | BV23: 7760 | BW23: 2022 | BX23: 2038 | BY23: 2087 | BZ23: 2113 | CA23: 8260 | CB23: =BW23*(1+CB24) -> 2118.4082 | CC23: =BX23*(1+CC24) -> 2135.1711 | CD23: =BY23*(1+CD24) -> 2186.5074 | CE23: =BZ23*(1+CE24) -> 2213.7471 | CF23: =SUM(CB23:CE23) -> 8653.8339 | CG23: =CF23*(1+CG24) -> 8999.9872 | CH23: =CG23*(1+CH24) -> 9359.9867 | CI23: =CH23*(1+CI24) -> 9640.7863 | CJ23: =CI23*(1+CJ24) -> 9930.0099 | CM23: =IFERROR((CJ23/CA23)^(1/5)-1,"n/m") -> 0.037513907 | CN23: =IFERROR((CA23/BB23)^(1/5)-1,"n/m") -> n/m | CO23: =IFERROR((CA23/AC23)^(1/10)-1,"n/m") -> n/m | CP23: =IFERROR((CA23/C23)^(1/20)-1,"n/m") -> n/m | CS23: Target cash & short-term investments before buybacks ($m) — buyback plug FY2027E+ | CT23: 60000 | CU23: 70000 | CV23: 80000 | CW23: Cash & short-term investments $76.8bn at 30-Jun-2026 ($94.6bn a year earlier) against $40.3bn of debt and $66.6bn of finance leases. Surplus above the target is returned through buybacks ($40.6bn left on the $60bn program); Bull = lower target (more buybacks). Assumption.
B24: y/y % | D24: =IF(AND(ISNUMBER(D23),ISNUMBER(C23)),IFERROR(D23/C23-1,""),"") | E24: =IF(AND(ISNUMBER(E23),ISNUMBER(D23)),IFERROR(E23/D23-1,""),"") | F24: =IF(AND(ISNUMBER(F23),ISNUMBER(E23)),IFERROR(F23/E23-1,""),"") | G24: =IF(AND(ISNUMBER(G23),ISNUMBER(F23)),IFERROR(G23/F23-1,""),"") | H24: =IF(AND(ISNUMBER(H23),ISNUMBER(G23)),IFERROR(H23/G23-1,""),"") | I24: =IF(AND(ISNUMBER(I23),ISNUMBER(H23)),IFERROR(I23/H23-1,""),"") | N24: =IF(AND(ISNUMBER(N23),ISNUMBER(I23)),IFERROR(N23/I23-1,""),"") | O24: =IF(AND(ISNUMBER(O23),ISNUMBER(J23)),IFERROR(O23/J23-1,""),"") | P24: =IF(AND(ISNUMBER(P23),ISNUMBER(K23)),IFERROR(P23/K23-1,""),"") | Q24: =IF(AND(ISNUMBER(Q23),ISNUMBER(L23)),IFERROR(Q23/L23-1,""),"") | R24: =IF(AND(ISNUMBER(R23),ISNUMBER(M23)),IFERROR(R23/M23-1,""),"") | S24: =IF(AND(ISNUMBER(S23),ISNUMBER(N23)),IFERROR(S23/N23-1,""),"") | T24: =IF(AND(ISNUMBER(T23),ISNUMBER(O23)),IFERROR(T23/O23-1,""),"") | U24: =IF(AND(ISNUMBER(U23),ISNUMBER(P23)),IFERROR(U23/P23-1,""),"") | ... CA24: =IF(AND(ISNUMBER(CA23),ISNUMBER(BV23)),IFERROR(CA23/BV23-1,""),"") -> 0.06443299 | CB24: =CB25+$CB$139 -> 0.047679645 | CC24: =CC25+$CB$139 -> 0.047679645 | CD24: =CD25+$CB$139 -> 0.047679645 | CE24: =CE25+$CB$139 -> 0.047679645 | CF24: =IF(AND(ISNUMBER(CF23),ISNUMBER(CA23)),IFERROR(CF23/CA23-1,""),"") -> 0.047679645 | CG24: =CHOOSE(MATCH($CK$2,{"Bull","Base","Bear"},0),$CT$47,$CU$47,$CV$47) -> 0.04 | CH24: =CHOOSE(MATCH($CK$2,{"Bull","Base","Bear"},0),$CT$48,$CU$48,$CV$48) -> 0.04 | CI24: =CHOOSE(MATCH($CK$2,{"Bull","Base","Bear"},0),$CT$49,$CU$49,$CV$49) -> 0.03 | CJ24: =CHOOSE(MATCH($CK$2,{"Bull","Base","Bear"},0),$CT$50,$CU$50,$CV$50) -> 0.03 | CS24: Minimum share repurchases per year ($m) | CT24: 25000 | CU24: 20000 | CV24: 15000 | CW24: FY2026 repurchases $22.3bn (program $16.7bn + $5.6bn tax withholding); FY2025 $18.4bn. Minimum per year by scenario (assumption).
B25: Growth before calibration (Q4/26 y/y, latest actual quarter) | CB25: =IFERROR(BZ23/BU23-1,0) -> 0.059679037 | CC25: =IFERROR(BZ23/BU23-1,0) -> 0.059679037 | CD25: =IFERROR(BZ23/BU23-1,0) -> 0.059679037 | CE25: =IFERROR(BZ23/BU23-1,0) -> 0.059679037
B26: Agents and Infra — segment revenue | C26: =IF(ISNUMBER(C11),C11+C14+C17+C20+C23,"") | D26: =IF(ISNUMBER(D11),D11+D14+D17+D20+D23,"") | E26: =IF(ISNUMBER(E11),E11+E14+E17+E20+E23,"") | F26: =IF(ISNUMBER(F11),F11+F14+F17+F20+F23,"") | G26: =IF(ISNUMBER(G11),G11+G14+G17+G20+G23,"") | H26: =IF(ISNUMBER(H11),H11+H14+H17+H20+H23,"") | I26: =IF(ISNUMBER(I11),I11+I14+I17+I20+I23,"") | J26: =IF(ISNUMBER(J11),J11+J14+J17+J20+J23,"") | ... CJ26: =IF(ISNUMBER(CJ11),CJ11+CJ14+CJ17+CJ20+CJ23,"") -> 599366.22 | CK26: Σ product & service lines. | CM26: =IFERROR((CJ26/CA26)^(1/5)-1,"n/m") -> 0.17454685 | CN26: =IFERROR((CA26/BB26)^(1/5)-1,"n/m") -> n/m | CO26: =IFERROR((CA26/AC26)^(1/10)-1,"n/m") -> n/m | CP26: =IFERROR((CA26/C26)^(1/20)-1,"n/m") -> n/m | CS26: AI_AZ (Azure y/y) | CT26: 0.06 | CU26: Δ → | CV26: -0.1 | CW26: FY26 +40% restated (Q4 +42%); Q1 FY27 guided +44–45% cc; capacity-constrained AI demand, commercial RPO +84% to $678bn. Decelerating with scale (assumption).
B27: Segment revenue y/y % | D27: =IF(AND(ISNUMBER(D26),ISNUMBER(C26)),IFERROR(D26/C26-1,""),"") | E27: =IF(AND(ISNUMBER(E26),ISNUMBER(D26)),IFERROR(E26/D26-1,""),"") | F27: =IF(AND(ISNUMBER(F26),ISNUMBER(E26)),IFERROR(F26/E26-1,""),"") | G27: =IF(AND(ISNUMBER(G26),ISNUMBER(F26)),IFERROR(G26/F26-1,""),"") | H27: =IF(AND(ISNUMBER(H26),ISNUMBER(G26)),IFERROR(H26/G26-1,""),"") | I27: =IF(AND(ISNUMBER(I26),ISNUMBER(H26)),IFERROR(I26/H26-1,""),"") | N27: =IF(AND(ISNUMBER(N26),ISNUMBER(I26)),IFERROR(N26/I26-1,""),"") | O27: =IF(AND(ISNUMBER(O26),ISNUMBER(J26)),IFERROR(O26/J26-1,""),"") | P27: =IF(AND(ISNUMBER(P26),ISNUMBER(K26)),IFERROR(P26/K26-1,""),"") | Q27: =IF(AND(ISNUMBER(Q26),ISNUMBER(L26)),IFERROR(Q26/L26-1,""),"") | R27: =IF(AND(ISNUMBER(R26),ISNUMBER(M26)),IFERROR(R26/M26-1,""),"") | S27: =IF(AND(ISNUMBER(S26),ISNUMBER(N26)),IFERROR(S26/N26-1,""),"") | T27: =IF(AND(ISNUMBER(T26),ISNUMBER(O26)),IFERROR(T26/O26-1,""),"") | U27: =IF(AND(ISNUMBER(U26),ISNUMBER(P26)),IFERROR(U26/P26-1,""),"") | ... CF27: =IF(AND(ISNUMBER(CF26),ISNUMBER(CA26)),IFERROR(CF26/CA26-1,""),"") -> 0.22841559 | CG27: =IF(AND(ISNUMBER(CG26),ISNUMBER(CF26)),IFERROR(CG26/CF26-1,""),"") -> 0.19330324 | CH27: =IF(AND(ISNUMBER(CH26),ISNUMBER(CG26)),IFERROR(CH26/CG26-1,""),"") -> 0.17340601 | CI27: =IF(AND(ISNUMBER(CI26),ISNUMBER(CH26)),IFERROR(CI26/CH26-1,""),"") -> 0.15016489 | CJ27: =IF(AND(ISNUMBER(CJ26),ISNUMBER(CI26)),IFERROR(CJ26/CI26-1,""),"") -> 0.12991861 | CS27: 2028E | CT27: =CU27+$CT$26 -> 0.38 | CU27: 0.32 | CV27: =CU27+$CV$26 -> 0.22
B28: % of total revenue | C28: =IF(AND(ISNUMBER(C26),ISNUMBER(C130)),IFERROR(C26/C130,""),"") | D28: =IF(AND(ISNUMBER(D26),ISNUMBER(D130)),IFERROR(D26/D130,""),"") | E28: =IF(AND(ISNUMBER(E26),ISNUMBER(E130)),IFERROR(E26/E130,""),"") | F28: =IF(AND(ISNUMBER(F26),ISNUMBER(F130)),IFERROR(F26/F130,""),"") | G28: =IF(AND(ISNUMBER(G26),ISNUMBER(G130)),IFERROR(G26/G130,""),"") | H28: =IF(AND(ISNUMBER(H26),ISNUMBER(H130)),IFERROR(H26/H130,""),"") | I28: =IF(AND(ISNUMBER(I26),ISNUMBER(I130)),IFERROR(I26/I130,""),"") | J28: =IF(AND(ISNUMBER(J26),ISNUMBER(J130)),IFERROR(J26/J130,""),"") | ... CJ28: =IF(AND(ISNUMBER(CJ26),ISNUMBER(CJ130)),IFERROR(CJ26/CJ130,""),"") -> 0.89231376 | CS28: 2029E | CT28: =CU28+$CT$26 -> 0.32 | CU28: 0.26 | CV28: =CU28+$CV$26 -> 0.16
B29: Memo: Agents and Infra segment revenue as restated (8-K 2-Sep-2026) | BR29: 50476 | BS29: 52766 | BT29: 54763 | BU29: 60778 | BV29: 218783 | BW29: 61672 | BX29: 64441 | BY29: 67438 | BZ29: 74576 | CA29: 268127 | CS29: 2030E | CT29: =CU29+$CT$26 -> 0.27 | CU29: 0.21 | CV29: =CU29+$CV$26 -> 0.11
B30: Check: product & service lines vs segment revenue (should be 0) | C30: =IF(AND(ISNUMBER(C26),ISNUMBER(C29)),IF(ABS(C26-C29)<=1,0,ROUND(C26-C29,0)),"") | D30: =IF(AND(ISNUMBER(D26),ISNUMBER(D29)),IF(ABS(D26-D29)<=1,0,ROUND(D26-D29,0)),"") | E30: =IF(AND(ISNUMBER(E26),ISNUMBER(E29)),IF(ABS(E26-E29)<=1,0,ROUND(E26-E29,0)),"") | F30: =IF(AND(ISNUMBER(F26),ISNUMBER(F29)),IF(ABS(F26-F29)<=1,0,ROUND(F26-F29,0)),"") | G30: =IF(AND(ISNUMBER(G26),ISNUMBER(G29)),IF(ABS(G26-G29)<=1,0,ROUND(G26-G29,0)),"") | H30: =IF(AND(ISNUMBER(H26),ISNUMBER(H29)),IF(ABS(H26-H29)<=1,0,ROUND(H26-H29,0)),"") | I30: =IF(AND(ISNUMBER(I26),ISNUMBER(I29)),IF(ABS(I26-I29)<=1,0,ROUND(I26-I29,0)),"") | J30: =IF(AND(ISNUMBER(J26),ISNUMBER(J29)),IF(ABS(J26-J29)<=1,0,ROUND(J26-J29,0)),"") | ... CA30: =IF(AND(ISNUMBER(CA26),ISNUMBER(CA29)),IF(ABS(CA26-CA29)<=1,0,ROUND(CA26-CA29,0)),"") -> 0 | CS30: 2031E | CT30: =CU30+$CT$26 -> 0.23 | CU30: 0.17 | CV30: =CU30+$CV$26 -> 0.07
B31: Agents and Infra — segment operating income | BR31: 26171 | BS31: 26718 | BT31: 27704 | BU31: 30221 | BV31: 110814 | BW31: 32718 | BX31: 33167 | BY31: 33748 | BZ31: 36732 | CA31: 136365 | CB31: =CB26*CB32 -> 38971.019 | CC31: =CC26*CC32 -> 39587.581 | CD31: =CD26*CD32 -> 40368.6 | CE31: =CE26*CE32 -> 43961.271 | CF31: =SUM(CB31:CE31) -> 162888.47 | CG31: =CG26*CG32 -> 184728.77 | CH31: =CH26*CH32 -> 214455.88 | CI31: =CI26*CI32 -> 249311.87 | CJ31: =CJ26*CJ32 -> 284698.96 | CK31: Segment operating income as restated (segment revenue − cost of revenue − operating expenses; all costs are allocated, no corporate line). Forecast = revenue × margin. | CM31: =IFERROR((CJ31/CA31)^(1/5)-1,"n/m") -> 0.15860818 | CN31: =IFERROR((CA31/BB31)^(1/5)-1,"n/m") -> n/m | CO31: =IFERROR((CA31/AC31)^(1/10)-1,"n/m") -> n/m | CP31: =IFERROR((CA31/C31)^(1/20)-1,"n/m") -> n/m | CS31: AI_M365 (Microsoft 365 cloud y/y) | CT31: 0.03 | CU31: Δ → | CV31: -0.05 | CW31: FY26 +18.5% (incl. GitHub, Security Copilot); Q1 FY27 M365 commercial cloud ~17% cc; seats +7%, ARPU from E5 / Copilot.
B32: Segment operating margin % | C32: =IF(AND(ISNUMBER(C31),ISNUMBER(C26)),IFERROR(C31/C26,""),"") | D32: =IF(AND(ISNUMBER(D31),ISNUMBER(D26)),IFERROR(D31/D26,""),"") | E32: =IF(AND(ISNUMBER(E31),ISNUMBER(E26)),IFERROR(E31/E26,""),"") | F32: =IF(AND(ISNUMBER(F31),ISNUMBER(F26)),IFERROR(F31/F26,""),"") | G32: =IF(AND(ISNUMBER(G31),ISNUMBER(G26)),IFERROR(G31/G26,""),"") | H32: =IF(AND(ISNUMBER(H31),ISNUMBER(H26)),IFERROR(H31/H26,""),"") | I32: =IF(AND(ISNUMBER(I31),ISNUMBER(I26)),IFERROR(I31/I26,""),"") | J32: =IF(AND(ISNUMBER(J31),ISNUMBER(J26)),IFERROR(J31/J26,""),"") | ... CA32: =IF(AND(ISNUMBER(CA31),ISNUMBER(CA26)),IFERROR(CA31/CA26,""),"") -> 0.50858362 | CB32: =CB33+$CB$148 -> 0.5165145 | CC32: =CC33+$CB$148 -> 0.50068607 | CD32: =CD33+$CB$148 -> 0.48642824 | CE32: =CE33+$CB$148 -> 0.47854274 | CF32: =IF(AND(ISNUMBER(CF31),ISNUMBER(CF26)),IFERROR(CF31/CF26,""),"") -> 0.49454348 | CG32: =CHOOSE(MATCH($CK$2,{"Bull","Base","Bear"},0),$CT$67,$CU$67,$CV$67) -> 0.47 | CH32: =CHOOSE(MATCH($CK$2,{"Bull","Base","Bear"},0),$CT$68,$CU$68,$CV$68) -> 0.465 | CI32: =CHOOSE(MATCH($CK$2,{"Bull","Base","Bear"},0),$CT$69,$CU$69,$CV$69) -> 0.47 | CJ32: =CHOOSE(MATCH($CK$2,{"Bull","Base","Bear"},0),$CT$70,$CU$70,$CV$70) -> 0.475 | CK32: Q1–Q4/27E: margin before calibration + uniform margin Δ solved in Q1/27E to the guided operating income (revenue − COGS − opex guidance), carried to Q2–Q4. 2028E+: scenario lever. | CM32: =IFERROR(AVERAGE(CF32,CG32,CH32,CI32,CJ32),"n/m") -> 0.4749087 | CN32: =IFERROR(AVERAGE(BG32,BL32,BQ32,BV32,CA32),"n/m") -> 0.50754275 | CO32: =IFERROR(AVERAGE(AH32,AM32,AR32,AW32,BB32,BG32,BL32,BQ32,BV32,CA32),"n/m") -> 0.50754275 | CP32: =IFERROR(AVERAGE(C32,D32,E32,F32,G32,H32,I32,N32,S32,X32,AC32,AH32,AM32,AR32,AW32,BB32,BG32,BL32,BQ32,BV32,CA32),"n/m") -> 0.50754275 | CS32: 2028E | CT32: =CU32+$CT$31 -> 0.17 | CU32: 0.14 | CV32: =CU32+$CV$31 -> 0.09
B33: Margin before calibration (prior-year quarter + FY26 vs FY25 margin drift) | CB33: =BW32+IFERROR(CA31/CA26-BV31/BV26,0) -> 0.53259802 | CC33: =BX32+IFERROR(CA31/CA26-BV31/BV26,0) -> 0.5167696 | CD33: =BY32+IFERROR(CA31/CA26-BV31/BV26,0) -> 0.50251177 | CE33: =BZ32+IFERROR(CA31/CA26-BV31/BV26,0) -> 0.49462626 | CS33: 2029E | CT33: =CU33+$CT$31 -> 0.16 | CU33: 0.13 | CV33: =CU33+$CV$31 -> 0.08
B34: Memo: segment gross margin % (revenue − cost of revenue, restated) | C34: =IF(AND(ISNUMBER(C29),ISNUMBER(C35)),IFERROR(1-C35/C29,""),"") | D34: =IF(AND(ISNUMBER(D29),ISNUMBER(D35)),IFERROR(1-D35/D29,""),"") | E34: =IF(AND(ISNUMBER(E29),ISNUMBER(E35)),IFERROR(1-E35/E29,""),"") | F34: =IF(AND(ISNUMBER(F29),ISNUMBER(F35)),IFERROR(1-F35/F29,""),"") | G34: =IF(AND(ISNUMBER(G29),ISNUMBER(G35)),IFERROR(1-G35/G29,""),"") | H34: =IF(AND(ISNUMBER(H29),ISNUMBER(H35)),IFERROR(1-H35/H29,""),"") | I34: =IF(AND(ISNUMBER(I29),ISNUMBER(I35)),IFERROR(1-I35/I29,""),"") | J34: =IF(AND(ISNUMBER(J29),ISNUMBER(J35)),IFERROR(1-J35/J29,""),"") | ... CA34: =IF(AND(ISNUMBER(CA29),ISNUMBER(CA35)),IFERROR(1-CA35/CA29,""),"") -> 0.69634912 | CS34: 2030E | CT34: =CU34+$CT$31 -> 0.15 | CU34: 0.12 | CV34: =CU34+$CV$31 -> 0.07
B35: Memo: segment cost of revenue (restated) | BR35: 13619 | BS35: 14630 | BT35: 15510 | BU35: 17533 | BV35: 61292 | BW35: 17701 | BX35: 19307 | BY35: 20949 | BZ35: 23460 | CA35: 81417 | CS35: 2031E | CT35: =CU35+$CT$31 -> 0.14 | CU35: 0.11 | CV35: =CU35+$CV$31 -> 0.06
B36: Memo: segment operating expenses (restated) | BR36: 10686 | BS36: 11418 | BT36: 11549 | BU36: 13024 | BV36: 46677 | BW36: 11253 | BX36: 11967 | BY36: 12741 | BZ36: 14384 | CA36: 50345 | CS36: AI_PSL (Productivity & server licensing y/y) | CT36: 0.03 | CU36: Δ → | CV36: -0.04 | CW36: FY26 +5.4% (lumpy on-premises server / Office transactional); Q1 FY27 guided to decline low-single digits; long-run cloud migration.
B37: Incremental segment margin (Δ operating income / Δ revenue) | D37: =IFERROR((D31-C31)/(D26-C26),"") | E37: =IFERROR((E31-D31)/(E26-D26),"") | F37: =IFERROR((F31-E31)/(F26-E26),"") | G37: =IFERROR((G31-F31)/(G26-F26),"") | H37: =IFERROR((H31-G31)/(H26-G26),"") | I37: =IFERROR((I31-H31)/(I26-H26),"") | N37: =IFERROR((N31-I31)/(N26-I26),"") | O37: =IFERROR((O31-J31)/(O26-J26),"") | P37: =IFERROR((P31-K31)/(P26-K26),"") | Q37: =IFERROR((Q31-L31)/(Q26-L26),"") | R37: =IFERROR((R31-M31)/(R26-M26),"") | S37: =IFERROR((S31-N31)/(S26-N26),"") | T37: =IFERROR((T31-O31)/(T26-O26),"") | U37: =IFERROR((U31-P31)/(U26-P26),"") | ... CF37: =IFERROR((CF31-CA31)/(CF26-CA26),"") -> 0.43307594 | CG37: =IFERROR((CG31-CF31)/(CG26-CF26),"") -> 0.34303123 | CH37: =IFERROR((CH31-CG31)/(CH26-CG26),"") -> 0.43616594 | CI37: =IFERROR((CI31-CH31)/(CI26-CH26),"") -> 0.50329673 | CJ37: =IFERROR((CJ31-CI31)/(CJ26-CI26),"") -> 0.51348563 | CS37: 2028E | CT37: =CU37+$CT$36 -> 0.01 | CU37: -0.02 | CV37: =CU37+$CV$36 -> -0.06
CS38: 2029E | CT38: =CU38+$CT$36 -> 0.01 | CU38: -0.02 | CV38: =CU38+$CV$36 -> -0.06
B39: Devices and Consumer (search & advertising incl. LinkedIn Marketing / Premium, XBOX content, services & hardware, Windows OEM & devices) | CK39: DEVICES AND CONSUMER — modelling logic (history: restated FY27 basis, 8-K 2-Sep-2026, Q1/25–Q4/26 only) | CS39: 2030E | CT39: =CU39+$CT$36 -> 0 | CU39: -0.03 | CV39: =CU39+$CV$36 -> -0.07
B40: Search and advertising revenue | BR40: 5159 | BS40: 5773 | BT40: 5437 | BU40: 5802 | BV40: 22171 | BW40: 5942 | BX40: 6393 | BY40: 6065 | BZ40: 6435 | CA40: 24835 | CB40: =BW40*(1+CB41) -> 6285.5982 | CC40: =BX40*(1+CC41) -> 6762.6774 | CD40: =BY40*(1+CD41) -> 6415.7107 | CE40: =BZ40*(1+CE41) -> 6807.1061 | CF40: =SUM(CB40:CE40) -> 26271.092 | CG40: =CF40*(1+CG41) -> 28372.78 | CH40: =CG40*(1+CH41) -> 30642.602 | CI40: =CH40*(1+CI41) -> 32787.584 | CJ40: =CI40*(1+CJ41) -> 35082.715 | CK40: Restated product & service revenue (FY27 definitions; 8-K 2-Sep-2026, Ex. 99.1). Q1–Q4/27E: prior-year quarter × (1 + growth). 2028E+: prior year × (1 + scenario lever). | CM40: =IFERROR((CJ40/CA40)^(1/5)-1,"n/m") -> 0.071533633 | CN40: =IFERROR((CA40/BB40)^(1/5)-1,"n/m") -> n/m | CO40: =IFERROR((CA40/AC40)^(1/10)-1,"n/m") -> n/m | CP40: =IFERROR((CA40/C40)^(1/20)-1,"n/m") -> n/m | CS40: 2031E | CT40: =CU40+$CT$36 -> 0 | CU40: -0.03 | CV40: =CU40+$CV$36 -> -0.07
B41: y/y % | D41: =IF(AND(ISNUMBER(D40),ISNUMBER(C40)),IFERROR(D40/C40-1,""),"") | E41: =IF(AND(ISNUMBER(E40),ISNUMBER(D40)),IFERROR(E40/D40-1,""),"") | F41: =IF(AND(ISNUMBER(F40),ISNUMBER(E40)),IFERROR(F40/E40-1,""),"") | G41: =IF(AND(ISNUMBER(G40),ISNUMBER(F40)),IFERROR(G40/F40-1,""),"") | H41: =IF(AND(ISNUMBER(H40),ISNUMBER(G40)),IFERROR(H40/G40-1,""),"") | I41: =IF(AND(ISNUMBER(I40),ISNUMBER(H40)),IFERROR(I40/H40-1,""),"") | N41: =IF(AND(ISNUMBER(N40),ISNUMBER(I40)),IFERROR(N40/I40-1,""),"") | O41: =IF(AND(ISNUMBER(O40),ISNUMBER(J40)),IFERROR(O40/J40-1,""),"") | P41: =IF(AND(ISNUMBER(P40),ISNUMBER(K40)),IFERROR(P40/K40-1,""),"") | Q41: =IF(AND(ISNUMBER(Q40),ISNUMBER(L40)),IFERROR(Q40/L40-1,""),"") | R41: =IF(AND(ISNUMBER(R40),ISNUMBER(M40)),IFERROR(R40/M40-1,""),"") | S41: =IF(AND(ISNUMBER(S40),ISNUMBER(N40)),IFERROR(S40/N40-1,""),"") | T41: =IF(AND(ISNUMBER(T40),ISNUMBER(O40)),IFERROR(T40/O40-1,""),"") | U41: =IF(AND(ISNUMBER(U40),ISNUMBER(P40)),IFERROR(U40/P40-1,""),"") | ... CA41: =IF(AND(ISNUMBER(CA40),ISNUMBER(BV40)),IFERROR(CA40/BV40-1,""),"") -> 0.12015696 | CB41: =CB42+$CB$144 -> 0.057825347 | CC41: =CC42+$CB$144 -> 0.057825347 | CD41: =CD42+$CB$144 -> 0.057825347 | CE41: =CE42+$CB$144 -> 0.057825347 | CF41: =IF(AND(ISNUMBER(CF40),ISNUMBER(CA40)),IFERROR(CF40/CA40-1,""),"") -> 0.057825347 | CG41: =CHOOSE(MATCH($CK$2,{"Bull","Base","Bear"},0),$CT$52,$CU$52,$CV$52) -> 0.08 | CH41: =CHOOSE(MATCH($CK$2,{"Bull","Base","Bear"},0),$CT$53,$CU$53,$CV$53) -> 0.08 | CI41: =CHOOSE(MATCH($CK$2,{"Bull","Base","Bear"},0),$CT$54,$CU$54,$CV$54) -> 0.07 | CJ41: =CHOOSE(MATCH($CK$2,{"Bull","Base","Bear"},0),$CT$55,$CU$55,$CV$55) -> 0.07 | CK41: Q1–Q4/27E: Q4/26 y/y growth of the line + the segment calibration Δ solved in Q1/27E to the segment revenue guidance (carried to Q2–Q4). 2028E–2031E: scenario lever (Bull/Base/Bear table →). | CS41: AI_IND (Industry solutions y/y) | CT41: 0.03 | CU41: Δ → | CV41: -0.04 | CW41: FY26 +10.5%; Q1 FY27 cloud high-single digits (Dynamics 365, LinkedIn Talent / Sales, healthcare).
B42: Growth before calibration (Q4/26 y/y, latest actual quarter) | CB42: =IFERROR(BZ40/BU40-1,0) -> 0.10910031 | CC42: =IFERROR(BZ40/BU40-1,0) -> 0.10910031 | CD42: =IFERROR(BZ40/BU40-1,0) -> 0.10910031 | CE42: =IFERROR(BZ40/BU40-1,0) -> 0.10910031 | CS42: 2028E | CT42: =CU42+$CT$41 -> 0.12 | CU42: 0.09 | CV42: =CU42+$CV$41 -> 0.05
B43: XBOX revenue | BR43: 5621 | BS43: 6581 | BT43: 5721 | BU43: 5532 | BV43: 23455 | BW43: 5508 | BX43: 5958 | BY43: 5341 | BZ43: 4983 | CA43: 21790 | CB43: =BW43*(1+CB44) -> 4678.9593 | CC43: =BX43*(1+CC44) -> 5061.2272 | CD43: =BY43*(1+CD44) -> 4537.0954 | CE43: =BZ43*(1+CE44) -> 4232.98 | CF43: =SUM(CB43:CE43) -> 18510.262 | CG43: =CF43*(1+CG44) -> 18880.467 | CH43: =CG43*(1+CH44) -> 19446.881 | CI43: =CH43*(1+CI44) -> 20030.288 | CJ43: =CI43*(1+CJ44) -> 20631.196 | CM43: =IFERROR((CJ43/CA43)^(1/5)-1,"n/m") -> -0.010869859 | CN43: =IFERROR((CA43/BB43)^(1/5)-1,"n/m") -> n/m | CO43: =IFERROR((CA43/AC43)^(1/10)-1,"n/m") -> n/m | CP43: =IFERROR((CA43/C43)^(1/20)-1,"n/m") -> n/m | CS43: 2029E | CT43: =CU43+$CT$41 -> 0.12 | CU43: 0.09 | CV43: =CU43+$CV$41 -> 0.05
B44: y/y % | D44: =IF(AND(ISNUMBER(D43),ISNUMBER(C43)),IFERROR(D43/C43-1,""),"") | E44: =IF(AND(ISNUMBER(E43),ISNUMBER(D43)),IFERROR(E43/D43-1,""),"") | F44: =IF(AND(ISNUMBER(F43),ISNUMBER(E43)),IFERROR(F43/E43-1,""),"") | G44: =IF(AND(ISNUMBER(G43),ISNUMBER(F43)),IFERROR(G43/F43-1,""),"") | H44: =IF(AND(ISNUMBER(H43),ISNUMBER(G43)),IFERROR(H43/G43-1,""),"") | I44: =IF(AND(ISNUMBER(I43),ISNUMBER(H43)),IFERROR(I43/H43-1,""),"") | N44: =IF(AND(ISNUMBER(N43),ISNUMBER(I43)),IFERROR(N43/I43-1,""),"") | O44: =IF(AND(ISNUMBER(O43),ISNUMBER(J43)),IFERROR(O43/J43-1,""),"") | P44: =IF(AND(ISNUMBER(P43),ISNUMBER(K43)),IFERROR(P43/K43-1,""),"") | Q44: =IF(AND(ISNUMBER(Q43),ISNUMBER(L43)),IFERROR(Q43/L43-1,""),"") | R44: =IF(AND(ISNUMBER(R43),ISNUMBER(M43)),IFERROR(R43/M43-1,""),"") | S44: =IF(AND(ISNUMBER(S43),ISNUMBER(N43)),IFERROR(S43/N43-1,""),"") | T44: =IF(AND(ISNUMBER(T43),ISNUMBER(O43)),IFERROR(T43/O43-1,""),"") | U44: =IF(AND(ISNUMBER(U43),ISNUMBER(P43)),IFERROR(U43/P43-1,""),"") | ... CA44: =IF(AND(ISNUMBER(CA43),ISNUMBER(BV43)),IFERROR(CA43/BV43-1,""),"") -> -0.070986996 | CB44: =CB45+$CB$144 -> -0.15051574 | CC44: =CC45+$CB$144 -> -0.15051574 | CD44: =CD45+$CB$144 -> -0.15051574 | CE44: =CE45+$CB$144 -> -0.15051574 | CF44: =IF(AND(ISNUMBER(CF43),ISNUMBER(CA43)),IFERROR(CF43/CA43-1,""),"") -> -0.15051574 | CG44: =CHOOSE(MATCH($CK$2,{"Bull","Base","Bear"},0),$CT$57,$CU$57,$CV$57) -> 0.02 | CH44: =CHOOSE(MATCH($CK$2,{"Bull","Base","Bear"},0),$CT$58,$CU$58,$CV$58) -> 0.03 | CI44: =CHOOSE(MATCH($CK$2,{"Bull","Base","Bear"},0),$CT$59,$CU$59,$CV$59) -> 0.03 | CJ44: =CHOOSE(MATCH($CK$2,{"Bull","Base","Bear"},0),$CT$60,$CU$60,$CV$60) -> 0.03 | CS44: 2030E | CT44: =CU44+$CT$41 -> 0.11 | CU44: 0.08 | CV44: =CU44+$CV$41 -> 0.04
B45: Growth before calibration (Q4/26 y/y, latest actual quarter) | CB45: =IFERROR(BZ43/BU43-1,0) -> -0.099240781 | CC45: =IFERROR(BZ43/BU43-1,0) -> -0.099240781 | CD45: =IFERROR(BZ43/BU43-1,0) -> -0.099240781 | CE45: =IFERROR(BZ43/BU43-1,0) -> -0.099240781 | CS45: 2031E | CT45: =CU45+$CT$41 -> 0.11 | CU45: 0.08 | CV45: =CU45+$CV$41 -> 0.04
B46: Windows OEM and devices revenue | BR46: 4329 | BS46: 4512 | BT46: 4145 | BU46: 4329 | BV46: 17315 | BW46: 4551 | BX46: 4481 | BY46: 4042 | BZ46: 4013 | CA46: 17087 | CB46: =BW46*(1+CB47) -> 3985.4425 | CC46: =BX46*(1+CC47) -> 3924.1415 | CD46: =BY46*(1+CD47) -> 3539.6965 | CE46: =BZ46*(1+CE47) -> 3514.3003 | CF46: =SUM(CB46:CE46) -> 14963.581 | CG46: =CF46*(1+CG47) -> 14963.581 | CH46: =CG46*(1+CH47) -> 15113.217 | CI46: =CH46*(1+CI47) -> 15264.349 | CJ46: =CI46*(1+CJ47) -> 15416.992 | CM46: =IFERROR((CJ46/CA46)^(1/5)-1,"n/m") -> -0.02035942 | CN46: =IFERROR((CA46/BB46)^(1/5)-1,"n/m") -> n/m | CO46: =IFERROR((CA46/AC46)^(1/10)-1,"n/m") -> n/m | CP46: =IFERROR((CA46/C46)^(1/20)-1,"n/m") -> n/m | CS46: AI_FSS (Frontier & support services y/y) | CT46: 0.02 | CU46: Δ → | CV46: -0.03 | CW46: FY26 +6.4% (enterprise support, industry consulting).
B47: y/y % | D47: =IF(AND(ISNUMBER(D46),ISNUMBER(C46)),IFERROR(D46/C46-1,""),"") | E47: =IF(AND(ISNUMBER(E46),ISNUMBER(D46)),IFERROR(E46/D46-1,""),"") | F47: =IF(AND(ISNUMBER(F46),ISNUMBER(E46)),IFERROR(F46/E46-1,""),"") | G47: =IF(AND(ISNUMBER(G46),ISNUMBER(F46)),IFERROR(G46/F46-1,""),"") | H47: =IF(AND(ISNUMBER(H46),ISNUMBER(G46)),IFERROR(H46/G46-1,""),"") | I47: =IF(AND(ISNUMBER(I46),ISNUMBER(H46)),IFERROR(I46/H46-1,""),"") | N47: =IF(AND(ISNUMBER(N46),ISNUMBER(I46)),IFERROR(N46/I46-1,""),"") | O47: =IF(AND(ISNUMBER(O46),ISNUMBER(J46)),IFERROR(O46/J46-1,""),"") | P47: =IF(AND(ISNUMBER(P46),ISNUMBER(K46)),IFERROR(P46/K46-1,""),"") | Q47: =IF(AND(ISNUMBER(Q46),ISNUMBER(L46)),IFERROR(Q46/L46-1,""),"") | R47: =IF(AND(ISNUMBER(R46),ISNUMBER(M46)),IFERROR(R46/M46-1,""),"") | S47: =IF(AND(ISNUMBER(S46),ISNUMBER(N46)),IFERROR(S46/N46-1,""),"") | T47: =IF(AND(ISNUMBER(T46),ISNUMBER(O46)),IFERROR(T46/O46-1,""),"") | U47: =IF(AND(ISNUMBER(U46),ISNUMBER(P46)),IFERROR(U46/P46-1,""),"") | ... CA47: =IF(AND(ISNUMBER(CA46),ISNUMBER(BV46)),IFERROR(CA46/BV46-1,""),"") -> -0.013167774 | CB47: =CB48+$CB$144 -> -0.12427104 | CC47: =CC48+$CB$144 -> -0.12427104 | CD47: =CD48+$CB$144 -> -0.12427104 | CE47: =CE48+$CB$144 -> -0.12427104 | CF47: =IF(AND(ISNUMBER(CF46),ISNUMBER(CA46)),IFERROR(CF46/CA46-1,""),"") -> -0.12427104 | CG47: =CHOOSE(MATCH($CK$2,{"Bull","Base","Bear"},0),$CT$62,$CU$62,$CV$62) -> 0 | CH47: =CHOOSE(MATCH($CK$2,{"Bull","Base","Bear"},0),$CT$63,$CU$63,$CV$63) -> 0.01 | CI47: =CHOOSE(MATCH($CK$2,{"Bull","Base","Bear"},0),$CT$64,$CU$64,$CV$64) -> 0.01 | CJ47: =CHOOSE(MATCH($CK$2,{"Bull","Base","Bear"},0),$CT$65,$CU$65,$CV$65) -> 0.01 | CS47: 2028E | CT47: =CU47+$CT$46 -> 0.06 | CU47: 0.04 | CV47: =CU47+$CV$46 -> 0.01
B48: Growth before calibration (Q4/26 y/y, latest actual quarter) | CB48: =IFERROR(BZ46/BU46-1,0) -> -0.072996073 | CC48: =IFERROR(BZ46/BU46-1,0) -> -0.072996073 | CD48: =IFERROR(BZ46/BU46-1,0) -> -0.072996073 | CE48: =IFERROR(BZ46/BU46-1,0) -> -0.072996073 | CS48: 2029E | CT48: =CU48+$CT$46 -> 0.06 | CU48: 0.04 | CV48: =CU48+$CV$46 -> 0.01
B49: Devices and Consumer — segment revenue | C49: =IF(ISNUMBER(C40),C40+C43+C46,"") | D49: =IF(ISNUMBER(D40),D40+D43+D46,"") | E49: =IF(ISNUMBER(E40),E40+E43+E46,"") | F49: =IF(ISNUMBER(F40),F40+F43+F46,"") | G49: =IF(ISNUMBER(G40),G40+G43+G46,"") | H49: =IF(ISNUMBER(H40),H40+H43+H46,"") | I49: =IF(ISNUMBER(I40),I40+I43+I46,"") | J49: =IF(ISNUMBER(J40),J40+J43+J46,"") | ... CJ49: =IF(ISNUMBER(CJ40),CJ40+CJ43+CJ46,"") -> 71130.904 | CM49: =IFERROR((CJ49/CA49)^(1/5)-1,"n/m") -> 0.022274241 | CN49: =IFERROR((CA49/BB49)^(1/5)-1,"n/m") -> n/m | CO49: =IFERROR((CA49/AC49)^(1/10)-1,"n/m") -> n/m | CP49: =IFERROR((CA49/C49)^(1/20)-1,"n/m") -> n/m | CS49: 2030E | CT49: =CU49+$CT$46 -> 0.05 | CU49: 0.03 | CV49: =CU49+$CV$46 -> 0
B50: Segment revenue y/y % | D50: =IF(AND(ISNUMBER(D49),ISNUMBER(C49)),IFERROR(D49/C49-1,""),"") | E50: =IF(AND(ISNUMBER(E49),ISNUMBER(D49)),IFERROR(E49/D49-1,""),"") | F50: =IF(AND(ISNUMBER(F49),ISNUMBER(E49)),IFERROR(F49/E49-1,""),"") | G50: =IF(AND(ISNUMBER(G49),ISNUMBER(F49)),IFERROR(G49/F49-1,""),"") | H50: =IF(AND(ISNUMBER(H49),ISNUMBER(G49)),IFERROR(H49/G49-1,""),"") | I50: =IF(AND(ISNUMBER(I49),ISNUMBER(H49)),IFERROR(I49/H49-1,""),"") | N50: =IF(AND(ISNUMBER(N49),ISNUMBER(I49)),IFERROR(N49/I49-1,""),"") | O50: =IF(AND(ISNUMBER(O49),ISNUMBER(J49)),IFERROR(O49/J49-1,""),"") | P50: =IF(AND(ISNUMBER(P49),ISNUMBER(K49)),IFERROR(P49/K49-1,""),"") | Q50: =IF(AND(ISNUMBER(Q49),ISNUMBER(L49)),IFERROR(Q49/L49-1,""),"") | R50: =IF(AND(ISNUMBER(R49),ISNUMBER(M49)),IFERROR(R49/M49-1,""),"") | S50: =IF(AND(ISNUMBER(S49),ISNUMBER(N49)),IFERROR(S49/N49-1,""),"") | T50: =IF(AND(ISNUMBER(T49),ISNUMBER(O49)),IFERROR(T49/O49-1,""),"") | U50: =IF(AND(ISNUMBER(U49),ISNUMBER(P49)),IFERROR(U49/P49-1,""),"") | ... CF50: =IF(AND(ISNUMBER(CF49),ISNUMBER(CA49)),IFERROR(CF49/CA49-1,""),"") -> -0.062265583 | CG50: =IF(AND(ISNUMBER(CG49),ISNUMBER(CF49)),IFERROR(CG49/CF49-1,""),"") -> 0.041374095 | CH50: =IF(AND(ISNUMBER(CH49),ISNUMBER(CG49)),IFERROR(CH49/CG49-1,""),"") -> 0.047991393 | CI50: =IF(AND(ISNUMBER(CI49),ISNUMBER(CH49)),IFERROR(CI49/CH49-1,""),"") -> 0.0441626 | CJ50: =IF(AND(ISNUMBER(CJ49),ISNUMBER(CI49)),IFERROR(CJ49/CI49-1,""),"") -> 0.04477943 | CS50: 2031E | CT50: =CU50+$CT$46 -> 0.05 | CU50: 0.03 | CV50: =CU50+$CV$46 -> 0
B51: % of total revenue | C51: =IF(AND(ISNUMBER(C49),ISNUMBER(C130)),IFERROR(C49/C130,""),"") | D51: =IF(AND(ISNUMBER(D49),ISNUMBER(D130)),IFERROR(D49/D130,""),"") | E51: =IF(AND(ISNUMBER(E49),ISNUMBER(E130)),IFERROR(E49/E130,""),"") | F51: =IF(AND(ISNUMBER(F49),ISNUMBER(F130)),IFERROR(F49/F130,""),"") | G51: =IF(AND(ISNUMBER(G49),ISNUMBER(G130)),IFERROR(G49/G130,""),"") | H51: =IF(AND(ISNUMBER(H49),ISNUMBER(H130)),IFERROR(H49/H130,""),"") | I51: =IF(AND(ISNUMBER(I49),ISNUMBER(I130)),IFERROR(I49/I130,""),"") | J51: =IF(AND(ISNUMBER(J49),ISNUMBER(J130)),IFERROR(J49/J130,""),"") | ... CJ51: =IF(AND(ISNUMBER(CJ49),ISNUMBER(CJ130)),IFERROR(CJ49/CJ130,""),"") -> 0.105897 | CS51: DC_SA (Search & advertising y/y) | CT51: 0.03 | CU51: Δ → | CV51: -0.05 | CW51: FY26 +12% (ex-TAC +14% restated); Q1 FY27 mid- to high-single digits.
B52: Memo: Devices and Consumer segment revenue as restated (8-K 2-Sep-2026) | BR52: 15109 | BS52: 16866 | BT52: 15303 | BU52: 15663 | BV52: 62941 | BW52: 16001 | BX52: 16832 | BY52: 15448 | BZ52: 15431 | CA52: 63712 | CS52: 2028E | CT52: =CU52+$CT$51 -> 0.11 | CU52: 0.08 | CV52: =CU52+$CV$51 -> 0.03
B53: Check: product & service lines vs segment revenue (should be 0) | C53: =IF(AND(ISNUMBER(C49),ISNUMBER(C52)),IF(ABS(C49-C52)<=1,0,ROUND(C49-C52,0)),"") | D53: =IF(AND(ISNUMBER(D49),ISNUMBER(D52)),IF(ABS(D49-D52)<=1,0,ROUND(D49-D52,0)),"") | E53: =IF(AND(ISNUMBER(E49),ISNUMBER(E52)),IF(ABS(E49-E52)<=1,0,ROUND(E49-E52,0)),"") | F53: =IF(AND(ISNUMBER(F49),ISNUMBER(F52)),IF(ABS(F49-F52)<=1,0,ROUND(F49-F52,0)),"") | G53: =IF(AND(ISNUMBER(G49),ISNUMBER(G52)),IF(ABS(G49-G52)<=1,0,ROUND(G49-G52,0)),"") | H53: =IF(AND(ISNUMBER(H49),ISNUMBER(H52)),IF(ABS(H49-H52)<=1,0,ROUND(H49-H52,0)),"") | I53: =IF(AND(ISNUMBER(I49),ISNUMBER(I52)),IF(ABS(I49-I52)<=1,0,ROUND(I49-I52,0)),"") | J53: =IF(AND(ISNUMBER(J49),ISNUMBER(J52)),IF(ABS(J49-J52)<=1,0,ROUND(J49-J52,0)),"") | ... CA53: =IF(AND(ISNUMBER(CA49),ISNUMBER(CA52)),IF(ABS(CA49-CA52)<=1,0,ROUND(CA49-CA52,0)),"") -> 0 | CS53: 2029E | CT53: =CU53+$CT$51 -> 0.11 | CU53: 0.08 | CV53: =CU53+$CV$51 -> 0.03
B54: Devices and Consumer — segment operating income | BR54: 4381 | BS54: 4935 | BT54: 4296 | BU54: 4102 | BV54: 17714 | BW54: 5243 | BX54: 5108 | BY54: 4650 | BZ54: 3871 | CA54: 18872 | CB54: =CB49*CB55 -> 4878.9812 | CC54: =CC49*CC55 -> 4758.3638 | CD54: =CD49*CD55 -> 4343.3462 | CE54: =CE49*CE55 -> 3631.9729 | CF54: =SUM(CB54:CE54) -> 17612.664 | CG54: =CG49*CG55 -> 18042.88 | CH54: =CH49*CH55 -> 18908.783 | CI54: =CI49*CI55 -> 20084.255 | CJ54: =CJ49*CJ55 -> 21339.271 | CM54: =IFERROR((CJ54/CA54)^(1/5)-1,"n/m") -> 0.024878378 | CN54: =IFERROR((CA54/BB54)^(1/5)-1,"n/m") -> n/m | CO54: =IFERROR((CA54/AC54)^(1/10)-1,"n/m") -> n/m | CP54: =IFERROR((CA54/C54)^(1/20)-1,"n/m") -> n/m | CS54: 2030E | CT54: =CU54+$CT$51 -> 0.1 | CU54: 0.07 | CV54: =CU54+$CV$51 -> 0.02
B55: Segment operating margin % | C55: =IF(AND(ISNUMBER(C54),ISNUMBER(C49)),IFERROR(C54/C49,""),"") | D55: =IF(AND(ISNUMBER(D54),ISNUMBER(D49)),IFERROR(D54/D49,""),"") | E55: =IF(AND(ISNUMBER(E54),ISNUMBER(E49)),IFERROR(E54/E49,""),"") | F55: =IF(AND(ISNUMBER(F54),ISNUMBER(F49)),IFERROR(F54/F49,""),"") | G55: =IF(AND(ISNUMBER(G54),ISNUMBER(G49)),IFERROR(G54/G49,""),"") | H55: =IF(AND(ISNUMBER(H54),ISNUMBER(H49)),IFERROR(H54/H49,""),"") | I55: =IF(AND(ISNUMBER(I54),ISNUMBER(I49)),IFERROR(I54/I49,""),"") | J55: =IF(AND(ISNUMBER(J54),ISNUMBER(J49)),IFERROR(J54/J49,""),"") | ... CA55: =IF(AND(ISNUMBER(CA54),ISNUMBER(CA49)),IFERROR(CA54/CA49,""),"") -> 0.29620794 | CB55: =CB56+$CB$148 -> 0.32635326 | CC55: =CC56+$CB$148 -> 0.30215582 | CD55: =CD56+$CB$148 -> 0.29969608 | CE55: =CE56+$CB$148 -> 0.2495449 | CF55: =IF(AND(ISNUMBER(CF54),ISNUMBER(CF49)),IFERROR(CF54/CF49,""),"") -> 0.29479761 | CG55: =CHOOSE(MATCH($CK$2,{"Bull","Base","Bear"},0),$CT$72,$CU$72,$CV$72) -> 0.29 | CH55: =CHOOSE(MATCH($CK$2,{"Bull","Base","Bear"},0),$CT$73,$CU$73,$CV$73) -> 0.29 | CI55: =CHOOSE(MATCH($CK$2,{"Bull","Base","Bear"},0),$CT$74,$CU$74,$CV$74) -> 0.295 | CJ55: =CHOOSE(MATCH($CK$2,{"Bull","Base","Bear"},0),$CT$75,$CU$75,$CV$75) -> 0.3 | CM55: =IFERROR(AVERAGE(CF55,CG55,CH55,CI55,CJ55),"n/m") -> 0.29395952 | CN55: =IFERROR(AVERAGE(BG55,BL55,BQ55,BV55,CA55),"n/m") -> 0.28882305 | CO55: =IFERROR(AVERAGE(AH55,AM55,AR55,AW55,BB55,BG55,BL55,BQ55,BV55,CA55),"n/m") -> 0.28882305 | CP55: =IFERROR(AVERAGE(C55,D55,E55,F55,G55,H55,I55,N55,S55,X55,AC55,AH55,AM55,AR55,AW55,BB55,BG55,BL55,BQ55,BV55,CA55),"n/m") -> 0.28882305 | CS55: 2031E | CT55: =CU55+$CT$51 -> 0.1 | CU55: 0.07 | CV55: =CU55+$CV$51 -> 0.02
B56: Margin before calibration (prior-year quarter + FY26 vs FY25 margin drift) | CB56: =BW55+IFERROR(CA54/CA49-BV54/BV49,0) -> 0.34243678 | CC56: =BX55+IFERROR(CA54/CA49-BV54/BV49,0) -> 0.31823935 | CD56: =BY55+IFERROR(CA54/CA49-BV54/BV49,0) -> 0.3157796 | CE56: =BZ55+IFERROR(CA54/CA49-BV54/BV49,0) -> 0.26562842 | CS56: DC_XBOX (XBOX y/y) | CT56: 0.04 | CU56: Δ → | CV56: -0.06 | CW56: FY26 −7%; Q1 FY27 content & services down mid-single digits, hardware down.
B57: Memo: segment gross margin % (revenue − cost of revenue, restated) | C57: =IF(AND(ISNUMBER(C52),ISNUMBER(C58)),IFERROR(1-C58/C52,""),"") | D57: =IF(AND(ISNUMBER(D52),ISNUMBER(D58)),IFERROR(1-D58/D52,""),"") | E57: =IF(AND(ISNUMBER(E52),ISNUMBER(E58)),IFERROR(1-E58/E52,""),"") | F57: =IF(AND(ISNUMBER(F52),ISNUMBER(F58)),IFERROR(1-F58/F52,""),"") | G57: =IF(AND(ISNUMBER(G52),ISNUMBER(G58)),IFERROR(1-G58/G52,""),"") | H57: =IF(AND(ISNUMBER(H52),ISNUMBER(H58)),IFERROR(1-H58/H52,""),"") | I57: =IF(AND(ISNUMBER(I52),ISNUMBER(I58)),IFERROR(1-I58/I52,""),"") | J57: =IF(AND(ISNUMBER(J52),ISNUMBER(J58)),IFERROR(1-J58/J52,""),"") | ... CA57: =IF(AND(ISNUMBER(CA52),ISNUMBER(CA58)),IFERROR(1-CA58/CA52,""),"") -> 0.60828415 | CS57: 2028E | CT57: =CU57+$CT$56 -> 0.06 | CU57: 0.02 | CV57: =CU57+$CV$56 -> -0.04
B58: Memo: segment cost of revenue (restated) | BR58: 6480 | BS58: 7169 | BT58: 6409 | BU58: 6481 | BV58: 26539 | BW58: 6342 | BX58: 6671 | BY58: 5879 | BZ58: 6065 | CA58: 24957 | CS58: 2029E | CT58: =CU58+$CT$56 -> 0.07 | CU58: 0.03 | CV58: =CU58+$CV$56 -> -0.03
B59: Memo: segment operating expenses (restated) | BR59: 4248 | BS59: 4762 | BT59: 4598 | BU59: 5080 | BV59: 18688 | BW59: 4416 | BX59: 5053 | BY59: 4919 | BZ59: 5495 | CA59: 19883 | CS59: 2030E | CT59: =CU59+$CT$56 -> 0.07 | CU59: 0.03 | CV59: =CU59+$CV$56 -> -0.03
B60: Incremental segment margin (Δ operating income / Δ revenue) | D60: =IFERROR((D54-C54)/(D49-C49),"") | E60: =IFERROR((E54-D54)/(E49-D49),"") | F60: =IFERROR((F54-E54)/(F49-E49),"") | G60: =IFERROR((G54-F54)/(G49-F49),"") | H60: =IFERROR((H54-G54)/(H49-G49),"") | I60: =IFERROR((I54-H54)/(I49-H49),"") | N60: =IFERROR((N54-I54)/(N49-I49),"") | O60: =IFERROR((O54-J54)/(O49-J49),"") | P60: =IFERROR((P54-K54)/(P49-K49),"") | Q60: =IFERROR((Q54-L54)/(Q49-L49),"") | R60: =IFERROR((R54-M54)/(R49-M49),"") | S60: =IFERROR((S54-N54)/(S49-N49),"") | T60: =IFERROR((T54-O54)/(T49-O49),"") | U60: =IFERROR((U54-P54)/(U49-P49),"") | ... CF60: =IFERROR((CF54-CA54)/(CF49-CA49),"") -> 0.31744778 | CG60: =IFERROR((CG54-CF54)/(CG49-CF49),"") -> 0.17404315 | CH60: =IFERROR((CH54-CG54)/(CH49-CG49),"") -> 0.29 | CI60: =IFERROR((CI54-CH54)/(CI49-CH49),"") -> 0.40821797 | CJ60: =IFERROR((CJ54-CI54)/(CJ49-CI49),"") -> 0.41165841 | CS60: 2031E | CT60: =CU60+$CT$56 -> 0.07 | CU60: 0.03 | CV60: =CU60+$CV$56 -> -0.03
CS61: DC_WIN (Windows OEM & devices y/y) | CT61: 0.03 | CU61: Δ → | CV61: -0.04 | CW61: FY26 −1.3% (Windows 10 end-of-support pull-forward); Q1 FY27 guided down low-twenties on that comparison; PC-market growth thereafter.
B62: Mix & KPIs (outputs) | CK62: MIX — outputs | CS62: 2028E | CT62: =CU62+$CT$61 -> 0.03 | CU62: 0 | CV62: =CU62+$CV$61 -> -0.04
B63: Azure % of total revenue | C63: =IF(ISNUMBER(C11),IFERROR(C11/C130,""),"") | D63: =IF(ISNUMBER(D11),IFERROR(D11/D130,""),"") | E63: =IF(ISNUMBER(E11),IFERROR(E11/E130,""),"") | F63: =IF(ISNUMBER(F11),IFERROR(F11/F130,""),"") | G63: =IF(ISNUMBER(G11),IFERROR(G11/G130,""),"") | H63: =IF(ISNUMBER(H11),IFERROR(H11/H130,""),"") | I63: =IF(ISNUMBER(I11),IFERROR(I11/I130,""),"") | J63: =IF(ISNUMBER(J11),IFERROR(J11/J130,""),"") | ... CJ63: =IF(ISNUMBER(CJ11),IFERROR(CJ11/CJ130,""),"") -> 0.50323256 | CM63: =IFERROR(AVERAGE(CF63,CG63,CH63,CI63,CJ63),"n/m") -> 0.44469484 | CN63: =IFERROR(AVERAGE(BG63,BL63,BQ63,BV63,CA63),"n/m") -> 0.28246283 | CO63: =IFERROR(AVERAGE(AH63,AM63,AR63,AW63,BB63,BG63,BL63,BQ63,BV63,CA63),"n/m") -> 0.28246283 | CP63: =IFERROR(AVERAGE(C63,D63,E63,F63,G63,H63,I63,N63,S63,X63,AC63,AH63,AM63,AR63,AW63,BB63,BG63,BL63,BQ63,BV63,CA63),"n/m") -> 0.28246283 | CS63: 2029E | CT63: =CU63+$CT$61 -> 0.04 | CU63: 0.01 | CV63: =CU63+$CV$61 -> -0.03
B64: Azure + Microsoft 365 cloud + Industry solutions revenue (proxy for the Microsoft Cloud metric; not the company definition) | C64: =IF(ISNUMBER(C11),C11+C14+C20,"") | D64: =IF(ISNUMBER(D11),D11+D14+D20,"") | E64: =IF(ISNUMBER(E11),E11+E14+E20,"") | F64: =IF(ISNUMBER(F11),F11+F14+F20,"") | G64: =IF(ISNUMBER(G11),G11+G14+G20,"") | H64: =IF(ISNUMBER(H11),H11+H14+H20,"") | I64: =IF(ISNUMBER(I11),I11+I14+I20,"") | J64: =IF(ISNUMBER(J11),J11+J14+J20,"") | ... CJ64: =IF(ISNUMBER(CJ11),CJ11+CJ14+CJ20,"") -> 553757.57 | CK64: Industry solutions includes on-premises products; Microsoft Cloud (company metric) counts only Industry solutions cloud — this row is a labelled proxy. | CM64: =IFERROR((CJ64/CA64)^(1/5)-1,"n/m") -> 0.19995767 | CN64: =IFERROR((CA64/BB64)^(1/5)-1,"n/m") -> n/m | CO64: =IFERROR((CA64/AC64)^(1/10)-1,"n/m") -> n/m | CP64: =IFERROR((CA64/C64)^(1/20)-1,"n/m") -> n/m | CS64: 2030E | CT64: =CU64+$CT$61 -> 0.04 | CU64: 0.01 | CV64: =CU64+$CV$61 -> -0.03
B65: y/y % | D65: =IF(AND(ISNUMBER(D64),ISNUMBER(C64)),IFERROR(D64/C64-1,""),"") | E65: =IF(AND(ISNUMBER(E64),ISNUMBER(D64)),IFERROR(E64/D64-1,""),"") | F65: =IF(AND(ISNUMBER(F64),ISNUMBER(E64)),IFERROR(F64/E64-1,""),"") | G65: =IF(AND(ISNUMBER(G64),ISNUMBER(F64)),IFERROR(G64/F64-1,""),"") | H65: =IF(AND(ISNUMBER(H64),ISNUMBER(G64)),IFERROR(H64/G64-1,""),"") | I65: =IF(AND(ISNUMBER(I64),ISNUMBER(H64)),IFERROR(I64/H64-1,""),"") | N65: =IF(AND(ISNUMBER(N64),ISNUMBER(I64)),IFERROR(N64/I64-1,""),"") | O65: =IF(AND(ISNUMBER(O64),ISNUMBER(J64)),IFERROR(O64/J64-1,""),"") | P65: =IF(AND(ISNUMBER(P64),ISNUMBER(K64)),IFERROR(P64/K64-1,""),"") | Q65: =IF(AND(ISNUMBER(Q64),ISNUMBER(L64)),IFERROR(Q64/L64-1,""),"") | R65: =IF(AND(ISNUMBER(R64),ISNUMBER(M64)),IFERROR(R64/M64-1,""),"") | S65: =IF(AND(ISNUMBER(S64),ISNUMBER(N64)),IFERROR(S64/N64-1,""),"") | T65: =IF(AND(ISNUMBER(T64),ISNUMBER(O64)),IFERROR(T64/O64-1,""),"") | U65: =IF(AND(ISNUMBER(U64),ISNUMBER(P64)),IFERROR(U64/P64-1,""),"") | ... CF65: =IF(AND(ISNUMBER(CF64),ISNUMBER(CA64)),IFERROR(CF64/CA64-1,""),"") -> 0.2635088 | CG65: =IF(AND(ISNUMBER(CG64),ISNUMBER(CF64)),IFERROR(CG64/CF64-1,""),"") -> 0.22796674 | CH65: =IF(AND(ISNUMBER(CH64),ISNUMBER(CG64)),IFERROR(CH64/CG64-1,""),"") -> 0.19855242 | CI65: =IF(AND(ISNUMBER(CI64),ISNUMBER(CH64)),IFERROR(CI64/CH64-1,""),"") -> 0.1693875 | CJ65: =IF(AND(ISNUMBER(CJ64),ISNUMBER(CI64)),IFERROR(CJ64/CI64-1,""),"") -> 0.14406127 | CS65: 2031E | CT65: =CU65+$CT$61 -> 0.04 | CU65: 0.01 | CV65: =CU65+$CV$61 -> -0.03
B66: Contribution to total revenue growth — Agents and Infra (pp) | D66: =IFERROR((D26-C26)/C130,"") | E66: =IFERROR((E26-D26)/D130,"") | F66: =IFERROR((F26-E26)/E130,"") | G66: =IFERROR((G26-F26)/F130,"") | H66: =IFERROR((H26-G26)/G130,"") | I66: =IFERROR((I26-H26)/H130,"") | N66: =IFERROR((N26-I26)/I130,"") | O66: =IFERROR((O26-J26)/J130,"") | P66: =IFERROR((P26-K26)/K130,"") | Q66: =IFERROR((Q26-L26)/L130,"") | R66: =IFERROR((R26-M26)/M130,"") | S66: =IFERROR((S26-N26)/N130,"") | T66: =IFERROR((T26-O26)/O130,"") | U66: =IFERROR((U26-P26)/P130,"") | ... CF66: =IFERROR((CF26-CA26)/CA130,"") -> 0.18456055 | CG66: =IFERROR((CG26-CF26)/CF130,"") -> 0.16362346 | CH66: =IFERROR((CH26-CG26)/CG130,"") -> 0.14965848 | CI66: =IFERROR((CI26-CH26)/CH130,"") -> 0.13144624 | CJ66: =IFERROR((CJ26-CI26)/CI130,"") -> 0.11498229 | CS66: AI_M (Agents and Infra operating margin) | CT66: 0.02 | CU66: Δ → | CV66: -0.04 | CW66: FY26 50.9% (FY25 50.6%; Q4/26 49.3%); depreciation from the FY26–27 capex wave (FY26 $34bn, +56%) compresses margins before operating leverage. Assumption.
B67: Contribution to total revenue growth — Devices and Consumer (pp) | D67: =IFERROR((D49-C49)/C130,"") | E67: =IFERROR((E49-D49)/D130,"") | F67: =IFERROR((F49-E49)/E130,"") | G67: =IFERROR((G49-F49)/F130,"") | H67: =IFERROR((H49-G49)/G130,"") | I67: =IFERROR((I49-H49)/H130,"") | N67: =IFERROR((N49-I49)/I130,"") | O67: =IFERROR((O49-J49)/J130,"") | P67: =IFERROR((P49-K49)/K130,"") | Q67: =IFERROR((Q49-L49)/L130,"") | R67: =IFERROR((R49-M49)/M130,"") | S67: =IFERROR((S49-N49)/N130,"") | T67: =IFERROR((T49-O49)/O130,"") | U67: =IFERROR((U49-P49)/P130,"") | ... CF67: =IFERROR((CF49-CA49)/CA130,"") -> -0.011954788 | CG67: =IFERROR((CG49-CF49)/CF130,"") -> 0.0063525802 | CH67: =IFERROR((CH49-CG49)/CG130,"") -> 0.006556495 | CI67: =IFERROR((CI49-CH49)/CH130,"") -> 0.0054653123 | CJ67: =IFERROR((CJ49-CI49)/CI130,"") -> 0.0050865901 | CS67: 2028E | CT67: =CU67+$CT$66 -> 0.49 | CU67: 0.47 | CV67: =CU67+$CV$66 -> 0.43
CS68: 2029E | CT68: =CU68+$CT$66 -> 0.485 | CU68: 0.465 | CV68: =CU68+$CV$66 -> 0.425
B69: Legacy segment structures — memo, as originally reported in each period's release / 10-K (not on the FY27 basis) | CK69: LEGACY SEGMENTS — memo only; each structure ties to consolidated revenue / profit in its own periods (check rows) | CS69: 2030E | CT69: =CU69+$CT$66 -> 0.49 | CU69: 0.47 | CV69: =CU69+$CV$66 -> 0.43
B70: Productivity and Business Processes / Intelligent Cloud / More Personal Computing (FY2016–FY2026; recast Aug-2019, Aug-2024 not applied) | CS70: 2031E | CT70: =CU70+$CT$66 -> 0.495 | CU70: 0.475 | CV70: =CU70+$CV$66 -> 0.435
B71: Productivity and Business Processes — revenue | Y71: 6306 | Z71: 6690 | AA71: 6522 | AB71: 6969 | AC71: 26487 | AD71: 6658 | AE71: 7382 | AF71: 7958 | AG71: 8446 | AH71: 30444 | AI71: 8238 | AJ71: 8953 | AK71: 9006 | AL71: 9668 | AM71: 35865 | AN71: 9771 | AO71: 10100 | AP71: 10242 | AQ71: 11047 | AR71: 41160 | AS71: 11077 | AT71: 11826 | AU71: 11743 | AV71: 11752 | AW71: 46398 | AX71: 12319 | AY71: 13353 | AZ71: 13552 | BA71: 14691 | BB71: 53915 | BC71: 15039 | BD71: 15936 | BE71: 15789 | BF71: 16600 | BG71: 63364 | BH71: 16465 | BI71: 17002 | BJ71: 17516 | BK71: 18291 | BL71: 69274 | BM71: 18592 | BN71: 19249 | BO71: 19570 | BP71: 20317 | BQ71: 77728 | BR71: 28317 | BS71: 29437 | BT71: 29944 | BU71: 33112 | BV71: 120810 | BW71: 33020 | BX71: 34116 | BY71: 35013 | BZ71: 37847 | CA71: 139996 | CM71: =IFERROR((CJ71/CA71)^(1/5)-1,"n/m") -> -1 | CN71: =IFERROR((CA71/BB71)^(1/5)-1,"n/m") -> 0.21026703 | CO71: =IFERROR((CA71/AC71)^(1/10)-1,"n/m") -> 0.18115879 | CP71: =IFERROR((CA71/C71)^(1/20)-1,"n/m") -> n/m | CS71: DC_M (Devices and Consumer operating margin) | CT71: 0.02 | CU71: Δ → | CV71: -0.03 | CW71: FY26 29.6% (FY25 28.1%); Q4/26 25.1% after XBOX charges.
B72: Intelligent Cloud — revenue | Y72: 5892 | Z72: 6343 | AA72: 6096 | AB72: 6711 | AC72: 25042 | AD72: 6382 | AE72: 6861 | AF72: 6763 | AG72: 7434 | AH72: 27440 | AI72: 6922 | AJ72: 7795 | AK72: 7896 | AL72: 9606 | AM72: 32219 | AN72: 8567 | AO72: 9378 | AP72: 9649 | AQ72: 11391 | AR72: 38985 | AS72: 10845 | AT72: 11869 | AU72: 12281 | AV72: 13371 | AW72: 48366 | AX72: 12986 | AY72: 14601 | AZ72: 15118 | BA72: 17375 | BB72: 60080 | BC72: 16964 | BD72: 18327 | BE72: 19051 | BF72: 20909 | BG72: 75251 | BH72: 20325 | BI72: 21508 | BJ72: 22081 | BK72: 23993 | BL72: 87907 | BM72: 24259 | BN72: 25880 | BO72: 26708 | BP72: 28515 | BQ72: 105362 | BR72: 24092 | BS72: 25544 | BT72: 26751 | BU72: 29878 | BV72: 106265 | BW72: 30897 | BX72: 32907 | BY72: 34681 | BZ72: 39306 | CA72: 137791 | CM72: =IFERROR((CJ72/CA72)^(1/5)-1,"n/m") -> -1 | CN72: =IFERROR((CA72/BB72)^(1/5)-1,"n/m") -> 0.18058751 | CO72: =IFERROR((CA72/AC72)^(1/10)-1,"n/m") -> 0.18591943 | CP72: =IFERROR((CA72/C72)^(1/20)-1,"n/m") -> n/m | CS72: 2028E | CT72: =CU72+$CT$71 -> 0.31 | CU72: 0.29 | CV72: =CU72+$CV$71 -> 0.26
B73: More Personal Computing — revenue | Y73: 9381 | Z73: 12660 | AA73: 9458 | AB73: 8897 | AC73: 40460 | AD73: 9294 | AE73: 11823 | AF73: 8836 | AG73: 8820 | AH73: 38773 | AI73: 9378 | AJ73: 12170 | AK73: 9917 | AL73: 10811 | AM73: 42276 | AN73: 10746 | AO73: 12993 | AP73: 10680 | AQ73: 11279 | AR73: 45698 | AS73: 11133 | AT73: 13211 | AU73: 10997 | AV73: 12910 | AW73: 48251 | AX73: 11849 | AY73: 15122 | AZ73: 13036 | BA73: 14086 | BB73: 54093 | BC73: 13314 | BD73: 17465 | BE73: 14520 | BF73: 14356 | BG73: 59655 | BH73: 13332 | BI73: 14237 | BJ73: 13260 | BK73: 13905 | BL73: 54734 | BM73: 13666 | BN73: 16891 | BO73: 15580 | BP73: 15895 | BQ73: 62032 | BR73: 13176 | BS73: 14651 | BT73: 13371 | BU73: 13451 | BV73: 54649 | BW73: 13756 | BX73: 14250 | BY73: 13192 | BZ73: 12854 | CA73: 54052 | CM73: =IFERROR((CJ73/CA73)^(1/5)-1,"n/m") -> -1 | CN73: =IFERROR((CA73/BB73)^(1/5)-1,"n/m") -> -0.00015163676 | CO73: =IFERROR((CA73/AC73)^(1/10)-1,"n/m") -> 0.029386786 | CP73: =IFERROR((CA73/C73)^(1/20)-1,"n/m") -> n/m | CS73: 2029E | CT73: =CU73+$CT$71 -> 0.31 | CU73: 0.29 | CV73: =CU73+$CV$71 -> 0.26
B74: Corporate and Other (FY2016–FY2018) — revenue | Y74: -1200 | Z74: -1897 | AA74: -1545 | AB74: -1963 | AC74: -6669 | AD74: -1881 | AE74: -1976 | AF74: -1467 | AG74: -1383 | AH74: -6707 | CS74: 2030E | CT74: =CU74+$CT$71 -> 0.315 | CU74: 0.295 | CV74: =CU74+$CV$71 -> 0.265
B75: Check: Σ revenue vs consolidated (should be 0) | C75: =IF(ISNUMBER(C71),ROUND(N(C71)+N(C72)+N(C73)+N(C74)-C179,0),"") | D75: =IF(ISNUMBER(D71),ROUND(N(D71)+N(D72)+N(D73)+N(D74)-D179,0),"") | E75: =IF(ISNUMBER(E71),ROUND(N(E71)+N(E72)+N(E73)+N(E74)-E179,0),"") | F75: =IF(ISNUMBER(F71),ROUND(N(F71)+N(F72)+N(F73)+N(F74)-F179,0),"") | G75: =IF(ISNUMBER(G71),ROUND(N(G71)+N(G72)+N(G73)+N(G74)-G179,0),"") | H75: =IF(ISNUMBER(H71),ROUND(N(H71)+N(H72)+N(H73)+N(H74)-H179,0),"") | I75: =IF(ISNUMBER(I71),ROUND(N(I71)+N(I72)+N(I73)+N(I74)-I179,0),"") | J75: =IF(ISNUMBER(J71),ROUND(N(J71)+N(J72)+N(J73)+N(J74)-J179,0),"") | ... CA75: =IF(ISNUMBER(CA71),ROUND(N(CA71)+N(CA72)+N(CA73)+N(CA74)-CA179,0),"") -> 0 | CS75: 2031E | CT75: =CU75+$CT$71 -> 0.32 | CU75: 0.3 | CV75: =CU75+$CV$71 -> 0.27
B76: Productivity and Business Processes — operating income | Y76: 3105 | Z76: 3305 | AA76: 2994 | AB76: 3000 | AC76: 12461 | AD76: 3120 | AE76: 3256 | AF76: 2783 | AG76: 2754 | AH76: 11913 | AI76: 3006 | AJ76: 3337 | AK76: 3115 | AL76: 3466 | AM76: 12924 | AN76: 3881 | AO76: 4015 | AP76: 3979 | AQ76: 4344 | AR76: 16219 | AS76: 4782 | AT76: 5182 | AU76: 4788 | AV76: 3972 | AW76: 18724 | AX76: 5706 | AY76: 6181 | AZ76: 6029 | BA76: 6435 | BB76: 24351 | BC76: 7581 | BD76: 7688 | BE76: 7184 | BF76: 7234 | BG76: 29687 | BH76: 8323 | BI76: 8175 | BJ76: 8639 | BK76: 9052 | BL76: 34189 | BM76: 9970 | BN76: 10284 | BO76: 10143 | BP76: 10143 | BQ76: 40540 | BR76: 16516 | BS76: 16885 | BT76: 17379 | BU76: 18993 | BV76: 69773 | BW76: 20407 | BX76: 20599 | BY76: 20973 | BZ76: 21900 | CA76: 83879 | CS76: M&A_spend (acquisitions, $m) | CT76: 2000 | CU76: Δ → | CV76: -3000 | CW76: Acquisition spend FY24 $69.1bn (Activision), FY25 $6.0bn, FY26 $1.7bn. Base $3bn p.a. of bolt-ons (assumption).
B77: Intelligent Cloud — operating income | Y77: 2400 | Z77: 2580 | AA77: 2188 | AB77: 2190 | AC77: 9358 | AD77: 2058 | AE77: 2398 | AF77: 2181 | AG77: 2501 | AH77: 9138 | AI77: 2137 | AJ77: 2832 | AK77: 2654 | AL77: 3901 | AM77: 11524 | AN77: 2931 | AO77: 3279 | AP77: 3208 | AQ77: 4502 | AR77: 13920 | AS77: 3889 | AT77: 4531 | AU77: 4560 | AV77: 5344 | AW77: 18324 | AX77: 5422 | AY77: 6492 | AZ77: 6425 | BA77: 7787 | BB77: 26126 | BC77: 7562 | BD77: 8197 | BE77: 8281 | BF77: 8681 | BG77: 32721 | BH77: 8978 | BI77: 8904 | BJ77: 9476 | BK77: 10526 | BL77: 37884 | BM77: 11751 | BN77: 12461 | BO77: 12513 | BP77: 12859 | BQ77: 49584 | BR77: 10503 | BS77: 10851 | BT77: 11095 | BU77: 12140 | BV77: 44589 | BW77: 13391 | BX77: 13873 | BY77: 13753 | BZ77: 15955 | CA77: 56972 | CS77: 2028E | CT77: =MAX(0,CU77+$CT$76) -> 5000 | CU77: 3000 | CV77: =MAX(0,CU77+$CV$76) -> 0
B78: More Personal Computing — operating income | Y78: 1562 | Z78: 2038 | AA78: 1645 | AB78: 964 | AC78: 6142 | AD78: 1928 | AE78: 2499 | AF78: 2097 | AG78: 1764 | AH78: 8288 | AI78: 2565 | AJ78: 2510 | AK78: 2523 | AL78: 3012 | AM78: 10610 | AN78: 3143 | AO78: 2964 | AP78: 3154 | AQ78: 3559 | AR78: 12820 | AS78: 4015 | AT78: 4178 | AU78: 3627 | AV78: 4091 | AW78: 15911 | AX78: 4748 | AY78: 5224 | AZ78: 4594 | BA78: 4873 | BB78: 19439 | BC78: 5095 | BD78: 6362 | BE78: 4899 | BF78: 4619 | BG78: 20975 | BH78: 4217 | BI78: 3320 | BJ78: 4237 | BK78: 4676 | BL78: 16450 | BM78: 5174 | BN78: 4287 | BO78: 4925 | BP78: 4923 | BQ78: 19309 | BR78: 3533 | BS78: 3917 | BT78: 3526 | BU78: 3190 | BV78: 14166 | BW78: 4163 | BX78: 3803 | BY78: 3672 | BZ78: 2748 | CA78: 14386 | CS78: 2029E | CT78: =MAX(0,CU78+$CT$76) -> 5000 | CU78: 3000 | CV78: =MAX(0,CU78+$CV$76) -> 0
B79: Corporate and Other — operating income | Y79: -1274 | Z79: -1897 | AA79: -1544 | AB79: -3074 | AC79: -7779 | AD79: -1881 | AE79: -1976 | AF79: -1467 | AG79: -1689 | AH79: -7013 | AL79: 0 | AM79: 0 | CS79: 2030E | CT79: =MAX(0,CU79+$CT$76) -> 5000 | CU79: 3000 | CV79: =MAX(0,CU79+$CV$76) -> 0
B80: Check: Σ operating income vs consolidated (should be 0) | C80: =IF(ISNUMBER(C76),ROUND(N(C76)+N(C77)+N(C78)+N(C79)-C190,0),"") | D80: =IF(ISNUMBER(D76),ROUND(N(D76)+N(D77)+N(D78)+N(D79)-D190,0),"") | E80: =IF(ISNUMBER(E76),ROUND(N(E76)+N(E77)+N(E78)+N(E79)-E190,0),"") | F80: =IF(ISNUMBER(F76),ROUND(N(F76)+N(F77)+N(F78)+N(F79)-F190,0),"") | G80: =IF(ISNUMBER(G76),ROUND(N(G76)+N(G77)+N(G78)+N(G79)-G190,0),"") | H80: =IF(ISNUMBER(H76),ROUND(N(H76)+N(H77)+N(H78)+N(H79)-H190,0),"") | I80: =IF(ISNUMBER(I76),ROUND(N(I76)+N(I77)+N(I78)+N(I79)-I190,0),"") | J80: =IF(ISNUMBER(J76),ROUND(N(J76)+N(J77)+N(J78)+N(J79)-J190,0),"") | ... CA80: =IF(ISNUMBER(CA76),ROUND(N(CA76)+N(CA77)+N(CA78)+N(CA79)-CA190,0),"") -> 0 | CS80: 2031E | CT80: =MAX(0,CU80+$CT$76) -> 5000 | CU80: 3000 | CV80: =MAX(0,CU80+$CV$76) -> 0
B81: Devices & Consumer / Commercial (FY2014–FY2015; revenue and gross margin only)
B82: D&C Licensing — revenue | O82: 4343 | P82: 5384 | Q82: 4382 | R82: 4694 | S82: 18803 | T82: 4093 | U82: 4167 | V82: 3476 | W82: 3233 | X82: 14969
B83: Computing and Gaming Hardware (D&C Hardware to Q3/14) — revenue | O83: 1485 | P83: 4729 | Q83: 1973 | R83: 1441 | S83: 9628 | T83: 2453 | U83: 3997 | V83: 1800 | W83: 1933 | X83: 10183
B84: Phone Hardware (Nokia, from Apr-2014) — revenue | R84: 1985 | S84: 1985 | T84: 2609 | U84: 2284 | V84: 1397 | W84: 1234 | X84: 7524
B85: D&C Other — revenue | O85: 1635 | P85: 1793 | Q85: 1950 | R85: 1880 | S85: 7258 | T85: 1809 | U85: 2436 | V85: 2280 | W85: 2300 | X85: 8825
B86: Commercial Licensing — revenue | O86: 9594 | P86: 10888 | Q86: 10323 | R86: 11222 | S86: 42027 | T86: 9873 | U86: 10679 | V86: 10036 | W86: 10451 | X86: 41039
B87: Commercial Other — revenue | O87: 1603 | P87: 1780 | Q87: 1902 | R87: 2262 | S87: 7547 | T87: 2407 | U87: 2593 | V87: 2760 | W87: 3076 | X87: 10836
B88: Corporate and Other — revenue | O88: -131 | P88: -55 | Q88: -127 | R88: -102 | S88: -415 | T88: -43 | U88: 314 | V88: -20 | W88: -47 | X88: 204
B89: Check: Σ revenue vs consolidated (should be 0) | C89: =IF(ISNUMBER(C86),ROUND(N(C82)+N(C83)+N(C84)+N(C85)+N(C86)+N(C87)+N(C88)-C179,0),"") | D89: =IF(ISNUMBER(D86),ROUND(N(D82)+N(D83)+N(D84)+N(D85)+N(D86)+N(D87)+N(D88)-D179,0),"") | E89: =IF(ISNUMBER(E86),ROUND(N(E82)+N(E83)+N(E84)+N(E85)+N(E86)+N(E87)+N(E88)-E179,0),"") | F89: =IF(ISNUMBER(F86),ROUND(N(F82)+N(F83)+N(F84)+N(F85)+N(F86)+N(F87)+N(F88)-F179,0),"") | G89: =IF(ISNUMBER(G86),ROUND(N(G82)+N(G83)+N(G84)+N(G85)+N(G86)+N(G87)+N(G88)-G179,0),"") | H89: =IF(ISNUMBER(H86),ROUND(N(H82)+N(H83)+N(H84)+N(H85)+N(H86)+N(H87)+N(H88)-H179,0),"") | I89: =IF(ISNUMBER(I86),ROUND(N(I82)+N(I83)+N(I84)+N(I85)+N(I86)+N(I87)+N(I88)-I179,0),"") | J89: =IF(ISNUMBER(J86),ROUND(N(J82)+N(J83)+N(J84)+N(J85)+N(J86)+N(J87)+N(J88)-J179,0),"") | ... CA89: =IF(ISNUMBER(CA86),ROUND(N(CA82)+N(CA83)+N(CA84)+N(CA85)+N(CA86)+N(CA87)+N(CA88)-CA179,0),"")
B90: D&C Licensing — gross margin | O90: 3925 | P90: 4978 | Q90: 3906 | R90: 4407 | S90: 17216 | T90: 3818 | U90: 3876 | V90: 3210 | W90: 2966 | X90: 13870
B91: Computing and Gaming Hardware (D&C Hardware to Q3/14) — gross margin | O91: 206 | P91: 411 | Q91: 258 | R91: 18 | S91: 893 | T91: 479 | U91: 460 | V91: 414 | W91: 435 | X91: 1788
B92: Phone Hardware (Nokia, from Apr-2014) — gross margin | R92: 54 | S92: 54 | T92: 478 | U92: 331 | V92: -4 | W92: -104 | X92: 701
B93: D&C Other — gross margin | O93: 352 | P93: 431 | Q93: 541 | R93: 446 | S93: 1770 | T93: 312 | U93: 550 | V93: 566 | W93: 594 | X93: 2022
B94: Commercial Licensing — gross margin | O94: 8801 | P94: 10077 | Q94: 9430 | R94: 10296 | S94: 38604 | T94: 9100 | U94: 9926 | V94: 9275 | W94: 9529 | X94: 37830
B95: Commercial Other — gross margin | O95: 275 | P95: 415 | Q95: 475 | R95: 691 | S95: 1856 | T95: 805 | U95: 900 | V95: 1144 | W95: 1350 | X95: 4199
B96: Corporate and Other — gross margin | O96: -144 | P96: -77 | Q96: -148 | R96: -125 | S96: -494 | T96: -64 | U96: 291 | V96: -37 | W96: -58 | X96: 132
B97: Check: Σ gross margin vs consolidated (should be 0) | C97: =IF(ISNUMBER(C94),ROUND(N(C90)+N(C91)+N(C92)+N(C93)+N(C94)+N(C95)+N(C96)-C183,0),"") | D97: =IF(ISNUMBER(D94),ROUND(N(D90)+N(D91)+N(D92)+N(D93)+N(D94)+N(D95)+N(D96)-D183,0),"") | E97: =IF(ISNUMBER(E94),ROUND(N(E90)+N(E91)+N(E92)+N(E93)+N(E94)+N(E95)+N(E96)-E183,0),"") | F97: =IF(ISNUMBER(F94),ROUND(N(F90)+N(F91)+N(F92)+N(F93)+N(F94)+N(F95)+N(F96)-F183,0),"") | G97: =IF(ISNUMBER(G94),ROUND(N(G90)+N(G91)+N(G92)+N(G93)+N(G94)+N(G95)+N(G96)-G183,0),"") | H97: =IF(ISNUMBER(H94),ROUND(N(H90)+N(H91)+N(H92)+N(H93)+N(H94)+N(H95)+N(H96)-H183,0),"") | I97: =IF(ISNUMBER(I94),ROUND(N(I90)+N(I91)+N(I92)+N(I93)+N(I94)+N(I95)+N(I96)-I183,0),"") | J97: =IF(ISNUMBER(J94),ROUND(N(J90)+N(J91)+N(J92)+N(J93)+N(J94)+N(J95)+N(J96)-J183,0),"") | ... CA97: =IF(ISNUMBER(CA94),ROUND(N(CA90)+N(CA91)+N(CA92)+N(CA93)+N(CA94)+N(CA95)+N(CA96)-CA183,0),"")
B98: Divisions (FY2006–FY2013; FY2006 seven segments aggregated into the FY2007 five divisions)
B99: Client / Windows (& Windows Live) Division — revenue | C99: 13001 | D99: 14812 | E99: 16472 | F99: 14414 | G99: 17788 | H99: 18778 | I99: 18818 | J99: 3244 | K99: 5881 | L99: 5703 | M99: 4411 | N99: 19239
B100: Server and Tools — revenue | C100: 10542 | D100: 11182 | E100: 13189 | F100: 14135 | G100: 14878 | H100: 17107 | I100: 18696 | J100: 4552 | K100: 5186 | L100: 5039 | M100: 5502 | N100: 20281
...

Sheet Bull-Base-Bear
B2: Microsoft Corporation (MSFT) — Bull / Base / Bear Case P&L Summary | J2: Share price ($): | K2: =Model!$CF$449 -> 541
B3: Adjusted figures (company "As Adjusted" definitions; adjusted EBITDA is a model definition) · USD millions · fiscal years ended 30 June · Live panel linked to Model — toggle scenario via Model!CK2. Bull and Bear panels are value snapshots generated from the Model with the switch set to each case. FY2027E = Q1/27E calibrated to the Q1 FY27 outlook (8-K 2-Sep-2026) + Q2–Q4/27E carrying the Q1 calibration. | J3: As of: | K3: =TODAY() -> 2026-10-13 00:00:00
B5: Scenario: | C5: =Model!$CK$2 -> Base | N5: Scenario: | O5: Bull | P5: Snapshot (values) — Model run with switch = Bull | Z5: Scenario: | AA5: Bear | AB5: Snapshot (values) — Model run with switch = Bear
B7: (USDm, except EPS and shares) | C7: 2026A | D7: 2027E | E7: 2028E | F7: 2029E | G7: 2030E | H7: 2031E | I7: 26-'31 CAGR | J7: LT Hist Avg | K7: LT Hist Min | L7: LT Hist Max | N7: (USDm, except EPS and shares) | O7: 2026A | P7: 2027E | Q7: 2028E | R7: 2029E | S7: 2030E | T7: 2031E | U7: 26-'31 CAGR | V7: LT Hist Avg | W7: LT Hist Min | X7: LT Hist Max | Z7: (USDm, except EPS and shares) | AA7: 2026A | AB7: 2027E | AC7: 2028E | AD7: 2029E | AE7: 2030E | AF7: 2031E | AG7: 26-'31 CAGR | AH7: LT Hist Avg | AI7: LT Hist Min | AJ7: LT Hist Max
B9: Revenue | C9: =Model!CA179 -> 331839 | D9: =Model!CF179 -> 389116.32 | E9: =Model!CG179 -> 455406.77 | F9: =Model!CH179 -> 526872.13 | G9: =Model!CI179 -> 599356.93 | H9: =Model!CJ179 -> 671698.96 | I9: =IFERROR((H9/C9)^(1/5)-1,"n/m") -> 0.15146158 | N9: Revenue | O9: 331839 | P9: 391416.05 | Q9: 474243.89 | R9: 569347.74 | S9: 673400.05 | T9: 785851.67 | U9: 0.18818108 | Z9: Revenue | AA9: 331839 | AB9: 386816.6 | AC9: 426941.19 | AD9: 463783.94 | AE9: 493711.76 | AF9: 516561.11 | AG9: 0.092543798
B10: Revenue y/y % | D10: =IFERROR(D9/C9-1,"") -> 0.17260576 | E10: =IFERROR(E9/D9-1,"") -> 0.17036152 | F10: =IFERROR(F9/E9-1,"") -> 0.15692643 | G10: =IFERROR(G9/F9-1,"") -> 0.1375757 | H10: =IFERROR(H9/G9-1,"") -> 0.12069941 | N10: Revenue y/y % | P10: 0.17953601 | Q10: 0.21161074 | R10: 0.20053785 | S10: 0.18275705 | T10: 0.16699082 | Z10: Revenue y/y % | AB10: 0.16567551 | AC10: 0.10373028 | AD10: 0.086294673 | AE10: 0.064529647 | AF10: 0.046280757
B11: Agents and Infra revenue y/y % | C11: =Model!CA271 -> 0.22553855 | D11: =Model!CF271 -> 0.22841559 | E11: =Model!CG271 -> 0.19330324 | F11: =Model!CH271 -> 0.17340601 | G11: =Model!CI271 -> 0.15016489 | H11: =Model!CJ271 -> 0.12991861 | N11: Agents and Infra revenue y/y % | O11: 0.22553855 | P11: 0.23328003 | Q11: 0.23605419 | R11: 0.21843731 | S11: 0.19685169 | T11: 0.17771728 | Z11: Agents and Infra revenue y/y % | AA11: 0.22553855 | AB11: 0.22355115 | AC11: 0.12394647 | AD11: 0.10031603 | AE11: 0.074674234 | AF11: 0.053162697
B12: Adjusted EBITDA (model) | C12: =Model!CA242 -> 193771 | D12: =Model!CF242 -> 236821.05 | E12: =Model!CG242 -> 283174.46 | F12: =Model!CH242 -> 335306.7 | G12: =Model!CI242 -> 389934.94 | H12: =Model!CJ242 -> 441920.38 | I12: =IFERROR((H12/C12)^(1/5)-1,"n/m") -> 0.17926403 | N12: Adjusted EBITDA (model) | O12: 193771 | P12: 239754.23 | Q12: 300970.72 | R12: 366971.48 | S12: 440929.69 | T12: 517793.03 | U12: 0.21723234 | Z12: Adjusted EBITDA (model) | AA12: 193771 | AB12: 233887.18 | AC12: 254004.81 | AD12: 287017.79 | AE12: 316753.99 | AF12: 339118.27 | AG12: 0.11843946
B13: Adjusted EBITDA margin % | C13: =IFERROR(C12/C9,"") -> 0.58393076 | D13: =IFERROR(D12/D9,"") -> 0.60861249 | E13: =IFERROR(E12/E9,"") -> 0.62180556 | F13: =IFERROR(F12/F9,"") -> 0.63641002 | G13: =IFERROR(G12/G9,"") -> 0.65058886 | H13: =IFERROR(H12/H9,"") -> 0.65791435 | J13: =IFERROR(AVERAGE(Model!C243,Model!D243,Model!E243,Model!F243,Model!G243,Model!H243,Model!I243,Model!N243,Model!S243,Model!X243,Model!AC243,Model!AH243,Model!AM243,Model!AR243,Model!AW243,Model!BB243,Model!BG243,Model!BL243,Model!BQ243,Model!BV243,Model!CA243),"") -> 0.44301264 | K13: =IFERROR(MIN(Model!C243,Model!D243,Model!E243,Model!F243,Model!G243,Model!H243,Model!I243,Model!N243,Model!S243,Model!X243,Model!AC243,Model!AH243,Model!AM243,Model!AR243,Model!AW243,Model!BB243,Model!BG243,Model!BL243,Model!BQ243,Model!BV243,Model!CA243),"") -> 0.364704 | L13: =IFERROR(MAX(Model!C243,Model!D243,Model!E243,Model!F243,Model!G243,Model!H243,Model!I243,Model!N243,Model!S243,Model!X243,Model!AC243,Model!AH243,Model!AM243,Model!AR243,Model!AW243,Model!BB243,Model!BG243,Model!BL243,Model!BQ243,Model!BV243,Model!CA243),"") -> 0.58393076 | N13: Adjusted EBITDA margin % | O13: 0.58393076 | P13: 0.61253041 | Q13: 0.63463279 | R13: 0.64454719 | S13: 0.6547812 | T13: 0.6588941 | V13: 0.44301264 | W13: 0.364704 | X13: 0.58393076 | Z13: Adjusted EBITDA margin % | AA13: 0.58393076 | AB13: 0.60464619 | AC13: 0.59494098 | AD13: 0.618861 | AE13: 0.64157677 | AF13: 0.65649207 | AH13: 0.44301264 | AI13: 0.364704 | AJ13: 0.58393076
B15: Operating income (GAAP) | C15: =Model!CA190 -> 155237 | D15: =Model!CF190 -> 180501.13 | E15: =Model!CG190 -> 202794.15 | F15: =Model!CH190 -> 233435.76 | G15: =Model!CI190 -> 269519.72 | H15: =Model!CJ190 -> 306218.5 | I15: =IFERROR((H15/C15)^(1/5)-1,"n/m") -> 0.14553203 | N15: Operating income (GAAP) | O15: 155237 | P15: 183434.31 | Q15: 220547.56 | R15: 263524.13 | S15: 316203.33 | T15: 373978.4 | U15: 0.19225803 | Z15: Operating income (GAAP) | AA15: 155237 | AB15: 177567.26 | AC15: 173688.79 | AD15: 187527.52 | AE15: 202776.28 | AF15: 215238.83 | AG15: 0.067542262
B16: Operating income y/y % | D16: =IFERROR(D15/C15-1,"") -> 0.16274557 | E16: =IFERROR(E15/D15-1,"") -> 0.12350626 | F16: =IFERROR(F15/E15-1,"") -> 0.15109708 | G16: =IFERROR(G15/F15-1,"") -> 0.15457767 | H16: =IFERROR(H15/G15-1,"") -> 0.13616365 | N16: Operating income y/y % | P16: 0.18164042 | Q16: 0.20232442 | R16: 0.19486307 | S16: 0.19990276 | T16: 0.18271494 | Z16: Operating income y/y % | AB16: 0.14384625 | AC16: -0.021842288 | AD16: 0.079675473 | AE16: 0.081314783 | AF16: 0.061459607
B17: Operating margin (GAAP) % | C17: =IFERROR(C15/C9,"") -> 0.46780818 | D17: =IFERROR(D15/D9,"") -> 0.46387449 | E17: =IFERROR(E15/E9,"") -> 0.44530333 | F17: =IFERROR(F15/F9,"") -> 0.44305961 | G17: =IFERROR(G15/G9,"") -> 0.44968148 | H17: =IFERROR(H15/H9,"") -> 0.45588652 | J17: =IFERROR(AVERAGE(Model!C283,Model!D283,Model!E283,Model!F283,Model!G283,Model!H283,Model!I283,Model!N283,Model!S283,Model!X283,Model!AC283,Model!AH283,Model!AM283,Model!AR283,Model!AW283,Model!BB283,Model!BG283,Model!BL283,Model!BQ283,Model!BV283,Model!CA283),"") -> 0.35812314 | K17: =IFERROR(MIN(Model!C283,Model!D283,Model!E283,Model!F283,Model!G283,Model!H283,Model!I283,Model!N283,Model!S283,Model!X283,Model!AC283,Model!AH283,Model!AM283,Model!AR283,Model!AW283,Model!BB283,Model!BG283,Model!BL283,Model!BQ283,Model!BV283,Model!CA283),"") -> 0.19406925 | L17: =IFERROR(MAX(Model!C283,Model!D283,Model!E283,Model!F283,Model!G283,Model!H283,Model!I283,Model!N283,Model!S283,Model!X283,Model!AC283,Model!AH283,Model!AM283,Model!AR283,Model!AW283,Model!BB283,Model!BG283,Model!BL283,Model!BQ283,Model!BV283,Model!CA283),"") -> 0.46780818 | N17: Operating margin (GAAP) % | O17: 0.46780818 | P17: 0.4686428 | Q17: 0.46505092 | R17: 0.46285269 | S17: 0.46956238 | T17: 0.4758893 | V17: 0.35812314 | W17: 0.19406925 | X17: 0.46780818 | Z17: Operating margin (GAAP) % | AA17: 0.46780818 | AB17: 0.45904768 | AC17: 0.40682134 | AD17: 0.40434242 | AE17: 0.41071795 | AF17: 0.41667642 | AH17: 0.35812314 | AI17: 0.19406925 | AJ17: 0.46780818
B19: Adjusted Net Income | C19: =Model!CA258 -> 128786 | D19: =Model!CF258 -> 144080.91 | E19: =Model!CG258 -> 162330.11 | F19: =Model!CH258 -> 186079.81 | G19: =Model!CI258 -> 214296.71 | H19: =Model!CJ258 -> 243062.9 | I19: =IFERROR((H19/C19)^(1/5)-1,"n/m") -> 0.1354552 | N19: Adjusted Net Income | O19: 128786 | P19: 146427.45 | Q19: 176426.87 | R19: 210113.81 | S19: 251668.11 | T19: 297351.43 | U19: 0.18217093 | Z19: Adjusted Net Income | AA19: 128786 | AB19: 141733.81 | AC19: 138860.23 | AD19: 149259.34 | AE19: 160755.23 | AF19: 170110.04 | AG19: 0.057236765
B21: FDSO (m) | C21: =Model!CA208 -> 7453 | D21: =Model!CF208 -> 7438.2282 | E21: =Model!CG208 -> 7407.4635 | F21: =Model!CH208 -> 7314.0087 | G21: =Model!CI208 -> 7165.7318 | H21: =Model!CJ208 -> 6970.4006 | I21: =IFERROR((H21/C21)^(1/5)-1,"n/m") -> -0.013299558 | N21: FDSO (m) | O21: 7453 | P21: 7426.5164 | Q21: 7377.4772 | R21: 7266.6004 | S21: 7089.6002 | T21: 6850.1554 | U21: -0.016727573 | Z21: FDSO (m) | AA21: 7453 | AB21: 7444.1368 | AC21: 7436.4614 | AD21: 7377.1408 | AE21: 7271.3536 | AF21: 7136.6404 | AG21: -0.0086373814
B23: Adjusted EPS — Diluted ($) | C23: =Model!CA262 -> 17.279753 | D23: =Model!CF262 -> 19.370326 | E23: =Model!CG262 -> 21.914399 | F23: =Model!CH262 -> 25.441562 | G23: =Model!CI262 -> 29.905768 | H23: =Model!CJ262 -> 34.870722 | I23: =IFERROR((H23/C23)^(1/5)-1,"n/m") -> 0.1507598 | N23: Adjusted EPS — Diluted ($) | O23: 17.279753 | P23: 19.716842 | Q23: 23.914254 | R23: 28.915009 | S23: 35.498209 | T23: 43.407983 | U23: 0.20228219 | Z23: Adjusted EPS — Diluted ($) | AA23: 17.279753 | AB23: 19.039657 | AC23: 18.672891 | AD23: 20.232682 | AE23: 22.10802 | AF23: 23.836151 | AG23: 0.066448084
B24: EPS y/y % | D24: =IFERROR(D23/C23-1,"") -> 0.12098397 | E24: =IFERROR(E23/D23-1,"") -> 0.13133866 | F24: =IFERROR(F23/E23-1,"") -> 0.16095184 | G24: =IFERROR(G23/F23-1,"") -> 0.17546902 | H24: =IFERROR(H23/G23-1,"") -> 0.16601996 | N24: EPS y/y % | P24: 0.14103726 | Q24: 0.21288461 | R24: 0.20911187 | S24: 0.22767417 | T24: 0.22282176 | Z24: EPS y/y % | AB24: 0.10184773 | AC24: -0.019263241 | AD24: 0.083532351 | AE24: 0.092688584 | AF24: 0.078167585
B26: P / E (x) — assumed (adjusted EPS) | G26: 30 | H26: 30 | N26: P / E (x) — assumed (adjusted EPS) | S26: 34 | T26: 34 | Z26: P / E (x) — assumed (adjusted EPS) | AD26: 24 | AE26: 24 | AF26: 24
B27: Price Target ($) | G27: =G26*G23 -> 897.17304 | H27: =H26*H23 -> 1046.1217 | N27: Price Target ($) | S27: =S26*S23 -> 1206.9391 | T27: =T26*T23 -> 1475.8714 | Z27: Price Target ($) | AD27: =AD26*AD23 -> 485.58436 | AE27: =AE26*AE23 -> 530.59249 | AF27: =AF26*AF23 -> 572.06762
B28: Upside / (Downside) vs current | G28: =IFERROR(G27/$K$2-1,"") -> 0.65836051 | H28: =IFERROR(H27/$K$2-1,"") -> 0.93368145 | N28: Upside / (Downside) vs current | S28: =IFERROR(S27/$K$2-1,"") -> 1.2309411 | T28: =IFERROR(T27/$K$2-1,"") -> 1.7280433 | Z28: Upside / (Downside) vs current | AD28: =IFERROR(AD27/$K$2-1,"") -> -0.10243187 | AE28: =IFERROR(AE27/$K$2-1,"") -> -0.019237547 | AF28: =IFERROR(AF27/$K$2-1,"") -> 0.057426286
B29: IRR (to 30-Jun of Y-1) | G29: =IFERROR((G27/$K$2)^(1/((DATE(2030-1,6,30)-$K$3)/365.25))-1,"") -> 0.20494281 | H29: =IFERROR((H27/$K$2)^(1/((DATE(2031-1,6,30)-$K$3)/365.25))-1,"") -> 0.19437358 | N29: IRR (to 30-Jun of Y-1) | S29: =IFERROR((S27/$K$2)^(1/((DATE(2030-1,6,30)-$K$3)/365.25))-1,"") -> 0.34412992 | T29: =IFERROR((T27/$K$2)^(1/((DATE(2031-1,6,30)-$K$3)/365.25))-1,"") -> 0.31038889 | Z29: IRR (to 30-Jun of Y-1) | AD29: =IFERROR((AD27/$K$2)^(1/((DATE(2029-1,6,30)-$K$3)/365.25))-1,"") -> -0.061106317 | AE29: =IFERROR((AE27/$K$2)^(1/((DATE(2030-1,6,30)-$K$3)/365.25))-1,"") -> -0.0071338471 | AF29: =IFERROR((AF27/$K$2)^(1/((DATE(2031-1,6,30)-$K$3)/365.25))-1,"") -> 0.01515409
B31: Free Cash Flow | C31: =Model!CA314 -> 66987 | D31: =Model!CF314 -> 55969.862 | E31: =Model!CG314 -> 97395.811 | F31: =Model!CH314 -> 141021.36 | G31: =Model!CI314 -> 191374.16 | H31: =Model!CJ314 -> 233824.58 | I31: =IFERROR((H31/C31)^(1/5)-1,"n/m") -> 0.28404406 | N31: Free Cash Flow | O31: 66987 | P31: 58642.022 | Q31: 106961.72 | R31: 156648.72 | S31: 217704.56 | T31: 274491.18 | U31: 0.32589024 | Z31: Free Cash Flow | AA31: 66987 | AB31: 53297.148 | AC31: 80650.719 | AD31: 116698.62 | AE31: 153558.42 | AF31: 179110.2 | AG31: 0.21737942
B32: FCF % | C32: =IFERROR(C31/C9,"") -> 0.20186597 | D32: =IFERROR(D31/D9,"") -> 0.14383838 | E32: =IFERROR(E31/E9,"") -> 0.21386553 | F32: =IFERROR(F31/F9,"") -> 0.26765766 | G32: =IFERROR(G31/G9,"") -> 0.31929916 | H32: =IFERROR(H31/H9,"") -> 0.34810919 | J32: =IFERROR(AVERAGE(Model!C317,Model!D317,Model!E317,Model!F317,Model!G317,Model!H317,Model!I317,Model!N317,Model!S317,Model!X317,Model!AC317,Model!AH317,Model!AM317,Model!AR317,Model!AW317,Model!BB317,Model!BG317,Model!BL317,Model!BQ317,Model!BV317,Model!CA317),"") -> 0.304809 | K32: =IFERROR(MIN(Model!C317,Model!D317,Model!E317,Model!F317,Model!G317,Model!H317,Model!I317,Model!N317,Model!S317,Model!X317,Model!AC317,Model!AH317,Model!AM317,Model!AR317,Model!AW317,Model!BB317,Model!BG317,Model!BL317,Model!BQ317,Model!BV317,Model!CA317),"") -> 0.20186597 | L32: =IFERROR(MAX(Model!C317,Model!D317,Model!E317,Model!F317,Model!G317,Model!H317,Model!I317,Model!N317,Model!S317,Model!X317,Model!AC317,Model!AH317,Model!AM317,Model!AR317,Model!AW317,Model!BB317,Model!BG317,Model!BL317,Model!BQ317,Model!BV317,Model!CA317),"") -> 0.39771849 | N32: FCF % | O32: 0.20186597 | P32: 0.14982018 | Q32: 0.2255416 | R32: 0.27513716 | S32: 0.32329157 | T32: 0.34929134 | V32: 0.304809 | W32: 0.20186597 | X32: 0.39771849 | Z32: FCF % | AA32: 0.20186597 | AB32: 0.13778403 | AC32: 0.18890358 | AD32: 0.25162282 | AE32: 0.31102849 | AF32: 0.34673574 | AH32: 0.304809 | AI32: 0.20186597 | AJ32: 0.39771849
B33: FCF / share ($) | C33: =IFERROR(C31/C21,"") -> 8.9879243 | D33: =IFERROR(D31/D21,"") -> 7.5246229 | E33: =IFERROR(E31/E21,"") -> 13.148335 | F33: =IFERROR(F31/F21,"") -> 19.280994 | G33: =IFERROR(G31/G21,"") -> 26.706856 | H33: =IFERROR(H31/H21,"") -> 33.545358 | N33: FCF / share ($) | O33: 8.9879243 | P33: 7.8963027 | Q33: 14.498415 | R33: 21.55736 | S33: 30.707593 | T33: 40.070796 | Z33: FCF / share ($) | AA33: 8.9879243 | AB33: 7.1596142 | AC33: 10.845309 | AD33: 15.81895 | AE33: 21.118272 | AF33: 25.097271
B34: FCF Yield (on PT) | F34: =IFERROR(F33/F$27,"") | G34: =IFERROR(G33/G$27,"") -> 0.029767787 | H34: =IFERROR(H33/H$27,"") -> 0.032066402 | N34: FCF Yield (on PT) | R34: =IFERROR(R33/R$27,"") | S34: =IFERROR(S33/S$27,"") -> 0.025442537 | T34: =IFERROR(T33/T$27,"") -> 0.027150601 | Z34: FCF Yield (on PT) | AD34: =IFERROR(AD33/AD$27,"") -> 0.03257714 | AE34: =IFERROR(AE33/AE$27,"") -> 0.039801302 | AF34: =IFERROR(AF33/AF$27,"") -> 0.043871161
B35: Adjusted EBITDA (leverage basis) | C35: =Model!CA242 -> 193771 | D35: =Model!CF242 -> 236821.05 | E35: =Model!CG242 -> 283174.46 | F35: =Model!CH242 -> 335306.7 | G35: =Model!CI242 -> 389934.94 | H35: =Model!CJ242 -> 441920.38 | I35: =IFERROR((H35/C35)^(1/5)-1,"n/m") -> 0.17926403 | N35: Adjusted EBITDA (leverage basis) | O35: 193771 | P35: 239754.23 | Q35: 300970.72 | R35: 366971.48 | S35: 440929.69 | T35: 517793.03 | U35: 0.21723234 | Z35: Adjusted EBITDA (leverage basis) | AA35: 193771 | AB35: 233887.18 | AC35: 254004.81 | AD35: 287017.79 | AE35: 316753.99 | AF35: 339118.27 | AG35: 0.11843946
B36: Adjusted EBITDA % of revenue | C36: =IFERROR(C35/C9,"") -> 0.58393076 | D36: =IFERROR(D35/D9,"") -> 0.60861249 | E36: =IFERROR(E35/E9,"") -> 0.62180556 | F36: =IFERROR(F35/F9,"") -> 0.63641002 | G36: =IFERROR(G35/G9,"") -> 0.65058886 | H36: =IFERROR(H35/H9,"") -> 0.65791435 | J36: =IFERROR(AVERAGE(Model!C282,Model!D282,Model!E282,Model!F282,Model!G282,Model!H282,Model!I282,Model!N282,Model!S282,Model!X282,Model!AC282,Model!AH282,Model!AM282,Model!AR282,Model!AW282,Model!BB282,Model!BG282,Model!BL282,Model!BQ282,Model!BV282,Model!CA282),"") -> 0.44301264 | K36: =IFERROR(MIN(Model!C282,Model!D282,Model!E282,Model!F282,Model!G282,Model!H282,Model!I282,Model!N282,Model!S282,Model!X282,Model!AC282,Model!AH282,Model!AM282,Model!AR282,Model!AW282,Model!BB282,Model!BG282,Model!BL282,Model!BQ282,Model!BV282,Model!CA282),"") -> 0.364704 | L36: =IFERROR(MAX(Model!C282,Model!D282,Model!E282,Model!F282,Model!G282,Model!H282,Model!I282,Model!N282,Model!S282,Model!X282,Model!AC282,Model!AH282,Model!AM282,Model!AR282,Model!AW282,Model!BB282,Model!BG282,Model!BL282,Model!BQ282,Model!BV282,Model!CA282),"") -> 0.58393076 | N36: Adjusted EBITDA % of revenue | O36: 0.58393076 | P36: 0.61253041 | Q36: 0.63463279 | R36: 0.64454719 | S36: 0.6547812 | T36: 0.6588941 | V36: 0.44301264 | W36: 0.364704 | X36: 0.58393076 | Z36: Adjusted EBITDA % of revenue | AA36: 0.58393076 | AB36: 0.60464619 | AC36: 0.59494098 | AD36: 0.618861 | AE36: 0.64157677 | AF36: 0.65649207 | AH36: 0.44301264 | AI36: 0.364704 | AJ36: 0.58393076
B38: Net Debt | C38: =Model!CA443 -> 30045 | D38: =Model!CF443 -> 58176.202 | E38: =Model!CG443 -> 87531.628 | F38: =Model!CH443 -> 113937.01 | G38: =Model!CI443 -> 140269.72 | H38: =Model!CJ443 -> 165242.67 | N38: Net Debt | O38: 30045 | P38: 68176.202 | Q38: 99015.051 | R38: 128294.33 | S38: 158870.25 | T38: 189659.51 | Z38: Net Debt | AA38: 30045 | AB38: 54455.852 | AC38: 75289.963 | AD38: 97429.36 | AE38: 117727.32 | AF38: 134852.89
B39: Net Debt / Adjusted EBITDA (x) | C39: =IFERROR(C38/C35,"") -> 0.15505416 | D39: =IFERROR(D38/D35,"") -> 0.24565469 | E39: =IFERROR(E38/E35,"") -> 0.30910848 | F39: =IFERROR(F38/F35,"") -> 0.33979937 | G39: =IFERROR(G38/G35,"") -> 0.35972596 | H39: =IFERROR(H38/H35,"") -> 0.37391955 | N39: Net Debt / Adjusted EBITDA (x) | O39: 0.15505416 | P39: 0.2843587 | Q39: 0.32898566 | R39: 0.349603 | S39: 0.36030744 | T39: 0.36628441 | Z39: Net Debt / Adjusted EBITDA (x) | AA39: 0.15505416 | AB39: 0.23282957 | AC39: 0.29641157 | AD39: 0.33945408 | AE39: 0.37166798 | AF39: 0.3976574
B40: Share repurchases ($m) | D40: =Model!CF327 -> 21393.064 | E40: =Model!CG327 -> 57251.145 | F40: =Model!CH327 -> 93974.252 | G40: =Model!CI327 -> 141500.83 | H40: =Model!CJ327 -> 178877.69 | N40: Share repurchases ($m) | P40: 34065.224 | Q40: 64920.122 | R40: 107679.12 | S40: 165849.5 | T40: 217518.53 | Z40: Share repurchases ($m) | AB40: 15000 | AC40: 37174.408 | AD40: 72578.199 | AE40: 106694.73 | AF40: 127235.53
B41: Implied avg buyback price ($) | D41: =Model!CF326 -> 541 | E41: =Model!CG326 -> 584.28 | F41: =Model!CH326 -> 631.0224 | G41: =Model!CI326 -> 681.50419 | H41: =Model!CJ326 -> 736.02453 | N41: Implied avg buyback price ($) | P41: 541 | Q41: 584.28 | R41: 631.0224 | S41: 681.50419 | T41: 736.02453 | Z41: Implied avg buyback price ($) | AB41: 541 | AC41: 584.28 | AD41: 631.0224 | AE41: 681.50419 | AF41: 736.02453
B42: Shares repurchased (m) | D42: =Model!CF329 -> 39.543557 | E42: =Model!CG329 -> 97.985803 | F42: =Model!CH329 -> 148.9238 | G42: =Model!CI329 -> 207.63017 | H42: =Model!CJ329 -> 243.03224 | N42: Shares repurchased (m) | P42: 62.967142 | Q42: 111.11132 | R42: 170.6423 | S42: 243.35801 | T42: 295.53163 | Z42: Shares repurchased (m) | AB42: 27.726433 | AC42: 63.624303 | AD42: 115.01683 | AE42: 156.5577 | AF42: 172.8686
B44: ROIC | C44: =Model!CA426 -> 0.26485678 | D44: =Model!CF426 -> 0.23668981 | E44: =Model!CG426 -> 0.22479256 | F44: =Model!CH426 -> 0.22640154 | G44: =Model!CI426 -> 0.23730078 | H44: =Model!CJ426 -> 0.24936307 | J44: =IFERROR(AVERAGE(Model!C426,Model!D426,Model!E426,Model!F426,Model!G426,Model!H426,Model!I426,Model!N426,Model!S426,Model!X426,Model!AC426,Model!AH426,Model!AM426,Model!AR426,Model!AW426,Model!BB426,Model!BG426,Model!BL426,Model!BQ426,Model!BV426,Model!CA426),"") -> 0.98736816 | K44: =IFERROR(MIN(Model!C426,Model!D426,Model!E426,Model!F426,Model!G426,Model!H426,Model!I426,Model!N426,Model!S426,Model!X426,Model!AC426,Model!AH426,Model!AM426,Model!AR426,Model!AW426,Model!BB426,Model!BG426,Model!BL426,Model!BQ426,Model!BV426,Model!CA426),"") -> 0.26485678 | L44: =IFERROR(MAX(Model!C426,Model!D426,Model!E426,Model!F426,Model!G426,Model!H426,Model!I426,Model!N426,Model!S426,Model!X426,Model!AC426,Model!AH426,Model!AM426,Model!AR426,Model!AW426,Model!BB426,Model!BG426,Model!BL426,Model!BQ426,Model!BV426,Model!CA426),"") -> 1.9121781 | N44: ROIC | O44: 0.26485678 | P44: 0.24063055 | Q44: 0.24167001 | R44: 0.24861067 | S44: 0.26576816 | T44: 0.28452532 | V44: 0.98736816 | W44: 0.26485678 | X44: 1.9121781 | Z44: ROIC | AA44: 0.26485678 | AB44: 0.23275125 | AC44: 0.19595713 | AD44: 0.18983884 | AE44: 0.19191482 | AF44: 0.19482281 | AH44: 0.98736816 | AI44: 0.26485678 | AJ44: 1.9121781
B45: RONTA | C45: =Model!CA437 -> 0.27170886 | D45: =Model!CF437 -> 0.24292535 | E45: =Model!CG437 -> 0.22995176 | F45: =Model!CH437 -> 0.23116165 | G45: =Model!CI437 -> 0.24212752 | H45: =Model!CJ437 -> 0.25440195 | J45: =IFERROR(AVERAGE(Model!C437,Model!D437,Model!E437,Model!F437,Model!G437,Model!H437,Model!I437,Model!N437,Model!S437,Model!X437,Model!AC437,Model!AH437,Model!AM437,Model!AR437,Model!AW437,Model!BB437,Model!BG437,Model!BL437,Model!BQ437,Model!BV437,Model!CA437),"") -> 0.29201731 | K45: =IFERROR(MIN(Model!C437,Model!D437,Model!E437,Model!F437,Model!G437,Model!H437,Model!I437,Model!N437,Model!S437,Model!X437,Model!AC437,Model!AH437,Model!AM437,Model!AR437,Model!AW437,Model!BB437,Model!BG437,Model!BL437,Model!BQ437,Model!BV437,Model!CA437),"") -> 0.099162492 | L45: =IFERROR(MAX(Model!C437,Model!D437,Model!E437,Model!F437,Model!G437,Model!H437,Model!I437,Model!N437,Model!S437,Model!X437,Model!AC437,Model!AH437,Model!AM437,Model!AR437,Model!AW437,Model!BB437,Model!BG437,Model!BL437,Model!BQ437,Model!BV437,Model!CA437),"") -> 0.57931953 | N45: RONTA | O45: 0.27170886 | P45: 0.25120011 | Q45: 0.25129471 | R45: 0.25790647 | S45: 0.27543813 | T45: 0.29472804 | V45: 0.29201731 | W45: 0.099162492 | X45: 0.57931953 | Z45: RONTA | AA45: 0.27170886 | AB45: 0.23739537 | AC45: 0.19692233 | AD45: 0.19021326 | AE45: 0.1919368 | AF45: 0.19459883 | AH45: 0.29201731 | AI45: 0.099162492 | AJ45: 0.57931953
B47: Implied Market Cap (USDm) | F47: =F27*F21 -> 0 | G47: =G27*G21 -> 6428901.3 | H47: =H27*H21 -> 7291887 | N47: Implied Market Cap (USDm) | R47: =R27*R21 -> 0 | S47: =S27*S21 -> 8556715.9 | T47: =T27*T21 -> 10109949 | Z47: Implied Market Cap (USDm) | AD47: =AD27*AD21 -> 3582224.2 | AE47: =AE27*AE21 -> 3858125.6 | AF47: =AF27*AF21 -> 4082640.9
B48: (+) Net Debt & NCI | F48: =F38+Model!CH360 -> 113937.01 | G48: =G38+Model!CI360 -> 140269.72 | H48: =H38+Model!CJ360 -> 165242.67 | N48: (+) Net Debt & NCI | R48: =R38+Model!CH360 -> 128294.33 | S48: =S38+Model!CI360 -> 158870.25 | T48: =T38+Model!CJ360 -> 189659.51 | Z48: (+) Net Debt & NCI | AD48: =AD38+Model!CH360 -> 97429.36 | AE48: =AE38+Model!CI360 -> 117727.32 | AF48: =AF38+Model!CJ360 -> 134852.89
B49: Implied Enterprise Value (USDm) | F49: =F47+F48 -> 113937.01 | G49: =G47+G48 -> 6569171 | H49: =H47+H48 -> 7457129.7 | N49: Implied Enterprise Value (USDm) | R49: =R47+R48 -> 128294.33 | S49: =S47+S48 -> 8715586.1 | T49: =T47+T48 -> 10299608 | Z49: Implied Enterprise Value (USDm) | AD49: =AD47+AD48 -> 3679653.6 | AE49: =AE47+AE48 -> 3975852.9 | AF49: =AF47+AF48 -> 4217493.8
B50: Implied EV / Adjusted EBITDA (x) | F50: =IFERROR(F49/F35,"") -> 0.33979937 | G50: =IFERROR(G49/G35,"") -> 16.846839 | H50: =IFERROR(H49/H35,"") -> 16.874374 | N50: Implied EV / Adjusted EBITDA (x) | R50: =IFERROR(R49/R35,"") -> 0.349603 | S50: =IFERROR(S49/S35,"") -> 19.766385 | T50: =IFERROR(T49/T35,"") -> 19.891361 | Z50: Implied EV / Adjusted EBITDA (x) | AD50: =IFERROR(AD49/AD35,"") -> 12.820298 | AE50: =IFERROR(AE49/AE35,"") -> 12.551864 | AF50: =IFERROR(AF49/AF35,"") -> 12.436646

Sheet DCF
B2: DCF VALUATION — MICROSOFT CORPORATION (MSFT)
B4: 1. WACC BUILD
B5: Risk-free rate (US 10Y govt) | C5: 0.0425 | D5: Assumption (~US 10Y Treasury yield, Oct-2026; government rate sources not reachable from the build environment); update to market
B6: Equity risk premium | C6: 0.05 | D6: Assumption: US implied ERP ~4.5–5.5%
B7: Levered beta | C7: 1.05 | D7: Assumption: mega-cap software / cloud peers (ORCL, CRM, SAP, AMZN, GOOGL) ~0.9–1.2; capex intensity of the AI build-out adds operating leverage
B8: Cost of equity | C8: =C5+C7*C6 -> 0.095
B9: Pre-tax cost of debt | C9: 0.045 | D9: Assumption: AAA-rated issuer; finance-lease discount rate 4.5% (FY2026 10-K); senior notes carry ~1.2% net of capitalised interest
B10: Tax rate | C10: 0.19 | D10: Model FY2028E+ effective tax rate (FY26 19.4%; Q1 FY27 guided ~20%)
B11: After-tax cost of debt | C11: =C9*(1-C10) -> 0.03645
B12: Target D/V | C12: 0.02 | D12: Debt $40.3bn + finance leases $66.6bn vs ~$4.0trn market cap ($541 × ~7.45bn diluted shares): D/V ~2–3%
B13: WACC | C13: =C8*(1-C12)+C11*C12 -> 0.093829
B15: Valuation date (live) | C15: =TODAY() -> 2026-10-13 00:00:00 | D15: Periods = (30-Jun of fiscal year − today) / 365.25; cash flows assumed at fiscal year-end (30 June); FY2026A (ended 30-Jun-2026) is the base year
B16: 2. UNLEVERED FREE CASH FLOW BUILD (USDm)
D17: 2027E | E17: 2028E | F17: 2029E | G17: 2030E | H17: 2031E | I17: 2032E | J17: 2033E | K17: 2034E | L17: 2035E | M17: 2036E | N17: Terminal | P17: CAGR 27–31E | Q17: CAGR 27–36E
B18: Adj. EBIT (= adjusted operating income; amortization and SBC are expensed) | D18: =Model!CF246-Model!CF248 -> 180501.13 | E18: =Model!CG246-Model!CG248 -> 202794.15 | F18: =Model!CH246-Model!CH248 -> 233435.76 | G18: =Model!CI246-Model!CI248 -> 269519.72 | H18: =Model!CJ246-Model!CJ248 -> 306218.5 | I18: =H18*(1+I$26) -> 336840.35 | J18: =I18*(1+J$26) -> 367155.98 | K18: =J18*(1+K$26) -> 396528.46 | L18: =K18*(1+L$26) -> 424285.46 | M18: =L18*(1+M$26) -> 449742.58 | P18: =(H18/D18)^(1/(COLUMNS(D18:H18)-1))-1 -> 0.14126861 | Q18: =(M18/D18)^(1/(COLUMNS(D18:M18)-1))-1 -> 0.10676084
B19: × (1 − tax rate) | D19: =1-$C$10 -> 0.81 | E19: =1-$C$10 -> 0.81 | F19: =1-$C$10 -> 0.81 | G19: =1-$C$10 -> 0.81 | H19: =1-$C$10 -> 0.81 | I19: =1-$C$10 -> 0.81 | J19: =1-$C$10 -> 0.81 | K19: =1-$C$10 -> 0.81 | ... M19: =1-$C$10 -> 0.81
B20: NOPAT | D20: =D18*D19 -> 146205.92 | E20: =E18*E19 -> 164263.26 | F20: =F18*F19 -> 189082.96 | G20: =G18*G19 -> 218310.97 | H20: =H18*H19 -> 248036.99 | I20: =I18*I19 -> 272840.69 | J20: =J18*J19 -> 297396.35 | K20: =K18*K19 -> 321188.06 | ... M20: =M18*M19 -> 364291.49
B21: plus D&A (depreciation, amortization & other) | D21: =Model!CF204 -> 56319.92 | E21: =Model!CG204 -> 80380.309 | F21: =Model!CH204 -> 101870.94 | G21: =Model!CI204 -> 120415.23 | H21: =Model!CJ204 -> 135701.88 | I21: =H21*(1+I$26) -> 149272.07 | J21: =I21*(1+J$26) -> 162706.55 | K21: =J21*(1+K$26) -> 175723.08 | L21: =K21*(1+L$26) -> 188023.69 | M21: =L21*(1+M$26) -> 199305.11
B22: − Capex incl. finance-lease assets and acquisitions (M&A lever 2028E–31E) | D22: =Model!CF297+Model!CF298-Model!CF168 -> -200000 | E22: =Model!CG297+Model!CG298-Model!CG168 -> -207933.05 | F22: =Model!CH297+Model!CH298-Model!CH168 -> -213748.85 | G22: =Model!CI297+Model!CI298-Model!CI168 -> -212774.93 | H22: =Model!CJ297+Model!CJ298-Model!CJ168 -> -217943.67 | I22: =Model!CJ297*(1+I$26) -> -195061.38 | J22: =I22*(1+J$26) -> -212616.9 | K22: =J22*(1+K$26) -> -229626.25 | L22: =K22*(1+L$26) -> -245700.09 | M22: =L22*(1+M$26) -> -260442.1
B23: − Δ Working capital (CF statement) | D23: =Model!CF295 -> 6027.0618 | E23: =Model!CG295 -> 6905.1039 | F23: =Model!CH295 -> 7444.1451 | G23: =Model!CI295 -> 7550.3346 | H23: =Model!CJ295 -> 7535.4628 | I23: =H23*(1+I$26) -> 8289.0091 | J23: =I23*(1+J$26) -> 9035.0199 | K23: =J23*(1+K$26) -> 9757.8215 | L23: =K23*(1+L$26) -> 10440.869 | M23: =L23*(1+M$26) -> 11067.321
B24: Unlevered FCF | D24: =D20+D21+D22+D23 -> 8552.9008 | E24: =E20+E21+E22+E23 -> 43615.63 | F24: =F20+F21+F22+F23 -> 84649.202 | G24: =G20+G21+G22+G23 -> 133501.6 | H24: =H20+H21+H22+H23 -> 173330.66 | I24: =I20+I21+I22+I23 -> 235340.38 | J24: =J20+J21+J22+J23 -> 256521.02 | K24: =K20+K21+K22+K23 -> 277042.7 | ... M24: =M20+M21+M22+M23 -> 314221.83 | N24: =M24*(1+$C$27) -> 325219.59 | P24: =(H24/D24)^(1/(COLUMNS(D24:H24)-1))-1 -> 1.1217318 | Q24: =(M24/D24)^(1/(COLUMNS(D24:M24)-1))-1 -> 0.49245947
B25: Terminal Value (Gordon Growth) | N25: =N24/($C$13-$C$27) -> 5528219
B26: Fade-period growth (2032E–36E; 10.0% → 6.0% linear) | I26: 0.1 | J26: =I26+($M$26-$I$26)/4 -> 0.09 | K26: =J26+($M$26-$I$26)/4 -> 0.08 | L26: =K26+($M$26-$I$26)/4 -> 0.07 | M26: 0.06
B27: Terminal growth rate | C27: 0.035
B29: Discount period (years) | D29: =(DATE(2027,6,30)-$C$15)/365.25 -> 0.7118412 | E29: =(DATE(2028,6,30)-$C$15)/365.25 -> 1.7138946 | F29: =(DATE(2029,6,30)-$C$15)/365.25 -> 2.7132101 | G29: =(DATE(2030,6,30)-$C$15)/365.25 -> 3.7125257 | H29: =(DATE(2031,6,30)-$C$15)/365.25 -> 4.7118412 | I29: =(DATE(2032,6,30)-$C$15)/365.25 -> 5.7138946 | J29: =(DATE(2033,6,30)-$C$15)/365.25 -> 6.7132101 | K29: =(DATE(2034,6,30)-$C$15)/365.25 -> 7.7125257 | L29: =(DATE(2035,6,30)-$C$15)/365.25 -> 8.7118412 | M29: =(DATE(2036,6,30)-$C$15)/365.25 -> 9.7138946 | N29: =M29 -> 9.7138946
B30: Discount factor | D30: =1/(1+$C$13)^D29 -> 0.93815412 | E30: =1/(1+$C$13)^E29 -> 0.85752102 | F30: =1/(1+$C$13)^F29 -> 0.78401072 | G30: =1/(1+$C$13)^G29 -> 0.71680203 | H30: =1/(1+$C$13)^H29 -> 0.65535476 | I30: =1/(1+$C$13)^I29 -> 0.59902789 | J30: =1/(1+$C$13)^J29 -> 0.54767671 | K30: =1/(1+$C$13)^K29 -> 0.50072756 | ... N30: =1/(1+$C$13)^N29 -> 0.41845553
B31: PV of UFCF | D31: =D24*D30 -> 8023.9391 | E31: =E24*E30 -> 37401.32 | F31: =F24*F30 -> 66365.882 | G31: =G24*G30 -> 95694.221 | H31: =H24*H30 -> 113593.07 | I31: =I24*I30 -> 140975.45 | J31: =J24*J30 -> 140490.59 | K31: =K24*K30 -> 138722.92 | ... M31: =M24*M30 -> 131487.86 | N31: =N25*N30 -> 2313313.8
D32: Microsoft's operating income already deducts amortization of acquired intangibles and stock-based compensation (neither is adjusted out). D&A is added back in row 21. Row 22 deducts capital expenditures INCLUDING finance-lease assets (datacenters) because finance-lease liabilities are counted in net debt; it also includes the M&A lever in FY2028E–31E. Investment gains / losses (incl. OpenAI) are excluded from UFCF; the OpenAI stake and other equity investments (~$36bn carrying value) are not added back (conservative). The FY2027E capex peak (Q1 guidance over $50bn) depresses near-term UFCF.
B33: IMPLIED ROIC — invested capital roll-forward (USDm)
B34: Opening invested capital | D34: =Model!CA423 -> 472432 | E34: =D38 -> 610085.02 | F34: =E38 -> 730732.65 | G34: =F38 -> 835166.42 | H34: =G38 -> 919975.78 | I34: =H38 -> 994682.11 | J34: =I38 -> 1032182.4 | K34: =J38 -> 1073057.7 | L34: =K38 -> 1117203.1 | M34: =L38 -> 1164438.6
B35: plus Capex and acquisitions | D35: =-D22 -> 200000 | E35: =-E22 -> 207933.05 | F35: =-F22 -> 213748.85 | G35: =-G22 -> 212774.93 | H35: =-H22 -> 217943.67 | I35: =-I22 -> 195061.38 | J35: =-J22 -> 212616.9 | K35: =-K22 -> 229626.25 | ... M35: =-M22 -> 260442.1
B36: less DD&A | D36: =-D21 -> -56319.92 | E36: =-E21 -> -80380.309 | F36: =-F21 -> -101870.94 | G36: =-G21 -> -120415.23 | H36: =-H21 -> -135701.88 | I36: =-I21 -> -149272.07 | J36: =-J21 -> -162706.55 | K36: =-K21 -> -175723.08 | ... M36: =-M21 -> -199305.11
B37: plus Δ Working capital investment | D37: =-D23 -> -6027.0618 | E37: =-E23 -> -6905.1039 | F37: =-F23 -> -7444.1451 | G37: =-G23 -> -7550.3346 | H37: =-H23 -> -7535.4628 | I37: =-I23 -> -8289.0091 | J37: =-J23 -> -9035.0199 | K37: =-K23 -> -9757.8215 | ... M37: =-M23 -> -11067.321
B38: Closing invested capital | D38: =SUM(D34:D37) -> 610085.02 | E38: =SUM(E34:E37) -> 730732.65 | F38: =SUM(F34:F37) -> 835166.42 | G38: =SUM(G34:G37) -> 919975.78 | H38: =SUM(H34:H37) -> 994682.11 | I38: =SUM(I34:I37) -> 1032182.4 | J38: =SUM(J34:J37) -> 1073057.7 | K38: =SUM(K34:K37) -> 1117203.1 | ... M38: =SUM(M34:M37) -> 1214508.3
B39: NOPAT (row 20) | D39: =D20 -> 146205.92 | E39: =E20 -> 164263.26 | F39: =F20 -> 189082.96 | G39: =G20 -> 218310.97 | H39: =H20 -> 248036.99 | I39: =I20 -> 272840.69 | J39: =J20 -> 297396.35 | K39: =K20 -> 321188.06 | ... M39: =M20 -> 364291.49
B40: Implied ROIC (NOPAT / avg. invested capital) | D40: =IFERROR(D39/AVERAGE(D34,D38),"") -> 0.27012216 | E40: =IFERROR(E39/AVERAGE(E34,E38),"") -> 0.24501954 | F40: =IFERROR(F39/AVERAGE(F34,F38),"") -> 0.24150083 | G40: =IFERROR(G39/AVERAGE(G34,G38),"") -> 0.24876727 | H40: =IFERROR(H39/AVERAGE(H34,H38),"") -> 0.25909275 | I40: =IFERROR(I39/AVERAGE(I34,I38),"") -> 0.26922439 | J40: =IFERROR(J39/AVERAGE(J34,J38),"") -> 0.28252962 | K40: =IFERROR(K39/AVERAGE(K34,K38),"") -> 0.29328749 | ... M40: =IFERROR(M39/AVERAGE(M34,M38),"") -> 0.30626282
B41: Reinvestment rate (net investment / NOPAT) | D41: =IFERROR(SUM(D35:D37)/D39,"") -> 0.94150099 | E41: =IFERROR(SUM(E35:E37)/E39,"") -> 0.73447727 | F41: =IFERROR(SUM(F35:F37)/F39,"") -> 0.55231714 | G41: =IFERROR(SUM(G35:G37)/G39,"") -> 0.38847963 | H41: =IFERROR(SUM(H35:H37)/H39,"") -> 0.30119026 | I41: =IFERROR(SUM(I35:I37)/I39,"") -> 0.13744395 | J41: =IFERROR(SUM(J35:J37)/J39,"") -> 0.13744395 | K41: =IFERROR(SUM(K35:K37)/K39,"") -> 0.13744395 | ... M41: =IFERROR(SUM(M35:M37)/M39,"") -> 0.13744395
B42: Implied terminal RONIC (g / reinvestment rate) | N42: =IFERROR($C$27/M41,"") -> 0.25464926
D43: Opening IC = Model FY2026A book IC (equity + net debt incl. finance leases at 30-Jun-2026), rolled forward with capex + M&A − D&A + ΔWC.
B44: 3. VALUATION SUMMARY
B45: Sum of PV (explicit + fade) | C45: =SUM(D31:M31) -> 1008464.4
B46: PV of Terminal Value | C46: =N31 -> 2313313.8
B47: Enterprise Value | C47: =C45+C46 -> 3321778.2
B48: Less: Net debt incl. finance leases + NCI (Model FY2026A year end, 30-Jun-2026) | C48: =Model!CA443+Model!CA360 -> 30045 | D48: MSFT: no noncontrolling interests; debt $40.3bn + finance leases $66.6bn − cash & short-term investments $76.8bn at the base-year end.
B49: Equity Value | C49: =C47-C48 -> 3291733.2
B50: Diluted shares (m, Model FY2026A period end) | C50: =Model!CA450 -> 7443
B51: Implied share price ($) | C51: =C49/C50 -> 442.25893
B52: Current share price ($) | C52: =Model!CA449 -> 541
B53: Implied upside / (downside) | C53: =C51/C52-1 -> -0.18251584
B54: Required discount to DCF value for target IRR | C54: =1-((1+C13)/(1+H54))^H55 -> 0.13949226 | D54: vs. current | E54: Target IRR | H54: 0.15
B55: Max entry price for target IRR ($) | C55: =C51*(1-C54) -> 380.56723 | D55: =C55/C52-1 -> -0.29654856 | E55: Years for discount to close | H55: 3
B58: 4. SENSITIVITY: IMPLIED PRICE ($) — WACC × Terminal Growth
D60: WACC →
B61: Terminal growth ↓ | D61: =F61-0.01 -> 0.083829 | E61: =F61-0.005 -> 0.088829 | F61: =$C$13 -> 0.093829 | G61: =F61+0.005 -> 0.098829 | H61: =F61+0.01 -> 0.103829
B62: =B64-0.01 -> 0.025 | D62: {=IFERROR((SUMPRODUCT($D$24:$M$24/(1+D$61)^$D$29:$M$29)+($M$24*(1+$B62)/(D$61-$B62))/(1+D$61)^$M$29-$C$48)/$C$50,"")} -> 476.16757 | E62: {=IFERROR((SUMPRODUCT($D$24:$M$24/(1+E$61)^$D$29:$M$29)+($M$24*(1+$B62)/(E$61-$B62))/(1+E$61)^$M$29-$C$48)/$C$50,"")} -> 432.07243 | F62: {=IFERROR((SUMPRODUCT($D$24:$M$24/(1+F$61)^$D$29:$M$29)+($M$24*(1+$B62)/(F$61-$B62))/(1+F$61)^$M$29-$C$48)/$C$50,"")} -> 394.53632 | G62: {=IFERROR((SUMPRODUCT($D$24:$M$24/(1+G$61)^$D$29:$M$29)+($M$24*(1+$B62)/(G$61-$B62))/(1+G$61)^$M$29-$C$48)/$C$50,"")} -> 362.22193 | H62: {=IFERROR((SUMPRODUCT($D$24:$M$24/(1+H$61)^$D$29:$M$29)+($M$24*(1+$B62)/(H$61-$B62))/(1+H$61)^$M$29-$C$48)/$C$50,"")} -> 334.13141
B63: =B64-0.005 -> 0.03 | D63: {=IFERROR((SUMPRODUCT($D$24:$M$24/(1+D$61)^$D$29:$M$29)+($M$24*(1+$B63)/(D$61-$B63))/(1+D$61)^$M$29-$C$48)/$C$50,"")} -> 509.2202 | E63: {=IFERROR((SUMPRODUCT($D$24:$M$24/(1+E$61)^$D$29:$M$29)+($M$24*(1+$B63)/(E$61-$B63))/(1+E$61)^$M$29-$C$48)/$C$50,"")} -> 458.85092 | F63: {=IFERROR((SUMPRODUCT($D$24:$M$24/(1+F$61)^$D$29:$M$29)+($M$24*(1+$B63)/(F$61-$B63))/(1+F$61)^$M$29-$C$48)/$C$50,"")} -> 416.52847 | G63: {=IFERROR((SUMPRODUCT($D$24:$M$24/(1+G$61)^$D$29:$M$29)+($M$24*(1+$B63)/(G$61-$B63))/(1+G$61)^$M$29-$C$48)/$C$50,"")} -> 380.49448 | H63: {=IFERROR((SUMPRODUCT($D$24:$M$24/(1+H$61)^$D$29:$M$29)+($M$24*(1+$B63)/(H$61-$B63))/(1+H$61)^$M$29-$C$48)/$C$50,"")} -> 349.46711
B64: =$C$27 -> 0.035 | D64: {=IFERROR((SUMPRODUCT($D$24:$M$24/(1+D$61)^$D$29:$M$29)+($M$24*(1+$B64)/(D$61-$B64))/(1+D$61)^$M$29-$C$48)/$C$50,"")} -> 549.0419 | E64: {=IFERROR((SUMPRODUCT($D$24:$M$24/(1+E$61)^$D$29:$M$29)+($M$24*(1+$B64)/(E$61-$B64))/(1+E$61)^$M$29-$C$48)/$C$50,"")} -> 490.60415 | F64: {=IFERROR((SUMPRODUCT($D$24:$M$24/(1+F$61)^$D$29:$M$29)+($M$24*(1+$B64)/(F$61-$B64))/(1+F$61)^$M$29-$C$48)/$C$50,"")} -> 442.25893 | G64: {=IFERROR((SUMPRODUCT($D$24:$M$24/(1+G$61)^$D$29:$M$29)+($M$24*(1+$B64)/(G$61-$B64))/(1+G$61)^$M$29-$C$48)/$C$50,"")} -> 401.62977 | H64: {=IFERROR((SUMPRODUCT($D$24:$M$24/(1+H$61)^$D$29:$M$29)+($M$24*(1+$B64)/(H$61-$B64))/(1+H$61)^$M$29-$C$48)/$C$50,"")} -> 367.03089
B65: =B64+0.005 -> 0.04 | D65: {=IFERROR((SUMPRODUCT($D$24:$M$24/(1+D$61)^$D$29:$M$29)+($M$24*(1+$B65)/(D$61-$B65))/(1+D$61)^$M$29-$C$48)/$C$50,"")} -> 597.94929 | E65: {=IFERROR((SUMPRODUCT($D$24:$M$24/(1+E$61)^$D$29:$M$29)+($M$24*(1+$B65)/(E$61-$B65))/(1+E$61)^$M$29-$C$48)/$C$50,"")} -> 528.86031 | F65: {=IFERROR((SUMPRODUCT($D$24:$M$24/(1+F$61)^$D$29:$M$29)+($M$24*(1+$B65)/(F$61-$B65))/(1+F$61)^$M$29-$C$48)/$C$50,"")} -> 472.76943 | G65: {=IFERROR((SUMPRODUCT($D$24:$M$24/(1+G$61)^$D$29:$M$29)+($M$24*(1+$B65)/(G$61-$B65))/(1+G$61)^$M$29-$C$48)/$C$50,"")} -> 426.35772 | H65: {=IFERROR((SUMPRODUCT($D$24:$M$24/(1+H$61)^$D$29:$M$29)+($M$24*(1+$B65)/(H$61-$B65))/(1+H$61)^$M$29-$C$48)/$C$50,"")} -> 387.34637
B66: =B64+0.01 -> 0.045 | D66: {=IFERROR((SUMPRODUCT($D$24:$M$24/(1+D$61)^$D$29:$M$29)+($M$24*(1+$B66)/(D$61-$B66))/(1+D$61)^$M$29-$C$48)/$C$50,"")} -> 659.45227 | E66: {=IFERROR((SUMPRODUCT($D$24:$M$24/(1+E$61)^$D$29:$M$29)+($M$24*(1+$B66)/(E$61-$B66))/(1+E$61)^$M$29-$C$48)/$C$50,"")} -> 575.84498 | F66: {=IFERROR((SUMPRODUCT($D$24:$M$24/(1+F$61)^$D$29:$M$29)+($M$24*(1+$B66)/(F$61-$B66))/(1+F$61)^$M$29-$C$48)/$C$50,"")} -> 509.52837 | G66: {=IFERROR((SUMPRODUCT($D$24:$M$24/(1+G$61)^$D$29:$M$29)+($M$24*(1+$B66)/(G$61-$B66))/(1+G$61)^$M$29-$C$48)/$C$50,"")} -> 455.67947 | H66: {=IFERROR((SUMPRODUCT($D$24:$M$24/(1+H$61)^$D$29:$M$29)+($M$24*(1+$B66)/(H$61-$B66))/(1+H$61)^$M$29-$C$48)/$C$50,"")} -> 411.11516
B69: 5. REVERSE DCF
B70: To solve for the market-implied path: Data ▸ What-If Analysis ▸ Goal Seek — set C51 to the current price (C52) by changing C27 (terminal growth) or the fade-period growth inputs (I26:M26).
B72: 6. MAUBOUSSIN EV / NOPAT — TWO-STAGE FRAMEWORK
B73: EV/NOPAT = 1/r + [g × (1 − r/ROIIC) / (r × (r − g))] × [1 − ((1+g)/(1+r))^N]
B74: Formula source: Mauboussin & Rappaport, "Expectations Investing" (2021); Counterpoint Global, "What Does a Price-Earnings Multiple Mean?" (2020).
B76: Input | C76: Value | D76: Rationale (Microsoft characteristics)
B77: r (Cost of capital / WACC) | C77: =$C$13 -> 0.093829 | D77: Linked from Section 1 WACC build
B78: g (NOPAT growth, Stage 1) | C78: 0.12 | D78: Model adjusted operating income CAGR FY2026–31E: Azure / Microsoft 365 cloud growth with margins absorbing the AI-capex depreciation ramp → ~12% NOPAT growth
B79: ROIIC (Return on incremental invested capital) | C79: 0.25 | D79: Software and cloud platforms with high switching costs; incremental AI infrastructure returns are lower than legacy software returns (capex-heavy), so RONIC fades toward ~25%
B80: N (Years of value creation / CAP) | C80: 20 | D80: Installed base across enterprise productivity, cloud infrastructure and developer tools sustains a long competitive-advantage period; risk from AI-capacity overbuild and pricing
B82: Calculation | C82: Value
B83: Steady-state component: 1 / r | C83: =1/C77 -> 10.657686
B84: Value-creation factor: 1 − r / ROIIC | C84: =1-C77/C79 -> 0.624684
B85: Growth multiplier: g × (1 − r/ROIIC) / (r × (r − g)) | C85: =C78*C84/(C77*(C77-C78)) -> -30.527007
B86: Time decay: 1 − ((1+g)/(1+r))^N | C86: =1-((1+C78)/(1+C77))^C80 -> -0.60461847
B87: PVGO component (growth value) | C87: =C85*C86 -> 18.457192
B88: Mauboussin EV / NOPAT (steady-state + PVGO) | C88: =C83+C87 -> 29.114878
B90: VALUATION — Applied to FY2029E NOPAT | C90: USDm
B91: FY2029E Adj. EBIT (adjusted operating income) | C91: =Model!CH246-Model!CH248 -> 233435.76
B92: Tax rate (from WACC build) | C92: =$C$10 -> 0.19
B93: FY2029E NOPAT | C93: =C91*(1-C92) -> 189082.96
B94: × Mauboussin EV/NOPAT multiple | C94: =C88 -> 29.114878
B95: Implied Enterprise Value (FY2029E basis) | C95: =C93*C94 -> 5505127.4
B96: Less: FY2028E year-end net debt incl. finance leases + NCI (Model) | C96: =Model!CG443+Model!CG360 -> 87531.628
B97: Implied Equity Value | C97: =C95-C96 -> 5417595.8
B98: Diluted shares FY2029E (m, Model) | C98: =Model!CH450 -> 7254.5468
B99: Implied share price FY2029 ($) | C99: =C97/C98 -> 746.78624
B101: Current share price ($) | C101: =C52 -> 541
B102: Implied upside / (downside) | C102: =C99/C101-1 -> 0.38038123
B104: MARKET-IMPLIED EV/NOPAT TODAY | C104: USDm
B105: Current market cap (spot × diluted shares) | C105: =C52*C50 -> 4026663
B106: Plus: FY2026A year-end net debt incl. finance leases + NCI | C106: =C48 -> 30045
B107: Implied Enterprise Value (today) | C107: =C105+C106 -> 4056708
B108: MSFT market-implied EV/NOPAT (on FY2029E NOPAT) | C108: =C107/C93 -> 21.454646
B110: Multiple gap (Mauboussin − Market) | C110: =C88-C108 -> 7.6602322
B111: Implied re-rating headroom | C111: =C88/C108-1 -> 0.35704305

Sheet Charts
B2: Microsoft Corporation — Operating Performance (FY2012–FY2026) and Model Forecast (FY2027E–FY2031E)
B3: USDm · fiscal years ended 30 June · Linked to Model. Bars = contribution of each FY27 segment to total revenue growth (pp; restated history FY2026 only). Adjusted EBITDA = model definition; operating income = GAAP. ROIC / RONTA on adjusted operating income.
C7: 2012 | D7: 2013 | E7: 2014 | F7: 2015 | G7: 2016 | H7: 2017 | I7: 2018 | J7: 2019 | K7: 2020 | L7: 2021 | M7: 2022 | N7: 2023 | O7: 2024 | P7: 2025 | Q7: 2026 | R7: 2027E | S7: 2028E | T7: 2029E | U7: 2030E | V7: 2031E
B8: Agents and Infra contribution to growth (pp) | C8: =IFERROR(Model!I66+0,0) -> 0 | D8: =IFERROR(Model!N66+0,0) -> 0 | E8: =IFERROR(Model!S66+0,0) -> 0 | F8: =IFERROR(Model!X66+0,0) -> 0 | G8: =IFERROR(Model!AC66+0,0) -> 0 | H8: =IFERROR(Model!AH66+0,0) -> 0 | I8: =IFERROR(Model!AM66+0,0) -> 0 | J8: =IFERROR(Model!AR66+0,0) -> 0 | K8: =IFERROR(Model!AW66+0,0) -> 0 | L8: =IFERROR(Model!BB66+0,0) -> 0 | M8: =IFERROR(Model!BG66+0,0) -> 0 | N8: =IFERROR(Model!BL66+0,0) -> 0 | O8: =IFERROR(Model!BQ66+0,0) -> 0 | P8: =IFERROR(Model!BV66+0,0) -> 0 | Q8: =IFERROR(Model!CA66+0,0) -> 0.17515015 | R8: =IFERROR(Model!CF66+0,0) -> 0.18456055 | S8: =IFERROR(Model!CG66+0,0) -> 0.16362346 | T8: =IFERROR(Model!CH66+0,0) -> 0.14965848 | U8: =IFERROR(Model!CI66+0,0) -> 0.13144624 | V8: =IFERROR(Model!CJ66+0,0) -> 0.11498229
B9: Devices and Consumer contribution to growth (pp) | C9: =IFERROR(Model!I67+0,0) -> 0 | D9: =IFERROR(Model!N67+0,0) -> 0 | E9: =IFERROR(Model!S67+0,0) -> 0 | F9: =IFERROR(Model!X67+0,0) -> 0 | G9: =IFERROR(Model!AC67+0,0) -> 0 | H9: =IFERROR(Model!AH67+0,0) -> 0 | I9: =IFERROR(Model!AM67+0,0) -> 0 | J9: =IFERROR(Model!AR67+0,0) -> 0 | K9: =IFERROR(Model!AW67+0,0) -> 0 | L9: =IFERROR(Model!BB67+0,0) -> 0 | M9: =IFERROR(Model!BG67+0,0) -> 0 | N9: =IFERROR(Model!BL67+0,0) -> 0 | O9: =IFERROR(Model!BQ67+0,0) -> 0 | P9: =IFERROR(Model!BV67+0,0) -> 0 | Q9: =IFERROR(Model!CA67+0,0) -> 0.002736721 | R9: =IFERROR(Model!CF67+0,0) -> -0.011954788 | S9: =IFERROR(Model!CG67+0,0) -> 0.0063525802 | T9: =IFERROR(Model!CH67+0,0) -> 0.006556495 | U9: =IFERROR(Model!CI67+0,0) -> 0.0054653123 | V9: =IFERROR(Model!CJ67+0,0) -> 0.0050865901
C11: =C7 -> 2012 | D11: =D7 -> 2013 | E11: =E7 -> 2014 | F11: =F7 -> 2015 | G11: =G7 -> 2016 | H11: =H7 -> 2017 | I11: =I7 -> 2018 | J11: =J7 -> 2019 | ... V11: =V7 -> 2031E
B12: Adjusted EBITDA | C12: =Model!I242 -> 31463 | D12: =Model!N242 -> 30712 | E12: =Model!S242 -> 32971 | F12: =Model!X242 -> 34129 | G12: =Model!AC242 -> 34557 | H12: =Model!AH242 -> 38117 | I12: =Model!AM242 -> 45319 | J12: =Model!AR242 -> 54641 | K12: =Model!AW242 -> 65755 | L12: =Model!BB242 -> 81602 | M12: =Model!BG242 -> 97843 | N12: =Model!BL242 -> 103555 | O12: =Model!BQ242 -> 131720 | P12: =Model!BV242 -> 162681 | Q12: =Model!CA242 -> 193771 | R12: =Model!CF242 -> 236821.05 | S12: =Model!CG242 -> 283174.46 | T12: =Model!CH242 -> 335306.7 | U12: =Model!CI242 -> 389934.94 | V12: =Model!CJ242 -> 441920.38
B13: Operating income (GAAP) | C13: =Model!I190 -> 21763 | D13: =Model!N190 -> 26764 | E13: =Model!S190 -> 27759 | F13: =Model!X190 -> 18161 | G13: =Model!AC190 -> 20182 | H13: =Model!AH190 -> 22326 | I13: =Model!AM190 -> 35058 | J13: =Model!AR190 -> 42959 | K13: =Model!AW190 -> 52959 | L13: =Model!BB190 -> 69916 | M13: =Model!BG190 -> 83383 | N13: =Model!BL190 -> 88523 | O13: =Model!BQ190 -> 109433 | P13: =Model!BV190 -> 128528 | Q13: =Model!CA190 -> 155237 | R13: =Model!CF190 -> 180501.13 | S13: =Model!CG190 -> 202794.15 | T13: =Model!CH190 -> 233435.76 | U13: =Model!CI190 -> 269519.72 | V13: =Model!CJ190 -> 306218.5
B14: Adj. EBITDA Margin % | C14: =Model!I282 -> 0.42677319 | D14: =Model!N282 -> 0.39450732 | E14: =Model!S282 -> 0.37970587 | F14: =Model!X282 -> 0.364704 | G14: =Model!AC282 -> 0.40502813 | H14: =Model!AH282 -> 0.42375764 | I14: =Model!AM282 -> 0.41064697 | J14: =Model!AR282 -> 0.43419976 | K14: =Model!AW282 -> 0.45977695 | L14: =Model!BB282 -> 0.4854719 | M14: =Model!BG282 -> 0.49348363 | N14: =Model!BL282 -> 0.48866291 | O14: =Model!BQ282 -> 0.53736507 | P14: =Model!BV282 -> 0.57744814 | Q14: =Model!CA282 -> 0.58393076 | R14: =Model!CF282 -> 0.60861249 | S14: =Model!CG282 -> 0.62180556 | T14: =Model!CH282 -> 0.63641002 | U14: =Model!CI282 -> 0.65058886 | V14: =Model!CJ282 -> 0.65791435
B15: Operating Margin % | C15: =Model!I283 -> 0.2951996 | D15: =Model!N283 -> 0.34379375 | E15: =Model!S283 -> 0.31968261 | F15: =Model!X283 -> 0.19406925 | G15: =Model!AC283 -> 0.23654477 | H15: =Model!AH283 -> 0.24820456 | I15: =Model!AM283 -> 0.31766945 | J15: =Model!AR283 -> 0.3413698 | K15: =Model!AW283 -> 0.37030381 | L15: =Model!BB283 -> 0.41594879 | M15: =Model!BG283 -> 0.42055278 | N15: =Model!BL283 -> 0.41772881 | O15: =Model!BQ283 -> 0.446443 | P15: =Model!BV283 -> 0.45621956 | Q15: =Model!CA283 -> 0.46780818 | R15: =Model!CF283 -> 0.46387449 | S15: =Model!CG283 -> 0.44530333 | T15: =Model!CH283 -> 0.44305961 | U15: =Model!CI283 -> 0.44968148 | V15: =Model!CJ283 -> 0.45588652
C17: =C7 -> 2012 | D17: =D7 -> 2013 | E17: =E7 -> 2014 | F17: =F7 -> 2015 | G17: =G7 -> 2016 | H17: =H7 -> 2017 | I17: =I7 -> 2018 | J17: =J7 -> 2019 | ... V17: =V7 -> 2031E
B18: ROIC | C18: =IFERROR(Model!I426+0,NA()) -> 1.4231642 | D18: =IFERROR(Model!N426+0,NA()) -> 1.2433639 | E18: =IFERROR(Model!S426+0,NA()) -> 0.82431134 | F18: =IFERROR(Model!X426+0,NA()) -> 0.98469995 | G18: =IFERROR(Model!AC426+0,NA()) -> 1.9092252 | H18: =IFERROR(Model!AH426+0,NA()) -> 0.95483782 | I18: =IFERROR(Model!AM426+0,NA()) -> 0.54008605 | J18: =IFERROR(Model!AR426+0,NA()) -> 0.81639383 | K18: =IFERROR(Model!AW426+0,NA()) -> 0.80982987 | L18: =IFERROR(Model!BB426+0,NA()) -> 0.7317009 | M18: =IFERROR(Model!BG426+0,NA()) -> 0.57286165 | N18: =IFERROR(Model!BL426+0,NA()) -> 0.45629179 | O18: =IFERROR(Model!BQ426+0,NA()) -> 0.32932995 | P18: =IFERROR(Model!BV426+0,NA()) -> 0.31300234 | Q18: =IFERROR(Model!CA426+0,NA()) -> 0.26485678 | R18: =IFERROR(Model!CF426+0,NA()) -> 0.23668981 | S18: =IFERROR(Model!CG426+0,NA()) -> 0.22479256 | T18: =IFERROR(Model!CH426+0,NA()) -> 0.22640154 | U18: =IFERROR(Model!CI426+0,NA()) -> 0.23730078 | V18: =IFERROR(Model!CJ426+0,NA()) -> 0.24936307
B19: RONTA | C19: =IFERROR(Model!I437+0,NA()) -> 0.29685551 | D19: =IFERROR(Model!N437+0,NA()) -> 0.24133174 | E19: =IFERROR(Model!S437+0,NA()) -> 0.21667863 | F19: =IFERROR(Model!X437+0,NA()) -> 0.16560883 | G19: =IFERROR(Model!AC437+0,NA()) -> 0.18910502 | H19: =IFERROR(Model!AH437+0,NA()) -> 0.18998608 | I19: =IFERROR(Model!AM437+0,NA()) -> 0.099162492 | J19: =IFERROR(Model!AR437+0,NA()) -> 0.22319594 | K19: =IFERROR(Model!AW437+0,NA()) -> 0.24246802 | L19: =IFERROR(Model!BB437+0,NA()) -> 0.30789074 | M19: =IFERROR(Model!BG437+0,NA()) -> 0.3740541 | N19: =IFERROR(Model!BL437+0,NA()) -> 0.30816171 | O19: =IFERROR(Model!BQ437+0,NA()) -> 0.35936222 | P19: =IFERROR(Model!BV437+0,NA()) -> 0.31260123 | Q19: =IFERROR(Model!CA437+0,NA()) -> 0.27170886 | R19: =IFERROR(Model!CF437+0,NA()) -> 0.24292535 | S19: =IFERROR(Model!CG437+0,NA()) -> 0.22995176 | T19: =IFERROR(Model!CH437+0,NA()) -> 0.23116165 | U19: =IFERROR(Model!CI437+0,NA()) -> 0.24212752 | V19: =IFERROR(Model!CJ437+0,NA()) -> 0.25440195
B20: Adj. EBITDA margin % | C20: =IFERROR(Model!I282+0,NA()) -> 0.42677319 | D20: =IFERROR(Model!N282+0,NA()) -> 0.39450732 | E20: =IFERROR(Model!S282+0,NA()) -> 0.37970587 | F20: =IFERROR(Model!X282+0,NA()) -> 0.364704 | G20: =IFERROR(Model!AC282+0,NA()) -> 0.40502813 | H20: =IFERROR(Model!AH282+0,NA()) -> 0.42375764 | I20: =IFERROR(Model!AM282+0,NA()) -> 0.41064697 | J20: =IFERROR(Model!AR282+0,NA()) -> 0.43419976 | K20: =IFERROR(Model!AW282+0,NA()) -> 0.45977695 | L20: =IFERROR(Model!BB282+0,NA()) -> 0.4854719 | M20: =IFERROR(Model!BG282+0,NA()) -> 0.49348363 | N20: =IFERROR(Model!BL282+0,NA()) -> 0.48866291 | O20: =IFERROR(Model!BQ282+0,NA()) -> 0.53736507 | P20: =IFERROR(Model!BV282+0,NA()) -> 0.57744814 | Q20: =IFERROR(Model!CA282+0,NA()) -> 0.58393076 | R20: =IFERROR(Model!CF282+0,NA()) -> 0.60861249 | S20: =IFERROR(Model!CG282+0,NA()) -> 0.62180556 | T20: =IFERROR(Model!CH282+0,NA()) -> 0.63641002 | U20: =IFERROR(Model!CI282+0,NA()) -> 0.65058886 | V20: =IFERROR(Model!CJ282+0,NA()) -> 0.65791435
B21: FCF margin % | C21: =IFERROR(Model!I317+0,NA()) -> 0.39771849 | D21: =IFERROR(Model!N317+0,NA()) -> 0.31568806 | E21: =IFERROR(Model!S317+0,NA()) -> 0.30801654 | F21: =IFERROR(Model!X317+0,NA()) -> 0.24723231 | G21: =IFERROR(Model!AC317+0,NA()) -> 0.29280356 | H21: =IFERROR(Model!AH317+0,NA()) -> 0.34883824 | I21: =IFERROR(Model!AM317+0,NA()) -> 0.29224357 | J21: =IFERROR(Model!AR317+0,NA()) -> 0.30402962 | K21: =IFERROR(Model!AW317+0,NA()) -> 0.3162885 | L21: =IFERROR(Model!BB317+0,NA()) -> 0.33386083 | M21: =IFERROR(Model!BG317+0,NA()) -> 0.32858728 | N21: =IFERROR(Model!BL317+0,NA()) -> 0.28065498 | O21: =IFERROR(Model!BQ317+0,NA()) -> 0.30218014 | P21: =IFERROR(Model!BV317+0,NA()) -> 0.2541885 | Q21: =IFERROR(Model!CA317+0,NA()) -> 0.20186597 | R21: =IFERROR(Model!CF317+0,NA()) -> 0.14383838 | S21: =IFERROR(Model!CG317+0,NA()) -> 0.21386553 | T21: =IFERROR(Model!CH317+0,NA()) -> 0.26765766 | U21: =IFERROR(Model!CI317+0,NA()) -> 0.31929916 | V21: =IFERROR(Model!CJ317+0,NA()) -> 0.34810919
