Workbook

Sheet Model
CF1: SCENARIO SWITCH ▼ (Bull / Base / Bear) — drives all scenario-linked forecast drivers
B2: Old Dominion Freight Line, Inc. (Nasdaq: ODFL) — 3-Statement Financial Model | CF2: Base
B3: US GAAP as reported · USD millions (per-share data in USD; shares in millions, split-adjusted; tons, shipments & miles in thousands) · Source: ODFL Forms 10-K / 10-Q, Form 8-K earnings releases (Ex. 99.1) and mid-quarter updates, SEC XBRL companyfacts, SEC EDGAR CIK 0000878927 (investor-relations releases are the same documents as filed on EDGAR)
B4: Basis notes: calendar fiscal year; single reportable segment (LTL); all periods as originally reported. Stock splits 3-for-2 Aug-2010, Sep-2012, Mar-2020 and 2-for-1 Mar-2024 (earlier shares / per-share data restated). Operating statistics on the total-tons basis to 2013, LTL from 2014; LTL / other services revenue split from 2019. ODFL publishes no non-GAAP measures or annual guidance: EBITDA / Adjusted EBITDA / adjusted EPS are model definitions; Q3/26E anchored to the 3-Sep-26 mid-quarter update, Q4/26E and the Q3/Q4 operating ratio on 2016–25 seasonality.
CH5: Forecast | CI5: Historical | CJ5: Historical | CK5: Historical
B6: (USDm) | C6: 2006 | D6: 2007 | E6: 2008 | F6: 2009 | G6: 2010 | H6: 2011 | I6: 2012 | J6: Q1/13 | K6: Q2/13 | L6: Q3/13 | M6: Q4/13 | N6: 2013 | O6: Q1/14 | P6: Q2/14 | Q6: Q3/14 | R6: Q4/14 | S6: 2014 | T6: Q1/15 | U6: Q2/15 | V6: Q3/15 | W6: Q4/15 | X6: 2015 | Y6: Q1/16 | Z6: Q2/16 | AA6: Q3/16 | AB6: Q4/16 | AC6: 2016 | AD6: Q1/17 | AE6: Q2/17 | AF6: Q3/17 | AG6: Q4/17 | AH6: 2017 | AI6: Q1/18 | AJ6: Q2/18 | AK6: Q3/18 | AL6: Q4/18 | AM6: 2018 | AN6: Q1/19 | AO6: Q2/19 | AP6: Q3/19 | AQ6: Q4/19 | AR6: 2019 | AS6: Q1/20 | AT6: Q2/20 | AU6: Q3/20 | AV6: Q4/20 | AW6: 2020 | AX6: Q1/21 | AY6: Q2/21 | AZ6: Q3/21 | BA6: Q4/21 | BB6: 2021 | BC6: Q1/22 | BD6: Q2/22 | BE6: Q3/22 | BF6: Q4/22 | BG6: 2022 | BH6: Q1/23 | BI6: Q2/23 | BJ6: Q3/23 | BK6: Q4/23 | BL6: 2023 | BM6: Q1/24 | BN6: Q2/24 | BO6: Q3/24 | BP6: Q4/24 | BQ6: 2024 | BR6: Q1/25 | BS6: Q2/25 | BT6: Q3/25 | BU6: Q4/25 | BV6: 2025 | BW6: Q1/26 | BX6: Q2/26 | BY6: Q3/26E | BZ6: Q4/26E | CA6: 2026E | CB6: 2027E | CC6: 2028E | CD6: 2029E | CE6: 2030E | CF6: Modelling Notes | CH6: 5Y CAGR | CI6: 5Y CAGR | CJ6: 10Y CAGR | CK6: 19Y CAGR
CH7: 25-'30 | CI7: 20-'25 | CJ7: 15-'25 | CK7: 06-'25
B8: LTL OPERATING BUILD — TONS PER DAY × WORK DAYS × REVENUE PER HUNDREDWEIGHT (EX-FUEL + FUEL SURCHARGE) · OTHER SERVICES · NETWORK | CF8: LTL OPERATING BUILD — modelling logic (tons/day × work days → tons; × 20 cwt × revenue/cwt → LTL revenue (statistics basis) → reported revenue → operating ratio → EPS)
CN9: SCENARIO INPUT TABLE — driver assumptions per Bull / Base / Bear | CO9: Bull | CP9: Base | CQ9: Bear | CR9: Bull / Bear = Base + Δ (Δ inputs on each block header). FY26 block: Q3/26E anchored to the 3-Sep-26 mid-quarter update; Q4/26E and the Q3/Q4 operating ratio from 2016–25 seasonality (best / average / worst).
B10: LTL volume — tonnage, shipments & weight per shipment (operating statistics as published; total tons & shipments to 2013, LTL from 2014) | CF10: VOLUME — modelling logic
B11: Work days | C11: 252 | D11: 253 | E11: 254 | F11: 253 | G11: 252 | H11: 253 | I11: 254 | J11: 63 | K11: 64 | L11: 64 | M11: 63 | N11: 254 | O11: 63 | P11: 64 | Q11: 64 | R11: 63 | S11: 254 | T11: 63 | U11: 64 | V11: 64 | W11: 63 | X11: 254 | Y11: 64 | Z11: 64 | AA11: 64 | AB11: 62 | AC11: 254 | AD11: 64 | AE11: 64 | AF11: 63 | AG11: 62 | AH11: 253 | AI11: 64 | AJ11: 64 | AK11: 63 | AL11: 62 | AM11: 253 | AN11: 63 | AO11: 64 | AP11: 64 | AQ11: 62 | AR11: 253 | AS11: 64 | AT11: 64 | AU11: 64 | AV11: 62 | AW11: 254 | AX11: 63 | AY11: 64 | AZ11: 64 | BA11: 61 | BB11: 252 | BC11: 64 | BD11: 64 | BE11: 64 | BF11: 61 | BG11: 253 | BH11: 64 | BI11: 64 | BJ11: 63 | BK11: 61 | BL11: 252 | BM11: 64 | BN11: 64 | BO11: 64 | BP11: 62 | BQ11: 254 | BR11: 63 | BS11: 64 | BT11: 64 | BU11: 62 | BV11: 253 | BW11: 63 | BX11: 64 | BY11: 64 | BZ11: 62 | CA11: =SUM(BW11,BX11,BY11,BZ11) | CB11: 252 | CC11: 253 | CD11: 253 | CE11: 253 | CF11: Published in the releases from 2012 (Q4) / 2013; earlier years per the ODFL calendar (weekdays less New Year, Memorial Day, July 4, Labor Day, Thanksgiving + Friday, Christmas Eve & Day — reproduces every published count 2012–26). Q3/26E 64, Q4/26E 62; 2027E–30E 252 / 253 / 253 / 253. | CN11: FY26 calibration — Q3/26E anchored to the 3-Sep-26 mid-quarter update; seasonality 2016–25 (formulas on the historical columns) | CO11: Bull | CP11: Base | CQ11: Bear | CR11: ODFL gives no revenue / EPS guidance. Bull / Base / Bear = best / average / worst historical sequential change, 2016–2025 (Q2→Q3 and Q3→Q4).
B12: LTL tons per day (total tons per day to 2013) | C12: 19281.746 | D12: 20833.992 | E12: 21830.709 | F12: 19375.494 | G12: 22444.444 | H12: 25284.585 | I12: 27066.929 | J12: 27253.968 | K12: 29359.375 | L12: 30062.5 | M12: 29619.048 | N12: 29074.803 | O12: 26666.667 | P12: 29109.375 | Q12: 30406.25 | R12: 30190.476 | S12: 29098.425 | T12: 29714.286 | U12: 31750 | V12: 32421.875 | W12: 31095.238 | X12: 31251.969 | Y12: 30060 | Z12: 31640 | AA12: 32016 | AB12: 31177 | AC12: 31224 | AD12: 30781 | AE12: 33563 | AF12: 34762 | AG12: 35661 | AH12: 33672 | AI12: 35531 | AJ12: 38468.75 | AK12: 37571.429 | AL12: 36693.548 | AM12: 37071.146 | AN12: 35016 | AO12: 36031 | AP12: 35609 | AQ12: 35048.387 | AR12: 35430.83 | AS12: 33641 | AT12: 31688 | AU12: 36078 | AV12: 36758 | AW12: 34528 | AX12: 37010 | AY12: 40600 | AZ12: 41020 | BA12: 42020 | BB12: 40153 | BC12: 41454 | BD12: 41746 | BE12: 39941 | BF12: 38195 | BG12: 40359 | BH12: 36540 | BI12: 35878 | BJ12: 37181 | BK12: 37419 | BL12: 36745 | BM12: 35380 | BN12: 36560 | BO12: 35408 | BP12: 34351 | BQ12: 35433 | BR12: 33135 | BS12: 33178 | BT12: 32231 | BU12: 30691 | BV12: 32319 | BW12: 30584 | BX12: 31804 | BY12: =BT12*(1+$CP$19) | BZ12: =BY12*(1+CHOOSE(MATCH($CF$2,{"Bull","Base","Bear"},0),$CO$14,$CP$14,$CQ$14)) | CA12: =IFERROR(CA15*1000/CA11,"") | CB12: =CA12*(1+CB13) | CC12: =CB12*(1+CC13) | CD12: =CC12*(1+CD13) | CE12: =CD12*(1+CE13) | CF12: Q3/26E: Q3/25 × (1 + Aug-26 tons/day y/y from the 3-Sep-26 update). Q4/26E: Q3/26E × (1 + 2016–25 Q3→Q4 sequential change: best / average / worst by scenario). 2027E+: prior year × (1 + scenario lever). Derived as tons ÷ work days where not published (2014–15, 2018–19). | CH12: =IFERROR((CE12/BV12)^(1/5)-1,"n/m") | CI12: =IFERROR((BV12/AW12)^(1/5)-1,"n/m") | CJ12: =IFERROR((BV12/X12)^(1/10)-1,"n/m") | CK12: =IFERROR((BV12/C12)^(1/19)-1,"n/m") | CN12: Q2→Q3 operating-ratio change (best / average / worst, 2016–25) | CO12: =MIN(AA92,AF92,AK92,AP92,AU92,AZ92,BE92,BJ92,BO92,BT92) | CP12: =AVERAGE(AA92,AF92,AK92,AP92,AU92,AZ92,BE92,BJ92,BO92,BT92) | CQ12: =MAX(AA92,AF92,AK92,AP92,AU92,AZ92,BE92,BJ92,BO92,BT92) | CR12: Applied to the Q2/26 operating ratio (70.1%). Best case = 2020 (−332 bps, COVID rebound); excluding 2020 the best is −166 bps (2023).
B13: y/y % | D13: =IF(AND(ISNUMBER(D12),ISNUMBER(C12)),IFERROR(D12/C12-1,""),"") | E13: =IF(AND(ISNUMBER(E12),ISNUMBER(D12)),IFERROR(E12/D12-1,""),"") | F13: =IF(AND(ISNUMBER(F12),ISNUMBER(E12)),IFERROR(F12/E12-1,""),"") | G13: =IF(AND(ISNUMBER(G12),ISNUMBER(F12)),IFERROR(G12/F12-1,""),"") | H13: =IF(AND(ISNUMBER(H12),ISNUMBER(G12)),IFERROR(H12/G12-1,""),"") | I13: =IF(AND(ISNUMBER(I12),ISNUMBER(H12)),IFERROR(I12/H12-1,""),"") | N13: =IF(AND(ISNUMBER(N12),ISNUMBER(I12)),IFERROR(N12/I12-1,""),"") | O13: =IF(AND(ISNUMBER(O12),ISNUMBER(J12)),IFERROR(O12/J12-1,""),"") | P13: =IF(AND(ISNUMBER(P12),ISNUMBER(K12)),IFERROR(P12/K12-1,""),"") | Q13: =IF(AND(ISNUMBER(Q12),ISNUMBER(L12)),IFERROR(Q12/L12-1,""),"") | R13: =IF(AND(ISNUMBER(R12),ISNUMBER(M12)),IFERROR(R12/M12-1,""),"") | S13: =IF(AND(ISNUMBER(S12),ISNUMBER(N12)),IFERROR(S12/N12-1,""),"") | T13: =IF(AND(ISNUMBER(T12),ISNUMBER(O12)),IFERROR(T12/O12-1,""),"") | U13: =IF(AND(ISNUMBER(U12),ISNUMBER(P12)),IFERROR(U12/P12-1,""),"") | ... CA13: =IF(AND(ISNUMBER(CA12),ISNUMBER(BV12)),IFERROR(CA12/BV12-1,""),"") | CB13: =CHOOSE(MATCH($CF$2,{"Bull","Base","Bear"},0),$CO$31,$CP$31,$CQ$31) | CC13: =CHOOSE(MATCH($CF$2,{"Bull","Base","Bear"},0),$CO$32,$CP$32,$CQ$32) | CD13: =CHOOSE(MATCH($CF$2,{"Bull","Base","Bear"},0),$CO$33,$CP$33,$CQ$33) | CE13: =CHOOSE(MATCH($CF$2,{"Bull","Base","Bear"},0),$CO$34,$CP$34,$CQ$34) | CF13: 2027E–2030E: scenario lever TPD (Bull / Base / Bear table →). | CH13: =IFERROR(AVERAGE(CA13,CB13,CC13,CD13,CE13),"n/m") | CI13: =IFERROR(AVERAGE(BB13,BG13,BL13,BQ13,BV13),"n/m") | CJ13: =IFERROR(AVERAGE(AC13,AH13,AM13,AR13,AW13,BB13,BG13,BL13,BQ13,BV13),"n/m") | CK13: =IFERROR(AVERAGE(C13,D13,E13,F13,G13,H13,I13,N13,S13,X13,AC13,AH13,AM13,AR13,AW13,BB13,BG13,BL13,BQ13,BV13),"n/m") | CN13: Q3→Q4 operating-ratio change (best / average / worst, 2016–25) | CO13: =MIN(AB92,AG92,AL92,AQ92,AV92,BA92,BF92,BK92,BP92,BU92) | CP13: =AVERAGE(AB92,AG92,AL92,AQ92,AV92,BA92,BF92,BK92,BP92,BU92) | CQ13: =MAX(AB92,AG92,AL92,AQ92,AV92,BA92,BF92,BK92,BP92,BU92) | CR13: Applied to the Q3/26E operating ratio. Q4 is seasonally weaker (fewer work days, winter weather, holiday freight mix).
B14: sequential % (vs prior quarter) | K14: =IF(AND(ISNUMBER(K12),ISNUMBER(J12)),IFERROR(K12/J12-1,""),"") | L14: =IF(AND(ISNUMBER(L12),ISNUMBER(K12)),IFERROR(L12/K12-1,""),"") | M14: =IF(AND(ISNUMBER(M12),ISNUMBER(L12)),IFERROR(M12/L12-1,""),"") | O14: =IF(AND(ISNUMBER(O12),ISNUMBER(M12)),IFERROR(O12/M12-1,""),"") | P14: =IF(AND(ISNUMBER(P12),ISNUMBER(O12)),IFERROR(P12/O12-1,""),"") | Q14: =IF(AND(ISNUMBER(Q12),ISNUMBER(P12)),IFERROR(Q12/P12-1,""),"") | R14: =IF(AND(ISNUMBER(R12),ISNUMBER(Q12)),IFERROR(R12/Q12-1,""),"") | T14: =IF(AND(ISNUMBER(T12),ISNUMBER(R12)),IFERROR(T12/R12-1,""),"") | U14: =IF(AND(ISNUMBER(U12),ISNUMBER(T12)),IFERROR(U12/T12-1,""),"") | V14: =IF(AND(ISNUMBER(V12),ISNUMBER(U12)),IFERROR(V12/U12-1,""),"") | W14: =IF(AND(ISNUMBER(W12),ISNUMBER(V12)),IFERROR(W12/V12-1,""),"") | Y14: =IF(AND(ISNUMBER(Y12),ISNUMBER(W12)),IFERROR(Y12/W12-1,""),"") | Z14: =IF(AND(ISNUMBER(Z12),ISNUMBER(Y12)),IFERROR(Z12/Y12-1,""),"") | AA14: =IF(AND(ISNUMBER(AA12),ISNUMBER(Z12)),IFERROR(AA12/Z12-1,""),"") | AB14: =IF(AND(ISNUMBER(AB12),ISNUMBER(AA12)),IFERROR(AB12/AA12-1,""),"") | AD14: =IF(AND(ISNUMBER(AD12),ISNUMBER(AB12)),IFERROR(AD12/AB12-1,""),"") | AE14: =IF(AND(ISNUMBER(AE12),ISNUMBER(AD12)),IFERROR(AE12/AD12-1,""),"") | AF14: =IF(AND(ISNUMBER(AF12),ISNUMBER(AE12)),IFERROR(AF12/AE12-1,""),"") | AG14: =IF(AND(ISNUMBER(AG12),ISNUMBER(AF12)),IFERROR(AG12/AF12-1,""),"") | AI14: =IF(AND(ISNUMBER(AI12),ISNUMBER(AG12)),IFERROR(AI12/AG12-1,""),"") | AJ14: =IF(AND(ISNUMBER(AJ12),ISNUMBER(AI12)),IFERROR(AJ12/AI12-1,""),"") | AK14: =IF(AND(ISNUMBER(AK12),ISNUMBER(AJ12)),IFERROR(AK12/AJ12-1,""),"") | AL14: =IF(AND(ISNUMBER(AL12),ISNUMBER(AK12)),IFERROR(AL12/AK12-1,""),"") | AN14: =IF(AND(ISNUMBER(AN12),ISNUMBER(AL12)),IFERROR(AN12/AL12-1,""),"") | AO14: =IF(AND(ISNUMBER(AO12),ISNUMBER(AN12)),IFERROR(AO12/AN12-1,""),"") | AP14: =IF(AND(ISNUMBER(AP12),ISNUMBER(AO12)),IFERROR(AP12/AO12-1,""),"") | AQ14: =IF(AND(ISNUMBER(AQ12),ISNUMBER(AP12)),IFERROR(AQ12/AP12-1,""),"") | AS14: =IF(AND(ISNUMBER(AS12),ISNUMBER(AQ12)),IFERROR(AS12/AQ12-1,""),"") | AT14: =IF(AND(ISNUMBER(AT12),ISNUMBER(AS12)),IFERROR(AT12/AS12-1,""),"") | AU14: =IF(AND(ISNUMBER(AU12),ISNUMBER(AT12)),IFERROR(AU12/AT12-1,""),"") | AV14: =IF(AND(ISNUMBER(AV12),ISNUMBER(AU12)),IFERROR(AV12/AU12-1,""),"") | AX14: =IF(AND(ISNUMBER(AX12),ISNUMBER(AV12)),IFERROR(AX12/AV12-1,""),"") | AY14: =IF(AND(ISNUMBER(AY12),ISNUMBER(AX12)),IFERROR(AY12/AX12-1,""),"") | AZ14: =IF(AND(ISNUMBER(AZ12),ISNUMBER(AY12)),IFERROR(AZ12/AY12-1,""),"") | BA14: =IF(AND(ISNUMBER(BA12),ISNUMBER(AZ12)),IFERROR(BA12/AZ12-1,""),"") | BC14: =IF(AND(ISNUMBER(BC12),ISNUMBER(BA12)),IFERROR(BC12/BA12-1,""),"") | BD14: =IF(AND(ISNUMBER(BD12),ISNUMBER(BC12)),IFERROR(BD12/BC12-1,""),"") | BE14: =IF(AND(ISNUMBER(BE12),ISNUMBER(BD12)),IFERROR(BE12/BD12-1,""),"") | BF14: =IF(AND(ISNUMBER(BF12),ISNUMBER(BE12)),IFERROR(BF12/BE12-1,""),"") | BH14: =IF(AND(ISNUMBER(BH12),ISNUMBER(BF12)),IFERROR(BH12/BF12-1,""),"") | BI14: =IF(AND(ISNUMBER(BI12),ISNUMBER(BH12)),IFERROR(BI12/BH12-1,""),"") | BJ14: =IF(AND(ISNUMBER(BJ12),ISNUMBER(BI12)),IFERROR(BJ12/BI12-1,""),"") | BK14: =IF(AND(ISNUMBER(BK12),ISNUMBER(BJ12)),IFERROR(BK12/BJ12-1,""),"") | BM14: =IF(AND(ISNUMBER(BM12),ISNUMBER(BK12)),IFERROR(BM12/BK12-1,""),"") | BN14: =IF(AND(ISNUMBER(BN12),ISNUMBER(BM12)),IFERROR(BN12/BM12-1,""),"") | BO14: =IF(AND(ISNUMBER(BO12),ISNUMBER(BN12)),IFERROR(BO12/BN12-1,""),"") | BP14: =IF(AND(ISNUMBER(BP12),ISNUMBER(BO12)),IFERROR(BP12/BO12-1,""),"") | BR14: =IF(AND(ISNUMBER(BR12),ISNUMBER(BP12)),IFERROR(BR12/BP12-1,""),"") | BS14: =IF(AND(ISNUMBER(BS12),ISNUMBER(BR12)),IFERROR(BS12/BR12-1,""),"") | BT14: =IF(AND(ISNUMBER(BT12),ISNUMBER(BS12)),IFERROR(BT12/BS12-1,""),"") | BU14: =IF(AND(ISNUMBER(BU12),ISNUMBER(BT12)),IFERROR(BU12/BT12-1,""),"") | BW14: =IF(AND(ISNUMBER(BW12),ISNUMBER(BU12)),IFERROR(BW12/BU12-1,""),"") | BX14: =IF(AND(ISNUMBER(BX12),ISNUMBER(BW12)),IFERROR(BX12/BW12-1,""),"") | BY14: =IF(AND(ISNUMBER(BY12),ISNUMBER(BX12)),IFERROR(BY12/BX12-1,""),"") | BZ14: =IF(AND(ISNUMBER(BZ12),ISNUMBER(BY12)),IFERROR(BZ12/BY12-1,""),"") | CN14: Q3→Q4 LTL tons per day, sequential % (best / average / worst) | CO14: =MAX(AB14,AG14,AL14,AQ14,AV14,BA14,BF14,BK14,BP14,BU14) | CP14: =AVERAGE(AB14,AG14,AL14,AQ14,AV14,BA14,BF14,BK14,BP14,BU14) | CQ14: =MIN(AB14,AG14,AL14,AQ14,AV14,BA14,BF14,BK14,BP14,BU14) | CR14: Applied to Q3/26E tons per day.
B15: LTL tons (thousands; total tons to 2013) | C15: 4859 | D15: 5271 | E15: 5545 | F15: 4902 | G15: 5656 | H15: 6397 | I15: 6875 | J15: 1717 | K15: 1879 | L15: 1924 | M15: 1866 | N15: 7385 | O15: 1680 | P15: 1863 | Q15: 1946 | R15: 1902 | S15: 7391 | T15: 1872 | U15: 2032 | V15: 2075 | W15: 1959 | X15: 7938 | Y15: 1924 | Z15: 2025 | AA15: 2049 | AB15: 1933 | AC15: 7931 | AD15: 1970 | AE15: 2148 | AF15: 2190 | AG15: 2211 | AH15: 8519 | AI15: 2274 | AJ15: 2462 | AK15: 2367 | AL15: 2275 | AM15: 9379 | AN15: 2206 | AO15: 2306 | AP15: 2279 | AQ15: 2173 | AR15: 8964 | AS15: 2153 | AT15: 2028 | AU15: 2309 | AV15: 2279 | AW15: 8770 | AX15: 2332 | AY15: 2598 | AZ15: 2625 | BA15: 2563 | BB15: 10119 | BC15: 2653 | BD15: 2672 | BE15: 2556 | BF15: 2330 | BG15: 10211 | BH15: 2339 | BI15: 2296 | BJ15: 2342 | BK15: 2283 | BL15: 9260 | BM15: 2264 | BN15: 2340 | BO15: 2266 | BP15: 2130 | BQ15: 9000 | BR15: 2087 | BS15: 2123 | BT15: 2063 | BU15: 1903 | BV15: 8177 | BW15: 1927 | BX15: 2035 | BY15: =BY12*BY11/1000 | BZ15: =BZ12*BZ11/1000 | CA15: =SUM(BW15,BX15,BY15,BZ15) | CB15: =CB12*CB11/1000 | CC15: =CC12*CC11/1000 | CD15: =CD12*CD11/1000 | CE15: =CE12*CE11/1000 | CH15: =IFERROR((CE15/BV15)^(1/5)-1,"n/m") | CI15: =IFERROR((BV15/AW15)^(1/5)-1,"n/m") | CJ15: =IFERROR((BV15/X15)^(1/10)-1,"n/m") | CK15: =IFERROR((BV15/C15)^(1/19)-1,"n/m") | CN15: Q3→Q4 LTL revenue/cwt ex fuel, sequential % (best / average / worst) | CO15: =MAX(AB30,AG30,AL30,AQ30,AV30,BA30,BF30,BK30,BP30,BU30) | CP15: =AVERAGE(AB30,AG30,AL30,AQ30,AV30,BA30,BF30,BK30,BP30,BU30) | CQ15: =MIN(AB30,AG30,AL30,AQ30,AV30,BA30,BF30,BK30,BP30,BU30) | CR15: Applied to Q3/26E ex-fuel yield.
B16: y/y % | D16: =IF(AND(ISNUMBER(D15),ISNUMBER(C15)),IFERROR(D15/C15-1,""),"") | E16: =IF(AND(ISNUMBER(E15),ISNUMBER(D15)),IFERROR(E15/D15-1,""),"") | F16: =IF(AND(ISNUMBER(F15),ISNUMBER(E15)),IFERROR(F15/E15-1,""),"") | G16: =IF(AND(ISNUMBER(G15),ISNUMBER(F15)),IFERROR(G15/F15-1,""),"") | H16: =IF(AND(ISNUMBER(H15),ISNUMBER(G15)),IFERROR(H15/G15-1,""),"") | I16: =IF(AND(ISNUMBER(I15),ISNUMBER(H15)),IFERROR(I15/H15-1,""),"") | N16: =IF(AND(ISNUMBER(N15),ISNUMBER(I15)),IFERROR(N15/I15-1,""),"") | O16: =IF(AND(ISNUMBER(O15),ISNUMBER(J15)),IFERROR(O15/J15-1,""),"") | P16: =IF(AND(ISNUMBER(P15),ISNUMBER(K15)),IFERROR(P15/K15-1,""),"") | Q16: =IF(AND(ISNUMBER(Q15),ISNUMBER(L15)),IFERROR(Q15/L15-1,""),"") | R16: =IF(AND(ISNUMBER(R15),ISNUMBER(M15)),IFERROR(R15/M15-1,""),"") | S16: =IF(AND(ISNUMBER(S15),ISNUMBER(N15)),IFERROR(S15/N15-1,""),"") | T16: =IF(AND(ISNUMBER(T15),ISNUMBER(O15)),IFERROR(T15/O15-1,""),"") | U16: =IF(AND(ISNUMBER(U15),ISNUMBER(P15)),IFERROR(U15/P15-1,""),"") | ... CA16: =IF(AND(ISNUMBER(CA15),ISNUMBER(BV15)),IFERROR(CA15/BV15-1,""),"") | CB16: =IF(AND(ISNUMBER(CB15),ISNUMBER(CA15)),IFERROR(CB15/CA15-1,""),"") | CC16: =IF(AND(ISNUMBER(CC15),ISNUMBER(CB15)),IFERROR(CC15/CB15-1,""),"") | CD16: =IF(AND(ISNUMBER(CD15),ISNUMBER(CC15)),IFERROR(CD15/CC15-1,""),"") | CE16: =IF(AND(ISNUMBER(CE15),ISNUMBER(CD15)),IFERROR(CE15/CD15-1,""),"") | CN16: 2H/26 share repurchases ($m) | CO16: 400 | CP16: 300 | CQ16: 150 | CR16: 1H/26 $239.7m; $1.31bn remaining under the $3.0bn 2023 programme at 30-Jun-26. FY25 $730m, FY24 $967m.
B17: LTL weight per shipment (lbs.) | C17: 1512 | D17: 1558 | E17: 1657 | F17: 1705 | G17: 1788 | H17: 1763 | I17: 1771 | J17: 1787 | K17: 1777 | L17: 1773 | M17: 1801 | N17: 1784 | O17: 1627 | P17: 1637 | Q17: 1617 | R17: 1636 | S17: 1629 | T17: 1598 | U17: 1574 | V17: 1543 | W17: 1558 | X17: 1567 | Y17: 1546 | Z17: 1559 | AA17: 1551 | AB17: 1597 | AC17: 1563 | AD17: 1561 | AE17: 1567 | AF17: 1579 | AG17: 1640 | AH17: 1587 | AI17: 1631 | AJ17: 1615 | AK17: 1557 | AL17: 1586 | AM17: 1597 | AN17: 1566 | AO17: 1553 | AP17: 1545 | AQ17: 1580 | AR17: 1560 | AS17: 1586 | AT17: 1636 | AU17: 1615 | AV17: 1619 | AW17: 1614 | AX17: 1606 | AY17: 1571 | AZ17: 1538 | BA17: 1575 | BB17: 1571 | BC17: 1589 | BD17: 1572 | BE17: 1561 | BF17: 1565 | BG17: 1572 | BH17: 1550 | BI17: 1527 | BJ17: 1497 | BK17: 1511 | BL17: 1521 | BM17: 1508 | BN17: 1509 | BO17: 1476 | BP17: 1501 | BQ17: 1499 | BR17: 1487 | BS17: 1478 | BT17: 1458 | BU17: 1486 | BV17: 1477 | BW17: 1491 | BX17: 1503 | BY17: =BT17*$BX$17/$BS$17 | BZ17: =BU17*$BX$17/$BS$17 | CA17: =IFERROR(CA15*2000/CA19,"") | CB17: =CA17 | CC17: =CB17 | CD17: =CC17 | CE17: =CD17 | CF17: Q3/Q4-26E: prior-year quarter × Q2/26 y/y change (+1.7%; Aug-26 +1.7%). 2027E+ flat.
B18: y/y % | D18: =IF(AND(ISNUMBER(D17),ISNUMBER(C17)),IFERROR(D17/C17-1,""),"") | E18: =IF(AND(ISNUMBER(E17),ISNUMBER(D17)),IFERROR(E17/D17-1,""),"") | F18: =IF(AND(ISNUMBER(F17),ISNUMBER(E17)),IFERROR(F17/E17-1,""),"") | G18: =IF(AND(ISNUMBER(G17),ISNUMBER(F17)),IFERROR(G17/F17-1,""),"") | H18: =IF(AND(ISNUMBER(H17),ISNUMBER(G17)),IFERROR(H17/G17-1,""),"") | I18: =IF(AND(ISNUMBER(I17),ISNUMBER(H17)),IFERROR(I17/H17-1,""),"") | N18: =IF(AND(ISNUMBER(N17),ISNUMBER(I17)),IFERROR(N17/I17-1,""),"") | O18: =IF(AND(ISNUMBER(O17),ISNUMBER(J17)),IFERROR(O17/J17-1,""),"") | P18: =IF(AND(ISNUMBER(P17),ISNUMBER(K17)),IFERROR(P17/K17-1,""),"") | Q18: =IF(AND(ISNUMBER(Q17),ISNUMBER(L17)),IFERROR(Q17/L17-1,""),"") | R18: =IF(AND(ISNUMBER(R17),ISNUMBER(M17)),IFERROR(R17/M17-1,""),"") | S18: =IF(AND(ISNUMBER(S17),ISNUMBER(N17)),IFERROR(S17/N17-1,""),"") | T18: =IF(AND(ISNUMBER(T17),ISNUMBER(O17)),IFERROR(T17/O17-1,""),"") | U18: =IF(AND(ISNUMBER(U17),ISNUMBER(P17)),IFERROR(U17/P17-1,""),"") | ... CA18: =IF(AND(ISNUMBER(CA17),ISNUMBER(BV17)),IFERROR(CA17/BV17-1,""),"") | CB18: =IF(AND(ISNUMBER(CB17),ISNUMBER(CA17)),IFERROR(CB17/CA17-1,""),"") | CC18: =IF(AND(ISNUMBER(CC17),ISNUMBER(CB17)),IFERROR(CC17/CB17-1,""),"") | CD18: =IF(AND(ISNUMBER(CD17),ISNUMBER(CC17)),IFERROR(CD17/CC17-1,""),"") | CE18: =IF(AND(ISNUMBER(CE17),ISNUMBER(CD17)),IFERROR(CE17/CD17-1,""),"") | CN18: FY26 point estimates & Q3/26E anchors (all cases)
B19: LTL shipments (thousands; total shipments to 2013) | C19: 6428 | D19: 6765 | E19: 6691 | F19: 5750 | G19: 6327 | H19: 7256 | I19: 7765 | J19: 1922 | K19: 2115 | L19: 2170 | M19: 2072 | N19: 8279 | O19: 2065 | P19: 2276 | Q19: 2407 | R19: 2325 | S19: 9073 | T19: 2344 | U19: 2582 | V19: 2689 | W19: 2515 | X19: 10129 | Y19: 2489 | Z19: 2597 | AA19: 2641 | AB19: 2421 | AC19: 10148 | AD19: 2523 | AE19: 2742 | AF19: 2774 | AG19: 2696 | AH19: 10736 | AI19: 2788 | AJ19: 3049 | AK19: 3042 | AL19: 2870 | AM19: 11748 | AN19: 2818 | AO19: 2970 | AP19: 2951 | AQ19: 2751 | AR19: 11491 | AS19: 2716 | AT19: 2478 | AU19: 2859 | AV19: 2816 | AW19: 10869 | AX19: 2904 | AY19: 3307 | AZ19: 3413 | BA19: 3256 | BB19: 12880 | BC19: 3340 | BD19: 3398 | BE19: 3274 | BF19: 2977 | BG19: 12989 | BH19: 3018 | BI19: 3008 | BJ19: 3129 | BK19: 3021 | BL19: 12176 | BM19: 3004 | BN19: 3100 | BO19: 3070 | BP19: 2837 | BQ19: 12011 | BR19: 2808 | BS19: 2874 | BT19: 2829 | BU19: 2561 | BV19: 11072 | BW19: 2585 | BX19: 2709 | BY19: =IFERROR(BY15*2000/BY17,"") | BZ19: =IFERROR(BZ15*2000/BZ17,"") | CA19: =SUM(BW19,BX19,BY19,BZ19) | CB19: =IFERROR(CB15*2000/CB17,"") | CC19: =IFERROR(CC15*2000/CC17,"") | CD19: =IFERROR(CD15*2000/CD17,"") | CE19: =IFERROR(CE15*2000/CE17,"") | CH19: =IFERROR((CE19/BV19)^(1/5)-1,"n/m") | CI19: =IFERROR((BV19/AW19)^(1/5)-1,"n/m") | CJ19: =IFERROR((BV19/X19)^(1/10)-1,"n/m") | CK19: =IFERROR((BV19/C19)^(1/19)-1,"n/m") | CN19: Q3/26E LTL tons per day y/y (Aug-26, 3-Sep-26 update) | CP19: -0.009 | CR19: August 2026 LTL tons per day −0.9% y/y (shipments/day −2.4%, weight/shipment +1.7%). July not separately disclosed; Q2/26 −4.1%.
B20: LTL shipments per day | C20: 25507.937 | D20: 26739.13 | E20: 26342.52 | F20: 22727.273 | G20: 25107.143 | H20: 28679.842 | I20: 30570.866 | J20: 30507.937 | K20: 33046.875 | L20: 33906.25 | M20: 32888.889 | N20: 32594.488 | O20: 32777.778 | P20: 35562.5 | Q20: 37609.375 | R20: 36904.762 | S20: 35720.472 | T20: 37206.349 | U20: 40343.75 | V20: 42015.625 | W20: 39920.635 | X20: 39877.953 | Y20: 38890.625 | Z20: 40578.125 | AA20: 41265.625 | AB20: 39048.387 | AC20: 39952.756 | AD20: 39421.875 | AE20: 42843.75 | AF20: 44031.746 | AG20: 43483.871 | AH20: 42434.783 | AI20: 43562.5 | AJ20: 47640.625 | AK20: 48285.714 | AL20: 46290.323 | AM20: 46434.783 | AN20: 44730 | AO20: 46406 | AP20: 46109 | AQ20: 44370.968 | AR20: 45418.972 | AS20: 42438 | AT20: 38719 | AU20: 44672 | AV20: 45419 | AW20: 42791 | AX20: 46090 | AY20: 51672 | AZ20: 53335 | BA20: 53374 | BB20: 51111 | BC20: 52190 | BD20: 53096 | BE20: 51162 | BF20: 48798 | BG20: 51341 | BH20: 47155 | BI20: 46998 | BJ20: 49670 | BK20: 49520 | BL20: 48317 | BM20: 46931 | BN20: 48444 | BO20: 47967 | BP20: 45763 | BQ20: 47288 | BR20: 44566 | BS20: 44907 | BT20: 44201 | BU20: 41308 | BV20: 43762 | BW20: 41037 | BX20: 42332 | BY20: =IFERROR(BY19*1000/BY11,"") | BZ20: =IFERROR(BZ19*1000/BZ11,"") | CA20: =IFERROR(CA19*1000/CA11,"") | CB20: =IFERROR(CB19*1000/CB11,"") | CC20: =IFERROR(CC19*1000/CC11,"") | CD20: =IFERROR(CD19*1000/CD11,"") | CE20: =IFERROR(CE19*1000/CE11,"") | CN20: Q3/26E LTL revenue/cwt ex fuel y/y (Jul–Aug QTD) | CP20: 0.048 | CR20: 3-Sep-26 update: quarter-to-date +4.8%.
B21: y/y % | D21: =IF(AND(ISNUMBER(D20),ISNUMBER(C20)),IFERROR(D20/C20-1,""),"") | E21: =IF(AND(ISNUMBER(E20),ISNUMBER(D20)),IFERROR(E20/D20-1,""),"") | F21: =IF(AND(ISNUMBER(F20),ISNUMBER(E20)),IFERROR(F20/E20-1,""),"") | G21: =IF(AND(ISNUMBER(G20),ISNUMBER(F20)),IFERROR(G20/F20-1,""),"") | H21: =IF(AND(ISNUMBER(H20),ISNUMBER(G20)),IFERROR(H20/G20-1,""),"") | I21: =IF(AND(ISNUMBER(I20),ISNUMBER(H20)),IFERROR(I20/H20-1,""),"") | N21: =IF(AND(ISNUMBER(N20),ISNUMBER(I20)),IFERROR(N20/I20-1,""),"") | O21: =IF(AND(ISNUMBER(O20),ISNUMBER(J20)),IFERROR(O20/J20-1,""),"") | P21: =IF(AND(ISNUMBER(P20),ISNUMBER(K20)),IFERROR(P20/K20-1,""),"") | Q21: =IF(AND(ISNUMBER(Q20),ISNUMBER(L20)),IFERROR(Q20/L20-1,""),"") | R21: =IF(AND(ISNUMBER(R20),ISNUMBER(M20)),IFERROR(R20/M20-1,""),"") | S21: =IF(AND(ISNUMBER(S20),ISNUMBER(N20)),IFERROR(S20/N20-1,""),"") | T21: =IF(AND(ISNUMBER(T20),ISNUMBER(O20)),IFERROR(T20/O20-1,""),"") | U21: =IF(AND(ISNUMBER(U20),ISNUMBER(P20)),IFERROR(U20/P20-1,""),"") | ... CA21: =IF(AND(ISNUMBER(CA20),ISNUMBER(BV20)),IFERROR(CA20/BV20-1,""),"") | CB21: =IF(AND(ISNUMBER(CB20),ISNUMBER(CA20)),IFERROR(CB20/CA20-1,""),"") | CC21: =IF(AND(ISNUMBER(CC20),ISNUMBER(CB20)),IFERROR(CC20/CB20-1,""),"") | CD21: =IF(AND(ISNUMBER(CD20),ISNUMBER(CC20)),IFERROR(CD20/CC20-1,""),"") | CE21: =IF(AND(ISNUMBER(CE20),ISNUMBER(CD20)),IFERROR(CE20/CD20-1,""),"") | CN21: Q3/26E LTL revenue/cwt incl. fuel y/y (Jul–Aug QTD) | CP21: 0.113 | CR21: 3-Sep-26 update: quarter-to-date +11.3% (fuel surcharge per cwt implied).
B22: Average length of haul (miles) | C22: 934 | D22: 935 | E22: 901 | F22: 928 | G22: 948 | H22: 952 | I22: 941 | J22: 935 | K22: 940 | L22: 938 | M22: 930 | N22: 936 | O22: 929 | P22: 927 | Q22: 929 | R22: 928 | S22: 928 | T22: 928 | U22: 928 | V22: 927 | W22: 927 | X22: 928 | Y22: 935 | Z22: 929 | AA22: 925 | AB22: 922 | AC22: 928 | AD22: 920 | AE22: 917 | AF22: 919 | AG22: 914 | AH22: 917 | AI22: 914 | AJ22: 915 | AK22: 920 | AL22: 923 | AM22: 918 | AN22: 918 | AO22: 917 | AP22: 918 | AQ22: 915 | AR22: 917 | AS22: 919 | AT22: 919 | AU22: 933 | AV22: 927 | AW22: 925 | AX22: 928 | AY22: 930 | AZ22: 940 | BA22: 944 | BB22: 935 | BC22: 939 | BD22: 934 | BE22: 932 | BF22: 932 | BG22: 934 | BH22: 925 | BI22: 925 | BJ22: 927 | BK22: 925 | BL22: 925 | BM22: 919 | BN22: 918 | BO22: 923 | BP22: 915 | BQ22: 919 | BR22: 916 | BS22: 912 | BT22: 909 | BU22: 906 | BV22: 911 | BW22: 913 | BX22: 909 | CN22: Memo: Aug-26 revenue per day y/y | CP22: 0.124 | CR22: 3-Sep-26 update: August revenue per day +12.4% (memo; not a calibration target).
B23: LTL intercity miles (thousands) | C23: 296464 | D23: 325268 | E23: 334219 | G23: 338535 | H23: 389588 | I23: 420214 | J23: 103472 | K23: 112321 | L23: 116215 | M23: 114525 | N23: 446532 | O23: 111555 | P23: 125186 | Q23: 133864 | R23: 133319 | S23: 503923 | T23: 129467 | U23: 143487 | V23: 149510 | W23: 143747 | X23: 566210 | Y23: 140816 | Z23: 145754 | AA23: 148993 | AB23: 141389 | AC23: 576953 | AD23: 139752 | AE23: 150991 | AF23: 156343 | AG23: 158119 | AH23: 605204 | AI23: 161190 | AJ23: 174013 | AK23: 173124 | AL23: 166180 | AM23: 674506 | AN23: 159654 | AO23: 163884 | AP23: 163061 | AQ23: 157687 | AR23: 644287 | AS23: 155949 | AT23: 141417 | AU23: 160543 | AV23: 159896 | AW23: 617805 | AX23: 161174 | AY23: 178938 | AZ23: 184812 | BA23: 182687 | BB23: 707611 | BC23: 183607 | BD23: 194726 | BE23: 190626 | BF23: 177068 | BG23: 746028 | BH23: 173637 | BI23: 170294 | BJ23: 176284 | BK23: 171417 | BL23: 691632 | BN23: 172361 | BO23: 168986 | BP23: 162124 | BQ23: 673237 | BR23: 157259 | BS23: 159582 | BT23: 155365 | BU23: 144055 | BV23: 616261 | BW23: 144718 | BX23: 151977 | CN23: FY26 depreciation & amortization ($m) | CP23: 372 | CR23: 1H/26 $184.0m + 2H at the Q2/26 run-rate ($91.7m) + new equipment; not guided on EDGAR.
B24: Average active full-time employees (from 2019 releases) | AT24: 17911 | AU24: 18766 | AV24: 19630 | AW24: 19064 | AX24: 20479 | AY24: 21621 | AZ24: 22682 | BA24: 23610 | BB24: 22098 | BC24: 24277 | BD24: 24893 | BE24: 24587 | BF24: 23799 | BG24: 24389 | BH24: 22971 | BI24: 22438 | BJ24: 22284 | BK24: 22814 | BL24: 22627 | BM24: 22891 | BN24: 22702 | BO24: 22465 | BP24: 22032 | BQ24: 22522 | BR24: 21817 | BS24: 21621 | BT24: 21073 | BU24: 20706 | BV24: 21304 | BW24: 20264 | BX24: 20081 | CN24: FY26 interest expense (income), net ($m) | CP24: -9 | CR24: 1H/26 −$4.3m (interest income $4.7m on cash; $20m notes).
B25: Statistics basis (definition in force) | C25: To 2013: total tons & shipments (LTL + truckload), revenue/cwt on the total basis; work days computed to 2011 | O25: From Q1-14: LTL tons, LTL shipments and LTL revenue/cwt (statistics exclude undelivered-freight adjustments & non-weight services) | CN25: Tax rate | CP25: 0.25 | CR25: 1H/26 effective rate 25.0%; FY25 24.8%.
CN26: Capital expenditures ($m) | CP26: 380 | CR26: Q2-26 release: ~$380m (real estate & service centers $180m; tractors & trailers $155m; IT & other $45m). 1H/26 $139.6m.
B27: Yield — LTL revenue per hundredweight (ex-fuel + fuel surcharge; statistics exclude undelivered-freight revenue adjustments) | CF27: YIELD — modelling logic
B28: LTL revenue per hundredweight, excluding fuel surcharges ($) | C28: 11.6 | D28: 11.65 | E28: 11.49 | F28: 11.49 | G28: 11.49 | H28: 12.31 | I28: 12.79 | J28: 12.89 | K28: 13.25 | L28: 13.54 | M28: 13.34 | N28: 13.3 | O28: 15.01 | P28: 15.34 | Q28: 15.64 | R28: 15.56 | S28: 15.4 | T28: 15.94 | U28: 16.16 | V28: 16.46 | W28: 16.51 | X28: 16.28 | Y28: 16.54 | Z28: 16.6 | AA28: 16.91 | AB28: 16.78 | AC28: 16.71 | AD28: 16.94 | AE28: 17.23 | AF28: 17.31 | AG28: 17.3 | AH28: 17.2 | AI28: 17.57 | AJ28: 17.94 | AK28: 18.86 | AL28: 19.16 | AM28: 18.38 | AN28: 19.26 | AO28: 19.73 | AP28: 19.95 | AQ28: 19.92 | AR28: 19.72 | AS28: 19.89 | AT28: 19.64 | AU28: 20.46 | AV28: 20.76 | AW28: 20.21 | AX28: 21.01 | AY28: 21.67 | AZ28: 22.52 | BA28: 22.67 | BB28: 21.99 | BC28: 23.11 | BD28: 23.69 | BE28: 24.15 | BF28: 24.65 | BG28: 23.87 | BH28: 25.09 | BI28: 25.5 | BJ28: 26.29 | BK28: 26.5 | BL28: 25.84 | BM28: 26.78 | BN28: 26.75 | BO28: 27.49 | BP28: 27.52 | BQ28: 27.13 | BR28: 27.89 | BS28: 28.17 | BT28: 28.78 | BU28: 28.88 | BV28: 28.42 | BW28: 29.13 | BX28: 29.71 | BY28: =BT28*(1+$CP$20) | BZ28: =BY28*(1+CHOOSE(MATCH($CF$2,{"Bull","Base","Bear"},0),$CO$15,$CP$15,$CQ$15)) | CA28: =IFERROR(SUMPRODUCT(BW28:BZ28,BW15:BZ15)/SUM(BW15:BZ15),"") | CB28: =CA28*(1+CB29) | CC28: =CB28*(1+CC29) | CD28: =CC28*(1+CD29) | CE28: =CD28*(1+CE29) | CF28: Q3/26E: Q3/25 × (1 + Jul–Aug quarter-to-date y/y from the 3-Sep-26 update, +4.8%). Q4/26E: Q3/26E × (1 + 2016–25 Q3→Q4 sequential change by scenario). 2027E+: scenario lever YXF. 2026E = tonnage-weighted average of the quarters. | CH28: =IFERROR((CE28/BV28)^(1/5)-1,"n/m") | CI28: =IFERROR((BV28/AW28)^(1/5)-1,"n/m") | CJ28: =IFERROR((BV28/X28)^(1/10)-1,"n/m") | CK28: =IFERROR((BV28/C28)^(1/19)-1,"n/m") | CN28: Target cash balance ($m) — buyback plug 2027E+ (surplus cash returned) | CO28: 150 | CP28: 250 | CQ28: 400 | CR28: ODFL runs with minimal debt and returns surplus cash (cash $120m at YE25, $284m at 30-Jun-26). Target cash: Bull $150m / Base $250m / Bear $400m.
B29: y/y % | D29: =IF(AND(ISNUMBER(D28),ISNUMBER(C28)),IFERROR(D28/C28-1,""),"") | E29: =IF(AND(ISNUMBER(E28),ISNUMBER(D28)),IFERROR(E28/D28-1,""),"") | F29: =IF(AND(ISNUMBER(F28),ISNUMBER(E28)),IFERROR(F28/E28-1,""),"") | G29: =IF(AND(ISNUMBER(G28),ISNUMBER(F28)),IFERROR(G28/F28-1,""),"") | H29: =IF(AND(ISNUMBER(H28),ISNUMBER(G28)),IFERROR(H28/G28-1,""),"") | I29: =IF(AND(ISNUMBER(I28),ISNUMBER(H28)),IFERROR(I28/H28-1,""),"") | N29: =IF(AND(ISNUMBER(N28),ISNUMBER(I28)),IFERROR(N28/I28-1,""),"") | O29: =IF(AND(ISNUMBER(O28),ISNUMBER(J28)),IFERROR(O28/J28-1,""),"") | P29: =IF(AND(ISNUMBER(P28),ISNUMBER(K28)),IFERROR(P28/K28-1,""),"") | Q29: =IF(AND(ISNUMBER(Q28),ISNUMBER(L28)),IFERROR(Q28/L28-1,""),"") | R29: =IF(AND(ISNUMBER(R28),ISNUMBER(M28)),IFERROR(R28/M28-1,""),"") | S29: =IF(AND(ISNUMBER(S28),ISNUMBER(N28)),IFERROR(S28/N28-1,""),"") | T29: =IF(AND(ISNUMBER(T28),ISNUMBER(O28)),IFERROR(T28/O28-1,""),"") | U29: =IF(AND(ISNUMBER(U28),ISNUMBER(P28)),IFERROR(U28/P28-1,""),"") | ... CA29: =IF(AND(ISNUMBER(CA28),ISNUMBER(BV28)),IFERROR(CA28/BV28-1,""),"") | CB29: =CHOOSE(MATCH($CF$2,{"Bull","Base","Bear"},0),$CO$36,$CP$36,$CQ$36) | CC29: =CHOOSE(MATCH($CF$2,{"Bull","Base","Bear"},0),$CO$37,$CP$37,$CQ$37) | CD29: =CHOOSE(MATCH($CF$2,{"Bull","Base","Bear"},0),$CO$38,$CP$38,$CQ$38) | CE29: =CHOOSE(MATCH($CF$2,{"Bull","Base","Bear"},0),$CO$39,$CP$39,$CQ$39) | CH29: =IFERROR(AVERAGE(CA29,CB29,CC29,CD29,CE29),"n/m") | CI29: =IFERROR(AVERAGE(BB29,BG29,BL29,BQ29,BV29),"n/m") | CJ29: =IFERROR(AVERAGE(AC29,AH29,AM29,AR29,AW29,BB29,BG29,BL29,BQ29,BV29),"n/m") | CK29: =IFERROR(AVERAGE(C29,D29,E29,F29,G29,H29,I29,N29,S29,X29,AC29,AH29,AM29,AR29,AW29,BB29,BG29,BL29,BQ29,BV29),"n/m")
B30: sequential % (vs prior quarter) | K30: =IF(AND(ISNUMBER(K28),ISNUMBER(J28)),IFERROR(K28/J28-1,""),"") | L30: =IF(AND(ISNUMBER(L28),ISNUMBER(K28)),IFERROR(L28/K28-1,""),"") | M30: =IF(AND(ISNUMBER(M28),ISNUMBER(L28)),IFERROR(M28/L28-1,""),"") | O30: =IF(AND(ISNUMBER(O28),ISNUMBER(M28)),IFERROR(O28/M28-1,""),"") | P30: =IF(AND(ISNUMBER(P28),ISNUMBER(O28)),IFERROR(P28/O28-1,""),"") | Q30: =IF(AND(ISNUMBER(Q28),ISNUMBER(P28)),IFERROR(Q28/P28-1,""),"") | R30: =IF(AND(ISNUMBER(R28),ISNUMBER(Q28)),IFERROR(R28/Q28-1,""),"") | T30: =IF(AND(ISNUMBER(T28),ISNUMBER(R28)),IFERROR(T28/R28-1,""),"") | U30: =IF(AND(ISNUMBER(U28),ISNUMBER(T28)),IFERROR(U28/T28-1,""),"") | V30: =IF(AND(ISNUMBER(V28),ISNUMBER(U28)),IFERROR(V28/U28-1,""),"") | W30: =IF(AND(ISNUMBER(W28),ISNUMBER(V28)),IFERROR(W28/V28-1,""),"") | Y30: =IF(AND(ISNUMBER(Y28),ISNUMBER(W28)),IFERROR(Y28/W28-1,""),"") | Z30: =IF(AND(ISNUMBER(Z28),ISNUMBER(Y28)),IFERROR(Z28/Y28-1,""),"") | AA30: =IF(AND(ISNUMBER(AA28),ISNUMBER(Z28)),IFERROR(AA28/Z28-1,""),"") | AB30: =IF(AND(ISNUMBER(AB28),ISNUMBER(AA28)),IFERROR(AB28/AA28-1,""),"") | AD30: =IF(AND(ISNUMBER(AD28),ISNUMBER(AB28)),IFERROR(AD28/AB28-1,""),"") | AE30: =IF(AND(ISNUMBER(AE28),ISNUMBER(AD28)),IFERROR(AE28/AD28-1,""),"") | AF30: =IF(AND(ISNUMBER(AF28),ISNUMBER(AE28)),IFERROR(AF28/AE28-1,""),"") | AG30: =IF(AND(ISNUMBER(AG28),ISNUMBER(AF28)),IFERROR(AG28/AF28-1,""),"") | AI30: =IF(AND(ISNUMBER(AI28),ISNUMBER(AG28)),IFERROR(AI28/AG28-1,""),"") | AJ30: =IF(AND(ISNUMBER(AJ28),ISNUMBER(AI28)),IFERROR(AJ28/AI28-1,""),"") | AK30: =IF(AND(ISNUMBER(AK28),ISNUMBER(AJ28)),IFERROR(AK28/AJ28-1,""),"") | AL30: =IF(AND(ISNUMBER(AL28),ISNUMBER(AK28)),IFERROR(AL28/AK28-1,""),"") | AN30: =IF(AND(ISNUMBER(AN28),ISNUMBER(AL28)),IFERROR(AN28/AL28-1,""),"") | AO30: =IF(AND(ISNUMBER(AO28),ISNUMBER(AN28)),IFERROR(AO28/AN28-1,""),"") | AP30: =IF(AND(ISNUMBER(AP28),ISNUMBER(AO28)),IFERROR(AP28/AO28-1,""),"") | AQ30: =IF(AND(ISNUMBER(AQ28),ISNUMBER(AP28)),IFERROR(AQ28/AP28-1,""),"") | AS30: =IF(AND(ISNUMBER(AS28),ISNUMBER(AQ28)),IFERROR(AS28/AQ28-1,""),"") | AT30: =IF(AND(ISNUMBER(AT28),ISNUMBER(AS28)),IFERROR(AT28/AS28-1,""),"") | AU30: =IF(AND(ISNUMBER(AU28),ISNUMBER(AT28)),IFERROR(AU28/AT28-1,""),"") | AV30: =IF(AND(ISNUMBER(AV28),ISNUMBER(AU28)),IFERROR(AV28/AU28-1,""),"") | AX30: =IF(AND(ISNUMBER(AX28),ISNUMBER(AV28)),IFERROR(AX28/AV28-1,""),"") | AY30: =IF(AND(ISNUMBER(AY28),ISNUMBER(AX28)),IFERROR(AY28/AX28-1,""),"") | AZ30: =IF(AND(ISNUMBER(AZ28),ISNUMBER(AY28)),IFERROR(AZ28/AY28-1,""),"") | BA30: =IF(AND(ISNUMBER(BA28),ISNUMBER(AZ28)),IFERROR(BA28/AZ28-1,""),"") | BC30: =IF(AND(ISNUMBER(BC28),ISNUMBER(BA28)),IFERROR(BC28/BA28-1,""),"") | BD30: =IF(AND(ISNUMBER(BD28),ISNUMBER(BC28)),IFERROR(BD28/BC28-1,""),"") | BE30: =IF(AND(ISNUMBER(BE28),ISNUMBER(BD28)),IFERROR(BE28/BD28-1,""),"") | BF30: =IF(AND(ISNUMBER(BF28),ISNUMBER(BE28)),IFERROR(BF28/BE28-1,""),"") | BH30: =IF(AND(ISNUMBER(BH28),ISNUMBER(BF28)),IFERROR(BH28/BF28-1,""),"") | BI30: =IF(AND(ISNUMBER(BI28),ISNUMBER(BH28)),IFERROR(BI28/BH28-1,""),"") | BJ30: =IF(AND(ISNUMBER(BJ28),ISNUMBER(BI28)),IFERROR(BJ28/BI28-1,""),"") | BK30: =IF(AND(ISNUMBER(BK28),ISNUMBER(BJ28)),IFERROR(BK28/BJ28-1,""),"") | BM30: =IF(AND(ISNUMBER(BM28),ISNUMBER(BK28)),IFERROR(BM28/BK28-1,""),"") | BN30: =IF(AND(ISNUMBER(BN28),ISNUMBER(BM28)),IFERROR(BN28/BM28-1,""),"") | BO30: =IF(AND(ISNUMBER(BO28),ISNUMBER(BN28)),IFERROR(BO28/BN28-1,""),"") | BP30: =IF(AND(ISNUMBER(BP28),ISNUMBER(BO28)),IFERROR(BP28/BO28-1,""),"") | BR30: =IF(AND(ISNUMBER(BR28),ISNUMBER(BP28)),IFERROR(BR28/BP28-1,""),"") | BS30: =IF(AND(ISNUMBER(BS28),ISNUMBER(BR28)),IFERROR(BS28/BR28-1,""),"") | BT30: =IF(AND(ISNUMBER(BT28),ISNUMBER(BS28)),IFERROR(BT28/BS28-1,""),"") | BU30: =IF(AND(ISNUMBER(BU28),ISNUMBER(BT28)),IFERROR(BU28/BT28-1,""),"") | BW30: =IF(AND(ISNUMBER(BW28),ISNUMBER(BU28)),IFERROR(BW28/BU28-1,""),"") | BX30: =IF(AND(ISNUMBER(BX28),ISNUMBER(BW28)),IFERROR(BX28/BW28-1,""),"") | BY30: =IF(AND(ISNUMBER(BY28),ISNUMBER(BX28)),IFERROR(BY28/BX28-1,""),"") | BZ30: =IF(AND(ISNUMBER(BZ28),ISNUMBER(BY28)),IFERROR(BZ28/BY28-1,""),"") | CN30: TPD (LTL tons per day y/y) | CO30: 0.02 | CP30: Δ → | CQ30: -0.03 | CR30: Freight-cycle recovery from the 2023–26 industrial recession (tons/day −15% from the 2022 peak) and share gains on service (99% on-time, 0.1% claims ratio).
B31: Fuel surcharge per hundredweight ($) | C31: =IF(AND(ISNUMBER(C33),ISNUMBER(C28)),C33-C28,"") | D31: =IF(AND(ISNUMBER(D33),ISNUMBER(D28)),D33-D28,"") | E31: =IF(AND(ISNUMBER(E33),ISNUMBER(E28)),E33-E28,"") | F31: =IF(AND(ISNUMBER(F33),ISNUMBER(F28)),F33-F28,"") | G31: =IF(AND(ISNUMBER(G33),ISNUMBER(G28)),G33-G28,"") | H31: =IF(AND(ISNUMBER(H33),ISNUMBER(H28)),H33-H28,"") | I31: =IF(AND(ISNUMBER(I33),ISNUMBER(I28)),I33-I28,"") | J31: =IF(AND(ISNUMBER(J33),ISNUMBER(J28)),J33-J28,"") | ... BX31: =IF(AND(ISNUMBER(BX33),ISNUMBER(BX28)),BX33-BX28,"") | BY31: =BY28*BY32 | BZ31: =BZ28*BZ32 | CA31: =CA33-CA28 | CB31: =CB28*CB32 | CC31: =CC28*CC32 | CD31: =CD28*CD32 | CE31: =CE28*CE32 | CN31: 2027E | CO31: =CP31+$CO$30 | CP31: 0.04 | CQ31: =CP31+$CQ$30
B32: Fuel surcharge % of ex-fuel yield | C32: =IF(AND(ISNUMBER(C31),ISNUMBER(C28)),IFERROR(C31/C28,""),"") | D32: =IF(AND(ISNUMBER(D31),ISNUMBER(D28)),IFERROR(D31/D28,""),"") | E32: =IF(AND(ISNUMBER(E31),ISNUMBER(E28)),IFERROR(E31/E28,""),"") | F32: =IF(AND(ISNUMBER(F31),ISNUMBER(F28)),IFERROR(F31/F28,""),"") | G32: =IF(AND(ISNUMBER(G31),ISNUMBER(G28)),IFERROR(G31/G28,""),"") | H32: =IF(AND(ISNUMBER(H31),ISNUMBER(H28)),IFERROR(H31/H28,""),"") | I32: =IF(AND(ISNUMBER(I31),ISNUMBER(I28)),IFERROR(I31/I28,""),"") | J32: =IF(AND(ISNUMBER(J31),ISNUMBER(J28)),IFERROR(J31/J28,""),"") | ... BX32: =IF(AND(ISNUMBER(BX31),ISNUMBER(BX28)),IFERROR(BX31/BX28,""),"") | BY32: =(1+$CP$21)*BT33/BY28-1 | BZ32: =BY32 | CA32: =IF(AND(ISNUMBER(CA31),ISNUMBER(CA28)),IFERROR(CA31/CA28,""),"") | CB32: =$BZ$32 | CC32: =$BZ$32 | CD32: =$BZ$32 | CE32: =$BZ$32 | CF32: Q3/26E implied by the Jul–Aug QTD revenue/cwt (+11.3% y/y) and ex-fuel (+4.8%) changes. Q4/26E and 2027E+ held at the Q3/26E level (diesel flat). | CH32: =IFERROR(AVERAGE(CA32,CB32,CC32,CD32,CE32),"n/m") | CI32: =IFERROR(AVERAGE(BB32,BG32,BL32,BQ32,BV32),"n/m") | CJ32: =IFERROR(AVERAGE(AC32,AH32,AM32,AR32,AW32,BB32,BG32,BL32,BQ32,BV32),"n/m") | CK32: =IFERROR(AVERAGE(C32,D32,E32,F32,G32,H32,I32,N32,S32,X32,AC32,AH32,AM32,AR32,AW32,BB32,BG32,BL32,BQ32,BV32),"n/m") | CN32: 2028E | CO32: =CP32+$CO$30 | CP32: 0.05 | CQ32: =CP32+$CQ$30
B33: LTL revenue per hundredweight ($) | C33: 13.16 | D33: 13.3 | E33: 13.88 | F33: 12.7 | G33: 13.09 | H33: 14.72 | I33: 15.35 | J33: 15.5 | K33: 15.75 | L33: 16.12 | M33: 15.83 | N33: 15.85 | O33: 18 | P33: 18.36 | Q33: 18.62 | R33: 18.3 | S33: 18.33 | T33: 18.08 | U33: 18.22 | V33: 18.33 | W33: 18.26 | X33: 18.23 | Y33: 18.14 | Z33: 18.37 | AA33: 18.79 | AB33: 18.74 | AC33: 18.51 | AD33: 19.03 | AE33: 19.31 | AF33: 19.47 | AG33: 19.7 | AH33: 19.39 | AI33: 20.16 | AJ33: 20.74 | AK33: 21.9 | AL33: 22.24 | AM33: 21.25 | AN33: 22.1 | AO33: 22.72 | AP33: 22.87 | AQ33: 22.84 | AR33: 22.64 | AS33: 22.68 | AT33: 21.85 | AU33: 22.74 | AV33: 23.1 | AW33: 22.62 | AX33: 23.96 | AY33: 25.1 | AZ33: 26.31 | BA33: 26.82 | BB33: 25.59 | BC33: 28.13 | BD33: 30.78 | BE33: 30.9 | BF33: 31.3 | BG33: 30.24 | BH33: 30.71 | BI33: 30.44 | BJ33: 31.87 | BK33: 32.23 | BL33: 31.31 | BM33: 31.98 | BN33: 31.77 | BO33: 32.36 | BP33: 32.1 | BQ33: 32.05 | BR33: 32.67 | BS33: 32.84 | BT33: 33.88 | BU33: 33.91 | BV33: 33.31 | BW33: 34.52 | BX33: 37.84 | BY33: =BY28+BY31 | BZ33: =BZ28+BZ31 | CA33: =IFERROR(SUMPRODUCT(BW33:BZ33,BW15:BZ15)/SUM(BW15:BZ15),"") | CB33: =CB28+CB31 | CC33: =CC28+CC31 | CD33: =CD28+CD31 | CE33: =CE28+CE31 | CH33: =IFERROR((CE33/BV33)^(1/5)-1,"n/m") | CI33: =IFERROR((BV33/AW33)^(1/5)-1,"n/m") | CJ33: =IFERROR((BV33/X33)^(1/10)-1,"n/m") | CK33: =IFERROR((BV33/C33)^(1/19)-1,"n/m") | CN33: 2029E | CO33: =CP33+$CO$30 | CP33: 0.04 | CQ33: =CP33+$CQ$30
B34: y/y % | D34: =IF(AND(ISNUMBER(D33),ISNUMBER(C33)),IFERROR(D33/C33-1,""),"") | E34: =IF(AND(ISNUMBER(E33),ISNUMBER(D33)),IFERROR(E33/D33-1,""),"") | F34: =IF(AND(ISNUMBER(F33),ISNUMBER(E33)),IFERROR(F33/E33-1,""),"") | G34: =IF(AND(ISNUMBER(G33),ISNUMBER(F33)),IFERROR(G33/F33-1,""),"") | H34: =IF(AND(ISNUMBER(H33),ISNUMBER(G33)),IFERROR(H33/G33-1,""),"") | I34: =IF(AND(ISNUMBER(I33),ISNUMBER(H33)),IFERROR(I33/H33-1,""),"") | N34: =IF(AND(ISNUMBER(N33),ISNUMBER(I33)),IFERROR(N33/I33-1,""),"") | O34: =IF(AND(ISNUMBER(O33),ISNUMBER(J33)),IFERROR(O33/J33-1,""),"") | P34: =IF(AND(ISNUMBER(P33),ISNUMBER(K33)),IFERROR(P33/K33-1,""),"") | Q34: =IF(AND(ISNUMBER(Q33),ISNUMBER(L33)),IFERROR(Q33/L33-1,""),"") | R34: =IF(AND(ISNUMBER(R33),ISNUMBER(M33)),IFERROR(R33/M33-1,""),"") | S34: =IF(AND(ISNUMBER(S33),ISNUMBER(N33)),IFERROR(S33/N33-1,""),"") | T34: =IF(AND(ISNUMBER(T33),ISNUMBER(O33)),IFERROR(T33/O33-1,""),"") | U34: =IF(AND(ISNUMBER(U33),ISNUMBER(P33)),IFERROR(U33/P33-1,""),"") | ... CA34: =IF(AND(ISNUMBER(CA33),ISNUMBER(BV33)),IFERROR(CA33/BV33-1,""),"") | CB34: =IF(AND(ISNUMBER(CB33),ISNUMBER(CA33)),IFERROR(CB33/CA33-1,""),"") | CC34: =IF(AND(ISNUMBER(CC33),ISNUMBER(CB33)),IFERROR(CC33/CB33-1,""),"") | CD34: =IF(AND(ISNUMBER(CD33),ISNUMBER(CC33)),IFERROR(CD33/CC33-1,""),"") | CE34: =IF(AND(ISNUMBER(CE33),ISNUMBER(CD33)),IFERROR(CE33/CD33-1,""),"") | CH34: =IFERROR(AVERAGE(CA34,CB34,CC34,CD34,CE34),"n/m") | CI34: =IFERROR(AVERAGE(BB34,BG34,BL34,BQ34,BV34),"n/m") | CJ34: =IFERROR(AVERAGE(AC34,AH34,AM34,AR34,AW34,BB34,BG34,BL34,BQ34,BV34),"n/m") | CK34: =IFERROR(AVERAGE(C34,D34,E34,F34,G34,H34,I34,N34,S34,X34,AC34,AH34,AM34,AR34,AW34,BB34,BG34,BL34,BQ34,BV34),"n/m") | CN34: 2030E | CO34: =CP34+$CO$30 | CP34: 0.035 | CQ34: =CP34+$CQ$30
B35: sequential % (vs prior quarter) | K35: =IF(AND(ISNUMBER(K33),ISNUMBER(J33)),IFERROR(K33/J33-1,""),"") | L35: =IF(AND(ISNUMBER(L33),ISNUMBER(K33)),IFERROR(L33/K33-1,""),"") | M35: =IF(AND(ISNUMBER(M33),ISNUMBER(L33)),IFERROR(M33/L33-1,""),"") | O35: =IF(AND(ISNUMBER(O33),ISNUMBER(M33)),IFERROR(O33/M33-1,""),"") | P35: =IF(AND(ISNUMBER(P33),ISNUMBER(O33)),IFERROR(P33/O33-1,""),"") | Q35: =IF(AND(ISNUMBER(Q33),ISNUMBER(P33)),IFERROR(Q33/P33-1,""),"") | R35: =IF(AND(ISNUMBER(R33),ISNUMBER(Q33)),IFERROR(R33/Q33-1,""),"") | T35: =IF(AND(ISNUMBER(T33),ISNUMBER(R33)),IFERROR(T33/R33-1,""),"") | U35: =IF(AND(ISNUMBER(U33),ISNUMBER(T33)),IFERROR(U33/T33-1,""),"") | V35: =IF(AND(ISNUMBER(V33),ISNUMBER(U33)),IFERROR(V33/U33-1,""),"") | W35: =IF(AND(ISNUMBER(W33),ISNUMBER(V33)),IFERROR(W33/V33-1,""),"") | Y35: =IF(AND(ISNUMBER(Y33),ISNUMBER(W33)),IFERROR(Y33/W33-1,""),"") | Z35: =IF(AND(ISNUMBER(Z33),ISNUMBER(Y33)),IFERROR(Z33/Y33-1,""),"") | AA35: =IF(AND(ISNUMBER(AA33),ISNUMBER(Z33)),IFERROR(AA33/Z33-1,""),"") | AB35: =IF(AND(ISNUMBER(AB33),ISNUMBER(AA33)),IFERROR(AB33/AA33-1,""),"") | AD35: =IF(AND(ISNUMBER(AD33),ISNUMBER(AB33)),IFERROR(AD33/AB33-1,""),"") | AE35: =IF(AND(ISNUMBER(AE33),ISNUMBER(AD33)),IFERROR(AE33/AD33-1,""),"") | AF35: =IF(AND(ISNUMBER(AF33),ISNUMBER(AE33)),IFERROR(AF33/AE33-1,""),"") | AG35: =IF(AND(ISNUMBER(AG33),ISNUMBER(AF33)),IFERROR(AG33/AF33-1,""),"") | AI35: =IF(AND(ISNUMBER(AI33),ISNUMBER(AG33)),IFERROR(AI33/AG33-1,""),"") | AJ35: =IF(AND(ISNUMBER(AJ33),ISNUMBER(AI33)),IFERROR(AJ33/AI33-1,""),"") | AK35: =IF(AND(ISNUMBER(AK33),ISNUMBER(AJ33)),IFERROR(AK33/AJ33-1,""),"") | AL35: =IF(AND(ISNUMBER(AL33),ISNUMBER(AK33)),IFERROR(AL33/AK33-1,""),"") | AN35: =IF(AND(ISNUMBER(AN33),ISNUMBER(AL33)),IFERROR(AN33/AL33-1,""),"") | AO35: =IF(AND(ISNUMBER(AO33),ISNUMBER(AN33)),IFERROR(AO33/AN33-1,""),"") | AP35: =IF(AND(ISNUMBER(AP33),ISNUMBER(AO33)),IFERROR(AP33/AO33-1,""),"") | AQ35: =IF(AND(ISNUMBER(AQ33),ISNUMBER(AP33)),IFERROR(AQ33/AP33-1,""),"") | AS35: =IF(AND(ISNUMBER(AS33),ISNUMBER(AQ33)),IFERROR(AS33/AQ33-1,""),"") | AT35: =IF(AND(ISNUMBER(AT33),ISNUMBER(AS33)),IFERROR(AT33/AS33-1,""),"") | AU35: =IF(AND(ISNUMBER(AU33),ISNUMBER(AT33)),IFERROR(AU33/AT33-1,""),"") | AV35: =IF(AND(ISNUMBER(AV33),ISNUMBER(AU33)),IFERROR(AV33/AU33-1,""),"") | AX35: =IF(AND(ISNUMBER(AX33),ISNUMBER(AV33)),IFERROR(AX33/AV33-1,""),"") | AY35: =IF(AND(ISNUMBER(AY33),ISNUMBER(AX33)),IFERROR(AY33/AX33-1,""),"") | AZ35: =IF(AND(ISNUMBER(AZ33),ISNUMBER(AY33)),IFERROR(AZ33/AY33-1,""),"") | BA35: =IF(AND(ISNUMBER(BA33),ISNUMBER(AZ33)),IFERROR(BA33/AZ33-1,""),"") | BC35: =IF(AND(ISNUMBER(BC33),ISNUMBER(BA33)),IFERROR(BC33/BA33-1,""),"") | BD35: =IF(AND(ISNUMBER(BD33),ISNUMBER(BC33)),IFERROR(BD33/BC33-1,""),"") | BE35: =IF(AND(ISNUMBER(BE33),ISNUMBER(BD33)),IFERROR(BE33/BD33-1,""),"") | BF35: =IF(AND(ISNUMBER(BF33),ISNUMBER(BE33)),IFERROR(BF33/BE33-1,""),"") | BH35: =IF(AND(ISNUMBER(BH33),ISNUMBER(BF33)),IFERROR(BH33/BF33-1,""),"") | BI35: =IF(AND(ISNUMBER(BI33),ISNUMBER(BH33)),IFERROR(BI33/BH33-1,""),"") | BJ35: =IF(AND(ISNUMBER(BJ33),ISNUMBER(BI33)),IFERROR(BJ33/BI33-1,""),"") | BK35: =IF(AND(ISNUMBER(BK33),ISNUMBER(BJ33)),IFERROR(BK33/BJ33-1,""),"") | BM35: =IF(AND(ISNUMBER(BM33),ISNUMBER(BK33)),IFERROR(BM33/BK33-1,""),"") | BN35: =IF(AND(ISNUMBER(BN33),ISNUMBER(BM33)),IFERROR(BN33/BM33-1,""),"") | BO35: =IF(AND(ISNUMBER(BO33),ISNUMBER(BN33)),IFERROR(BO33/BN33-1,""),"") | BP35: =IF(AND(ISNUMBER(BP33),ISNUMBER(BO33)),IFERROR(BP33/BO33-1,""),"") | BR35: =IF(AND(ISNUMBER(BR33),ISNUMBER(BP33)),IFERROR(BR33/BP33-1,""),"") | BS35: =IF(AND(ISNUMBER(BS33),ISNUMBER(BR33)),IFERROR(BS33/BR33-1,""),"") | BT35: =IF(AND(ISNUMBER(BT33),ISNUMBER(BS33)),IFERROR(BT33/BS33-1,""),"") | BU35: =IF(AND(ISNUMBER(BU33),ISNUMBER(BT33)),IFERROR(BU33/BT33-1,""),"") | BW35: =IF(AND(ISNUMBER(BW33),ISNUMBER(BU33)),IFERROR(BW33/BU33-1,""),"") | BX35: =IF(AND(ISNUMBER(BX33),ISNUMBER(BW33)),IFERROR(BX33/BW33-1,""),"") | BY35: =IF(AND(ISNUMBER(BY33),ISNUMBER(BX33)),IFERROR(BY33/BX33-1,""),"") | BZ35: =IF(AND(ISNUMBER(BZ33),ISNUMBER(BY33)),IFERROR(BZ33/BY33-1,""),"") | CN35: YXF (LTL revenue/cwt ex fuel y/y) | CO35: 0.01 | CP35: Δ → | CQ35: -0.015 | CR35: Yield discipline: cost-plus pricing targets inflation + reinvestment; ex-fuel revenue/cwt +4–6% p.a. 2016–25 (weight-per-shipment mix headwind as volumes recover).
B36: LTL revenue per shipment ($) | C36: 199.03 | D36: 207.24 | E36: 229.99 | F36: 216.49 | G36: 234.09 | H36: 259.5 | I36: 271.82 | J36: 276.97 | K36: 279.9 | L36: 285.7 | M36: 285.16 | N36: 282.78 | O36: 292.95 | P36: 300.5 | Q36: 301.08 | R36: 299.38 | S36: 298.65 | T36: 288.83 | U36: 286.85 | V36: 282.9 | W36: 284.47 | X36: 285.67 | Y36: 280.33 | Z36: 286.51 | AA36: 291.51 | AB36: 299.34 | AC36: 289.36 | AD36: 297.11 | AE36: 302.51 | AF36: 307.45 | AG36: 322.97 | AH36: 307.66 | AI36: 328.78 | AJ36: 334.95 | AK36: 340.91 | AL36: 352.65 | AM36: 339.35 | AN36: 346.02 | AO36: 352.88 | AP36: 353.24 | AQ36: 360.8 | AR36: 353.18 | AS36: 359.64 | AT36: 357.65 | AU36: 367.28 | AV36: 374.08 | AW36: 364.94 | AX36: 384.76 | AY36: 394.49 | AZ36: 404.65 | BA36: 422.28 | BB36: 402.01 | BC36: 446.86 | BD36: 484.08 | BE36: 482.46 | BF36: 489.96 | BG36: 475.45 | BH36: 475.88 | BI36: 464.79 | BJ36: 477.13 | BK36: 487.13 | BL36: 476.25 | BM36: 482.24 | BN36: 479.48 | BO36: 477.7 | BP36: 481.91 | BQ36: 480.29 | BR36: 485.79 | BS36: 485.31 | BT36: 494.17 | BU36: 503.95 | BV36: 492.01 | BW36: 514.56 | BX36: 568.55 | BY36: =BY33*BY17/100 | BZ36: =BZ33*BZ17/100 | CA36: =CA33*CA17/100 | CB36: =CB33*CB17/100 | CC36: =CC33*CC17/100 | CD36: =CD33*CD17/100 | CE36: =CE33*CE17/100 | CN36: 2027E | CO36: =CP36+$CO$35 | CP36: 0.05 | CQ36: =CP36+$CQ$35
B37: LTL revenue per shipment, excluding fuel surcharges ($) | C37: 175.38 | D37: 181.47 | E37: 190.44 | F37: 195.81 | G37: 205.38 | H37: 217.04 | I37: 226.5 | J37: 230.4 | K37: 235.36 | L37: 240 | M37: 240.27 | N37: 237.37 | O37: 244.24 | P37: 251.08 | Q37: 253.01 | R37: 254.54 | S37: 250.92 | T37: 254.75 | U37: 254.44 | V37: 254.01 | W37: 257.25 | X37: 255.1 | Y37: 255.72 | Z37: 258.9 | AA37: 262.35 | AB37: 268.1 | AC37: 261.21 | AD37: 264.47 | AE37: 269.92 | AF37: 273.38 | AG37: 283.6 | AH37: 272.97 | AI37: 286.66 | AJ37: 289.69 | AK37: 293.56 | AL37: 303.8 | AM37: 293.42 | AN37: 301.56 | AO37: 306.37 | AP37: 308.26 | AQ37: 314.7 | AR37: 307.67 | AS37: 315.43 | AT37: 321.47 | AU37: 330.43 | AV37: 336.04 | AW37: 326.09 | AX37: 337.46 | AY37: 340.48 | AZ37: 346.46 | BA37: 356.93 | BB37: 345.54 | BC37: 367.07 | BD37: 372.56 | BE37: 377.14 | BF37: 385.89 | BG37: 375.36 | BH37: 388.82 | BI37: 389.39 | BJ37: 393.57 | BK37: 400.45 | BL37: 393.07 | BM37: 403.71 | BN37: 403.77 | BO37: 405.85 | BP37: 413.21 | BQ37: 406.52 | BR37: 414.68 | BS37: 416.31 | BT37: 419.67 | BU37: 429.21 | BV37: 419.74 | BW37: 434.16 | BX37: 446.44 | BY37: =BY28*BY17/100 | BZ37: =BZ28*BZ17/100 | CA37: =CA28*CA17/100 | CB37: =CB28*CB17/100 | CC37: =CC28*CC17/100 | CD37: =CD28*CD17/100 | CE37: =CE28*CE17/100 | CN37: 2028E | CO37: =CP37+$CO$35 | CP37: 0.045 | CQ37: =CP37+$CQ$35
CN38: 2029E | CO38: =CP38+$CO$35 | CP38: 0.045 | CQ38: =CP38+$CQ$35
B39: Revenue build — LTL services (statistics basis × revenue-recognition adjustment) + other services | CF39: REVENUE BUILD — modelling logic | CN39: 2030E | CO39: =CP39+$CO$35 | CP39: 0.04 | CQ39: =CP39+$CQ$35
B40: LTL revenue — statistics basis (tons × 20 cwt × revenue/cwt) | C40: =IF(AND(ISNUMBER(C15),ISNUMBER(C33)),C15*20*C33/1000,"") | D40: =IF(AND(ISNUMBER(D15),ISNUMBER(D33)),D15*20*D33/1000,"") | E40: =IF(AND(ISNUMBER(E15),ISNUMBER(E33)),E15*20*E33/1000,"") | F40: =IF(AND(ISNUMBER(F15),ISNUMBER(F33)),F15*20*F33/1000,"") | G40: =IF(AND(ISNUMBER(G15),ISNUMBER(G33)),G15*20*G33/1000,"") | H40: =IF(AND(ISNUMBER(H15),ISNUMBER(H33)),H15*20*H33/1000,"") | I40: =IF(AND(ISNUMBER(I15),ISNUMBER(I33)),I15*20*I33/1000,"") | J40: =IF(AND(ISNUMBER(J15),ISNUMBER(J33)),J15*20*J33/1000,"") | ... CE40: =IF(AND(ISNUMBER(CE15),ISNUMBER(CE33)),CE15*20*CE33/1000,"") | CF40: Operating statistics exclude undelivered-freight adjustments (revenue recognised over transit) and non-weight-priced services. | CN40: OR (operating ratio) | CO40: -0.015 | CP40: Δ → | CQ40: 0.025 | CR40: FY2022 record 70.6%; FY25 74.7% (de-leverage at −8% tons/day). Density recovery on a network with ~30% excess capacity; long-term ambition low/mid-60s.
B41: Revenue-recognition, undelivered-freight & other adjustments (reported LTL revenue − statistics basis) | C41: =IF(ISNUMBER(C40),IF(ISNUMBER(C43),C43,C100)-C40,"") | D41: =IF(ISNUMBER(D40),IF(ISNUMBER(D43),D43,D100)-D40,"") | E41: =IF(ISNUMBER(E40),IF(ISNUMBER(E43),E43,E100)-E40,"") | F41: =IF(ISNUMBER(F40),IF(ISNUMBER(F43),F43,F100)-F40,"") | G41: =IF(ISNUMBER(G40),IF(ISNUMBER(G43),G43,G100)-G40,"") | H41: =IF(ISNUMBER(H40),IF(ISNUMBER(H43),H43,H100)-H40,"") | I41: =IF(ISNUMBER(I40),IF(ISNUMBER(I43),I43,I100)-I40,"") | J41: =IF(ISNUMBER(J40),IF(ISNUMBER(J43),J43,J100)-J40,"") | ... BX41: =IF(ISNUMBER(BX40),IF(ISNUMBER(BX43),BX43,BX100)-BX40,"") | BY41: =BY40*BY42 | BZ41: =BZ40*BZ42 | CA41: =SUM(BW41,BX41,BY41,BZ41) | CB41: =CB40*CB42 | CC41: =CC40*CC42 | CD41: =CD40*CD42 | CE41: =CE40*CE42 | CF41: To 2018 (LTL / other services split not published) = total revenue − statistics basis, i.e. includes other services. | CN41: 2027E | CO41: =CP41+$CO$40 | CP41: 0.705 | CQ41: =CP41+$CQ$40
B42: Adjustment % of statistics-basis revenue | C42: =IF(AND(ISNUMBER(C41),ISNUMBER(C40)),IFERROR(C41/C40,""),"") | D42: =IF(AND(ISNUMBER(D41),ISNUMBER(D40)),IFERROR(D41/D40,""),"") | E42: =IF(AND(ISNUMBER(E41),ISNUMBER(E40)),IFERROR(E41/E40,""),"") | F42: =IF(AND(ISNUMBER(F41),ISNUMBER(F40)),IFERROR(F41/F40,""),"") | G42: =IF(AND(ISNUMBER(G41),ISNUMBER(G40)),IFERROR(G41/G40,""),"") | H42: =IF(AND(ISNUMBER(H41),ISNUMBER(H40)),IFERROR(H41/H40,""),"") | I42: =IF(AND(ISNUMBER(I41),ISNUMBER(I40)),IFERROR(I41/I40,""),"") | J42: =IF(AND(ISNUMBER(J41),ISNUMBER(J40)),IFERROR(J41/J40,""),"") | ... BX42: =IF(AND(ISNUMBER(BX41),ISNUMBER(BX40)),IFERROR(BX41/BX40,""),"") | BY42: =IFERROR((BW41+BX41)/(BW40+BX40),"") | BZ42: =IFERROR((BW41+BX41)/(BW40+BX40),"") | CA42: =IF(AND(ISNUMBER(CA41),ISNUMBER(CA40)),IFERROR(CA41/CA40,""),"") | CB42: =$BY$42 | CC42: =$BY$42 | CD42: =$BY$42 | CE42: =$BY$42 | CH42: =IFERROR(AVERAGE(CA42,CB42,CC42,CD42,CE42),"n/m") | CI42: =IFERROR(AVERAGE(BB42,BG42,BL42,BQ42,BV42),"n/m") | CJ42: =IFERROR(AVERAGE(AC42,AH42,AM42,AR42,AW42,BB42,BG42,BL42,BQ42,BV42),"n/m") | CK42: =IFERROR(AVERAGE(C42,D42,E42,F42,G42,H42,I42,N42,S42,X42,AC42,AH42,AM42,AR42,AW42,BB42,BG42,BL42,BQ42,BV42),"n/m") | CN42: 2028E | CO42: =CP42+$CO$40 | CP42: 0.695 | CQ42: =CP42+$CQ$40
B43: LTL services revenue (reported; from 2019) | AI43: 911.054 | AJ43: 1018.491 | AK43: 1041.854 | AL43: 1011.259 | AM43: 3982.658 | AN43: 976.563 | AO43: 1047.208 | AP43: 1035.093 | AQ43: 996.603 | AR43: 4055.467 | AS43: 974.431 | AT43: 884.069 | AU43: 1044.64 | AV43: 1057.914 | AW43: 3961.054 | AX43: 1109.622 | AY43: 1299.76 | AZ43: 1378.339 | BA43: 1389.776 | BB43: 5177.497 | BC43: 1475.781 | BD43: 1644.659 | BE43: 1582.952 | BF43: 1473.663 | BG43: 6177.055 | BH43: 1424.372 | BI43: 1397.815 | BJ43: 1501.266 | BK43: 1481.486 | BL43: 5804.939 | BM43: 1446.733 | BN43: 1484.967 | BO43: 1457.108 | BP43: 1372.297 | BQ43: 5761.105 | BR43: 1360.839 | BS43: 1395.112 | BT43: 1394.338 | BU43: 1295.862 | BV43: 5446.151 | BW43: 1321.891 | BX43: 1538.938 | BY43: =BY40+BY41 | BZ43: =BZ40+BZ41 | CA43: =SUM(BW43,BX43,BY43,BZ43) | CB43: =CB40+CB41 | CC43: =CC40+CC41 | CD43: =CD40+CD41 | CE43: =CE40+CE41 | CH43: =IFERROR((CE43/BV43)^(1/5)-1,"n/m") | CI43: =IFERROR((BV43/AW43)^(1/5)-1,"n/m") | CJ43: =IFERROR((BV43/X43)^(1/10)-1,"n/m") | CK43: =IFERROR((BV43/C43)^(1/19)-1,"n/m") | CN43: 2029E | CO43: =CP43+$CO$40 | CP43: 0.69 | CQ43: =CP43+$CQ$40
B44: y/y % | D44: =IF(AND(ISNUMBER(D43),ISNUMBER(C43)),IFERROR(D43/C43-1,""),"") | E44: =IF(AND(ISNUMBER(E43),ISNUMBER(D43)),IFERROR(E43/D43-1,""),"") | F44: =IF(AND(ISNUMBER(F43),ISNUMBER(E43)),IFERROR(F43/E43-1,""),"") | G44: =IF(AND(ISNUMBER(G43),ISNUMBER(F43)),IFERROR(G43/F43-1,""),"") | H44: =IF(AND(ISNUMBER(H43),ISNUMBER(G43)),IFERROR(H43/G43-1,""),"") | I44: =IF(AND(ISNUMBER(I43),ISNUMBER(H43)),IFERROR(I43/H43-1,""),"") | N44: =IF(AND(ISNUMBER(N43),ISNUMBER(I43)),IFERROR(N43/I43-1,""),"") | O44: =IF(AND(ISNUMBER(O43),ISNUMBER(J43)),IFERROR(O43/J43-1,""),"") | P44: =IF(AND(ISNUMBER(P43),ISNUMBER(K43)),IFERROR(P43/K43-1,""),"") | Q44: =IF(AND(ISNUMBER(Q43),ISNUMBER(L43)),IFERROR(Q43/L43-1,""),"") | R44: =IF(AND(ISNUMBER(R43),ISNUMBER(M43)),IFERROR(R43/M43-1,""),"") | S44: =IF(AND(ISNUMBER(S43),ISNUMBER(N43)),IFERROR(S43/N43-1,""),"") | T44: =IF(AND(ISNUMBER(T43),ISNUMBER(O43)),IFERROR(T43/O43-1,""),"") | U44: =IF(AND(ISNUMBER(U43),ISNUMBER(P43)),IFERROR(U43/P43-1,""),"") | ... CA44: =IF(AND(ISNUMBER(CA43),ISNUMBER(BV43)),IFERROR(CA43/BV43-1,""),"") | CB44: =IF(AND(ISNUMBER(CB43),ISNUMBER(CA43)),IFERROR(CB43/CA43-1,""),"") | CC44: =IF(AND(ISNUMBER(CC43),ISNUMBER(CB43)),IFERROR(CC43/CB43-1,""),"") | CD44: =IF(AND(ISNUMBER(CD43),ISNUMBER(CC43)),IFERROR(CD43/CC43-1,""),"") | CE44: =IF(AND(ISNUMBER(CE43),ISNUMBER(CD43)),IFERROR(CE43/CD43-1,""),"") | CN44: 2030E | CO44: =CP44+$CO$40 | CP44: 0.685 | CQ44: =CP44+$CQ$40
B45: Other services revenue (container drayage, truckload brokerage, supply-chain consulting) | AI45: 13.966 | AJ45: 15.007 | AK45: 16.379 | AL45: 15.685 | AM45: 61.037 | AN45: 14.219 | AO45: 13.458 | AP45: 13.364 | AQ45: 12.603 | AR45: 53.644 | AS45: 12.933 | AT45: 12.141 | AU45: 13.526 | AV45: 15.475 | AW45: 54.075 | AX45: 16.893 | AY45: 19.649 | AZ45: 21.707 | BA45: 20.582 | BB45: 78.831 | BC45: 21.499 | BD45: 22.789 | BE45: 20.738 | BF45: 17.996 | BG45: 83.022 | BH45: 17.764 | BI45: 15.374 | BJ45: 14.011 | BK45: 14.064 | BL45: 61.213 | BM45: 13.34 | BN45: 13.73 | BO45: 13.103 | BP45: 13.532 | BQ45: 53.705 | BR45: 14.019 | BS45: 12.612 | BT45: 12.173 | BU45: 11.434 | BV45: 50.238 | BW45: 12.805 | BX45: 15.066 | BY45: =BT45*(BW45+BX45)/(BR45+BS45) | BZ45: =BU45*(BW45+BX45)/(BR45+BS45) | CA45: =SUM(BW45,BX45,BY45,BZ45) | CB45: =CA45*(1+CB46) | CC45: =CB45*(1+CC46) | CD45: =CC45*(1+CD46) | CE45: =CD45*(1+CE46) | CF45: Q3/Q4-26E: prior-year quarter × 1H/26 y/y. 2027E+: growth input.
B46: y/y % | D46: =IF(AND(ISNUMBER(D45),ISNUMBER(C45)),IFERROR(D45/C45-1,""),"") | E46: =IF(AND(ISNUMBER(E45),ISNUMBER(D45)),IFERROR(E45/D45-1,""),"") | F46: =IF(AND(ISNUMBER(F45),ISNUMBER(E45)),IFERROR(F45/E45-1,""),"") | G46: =IF(AND(ISNUMBER(G45),ISNUMBER(F45)),IFERROR(G45/F45-1,""),"") | H46: =IF(AND(ISNUMBER(H45),ISNUMBER(G45)),IFERROR(H45/G45-1,""),"") | I46: =IF(AND(ISNUMBER(I45),ISNUMBER(H45)),IFERROR(I45/H45-1,""),"") | N46: =IF(AND(ISNUMBER(N45),ISNUMBER(I45)),IFERROR(N45/I45-1,""),"") | O46: =IF(AND(ISNUMBER(O45),ISNUMBER(J45)),IFERROR(O45/J45-1,""),"") | P46: =IF(AND(ISNUMBER(P45),ISNUMBER(K45)),IFERROR(P45/K45-1,""),"") | Q46: =IF(AND(ISNUMBER(Q45),ISNUMBER(L45)),IFERROR(Q45/L45-1,""),"") | R46: =IF(AND(ISNUMBER(R45),ISNUMBER(M45)),IFERROR(R45/M45-1,""),"") | S46: =IF(AND(ISNUMBER(S45),ISNUMBER(N45)),IFERROR(S45/N45-1,""),"") | T46: =IF(AND(ISNUMBER(T45),ISNUMBER(O45)),IFERROR(T45/O45-1,""),"") | U46: =IF(AND(ISNUMBER(U45),ISNUMBER(P45)),IFERROR(U45/P45-1,""),"") | ... CA46: =IF(AND(ISNUMBER(CA45),ISNUMBER(BV45)),IFERROR(CA45/BV45-1,""),"") | CB46: 0.04 | CC46: 0.04 | CD46: 0.04 | CE46: 0.04
B47: Total revenue (LTL operating build) | C47: =IF(ISNUMBER(C40),IF(ISNUMBER(C43),C43+N(C45),C40+C41),"") | D47: =IF(ISNUMBER(D40),IF(ISNUMBER(D43),D43+N(D45),D40+D41),"") | E47: =IF(ISNUMBER(E40),IF(ISNUMBER(E43),E43+N(E45),E40+E41),"") | F47: =IF(ISNUMBER(F40),IF(ISNUMBER(F43),F43+N(F45),F40+F41),"") | G47: =IF(ISNUMBER(G40),IF(ISNUMBER(G43),G43+N(G45),G40+G41),"") | H47: =IF(ISNUMBER(H40),IF(ISNUMBER(H43),H43+N(H45),H40+H41),"") | I47: =IF(ISNUMBER(I40),IF(ISNUMBER(I43),I43+N(I45),I40+I41),"") | J47: =IF(ISNUMBER(J40),IF(ISNUMBER(J43),J43+N(J45),J40+J41),"") | ... BX47: =IF(ISNUMBER(BX40),IF(ISNUMBER(BX43),BX43+N(BX45),BX40+BX41),"") | BY47: =BY43+BY45 | BZ47: =BZ43+BZ45 | CA47: =CA43+CA45 | CB47: =CB43+CB45 | CC47: =CC43+CC45 | CD47: =CD43+CD45 | CE47: =CE43+CE45 | CF47: Σ LTL services + other services revenue (historically = statistics basis + adjustments).
B48: Revenue y/y % | D48: =IF(AND(ISNUMBER(D47),ISNUMBER(C47)),IFERROR(D47/C47-1,""),"") | E48: =IF(AND(ISNUMBER(E47),ISNUMBER(D47)),IFERROR(E47/D47-1,""),"") | F48: =IF(AND(ISNUMBER(F47),ISNUMBER(E47)),IFERROR(F47/E47-1,""),"") | G48: =IF(AND(ISNUMBER(G47),ISNUMBER(F47)),IFERROR(G47/F47-1,""),"") | H48: =IF(AND(ISNUMBER(H47),ISNUMBER(G47)),IFERROR(H47/G47-1,""),"") | I48: =IF(AND(ISNUMBER(I47),ISNUMBER(H47)),IFERROR(I47/H47-1,""),"") | N48: =IF(AND(ISNUMBER(N47),ISNUMBER(I47)),IFERROR(N47/I47-1,""),"") | O48: =IF(AND(ISNUMBER(O47),ISNUMBER(J47)),IFERROR(O47/J47-1,""),"") | P48: =IF(AND(ISNUMBER(P47),ISNUMBER(K47)),IFERROR(P47/K47-1,""),"") | Q48: =IF(AND(ISNUMBER(Q47),ISNUMBER(L47)),IFERROR(Q47/L47-1,""),"") | R48: =IF(AND(ISNUMBER(R47),ISNUMBER(M47)),IFERROR(R47/M47-1,""),"") | S48: =IF(AND(ISNUMBER(S47),ISNUMBER(N47)),IFERROR(S47/N47-1,""),"") | T48: =IF(AND(ISNUMBER(T47),ISNUMBER(O47)),IFERROR(T47/O47-1,""),"") | U48: =IF(AND(ISNUMBER(U47),ISNUMBER(P47)),IFERROR(U47/P47-1,""),"") | ... CA48: =IF(AND(ISNUMBER(CA47),ISNUMBER(BV47)),IFERROR(CA47/BV47-1,""),"") | CB48: =IF(AND(ISNUMBER(CB47),ISNUMBER(CA47)),IFERROR(CB47/CA47-1,""),"") | CC48: =IF(AND(ISNUMBER(CC47),ISNUMBER(CB47)),IFERROR(CC47/CB47-1,""),"") | CD48: =IF(AND(ISNUMBER(CD47),ISNUMBER(CC47)),IFERROR(CD47/CC47-1,""),"") | CE48: =IF(AND(ISNUMBER(CE47),ISNUMBER(CD47)),IFERROR(CE47/CD47-1,""),"")
B49: Check: LTL operating build vs consolidated revenue (should be 0) | C49: =IF(ISNUMBER(C47),ROUND(C47-C100,1),"") | D49: =IF(ISNUMBER(D47),ROUND(D47-D100,1),"") | E49: =IF(ISNUMBER(E47),ROUND(E47-E100,1),"") | F49: =IF(ISNUMBER(F47),ROUND(F47-F100,1),"") | G49: =IF(ISNUMBER(G47),ROUND(G47-G100,1),"") | H49: =IF(ISNUMBER(H47),ROUND(H47-H100,1),"") | I49: =IF(ISNUMBER(I47),ROUND(I47-I100,1),"") | J49: =IF(ISNUMBER(J47),ROUND(J47-J100,1),"") | ... CE49: =IF(ISNUMBER(CE47),ROUND(CE47-CE100,1),"")
B50: Revenue per work day ($m) | C50: =IF(AND(ISNUMBER(C100),ISNUMBER(C11)),IFERROR(C100/C11,""),"") | D50: =IF(AND(ISNUMBER(D100),ISNUMBER(D11)),IFERROR(D100/D11,""),"") | E50: =IF(AND(ISNUMBER(E100),ISNUMBER(E11)),IFERROR(E100/E11,""),"") | F50: =IF(AND(ISNUMBER(F100),ISNUMBER(F11)),IFERROR(F100/F11,""),"") | G50: =IF(AND(ISNUMBER(G100),ISNUMBER(G11)),IFERROR(G100/G11,""),"") | H50: =IF(AND(ISNUMBER(H100),ISNUMBER(H11)),IFERROR(H100/H11,""),"") | I50: =IF(AND(ISNUMBER(I100),ISNUMBER(I11)),IFERROR(I100/I11,""),"") | J50: =IF(AND(ISNUMBER(J100),ISNUMBER(J11)),IFERROR(J100/J11,""),"") | ... CE50: =IF(AND(ISNUMBER(CE100),ISNUMBER(CE11)),IFERROR(CE100/CE11,""),"")
B51: Revenue per day y/y % (mid-quarter update metric) | D51: =IF(AND(ISNUMBER(D50),ISNUMBER(C50)),IFERROR(D50/C50-1,""),"") | E51: =IF(AND(ISNUMBER(E50),ISNUMBER(D50)),IFERROR(E50/D50-1,""),"") | F51: =IF(AND(ISNUMBER(F50),ISNUMBER(E50)),IFERROR(F50/E50-1,""),"") | G51: =IF(AND(ISNUMBER(G50),ISNUMBER(F50)),IFERROR(G50/F50-1,""),"") | H51: =IF(AND(ISNUMBER(H50),ISNUMBER(G50)),IFERROR(H50/G50-1,""),"") | I51: =IF(AND(ISNUMBER(I50),ISNUMBER(H50)),IFERROR(I50/H50-1,""),"") | N51: =IF(AND(ISNUMBER(N50),ISNUMBER(I50)),IFERROR(N50/I50-1,""),"") | O51: =IF(AND(ISNUMBER(O50),ISNUMBER(J50)),IFERROR(O50/J50-1,""),"") | P51: =IF(AND(ISNUMBER(P50),ISNUMBER(K50)),IFERROR(P50/K50-1,""),"") | Q51: =IF(AND(ISNUMBER(Q50),ISNUMBER(L50)),IFERROR(Q50/L50-1,""),"") | R51: =IF(AND(ISNUMBER(R50),ISNUMBER(M50)),IFERROR(R50/M50-1,""),"") | S51: =IF(AND(ISNUMBER(S50),ISNUMBER(N50)),IFERROR(S50/N50-1,""),"") | T51: =IF(AND(ISNUMBER(T50),ISNUMBER(O50)),IFERROR(T50/O50-1,""),"") | U51: =IF(AND(ISNUMBER(U50),ISNUMBER(P50)),IFERROR(U50/P50-1,""),"") | ... CA51: =IF(AND(ISNUMBER(CA50),ISNUMBER(BV50)),IFERROR(CA50/BV50-1,""),"") | CB51: =IF(AND(ISNUMBER(CB50),ISNUMBER(CA50)),IFERROR(CB50/CA50-1,""),"") | CC51: =IF(AND(ISNUMBER(CC50),ISNUMBER(CB50)),IFERROR(CC50/CB50-1,""),"") | CD51: =IF(AND(ISNUMBER(CD50),ISNUMBER(CC50)),IFERROR(CD50/CC50-1,""),"") | CE51: =IF(AND(ISNUMBER(CE50),ISNUMBER(CD50)),IFERROR(CE50/CD50-1,""),"")
B52: Δ LTL revenue (statistics basis) y/y — volume / ex-fuel yield / fuel surcharge:
B53: Volume effect (Δ tons × prior-period revenue/cwt) | D53: =IF(AND(ISNUMBER(D15),ISNUMBER(C15),ISNUMBER(C33)),(D15-C15)*20*C33/1000,"") | E53: =IF(AND(ISNUMBER(E15),ISNUMBER(D15),ISNUMBER(D33)),(E15-D15)*20*D33/1000,"") | F53: =IF(AND(ISNUMBER(F15),ISNUMBER(E15),ISNUMBER(E33)),(F15-E15)*20*E33/1000,"") | G53: =IF(AND(ISNUMBER(G15),ISNUMBER(F15),ISNUMBER(F33)),(G15-F15)*20*F33/1000,"") | H53: =IF(AND(ISNUMBER(H15),ISNUMBER(G15),ISNUMBER(G33)),(H15-G15)*20*G33/1000,"") | I53: =IF(AND(ISNUMBER(I15),ISNUMBER(H15),ISNUMBER(H33)),(I15-H15)*20*H33/1000,"") | N53: =IF(AND(ISNUMBER(N15),ISNUMBER(I15),ISNUMBER(I33)),(N15-I15)*20*I33/1000,"") | O53: =IF(AND(ISNUMBER(O15),ISNUMBER(J15),ISNUMBER(J33)),(O15-J15)*20*J33/1000,"") | P53: =IF(AND(ISNUMBER(P15),ISNUMBER(K15),ISNUMBER(K33)),(P15-K15)*20*K33/1000,"") | Q53: =IF(AND(ISNUMBER(Q15),ISNUMBER(L15),ISNUMBER(L33)),(Q15-L15)*20*L33/1000,"") | R53: =IF(AND(ISNUMBER(R15),ISNUMBER(M15),ISNUMBER(M33)),(R15-M15)*20*M33/1000,"") | S53: =IF(AND(ISNUMBER(S15),ISNUMBER(N15),ISNUMBER(N33)),(S15-N15)*20*N33/1000,"") | T53: =IF(AND(ISNUMBER(T15),ISNUMBER(O15),ISNUMBER(O33)),(T15-O15)*20*O33/1000,"") | U53: =IF(AND(ISNUMBER(U15),ISNUMBER(P15),ISNUMBER(P33)),(U15-P15)*20*P33/1000,"") | ... CA53: =IF(AND(ISNUMBER(CA15),ISNUMBER(BV15),ISNUMBER(BV33)),(CA15-BV15)*20*BV33/1000,"") | CB53: =IF(AND(ISNUMBER(CB15),ISNUMBER(CA15),ISNUMBER(CA33)),(CB15-CA15)*20*CA33/1000,"") | CC53: =IF(AND(ISNUMBER(CC15),ISNUMBER(CB15),ISNUMBER(CB33)),(CC15-CB15)*20*CB33/1000,"") | CD53: =IF(AND(ISNUMBER(CD15),ISNUMBER(CC15),ISNUMBER(CC33)),(CD15-CC15)*20*CC33/1000,"") | CE53: =IF(AND(ISNUMBER(CE15),ISNUMBER(CD15),ISNUMBER(CD33)),(CE15-CD15)*20*CD33/1000,"")
B54: Ex-fuel yield effect (Δ ex-fuel revenue/cwt × tons) | D54: =IF(AND(ISNUMBER(D28),ISNUMBER(C28),ISNUMBER(D15)),(D28-C28)*20*D15/1000,"") | E54: =IF(AND(ISNUMBER(E28),ISNUMBER(D28),ISNUMBER(E15)),(E28-D28)*20*E15/1000,"") | F54: =IF(AND(ISNUMBER(F28),ISNUMBER(E28),ISNUMBER(F15)),(F28-E28)*20*F15/1000,"") | G54: =IF(AND(ISNUMBER(G28),ISNUMBER(F28),ISNUMBER(G15)),(G28-F28)*20*G15/1000,"") | H54: =IF(AND(ISNUMBER(H28),ISNUMBER(G28),ISNUMBER(H15)),(H28-G28)*20*H15/1000,"") | I54: =IF(AND(ISNUMBER(I28),ISNUMBER(H28),ISNUMBER(I15)),(I28-H28)*20*I15/1000,"") | N54: =IF(AND(ISNUMBER(N28),ISNUMBER(I28),ISNUMBER(N15)),(N28-I28)*20*N15/1000,"") | O54: =IF(AND(ISNUMBER(O28),ISNUMBER(J28),ISNUMBER(O15)),(O28-J28)*20*O15/1000,"") | P54: =IF(AND(ISNUMBER(P28),ISNUMBER(K28),ISNUMBER(P15)),(P28-K28)*20*P15/1000,"") | Q54: =IF(AND(ISNUMBER(Q28),ISNUMBER(L28),ISNUMBER(Q15)),(Q28-L28)*20*Q15/1000,"") | R54: =IF(AND(ISNUMBER(R28),ISNUMBER(M28),ISNUMBER(R15)),(R28-M28)*20*R15/1000,"") | S54: =IF(AND(ISNUMBER(S28),ISNUMBER(N28),ISNUMBER(S15)),(S28-N28)*20*S15/1000,"") | T54: =IF(AND(ISNUMBER(T28),ISNUMBER(O28),ISNUMBER(T15)),(T28-O28)*20*T15/1000,"") | U54: =IF(AND(ISNUMBER(U28),ISNUMBER(P28),ISNUMBER(U15)),(U28-P28)*20*U15/1000,"") | ... CA54: =IF(AND(ISNUMBER(CA28),ISNUMBER(BV28),ISNUMBER(CA15)),(CA28-BV28)*20*CA15/1000,"") | CB54: =IF(AND(ISNUMBER(CB28),ISNUMBER(CA28),ISNUMBER(CB15)),(CB28-CA28)*20*CB15/1000,"") | CC54: =IF(AND(ISNUMBER(CC28),ISNUMBER(CB28),ISNUMBER(CC15)),(CC28-CB28)*20*CC15/1000,"") | CD54: =IF(AND(ISNUMBER(CD28),ISNUMBER(CC28),ISNUMBER(CD15)),(CD28-CC28)*20*CD15/1000,"") | CE54: =IF(AND(ISNUMBER(CE28),ISNUMBER(CD28),ISNUMBER(CE15)),(CE28-CD28)*20*CE15/1000,"")
B55: Fuel surcharge effect (Δ fuel surcharge/cwt × tons) | D55: =IF(AND(ISNUMBER(D31),ISNUMBER(C31),ISNUMBER(D15)),(D31-C31)*20*D15/1000,"") | E55: =IF(AND(ISNUMBER(E31),ISNUMBER(D31),ISNUMBER(E15)),(E31-D31)*20*E15/1000,"") | F55: =IF(AND(ISNUMBER(F31),ISNUMBER(E31),ISNUMBER(F15)),(F31-E31)*20*F15/1000,"") | G55: =IF(AND(ISNUMBER(G31),ISNUMBER(F31),ISNUMBER(G15)),(G31-F31)*20*G15/1000,"") | H55: =IF(AND(ISNUMBER(H31),ISNUMBER(G31),ISNUMBER(H15)),(H31-G31)*20*H15/1000,"") | I55: =IF(AND(ISNUMBER(I31),ISNUMBER(H31),ISNUMBER(I15)),(I31-H31)*20*I15/1000,"") | N55: =IF(AND(ISNUMBER(N31),ISNUMBER(I31),ISNUMBER(N15)),(N31-I31)*20*N15/1000,"") | O55: =IF(AND(ISNUMBER(O31),ISNUMBER(J31),ISNUMBER(O15)),(O31-J31)*20*O15/1000,"") | P55: =IF(AND(ISNUMBER(P31),ISNUMBER(K31),ISNUMBER(P15)),(P31-K31)*20*P15/1000,"") | Q55: =IF(AND(ISNUMBER(Q31),ISNUMBER(L31),ISNUMBER(Q15)),(Q31-L31)*20*Q15/1000,"") | R55: =IF(AND(ISNUMBER(R31),ISNUMBER(M31),ISNUMBER(R15)),(R31-M31)*20*R15/1000,"") | S55: =IF(AND(ISNUMBER(S31),ISNUMBER(N31),ISNUMBER(S15)),(S31-N31)*20*S15/1000,"") | T55: =IF(AND(ISNUMBER(T31),ISNUMBER(O31),ISNUMBER(T15)),(T31-O31)*20*T15/1000,"") | U55: =IF(AND(ISNUMBER(U31),ISNUMBER(P31),ISNUMBER(U15)),(U31-P31)*20*U15/1000,"") | ... CA55: =IF(AND(ISNUMBER(CA31),ISNUMBER(BV31),ISNUMBER(CA15)),(CA31-BV31)*20*CA15/1000,"") | CB55: =IF(AND(ISNUMBER(CB31),ISNUMBER(CA31),ISNUMBER(CB15)),(CB31-CA31)*20*CB15/1000,"") | CC55: =IF(AND(ISNUMBER(CC31),ISNUMBER(CB31),ISNUMBER(CC15)),(CC31-CB31)*20*CC15/1000,"") | CD55: =IF(AND(ISNUMBER(CD31),ISNUMBER(CC31),ISNUMBER(CD15)),(CD31-CC31)*20*CD15/1000,"") | CE55: =IF(AND(ISNUMBER(CE31),ISNUMBER(CD31),ISNUMBER(CE15)),(CE31-CD31)*20*CE15/1000,"")
B56: Check: Σ effects vs Δ statistics-basis revenue (should be 0) | D56: =IF(ISNUMBER(D53),ROUND(D53+D54+D55-(D40-C40),1),"") | E56: =IF(ISNUMBER(E53),ROUND(E53+E54+E55-(E40-D40),1),"") | F56: =IF(ISNUMBER(F53),ROUND(F53+F54+F55-(F40-E40),1),"") | G56: =IF(ISNUMBER(G53),ROUND(G53+G54+G55-(G40-F40),1),"") | H56: =IF(ISNUMBER(H53),ROUND(H53+H54+H55-(H40-G40),1),"") | I56: =IF(ISNUMBER(I53),ROUND(I53+I54+I55-(I40-H40),1),"") | N56: =IF(ISNUMBER(N53),ROUND(N53+N54+N55-(N40-I40),1),"") | O56: =IF(ISNUMBER(O53),ROUND(O53+O54+O55-(O40-J40),1),"") | P56: =IF(ISNUMBER(P53),ROUND(P53+P54+P55-(P40-K40),1),"") | Q56: =IF(ISNUMBER(Q53),ROUND(Q53+Q54+Q55-(Q40-L40),1),"") | R56: =IF(ISNUMBER(R53),ROUND(R53+R54+R55-(R40-M40),1),"") | S56: =IF(ISNUMBER(S53),ROUND(S53+S54+S55-(S40-N40),1),"") | T56: =IF(ISNUMBER(T53),ROUND(T53+T54+T55-(T40-O40),1),"") | U56: =IF(ISNUMBER(U53),ROUND(U53+U54+U55-(U40-P40),1),"") | ... CA56: =IF(ISNUMBER(CA53),ROUND(CA53+CA54+CA55-(CA40-BV40),1),"") | CB56: =IF(ISNUMBER(CB53),ROUND(CB53+CB54+CB55-(CB40-CA40),1),"") | CC56: =IF(ISNUMBER(CC53),ROUND(CC53+CC54+CC55-(CC40-CB40),1),"") | CD56: =IF(ISNUMBER(CD53),ROUND(CD53+CD54+CD55-(CD40-CC40),1),"") | CE56: =IF(ISNUMBER(CE53),ROUND(CE53+CE54+CE55-(CE40-CD40),1),"")
B58: Network, capacity & productivity (10-K, year end; memo — historical only) | CF58: NETWORK — historical only (not forecast)
B59: Service centers (year end) | C59: 182 | D59: 192 | E59: 206 | F59: 210 | G59: 213 | H59: 216 | I59: 218 | N59: 221 | S59: 222 | X59: 225 | AC59: 226 | AH59: 228 | AM59: 235 | AR59: 236 | AW59: 244 | BB59: 251 | BG59: 255 | BL59: 257 | BQ59: 261 | BV59: 260 | CH59: =IFERROR((CE59/BV59)^(1/5)-1,"n/m") | CI59: =IFERROR((BV59/AW59)^(1/5)-1,"n/m") | CJ59: =IFERROR((BV59/X59)^(1/10)-1,"n/m") | CK59: =IFERROR((BV59/C59)^(1/19)-1,"n/m")
B60: Tractors (owned, year end) | C60: 4643 | D60: 5016 | E60: 5058 | F60: 5390 | G60: 5718 | H60: 5830 | I60: 6099 | N60: 6296 | S60: 6907 | X60: 7688 | AC60: 7994 | AH60: 8316 | AM60: 9254 | AR60: 9296 | AW60: 9288 | BB60: 10403 | BG60: 11274 | BL60: 10791 | BQ60: 11284 | BV60: 10184
B61: Linehaul trailers (year end) | C61: 13122 | D61: 14001 | E61: 14365 | F61: 15538 | G61: 15178 | H61: 16302 | I61: 17280 | N61: 18077 | S61: 19556 | X61: 21540 | AC61: 22970 | AH61: 23100 | AM61: 24685 | AR61: 25357 | AW61: 24583 | BB61: 27917 | BG61: 31252 | BL61: 31233 | BQ61: 31451 | BV61: 30824
B62: Full-time employees (year end) | C62: 10762 | D62: 11573 | E62: 10864 | F62: 9608 | G62: 11179 | H62: 12022 | I62: 13016 | N62: 14073 | S62: 16443 | X62: 17931 | AC62: 17543 | AH62: 19183 | AM62: 21279 | AR62: 20105 | AW62: 19779 | BB62: 23663 | BG62: 23471 | BL62: 22902 | BQ62: 21895 | BV62: 20591
B63: LTL tons per day per service center | C63: =IF(ISNUMBER(C59),IFERROR(C12/C59,""),"") | D63: =IF(ISNUMBER(D59),IFERROR(D12/D59,""),"") | E63: =IF(ISNUMBER(E59),IFERROR(E12/E59,""),"") | F63: =IF(ISNUMBER(F59),IFERROR(F12/F59,""),"") | G63: =IF(ISNUMBER(G59),IFERROR(G12/G59,""),"") | H63: =IF(ISNUMBER(H59),IFERROR(H12/H59,""),"") | I63: =IF(ISNUMBER(I59),IFERROR(I12/I59,""),"") | N63: =IF(ISNUMBER(N59),IFERROR(N12/N59,""),"") | S63: =IF(ISNUMBER(S59),IFERROR(S12/S59,""),"") | X63: =IF(ISNUMBER(X59),IFERROR(X12/X59,""),"") | AC63: =IF(ISNUMBER(AC59),IFERROR(AC12/AC59,""),"") | AH63: =IF(ISNUMBER(AH59),IFERROR(AH12/AH59,""),"") | AM63: =IF(ISNUMBER(AM59),IFERROR(AM12/AM59,""),"") | AR63: =IF(ISNUMBER(AR59),IFERROR(AR12/AR59,""),"") | AW63: =IF(ISNUMBER(AW59),IFERROR(AW12/AW59,""),"") | BB63: =IF(ISNUMBER(BB59),IFERROR(BB12/BB59,""),"") | BG63: =IF(ISNUMBER(BG59),IFERROR(BG12/BG59,""),"") | BL63: =IF(ISNUMBER(BL59),IFERROR(BL12/BL59,""),"") | BQ63: =IF(ISNUMBER(BQ59),IFERROR(BQ12/BQ59,""),"") | BV63: =IF(ISNUMBER(BV59),IFERROR(BV12/BV59,""),"")
B64: Revenue per year-end employee ($000) | C64: =IF(ISNUMBER(C62),IFERROR(C100/C62*1000,""),"") | D64: =IF(ISNUMBER(D62),IFERROR(D100/D62*1000,""),"") | E64: =IF(ISNUMBER(E62),IFERROR(E100/E62*1000,""),"") | F64: =IF(ISNUMBER(F62),IFERROR(F100/F62*1000,""),"") | G64: =IF(ISNUMBER(G62),IFERROR(G100/G62*1000,""),"") | H64: =IF(ISNUMBER(H62),IFERROR(H100/H62*1000,""),"") | I64: =IF(ISNUMBER(I62),IFERROR(I100/I62*1000,""),"") | N64: =IF(ISNUMBER(N62),IFERROR(N100/N62*1000,""),"") | S64: =IF(ISNUMBER(S62),IFERROR(S100/S62*1000,""),"") | X64: =IF(ISNUMBER(X62),IFERROR(X100/X62*1000,""),"") | AC64: =IF(ISNUMBER(AC62),IFERROR(AC100/AC62*1000,""),"") | AH64: =IF(ISNUMBER(AH62),IFERROR(AH100/AH62*1000,""),"") | AM64: =IF(ISNUMBER(AM62),IFERROR(AM100/AM62*1000,""),"") | AR64: =IF(ISNUMBER(AR62),IFERROR(AR100/AR62*1000,""),"") | AW64: =IF(ISNUMBER(AW62),IFERROR(AW100/AW62*1000,""),"") | BB64: =IF(ISNUMBER(BB62),IFERROR(BB100/BB62*1000,""),"") | BG64: =IF(ISNUMBER(BG62),IFERROR(BG100/BG62*1000,""),"") | BL64: =IF(ISNUMBER(BL62),IFERROR(BL100/BL62*1000,""),"") | BQ64: =IF(ISNUMBER(BQ62),IFERROR(BQ100/BQ62*1000,""),"") | BV64: =IF(ISNUMBER(BV62),IFERROR(BV100/BV62*1000,""),"")
B65: LTL shipments per day per 100 average employees (from 2019) | C65: =IF(ISNUMBER(C24),IFERROR(C20/C24*100,""),"") | D65: =IF(ISNUMBER(D24),IFERROR(D20/D24*100,""),"") | E65: =IF(ISNUMBER(E24),IFERROR(E20/E24*100,""),"") | F65: =IF(ISNUMBER(F24),IFERROR(F20/F24*100,""),"") | G65: =IF(ISNUMBER(G24),IFERROR(G20/G24*100,""),"") | H65: =IF(ISNUMBER(H24),IFERROR(H20/H24*100,""),"") | I65: =IF(ISNUMBER(I24),IFERROR(I20/I24*100,""),"") | J65: =IF(ISNUMBER(J24),IFERROR(J20/J24*100,""),"") | ... BX65: =IF(ISNUMBER(BX24),IFERROR(BX20/BX24*100,""),"")
B67: Operating ratio build — cost lines % of revenue → operating ratio → Q3/Q4-26E calibration (seasonality) · 2027E+ OR lever | CF67: OPERATING RATIO — modelling logic (operating ratio = total operating expenses ÷ revenue; ODFL's primary profitability KPI)
B68: Salaries, wages & benefits % of revenue | C68: =IF(AND(ISNUMBER(C101),ISNUMBER(C100)),IFERROR(C101/C100,""),"") | D68: =IF(AND(ISNUMBER(D101),ISNUMBER(D100)),IFERROR(D101/D100,""),"") | E68: =IF(AND(ISNUMBER(E101),ISNUMBER(E100)),IFERROR(E101/E100,""),"") | F68: =IF(AND(ISNUMBER(F101),ISNUMBER(F100)),IFERROR(F101/F100,""),"") | G68: =IF(AND(ISNUMBER(G101),ISNUMBER(G100)),IFERROR(G101/G100,""),"") | H68: =IF(AND(ISNUMBER(H101),ISNUMBER(H100)),IFERROR(H101/H100,""),"") | I68: =IF(AND(ISNUMBER(I101),ISNUMBER(I100)),IFERROR(I101/I100,""),"") | J68: =IF(AND(ISNUMBER(J101),ISNUMBER(J100)),IFERROR(J101/J100,""),"") | ... BX68: =IF(AND(ISNUMBER(BX101),ISNUMBER(BX100)),IFERROR(BX101/BX100,""),"") | BY68: =BY69*(1+BY87) | BZ68: =BZ69*(1+BZ87) | CA68: =IF(AND(ISNUMBER(CA101),ISNUMBER(CA100)),IFERROR(CA101/CA100,""),"") | CB68: =$CA$68*CB89 | CC68: =$CA$68*CC89 | CD68: =$CA$68*CD89 | CE68: =$CA$68*CE89 | CH68: =IFERROR(AVERAGE(CA68,CB68,CC68,CD68,CE68),"n/m") | CI68: =IFERROR(AVERAGE(BB68,BG68,BL68,BQ68,BV68),"n/m") | CJ68: =IFERROR(AVERAGE(AC68,AH68,AM68,AR68,AW68,BB68,BG68,BL68,BQ68,BV68),"n/m") | CK68: =IFERROR(AVERAGE(C68,D68,E68,F68,G68,H68,I68,N68,S68,X68,AC68,AH68,AM68,AR68,AW68,BB68,BG68,BL68,BQ68,BV68),"n/m")
B69: before calibration (Q3/Q4-26E helper: prior-year quarter + 1H/26 y/y drift) | BY69: =BT68+((BW101+BX101)/(BW100+BX100)-(BR101+BS101)/(BR100+BS100)) | BZ69: =BU68+((BW101+BX101)/(BW100+BX100)-(BR101+BS101)/(BR100+BS100))
B70: Operating supplies & expenses (incl. fuel) % of revenue | C70: =IF(AND(ISNUMBER(C102),ISNUMBER(C100)),IFERROR(C102/C100,""),"") | D70: =IF(AND(ISNUMBER(D102),ISNUMBER(D100)),IFERROR(D102/D100,""),"") | E70: =IF(AND(ISNUMBER(E102),ISNUMBER(E100)),IFERROR(E102/E100,""),"") | F70: =IF(AND(ISNUMBER(F102),ISNUMBER(F100)),IFERROR(F102/F100,""),"") | G70: =IF(AND(ISNUMBER(G102),ISNUMBER(G100)),IFERROR(G102/G100,""),"") | H70: =IF(AND(ISNUMBER(H102),ISNUMBER(H100)),IFERROR(H102/H100,""),"") | I70: =IF(AND(ISNUMBER(I102),ISNUMBER(I100)),IFERROR(I102/I100,""),"") | J70: =IF(AND(ISNUMBER(J102),ISNUMBER(J100)),IFERROR(J102/J100,""),"") | ... BX70: =IF(AND(ISNUMBER(BX102),ISNUMBER(BX100)),IFERROR(BX102/BX100,""),"") | BY70: =BY71*(1+BY87) | BZ70: =BZ71*(1+BZ87) | CA70: =IF(AND(ISNUMBER(CA102),ISNUMBER(CA100)),IFERROR(CA102/CA100,""),"") | CB70: =$CA$70*CB89 | CC70: =$CA$70*CC89 | CD70: =$CA$70*CD89 | CE70: =$CA$70*CE89 | CH70: =IFERROR(AVERAGE(CA70,CB70,CC70,CD70,CE70),"n/m") | CI70: =IFERROR(AVERAGE(BB70,BG70,BL70,BQ70,BV70),"n/m") | CJ70: =IFERROR(AVERAGE(AC70,AH70,AM70,AR70,AW70,BB70,BG70,BL70,BQ70,BV70),"n/m") | CK70: =IFERROR(AVERAGE(C70,D70,E70,F70,G70,H70,I70,N70,S70,X70,AC70,AH70,AM70,AR70,AW70,BB70,BG70,BL70,BQ70,BV70),"n/m")
B71: before calibration (Q3/Q4-26E helper: prior-year quarter + 1H/26 y/y drift) | BY71: =BT70+((BW102+BX102)/(BW100+BX100)-(BR102+BS102)/(BR100+BS100)) | BZ71: =BU70+((BW102+BX102)/(BW100+BX100)-(BR102+BS102)/(BR100+BS100))
B72: General supplies & expenses % of revenue | C72: =IF(AND(ISNUMBER(C103),ISNUMBER(C100)),IFERROR(C103/C100,""),"") | D72: =IF(AND(ISNUMBER(D103),ISNUMBER(D100)),IFERROR(D103/D100,""),"") | E72: =IF(AND(ISNUMBER(E103),ISNUMBER(E100)),IFERROR(E103/E100,""),"") | F72: =IF(AND(ISNUMBER(F103),ISNUMBER(F100)),IFERROR(F103/F100,""),"") | G72: =IF(AND(ISNUMBER(G103),ISNUMBER(G100)),IFERROR(G103/G100,""),"") | H72: =IF(AND(ISNUMBER(H103),ISNUMBER(H100)),IFERROR(H103/H100,""),"") | I72: =IF(AND(ISNUMBER(I103),ISNUMBER(I100)),IFERROR(I103/I100,""),"") | J72: =IF(AND(ISNUMBER(J103),ISNUMBER(J100)),IFERROR(J103/J100,""),"") | ... BX72: =IF(AND(ISNUMBER(BX103),ISNUMBER(BX100)),IFERROR(BX103/BX100,""),"") | BY72: =BY73*(1+BY87) | BZ72: =BZ73*(1+BZ87) | CA72: =IF(AND(ISNUMBER(CA103),ISNUMBER(CA100)),IFERROR(CA103/CA100,""),"") | CB72: =$CA$72*CB89 | CC72: =$CA$72*CC89 | CD72: =$CA$72*CD89 | CE72: =$CA$72*CE89 | CH72: =IFERROR(AVERAGE(CA72,CB72,CC72,CD72,CE72),"n/m") | CI72: =IFERROR(AVERAGE(BB72,BG72,BL72,BQ72,BV72),"n/m") | CJ72: =IFERROR(AVERAGE(AC72,AH72,AM72,AR72,AW72,BB72,BG72,BL72,BQ72,BV72),"n/m") | CK72: =IFERROR(AVERAGE(C72,D72,E72,F72,G72,H72,I72,N72,S72,X72,AC72,AH72,AM72,AR72,AW72,BB72,BG72,BL72,BQ72,BV72),"n/m")
B73: before calibration (Q3/Q4-26E helper: prior-year quarter + 1H/26 y/y drift) | BY73: =BT72+((BW103+BX103)/(BW100+BX100)-(BR103+BS103)/(BR100+BS100)) | BZ73: =BU72+((BW103+BX103)/(BW100+BX100)-(BR103+BS103)/(BR100+BS100))
B74: Operating taxes & licenses % of revenue | C74: =IF(AND(ISNUMBER(C104),ISNUMBER(C100)),IFERROR(C104/C100,""),"") | D74: =IF(AND(ISNUMBER(D104),ISNUMBER(D100)),IFERROR(D104/D100,""),"") | E74: =IF(AND(ISNUMBER(E104),ISNUMBER(E100)),IFERROR(E104/E100,""),"") | F74: =IF(AND(ISNUMBER(F104),ISNUMBER(F100)),IFERROR(F104/F100,""),"") | G74: =IF(AND(ISNUMBER(G104),ISNUMBER(G100)),IFERROR(G104/G100,""),"") | H74: =IF(AND(ISNUMBER(H104),ISNUMBER(H100)),IFERROR(H104/H100,""),"") | I74: =IF(AND(ISNUMBER(I104),ISNUMBER(I100)),IFERROR(I104/I100,""),"") | J74: =IF(AND(ISNUMBER(J104),ISNUMBER(J100)),IFERROR(J104/J100,""),"") | ... BX74: =IF(AND(ISNUMBER(BX104),ISNUMBER(BX100)),IFERROR(BX104/BX100,""),"") | BY74: =BY75*(1+BY87) | BZ74: =BZ75*(1+BZ87) | CA74: =IF(AND(ISNUMBER(CA104),ISNUMBER(CA100)),IFERROR(CA104/CA100,""),"") | CB74: =$CA$74*CB89 | CC74: =$CA$74*CC89 | CD74: =$CA$74*CD89 | CE74: =$CA$74*CE89 | CH74: =IFERROR(AVERAGE(CA74,CB74,CC74,CD74,CE74),"n/m") | CI74: =IFERROR(AVERAGE(BB74,BG74,BL74,BQ74,BV74),"n/m") | CJ74: =IFERROR(AVERAGE(AC74,AH74,AM74,AR74,AW74,BB74,BG74,BL74,BQ74,BV74),"n/m") | CK74: =IFERROR(AVERAGE(C74,D74,E74,F74,G74,H74,I74,N74,S74,X74,AC74,AH74,AM74,AR74,AW74,BB74,BG74,BL74,BQ74,BV74),"n/m")
B75: before calibration (Q3/Q4-26E helper: prior-year quarter + 1H/26 y/y drift) | BY75: =BT74+((BW104+BX104)/(BW100+BX100)-(BR104+BS104)/(BR100+BS100)) | BZ75: =BU74+((BW104+BX104)/(BW100+BX100)-(BR104+BS104)/(BR100+BS100))
B76: Insurance & claims % of revenue | C76: =IF(AND(ISNUMBER(C105),ISNUMBER(C100)),IFERROR(C105/C100,""),"") | D76: =IF(AND(ISNUMBER(D105),ISNUMBER(D100)),IFERROR(D105/D100,""),"") | E76: =IF(AND(ISNUMBER(E105),ISNUMBER(E100)),IFERROR(E105/E100,""),"") | F76: =IF(AND(ISNUMBER(F105),ISNUMBER(F100)),IFERROR(F105/F100,""),"") | G76: =IF(AND(ISNUMBER(G105),ISNUMBER(G100)),IFERROR(G105/G100,""),"") | H76: =IF(AND(ISNUMBER(H105),ISNUMBER(H100)),IFERROR(H105/H100,""),"") | I76: =IF(AND(ISNUMBER(I105),ISNUMBER(I100)),IFERROR(I105/I100,""),"") | J76: =IF(AND(ISNUMBER(J105),ISNUMBER(J100)),IFERROR(J105/J100,""),"") | ... BX76: =IF(AND(ISNUMBER(BX105),ISNUMBER(BX100)),IFERROR(BX105/BX100,""),"") | BY76: =BY77*(1+BY87) | BZ76: =BZ77*(1+BZ87) | CA76: =IF(AND(ISNUMBER(CA105),ISNUMBER(CA100)),IFERROR(CA105/CA100,""),"") | CB76: =$CA$76*CB89 | CC76: =$CA$76*CC89 | CD76: =$CA$76*CD89 | CE76: =$CA$76*CE89 | CH76: =IFERROR(AVERAGE(CA76,CB76,CC76,CD76,CE76),"n/m") | CI76: =IFERROR(AVERAGE(BB76,BG76,BL76,BQ76,BV76),"n/m") | CJ76: =IFERROR(AVERAGE(AC76,AH76,AM76,AR76,AW76,BB76,BG76,BL76,BQ76,BV76),"n/m") | CK76: =IFERROR(AVERAGE(C76,D76,E76,F76,G76,H76,I76,N76,S76,X76,AC76,AH76,AM76,AR76,AW76,BB76,BG76,BL76,BQ76,BV76),"n/m")
B77: before calibration (Q3/Q4-26E helper: prior-year quarter + 1H/26 y/y drift) | BY77: =BT76+((BW105+BX105)/(BW100+BX100)-(BR105+BS105)/(BR100+BS100)) | BZ77: =BU76+((BW105+BX105)/(BW100+BX100)-(BR105+BS105)/(BR100+BS100))
B78: Communications & utilities % of revenue | C78: =IF(AND(ISNUMBER(C106),ISNUMBER(C100)),IFERROR(C106/C100,""),"") | D78: =IF(AND(ISNUMBER(D106),ISNUMBER(D100)),IFERROR(D106/D100,""),"") | E78: =IF(AND(ISNUMBER(E106),ISNUMBER(E100)),IFERROR(E106/E100,""),"") | F78: =IF(AND(ISNUMBER(F106),ISNUMBER(F100)),IFERROR(F106/F100,""),"") | G78: =IF(AND(ISNUMBER(G106),ISNUMBER(G100)),IFERROR(G106/G100,""),"") | H78: =IF(AND(ISNUMBER(H106),ISNUMBER(H100)),IFERROR(H106/H100,""),"") | I78: =IF(AND(ISNUMBER(I106),ISNUMBER(I100)),IFERROR(I106/I100,""),"") | J78: =IF(AND(ISNUMBER(J106),ISNUMBER(J100)),IFERROR(J106/J100,""),"") | ... BX78: =IF(AND(ISNUMBER(BX106),ISNUMBER(BX100)),IFERROR(BX106/BX100,""),"") | BY78: =BY79*(1+BY87) | BZ78: =BZ79*(1+BZ87) | CA78: =IF(AND(ISNUMBER(CA106),ISNUMBER(CA100)),IFERROR(CA106/CA100,""),"") | CB78: =$CA$78*CB89 | CC78: =$CA$78*CC89 | CD78: =$CA$78*CD89 | CE78: =$CA$78*CE89 | CH78: =IFERROR(AVERAGE(CA78,CB78,CC78,CD78,CE78),"n/m") | CI78: =IFERROR(AVERAGE(BB78,BG78,BL78,BQ78,BV78),"n/m") | CJ78: =IFERROR(AVERAGE(AC78,AH78,AM78,AR78,AW78,BB78,BG78,BL78,BQ78,BV78),"n/m") | CK78: =IFERROR(AVERAGE(C78,D78,E78,F78,G78,H78,I78,N78,S78,X78,AC78,AH78,AM78,AR78,AW78,BB78,BG78,BL78,BQ78,BV78),"n/m")
B79: before calibration (Q3/Q4-26E helper: prior-year quarter + 1H/26 y/y drift) | BY79: =BT78+((BW106+BX106)/(BW100+BX100)-(BR106+BS106)/(BR100+BS100)) | BZ79: =BU78+((BW106+BX106)/(BW100+BX100)-(BR106+BS106)/(BR100+BS100))
B80: Purchased transportation % of revenue | C80: =IF(AND(ISNUMBER(C107),ISNUMBER(C100)),IFERROR(C107/C100,""),"") | D80: =IF(AND(ISNUMBER(D107),ISNUMBER(D100)),IFERROR(D107/D100,""),"") | E80: =IF(AND(ISNUMBER(E107),ISNUMBER(E100)),IFERROR(E107/E100,""),"") | F80: =IF(AND(ISNUMBER(F107),ISNUMBER(F100)),IFERROR(F107/F100,""),"") | G80: =IF(AND(ISNUMBER(G107),ISNUMBER(G100)),IFERROR(G107/G100,""),"") | H80: =IF(AND(ISNUMBER(H107),ISNUMBER(H100)),IFERROR(H107/H100,""),"") | I80: =IF(AND(ISNUMBER(I107),ISNUMBER(I100)),IFERROR(I107/I100,""),"") | J80: =IF(AND(ISNUMBER(J107),ISNUMBER(J100)),IFERROR(J107/J100,""),"") | ... BX80: =IF(AND(ISNUMBER(BX107),ISNUMBER(BX100)),IFERROR(BX107/BX100,""),"") | BY80: =BY81*(1+BY87) | BZ80: =BZ81*(1+BZ87) | CA80: =IF(AND(ISNUMBER(CA107),ISNUMBER(CA100)),IFERROR(CA107/CA100,""),"") | CB80: =$CA$80*CB89 | CC80: =$CA$80*CC89 | CD80: =$CA$80*CD89 | CE80: =$CA$80*CE89 | CH80: =IFERROR(AVERAGE(CA80,CB80,CC80,CD80,CE80),"n/m") | CI80: =IFERROR(AVERAGE(BB80,BG80,BL80,BQ80,BV80),"n/m") | CJ80: =IFERROR(AVERAGE(AC80,AH80,AM80,AR80,AW80,BB80,BG80,BL80,BQ80,BV80),"n/m") | CK80: =IFERROR(AVERAGE(C80,D80,E80,F80,G80,H80,I80,N80,S80,X80,AC80,AH80,AM80,AR80,AW80,BB80,BG80,BL80,BQ80,BV80),"n/m")
B81: before calibration (Q3/Q4-26E helper: prior-year quarter + 1H/26 y/y drift) | BY81: =BT80+((BW107+BX107)/(BW100+BX100)-(BR107+BS107)/(BR100+BS100)) | BZ81: =BU80+((BW107+BX107)/(BW100+BX100)-(BR107+BS107)/(BR100+BS100))
B82: Depreciation & amortization % of revenue | C82: =IF(AND(ISNUMBER(C108),ISNUMBER(C100)),IFERROR(C108/C100,""),"") | D82: =IF(AND(ISNUMBER(D108),ISNUMBER(D100)),IFERROR(D108/D100,""),"") | E82: =IF(AND(ISNUMBER(E108),ISNUMBER(E100)),IFERROR(E108/E100,""),"") | F82: =IF(AND(ISNUMBER(F108),ISNUMBER(F100)),IFERROR(F108/F100,""),"") | G82: =IF(AND(ISNUMBER(G108),ISNUMBER(G100)),IFERROR(G108/G100,""),"") | H82: =IF(AND(ISNUMBER(H108),ISNUMBER(H100)),IFERROR(H108/H100,""),"") | I82: =IF(AND(ISNUMBER(I108),ISNUMBER(I100)),IFERROR(I108/I100,""),"") | J82: =IF(AND(ISNUMBER(J108),ISNUMBER(J100)),IFERROR(J108/J100,""),"") | ... CA82: =IF(AND(ISNUMBER(CA108),ISNUMBER(CA100)),IFERROR(CA108/CA100,""),"") | CB82: 0.066 | CC82: 0.066 | CD82: 0.066 | CE82: 0.066 | CF82: Q3/Q4-26E: FY26 D&A point estimate (ODFL guides D&A in the Q4 call; not on EDGAR) less 1H/26, split evenly. 2027E+ input (FY2025 6.6%; capex-led). | CH82: =IFERROR(AVERAGE(CA82,CB82,CC82,CD82,CE82),"n/m") | CI82: =IFERROR(AVERAGE(BB82,BG82,BL82,BQ82,BV82),"n/m") | CJ82: =IFERROR(AVERAGE(AC82,AH82,AM82,AR82,AW82,BB82,BG82,BL82,BQ82,BV82),"n/m") | CK82: =IFERROR(AVERAGE(C82,D82,E82,F82,G82,H82,I82,N82,S82,X82,AC82,AH82,AM82,AR82,AW82,BB82,BG82,BL82,BQ82,BV82),"n/m")
B83: Miscellaneous (income) expense, net % of revenue (incl. disposal gains / losses) | C83: =IF(AND(ISNUMBER(C110),ISNUMBER(C100)),IFERROR(C110/C100,""),"") | D83: =IF(AND(ISNUMBER(D110),ISNUMBER(D100)),IFERROR(D110/D100,""),"") | E83: =IF(AND(ISNUMBER(E110),ISNUMBER(E100)),IFERROR(E110/E100,""),"") | F83: =IF(AND(ISNUMBER(F110),ISNUMBER(F100)),IFERROR(F110/F100,""),"") | G83: =IF(AND(ISNUMBER(G110),ISNUMBER(G100)),IFERROR(G110/G100,""),"") | H83: =IF(AND(ISNUMBER(H110),ISNUMBER(H100)),IFERROR(H110/H100,""),"") | I83: =IF(AND(ISNUMBER(I110),ISNUMBER(I100)),IFERROR(I110/I100,""),"") | J83: =IF(AND(ISNUMBER(J110),ISNUMBER(J100)),IFERROR(J110/J100,""),"") | ... BX83: =IF(AND(ISNUMBER(BX110),ISNUMBER(BX100)),IFERROR(BX110/BX100,""),"") | BY83: =IFERROR(((BW110+BX110)-(BW152+BX152))/(BW100+BX100),"") | BZ83: =IFERROR(((BW110+BX110)-(BW152+BX152))/(BW100+BX100),"") | CA83: =IF(AND(ISNUMBER(CA110),ISNUMBER(CA100)),IFERROR(CA110/CA100,""),"") | CB83: =$BY$83 | CC83: =$BY$83 | CD83: =$BY$83 | CE83: =$BY$83 | CF83: Q3/Q4-26E and 2027E+: 1H/26 run-rate excluding net gains on disposal of property & equipment (no disposal gains forecast). | CH83: =IFERROR(AVERAGE(CA83,CB83,CC83,CD83,CE83),"n/m") | CI83: =IFERROR(AVERAGE(BB83,BG83,BL83,BQ83,BV83),"n/m") | CJ83: =IFERROR(AVERAGE(AC83,AH83,AM83,AR83,AW83,BB83,BG83,BL83,BQ83,BV83),"n/m") | CK83: =IFERROR(AVERAGE(C83,D83,E83,F83,G83,H83,I83,N83,S83,X83,AC83,AH83,AM83,AR83,AW83,BB83,BG83,BL83,BQ83,BV83),"n/m")
B84: Building & office equipment rents % of revenue (separate line to 2012) | C84: =IF(AND(ISNUMBER(C109),ISNUMBER(C100)),IFERROR(C109/C100,""),"") | D84: =IF(AND(ISNUMBER(D109),ISNUMBER(D100)),IFERROR(D109/D100,""),"") | E84: =IF(AND(ISNUMBER(E109),ISNUMBER(E100)),IFERROR(E109/E100,""),"") | F84: =IF(AND(ISNUMBER(F109),ISNUMBER(F100)),IFERROR(F109/F100,""),"") | G84: =IF(AND(ISNUMBER(G109),ISNUMBER(G100)),IFERROR(G109/G100,""),"") | H84: =IF(AND(ISNUMBER(H109),ISNUMBER(H100)),IFERROR(H109/H100,""),"") | I84: =IF(AND(ISNUMBER(I109),ISNUMBER(I100)),IFERROR(I109/I100,""),"") | J84: =IF(AND(ISNUMBER(J109),ISNUMBER(J100)),IFERROR(J109/J100,""),"") | ... BX84: =IF(AND(ISNUMBER(BX109),ISNUMBER(BX100)),IFERROR(BX109/BX100,""),"")
B85: Operating ratio before calibration (Q3/Q4-26E helper) | BY85: =BY69+BY71+BY73+BY75+BY77+BY79+BY81+BY82+BY83 | BZ85: =BZ69+BZ71+BZ73+BZ75+BZ77+BZ79+BZ81+BZ82+BZ83
B86: Operating-ratio target: prior quarter + 2016–25 sequential change (scenario: best / average / worst) | BY86: =$BX$90+CHOOSE(MATCH($CF$2,{"Bull","Base","Bear"},0),$CO$12,$CP$12,$CQ$12) | BZ86: =$BY$90+CHOOSE(MATCH($CF$2,{"Bull","Base","Bear"},0),$CO$13,$CP$13,$CQ$13) | CF86: Q3/26E = Q2/26 operating ratio + Q2→Q3 change; Q4/26E = Q3/26E + Q3→Q4 change (min / average / max of 2016–25 by scenario). Note: the 2016–25 Q2→Q3 best case is 2020 (−332 bps, COVID rebound).
B87: Outlook calibration: proportional shift on variable cost lines (Q3/Q4-26E) | BY87: =(BY86-BY82-BY83)/(BY69+BY71+BY73+BY75+BY77+BY79+BY81)-1 | BZ87: =(BZ86-BZ82-BZ83)/(BZ69+BZ71+BZ73+BZ75+BZ77+BZ79+BZ81)-1 | CF87: Solves the uniform % change in the seven variable cost ratios (vs prior-year quarter + 1H drift) so the operating ratio equals the seasonality target.
B88: Operating ratio — scenario lever (2027E+) | CB88: =CHOOSE(MATCH($CF$2,{"Bull","Base","Bear"},0),$CO$41,$CP$41,$CQ$41) | CC88: =CHOOSE(MATCH($CF$2,{"Bull","Base","Bear"},0),$CO$42,$CP$42,$CQ$42) | CD88: =CHOOSE(MATCH($CF$2,{"Bull","Base","Bear"},0),$CO$43,$CP$43,$CQ$43) | CE88: =CHOOSE(MATCH($CF$2,{"Bull","Base","Bear"},0),$CO$44,$CP$44,$CQ$44) | CF88: Scenario lever OR (Bull / Base / Bear table →). Variable cost lines scaled pro rata to the FY26E mix; D&A and miscellaneous per their inputs.
B89: Variable cost scaling vs FY26E mix (2027E+ helper) | CB89: =(CB88-CB82-CB83)/($CA$68+$CA$70+$CA$72+$CA$74+$CA$76+$CA$78+$CA$80) | CC89: =(CC88-CC82-CC83)/($CA$68+$CA$70+$CA$72+$CA$74+$CA$76+$CA$78+$CA$80) | CD89: =(CD88-CD82-CD83)/($CA$68+$CA$70+$CA$72+$CA$74+$CA$76+$CA$78+$CA$80) | CE89: =(CE88-CE82-CE83)/($CA$68+$CA$70+$CA$72+$CA$74+$CA$76+$CA$78+$CA$80)
B90: Operating ratio (total operating expenses ÷ revenue) | C90: =IF(AND(ISNUMBER(C111),ISNUMBER(C100)),IFERROR(C111/C100,""),"") | D90: =IF(AND(ISNUMBER(D111),ISNUMBER(D100)),IFERROR(D111/D100,""),"") | E90: =IF(AND(ISNUMBER(E111),ISNUMBER(E100)),IFERROR(E111/E100,""),"") | F90: =IF(AND(ISNUMBER(F111),ISNUMBER(F100)),IFERROR(F111/F100,""),"") | G90: =IF(AND(ISNUMBER(G111),ISNUMBER(G100)),IFERROR(G111/G100,""),"") | H90: =IF(AND(ISNUMBER(H111),ISNUMBER(H100)),IFERROR(H111/H100,""),"") | I90: =IF(AND(ISNUMBER(I111),ISNUMBER(I100)),IFERROR(I111/I100,""),"") | J90: =IF(AND(ISNUMBER(J111),ISNUMBER(J100)),IFERROR(J111/J100,""),"") | ... CE90: =IF(AND(ISNUMBER(CE111),ISNUMBER(CE100)),IFERROR(CE111/CE100,""),"") | CH90: =IFERROR(AVERAGE(CA90,CB90,CC90,CD90,CE90),"n/m") | CI90: =IFERROR(AVERAGE(BB90,BG90,BL90,BQ90,BV90),"n/m") | CJ90: =IFERROR(AVERAGE(AC90,AH90,AM90,AR90,AW90,BB90,BG90,BL90,BQ90,BV90),"n/m") | CK90: =IFERROR(AVERAGE(C90,D90,E90,F90,G90,H90,I90,N90,S90,X90,AC90,AH90,AM90,AR90,AW90,BB90,BG90,BL90,BQ90,BV90),"n/m")
B91: Check: Q3/Q4-26E operating ratio vs seasonality target; 2027E+ vs scenario lever (should be 0, bps) | BY91: =ROUND((BY90-BY86)*10000,1) | BZ91: =ROUND((BZ90-BZ86)*10000,1) | CB91: =ROUND((CB90-CB88)*10000,1) | CC91: =ROUND((CC90-CC88)*10000,1) | CD91: =ROUND((CD90-CD88)*10000,1) | CE91: =ROUND((CE90-CE88)*10000,1)
B92: Operating ratio change vs prior quarter (bps → %) | K92: =IF(AND(ISNUMBER(K90),ISNUMBER(J90)),K90-J90,"") | L92: =IF(AND(ISNUMBER(L90),ISNUMBER(K90)),L90-K90,"") | M92: =IF(AND(ISNUMBER(M90),ISNUMBER(L90)),M90-L90,"") | O92: =IF(AND(ISNUMBER(O90),ISNUMBER(M90)),O90-M90,"") | P92: =IF(AND(ISNUMBER(P90),ISNUMBER(O90)),P90-O90,"") | Q92: =IF(AND(ISNUMBER(Q90),ISNUMBER(P90)),Q90-P90,"") | R92: =IF(AND(ISNUMBER(R90),ISNUMBER(Q90)),R90-Q90,"") | T92: =IF(AND(ISNUMBER(T90),ISNUMBER(R90)),T90-R90,"") | U92: =IF(AND(ISNUMBER(U90),ISNUMBER(T90)),U90-T90,"") | V92: =IF(AND(ISNUMBER(V90),ISNUMBER(U90)),V90-U90,"") | W92: =IF(AND(ISNUMBER(W90),ISNUMBER(V90)),W90-V90,"") | Y92: =IF(AND(ISNUMBER(Y90),ISNUMBER(W90)),Y90-W90,"") | Z92: =IF(AND(ISNUMBER(Z90),ISNUMBER(Y90)),Z90-Y90,"") | AA92: =IF(AND(ISNUMBER(AA90),ISNUMBER(Z90)),AA90-Z90,"") | AB92: =IF(AND(ISNUMBER(AB90),ISNUMBER(AA90)),AB90-AA90,"") | AD92: =IF(AND(ISNUMBER(AD90),ISNUMBER(AB90)),AD90-AB90,"") | AE92: =IF(AND(ISNUMBER(AE90),ISNUMBER(AD90)),AE90-AD90,"") | AF92: =IF(AND(ISNUMBER(AF90),ISNUMBER(AE90)),AF90-AE90,"") | AG92: =IF(AND(ISNUMBER(AG90),ISNUMBER(AF90)),AG90-AF90,"") | AI92: =IF(AND(ISNUMBER(AI90),ISNUMBER(AG90)),AI90-AG90,"") | AJ92: =IF(AND(ISNUMBER(AJ90),ISNUMBER(AI90)),AJ90-AI90,"") | AK92: =IF(AND(ISNUMBER(AK90),ISNUMBER(AJ90)),AK90-AJ90,"") | AL92: =IF(AND(ISNUMBER(AL90),ISNUMBER(AK90)),AL90-AK90,"") | AN92: =IF(AND(ISNUMBER(AN90),ISNUMBER(AL90)),AN90-AL90,"") | AO92: =IF(AND(ISNUMBER(AO90),ISNUMBER(AN90)),AO90-AN90,"") | AP92: =IF(AND(ISNUMBER(AP90),ISNUMBER(AO90)),AP90-AO90,"") | AQ92: =IF(AND(ISNUMBER(AQ90),ISNUMBER(AP90)),AQ90-AP90,"") | AS92: =IF(AND(ISNUMBER(AS90),ISNUMBER(AQ90)),AS90-AQ90,"") | AT92: =IF(AND(ISNUMBER(AT90),ISNUMBER(AS90)),AT90-AS90,"") | AU92: =IF(AND(ISNUMBER(AU90),ISNUMBER(AT90)),AU90-AT90,"") | AV92: =IF(AND(ISNUMBER(AV90),ISNUMBER(AU90)),AV90-AU90,"") | AX92: =IF(AND(ISNUMBER(AX90),ISNUMBER(AV90)),AX90-AV90,"") | AY92: =IF(AND(ISNUMBER(AY90),ISNUMBER(AX90)),AY90-AX90,"") | AZ92: =IF(AND(ISNUMBER(AZ90),ISNUMBER(AY90)),AZ90-AY90,"") | BA92: =IF(AND(ISNUMBER(BA90),ISNUMBER(AZ90)),BA90-AZ90,"") | BC92: =IF(AND(ISNUMBER(BC90),ISNUMBER(BA90)),BC90-BA90,"") | BD92: =IF(AND(ISNUMBER(BD90),ISNUMBER(BC90)),BD90-BC90,"") | BE92: =IF(AND(ISNUMBER(BE90),ISNUMBER(BD90)),BE90-BD90,"") | BF92: =IF(AND(ISNUMBER(BF90),ISNUMBER(BE90)),BF90-BE90,"") | BH92: =IF(AND(ISNUMBER(BH90),ISNUMBER(BF90)),BH90-BF90,"") | BI92: =IF(AND(ISNUMBER(BI90),ISNUMBER(BH90)),BI90-BH90,"") | BJ92: =IF(AND(ISNUMBER(BJ90),ISNUMBER(BI90)),BJ90-BI90,"") | BK92: =IF(AND(ISNUMBER(BK90),ISNUMBER(BJ90)),BK90-BJ90,"") | BM92: =IF(AND(ISNUMBER(BM90),ISNUMBER(BK90)),BM90-BK90,"") | BN92: =IF(AND(ISNUMBER(BN90),ISNUMBER(BM90)),BN90-BM90,"") | BO92: =IF(AND(ISNUMBER(BO90),ISNUMBER(BN90)),BO90-BN90,"") | BP92: =IF(AND(ISNUMBER(BP90),ISNUMBER(BO90)),BP90-BO90,"") | BR92: =IF(AND(ISNUMBER(BR90),ISNUMBER(BP90)),BR90-BP90,"") | BS92: =IF(AND(ISNUMBER(BS90),ISNUMBER(BR90)),BS90-BR90,"") | BT92: =IF(AND(ISNUMBER(BT90),ISNUMBER(BS90)),BT90-BS90,"") | BU92: =IF(AND(ISNUMBER(BU90),ISNUMBER(BT90)),BU90-BT90,"") | BW92: =IF(AND(ISNUMBER(BW90),ISNUMBER(BU90)),BW90-BU90,"") | BX92: =IF(AND(ISNUMBER(BX90),ISNUMBER(BW90)),BX90-BW90,"") | BY92: =IF(AND(ISNUMBER(BY90),ISNUMBER(BX90)),BY90-BX90,"") | BZ92: =IF(AND(ISNUMBER(BZ90),ISNUMBER(BY90)),BZ90-BY90,"")
B93: Operating ratio change y/y | D93: =IF(AND(ISNUMBER(D90),ISNUMBER(C90)),D90-C90,"") | E93: =IF(AND(ISNUMBER(E90),ISNUMBER(D90)),E90-D90,"") | F93: =IF(AND(ISNUMBER(F90),ISNUMBER(E90)),F90-E90,"") | G93: =IF(AND(ISNUMBER(G90),ISNUMBER(F90)),G90-F90,"") | H93: =IF(AND(ISNUMBER(H90),ISNUMBER(G90)),H90-G90,"") | I93: =IF(AND(ISNUMBER(I90),ISNUMBER(H90)),I90-H90,"") | N93: =IF(AND(ISNUMBER(N90),ISNUMBER(I90)),N90-I90,"") | O93: =IF(AND(ISNUMBER(O90),ISNUMBER(J90)),O90-J90,"") | P93: =IF(AND(ISNUMBER(P90),ISNUMBER(K90)),P90-K90,"") | Q93: =IF(AND(ISNUMBER(Q90),ISNUMBER(L90)),Q90-L90,"") | R93: =IF(AND(ISNUMBER(R90),ISNUMBER(M90)),R90-M90,"") | S93: =IF(AND(ISNUMBER(S90),ISNUMBER(N90)),S90-N90,"") | T93: =IF(AND(ISNUMBER(T90),ISNUMBER(O90)),T90-O90,"") | U93: =IF(AND(ISNUMBER(U90),ISNUMBER(P90)),U90-P90,"") | ... CA93: =IF(AND(ISNUMBER(CA90),ISNUMBER(BV90)),CA90-BV90,"") | CB93: =IF(AND(ISNUMBER(CB90),ISNUMBER(CA90)),CB90-CA90,"") | CC93: =IF(AND(ISNUMBER(CC90),ISNUMBER(CB90)),CC90-CB90,"") | CD93: =IF(AND(ISNUMBER(CD90),ISNUMBER(CC90)),CD90-CC90,"") | CE93: =IF(AND(ISNUMBER(CE90),ISNUMBER(CD90)),CE90-CD90,"")
B94: Memo: operating ratio as published | C94: 0.898 | D94: 0.907 | E94: 0.916 | F94: 0.943 | G94: 0.907 | H94: 0.876 | I94: 0.865 | J94: 0.876 | K94: 0.835 | L94: 0.841 | M94: 0.87 | N94: 0.855 | O94: 0.871 | P94: 0.825 | Q94: 0.83 | R94: 0.844 | S94: 0.842 | T94: 0.851 | U94: 0.815 | V94: 0.821 | W94: 0.845 | X94: 0.832 | Y94: 0.859 | Z94: 0.823 | AA94: 0.824 | AB94: 0.848 | AC94: 0.838 | AD94: 0.857 | AE94: 0.809 | AF94: 0.812 | AG94: 0.839 | AH94: 0.829 | AI94: 0.839 | AJ94: 0.787 | AK94: 0.784 | AL94: 0.787 | AM94: 0.798 | AN94: 0.82 | AO94: 0.779 | AP94: 0.793 | AQ94: 0.813 | AR94: 0.801 | AS94: 0.814 | AT94: 0.778 | AU94: 0.745 | AV94: 0.763 | AW94: 0.774 | AX94: 0.761 | AY94: 0.723 | AZ94: 0.726 | BA94: 0.736 | BB94: 0.735 | BC94: 0.729 | BD94: 0.695 | BE94: 0.691 | BF94: 0.712 | BG94: 0.706 | BH94: 0.734 | BI94: 0.723 | BJ94: 0.706 | BK94: 0.718 | BL94: 0.72 | BM94: 0.735 | BN94: 0.719 | BO94: 0.727 | BP94: 0.759 | BQ94: 0.734 | BR94: 0.754 | BS94: 0.746 | BT94: 0.743 | BU94: 0.767 | BV94: 0.752 | BW94: 0.762 | BX94: 0.701
B95: Check: Q3/26E tons per day y/y vs Aug-26 update anchor (should be 0) | BY95: =ROUND(BY13-$CP$19,6)
B96: Check: Q3/26E revenue/cwt (incl. & excl. fuel) y/y vs Jul–Aug QTD update anchors (should be 0) | BY96: =ROUND(ABS(BY34-$CP$21)+ABS(BY29-$CP$20),6)
B97: Memo: Aug-26 revenue per day y/y (3-Sep-26 update; Q3/26E model revenue per day y/y above) | BY97: =$CP$22
B99: STATEMENT OF OPERATIONS (US GAAP) | CF99: STATEMENT OF OPERATIONS — forecast logic
B100: Revenue | C100: 1279.431 | D100: 1401.542 | E100: 1537.724 | F100: 1245.005 | G100: 1480.998 | H100: 1882.541 | I100: 2110.483 | J100: 532.575 | K100: 590.209 | L100: 616.458 | M100: 592.47 | N100: 2337.648 | O100: 620.276 | P100: 702.987 | Q100: 743.586 | R100: 721.048 | S100: 2787.897 | T100: 696.245 | U100: 762.151 | V100: 779.474 | W100: 734.572 | X100: 2972.442 | Y100: 707.733 | Z100: 755.435 | AA100: 782.611 | AB100: 745.738 | AC100: 2991.517 | AD100: 754.096 | AE100: 839.912 | AF100: 872.987 | AG100: 891.117 | AH100: 3358.112 | AI100: 925.02 | AJ100: 1033.498 | AK100: 1058.233 | AL100: 1026.944 | AM100: 4043.695 | AN100: 990.782 | AO100: 1060.666 | AP100: 1048.457 | AQ100: 1009.206 | AR100: 4109.111 | AS100: 987.364 | AT100: 896.21 | AU100: 1058.166 | AV100: 1073.389 | AW100: 4015.129 | AX100: 1126.515 | AY100: 1319.409 | AZ100: 1400.046 | BA100: 1410.358 | BB100: 5256.328 | BC100: 1497.28 | BD100: 1667.448 | BE100: 1603.69 | BF100: 1491.659 | BG100: 6260.077 | BH100: 1442.136 | BI100: 1413.189 | BJ100: 1515.277 | BK100: 1495.55 | BL100: 5866.152 | BM100: 1460.073 | BN100: 1498.697 | BO100: 1470.211 | BP100: 1385.829 | BQ100: 5814.81 | BR100: 1374.858 | BS100: 1407.724 | BT100: 1406.511 | BU100: 1307.296 | BV100: 5496.389 | BW100: 1334.696 | BX100: 1554.004 | BY100: =BY47 | BZ100: =BZ47 | CA100: =SUM(BW100,BX100,BY100,BZ100) | CB100: =CB47 | CC100: =CC47 | CD100: =CD47 | CE100: =CE47 | CF100: Forecast linked to the LTL operating build. | CH100: =IFERROR((CE100/BV100)^(1/5)-1,"n/m") | CI100: =IFERROR((BV100/AW100)^(1/5)-1,"n/m") | CJ100: =IFERROR((BV100/X100)^(1/10)-1,"n/m") | CK100: =IFERROR((BV100/C100)^(1/19)-1,"n/m")
B101: Salaries, wages & benefits | C101: 682.886 | D101: 751.371 | E101: 804.636 | F101: 718.744 | G101: 808.819 | H101: 956.079 | I101: 1066.551 | J101: 270.8 | K101: 287.961 | L101: 303.853 | M101: 308.159 | N101: 1170.773 | O101: 311.181 | P101: 340.309 | Q101: 363.42 | R101: 366.367 | S101: 1381.277 | T101: 368.442 | U101: 387.423 | V101: 406.592 | W101: 407.334 | X101: 1569.791 | Y101: 400.869 | Z101: 408.424 | AA101: 425.076 | AB101: 417.686 | AC101: 1652.055 | AD101: 416.504 | AE101: 441.904 | AF101: 461.799 | AG101: 482.233 | AH101: 1802.44 | AI101: 501.311 | AJ101: 522.249 | AK101: 536.513 | AL101: 515.529 | AM101: 2075.602 | AN101: 522.344 | AO101: 532.583 | AP101: 533.451 | AQ101: 534.086 | AR101: 2122.464 | AS101: 524.483 | AT101: 460.906 | AU101: 524.658 | AV101: 543.847 | AW101: 2053.894 | AX101: 545.659 | AY101: 611.518 | AZ101: 649.685 | BA101: 661.123 | BB101: 2467.985 | BC101: 680.189 | BD101: 705.71 | BE101: 675.084 | BF101: 655.852 | BG101: 2716.835 | BH101: 652.075 | BI101: 642.841 | BJ101: 663.81 | BK101: 670.95 | BL101: 2629.676 | BM101: 668.39 | BN101: 683.784 | BO101: 681.238 | BP101: 655.902 | BQ101: 2689.314 | BR101: 658.085 | BS101: 672.093 | BT101: 663.034 | BU101: 642.113 | BV101: 2635.325 | BW101: 638.295 | BX101: 687.348 | BY101: =BY100*BY68 | BZ101: =BZ100*BZ68 | CA101: =SUM(BW101,BX101,BY101,BZ101) | CB101: =CB100*CB68 | CC101: =CC100*CC68 | CD101: =CD100*CD68 | CE101: =CE100*CE68 | CH101: =IFERROR((CE101/BV101)^(1/5)-1,"n/m") | CI101: =IFERROR((BV101/AW101)^(1/5)-1,"n/m") | CJ101: =IFERROR((BV101/X101)^(1/10)-1,"n/m") | CK101: =IFERROR((BV101/C101)^(1/19)-1,"n/m")
B102: Operating supplies & expenses (incl. fuel) | C102: 204.386 | D102: 238.879 | E102: 305.158 | F102: 181.329 | G102: 244.291 | H102: 355.186 | I102: 378.534 | J102: 95.703 | K102: 95.115 | L102: 96.792 | M102: 97.591 | N102: 385.201 | O102: 106.294 | P102: 109.917 | Q102: 111.67 | R102: 104.794 | S102: 432.675 | T102: 88.049 | U102: 93.39 | V102: 88.669 | W102: 83.781 | X102: 353.889 | Y102: 75.372 | Z102: 80.335 | AA102: 83.197 | AB102: 84.093 | AC102: 322.997 | AD102: 90.987 | AE102: 88.58 | AF102: 95.543 | AG102: 106.688 | AH102: 381.798 | AI102: 114.061 | AJ102: 124.919 | AK102: 126.024 | AL102: 126.026 | AM102: 491.03 | AN102: 121.357 | AO102: 122.41 | AP102: 117.343 | AQ102: 112.004 | AR102: 473.114 | AS102: 107.693 | AT102: 75.412 | AU102: 90.269 | AV102: 100.057 | AW102: 373.431 | AX102: 124.156 | AY102: 137.577 | AZ102: 146.509 | BA102: 159.373 | BB102: 567.615 | BC102: 191.357 | BD102: 236.712 | BE102: 217.26 | BF102: 207.626 | BG102: 852.955 | BH102: 192.384 | BI102: 165.373 | BJ102: 180.653 | BK102: 179.916 | BL102: 718.326 | BM102: 172.472 | BN102: 161.02 | BO102: 156.177 | BP102: 145.651 | BQ102: 635.32 | BR102: 149.892 | BS102: 142.457 | BT102: 144.185 | BU102: 134.447 | BV102: 570.981 | BW102: 146.718 | BX102: 177.683 | BY102: =BY100*BY70 | BZ102: =BZ100*BZ70 | CA102: =SUM(BW102,BX102,BY102,BZ102) | CB102: =CB100*CB70 | CC102: =CC100*CC70 | CD102: =CD100*CD70 | CE102: =CE100*CE70 | CH102: =IFERROR((CE102/BV102)^(1/5)-1,"n/m") | CI102: =IFERROR((BV102/AW102)^(1/5)-1,"n/m") | CJ102: =IFERROR((BV102/X102)^(1/10)-1,"n/m") | CK102: =IFERROR((BV102/C102)^(1/19)-1,"n/m")
B103: General supplies & expenses | C103: 37.507 | D103: 40.075 | E103: 44.674 | F103: 36.363 | G103: 41.58 | H103: 49.9 | I103: 58.908 | J103: 17.761 | K103: 17.639 | L103: 18.311 | M103: 16.054 | N103: 69.765 | O103: 19.135 | P103: 20.889 | Q103: 21.931 | R103: 21.21 | S103: 83.165 | T103: 21.292 | U103: 23.533 | V103: 24.35 | W103: 20.133 | X103: 89.308 | Y103: 21.142 | Z103: 22.778 | AA103: 22.01 | AB103: 20.696 | AC103: 86.626 | AD103: 22.872 | AE103: 28.283 | AF103: 28.785 | AG103: 27.793 | AH103: 107.733 | AI103: 29.976 | AJ103: 29.891 | AK103: 31.209 | AL103: 28.104 | AM103: 119.18 | AN103: 31.56 | AO103: 32.391 | AP103: 33.633 | AQ103: 26.391 | AR103: 123.975 | AS103: 33.608 | AT103: 25.881 | AU103: 27.383 | AV103: 23.407 | AW103: 110.279 | AX103: 31.168 | AY103: 34.427 | AZ103: 37.312 | BA103: 33.152 | BB103: 136.059 | BC103: 35.513 | BD103: 39.116 | BE103: 45.951 | BF103: 39.418 | BG103: 159.998 | BH103: 39.545 | BI103: 38.606 | BJ103: 41.745 | BK103: 42.52 | BL103: 162.416 | BM103: 45.576 | BN103: 44.371 | BO103: 46.04 | BP103: 40.559 | BQ103: 176.546 | BR103: 39.88 | BS103: 41.676 | BT103: 45.075 | BU103: 42.53 | BV103: 169.161 | BW103: 47.069 | BX103: 46.413 | BY103: =BY100*BY72 | BZ103: =BZ100*BZ72 | CA103: =SUM(BW103,BX103,BY103,BZ103) | CB103: =CB100*CB72 | CC103: =CC100*CC72 | CD103: =CD100*CD72 | CE103: =CE100*CE72
...

Sheet Bull-Base-Bear
B2: Old Dominion Freight Line (ODFL) — Bull / Base / Bear Case P&L Summary | J2: Share price ($): | K2: =Model!$CA$355
B3: Adjusted figures are model definitions (ODFL publishes no non-GAAP measures): Adjusted EBITDA / adjusted EPS exclude net gains on disposal of property & equipment and company-named one-offs · USD millions · Live panel linked to Model — toggle scenario via Model!CF2. Bull and Bear panels are value snapshots generated from the Model with the switch set to each case. | J3: As of: | K3: =TODAY()
B5: Scenario: | C5: =Model!$CF$2 | N5: Scenario: | O5: Bull | P5: Snapshot (values) — Model run with switch = Bull | Z5: Scenario: | AA5: Bear | AB5: Snapshot (values) — Model run with switch = Bear
B7: (USDm, except EPS and shares) | C7: 2025A | D7: 2026E | E7: 2027E | F7: 2028E | G7: 2029E | H7: 2030E | I7: 25-'30 CAGR | J7: LT Hist Avg | K7: LT Hist Min | L7: LT Hist Max | N7: (USDm, except EPS and shares) | O7: 2025A | P7: 2026E | Q7: 2027E | R7: 2028E | S7: 2029E | T7: 2030E | U7: 25-'30 CAGR | V7: LT Hist Avg | W7: LT Hist Min | X7: LT Hist Max | Z7: (USDm, except EPS and shares) | AA7: 2025A | AB7: 2026E | AC7: 2027E | AD7: 2028E | AE7: 2029E | AF7: 2030E | AG7: 25-'30 CAGR | AH7: LT Hist Avg | AI7: LT Hist Min | AJ7: LT Hist Max
B9: Revenue | C9: =Model!BV100 | D9: =Model!CA100 | E9: =Model!CB100 | F9: =Model!CC100 | G9: =Model!CD100 | H9: =Model!CE100 | I9: =IFERROR((H9/C9)^(1/5)-1,"n/m") | N9: Revenue | O9: 5496.389 | P9: 6008.4957 | Q9: 6770.3343 | R9: 7667.9167 | S9: 8570.5786 | T9: 9490.0515 | U9: 0.11541947 | Z9: Revenue | AA9: 5496.389 | AB9: 5856.3706 | AC9: 6144.2458 | AD9: 6479.9527 | AE9: 6741.0778 | AF9: 6944.7368 | AG9: 0.047889927
B10: Revenue y/y % | D10: =IFERROR(D9/C9-1,"") | E10: =IFERROR(E9/D9-1,"") | F10: =IFERROR(F9/E9-1,"") | G10: =IFERROR(G9/F9-1,"") | H10: =IFERROR(H9/G9-1,"") | N10: Revenue y/y % | P10: 0.093171473 | Q10: 0.12679358 | R10: 0.13257579 | S10: 0.1177193 | T10: 0.10728248 | Z10: Revenue y/y % | AB10: 0.065494193 | AC10: 0.049155917 | AD10: 0.054637612 | AE10: 0.040297367 | AF10: 0.030211637
B11: LTL tons per day y/y % | C11: =Model!BV185 | D11: =Model!CA185 | E11: =Model!CB185 | F11: =Model!CC185 | G11: =Model!CD185 | H11: =Model!CE185 | N11: LTL tons per day y/y % | O11: -0.087884176 | P11: -0.016991721 | Q11: 0.06 | R11: 0.07 | S11: 0.06 | T11: 0.055 | Z11: LTL tons per day y/y % | AA11: -0.087884176 | AB11: -0.034827178 | AC11: 0.01 | AD11: 0.02 | AE11: 0.01 | AF11: 0.005
B12: Adjusted EBITDA (model) | C12: =Model!BV157 | D12: =Model!CA157 | E12: =Model!CB157 | F12: =Model!CC157 | G12: =Model!CD157 | H12: =Model!CE157 | I12: =IFERROR((H12/C12)^(1/5)-1,"n/m") | N12: Adjusted EBITDA (model) | O12: 1728.666 | P12: 2167.8888 | Q12: 2545.6457 | R12: 2959.8159 | S12: 3351.0962 | T12: 3758.0604 | U12: 0.16802068 | Z12: Adjusted EBITDA (model) | AA12: 1728.666 | AB12: 1936.956 | AC12: 2064.4666 | AD12: 2242.0636 | AE12: 2366.1183 | AF12: 2472.3263 | AG12: 0.074184644
B13: Adjusted EBITDA margin % | C13: =IFERROR(C12/C9,"") | D13: =IFERROR(D12/D9,"") | E13: =IFERROR(E12/E9,"") | F13: =IFERROR(F12/F9,"") | G13: =IFERROR(G12/G9,"") | H13: =IFERROR(H12/H9,"") | J13: =IFERROR(AVERAGE(Model!C158,Model!D158,Model!E158,Model!F158,Model!G158,Model!H158,Model!I158,Model!N158,Model!S158,Model!X158,Model!AC158,Model!AH158,Model!AM158,Model!AR158,Model!AW158,Model!BB158,Model!BG158,Model!BL158,Model!BQ158,Model!BV158),"") | K13: =IFERROR(MIN(Model!C158,Model!D158,Model!E158,Model!F158,Model!G158,Model!H158,Model!I158,Model!N158,Model!S158,Model!X158,Model!AC158,Model!AH158,Model!AM158,Model!AR158,Model!AW158,Model!BB158,Model!BG158,Model!BL158,Model!BQ158,Model!BV158),"") | L13: =IFERROR(MAX(Model!C158,Model!D158,Model!E158,Model!F158,Model!G158,Model!H158,Model!I158,Model!N158,Model!S158,Model!X158,Model!AC158,Model!AH158,Model!AM158,Model!AR158,Model!AW158,Model!BB158,Model!BG158,Model!BL158,Model!BQ158,Model!BV158),"") | N13: Adjusted EBITDA margin % | O13: 0.3145094 | P13: 0.36080392 | Q13: 0.376 | R13: 0.386 | S13: 0.391 | T13: 0.396 | V13: 0.23023337 | W13: 0.13280911 | X13: 0.33505291 | Z13: Adjusted EBITDA margin % | AA13: 0.3145094 | AB13: 0.33074342 | AC13: 0.336 | AD13: 0.346 | AE13: 0.351 | AF13: 0.356 | AH13: 0.23023337 | AI13: 0.13280911 | AJ13: 0.33505291
B15: Operating Income (GAAP) | C15: =Model!BV114 | D15: =Model!CA114 | E15: =Model!CB114 | F15: =Model!CC114 | G15: =Model!CD114 | H15: =Model!CE114 | I15: =IFERROR((H15/C15)^(1/5)-1,"n/m") | N15: Operating Income (GAAP) | O15: 1361.045 | P15: 1815.9558 | Q15: 2098.8036 | R15: 2453.7334 | S15: 2785.438 | T15: 3131.717 | U15: 0.1813593 | Z15: Operating Income (GAAP) | AA15: 1361.045 | AB15: 1585.023 | AC15: 1658.9464 | AD15: 1814.3868 | AE15: 1921.2072 | AF15: 2013.9737 | AG15: 0.081524247
B16: Operating income y/y % | D16: =IFERROR(D15/C15-1,"") | E16: =IFERROR(E15/D15-1,"") | F16: =IFERROR(F15/E15-1,"") | G16: =IFERROR(G15/F15-1,"") | H16: =IFERROR(H15/G15-1,"") | N16: Operating income y/y % | P16: 0.33423641 | Q16: 0.15575701 | R16: 0.16911049 | S16: 0.13518367 | T16: 0.1243176 | Z16: Operating income y/y % | AB16: 0.16456326 | AC16: 0.046638671 | AD16: 0.093698264 | AE16: 0.058874106 | AF16: 0.048285526
B17: Operating margin (1 − operating ratio) % | C17: =IFERROR(C15/C9,"") | D17: =IFERROR(D15/D9,"") | E17: =IFERROR(E15/E9,"") | F17: =IFERROR(F15/F9,"") | G17: =IFERROR(G15/G9,"") | H17: =IFERROR(H15/H9,"") | J17: =IFERROR(AVERAGE(Model!C194,Model!D194,Model!E194,Model!F194,Model!G194,Model!H194,Model!I194,Model!N194,Model!S194,Model!X194,Model!AC194,Model!AH194,Model!AM194,Model!AR194,Model!AW194,Model!BB194,Model!BG194,Model!BL194,Model!BQ194,Model!BV194),"") | K17: =IFERROR(MIN(Model!C194,Model!D194,Model!E194,Model!F194,Model!G194,Model!H194,Model!I194,Model!N194,Model!S194,Model!X194,Model!AC194,Model!AH194,Model!AM194,Model!AR194,Model!AW194,Model!BB194,Model!BG194,Model!BL194,Model!BQ194,Model!BV194),"") | L17: =IFERROR(MAX(Model!C194,Model!D194,Model!E194,Model!F194,Model!G194,Model!H194,Model!I194,Model!N194,Model!S194,Model!X194,Model!AC194,Model!AH194,Model!AM194,Model!AR194,Model!AW194,Model!BB194,Model!BG194,Model!BL194,Model!BQ194,Model!BV194),"") | N17: Operating margin (1 − operating ratio) % | O17: 0.2476253 | P17: 0.30223136 | Q17: 0.31 | R17: 0.32 | S17: 0.325 | T17: 0.33 | V17: 0.17351843 | W17: 0.056538729 | X17: 0.29402705 | Z17: Operating margin (1 − operating ratio) % | AA17: 0.2476253 | AB17: 0.27064937 | AC17: 0.27 | AD17: 0.28 | AE17: 0.285 | AF17: 0.29 | AH17: 0.17351843 | AI17: 0.056538729 | AJ17: 0.29402705
B19: Adjusted Net Income (model) | C19: =Model!BV174 | D19: =Model!CA174 | E19: =Model!CB174 | F19: =Model!CC174 | G19: =Model!CD174 | H19: =Model!CE174 | I19: =IFERROR((H19/C19)^(1/5)-1,"n/m") | N19: Adjusted Net Income (model) | O19: 1025.9124 | P19: 1350.9031 | Q19: 1585.4945 | R19: 1841.6126 | S19: 2090.3911 | T19: 2350.1003 | U19: 0.18030766 | Z19: Adjusted Net Income (model) | AA19: 1025.9124 | AB19: 1177.7035 | AC19: 1257.7399 | AD19: 1368.6651 | AE19: 1448.7804 | AF19: 1518.3553 | AG19: 0.08156501
B21: FDSO (m) | C21: =Model!BV130 | D21: =Model!CA130 | E21: =Model!CB130 | F21: =Model!CC130 | G21: =Model!CD130 | H21: =Model!CE130 | I21: =IFERROR((H21/C21)^(1/5)-1,"n/m") | N21: FDSO (m) | O21: 211.598 | P21: 208.36144 | Q21: 203.29104 | R21: 197.38291 | S21: 191.89524 | T21: 186.03552 | U21: -0.025421422 | Z21: FDSO (m) | AA21: 211.598 | AB21: 208.67648 | AC21: 205.63979 | AD21: 201.73972 | AE21: 198.31803 | AF21: 194.97682 | AG21: -0.016228394
B23: Adjusted EPS — Diluted ($) | C23: =Model!BV176 | D23: =Model!CA176 | E23: =Model!CB176 | F23: =Model!CC176 | G23: =Model!CD176 | H23: =Model!CE176 | I23: =IFERROR((H23/C23)^(1/5)-1,"n/m") | N23: Adjusted EPS — Diluted ($) | O23: 4.848403 | P23: 6.4834601 | Q23: 7.7991361 | R23: 9.3301522 | S23: 10.893397 | T23: 12.632536 | U23: 0.21109543 | Z23: Adjusted EPS — Diluted ($) | AA23: 4.848403 | AB23: 5.6436812 | AC23: 6.1162282 | AD23: 6.7843116 | AE23: 7.3053392 | AF23: 7.7873633 | AG23: 0.099406614
B24: EPS y/y % | D24: =IFERROR(D23/C23-1,"") | E24: =IFERROR(E23/D23-1,"") | F24: =IFERROR(F23/E23-1,"") | G24: =IFERROR(G23/F23-1,"") | H24: =IFERROR(H23/G23-1,"") | N24: EPS y/y % | P24: 0.33723623 | Q24: 0.20292806 | R24: 0.19630585 | S24: 0.16754763 | T24: 0.15965072 | Z24: EPS y/y % | AB24: 0.1640289 | AC24: 0.083730286 | AD24: 0.10923127 | AE24: 0.076798884 | AF24: 0.065982448
B26: P / E (x) — assumed (adjusted EPS) | G26: 28 | H26: 28 | N26: P / E (x) — assumed (adjusted EPS) | S26: 32 | T26: 32 | Z26: P / E (x) — assumed (adjusted EPS) | AD26: 22 | AE26: 22 | AF26: 22
B27: Price Target ($) | G27: =G26*G23 | H27: =H26*H23 | N27: Price Target ($) | S27: =S26*S23 | T27: =T26*T23 | Z27: Price Target ($) | AD27: =AD26*AD23 | AE27: =AE26*AE23 | AF27: =AF26*AF23
B28: Upside / (Downside) vs current | G28: =IFERROR(G27/$K$2-1,"") | H28: =IFERROR(H27/$K$2-1,"") | N28: Upside / (Downside) vs current | S28: =IFERROR(S27/$K$2-1,"") | T28: =IFERROR(T27/$K$2-1,"") | Z28: Upside / (Downside) vs current | AD28: =IFERROR(AD27/$K$2-1,"") | AE28: =IFERROR(AE27/$K$2-1,"") | AF28: =IFERROR(AF27/$K$2-1,"")
B29: IRR (to Dec-Y-1) | G29: =IFERROR((G27/$K$2)^(1/((DATE(2029-1,12,31)-$K$3)/365.25))-1,"") | H29: =IFERROR((H27/$K$2)^(1/((DATE(2030-1,12,31)-$K$3)/365.25))-1,"") | N29: IRR (to Dec-Y-1) | S29: =IFERROR((S27/$K$2)^(1/((DATE(2029-1,12,31)-$K$3)/365.25))-1,"") | T29: =IFERROR((T27/$K$2)^(1/((DATE(2030-1,12,31)-$K$3)/365.25))-1,"") | Z29: IRR (to Dec-Y-1) | AD29: =IFERROR((AD27/$K$2)^(1/((DATE(2028-1,12,31)-$K$3)/365.25))-1,"") | AE29: =IFERROR((AE27/$K$2)^(1/((DATE(2029-1,12,31)-$K$3)/365.25))-1,"") | AF29: =IFERROR((AF27/$K$2)^(1/((DATE(2030-1,12,31)-$K$3)/365.25))-1,"")
B31: Free Cash Flow | C31: =Model!BV226 | D31: =Model!CA226 | E31: =Model!CB226 | F31: =Model!CC226 | G31: =Model!CD226 | H31: =Model!CE226 | I31: =IFERROR((H31/C31)^(1/5)-1,"n/m") | N31: Free Cash Flow | O31: 955.099 | P31: 1292.5544 | Q31: 1309.9746 | R31: 1526.4005 | S31: 1737.9512 | T31: 1958.9762 | U31: 0.15450589 | Z31: Free Cash Flow | AA31: 955.099 | AB31: 1124.3821 | AC31: 1017.3524 | AD31: 1112.6571 | AE31: 1183.5723 | AF31: 1245.5714 | AG31: 0.054542395
B32: FCF % | C32: =IFERROR(C31/C9,"") | D32: =IFERROR(D31/D9,"") | E32: =IFERROR(E31/E9,"") | F32: =IFERROR(F31/F9,"") | G32: =IFERROR(G31/G9,"") | H32: =IFERROR(H31/H9,"") | J32: =IFERROR(AVERAGE(Model!C228,Model!D228,Model!E228,Model!F228,Model!G228,Model!H228,Model!I228,Model!N228,Model!S228,Model!X228,Model!AC228,Model!AH228,Model!AM228,Model!AR228,Model!AW228,Model!BB228,Model!BG228,Model!BL228,Model!BQ228,Model!BV228),"") | K32: =IFERROR(MIN(Model!C228,Model!D228,Model!E228,Model!F228,Model!G228,Model!H228,Model!I228,Model!N228,Model!S228,Model!X228,Model!AC228,Model!AH228,Model!AM228,Model!AR228,Model!AW228,Model!BB228,Model!BG228,Model!BL228,Model!BQ228,Model!BV228),"") | L32: =IFERROR(MAX(Model!C228,Model!D228,Model!E228,Model!F228,Model!G228,Model!H228,Model!I228,Model!N228,Model!S228,Model!X228,Model!AC228,Model!AH228,Model!AM228,Model!AR228,Model!AW228,Model!BB228,Model!BG228,Model!BL228,Model!BQ228,Model!BV228),"") | N32: FCF % | O32: 0.17376845 | P32: 0.21512114 | Q32: 0.19348744 | R32: 0.19906326 | S32: 0.20278109 | T32: 0.20642419 | V32: 0.058908561 | W32: -0.064394922 | X32: 0.17631887 | Z32: FCF % | AA32: 0.17376845 | AB32: 0.191993 | AC32: 0.16557807 | AD32: 0.17170759 | AE32: 0.17557613 | AF32: 0.17935472 | AH32: 0.058908561 | AI32: -0.064394922 | AJ32: 0.17631887
B33: FCF / share ($) | C33: =IFERROR(C31/C21,"") | D33: =IFERROR(D31/D21,"") | E33: =IFERROR(E31/E21,"") | F33: =IFERROR(F31/F21,"") | G33: =IFERROR(G31/G21,"") | H33: =IFERROR(H31/H21,"") | N33: FCF / share ($) | O33: 4.513743 | P33: 6.2034242 | Q33: 6.4438387 | R33: 7.7331949 | S33: 9.0567708 | T33: 10.530119 | Z33: FCF / share ($) | AA33: 4.513743 | AB33: 5.3881595 | AC33: 4.9472544 | AD33: 5.5153098 | AE33: 5.9680522 | AF33: 6.3883049
B34: FCF Yield (on PT) | F34: =IFERROR(F33/F$27,"") | G34: =IFERROR(G33/G$27,"") | H34: =IFERROR(H33/H$27,"") | N34: FCF Yield (on PT) | R34: =IFERROR(R33/R$27,"") | S34: =IFERROR(S33/S$27,"") | T34: =IFERROR(T33/T$27,"") | Z34: FCF Yield (on PT) | AD34: =IFERROR(AD33/AD$27,"") | AE34: =IFERROR(AE33/AE$27,"") | AF34: =IFERROR(AF33/AF$27,"")
B35: Adjusted EBITDA (leverage basis) | C35: =Model!BV157 | D35: =Model!CA157 | E35: =Model!CB157 | F35: =Model!CC157 | G35: =Model!CD157 | H35: =Model!CE157 | I35: =IFERROR((H35/C35)^(1/5)-1,"n/m") | N35: Adjusted EBITDA (leverage basis) | O35: 1728.666 | P35: 2167.8888 | Q35: 2545.6457 | R35: 2959.8159 | S35: 3351.0962 | T35: 3758.0604 | U35: 0.16802068 | Z35: Adjusted EBITDA (leverage basis) | AA35: 1728.666 | AB35: 1936.956 | AC35: 2064.4666 | AD35: 2242.0636 | AE35: 2366.1183 | AF35: 2472.3263 | AG35: 0.074184644
B36: Adjusted EBITDA % of revenue | C36: =IFERROR(C35/C9,"") | D36: =IFERROR(D35/D9,"") | E36: =IFERROR(E35/E9,"") | F36: =IFERROR(F35/F9,"") | G36: =IFERROR(G35/G9,"") | H36: =IFERROR(H35/H9,"") | J36: =IFERROR(AVERAGE(Model!C192,Model!D192,Model!E192,Model!F192,Model!G192,Model!H192,Model!I192,Model!N192,Model!S192,Model!X192,Model!AC192,Model!AH192,Model!AM192,Model!AR192,Model!AW192,Model!BB192,Model!BG192,Model!BL192,Model!BQ192,Model!BV192),"") | K36: =IFERROR(MIN(Model!C192,Model!D192,Model!E192,Model!F192,Model!G192,Model!H192,Model!I192,Model!N192,Model!S192,Model!X192,Model!AC192,Model!AH192,Model!AM192,Model!AR192,Model!AW192,Model!BB192,Model!BG192,Model!BL192,Model!BQ192,Model!BV192),"") | L36: =IFERROR(MAX(Model!C192,Model!D192,Model!E192,Model!F192,Model!G192,Model!H192,Model!I192,Model!N192,Model!S192,Model!X192,Model!AC192,Model!AH192,Model!AM192,Model!AR192,Model!AW192,Model!BB192,Model!BG192,Model!BL192,Model!BQ192,Model!BV192),"") | N36: Adjusted EBITDA % of revenue | O36: 0.3145094 | P36: 0.36080392 | Q36: 0.376 | R36: 0.386 | S36: 0.391 | T36: 0.396 | V36: 0.23023337 | W36: 0.13280911 | X36: 0.33505291 | Z36: Adjusted EBITDA % of revenue | AA36: 0.3145094 | AB36: 0.33074342 | AC36: 0.336 | AD36: 0.346 | AE36: 0.351 | AF36: 0.356 | AH36: 0.23023337 | AI36: 0.13280911 | AJ36: 0.33505291
B38: Net Debt (negative = net cash) | C38: =Model!BV350 | D38: =Model!CA350 | E38: =Model!CB350 | F38: =Model!CC350 | G38: =Model!CD350 | H38: =Model!CE350 | N38: Net Debt (negative = net cash) | O38: -80.096 | P38: -529.9149 | Q38: -150.003 | R38: -150.003 | S38: -150.003 | T38: -150.003 | Z38: Net Debt (negative = net cash) | AA38: -80.096 | AB38: -611.37719 | AC38: -400.003 | AD38: -400.003 | AE38: -400.003 | AF38: -400.003
B39: Net Debt / Adjusted EBITDA (x) | C39: =IFERROR(C38/C35,"") | D39: =IFERROR(D38/D35,"") | E39: =IFERROR(E38/E35,"") | F39: =IFERROR(F38/F35,"") | G39: =IFERROR(G38/G35,"") | H39: =IFERROR(H38/H35,"") | N39: Net Debt / Adjusted EBITDA (x) | O39: -0.046333994 | P39: -0.24443823 | Q39: -0.058925325 | R39: -0.050679842 | S39: -0.044762367 | T39: -0.039915005 | Z39: Net Debt / Adjusted EBITDA (x) | AA39: -0.046333994 | AB39: -0.31563814 | AC39: -0.1937561 | AD39: -0.17840841 | AE39: -0.16905452 | AF39: -0.16179216
B41: ROIC | C41: =Model!BV332 | D41: =Model!CA332 | E41: =Model!CB332 | F41: =Model!CC332 | G41: =Model!CD332 | H41: =Model!CE332 | J41: =IFERROR(AVERAGE(Model!C332,Model!D332,Model!E332,Model!F332,Model!G332,Model!H332,Model!I332,Model!N332,Model!S332,Model!X332,Model!AC332,Model!AH332,Model!AM332,Model!AR332,Model!AW332,Model!BB332,Model!BG332,Model!BL332,Model!BQ332,Model!BV332),"") | K41: =IFERROR(MIN(Model!C332,Model!D332,Model!E332,Model!F332,Model!G332,Model!H332,Model!I332,Model!N332,Model!S332,Model!X332,Model!AC332,Model!AH332,Model!AM332,Model!AR332,Model!AW332,Model!BB332,Model!BG332,Model!BL332,Model!BQ332,Model!BV332),"") | L41: =IFERROR(MAX(Model!C332,Model!D332,Model!E332,Model!F332,Model!G332,Model!H332,Model!I332,Model!N332,Model!S332,Model!X332,Model!AC332,Model!AH332,Model!AM332,Model!AR332,Model!AW332,Model!BB332,Model!BG332,Model!BL332,Model!BQ332,Model!BV332),"") | N41: ROIC | O41: 0.24243064 | P41: 0.31454118 | Q41: 0.34723048 | R41: 0.38173247 | S41: 0.40623781 | T41: 0.42709415 | V41: 0.19449807 | W41: 0.048128744 | X41: 0.38730786 | Z41: ROIC | AA41: 0.24243064 | AB41: 0.27444001 | AC41: 0.27679632 | AD41: 0.28783236 | AE41: 0.28999892 | AF41: 0.28956148 | AH41: 0.19449807 | AI41: 0.048128744 | AJ41: 0.38730786
B42: RONTA | C42: =Model!BV344 | D42: =Model!CA344 | E42: =Model!CB344 | F42: =Model!CC344 | G42: =Model!CD344 | H42: =Model!CE344 | J42: =IFERROR(AVERAGE(Model!C344,Model!D344,Model!E344,Model!F344,Model!G344,Model!H344,Model!I344,Model!N344,Model!S344,Model!X344,Model!AC344,Model!AH344,Model!AM344,Model!AR344,Model!AW344,Model!BB344,Model!BG344,Model!BL344,Model!BQ344,Model!BV344),"") | K42: =IFERROR(MIN(Model!C344,Model!D344,Model!E344,Model!F344,Model!G344,Model!H344,Model!I344,Model!N344,Model!S344,Model!X344,Model!AC344,Model!AH344,Model!AM344,Model!AR344,Model!AW344,Model!BB344,Model!BG344,Model!BL344,Model!BQ344,Model!BV344),"") | L42: =IFERROR(MAX(Model!C344,Model!D344,Model!E344,Model!F344,Model!G344,Model!H344,Model!I344,Model!N344,Model!S344,Model!X344,Model!AC344,Model!AH344,Model!AM344,Model!AR344,Model!AW344,Model!BB344,Model!BG344,Model!BL344,Model!BQ344,Model!BV344),"") | N42: RONTA | O42: 0.20488665 | P42: 0.24539081 | Q42: 0.29367062 | R42: 0.32469941 | S42: 0.34764152 | T42: 0.36778829 | V42: 0.1546431 | W42: 0.04206873 | X42: 0.31469203 | Z42: RONTA | AA42: 0.20488665 | AB42: 0.21091303 | AC42: 0.2233038 | AD42: 0.23363186 | AE42: 0.23677894 | AF42: 0.23775002 | AH42: 0.1546431 | AI42: 0.04206873 | AJ42: 0.31469203
B44: Implied Market Cap (USDm) | F44: =F27*F21 | G44: =G27*G21 | H44: =H27*H21 | N44: Implied Market Cap (USDm) | R44: =R27*R21 | S44: =S27*S21 | T44: =T27*T21 | Z44: Implied Market Cap (USDm) | AD44: =AD27*AD21 | AE44: =AE27*AE21 | AF44: =AF27*AF21
B45: (+) Net Debt & NCI | F45: =F38+Model!CC359 | G45: =G38+Model!CD359 | H45: =H38+Model!CE359 | N45: (+) Net Debt & NCI | R45: =R38+Model!CC359 | S45: =S38+Model!CD359 | T45: =T38+Model!CE359 | Z45: (+) Net Debt & NCI | AD45: =AD38+Model!CC359 | AE45: =AE38+Model!CD359 | AF45: =AF38+Model!CE359
B46: Implied Enterprise Value (USDm) | F46: =F44+F45 | G46: =G44+G45 | H46: =H44+H45 | N46: Implied Enterprise Value (USDm) | R46: =R44+R45 | S46: =S44+S45 | T46: =T44+T45 | Z46: Implied Enterprise Value (USDm) | AD46: =AD44+AD45 | AE46: =AE44+AE45 | AF46: =AF44+AF45
B47: Implied EV / Adjusted EBITDA (x) | F47: =IFERROR(F46/F35,"") | G47: =IFERROR(G46/G35,"") | H47: =IFERROR(H46/H35,"") | N47: Implied EV / Adjusted EBITDA (x) | R47: =IFERROR(R46/R35,"") | S47: =IFERROR(S46/S35,"") | T47: =IFERROR(T46/T35,"") | Z47: Implied EV / Adjusted EBITDA (x) | AD47: =IFERROR(AD46/AD35,"") | AE47: =IFERROR(AE46/AE35,"") | AF47: =IFERROR(AF46/AF35,"")

Sheet DCF
B2: DCF VALUATION — OLD DOMINION FREIGHT LINE (ODFL)
B4: 1. WACC BUILD
B5: Risk-free rate (US 10Y govt) | C5: 0.055 | D5: Assumption (~US 10Y Treasury yield); update to market
B6: Equity risk premium | C6: 0.05 | D6: US implied ERP ~4.5–5.5% (Damodaran)
B7: Levered beta | C7: 1.05 | D7: LTL peers (SAIA, XPO, ArcBest, TFI) ~1.1–1.4; ODFL ~1.0–1.1 — union-free, net-cash balance sheet and best-in-class service dampen cyclicality
B8: Cost of equity | C8: =C5+C7*C6
B9: Pre-tax cost of debt | C9: 0.048 | D9: Minimal debt ($20m Series B 2.79% notes, final May-2027); $400m revolver at SOFR + 1.00%; marginal cost ~4.5–5.0%
B10: Tax rate | C10: 0.25 | D10: Model 2027E+ effective tax rate (1H/26 25.0%)
B11: After-tax cost of debt | C11: =C9*(1-C10)
B12: Target D/V | C12: 0.02 | D12: Net cash (~$264m at 30-Jun-26) vs ~$41bn market cap ($198.39 × ~208m shares); capital structure effectively all equity
B13: WACC | C13: =C8*(1-C12)+C11*C12
B15: Valuation date (live) | C15: =TODAY() | D15: Periods = (Dec-31-Year − today) / 365.25; cash flows assumed at year-end
B16: 2. UNLEVERED FREE CASH FLOW BUILD (USDm)
D17: 2026E | E17: 2027E | F17: 2028E | G17: 2029E | H17: 2030E | I17: 2031E | J17: 2032E | K17: 2033E | L17: 2034E | M17: 2035E | N17: Terminal | P17: CAGR 26–30E | Q17: CAGR 26–35E
B18: Adjusted EBIT (Model; Adjusted EBITDA − D&A) | D18: =Model!CA164 | E18: =Model!CB164 | F18: =Model!CC164 | G18: =Model!CD164 | H18: =Model!CE164 | I18: =H18*(1+I$31) | J18: =I18*(1+J$31) | K18: =J18*(1+K$31) | L18: =K18*(1+L$31) | M18: =L18*(1+M$31) | P18: =IFERROR(($H18/$D18)^(1/(VALUE(LEFT($H$17,4))-VALUE(LEFT($D$17,4))))-1,"n/m") | Q18: =IFERROR(($M18/$D18)^(1/(VALUE(LEFT($M$17,4))-VALUE(LEFT($D$17,4))))-1,"n/m")
B19: y/y % | E19: =IFERROR(E18/D18-1,"") | F19: =IFERROR(F18/E18-1,"") | G19: =IFERROR(G18/F18-1,"") | H19: =IFERROR(H18/G18-1,"") | I19: =IFERROR(I18/H18-1,"") | J19: =IFERROR(J18/I18-1,"") | K19: =IFERROR(K18/J18-1,"") | L19: =IFERROR(L18/K18-1,"") | M19: =IFERROR(M18/L18-1,"")
B20: (−) Company-identified one-off items (pre-tax; nil in forecast) | D20: =-Model!CA155 | E20: =-Model!CB155 | F20: =-Model!CC155 | G20: =-Model!CD155 | H20: =-Model!CE155 | I20: =H20*(1+I$31) | J20: =I20*(1+J$31) | K20: =J20*(1+K$31) | L20: =K20*(1+L$31) | M20: =L20*(1+M$31)
B21: × (1 − tax rate) | D21: =1-$C$10 | E21: =1-$C$10 | F21: =1-$C$10 | G21: =1-$C$10 | H21: =1-$C$10 | I21: =1-$C$10 | J21: =1-$C$10 | K21: =1-$C$10 | ... M21: =1-$C$10
B22: NOPAT = (Adjusted EBIT − one-off items) × (1 − t) | D22: =(D18+D20)*D21 | E22: =(E18+E20)*E21 | F22: =(F18+F20)*F21 | G22: =(G18+G20)*G21 | H22: =(H18+H20)*H21 | I22: =(I18+I20)*I21 | J22: =(J18+J20)*J21 | K22: =(K18+K20)*K21 | ... M22: =(M18+M20)*M21
B23: plus depreciation & amortization | D23: =Model!CA108 | E23: =Model!CB108 | F23: =Model!CC108 | G23: =Model!CD108 | H23: =Model!CE108 | I23: =H23*(1+I$31) | J23: =I23*(1+J$31) | K23: =J23*(1+K$31) | L23: =K23*(1+L$31) | M23: =L23*(1+M$31)
B24: − Capex (property & equipment) and acquisitions of business assets | D24: =D29 | E24: =E29+Model!CB211 | F24: =F29+Model!CC211 | G24: =G29+Model!CD211 | H24: =H29+Model!CE211 | I24: =I29 | J24: =J29 | K24: =K29 | L24: =L29 | M24: =M29
B25: − Δ Working capital (CF statement) | D25: =Model!CA206 | E25: =Model!CB206 | F25: =Model!CC206 | G25: =Model!CD206 | H25: =Model!CE206 | I25: =H25*(1+I$31) | J25: =I25*(1+J$31) | K25: =J25*(1+K$31) | L25: =K25*(1+L$31) | M25: =L25*(1+M$31)
B26: Unlevered FCF | D26: =D22+D23+D24+D25 | E26: =E22+E23+E24+E25 | F26: =F22+F23+F24+F25 | G26: =G22+G23+G24+G25 | H26: =H22+H23+H24+H25 | I26: =I22+I23+I24+I25 | J26: =J22+J23+J24+J25 | K26: =K22+K23+K24+K25 | ... M26: =M22+M23+M24+M25 | N26: =M26*(1+$C$32) | P26: =IFERROR(($H26/$D26)^(1/(VALUE(LEFT($H$17,4))-VALUE(LEFT($D$17,4))))-1,"n/m") | Q26: =IFERROR(($M26/$D26)^(1/(VALUE(LEFT($M$17,4))-VALUE(LEFT($D$17,4))))-1,"n/m")
B27: y/y % | E27: =IFERROR(E26/D26-1,"") | F27: =IFERROR(F26/E26-1,"") | G27: =IFERROR(G26/F26-1,"") | H27: =IFERROR(H26/G26-1,"") | I27: =IFERROR(I26/H26-1,"") | J27: =IFERROR(J26/I26-1,"") | K27: =IFERROR(K26/J26-1,"") | L27: =IFERROR(L26/K26-1,"") | M27: =IFERROR(M26/L26-1,"")
B28: Terminal Value (Gordon Growth) | N28: =N26/($C$13-$C$32)
B29: memo: PP&E capex only (fade years carry no new acquisitions) | D29: =Model!CA208 | E29: =Model!CB208 | F29: =Model!CC208 | G29: =Model!CD208 | H29: =Model!CE208 | I29: =H29*(1+I$31) | J29: =I29*(1+J$31) | K29: =J29*(1+K$31) | L29: =K29*(1+L$31) | M29: =L29*(1+M$31)
B31: Fade-period growth (2031E–35E) | I31: 0.06 | J31: =I31+($M$31-$I$31)/(COLUMNS($I$31:$M$31)-1) | K31: =J31+($M$31-$I$31)/(COLUMNS($I$31:$M$31)-1) | L31: =K31+($M$31-$I$31)/(COLUMNS($I$31:$M$31)-1) | M31: 0.05
B32: Terminal growth rate | C32: 0.04
B34: Discount period (years) | D34: =(DATE(2026,12,31)-$C$15)/365.25 | E34: =(DATE(2027,12,31)-$C$15)/365.25 | F34: =(DATE(2028,12,31)-$C$15)/365.25 | G34: =(DATE(2029,12,31)-$C$15)/365.25 | H34: =(DATE(2030,12,31)-$C$15)/365.25 | I34: =(DATE(2031,12,31)-$C$15)/365.25 | J34: =(DATE(2032,12,31)-$C$15)/365.25 | K34: =(DATE(2033,12,31)-$C$15)/365.25 | L34: =(DATE(2034,12,31)-$C$15)/365.25 | M34: =(DATE(2035,12,31)-$C$15)/365.25 | N34: =M34
B35: Discount factor | D35: =1/(1+$C$13)^D34 | E35: =1/(1+$C$13)^E34 | F35: =1/(1+$C$13)^F34 | G35: =1/(1+$C$13)^G34 | H35: =1/(1+$C$13)^H34 | I35: =1/(1+$C$13)^I34 | J35: =1/(1+$C$13)^J34 | K35: =1/(1+$C$13)^K34 | ... N35: =1/(1+$C$13)^N34
B36: PV of UFCF | D36: =D26*D35 | E36: =E26*E35 | F36: =F26*F35 | G36: =G26*G35 | H36: =H26*H35 | I36: =I26*I35 | J36: =J26*J35 | K36: =K26*K35 | ... M36: =M26*M35 | N36: =N28*N35
D37: ODFL's Adjusted EBITDA (model) expenses share-based compensation and excludes disposal gains on revenue equipment / real estate; capex is gross of ~0.6% of revenue disposal proceeds (conservative). ODFL capex runs well above D&A in growth phases (2021–24 ~13–15% of revenue).
B39: Implied ROIC & incremental ROIC (USDm) | D39: =D17 | E39: =E17 | F39: =F17 | G39: =G17 | H39: =H17 | I39: =I17 | J39: =J17 | K39: =K17 | ... M39: =M17 | N39: Terminal
B40: NOPAT (row 22) | D40: =D22 | E40: =E22 | F40: =F22 | G40: =G22 | H40: =H22 | I40: =I22 | J40: =J22 | K40: =K22 | ... M40: =M22 | N40: =M40*(1+$C$32)
B41: Net investment = NOPAT − UFCF | D41: =D40-D26 | E41: =E40-E26 | F41: =F40-F26 | G41: =G40-G26 | H41: =H40-H26 | I41: =I40-I26 | J41: =J40-J26 | K41: =K40-K26 | ... N41: =N40-N26
B42: Opening invested capital | D42: =Model!BV329 | E42: =D43 | F42: =E43 | G42: =F43 | H42: =G43 | I42: =H43 | J42: =I43 | K42: =J43 | L42: =K43 | ... N42: =M43
B43: Closing invested capital | D43: =D42+D41 | E43: =E42+E41 | F43: =F42+F41 | G43: =G42+G41 | H43: =H42+H41 | I43: =I42+I41 | J43: =J42+J41 | K43: =K42+K41 | ... M43: =M42+M41
B44: Implied ROIC = NOPAT / opening IC | D44: =IFERROR(D40/D42,"") | E44: =IFERROR(E40/E42,"") | F44: =IFERROR(F40/F42,"") | G44: =IFERROR(G40/G42,"") | H44: =IFERROR(H40/H42,"") | I44: =IFERROR(I40/I42,"") | J44: =IFERROR(J40/J42,"") | K44: =IFERROR(K40/K42,"") | ... N44: =IFERROR(N40/N42,"")
B45: Reinvestment rate = net inv. / NOPAT | D45: =IFERROR(D41/D40,"") | E45: =IFERROR(E41/E40,"") | F45: =IFERROR(F41/F40,"") | G45: =IFERROR(G41/G40,"") | H45: =IFERROR(H41/H40,"") | I45: =IFERROR(I41/I40,"") | J45: =IFERROR(J41/J40,"") | K45: =IFERROR(K41/K40,"") | ... N45: =IFERROR(N41/N40,"")
B46: Incremental ROIC = Δ NOPAT / prior-yr net inv. | E46: =IFERROR((E40-D40)/D41,"") | F46: =IFERROR((F40-E40)/E41,"") | G46: =IFERROR((G40-F40)/F41,"") | H46: =IFERROR((H40-G40)/G41,"") | I46: =IFERROR((I40-H40)/H41,"") | J46: =IFERROR((J40-I40)/I41,"") | K46: =IFERROR((K40-J40)/J41,"") | L46: =IFERROR((L40-K40)/K41,"") | M46: =IFERROR((M40-L40)/L41,"") | N46: =IFERROR($C$32/N45,"")
B47: Cumulative incremental ROIC 2026E–35E | C47: =IFERROR((M40-D40)/SUM(D41:L41),"")
D48: Opening IC = Model 2025A book IC (equity + net debt), rolled forward with DCF net investment (capex − D&A + ΔWC). Terminal incremental ROIC = g / reinvestment rate.
B49: 3. VALUATION SUMMARY
B50: Sum of PV (explicit + fade) | C50: =SUM(D36:M36)
B51: PV of Terminal Value | C51: =N36
B52: Enterprise Value | C52: =C50+C51
B53: Less: net debt (Model 2026E YE; negative = net cash) | C53: =Model!CA350
B54: Less: non-controlling interests (none) | C54: =Model!CA359
B55: Equity Value | C55: =C52-C53-C54
B56: Diluted shares (m, Model 2026E period end) | C56: =Model!CA356
B57: Implied share price ($) | C57: =C55/C56
B58: Current share price ($) | C58: =Model!CA355
B59: Implied upside / (downside) | C59: =C57/C58-1
B60: Required discount to DCF value for target IRR (discount closes over horizon; value compounds at WACC) | C60: =1-((1+C13)/(1+F60))^F61 | E60: Target IRR | F60: 0.15
B61: Max entry price for target IRR ($) — % vs. current share price shown right | C61: =C57*(1-C60) | D61: =C61/C58-1 | E61: Years for discount to close | F61: 3
B64: 4. SENSITIVITY: IMPLIED PRICE ($) — WACC × Terminal Growth
B65: WACC step (across) | C65: 0.005
B66: Terminal growth step (down) | C66: 0.005
B67: g (down) / WACC | D67: =E67-$C$65 | E67: =F67-$C$65 | F67: =$C$13 | G67: =F67+$C$65 | H67: =G67+$C$65
B68: =B69-$C$66 | D68: =IFERROR((SUMPRODUCT($D$26:$M$26/(1+D$67)^$D$34:$M$34)+($M$26*(1+$B68)/(D$67-$B68))/(1+D$67)^$M$34-$C$53-$C$54)/$C$56,"") | E68: =IFERROR((SUMPRODUCT($D$26:$M$26/(1+E$67)^$D$34:$M$34)+($M$26*(1+$B68)/(E$67-$B68))/(1+E$67)^$M$34-$C$53-$C$54)/$C$56,"") | F68: =IFERROR((SUMPRODUCT($D$26:$M$26/(1+F$67)^$D$34:$M$34)+($M$26*(1+$B68)/(F$67-$B68))/(1+F$67)^$M$34-$C$53-$C$54)/$C$56,"") | G68: =IFERROR((SUMPRODUCT($D$26:$M$26/(1+G$67)^$D$34:$M$34)+($M$26*(1+$B68)/(G$67-$B68))/(1+G$67)^$M$34-$C$53-$C$54)/$C$56,"") | H68: =IFERROR((SUMPRODUCT($D$26:$M$26/(1+H$67)^$D$34:$M$34)+($M$26*(1+$B68)/(H$67-$B68))/(1+H$67)^$M$34-$C$53-$C$54)/$C$56,"")
B69: =B70-$C$66 | D69: =IFERROR((SUMPRODUCT($D$26:$M$26/(1+D$67)^$D$34:$M$34)+($M$26*(1+$B69)/(D$67-$B69))/(1+D$67)^$M$34-$C$53-$C$54)/$C$56,"") | E69: =IFERROR((SUMPRODUCT($D$26:$M$26/(1+E$67)^$D$34:$M$34)+($M$26*(1+$B69)/(E$67-$B69))/(1+E$67)^$M$34-$C$53-$C$54)/$C$56,"") | F69: =IFERROR((SUMPRODUCT($D$26:$M$26/(1+F$67)^$D$34:$M$34)+($M$26*(1+$B69)/(F$67-$B69))/(1+F$67)^$M$34-$C$53-$C$54)/$C$56,"") | G69: =IFERROR((SUMPRODUCT($D$26:$M$26/(1+G$67)^$D$34:$M$34)+($M$26*(1+$B69)/(G$67-$B69))/(1+G$67)^$M$34-$C$53-$C$54)/$C$56,"") | H69: =IFERROR((SUMPRODUCT($D$26:$M$26/(1+H$67)^$D$34:$M$34)+($M$26*(1+$B69)/(H$67-$B69))/(1+H$67)^$M$34-$C$53-$C$54)/$C$56,"")
B70: =$C$32 | D70: =IFERROR((SUMPRODUCT($D$26:$M$26/(1+D$67)^$D$34:$M$34)+($M$26*(1+$B70)/(D$67-$B70))/(1+D$67)^$M$34-$C$53-$C$54)/$C$56,"") | E70: =IFERROR((SUMPRODUCT($D$26:$M$26/(1+E$67)^$D$34:$M$34)+($M$26*(1+$B70)/(E$67-$B70))/(1+E$67)^$M$34-$C$53-$C$54)/$C$56,"") | F70: =IFERROR((SUMPRODUCT($D$26:$M$26/(1+F$67)^$D$34:$M$34)+($M$26*(1+$B70)/(F$67-$B70))/(1+F$67)^$M$34-$C$53-$C$54)/$C$56,"") | G70: =IFERROR((SUMPRODUCT($D$26:$M$26/(1+G$67)^$D$34:$M$34)+($M$26*(1+$B70)/(G$67-$B70))/(1+G$67)^$M$34-$C$53-$C$54)/$C$56,"") | H70: =IFERROR((SUMPRODUCT($D$26:$M$26/(1+H$67)^$D$34:$M$34)+($M$26*(1+$B70)/(H$67-$B70))/(1+H$67)^$M$34-$C$53-$C$54)/$C$56,"")
B71: =B70+$C$66 | D71: =IFERROR((SUMPRODUCT($D$26:$M$26/(1+D$67)^$D$34:$M$34)+($M$26*(1+$B71)/(D$67-$B71))/(1+D$67)^$M$34-$C$53-$C$54)/$C$56,"") | E71: =IFERROR((SUMPRODUCT($D$26:$M$26/(1+E$67)^$D$34:$M$34)+($M$26*(1+$B71)/(E$67-$B71))/(1+E$67)^$M$34-$C$53-$C$54)/$C$56,"") | F71: =IFERROR((SUMPRODUCT($D$26:$M$26/(1+F$67)^$D$34:$M$34)+($M$26*(1+$B71)/(F$67-$B71))/(1+F$67)^$M$34-$C$53-$C$54)/$C$56,"") | G71: =IFERROR((SUMPRODUCT($D$26:$M$26/(1+G$67)^$D$34:$M$34)+($M$26*(1+$B71)/(G$67-$B71))/(1+G$67)^$M$34-$C$53-$C$54)/$C$56,"") | H71: =IFERROR((SUMPRODUCT($D$26:$M$26/(1+H$67)^$D$34:$M$34)+($M$26*(1+$B71)/(H$67-$B71))/(1+H$67)^$M$34-$C$53-$C$54)/$C$56,"")
B72: =B71+$C$66 | D72: =IFERROR((SUMPRODUCT($D$26:$M$26/(1+D$67)^$D$34:$M$34)+($M$26*(1+$B72)/(D$67-$B72))/(1+D$67)^$M$34-$C$53-$C$54)/$C$56,"") | E72: =IFERROR((SUMPRODUCT($D$26:$M$26/(1+E$67)^$D$34:$M$34)+($M$26*(1+$B72)/(E$67-$B72))/(1+E$67)^$M$34-$C$53-$C$54)/$C$56,"") | F72: =IFERROR((SUMPRODUCT($D$26:$M$26/(1+F$67)^$D$34:$M$34)+($M$26*(1+$B72)/(F$67-$B72))/(1+F$67)^$M$34-$C$53-$C$54)/$C$56,"") | G72: =IFERROR((SUMPRODUCT($D$26:$M$26/(1+G$67)^$D$34:$M$34)+($M$26*(1+$B72)/(G$67-$B72))/(1+G$67)^$M$34-$C$53-$C$54)/$C$56,"") | H72: =IFERROR((SUMPRODUCT($D$26:$M$26/(1+H$67)^$D$34:$M$34)+($M$26*(1+$B72)/(H$67-$B72))/(1+H$67)^$M$34-$C$53-$C$54)/$C$56,"")
B75: 5. REVERSE DCF
B76: To solve for the market-implied path: Data ▸ What-If Analysis ▸ Goal Seek — set C57 (implied price) to the current price (C58) by changing C32 (terminal growth) or the Model scenario levers (tons/day growth, ex-fuel yield, operating ratio).
B78: 6. MAUBOUSSIN EV / NOPAT — TWO-STAGE FRAMEWORK
B79: EV/NOPAT = 1/r + [g × (1 − r/ROIIC) / (r × (r − g))] × [1 − ((1+g)/(1+r))^N]
B80: Formula source: Mauboussin & Rappaport, "Expectations Investing" (2021); Counterpoint Global, "What Does a Price-Earnings Multiple Mean?" (2020).
B82: Input | C82: Value | D82: Rationale (Old Dominion characteristics)
B83: r (Cost of capital / WACC) | C83: =$C$13 | D83: Linked from Section 1 WACC build
B84: g (NOPAT growth, Stage 1) | C84: 0.11 | D84: Model Adjusted EBIT CAGR 2026–30E: tons/day recovery (+4–5% p.a.), ex-fuel yield +4–5% and operating-ratio improvement toward 68.5% → ~12% NOPAT growth
B85: ROIIC (Return on incremental invested capital) | C85: 0.25 | D85: Service-led share gains on a network with excess door capacity: incremental density earns very high returns (2016–25 ROIC 20–30% after tax on book IC)
B86: N (Years of value creation / CAP) | C86: 15 | D86: Union-free, owned real estate (240 of 260 service centers), 99% on-time / 0.1% claims ratio and a decades-long record of LTL share gains; long runway in a consolidating industry
B88: Calculation | C88: Value
B89: Steady-state component: 1 / r | C89: =1/C83
B90: Value-creation factor: 1 − r / ROIIC | C90: =1-C83/C85
B91: Growth multiplier: g × (1 − r/ROIIC) / (r × (r − g)) | C91: =C84*C90/(C83*(C83-C84))
B92: Time decay: 1 − ((1+g)/(1+r))^N | C92: =1-((1+C84)/(1+C83))^C86
B93: PVGO component (growth value) | C93: =C91*C92
B94: Mauboussin EV / NOPAT (steady-state + PVGO) | C94: =C89+C93
B96: VALUATION — Applied to 2028E NOPAT | C96: USDm
B97: 2028E Adjusted EBIT (Model) | C97: =Model!CC164
B98: (−) 2028E company-identified one-off items | C98: =-Model!CC155
B99: Tax rate (from WACC build) | C99: =$C$10
B100: 2028E NOPAT = (Adj. EBIT − one-off items) × (1 − t) | C100: =(C97+C98)*(1-C99)
B101: × Mauboussin EV/NOPAT multiple | C101: =C94
B102: Implied Enterprise Value (2028E basis) | C102: =C100*C101
B103: Less: YE2027 net debt + NCI (Model) | C103: =Model!CB350+Model!CB359
B104: Implied Equity Value | C104: =C102-C103
B105: Diluted shares 2028E (m, Model) | C105: =Model!CC356
B106: Implied share price 2028 ($) | C106: =C104/C105
B108: Current share price ($) | C108: =C58
B109: Implied upside / (downside) | C109: =C106/C108-1
B111: MARKET-IMPLIED EV/NOPAT TODAY | C111: USDm
B112: Current market cap (spot × diluted shares) | C112: =C58*C56
B113: Plus: YE2026 net debt & NCI | C113: =C53+C54
B114: Implied Enterprise Value (today) | C114: =C112+C113
B115: ODFL's market-implied EV/NOPAT (on 2028E NOPAT) | C115: =C114/C100
B117: Multiple gap (Mauboussin − Market) | C117: =C94-C115
...

Sheet Charts
B2: Old Dominion Freight Line — Historical Operating Performance (2006–2025)
B3: All historicals · USDm · Linked to Model. Volume / price = tons per day and revenue per hundredweight excluding fuel surcharges, y/y (total-tons basis to 2013, LTL from 2014). Adjusted EBITDA = model definition (ODFL publishes no non-GAAP measures). ROIC / RONTA on Adjusted EBIT.
C7: 2006 | D7: 2007 | E7: 2008 | F7: 2009 | G7: 2010 | H7: 2011 | I7: 2012 | J7: 2013 | K7: 2014 | L7: 2015 | M7: 2016 | N7: 2017 | O7: 2018 | P7: 2019 | Q7: 2020 | R7: 2021 | S7: 2022 | T7: 2023 | U7: 2024 | V7: 2025
B8: Tons per day y/y % | C8: =IFERROR(Model!C13+0,IFERROR(Model!C13+0,0)) | D8: =IFERROR(Model!D13+0,IFERROR(Model!D13+0,0)) | E8: =IFERROR(Model!E13+0,IFERROR(Model!E13+0,0)) | F8: =IFERROR(Model!F13+0,IFERROR(Model!F13+0,0)) | G8: =IFERROR(Model!G13+0,IFERROR(Model!G13+0,0)) | H8: =IFERROR(Model!H13+0,IFERROR(Model!H13+0,0)) | I8: =IFERROR(Model!I13+0,IFERROR(Model!I13+0,0)) | J8: =IFERROR(Model!N13+0,IFERROR(Model!N13+0,0)) | K8: =IFERROR(Model!S13+0,IFERROR(Model!S13+0,0)) | L8: =IFERROR(Model!X13+0,IFERROR(Model!X13+0,0)) | M8: =IFERROR(Model!AC13+0,IFERROR(Model!AC13+0,0)) | N8: =IFERROR(Model!AH13+0,IFERROR(Model!AH13+0,0)) | O8: =IFERROR(Model!AM13+0,IFERROR(Model!AM13+0,0)) | P8: =IFERROR(Model!AR13+0,IFERROR(Model!AR13+0,0)) | Q8: =IFERROR(Model!AW13+0,IFERROR(Model!AW13+0,0)) | R8: =IFERROR(Model!BB13+0,IFERROR(Model!BB13+0,0)) | S8: =IFERROR(Model!BG13+0,IFERROR(Model!BG13+0,0)) | T8: =IFERROR(Model!BL13+0,IFERROR(Model!BL13+0,0)) | U8: =IFERROR(Model!BQ13+0,IFERROR(Model!BQ13+0,0)) | V8: =IFERROR(Model!BV13+0,IFERROR(Model!BV13+0,0))
B9: Revenue/cwt ex fuel y/y % | C9: =IFERROR(Model!C29+0,IFERROR(Model!C29+0,0)) | D9: =IFERROR(Model!D29+0,IFERROR(Model!D29+0,0)) | E9: =IFERROR(Model!E29+0,IFERROR(Model!E29+0,0)) | F9: =IFERROR(Model!F29+0,IFERROR(Model!F29+0,0)) | G9: =IFERROR(Model!G29+0,IFERROR(Model!G29+0,0)) | H9: =IFERROR(Model!H29+0,IFERROR(Model!H29+0,0)) | I9: =IFERROR(Model!I29+0,IFERROR(Model!I29+0,0)) | J9: =IFERROR(Model!N29+0,IFERROR(Model!N29+0,0)) | K9: =IFERROR(Model!S29+0,IFERROR(Model!S29+0,0)) | L9: =IFERROR(Model!X29+0,IFERROR(Model!X29+0,0)) | M9: =IFERROR(Model!AC29+0,IFERROR(Model!AC29+0,0)) | N9: =IFERROR(Model!AH29+0,IFERROR(Model!AH29+0,0)) | O9: =IFERROR(Model!AM29+0,IFERROR(Model!AM29+0,0)) | P9: =IFERROR(Model!AR29+0,IFERROR(Model!AR29+0,0)) | Q9: =IFERROR(Model!AW29+0,IFERROR(Model!AW29+0,0)) | R9: =IFERROR(Model!BB29+0,IFERROR(Model!BB29+0,0)) | S9: =IFERROR(Model!BG29+0,IFERROR(Model!BG29+0,0)) | T9: =IFERROR(Model!BL29+0,IFERROR(Model!BL29+0,0)) | U9: =IFERROR(Model!BQ29+0,IFERROR(Model!BQ29+0,0)) | V9: =IFERROR(Model!BV29+0,IFERROR(Model!BV29+0,0))
C11: =C7 | D11: =D7 | E11: =E7 | F11: =F7 | G11: =G7 | H11: =H7 | I11: =I7 | J11: =J7 | ... V11: =V7
B12: Adjusted EBITDA | C12: =Model!C157 | D12: =Model!D157 | E12: =Model!E157 | F12: =Model!F157 | G12: =Model!G157 | H12: =Model!H157 | I12: =Model!I157 | J12: =Model!N157 | K12: =Model!S157 | L12: =Model!X157 | M12: =Model!AC157 | N12: =Model!AH157 | O12: =Model!AM157 | P12: =Model!AR157 | Q12: =Model!AW157 | R12: =Model!BB157 | S12: =Model!BG157 | T12: =Model!BL157 | U12: =Model!BQ157 | V12: =Model!BV157
B13: Operating Income (GAAP) | C13: =Model!C114 | D13: =Model!D114 | E13: =Model!E114 | F13: =Model!F114 | G13: =Model!G114 | H13: =Model!H114 | I13: =Model!I114 | J13: =Model!N114 | K13: =Model!S114 | L13: =Model!X114 | M13: =Model!AC114 | N13: =Model!AH114 | O13: =Model!AM114 | P13: =Model!AR114 | Q13: =Model!AW114 | R13: =Model!BB114 | S13: =Model!BG114 | T13: =Model!BL114 | U13: =Model!BQ114 | V13: =Model!BV114
B14: Adj. EBITDA Margin % | C14: =Model!C192 | D14: =Model!D192 | E14: =Model!E192 | F14: =Model!F192 | G14: =Model!G192 | H14: =Model!H192 | I14: =Model!I192 | J14: =Model!N192 | K14: =Model!S192 | L14: =Model!X192 | M14: =Model!AC192 | N14: =Model!AH192 | O14: =Model!AM192 | P14: =Model!AR192 | Q14: =Model!AW192 | R14: =Model!BB192 | S14: =Model!BG192 | T14: =Model!BL192 | U14: =Model!BQ192 | V14: =Model!BV192
B15: GAAP Op. Margin % | C15: =Model!C194 | D15: =Model!D194 | E15: =Model!E194 | F15: =Model!F194 | G15: =Model!G194 | H15: =Model!H194 | I15: =Model!I194 | J15: =Model!N194 | K15: =Model!S194 | L15: =Model!X194 | M15: =Model!AC194 | N15: =Model!AH194 | O15: =Model!AM194 | P15: =Model!AR194 | Q15: =Model!AW194 | R15: =Model!BB194 | S15: =Model!BG194 | T15: =Model!BL194 | U15: =Model!BQ194 | V15: =Model!BV194
C17: =C7 | D17: =D7 | E17: =E7 | F17: =F7 | G17: =G7 | H17: =H7 | I17: =I7 | J17: =J7 | ... V17: =V7
B18: ROIC | C18: =IFERROR(Model!C332+0,NA()) | D18: =IFERROR(Model!D332+0,NA()) | E18: =IFERROR(Model!E332+0,NA()) | F18: =IFERROR(Model!F332+0,NA()) | G18: =IFERROR(Model!G332+0,NA()) | H18: =IFERROR(Model!H332+0,NA()) | I18: =IFERROR(Model!I332+0,NA()) | J18: =IFERROR(Model!N332+0,NA()) | K18: =IFERROR(Model!S332+0,NA()) | L18: =IFERROR(Model!X332+0,NA()) | M18: =IFERROR(Model!AC332+0,NA()) | N18: =IFERROR(Model!AH332+0,NA()) | O18: =IFERROR(Model!AM332+0,NA()) | P18: =IFERROR(Model!AR332+0,NA()) | Q18: =IFERROR(Model!AW332+0,NA()) | R18: =IFERROR(Model!BB332+0,NA()) | S18: =IFERROR(Model!BG332+0,NA()) | T18: =IFERROR(Model!BL332+0,NA()) | U18: =IFERROR(Model!BQ332+0,NA()) | V18: =IFERROR(Model!BV332+0,NA())
B19: RONTA | C19: =IFERROR(Model!C344+0,NA()) | D19: =IFERROR(Model!D344+0,NA()) | E19: =IFERROR(Model!E344+0,NA()) | F19: =IFERROR(Model!F344+0,NA()) | G19: =IFERROR(Model!G344+0,NA()) | H19: =IFERROR(Model!H344+0,NA()) | I19: =IFERROR(Model!I344+0,NA()) | J19: =IFERROR(Model!N344+0,NA()) | K19: =IFERROR(Model!S344+0,NA()) | L19: =IFERROR(Model!X344+0,NA()) | M19: =IFERROR(Model!AC344+0,NA()) | N19: =IFERROR(Model!AH344+0,NA()) | O19: =IFERROR(Model!AM344+0,NA()) | P19: =IFERROR(Model!AR344+0,NA()) | Q19: =IFERROR(Model!AW344+0,NA()) | R19: =IFERROR(Model!BB344+0,NA()) | S19: =IFERROR(Model!BG344+0,NA()) | T19: =IFERROR(Model!BL344+0,NA()) | U19: =IFERROR(Model!BQ344+0,NA()) | V19: =IFERROR(Model!BV344+0,NA())
B20: Adj. EBITDA margin % | C20: =IFERROR(Model!C192+0,NA()) | D20: =IFERROR(Model!D192+0,NA()) | E20: =IFERROR(Model!E192+0,NA()) | F20: =IFERROR(Model!F192+0,NA()) | G20: =IFERROR(Model!G192+0,NA()) | H20: =IFERROR(Model!H192+0,NA()) | I20: =IFERROR(Model!I192+0,NA()) | J20: =IFERROR(Model!N192+0,NA()) | K20: =IFERROR(Model!S192+0,NA()) | L20: =IFERROR(Model!X192+0,NA()) | M20: =IFERROR(Model!AC192+0,NA()) | N20: =IFERROR(Model!AH192+0,NA()) | O20: =IFERROR(Model!AM192+0,NA()) | P20: =IFERROR(Model!AR192+0,NA()) | Q20: =IFERROR(Model!AW192+0,NA()) | R20: =IFERROR(Model!BB192+0,NA()) | S20: =IFERROR(Model!BG192+0,NA()) | T20: =IFERROR(Model!BL192+0,NA()) | U20: =IFERROR(Model!BQ192+0,NA()) | V20: =IFERROR(Model!BV192+0,NA())
B21: FCF margin % | C21: =IFERROR(Model!C228+0,NA()) | D21: =IFERROR(Model!D228+0,NA()) | E21: =IFERROR(Model!E228+0,NA()) | F21: =IFERROR(Model!F228+0,NA()) | G21: =IFERROR(Model!G228+0,NA()) | H21: =IFERROR(Model!H228+0,NA()) | I21: =IFERROR(Model!I228+0,NA()) | J21: =IFERROR(Model!N228+0,NA()) | K21: =IFERROR(Model!S228+0,NA()) | L21: =IFERROR(Model!X228+0,NA()) | M21: =IFERROR(Model!AC228+0,NA()) | N21: =IFERROR(Model!AH228+0,NA()) | O21: =IFERROR(Model!AM228+0,NA()) | P21: =IFERROR(Model!AR228+0,NA()) | Q21: =IFERROR(Model!AW228+0,NA()) | R21: =IFERROR(Model!BB228+0,NA()) | S21: =IFERROR(Model!BG228+0,NA()) | T21: =IFERROR(Model!BL228+0,NA()) | U21: =IFERROR(Model!BQ228+0,NA()) | V21: =IFERROR(Model!BV228+0,NA())
