Workbook

Sheet Model
CT1: SCENARIO SWITCH ▼ (Bull / Base / Bear) — drives all scenario-linked forecast drivers
B2: RB Global, Inc. (NYSE / TSX: RBA) — 3-Statement Financial Model | CT2: Base
B3: US GAAP as reported (2015+) · USD millions (per-share data in USD) · Source: RB Global / Ritchie Bros. Auctioneers Forms 40-F (2006–14), 6-K (2013–15 quarters), 10-K / 10-Q (2015+) and Form 8-K earnings releases (Ex. 99.1), SEC EDGAR CIK 0001046102
B4: Basis notes: FY2006–10 Canadian GAAP and FY2011–12 / 2013–14 quarters IFRS (40-F / 6-K), FY2013–14 annuals US GAAP as recast in the FY2015 10-K; 2015+ US GAAP. Pre-2017 revenue on the legacy net (agency) basis — ASC 606 (2018, full retrospective) recast 2017 to gross inventory sales; 2016 shown with a recast memo. IronPlanet from 31-May-2017; IAA from 20-Mar-2023 (single reportable segment since 2023). Q3/26E–Q4/26E = FY26 outlook less 1H/26 actuals.
CV5: Forecast | CW5: Historical | CX5: Historical | CY5: Historical
B6: (USDm) | C6: 2006 | D6: 2007 | E6: 2008 | F6: 2009 | G6: 2010 | H6: 2011 | I6: 2012 | J6: Q1/13 | K6: Q2/13 | L6: 1H/13 | M6: Q3/13 | N6: Q4/13 | O6: 2013 | P6: Q1/14 | Q6: Q2/14 | R6: 1H/14 | S6: Q3/14 | T6: Q4/14 | U6: 2014 | V6: Q1/15 | W6: Q2/15 | X6: 1H/15 | Y6: Q3/15 | Z6: Q4/15 | AA6: 2015 | AB6: Q1/16 | AC6: Q2/16 | AD6: 1H/16 | AE6: Q3/16 | AF6: Q4/16 | AG6: 2016 | AH6: Q1/17 | AI6: Q2/17 | AJ6: 1H/17 | AK6: Q3/17 | AL6: Q4/17 | AM6: 2017 | AN6: Q1/18 | AO6: Q2/18 | AP6: 1H/18 | AQ6: Q3/18 | AR6: Q4/18 | AS6: 2018 | AT6: Q1/19 | AU6: Q2/19 | AV6: 1H/19 | AW6: Q3/19 | AX6: Q4/19 | AY6: 2019 | AZ6: Q1/20 | BA6: Q2/20 | BB6: 1H/20 | BC6: Q3/20 | BD6: Q4/20 | BE6: 2020 | BF6: Q1/21 | BG6: Q2/21 | BH6: 1H/21 | BI6: Q3/21 | BJ6: Q4/21 | BK6: 2021 | BL6: Q1/22 | BM6: Q2/22 | BN6: 1H/22 | BO6: Q3/22 | BP6: Q4/22 | BQ6: 2022 | BR6: Q1/23 | BS6: Q2/23 | BT6: 1H/23 | BU6: Q3/23 | BV6: Q4/23 | BW6: 2023 | BX6: Q1/24 | BY6: Q2/24 | BZ6: 1H/24 | CA6: Q3/24 | CB6: Q4/24 | CC6: 2024 | CD6: Q1/25 | CE6: Q2/25 | CF6: 1H/25 | CG6: Q3/25 | CH6: Q4/25 | CI6: 2025 | CJ6: Q1/26 | CK6: Q2/26 | CL6: 1H/26 | CM6: Q3/26E | CN6: Q4/26E | CO6: 2026E | CP6: 2027E | CQ6: 2028E | CR6: 2029E | CS6: 2030E | CT6: Modelling Notes | CV6: 5Y CAGR | CW6: 5Y CAGR | CX6: 10Y CAGR | CY6: 19Y CAGR
CV7: 25-'30 | CW7: 20-'25 | CX7: 15-'25 | CY7: 06-'25
B8: REVENUE BUILD — GTV BY SECTOR × TAKE RATE + INVENTORY SALES (single reportable segment) | CT8: REVENUE BUILD — modelling logic (RB Global reports one operating segment; the build replaces HII's segment P&L)
DB9: SCENARIO INPUT TABLE — driver assumptions per Bull / Base / Bear | DC9: Bull | DD9: Base | DE9: Bear | DF9: Bull / Bear = Base + Δ (Δ inputs on each block header). Outlook block = high / mid / low end of FY26 ranges.
B10: Automotive (salvage & remarketed passenger vehicles; IAA from 20-Mar-2023) | CT10: AUTOMOTIVE — modelling logic
B11: GTV (USDm) | BR11: 331.7 | BS11: 2101.9 | BT11: =BR11+BS11 -> 2433.6 | BU11: 2051.1 | BV11: 2046.4 | BW11: 6531.2 | BX11: 2105 | BY11: 2007.7 | BZ11: =BX11+BY11 -> 4112.7 | CA11: 2031.1 | CB11: 2133.9 | CC11: 8277.6 | CD11: 2144.7 | CE11: 2161.5 | CF11: =CD11+CE11 -> 4306.2 | CG11: 2152.2 | CH11: 2200.7 | CI11: 8659.1 | CJ11: 2289.2 | CK11: 2448.7 | CL11: =CJ11+CK11 -> 4737.9 | CM11: =CM39*CG11*CL11/CF11/(CG11*CL11/CF11+CG19*CL19/CF19+CG29*CL29/CF29) -> 2273.9582 | CN11: =CN39*CH11*CL11/CF11/(CH11*CL11/CF11+CH19*CL19/CF19+CH29*CL29/CF29) -> 2320.9804 | CO11: =SUM(CJ11,CK11,CM11,CN11) -> 9332.8386 | CP11: =CO11*(1+CP15) -> 9799.4806 | CQ11: =CP11*(1+CQ15) -> 10289.455 | CR11: =CQ11*(1+CR15) -> 10752.48 | CS11: =CR11*(1+CS15) -> 11236.342 | CT11: Q3/26E–Q4/26E: total GTV (FY26 outlook) allocated across sectors by prior-year same-quarter sector GTV × 1H/26 sector y/y momentum. 2027E+: prior year × (1 + scenario sector GTV growth). | CV11: =IFERROR((CS11/CI11)^(1/5)-1,"n/m") -> 0.053490045 | CW11: =IFERROR((CI11/BE11)^(1/5)-1,"n/m") -> n/m | CX11: =IFERROR((CI11/AA11)^(1/10)-1,"n/m") -> n/m | CY11: =IFERROR((CI11/C11)^(1/19)-1,"n/m") -> n/m | DB11: FY26 outlook — Q2-26 release (4-Aug-26) | DC11: High | DD11: Mid | DE11: Low
B12: Lots sold (000s) | BR12: 87.5 | BS12: 573.4 | BT12: =BR12+BS12 -> 660.9 | BU12: 555 | BV12: 572.5 | BW12: 1788.4 | BX12: 584.6 | BY12: 547.7 | BZ12: =BX12+BY12 -> 1132.3 | CA12: 553.8 | CB12: 611.1 | CC12: 2297.2 | CD12: 625.6 | CE12: 595.9 | CF12: =CD12+CE12 -> 1221.5 | CG12: 601.7 | CH12: 624.5 | CI12: 2447.7 | CJ12: 631.3 | CK12: 658.8 | CL12: =CJ12+CK12 -> 1290.1 | CM12: =IFERROR(CM11/CM13*1000,"") -> 617.22376 | CN12: =IFERROR(CN11/CN13*1000,"") -> 639.44891 | CO12: =SUM(CJ12,CK12,CM12,CN12) -> 2546.7727 | CP12: =IFERROR(CP11/CP13*1000,"") -> 2608.8891 | CQ12: =IFERROR(CQ11/CQ13*1000,"") -> 2672.5205 | CR12: =IFERROR(CR11/CR13*1000,"") -> 2738.0235 | CS12: =IFERROR(CS11/CS13*1000,"") -> 2805.1319 | DB12: GTV growth % | DC12: 0.11 | DD12: 0.1 | DE12: 0.09
B13: GTV per lot sold ($) | C13: =IFERROR(C11/C12*1000,"") | D13: =IFERROR(D11/D12*1000,"") | E13: =IFERROR(E11/E12*1000,"") | F13: =IFERROR(F11/F12*1000,"") | G13: =IFERROR(G11/G12*1000,"") | H13: =IFERROR(H11/H12*1000,"") | I13: =IFERROR(I11/I12*1000,"") | J13: =IFERROR(J11/J12*1000,"") | ... CL13: =IFERROR(CL11/CL12*1000,"") -> 3672.506 | CM13: =CG13*(1+$CO$14) -> 3684.1715 | CN13: =CH13*(1+$CO$14) -> 3629.6573 | CO13: =IFERROR(CO11/CO12*1000,"") -> 3664.5747 | CP13: =CO13*(1+CP14) -> 3756.189 | CQ13: =CP13*(1+CQ14) -> 3850.0938 | CR13: =CQ13*(1+CR14) -> 3927.0956 | CS13: =CR13*(1+CS14) -> 4005.6376 | DB13: Adjusted EBITDA ($m) | DC13: 1545 | DD13: 1520 | DE13: 1495
B14: GTV per lot y/y % (forecast input) | D14: =IFERROR(D13/C13-1,"") | E14: =IFERROR(E13/D13-1,"") | F14: =IFERROR(F13/E13-1,"") | G14: =IFERROR(G13/F13-1,"") | H14: =IFERROR(H13/G13-1,"") | I14: =IFERROR(I13/H13-1,"") | O14: =IFERROR(O13/I13-1,"") | P14: =IFERROR(P13/J13-1,"") | Q14: =IFERROR(Q13/K13-1,"") | R14: =IFERROR(R13/L13-1,"") | S14: =IFERROR(S13/M13-1,"") | T14: =IFERROR(T13/N13-1,"") | U14: =IFERROR(U13/O13-1,"") | V14: =IFERROR(V13/P13-1,"") | ... CL14: =IFERROR(CL13/CF13-1,"") -> 0.041745875 | CO14: 0.03 | CP14: 0.025 | CQ14: 0.025 | CR14: 0.02 | CS14: 0.02 | CT14: Price/mix per lot (input). 2026E cell drives Q3/Q4-26E lots (vs prior-year quarter GTV per lot).
B15: GTV y/y % | D15: =IFERROR(D11/C11-1,"") | E15: =IFERROR(E11/D11-1,"") | F15: =IFERROR(F11/E11-1,"") | G15: =IFERROR(G11/F11-1,"") | H15: =IFERROR(H11/G11-1,"") | I15: =IFERROR(I11/H11-1,"") | O15: =IFERROR(O11/I11-1,"") | P15: =IFERROR(P11/J11-1,"") | Q15: =IFERROR(Q11/K11-1,"") | R15: =IFERROR(R11/L11-1,"") | S15: =IFERROR(S11/M11-1,"") | T15: =IFERROR(T11/N11-1,"") | U15: =IFERROR(U11/O11-1,"") | V15: =IFERROR(V11/P11-1,"") | ... CO15: =IFERROR(CO11/CI11-1,"") -> 0.077807003 | CP15: =CHOOSE(MATCH($CT$2,{"Bull","Base","Bear"},0),$DC$21,$DD$21,$DE$21) -> 0.05 | CQ15: =CHOOSE(MATCH($CT$2,{"Bull","Base","Bear"},0),$DC$22,$DD$22,$DE$22) -> 0.05 | CR15: =CHOOSE(MATCH($CT$2,{"Bull","Base","Bear"},0),$DC$23,$DD$23,$DE$23) -> 0.045 | CS15: =CHOOSE(MATCH($CT$2,{"Bull","Base","Bear"},0),$DC$24,$DD$24,$DE$24) -> 0.045 | CT15: 2027E–2030E: scenario lever (AUTO_gtvGrowth, Bull/Base/Bear table →). | DB15: FY26 outlook — point estimates (all cases)
B16: Lots sold y/y % | D16: =IFERROR(D12/C12-1,"") | E16: =IFERROR(E12/D12-1,"") | F16: =IFERROR(F12/E12-1,"") | G16: =IFERROR(G12/F12-1,"") | H16: =IFERROR(H12/G12-1,"") | I16: =IFERROR(I12/H12-1,"") | O16: =IFERROR(O12/I12-1,"") | P16: =IFERROR(P12/J12-1,"") | Q16: =IFERROR(Q12/K12-1,"") | R16: =IFERROR(R12/L12-1,"") | S16: =IFERROR(S12/M12-1,"") | T16: =IFERROR(T12/N12-1,"") | U16: =IFERROR(U12/O12-1,"") | V16: =IFERROR(V12/P12-1,"") | ... CO16: =IFERROR(CO12/CI12-1,"") -> 0.040475823 | CP16: =IFERROR(CP12/CO12-1,"") -> 0.024390244 | CQ16: =IFERROR(CQ12/CP12-1,"") -> 0.024390244 | CR16: =IFERROR(CR12/CQ12-1,"") -> 0.024509804 | CS16: =IFERROR(CS12/CR12-1,"") -> 0.024509804 | DB16: Tax rate (GAAP & adjusted) | DD16: 0.24
DB17: Capital expenditures ($m) | DD17: 375
B18: Heavy Equipment & Transportation (HE&T — current basis from Q1/25) | CT18: HEAVY EQUIPMENT & TRANSPORTATION — modelling logic
B19: GTV (USDm) | CD19: 1562.7 | CE19: 1928.1 | CF19: =CD19+CE19 -> 3490.8 | CG19: 1627.3 | CH19: 1957.7 | CI19: 7075.8 | CJ19: 1943.5 | CK19: 2076.6 | CL19: =CJ19+CK19 -> 4020.1 | CM19: =CM39*CG19*CL19/CF19/(CG11*CL11/CF11+CG19*CL19/CF19+CG29*CL29/CF29) -> 1799.6484 | CN19: =CN39*CH19*CL19/CF19/(CH11*CL11/CF11+CH19*CL19/CF19+CH29*CL29/CF29) -> 2161.1105 | CO19: =SUM(CJ19,CK19,CM19,CN19) -> 7980.8589 | CP19: =CO19*(1+CP23) -> 8459.7104 | CQ19: =CP19*(1+CQ23) -> 8840.3974 | CR19: =CQ19*(1+CR23) -> 9194.0133 | CS19: =CR19*(1+CS23) -> 9561.7738 | CT19: Q3/26E–Q4/26E: total GTV (FY26 outlook) allocated across sectors by prior-year same-quarter sector GTV × 1H/26 sector y/y momentum. 2027E+: prior year × (1 + scenario sector GTV growth). | CV19: =IFERROR((CS19/CI19)^(1/5)-1,"n/m") -> 0.062068635 | CW19: =IFERROR((CI19/BE19)^(1/5)-1,"n/m") -> n/m | CX19: =IFERROR((CI19/AA19)^(1/10)-1,"n/m") -> n/m | CY19: =IFERROR((CI19/C19)^(1/19)-1,"n/m") -> n/m
B20: Lots sold (000s) | CD20: 156.5 | CE20: 186.4 | CF20: =CD20+CE20 -> 342.9 | CG20: 163 | CH20: 197.4 | CI20: 703.3 | CJ20: 179.4 | CK20: 200 | CL20: =CJ20+CK20 -> 379.4 | CM20: =IFERROR(CM19/CM21*1000,"") -> 176.72886 | CN20: =IFERROR(CN19/CN21*1000,"") -> 213.63766 | CO20: =SUM(CJ20,CK20,CM20,CN20) -> 769.76652 | CP20: =IFERROR(CP19/CP21*1000,"") -> 799.95344 | CQ20: =IFERROR(CQ19/CQ21*1000,"") -> 819.56014 | CR20: =IFERROR(CR19/CR21*1000,"") -> 835.62995 | CS20: =IFERROR(CS19/CS21*1000,"") -> 852.01485 | DB20: AUTO_gtvGrowth (Automotive GTV y/y) | DC20: 0.02 | DD20: Δ → | DE20: -0.03 | DF20: Automotive: US salvage volumes (accident frequency × total-loss rate), insurer share gains, price per vehicle.
B21: GTV per lot sold ($) | C21: =IFERROR(C19/C20*1000,"") | D21: =IFERROR(D19/D20*1000,"") | E21: =IFERROR(E19/E20*1000,"") | F21: =IFERROR(F19/F20*1000,"") | G21: =IFERROR(G19/G20*1000,"") | H21: =IFERROR(H19/H20*1000,"") | I21: =IFERROR(I19/I20*1000,"") | J21: =IFERROR(J19/J20*1000,"") | ... CL21: =IFERROR(CL19/CL20*1000,"") -> 10595.941 | CM21: =CG21*(1+$CO$22) -> 10183.104 | CN21: =CH21*(1+$CO$22) -> 10115.775 | CO21: =IFERROR(CO19/CO20*1000,"") -> 10367.896 | CP21: =CO21*(1+CP22) -> 10575.254 | CQ21: =CP21*(1+CQ22) -> 10786.759 | CR21: =CQ21*(1+CR22) -> 11002.494 | CS21: =CR21*(1+CS22) -> 11222.544 | DB21: 2027E | DC21: =DD21+$DC$20 -> 0.07 | DD21: 0.05 | DE21: =DD21+$DE$20 -> 0.02
B22: GTV per lot y/y % (forecast input) | D22: =IFERROR(D21/C21-1,"") | E22: =IFERROR(E21/D21-1,"") | F22: =IFERROR(F21/E21-1,"") | G22: =IFERROR(G21/F21-1,"") | H22: =IFERROR(H21/G21-1,"") | I22: =IFERROR(I21/H21-1,"") | O22: =IFERROR(O21/I21-1,"") | P22: =IFERROR(P21/J21-1,"") | Q22: =IFERROR(Q21/K21-1,"") | R22: =IFERROR(R21/L21-1,"") | S22: =IFERROR(S21/M21-1,"") | T22: =IFERROR(T21/N21-1,"") | U22: =IFERROR(U21/O21-1,"") | V22: =IFERROR(V21/P21-1,"") | ... CL22: =IFERROR(CL21/CF21-1,"") -> 0.040835383 | CO22: 0.02 | CP22: 0.02 | CQ22: 0.02 | CR22: 0.02 | CS22: 0.02 | CT22: Price/mix per lot (input). 2026E cell drives Q3/Q4-26E lots (vs prior-year quarter GTV per lot). | DB22: 2028E | DC22: =DD22+$DC$20 -> 0.07 | DD22: 0.05 | DE22: =DD22+$DE$20 -> 0.02
B23: GTV y/y % | D23: =IFERROR(D19/C19-1,"") | E23: =IFERROR(E19/D19-1,"") | F23: =IFERROR(F19/E19-1,"") | G23: =IFERROR(G19/F19-1,"") | H23: =IFERROR(H19/G19-1,"") | I23: =IFERROR(I19/H19-1,"") | O23: =IFERROR(O19/I19-1,"") | P23: =IFERROR(P19/J19-1,"") | Q23: =IFERROR(Q19/K19-1,"") | R23: =IFERROR(R19/L19-1,"") | S23: =IFERROR(S19/M19-1,"") | T23: =IFERROR(T19/N19-1,"") | U23: =IFERROR(U19/O19-1,"") | V23: =IFERROR(V19/P19-1,"") | ... CO23: =IFERROR(CO19/CI19-1,"") -> 0.12790906 | CP23: =CHOOSE(MATCH($CT$2,{"Bull","Base","Bear"},0),$DC$27,$DD$27,$DE$27) -> 0.06 | CQ23: =CHOOSE(MATCH($CT$2,{"Bull","Base","Bear"},0),$DC$28,$DD$28,$DE$28) -> 0.045 | CR23: =CHOOSE(MATCH($CT$2,{"Bull","Base","Bear"},0),$DC$29,$DD$29,$DE$29) -> 0.04 | CS23: =CHOOSE(MATCH($CT$2,{"Bull","Base","Bear"},0),$DC$30,$DD$30,$DE$30) -> 0.04 | CT23: 2027E–2030E: scenario lever (HET_gtvGrowth, Bull/Base/Bear table →). | DB23: 2029E | DC23: =DD23+$DC$20 -> 0.065 | DD23: 0.045 | DE23: =DD23+$DE$20 -> 0.015
B24: Lots sold y/y % | D24: =IFERROR(D20/C20-1,"") | E24: =IFERROR(E20/D20-1,"") | F24: =IFERROR(F20/E20-1,"") | G24: =IFERROR(G20/F20-1,"") | H24: =IFERROR(H20/G20-1,"") | I24: =IFERROR(I20/H20-1,"") | O24: =IFERROR(O20/I20-1,"") | P24: =IFERROR(P20/J20-1,"") | Q24: =IFERROR(Q20/K20-1,"") | R24: =IFERROR(R20/L20-1,"") | S24: =IFERROR(S20/M20-1,"") | T24: =IFERROR(T20/N20-1,"") | U24: =IFERROR(U20/O20-1,"") | V24: =IFERROR(V20/P20-1,"") | ... CO24: =IFERROR(CO20/CI20-1,"") -> 0.094506636 | CP24: =IFERROR(CP20/CO20-1,"") -> 0.039215686 | CQ24: =IFERROR(CQ20/CP20-1,"") -> 0.024509804 | CR24: =IFERROR(CR20/CQ20-1,"") -> 0.019607843 | CS24: =IFERROR(CS20/CR20-1,"") -> 0.019607843 | DB24: 2030E | DC24: =DD24+$DC$20 -> 0.065 | DD24: 0.045 | DE24: =DD24+$DE$20 -> 0.015
B25: Memo: CC&T GTV — legacy basis (2023–Q1/26) | BR25: 1190 | BS25: 1481.3 | BT25: =BR25+BS25 -> 2671.3 | BU25: 1352.5 | BV25: 1422.8 | BW25: 5446.5 | BX25: 1561.2 | BY25: 1613.3 | BZ25: =BX25+BY25 -> 3174.5 | CA25: 1217.6 | CB25: 1413.7 | CC25: 5805.8 | CD25: 1276.7 | CE25: 1523.2 | CF25: =CD25+CE25 -> 2799.9 | CG25: 1328.9 | CH25: 1534.7 | CI25: 5663.6 | CJ25: 1622
B26: Memo: CC&T lots sold (000s) — legacy basis | BR26: 56.6 | BS26: 84.4 | BT26: =BR26+BS26 -> 141 | BU26: 86.6 | BV26: 86.9 | BW26: 314.5 | BX26: 108.8 | BY26: 118.2 | BZ26: =BX26+BY26 -> 227 | CA26: 103.1 | CB26: 102.2 | CC26: 432.3 | CD26: 87.6 | CE26: 97.5 | CF26: =CD26+CE26 -> 185.1 | CG26: 87.8 | CH26: 103.2 | CI26: 376.1 | CJ26: 97.8 | DB26: HET_gtvGrowth (Heavy Equipment & Transportation GTV y/y) | DC26: 0.02 | DD26: Δ → | DE26: -0.04 | DF26: HE&T: used-equipment supply (fleet de-fleeting, rental), pricing cycle, J.M. Wood / BigIron annualisation in 2026–27.
DB27: 2027E | DC27: =DD27+$DC$26 -> 0.08 | DD27: 0.06 | DE27: =DD27+$DE$26 -> 0.02
B28: Other (consumer goods, real estate, parts — current basis from Q1/25) | CT28: OTHER — modelling logic | DB28: 2028E | DC28: =DD28+$DC$26 -> 0.065 | DD28: 0.045 | DE28: =DD28+$DE$26 -> 0.005
B29: GTV (USDm) | CD29: 121.5 | CE29: 108.5 | CF29: =CD29+CE29 -> 230 | CG29: 114.3 | CH29: 122.8 | CI29: 467.1 | CJ29: 108.2 | CK29: 147.4 | CL29: =CJ29+CK29 -> 255.6 | CM29: =CM39*CG29*CL29/CF29/(CG11*CL11/CF11+CG19*CL19/CF19+CG29*CL29/CF29) -> 121.97966 | CN29: =CN39*CH29*CL29/CF29/(CH11*CL11/CF11+CH19*CL19/CF19+CH29*CL29/CF29) -> 130.81282 | CO29: =SUM(CJ29,CK29,CM29,CN29) -> 508.39248 | CP29: =CO29*(1+CP33) -> 533.8121 | CQ29: =CP29*(1+CQ33) -> 560.50271 | CR29: =CQ29*(1+CR33) -> 588.52784 | CS29: =CR29*(1+CS33) -> 617.95424 | CT29: Q3/26E–Q4/26E: total GTV (FY26 outlook) allocated across sectors by prior-year same-quarter sector GTV × 1H/26 sector y/y momentum. 2027E+: prior year × (1 + scenario sector GTV growth). | CV29: =IFERROR((CS29/CI29)^(1/5)-1,"n/m") -> 0.057570405 | CW29: =IFERROR((CI29/BE29)^(1/5)-1,"n/m") -> n/m | CX29: =IFERROR((CI29/AA29)^(1/10)-1,"n/m") -> n/m | CY29: =IFERROR((CI29/C29)^(1/19)-1,"n/m") -> n/m | DB29: 2029E | DC29: =DD29+$DC$26 -> 0.06 | DD29: 0.04 | DE29: =DD29+$DE$26 -> 0
B30: Lots sold (000s) | CD30: 73 | CE30: 64.9 | CF30: =CD30+CE30 -> 137.9 | CG30: 51.5 | CH30: 53.4 | CI30: 242.8 | CJ30: 46.8 | CK30: 52.4 | CL30: =CJ30+CK30 -> 99.2 | CM30: =IFERROR(CM29/CM31*1000,"") -> 54.960212 | CN30: =IFERROR(CN29/CN31*1000,"") -> 56.884404 | CO30: =SUM(CJ30,CK30,CM30,CN30) -> 211.04462 | CP30: =IFERROR(CP29/CP31*1000,"") -> 221.59685 | CQ30: =IFERROR(CQ29/CQ31*1000,"") -> 232.67669 | CR30: =IFERROR(CR29/CR31*1000,"") -> 244.31052 | CS30: =IFERROR(CS29/CS31*1000,"") -> 256.52605 | DB30: 2030E | DC30: =DD30+$DC$26 -> 0.06 | DD30: 0.04 | DE30: =DD30+$DE$26 -> 0
B31: GTV per lot sold ($) | C31: =IFERROR(C29/C30*1000,"") | D31: =IFERROR(D29/D30*1000,"") | E31: =IFERROR(E29/E30*1000,"") | F31: =IFERROR(F29/F30*1000,"") | G31: =IFERROR(G29/G30*1000,"") | H31: =IFERROR(H29/H30*1000,"") | I31: =IFERROR(I29/I30*1000,"") | J31: =IFERROR(J29/J30*1000,"") | ... CL31: =IFERROR(CL29/CL30*1000,"") -> 2576.6129 | CM31: =CG31*(1+$CO$32) -> 2219.4175 | CN31: =CH31*(1+$CO$32) -> 2299.6255 | CO31: =IFERROR(CO29/CO30*1000,"") -> 2408.9337 | CP31: =CO31*(1+CP32) -> 2408.9337 | CQ31: =CP31*(1+CQ32) -> 2408.9337 | CR31: =CQ31*(1+CR32) -> 2408.9337 | CS31: =CR31*(1+CS32) -> 2408.9337
B32: GTV per lot y/y % (forecast input) | D32: =IFERROR(D31/C31-1,"") | E32: =IFERROR(E31/D31-1,"") | F32: =IFERROR(F31/E31-1,"") | G32: =IFERROR(G31/F31-1,"") | H32: =IFERROR(H31/G31-1,"") | I32: =IFERROR(I31/H31-1,"") | O32: =IFERROR(O31/I31-1,"") | P32: =IFERROR(P31/J31-1,"") | Q32: =IFERROR(Q31/K31-1,"") | R32: =IFERROR(R31/L31-1,"") | S32: =IFERROR(S31/M31-1,"") | T32: =IFERROR(T31/N31-1,"") | U32: =IFERROR(U31/O31-1,"") | V32: =IFERROR(V31/P31-1,"") | ... CL32: =IFERROR(CL31/CF31-1,"") -> 0.54484748 | CO32: 0 | CP32: 0 | CQ32: 0 | CR32: 0 | CS32: 0 | CT32: Price/mix per lot (input). 2026E cell drives Q3/Q4-26E lots (vs prior-year quarter GTV per lot). | DB32: OTH_gtvGrowth (Other GTV y/y) | DC32: 0.02 | DD32: Δ → | DE32: -0.03
B33: GTV y/y % | D33: =IFERROR(D29/C29-1,"") | E33: =IFERROR(E29/D29-1,"") | F33: =IFERROR(F29/E29-1,"") | G33: =IFERROR(G29/F29-1,"") | H33: =IFERROR(H29/G29-1,"") | I33: =IFERROR(I29/H29-1,"") | O33: =IFERROR(O29/I29-1,"") | P33: =IFERROR(P29/J29-1,"") | Q33: =IFERROR(Q29/K29-1,"") | R33: =IFERROR(R29/L29-1,"") | S33: =IFERROR(S29/M29-1,"") | T33: =IFERROR(T29/N29-1,"") | U33: =IFERROR(U29/O29-1,"") | V33: =IFERROR(V29/P29-1,"") | ... CO33: =IFERROR(CO29/CI29-1,"") -> 0.088401795 | CP33: =CHOOSE(MATCH($CT$2,{"Bull","Base","Bear"},0),$DC$33,$DD$33,$DE$33) -> 0.05 | CQ33: =CHOOSE(MATCH($CT$2,{"Bull","Base","Bear"},0),$DC$34,$DD$34,$DE$34) -> 0.05 | CR33: =CHOOSE(MATCH($CT$2,{"Bull","Base","Bear"},0),$DC$35,$DD$35,$DE$35) -> 0.05 | CS33: =CHOOSE(MATCH($CT$2,{"Bull","Base","Bear"},0),$DC$36,$DD$36,$DE$36) -> 0.05 | CT33: 2027E–2030E: scenario lever (OTH_gtvGrowth, Bull/Base/Bear table →). | DB33: 2027E | DC33: =DD33+$DC$32 -> 0.07 | DD33: 0.05 | DE33: =DD33+$DE$32 -> 0.02
B34: Lots sold y/y % | D34: =IFERROR(D30/C30-1,"") | E34: =IFERROR(E30/D30-1,"") | F34: =IFERROR(F30/E30-1,"") | G34: =IFERROR(G30/F30-1,"") | H34: =IFERROR(H30/G30-1,"") | I34: =IFERROR(I30/H30-1,"") | O34: =IFERROR(O30/I30-1,"") | P34: =IFERROR(P30/J30-1,"") | Q34: =IFERROR(Q30/K30-1,"") | R34: =IFERROR(R30/L30-1,"") | S34: =IFERROR(S30/M30-1,"") | T34: =IFERROR(T30/N30-1,"") | U34: =IFERROR(U30/O30-1,"") | V34: =IFERROR(V30/P30-1,"") | ... CO34: =IFERROR(CO30/CI30-1,"") -> -0.13078824 | CP34: =IFERROR(CP30/CO30-1,"") -> 0.05 | CQ34: =IFERROR(CQ30/CP30-1,"") -> 0.05 | CR34: =IFERROR(CR30/CQ30-1,"") -> 0.05 | CS34: =IFERROR(CS30/CR30-1,"") -> 0.05 | DB34: 2028E | DC34: =DD34+$DC$32 -> 0.07 | DD34: 0.05 | DE34: =DD34+$DE$32 -> 0.02
B35: Memo: Other GTV — legacy basis (2023–Q1/26) | BR35: 377.5 | BS35: 560.8 | BT35: =BR35+BS35 -> 938.3 | BU35: 471.8 | BV35: 542.8 | BW35: 1952.9 | BX35: 411.2 | BY35: 483.1 | BZ35: =BX35+BY35 -> 894.3 | CA35: 373.5 | CB35: 553.6 | CC35: 1821.4 | CD35: 407.5 | CE35: 513.4 | CF35: =CD35+CE35 -> 920.9 | CG35: 412.7 | CH35: 545.7 | CI35: 1879.2 | CJ35: 429.7 | DB35: 2029E | DC35: =DD35+$DC$32 -> 0.07 | DD35: 0.05 | DE35: =DD35+$DE$32 -> 0.02
B36: Memo: Other lots sold (000s) — legacy basis | BR36: 105.2 | BS36: 172.8 | BT36: =BR36+BS36 -> 278 | BU36: 157.8 | BV36: 155.3 | BW36: 591.1 | BX36: 145.6 | BY36: 173.6 | BZ36: =BX36+BY36 -> 319.2 | CA36: 140.8 | CB36: 157.4 | CC36: 617.3 | CD36: 141.9 | CE36: 153.8 | CF36: =CD36+CE36 -> 295.7 | CG36: 126.7 | CH36: 147.6 | CI36: 570 | CJ36: 128.4 | DB36: 2030E | DC36: =DD36+$DC$32 -> 0.07 | DD36: 0.05 | DE36: =DD36+$DE$32 -> 0.02
B38: Total GTV & lots | CT38: TOTAL GTV — modelling logic | DB38: ADJ_EBITDA_margin (% of total revenue) | DC38: 0.01 | DD38: Δ → | DE38: -0.015 | DF38: FY25 31.6% of revenue; FY26 outlook implies ~30% (inventory-sales mix and acquisitions dilute).
B39: Gross transaction value (GTV; 'gross auction proceeds' to Q2/17) | C39: 2721.023 | D39: 3186.483 | E39: 3567.16 | F39: 3492.021 | G39: 3277.771 | H39: 3714.281 | I39: 3907.991 | J39: 845.353 | K39: 1072.942 | L39: =J39+K39 -> 1918.295 | M39: 789.64 | N39: 1109.834 | O39: 3817.769 | P39: 855.377 | Q39: 1229.204 | R39: =P39+Q39 -> 2084.581 | S39: 886.876 | T39: 1241.184 | U39: 4212.641 | V39: 955.561 | W39: 1262.168 | X39: =V39+W39 -> 2217.729 | Y39: 894.509 | Z39: 1135.397 | AA39: 4247.635 | AB39: 1019.922 | AC39: 1275.682 | AD39: =AB39+AC39 -> 2295.604 | AE39: 998.859 | AF39: 1040.352 | AG39: 4334.815 | AH39: 899.41 | AI39: 1254.318 | AJ39: =AH39+AI39 -> 2153.728 | AK39: 1019.322 | AL39: 1294.932 | AM39: 4467.982 | AN39: 1160.712 | AO39: 1426.412 | AP39: =AN39+AO39 -> 2587.124 | AQ39: 1039.427 | AR39: 1337.614 | AS39: 4964.165 | AT39: 1174.681 | AU39: 1497.757 | AV39: =AT39+AU39 -> 2672.438 | AW39: 1084.241 | AX39: 1383.908 | AY39: 5140.587 | AZ39: 1147.025 | BA39: 1493.982 | BB39: =AZ39+BA39 -> 2641.007 | BC39: 1321.379 | BD39: 1448.832 | BE39: 5411.218 | BF39: 1274.539 | BG39: 1527.642 | BH39: =BF39+BG39 -> 2802.181 | BI39: 1270.258 | BJ39: 1461.492 | BK39: 5533.931 | BL39: 1439.105 | BM39: 1684.276 | BN39: =BL39+BM39 -> 3123.381 | BO39: 1358.242 | BP39: 1544.267 | BQ39: 6025.889 | BR39: 1899.2 | BS39: 4144 | BT39: =BR39+BS39 -> 6043.2 | BU39: 3875.4 | BV39: 4012 | BW39: 13930.6 | BX39: 4077.4 | BY39: 4104.1 | BZ39: =BX39+BY39 -> 8181.5 | CA39: 3622.2 | CB39: 4101.2 | CC39: 15904.8 | CD39: 3828.9 | CE39: 4198.1 | CF39: =CD39+CE39 -> 8027 | CG39: 3893.8 | CH39: 4281.1 | CI39: 16201.9 | CJ39: 4340.9 | CK39: 4672.7 | CL39: =CJ39+CK39 -> 9013.6 | CM39: =(CI39*(1+CHOOSE(MATCH($CT$2,{"Bull","Base","Bear"},0),$DC$12,$DD$12,$DE$12))-CL39)*CG39/(CG39+CH39) -> 4195.5863 | CN39: =(CI39*(1+CHOOSE(MATCH($CT$2,{"Bull","Base","Bear"},0),$DC$12,$DD$12,$DE$12))-CL39)*CH39/(CG39+CH39) -> 4612.9037 | CO39: =SUM(CJ39,CK39,CM39,CN39) -> 17822.09 | CP39: =CP11+CP19+CP29 -> 18793.003 | CQ39: =CQ11+CQ19+CQ29 -> 19690.355 | CR39: =CR11+CR19+CR29 -> 20535.021 | CS39: =CS11+CS19+CS29 -> 21416.07 | CT39: Q3/26E–Q4/26E: FY26 outlook GTV growth (scenario: 11% / 10% / 9%) on FY25 GTV, less 1H/26 actual, split by Q3/Q4-25 seasonality. 2027E+: sum of sectors. | CV39: =IFERROR((CS39/CI39)^(1/5)-1,"n/m") -> 0.057388943 | CW39: =IFERROR((CI39/BE39)^(1/5)-1,"n/m") -> 0.24524321 | CX39: =IFERROR((CI39/AA39)^(1/10)-1,"n/m") -> 0.14325175 | CY39: =IFERROR((CI39/C39)^(1/19)-1,"n/m") -> 0.098451087 | DB39: 2027E | DC39: =DD39+$DC$38 -> 0.315 | DD39: 0.305 | DE39: =DD39+$DE$38 -> 0.29
B40: GTV y/y % | D40: =IFERROR(D39/C39-1,"") -> 0.17106066 | E40: =IFERROR(E39/D39-1,"") -> 0.1194662 | F40: =IFERROR(F39/E39-1,"") -> -0.021064096 | G40: =IFERROR(G39/F39-1,"") -> -0.061354156 | H40: =IFERROR(H39/G39-1,"") -> 0.13317282 | I40: =IFERROR(I39/H39-1,"") -> 0.052152759 | O40: =IFERROR(O39/I39-1,"") -> -0.023086542 | P40: =IFERROR(P39/J39-1,"") -> 0.011857768 | Q40: =IFERROR(Q39/K39-1,"") -> 0.14563881 | R40: =IFERROR(R39/L39-1,"") -> 0.086684269 | S40: =IFERROR(S39/M39-1,"") -> 0.12313966 | T40: =IFERROR(T39/N39-1,"") -> 0.11835103 | U40: =IFERROR(U39/O39-1,"") -> 0.10343004 | V40: =IFERROR(V39/P39-1,"") -> 0.11712263 | ... CO40: =IFERROR(CO39/CI39-1,"") -> 0.1 | CP40: =IFERROR(CP39/CO39-1,"") -> 0.054478071 | CQ40: =IFERROR(CQ39/CP39-1,"") -> 0.047749239 | CR40: =IFERROR(CR39/CQ39-1,"") -> 0.042897474 | CS40: =IFERROR(CS39/CR39-1,"") -> 0.042904681 | DB40: 2028E | DC40: =DD40+$DC$38 -> 0.32 | DD40: 0.31 | DE40: =DD40+$DE$38 -> 0.295
B41: Non-automotive GTV (HE&T + Other; total − Automotive) | C41: =IF(ISNUMBER(C11),C39-C11,"") | D41: =IF(ISNUMBER(D11),D39-D11,"") | E41: =IF(ISNUMBER(E11),E39-E11,"") | F41: =IF(ISNUMBER(F11),F39-F11,"") | G41: =IF(ISNUMBER(G11),G39-G11,"") | H41: =IF(ISNUMBER(H11),H39-H11,"") | I41: =IF(ISNUMBER(I11),I39-I11,"") | J41: =IF(ISNUMBER(J11),J39-J11,"") | ... CL41: =IF(ISNUMBER(CL11),CL39-CL11,"") -> 4275.7 | CM41: =CM39-CM11 -> 1921.6281 | CN41: =CN39-CN11 -> 2291.9233 | CO41: =SUM(CJ41,CK41,CM41,CN41) -> 8489.2514 | CP41: =CP39-CP11 -> 8993.5225 | CQ41: =CQ39-CQ11 -> 9400.9001 | CR41: =CR39-CR11 -> 9782.5411 | CS41: =CS39-CS11 -> 10179.728 | CT41: Comparable across the 2026 sector re-presentation (Automotive composition unchanged). | DB41: 2029E | DC41: =DD41+$DC$38 -> 0.325 | DD41: 0.315 | DE41: =DD41+$DE$38 -> 0.3
B42: Non-automotive GTV y/y % | D42: =IFERROR(D41/C41-1,"") | E42: =IFERROR(E41/D41-1,"") | F42: =IFERROR(F41/E41-1,"") | G42: =IFERROR(G41/F41-1,"") | H42: =IFERROR(H41/G41-1,"") | I42: =IFERROR(I41/H41-1,"") | O42: =IFERROR(O41/I41-1,"") | P42: =IFERROR(P41/J41-1,"") | Q42: =IFERROR(Q41/K41-1,"") | R42: =IFERROR(R41/L41-1,"") | S42: =IFERROR(S41/M41-1,"") | T42: =IFERROR(T41/N41-1,"") | U42: =IFERROR(U41/O41-1,"") | V42: =IFERROR(V41/P41-1,"") | ... CO42: =IFERROR(CO41/CI41-1,"") -> 0.12547746 | CP42: =IFERROR(CP41/CO41-1,"") -> 0.059401134 | CQ42: =IFERROR(CQ41/CP41-1,"") -> 0.045296776 | CR42: =IFERROR(CR41/CQ41-1,"") -> 0.040596222 | CS42: =IFERROR(CS41/CR41-1,"") -> 0.04060161 | DB42: 2030E | DC42: =DD42+$DC$38 -> 0.33 | DD42: 0.32 | DE42: =DD42+$DE$38 -> 0.305
B43: Automotive % of GTV | C43: =IF(ISNUMBER(C11),C11/C39,"") | D43: =IF(ISNUMBER(D11),D11/D39,"") | E43: =IF(ISNUMBER(E11),E11/E39,"") | F43: =IF(ISNUMBER(F11),F11/F39,"") | G43: =IF(ISNUMBER(G11),G11/G39,"") | H43: =IF(ISNUMBER(H11),H11/H39,"") | I43: =IF(ISNUMBER(I11),I11/I39,"") | J43: =IF(ISNUMBER(J11),J11/J39,"") | ... CL43: =IF(ISNUMBER(CL11),CL11/CL39,"") -> 0.52563903 | CM43: =IFERROR(CM11/CM39,"") -> 0.54198819 | CN43: =IFERROR(CN11/CN39,"") -> 0.50314955 | CO43: =IFERROR(CO11/CO39,"") -> 0.5236669 | CP43: =IFERROR(CP11/CP39,"") -> 0.52144303 | CQ43: =IFERROR(CQ11/CQ39,"") -> 0.52256319 | CR43: =IFERROR(CR11/CR39,"") -> 0.5236167 | CS43: =IFERROR(CS11/CS39,"") -> 0.52466871
B44: Total lots sold (000s) | F44: 283 | G44: 277 | H44: 268.5 | I44: 287 | J44: 62 | K44: 85.5 | L44: =J44+K44 -> 147.5 | M44: 69 | N44: 84.5 | O44: 301 | P44: 62.5 | Q44: 83.5 | R44: =P44+Q44 -> 146 | S44: 73 | T44: 100.5 | U44: 319.5 | V44: 72.5 | W44: 96 | X44: =V44+W44 -> 168.5 | Y44: 85 | Z44: 101 | AA44: 354.5 | AB44: 93 | AC44: 110.5 | AD44: =AB44+AC44 -> 203.5 | AE44: 90.5 | AF44: 104.5 | AG44: 398.5 | AH44: 84 | AI44: 108 | AJ44: =AH44+AI44 -> 192 | AK44: 84 | AL44: 106.5 | AM44: 382.5 | AN44: 81 | AO44: 103.5 | AP44: =AN44+AO44 -> 184.5 | AQ44: 89 | AR44: 103.5 | AS44: 377 | AZ44: 100.805 | BA44: 148.957 | BB44: =AZ44+BA44 -> 249.762 | BC44: 142.472 | BD44: 151.108 | BE44: 543.342 | BF44: 116.259 | BG44: 148.206 | BH44: =BF44+BG44 -> 264.465 | BI44: 107.825 | BJ44: 121.081 | BK44: 493.371 | BL44: 105.767 | BM44: 144.167 | BN44: =BL44+BM44 -> 249.934 | BO44: 125.661 | BP44: 145.364 | BQ44: 520.959 | BR44: 249.3 | BS44: 830.6 | BT44: =BR44+BS44 -> 1079.9 | BU44: 799.4 | BV44: 814.7 | BW44: 2694 | BX44: 839 | BY44: 839.5 | BZ44: =BX44+BY44 -> 1678.5 | CA44: 797.7 | CB44: 870.7 | CC44: 3346.8 | CD44: 855.1 | CE44: 847.2 | CF44: =CD44+CE44 -> 1702.3 | CG44: 816.2 | CH44: 875.3 | CI44: 3393.8 | CJ44: 857.5 | CK44: 911.2 | CL44: =CJ44+CK44 -> 1768.7 | CM44: =CM12+CM20+CM30 -> 848.91284 | CN44: =CN12+CN20+CN30 -> 909.97097 | CO44: =SUM(CJ44,CK44,CM44,CN44) -> 3527.5838 | CP44: =CP12+CP20+CP30 -> 3630.4394 | CQ44: =CQ12+CQ20+CQ30 -> 3724.7573 | CR44: =CR12+CR20+CR30 -> 3817.9639 | CS44: =CS12+CS20+CS30 -> 3913.6728 | DB44: Buybacks ($m) | DC44: 150 | DD44: Δ → | DE44: -200 | DF44: NCIB approved Q1-26: up to 10.0m shares / $500m; $150m repurchased in Q2-26 ($350m remaining at 30-Jun-26).
B45: Check: sector GTV vs total (should be 0) | C45: =IF(ISNUMBER(C19),ROUND(C39-C11-C19-C29,1),"") | D45: =IF(ISNUMBER(D19),ROUND(D39-D11-D19-D29,1),"") | E45: =IF(ISNUMBER(E19),ROUND(E39-E11-E19-E29,1),"") | F45: =IF(ISNUMBER(F19),ROUND(F39-F11-F19-F29,1),"") | G45: =IF(ISNUMBER(G19),ROUND(G39-G11-G19-G29,1),"") | H45: =IF(ISNUMBER(H19),ROUND(H39-H11-H19-H29,1),"") | I45: =IF(ISNUMBER(I19),ROUND(I39-I11-I19-I29,1),"") | J45: =IF(ISNUMBER(J19),ROUND(J39-J11-J19-J29,1),"") | ... CL45: =IF(ISNUMBER(CL19),ROUND(CL39-CL11-CL19-CL29,1),"") -> 0 | CM45: =ROUND(CM39-CM11-CM19-CM29,1) -> 0 | CN45: =ROUND(CN39-CN11-CN19-CN29,1) -> 0 | CO45: =ROUND(CO39-CO11-CO19-CO29,1) -> 0 | CP45: =ROUND(CP39-CP11-CP19-CP29,1) -> 0 | CQ45: =ROUND(CQ39-CQ11-CQ19-CQ29,1) -> 0 | CR45: =ROUND(CR39-CR11-CR19-CR29,1) -> 0 | CS45: =ROUND(CS39-CS11-CS19-CS29,1) -> 0 | DB45: 2H/26E | DC45: =MAX(0,DD45+$DC$44) -> 350 | DD45: 200 | DE45: =MAX(0,DD45+$DE$44) -> 0
DB46: 2027E | DC46: =MAX(0,DD46+$DC$44) -> 550 | DD46: 400 | DE46: =MAX(0,DD46+$DE$44) -> 200
B47: Revenue streams | CT47: REVENUE STREAMS — modelling logic | DB47: 2028E | DC47: =MAX(0,DD47+$DC$44) -> 550 | DD47: 400 | DE47: =MAX(0,DD47+$DE$44) -> 200
B48: Transactional seller revenue (2023+) | BR48: 139.2 | BS48: 244.6 | BT48: =BR48+BS48 -> 383.8 | BU48: 223.2 | BV48: 244.7 | BW48: 851.7 | BX48: 238.6 | BY48: 250.7 | BZ48: =BX48+BY48 -> 489.3 | CA48: 206.6 | CB48: 243.5 | CC48: 939.4 | CD48: 216.8 | CE48: 241 | CF48: =CD48+CE48 -> 457.8 | CG48: 215.8 | CH48: 255.2 | CI48: 928.8 | CJ48: 241.3 | CK48: 239.2 | CL48: =CJ48+CK48 -> 480.5 | CM48: =CM53*CL48/CL53 -> 223.65972 | CN48: =CN53*CL48/CL53 -> 245.90621 | CO48: =SUM(CJ48,CK48,CM48,CN48) -> 950.06593 | CP48: =CP53*CO48/CO53 -> 986.29654 | CQ48: =CQ53*CP48/CP53 -> 1033.3915 | CR48: =CR53*CQ48/CQ53 -> 1077.7213 | CS48: =CS53*CR48/CR53 -> 1123.9606 | CT48: Service revenue split held at the prior-period mix (1H/26 mix for Q3/Q4-26E). | DB48: 2029E | DC48: =MAX(0,DD48+$DC$44) -> 600 | DD48: 450 | DE48: =MAX(0,DD48+$DE$44) -> 250
B49: Transactional buyer revenue (2023+) | BR49: 145.3 | BS49: 482.7 | BT49: =BR49+BS49 -> 628 | BU49: 476.6 | BV49: 488.7 | BW49: 1593.2 | BX49: 525.4 | BY49: 510 | BZ49: =BX49+BY49 -> 1035.4 | CA49: 486.9 | CB49: 544.8 | CC49: 2067.1 | CD49: 556.7 | CE49: 560.6 | CF49: =CD49+CE49 -> 1117.3 | CG49: 543.8 | CH49: 577.2 | CI49: 2238.3 | CJ49: 577.5 | CK49: 610.9 | CL49: =CJ49+CK49 -> 1188.4 | CM49: =CM53*CL49/CL53 -> 553.16796 | CN49: =CN53*CL49/CL53 -> 608.18927 | CO49: =SUM(CJ49,CK49,CM49,CN49) -> 2349.7572 | CP49: =CP53*CO49/CO53 -> 2439.3648 | CQ49: =CQ53*CP49/CP53 -> 2555.8427 | CR49: =CR53*CQ49/CQ53 -> 2665.4819 | CS49: =CS53*CR49/CR53 -> 2779.8435 | DB49: 2030E | DC49: =MAX(0,DD49+$DC$44) -> 650 | DD49: 500 | DE49: =MAX(0,DD49+$DE$44) -> 300
B50: Marketplace services revenue (2023+) | BR50: 59.1 | BS50: 78.8 | BT50: =BR50+BS50 -> 137.9 | BU50: 74 | BV50: 75.7 | BW50: 287.6 | BX50: 85.1 | BY50: 98.4 | BZ50: =BX50+BY50 -> 183.5 | CA50: 86.4 | CB50: 87.2 | CC50: 357.1 | CD50: 79 | CE50: 85.6 | CF50: =CD50+CE50 -> 164.6 | CG50: 85.4 | CH50: 85.1 | CI50: 335.1 | CJ50: 78.9 | CK50: 83.3 | CL50: =CJ50+CK50 -> 162.2 | CM50: =CM53-CM48-CM49 -> 75.4997 | CN50: =CN53-CN48-CN49 -> 83.009339 | CO50: =SUM(CJ50,CK50,CM50,CN50) -> 320.70904 | CP50: =CP53-CP48-CP49 -> 332.93923 | CQ50: =CQ53-CQ48-CQ49 -> 348.83682 | CR50: =CR53-CR48-CR49 -> 363.80104 | CS50: =CS53-CS48-CS49 -> 379.40981
B51: Commissions (legacy presentation, ≤2022) | G51: 326.768 | H51: 342.774 | I51: 351.017 | J51: 82.044 | K51: 102.138 | L51: =J51+K51 -> 184.182 | M51: 85.474 | N51: 104.451 | O51: 374.107 | P51: 78.174 | Q51: 112.684 | R51: =P51+Q51 -> 190.858 | S51: 80.193 | T51: 108.289 | U51: 379.34 | V51: 93.14 | W51: 124.592 | X51: =V51+W51 -> 217.732 | Y51: 83.648 | Z51: 103.929 | AA51: 405.308 | AB51: 99.793 | AC51: 118.18 | AD51: =AB51+AC51 -> 217.973 | AE51: 96.11 | AF51: 110.044 | AG51: 424.128 | AH51: 79.297 | AI51: 112.242 | AJ51: =AH51+AI51 -> 191.539 | AK51: 88.696 | AL51: 114.162 | AM51: 394.397 | AN51: 101.294 | AO51: 124.697 | AP51: =AN51+AO51 -> 225.991 | AQ51: 87.548 | AR51: 106.621 | AS51: 420.16 | AT51: 92.28 | AU51: 134.466 | AV51: =AT51+AU51 -> 226.746 | AW51: 90.928 | AX51: 114.107 | AY51: 431.781 | AZ51: 93.484 | BA51: 125.465 | BB51: =AZ51+BA51 -> 218.949 | BC51: 112.762 | BD51: 121.17 | BE51: 452.882 | BF51: 103.975 | BG51: 129.334 | BH51: =BF51+BG51 -> 233.309 | BI51: 110.275 | BJ51: 126.135 | BK51: 469.718 | BL51: 116.375 | BM51: 136.403 | BN51: =BL51+BM51 -> 252.778 | BO51: 108.238 | BP51: 124.898 | BQ51: 485.916
B52: Fees (legacy presentation, ≤2022) | G52: 30.601 | H52: 53.325 | I52: 86.938 | J52: 20.014 | K52: 26.184 | L52: =J52+K52 -> 46.198 | M52: 20.326 | N52: 26.772 | O52: 93.296 | P52: 20.414 | Q52: 29.151 | R52: =P52+Q52 -> 49.565 | S52: 22.024 | T52: 30.168 | U52: 101.757 | V52: 22.478 | W52: 30.885 | X52: =V52+W52 -> 53.363 | Y52: 25.67 | Z52: 31.533 | AA52: 110.567 | AB52: 32.152 | AC52: 40.625 | AD52: =AB52+AC52 -> 72.777 | AE52: 32.766 | AF52: 36.725 | AG52: 142.267 | AH52: 44.082 | AI52: 60.507 | AJ52: =AH52+AI52 -> 104.589 | AK52: 57.242 | AL52: 68.189 | AM52: 230.02 | AN52: 74.722 | AO52: 89.649 | AP52: =AN52+AO52 -> 164.371 | AQ52: 73.826 | AR52: 91.158 | AS52: 329.355 | AT52: 80.092 | AU52: 100.14 | AV52: =AT52+AU52 -> 180.232 | AW52: 87.649 | AX52: 104.362 | AY52: 372.243 | AZ52: 89.639 | BA52: 108.674 | BB52: =AZ52+BA52 -> 198.313 | BC52: 109.917 | BD52: 110.485 | BE52: 418.714 | BF52: 102.055 | BG52: 123.414 | BH52: =BF52+BG52 -> 225.469 | BI52: 103.918 | BJ52: 118.653 | BK52: 448.041 | BL52: 128.486 | BM52: 150.099 | BN52: =BL52+BM52 -> 278.585 | BO52: 138.458 | BP52: 147.625 | BQ52: 564.667
B53: Service revenue (build) | C53: =IF(COUNT(C48,C49,C50,C51,C52)=0,"n/d",SUM(C48,C49,C50,C51,C52)) -> n/d | D53: =IF(COUNT(D48,D49,D50,D51,D52)=0,"n/d",SUM(D48,D49,D50,D51,D52)) -> n/d | E53: =IF(COUNT(E48,E49,E50,E51,E52)=0,"n/d",SUM(E48,E49,E50,E51,E52)) -> n/d | F53: =IF(COUNT(F48,F49,F50,F51,F52)=0,"n/d",SUM(F48,F49,F50,F51,F52)) -> n/d | G53: =IF(COUNT(G48,G49,G50,G51,G52)=0,"n/d",SUM(G48,G49,G50,G51,G52)) -> 357.369 | H53: =IF(COUNT(H48,H49,H50,H51,H52)=0,"n/d",SUM(H48,H49,H50,H51,H52)) -> 396.099 | I53: =IF(COUNT(I48,I49,I50,I51,I52)=0,"n/d",SUM(I48,I49,I50,I51,I52)) -> 437.955 | J53: =IF(COUNT(J48,J49,J50,J51,J52)=0,"n/d",SUM(J48,J49,J50,J51,J52)) -> 102.058 | ... CL53: =IF(COUNT(CL48,CL49,CL50,CL51,CL52)=0,"n/d",SUM(CL48,CL49,CL50,CL51,CL52)) -> 1831.1 | CM53: =CM39*CM54 -> 852.32738 | CN53: =CN39*CN54 -> 937.10482 | CO53: =SUM(CJ53,CK53,CM53,CN53) -> 3620.5322 | CP53: =CP39*CP54 -> 3758.6006 | CQ53: =CQ39*CQ54 -> 3938.0709 | CR53: =CR39*CR54 -> 4107.0042 | CS53: =CS39*CS54 -> 4283.2139 | CT53: Forecast service revenue = GTV × service revenue take rate. | CV53: =IFERROR((CS53/CI53)^(1/5)-1,"n/m") -> 0.041083983 | CW53: =IFERROR((CI53/BE53)^(1/5)-1,"n/m") -> 0.32070294 | CX53: =IFERROR((CI53/AA53)^(1/10)-1,"n/m") -> 0.211099 | CY53: =IFERROR((CI53/C53)^(1/19)-1,"n/m") -> n/m
B54: Service revenue take rate (service revenue / GTV) | C54: =IFERROR(C93/C39,"") -> 0.094764726 | D54: =IFERROR(D93/D39,"") -> 0.097884094 | E54: =IFERROR(E93/E39,"") -> 0.099467924 | F54: =IFERROR(F93/F39,"") -> 0.10802083 | G54: =IFERROR(G93/G39,"") -> 0.10902806 | H54: =IFERROR(H93/H39,"") -> 0.10664217 | I54: =IFERROR(I93/I39,"") -> 0.11206653 | J54: =IFERROR(J93/J39,"") -> 0.12072826 | ... CL54: =IFERROR(CL93/CL39,"") -> 0.20314858 | CM54: =$CL$54+$CO$55 -> 0.20314858 | CN54: =$CL$54+$CO$55 -> 0.20314858 | CO54: =IFERROR(CO93/CO39,"") -> 0.20314858 | CP54: 0.2 | CQ54: 0.2 | CR54: 0.2 | CS54: 0.2 | CT54: Q3/Q4-26E: 1H/26 take rate + Δ input (row below). 2027E+: input — acquired businesses (J.J. Kane, BigIron) and automotive volume incentives carry lower take rates.
B55: Q3/Q4-26E take-rate change vs 1H/26 (bps, input) | CO55: 0
B56: Inventory sales revenue (gross basis from 2018, ASC 606) | AH56: 76.048 | AI56: 79.864 | AJ56: =AH56+AI56 -> 155.912 | AK56: 81.463 | AL56: 109.399 | AM56: 346.774 | AN56: 84.162 | AO56: 94.184 | AP56: =AN56+AO56 -> 178.346 | AQ56: 83.972 | AR56: 158.193 | AS56: 420.511 | AT56: 131.057 | AU56: 158.616 | AV56: =AT56+AU56 -> 289.673 | AW56: 111.219 | AX56: 113.725 | AY56: 514.617 | AZ56: 90.132 | BA56: 154.911 | BB56: =AZ56+BA56 -> 245.043 | BC56: 108.863 | BD56: 151.758 | BE56: 505.664 | BF56: 125.525 | BG56: 143.613 | BH56: =BF56+BG56 -> 269.138 | BI56: 115.489 | BJ56: 114.585 | BK56: 499.212 | BL56: 149.06 | BM56: 198.044 | BN56: =BL56+BM56 -> 347.104 | BO56: 164.783 | BP56: 171.338 | BQ56: 683.225 | BR56: 168.8 | BS56: 300.4 | BT56: =BR56+BS56 -> 469.2 | BU56: 246 | BV56: 231.8 | BW56: 947.1 | BX56: 215.6 | BY56: 237 | BZ56: =BX56+BY56 -> 452.6 | CA56: 201.9 | CB56: 266.1 | CC56: 920.6 | CD56: 256.1 | CE56: 298.8 | CF56: =CD56+CE56 -> 554.9 | CG56: 247.7 | CH56: 285.9 | CI56: 1088.5 | CJ56: 336.9 | CK56: 383.7 | CL56: =CJ56+CK56 -> 720.6 | CM56: =CM39*CM57 -> 308.65942 | CN56: =CN39*CN57 -> 356.26051 | CO56: =SUM(CJ56,CK56,CM56,CN56) -> 1385.5199 | CP56: =CP39*CP57 -> 1503.4402 | CQ56: =CQ39*CQ57 -> 1575.2284 | CR56: =CR39*CR57 -> 1642.8017 | CS56: =CS39*CS57 -> 1713.2856 | CT56: Forecast inventory sales = GTV × inventory sales % of GTV. | CV56: =IFERROR((CS56/CI56)^(1/5)-1,"n/m") -> 0.09496507 | CW56: =IFERROR((CI56/BE56)^(1/5)-1,"n/m") -> 0.1657174 | CX56: =IFERROR((CI56/AA56)^(1/10)-1,"n/m") -> n/m | CY56: =IFERROR((CI56/C56)^(1/19)-1,"n/m") -> n/m
B57: Inventory sales % of GTV | C57: =IFERROR(C56/C39,"") -> 0 | D57: =IFERROR(D56/D39,"") -> 0 | E57: =IFERROR(E56/E39,"") -> 0 | F57: =IFERROR(F56/F39,"") -> 0 | G57: =IFERROR(G56/G39,"") -> 0 | H57: =IFERROR(H56/H39,"") -> 0 | I57: =IFERROR(I56/I39,"") -> 0 | J57: =IFERROR(J56/J39,"") -> 0 | ... CL57: =IFERROR(CL56/CL39,"") -> 0.07994586 | CM57: =CG57*$CL$57/$CF$57 -> 0.073567649 | CN57: =CH57*$CL$57/$CF$57 -> 0.077231292 | CO57: =IFERROR(CO56/CO39,"") -> 0.07774172 | CP57: 0.08 | CQ57: 0.08 | CR57: 0.08 | CS57: 0.08 | CT57: Q3/Q4-26E: prior-year quarter ratio scaled by the 1H/26 vs 1H/25 change (HE&T shift to inventory contracts). 2027E+: input.
B58: Inventory return (inventory sales − cost of inventory sold) | C58: =IF(ISNUMBER(C56),C56-C98,"") | D58: =IF(ISNUMBER(D56),D56-D98,"") | E58: =IF(ISNUMBER(E56),E56-E98,"") | F58: =IF(ISNUMBER(F56),F56-F98,"") | G58: =IF(ISNUMBER(G56),G56-G98,"") | H58: =IF(ISNUMBER(H56),H56-H98,"") | I58: =IF(ISNUMBER(I56),I56-I98,"") | J58: =IF(ISNUMBER(J56),J56-J98,"") | ... CL58: =IF(ISNUMBER(CL56),CL56-CL98,"") -> 53 | CM58: =CM56-CM98 -> 22.701845 | CN58: =CN56-CN98 -> 26.202896 | CO58: =SUM(CJ58,CK58,CM58,CN58) -> 101.90474 | CP58: =CP56-CP98 -> 105.24082 | CQ58: =CQ56-CQ98 -> 110.26599 | CR58: =CR56-CR98 -> 114.99612 | CS58: =CS56-CS98 -> 119.92999
B59: Inventory rate (inventory return / inventory sales) | C59: =IFERROR(C58/C56,"") | D59: =IFERROR(D58/D56,"") | E59: =IFERROR(E58/E56,"") | F59: =IFERROR(F58/F56,"") | G59: =IFERROR(G58/G56,"") | H59: =IFERROR(H58/H56,"") | I59: =IFERROR(I58/I56,"") | J59: =IFERROR(J58/J56,"") | ... CL59: =IFERROR(CL58/CL56,"") -> 0.07354982 | CM59: =$CL$59 -> 0.07354982 | CN59: =$CL$59 -> 0.07354982 | CO59: =IFERROR(CO58/CO56,"") -> 0.07354982 | CP59: 0.07 | CQ59: 0.07 | CR59: 0.07 | CS59: 0.07 | CT59: Q3/Q4-26E at the 1H/26 inventory rate; 2027E+ input (5-yr range ~5–9%).
B60: Total revenue (build) | C60: =IF(ISNUMBER(C53),C53+N(C56),C93+N(C56)) -> 257.857 | D60: =IF(ISNUMBER(D53),D53+N(D56),D93+N(D56)) -> 311.906 | E60: =IF(ISNUMBER(E53),E53+N(E56),E93+N(E56)) -> 354.818 | F60: =IF(ISNUMBER(F53),F53+N(F56),F93+N(F56)) -> 377.211 | G60: =IF(ISNUMBER(G53),G53+N(G56),G93+N(G56)) -> 357.369 | H60: =IF(ISNUMBER(H53),H53+N(H56),H93+N(H56)) -> 396.099 | I60: =IF(ISNUMBER(I53),I53+N(I56),I93+N(I56)) -> 437.955 | J60: =IF(ISNUMBER(J53),J53+N(J56),J93+N(J56)) -> 102.058 | ... CL60: =IF(ISNUMBER(CL53),CL53+N(CL56),CL93+N(CL56)) -> 2551.7 | CM60: =CM53+CM56 -> 1160.9868 | CN60: =CN53+CN56 -> 1293.3653 | CO60: =SUM(CJ60,CK60,CM60,CN60) -> 5006.0521 | CP60: =CP53+CP56 -> 5262.0409 | CQ60: =CQ53+CQ56 -> 5513.2993 | CR60: =CR53+CR56 -> 5749.8059 | CS60: =CS53+CS56 -> 5996.4995 | CT60: Group revenue = service revenue + inventory sales revenue (ties to the GAAP income statement). | CV60: =IFERROR((CS60/CI60)^(1/5)-1,"n/m") -> 0.054881748 | CW60: =IFERROR((CI60/BE60)^(1/5)-1,"n/m") -> 0.2722504 | CX60: =IFERROR((CI60/AA60)^(1/10)-1,"n/m") -> 0.2443239 | CY60: =IFERROR((CI60/C60)^(1/19)-1,"n/m") -> 0.16363236
B61: Total revenue % of GTV | C61: =IFERROR(C60/C39,"") -> 0.094764726 | D61: =IFERROR(D60/D39,"") -> 0.097884094 | E61: =IFERROR(E60/E39,"") -> 0.099467924 | F61: =IFERROR(F60/F39,"") -> 0.10802083 | G61: =IFERROR(G60/G39,"") -> 0.10902806 | H61: =IFERROR(H60/H39,"") -> 0.10664217 | I61: =IFERROR(I60/I39,"") -> 0.11206653 | J61: =IFERROR(J60/J39,"") -> 0.12072826 | ... CS61: =IFERROR(CS60/CS39,"") -> 0.28
B62: Check: service revenue build vs income statement (should be 0) | C62: =IF(ISNUMBER(C53),ROUND(C53-C93,1),"n/d") -> n/d | D62: =IF(ISNUMBER(D53),ROUND(D53-D93,1),"n/d") -> n/d | E62: =IF(ISNUMBER(E53),ROUND(E53-E93,1),"n/d") -> n/d | F62: =IF(ISNUMBER(F53),ROUND(F53-F93,1),"n/d") -> n/d | G62: =IF(ISNUMBER(G53),ROUND(G53-G93,1),"n/d") -> 0 | H62: =IF(ISNUMBER(H53),ROUND(H53-H93,1),"n/d") -> 0 | I62: =IF(ISNUMBER(I53),ROUND(I53-I93,1),"n/d") -> 0 | J62: =IF(ISNUMBER(J53),ROUND(J53-J93,1),"n/d") -> 0 | ... CL62: =IF(ISNUMBER(CL53),ROUND(CL53-CL93,1),"n/d") -> 0 | CM62: =ROUND(CM60-CM95,1) -> 0 | CN62: =ROUND(CN60-CN95,1) -> 0 | CO62: =ROUND(CO60-CO95,1) -> 0 | CP62: =ROUND(CP60-CP95,1) -> 0 | CQ62: =ROUND(CQ60-CQ95,1) -> 0 | CR62: =ROUND(CR60-CR95,1) -> 0 | CS62: =ROUND(CS60-CS95,1) -> 0
B64: Cost drivers (% of revenue) | CT64: % OF REVENUE drivers — hardcoded inputs that drive forecast cost lines
B65: Costs of services % of service revenue | C65: =IFERROR(C97/C93,"") -> 0.15689704 | D65: =IFERROR(D97/D93,"") -> 0.14902246 | E65: =IFERROR(E97/E93,"") -> 0.14021273 | F65: =IFERROR(F97/F93,"") -> 0.13226019 | G65: =IFERROR(G97/G93,"") -> 0.13157549 | H65: =IFERROR(H97/H93,"") -> 0.12129291 | I65: =IFERROR(I97/I93,"") -> 0.1134523 | J65: =IFERROR(J97/J93,"") -> 0.091722354 | ... CL65: =IFERROR(CL97/CL93,"") -> 0.40778767 | CM65: =CG65*$CL$65/$CF$65 -> 0.41403281 | CN65: =CH65*$CL$65/$CF$65 -> 0.39157837 | CO65: =IFERROR(CO97/CO93,"") -> 0.4050624 | CP65: 0.405 | CQ65: 0.403 | CR65: 0.401 | CS65: 0.4 | CT65: Costs of services (ex D&A): towing, yard & auction-site labour, inspection, buyer-fee related costs. Q3/Q4-26E: prior-year quarter ratio × 1H/26 vs 1H/25 drift; 2027E+ input.
B66: Adjusted D&A % of revenue (ex acquired-intangible amortization) | C66: =IFERROR(C86/C95,"") -> 0.058237705 | D66: =IFERROR(D86/D95,"") -> 0.06225273 | E66: =IFERROR(E86/E95,"") -> 0.069793528 | F66: =IFERROR(F86/F95,"") -> 0.084199559 | G66: =IFERROR(G86/G95,"") -> 0.1058094 | H66: =IFERROR(H86/H95,"") -> 0.10706414 | I66: =IFERROR(I86/I95,"") -> 0.093932025 | J66: =IFERROR(J86/J95,"") -> 0.10111897 | ... CL66: =IFERROR(CL86/CL95,"") -> 0.043226085 | CM66: =$CL$66 -> 0.043226085 | CN66: =$CL$66 -> 0.043226085 | CO66: =IFERROR(CO86/CO95,"") -> 0.043226085 | CP66: 0.043 | CQ66: 0.043 | CR66: 0.043 | CS66: 0.043 | CT66: Depreciation of yards / IT and amortization of software (ex acquired intangibles). 1H/26 ratio for Q3/Q4-26E; 2027E+ input.
B67: Stock-based compensation % of revenue | C67: =IFERROR(C143/C95,"") -> 0 | D67: =IFERROR(D143/D95,"") -> 0 | E67: =IFERROR(E143/E95,"") -> 0 | F67: =IFERROR(F143/F95,"") -> 0 | G67: =IFERROR(G143/G95,"") -> 0 | H67: =IFERROR(H143/H95,"") -> 0 | I67: =IFERROR(I143/I95,"") -> 0 | J67: =IFERROR(J143/J95,"") -> 0 | ... CS67: =IFERROR(CS143/CS95,"") -> 0.015008756
B69: Revenue by geography (location of auction / service) | CT69: GEOGRAPHY — historical disclosure only (not forecast)
B70: United States | C70: 155.558 | D70: 173.983 | E70: 191.459 | F70: 202.415 | G70: 185.486 | H70: 195.274 | I70: 211.16 | O70: 224.214 | U70: 223.77 | AY70: 743.793 | BE70: 754.815 | BK70: 748.73 | BQ70: 970.848 | BR70: 360.1 | BS70: 754.3 | BT70: =BR70+BS70 -> 1114.4 | BU70: 767.1 | BV70: 710.1 | BW70: 2591.6 | BX70: 791.2 | BY70: 767.5 | BZ70: =BX70+BY70 -> 1558.7 | CA70: 724 | CB70: 811.4 | CC70: 3094.1 | CD70: 854.7 | CE70: 815.7 | CF70: =CD70+CE70 -> 1670.4 | CG70: 799.7 | CH70: 837.1 | CI70: 3307.2 | CJ70: 874.9 | CK70: 897.2 | CL70: =CJ70+CK70 -> 1772.1
B71: Canada | C71: 54.306 | D71: 71.271 | E71: 75.683 | F71: 90.148 | G71: 82.894 | H71: 100.404 | I71: 124.392 | O71: 135.545 | U71: 154.392 | AY71: 247.737 | BE71: 305.236 | BK71: 281.105 | BQ71: 375.67 | BR71: 68.3 | BS71: 188.3 | BT71: =BR71+BS71 -> 256.6 | BU71: 126.8 | BV71: 168.1 | BW71: 551.5 | BX71: 142.4 | BY71: 193.3 | BZ71: =BX71+BY71 -> 335.7 | CA71: 130.7 | CB71: 174.2 | CC71: 640.6 | CD71: 124.9 | CE71: 213.8 | CF71: =CD71+CE71 -> 338.7 | CG71: 157.9 | CH71: 199 | CI71: 695.6 | CJ71: 151.8 | CK71: 207 | CL71: =CJ71+CK71 -> 358.8
B72: Europe | C72: 28.505 | D72: 38.771 | E72: 54.635 | F72: 57.714 | G72: 51.428 | H72: 51.403 | I72: 60.572 | O72: 65.016 | U72: 58.782 | AY72: 173.054 | BE72: 158.999 | BK72: 183.004 | BQ72: 143.232 | BR72: 50.7 | BS72: 91.8 | BT72: =BR72+BS72 -> 142.5 | BU72: 80.6 | BV72: 98.7 | BW72: 321.8 | BX72: 87.1 | BY72: 76.5 | BZ72: =BX72+BY72 -> 163.6 | CA72: 84.9 | CB72: 84.5 | CC72: 333 | CD72: 90.6 | CE72: 78.6 | CF72: =CD72+CE72 -> 169.2 | CG72: 79.1 | CH72: 90.6 | CI72: 338.9 | CJ72: 105.5 | CK72: 80.9 | CL72: =CJ72+CK72 -> 186.4
B73: Australia | AY73: 98.365 | BE73: 119.49 | BK73: 149.551 | BQ73: 181.339 | BR73: 19.1 | BS73: 46.2 | BT73: =BR73+BS73 -> 65.3 | BU73: 25 | BV73: 46.4 | BW73: 136.7 | BX73: 27.6 | BY73: 34.2 | BZ73: =BX73+BY73 -> 61.8 | CA73: 27.1 | CB73: 48.3 | CC73: 137.2 | CD73: 17.1 | CE73: 53.1 | CF73: =CD73+CE73 -> 70.2 | CG73: 33.7 | CH73: 47.3 | CI73: 151.2 | CJ73: 71.4 | CK73: 98.1 | CL73: =CJ73+CK73 -> 169.5
B74: Other | C74: 19.488 | D74: 27.881 | E74: 33.041 | F74: 26.934 | G74: 37.561 | H74: 49.018 | I74: 41.831 | O74: 42.628 | U74: 44.153 | AY74: 55.692 | BE74: 38.72 | BK74: 54.581 | BQ74: 62.719 | BR74: 14.2 | BS74: 25.9 | BT74: =BR74+BS74 -> 40.1 | BU74: 20.3 | BV74: 17.6 | BW74: 78 | BX74: 16.4 | BY74: 24.6 | BZ74: =BX74+BY74 -> 41 | CA74: 15.1 | CB74: 23.2 | CC74: 79.3 | CD74: 21.3 | CE74: 24.8 | CF74: =CD74+CE74 -> 46.1 | CG74: 22.3 | CH74: 29.4 | CI74: 97.8 | CJ74: 31 | CK74: 33.9 | CL74: =CJ74+CK74 -> 64.9
B75: International (legacy: non-US/Canada)
B76: United States % of revenue | C76: =IF(ISNUMBER(C70),C70/C95,"") -> 0.60327236 | D76: =IF(ISNUMBER(D70),D70/D95,"") -> 0.55780588 | E76: =IF(ISNUMBER(E70),E70/E95,"") -> 0.53959777 | F76: =IF(ISNUMBER(F70),F70/F95,"") -> 0.53660948 | G76: =IF(ISNUMBER(G70),G70/G95,"") -> 0.51903215 | H76: =IF(ISNUMBER(H70),H70/H95,"") -> 0.49299291 | I76: =IF(ISNUMBER(I70),I70/I95,"") -> 0.48214999 | J76: =IF(ISNUMBER(J70),J70/J95,"") | ... CL76: =IF(ISNUMBER(CL70),CL70/CL95,"") -> 0.69447819
B78: Group Total — adjusted EBITDA & adjusted EBIT (RB Global's primary profit KPIs) | CT78: GROUP TOTAL (CONSOLIDATED) — modelling logic
B79: Total revenue | C79: =C95 -> 257.857 | D79: =D95 -> 311.906 | E79: =E95 -> 354.818 | F79: =F95 -> 377.211 | G79: =G95 -> 357.369 | H79: =H95 -> 396.099 | I79: =I95 -> 437.955 | J79: =J95 -> 102.058 | ... CN79: =CN95 -> 1293.3653 | CO79: =SUM(CJ79,CK79,CM79,CN79) -> 5006.0521 | CP79: =CP95 -> 5262.0409 | CQ79: =CQ95 -> 5513.2993 | CR79: =CR95 -> 5749.8059 | CS79: =CS95 -> 5996.4995 | CV79: =IFERROR((CS79/CI79)^(1/5)-1,"n/m") -> 0.054881748 | CW79: =IFERROR((CI79/BE79)^(1/5)-1,"n/m") -> 0.2722504 | CX79: =IFERROR((CI79/AA79)^(1/10)-1,"n/m") -> 0.2443239 | CY79: =IFERROR((CI79/C79)^(1/19)-1,"n/m") -> 0.16363236
B80: Adjusted EBITDA (company definition of the period) | C80: =IF(ISNUMBER(C158),C158,C156) -> 101.591 | D80: =IF(ISNUMBER(D158),D158,D156) -> 125.125 | E80: =IF(ISNUMBER(E158),E158,E156) -> 159.913 | F80: =IF(ISNUMBER(F158),F158,F156) -> 161.428 | G80: =IF(ISNUMBER(G158),G158,G156) -> 131.352 | H80: =IF(ISNUMBER(H158),H158,H156) -> 153.638 | I80: =IF(ISNUMBER(I158),I158,I156) -> 157.593 | J80: =IF(ISNUMBER(J158),J158,J156) -> 31.998 | ... CL80: =IF(ISNUMBER(CL158),CL158,CL156) -> 749.9 | CM80: =(CHOOSE(MATCH($CT$2,{"Bull","Base","Bear"},0),$DC$13,$DD$13,$DE$13)-CL80)*CM95/(CM95+CN95) -> 364.28185 | CN80: =(CHOOSE(MATCH($CT$2,{"Bull","Base","Bear"},0),$DC$13,$DD$13,$DE$13)-CL80)*CN95/(CM95+CN95) -> 405.81815 | CO80: =SUM(CJ80,CK80,CM80,CN80) -> 1520 | CP80: =CP95*CP81 -> 1604.9225 | CQ80: =CQ95*CQ81 -> 1709.1228 | CR80: =CR95*CR81 -> 1811.1889 | CS80: =CS95*CS81 -> 1918.8798 | CT80: Historical = company-published adjusted EBITDA (model bridge where not published). Q3/26E–Q4/26E: FY26 outlook ($1,545m / $1,520m / $1,495m by scenario) less 1H/26, split by quarterly revenue. 2027E+: revenue × scenario adjusted EBITDA margin. | CV80: =IFERROR((CS80/CI80)^(1/5)-1,"n/m") -> 0.065129869 | CW80: =IFERROR((CI80/BE80)^(1/5)-1,"n/m") -> 0.30185971 | CX80: =IFERROR((CI80/AA80)^(1/10)-1,"n/m") -> 0.20751048 | CY80: =IFERROR((CI80/C80)^(1/19)-1,"n/m") -> 0.14803949
B81: Adjusted EBITDA margin % (of total revenue) | C81: =IFERROR(C80/C95,"") -> 0.39398194 | D81: =IFERROR(D80/D95,"") -> 0.40116253 | E81: =IFERROR(E80/E95,"") -> 0.45069021 | F81: =IFERROR(F80/F95,"") -> 0.42795146 | G81: =IFERROR(G80/G95,"") -> 0.36755287 | H81: =IFERROR(H80/H95,"") -> 0.38787778 | I81: =IFERROR(I80/I95,"") -> 0.35983834 | J81: =IFERROR(J80/J95,"") -> 0.3135276 | ... CO81: =IFERROR(CO80/CO95,"") -> 0.30363248 | CP81: =CHOOSE(MATCH($CT$2,{"Bull","Base","Bear"},0),$DC$39,$DD$39,$DE$39) -> 0.305 | CQ81: =CHOOSE(MATCH($CT$2,{"Bull","Base","Bear"},0),$DC$40,$DD$40,$DE$40) -> 0.31 | CR81: =CHOOSE(MATCH($CT$2,{"Bull","Base","Bear"},0),$DC$41,$DD$41,$DE$41) -> 0.315 | CS81: =CHOOSE(MATCH($CT$2,{"Bull","Base","Bear"},0),$DC$42,$DD$42,$DE$42) -> 0.32 | CT81: 2027E–2030E: scenario lever (ADJ_EBITDA_margin). Inventory-sales mix dilutes the revenue margin; see % of GTV and % of service revenue + inventory return below. | CV81: =IFERROR(AVERAGE(CO81,CP81,CQ81,CR81,CS81),"n/m") -> 0.3107265 | CW81: =IFERROR(AVERAGE(BK81,BQ81,BW81,CC81,CI81),"n/m") -> 0.28598145 | CX81: =IFERROR(AVERAGE(AG81,AM81,AS81,AY81,BE81,BK81,BQ81,BW81,CC81,CI81),"n/m") -> 0.27284756 | CY81: =IFERROR(AVERAGE(C81,D81,E81,F81,G81,H81,I81,O81,U81,AA81,AG81,AM81,AS81,AY81,BE81,BK81,BQ81,BW81,CC81,CI81),"n/m") -> 0.33418027
B82: Adjusted EBITDA % of GTV | C82: =IFERROR(C80/C39,"") -> 0.03733559 | D82: =IFERROR(D80/D39,"") -> 0.039267431 | E82: =IFERROR(E80/E39,"") -> 0.04482922 | F82: =IFERROR(F80/F39,"") -> 0.046227672 | G82: =IFERROR(G80/G39,"") -> 0.040073574 | H82: =IFERROR(H80/H39,"") -> 0.041364129 | I82: =IFERROR(I80/I39,"") -> 0.040325835 | J82: =IFERROR(J80/J39,"") -> 0.037851643 | ... CS82: =IFERROR(CS80/CS39,"") -> 0.0896 | CV82: =IFERROR(AVERAGE(CO82,CP82,CQ82,CR82,CS82),"n/m") -> 0.087057483 | CW82: =IFERROR(AVERAGE(BK82,BQ82,BW82,CC82,CI82),"n/m") -> 0.077853641 | CX82: =IFERROR(AVERAGE(AG82,AM82,AS82,AY82,BE82,BK82,BQ82,BW82,CC82,CI82),"n/m") -> 0.066284768 | CY82: =IFERROR(AVERAGE(C82,D82,E82,F82,G82,H82,I82,O82,U82,AA82,AG82,AM82,AS82,AY82,BE82,BK82,BQ82,BW82,CC82,CI82),"n/m") -> 0.054575181
B83: Adjusted EBITDA % of (service revenue + inventory return) | C83: =IFERROR(C80/(C93+N(C58)),"") -> 0.39398194 | D83: =IFERROR(D80/(D93+N(D58)),"") -> 0.40116253 | E83: =IFERROR(E80/(E93+N(E58)),"") -> 0.45069021 | F83: =IFERROR(F80/(F93+N(F58)),"") -> 0.42795146 | G83: =IFERROR(G80/(G93+N(G58)),"") -> 0.36755287 | H83: =IFERROR(H80/(H93+N(H58)),"") -> 0.38787778 | I83: =IFERROR(I80/(I93+N(I58)),"") -> 0.35983834 | J83: =IFERROR(J80/(J93+N(J58)),"") -> 0.3135276 | ... CL83: =IFERROR(CL80/(CL93+N(CL58)),"") -> 0.39801497 | CM83: =IFERROR(CM80/(CM93+CM58),"") -> 0.41630821 | CN83: =IFERROR(CN80/(CN93+CN58),"") -> 0.42127572 | CO83: =IFERROR(CO80/(CO93+CO58),"") -> 0.40833465 | CP83: =IFERROR(CP80/(CP93+CP58),"") -> 0.41536965 | CQ83: =IFERROR(CQ80/(CQ93+CQ58),"") -> 0.42217899 | CR83: =IFERROR(CR80/(CR93+CR58),"") -> 0.42898833 | CS83: =IFERROR(CS80/(CS93+CS58),"") -> 0.43579767
B84: Adjusted EBITDA y/y % | D84: =IFERROR(D80/C80-1,"") -> 0.23165438 | E84: =IFERROR(E80/D80-1,"") -> 0.27802597 | F84: =IFERROR(F80/E80-1,"") -> 0.0094739014 | G84: =IFERROR(G80/F80-1,"") -> -0.18631216 | H84: =IFERROR(H80/G80-1,"") -> 0.16966624 | I84: =IFERROR(I80/H80-1,"") -> 0.025742329 | O84: =IFERROR(O80/I80-1,"") -> 0.11045541 | P84: =IFERROR(P80/J80-1,"") -> -0.047284205 | Q84: =IFERROR(Q80/K80-1,"") -> 0.19071304 | R84: =IFERROR(R80/L80-1,"") -> 0.1014107 | S84: =IFERROR(S80/M80-1,"") -> -0.25459039 | T84: =IFERROR(T80/N80-1,"") -> -0.066701836 | U84: =IFERROR(U80/O80-1,"") -> 0.044571429 | V84: =IFERROR(V80/P80-1,"") -> 0.46239134 | ... CO84: =IFERROR(CO80/CI80-1,"") -> 0.085946989 | CP84: =IFERROR(CP80/CO80-1,"") -> 0.055870042 | CQ84: =IFERROR(CQ80/CP80-1,"") -> 0.064925456 | CR84: =IFERROR(CR80/CQ80-1,"") -> 0.059718401 | CS84: =IFERROR(CS80/CR80-1,"") -> 0.059458723
B85: Incremental adjusted EBITDA margin (ΔAdj. EBITDA / ΔRevenue) | D85: =IFERROR((D80-C80)/(D95-C95),"") -> 0.43541971 | E85: =IFERROR((E80-D80)/(E95-D95),"") -> 0.81068233 | F85: =IFERROR((F80-E80)/(F95-E95),"") -> 0.067655071 | G85: =IFERROR((G80-F80)/(G95-F95),"") -> 1.5157746 | H85: =IFERROR((H80-G80)/(H95-G95),"") -> 0.57541957 | I85: =IFERROR((I80-H80)/(I95-H95),"") -> 0.094490635 | O85: =IFERROR((O80-I80)/(O95-I95),"") -> 0.59110975 | P85: =IFERROR((P80-J80)/(P95-J95),"") -> 0.43602305 | Q85: =IFERROR((Q80-K80)/(Q95-K95),"") -> 0.75194257 | R85: =IFERROR((R80-L80)/(R95-L95),"") -> 0.86109728 | S85: =IFERROR((S80-M80)/(S95-M95),"") -> 2.6740162 | T85: =IFERROR((T80-N80)/(T95-N95),"") -> -0.59427703 | U85: =IFERROR((U80-O80)/(U95-O95),"") -> 0.56959252 | V85: =IFERROR((V80-P80)/(V95-P95),"") -> 0.8277158 | ... CO85: =IFERROR((CO80-CI80)/(CO95-CI95),"") -> 0.28963376 | CP85: =IFERROR((CP80-CO80)/(CP95-CO95),"") -> 0.33174297 | CQ85: =IFERROR((CQ80-CP80)/(CQ95-CP95),"") -> 0.41471371 | CR85: =IFERROR((CR80-CQ80)/(CR95-CQ95),"") -> 0.43155698 | CS85: =IFERROR((CS80-CR80)/(CS95-CR95),"") -> 0.4365374
B86: Adjusted D&A (total D&A − amortization of acquired intangibles) | C86: =C101-N(C172) -> 15.017 | D86: =D101-N(D172) -> 19.417 | E86: =E101-N(E172) -> 24.764 | F86: =F101-N(F172) -> 31.761 | G86: =G101-N(G172) -> 37.813 | H86: =H101-N(H172) -> 42.408 | I86: =I101-N(I172) -> 41.138 | J86: =J101-N(J172) -> 10.32 | ... CL86: =CL101-N(CL172) -> 110.3 | CM86: =CM95*CM66 -> 50.184914 | CN86: =CN95*CN66 -> 55.907119 | CO86: =SUM(CJ86,CK86,CM86,CN86) -> 216.39203 | CP86: =CP95*CP66 -> 226.26776 | CQ86: =CQ95*CQ66 -> 237.07187 | CR86: =CR95*CR66 -> 247.24165 | CS86: =CS95*CS66 -> 257.84948 | CT86: Amortization of acquired intangibles is disclosed as an adjusting item from 2023 (IAA); before 2023 adjusted D&A = total D&A.
B87: Adjusted EBIT (adjusted EBITDA − adjusted D&A) | C87: =C80-C86 -> 86.574 | D87: =D80-D86 -> 105.708 | E87: =E80-E86 -> 135.149 | F87: =F80-F86 -> 129.667 | G87: =G80-G86 -> 93.539 | H87: =H80-H86 -> 111.23 | I87: =I80-I86 -> 116.455 | J87: =J80-J86 -> 21.678 | ... CN87: =CN80-CN86 -> 349.91103 | CO87: =SUM(CJ87,CK87,CM87,CN87) -> 1303.608 | CP87: =CP80-CP86 -> 1378.6547 | CQ87: =CQ80-CQ86 -> 1472.0509 | CR87: =CR80-CR86 -> 1563.9472 | CS87: =CS80-CS86 -> 1661.0304 | CT87: Model measure (RB Global does not publish adjusted EBIT): adjusted operating profit after the depreciation of yards / IT but before acquired-intangible amortization — the 'segment OI' analogue. | CV87: =IFERROR((CS87/CI87)^(1/5)-1,"n/m") -> 0.067415275 | CW87: =IFERROR((CI87/BE87)^(1/5)-1,"n/m") -> 0.30191935 | CX87: =IFERROR((CI87/AA87)^(1/10)-1,"n/m") -> 0.21544641 | CY87: =IFERROR((CI87/C87)^(1/19)-1,"n/m") -> 0.14833773
B88: Adjusted EBIT margin % | C88: =IFERROR(C87/C95,"") -> 0.33574423 | D88: =IFERROR(D87/D95,"") -> 0.3389098 | E88: =IFERROR(E87/E95,"") -> 0.38089669 | F88: =IFERROR(F87/F95,"") -> 0.34375191 | G88: =IFERROR(G87/G95,"") -> 0.26174346 | H88: =IFERROR(H87/H95,"") -> 0.28081363 | I88: =IFERROR(I87/I95,"") -> 0.26590631 | J88: =IFERROR(J87/J95,"") -> 0.21240863 | ... CS88: =IFERROR(CS87/CS95,"") -> 0.277 | CV88: =IFERROR(AVERAGE(CO88,CP88,CQ88,CR88,CS88),"n/m") -> 0.26768128 | CW88: =IFERROR(AVERAGE(BK88,BQ88,BW88,CC88,CI88),"n/m") -> 0.24664867 | CX88: =IFERROR(AVERAGE(AG88,AM88,AS88,AY88,BE88,BK88,BQ88,BW88,CC88,CI88),"n/m") -> 0.22715849 | CY88: =IFERROR(AVERAGE(C88,D88,E88,F88,G88,H88,I88,O88,U88,AA88,AG88,AM88,AS88,AY88,BE88,BK88,BQ88,BW88,CC88,CI88),"n/m") -> 0.268939
B89: EBITDA (GAAP-derived: net income + D&A + interest − interest income + tax) | C89: =C139 -> 101.591 | D89: =D139 -> 125.125 | E89: =E139 -> 159.913 | F89: =F139 -> 161.428 | G89: =G139 -> 131.352 | H89: =H139 -> 153.638 | I89: =I139 -> 157.593 | J89: =J139 -> 31.998 | ... CN89: =CN139 -> 377.31815 | CO89: =SUM(CJ89,CK89,CM89,CN89) -> 1409.9 | CP89: =CP139 -> 1508.9225 | CQ89: =CQ139 -> 1608.1228 | CR89: =CR139 -> 1705.1889 | CS89: =CS139 -> 1807.8798
B90: Check: adjusted EBITDA model bridge vs KPI (should be 0) | C90: =IF(ISNUMBER(C158),ROUND(C156-C80,1),"n/p") -> n/p | D90: =IF(ISNUMBER(D158),ROUND(D156-D80,1),"n/p") -> n/p | E90: =IF(ISNUMBER(E158),ROUND(E156-E80,1),"n/p") -> n/p | F90: =IF(ISNUMBER(F158),ROUND(F156-F80,1),"n/p") -> n/p | G90: =IF(ISNUMBER(G158),ROUND(G156-G80,1),"n/p") -> n/p | H90: =IF(ISNUMBER(H158),ROUND(H156-H80,1),"n/p") -> n/p | I90: =IF(ISNUMBER(I158),ROUND(I156-I80,1),"n/p") -> n/p | J90: =IF(ISNUMBER(J158),ROUND(J156-J80,1),"n/p") -> n/p | ... CL90: =IF(ISNUMBER(CL158),ROUND(CL156-CL80,1),"n/p") -> 0 | CM90: =ROUND(CM156-CM80,1) -> 0 | CN90: =ROUND(CN156-CN80,1) -> 0 | CO90: =ROUND(CO156-CO80,1) -> 0 | CP90: =ROUND(CP156-CP80,1) -> 0 | CQ90: =ROUND(CQ156-CQ80,1) -> 0 | CR90: =ROUND(CR156-CR80,1) -> 0 | CS90: =ROUND(CS156-CS80,1) -> 0
B92: CONSOLIDATED INCOME STATEMENT (US GAAP) | CT92: CONSOLIDATED IS — forecast logic
B93: Service revenue (pre-2018: total revenues, commissions + fees) | C93: 257.857 | D93: 311.906 | E93: 354.818 | F93: 377.211 | G93: 357.369 | H93: 396.099 | I93: 437.955 | J93: 102.058 | K93: 128.322 | L93: =J93+K93 -> 230.38 | M93: 105.8 | N93: 131.223 | O93: 467.403 | P93: 98.588 | Q93: 141.835 | R93: =P93+Q93 -> 240.423 | S93: 102.217 | T93: 138.457 | U93: 481.097 | V93: 115.618 | W93: 155.477 | X93: =V93+W93 -> 271.095 | Y93: 109.318 | Z93: 135.462 | AA93: 515.875 | AB93: 131.945 | AC93: 158.805 | AD93: =AB93+AC93 -> 290.75 | AE93: 128.876 | AF93: 146.769 | AG93: 566.395 | AH93: 123.379 | AI93: 172.749 | AJ93: =AH93+AI93 -> 296.128 | AK93: 145.938 | AL93: 182.351 | AM93: 624.417 | AN93: 176.016 | AO93: 214.346 | AP93: =AN93+AO93 -> 390.362 | AQ93: 161.374 | AR93: 197.779 | AS93: 749.515 | AT93: 172.372 | AU93: 234.606 | AV93: =AT93+AU93 -> 406.978 | AW93: 178.577 | AX93: 218.469 | AY93: 804.024 | AZ93: 183.123 | BA93: 234.139 | BB93: =AZ93+BA93 -> 417.262 | BC93: 222.679 | BD93: 231.655 | BE93: 871.596 | BF93: 206.03 | BG93: 252.748 | BH93: =BF93+BG93 -> 458.778 | BI93: 214.193 | BJ93: 244.788 | BK93: 917.759 | BL93: 244.861 | BM93: 286.502 | BN93: =BL93+BM93 -> 531.363 | BO93: 246.696 | BP93: 272.523 | BQ93: 1050.583 | BR93: 343.6 | BS93: 806.1 | BT93: =BR93+BS93 -> 1149.7 | BU93: 773.8 | BV93: 809.1 | BW93: 2732.5 | BX93: 849.1 | BY93: 859.1 | BZ93: =BX93+BY93 -> 1708.2 | CA93: 779.9 | CB93: 875.5 | CC93: 3363.6 | CD93: 852.5 | CE93: 887.2 | CF93: =CD93+CE93 -> 1739.7 | CG93: 845 | CH93: 917.5 | CI93: 3502.2 | CJ93: 897.7 | CK93: 933.4 | CL93: =CJ93+CK93 -> 1831.1 | CM93: =CM53 -> 852.32738 | CN93: =CN53 -> 937.10482 | CO93: =SUM(CJ93,CK93,CM93,CN93) -> 3620.5322 | CP93: =CP53 -> 3758.6006 | CQ93: =CQ53 -> 3938.0709 | CR93: =CR53 -> 4107.0042 | CS93: =CS53 -> 4283.2139 | CT93: Forecast linked to the revenue build. | CV93: =IFERROR((CS93/CI93)^(1/5)-1,"n/m") -> 0.041083983 | CW93: =IFERROR((CI93/BE93)^(1/5)-1,"n/m") -> 0.32070294 | CX93: =IFERROR((CI93/AA93)^(1/10)-1,"n/m") -> 0.211099 | CY93: =IFERROR((CI93/C93)^(1/19)-1,"n/m") -> 0.14717475
B94: Inventory sales revenue | AH94: 76.048 | AI94: 79.864 | AJ94: =AH94+AI94 -> 155.912 | AK94: 81.463 | AL94: 109.399 | AM94: 346.774 | AN94: 84.162 | AO94: 94.184 | AP94: =AN94+AO94 -> 178.346 | AQ94: 83.972 | AR94: 158.193 | AS94: 420.511 | AT94: 131.057 | AU94: 158.616 | AV94: =AT94+AU94 -> 289.673 | AW94: 111.219 | AX94: 113.725 | AY94: 514.617 | AZ94: 90.132 | BA94: 154.911 | BB94: =AZ94+BA94 -> 245.043 | BC94: 108.863 | BD94: 151.758 | BE94: 505.664 | BF94: 125.525 | BG94: 143.613 | BH94: =BF94+BG94 -> 269.138 | BI94: 115.489 | BJ94: 114.585 | BK94: 499.212 | BL94: 149.06 | BM94: 198.044 | BN94: =BL94+BM94 -> 347.104 | BO94: 164.783 | BP94: 171.338 | BQ94: 683.225 | BR94: 168.8 | BS94: 300.4 | BT94: =BR94+BS94 -> 469.2 | BU94: 246 | BV94: 231.8 | BW94: 947.1 | BX94: 215.6 | BY94: 237 | BZ94: =BX94+BY94 -> 452.6 | CA94: 201.9 | CB94: 266.1 | CC94: 920.6 | CD94: 256.1 | CE94: 298.8 | CF94: =CD94+CE94 -> 554.9 | CG94: 247.7 | CH94: 285.9 | CI94: 1088.5 | CJ94: 336.9 | CK94: 383.7 | CL94: =CJ94+CK94 -> 720.6 | CM94: =CM56 -> 308.65942 | CN94: =CN56 -> 356.26051 | CO94: =SUM(CJ94,CK94,CM94,CN94) -> 1385.5199 | CP94: =CP56 -> 1503.4402 | CQ94: =CQ56 -> 1575.2284 | CR94: =CR56 -> 1642.8017 | CS94: =CS56 -> 1713.2856 | CV94: =IFERROR((CS94/CI94)^(1/5)-1,"n/m") -> 0.09496507 | CW94: =IFERROR((CI94/BE94)^(1/5)-1,"n/m") -> 0.1657174 | CX94: =IFERROR((CI94/AA94)^(1/10)-1,"n/m") -> n/m | CY94: =IFERROR((CI94/C94)^(1/19)-1,"n/m") -> n/m
B95: Total revenue | C95: =C93+C94 -> 257.857 | D95: =D93+D94 -> 311.906 | E95: =E93+E94 -> 354.818 | F95: =F93+F94 -> 377.211 | G95: =G93+G94 -> 357.369 | H95: =H93+H94 -> 396.099 | I95: =I93+I94 -> 437.955 | J95: =J93+J94 -> 102.058 | ... CN95: =CN93+CN94 -> 1293.3653 | CO95: =SUM(CJ95,CK95,CM95,CN95) -> 5006.0521 | CP95: =CP93+CP94 -> 5262.0409 | CQ95: =CQ93+CQ94 -> 5513.2993 | CR95: =CR93+CR94 -> 5749.8059 | CS95: =CS93+CS94 -> 5996.4995 | CV95: =IFERROR((CS95/CI95)^(1/5)-1,"n/m") -> 0.054881748 | CW95: =IFERROR((CI95/BE95)^(1/5)-1,"n/m") -> 0.2722504 | CX95: =IFERROR((CI95/AA95)^(1/10)-1,"n/m") -> 0.2443239 | CY95: =IFERROR((CI95/C95)^(1/19)-1,"n/m") -> 0.16363236
B96: Memo: total revenue on ASC 606 basis — company recast of 2016 (FY2018 10-K) | AB96: 255.504 | AC96: 275.667 | AD96: =AB96+AC96 -> 531.171 | AE96: 300.976 | AF96: 294.83 | AG96: 1126.977
B97: Costs of services (ex D&A; legacy 'direct expenses') | C97: 40.457 | D97: 46.481 | E97: 49.75 | F97: 49.89 | G97: 47.021 | H97: 48.044 | I97: 49.687 | J97: 9.361 | K97: 15.551 | L97: =J97+K97 -> 24.912 | M97: 11.9 | N97: 17.196 | O97: 54.008 | P97: 10.3 | Q97: 17.616 | R97: =P97+Q97 -> 27.916 | S97: 12.45 | T97: 17.518 | U97: 57.884 | V97: 11.609 | W97: 17.027 | X97: =V97+W97 -> 28.636 | Y97: 12.045 | Z97: 15.345 | AA97: 56.026 | AB97: 15.313 | AC97: 19.758 | AD97: =AB97+AC97 -> 35.071 | AE97: 14.75 | AF97: 16.241 | AG97: 66.062 | AH97: 24.34 | AI97: 36.292 | AJ97: =AH97+AI97 -> 60.632 | AK97: 33.461 | AL97: 39.096 | AM97: 133.189 | AN97: 36.657 | AO97: 43.033 | AP97: =AN97+AO97 -> 79.69 | AQ97: 33.053 | AR97: 46.315 | AS97: 159.058 | AT97: 36.069 | AU97: 50.268 | AV97: =AT97+AU97 -> 86.337 | AW97: 36.382 | AX97: 42.258 | AY97: 164.977 | AZ97: 39.355 | BA97: 39.448 | BB97: =AZ97+BA97 -> 78.803 | BC97: 39.223 | BD97: 39.27 | BE97: 164.528 | BF97: 37.866 | BG97: 41.301 | BH97: =BF97+BG97 -> 79.167 | BI97: 35.108 | BJ97: 40.984 | BK97: 155.258 | BL97: 39.015 | BM97: 45.039 | BN97: =BL97+BM97 -> 84.054 | BO97: 41.521 | BP97: 42.553 | BQ97: 168.127 | BR97: 76.4 | BS97: 287.3 | BT97: =BR97+BS97 -> 363.7 | BU97: 316.8 | BV97: 327.1 | BW97: 1007.6 | BX97: 353 | BY97: 348.8 | BZ97: =BX97+BY97 -> 701.8 | CA97: 339.7 | CB97: 374.2 | CC97: 1415.7 | CD97: 361.9 | CE97: 353.9 | CF97: =CD97+CE97 -> 715.8 | CG97: 353 | CH97: 362.5 | CI97: 1431.3 | CJ97: 365.1 | CK97: 381.6 | CL97: =CJ97+CK97 -> 746.7 | CM97: =CM93*CM65 -> 352.8915 | CN97: =CN93*CN65 -> 366.94998 | CO97: =SUM(CJ97,CK97,CM97,CN97) -> 1466.5415 | CP97: =CP93*CP65 -> 1522.2333 | CQ97: =CQ93*CQ65 -> 1587.0426 | CR97: =CR93*CR65 -> 1646.9087 | CS97: =CS93*CS65 -> 1713.2856 | CT97: Costs of services = service revenue × cost-of-services % (driver block).
B98: Cost of inventory sold | AH98: 63.401 | AI98: 71.726 | AJ98: =AH98+AI98 -> 135.127 | AK98: 72.476 | AL98: 98.895 | AM98: 306.498 | AN98: 75.791 | AO98: 81.702 | AP98: =AN98+AO98 -> 157.493 | AQ98: 74.341 | AR98: 142.505 | AS98: 374.339 | AT98: 120.475 | AU98: 149.818 | AV98: =AT98+AU98 -> 270.293 | AW98: 102.41 | AX98: 108.136 | AY98: 480.839 | AZ98: 81.585 | BA98: 143.134 | BB98: =AZ98+BA98 -> 224.719 | BC98: 96.253 | BD98: 137.322 | BE98: 458.293 | BF98: 110.747 | BG98: 131.023 | BH98: =BF98+BG98 -> 241.77 | BI98: 102.993 | BJ98: 103.159 | BK98: 447.921 | BL98: 131.582 | BM98: 176.171 | BN98: =BL98+BM98 -> 307.753 | BO98: 147.253 | BP98: 153.567 | BQ98: 608.574 | BR98: 151.5 | BS98: 291.9 | BT98: =BR98+BS98 -> 443.4 | BU98: 230 | BV98: 220.2 | BW98: 893.6 | BX98: 196.6 | BY98: 222.7 | BZ98: =BX98+BY98 -> 419.3 | CA98: 193.5 | CB98: 251 | CC98: 863.8 | CD98: 235 | CE98: 286.4 | CF98: =CD98+CE98 -> 521.4 | CG98: 236.1 | CH98: 273.1 | CI98: 1030.6 | CJ98: 306.7 | CK98: 360.9 | CL98: =CJ98+CK98 -> 667.6 | CM98: =CM94*(1-CM59) -> 285.95758 | CN98: =CN94*(1-CN59) -> 330.05761 | CO98: =SUM(CJ98,CK98,CM98,CN98) -> 1283.6152 | CP98: =CP94*(1-CP59) -> 1398.1994 | CQ98: =CQ94*(1-CQ59) -> 1464.9624 | CR98: =CR94*(1-CR59) -> 1527.8056 | CS98: =CS94*(1-CS59) -> 1593.3556 | CT98: Cost of inventory sold = inventory sales × (1 − inventory rate).
B99: Selling, general and administrative expenses | C99: 117.714 | D99: 144.816 | E99: 164.556 | F99: 168.312 | G99: 181.02 | H99: 201.935 | I99: 227.091 | J99: 60.769 | K99: 60.417 | L99: =J99+K99 -> 121.186 | M99: 57.687 | N99: 64.863 | O99: 243.736 | P99: 59.972 | Q99: 61.513 | R99: =P99+Q99 -> 121.485 | S99: 58.556 | T99: 68.179 | U99: 248.22 | V99: 63.756 | W99: 65.239 | X99: =V99+W99 -> 128.995 | Y99: 58.17 | Z99: 67.224 | AA99: 254.389 | AB99: 67.11 | AC99: 73.992 | AD99: =AB99+AC99 -> 141.102 | AE99: 68.293 | AF99: 74.134 | AG99: 283.529 | AH99: 70.575 | AI99: 74.377 | AJ99: =AH99+AI99 -> 144.952 | AK99: 85.335 | AL99: 92.983 | AM99: 323.27 | AN99: 97.47 | AO99: 101.259 | AP99: =AN99+AO99 -> 198.729 | AQ99: 88.323 | AR99: 95.624 | AS99: 382.676 | AT99: 95.184 | AU99: 97.714 | AV99: =AT99+AU99 -> 192.898 | AW99: 93.691 | AX99: 95.8 | AY99: 382.389 | AZ99: 98.385 | BA99: 100.632 | BB99: =AZ99+BA99 -> 199.017 | BC99: 110.186 | BD99: 108.318 | BE99: 410.291 | BF99: 114.239 | BG99: 109.56 | BH99: =BF99+BG99 -> 223.799 | BI99: 106.508 | BJ99: 125.896 | BK99: 456.203 | BL99: 126.606 | BM99: 144.277 | BN99: =BL99+BM99 -> 270.883 | BO99: 133.193 | BP99: 135.856 | BQ99: 539.933 | BR99: 148.2 | BS99: 194.5 | BT99: =BR99+BS99 -> 342.7 | BU99: 203.5 | BV99: 197.5 | BW99: 743.7 | BX99: 198.1 | BY99: 208.6 | BZ99: =BX99+BY99 -> 406.7 | CA99: 177.8 | CB99: 189.4 | CC99: 773.9 | CD99: 205 | CE99: 222.2 | CF99: =CD99+CE99 -> 427.2 | CG99: 217.8 | CH99: 260.2 | CI99: 905.2 | CJ99: 214.2 | CK99: 210.8 | CL99: =CJ99+CK99 -> 425 | CM99: =CM95-CM97-CM98-CM100-CM102+CM104+CM105-CM80+CM155+CM109+CM110+CM111 -> 180.35588 | CN99: =CN95-CN97-CN98-CN100-CN102+CN104+CN105-CN80+CN155+CN109+CN110+CN111 -> 213.03959 | CO99: =SUM(CJ99,CK99,CM99,CN99) -> 818.39546 | CP99: =CP95-CP97-CP98-CP100-CP102+CP104+CP105-CP80+CP155+CP109+CP110+CP111 -> 822.68572 | CQ99: =CQ95-CQ97-CQ98-CQ100-CQ102+CQ104+CQ105-CQ80+CQ155+CQ109+CQ110+CQ111 -> 843.17155 | CR99: =CR95-CR97-CR98-CR100-CR102+CR104+CR105-CR80+CR155+CR109+CR110+CR111 -> 859.90279 | CS99: =CS95-CS97-CS98-CS100-CS102+CS104+CS105-CS80+CS155+CS109+CS110+CS111 -> 871.97851 | CT99: Forecast SG&A is the balancing line so that adjusted EBITDA equals the KPI driver (outlook / margin lever): SG&A = revenue − costs of services − cost of inventory − adj. EBITDA + SBC, restructuring & other adjusting items recorded in SG&A.
B100: Acquisition-related and integration costs | Z100: 0.601 | AA100: 0.601 | AB100: 1.197 | AC100: 0.603 | AD100: =AB100+AC100 -> 1.8 | AE100: 5.398 | AF100: 4.631 | AG100: 11.829 | AH100: 8.627 | AI100: 22.948 | AJ100: =AH100+AI100 -> 31.575 | AK100: 3.587 | AL100: 3.11 | AM100: 38.272 | AN100: 1.633 | AO100: 1.399 | AP100: =AN100+AO100 -> 3.032 | AQ100: 2.007 | AR100: 0.054 | AS100: 5.093 | AT100: 0.669 | AU100: 0.038 | AV100: =AT100+AU100 -> 0.707 | AW100: 0.045 | AX100: 0.025 | AY100: 0.777 | AZ100: 0 | BA100: 0 | BB100: =AZ100+BA100 -> 0 | BC100: 0 | BD100: 6.014 | BE100: 6.014 | BF100: 2.922 | BG100: 3.049 | BH100: =BF100+BG100 -> 5.971 | BI100: 10.255 | BJ100: 13.971 | BK100: 30.197 | BL100: 9.637 | BM100: 3.399 | BN100: =BL100+BM100 -> 13.036 | BO100: 2.031 | BP100: 22.194 | BQ100: 37.261 | BR100: 126.2 | BS100: 46.3 | BT100: =BR100+BS100 -> 172.5 | BU100: 23.1 | BV100: 20.5 | BW100: 216.1 | BX100: 12.8 | BY100: 4.1 | BZ100: =BX100+BY100 -> 16.9 | CA100: 6 | CB100: 6.1 | CC100: 29 | CD100: 3.1 | CE100: 2.7 | CF100: =CD100+CE100 -> 5.8 | CG100: 4 | CH100: 9.6 | CI100: 19.4 | CJ100: 6.2 | CK100: 7.7 | CL100: =CJ100+CK100 -> 13.9 | CM100: =CM144 -> 6 | CN100: =CN144 -> 6 | CO100: =SUM(CJ100,CK100,CM100,CN100) -> 25.9 | CP100: =CP144 -> 10 | CQ100: =CQ144 -> 10 | CR100: =CR144 -> 10 | CS100: =CS144 -> 10
B101: Depreciation and amortization | C101: 15.017 | D101: 19.417 | E101: 24.764 | F101: 31.761 | G101: 37.813 | H101: 42.408 | I101: 41.138 | J101: 10.32 | K101: 10.719 | L101: =J101+K101 -> 21.039 | M101: 10.815 | N101: 11.426 | O101: 43.28 | P101: 10.597 | Q101: 10.979 | R101: =P101+Q101 -> 21.576 | S101: 11.406 | T101: 11.554 | U101: 44.536 | V101: 10.616 | W101: 10.769 | X101: =V101+W101 -> 21.385 | Y101: 10.017 | Z101: 10.63 | AA101: 42.032 | AB101: 10.08 | AC101: 10.284 | AD101: =AB101+AC101 -> 20.364 | AE101: 10.196 | AF101: 10.301 | AG101: 40.861 | AH101: 10.338 | AI101: 11.872 | AJ101: =AH101+AI101 -> 22.21 | AK101: 14.837 | AL101: 15.647 | AM101: 52.694 | AN101: 16.191 | AO101: 16.537 | AP101: =AN101+AO101 -> 32.728 | AQ101: 16.723 | AR101: 17.163 | AS101: 66.614 | AT101: 17.115 | AU101: 17.112 | AV101: =AT101+AU101 -> 34.227 | AW101: 17.692 | AX101: 18.582 | AY101: 70.501 | AZ101: 19.293 | BA101: 17.857 | BB101: =AZ101+BA101 -> 37.15 | BC101: 18.436 | BD101: 19.337 | BE101: 74.921 | BF101: 21.07 | BG101: 21.935 | BH101: =BF101+BG101 -> 43.005 | BI101: 21.907 | BJ101: 22.977 | BK101: 87.889 | BL101: 24.225 | BM101: 24.298 | BN101: =BL101+BM101 -> 48.523 | BO101: 24.29 | BP101: 24.342 | BQ101: 97.155 | BR101: 36.2 | BS101: 109.6 | BT101: =BR101+BS101 -> 145.8 | BU101: 101.1 | BV101: 105.3 | BW101: 352.2 | BX101: 107.7 | BY101: 110.3 | BZ101: =BX101+BY101 -> 218 | CA101: 111.9 | CB101: 114.5 | CC101: 444.4 | CD101: 114.5 | CE101: 116.7 | CF101: =CD101+CE101 -> 231.2 | CG101: 124.7 | CH101: 127.5 | CI101: 483.4 | CJ101: 126.7 | CK101: 130.4 | CL101: =CJ101+CK101 -> 257.1 | CM101: =CM86+CM172 -> 125.28491 | CN101: =CN86+CN172 -> 131.00712 | CO101: =SUM(CJ101,CK101,CM101,CN101) -> 513.39203 | CP101: =CP86+CP172 -> 463.26776 | CQ101: =CQ86+CQ172 -> 420.07187 | CR101: =CR86+CR172 -> 408.24165 | CS101: =CS86+CS172 -> 411.84948 | CT101: D&A = adjusted D&A (% of revenue) + amortization of acquired intangibles (10-K schedule). | CV101: =IFERROR((CS101/CI101)^(1/5)-1,"n/m") -> -0.031529548 | CW101: =IFERROR((CI101/BE101)^(1/5)-1,"n/m") -> 0.45191307 | CX101: =IFERROR((CI101/AA101)^(1/10)-1,"n/m") -> 0.27665238 | CY101: =IFERROR((CI101/C101)^(1/19)-1,"n/m") -> 0.20047706
B102: Impairment losses | O102: 0 | S102: 8.084 | U102: 8.084 | AA102: 0 | AE102: 28.243 | AF102: 0 | AG102: 28.243 | AI102: 8.911 | AJ102: =N(AH102)+N(AI102) -> 8.911 | AK102: 0 | AM102: 8.911 | AO102: 0 | AP102: =N(AN102)+N(AO102) -> 0 | AQ102: 0 | AS102: 0 | CM102: 0 | CN102: 0 | CO102: =SUM(CJ102,CK102,CM102,CN102) -> 0 | CP102: 0 | CQ102: 0 | CR102: 0 | CS102: 0
B103: Total operating expenses | C103: =C97+N(C98)+C99+N(C100)+C101+N(C102) -> 173.188 | D103: =D97+N(D98)+D99+N(D100)+D101+N(D102) -> 210.714 | E103: =E97+N(E98)+E99+N(E100)+E101+N(E102) -> 239.07 | F103: =F97+N(F98)+F99+N(F100)+F101+N(F102) -> 249.963 | G103: =G97+N(G98)+G99+N(G100)+G101+N(G102) -> 265.854 | H103: =H97+N(H98)+H99+N(H100)+H101+N(H102) -> 292.387 | I103: =I97+N(I98)+I99+N(I100)+I101+N(I102) -> 317.916 | J103: =J97+N(J98)+J99+N(J100)+J101+N(J102) -> 80.45 | ... CL103: =CL97+N(CL98)+CL99+N(CL100)+CL101+N(CL102) -> 2110.3 | CM103: =CM97+CM98+CM99+CM100+CM101+CM102 -> 950.48986 | CN103: =CN97+CN98+CN99+CN100+CN101+CN102 -> 1047.0543 | CO103: =SUM(CJ103,CK103,CM103,CN103) -> 4107.8442 | CP103: =CP97+CP98+CP99+CP100+CP101+CP102 -> 4216.3862 | CQ103: =CQ97+CQ98+CQ99+CQ100+CQ101+CQ102 -> 4325.2484 | CR103: =CR97+CR98+CR99+CR100+CR101+CR102 -> 4452.8587 | CS103: =CS97+CS98+CS99+CS100+CS101+CS102 -> 4600.4692
B104: Gain (loss) on disposition of property, plant and equipment | C104: 1.277 | D104: 0.243 | E104: 6.37 | F104: 0.647 | G104: 0.25 | H104: 3.861 | I104: -2.074 | J104: -0.011 | K104: 0.13 | L104: =J104+K104 -> 0.119 | M104: 0.785 | N104: 9.648 | O104: 10.552 | P104: 0.071 | Q104: 0.258 | R104: =P104+Q104 -> 0.329 | S104: 3.104 | T104: 0.079 | U104: 3.512 | V104: 0.175 | W104: 0.791 | X104: =V104+W104 -> 0.966 | Y104: 0.234 | Z104: 8.491 | AA104: 9.691 | AB104: 0.246 | AC104: 0.201 | AD104: =AB104+AC104 -> 0.447 | AE104: 0.57 | AF104: 0.265 | AG104: 1.282 | AH104: 0.721 | AI104: 0.308 | AJ104: =AH104+AI104 -> 1.029 | AK104: 0.042 | AL104: 0.585 | AM104: 1.656 | AN104: 0.345 | AO104: 0.271 | AP104: =AN104+AO104 -> 0.616 | AQ104: 0.342 | AR104: 1.773 | AS104: 2.731 | AT104: 0.149 | AU104: 0.101 | AV104: =AT104+AU104 -> 0.25 | AW104: 0.821 | AX104: 0.036 | AY104: 1.107 | AZ104: 0.047 | BA104: 1.213 | BB104: =AZ104+BA104 -> 1.26 | BC104: 0.276 | BD104: 0.022 | BE104: 1.559 | BF104: 0.068 | BG104: 0.175 | BH104: =BF104+BG104 -> 0.243 | BI104: 1.068 | BJ104: 0.125 | BK104: 1.436 | BL104: 169.82 | BM104: 0.347 | BN104: =BL104+BM104 -> 170.167 | BO104: 0.333 | BP104: 0.333 | BQ104: 170.833 | BR104: 1.2 | BS104: 2.7 | BT104: =BR104+BS104 -> 3.9 | BU104: 0.5 | BV104: 0.5 | BW104: 4.9 | BX104: 2.4 | BY104: 0.3 | BZ104: =BX104+BY104 -> 2.7 | CA104: 0.5 | CB104: 0.6 | CC104: 3.8 | CD104: 0.4 | CE104: 0 | CF104: =CD104+CE104 -> 0.4 | CG104: 1.2 | CH104: 0.6 | CI104: 2.2 | CJ104: 1.8 | CK104: -0.9 | CL104: =CJ104+CK104 -> 0.9 | CM104: 0 | CN104: 0 | CO104: =SUM(CJ104,CK104,CM104,CN104) -> 0.9 | CP104: 0 | CQ104: 0 | CR104: 0 | CS104: 0 | CT104: Forecast nil (large historical gains were surplus-land sales).
B105: Other operating items (e.g. loss on deconsolidation / divestiture) | BY105: 0 | BZ105: =N(BX105)+N(BY105) -> 0 | CA105: 0 | CB105: 0 | CC105: 0 | CE105: -15.5 | CF105: =N(CD105)+N(CE105) -> -15.5 | CG105: 0 | CH105: 5.9 | CI105: -9.6 | CK105: 0 | CL105: =N(CJ105)+N(CK105) -> 0 | CM105: 0 | CN105: 0 | CO105: =SUM(CJ105,CK105,CM105,CN105) -> 0 | CP105: 0 | CQ105: 0 | CR105: 0 | CS105: 0
...

Sheet Bull-Base-Bear
B2: RB Global, Inc. (RBA) — Bull / Base / Bear Case P&L Summary | J2: Share price ($): | K2: =Model!$CO$381 -> 80
B3: Adjusted figures (company definitions) · USD millions · Live panel linked to Model — toggle scenario via Model!CT2. Bull and Bear panels are value snapshots generated from the Model with the switch set to each case. | J3: As of: | K3: =TODAY() -> 46298
B5: Scenario: | C5: =Model!CT2 -> Base | N5: Scenario: | O5: Bull | P5: Snapshot (values) — Model run with switch = Bull | Z5: Scenario: | AA5: Bear | AB5: Snapshot (values) — Model run with switch = Bear
B7: (USDm, except EPS and shares) | C7: 2025A | D7: 2026E | E7: 2027E | F7: 2028E | G7: 2029E | H7: 2030E | I7: 25-'30 CAGR | J7: LT Hist Avg | K7: LT Hist Min | L7: LT Hist Max | N7: (USDm, except EPS and shares) | O7: 2025A | P7: 2026E | Q7: 2027E | R7: 2028E | S7: 2029E | T7: 2030E | U7: 25-'30 CAGR | V7: LT Hist Avg | W7: LT Hist Min | X7: LT Hist Max | Z7: (USDm, except EPS and shares) | AA7: 2025A | AB7: 2026E | AC7: 2027E | AD7: 2028E | AE7: 2029E | AF7: 2030E | AG7: 25-'30 CAGR | AH7: LT Hist Avg | AI7: LT Hist Min | AJ7: LT Hist Max
B9: Revenue | C9: =Model!CI95 -> 4590.7 | D9: =Model!CO95 -> 5006.0521 | E9: =Model!CP95 -> 5262.0409 | F9: =Model!CQ95 -> 5513.2993 | G9: =Model!CR95 -> 5749.8059 | H9: =Model!CS95 -> 5996.4995 | I9: =IFERROR((H9/C9)^(1/5)-1,"n/m") -> 0.054881748 | N9: Revenue | O9: 4590.7 | P9: 5051.1963 | Q9: 5410.5894 | R9: 5777.1535 | S9: 6140.5221 | T9: 6526.7891 | U9: 0.072912074 | Z9: Revenue | AA9: 4590.7 | AB9: 4960.908 | AC9: 5043.7163 | AD9: 5110.7127 | AE9: 5154.0598 | AF9: 5198.0718 | AG9: 0.025162409
B10: Revenue y/y % | D10: =IFERROR(D9/C9-1,"") -> 0.090476862 | E10: =IFERROR(E9/D9-1,"") -> 0.051135851 | F10: =IFERROR(F9/E9-1,"") -> 0.047749239 | G10: =IFERROR(G9/F9-1,"") -> 0.042897474 | H10: =IFERROR(H9/G9-1,"") -> 0.042904681 | N10: Revenue y/y % | P10: 0.10031069 | Q10: 0.071150112 | R10: 0.067749374 | S10: 0.062897512 | T10: 0.062904583 | Z10: Revenue y/y % | AB10: 0.080643037 | AC10: 0.016692163 | AD10: 0.013283147 | AE10: 0.0084816217 | AF10: 0.0085392904
B11: GTV | C11: =Model!CI39 -> 16201.9 | D11: =Model!CO39 -> 17822.09 | E11: =Model!CP39 -> 18793.003 | F11: =Model!CQ39 -> 19690.355 | G11: =Model!CR39 -> 20535.021 | H11: =Model!CS39 -> 21416.07 | I11: =IFERROR((H11/C11)^(1/5)-1,"n/m") -> 0.057388943 | N11: GTV | O11: 16201.9 | P11: 17984.109 | Q11: 19323.534 | R11: 20632.691 | S11: 21930.436 | T11: 23309.961 | U11: 0.075462123 | Z11: GTV | AA11: 16201.9 | AB11: 17660.071 | AC11: 18013.272 | AD11: 18252.545 | AE11: 18407.357 | AF11: 18564.542 | AG11: 0.027598969
B12: Adjusted EBIT (model) | C12: =Model!CI87 -> 1198.7 | D12: =Model!CO87 -> 1303.608 | E12: =Model!CP87 -> 1378.6547 | F12: =Model!CQ87 -> 1472.0509 | G12: =Model!CR87 -> 1563.9472 | H12: =Model!CS87 -> 1661.0304 | I12: =IFERROR((H12/C12)^(1/5)-1,"n/m") -> 0.067415275 | N12: Adjusted EBIT (model) | O12: 1198.7 | P12: 1326.6566 | Q12: 1471.6803 | R12: 1600.2715 | S12: 1731.6272 | T12: 1873.1885 | U12: 0.093387724 | Z12: Adjusted EBIT (model) | AA12: 1198.7 | AB12: 1280.5594 | AC12: 1245.7979 | AD12: 1287.8996 | AE12: 1324.5934 | AF12: 1361.8948 | AG12: 0.025856496
B13: Adjusted EBIT margin % | C13: =IFERROR(C12/C9,"") -> 0.26111486 | D13: =IFERROR(D12/D9,"") -> 0.26040639 | E13: =IFERROR(E12/E9,"") -> 0.262 | F13: =IFERROR(F12/F9,"") -> 0.267 | G13: =IFERROR(G12/G9,"") -> 0.272 | H13: =IFERROR(H12/H9,"") -> 0.277 | J13: =IFERROR(AVERAGE(Model!C88,Model!D88,Model!E88,Model!F88,Model!G88,Model!H88,Model!I88,Model!O88,Model!U88,Model!AA88,Model!AG88,Model!AM88,Model!AS88,Model!AY88,Model!BE88,Model!BK88,Model!BQ88,Model!BW88,Model!CC88,Model!CI88),"") -> 0.268939 | K13: =IFERROR(MIN(Model!C88,Model!D88,Model!E88,Model!F88,Model!G88,Model!H88,Model!I88,Model!O88,Model!U88,Model!AA88,Model!AG88,Model!AM88,Model!AS88,Model!AY88,Model!BE88,Model!BK88,Model!BQ88,Model!BW88,Model!CC88,Model!CI88),"") -> 0.14294819 | L13: =IFERROR(MAX(Model!C88,Model!D88,Model!E88,Model!F88,Model!G88,Model!H88,Model!I88,Model!O88,Model!U88,Model!AA88,Model!AG88,Model!AM88,Model!AS88,Model!AY88,Model!BE88,Model!BK88,Model!BQ88,Model!BW88,Model!CC88,Model!CI88),"") -> 0.38089669 | N13: Adjusted EBIT margin % | O13: 0.26111486 | P13: 0.26264205 | Q13: 0.272 | R13: 0.277 | S13: 0.282 | T13: 0.287 | V13: 0.268939 | W13: 0.14294819 | X13: 0.38089669 | Z13: Adjusted EBIT margin % | AA13: 0.26111486 | AB13: 0.25813004 | AC13: 0.247 | AD13: 0.252 | AE13: 0.257 | AF13: 0.262 | AH13: 0.268939 | AI13: 0.14294819 | AJ13: 0.38089669
B15: Operating Income (GAAP) | C15: =Model!CI106 -> 713.4 | D15: =Model!CO106 -> 899.10797 | E15: =Model!CP106 -> 1045.6547 | F15: =Model!CQ106 -> 1188.0509 | G15: =Model!CR106 -> 1296.9472 | H15: =Model!CS106 -> 1396.0304 | I15: =IFERROR((H15/C15)^(1/5)-1,"n/m") -> 0.14370061 | N15: Operating Income (GAAP) | O15: 713.4 | P15: 922.15656 | Q15: 1138.6803 | R15: 1316.2715 | S15: 1464.6272 | T15: 1608.1885 | U15: 0.17652394 | Z15: Operating Income (GAAP) | AA15: 713.4 | AB15: 876.05937 | AC15: 912.79792 | AD15: 1003.8996 | AE15: 1057.5934 | AF15: 1096.8948 | AG15: 0.089849116
B16: Operating income y/y % | D16: =IFERROR(D15/C15-1,"") -> 0.26031394 | E16: =IFERROR(E15/D15-1,"") -> 0.16299126 | F16: =IFERROR(F15/E15-1,"") -> 0.136179 | G16: =IFERROR(G15/F15-1,"") -> 0.091659621 | H16: =IFERROR(H15/G15-1,"") -> 0.076397214 | N16: Operating income y/y % | P16: 0.29262204 | Q16: 0.23480152 | R16: 0.15596229 | S16: 0.11270905 | T16: 0.098018957 | Z16: Operating income y/y % | AB16: 0.22800585 | AC16: 0.041936141 | AD16: 0.099804873 | AE16: 0.053485205 | AF16: 0.037161207
B17: Operating margin (GAAP) % | C17: =IFERROR(C15/C9,"") -> 0.15540114 | D17: =IFERROR(D15/D9,"") -> 0.1796042 | E17: =IFERROR(E15/E9,"") -> 0.19871657 | F17: =IFERROR(F15/F9,"") -> 0.21548819 | G17: =IFERROR(G15/G9,"") -> 0.22556365 | H17: =IFERROR(H15/H9,"") -> 0.23280755 | J17: =IFERROR(AVERAGE(Model!C210,Model!D210,Model!E210,Model!F210,Model!G210,Model!H210,Model!I210,Model!O210,Model!U210,Model!AA210,Model!AG210,Model!AM210,Model!AS210,Model!AY210,Model!BE210,Model!BK210,Model!BQ210,Model!BW210,Model!CC210,Model!CI210),"") -> 0.23970623 | K17: =IFERROR(MIN(Model!C210,Model!D210,Model!E210,Model!F210,Model!G210,Model!H210,Model!I210,Model!O210,Model!U210,Model!AA210,Model!AG210,Model!AM210,Model!AS210,Model!AY210,Model!BE210,Model!BK210,Model!BQ210,Model!BW210,Model!CC210,Model!CI210),"") -> 0.11327638 | L17: =IFERROR(MAX(Model!C210,Model!D210,Model!E210,Model!F210,Model!G210,Model!H210,Model!I210,Model!O210,Model!U210,Model!AA210,Model!AG210,Model!AM210,Model!AS210,Model!AY210,Model!BE210,Model!BK210,Model!BQ210,Model!BW210,Model!CC210,Model!CI210),"") -> 0.34417081 | N17: Operating margin (GAAP) % | O17: 0.15540114 | P17: 0.18256201 | Q17: 0.21045403 | R17: 0.22784084 | S17: 0.23851836 | T17: 0.24639811 | V17: 0.23970623 | W17: 0.11327638 | X17: 0.34417081 | Z17: Operating margin (GAAP) % | AA17: 0.15540114 | AB17: 0.17659255 | AC17: 0.18097725 | AD17: 0.19643045 | AE17: 0.20519618 | AF17: 0.21101956 | AH17: 0.23970623 | AI17: 0.11327638 | AJ17: 0.34417081
B19: Net Income (Adjusted, available to common) | C19: =Model!CI188 -> 747 | D19: =Model!CO188 -> 821.88606 | E19: =Model!CP188 -> 872.71941 | F19: =Model!CQ188 -> 948.91795 | G19: =Model!CR188 -> 1024.9357 | H19: =Model!CS188 -> 1103.1648 | I19: =IFERROR((H19/C19)^(1/5)-1,"n/m") -> 0.081095246 | N19: Net Income (Adjusted, available to common) | O19: 747 | P19: 839.40299 | Q19: 938.63092 | R19: 1039.2725 | S19: 1143.3414 | T19: 1253.8575 | U19: 0.10913782 | Z19: Net Income (Adjusted, available to common) | AA19: 747 | AB19: 804.36912 | AC19: 778.50699 | AD19: 818.74764 | AE19: 855.25771 | AF19: 889.85779 | AG19: 0.035618979
B21: FDSO (m) | C21: =Model!CI127 -> 186.9 | D21: =Model!CO127 -> 186.1125 | E21: =Model!CP127 -> 182.36355 | F21: =Model!CQ127 -> 178.44351 | G21: =Model!CR127 -> 174.56407 | H21: =Model!CS127 -> 170.48419 | I21: =IFERROR((H21/C21)^(1/5)-1,"n/m") -> -0.018218239 | N21: FDSO (m) | O21: 186.9 | P21: 185.40938 | Q21: 179.61238 | R21: 173.99732 | S21: 168.53376 | T21: 162.97338 | U21: -0.027025465 | Z21: FDSO (m) | AA21: 186.9 | AB21: 187.05 | AC21: 186.03178 | AD21: 184.37175 | AE21: 182.60449 | AF21: 180.4986 | AG21: -0.0069459088
B23: Adjusted EPS — Diluted ($) | C23: =Model!CI191 -> 3.9967897 | D23: =Model!CO191 -> 4.4160712 | E23: =Model!CP191 -> 4.7856022 | F23: =Model!CQ191 -> 5.31775 | G23: =Model!CR191 -> 5.8714014 | H23: =Model!CS191 -> 6.4707749 | I23: =IFERROR((H23/C23)^(1/5)-1,"n/m") -> 0.10115638 | N23: Adjusted EPS — Diluted ($) | O23: 3.9967897 | P23: 4.5272953 | Q23: 5.2258697 | R23: 5.9729226 | S23: 6.78405 | T23: 7.6936337 | U23: 0.13994537 | Z23: Adjusted EPS — Diluted ($) | AA23: 3.9967897 | AB23: 4.3002893 | AC23: 4.1848065 | AD23: 4.4407433 | AE23: 4.683662 | AF23: 4.9299984 | AG23: 0.042862607
B24: EPS y/y % | D24: =IFERROR(D23/C23-1,"") -> 0.10490457 | E24: =IFERROR(E23/D23-1,"") -> 0.083678675 | F24: =IFERROR(F23/E23-1,"") -> 0.11119765 | G24: =IFERROR(G23/F23-1,"") -> 0.10411386 | H24: =IFERROR(H23/G23-1,"") -> 0.10208353 | N24: EPS y/y % | P24: 0.13273291 | Q24: 0.15430283 | R24: 0.14295282 | S24: 0.13580077 | T24: 0.13407678 | Z24: EPS y/y % | AB24: 0.075935849 | AC24: -0.026854667 | AD24: 0.061158584 | AE24: 0.054702259 | AF24: 0.05259482
B26: P / E (x) — assumed (adjusted EPS) | E26: 22 | F26: =E26 -> 22 | G26: =F26 -> 22 | H26: =G26 -> 22 | N26: P / E (x) — assumed (adjusted EPS) | Q26: 26 | R26: =Q26 -> 26 | S26: =R26 -> 26 | T26: =S26 -> 26 | Z26: P / E (x) — assumed (adjusted EPS) | AC26: 17 | AD26: =AC26 -> 17 | AE26: =AD26 -> 17 | AF26: =AE26 -> 17
B27: Price Target ($) | E27: =E26*E23 -> 105.28325 | F27: =F26*F23 -> 116.9905 | G27: =G26*G23 -> 129.17083 | H27: =H26*H23 -> 142.35705 | N27: Price Target ($) | Q27: =Q26*Q23 -> 135.87261 | R27: =R26*R23 -> 155.29599 | S27: =S26*S23 -> 176.3853 | T27: =T26*T23 -> 200.03447 | Z27: Price Target ($) | AC27: =AC26*AC23 -> 71.141711 | AD27: =AD26*AD23 -> 75.492637 | AE27: =AE26*AE23 -> 79.622255 | AF27: =AF26*AF23 -> 83.809973
B28: Upside / (Downside) vs current | E28: =IFERROR(E27/$K$2-1,"") -> 0.31604061 | F28: =IFERROR(F27/$K$2-1,"") -> 0.46238124 | G28: =IFERROR(G27/$K$2-1,"") -> 0.6146354 | H28: =IFERROR(H27/$K$2-1,"") -> 0.77946308 | N28: Upside / (Downside) vs current | Q28: =IFERROR(Q27/$K$2-1,"") -> 0.69840767 | R28: =IFERROR(R27/$K$2-1,"") -> 0.94119984 | S28: =IFERROR(S27/$K$2-1,"") -> 1.2048163 | T28: =IFERROR(T27/$K$2-1,"") -> 1.5004309 | Z28: Upside / (Downside) vs current | AC28: =IFERROR(AC27/$K$2-1,"") -> -0.11072862 | AD28: =IFERROR(AD27/$K$2-1,"") -> -0.056342038 | AE28: =IFERROR(AE27/$K$2-1,"") -> -0.0047218163 | AF28: =IFERROR(AF27/$K$2-1,"") -> 0.047624661
B29: IRR (to Dec-Y-1) | F29: =IFERROR((F27/$K$2)^(1/((DATE(2028-1,12,31)-$K$3)/365.25))-1,"") -> 0.35766869 | G29: =IFERROR((G27/$K$2)^(1/((DATE(2029-1,12,31)-$K$3)/365.25))-1,"") -> 0.2378897 | H29: =IFERROR((H27/$K$2)^(1/((DATE(2030-1,12,31)-$K$3)/365.25))-1,"") -> 0.19438966 | N29: IRR (to Dec-Y-1) | R29: =IFERROR((R27/$K$2)^(1/((DATE(2028-1,12,31)-$K$3)/365.25))-1,"") -> 0.70512788 | S29: =IFERROR((S27/$K$2)^(1/((DATE(2029-1,12,31)-$K$3)/365.25))-1,"") -> 0.42215614 | T29: =IFERROR((T27/$K$2)^(1/((DATE(2030-1,12,31)-$K$3)/365.25))-1,"") -> 0.32641451 | Z29: IRR (to Dec-Y-1) | AD29: =IFERROR((AD27/$K$2)^(1/((DATE(2028-1,12,31)-$K$3)/365.25))-1,"") -> -0.045583444 | AE29: =IFERROR((AE27/$K$2)^(1/((DATE(2029-1,12,31)-$K$3)/365.25))-1,"") -> -0.0021059841 | AF29: =IFERROR((AF27/$K$2)^(1/((DATE(2030-1,12,31)-$K$3)/365.25))-1,"") -> 0.014443733
B31: Free Cash Flow | C31: =Model!CI251 -> 608 | D31: =Model!CO251 -> 715.07608 | E31: =Model!CP251 -> 805.7705 | F31: =Model!CQ251 -> 889.86212 | G31: =Model!CR251 -> 976.26565 | H31: =Model!CS251 -> 1071.5299 | I31: =IFERROR((H31/C31)^(1/5)-1,"n/m") -> 0.12000547 | N31: Free Cash Flow | O31: 608 | P31: 737.99728 | Q31: 877.3761 | R31: 985.01347 | S31: 1098.8974 | T31: 1226.4717 | U31: 0.15067 | Z31: Free Cash Flow | AA31: 608 | AB31: 692.15489 | AC31: 701.36808 | AD31: 751.71846 | AE31: 800.24583 | AF31: 852.56091 | AG31: 0.069952178
B32: FCF % | C32: =IFERROR(C31/C9,"") -> 0.13244168 | D32: =IFERROR(D31/D9,"") -> 0.14284232 | E32: =IFERROR(E31/E9,"") -> 0.15312889 | F32: =IFERROR(F31/F9,"") -> 0.16140283 | G32: =IFERROR(G31/G9,"") -> 0.16979106 | H32: =IFERROR(H31/H9,"") -> 0.17869257 | J32: =IFERROR(AVERAGE(Model!C253,Model!D253,Model!E253,Model!F253,Model!G253,Model!H253,Model!I253,Model!O253,Model!U253,Model!AA253,Model!AG253,Model!AM253,Model!AS253,Model!AY253,Model!BE253,Model!BK253,Model!BQ253,Model!BW253,Model!CC253,Model!CI253),"") -> 0.14542509 | K32: =IFERROR(MIN(Model!C253,Model!D253,Model!E253,Model!F253,Model!G253,Model!H253,Model!I253,Model!O253,Model!U253,Model!AA253,Model!AG253,Model!AM253,Model!AS253,Model!AY253,Model!BE253,Model!BK253,Model!BQ253,Model!BW253,Model!CC253,Model!CI253),"") -> -0.057840921 | L32: =IFERROR(MAX(Model!C253,Model!D253,Model!E253,Model!F253,Model!G253,Model!H253,Model!I253,Model!O253,Model!U253,Model!AA253,Model!AG253,Model!AM253,Model!AS253,Model!AY253,Model!BE253,Model!BK253,Model!BQ253,Model!BW253,Model!CC253,Model!CI253),"") -> 0.35339375 | N32: FCF % | O32: 0.13244168 | P32: 0.14610346 | Q32: 0.16215906 | R32: 0.17050152 | S32: 0.1789583 | T32: 0.18791349 | V32: 0.14542509 | W32: -0.057840921 | X32: 0.35339375 | Z32: FCF % | AA32: 0.13244168 | AB32: 0.13952182 | AC32: 0.1390578 | AD32: 0.14708682 | AE32: 0.15526514 | AF32: 0.16401484 | AH32: 0.14542509 | AI32: -0.057840921 | AJ32: 0.35339375
B33: FCF / share ($) | C33: =IFERROR(C31/C21,"") -> 3.2530765 | D33: =IFERROR(D31/D21,"") -> 3.8421712 | E33: =IFERROR(E31/E21,"") -> 4.4184843 | F33: =IFERROR(F31/F21,"") -> 4.9868003 | G33: =IFERROR(G31/G21,"") -> 5.5925921 | H33: =IFERROR(H31/H21,"") -> 6.2852158 | N33: FCF / share ($) | O33: 3.2530765 | P33: 3.9803666 | Q33: 4.8848308 | R33: 5.6610842 | S33: 6.5203399 | T33: 7.5255954 | Z33: FCF / share ($) | AA33: 3.2530765 | AB33: 3.7003737 | AC33: 3.770152 | AD33: 4.0771889 | AE33: 4.3823996 | AF33: 4.7233659
B34: FCF Yield (on PT) | E34: =IFERROR(E33/E$27,"") -> 0.041967591 | F34: =IFERROR(F33/F$27,"") -> 0.042625686 | G34: =IFERROR(G33/G$27,"") -> 0.043296091 | H34: =IFERROR(H33/H$27,"") -> 0.044151069 | N34: FCF Yield (on PT) | Q34: =IFERROR(Q33/Q$27,"") -> 0.035951548 | R34: =IFERROR(R33/R$27,"") -> 0.036453512 | S34: =IFERROR(S33/S$27,"") -> 0.036966459 | T34: =IFERROR(T33/T$27,"") -> 0.037621492 | Z34: FCF Yield (on PT) | AC34: =IFERROR(AC33/AC$27,"") -> 0.052994959 | AD34: =IFERROR(AD33/AD$27,"") -> 0.054007769 | AE34: =IFERROR(AE33/AE$27,"") -> 0.055039883 | AF34: =IFERROR(AF33/AF$27,"") -> 0.056358041
B35: Adjusted EBITDA | C35: =Model!CI80 -> 1399.7 | D35: =Model!CO80 -> 1520 | E35: =Model!CP80 -> 1604.9225 | F35: =Model!CQ80 -> 1709.1228 | G35: =Model!CR80 -> 1811.1889 | H35: =Model!CS80 -> 1918.8798 | I35: =IFERROR((H35/C35)^(1/5)-1,"n/m") -> 0.065129869 | N35: Adjusted EBITDA | O35: 1399.7 | P35: 1545 | Q35: 1704.3357 | R35: 1848.6891 | S35: 1995.6697 | T35: 2153.8404 | U35: 0.090023123 | Z35: Adjusted EBITDA | AA35: 1399.7 | AB35: 1495 | AC35: 1462.6777 | AD35: 1507.6602 | AE35: 1546.218 | AF35: 1585.4119 | AG35: 0.025230295
B36: Adjusted EBITDA margin % | C36: =IFERROR(C35/C9,"") -> 0.30489904 | D36: =IFERROR(D35/D9,"") -> 0.30363248 | E36: =IFERROR(E35/E9,"") -> 0.305 | F36: =IFERROR(F35/F9,"") -> 0.31 | G36: =IFERROR(G35/G9,"") -> 0.315 | H36: =IFERROR(H35/H9,"") -> 0.32 | J36: =IFERROR(AVERAGE(Model!C209,Model!D209,Model!E209,Model!F209,Model!G209,Model!H209,Model!I209,Model!O209,Model!U209,Model!AA209,Model!AG209,Model!AM209,Model!AS209,Model!AY209,Model!BE209,Model!BK209,Model!BQ209,Model!BW209,Model!CC209,Model!CI209),"") -> 0.33418027 | K36: =IFERROR(MIN(Model!C209,Model!D209,Model!E209,Model!F209,Model!G209,Model!H209,Model!I209,Model!O209,Model!U209,Model!AA209,Model!AG209,Model!AM209,Model!AS209,Model!AY209,Model!BE209,Model!BK209,Model!BQ209,Model!BW209,Model!CC209,Model!CI209),"") -> 0.19720529 | L36: =IFERROR(MAX(Model!C209,Model!D209,Model!E209,Model!F209,Model!G209,Model!H209,Model!I209,Model!O209,Model!U209,Model!AA209,Model!AG209,Model!AM209,Model!AS209,Model!AY209,Model!BE209,Model!BK209,Model!BQ209,Model!BW209,Model!CC209,Model!CI209),"") -> 0.45069021 | N36: Adjusted EBITDA margin % | O36: 0.30489904 | P36: 0.30586814 | Q36: 0.315 | R36: 0.32 | S36: 0.325 | T36: 0.33 | V36: 0.33418027 | W36: 0.19720529 | X36: 0.45069021 | Z36: Adjusted EBITDA margin % | AA36: 0.30489904 | AB36: 0.30135612 | AC36: 0.29 | AD36: 0.295 | AE36: 0.3 | AF36: 0.305 | AH36: 0.33418027 | AI36: 0.19720529 | AJ36: 0.45069021
B38: Net Debt (adjusted) | C38: =Model!CI376 -> 1940 | D38: =Model!CO376 -> 2167.1119 | E38: =Model!CP376 -> 2018.8441 | F38: =Model!CQ376 -> 1795.595 | G38: =Model!CR376 -> 1545.323 | H38: =Model!CS376 -> 1259.0513 | N38: Net Debt (adjusted) | O38: 1940 | P38: 2293.2907 | Q38: 2219.6845 | R38: 2044.8896 | S38: 1812.7926 | T38: 1509.4419 | Z38: Net Debt (adjusted) | AA38: 1940 | AB38: 1991.2331 | AC38: 1752.3448 | AD38: 1475.7654 | AE38: 1213.7708 | AF38: 962.65114
B39: Net Debt / Adjusted EBITDA (x) | C39: =IFERROR(C38/C35,"") -> 1.3860113 | D39: =IFERROR(D38/D35,"") -> 1.4257315 | E39: =IFERROR(E38/E35,"") -> 1.2579076 | F39: =IFERROR(F38/F35,"") -> 1.0505945 | G39: =IFERROR(G38/G35,"") -> 0.85320919 | H39: =IFERROR(H38/H35,"") -> 0.65613871 | N39: Net Debt / Adjusted EBITDA (x) | O39: 1.3860113 | P39: 1.4843306 | Q39: 1.3023752 | R39: 1.1061295 | S39: 0.90836304 | T39: 0.70081417 | Z39: Net Debt / Adjusted EBITDA (x) | AA39: 1.3860113 | AB39: 1.3319285 | AC39: 1.1980389 | AD39: 0.97884481 | AE39: 0.78499334 | AF39: 0.60719308
B41: ROIC | C41: =Model!CI356 -> 0.11950879 | D41: =Model!CO356 -> 0.12006215 | E41: =Model!CP356 -> 0.1277394 | F41: =Model!CQ356 -> 0.13660667 | G41: =Model!CR356 -> 0.14518264 | H41: =Model!CS356 -> 0.15439116 | J41: =IFERROR(AVERAGE(Model!C356,Model!D356,Model!E356,Model!F356,Model!G356,Model!H356,Model!I356,Model!O356,Model!U356,Model!AA356,Model!AG356,Model!AM356,Model!AS356,Model!AY356,Model!BE356,Model!BK356,Model!BQ356,Model!BW356,Model!CC356,Model!CI356),"") -> 0.1488023 | K41: =IFERROR(MIN(Model!C356,Model!D356,Model!E356,Model!F356,Model!G356,Model!H356,Model!I356,Model!O356,Model!U356,Model!AA356,Model!AG356,Model!AM356,Model!AS356,Model!AY356,Model!BE356,Model!BK356,Model!BQ356,Model!BW356,Model!CC356,Model!CI356),"") -> 0.082450537 | L41: =IFERROR(MAX(Model!C356,Model!D356,Model!E356,Model!F356,Model!G356,Model!H356,Model!I356,Model!O356,Model!U356,Model!AA356,Model!AG356,Model!AM356,Model!AS356,Model!AY356,Model!BE356,Model!BK356,Model!BQ356,Model!BW356,Model!CC356,Model!CI356),"") -> 0.23134292 | N41: ROIC | O41: 0.11950879 | P41: 0.122265 | Q41: 0.13650361 | R41: 0.14869126 | S41: 0.16094825 | T41: 0.17430168 | V41: 0.1488023 | W41: 0.082450537 | X41: 0.23134292 | Z41: ROIC | AA41: 0.11950879 | AB41: 0.11786219 | AC41: 0.11525843 | AD41: 0.11929264 | AE41: 0.12272909 | AF41: 0.12637749 | AH41: 0.1488023 | AI41: 0.082450537 | AJ41: 0.23134292
B42: RONTA | C42: =Model!CI368 -> 0.26722621 | D42: =Model!CO368 -> 0.25952282 | E42: =Model!CP368 -> 0.26279298 | F42: =Model!CQ368 -> 0.2649087 | G42: =Model!CR368 -> 0.26509019 | H42: =Model!CS368 -> 0.26438957 | J42: =IFERROR(AVERAGE(Model!C368,Model!D368,Model!E368,Model!F368,Model!G368,Model!H368,Model!I368,Model!O368,Model!U368,Model!AA368,Model!AG368,Model!AM368,Model!AS368,Model!AY368,Model!BE368,Model!BK368,Model!BQ368,Model!BW368,Model!CC368,Model!CI368),"") -> 0.18381418 | K42: =IFERROR(MIN(Model!C368,Model!D368,Model!E368,Model!F368,Model!G368,Model!H368,Model!I368,Model!O368,Model!U368,Model!AA368,Model!AG368,Model!AM368,Model!AS368,Model!AY368,Model!BE368,Model!BK368,Model!BQ368,Model!BW368,Model!CC368,Model!CI368),"") -> 0.098495413 | L42: =IFERROR(MAX(Model!C368,Model!D368,Model!E368,Model!F368,Model!G368,Model!H368,Model!I368,Model!O368,Model!U368,Model!AA368,Model!AG368,Model!AM368,Model!AS368,Model!AY368,Model!BE368,Model!BK368,Model!BQ368,Model!BW368,Model!CC368,Model!CI368),"") -> 0.38071221 | N42: RONTA | O42: 0.26722621 | P42: 0.27362011 | Q42: 0.29645127 | R42: 0.30769135 | S42: 0.31440733 | T42: 0.31761069 | V42: 0.18381418 | W42: 0.098495413 | X42: 0.38071221 | Z42: RONTA | AA42: 0.26722621 | AB42: 0.24331119 | AC42: 0.22162639 | AD42: 0.21397281 | AE42: 0.20708654 | AF42: 0.20160121 | AH42: 0.18381418 | AI42: 0.098495413 | AJ42: 0.38071221
B44: Implied Market Cap (USDm) | E44: =E27*E21 -> 19199.827 | F44: =F27*F21 -> 20876.195 | G44: =G27*G21 -> 22548.586 | H44: =H27*H21 -> 24269.625 | N44: Implied Market Cap (USDm) | Q44: =Q27*Q21 -> 24404.404 | R44: =R27*R21 -> 27021.086 | S44: =S27*S21 -> 29726.878 | T44: =T27*T21 -> 32600.294 | Z44: Implied Market Cap (USDm) | AC44: =AC27*AC21 -> 13234.619 | AD44: =AD27*AD21 -> 13918.71 | AE44: =AE27*AE21 -> 14539.381 | AF44: =AF27*AF21 -> 15127.582
B45: (+) Net Debt, preferred & NCI | E45: =E38+Model!CP385 -> 2502.7441 | F45: =F38+Model!CQ385 -> 2279.495 | G45: =G38+Model!CR385 -> 2029.223 | H45: =H38+Model!CS385 -> 1742.9513 | N45: (+) Net Debt, preferred & NCI | Q45: =Q38+Model!CP385 -> 2703.5845 | R45: =R38+Model!CQ385 -> 2528.7896 | S45: =S38+Model!CR385 -> 2296.6926 | T45: =T38+Model!CS385 -> 1993.3419 | Z45: (+) Net Debt, preferred & NCI | AC45: =AC38+Model!CP385 -> 2236.2448 | AD45: =AD38+Model!CQ385 -> 1959.6654 | AE45: =AE38+Model!CR385 -> 1697.6708 | AF45: =AF38+Model!CS385 -> 1446.5511
B46: Implied Enterprise Value (USDm) | E46: =E44+E45 -> 21702.571 | F46: =F44+F45 -> 23155.69 | G46: =G44+G45 -> 24577.809 | H46: =H44+H45 -> 26012.577 | N46: Implied Enterprise Value (USDm) | Q46: =Q44+Q45 -> 27107.988 | R46: =R44+R45 -> 29549.875 | S46: =S44+S45 -> 32023.57 | T46: =T44+T45 -> 34593.636 | Z46: Implied Enterprise Value (USDm) | AC46: =AC44+AC45 -> 15470.864 | AD46: =AD44+AD45 -> 15878.375 | AE46: =AE44+AE45 -> 16237.052 | AF46: =AF44+AF45 -> 16574.134
B47: Implied EV / Adjusted EBITDA (x) | E47: =IFERROR(E46/E35,"") -> 13.522505 | F47: =IFERROR(F46/F35,"") -> 13.548289 | G47: =IFERROR(G46/G35,"") -> 13.569987 | H47: =IFERROR(H46/H35,"") -> 13.556126 | N47: Implied EV / Adjusted EBITDA (x) | Q47: =IFERROR(Q46/Q35,"") -> 15.905311 | R47: =IFERROR(R46/R35,"") -> 15.984232 | S47: =IFERROR(S46/S35,"") -> 16.046528 | T47: =IFERROR(T46/T35,"") -> 16.061374 | Z47: Implied EV / Adjusted EBITDA (x) | AC47: =IFERROR(AC46/AC35,"") -> 10.577083 | AD47: =IFERROR(AD46/AD35,"") -> 10.531799 | AE47: =IFERROR(AE46/AE35,"") -> 10.501141 | AF47: =IFERROR(AF46/AF35,"") -> 10.45415

Sheet DCF
B2: DCF VALUATION — RB GLOBAL, INC. (RBA)
B4: 1. WACC BUILD
B5: Risk-free rate (US 10Y govt) | C5: 0.0425 | D5: Assumption (~US 10Y Treasury yield); update to market
B6: Equity risk premium | C6: 0.055 | D6: Damodaran-style US ERP estimate
B7: Levered beta | C7: 1.05 | D7: Marketplace / auction peers (Copart ~1.0–1.1); cyclical used-equipment exposure, automotive salvage defensive
B8: Cost of equity | C8: =C5+C7*C6 -> 0.10025
B9: Pre-tax cost of debt | C9: 0.0625 | D9: BB-rated; 6.75% secured notes 2028, 7.75% unsecured 2031, TLA at SOFR + margin (~6.2% blended at 30-Jun-26)
B10: Tax rate | C10: 0.24 | D10: FY26 outlook 23–25% (GAAP and adjusted)
B11: After-tax cost of debt | C11: =C9*(1-C10) -> 0.0475
B12: Target D/V | C12: 0.2 | D12: Adjusted net debt / adjusted EBITDA target ~1.5–2.0x
B13: WACC | C13: =C8*(1-C12)+C11*C12 -> 0.0897
B15: Valuation date (live) | C15: =TODAY() -> 46298 | D15: Periods = (Dec-31-Year − today) / 365.25; cash flows assumed at year-end
B16: 2. UNLEVERED FREE CASH FLOW BUILD (USDm)
D17: 2026E | E17: 2027E | F17: 2028E | G17: 2029E | H17: 2030E | I17: 2031E | J17: 2032E | K17: 2033E | L17: 2034E | M17: 2035E | N17: Terminal
B18: Adjusted EBIT (Model) | D18: =Model!CO87 -> 1303.608 | E18: =Model!CP87 -> 1378.6547 | F18: =Model!CQ87 -> 1472.0509 | G18: =Model!CR87 -> 1563.9472 | H18: =Model!CS87 -> 1661.0304 | I18: =H18*(1+I$29) -> 1760.6922 | J18: =I18*(1+J$29) -> 1857.5303 | K18: =J18*(1+K$29) -> 1950.4068 | L18: =K18*(1+L$29) -> 2038.1751 | M18: =L18*(1+M$29) -> 2119.7021
B19: (−) Stock-based compensation (economic cost) | D19: =-Model!CO143 -> -69.2 | E19: =-Model!CP143 -> -75 | F19: =-Model!CQ143 -> -80 | G19: =-Model!CR143 -> -85 | H19: =-Model!CS143 -> -90 | I19: =H19*(1+I$29) -> -95.4 | J19: =I19*(1+J$29) -> -100.647 | K19: =J19*(1+K$29) -> -105.67935 | L19: =K19*(1+L$29) -> -110.43492 | M19: =L19*(1+M$29) -> -114.85232
B20: × (1 − tax rate) | D20: =1-$C$10 -> 0.76 | E20: =1-$C$10 -> 0.76 | F20: =1-$C$10 -> 0.76 | G20: =1-$C$10 -> 0.76 | H20: =1-$C$10 -> 0.76 | I20: =1-$C$10 -> 0.76 | J20: =1-$C$10 -> 0.76 | K20: =1-$C$10 -> 0.76 | ... M20: =1-$C$10 -> 0.76
B21: NOPAT = (Adj. EBIT − SBC) × (1 − t) | D21: =(D18+D19)*D20 -> 938.15006 | E21: =(E18+E19)*E20 -> 990.77758 | F21: =(F18+F19)*F20 -> 1057.9587 | G21: =(G18+G19)*G20 -> 1123.9999 | H21: =(H18+H19)*H20 -> 1193.9831 | I21: =(I18+I19)*I20 -> 1265.6221 | J21: =(J18+J19)*J20 -> 1335.2313 | K21: =(K18+K19)*K20 -> 1401.9928 | ... M21: =(M18+M19)*M20 -> 1523.6858
B22: plus adjusted D&A (ex acquired-intangible amortization) | D22: =Model!CO86 -> 216.39203 | E22: =Model!CP86 -> 226.26776 | F22: =Model!CQ86 -> 237.07187 | G22: =Model!CR86 -> 247.24165 | H22: =Model!CS86 -> 257.84948 | I22: =H22*(1+I$29) -> 273.32045 | J22: =I22*(1+J$29) -> 288.35307 | K22: =J22*(1+K$29) -> 302.77073 | L22: =K22*(1+L$29) -> 316.39541 | M22: =L22*(1+M$29) -> 329.05123
B23: − Capex (PP&E + intangibles, net of disposal proceeds) | D23: =Model!CO229+Model!CO230+Model!CO231 -> -371.7 | E23: =Model!CP229+Model!CP230+Model!CP231 -> -381.49796 | F23: =Model!CQ229+Model!CQ230+Model!CQ231 -> -385.93095 | G23: =Model!CR229+Model!CR230+Model!CR231 -> -388.1119 | H23: =Model!CS229+Model!CS230+Model!CS231 -> -389.77247 | I23: =H23*(1+I$29) -> -413.15882 | J23: =I23*(1+J$29) -> -435.88255 | K23: =J23*(1+K$29) -> -457.67668 | L23: =K23*(1+L$29) -> -478.27213 | M23: =L23*(1+M$29) -> -497.40302
B24: − Δ Working capital (CF statement) | D24: =Model!CO227 -> -3.9020033 | E24: =Model!CP227 -> 12.67825 | F24: =Model!CQ227 -> 18.686547 | G24: =Model!CR227 -> 17.57632 | H24: =Model!CS227 -> 18.326948 | I24: =H24*(1+I$29) -> 19.426565 | J24: =I24*(1+J$29) -> 20.495026 | K24: =J24*(1+K$29) -> 21.519777 | L24: =K24*(1+L$29) -> 22.488167 | M24: =L24*(1+M$29) -> 23.387694
B25: Unlevered FCF | D25: =D21+D22+D23+D24 -> 778.94008 | E25: =E21+E22+E23+E24 -> 848.22562 | F25: =F21+F22+F23+F24 -> 927.78616 | G25: =G21+G22+G23+G24 -> 1000.706 | H25: =H21+H22+H23+H24 -> 1080.387 | I25: =I21+I22+I23+I24 -> 1145.2103 | J25: =J21+J22+J23+J24 -> 1208.1968 | K25: =K21+K22+K23+K24 -> 1268.6067 | ... M25: =M21+M22+M23+M24 -> 1378.7217 | N25: =M25*(1+$C$30) -> 1420.0834
B26: Terminal Value (Gordon Growth) | N26: =N25/($C$13-$C$30) -> 23786.991
B29: Fade-period growth (2031E–35E) | I29: 0.06 | J29: 0.055 | K29: 0.05 | L29: 0.045 | M29: 0.04
B30: Terminal growth rate | C30: 0.03
B32: Discount period (years) | D32: =(DATE(2026,12,31)-$C$15)/365.25 -> 0.24366872 | E32: =(DATE(2027,12,31)-$C$15)/365.25 -> 1.2429843 | F32: =(DATE(2028,12,31)-$C$15)/365.25 -> 2.2450376 | G32: =(DATE(2029,12,31)-$C$15)/365.25 -> 3.2443532 | H32: =(DATE(2030,12,31)-$C$15)/365.25 -> 4.2436687 | I32: =(DATE(2031,12,31)-$C$15)/365.25 -> 5.2429843 | J32: =(DATE(2032,12,31)-$C$15)/365.25 -> 6.2450376 | K32: =(DATE(2033,12,31)-$C$15)/365.25 -> 7.2443532 | L32: =(DATE(2034,12,31)-$C$15)/365.25 -> 8.2436687 | M32: =(DATE(2035,12,31)-$C$15)/365.25 -> 9.2429843 | N32: =M32 -> 9.2429843
B33: Discount factor | D33: =1/(1+$C$13)^D32 -> 0.97928581 | E33: =1/(1+$C$13)^E32 -> 0.89872753 | F33: =1/(1+$C$13)^F32 -> 0.8246022 | G33: =1/(1+$C$13)^G32 -> 0.75676855 | H33: =1/(1+$C$13)^H32 -> 0.69451505 | I33: =1/(1+$C$13)^I32 -> 0.63738266 | J33: =1/(1+$C$13)^J32 -> 0.58481255 | K33: =1/(1+$C$13)^K32 -> 0.53670454 | ... N33: =1/(1+$C$13)^N32 -> 0.45203539
B34: PV of UFCF | D34: =D25*D33 -> 762.80497 | E34: =E25*E33 -> 762.32372 | F34: =F25*F33 -> 765.05451 | G34: =G25*G33 -> 757.3028 | H34: =H25*H33 -> 750.34505 | I34: =I25*I33 -> 729.93716 | J34: =J25*J33 -> 706.56867 | K34: =K25*K33 -> 680.86696 | ... M34: =M25*M33 -> 623.23102 | N34: =N26*N33 -> 10752.562
D35: SBC is deducted as an economic cost (RB Global adds it back in adjusted EBITDA / EPS). Acquired-intangible amortization is non-cash and excluded; operating-lease costs sit inside adjusted EBITDA (lease liabilities therefore not deducted as debt).
B37: 3. VALUATION SUMMARY
B38: Sum of PV (explicit + fade) | C38: =SUM(D34:M34) -> 7191.4107
B39: PV of Terminal Value | C39: =N34 -> 10752.562
B40: Enterprise Value | C40: =C38+C39 -> 17943.973
B41: Less: adjusted net debt (Model 2026E YE) | C41: =Model!CO376 -> 2167.1119
B42: Less: Series A preferred, redeemable NCI & NCI (Model 2026E) | C42: =Model!CO385 -> 483.9
B43: Equity Value | C43: =C40-C41-C42 -> 15292.961
B44: Diluted shares (m, Model 2026E) | C44: =Model!CO127 -> 186.1125
B45: Implied share price ($) | C45: =C43/C44 -> 82.170519
B46: Current share price ($) | C46: =Model!CO381 -> 80
B47: Implied upside / (downside) | C47: =C45/C46-1 -> 0.027131489
B50: 4. SENSITIVITY: IMPLIED PRICE ($) — WACC × Terminal Growth
B52: WACC (across):
B53: g (down) / WACC | D53: 0.07 | E53: 0.075 | F53: 0.08 | G53: 0.085 | H53: 0.09
B54: 0.02 | D54: =IFERROR((SUMPRODUCT($D$25:$M$25/(1+D$53)^$D$32:$M$32)+($M$25*(1+$B54)/(D$53-$B54))/(1+D$53)^$M$32-$C$41-$C$42)/$C$44,"") -> 108.66662 | E54: =IFERROR((SUMPRODUCT($D$25:$M$25/(1+E$53)^$D$32:$M$32)+($M$25*(1+$B54)/(E$53-$B54))/(1+E$53)^$M$32-$C$41-$C$42)/$C$44,"") -> 97.305837 | F54: =IFERROR((SUMPRODUCT($D$25:$M$25/(1+F$53)^$D$32:$M$32)+($M$25*(1+$B54)/(F$53-$B54))/(1+F$53)^$M$32-$C$41-$C$42)/$C$44,"") -> 87.849918 | G54: =IFERROR((SUMPRODUCT($D$25:$M$25/(1+G$53)^$D$32:$M$32)+($M$25*(1+$B54)/(G$53-$B54))/(1+G$53)^$M$32-$C$41-$C$42)/$C$44,"") -> 79.858905 | H54: =IFERROR((SUMPRODUCT($D$25:$M$25/(1+H$53)^$D$32:$M$32)+($M$25*(1+$B54)/(H$53-$B54))/(1+H$53)^$M$32-$C$41-$C$42)/$C$44,"") -> 73.018555
B55: 0.025 | D55: =IFERROR((SUMPRODUCT($D$25:$M$25/(1+D$53)^$D$32:$M$32)+($M$25*(1+$B55)/(D$53-$B55))/(1+D$53)^$M$32-$C$41-$C$42)/$C$44,"") -> 118.09156 | E55: =IFERROR((SUMPRODUCT($D$25:$M$25/(1+E$53)^$D$32:$M$32)+($M$25*(1+$B55)/(E$53-$B55))/(1+E$53)^$M$32-$C$41-$C$42)/$C$44,"") -> 104.72643 | F55: =IFERROR((SUMPRODUCT($D$25:$M$25/(1+F$53)^$D$32:$M$32)+($M$25*(1+$B55)/(F$53-$B55))/(1+F$53)^$M$32-$C$41-$C$42)/$C$44,"") -> 93.801681 | G55: =IFERROR((SUMPRODUCT($D$25:$M$25/(1+G$53)^$D$32:$M$32)+($M$25*(1+$B55)/(G$53-$B55))/(1+G$53)^$M$32-$C$41-$C$42)/$C$44,"") -> 84.706873 | H55: =IFERROR((SUMPRODUCT($D$25:$M$25/(1+H$53)^$D$32:$M$32)+($M$25*(1+$B55)/(H$53-$B55))/(1+H$53)^$M$32-$C$41-$C$42)/$C$44,"") -> 77.019418
B56: 0.03 | D56: =IFERROR((SUMPRODUCT($D$25:$M$25/(1+D$53)^$D$32:$M$32)+($M$25*(1+$B56)/(D$53-$B56))/(1+D$53)^$M$32-$C$41-$C$42)/$C$44,"") -> 129.87274 | E56: =IFERROR((SUMPRODUCT($D$25:$M$25/(1+E$53)^$D$32:$M$32)+($M$25*(1+$B56)/(E$53-$B56))/(1+E$53)^$M$32-$C$41-$C$42)/$C$44,"") -> 113.79605 | F56: =IFERROR((SUMPRODUCT($D$25:$M$25/(1+F$53)^$D$32:$M$32)+($M$25*(1+$B56)/(F$53-$B56))/(1+F$53)^$M$32-$C$41-$C$42)/$C$44,"") -> 100.9438 | G56: =IFERROR((SUMPRODUCT($D$25:$M$25/(1+G$53)^$D$32:$M$32)+($M$25*(1+$B56)/(G$53-$B56))/(1+G$53)^$M$32-$C$41-$C$42)/$C$44,"") -> 90.436289 | H56: =IFERROR((SUMPRODUCT($D$25:$M$25/(1+H$53)^$D$32:$M$32)+($M$25*(1+$B56)/(H$53-$B56))/(1+H$53)^$M$32-$C$41-$C$42)/$C$44,"") -> 81.687091
B57: 0.035 | D57: =IFERROR((SUMPRODUCT($D$25:$M$25/(1+D$53)^$D$32:$M$32)+($M$25*(1+$B57)/(D$53-$B57))/(1+D$53)^$M$32-$C$41-$C$42)/$C$44,"") -> 145.01996 | E57: =IFERROR((SUMPRODUCT($D$25:$M$25/(1+E$53)^$D$32:$M$32)+($M$25*(1+$B57)/(E$53-$B57))/(1+E$53)^$M$32-$C$41-$C$42)/$C$44,"") -> 125.13308 | F57: =IFERROR((SUMPRODUCT($D$25:$M$25/(1+F$53)^$D$32:$M$32)+($M$25*(1+$B57)/(F$53-$B57))/(1+F$53)^$M$32-$C$41-$C$42)/$C$44,"") -> 109.67305 | G57: =IFERROR((SUMPRODUCT($D$25:$M$25/(1+G$53)^$D$32:$M$32)+($M$25*(1+$B57)/(G$53-$B57))/(1+G$53)^$M$32-$C$41-$C$42)/$C$44,"") -> 97.311588 | H57: =IFERROR((SUMPRODUCT($D$25:$M$25/(1+H$53)^$D$32:$M$32)+($M$25*(1+$B57)/(H$53-$B57))/(1+H$53)^$M$32-$C$41-$C$42)/$C$44,"") -> 87.203432
B58: 0.04 | D58: =IFERROR((SUMPRODUCT($D$25:$M$25/(1+D$53)^$D$32:$M$32)+($M$25*(1+$B58)/(D$53-$B58))/(1+D$53)^$M$32-$C$41-$C$42)/$C$44,"") -> 165.21626 | E58: =IFERROR((SUMPRODUCT($D$25:$M$25/(1+E$53)^$D$32:$M$32)+($M$25*(1+$B58)/(E$53-$B58))/(1+E$53)^$M$32-$C$41-$C$42)/$C$44,"") -> 139.70925 | F58: =IFERROR((SUMPRODUCT($D$25:$M$25/(1+F$53)^$D$32:$M$32)+($M$25*(1+$B58)/(F$53-$B58))/(1+F$53)^$M$32-$C$41-$C$42)/$C$44,"") -> 120.58462 | G58: =IFERROR((SUMPRODUCT($D$25:$M$25/(1+G$53)^$D$32:$M$32)+($M$25*(1+$B58)/(G$53-$B58))/(1+G$53)^$M$32-$C$41-$C$42)/$C$44,"") -> 105.71473 | H58: =IFERROR((SUMPRODUCT($D$25:$M$25/(1+H$53)^$D$32:$M$32)+($M$25*(1+$B58)/(H$53-$B58))/(1+H$53)^$M$32-$C$41-$C$42)/$C$44,"") -> 93.823041
B61: 5. REVERSE DCF
B62: To solve for the market-implied path: Data ▸ What-If Analysis ▸ Goal Seek — set C45 to the current price (C46) by changing C30 (terminal growth) or the Model scenario levers (sector GTV growth, adjusted EBITDA margin).
B64: 6. MAUBOUSSIN EV / NOPAT — TWO-STAGE FRAMEWORK
B65: EV/NOPAT = 1/r + [g × (1 − r/ROIIC) / (r × (r − g))] × [1 − ((1+g)/(1+r))^N]
B66: Formula source: Mauboussin & Rappaport, "Expectations Investing" (2021); Counterpoint Global, "What Does a Price-Earnings Multiple Mean?" (2020).
B68: Input | C68: Value | D68: Rationale (RB Global characteristics)
B69: r (Cost of capital / WACC) | C69: =$C$13 -> 0.0897 | D69: Linked from Section 1 WACC build
B70: g (NOPAT growth, Stage 1) | C70: 0.08 | D70: Model adjusted EBIT CAGR 2025–30E; GTV growth mid-single digit + margin expansion from IAA integration / marketplace scale
B71: ROIIC (Return on incremental invested capital) | C71: 0.15 | D71: Asset-light incremental growth (online marketplace, services) vs. goodwill-heavy base (IAA): reported ROIC ~5–8%, incremental much higher
B72: N (Years of value creation / CAP) | C72: 12 | D72: Two-sided marketplace network effects (largest buyer base for used heavy equipment; #2 US salvage auction duopoly with Copart)
B74: Calculation | C74: Value
B75: Steady-state component: 1 / r | C75: =1/C69 -> 11.148272
B76: Value-creation factor: 1 − r / ROIIC | C76: =1-C69/C71 -> 0.402
B77: Growth multiplier: g × (1 − r/ROIIC) / (r × (r − g)) | C77: =C70*C76/(C69*(C69-C70)) -> 36.961694
B78: Time decay: 1 − ((1+g)/(1+r))^N | C78: =1-((1+C70)/(1+C69))^C72 -> 0.10174084
B79: PVGO component (growth value) | C79: =C77*C78 -> 3.7605137
B80: Mauboussin EV / NOPAT (steady-state + PVGO) | C80: =C75+C79 -> 14.908786
B82: VALUATION — Applied to 2028E NOPAT | C82: USDm
B83: 2028E Adjusted EBIT (Model) | C83: =Model!CQ87 -> 1472.0509
B84: (−) 2028E stock-based compensation | C84: =-Model!CQ143 -> -80
B85: Tax rate (from WACC build) | C85: =$C$10 -> 0.24
B86: 2028E NOPAT = (EBIT − SBC) × (1 − t) | C86: =(C83+C84)*(1-C85) -> 1057.9587
B87: × Mauboussin EV/NOPAT multiple | C87: =C80 -> 14.908786
B88: Implied Enterprise Value (2028E basis) | C88: =C86*C87 -> 15772.88
B89: Less: YE2027 adjusted net debt + preferred / NCI (Model) | C89: =Model!CP376+Model!CP385 -> 2502.7441
B90: Implied Equity Value | C90: =C88-C89 -> 13270.135
B91: Diluted shares 2028E (m, Model) | C91: =Model!CQ127 -> 178.44351
B92: Implied share price 2028 ($) | C92: =C90/C91 -> 74.366032
B94: Current share price ($) | C94: =C46 -> 80
B95: Implied upside / (downside) | C95: =C92/C94-1 -> -0.070424605
B97: MARKET-IMPLIED EV/NOPAT TODAY | C97: USDm
B98: Current market cap (spot × diluted shares) | C98: =C46*C44 -> 14889
B99: Plus: YE2026 adjusted net debt, preferred & NCI | C99: =C41+C42 -> 2651.0119
B100: Implied Enterprise Value (today) | C100: =C98+C99 -> 17540.012
B101: RBA's market-implied EV/NOPAT (on 2028E NOPAT) | C101: =C100/C86 -> 16.579108
B103: Multiple gap (Mauboussin − Market) | C103: =C80-C101 -> -1.6703227
B104: Implied re-rating headroom | C104: =C80/C101-1 -> -0.10074864

Sheet Charts
B2: RB Global — Historical Operating Performance (2006–2025)
B3: All historicals · USDm · Linked to Model. M&A % reflects disclosed acquired revenue only (e.g. IronPlanet 2017, IAA 2023). Pre-2018 revenue on the legacy net (agency) basis; 2017+ ASC 606 gross basis.
C7: 2006 | D7: 2007 | E7: 2008 | F7: 2009 | G7: 2010 | H7: 2011 | I7: 2012 | J7: 2013 | K7: 2014 | L7: 2015 | M7: 2016 | N7: 2017 | O7: 2018 | P7: 2019 | Q7: 2020 | R7: 2021 | S7: 2022 | T7: 2023 | U7: 2024 | V7: 2025
B8: Organic % | C8: =IFERROR(Model!C199+0,0) -> 0 | D8: =IFERROR(Model!D199+0,0) -> 0.20960843 | E8: =IFERROR(Model!E199+0,0) -> 0.13757991 | F8: =IFERROR(Model!F199+0,0) -> 0.063111229 | G8: =IFERROR(Model!G199+0,0) -> -0.052601859 | H8: =IFERROR(Model!H199+0,0) -> 0.10837538 | I8: =IFERROR(Model!I199+0,0) -> 0.08097723 | J8: =IFERROR(Model!O199+0,0) -> 0.067239785 | K8: =IFERROR(Model!U199+0,0) -> 0.029298058 | L8: =IFERROR(Model!AA199+0,0) -> 0.072288956 | M8: =IFERROR(Model!AG199+0,0) -> 0.0979307 | N8: =IFERROR(Model!AM199+0,0) -> 0.71468851 | O8: =IFERROR(Model!AS199+0,0) -> 0.20473316 | P8: =IFERROR(Model!AY199+0,0) -> 0.12701854 | Q8: =IFERROR(Model!BE199+0,0) -> 0.044454101 | R8: =IFERROR(Model!BK199+0,0) -> 0.0075592118 | S8: =IFERROR(Model!BQ199+0,0) -> 0.22360161 | T8: =IFERROR(Model!BW199+0,0) -> 0.10894632 | U8: =IFERROR(Model!CC199+0,0) -> 0.16431134 | V8: =IFERROR(Model!CI199+0,0) -> 0.071541945
B9: M&A % | C9: =IFERROR(Model!C200+0,0) -> 0 | D9: =IFERROR(Model!D200+0,0) -> 0 | E9: =IFERROR(Model!E200+0,0) -> 0 | F9: =IFERROR(Model!F200+0,0) -> 0 | G9: =IFERROR(Model!G200+0,0) -> 0 | H9: =IFERROR(Model!H200+0,0) -> 0 | I9: =IFERROR(Model!I200+0,0) -> 0.024693322 | J9: =IFERROR(Model!O200+0,0) -> 0 | K9: =IFERROR(Model!U200+0,0) -> 0 | L9: =IFERROR(Model!AA200+0,0) -> 0 | M9: =IFERROR(Model!AG200+0,0) -> 0 | N9: =IFERROR(Model!AM200+0,0) -> 0 | O9: =IFERROR(Model!AS200+0,0) -> 0 | P9: =IFERROR(Model!AY200+0,0) -> 0 | Q9: =IFERROR(Model!BE200+0,0) -> 0 | R9: =IFERROR(Model!BK200+0,0) -> 0.021274124 | S9: =IFERROR(Model!BQ200+0,0) -> 0 | T9: =IFERROR(Model!BW200+0,0) -> 1.0133187 | U9: =IFERROR(Model!CC200+0,0) -> 0 | V9: =IFERROR(Model!CI200+0,0) -> 0
C11: =C7 -> 2006 | D11: =D7 -> 2007 | E11: =E7 -> 2008 | F11: =F7 -> 2009 | G11: =G7 -> 2010 | H11: =H7 -> 2011 | I11: =I7 -> 2012 | J11: =J7 -> 2013 | ... V11: =V7 -> 2025
B12: Adjusted EBITDA | C12: =Model!C80 -> 101.591 | D12: =Model!D80 -> 125.125 | E12: =Model!E80 -> 159.913 | F12: =Model!F80 -> 161.428 | G12: =Model!G80 -> 131.352 | H12: =Model!H80 -> 153.638 | I12: =Model!I80 -> 157.593 | J12: =Model!O80 -> 175 | K12: =Model!U80 -> 182.8 | L12: =Model!AA80 -> 212.386 | M12: =Model!AG80 -> 210.086 | N12: =Model!AM80 -> 191.524 | O12: =Model!AS80 -> 257.331 | P12: =Model!AY80 -> 314.814 | Q12: =Model!BE80 -> 374.295 | R12: =Model!BK80 -> 385.324 | S12: =Model!BQ80 -> 465.215 | T12: =Model!BW80 -> 1032.8 | U12: =Model!CC80 -> 1302.7 | V12: =Model!CI80 -> 1399.7
B13: Operating Income (GAAP) | C13: =Model!C106 -> 85.946 | D13: =Model!D106 -> 101.435 | E13: =Model!E106 -> 122.118 | F13: =Model!F106 -> 127.895 | G13: =Model!G106 -> 91.765 | H13: =Model!H106 -> 107.573 | I13: =Model!I106 -> 117.965 | J13: =Model!O106 -> 136.931 | K13: =Model!U106 -> 125.885 | L13: =Model!AA106 -> 172.518 | M13: =Model!AG106 -> 137.153 | N13: =Model!AM106 -> 110.013 | O13: =Model!AS106 -> 184.977 | P13: =Model!AY106 -> 220.265 | Q13: =Model!BE106 -> 264.772 | R13: =Model!BK106 -> 240.939 | S13: =Model!BQ106 -> 453.591 | T13: =Model!BW106 -> 471.3 | U13: =Model!CC106 -> 761.2 | V13: =Model!CI106 -> 713.4
B14: Adj. EBITDA Margin % | C14: =Model!C209 -> 0.39398194 | D14: =Model!D209 -> 0.40116253 | E14: =Model!E209 -> 0.45069021 | F14: =Model!F209 -> 0.42795146 | G14: =Model!G209 -> 0.36755287 | H14: =Model!H209 -> 0.38787778 | I14: =Model!I209 -> 0.35983834 | J14: =Model!O209 -> 0.37440924 | K14: =Model!U209 -> 0.37996496 | L14: =Model!AA209 -> 0.41170051 | M14: =Model!AG209 -> 0.37091782 | N14: =Model!AM209 -> 0.19720529 | O14: =Model!AS209 -> 0.21993614 | P14: =Model!AY209 -> 0.23874125 | Q14: =Model!BE209 -> 0.27176786 | R14: =Model!BK209 -> 0.27193499 | S14: =Model!BQ209 -> 0.26831979 | T14: =Model!BW209 -> 0.28068268 | U14: =Model!CC209 -> 0.30407077 | V14: =Model!CI209 -> 0.30489904
B15: GAAP Op. Margin % | C15: =Model!C210 -> 0.33330877 | D15: =Model!D210 -> 0.32521016 | E15: =Model!E210 -> 0.34417081 | F15: =Model!F210 -> 0.33905427 | G15: =Model!G210 -> 0.25677941 | H15: =Model!H210 -> 0.27158109 | I15: =Model!I210 -> 0.26935416 | J15: =Model!O210 -> 0.29296132 | K15: =Model!U210 -> 0.26166241 | L15: =Model!AA210 -> 0.33441822 | M15: =Model!AG210 -> 0.2421508 | N15: =Model!AM210 -> 0.11327638 | O15: =Model!AS210 -> 0.15809649 | P15: =Model!AY210 -> 0.1670394 | Q15: =Model!BE210 -> 0.19224547 | R15: =Model!BK210 -> 0.17003806 | S15: =Model!BQ210 -> 0.26161547 | T15: =Model!BW210 -> 0.12808457 | U15: =Model!CC210 -> 0.17767611 | V15: =Model!CI210 -> 0.15540114
C17: =C7 -> 2006 | D17: =D7 -> 2007 | E17: =E7 -> 2008 | F17: =F7 -> 2009 | G17: =G7 -> 2010 | H17: =H7 -> 2011 | I17: =I7 -> 2012 | J17: =J7 -> 2013 | ... V17: =V7 -> 2025
B18: ROIC | C18: =IFERROR(Model!C356+0,NA()) -> 0.22424826 | D18: =IFERROR(Model!D356+0,NA()) -> 0.21759541 | E18: =IFERROR(Model!E356+0,NA()) -> 0.23134292 | F18: =IFERROR(Model!F356+0,NA()) -> 0.16532726 | G18: =IFERROR(Model!G356+0,NA()) -> 0.10481234 | H18: =IFERROR(Model!H356+0,NA()) -> 0.12046844 | I18: =IFERROR(Model!I356+0,NA()) -> 0.11506653 | J18: =IFERROR(Model!O356+0,NA()) -> 0.14383876 | K18: =IFERROR(Model!U356+0,NA()) -> 0.14413993 | L18: =IFERROR(Model!AA356+0,NA()) -> 0.2116185 | M18: =IFERROR(Model!AG356+0,NA()) -> 0.10949277 | N18: =IFERROR(Model!AM356+0,NA()) -> 0.1034524 | O18: =IFERROR(Model!AS356+0,NA()) -> 0.11423636 | P18: =IFERROR(Model!AY356+0,NA()) -> 0.17297738 | Q18: =IFERROR(Model!BE356+0,NA()) -> 0.16538527 | R18: =IFERROR(Model!BK356+0,NA()) -> 0.0967494 | S18: =IFERROR(Model!BQ356+0,NA()) -> 0.22482019 | T18: =IFERROR(Model!BW356+0,NA()) -> 0.082450537 | U18: =IFERROR(Model!CC356+0,NA()) -> 0.10851456 | V18: =IFERROR(Model!CI356+0,NA()) -> 0.11950879
B19: RONTA | C19: =IFERROR(Model!C368+0,NA()) -> 0.14113507 | D19: =IFERROR(Model!D368+0,NA()) -> 0.15897151 | E19: =IFERROR(Model!E368+0,NA()) -> 0.19582998 | F19: =IFERROR(Model!F368+0,NA()) -> 0.14193998 | G19: =IFERROR(Model!G368+0,NA()) -> 0.098495413 | H19: =IFERROR(Model!H368+0,NA()) -> 0.10616201 | I19: =IFERROR(Model!I368+0,NA()) -> 0.10176924 | J19: =IFERROR(Model!O368+0,NA()) -> 0.11725123 | K19: =IFERROR(Model!U368+0,NA()) -> 0.1327015 | L19: =IFERROR(Model!AA368+0,NA()) -> 0.17896063 | M19: =IFERROR(Model!AG368+0,NA()) -> 0.10099073 | N19: =IFERROR(Model!AM368+0,NA()) -> 0.18741801 | O19: =IFERROR(Model!AS368+0,NA()) -> 0.20868254 | P19: =IFERROR(Model!AY368+0,NA()) -> 0.24500246 | Q19: =IFERROR(Model!BE368+0,NA()) -> 0.31493369 | R19: =IFERROR(Model!BK368+0,NA()) -> 0.14031296 | S19: =IFERROR(Model!BQ368+0,NA()) -> 0.38071221 | T19: =IFERROR(Model!BW368+0,NA()) -> 0.20219346 | U19: =IFERROR(Model!CC368+0,NA()) -> 0.25559468 | V19: =IFERROR(Model!CI368+0,NA()) -> 0.26722621
B20: Adj. EBITDA margin % | C20: =IFERROR(Model!C209+0,NA()) -> 0.39398194 | D20: =IFERROR(Model!D209+0,NA()) -> 0.40116253 | E20: =IFERROR(Model!E209+0,NA()) -> 0.45069021 | F20: =IFERROR(Model!F209+0,NA()) -> 0.42795146 | G20: =IFERROR(Model!G209+0,NA()) -> 0.36755287 | H20: =IFERROR(Model!H209+0,NA()) -> 0.38787778 | I20: =IFERROR(Model!I209+0,NA()) -> 0.35983834 | J20: =IFERROR(Model!O209+0,NA()) -> 0.37440924 | K20: =IFERROR(Model!U209+0,NA()) -> 0.37996496 | L20: =IFERROR(Model!AA209+0,NA()) -> 0.41170051 | M20: =IFERROR(Model!AG209+0,NA()) -> 0.37091782 | N20: =IFERROR(Model!AM209+0,NA()) -> 0.19720529 | O20: =IFERROR(Model!AS209+0,NA()) -> 0.21993614 | P20: =IFERROR(Model!AY209+0,NA()) -> 0.23874125 | Q20: =IFERROR(Model!BE209+0,NA()) -> 0.27176786 | R20: =IFERROR(Model!BK209+0,NA()) -> 0.27193499 | S20: =IFERROR(Model!BQ209+0,NA()) -> 0.26831979 | T20: =IFERROR(Model!BW209+0,NA()) -> 0.28068268 | U20: =IFERROR(Model!CC209+0,NA()) -> 0.30407077 | V20: =IFERROR(Model!CI209+0,NA()) -> 0.30489904
B21: Service take rate % | C21: =IFERROR(Model!C207+0,NA()) -> 0.094764726 | D21: =IFERROR(Model!D207+0,NA()) -> 0.097884094 | E21: =IFERROR(Model!E207+0,NA()) -> 0.099467924 | F21: =IFERROR(Model!F207+0,NA()) -> 0.10802083 | G21: =IFERROR(Model!G207+0,NA()) -> 0.10902806 | H21: =IFERROR(Model!H207+0,NA()) -> 0.10664217 | I21: =IFERROR(Model!I207+0,NA()) -> 0.11206653 | J21: =IFERROR(Model!O207+0,NA()) -> 0.12242831 | K21: =IFERROR(Model!U207+0,NA()) -> 0.11420318 | L21: =IFERROR(Model!AA207+0,NA()) -> 0.12144994 | M21: =IFERROR(Model!AG207+0,NA()) -> 0.13066186 | N21: =IFERROR(Model!AM207+0,NA()) -> 0.1397537 | O21: =IFERROR(Model!AS207+0,NA()) -> 0.15098511 | P21: =IFERROR(Model!AY207+0,NA()) -> 0.15640704 | Q21: =IFERROR(Model!BE207+0,NA()) -> 0.16107205 | R21: =IFERROR(Model!BK207+0,NA()) -> 0.16584215 | S21: =IFERROR(Model!BQ207+0,NA()) -> 0.1743449 | T21: =IFERROR(Model!BW207+0,NA()) -> 0.19615092 | U21: =IFERROR(Model!CC207+0,NA()) -> 0.21148333 | V21: =IFERROR(Model!CI207+0,NA()) -> 0.21615983

Sheet Sheet1
