Workbook

Sheet Model
CL1: SCENARIO SWITCH ▼ (Bull / Base / Bear) — drives all scenario-linked forecast drivers
B2: RBC Bearings Incorporated (NYSE: RBC) — 3-Statement Financial Model | CL2: Base
B3: US GAAP as reported · USD millions (per-share data in USD; shares in millions) · Fiscal years end on the Saturday nearest 31 March (FY2027 = 29-Mar-2026 – 3-Apr-2027, 53 weeks) · Source: RBC Bearings Forms 10-K / 10-Q, Form 8-K earnings releases (Ex. 99.1) and deal / financing 8-Ks, SEC EDGAR (CIK 1324948); XBRL company facts; investor-relations releases are the same documents as filed on EDGAR
B4: Basis notes: as originally reported (the FY2022 10-K/A restatement of FY2020–22 stock-based compensation is shown as memo rows). Segments: Roller / Plain / Ball / Other (Engineered Products from FY2016) to Q2 FY22; Aerospace & Defense / Industrial from Q3 FY22 (FY2021 and Q3 FY21–Q2 FY22 re-presented). Acquisitions: Sargent Apr-15, Dodge 1-Nov-21 (MCPS / notes / term loan), VACCO 18-Jul-25, PSC Couplings 10-Aug-26. Q2/27E calibrated to the Q2 FY27 outlook (31-Jul-2026), Δ carried to Q3–Q4/27E; Q4/27E has 14 weeks.
CN5: Forecast | CO5: Historical | CP5: Historical | CQ5: Historical
B6: (USDm) | C6: 2006 | D6: 2007 | E6: 2008 | F6: 2009 | G6: 2010 | H6: 2011 | I6: 2012 | J6: Q1/13 | K6: Q2/13 | L6: Q3/13 | M6: Q4/13 | N6: 2013 | O6: Q1/14 | P6: Q2/14 | Q6: Q3/14 | R6: Q4/14 | S6: 2014 | T6: Q1/15 | U6: Q2/15 | V6: Q3/15 | W6: Q4/15 | X6: 2015 | Y6: Q1/16 | Z6: Q2/16 | AA6: Q3/16 | AB6: Q4/16 | AC6: 2016 | AD6: Q1/17 | AE6: Q2/17 | AF6: Q3/17 | AG6: Q4/17 | AH6: 2017 | AI6: Q1/18 | AJ6: Q2/18 | AK6: Q3/18 | AL6: Q4/18 | AM6: 2018 | AN6: Q1/19 | AO6: Q2/19 | AP6: Q3/19 | AQ6: Q4/19 | AR6: 2019 | AS6: Q1/20 | AT6: Q2/20 | AU6: Q3/20 | AV6: Q4/20 | AW6: 2020 | AX6: Q1/21 | AY6: Q2/21 | AZ6: Q3/21 | BA6: Q4/21 | BB6: 2021 | BC6: Q1/22 | BD6: Q2/22 | BE6: Q3/22 | BF6: Q4/22 | BG6: 2022 | BH6: Q1/23 | BI6: Q2/23 | BJ6: Q3/23 | BK6: Q4/23 | BL6: 2023 | BM6: Q1/24 | BN6: Q2/24 | BO6: Q3/24 | BP6: Q4/24 | BQ6: 2024 | BR6: Q1/25 | BS6: Q2/25 | BT6: Q3/25 | BU6: Q4/25 | BV6: 2025 | BW6: Q1/26 | BX6: Q2/26 | BY6: Q3/26 | BZ6: Q4/26 | CA6: 2026 | CB6: Q1/27 | CC6: Q2/27E | CD6: Q3/27E | CE6: Q4/27E | CF6: 2027E | CG6: 2028E | CH6: 2029E | CI6: 2030E | CJ6: 2031E | CK6: 2032E | CL6: Modelling Notes | CN6: 5Y CAGR | CO6: 5Y CAGR | CP6: 10Y CAGR | CQ6: 20Y CAGR
CN7: 27-'32 | CO7: 21-'26 | CP7: 16-'26 | CQ7: 06-'26
B8: SEGMENT P&L — AEROSPACE & DEFENSE · INDUSTRIAL (external net sales × segment gross margin) | CL8: SEGMENT BUILD — modelling logic (segment net sales → segment gross margin (the CODM measure) → − SG&A − other, net = operating income → GAAP P&L)
CT9: SCENARIO INPUT TABLE — driver assumptions per Bull / Base / Bear | CU9: Bull | CV9: Base | CW9: Bear | CX9: Bull / Bear = Base + Δ (Δ inputs on each block header). Outlook block = high / mid / low end of the Q2 FY27 guidance ranges.
B10: Aerospace & Defense (bearings, precision components and systems for commercial aerospace, defense aerospace / marine / ground, missiles, space; VACCO from 18-Jul-2025) | CL10: AEROSPACE & DEFENSE — modelling logic
B11: Aerospace & Defense — segment net external sales | AZ11: 93.267 | BA11: 96.389 | BB11: 396.222 | BC11: 90.365 | BD11: 92.915 | BE11: 93.203 | BF11: 104.985 | BG11: 381.468 | BH11: 99.399 | BI11: 103.548 | BJ11: 105.532 | BK11: 121.828 | BL11: 430.307 | BM11: 120.472 | BN11: 127.271 | BO11: 129.293 | BP11: 142.313 | BQ11: 519.349 | BR11: 149.1 | BS11: 143.2 | BT11: 143.2 | BU11: 157.3 | BV11: 592.8 | BW11: 164.6 | BX11: 198.8 | BY11: 202.5 | BZ11: 222.1 | CA11: 788 | CB11: 225.4 | CC11: =BX11*(1+CC12)*CC34+CC14 -> 234.90051 | CD11: =BY11*(1+CD12)*CD34+CD14 -> 231.22537 | CE11: =BZ11*(1+CE12)*CE34+CE14 -> 273.11383 | CF11: =SUM(CB11:CE11) -> 964.63971 | CG11: =CF11*(1+CG12) -> 1070.7501 | CH11: =CG11*(1+CH12) -> 1177.8251 | CI11: =CH11*(1+CI12) -> 1283.8293 | CJ11: =CI11*(1+CJ12) -> 1386.5357 | CK11: =CJ11*(1+CK12) -> 1483.5932 | CL11: Release segment data (Aerospace & Defense / Industrial from the Q3 FY22 release; FY2021 and Q3 FY21–Q2 FY22 from the re-presented comparatives). Q2–Q4/27E: prior-year quarter × (1 + organic growth) × week factor + acquired sales not in the prior-year base. FY2028E+: prior year × (1 + scenario growth). | CN11: =IFERROR((CK11/CF11)^(1/5)-1,"n/m") -> 0.089908248 | CO11: =IFERROR((CA11/BB11)^(1/5)-1,"n/m") -> 0.14740708 | CP11: =IFERROR((CA11/AC11)^(1/10)-1,"n/m") -> n/m | CQ11: =IFERROR((CA11/C11)^(1/20)-1,"n/m") -> n/m | CT11: Q2 FY27 guidance — Q1 FY27 release (31-Jul-2026) | CU11: High | CV11: Mid | CW11: Low | CX11: Net sales approximately $505.0 to $515.0 million in Q2 FY27 (vs $455.3 million, +10.9% to 13.1%); gross margin 45.5% to 45.75%; SG&A 16.5% to 16.75% of net sales. RBC guides one quarter ahead; no full-year guidance is published.
B12: y/y % (Q2–Q4/27E: organic, before acquired sales) | D12: =IF(AND(ISNUMBER(D11),ISNUMBER(C11)),IFERROR(D11/C11-1,""),"") | E12: =IF(AND(ISNUMBER(E11),ISNUMBER(D11)),IFERROR(E11/D11-1,""),"") | F12: =IF(AND(ISNUMBER(F11),ISNUMBER(E11)),IFERROR(F11/E11-1,""),"") | G12: =IF(AND(ISNUMBER(G11),ISNUMBER(F11)),IFERROR(G11/F11-1,""),"") | H12: =IF(AND(ISNUMBER(H11),ISNUMBER(G11)),IFERROR(H11/G11-1,""),"") | I12: =IF(AND(ISNUMBER(I11),ISNUMBER(H11)),IFERROR(I11/H11-1,""),"") | N12: =IF(AND(ISNUMBER(N11),ISNUMBER(I11)),IFERROR(N11/I11-1,""),"") | O12: =IF(AND(ISNUMBER(O11),ISNUMBER(J11)),IFERROR(O11/J11-1,""),"") | P12: =IF(AND(ISNUMBER(P11),ISNUMBER(K11)),IFERROR(P11/K11-1,""),"") | Q12: =IF(AND(ISNUMBER(Q11),ISNUMBER(L11)),IFERROR(Q11/L11-1,""),"") | R12: =IF(AND(ISNUMBER(R11),ISNUMBER(M11)),IFERROR(R11/M11-1,""),"") | S12: =IF(AND(ISNUMBER(S11),ISNUMBER(N11)),IFERROR(S11/N11-1,""),"") | T12: =IF(AND(ISNUMBER(T11),ISNUMBER(O11)),IFERROR(T11/O11-1,""),"") | U12: =IF(AND(ISNUMBER(U11),ISNUMBER(P11)),IFERROR(U11/P11-1,""),"") | ... CB12: =IF(AND(ISNUMBER(CB11),ISNUMBER(BW11)),IFERROR(CB11/BW11-1,""),"") -> 0.36938032 | CC12: =CC13+$CC$74 -> 0.14185367 | CD12: =CD13+$CC$74 -> 0.14185367 | CE12: =CE13+$CC$74 -> 0.14185367 | CF12: =IF(AND(ISNUMBER(CF11),ISNUMBER(CA11)),IFERROR(CF11/CA11-1,""),"") -> 0.22416206 | CG12: =CHOOSE(MATCH($CL$2,{"Bull","Base","Bear"},0),$CU$27,$CV$27,$CW$27) -> 0.11 | CH12: =CHOOSE(MATCH($CL$2,{"Bull","Base","Bear"},0),$CU$28,$CV$28,$CW$28) -> 0.1 | CI12: =CHOOSE(MATCH($CL$2,{"Bull","Base","Bear"},0),$CU$29,$CV$29,$CW$29) -> 0.09 | CJ12: =CHOOSE(MATCH($CL$2,{"Bull","Base","Bear"},0),$CU$30,$CV$30,$CW$30) -> 0.08 | CK12: =CHOOSE(MATCH($CL$2,{"Bull","Base","Bear"},0),$CU$31,$CV$31,$CW$31) -> 0.07 | CL12: Q2–Q4/27E: Q1 FY27 organic y/y + the Q2 sales-guidance calibration Δ (solved in Q2/27E, carried into Q3–Q4). FY2028E+: scenario lever. | CT12: Q2 FY27 net sales ($m) | CU12: 515 | CV12: 510 | CW12: 505 | CX12: Guided ~$505–515m. Drives the Q2/27E sales calibration (Δ carried into Q3–Q4).
B13: Q2–Q4/27E organic growth before calibration (Q1 FY27 organic y/y) | CC13: =IFERROR((SUM(CB11:CB11)-SUM(CB14:CB14))/SUM(BW11:BW11)-1,0) -> 0.16038882 | CD13: =IFERROR((SUM(CB11:CB11)-SUM(CB14:CB14))/SUM(BW11:BW11)-1,0) -> 0.16038882 | CE13: =IFERROR((SUM(CB11:CB11)-SUM(CB14:CB14))/SUM(BW11:BW11)-1,0) -> 0.16038882 | CT13: Q2 FY27 gross margin % | CU13: 0.4575 | CV13: 0.45625 | CW13: 0.455 | CX13: Guided 45.5–45.75%. Drives the Q2/27E segment gross-margin calibration (Δ carried).
B14: Acquired sales not in the prior-year base (VACCO / PSC Couplings; input) | CB14: 34.4 | CC14: 7.9 | CD14: 0 | CE14: 0 | CL14: Q1 FY27: VACCO $34.4m (release: "$34.4 of net sales this quarter came from VACCO, which we acquired on July 18, 2025"; not in the Q1 FY26 base). Q2/27E: VACCO sales for the ~3 weeks before the 18-Jul anniversary that are not in the Q2 FY26 base = $34.4m × 3/13 (assumption). Q3–Q4: nil. | CT14: Q2 FY27 SG&A % of net sales (Bull = low end) | CU14: 0.165 | CV14: 0.16625 | CW14: 0.1675 | CX14: Guided 16.5–16.75%. Applied directly in Q2/27E.
B15: % of total net sales | C15: =IF(AND(ISNUMBER(C11),ISNUMBER(C65)),IFERROR(C11/C65,""),"") | D15: =IF(AND(ISNUMBER(D11),ISNUMBER(D65)),IFERROR(D11/D65,""),"") | E15: =IF(AND(ISNUMBER(E11),ISNUMBER(E65)),IFERROR(E11/E65,""),"") | F15: =IF(AND(ISNUMBER(F11),ISNUMBER(F65)),IFERROR(F11/F65,""),"") | G15: =IF(AND(ISNUMBER(G11),ISNUMBER(G65)),IFERROR(G11/G65,""),"") | H15: =IF(AND(ISNUMBER(H11),ISNUMBER(H65)),IFERROR(H11/H65,""),"") | I15: =IF(AND(ISNUMBER(I11),ISNUMBER(I65)),IFERROR(I11/I65,""),"") | J15: =IF(AND(ISNUMBER(J11),ISNUMBER(J65)),IFERROR(J11/J65,""),"") | ... CK15: =IF(AND(ISNUMBER(CK11),ISNUMBER(CK65)),IFERROR(CK11/CK65,""),"") -> 0.42117003 | CN15: =IFERROR(AVERAGE(CG15,CH15,CI15,CJ15,CK15),"n/m") -> 0.43508658 | CO15: =IFERROR(AVERAGE(BG15,BL15,BQ15,BV15,CA15),"n/m") -> 0.36274884 | CP15: =IFERROR(AVERAGE(AH15,AM15,AR15,AW15,BB15,BG15,BL15,BQ15,BV15,CA15),"n/m") -> 0.41072869 | CQ15: =IFERROR(AVERAGE(C15,D15,E15,F15,G15,H15,I15,N15,S15,X15,AC15,AH15,AM15,AR15,AW15,BB15,BG15,BL15,BQ15,BV15,CA15),"n/m") -> 0.41072869
B16: Aerospace & Defense segment gross margin | AZ16: 38.056 | BA16: 39.23 | BB16: 161.19 | BC16: 38.632 | BD16: 36.58 | BE16: 37.486 | BF16: 42.461 | BG16: 155.127 | BH16: 38.6 | BI16: 41.033 | BJ16: 41.65 | BK16: 49.717 | BL16: 171 | BM16: 47.3 | BN16: 50.6 | BO16: 53.3 | BP16: 57.6 | BQ16: 208.8 | BR16: 63.1 | BS16: 56.8 | BT16: 57.9 | BU16: 65.3 | BV16: 243.1 | BW16: 70.2 | BX16: 76.9 | BY16: 81.2 | BZ16: 92.4 | CA16: 320.7 | CB16: 100.2 | CC16: =CC11*CC17 -> 92.135539 | CD16: =CD11*CD17 -> 93.969737 | CE16: =CE11*CE17 -> 115.10111 | CF16: =SUM(CB16:CE16) -> 401.40639 | CG16: =CG11*CG17 -> 471.13003 | CH16: =CH11*CH17 -> 524.13216 | CI16: =CI11*CI17 -> 577.7232 | CJ16: =CJ11*CJ17 -> 626.71413 | CK16: =CK11*CK17 -> 675.0349 | CL16: 10-Q / 10-K segment note (segment gross margin is the CODM measure; Q4 = fiscal year − nine months). Forecast = segment sales × gross margin %. | CN16: =IFERROR((CK16/CF16)^(1/5)-1,"n/m") -> 0.10955386 | CO16: =IFERROR((CA16/BB16)^(1/5)-1,"n/m") -> 0.14749862 | CP16: =IFERROR((CA16/AC16)^(1/10)-1,"n/m") -> n/m | CQ16: =IFERROR((CA16/C16)^(1/20)-1,"n/m") -> n/m | CT16: Q2–Q4 FY27E point estimates (all cases)
B17: Segment gross margin % | C17: =IF(AND(ISNUMBER(C16),ISNUMBER(C11)),IFERROR(C16/C11,""),"") | D17: =IF(AND(ISNUMBER(D16),ISNUMBER(D11)),IFERROR(D16/D11,""),"") | E17: =IF(AND(ISNUMBER(E16),ISNUMBER(E11)),IFERROR(E16/E11,""),"") | F17: =IF(AND(ISNUMBER(F16),ISNUMBER(F11)),IFERROR(F16/F11,""),"") | G17: =IF(AND(ISNUMBER(G16),ISNUMBER(G11)),IFERROR(G16/G11,""),"") | H17: =IF(AND(ISNUMBER(H16),ISNUMBER(H11)),IFERROR(H16/H11,""),"") | I17: =IF(AND(ISNUMBER(I16),ISNUMBER(I11)),IFERROR(I16/I11,""),"") | J17: =IF(AND(ISNUMBER(J16),ISNUMBER(J11)),IFERROR(J16/J11,""),"") | ... CB17: =IF(AND(ISNUMBER(CB16),ISNUMBER(CB11)),IFERROR(CB16/CB11,""),"") -> 0.44454303 | CC17: =CC18+$CC$78 -> 0.39223218 | CD17: =CD18+$CC$78 -> 0.40639891 | CE17: =CE18+$CC$78 -> 0.42144007 | CF17: =IF(AND(ISNUMBER(CF16),ISNUMBER(CF11)),IFERROR(CF16/CF11,""),"") -> 0.41612053 | CG17: =CHOOSE(MATCH($CL$2,{"Bull","Base","Bear"},0),$CU$39,$CV$39,$CW$39) -> 0.44 | CH17: =CHOOSE(MATCH($CL$2,{"Bull","Base","Bear"},0),$CU$40,$CV$40,$CW$40) -> 0.445 | CI17: =CHOOSE(MATCH($CL$2,{"Bull","Base","Bear"},0),$CU$41,$CV$41,$CW$41) -> 0.45 | CJ17: =CHOOSE(MATCH($CL$2,{"Bull","Base","Bear"},0),$CU$42,$CV$42,$CW$42) -> 0.452 | CK17: =CHOOSE(MATCH($CL$2,{"Bull","Base","Bear"},0),$CU$43,$CV$43,$CW$43) -> 0.455 | CL17: Q2–Q4/27E: margin before calibration + the Q2 gross-margin-guidance Δ (solved in Q2/27E, carried). FY2028E+: scenario lever. | CN17: =IFERROR(AVERAGE(CG17,CH17,CI17,CJ17,CK17),"n/m") -> 0.4484 | CO17: =IFERROR(AVERAGE(BG17,BL17,BQ17,BV17,CA17),"n/m") -> 0.40463157 | CP17: =IFERROR(AVERAGE(AH17,AM17,AR17,AW17,BB17,BG17,BL17,BQ17,BV17,CA17),"n/m") -> 0.40499588 | CQ17: =IFERROR(AVERAGE(C17,D17,E17,F17,G17,H17,I17,N17,S17,X17,AC17,AH17,AM17,AR17,AW17,BB17,BG17,BL17,BQ17,BV17,CA17),"n/m") -> 0.40499588 | CT17: Q2–Q4/27E tax rate (GAAP) | CV17: 0.225 | CX17: Not guided. Q1 FY27 22.1% (23.2% excluding discrete stock-compensation benefits); FY2026 22.1%.
B18: Q2–Q4/27E margin before calibration (prior-year quarter + Q1 FY27 y/y drift) | CC18: =BX17+IFERROR(SUM(CB16:CB16)/SUM(CB11:CB11)-SUM(BW16:BW16)/SUM(BW11:BW11),0) -> 0.4048755 | CD18: =BY17+IFERROR(SUM(CB16:CB16)/SUM(CB11:CB11)-SUM(BW16:BW16)/SUM(BW11:BW11),0) -> 0.41904223 | CE18: =BZ17+IFERROR(SUM(CB16:CB16)/SUM(CB11:CB11)-SUM(BW16:BW16)/SUM(BW11:BW11),0) -> 0.43408339 | CT18: Q2–Q4/27E adjusted tax rate | CV18: 0.22 | CX18: Q1 FY27 "overall tax rate applied to adjusted pre-tax earnings" 22.0% (Q1 FY26 22.5%).
B19: Incremental gross margin (Δ gross margin / Δ sales) | D19: =IFERROR((D16-C16)/(D11-C11),"") | E19: =IFERROR((E16-D16)/(E11-D11),"") | F19: =IFERROR((F16-E16)/(F11-E11),"") | G19: =IFERROR((G16-F16)/(G11-F11),"") | H19: =IFERROR((H16-G16)/(H11-G11),"") | I19: =IFERROR((I16-H16)/(I11-H11),"") | N19: =IFERROR((N16-I16)/(N11-I11),"") | O19: =IFERROR((O16-J16)/(O11-J11),"") | P19: =IFERROR((P16-K16)/(P11-K11),"") | Q19: =IFERROR((Q16-L16)/(Q11-L11),"") | R19: =IFERROR((R16-M16)/(R11-M11),"") | S19: =IFERROR((S16-N16)/(S11-N11),"") | T19: =IFERROR((T16-O16)/(T11-O11),"") | U19: =IFERROR((U16-P16)/(U11-P11),"") | ... CF19: =IFERROR((CF16-CA16)/(CF11-CA11),"") -> 0.45689833 | CG19: =IFERROR((CG16-CF16)/(CG11-CF11),"") -> 0.65708608 | CH19: =IFERROR((CH16-CG16)/(CH11-CG11),"") -> 0.495 | CI19: =IFERROR((CI16-CH16)/(CI11-CH11),"") -> 0.50555556 | CJ19: =IFERROR((CJ16-CI16)/(CJ11-CI11),"") -> 0.477 | CK19: =IFERROR((CK16-CJ16)/(CK11-CJ11),"") -> 0.49785714 | CT19: Q2–Q4/27E restructuring & consolidation per quarter ($m) | CV19: 0.5 | CX19: Q1 FY27 $0.4m; FY2026 $6.2m (assumption).
B20: Memo: Aerospace & Defense segment operating income as reported (FY2022–FY2025 segment note) | BA20: 28.756 | BB20: 122.402 | BE20: 28.543 | BF20: 33.229 | BG20: 117.858 | BH20: 29.504 | BI20: 31.48 | BJ20: 32.081 | BK20: 39.635 | BL20: 132.7 | BM20: 36.8 | BN20: 39.7 | BO20: 38.6 | BP20: 46.6 | BQ20: 161.7 | BR20: 50.6 | BS20: 46.3 | BT20: 46.8 | CT20: Q2–Q4/27E other, net excl. M&A amortization & items per quarter ($m) | CV20: 1.5 | CX20: Q1 FY27 $1.3m ($21.0m amortization of intangible assets − $19.5m M&A-related + $0.4m restructuring − $0.2m other items); mostly software amortization.
CT21: Q2–Q4/27E amortization of deferred finance fees per quarter ($m) | CV21: 0.4 | CX21: Q1 FY27 $0.8m; $0.6m of term-loan fees remain to Nov-2026 and $2.1m of revolver fees amortize to Oct-2030 (10-Q Note 10).
B22: Industrial (bearings, gearing and power-transmission components for construction, mining, food & beverage, warehousing, semicon, energy; Dodge from 1-Nov-2021) | CL22: INDUSTRIAL — modelling logic | CT22: Q2–Q4/27E other non-operating expense per quarter ($m) | CV22: 0.5 | CX22: Q1 FY27 $0.5m; FY2026 $1.9m (pension and other).
B23: Industrial — segment net external sales | AZ23: 52.594 | BA23: 63.906 | BB23: 212.762 | BC23: 65.84 | BD23: 67.985 | BE23: 173.75 | BF23: 253.894 | BG23: 561.469 | BH23: 254.681 | BI23: 265.619 | BJ23: 246.093 | BK23: 272.594 | BL23: 1038.987 | BM23: 266.65 | BN23: 258.301 | BO23: 244.613 | BP23: 271.367 | BQ23: 1040.931 | BR23: 257.2 | BS23: 254.7 | BT23: 251.2 | BU23: 280.4 | BV23: 1043.5 | BW23: 271.4 | BX23: 256.5 | BY23: 259.1 | BZ23: 295.9 | CA23: 1082.9 | CB23: 294.1 | CC23: =BX23*(1+CC24)*CC34+CC26 -> 275.09949 | CD23: =BY23*(1+CD24)*CD34+CD26 -> 279.76876 | CE23: =BZ23*(1+CE24)*CE34+CE26 -> 343.50807 | CF23: =SUM(CB23:CE23) -> 1192.4763 | CG23: =CF23*(1+CG24) -> 1264.0249 | CH23: =CG23*(1+CH24) -> 1333.5463 | CI23: =CH23*(1+CI24) -> 1400.2236 | CJ23: =CI23*(1+CJ24) -> 1470.2348 | CK23: =CJ23*(1+CK24) -> 1536.3953 | CN23: =IFERROR((CK23/CF23)^(1/5)-1,"n/m") -> 0.051987653 | CO23: =IFERROR((CA23/BB23)^(1/5)-1,"n/m") -> 0.38464633 | CP23: =IFERROR((CA23/AC23)^(1/10)-1,"n/m") -> n/m | CQ23: =IFERROR((CA23/C23)^(1/20)-1,"n/m") -> n/m
B24: y/y % (Q2–Q4/27E: organic, before acquired sales) | D24: =IF(AND(ISNUMBER(D23),ISNUMBER(C23)),IFERROR(D23/C23-1,""),"") | E24: =IF(AND(ISNUMBER(E23),ISNUMBER(D23)),IFERROR(E23/D23-1,""),"") | F24: =IF(AND(ISNUMBER(F23),ISNUMBER(E23)),IFERROR(F23/E23-1,""),"") | G24: =IF(AND(ISNUMBER(G23),ISNUMBER(F23)),IFERROR(G23/F23-1,""),"") | H24: =IF(AND(ISNUMBER(H23),ISNUMBER(G23)),IFERROR(H23/G23-1,""),"") | I24: =IF(AND(ISNUMBER(I23),ISNUMBER(H23)),IFERROR(I23/H23-1,""),"") | N24: =IF(AND(ISNUMBER(N23),ISNUMBER(I23)),IFERROR(N23/I23-1,""),"") | O24: =IF(AND(ISNUMBER(O23),ISNUMBER(J23)),IFERROR(O23/J23-1,""),"") | P24: =IF(AND(ISNUMBER(P23),ISNUMBER(K23)),IFERROR(P23/K23-1,""),"") | Q24: =IF(AND(ISNUMBER(Q23),ISNUMBER(L23)),IFERROR(Q23/L23-1,""),"") | R24: =IF(AND(ISNUMBER(R23),ISNUMBER(M23)),IFERROR(R23/M23-1,""),"") | S24: =IF(AND(ISNUMBER(S23),ISNUMBER(N23)),IFERROR(S23/N23-1,""),"") | T24: =IF(AND(ISNUMBER(T23),ISNUMBER(O23)),IFERROR(T23/O23-1,""),"") | U24: =IF(AND(ISNUMBER(U23),ISNUMBER(P23)),IFERROR(U23/P23-1,""),"") | ... CB24: =IF(AND(ISNUMBER(CB23),ISNUMBER(BW23)),IFERROR(CB23/BW23-1,""),"") -> 0.083640383 | CC24: =CC25+$CC$74 -> 0.065105228 | CD24: =CD25+$CC$74 -> 0.065105228 | CE24: =CE25+$CC$74 -> 0.065105228 | CF24: =IF(AND(ISNUMBER(CF23),ISNUMBER(CA23)),IFERROR(CF23/CA23-1,""),"") -> 0.10118785 | CG24: =CHOOSE(MATCH($CL$2,{"Bull","Base","Bear"},0),$CU$33,$CV$33,$CW$33) -> 0.06 | CH24: =CHOOSE(MATCH($CL$2,{"Bull","Base","Bear"},0),$CU$34,$CV$34,$CW$34) -> 0.055 | CI24: =CHOOSE(MATCH($CL$2,{"Bull","Base","Bear"},0),$CU$35,$CV$35,$CW$35) -> 0.05 | CJ24: =CHOOSE(MATCH($CL$2,{"Bull","Base","Bear"},0),$CU$36,$CV$36,$CW$36) -> 0.05 | CK24: =CHOOSE(MATCH($CL$2,{"Bull","Base","Bear"},0),$CU$37,$CV$37,$CW$37) -> 0.045 | CT24: Maximum net debt / adjusted EBITDA before buybacks (x) — buyback floor FY2028E+ | CU24: 1.5 | CV24: 1 | CW24: 0.5 | CX24: Net debt $682m at 27-Jun-2026 ≈ 1.0x LTM adjusted EBITDA (FY2026 $605m); the credit agreement allows up to 4.5x. RBC has made no open-market buybacks (the $100m 2019 authorization is unused) and has deployed cash to debt reduction and acquisitions. Target = leverage up to which surplus cash after the M&A lever is returned via buybacks (assumption).
B25: Q2–Q4/27E organic growth before calibration (Q1 FY27 organic y/y) | CC25: =IFERROR((SUM(CB23:CB23)-SUM(CB26:CB26))/SUM(BW23:BW23)-1,0) -> 0.083640383 | CD25: =IFERROR((SUM(CB23:CB23)-SUM(CB26:CB26))/SUM(BW23:BW23)-1,0) -> 0.083640383 | CE25: =IFERROR((SUM(CB23:CB23)-SUM(CB26:CB26))/SUM(BW23:BW23)-1,0) -> 0.083640383
B26: Acquired sales not in the prior-year base (VACCO / PSC Couplings; input) | CC26: 1.9 | CD26: 3.8 | CE26: 4.1 | CL26: PSC Couplings (closed 10-Aug-2026; LTM net sales ~$15.1m, 8-K 11-Aug-2026): run-rate × days consolidated (47 days in Q2, 91 in Q3, 98 in the 14-week Q4). Outside the Q2 guidance (issued 31-Jul-2026). | CT26: AERO_G (Aerospace & Defense sales y/y, organic + future acquisitions excluded) | CU26: 0.03 | CV26: Δ → | CW26: -0.05 | CX26: Q1 FY27 +36.9% (+16.0% organic ex VACCO $34.4m); backlog $2.3bn. Defense (submarines, munitions, space) and commercial aerospace rate increases; FY2023–26 A&D sales CAGR 22% incl. VACCO.
B27: % of total net sales | C27: =IF(AND(ISNUMBER(C23),ISNUMBER(C65)),IFERROR(C23/C65,""),"") | D27: =IF(AND(ISNUMBER(D23),ISNUMBER(D65)),IFERROR(D23/D65,""),"") | E27: =IF(AND(ISNUMBER(E23),ISNUMBER(E65)),IFERROR(E23/E65,""),"") | F27: =IF(AND(ISNUMBER(F23),ISNUMBER(F65)),IFERROR(F23/F65,""),"") | G27: =IF(AND(ISNUMBER(G23),ISNUMBER(G65)),IFERROR(G23/G65,""),"") | H27: =IF(AND(ISNUMBER(H23),ISNUMBER(H65)),IFERROR(H23/H65,""),"") | I27: =IF(AND(ISNUMBER(I23),ISNUMBER(I65)),IFERROR(I23/I65,""),"") | J27: =IF(AND(ISNUMBER(J23),ISNUMBER(J65)),IFERROR(J23/J65,""),"") | ... CK27: =IF(AND(ISNUMBER(CK23),ISNUMBER(CK65)),IFERROR(CK23/CK65,""),"") -> 0.43615978 | CN27: =IFERROR(AVERAGE(CG27,CH27,CI27,CJ27,CK27),"n/m") -> 0.47903713 | CO27: =IFERROR(AVERAGE(BG27,BL27,BQ27,BV27,CA27),"n/m") -> 0.63725116 | CP27: =IFERROR(AVERAGE(AH27,AM27,AR27,AW27,BB27,BG27,BL27,BQ27,BV27,CA27),"n/m") -> 0.58927131 | CQ27: =IFERROR(AVERAGE(C27,D27,E27,F27,G27,H27,I27,N27,S27,X27,AC27,AH27,AM27,AR27,AW27,BB27,BG27,BL27,BQ27,BV27,CA27),"n/m") -> 0.58927131 | CT27: 2028E | CU27: =CV27+$CU$26 -> 0.14 | CV27: 0.11 | CW27: =CV27+$CW$26 -> 0.06
B28: Industrial segment gross margin | AZ28: 17.532 | BA28: 23.239 | BB28: 72.916 | BC28: 25.141 | BD28: 25.884 | BE28: 55.859 | BF28: 95.025 | BG28: 201.941 | BH28: 102.552 | BI28: 110.114 | BJ28: 104.39 | BK28: 116.744 | BL28: 433.8 | BM28: 120.6 | BN28: 115.7 | BO28: 104.7 | BP28: 120.7 | BQ28: 461.7 | BR28: 120.9 | BS28: 117 | BT28: 117 | BU28: 128.1 | BV28: 483 | BW28: 125 | BX28: 123.7 | BY28: 123.2 | BZ28: 137.6 | CA28: 509.5 | CB28: 147.6 | CC28: =CC23*CC29 -> 140.55196 | CD28: =CD23*CD29 -> 141.04377 | CE28: =CE23*CE29 -> 169.58099 | CF28: =SUM(CB28:CE28) -> 598.77672 | CG28: =CG23*CG29 -> 613.05208 | CH28: =CH23*CH29 -> 653.43768 | CI28: =CI23*CI29 -> 693.11068 | CJ28: =CJ23*CJ29 -> 730.70668 | CK28: =CK23*CK29 -> 768.19767 | CN28: =IFERROR((CK28/CF28)^(1/5)-1,"n/m") -> 0.051094142 | CO28: =IFERROR((CA28/BB28)^(1/5)-1,"n/m") -> 0.4752454 | CP28: =IFERROR((CA28/AC28)^(1/10)-1,"n/m") -> n/m | CQ28: =IFERROR((CA28/C28)^(1/20)-1,"n/m") -> n/m | CT28: 2029E | CU28: =CV28+$CU$26 -> 0.13 | CV28: 0.1 | CW28: =CV28+$CW$26 -> 0.05
B29: Segment gross margin % | C29: =IF(AND(ISNUMBER(C28),ISNUMBER(C23)),IFERROR(C28/C23,""),"") | D29: =IF(AND(ISNUMBER(D28),ISNUMBER(D23)),IFERROR(D28/D23,""),"") | E29: =IF(AND(ISNUMBER(E28),ISNUMBER(E23)),IFERROR(E28/E23,""),"") | F29: =IF(AND(ISNUMBER(F28),ISNUMBER(F23)),IFERROR(F28/F23,""),"") | G29: =IF(AND(ISNUMBER(G28),ISNUMBER(G23)),IFERROR(G28/G23,""),"") | H29: =IF(AND(ISNUMBER(H28),ISNUMBER(H23)),IFERROR(H28/H23,""),"") | I29: =IF(AND(ISNUMBER(I28),ISNUMBER(I23)),IFERROR(I28/I23,""),"") | J29: =IF(AND(ISNUMBER(J28),ISNUMBER(J23)),IFERROR(J28/J23,""),"") | ... CB29: =IF(AND(ISNUMBER(CB28),ISNUMBER(CB23)),IFERROR(CB28/CB23,""),"") -> 0.50187011 | CC29: =CC30+$CC$78 -> 0.5109132 | CD29: =CD30+$CC$78 -> 0.50414408 | CE29: =CE30+$CC$78 -> 0.49367396 | CF29: =IF(AND(ISNUMBER(CF28),ISNUMBER(CF23)),IFERROR(CF28/CF23,""),"") -> 0.50212881 | CG29: =CHOOSE(MATCH($CL$2,{"Bull","Base","Bear"},0),$CU$45,$CV$45,$CW$45) -> 0.485 | CH29: =CHOOSE(MATCH($CL$2,{"Bull","Base","Bear"},0),$CU$46,$CV$46,$CW$46) -> 0.49 | CI29: =CHOOSE(MATCH($CL$2,{"Bull","Base","Bear"},0),$CU$47,$CV$47,$CW$47) -> 0.495 | CJ29: =CHOOSE(MATCH($CL$2,{"Bull","Base","Bear"},0),$CU$48,$CV$48,$CW$48) -> 0.497 | CK29: =CHOOSE(MATCH($CL$2,{"Bull","Base","Bear"},0),$CU$49,$CV$49,$CW$49) -> 0.5 | CN29: =IFERROR(AVERAGE(CG29,CH29,CI29,CJ29,CK29),"n/m") -> 0.4934 | CO29: =IFERROR(AVERAGE(BG29,BL29,BQ29,BV29,CA29),"n/m") -> 0.4308188 | CP29: =IFERROR(AVERAGE(AH29,AM29,AR29,AW29,BB29,BG29,BL29,BQ29,BV29,CA29),"n/m") -> 0.41613426 | CQ29: =IFERROR(AVERAGE(C29,D29,E29,F29,G29,H29,I29,N29,S29,X29,AC29,AH29,AM29,AR29,AW29,BB29,BG29,BL29,BQ29,BV29,CA29),"n/m") -> 0.41613426 | CT29: 2030E | CU29: =CV29+$CU$26 -> 0.12 | CV29: 0.09 | CW29: =CV29+$CW$26 -> 0.04
B30: Q2–Q4/27E margin before calibration (prior-year quarter + Q1 FY27 y/y drift) | CC30: =BX29+IFERROR(SUM(CB28:CB28)/SUM(CB23:CB23)-SUM(BW28:BW28)/SUM(BW23:BW23),0) -> 0.52355652 | CD30: =BY29+IFERROR(SUM(CB28:CB28)/SUM(CB23:CB23)-SUM(BW28:BW28)/SUM(BW23:BW23),0) -> 0.5167874 | CE30: =BZ29+IFERROR(SUM(CB28:CB28)/SUM(CB23:CB23)-SUM(BW28:BW28)/SUM(BW23:BW23),0) -> 0.50631728 | CT30: 2031E | CU30: =CV30+$CU$26 -> 0.11 | CV30: 0.08 | CW30: =CV30+$CW$26 -> 0.03
B31: Incremental gross margin (Δ gross margin / Δ sales) | D31: =IFERROR((D28-C28)/(D23-C23),"") | E31: =IFERROR((E28-D28)/(E23-D23),"") | F31: =IFERROR((F28-E28)/(F23-E23),"") | G31: =IFERROR((G28-F28)/(G23-F23),"") | H31: =IFERROR((H28-G28)/(H23-G23),"") | I31: =IFERROR((I28-H28)/(I23-H23),"") | N31: =IFERROR((N28-I28)/(N23-I23),"") | O31: =IFERROR((O28-J28)/(O23-J23),"") | P31: =IFERROR((P28-K28)/(P23-K23),"") | Q31: =IFERROR((Q28-L28)/(Q23-L23),"") | R31: =IFERROR((R28-M28)/(R23-M23),"") | S31: =IFERROR((S28-N28)/(S23-N23),"") | T31: =IFERROR((T28-O28)/(T23-O23),"") | U31: =IFERROR((U28-P28)/(U23-P23),"") | ... CF31: =IFERROR((CF28-CA28)/(CF23-CA23),"") -> 0.81474457 | CG31: =IFERROR((CG28-CF28)/(CG23-CF23),"") -> 0.19951986 | CH31: =IFERROR((CH28-CG28)/(CH23-CG23),"") -> 0.58090909 | CI31: =IFERROR((CI28-CH28)/(CI23-CH23),"") -> 0.595 | CJ31: =IFERROR((CJ28-CI28)/(CJ23-CI23),"") -> 0.537 | CK31: =IFERROR((CK28-CJ28)/(CK23-CJ23),"") -> 0.56666667 | CT31: 2032E | CU31: =CV31+$CU$26 -> 0.1 | CV31: 0.07 | CW31: =CV31+$CW$26 -> 0.02
B32: Memo: Industrial segment operating income as reported (FY2022–FY2025 segment note) | BA32: 17.664 | BB32: 52.911 | BE32: 23.197 | BF32: 45.064 | BG32: 107.478 | BH32: 53.295 | BI32: 60.05 | BJ32: 59.255 | BK32: 63.9 | BL32: 236.5 | BM32: 71.1 | BN32: 69.5 | BO32: 59.3 | BP32: 72.7 | BQ32: 272.6 | BR32: 72.5 | BS32: 68.5 | BT32: 68.2 | CT32: IND_G (Industrial sales y/y) | CU32: 0.02 | CV32: Δ → | CW32: -0.06 | CX32: Q1 FY27 +8.4% (semicon, grain, food & beverage); FY2023–26 Industrial sales flat to +4% a year after the Dodge-led FY2023 step-up; cyclical downside (FY2021 −12% legacy industrial).
CT33: 2028E | CU33: =CV33+$CU$32 -> 0.08 | CV33: 0.06 | CW33: =CV33+$CW$32 -> 0
B34: Week factor (Q4/27E: 14 of 13 weeks — FY2027 is a 53-week year) | CC34: 1 | CD34: 1 | CE34: 1.0769231 | CL34: Q1 FY27 10-Q, MD&A overview: fiscal 2027 has 53 weeks (FY2026 52); Q1 FY27 and Q1 FY26 had 13 weeks. The extra week falls in Q4 (Q1 had 13 weeks); applied to sales only (assumption). | CT34: 2029E | CU34: =CV34+$CU$32 -> 0.075 | CV34: 0.055 | CW34: =CV34+$CW$32 -> -0.005
B35: Net sales not on the current segment basis (FY2006–FY2020 and Q1–Q2 FY21: total) | C35: =IF(ISNUMBER(C11),"",C108) -> 274.509 | D35: =IF(ISNUMBER(D11),"",D108) -> 306.062 | E35: =IF(ISNUMBER(E11),"",E108) -> 330.6 | F35: =IF(ISNUMBER(F11),"",F108) -> 355.796 | G35: =IF(ISNUMBER(G11),"",G108) -> 274.702 | H35: =IF(ISNUMBER(H11),"",H108) -> 335.625 | I35: =IF(ISNUMBER(I11),"",I108) -> 397.511 | J35: =IF(ISNUMBER(J11),"",J108) -> 103.334 | ... CB35: =IF(ISNUMBER(CB11),"",CB108) | CL35: Aerospace & Defense / Industrial were introduced after the Dodge acquisition; earlier periods were never re-presented (legacy segments below). | CT35: 2030E | CU35: =CV35+$CU$32 -> 0.07 | CV35: 0.05 | CW35: =CV35+$CW$32 -> -0.01
B36: Memo: corporate operating loss as reported (segment note) | BA36: -16.68 | BB36: -63.855 | BE36: -37.369 | BF36: -20.447 | BG36: -95.273 | BH36: -18.329 | BI36: -19.513 | BJ36: -20.944 | BK36: -17.414 | BL36: -76.2 | BM36: -22.9 | BN36: -21.4 | BO36: -22.7 | BP36: -25.1 | BQ36: -92.1 | BR36: -25.6 | BS36: -28.7 | BT36: -29.4 | CT36: 2031E | CU36: =CV36+$CU$32 -> 0.07 | CV36: 0.05 | CW36: =CV36+$CW$32 -> -0.01
B37: Check: segment operating income + corporate vs operating income (should be 0) | C37: =IF(ISNUMBER(C20),IF(ABS(C20+C32+N(C36)-C116)<=0.15,0,ROUND(C20+C32+N(C36)-C116,1)),"") | D37: =IF(ISNUMBER(D20),IF(ABS(D20+D32+N(D36)-D116)<=0.15,0,ROUND(D20+D32+N(D36)-D116,1)),"") | E37: =IF(ISNUMBER(E20),IF(ABS(E20+E32+N(E36)-E116)<=0.15,0,ROUND(E20+E32+N(E36)-E116,1)),"") | F37: =IF(ISNUMBER(F20),IF(ABS(F20+F32+N(F36)-F116)<=0.15,0,ROUND(F20+F32+N(F36)-F116,1)),"") | G37: =IF(ISNUMBER(G20),IF(ABS(G20+G32+N(G36)-G116)<=0.15,0,ROUND(G20+G32+N(G36)-G116,1)),"") | H37: =IF(ISNUMBER(H20),IF(ABS(H20+H32+N(H36)-H116)<=0.15,0,ROUND(H20+H32+N(H36)-H116,1)),"") | I37: =IF(ISNUMBER(I20),IF(ABS(I20+I32+N(I36)-I116)<=0.15,0,ROUND(I20+I32+N(I36)-I116,1)),"") | J37: =IF(ISNUMBER(J20),IF(ABS(J20+J32+N(J36)-J116)<=0.15,0,ROUND(J20+J32+N(J36)-J116,1)),"") | ... CB37: =IF(ISNUMBER(CB20),IF(ABS(CB20+CB32+N(CB36)-CB116)<=0.15,0,ROUND(CB20+CB32+N(CB36)-CB116,1)),"") | CT37: 2032E | CU37: =CV37+$CU$32 -> 0.065 | CV37: 0.045 | CW37: =CV37+$CW$32 -> -0.015
B38: Legacy segments (net external sales as originally reported, FY2006–Q2 FY22): | CT38: AERO_M (Aerospace & Defense segment gross margin %) | CU38: 0.01 | CV38: Δ → | CW38: -0.025 | CX38: Q1 FY27 44.5%; FY2026 40.7% (VACCO integration), FY2023 39.7%; volume leverage and VACCO margin improvement.
B39: Plain bearings | C39: 115.091 | D39: 143.907 | E39: 154.535 | F39: 166.658 | G39: 134.303 | H39: 168.777 | I39: 200.141 | J39: 55.397 | K39: 53.272 | L39: 51.497 | M39: 55.797 | N39: 215.963 | O39: 57.09 | P39: 52.828 | Q39: 52.991 | R39: 60.19 | S39: 223.099 | T39: 59.873 | U39: 57.458 | V39: 53.77 | W39: 59.067 | X39: 230.168 | Y39: 65.677 | Z39: 67.607 | AA39: 64.171 | AB39: 73.079 | AC39: 270.534 | AD39: 70.45 | AE39: 68.835 | AF39: 65.822 | AG39: 72.593 | AH39: 277.7 | AI39: 72.653 | AJ39: 72.392 | AK39: 69.764 | AL39: 81.899 | AM39: 296.708 | AN39: 78.525 | AO39: 77.48 | AP39: 79.306 | AQ39: 87.94 | AR39: 323.251 | AS39: 87.489 | AT39: 90.007 | AU39: 86.876 | AV39: 93.919 | AW39: 358.291 | AX39: 78.875 | AY39: 71.053 | AZ39: 69.321 | BA39: 74.741 | BB39: 293.99 | BC39: 73.321 | BD39: 74.079 | CT39: 2028E | CU39: =CV39+$CU$38 -> 0.45 | CV39: 0.44 | CW39: =CV39+$CW$38 -> 0.415
B40: Roller bearings | C40: 96.466 | D40: 92.123 | E40: 97.019 | F40: 94.428 | G40: 73.164 | H40: 98.942 | I40: 123.803 | J40: 31.397 | K40: 30.052 | L40: 26.115 | M40: 27.457 | N40: 115.021 | O40: 28.35 | P40: 30.277 | Q40: 27.284 | R40: 29.895 | S40: 115.806 | T40: 31.765 | U40: 33.504 | V40: 31.358 | W40: 32.075 | X40: 128.702 | Y40: 30.58 | Z40: 27.151 | AA40: 26.294 | AB40: 28.014 | AC40: 112.039 | AD40: 27.834 | AE40: 26.795 | AF40: 26.157 | AG40: 28.697 | AH40: 109.483 | AI40: 31.413 | AJ40: 32.317 | AK40: 32.485 | AL40: 35.806 | AM40: 132.021 | AN40: 35.87 | AO40: 37 | AP40: 34.841 | AQ40: 36.121 | AR40: 143.832 | AS40: 36.859 | AT40: 32.585 | AU40: 31.829 | AV40: 31.369 | AW40: 132.642 | AX40: 22.9 | AY40: 21.579 | AZ40: 22.408 | BA40: 24.77 | BB40: 91.657 | BC40: 25.247 | BD40: 27.309 | CT40: 2029E | CU40: =CV40+$CU$38 -> 0.455 | CV40: 0.445 | CW40: =CV40+$CW$38 -> 0.42
B41: Ball bearings | C41: 46.378 | D41: 50.466 | E41: 56.677 | F41: 63.625 | G41: 45.442 | H41: 40.637 | I41: 42.33 | J41: 9.387 | K41: 9.98 | L41: 10.779 | M41: 11.22 | N41: 41.366 | O41: 9.455 | P41: 11.2 | Q41: 13.054 | R41: 15.846 | S41: 49.555 | T41: 13.545 | U41: 14.093 | V41: 14.038 | W41: 14.788 | X41: 56.464 | Y41: 12.819 | Z41: 13.122 | AA41: 12.85 | AB41: 14.859 | AC41: 53.65 | AD41: 13.71 | AE41: 14.569 | AF41: 13.7 | AG41: 16.469 | AH41: 58.448 | AI41: 15.78 | AJ41: 16.48 | AK41: 16.496 | AL41: 19.05 | AM41: 67.806 | AN41: 18.074 | AO41: 18.038 | AP41: 16.72 | AQ41: 19.475 | AR41: 72.307 | AS41: 17.71 | AT41: 17.424 | AU41: 18.475 | AV41: 20.622 | AW41: 74.231 | AX41: 18.84 | AY41: 21.099 | AZ41: 20.675 | BA41: 23.09 | BB41: 83.704 | BC41: 23.128 | BD41: 24.431 | CT41: 2030E | CU41: =CV41+$CU$38 -> 0.46 | CV41: 0.45 | CW41: =CV41+$CW$38 -> 0.425
B42: Other / Engineered products (renamed FY2016, Sargent) | C42: 16.574 | D42: 19.566 | E42: 22.369 | F42: 31.085 | G42: 21.793 | H42: 27.269 | I42: 31.237 | J42: 7.153 | K42: 7.071 | L42: 7.945 | M42: 8.532 | N42: 30.701 | O42: 7.773 | P42: 7.649 | Q42: 7.217 | R42: 7.787 | S42: 30.426 | T42: 7.801 | U42: 7.5 | V42: 7.156 | W42: 7.487 | X42: 29.944 | Y42: 33.232 | Z42: 40.816 | AA42: 40.901 | AB42: 46.3 | AC42: 161.249 | AD42: 42.585 | AE42: 43.744 | AF42: 40.977 | AG42: 42.451 | AH42: 169.757 | AI42: 44.051 | AJ42: 43.128 | AK42: 48.113 | AL42: 43.122 | AM42: 178.414 | AN42: 43.516 | AO42: 40.398 | AP42: 40.586 | AQ42: 38.626 | AR42: 163.126 | AS42: 40.632 | AT42: 41.893 | AU42: 39.839 | AV42: 39.933 | AW42: 162.297 | AX42: 35.878 | AY42: 32.604 | AZ42: 33.457 | BA42: 37.694 | BB42: 139.633 | BC42: 34.509 | BD42: 35.081 | CT42: 2031E | CU42: =CV42+$CU$38 -> 0.462 | CV42: 0.452 | CW42: =CV42+$CW$38 -> 0.427
B43: Check: legacy segments vs net sales (should be 0) | C43: =IF(ISNUMBER(C39),IF(ABS(N(C39)+N(C40)+N(C41)+N(C42)-C108)<=0.15,0,ROUND(N(C39)+N(C40)+N(C41)+N(C42)-C108,1)),"") -> 0 | D43: =IF(ISNUMBER(D39),IF(ABS(N(D39)+N(D40)+N(D41)+N(D42)-D108)<=0.15,0,ROUND(N(D39)+N(D40)+N(D41)+N(D42)-D108,1)),"") -> 0 | E43: =IF(ISNUMBER(E39),IF(ABS(N(E39)+N(E40)+N(E41)+N(E42)-E108)<=0.15,0,ROUND(N(E39)+N(E40)+N(E41)+N(E42)-E108,1)),"") -> 0 | F43: =IF(ISNUMBER(F39),IF(ABS(N(F39)+N(F40)+N(F41)+N(F42)-F108)<=0.15,0,ROUND(N(F39)+N(F40)+N(F41)+N(F42)-F108,1)),"") -> 0 | G43: =IF(ISNUMBER(G39),IF(ABS(N(G39)+N(G40)+N(G41)+N(G42)-G108)<=0.15,0,ROUND(N(G39)+N(G40)+N(G41)+N(G42)-G108,1)),"") -> 0 | H43: =IF(ISNUMBER(H39),IF(ABS(N(H39)+N(H40)+N(H41)+N(H42)-H108)<=0.15,0,ROUND(N(H39)+N(H40)+N(H41)+N(H42)-H108,1)),"") -> 0 | I43: =IF(ISNUMBER(I39),IF(ABS(N(I39)+N(I40)+N(I41)+N(I42)-I108)<=0.15,0,ROUND(N(I39)+N(I40)+N(I41)+N(I42)-I108,1)),"") -> 0 | J43: =IF(ISNUMBER(J39),IF(ABS(N(J39)+N(J40)+N(J41)+N(J42)-J108)<=0.15,0,ROUND(N(J39)+N(J40)+N(J41)+N(J42)-J108,1)),"") -> 0 | ... CB43: =IF(ISNUMBER(CB39),IF(ABS(N(CB39)+N(CB40)+N(CB41)+N(CB42)-CB108)<=0.15,0,ROUND(N(CB39)+N(CB40)+N(CB41)+N(CB42)-CB108,1)),"") | CT43: 2032E | CU43: =CV43+$CU$38 -> 0.465 | CV43: 0.455 | CW43: =CV43+$CW$38 -> 0.43
B44: Contribution to total sales growth — Aerospace & Defense (pp) | D44: =IF(AND(ISNUMBER(D11),ISNUMBER(C11)),IFERROR((D11-C11)/C65,""),"") | E44: =IF(AND(ISNUMBER(E11),ISNUMBER(D11)),IFERROR((E11-D11)/D65,""),"") | F44: =IF(AND(ISNUMBER(F11),ISNUMBER(E11)),IFERROR((F11-E11)/E65,""),"") | G44: =IF(AND(ISNUMBER(G11),ISNUMBER(F11)),IFERROR((G11-F11)/F65,""),"") | H44: =IF(AND(ISNUMBER(H11),ISNUMBER(G11)),IFERROR((H11-G11)/G65,""),"") | I44: =IF(AND(ISNUMBER(I11),ISNUMBER(H11)),IFERROR((I11-H11)/H65,""),"") | N44: =IF(AND(ISNUMBER(N11),ISNUMBER(I11)),IFERROR((N11-I11)/I65,""),"") | O44: =IF(AND(ISNUMBER(O11),ISNUMBER(J11)),IFERROR((O11-J11)/J65,""),"") | P44: =IF(AND(ISNUMBER(P11),ISNUMBER(K11)),IFERROR((P11-K11)/K65,""),"") | Q44: =IF(AND(ISNUMBER(Q11),ISNUMBER(L11)),IFERROR((Q11-L11)/L65,""),"") | R44: =IF(AND(ISNUMBER(R11),ISNUMBER(M11)),IFERROR((R11-M11)/M65,""),"") | S44: =IF(AND(ISNUMBER(S11),ISNUMBER(N11)),IFERROR((S11-N11)/N65,""),"") | T44: =IF(AND(ISNUMBER(T11),ISNUMBER(O11)),IFERROR((T11-O11)/O65,""),"") | U44: =IF(AND(ISNUMBER(U11),ISNUMBER(P11)),IFERROR((U11-P11)/P65,""),"") | ... CF44: =IF(AND(ISNUMBER(CF11),ISNUMBER(CA11)),IFERROR((CF11-CA11)/CA65,""),"") -> 0.094414296 | CG44: =IF(AND(ISNUMBER(CG11),ISNUMBER(CF11)),IFERROR((CG11-CF11)/CF65,""),"") -> 0.049190848 | CH44: =IF(AND(ISNUMBER(CH11),ISNUMBER(CG11)),IFERROR((CH11-CG11)/CG65,""),"") -> 0.044899417 | CI44: =IF(AND(ISNUMBER(CI11),ISNUMBER(CH11)),IFERROR((CI11-CH11)/CH65,""),"") -> 0.039755999 | CJ44: =IF(AND(ISNUMBER(CJ11),ISNUMBER(CI11)),IFERROR((CJ11-CI11)/CI65,""),"") -> 0.03482394 | CK44: =IF(AND(ISNUMBER(CK11),ISNUMBER(CJ11)),IFERROR((CK11-CJ11)/CJ65,""),"") -> 0.02997653 | CT44: IND_M (Industrial segment gross margin %) | CU44: 0.01 | CV44: Δ → | CW44: -0.025 | CX44: Q1 FY27 50.2%; FY2026 47.1%, FY2023 41.8%: Dodge pricing and productivity (synergies); cyclical downside.
B45: Contribution to total sales growth — Industrial (pp) | D45: =IF(AND(ISNUMBER(D23),ISNUMBER(C23)),IFERROR((D23-C23)/C65,""),"") | E45: =IF(AND(ISNUMBER(E23),ISNUMBER(D23)),IFERROR((E23-D23)/D65,""),"") | F45: =IF(AND(ISNUMBER(F23),ISNUMBER(E23)),IFERROR((F23-E23)/E65,""),"") | G45: =IF(AND(ISNUMBER(G23),ISNUMBER(F23)),IFERROR((G23-F23)/F65,""),"") | H45: =IF(AND(ISNUMBER(H23),ISNUMBER(G23)),IFERROR((H23-G23)/G65,""),"") | I45: =IF(AND(ISNUMBER(I23),ISNUMBER(H23)),IFERROR((I23-H23)/H65,""),"") | N45: =IF(AND(ISNUMBER(N23),ISNUMBER(I23)),IFERROR((N23-I23)/I65,""),"") | O45: =IF(AND(ISNUMBER(O23),ISNUMBER(J23)),IFERROR((O23-J23)/J65,""),"") | P45: =IF(AND(ISNUMBER(P23),ISNUMBER(K23)),IFERROR((P23-K23)/K65,""),"") | Q45: =IF(AND(ISNUMBER(Q23),ISNUMBER(L23)),IFERROR((Q23-L23)/L65,""),"") | R45: =IF(AND(ISNUMBER(R23),ISNUMBER(M23)),IFERROR((R23-M23)/M65,""),"") | S45: =IF(AND(ISNUMBER(S23),ISNUMBER(N23)),IFERROR((S23-N23)/N65,""),"") | T45: =IF(AND(ISNUMBER(T23),ISNUMBER(O23)),IFERROR((T23-O23)/O65,""),"") | U45: =IF(AND(ISNUMBER(U23),ISNUMBER(P23)),IFERROR((U23-P23)/P65,""),"") | ... CF45: =IF(AND(ISNUMBER(CF23),ISNUMBER(CA23)),IFERROR((CF23-CA23)/CA65,""),"") -> 0.058568778 | CG45: =IF(AND(ISNUMBER(CG23),ISNUMBER(CF23)),IFERROR((CG23-CF23)/CF65,""),"") -> 0.033168628 | CH45: =IF(AND(ISNUMBER(CH23),ISNUMBER(CG23)),IFERROR((CH23-CG23)/CG65,""),"") -> 0.029152172 | CI45: =IF(AND(ISNUMBER(CI23),ISNUMBER(CH23)),IFERROR((CI23-CH23)/CH65,""),"") -> 0.025006762 | CJ45: =IF(AND(ISNUMBER(CJ23),ISNUMBER(CI23)),IFERROR((CJ23-CI23)/CI65,""),"") -> 0.023738212 | CK45: =IF(AND(ISNUMBER(CK23),ISNUMBER(CJ23)),IFERROR((CK23-CJ23)/CJ65,""),"") -> 0.02043391 | CT45: 2028E | CU45: =CV45+$CU$44 -> 0.495 | CV45: 0.485 | CW45: =CV45+$CW$44 -> 0.46
B46: Total net sales growth where the segment split is not available (pp) | D46: =IF(ISNUMBER(D11),"",IFERROR(D108/C108-1,"")) -> 0.11494341 | E46: =IF(ISNUMBER(E11),"",IFERROR(E108/D108-1,"")) -> 0.080173298 | F46: =IF(ISNUMBER(F11),"",IFERROR(F108/E108-1,"")) -> 0.076212946 | G46: =IF(ISNUMBER(G11),"",IFERROR(G108/F108-1,"")) -> -0.22792274 | H46: =IF(ISNUMBER(H11),"",IFERROR(H108/G108-1,"")) -> 0.22177851 | I46: =IF(ISNUMBER(I11),"",IFERROR(I108/H108-1,"")) -> 0.18439032 | N46: =IF(ISNUMBER(N11),"",IFERROR(N108/I108-1,"")) -> 0.013936721 | O46: =IF(ISNUMBER(O11),"",IFERROR(O108/J108-1,"")) -> -0.0064451197 | P46: =IF(ISNUMBER(P11),"",IFERROR(P108/K108-1,"")) -> 0.015731009 | Q46: =IF(ISNUMBER(Q11),"",IFERROR(Q108/L108-1,"")) -> 0.043701212 | R46: =IF(ISNUMBER(R11),"",IFERROR(R108/M108-1,"")) -> 0.10399394 | S46: =IF(ISNUMBER(S11),"",IFERROR(S108/N108-1,"")) -> 0.039287832 | T46: =IF(ISNUMBER(T11),"",IFERROR(T108/O108-1,"")) -> 0.10047921 | U46: =IF(ISNUMBER(U11),"",IFERROR(U108/P108-1,"")) -> 0.10397826 | ... CB46: =IF(ISNUMBER(CB11),"",IFERROR(CB108/BW108-1,"")) | CT46: 2029E | CU46: =CV46+$CU$44 -> 0.5 | CV46: 0.49 | CW46: =CV46+$CW$44 -> 0.465
B47: Memo: backlog at period end (release) | C47: 160.761 | D47: 176.578 | E47: 217.709 | F47: 179.316 | G47: 157.918 | H47: 196.697 | I47: 215.873 | J47: 211.532 | K47: 216.086 | L47: 211.286 | M47: 216.51 | N47: 216.51 | O47: 218.876 | P47: 222.321 | Q47: 218.567 | R47: 218.388 | S47: 218.388 | T47: 219.776 | U47: 217.955 | V47: 217.525 | W47: 209.55 | X47: 209.55 | Y47: 340.804 | Z47: 347.792 | AA47: 351.297 | AB47: 346.442 | AC47: 346.442 | AD47: 352.556 | AE47: 341.812 | AF47: 349.123 | AG47: 354.068 | AH47: 354.068 | AI47: 380.45 | AJ47: 390.185 | AK47: 392.462 | AL47: 392.085 | AM47: 392.085 | AN47: 419.249 | AO47: 429.904 | AP47: 428.231 | AQ47: 445.099 | AR47: 445.099 | AS47: 459.413 | AT47: 473.233 | AU47: 477.702 | AV47: 478.582 | AW47: 478.582 | AX47: 431.948 | AY47: 402.958 | AZ47: 393.934 | BA47: 394.773 | BB47: 394.773 | BC47: 420.218 | BD47: 456.741 | BE47: 552.712 | BF47: 603.09 | BG47: 603.09 | BH47: 635.741 | BI47: 653.238 | BJ47: 613.582 | BK47: 663.83 | BL47: 663.83 | BM47: 641.124 | BN47: 641.282 | BO47: 652.138 | BP47: 726.1 | BQ47: 726.1 | BR47: 825.8 | BS47: 864 | BT47: 896.5 | BU47: 940.7 | BV47: 940.7 | BW47: 1017.3 | BX47: 1600 | BY47: 2100 | BZ47: 2300 | CA47: 2300 | CB47: 2300 | CT47: 2030E | CU47: =CV47+$CU$44 -> 0.505 | CV47: 0.495 | CW47: =CV47+$CW$44 -> 0.47
CT48: 2031E | CU48: =CV48+$CU$44 -> 0.507 | CV48: 0.497 | CW48: =CV48+$CW$44 -> 0.472
B49: Future acquisitions (M&A lever — bolt-ons from FY2028E, unallocated) | CL49: M&A LEVER — acquired revenue = spend ÷ EV/sales; mid-year convention | CT49: 2032E | CU49: =CV49+$CU$44 -> 0.51 | CV49: 0.5 | CW49: =CV49+$CW$44 -> 0.475
B50: Acquisition spend (USDm, scenario) | CF50: 0 | CG50: =MAX(0,CHOOSE(MATCH($CL$2,{"Bull","Base","Bear"},0),$CU$57,$CV$57,$CW$57)) -> 250 | CH50: =MAX(0,CHOOSE(MATCH($CL$2,{"Bull","Base","Bear"},0),$CU$58,$CV$58,$CW$58)) -> 250 | CI50: =MAX(0,CHOOSE(MATCH($CL$2,{"Bull","Base","Bear"},0),$CU$59,$CV$59,$CW$59)) -> 250 | CJ50: =MAX(0,CHOOSE(MATCH($CL$2,{"Bull","Base","Bear"},0),$CU$60,$CV$60,$CW$60)) -> 250 | CK50: =MAX(0,CHOOSE(MATCH($CL$2,{"Bull","Base","Bear"},0),$CU$61,$CV$61,$CW$61)) -> 250 | CL50: Scenario lever M&A_spend (Base $250m p.a. of acquisitions from FY2028E). Funded from cash / revolver (debt schedule). | CT50: SGA (SG&A % of net sales) | CU50: -0.003 | CV50: Δ → | CW50: 0.005 | CX50: Q1 FY27 16.5%; FY2026 16.9%, FY2025 17.1%; operating leverage on fixed corporate costs. Bull = lower ratio.
B51: Purchase multiple — EV / sales (x) | CF51: 0 | CG51: 2.5 | CH51: 2.5 | CI51: 2.5 | CJ51: 2.5 | CK51: 2.5 | CL51: VACCO $276.7m on ~$118m LTM revenue (2.3x); PSC Couplings $24.2m on ~$15.1m (1.6x); Sargent (FY2016) $500m. 2.5x input (assumption). | CT51: 2028E | CU51: =CV51+$CU$50 -> 0.16 | CV51: 0.163 | CW51: =CV51+$CW$50 -> 0.168
B52: Annualised revenue acquired in the year | CF52: 0 | CG52: =IFERROR(CG50/CG51,0) -> 100 | CH52: =IFERROR(CH50/CH51,0) -> 100 | CI52: =IFERROR(CI50/CI51,0) -> 100 | CJ52: =IFERROR(CJ50/CJ51,0) -> 100 | CK52: =IFERROR(CK50/CK51,0) -> 100 | CT52: 2029E | CU52: =CV52+$CU$50 -> 0.159 | CV52: 0.162 | CW52: =CV52+$CW$50 -> 0.167
B53: Growth of acquired businesses after acquisition % | CF53: 0 | CG53: 0.05 | CH53: 0.05 | CI53: 0.05 | CJ53: 0.05 | CK53: 0.05 | CT53: 2030E | CU53: =CV53+$CU$50 -> 0.158 | CV53: 0.161 | CW53: =CV53+$CW$50 -> 0.166
B54: Run-rate revenue of businesses acquired (year end) | CF54: 0 | CG54: =CF54*(1+CG53)+CG52 -> 100 | CH54: =CG54*(1+CH53)+CH52 -> 205 | CI54: =CH54*(1+CI53)+CI52 -> 315.25 | CJ54: =CI54*(1+CJ53)+CJ52 -> 431.0125 | CK54: =CJ54*(1+CK53)+CK52 -> 552.56313 | CT54: 2031E | CU54: =CV54+$CU$50 -> 0.157 | CV54: 0.16 | CW54: =CV54+$CW$50 -> 0.165
B55: Revenue from future acquisitions | CF55: 0 | CG55: =CF54*(1+CG53)+0.5*CG52 -> 50 | CH55: =CG54*(1+CH53)+0.5*CH52 -> 155 | CI55: =CH54*(1+CI53)+0.5*CI52 -> 265.25 | CJ55: =CI54*(1+CJ53)+0.5*CJ52 -> 381.0125 | CK55: =CJ54*(1+CK53)+0.5*CK52 -> 502.56313 | CL55: Mid-year convention. | CT55: 2032E | CU55: =CV55+$CU$50 -> 0.157 | CV55: 0.16 | CW55: =CV55+$CW$50 -> 0.165
B56: Gross margin of acquired businesses % | CF56: 0 | CG56: 0.38 | CH56: 0.38 | CI56: 0.38 | CJ56: 0.38 | CK56: 0.38 | CL56: Assumption: below the group (~45%) before integration (VACCO and Dodge were acquired below RBC margins). | CT56: M&A_spend (acquisitions, $m) | CU56: 150 | CV56: Δ → | CW56: -250 | CX56: RBC spent $276.7m on VACCO (FY2026), $24.2m on PSC (FY2027), $2.9bn on Dodge (FY2022), $500m on Sargent (FY2016). Base $250m p.a. (assumption).
B57: Gross margin from future acquisitions | CF57: 0 | CG57: =CG55*CG56 -> 19 | CH57: =CH55*CH56 -> 58.9 | CI57: =CI55*CI56 -> 100.795 | CJ57: =CJ55*CJ56 -> 144.78475 | CK57: =CK55*CK56 -> 190.97399 | CT57: 2028E | CU57: =MAX(0,CV57+$CU$56) -> 400 | CV57: 250 | CW57: =MAX(0,CV57+$CW$56) -> 0
B58: PP&E % of spend | CF58: 0 | CG58: 0.12 | CH58: 0.12 | CI58: 0.12 | CJ58: 0.12 | CK58: 0.12 | CL58: VACCO: PP&E $40.6m of $276.7m (15%); Dodge $165.1m of $2,880.8m (6%). | CT58: 2029E | CU58: =MAX(0,CV58+$CU$56) -> 400 | CV58: 250 | CW58: =MAX(0,CV58+$CW$56) -> 0
B59: Acquired intangibles % of spend | CF59: 0 | CG59: 0.45 | CH59: 0.45 | CI59: 0.45 | CJ59: 0.45 | CK59: 0.45 | CL59: PPAs: VACCO 45% of consideration in intangibles ($123.8m), Dodge 48% ($1,385.1m). | CT59: 2030E | CU59: =MAX(0,CV59+$CU$56) -> 400 | CV59: 250 | CW59: =MAX(0,CV59+$CW$56) -> 0
B60: Intangible amortization life (years) | CF60: 0 | CG60: 15 | CH60: 15 | CI60: 15 | CJ60: 15 | CK60: 15 | CT60: 2031E | CU60: =MAX(0,CV60+$CU$56) -> 400 | CV60: 250 | CW60: =MAX(0,CV60+$CW$56) -> 0
B61: Cumulative acquired intangibles (gross) | CF61: 0 | CG61: =CF61+CG50*CG59 -> 112.5 | CH61: =CG61+CH50*CH59 -> 225 | CI61: =CH61+CI50*CI59 -> 337.5 | CJ61: =CI61+CJ50*CJ59 -> 450 | CK61: =CJ61+CK50*CK59 -> 562.5 | CT61: 2032E | CU61: =MAX(0,CV61+$CU$56) -> 400 | CV61: 250 | CW61: =MAX(0,CV61+$CW$56) -> 0
B62: Amortization of future-acquisition intangibles (M&A-related; added back in adjusted EPS) | CF62: 0 | CG62: =IFERROR((CF61+0.5*CG50*CG59)/CG60,0) -> 3.75 | CH62: =IFERROR((CG61+0.5*CH50*CH59)/CH60,0) -> 11.25 | CI62: =IFERROR((CH61+0.5*CI50*CI59)/CI60,0) -> 18.75 | CJ62: =IFERROR((CI61+0.5*CJ50*CJ59)/CJ60,0) -> 26.25 | CK62: =IFERROR((CJ61+0.5*CK50*CK59)/CK60,0) -> 33.75
B64: Group Total — net sales & gross margin (segment build) → Q2 FY27 guidance calibration | CL64: GROUP TOTAL (CONSOLIDATED) — modelling logic
B65: Net sales (segment build) | C65: =IF(ISNUMBER(C11),C11+C23,C108) -> 274.509 | D65: =IF(ISNUMBER(D11),D11+D23,D108) -> 306.062 | E65: =IF(ISNUMBER(E11),E11+E23,E108) -> 330.6 | F65: =IF(ISNUMBER(F11),F11+F23,F108) -> 355.796 | G65: =IF(ISNUMBER(G11),G11+G23,G108) -> 274.702 | H65: =IF(ISNUMBER(H11),H11+H23,H108) -> 335.625 | I65: =IF(ISNUMBER(I11),I11+I23,I108) -> 397.511 | J65: =IF(ISNUMBER(J11),J11+J23,J108) -> 103.334 | ... CB65: =IF(ISNUMBER(CB11),CB11+CB23,CB108) -> 519.5 | CC65: =CC11+CC23+N(CC55) -> 510 | CD65: =CD11+CD23+N(CD55) -> 510.99413 | CE65: =CE11+CE23+N(CE55) -> 616.6219 | CF65: =CF11+CF23+N(CF55) -> 2157.116 | CG65: =CG11+CG23+N(CG55) -> 2384.775 | CH65: =CH11+CH23+N(CH55) -> 2666.3714 | CI65: =CI11+CI23+N(CI55) -> 2949.3029 | CJ65: =CJ11+CJ23+N(CJ55) -> 3237.783 | CK65: =CK11+CK23+N(CK55) -> 3522.5516 | CL65: Σ segment sales (+ future acquisitions from FY2028E); history before the segment split = reported net sales. | CN65: =IFERROR((CK65/CF65)^(1/5)-1,"n/m") -> 0.103054 | CO65: =IFERROR((CA65/BB65)^(1/5)-1,"n/m") -> 0.25166739 | CP65: =IFERROR((CA65/AC65)^(1/10)-1,"n/m") -> 0.1209166 | CQ65: =IFERROR((CA65/C65)^(1/20)-1,"n/m") -> 0.10071453
B66: Net sales y/y % | D66: =IF(AND(ISNUMBER(D65),ISNUMBER(C65)),IFERROR(D65/C65-1,""),"") -> 0.11494341 | E66: =IF(AND(ISNUMBER(E65),ISNUMBER(D65)),IFERROR(E65/D65-1,""),"") -> 0.080173298 | F66: =IF(AND(ISNUMBER(F65),ISNUMBER(E65)),IFERROR(F65/E65-1,""),"") -> 0.076212946 | G66: =IF(AND(ISNUMBER(G65),ISNUMBER(F65)),IFERROR(G65/F65-1,""),"") -> -0.22792274 | H66: =IF(AND(ISNUMBER(H65),ISNUMBER(G65)),IFERROR(H65/G65-1,""),"") -> 0.22177851 | I66: =IF(AND(ISNUMBER(I65),ISNUMBER(H65)),IFERROR(I65/H65-1,""),"") -> 0.18439032 | N66: =IF(AND(ISNUMBER(N65),ISNUMBER(I65)),IFERROR(N65/I65-1,""),"") -> 0.013936721 | O66: =IF(AND(ISNUMBER(O65),ISNUMBER(J65)),IFERROR(O65/J65-1,""),"") -> -0.0064451197 | P66: =IF(AND(ISNUMBER(P65),ISNUMBER(K65)),IFERROR(P65/K65-1,""),"") -> 0.015731009 | Q66: =IF(AND(ISNUMBER(Q65),ISNUMBER(L65)),IFERROR(Q65/L65-1,""),"") -> 0.043701212 | R66: =IF(AND(ISNUMBER(R65),ISNUMBER(M65)),IFERROR(R65/M65-1,""),"") -> 0.10399394 | S66: =IF(AND(ISNUMBER(S65),ISNUMBER(N65)),IFERROR(S65/N65-1,""),"") -> 0.039287832 | T66: =IF(AND(ISNUMBER(T65),ISNUMBER(O65)),IFERROR(T65/O65-1,""),"") -> 0.10047921 | U66: =IF(AND(ISNUMBER(U65),ISNUMBER(P65)),IFERROR(U65/P65-1,""),"") -> 0.10397826 | ... CF66: =IF(AND(ISNUMBER(CF65),ISNUMBER(CA65)),IFERROR(CF65/CA65-1,""),"") -> 0.15298307 | CG66: =IF(AND(ISNUMBER(CG65),ISNUMBER(CF65)),IFERROR(CG65/CF65-1,""),"") -> 0.10553857 | CH66: =IF(AND(ISNUMBER(CH65),ISNUMBER(CG65)),IFERROR(CH65/CG65-1,""),"") -> 0.1180809 | CI66: =IF(AND(ISNUMBER(CI65),ISNUMBER(CH65)),IFERROR(CI65/CH65-1,""),"") -> 0.10611109 | CJ66: =IF(AND(ISNUMBER(CJ65),ISNUMBER(CI65)),IFERROR(CJ65/CI65-1,""),"") -> 0.097812952 | CK66: =IF(AND(ISNUMBER(CK65),ISNUMBER(CJ65)),IFERROR(CK65/CJ65-1,""),"") -> 0.087951753
B67: Check: segment build vs consolidated net sales (should be 0) | C67: =IF(ISNUMBER(C65),IF(ABS(C65-C108)<=0.15,0,ROUND(C65-C108,1)),"") -> 0 | D67: =IF(ISNUMBER(D65),IF(ABS(D65-D108)<=0.15,0,ROUND(D65-D108,1)),"") -> 0 | E67: =IF(ISNUMBER(E65),IF(ABS(E65-E108)<=0.15,0,ROUND(E65-E108,1)),"") -> 0 | F67: =IF(ISNUMBER(F65),IF(ABS(F65-F108)<=0.15,0,ROUND(F65-F108,1)),"") -> 0 | G67: =IF(ISNUMBER(G65),IF(ABS(G65-G108)<=0.15,0,ROUND(G65-G108,1)),"") -> 0 | H67: =IF(ISNUMBER(H65),IF(ABS(H65-H108)<=0.15,0,ROUND(H65-H108,1)),"") -> 0 | I67: =IF(ISNUMBER(I65),IF(ABS(I65-I108)<=0.15,0,ROUND(I65-I108,1)),"") -> 0 | J67: =IF(ISNUMBER(J65),IF(ABS(J65-J108)<=0.15,0,ROUND(J65-J108,1)),"") -> 0 | ... CK67: =IF(ISNUMBER(CK65),IF(ABS(CK65-CK108)<=0.15,0,ROUND(CK65-CK108,1)),"") -> 0
B68: Adjusted gross margin (segment build) | C68: =IF(ISNUMBER(C16),C16+C28+C104,"") | D68: =IF(ISNUMBER(D16),D16+D28+D104,"") | E68: =IF(ISNUMBER(E16),E16+E28+E104,"") | F68: =IF(ISNUMBER(F16),F16+F28+F104,"") | G68: =IF(ISNUMBER(G16),G16+G28+G104,"") | H68: =IF(ISNUMBER(H16),H16+H28+H104,"") | I68: =IF(ISNUMBER(I16),I16+I28+I104,"") | J68: =IF(ISNUMBER(J16),J16+J28+J104,"") | ... CB68: =IF(ISNUMBER(CB16),CB16+CB28+CB104,"") -> 247.8 | CC68: =CC16+CC28+N(CC57) -> 232.6875 | CD68: =CD16+CD28+N(CD57) -> 235.0135 | CE68: =CE16+CE28+N(CE57) -> 284.6821 | CF68: =CF16+CF28+N(CF57) -> 1000.1831 | CG68: =CG16+CG28+N(CG57) -> 1103.1821 | CH68: =CH16+CH28+N(CH57) -> 1236.4698 | CI68: =CI16+CI28+N(CI57) -> 1371.6289 | CJ68: =CJ16+CJ28+N(CJ57) -> 1502.2056 | CK68: =CK16+CK28+N(CK57) -> 1634.2066 | CL68: Σ segment gross margin (+ future acquisitions) + items adjusted out of cost of sales (history) = company adjusted gross margin; drives the GAAP P&L below. | CN68: =IFERROR((CK68/CF68)^(1/5)-1,"n/m") -> 0.10317773 | CO68: =IFERROR((CA68/BB68)^(1/5)-1,"n/m") -> 0.28946099 | CP68: =IFERROR((CA68/AC68)^(1/10)-1,"n/m") -> n/m | CQ68: =IFERROR((CA68/C68)^(1/20)-1,"n/m") -> n/m
B69: Adjusted gross margin % | C69: =IF(AND(ISNUMBER(C68),ISNUMBER(C108)),IFERROR(C68/C108,""),"") | D69: =IF(AND(ISNUMBER(D68),ISNUMBER(D108)),IFERROR(D68/D108,""),"") | E69: =IF(AND(ISNUMBER(E68),ISNUMBER(E108)),IFERROR(E68/E108,""),"") | F69: =IF(AND(ISNUMBER(F68),ISNUMBER(F108)),IFERROR(F68/F108,""),"") | G69: =IF(AND(ISNUMBER(G68),ISNUMBER(G108)),IFERROR(G68/G108,""),"") | H69: =IF(AND(ISNUMBER(H68),ISNUMBER(H108)),IFERROR(H68/H108,""),"") | I69: =IF(AND(ISNUMBER(I68),ISNUMBER(I108)),IFERROR(I68/I108,""),"") | J69: =IF(AND(ISNUMBER(J68),ISNUMBER(J108)),IFERROR(J68/J108,""),"") | ... CK69: =IF(AND(ISNUMBER(CK68),ISNUMBER(CK108)),IFERROR(CK68/CK108,""),"") -> 0.46392693 | CN69: =IFERROR(AVERAGE(CG69,CH69,CI69,CJ69,CK69),"n/m") -> 0.46385565 | CO69: =IFERROR(AVERAGE(BG69,BL69,BQ69,BV69,CA69),"n/m") -> 0.42632614 | CP69: =IFERROR(AVERAGE(AH69,AM69,AR69,AW69,BB69,BG69,BL69,BQ69,BV69,CA69),"n/m") -> 0.42018235 | CQ69: =IFERROR(AVERAGE(C69,D69,E69,F69,G69,H69,I69,N69,S69,X69,AC69,AH69,AM69,AR69,AW69,BB69,BG69,BL69,BQ69,BV69,CA69),"n/m") -> 0.42018235
B70: Check: segment build vs adjusted gross margin (should be 0) | C70: =IF(AND(ISNUMBER(C68),ISNUMBER(C112)),IF(ABS(C68-C112)<=0.15,0,ROUND(C68-C112,1)),"") | D70: =IF(AND(ISNUMBER(D68),ISNUMBER(D112)),IF(ABS(D68-D112)<=0.15,0,ROUND(D68-D112,1)),"") | E70: =IF(AND(ISNUMBER(E68),ISNUMBER(E112)),IF(ABS(E68-E112)<=0.15,0,ROUND(E68-E112,1)),"") | F70: =IF(AND(ISNUMBER(F68),ISNUMBER(F112)),IF(ABS(F68-F112)<=0.15,0,ROUND(F68-F112,1)),"") | G70: =IF(AND(ISNUMBER(G68),ISNUMBER(G112)),IF(ABS(G68-G112)<=0.15,0,ROUND(G68-G112,1)),"") | H70: =IF(AND(ISNUMBER(H68),ISNUMBER(H112)),IF(ABS(H68-H112)<=0.15,0,ROUND(H68-H112,1)),"") | I70: =IF(AND(ISNUMBER(I68),ISNUMBER(I112)),IF(ABS(I68-I112)<=0.15,0,ROUND(I68-I112,1)),"") | J70: =IF(AND(ISNUMBER(J68),ISNUMBER(J112)),IF(ABS(J68-J112)<=0.15,0,ROUND(J68-J112,1)),"") | ... CK70: =IF(AND(ISNUMBER(CK68),ISNUMBER(CK112)),IF(ABS(CK68-CK112)<=0.15,0,ROUND(CK68-CK112,1)),"") -> 0
B71: Memo: Q2 FY27 net sales guidance (scenario end-point) | CC71: =CHOOSE(MATCH($CL$2,{"Bull","Base","Bear"},0),$CU$12,$CV$12,$CW$12) -> 510 | CL71: Company Q2 FY27 net sales outlook $505.0–515.0m (Q1 FY27 release, 31-Jul-2026). Drives the sales calibration.
B72: Net sales before calibration (Q2/27E helper) | CC72: =BX11*(1+CC13)*CC34+CC14+BX23*(1+CC25)*CC34+CC26 -> 518.43906
B73: Net sales sensitivity to +1.00 of growth (Q2/27E helper) | CC73: =BX11*CC34+BX23*CC34 -> 455.3
B74: Guidance calibration: Δ y/y growth applied to both segments (solved in Q2/27E, carried to Q3–Q4/27E) | CC74: =(CC71-CC72)/CC73 -> -0.018535155 | CD74: =$CC$74 -> -0.018535155 | CE74: =$CC$74 -> -0.018535155 | CL74: Solves the uniform growth shift (vs Q1 FY27 organic rates) so that Q2 FY27 net sales = the guidance end-point for the active scenario; RBC guides one quarter ahead, so the same Δ is carried into Q3–Q4 (UBER precedent).
B75: Check: Q2 FY27 net sales vs guidance end-point (should be 0) | CC75: =ROUND(CC65-CC71,1) -> 0
B76: Memo: Q2 FY27 gross margin guidance (scenario end-point, %) | CC76: =CHOOSE(MATCH($CL$2,{"Bull","Base","Bear"},0),$CU$13,$CV$13,$CW$13) -> 0.45625 | CL76: Company Q2 FY27 gross margin outlook 45.5–45.75% (Q1 FY27 release). Drives the segment gross-margin calibration.
B77: Gross margin before calibration (Q2/27E helper) | CC77: =CC11*CC18+CC23*CC30 -> 239.13559
B78: Guidance calibration: Δ segment gross margin (solved in Q2/27E, carried to Q3–Q4/27E) | CC78: =(CC76*CC65-CC77)/(CC11+CC23) -> -0.012643323 | CD78: =$CC$78 -> -0.012643323 | CE78: =$CC$78 -> -0.012643323 | CL78: Solves the uniform segment gross-margin shift so that Q2 FY27 gross margin = the guidance end-point; carried into Q3–Q4.
B79: Check: Q2 FY27 gross margin % vs guidance end-point (should be 0.0%) | CC79: =ROUND(CC69-CC76,4) -> 0
B80: Memo: Q2 FY27 SG&A % of net sales guidance (scenario end-point; applied directly) | CC80: =CHOOSE(MATCH($CL$2,{"Bull","Base","Bear"},0),$CU$14,$CV$14,$CW$14) -> 0.16625
B81: Memo: FY2027E net sales y/y (output; RBC publishes no full-year guidance) | CF81: =CF65/CA65-1 -> 0.15298307
B83: Cost drivers, D&A & adjusting items | CL83: COST DRIVERS — inputs that drive forecast cost lines (Q2–Q4/27E: guidance / point estimates; FY2028E+: % of sales or schedules)
B84: SG&A % of net sales | C84: =IF(AND(ISNUMBER(C114),ISNUMBER(C108)),IFERROR(C114/C108,""),"") -> 0.15280009 | D84: =IF(AND(ISNUMBER(D114),ISNUMBER(D108)),IFERROR(D114/D108,""),"") -> 0.13806353 | E84: =IF(AND(ISNUMBER(E114),ISNUMBER(E108)),IFERROR(E114/E108,""),"") -> 0.14792498 | F84: =IF(AND(ISNUMBER(F114),ISNUMBER(F108)),IFERROR(F114/F108,""),"") -> 0.15677242 | G84: =IF(AND(ISNUMBER(G114),ISNUMBER(G108)),IFERROR(G114/G108,""),"") -> 0.17243049 | H84: =IF(AND(ISNUMBER(H114),ISNUMBER(H108)),IFERROR(H114/H108,""),"") -> 0.15703836 | I84: =IF(AND(ISNUMBER(I114),ISNUMBER(I108)),IFERROR(I114/I108,""),"") -> 0.15421712 | J84: =IF(AND(ISNUMBER(J114),ISNUMBER(J108)),IFERROR(J114/J108,""),"") -> 0.15577641 | ... CB84: =IF(AND(ISNUMBER(CB114),ISNUMBER(CB108)),IFERROR(CB114/CB108,""),"") -> 0.16515881 | CC84: =CC80 -> 0.16625 | CD84: =BY84+(CC84-BX84) -> 0.16501303 | CE84: =BZ84+(CC84-BX84) -> 0.16401281 | CF84: =IF(AND(ISNUMBER(CF114),ISNUMBER(CF108)),IFERROR(CF114/CF108,""),"") -> 0.16505467 | CG84: =CHOOSE(MATCH($CL$2,{"Bull","Base","Bear"},0),$CU$51,$CV$51,$CW$51) -> 0.163 | CH84: =CHOOSE(MATCH($CL$2,{"Bull","Base","Bear"},0),$CU$52,$CV$52,$CW$52) -> 0.162 | CI84: =CHOOSE(MATCH($CL$2,{"Bull","Base","Bear"},0),$CU$53,$CV$53,$CW$53) -> 0.161 | CJ84: =CHOOSE(MATCH($CL$2,{"Bull","Base","Bear"},0),$CU$54,$CV$54,$CW$54) -> 0.16 | CK84: =CHOOSE(MATCH($CL$2,{"Bull","Base","Bear"},0),$CU$55,$CV$55,$CW$55) -> 0.16 | CL84: Q2/27E: guided ratio (scenario end-point). Q3–Q4/27E: prior-year quarter ratio + the Q2 guided change vs Q2 FY26. FY2028E+: scenario lever. | CN84: =IFERROR(AVERAGE(CG84,CH84,CI84,CJ84,CK84),"n/m") -> 0.1612 | CO84: =IFERROR(AVERAGE(BG84,BL84,BQ84,BV84,CA84),"n/m") -> 0.16533635 | CP84: =IFERROR(AVERAGE(AH84,AM84,AR84,AW84,BB84,BG84,BL84,BQ84,BV84,CA84),"n/m") -> 0.16713382 | CQ84: =IFERROR(AVERAGE(C84,D84,E84,F84,G84,H84,I84,N84,S84,X84,AC84,AH84,AM84,AR84,AW84,BB84,BG84,BL84,BQ84,BV84,CA84),"n/m") -> 0.16291587
B85: Depreciation & amortization (total; cash-flow statement) | C85: 9.331 | D85: 9.646 | E85: 10.465 | F85: 12.16 | G85: 11.83 | H85: 12.971 | I85: 14.19 | J85: 3.683 | K85: 3.693 | L85: 3.698 | M85: 3.645 | N85: 14.719 | O85: 3.735 | P85: 3.855 | Q85: 3.718 | R85: 3.679 | S85: 14.987 | T85: 4.058 | U85: 4.009 | V85: 3.778 | W85: 3.2 | X85: 15.045 | Y85: 5.663 | Z85: 6.809 | AA85: 6.698 | AB85: 6.637 | AC85: 25.807 | AD85: 6.74 | AE85: 6.959 | AF85: 6.779 | AG85: 6.894 | AH85: 27.372 | AI85: 7.098 | AJ85: 7.14 | AK85: 6.958 | AL85: 7.164 | AM85: 28.36 | AN85: 7.313 | AO85: 7.639 | AP85: 7.31 | AQ85: 7.396 | AR85: 29.658 | AS85: 7.52 | AT85: 7.802 | AU85: 7.953 | AV85: 8.145 | AW85: 31.42 | AX85: 8.396 | AY85: 8.437 | AZ85: 7.979 | BA85: 7.932 | BB85: 32.744 | BC85: 8.212 | BD85: 8.645 | BE85: 20.498 | BF85: 28.177 | BG85: 65.532 | BH85: 28.642 | BI85: 28.426 | BJ85: 28.743 | BK85: 29.589 | BL85: 115.4 | BM85: 29.7 | BN85: 30 | BO85: 29.9 | BP85: 29.7 | BQ85: 119.3 | BR85: 30 | BS85: 30.2 | BT85: 29.7 | BU85: 30.1 | BV85: 120 | BW85: 29.6 | BX85: 32.9 | BY85: 32.9 | BZ85: 33.4 | CA85: 128.8 | CB85: 33.3 | CC85: =CC89+CC86 -> 32.891642 | CD85: =CD89+CD86 -> 32.91805 | CE85: =CE89+CE86 -> 35.909947 | CF85: =SUM(CB85:CE85) -> 135.01964 | CG85: =CG89+CG86 -> 146.1327 | CH85: =CH89+CH86 -> 159.1924 | CI85: =CI89+CI86 -> 169.22048 | CJ85: =CJ89+CJ86 -> 181.35692 | CK85: =CK89+CK86 -> 196.83045 | CL85: History: cash-flow statement (discrete quarters derived from year to date). | CN85: =IFERROR((CK85/CF85)^(1/5)-1,"n/m") -> 0.078298664 | CO85: =IFERROR((CA85/BB85)^(1/5)-1,"n/m") -> 0.31509409 | CP85: =IFERROR((CA85/AC85)^(1/10)-1,"n/m") -> 0.17440484 | CQ85: =IFERROR((CA85/C85)^(1/20)-1,"n/m") -> 0.14024817
B86: M&A-related amortization of intangibles (adjusted EPS add-back; FY2023+ as published) | BI86: 16.145 | BJ86: 16.276 | BK86: 16.278 | BL86: 65.11 | BM86: 16.258 | BN86: 16.347 | BO86: 16.463 | BP86: 16.409 | BQ86: 65.477 | BR86: 16.4 | BS86: 16.4 | BT86: 16.4 | BU86: 16.4 | BV86: 65.6 | BW86: 16.2 | BX86: 18.3 | BY86: 19.7 | BZ86: 19.5 | CA86: 73.7 | CB86: 19.5 | CC86: =CC87*CC88 -> 19.344 | CD86: =CD87*CD88 -> 19.344 | CE86: =CE87*CE88 -> 19.53 | CF86: =SUM(CB86:CE86) -> 77.718 | CG86: =CG87*CG88+N(CG62) -> 79.359 | CH86: =CH87*CH88+N(CH62) -> 84.534 | CI86: =CI87*CI88+N(CI62) -> 86.64 | CJ86: =CJ87*CJ88+N(CJ62) -> 90.699 | CK86: =CK87*CK88+N(CK62) -> 98.199 | CL86: Forecast: intangible-amortization schedule (10-Q) × M&A-related share + future-acquisition amortization. | CN86: =IFERROR((CK86/CF86)^(1/5)-1,"n/m") -> 0.047893363 | CO86: =IFERROR((CA86/BB86)^(1/5)-1,"n/m") -> n/m | CP86: =IFERROR((CA86/AC86)^(1/10)-1,"n/m") -> n/m | CQ86: =IFERROR((CA86/C86)^(1/20)-1,"n/m") -> n/m
B87: Amortization schedule — intangibles held at 27-Jun-2026 (10-Q, input) | CC87: 20.8 | CD87: 20.8 | CE87: 21 | CG87: 81.3 | CH87: 78.8 | CI87: 73 | CJ87: 69.3 | CK87: 69.3 | CL87: Q1 FY27 10-Q Note 8 (estimated amortization expense of intangible assets held at 27-Jun-2026): remainder of FY2027 $62.6m (split $20.8m / $20.8m / $21.0m), FY2028 $81.3m, FY2029 $78.8m, FY2030 $73.0m, FY2031 $69.3m, FY2032 $69.3m.
B88: M&A-related share of the amortization schedule % | CC88: 0.93 | CD88: 0.93 | CE88: 0.93 | CG88: 0.93 | CH88: 0.93 | CI88: 0.93 | CJ88: 0.93 | CK88: 0.93 | CL88: Q1 FY27: M&A-related amortization $19.5m of $21.0m total amortization of intangible assets (release text); the rest is mainly software.
B89: D&A excluding M&A-related amortization (depreciation + other amortization) | C89: =IF(AND(ISNUMBER(C86),ISNUMBER(C85)),C85-C86,"") | D89: =IF(AND(ISNUMBER(D86),ISNUMBER(D85)),D85-D86,"") | E89: =IF(AND(ISNUMBER(E86),ISNUMBER(E85)),E85-E86,"") | F89: =IF(AND(ISNUMBER(F86),ISNUMBER(F85)),F85-F86,"") | G89: =IF(AND(ISNUMBER(G86),ISNUMBER(G85)),G85-G86,"") | H89: =IF(AND(ISNUMBER(H86),ISNUMBER(H85)),H85-H86,"") | I89: =IF(AND(ISNUMBER(I86),ISNUMBER(I85)),I85-I86,"") | J89: =IF(AND(ISNUMBER(J86),ISNUMBER(J85)),J85-J86,"") | ... CB89: =IF(AND(ISNUMBER(CB86),ISNUMBER(CB85)),CB85-CB86,"") -> 13.8 | CC89: =CC108*CC90 -> 13.547642 | CD89: =CD108*CD90 -> 13.57405 | CE89: =CE108*CE90 -> 16.379947 | CF89: =SUM(CB89:CE89) -> 57.301639 | CG89: =CG108*CG90 -> 66.773699 | CH89: =CH108*CH90 -> 74.658398 | CI89: =CI108*CI90 -> 82.580482 | CJ89: =CJ108*CJ90 -> 90.657923 | CK89: =CK108*CK90 -> 98.631446
B90: D&A excl. M&A amortization % of net sales | C90: =IF(AND(ISNUMBER(C89),ISNUMBER(C108)),IFERROR(C89/C108,""),"") | D90: =IF(AND(ISNUMBER(D89),ISNUMBER(D108)),IFERROR(D89/D108,""),"") | E90: =IF(AND(ISNUMBER(E89),ISNUMBER(E108)),IFERROR(E89/E108,""),"") | F90: =IF(AND(ISNUMBER(F89),ISNUMBER(F108)),IFERROR(F89/F108,""),"") | G90: =IF(AND(ISNUMBER(G89),ISNUMBER(G108)),IFERROR(G89/G108,""),"") | H90: =IF(AND(ISNUMBER(H89),ISNUMBER(H108)),IFERROR(H89/H108,""),"") | I90: =IF(AND(ISNUMBER(I89),ISNUMBER(I108)),IFERROR(I89/I108,""),"") | J90: =IF(AND(ISNUMBER(J89),ISNUMBER(J108)),IFERROR(J89/J108,""),"") | ... CB90: =IF(AND(ISNUMBER(CB89),ISNUMBER(CB108)),IFERROR(CB89/CB108,""),"") -> 0.026564004 | CC90: =IFERROR(SUM(CB89:CB89)/SUM(CB108:CB108),0) -> 0.026564004 | CD90: =IFERROR(SUM(CB89:CB89)/SUM(CB108:CB108),0) -> 0.026564004 | CE90: =IFERROR(SUM(CB89:CB89)/SUM(CB108:CB108),0) -> 0.026564004 | CF90: =IF(AND(ISNUMBER(CF89),ISNUMBER(CF108)),IFERROR(CF89/CF108,""),"") -> 0.026564004 | CG90: 0.028 | CH90: 0.028 | CI90: 0.028 | CJ90: 0.028 | CK90: 0.028 | CN90: =IFERROR(AVERAGE(CG90,CH90,CI90,CJ90,CK90),"n/m") -> 0.028 | CO90: =IFERROR(AVERAGE(BG90,BL90,BQ90,BV90,CA90),"n/m") -> 0.032854819 | CP90: =IFERROR(AVERAGE(AH90,AM90,AR90,AW90,BB90,BG90,BL90,BQ90,BV90,CA90),"n/m") -> 0.032854819 | CQ90: =IFERROR(AVERAGE(C90,D90,E90,F90,G90,H90,I90,N90,S90,X90,AC90,AH90,AM90,AR90,AW90,BB90,BG90,BL90,BQ90,BV90,CA90),"n/m") -> 0.032854819
B91: Stock-based compensation (cash-flow statement) | C91: 0.365 | D91: 0.767 | E91: 1.255 | F91: 2.502 | G91: 3.182 | H91: 4.057 | I91: 4.121 | J91: 1.127 | K91: 1.313 | L91: 1.573 | M91: 1.275 | N91: 5.288 | O91: 1.22 | P91: 1.519 | Q91: 1.561 | R91: 1.533 | S91: 5.833 | T91: 1.767 | U91: 2.268 | V91: 2.196 | W91: 2.108 | X91: 8.339 | Y91: 2.132 | Z91: 2.496 | AA91: 2.565 | AB91: 3.007 | AC91: 10.2 | AD91: 2.774 | AE91: 3.178 | AF91: 2.962 | AG91: 3.197 | AH91: 12.111 | AI91: 3.228 | AJ91: 3.402 | AK91: 3.267 | AL91: 3.506 | AM91: 13.403 | AN91: 3.766 | AO91: 4.039 | AP91: 3.904 | AQ91: 4.378 | AR91: 16.087 | AS91: 4.802 | AT91: 5.059 | AU91: 5.135 | AV91: 5.154 | AW91: 20.15 | AX91: 5.438 | AY91: 5.231 | AZ91: 5.173 | BA91: 5.457 | BB91: 21.299 | BC91: 5.772 | BD91: 6.224 | BE91: 6.038 | BF91: 5.891 | BG91: 23.925 | BH91: 3.819 | BI91: 4.354 | BJ91: 2.874 | BK91: 2.953 | BL91: 14 | BM91: 5.4 | BN91: 3.7 | BO91: 4.2 | BP91: 4.1 | BQ91: 17.4 | BR91: 6.5 | BS91: 6.6 | BT91: 7.2 | BU91: 8.1 | BV91: 28.4 | BW91: 6.6 | BX91: 7.4 | BY91: 9.3 | BZ91: 11.2 | CA91: 34.5 | CB91: 6.7 | CC91: =CC108*CC92 -> 6.5774783 | CD91: =CD108*CD92 -> 6.5902997 | CE91: =CE108*CE92 -> 7.9525827 | CF91: =SUM(CB91:CE91) -> 27.820361 | CG91: =CG108*CG92 -> 42.92595 | CH91: =CH108*CH92 -> 47.994684 | CI91: =CI108*CI92 -> 53.087453 | CJ91: =CJ108*CJ92 -> 58.280093 | CK91: =CK108*CK92 -> 63.40593 | CL91: RBC adds stock compensation back in adjusted EPS (from Q2 FY23) and adjusted EBITDA; the DCF deducts it.
B92: Stock-based compensation % of net sales | C92: =IF(AND(ISNUMBER(C91),ISNUMBER(C108)),IFERROR(C91/C108,""),"") -> 0.0013296468 | D92: =IF(AND(ISNUMBER(D91),ISNUMBER(D108)),IFERROR(D91/D108,""),"") -> 0.0025060282 | E92: =IF(AND(ISNUMBER(E91),ISNUMBER(E108)),IFERROR(E91/E108,""),"") -> 0.0037961283 | F92: =IF(AND(ISNUMBER(F91),ISNUMBER(F108)),IFERROR(F91/F108,""),"") -> 0.0070321195 | G92: =IF(AND(ISNUMBER(G91),ISNUMBER(G108)),IFERROR(G91/G108,""),"") -> 0.011583461 | H92: =IF(AND(ISNUMBER(H91),ISNUMBER(H108)),IFERROR(H91/H108,""),"") -> 0.012087896 | I92: =IF(AND(ISNUMBER(I91),ISNUMBER(I108)),IFERROR(I91/I108,""),"") -> 0.010367009 | J92: =IF(AND(ISNUMBER(J91),ISNUMBER(J108)),IFERROR(J91/J108,""),"") -> 0.010906381 | ... CB92: =IF(AND(ISNUMBER(CB91),ISNUMBER(CB108)),IFERROR(CB91/CB108,""),"") -> 0.012897016 | CC92: =IFERROR(SUM(CB91:CB91)/SUM(CB108:CB108),0) -> 0.012897016 | CD92: =IFERROR(SUM(CB91:CB91)/SUM(CB108:CB108),0) -> 0.012897016 | CE92: =IFERROR(SUM(CB91:CB91)/SUM(CB108:CB108),0) -> 0.012897016 | CF92: =IF(AND(ISNUMBER(CF91),ISNUMBER(CF108)),IFERROR(CF91/CF108,""),"") -> 0.012897016 | CG92: 0.018 | CH92: 0.018 | CI92: 0.018 | CJ92: 0.018 | CK92: 0.018 | CN92: =IFERROR(AVERAGE(CG92,CH92,CI92,CJ92,CK92),"n/m") -> 0.018 | CO92: =IFERROR(AVERAGE(BG92,BL92,BQ92,BV92,CA92),"n/m") -> 0.016369891 | CP92: =IFERROR(AVERAGE(AH92,AM92,AR92,AW92,BB92,BG92,BL92,BQ92,BV92,CA92),"n/m") -> 0.020696036 | CQ92: =IFERROR(AVERAGE(C92,D92,E92,F92,G92,H92,I92,N92,S92,X92,AC92,AH92,AM92,AR92,AW92,BB92,BG92,BL92,BQ92,BV92,CA92),"n/m") -> 0.015167008
B93: Other, net excl. M&A amortization and adjusting items (other amortization, FX, other) | C93: =IF(ISNUMBER(C115),C115-N(C86)-(C157-C104),"") -> -4.362 | D93: =IF(ISNUMBER(D115),D115-N(D86)-(D157-D104),"") -> 0.007 | E93: =IF(ISNUMBER(E115),E115-N(E86)-(E157-E104),"") -> 0.724 | F93: =IF(ISNUMBER(F115),F115-N(F86)-(F157-F104),"") -> -0.505 | G93: =IF(ISNUMBER(G115),G115-N(G86)-(G157-G104),"") -> -1.523 | H93: =IF(ISNUMBER(H115),H115-N(H86)-(H157-H104),"") -> 1.732 | I93: =IF(ISNUMBER(I115),I115-N(I86)-(I157-I104),"") -> 1.629 | J93: =IF(ISNUMBER(J115),J115-N(J86)-(J157-J104),"") -> 0.352 | ... CB93: =IF(ISNUMBER(CB115),CB115-N(CB86)-(CB157-CB104),"") -> 1.3 | CC93: =$CV$20 -> 1.5 | CD93: =$CV$20 -> 1.5 | CE93: =$CV$20 -> 1.5 | CF93: =SUM(CB93:CE93) -> 5.8 | CG93: =CG108*CG94 -> 7.1543249 | CH93: =CH108*CH94 -> 7.9991141 | CI93: =CI108*CI94 -> 8.8479088 | CJ93: =CJ108*CJ94 -> 9.7133489 | CK93: =CK108*CK94 -> 10.567655 | CL93: History before FY2023 includes all amortization of intangibles (M&A-related amortization not published separately).
B94: Other, net excl. M&A amortization and items % of net sales | C94: =IF(AND(ISNUMBER(C93),ISNUMBER(C108)),IFERROR(C93/C108,""),"") -> -0.015890189 | D94: =IF(AND(ISNUMBER(D93),ISNUMBER(D108)),IFERROR(D93/D108,""),"") -> 2.2871183e-05 | E94: =IF(AND(ISNUMBER(E93),ISNUMBER(E108)),IFERROR(E93/E108,""),"") -> 0.0021899577 | F94: =IF(AND(ISNUMBER(F93),ISNUMBER(F108)),IFERROR(F93/F108,""),"") -> -0.0014193527 | G94: =IF(AND(ISNUMBER(G93),ISNUMBER(G108)),IFERROR(G93/G108,""),"") -> -0.0055441897 | H94: =IF(AND(ISNUMBER(H93),ISNUMBER(H108)),IFERROR(H93/H108,""),"") -> 0.0051605214 | I94: =IF(AND(ISNUMBER(I93),ISNUMBER(I108)),IFERROR(I93/I108,""),"") -> 0.0040979998 | J94: =IF(AND(ISNUMBER(J93),ISNUMBER(J108)),IFERROR(J93/J108,""),"") -> 0.0034064296 | ... CF94: =IF(AND(ISNUMBER(CF93),ISNUMBER(CF108)),IFERROR(CF93/CF108,""),"") -> 0.0026887752 | CG94: 0.003 | CH94: 0.003 | CI94: 0.003 | CJ94: 0.003 | CK94: 0.003
B95: Adjusting items (pre-tax, adjusted out by the company; forecast inputs):
B96: Restructuring & consolidation (plant moves, integration) | C96: 1.024 | D96: 5.455 | E96: 0.734 | F96: 1.231 | G96: 1.197 | H96: 0.219 | I96: 0 | J96: 0 | K96: 0 | L96: 0 | M96: 6.738 | N96: 6.738 | O96: 0.628 | P96: 0.87 | Q96: 0 | R96: 0 | S96: 1.498 | T96: 0 | U96: 6.382 | V96: 0.088 | W96: 0 | X96: 6.47 | Y96: 0.79 | Z96: 0.209 | AA96: 0 | AB96: 0 | AC96: 0.999 | AD96: 0 | AE96: 0.222 | AF96: 7.06 | AG96: 0 | AH96: 7.282 | AI96: 0 | AJ96: 6.494 | AK96: 1.091 | AL96: 0.397 | AM96: 7.982 | AN96: 0 | AO96: 0 | AP96: 0 | AQ96: 1.18 | AR96: 1.18 | AS96: 0 | AT96: 0.084 | AU96: 0.147 | AV96: 0.805 | AW96: 1.036 | AX96: 1.119 | AY96: 3.514 | AZ96: 1.341 | BA96: 1.273 | BB96: 7.247 | BC96: 0.557 | BD96: 1.987 | BE96: 0 | BF96: 0 | BG96: 2.544 | BH96: 0 | BI96: 0.017 | BJ96: 0 | BK96: 2.643 | BL96: 2.66 | BM96: 0.29 | BN96: 0.631 | BO96: 0.065 | BP96: 1.998 | BQ96: 2.984 | BR96: 0 | BS96: 0.5 | BT96: 0.1 | BU96: 0.9 | BV96: 1.5 | BW96: 4.1 | BX96: 3 | BY96: -0.2 | BZ96: -0.7 | CA96: 6.2 | CB96: 0.4 | CC96: =$CV$19 -> 0.5 | CD96: =$CV$19 -> 0.5 | CE96: =$CV$19 -> 0.5 | CF96: =SUM(CB96:CE96) -> 1.9 | CG96: 2 | CH96: 2 | CI96: 2 | CJ96: 2 | CK96: 2
B97: Transaction & related costs, transition services (acquisitions) | C97: 0 | D97: 0 | E97: 0 | F97: 0 | G97: 0 | H97: 0 | I97: 0 | J97: 0 | K97: 0 | L97: 0 | M97: 0 | N97: 0 | O97: 0 | P97: 0.374 | Q97: 0 | R97: 0 | S97: 0.501 | T97: 0 | U97: 0 | V97: 1.527 | W97: 0.06 | X97: 1.587 | Y97: 3.998 | Z97: 1.074 | AA97: 0.025 | AB97: 0 | AC97: 5.097 | AD97: 0 | AE97: 0 | AF97: 0 | AG97: 0 | AH97: 0 | AI97: 0 | AJ97: 0 | AK97: 0 | AL97: 0 | AM97: 0 | AN97: 0 | AO97: 0 | AP97: 0 | AQ97: 0 | AR97: 0 | AS97: 0 | AT97: 0.901 | AU97: 0 | AV97: 0 | AW97: 0.901 | AX97: 0 | AY97: 0 | AZ97: 0 | BA97: 0 | BB97: 0 | BC97: 0 | BD97: 1.433 | BE97: 30.443 | BF97: 12.528 | BG97: 44.404 | BH97: 3.787 | BI97: 3.984 | BJ97: 1.247 | BK97: -0.108 | BL97: 8.91 | BM97: 0 | BN97: 0.025 | BO97: 0.113 | BP97: 0.145 | BQ97: 0.283 | BR97: 0 | BS97: 0 | BT97: 0 | BU97: 0 | BV97: 0 | BW97: 0.1 | BX97: 4.2 | BY97: 4.6 | BZ97: 5.9 | CA97: 14.8 | CB97: 0 | CC97: 0.3 | CD97: 0 | CE97: 0 | CF97: =SUM(CB97:CE97) -> 0.3 | CG97: =CG50*CG98 -> 5 | CH97: =CH50*CH98 -> 5 | CI97: =CI50*CI98 -> 5 | CJ97: =CJ50*CJ98 -> 5 | CK97: =CK50*CK98 -> 5 | CL97: Q2/27E: PSC Couplings deal costs (assumption).
B98: Transaction costs % of acquisition spend | CG98: 0.02 | CH98: 0.02 | CI98: 0.02 | CJ98: 0.02 | CK98: 0.02
B99: Inventory purchase-accounting (fair-value step-up) | C99: 0 | D99: 0 | E99: 0 | F99: 0 | G99: 0 | H99: 0 | I99: 0 | J99: 0 | K99: 0 | L99: 0 | M99: 0 | N99: 0 | O99: 0 | P99: 0 | Q99: 0 | R99: 0 | S99: 0 | T99: 0 | U99: 0 | V99: 0 | W99: 0 | X99: 0 | Y99: 2.331 | Z99: 4.295 | AA99: 0.562 | AB99: 0 | AC99: 7.188 | AD99: 0.382 | AE99: 0 | AF99: 0 | AG99: 0 | AH99: 0.382 | AI99: 0 | AJ99: 0 | AK99: 0 | AL99: 0 | AM99: 0 | AN99: 0 | AO99: 0 | AP99: 0 | AQ99: 0 | AR99: 0 | AS99: 0 | AT99: 0.084 | AU99: 0.187 | AV99: 0.097 | AW99: 0.368 | AX99: 0 | AY99: 0 | AZ99: 0 | BA99: 0 | BB99: 0 | BC99: 0 | BD99: 0 | BE99: 0 | BF99: 0 | BG99: 0 | BH99: 0 | BI99: 0 | BJ99: 0 | BK99: 0 | BL99: 0 | BM99: 0 | BN99: 0 | BO99: 0 | BP99: 0 | BQ99: 0 | BR99: 0 | BS99: 0 | BT99: 0 | BU99: 0 | BV99: 0 | BW99: 0 | BX99: 0 | BY99: 0 | BZ99: 0 | CA99: 0 | CB99: 0 | CC99: =0 -> 0 | CD99: =0 -> 0 | CE99: =0 -> 0 | CF99: =SUM(CB99:CE99) -> 0 | CG99: =0 -> 0 | CH99: =0 -> 0 | CI99: =0 -> 0 | CJ99: =0 -> 0 | CK99: =0 -> 0
B100: Litigation / legal reserves | C100: 0 | D100: 0 | E100: 0 | F100: 0 | G100: 0 | H100: 0 | I100: 0 | J100: 0 | K100: 0 | L100: 0 | M100: 0 | N100: 0 | O100: 0 | P100: 0 | Q100: 0 | R100: 0 | S100: 0 | T100: 0 | U100: 0 | V100: 0 | W100: 0 | X100: 0 | Y100: 0 | Z100: 0 | AA100: 0 | AB100: 1.696 | AC100: 1.696 | AD100: 0 | AE100: 0 | AF100: 0 | AG100: 0 | AH100: 0 | AI100: 0 | AJ100: 0 | AK100: 0 | AL100: 0 | AM100: 0 | AN100: 0 | AO100: 0 | AP100: 0 | AQ100: 0 | AR100: 0 | AS100: 0 | AT100: 0 | AU100: 0 | AV100: 0 | AW100: 0 | AX100: 0 | AY100: 0 | AZ100: 0 | BA100: 0 | BB100: 0 | BC100: 0 | BD100: 0 | BE100: 0 | BF100: 0 | BG100: 0 | BH100: 0 | BI100: 0 | BJ100: 0 | BK100: 0 | BL100: 0 | BM100: 0 | BN100: 0 | BO100: 0 | BP100: 0 | BQ100: 0 | BR100: 0 | BS100: 0 | BT100: 0 | BU100: 0 | BV100: 0 | BW100: 0 | BX100: 0 | BY100: 0 | BZ100: 0 | CA100: 0 | CB100: 0 | CC100: =0 -> 0 | CD100: =0 -> 0 | CE100: =0 -> 0 | CF100: =SUM(CB100:CE100) -> 0 | CG100: =0 -> 0 | CH100: =0 -> 0 | CI100: =0 -> 0 | CJ100: =0 -> 0 | CK100: =0 -> 0
B101: (Gains) / losses on disposals | C101: 0.024 | D101: -0.294 | E101: 0.366 | F101: 4.445 | G101: 0.215 | H101: -1.076 | I101: 0 | J101: 0 | K101: 0 | L101: 0 | M101: 0.18 | N101: 0.18 | O101: 0 | P101: 0.043 | Q101: 0 | R101: 0 | S101: 0.043 | T101: 0 | U101: 0 | V101: 0 | W101: 0 | X101: 0 | Y101: 0 | Z101: 0 | AA101: 0 | AB101: 0 | AC101: 0 | AD101: 0 | AE101: 0 | AF101: 0 | AG101: 0 | AH101: 0 | AI101: 0 | AJ101: 0 | AK101: 0 | AL101: 0 | AM101: 0 | AN101: 0 | AO101: 0 | AP101: 16.802 | AQ101: -0.258 | AR101: 16.544 | AS101: 0 | AT101: 0 | AU101: 0 | AV101: -1.44 | AW101: -1.44 | AX101: 0 | AY101: 0 | AZ101: 0 | BA101: 0 | BB101: 0 | BC101: 0 | BD101: 0 | BE101: 0 | BF101: 0 | BG101: 0 | BH101: 0 | BI101: 0 | BJ101: 0 | BK101: 0 | BL101: 0 | BM101: 0 | BN101: 0 | BO101: 0 | BP101: 0 | BQ101: 0 | BR101: 0 | BS101: 0 | BT101: 0 | BU101: 0 | BV101: 0 | BW101: 0 | BX101: 0 | BY101: 0 | BZ101: 0 | CA101: 0 | CB101: 0 | CC101: =0 -> 0 | CD101: =0 -> 0 | CE101: =0 -> 0 | CF101: =SUM(CB101:CE101) -> 0 | CG101: =0 -> 0 | CH101: =0 -> 0 | CI101: =0 -> 0 | CJ101: =0 -> 0 | CK101: =0 -> 0
B102: Stock-option compensation (adjusted out of operating income FY2006–07 only) | C102: 0 | D102: 0.766 | E102: 0 | F102: 0 | G102: 0 | H102: 0 | I102: 0 | J102: 0 | K102: 0 | L102: 0 | M102: 0 | N102: 0 | O102: 0 | P102: 0 | Q102: 0 | R102: 0 | S102: 0 | T102: 0 | U102: 0 | V102: 0 | W102: 0 | X102: 0 | Y102: 0 | Z102: 0 | AA102: 0 | AB102: 0 | AC102: 0 | AD102: 0 | AE102: 0 | AF102: 0 | AG102: 0 | AH102: 0 | AI102: 0 | AJ102: 0 | AK102: 0 | AL102: 0 | AM102: 0 | AN102: 0 | AO102: 0 | AP102: 0 | AQ102: 0 | AR102: 0 | AS102: 0 | AT102: 0 | AU102: 0 | AV102: 0 | AW102: 0 | AX102: 0 | AY102: 0 | AZ102: 0 | BA102: 0 | BB102: 0 | BC102: 0 | BD102: 0 | BE102: 0 | BF102: 0 | BG102: 0 | BH102: 0 | BI102: 0 | BJ102: 0 | BK102: 0 | BL102: 0 | BM102: 0 | BN102: 0 | BO102: 0 | BP102: 0 | BQ102: 0 | BR102: 0 | BS102: 0 | BT102: 0 | BU102: 0 | BV102: 0 | BW102: 0 | BX102: 0 | BY102: 0 | BZ102: 0 | CA102: 0 | CB102: 0 | CC102: =0 -> 0 | CD102: =0 -> 0 | CE102: =0 -> 0 | CF102: =SUM(CB102:CE102) -> 0 | CG102: =0 -> 0 | CH102: =0 -> 0 | CI102: =0 -> 0 | CJ102: =0 -> 0 | CK102: =0 -> 0
...

Sheet Bull-Base-Bear
B2: RBC Bearings Incorporated (RBC) — Bull / Base / Bear Case P&L Summary | J2: Share price ($): | K2: =Model!$CG$393 -> 510
B3: Adjusted figures (company definitions: adjusted operating income, adjusted EBITDA, adjusted EPS — current definition) · USD millions · fiscal years ending ~31 March · Live panel linked to Model — toggle scenario via Model!CL2. Bull and Bear panels are value snapshots generated from the Model with the switch set to each case. FY2027E = Q1 actual + Q2 calibrated to the Q2 FY27 outlook (sales $505–515m, gross margin 45.5–45.75%) + Q3–Q4 with the same Δ. | J3: As of: | K3: =TODAY() -> 2026-10-13 00:00:00
B5: Scenario: | C5: =Model!$CL$2 -> Base | N5: Scenario: | O5: Bull | P5: Snapshot (values) — Model run with switch = Bull | Z5: Scenario: | AA5: Bear | AB5: Snapshot (values) — Model run with switch = Bear
B7: (USDm, except EPS and shares) | C7: 2027E | D7: 2028E | E7: 2029E | F7: 2030E | G7: 2031E | H7: 2032E | I7: 27-'32 CAGR | J7: LT Hist Avg | K7: LT Hist Min | L7: LT Hist Max | N7: (USDm, except EPS and shares) | O7: 2027E | P7: 2028E | Q7: 2029E | R7: 2030E | S7: 2031E | T7: 2032E | U7: 27-'32 CAGR | V7: LT Hist Avg | W7: LT Hist Min | X7: LT Hist Max | Z7: (USDm, except EPS and shares) | AA7: 2027E | AB7: 2028E | AC7: 2029E | AD7: 2030E | AE7: 2031E | AF7: 2032E | AG7: 27-'32 CAGR | AH7: LT Hist Avg | AI7: LT Hist Min | AJ7: LT Hist Max
B9: Net sales | C9: =Model!CF108 -> 2157.116 | D9: =Model!CG108 -> 2384.775 | E9: =Model!CH108 -> 2666.3714 | F9: =Model!CI108 -> 2949.3029 | G9: =Model!CJ108 -> 3237.783 | H9: =Model!CK108 -> 3522.5516 | I9: =IFERROR((H9/C9)^(1/5)-1,"n/m") -> 0.103054 | N9: Net sales | O9: 2173.3114 | P9: 2485.4767 | Q9: 2894.8113 | R9: 3319.0736 | S9: 3762.9974 | T9: 4216.9123 | U9: 0.14175921 | Z9: Net sales | AA9: 2140.9207 | AB9: 2198.3771 | AC9: 2243.2136 | AD9: 2274.0723 | AE9: 2295.6695 | AF9: 2301.194 | AG9: 0.014543164
B10: Net sales y/y % | D10: =IFERROR(D9/C9-1,"") -> 0.10553857 | E10: =IFERROR(E9/D9-1,"") -> 0.1180809 | F10: =IFERROR(F9/E9-1,"") -> 0.10611109 | G10: =IFERROR(G9/F9-1,"") -> 0.097812952 | H10: =IFERROR(H9/G9-1,"") -> 0.087951753 | N10: Net sales y/y % | P10: 0.1436358 | Q10: 0.16469061 | R10: 0.14655956 | S10: 0.13374929 | T10: 0.12062589 | Z10: Net sales y/y % | AB10: 0.026837221 | AC10: 0.020395294 | AD10: 0.013756443 | AE10: 0.0094971493 | AF10: 0.0024064937
B11: Aerospace & Defense sales y/y % | C11: =Model!CF217 -> 0.22416206 | D11: =Model!CG217 -> 0.11 | E11: =Model!CH217 -> 0.1 | F11: =Model!CI217 -> 0.09 | G11: =Model!CJ217 -> 0.08 | H11: =Model!CK217 -> 0.07 | N11: Aerospace & Defense sales y/y % | O11: 0.23308802 | P11: 0.14 | Q11: 0.13 | R11: 0.12 | S11: 0.11 | T11: 0.1 | Z11: Aerospace & Defense sales y/y % | AA11: 0.21523611 | AB11: 0.06 | AC11: 0.05 | AD11: 0.04 | AE11: 0.03 | AF11: 0.02
B12: Adjusted EBITDA | C12: =Model!CF179 -> 723.46302 | D12: =Model!CG179 -> 817.00911 | E12: =Model!CH179 -> 919.17164 | F12: =Model!CI179 -> 1023.6111 | G12: =Model!CJ179 -> 1123.385 | H12: =Model!CK179 -> 1222.068 | I12: =IFERROR((H12/C12)^(1/5)-1,"n/m") -> 0.1105441 | N12: Adjusted EBITDA | O12: 732.98677 | P12: 880.46334 | Q12: 1025.5206 | R12: 1178.3025 | S12: 1331.4106 | T12: 1488.3359 | U12: 0.15218168 | Z12: Adjusted EBITDA | AA12: 714.02024 | AB12: 690.77851 | AC12: 716.97415 | AD12: 739.22291 | AE12: 752.10774 | AF12: 759.91737 | AG12: 0.012537623
B13: Adjusted EBITDA margin % | C13: =IFERROR(C12/C9,"") -> 0.33538438 | D13: =IFERROR(D12/D9,"") -> 0.3425938 | E13: =IFERROR(E12/E9,"") -> 0.34472754 | F13: =IFERROR(F12/F9,"") -> 0.34706884 | G13: =IFERROR(G12/G9,"") -> 0.34696117 | H13: =IFERROR(H12/H9,"") -> 0.34692693 | J13: =IFERROR(AVERAGE(Model!C180,Model!D180,Model!E180,Model!F180,Model!G180,Model!H180,Model!I180,Model!N180,Model!S180,Model!X180,Model!AC180,Model!AH180,Model!AM180,Model!AR180,Model!AW180,Model!BB180,Model!BG180,Model!BL180,Model!BQ180,Model!BV180,Model!CA180),"") -> 0.26140804 | K13: =IFERROR(MIN(Model!C180,Model!D180,Model!E180,Model!F180,Model!G180,Model!H180,Model!I180,Model!N180,Model!S180,Model!X180,Model!AC180,Model!AH180,Model!AM180,Model!AR180,Model!AW180,Model!BB180,Model!BG180,Model!BL180,Model!BQ180,Model!BV180,Model!CA180),"") -> 0.19560833 | L13: =IFERROR(MAX(Model!C180,Model!D180,Model!E180,Model!F180,Model!G180,Model!H180,Model!I180,Model!N180,Model!S180,Model!X180,Model!AC180,Model!AH180,Model!AM180,Model!AR180,Model!AW180,Model!BB180,Model!BG180,Model!BL180,Model!BQ180,Model!BV180,Model!CA180),"") -> 0.32353413 | N13: Adjusted EBITDA margin % | O13: 0.33726726 | P13: 0.35424325 | Q13: 0.35426164 | R13: 0.35500946 | S13: 0.35381651 | T13: 0.35294448 | V13: 0.26140804 | W13: 0.19560833 | X13: 0.32353413 | Z13: Adjusted EBITDA margin % | AA13: 0.33351083 | AB13: 0.31422203 | AC13: 0.3196192 | AD13: 0.32506571 | AE13: 0.32762022 | AF13: 0.33022743 | AH13: 0.26140804 | AI13: 0.19560833 | AJ13: 0.32353413
B15: Operating income (GAAP) | C15: =Model!CF116 -> 558.42302 | D15: =Model!CG116 -> 620.95047 | E15: =Model!CH116 -> 704.98456 | F15: =Model!CI116 -> 794.3032 | G15: =Model!CJ116 -> 876.74794 | H15: =Model!CK116 -> 954.83164 | I15: =IFERROR((H15/C15)^(1/5)-1,"n/m") -> 0.11324998 | N15: Operating income (GAAP) | O15: 567.30768 | P15: 674.52241 | Q15: 791.0753 | R15: 917.73516 | S15: 1041.8637 | T15: 1165.909 | U15: 0.15496599 | Z15: Operating income (GAAP) | AA15: 549.61933 | AB15: 512.04417 | AC15: 538.50232 | AD15: 564.72558 | AE15: 580.05795 | AF15: 587.61345 | AG15: 0.013458445
B16: Operating income y/y % | D16: =IFERROR(D15/C15-1,"") -> 0.11197146 | E16: =IFERROR(E15/D15-1,"") -> 0.1353314 | F16: =IFERROR(F15/E15-1,"") -> 0.12669588 | G16: =IFERROR(G15/F15-1,"") -> 0.10379505 | H16: =IFERROR(H15/G15-1,"") -> 0.089060599 | N16: Operating income y/y % | P16: 0.18898867 | Q16: 0.1727932 | R16: 0.160111 | S16: 0.1352553 | T16: 0.11906093 | Z16: Operating income y/y % | AB16: -0.068365795 | AC16: 0.051671624 | AD16: 0.04869666 | AE16: 0.02715011 | AF16: 0.013025428
B17: Operating margin (GAAP) % | C17: =IFERROR(C15/C9,"") -> 0.25887482 | D17: =IFERROR(D15/D9,"") -> 0.26038116 | E17: =IFERROR(E15/E9,"") -> 0.26439849 | F17: =IFERROR(F15/F9,"") -> 0.26931896 | G17: =IFERROR(G15/G9,"") -> 0.27078651 | H17: =IFERROR(H15/H9,"") -> 0.27106249 | J17: =IFERROR(AVERAGE(Model!C228,Model!D228,Model!E228,Model!F228,Model!G228,Model!H228,Model!I228,Model!N228,Model!S228,Model!X228,Model!AC228,Model!AH228,Model!AM228,Model!AR228,Model!AW228,Model!BB228,Model!BG228,Model!BL228,Model!BQ228,Model!BV228,Model!CA228),"") -> 0.18525724 | K17: =IFERROR(MIN(Model!C228,Model!D228,Model!E228,Model!F228,Model!G228,Model!H228,Model!I228,Model!N228,Model!S228,Model!X228,Model!AC228,Model!AH228,Model!AM228,Model!AR228,Model!AW228,Model!BB228,Model!BG228,Model!BL228,Model!BQ228,Model!BV228,Model!CA228),"") -> 0.12620949 | L17: =IFERROR(MAX(Model!C228,Model!D228,Model!E228,Model!F228,Model!G228,Model!H228,Model!I228,Model!N228,Model!S228,Model!X228,Model!AC228,Model!AH228,Model!AM228,Model!AR228,Model!AW228,Model!BB228,Model!BG228,Model!BL228,Model!BQ228,Model!BV228,Model!CA228),"") -> 0.22605879 | N17: Operating margin (GAAP) % | O17: 0.26103378 | P17: 0.27138553 | Q17: 0.27327353 | R17: 0.27650341 | S17: 0.2768707 | T17: 0.27648404 | V17: 0.18525724 | W17: 0.12620949 | X17: 0.22605879 | Z17: Operating margin (GAAP) % | AA17: 0.25672101 | AB17: 0.23291917 | AC17: 0.24005842 | AD17: 0.24833229 | AE17: 0.25267485 | AF17: 0.25535155 | AH17: 0.18525724 | AI17: 0.12620949 | AJ17: 0.22605879
B19: Adjusted Net Income (to common) | C19: =Model!CF201 -> 491.12988 | D19: =Model!CG201 -> 560.40958 | E19: =Model!CH201 -> 620.04944 | F19: =Model!CI201 -> 688.9146 | G19: =Model!CJ201 -> 753.95524 | H19: =Model!CK201 -> 820.3889 | I19: =IFERROR((H19/C19)^(1/5)-1,"n/m") -> 0.10806359 | N19: Adjusted Net Income (to common) | O19: 498.22284 | P19: 607.47278 | Q19: 677.99492 | R19: 776.78594 | S19: 874.95404 | T19: 977.82183 | U19: 0.14437199 | Z19: Adjusted Net Income (to common) | AA19: 484.10008 | AB19: 466.55765 | AC19: 488.71607 | AD19: 503.10919 | AE19: 510.47682 | AF19: 516.30954 | AG19: 0.012966307
B21: FDSO (m) | C21: =Model!CF141 -> 31.744686 | D21: =Model!CG141 -> 31.435132 | E21: =Model!CH141 -> 30.746464 | F21: =Model!CI141 -> 30.219927 | G21: =Model!CJ141 -> 29.641862 | H21: =Model!CK141 -> 29.042475 | I21: =IFERROR((H21/C21)^(1/5)-1,"n/m") -> -0.017635822 | N21: FDSO (m) | O21: 31.744686 | P21: 31.090555 | Q21: 30.079967 | R21: 29.568066 | S21: 28.949695 | T21: 28.263129 | U21: -0.022965631 | Z21: FDSO (m) | AA21: 31.744686 | AB21: 31.687012 | AC21: 31.146111 | AD21: 30.46446 | AE21: 29.827319 | AF21: 29.249599 | AG21: -0.016238602
B23: Adjusted EPS — Diluted ($) | C23: =Model!CF203 -> 15.471247 | D23: =Model!CG203 -> 17.827492 | E23: =Model!CH203 -> 20.166529 | F23: =Model!CI203 -> 22.7967 | G23: =Model!CJ203 -> 25.435488 | H23: =Model!CK203 -> 28.247899 | I23: =IFERROR((H23/C23)^(1/5)-1,"n/m") -> 0.12795602 | N23: Adjusted EPS — Diluted ($) | O23: 15.694685 | P23: 19.538821 | Q23: 22.539749 | R23: 26.27111 | S23: 30.223256 | T23: 34.597083 | U23: 0.17127097 | Z23: Adjusted EPS — Diluted ($) | AA23: 15.249799 | AB23: 14.72394 | AC23: 15.691079 | AD23: 16.514627 | AE23: 17.114405 | AF23: 17.65185 | AG23: 0.029686983
B24: EPS y/y % | D24: =IFERROR(D23/C23-1,"") -> 0.15229835 | E24: =IFERROR(E23/D23-1,"") -> 0.13120388 | F24: =IFERROR(F23/E23-1,"") -> 0.13042262 | G24: =IFERROR(G23/F23-1,"") -> 0.11575309 | H24: =IFERROR(H23/G23-1,"") -> 0.11057033 | N24: EPS y/y % | P24: 0.24493236 | Q24: 0.153588 | R24: 0.16554582 | S24: 0.15043693 | T24: 0.14471729 | Z24: EPS y/y % | AB24: -0.034483024 | AC24: 0.065684784 | AD24: 0.052485126 | AE24: 0.036317994 | AF24: 0.031403091
B26: P / E (x) — assumed (adjusted EPS) | G26: 32 | H26: 32 | N26: P / E (x) — assumed (adjusted EPS) | S26: 36 | T26: 36 | Z26: P / E (x) — assumed (adjusted EPS) | AD26: 25 | AE26: 25 | AF26: 25
B27: Price Target ($) | G27: =G26*G23 -> 813.93563 | H27: =H26*H23 -> 903.93276 | N27: Price Target ($) | S27: =S26*S23 -> 1088.0372 | T27: =T26*T23 -> 1245.495 | Z27: Price Target ($) | AD27: =AD26*AD23 -> 412.86567 | AE27: =AE26*AE23 -> 427.86012 | AF27: =AF26*AF23 -> 441.29625
B28: Upside / (Downside) vs current | G28: =IFERROR(G27/$K$2-1,"") -> 0.59595222 | H28: =IFERROR(H27/$K$2-1,"") -> 0.77241719 | N28: Upside / (Downside) vs current | S28: =IFERROR(S27/$K$2-1,"") -> 1.1334063 | T28: =IFERROR(T27/$K$2-1,"") -> 1.4421471 | Z28: Upside / (Downside) vs current | AD28: =IFERROR(AD27/$K$2-1,"") -> -0.19045947 | AE28: =IFERROR(AE27/$K$2-1,"") -> -0.16105859 | AF28: =IFERROR(AF27/$K$2-1,"") -> -0.13471323
B29: IRR (to ~31-Mar of Y-1) | G29: =IFERROR((G27/$K$2)^(1/((DATE(2031-1,3,31)-$K$3)/365.25))-1,"") -> 0.1445084 | H29: =IFERROR((H27/$K$2)^(1/((DATE(2032-1,3,31)-$K$3)/365.25))-1,"") -> 0.13683804 | N29: IRR (to ~31-Mar of Y-1) | S29: =IFERROR((S27/$K$2)^(1/((DATE(2031-1,3,31)-$K$3)/365.25))-1,"") -> 0.24455793 | T29: =IFERROR((T27/$K$2)^(1/((DATE(2032-1,3,31)-$K$3)/365.25))-1,"") -> 0.22149533 | Z29: IRR (to ~31-Mar of Y-1) | AD29: =IFERROR((AD27/$K$2)^(1/((DATE(2030-1,3,31)-$K$3)/365.25))-1,"") -> -0.082174408 | AE29: =IFERROR((AE27/$K$2)^(1/((DATE(2031-1,3,31)-$K$3)/365.25))-1,"") -> -0.04944196 | AF29: =IFERROR((AF27/$K$2)^(1/((DATE(2032-1,3,31)-$K$3)/365.25))-1,"") -> -0.031903072
B31: Free Cash Flow | C31: =Model!CF257 -> 380.25447 | D31: =Model!CG257 -> 476.87711 | E31: =Model!CH257 -> 526.41701 | F31: =Model!CI257 -> 605.98123 | G31: =Model!CJ257 -> 663.30601 | H31: =Model!CK257 -> 720.30829 | I31: =IFERROR((H31/C31)^(1/5)-1,"n/m") -> 0.13628904 | N31: Free Cash Flow | O31: 382.0972 | P31: 500.93474 | Q31: 534.03671 | R31: 641.55513 | S31: 728.21924 | T31: 815.87445 | U31: 0.16383093 | Z31: Free Cash Flow | AA31: 378.49844 | AB31: 422.78235 | AC31: 489.347 | AD31: 514.82844 | AE31: 517.84261 | AF31: 520.51189 | AG31: 0.065794103
B32: FCF % | C32: =IFERROR(C31/C9,"") -> 0.1762791 | D32: =IFERROR(D31/D9,"") -> 0.19996734 | E32: =IFERROR(E31/E9,"") -> 0.19742824 | F32: =IFERROR(F31/F9,"") -> 0.20546592 | G32: =IFERROR(G31/G9,"") -> 0.20486426 | H32: =IFERROR(H31/H9,"") -> 0.20448481 | J32: =IFERROR(AVERAGE(Model!C260,Model!D260,Model!E260,Model!F260,Model!G260,Model!H260,Model!I260,Model!N260,Model!S260,Model!X260,Model!AC260,Model!AH260,Model!AM260,Model!AR260,Model!AW260,Model!BB260,Model!BG260,Model!BL260,Model!BQ260,Model!BV260,Model!CA260),"") -> 0.11532151 | K32: =IFERROR(MIN(Model!C260,Model!D260,Model!E260,Model!F260,Model!G260,Model!H260,Model!I260,Model!N260,Model!S260,Model!X260,Model!AC260,Model!AH260,Model!AM260,Model!AR260,Model!AW260,Model!BB260,Model!BG260,Model!BL260,Model!BQ260,Model!BV260,Model!CA260),"") -> 0.028188143 | L32: =IFERROR(MAX(Model!C260,Model!D260,Model!E260,Model!F260,Model!G260,Model!H260,Model!I260,Model!N260,Model!S260,Model!X260,Model!AC260,Model!AH260,Model!AM260,Model!AR260,Model!AW260,Model!BB260,Model!BG260,Model!BL260,Model!BQ260,Model!BV260,Model!CA260),"") -> 0.23100935 | N32: FCF % | O32: 0.17581337 | P32: 0.20154474 | Q32: 0.18448066 | R32: 0.19329343 | S32: 0.19352106 | T32: 0.19347674 | V32: 0.11532151 | W32: 0.028188143 | X32: 0.23100935 | Z32: FCF % | AA32: 0.17679237 | AB32: 0.19231567 | AC32: 0.21814552 | AD32: 0.22639054 | AE32: 0.22557368 | AF32: 0.2261921 | AH32: 0.11532151 | AI32: 0.028188143 | AJ32: 0.23100935
B33: FCF / share ($) | C33: =IFERROR(C31/C21,"") -> 11.978523 | D33: =IFERROR(D31/D21,"") -> 15.170196 | E33: =IFERROR(E31/E21,"") -> 17.121221 | F33: =IFERROR(F31/F21,"") -> 20.052373 | G33: =IFERROR(G31/G21,"") -> 22.377339 | H33: =IFERROR(H31/H21,"") -> 24.801891 | N33: FCF / share ($) | O33: 12.036572 | P33: 16.11212 | Q33: 17.753899 | R33: 21.697568 | S33: 25.154643 | T33: 28.867096 | Z33: FCF / share ($) | AA33: 11.923206 | AB33: 13.342449 | AC33: 15.711336 | AD33: 16.899313 | AE33: 17.361353 | AF33: 17.795522
B34: FCF Yield (on PT) | F34: =IFERROR(F33/F$27,"") | G34: =IFERROR(G33/G$27,"") -> 0.027492763 | H34: =IFERROR(H33/H$27,"") -> 0.027437761 | N34: FCF Yield (on PT) | R34: =IFERROR(R33/R$27,"") | S34: =IFERROR(S33/S$27,"") -> 0.023119285 | T34: =IFERROR(T33/T$27,"") -> 0.023177207 | Z34: FCF Yield (on PT) | AD34: =IFERROR(AD33/AD$27,"") -> 0.040931746 | AE34: =IFERROR(AE33/AE$27,"") -> 0.040577169 | AF34: =IFERROR(AF33/AF$27,"") -> 0.040325568
B35: Adjusted EBITDA (leverage basis) | C35: =Model!CF179 -> 723.46302 | D35: =Model!CG179 -> 817.00911 | E35: =Model!CH179 -> 919.17164 | F35: =Model!CI179 -> 1023.6111 | G35: =Model!CJ179 -> 1123.385 | H35: =Model!CK179 -> 1222.068 | I35: =IFERROR((H35/C35)^(1/5)-1,"n/m") -> 0.1105441 | N35: Adjusted EBITDA (leverage basis) | O35: 732.98677 | P35: 880.46334 | Q35: 1025.5206 | R35: 1178.3025 | S35: 1331.4106 | T35: 1488.3359 | U35: 0.15218168 | Z35: Adjusted EBITDA (leverage basis) | AA35: 714.02024 | AB35: 690.77851 | AC35: 716.97415 | AD35: 739.22291 | AE35: 752.10774 | AF35: 759.91737 | AG35: 0.012537623
B36: Adjusted EBITDA % of net sales | C36: =IFERROR(C35/C9,"") -> 0.33538438 | D36: =IFERROR(D35/D9,"") -> 0.3425938 | E36: =IFERROR(E35/E9,"") -> 0.34472754 | F36: =IFERROR(F35/F9,"") -> 0.34706884 | G36: =IFERROR(G35/G9,"") -> 0.34696117 | H36: =IFERROR(H35/H9,"") -> 0.34692693 | J36: =IFERROR(AVERAGE(Model!C227,Model!D227,Model!E227,Model!F227,Model!G227,Model!H227,Model!I227,Model!N227,Model!S227,Model!X227,Model!AC227,Model!AH227,Model!AM227,Model!AR227,Model!AW227,Model!BB227,Model!BG227,Model!BL227,Model!BQ227,Model!BV227,Model!CA227),"") -> 0.26140804 | K36: =IFERROR(MIN(Model!C227,Model!D227,Model!E227,Model!F227,Model!G227,Model!H227,Model!I227,Model!N227,Model!S227,Model!X227,Model!AC227,Model!AH227,Model!AM227,Model!AR227,Model!AW227,Model!BB227,Model!BG227,Model!BL227,Model!BQ227,Model!BV227,Model!CA227),"") -> 0.19560833 | L36: =IFERROR(MAX(Model!C227,Model!D227,Model!E227,Model!F227,Model!G227,Model!H227,Model!I227,Model!N227,Model!S227,Model!X227,Model!AC227,Model!AH227,Model!AM227,Model!AR227,Model!AW227,Model!BB227,Model!BG227,Model!BL227,Model!BQ227,Model!BV227,Model!CA227),"") -> 0.32353413 | N36: Adjusted EBITDA % of net sales | O36: 0.33726726 | P36: 0.35424325 | Q36: 0.35426164 | R36: 0.35500946 | S36: 0.35381651 | T36: 0.35294448 | V36: 0.26140804 | W36: 0.19560833 | X36: 0.32353413 | Z36: Adjusted EBITDA % of net sales | AA36: 0.33351083 | AB36: 0.31422203 | AC36: 0.3196192 | AD36: 0.32506571 | AE36: 0.32762022 | AF36: 0.33022743 | AH36: 0.26140804 | AI36: 0.19560833 | AJ36: 0.32353413
B38: Net Debt | C38: =Model!CF387 -> 470.54553 | D38: =Model!CG387 -> 817.00911 | E38: =Model!CH387 -> 919.17164 | F38: =Model!CI387 -> 1023.6111 | G38: =Model!CJ387 -> 1123.385 | H38: =Model!CK387 -> 1222.068 | N38: Net Debt | O38: 468.7028 | P38: 1320.695 | Q38: 1538.2809 | R38: 1767.4538 | S38: 1997.1159 | T38: 2232.5039 | Z38: Net Debt | AA38: 472.30156 | AB38: 345.38926 | AC38: 358.48707 | AD38: 369.61145 | AE38: 376.05387 | AF38: 379.95869
B39: Net Debt / Adjusted EBITDA (x) | C39: =IFERROR(C38/C35,"") -> 0.65040717 | D39: =IFERROR(D38/D35,"") -> 1 | E39: =IFERROR(E38/E35,"") -> 1 | F39: =IFERROR(F38/F35,"") -> 1 | G39: =IFERROR(G38/G35,"") -> 1 | H39: =IFERROR(H38/H35,"") -> 1 | N39: Net Debt / Adjusted EBITDA (x) | O39: 0.63944238 | P39: 1.5 | Q39: 1.5 | R39: 1.5 | S39: 1.5 | T39: 1.5 | Z39: Net Debt / Adjusted EBITDA (x) | AA39: 0.66146803 | AB39: 0.5 | AC39: 0.5 | AD39: 0.5 | AE39: 0.5 | AF39: 0.5
B40: Share repurchases ($m; open market, ex withholding) | D40: =Model!CG270 -> 573.34069 | E40: =Model!CH270 -> 378.57954 | F40: =Model!CI270 -> 460.42072 | G40: =Model!CJ270 -> 513.07983 | H40: =Model!CK270 -> 568.99135 | N40: Share repurchases ($m; open market, ex withholding) | P40: 952.92694 | Q40: 351.62263 | R40: 470.72802 | S40: 557.8813 | T40: 651.26247 | AB40: 295.87005 | AC40: 502.44482 | AD40: 525.95282 | AE40: 524.28502 | AF40: 524.41671
B41: Implied avg buyback price ($) | D41: =Model!CG269 -> 550.8 | E41: =Model!CH269 -> 594.864 | F41: =Model!CI269 -> 642.45312 | G41: =Model!CJ269 -> 693.84937 | H41: =Model!CK269 -> 749.35732 | N41: Implied avg buyback price ($) | P41: 550.8 | Q41: 594.864 | R41: 642.45312 | S41: 693.84937 | T41: 749.35732 | AB41: 550.8 | AC41: 594.864 | AD41: 642.45312 | AE41: 693.84937 | AF41: 749.35732
B42: Shares repurchased (m) | D42: =Model!CG271 -> 1.0409236 | E42: =Model!CH271 -> 0.6364136 | F42: =Model!CI271 -> 0.71666041 | G42: =Model!CJ271 -> 0.73946861 | H42: =Model!CK271 -> 0.75930579 | N42: Shares repurchased (m) | P42: 1.730078 | Q42: 0.59109752 | R42: 0.73270407 | S42: 0.80403805 | T42: 0.86909469 | AB42: 0.53716421 | AC42: 0.84463814 | AD42: 0.81866334 | AE42: 0.75561793 | AF42: 0.69982196
B44: ROIC | C44: =Model!CF370 -> 0.10272164 | D44: =Model!CG370 -> 0.10742003 | E44: =Model!CH370 -> 0.11471249 | F44: =Model!CI370 -> 0.12228657 | G44: =Model!CJ370 -> 0.12797612 | H44: =Model!CK370 -> 0.13240787 | J44: =IFERROR(AVERAGE(Model!C370,Model!D370,Model!E370,Model!F370,Model!G370,Model!H370,Model!I370,Model!N370,Model!S370,Model!X370,Model!AC370,Model!AH370,Model!AM370,Model!AR370,Model!AW370,Model!BB370,Model!BG370,Model!BL370,Model!BQ370,Model!BV370,Model!CA370),"") -> 0.11263111 | K44: =IFERROR(MIN(Model!C370,Model!D370,Model!E370,Model!F370,Model!G370,Model!H370,Model!I370,Model!N370,Model!S370,Model!X370,Model!AC370,Model!AH370,Model!AM370,Model!AR370,Model!AW370,Model!BB370,Model!BG370,Model!BL370,Model!BQ370,Model!BV370,Model!CA370),"") -> 0.039948322 | L44: =IFERROR(MAX(Model!C370,Model!D370,Model!E370,Model!F370,Model!G370,Model!H370,Model!I370,Model!N370,Model!S370,Model!X370,Model!AC370,Model!AH370,Model!AM370,Model!AR370,Model!AW370,Model!BB370,Model!BG370,Model!BL370,Model!BQ370,Model!BV370,Model!CA370),"") -> 0.16854484 | N44: ROIC | O44: 0.10422078 | P44: 0.11275862 | Q44: 0.11990058 | R44: 0.12751923 | S44: 0.13353192 | T44: 0.13852951 | V44: 0.11263111 | W44: 0.039948322 | X44: 0.16854484 | Z44: ROIC | AA44: 0.10123421 | AB44: 0.093914386 | AC44: 0.099995872 | AD44: 0.10636643 | AE44: 0.11065862 | AF44: 0.11347671 | AH44: 0.11263111 | AI44: 0.039948322 | AJ44: 0.16854484
B45: RONTA | C45: =Model!CF381 -> 0.28561418 | D45: =Model!CG381 -> 0.29256122 | E45: =Model!CH381 -> 0.3052408 | F45: =Model!CI381 -> 0.31969823 | G45: =Model!CJ381 -> 0.328226 | H45: =Model!CK381 -> 0.33236244 | J45: =IFERROR(AVERAGE(Model!C381,Model!D381,Model!E381,Model!F381,Model!G381,Model!H381,Model!I381,Model!N381,Model!S381,Model!X381,Model!AC381,Model!AH381,Model!AM381,Model!AR381,Model!AW381,Model!BB381,Model!BG381,Model!BL381,Model!BQ381,Model!BV381,Model!CA381),"") -> 0.15926997 | K45: =IFERROR(MIN(Model!C381,Model!D381,Model!E381,Model!F381,Model!G381,Model!H381,Model!I381,Model!N381,Model!S381,Model!X381,Model!AC381,Model!AH381,Model!AM381,Model!AR381,Model!AW381,Model!BB381,Model!BG381,Model!BL381,Model!BQ381,Model!BV381,Model!CA381),"") -> 0.081484184 | L45: =IFERROR(MAX(Model!C381,Model!D381,Model!E381,Model!F381,Model!G381,Model!H381,Model!I381,Model!N381,Model!S381,Model!X381,Model!AC381,Model!AH381,Model!AM381,Model!AR381,Model!AW381,Model!BB381,Model!BG381,Model!BL381,Model!BQ381,Model!BV381,Model!CA381),"") -> 0.25242312 | N45: RONTA | O45: 0.28914826 | P45: 0.31059453 | Q45: 0.32327794 | R45: 0.33807283 | S45: 0.34722586 | T45: 0.35214837 | V45: 0.15926997 | W45: 0.081484184 | X45: 0.25242312 | Z45: RONTA | AA45: 0.2821016 | AB45: 0.23698516 | AC45: 0.24811162 | AD45: 0.26062182 | AE45: 0.26684562 | AF45: 0.26857611 | AH45: 0.15926997 | AI45: 0.081484184 | AJ45: 0.25242312
B47: Implied Market Cap (USDm) | F47: =F27*F21 -> 0 | G47: =G27*G21 -> 24126.568 | H47: =H27*H21 -> 26252.445 | N47: Implied Market Cap (USDm) | R47: =R27*R21 -> 0 | S47: =S27*S21 -> 31498.346 | T47: =T27*T21 -> 35201.586 | Z47: Implied Market Cap (USDm) | AD47: =AD27*AD21 -> 12577.73 | AE47: =AE27*AE21 -> 12761.92 | AF47: =AF27*AF21 -> 12907.739
B48: (+) Net Debt & NCI | F48: =F38+Model!CI397 -> 1023.6111 | G48: =G38+Model!CJ397 -> 1123.385 | H48: =H38+Model!CK397 -> 1222.068 | N48: (+) Net Debt & NCI | R48: =R38+Model!CI397 -> 1767.4538 | S48: =S38+Model!CJ397 -> 1997.1159 | T48: =T38+Model!CK397 -> 2232.5039 | Z48: (+) Net Debt & NCI | AD48: =AD38+Model!CI397 -> 369.61145 | AE48: =AE38+Model!CJ397 -> 376.05387 | AF48: =AF38+Model!CK397 -> 379.95869
B49: Implied Enterprise Value (USDm) | F49: =F47+F48 -> 1023.6111 | G49: =G47+G48 -> 25249.953 | H49: =H47+H48 -> 27474.513 | N49: Implied Enterprise Value (USDm) | R49: =R47+R48 -> 1767.4538 | S49: =S47+S48 -> 33495.461 | T49: =T47+T48 -> 37434.09 | Z49: Implied Enterprise Value (USDm) | AD49: =AD47+AD48 -> 12947.341 | AE49: =AE47+AE48 -> 13137.974 | AF49: =AF47+AF48 -> 13287.697
B50: Implied EV / Adjusted EBITDA (x) | F50: =IFERROR(F49/F35,"") -> 1 | G50: =IFERROR(G49/G35,"") -> 22.47667 | H50: =IFERROR(H49/H35,"") -> 22.481983 | N50: Implied EV / Adjusted EBITDA (x) | R50: =IFERROR(R49/R35,"") -> 1.5 | S50: =IFERROR(S49/S35,"") -> 25.157875 | T50: =IFERROR(T49/T35,"") -> 25.15164 | Z50: Implied EV / Adjusted EBITDA (x) | AD50: =IFERROR(AD49/AD35,"") -> 17.5148 | AE50: =IFERROR(AE49/AE35,"") -> 17.468208 | AF50: =IFERROR(AF49/AF35,"") -> 17.485713

Sheet DCF
B2: DCF VALUATION — RBC BEARINGS INCORPORATED (RBC)
B4: 1. WACC BUILD
B5: Risk-free rate (US 10Y govt) | C5: 0.0425 | D5: Assumption (~US 10Y Treasury yield, Oct-2026; government rate sources are not reachable from the build environment); update to market
B6: Equity risk premium | C6: 0.05 | D6: Assumption: US implied ERP ~4.5–5.5%
B7: Levered beta | C7: 1.05 | D7: Assumption: precision-components / aerospace peers (TDG, HEI, CW, TKR, KMT) ~0.9–1.3; ~58% of sales Industrial (cyclical: mining, construction, oil & gas)
B8: Cost of equity | C8: =C5+C7*C6 -> 0.095
B9: Pre-tax cost of debt | C9: 0.055 | D9: Assumption: 4.375% senior notes due 2029 and the revolver at SOFR + 0.85% (~5.0%); marginal cost of new notes ~5.5%
B10: Tax rate | C10: 0.23 | D10: Model FY2028E+ effective tax rate (FY2026 22.1%; Q1 FY27 22.1%)
B11: After-tax cost of debt | C11: =C9*(1-C10) -> 0.04235
B12: Target D/V | C12: 0.05 | D12: Net debt ~$0.7bn at 27-Jun-2026 vs ~$16bn market cap ($510 × ~31.8m diluted shares); ~1.0x adjusted EBITDA
B13: WACC | C13: =C8*(1-C12)+C11*C12 -> 0.0923675
B15: Valuation date (live) | C15: =TODAY() -> 2026-10-13 00:00:00 | D15: Periods = (31-Mar of fiscal year − today) / 365.25; cash flows assumed at fiscal year end; FY2027E (ends 3-Apr-2027) is the base year — its cash flow is in the net debt below
B16: 2. UNLEVERED FREE CASH FLOW BUILD (USDm)
D17: 2028E | E17: 2029E | F17: 2030E | G17: 2031E | H17: 2032E | I17: 2033E | J17: 2034E | K17: 2035E | L17: 2036E | M17: 2037E | N17: Terminal | P17: CAGR 28–32E | Q17: CAGR 28–37E
B18: Adj. EBITA (after stock comp; before M&A amortization) less transaction & restructuring costs | D18: =Model!CG186-Model!CG187 -> 700.30947 | E18: =Model!CH186-Model!CH187 -> 789.51856 | F18: =Model!CI186-Model!CI187 -> 880.9432 | G18: =Model!CJ186-Model!CJ187 -> 967.44694 | H18: =Model!CK186-Model!CK187 -> 1053.0306 | I18: =H18*(1+I$26) -> 1126.7428 | J18: =I18*(1+J$26) -> 1199.9811 | K18: =J18*(1+K$26) -> 1271.9799 | L18: =K18*(1+L$26) -> 1341.9388 | M18: =L18*(1+M$26) -> 1409.0358 | P18: =(H18/D18)^(1/(COLUMNS(D18:H18)-1))-1 -> 0.10735725 | Q18: =(M18/D18)^(1/(COLUMNS(D18:M18)-1))-1 -> 0.080778984
B19: × (1 − tax rate) | D19: =1-$C$10 -> 0.77 | E19: =1-$C$10 -> 0.77 | F19: =1-$C$10 -> 0.77 | G19: =1-$C$10 -> 0.77 | H19: =1-$C$10 -> 0.77 | I19: =1-$C$10 -> 0.77 | J19: =1-$C$10 -> 0.77 | K19: =1-$C$10 -> 0.77 | ... M19: =1-$C$10 -> 0.77
B20: NOPAT | D20: =D18*D19 -> 539.23829 | E20: =E18*E19 -> 607.92929 | F20: =F18*F19 -> 678.32626 | G20: =G18*G19 -> 744.93414 | H20: =H18*H19 -> 810.83359 | I20: =I18*I19 -> 867.59194 | J20: =J18*J19 -> 923.98542 | K20: =K18*K19 -> 979.42454 | ... M20: =M18*M19 -> 1084.9575
B21: plus D&A excluding M&A-related amortization (depreciation & software) | D21: =Model!CG89 -> 66.773699 | E21: =Model!CH89 -> 74.658398 | F21: =Model!CI89 -> 82.580482 | G21: =Model!CJ89 -> 90.657923 | H21: =Model!CK89 -> 98.631446 | I21: =H21*(1+I$26) -> 105.53565 | J21: =I21*(1+J$26) -> 112.39546 | K21: =J21*(1+K$26) -> 119.13919 | L21: =K21*(1+L$26) -> 125.69185 | M21: =L21*(1+M$26) -> 131.97644
B22: − Capex (PP&E) and acquisitions (M&A lever FY2028E–32E) | D22: =Model!CG240+Model!CG241 -> -345.391 | E22: =Model!CH240+Model!CH241 -> -351.32211 | F22: =Model!CI240+Model!CI241 -> -353.2256 | G22: =Model!CJ240+Model!CJ241 -> -363.3224 | H22: =Model!CK240+Model!CK241 -> -373.28931 | I22: =Model!CK240*(1+I$26) -> -131.91956 | J22: =I22*(1+J$26) -> -140.49433 | K22: =J22*(1+K$26) -> -148.92399 | L22: =K22*(1+L$26) -> -157.11481 | M22: =L22*(1+M$26) -> -164.97055
B23: − Δ Working capital (CF statement) | D23: =Model!CG238 -> -73.573162 | E23: =Model!CH238 -> -87.597994 | F23: =Model!CI238 -> -84.12896 | G23: =Model!CJ238 -> -91.533718 | H23: =Model!CK238 -> -101.44705 | I23: =H23*(1+I$26) -> -108.54834 | J23: =I23*(1+J$26) -> -115.60398 | K23: =J23*(1+K$26) -> -122.54022 | L23: =K23*(1+L$26) -> -129.27993 | M23: =L23*(1+M$26) -> -135.74393
B24: Unlevered FCF | D24: =D20+D21+D22+D23 -> 187.04783 | E24: =E20+E21+E22+E23 -> 243.66759 | F24: =F20+F21+F22+F23 -> 323.55218 | G24: =G20+G21+G22+G23 -> 380.73594 | H24: =H20+H21+H22+H23 -> 434.72868 | I24: =I20+I21+I22+I23 -> 732.65969 | J24: =J20+J21+J22+J23 -> 780.28257 | K24: =K20+K21+K22+K23 -> 827.09952 | ... M24: =M20+M21+M22+M23 -> 916.2195 | N24: =M24*(1+$C$27) -> 952.86828 | P24: =(H24/D24)^(1/(COLUMNS(D24:H24)-1))-1 -> 0.2347141 | Q24: =(M24/D24)^(1/(COLUMNS(D24:M24)-1))-1 -> 0.19308634
B25: Terminal Value (Gordon Growth) | N25: =N24/($C$13-$C$27) -> 18195.795
B26: Fade-period growth (FY2033E–37E; 7.0% → 5.0% linear) | I26: 0.07 | J26: =I26+($M$26-$I$26)/4 -> 0.065 | K26: =J26+($M$26-$I$26)/4 -> 0.06 | L26: =K26+($M$26-$I$26)/4 -> 0.055 | M26: 0.05
B27: Terminal growth rate | C27: 0.04
B29: Discount period (years) | D29: =(DATE(2028,3,31)-$C$15)/365.25 -> 1.4647502 | E29: =(DATE(2029,3,31)-$C$15)/365.25 -> 2.4640657 | F29: =(DATE(2030,3,31)-$C$15)/365.25 -> 3.4633812 | G29: =(DATE(2031,3,31)-$C$15)/365.25 -> 4.4626968 | H29: =(DATE(2032,3,31)-$C$15)/365.25 -> 5.4647502 | I29: =(DATE(2033,3,31)-$C$15)/365.25 -> 6.4640657 | J29: =(DATE(2034,3,31)-$C$15)/365.25 -> 7.4633812 | K29: =(DATE(2035,3,31)-$C$15)/365.25 -> 8.4626968 | L29: =(DATE(2036,3,31)-$C$15)/365.25 -> 9.4647502 | M29: =(DATE(2037,3,31)-$C$15)/365.25 -> 10.464066 | N29: =M29 -> 10.464066
B30: Discount factor | D30: =1/(1+$C$13)^D29 -> 0.87861646 | E30: =1/(1+$C$13)^E29 -> 0.80437178 | F30: =1/(1+$C$13)^F29 -> 0.73640092 | G30: =1/(1+$C$13)^G29 -> 0.67417371 | H30: =1/(1+$C$13)^H29 -> 0.61705554 | I30: =1/(1+$C$13)^I29 -> 0.56491323 | J30: =1/(1+$C$13)^J29 -> 0.51717704 | K30: =1/(1+$C$13)^K29 -> 0.47347465 | ... N30: =1/(1+$C$13)^N29 -> 0.39674062
B31: PV of UFCF | D31: =D24*D30 -> 164.3433 | E31: =E24*E30 -> 195.99933 | F31: =F24*F30 -> 238.26412 | G31: =G24*G30 -> 256.68216 | H31: =H24*H30 -> 268.25174 | I31: =I24*I30 -> 413.88915 | J31: =J24*J30 -> 403.54423 | K31: =K24*K30 -> 391.61066 | ... M31: =M24*M30 -> 363.50149 | N31: =N25*N30 -> 7219.0108
D32: NOPAT basis (playbook 5.7): RBC's adjusted EPS and adjusted EBITDA add back stock compensation; here it is deducted (row 18 starts from adjusted operating income, which is after stock compensation) and M&A-related amortization of acquired intangibles is added back (EBITA), so the tax is charged on pre-amortization profit; row 21 adds back depreciation and non-acquired amortization only. Transaction, transition and restructuring costs (cash; adjusted out by the company) are deducted in row 18. Row 22 includes acquisitions from the M&A lever in FY2028E–32E; the fade period and terminal value assume no new acquisitions. The cash tax shield on acquired-intangible amortization (e.g. VACCO, Section 338(h)(10) election per the FY2026 10-K) is not modelled separately.
B33: IMPLIED ROIC — invested capital roll-forward (USDm)
B34: Opening invested capital | D34: =Model!CF367 -> 4257.6237 | E34: =D38 -> 4609.8142 | F34: =E38 -> 4974.0759 | G34: =F38 -> 5328.85 | H34: =G38 -> 5693.0482 | I34: =H38 -> 6069.1531 | J34: =I38 -> 6204.0853 | K34: =J38 -> 6347.7882 | L34: =K38 -> 6500.1132 | M34: =L38 -> 6660.8161
B35: plus Capex and acquisitions | D35: =-D22 -> 345.391 | E35: =-E22 -> 351.32211 | F35: =-F22 -> 353.2256 | G35: =-G22 -> 363.3224 | H35: =-H22 -> 373.28931 | I35: =-I22 -> 131.91956 | J35: =-J22 -> 140.49433 | K35: =-K22 -> 148.92399 | ... M35: =-M22 -> 164.97055
B36: less DD&A | D36: =-D21 -> -66.773699 | E36: =-E21 -> -74.658398 | F36: =-F21 -> -82.580482 | G36: =-G21 -> -90.657923 | H36: =-H21 -> -98.631446 | I36: =-I21 -> -105.53565 | J36: =-J21 -> -112.39546 | K36: =-K21 -> -119.13919 | ... M36: =-M21 -> -131.97644
B37: plus Δ Working capital investment | D37: =-D23 -> 73.573162 | E37: =-E23 -> 87.597994 | F37: =-F23 -> 84.12896 | G37: =-G23 -> 91.533718 | H37: =-H23 -> 101.44705 | I37: =-I23 -> 108.54834 | J37: =-J23 -> 115.60398 | K37: =-K23 -> 122.54022 | ... M37: =-M23 -> 135.74393
B38: Closing invested capital | D38: =SUM(D34:D37) -> 4609.8142 | E38: =SUM(E34:E37) -> 4974.0759 | F38: =SUM(F34:F37) -> 5328.85 | G38: =SUM(G34:G37) -> 5693.0482 | H38: =SUM(H34:H37) -> 6069.1531 | I38: =SUM(I34:I37) -> 6204.0853 | J38: =SUM(J34:J37) -> 6347.7882 | K38: =SUM(K34:K37) -> 6500.1132 | ... M38: =SUM(M34:M37) -> 6829.5541
B39: NOPAT (row 20) | D39: =D20 -> 539.23829 | E39: =E20 -> 607.92929 | F39: =F20 -> 678.32626 | G39: =G20 -> 744.93414 | H39: =H20 -> 810.83359 | I39: =I20 -> 867.59194 | J39: =J20 -> 923.98542 | K39: =K20 -> 979.42454 | ... M39: =M20 -> 1084.9575
B40: Implied ROIC (NOPAT / avg. invested capital) | D40: =IFERROR(D39/AVERAGE(D34,D38),"") -> 0.12162212 | E40: =IFERROR(E39/AVERAGE(E34,E38),"") -> 0.12686483 | F40: =IFERROR(F39/AVERAGE(F34,F38),"") -> 0.13167643 | G40: =IFERROR(G39/AVERAGE(G34,G38),"") -> 0.13517348 | H40: =IFERROR(H39/AVERAGE(H34,H38),"") -> 0.13787106 | I40: =IFERROR(I39/AVERAGE(I34,I38),"") -> 0.14137946 | J40: =IFERROR(J39/AVERAGE(J34,J38),"") -> 0.14722669 | K40: =IFERROR(K39/AVERAGE(K34,K38),"") -> 0.15246452 | ... M40: =IFERROR(M39/AVERAGE(M34,M38),"") -> 0.16084919
B41: Reinvestment rate (net investment / NOPAT) | D41: =IFERROR(SUM(D35:D37)/D39,"") -> 0.65312584 | E41: =IFERROR(SUM(E35:E37)/E39,"") -> 0.59918433 | F41: =IFERROR(SUM(F35:F37)/F39,"") -> 0.52301392 | G41: =IFERROR(SUM(G35:G37)/G39,"") -> 0.48889986 | H41: =IFERROR(SUM(H35:H37)/H39,"") -> 0.46384969 | I41: =IFERROR(SUM(I35:I37)/I39,"") -> 0.15552502 | J41: =IFERROR(SUM(J35:J37)/J39,"") -> 0.15552502 | K41: =IFERROR(SUM(K35:K37)/K39,"") -> 0.15552502 | ... M41: =IFERROR(SUM(M35:M37)/M39,"") -> 0.15552502
B42: Implied terminal RONIC (g / reinvestment rate) | N42: =IFERROR($C$27/M41,"") -> 0.25719335
D43: Opening IC = Model FY2027E book IC (equity + net debt at the FY2027E year end), rolled forward with capex + M&A − D&A excl. M&A amortization + ΔWC.
B44: 3. VALUATION SUMMARY
B45: Sum of PV (explicit + fade) | C45: =SUM(D31:M31) -> 3074.2321
B46: PV of Terminal Value | C46: =N31 -> 7219.0108
B47: Enterprise Value | C47: =C45+C46 -> 10293.243
B48: Less: Net debt + NCI (Model FY2027E year end) | C48: =Model!CF387+Model!CF397 -> 470.54553 | D48: RBC: no noncontrolling interests; net debt at the base-year end (3-Apr-2027) so that FY2028E+ cash flows are not double counted; operating leases not treated as debt.
B49: Equity Value | C49: =C47-C48 -> 9822.6974
B50: Diluted shares (m, Model FY2027E period end) | C50: =Model!CF394 -> 31.875726
B51: Implied share price ($) | C51: =C49/C50 -> 308.15604
B52: Current share price ($) | C52: =Model!CF393 -> 510
B53: Implied upside / (downside) | C53: =C51/C52-1 -> -0.39577248
B54: Required discount to DCF value for target IRR | C54: =1-((1+C13)/(1+H54))^H55 -> 0.14293691 | D54: vs. current | E54: Target IRR | H54: 0.15
B55: Max entry price for target IRR ($) | C55: =C51*(1-C54) -> 264.10916 | D55: =C55/C52-1 -> -0.4821389 | E55: Years for discount to close | H55: 3
B58: 4. SENSITIVITY: IMPLIED PRICE ($) — WACC × Terminal Growth
D60: WACC →
B61: Terminal growth ↓ | D61: =F61-0.01 -> 0.0823675 | E61: =F61-0.005 -> 0.0873675 | F61: =$C$13 -> 0.0923675 | G61: =F61+0.005 -> 0.0973675 | H61: =F61+0.01 -> 0.1023675
B62: =B64-0.01 -> 0.03 | D62: {=IFERROR((SUMPRODUCT($D$24:$M$24/(1+D$61)^$D$29:$M$29)+($M$24*(1+$B62)/(D$61-$B62))/(1+D$61)^$M$29-$C$48)/$C$50,"")} -> 334.7798 | E62: {=IFERROR((SUMPRODUCT($D$24:$M$24/(1+E$61)^$D$29:$M$29)+($M$24*(1+$B62)/(E$61-$B62))/(1+E$61)^$M$29-$C$48)/$C$50,"")} -> 299.50827 | F62: {=IFERROR((SUMPRODUCT($D$24:$M$24/(1+F$61)^$D$29:$M$29)+($M$24*(1+$B62)/(F$61-$B62))/(1+F$61)^$M$29-$C$48)/$C$50,"")} -> 270.0148 | G62: {=IFERROR((SUMPRODUCT($D$24:$M$24/(1+G$61)^$D$29:$M$29)+($M$24*(1+$B62)/(G$61-$B62))/(1+G$61)^$M$29-$C$48)/$C$50,"")} -> 245.00891 | H62: {=IFERROR((SUMPRODUCT($D$24:$M$24/(1+H$61)^$D$29:$M$29)+($M$24*(1+$B62)/(H$61-$B62))/(1+H$61)^$M$29-$C$48)/$C$50,"")} -> 223.55688
B63: =B64-0.005 -> 0.035 | D63: {=IFERROR((SUMPRODUCT($D$24:$M$24/(1+D$61)^$D$29:$M$29)+($M$24*(1+$B63)/(D$61-$B63))/(1+D$61)^$M$29-$C$48)/$C$50,"")} -> 362.17297 | E63: {=IFERROR((SUMPRODUCT($D$24:$M$24/(1+E$61)^$D$29:$M$29)+($M$24*(1+$B63)/(E$61-$B63))/(1+E$61)^$M$29-$C$48)/$C$50,"")} -> 321.16104 | F63: {=IFERROR((SUMPRODUCT($D$24:$M$24/(1+F$61)^$D$29:$M$29)+($M$24*(1+$B63)/(F$61-$B63))/(1+F$61)^$M$29-$C$48)/$C$50,"")} -> 287.42328 | G63: {=IFERROR((SUMPRODUCT($D$24:$M$24/(1+G$61)^$D$29:$M$29)+($M$24*(1+$B63)/(G$61-$B63))/(1+G$61)^$M$29-$C$48)/$C$50,"")} -> 259.20621 | H63: {=IFERROR((SUMPRODUCT($D$24:$M$24/(1+H$61)^$D$29:$M$29)+($M$24*(1+$B63)/(H$61-$B63))/(1+H$61)^$M$29-$C$48)/$C$50,"")} -> 235.27709
B64: =$C$27 -> 0.04 | D64: {=IFERROR((SUMPRODUCT($D$24:$M$24/(1+D$61)^$D$29:$M$29)+($M$24*(1+$B64)/(D$61-$B64))/(1+D$61)^$M$29-$C$48)/$C$50,"")} -> 396.03175 | E64: {=IFERROR((SUMPRODUCT($D$24:$M$24/(1+E$61)^$D$29:$M$29)+($M$24*(1+$B64)/(E$61-$B64))/(1+E$61)^$M$29-$C$48)/$C$50,"")} -> 347.38504 | F64: {=IFERROR((SUMPRODUCT($D$24:$M$24/(1+F$61)^$D$29:$M$29)+($M$24*(1+$B64)/(F$61-$B64))/(1+F$61)^$M$29-$C$48)/$C$50,"")} -> 308.15604 | G64: {=IFERROR((SUMPRODUCT($D$24:$M$24/(1+G$61)^$D$29:$M$29)+($M$24*(1+$B64)/(G$61-$B64))/(1+G$61)^$M$29-$C$48)/$C$50,"")} -> 275.87831 | H64: {=IFERROR((SUMPRODUCT($D$24:$M$24/(1+H$61)^$D$29:$M$29)+($M$24*(1+$B64)/(H$61-$B64))/(1+H$61)^$M$29-$C$48)/$C$50,"")} -> 248.87653
B65: =B64+0.005 -> 0.045 | D65: {=IFERROR((SUMPRODUCT($D$24:$M$24/(1+D$61)^$D$29:$M$29)+($M$24*(1+$B65)/(D$61-$B65))/(1+D$61)^$M$29-$C$48)/$C$50,"")} -> 438.95155 | E65: {=IFERROR((SUMPRODUCT($D$24:$M$24/(1+E$61)^$D$29:$M$29)+($M$24*(1+$B65)/(E$61-$B65))/(1+E$61)^$M$29-$C$48)/$C$50,"")} -> 379.7987 | F65: {=IFERROR((SUMPRODUCT($D$24:$M$24/(1+F$61)^$D$29:$M$29)+($M$24*(1+$B65)/(F$61-$B65))/(1+F$61)^$M$29-$C$48)/$C$50,"")} -> 333.2658 | G65: {=IFERROR((SUMPRODUCT($D$24:$M$24/(1+G$61)^$D$29:$M$29)+($M$24*(1+$B65)/(G$61-$B65))/(1+G$61)^$M$29-$C$48)/$C$50,"")} -> 295.73408 | H65: {=IFERROR((SUMPRODUCT($D$24:$M$24/(1+H$61)^$D$29:$M$29)+($M$24*(1+$B65)/(H$61-$B65))/(1+H$61)^$M$29-$C$48)/$C$50,"")} -> 264.84654
B66: =B64+0.01 -> 0.05 | D66: {=IFERROR((SUMPRODUCT($D$24:$M$24/(1+D$61)^$D$29:$M$29)+($M$24*(1+$B66)/(D$61-$B66))/(1+D$61)^$M$29-$C$48)/$C$50,"")} -> 495.13151 | E66: {=IFERROR((SUMPRODUCT($D$24:$M$24/(1+E$61)^$D$29:$M$29)+($M$24*(1+$B66)/(E$61-$B66))/(1+E$61)^$M$29-$C$48)/$C$50,"")} -> 420.88664 | F66: {=IFERROR((SUMPRODUCT($D$24:$M$24/(1+F$61)^$D$29:$M$29)+($M$24*(1+$B66)/(F$61-$B66))/(1+F$61)^$M$29-$C$48)/$C$50,"")} -> 364.30221 | G66: {=IFERROR((SUMPRODUCT($D$24:$M$24/(1+G$61)^$D$29:$M$29)+($M$24*(1+$B66)/(G$61-$B66))/(1+G$61)^$M$29-$C$48)/$C$50,"")} -> 319.78171 | H66: {=IFERROR((SUMPRODUCT($D$24:$M$24/(1+H$61)^$D$29:$M$29)+($M$24*(1+$B66)/(H$61-$B66))/(1+H$61)^$M$29-$C$48)/$C$50,"")} -> 283.86616
B69: 5. REVERSE DCF
B70: To solve for the market-implied path: Data ▸ What-If Analysis ▸ Goal Seek — set C51 to the current price (C52) by changing C27 (terminal growth) or the fade-period growth inputs (I26:M26).
B72: 6. MAUBOUSSIN EV / NOPAT — TWO-STAGE FRAMEWORK
B73: EV/NOPAT = 1/r + [g × (1 − r/ROIIC) / (r × (r − g))] × [1 − ((1+g)/(1+r))^N]
B74: Formula source: Mauboussin & Rappaport, "Expectations Investing" (2021); Counterpoint Global, "What Does a Price-Earnings Multiple Mean?" (2020).
B76: Input | C76: Value | D76: Rationale (RBC Bearings characteristics)
B77: r (Cost of capital / WACC) | C77: =$C$13 -> 0.0923675 | D77: Linked from Section 1 WACC build
B78: g (NOPAT growth, Stage 1) | C78: 0.09 | D78: Model adjusted EBITA CAGR FY2027–32E: high-single-digit sales growth (defense / space / commercial aerospace, Dodge industrial) with stable margins → ~9% NOPAT growth
B79: ROIIC (Return on incremental invested capital) | C79: 0.15 | D79: Sole-source, certified bearings on long-lived aircraft and defense platforms plus Dodge replacement demand earn high incremental returns; the Dodge goodwill depresses reported ROIC (~8–10%)
B80: N (Years of value creation / CAP) | C80: 15 | D80: Qualification barriers (OEM approvals, military specs) and a large aftermarket sustain a long competitive-advantage period; Industrial exposure is cyclical
B82: Calculation | C82: Value
B83: Steady-state component: 1 / r | C83: =1/C77 -> 10.826319
B84: Value-creation factor: 1 − r / ROIIC | C84: =1-C77/C79 -> 0.38421667
B85: Growth multiplier: g × (1 − r/ROIIC) / (r × (r − g)) | C85: =C78*C84/(C77*(C77-C78)) -> 158.12827
B86: Time decay: 1 − ((1+g)/(1+r))^N | C86: =1-((1+C78)/(1+C77))^C80 -> 0.032021056
B87: PVGO component (growth value) | C87: =C85*C86 -> 5.0634343
B88: Mauboussin EV / NOPAT (steady-state + PVGO) | C88: =C83+C87 -> 15.889753
B90: VALUATION — Applied to FY2030E NOPAT | C90: USDm
B91: FY2030E Adj. EBITA less transaction & restructuring costs | C91: =Model!CI186-Model!CI187 -> 880.9432
B92: Tax rate (from WACC build) | C92: =$C$10 -> 0.23
B93: FY2030E NOPAT | C93: =C91*(1-C92) -> 678.32626
B94: × Mauboussin EV/NOPAT multiple | C94: =C88 -> 15.889753
B95: Implied Enterprise Value (FY2030E basis) | C95: =C93*C94 -> 10778.437
B96: Less: FY2029E year-end net debt + NCI (Model) | C96: =Model!CH387+Model!CH397 -> 919.17164
B97: Implied Equity Value | C97: =C95-C96 -> 9859.2652
B98: Diluted shares FY2030E (m, Model) | C98: =Model!CI394 -> 29.936596
B99: Implied share price FY2030 ($) | C99: =C97/C98 -> 329.33821
B101: Current share price ($) | C101: =C52 -> 510
B102: Implied upside / (downside) | C102: =C99/C101-1 -> -0.3542388
B104: MARKET-IMPLIED EV/NOPAT TODAY | C104: USDm
B105: Current market cap (spot × diluted shares) | C105: =C52*C50 -> 16256.62
B106: Plus: FY2027E year-end net debt + NCI | C106: =C48 -> 470.54553
B107: Implied Enterprise Value (today) | C107: =C105+C106 -> 16727.166
B108: RBC market-implied EV/NOPAT (on FY2030E NOPAT) | C108: =C107/C93 -> 24.659469
B110: Multiple gap (Mauboussin − Market) | C110: =C88-C108 -> -8.7697164
B111: Implied re-rating headroom | C111: =C88/C108-1 -> -0.35563281

Sheet Charts
B2: RBC Bearings — Operating Performance (FY2007–FY2026) and Model Forecast (FY2027E–FY2032E)
B3: USDm · fiscal years ending ~31 March · Linked to Model. Bars = contribution of each segment to total net-sales growth (pp; Aerospace & Defense / Industrial from FY2022, total growth before). Adjusted EBITDA = company definition (adjusted operating income + D&A + stock compensation). ROIC / RONTA on adjusted EBIT (full-cost).
C7: 2013 | D7: 2014 | E7: 2015 | F7: 2016 | G7: 2017 | H7: 2018 | I7: 2019 | J7: 2020 | K7: 2021 | L7: 2022 | M7: 2023 | N7: 2024 | O7: 2025 | P7: 2026 | Q7: 2027E | R7: 2028E | S7: 2029E | T7: 2030E | U7: 2031E | V7: 2032E
B8: Aerospace & Defense contribution to growth (pp; total before FY2022) | C8: =IFERROR(Model!N44+0,IFERROR(Model!N46+0,0)) -> 0.013936721 | D8: =IFERROR(Model!S44+0,IFERROR(Model!S46+0,0)) -> 0.039287832 | E8: =IFERROR(Model!X44+0,IFERROR(Model!X46+0,0)) -> 0.063005209 | F8: =IFERROR(Model!AC44+0,IFERROR(Model!AC46+0,0)) -> 0.34179546 | G8: =IFERROR(Model!AH44+0,IFERROR(Model!AH46+0,0)) -> 0.029986342 | H8: =IFERROR(Model!AM44+0,IFERROR(Model!AM46+0,0)) -> 0.096786093 | I8: =IFERROR(Model!AR44+0,IFERROR(Model!AR46+0,0)) -> 0.040843086 | J8: =IFERROR(Model!AW44+0,IFERROR(Model!AW46+0,0)) -> 0.035508088 | K8: =IFERROR(Model!BB44+0,IFERROR(Model!BB46+0,0)) -> 0 | L8: =IFERROR(Model!BG44+0,IFERROR(Model!BG46+0,0)) -> -0.024227237 | M8: =IFERROR(Model!BL44+0,IFERROR(Model!BL46+0,0)) -> 0.051794553 | N8: =IFERROR(Model!BQ44+0,IFERROR(Model!BQ46+0,0)) -> 0.060601895 | O8: =IFERROR(Model!BV44+0,IFERROR(Model!BV46+0,0)) -> 0.047075525 | P8: =IFERROR(Model!CA44+0,IFERROR(Model!CA46+0,0)) -> 0.11929353 | Q8: =IFERROR(Model!CF44+0,IFERROR(Model!CF46+0,0)) -> 0.094414296 | R8: =IFERROR(Model!CG44+0,IFERROR(Model!CG46+0,0)) -> 0.049190848 | S8: =IFERROR(Model!CH44+0,IFERROR(Model!CH46+0,0)) -> 0.044899417 | T8: =IFERROR(Model!CI44+0,IFERROR(Model!CI46+0,0)) -> 0.039755999 | U8: =IFERROR(Model!CJ44+0,IFERROR(Model!CJ46+0,0)) -> 0.03482394 | V8: =IFERROR(Model!CK44+0,IFERROR(Model!CK46+0,0)) -> 0.02997653
B9: Industrial contribution to growth (pp) | C9: =IFERROR(Model!N45+0,0) -> 0 | D9: =IFERROR(Model!S45+0,0) -> 0 | E9: =IFERROR(Model!X45+0,0) -> 0 | F9: =IFERROR(Model!AC45+0,0) -> 0 | G9: =IFERROR(Model!AH45+0,0) -> 0 | H9: =IFERROR(Model!AM45+0,0) -> 0 | I9: =IFERROR(Model!AR45+0,0) -> 0 | J9: =IFERROR(Model!AW45+0,0) -> 0 | K9: =IFERROR(Model!BB45+0,0) -> 0 | L9: =IFERROR(Model!BG45+0,0) -> 0.57260453 | M9: =IFERROR(Model!BL45+0,0) -> 0.50641559 | N9: =IFERROR(Model!BQ45+0,0) -> 0.0013230844 | O9: =IFERROR(Model!BV45+0,0) -> 0.0016464993 | P9: =IFERROR(Model!CA45+0,0) -> 0.024078714 | Q9: =IFERROR(Model!CF45+0,0) -> 0.058568778 | R9: =IFERROR(Model!CG45+0,0) -> 0.033168628 | S9: =IFERROR(Model!CH45+0,0) -> 0.029152172 | T9: =IFERROR(Model!CI45+0,0) -> 0.025006762 | U9: =IFERROR(Model!CJ45+0,0) -> 0.023738212 | V9: =IFERROR(Model!CK45+0,0) -> 0.02043391
C11: =C7 -> 2013 | D11: =D7 -> 2014 | E11: =E7 -> 2015 | F11: =F7 -> 2016 | G11: =G7 -> 2017 | H11: =H7 -> 2018 | I11: =I7 -> 2019 | J11: =J7 -> 2020 | ... V11: =V7 -> 2032E
B12: Adjusted EBITDA | C12: =Model!N179 -> 105.026 | D12: =Model!S179 -> 111.512 | E12: =Model!X179 -> 119.871 | F12: =Model!AC179 -> 154.828 | G12: =Model!AH179 -> 160.84 | H12: =Model!AM179 -> 177.886 | I12: =Model!AR179 -> 195.504 | J12: =Model!AW179 -> 209.22 | K12: =Model!BB179 -> 174.255 | L12: =Model!BG179 -> 266.468 | M12: =Model!BL179 -> 433.97 | N12: =Model!BQ179 -> 482.167 | O12: =Model!BV179 -> 519.8 | P12: =Model!CA179 -> 605.3 | Q12: =Model!CF179 -> 723.46302 | R12: =Model!CG179 -> 817.00911 | S12: =Model!CH179 -> 919.17164 | T12: =Model!CI179 -> 1023.6111 | U12: =Model!CJ179 -> 1123.385 | V12: =Model!CK179 -> 1222.068
B13: Operating income (GAAP) | C13: =Model!N116 -> 78.101 | D13: =Model!S116 -> 88.65 | E13: =Model!X116 -> 88.43 | F13: =Model!AC116 -> 103.841 | G13: =Model!AH116 -> 113.693 | H13: =Model!AM116 -> 128.141 | I13: =Model!AR116 -> 132.035 | J13: =Model!AW116 -> 156.785 | K13: =Model!BB116 -> 111.458 | L13: =Model!BG116 -> 130.063 | M13: =Model!BL116 -> 293 | N13: =Model!BQ116 -> 342.2 | O13: =Model!BV116 -> 369.9 | P13: =Model!CA116 -> 421 | Q13: =Model!CF116 -> 558.42302 | R13: =Model!CG116 -> 620.95047 | S13: =Model!CH116 -> 704.98456 | T13: =Model!CI116 -> 794.3032 | U13: =Model!CJ116 -> 876.74794 | V13: =Model!CK116 -> 954.83164
B14: Adj. EBITDA Margin % | C14: =Model!N227 -> 0.26057745 | D14: =Model!S227 -> 0.26621085 | E14: =Model!X227 -> 0.26920486 | F14: =Model!AC227 -> 0.2591385 | G14: =Model!AH227 -> 0.26136356 | H14: =Model!AM227 -> 0.26355473 | I14: =Model!AR227 -> 0.27829117 | J14: =Model!AW227 -> 0.28760305 | K14: =Model!BB227 -> 0.28614052 | L14: =Model!BG227 -> 0.28259364 | M14: =Model!BL227 -> 0.29535833 | N14: =Model!BQ227 -> 0.30902198 | O14: =Model!BV227 -> 0.31766791 | P14: =Model!CA227 -> 0.32353413 | Q14: =Model!CF227 -> 0.33538438 | R14: =Model!CG227 -> 0.3425938 | S14: =Model!CH227 -> 0.34472754 | T14: =Model!CI227 -> 0.34706884 | U14: =Model!CJ227 -> 0.34696117 | V14: =Model!CK227 -> 0.34692693
B15: Operating Margin % | C15: =Model!N228 -> 0.19377449 | D15: =Model!S228 -> 0.21163276 | E15: =Model!X228 -> 0.19859504 | F15: =Model!AC228 -> 0.17380061 | G15: =Model!AH228 -> 0.18475011 | H15: =Model!AM228 -> 0.18985286 | I15: =Model!AR228 -> 0.1879459 | J15: =Model!AW228 -> 0.21552358 | K15: =Model!BB228 -> 0.18302287 | L15: =Model!BG228 -> 0.13793392 | M15: =Model!BL228 -> 0.19941469 | N15: =Model!BQ228 -> 0.2193168 | O15: =Model!BV228 -> 0.22605879 | P15: =Model!CA228 -> 0.22502539 | Q15: =Model!CF228 -> 0.25887482 | R15: =Model!CG228 -> 0.26038116 | S15: =Model!CH228 -> 0.26439849 | T15: =Model!CI228 -> 0.26931896 | U15: =Model!CJ228 -> 0.27078651 | V15: =Model!CK228 -> 0.27106249
C17: =C7 -> 2013 | D17: =D7 -> 2014 | E17: =E7 -> 2015 | F17: =F7 -> 2016 | G17: =G7 -> 2017 | H17: =H7 -> 2018 | I17: =I7 -> 2019 | J17: =J7 -> 2020 | ... V17: =V7 -> 2032E
B18: ROIC | C18: =IFERROR(Model!N370+0,NA()) -> 0.15138629 | D18: =IFERROR(Model!S370+0,NA()) -> 0.14143422 | E18: =IFERROR(Model!X370+0,NA()) -> 0.1498788 | F18: =IFERROR(Model!AC370+0,NA()) -> 0.084416109 | G18: =IFERROR(Model!AH370+0,NA()) -> 0.085954295 | H18: =IFERROR(Model!AM370+0,NA()) -> 0.10497164 | I18: =IFERROR(Model!AR370+0,NA()) -> 0.12625241 | J18: =IFERROR(Model!AW370+0,NA()) -> 0.12329151 | K18: =IFERROR(Model!BB370+0,NA()) -> 0.089385657 | L18: =IFERROR(Model!BG370+0,NA()) -> 0.039948322 | M18: =IFERROR(Model!BL370+0,NA()) -> 0.06168704 | N18: =IFERROR(Model!BQ370+0,NA()) -> 0.069752387 | O18: =IFERROR(Model!BV370+0,NA()) -> 0.073203749 | P18: =IFERROR(Model!CA370+0,NA()) -> 0.082669297 | Q18: =IFERROR(Model!CF370+0,NA()) -> 0.10272164 | R18: =IFERROR(Model!CG370+0,NA()) -> 0.10742003 | S18: =IFERROR(Model!CH370+0,NA()) -> 0.11471249 | T18: =IFERROR(Model!CI370+0,NA()) -> 0.12228657 | U18: =IFERROR(Model!CJ370+0,NA()) -> 0.12797612 | V18: =IFERROR(Model!CK370+0,NA()) -> 0.13240787
B19: RONTA | C19: =IFERROR(Model!N381+0,NA()) -> 0.12010948 | D19: =IFERROR(Model!S381+0,NA()) -> 0.11602002 | E19: =IFERROR(Model!X381+0,NA()) -> 0.12116714 | F19: =IFERROR(Model!AC381+0,NA()) -> 0.1461271 | G19: =IFERROR(Model!AH381+0,NA()) -> 0.14418822 | H19: =IFERROR(Model!AM381+0,NA()) -> 0.16550902 | I19: =IFERROR(Model!AR381+0,NA()) -> 0.19359177 | J19: =IFERROR(Model!AW381+0,NA()) -> 0.16318396 | K19: =IFERROR(Model!BB381+0,NA()) -> 0.10676873 | L19: =IFERROR(Model!BG381+0,NA()) -> 0.13831172 | M19: =IFERROR(Model!BL381+0,NA()) -> 0.22497524 | N19: =IFERROR(Model!BQ381+0,NA()) -> 0.24138071 | O19: =IFERROR(Model!BV381+0,NA()) -> 0.24403536 | P19: =IFERROR(Model!CA381+0,NA()) -> 0.25242312 | Q19: =IFERROR(Model!CF381+0,NA()) -> 0.28561418 | R19: =IFERROR(Model!CG381+0,NA()) -> 0.29256122 | S19: =IFERROR(Model!CH381+0,NA()) -> 0.3052408 | T19: =IFERROR(Model!CI381+0,NA()) -> 0.31969823 | U19: =IFERROR(Model!CJ381+0,NA()) -> 0.328226 | V19: =IFERROR(Model!CK381+0,NA()) -> 0.33236244
B20: Adj. EBITDA margin % | C20: =IFERROR(Model!N227+0,NA()) -> 0.26057745 | D20: =IFERROR(Model!S227+0,NA()) -> 0.26621085 | E20: =IFERROR(Model!X227+0,NA()) -> 0.26920486 | F20: =IFERROR(Model!AC227+0,NA()) -> 0.2591385 | G20: =IFERROR(Model!AH227+0,NA()) -> 0.26136356 | H20: =IFERROR(Model!AM227+0,NA()) -> 0.26355473 | I20: =IFERROR(Model!AR227+0,NA()) -> 0.27829117 | J20: =IFERROR(Model!AW227+0,NA()) -> 0.28760305 | K20: =IFERROR(Model!BB227+0,NA()) -> 0.28614052 | L20: =IFERROR(Model!BG227+0,NA()) -> 0.28259364 | M20: =IFERROR(Model!BL227+0,NA()) -> 0.29535833 | N20: =IFERROR(Model!BQ227+0,NA()) -> 0.30902198 | O20: =IFERROR(Model!BV227+0,NA()) -> 0.31766791 | P20: =IFERROR(Model!CA227+0,NA()) -> 0.32353413 | Q20: =IFERROR(Model!CF227+0,NA()) -> 0.33538438 | R20: =IFERROR(Model!CG227+0,NA()) -> 0.3425938 | S20: =IFERROR(Model!CH227+0,NA()) -> 0.34472754 | T20: =IFERROR(Model!CI227+0,NA()) -> 0.34706884 | U20: =IFERROR(Model!CJ227+0,NA()) -> 0.34696117 | V20: =IFERROR(Model!CK227+0,NA()) -> 0.34692693
B21: FCF margin % | C21: =IFERROR(Model!N260+0,NA()) -> 0.060153678 | D21: =IFERROR(Model!S260+0,NA()) -> 0.045489704 | E21: =IFERROR(Model!X260+0,NA()) -> 0.11429489 | F21: =IFERROR(Model!AC260+0,NA()) -> 0.10460072 | G21: =IFERROR(Model!AH260+0,NA()) -> 0.13056478 | H21: =IFERROR(Model!AM260+0,NA()) -> 0.15158627 | I21: =IFERROR(Model!AR260+0,NA()) -> 0.095657608 | J21: =IFERROR(Model!AW260+0,NA()) -> 0.16265339 | K21: =IFERROR(Model!BB260+0,NA()) -> 0.23100935 | L21: =IFERROR(Model!BG260+0,NA()) -> 0.15964375 | M21: =IFERROR(Model!BL260+0,NA()) -> 0.12155448 | N21: =IFERROR(Model!BQ260+0,NA()) -> 0.15477793 | O21: =IFERROR(Model!BV260+0,NA()) -> 0.14899468 | P21: =IFERROR(Model!CA260+0,NA()) -> 0.18312042 | Q21: =IFERROR(Model!CF260+0,NA()) -> 0.1762791 | R21: =IFERROR(Model!CG260+0,NA()) -> 0.19996734 | S21: =IFERROR(Model!CH260+0,NA()) -> 0.19742824 | T21: =IFERROR(Model!CI260+0,NA()) -> 0.20546592 | U21: =IFERROR(Model!CJ260+0,NA()) -> 0.20486426 | V21: =IFERROR(Model!CK260+0,NA()) -> 0.20448481
