Workbook

Sheet Model
BD1: SCENARIO SWITCH ▼ (Bull / Base / Bear) — drives all scenario-linked forecast drivers
B2: Hermès International S.C.A. (Euronext Paris: RMS) — 3-Statement Financial Model | BD2: Base
B3: IFRS as reported · EUR millions (per-share data in EUR) · Source: Hermès registration documents / Universal Registration Documents (annual financial reports FY2010–FY2025; FY2009 comparatives and FY2006–08 key figures from the 2010 document), half-year financial reports (H1 2013–H1 2026), half-year / full-year results and quarterly revenue releases — finance.hermes.com (documents filed with the AMF). Hermès is not an SEC registrant: EDGAR holds only ADR (Form F-6) registrations, no 10-K / 10-Q / 8-K.
B4: Basis notes: calendar fiscal year; interim columns are half-years (Hermès publishes full statements for H1 and FY only): H1 as reported, H2 = FY − H1 (balances = 31-Dec). Each period as originally reported (2018 pre-IFRS 16; IFRS 16 from 2019, 2018 not restated). Tableware folded into Other Hermès sectors (separate to 2013). Free-share plan expense reclassified from S&A to other income & expenses from 2015 (2014 as reported). Non-recurring items: 2018 HK property gain €52.7m; 2020 Shang Xia deconsolidation €91.1m. French exceptional contribution on large companies' profits in 2025 (€331m) and renewed for 2026. H2/26E–2030E = forecast (no company numeric guidance; scenario-driven).
BF5: Forecast | BG5: Historical | BH5: Historical | BI5: Historical
B6: (EURm) | C6: 2006 | D6: 2007 | E6: 2008 | F6: 2009 | G6: 2010 | H6: 2011 | I6: 2012 | J6: H1/13 | K6: H2/13 | L6: 2013 | M6: H1/14 | N6: H2/14 | O6: 2014 | P6: H1/15 | Q6: H2/15 | R6: 2015 | S6: H1/16 | T6: H2/16 | U6: 2016 | V6: H1/17 | W6: H2/17 | X6: 2017 | Y6: H1/18 | Z6: H2/18 | AA6: 2018 | AB6: H1/19 | AC6: H2/19 | AD6: 2019 | AE6: H1/20 | AF6: H2/20 | AG6: 2020 | AH6: H1/21 | AI6: H2/21 | AJ6: 2021 | AK6: H1/22 | AL6: H2/22 | AM6: 2022 | AN6: H1/23 | AO6: H2/23 | AP6: 2023 | AQ6: H1/24 | AR6: H2/24 | AS6: 2024 | AT6: H1/25 | AU6: H2/25 | AV6: 2025 | AW6: H1/26 | AX6: H2/26E | AY6: 2026E | AZ6: 2027E | BA6: 2028E | BB6: 2029E | BC6: 2030E | BD6: Modelling Notes | BF6: 5Y CAGR | BG6: 5Y CAGR | BH6: 10Y CAGR | BI6: 19Y CAGR
BF7: 25-'30 | BG7: 20-'25 | BH7: 15-'25 | BI7: 06-'25
B8: MÉTIER REVENUE BUILD — SEVEN SECTORS (prior period × (1 + constant-currency growth + currency effect)) | BD8: MÉTIER BUILD — modelling logic (constant-currency growth by métier + group currency effect)
BL9: SCENARIO INPUT TABLE — driver assumptions per Bull / Base / Bear | BM9: Bull | BN9: Base | BO9: Bear | BP9: Bull / Bear = Base + Δ (Δ inputs on each block header). Point-estimate block applies to all cases except the H2/26E currency effect.
B10: Leather Goods & Saddlery (bags, travel, small leather goods, saddles & equestrian) | BD10: LEATHER GOODS & SADDLERY — modelling logic
B11: Revenue | F11: 936 | G11: 1205 | H11: 1348 | I11: 1596.6 | J11: 779.9 | K11: =L11-J11 -> 853.9 | L11: 1633.8 | M11: 840.7 | N11: =O11-M11 -> 1001.4 | O11: 1842.1 | P11: 1067.4 | Q11: =R11-P11 -> 1206.9 | R11: 2274.3 | S11: 1231.2 | T11: =U11-S11 -> 1372.5 | U11: 2603.7 | V11: 1404 | W11: =X11-V11 -> 1396.3 | X11: 2800.3 | Y11: 1425.1 | Z11: =AA11-Y11 -> 1550.7 | AA11: 2975.8 | AB11: 1652.4 | AC11: =AD11-AB11 -> 1761.9 | AD11: 3414.3 | AE11: 1280.1 | AF11: =AG11-AE11 -> 1929.1 | AG11: 3209.2 | AH11: 1999.3 | AI11: =AJ11-AH11 -> 2091.7 | AJ11: 4091 | AK11: 2358 | AL11: =AM11-AK11 -> 2605 | AM11: 4963 | AN11: 2780 | AO11: =AP11-AN11 -> 2767 | AP11: 5547 | AQ11: 3215 | AR11: =AS11-AQ11 -> 3242 | AS11: 6457 | AT11: 3578 | AU11: =AV11-AT11 -> 3492 | AV11: 7070 | AW11: 3761 | AX11: =AU11*(1+AX13+AX64) -> 3701.52 | AY11: =AW11+AX11 -> 7462.52 | AZ11: =AY11*(1+AZ13+AZ64) -> 8134.1468 | BA11: =AZ11*(1+BA13+BA64) -> 8866.22 | BB11: =BA11*(1+BB13+BB64) -> 9619.8487 | BC11: =BB11*(1+BC13+BC64) -> 10389.437 | BD11: H2/26E: H2/25 × (1 + scenario constant-currency growth + H2/26E currency effect). 2027E+: prior year × (1 + scenario cc growth + currency effect). | BF11: =IFERROR((BC11/AV11)^(1/5)-1,"n/m") -> 0.080026761 | BG11: =IFERROR((AV11/AG11)^(1/5)-1,"n/m") -> 0.17112844 | BH11: =IFERROR((AV11/R11)^(1/10)-1,"n/m") -> 0.12010095 | BI11: =IFERROR((AV11/C11)^(1/19)-1,"n/m") -> n/m | BL11: 2026E point estimates — H2/26E drivers (company has no numeric FY26 guidance)
B12: Revenue y/y % (reported) | D12: =IF(AND(ISNUMBER(D11),ISNUMBER(C11)),IFERROR(D11/C11-1,""),"") | E12: =IF(AND(ISNUMBER(E11),ISNUMBER(D11)),IFERROR(E11/D11-1,""),"") | F12: =IF(AND(ISNUMBER(F11),ISNUMBER(E11)),IFERROR(F11/E11-1,""),"") | G12: =IF(AND(ISNUMBER(G11),ISNUMBER(F11)),IFERROR(G11/F11-1,""),"") -> 0.28739316 | H12: =IF(AND(ISNUMBER(H11),ISNUMBER(G11)),IFERROR(H11/G11-1,""),"") -> 0.1186722 | I12: =IF(AND(ISNUMBER(I11),ISNUMBER(H11)),IFERROR(I11/H11-1,""),"") -> 0.18442136 | L12: =IF(AND(ISNUMBER(L11),ISNUMBER(I11)),IFERROR(L11/I11-1,""),"") -> 0.023299511 | M12: =IF(AND(ISNUMBER(M11),ISNUMBER(J11)),IFERROR(M11/J11-1,""),"") -> 0.077958713 | N12: =IF(AND(ISNUMBER(N11),ISNUMBER(K11)),IFERROR(N11/K11-1,""),"") -> 0.17273685 | O12: =IF(AND(ISNUMBER(O11),ISNUMBER(L11)),IFERROR(O11/L11-1,""),"") -> 0.12749419 | P12: =IF(AND(ISNUMBER(P11),ISNUMBER(M11)),IFERROR(P11/M11-1,""),"") -> 0.26965624 | Q12: =IF(AND(ISNUMBER(Q11),ISNUMBER(N11)),IFERROR(Q11/N11-1,""),"") -> 0.2052127 | R12: =IF(AND(ISNUMBER(R11),ISNUMBER(O11)),IFERROR(R11/O11-1,""),"") -> 0.23462353 | S12: =IF(AND(ISNUMBER(S11),ISNUMBER(P11)),IFERROR(S11/P11-1,""),"") -> 0.153457 | ... AY12: =IF(AND(ISNUMBER(AY11),ISNUMBER(AV11)),IFERROR(AY11/AV11-1,""),"") -> 0.055519095 | AZ12: =IF(AND(ISNUMBER(AZ11),ISNUMBER(AY11)),IFERROR(AZ11/AY11-1,""),"") -> 0.09 | BA12: =IF(AND(ISNUMBER(BA11),ISNUMBER(AZ11)),IFERROR(BA11/AZ11-1,""),"") -> 0.09 | BB12: =IF(AND(ISNUMBER(BB11),ISNUMBER(BA11)),IFERROR(BB11/BA11-1,""),"") -> 0.085 | BC12: =IF(AND(ISNUMBER(BC11),ISNUMBER(BB11)),IFERROR(BC11/BB11-1,""),"") -> 0.08 | BL12: H2/26E currency effect on revenue growth (pts) | BM12: -0.02 | BN12: -0.03 | BO12: -0.05 | BP12: H2/26E currency effect on reported revenue growth (H1/26: −4.5 pts: +1.6% reported vs +6.1% at constant rates). USD, JPY and CNY weaker vs the euro than in H2/25.
B13: Revenue y/y % at constant exchange rates (company) | G13: 0.208 | H13: 0.115 | I13: 0.118 | J13: 0.099 | L13: 0.088 | M13: 0.126 | O13: 0.146 | P13: 0.136 | R13: 0.126 | S13: 0.163 | U13: 0.14 | V13: 0.122 | X13: 0.097 | Y13: 0.08 | AA13: 0.094 | AB13: 0.124 | AD13: 0.113 | AE13: -0.233 | AG13: -0.048 | AH13: 0.629 | AJ13: 0.289 | AK13: 0.121 | AM13: 0.156 | AN13: 0.208 | AP13: 0.167 | AQ13: 0.191 | AS13: 0.183 | AT13: 0.124 | AV13: 0.131 | AW13: 0.098 | AX13: =CHOOSE(MATCH($BD$2,{"Bull","Base","Bear"},0),$BM$19,$BN$19,$BO$19) -> 0.09 | AY13: =(AT11*(1+AW13)+AU11*(1+AX13))/AV11-1 -> 0.094048656 | AZ13: =CHOOSE(MATCH($BD$2,{"Bull","Base","Bear"},0),$BM$20,$BN$20,$BO$20) -> 0.09 | BA13: =CHOOSE(MATCH($BD$2,{"Bull","Base","Bear"},0),$BM$21,$BN$21,$BO$21) -> 0.09 | BB13: =CHOOSE(MATCH($BD$2,{"Bull","Base","Bear"},0),$BM$22,$BN$22,$BO$22) -> 0.085 | BC13: =CHOOSE(MATCH($BD$2,{"Bull","Base","Bear"},0),$BM$23,$BN$23,$BO$23) -> 0.08 | BD13: Scenario lever (LEATHER_ccGrowth, Bull/Base/Bear table →). 2026E = H1/26 actual and H2/26E growth weighted by 2025 halves. Company figures to one decimal (press releases). | BF13: =IFERROR(AVERAGE(AY13,AZ13,BA13,BB13,BC13),"n/m") -> 0.087809731 | BG13: =IFERROR(AVERAGE(AJ13,AM13,AP13,AS13,AV13),"n/m") -> 0.1852 | BH13: =IFERROR(AVERAGE(U13,X13,AA13,AD13,AG13,AJ13,AM13,AP13,AS13,AV13),"n/m") -> 0.1322 | BI13: =IFERROR(AVERAGE(C13,D13,E13,F13,G13,H13,I13,L13,O13,R13,U13,X13,AA13,AD13,AG13,AJ13,AM13,AP13,AS13,AV13),"n/m") -> 0.1326875 | BL13: 2026E effective tax rate (incl. French exceptional contribution) | BN13: 0.33 | BP13: ETR 33% and contribution ≈ 5 pts of pre-tax income: H1/26 report outlook. Capex: 2025 €1,161m, H1/26 €344m; 2024 URD guided ~€1bn for 2025.
B14: Currency (and scope) effect on growth, pts (reported − constant FX) | C14: =IF(AND(ISNUMBER(C12),ISNUMBER(C13)),C12-C13,"") | D14: =IF(AND(ISNUMBER(D12),ISNUMBER(D13)),D12-D13,"") | E14: =IF(AND(ISNUMBER(E12),ISNUMBER(E13)),E12-E13,"") | F14: =IF(AND(ISNUMBER(F12),ISNUMBER(F13)),F12-F13,"") | G14: =IF(AND(ISNUMBER(G12),ISNUMBER(G13)),G12-G13,"") -> 0.079393162 | H14: =IF(AND(ISNUMBER(H12),ISNUMBER(H13)),H12-H13,"") -> 0.0036721992 | I14: =IF(AND(ISNUMBER(I12),ISNUMBER(I13)),I12-I13,"") -> 0.066421365 | J14: =IF(AND(ISNUMBER(J12),ISNUMBER(J13)),J12-J13,"") | ... AW14: =IF(AND(ISNUMBER(AW12),ISNUMBER(AW13)),AW12-AW13,"") -> -0.046854108 | AX14: =AX64 -> -0.03 | AY14: =AY12-AY13 -> -0.038529562 | AZ14: =AZ64 -> 0 | BA14: =BA64 -> 0 | BB14: =BB64 -> 0 | BC14: =BC64 -> 0 | BD14: Forecast: group currency effect applied to every métier. | BL14: 2026E exceptional contribution (pts of pre-tax income) | BN14: 0.05
B15: % of group revenue | C15: =IF(AND(ISNUMBER(C11),ISNUMBER(C61)),IFERROR(C11/C61,""),"") | D15: =IF(AND(ISNUMBER(D11),ISNUMBER(D61)),IFERROR(D11/D61,""),"") | E15: =IF(AND(ISNUMBER(E11),ISNUMBER(E61)),IFERROR(E11/E61,""),"") | F15: =IF(AND(ISNUMBER(F11),ISNUMBER(F61)),IFERROR(F11/F61,""),"") -> 0.48902821 | G15: =IF(AND(ISNUMBER(G11),ISNUMBER(G61)),IFERROR(G11/G61,""),"") -> 0.50166528 | H15: =IF(AND(ISNUMBER(H11),ISNUMBER(H61)),IFERROR(H11/H61,""),"") -> 0.47431386 | I15: =IF(AND(ISNUMBER(I11),ISNUMBER(I61)),IFERROR(I11/I61,""),"") -> 0.45824006 | J15: =IF(AND(ISNUMBER(J11),ISNUMBER(J61)),IFERROR(J11/J61,""),"") -> 0.44134458 | ... BC15: =IF(AND(ISNUMBER(BC11),ISNUMBER(BC61)),IFERROR(BC11/BC61,""),"") -> 0.47928867 | BF15: =IFERROR(AVERAGE(AY15,AZ15,BA15,BB15,BC15),"n/m") -> 0.46745655 | BG15: =IFERROR(AVERAGE(AJ15,AM15,AP15,AS15,AV15),"n/m") -> 0.43278761 | BH15: =IFERROR(AVERAGE(U15,X15,AA15,AD15,AG15,AJ15,AM15,AP15,AS15,AV15),"n/m") -> 0.4666144 | BI15: =IFERROR(AVERAGE(C15,D15,E15,F15,G15,H15,I15,L15,O15,R15,U15,X15,AA15,AD15,AG15,AJ15,AM15,AP15,AS15,AV15),"n/m") -> 0.46715038 | BL15: 2026E operating investments (€m) | BN15: 1150
B17: Ready-to-wear and Accessories (men's & women's RTW, belts, fashion jewellery, gloves, hats, shoes) | BD17: READY-TO-WEAR AND ACCESSORIES — modelling logic
B18: Revenue | F18: 360 | G18: 445 | H18: 576 | I18: 745.6 | J18: 395.6 | K18: =L18-J18 -> 447.5 | L18: 843.1 | M18: 440.6 | N18: =O18-M18 -> 493 | O18: 933.6 | P18: 534.1 | Q18: =R18-P18 -> 566.5 | R18: 1100.6 | S18: 517.5 | T18: =U18-S18 -> 581.6 | U18: 1099.1 | V18: 579.2 | W18: =X18-V18 -> 601.9 | X18: 1181.1 | Y18: 637.3 | Z18: =AA18-Y18 -> 673.1 | AA18: 1310.4 | AB18: 754.6 | AC18: =AD18-AB18 -> 819.6 | AD18: 1574.2 | AE18: 537 | AF18: =AG18-AE18 -> 871.9 | AG18: 1408.9 | AH18: 1025.1 | AI18: =AJ18-AH18 -> 1193.9 | AJ18: 2219 | AK18: 1458 | AL18: =AM18-AK18 -> 1694 | AM18: 3152 | AN18: 1922 | AO18: =AP18-AN18 -> 1957 | AP18: 3879 | AQ18: 2162 | AR18: =AS18-AQ18 -> 2243 | AS18: 4405 | AT18: 2255 | AU18: =AV18-AT18 -> 2270 | AV18: 4525 | AW18: 2198 | AX18: =AU18*(1+AX20+AX64) -> 2292.7 | AY18: =AW18+AX18 -> 4490.7 | AZ18: =AY18*(1+AZ20+AZ64) -> 4760.142 | BA18: =AZ18*(1+BA20+BA64) -> 5045.7505 | BB18: =BA18*(1+BB20+BB64) -> 5348.4956 | BC18: =BB18*(1+BC20+BC64) -> 5642.6628 | BD18: H2/26E: H2/25 × (1 + scenario constant-currency growth + H2/26E currency effect). 2027E+: prior year × (1 + scenario cc growth + currency effect). | BF18: =IFERROR((BC18/AV18)^(1/5)-1,"n/m") -> 0.045136711 | BG18: =IFERROR((AV18/AG18)^(1/5)-1,"n/m") -> 0.26283812 | BH18: =IFERROR((AV18/R18)^(1/10)-1,"n/m") -> 0.15185791 | BI18: =IFERROR((AV18/C18)^(1/19)-1,"n/m") -> n/m | BL18: LEATHER_ccGrowth (Leather Goods & Saddlery revenue y/y, constant FX) | BM18: 0.02 | BN18: Δ → | BO18: -0.03 | BP18: H1/26 +9.8% (Q2 slightly above Q1); FY25 +13.1%, FY24 +18.3%. Capacity: 25th workshop (Loupes, 2026), three more by 2030.
B19: Revenue y/y % (reported) | D19: =IF(AND(ISNUMBER(D18),ISNUMBER(C18)),IFERROR(D18/C18-1,""),"") | E19: =IF(AND(ISNUMBER(E18),ISNUMBER(D18)),IFERROR(E18/D18-1,""),"") | F19: =IF(AND(ISNUMBER(F18),ISNUMBER(E18)),IFERROR(F18/E18-1,""),"") | G19: =IF(AND(ISNUMBER(G18),ISNUMBER(F18)),IFERROR(G18/F18-1,""),"") -> 0.23611111 | H19: =IF(AND(ISNUMBER(H18),ISNUMBER(G18)),IFERROR(H18/G18-1,""),"") -> 0.29438202 | I19: =IF(AND(ISNUMBER(I18),ISNUMBER(H18)),IFERROR(I18/H18-1,""),"") -> 0.29444444 | L19: =IF(AND(ISNUMBER(L18),ISNUMBER(I18)),IFERROR(L18/I18-1,""),"") -> 0.13076717 | M19: =IF(AND(ISNUMBER(M18),ISNUMBER(J18)),IFERROR(M18/J18-1,""),"") -> 0.11375126 | N19: =IF(AND(ISNUMBER(N18),ISNUMBER(K18)),IFERROR(N18/K18-1,""),"") -> 0.10167598 | O19: =IF(AND(ISNUMBER(O18),ISNUMBER(L18)),IFERROR(O18/L18-1,""),"") -> 0.10734195 | P19: =IF(AND(ISNUMBER(P18),ISNUMBER(M18)),IFERROR(P18/M18-1,""),"") -> 0.21221062 | Q19: =IF(AND(ISNUMBER(Q18),ISNUMBER(N18)),IFERROR(Q18/N18-1,""),"") -> 0.14908722 | R19: =IF(AND(ISNUMBER(R18),ISNUMBER(O18)),IFERROR(R18/O18-1,""),"") -> 0.17887746 | S19: =IF(AND(ISNUMBER(S18),ISNUMBER(P18)),IFERROR(S18/P18-1,""),"") -> -0.031080322 | ... AY19: =IF(AND(ISNUMBER(AY18),ISNUMBER(AV18)),IFERROR(AY18/AV18-1,""),"") -> -0.0075801105 | AZ19: =IF(AND(ISNUMBER(AZ18),ISNUMBER(AY18)),IFERROR(AZ18/AY18-1,""),"") -> 0.06 | BA19: =IF(AND(ISNUMBER(BA18),ISNUMBER(AZ18)),IFERROR(BA18/AZ18-1,""),"") -> 0.06 | BB19: =IF(AND(ISNUMBER(BB18),ISNUMBER(BA18)),IFERROR(BB18/BA18-1,""),"") -> 0.06 | BC19: =IF(AND(ISNUMBER(BC18),ISNUMBER(BB18)),IFERROR(BC18/BB18-1,""),"") -> 0.055 | BL19: H2/26E | BM19: =BN19+$BM$18 -> 0.11 | BN19: 0.09 | BO19: =BN19+$BO$18 -> 0.06
B20: Revenue y/y % at constant exchange rates (company) | G20: 0.175 | H20: 0.3 | I20: 0.223 | J20: 0.208 | L20: 0.179 | M20: 0.158 | O20: 0.12 | P20: 0.081 | R20: 0.078 | S20: -0.017 | U20: 0.002 | V20: 0.104 | X20: 0.094 | Y20: 0.167 | AA20: 0.141 | AB20: 0.152 | AD20: 0.171 | AE20: -0.293 | AG20: -0.092 | AH20: 0.98 | AJ20: 0.588 | AK20: 0.359 | AM20: 0.358 | AN20: 0.348 | AP20: 0.282 | AQ20: 0.155 | AS20: 0.154 | AT20: 0.055 | AV20: 0.061 | AW20: 0.02 | AX20: =CHOOSE(MATCH($BD$2,{"Bull","Base","Bear"},0),$BM$25,$BN$25,$BO$25) -> 0.04 | AY20: =(AT18*(1+AW20)+AU18*(1+AX20))/AV18-1 -> 0.030033149 | AZ20: =CHOOSE(MATCH($BD$2,{"Bull","Base","Bear"},0),$BM$26,$BN$26,$BO$26) -> 0.06 | BA20: =CHOOSE(MATCH($BD$2,{"Bull","Base","Bear"},0),$BM$27,$BN$27,$BO$27) -> 0.06 | BB20: =CHOOSE(MATCH($BD$2,{"Bull","Base","Bear"},0),$BM$28,$BN$28,$BO$28) -> 0.06 | BC20: =CHOOSE(MATCH($BD$2,{"Bull","Base","Bear"},0),$BM$29,$BN$29,$BO$29) -> 0.055 | BD20: Scenario lever (RTW_ccGrowth, Bull/Base/Bear table →). 2026E = H1/26 actual and H2/26E growth weighted by 2025 halves. Company figures to one decimal (press releases). | BF20: =IFERROR(AVERAGE(AY20,AZ20,BA20,BB20,BC20),"n/m") -> 0.05300663 | BG20: =IFERROR(AVERAGE(AJ20,AM20,AP20,AS20,AV20),"n/m") -> 0.2886 | BH20: =IFERROR(AVERAGE(U20,X20,AA20,AD20,AG20,AJ20,AM20,AP20,AS20,AV20),"n/m") -> 0.1759 | BI20: =IFERROR(AVERAGE(C20,D20,E20,F20,G20,H20,I20,L20,O20,R20,U20,X20,AA20,AD20,AG20,AJ20,AM20,AP20,AS20,AV20),"n/m") -> 0.177125 | BL20: 2027E | BM20: =BN20+$BM$18 -> 0.11 | BN20: 0.09 | BO20: =BN20+$BO$18 -> 0.06
B21: Currency (and scope) effect on growth, pts (reported − constant FX) | C21: =IF(AND(ISNUMBER(C19),ISNUMBER(C20)),C19-C20,"") | D21: =IF(AND(ISNUMBER(D19),ISNUMBER(D20)),D19-D20,"") | E21: =IF(AND(ISNUMBER(E19),ISNUMBER(E20)),E19-E20,"") | F21: =IF(AND(ISNUMBER(F19),ISNUMBER(F20)),F19-F20,"") | G21: =IF(AND(ISNUMBER(G19),ISNUMBER(G20)),G19-G20,"") -> 0.061111111 | H21: =IF(AND(ISNUMBER(H19),ISNUMBER(H20)),H19-H20,"") -> -0.0056179775 | I21: =IF(AND(ISNUMBER(I19),ISNUMBER(I20)),I19-I20,"") -> 0.071444444 | J21: =IF(AND(ISNUMBER(J19),ISNUMBER(J20)),J19-J20,"") | ... AW21: =IF(AND(ISNUMBER(AW19),ISNUMBER(AW20)),AW19-AW20,"") -> -0.045277162 | AX21: =AX64 -> -0.03 | AY21: =AY19-AY20 -> -0.03761326 | AZ21: =AZ64 -> 0 | BA21: =BA64 -> 0 | BB21: =BB64 -> 0 | BC21: =BC64 -> 0 | BL21: 2028E | BM21: =BN21+$BM$18 -> 0.11 | BN21: 0.09 | BO21: =BN21+$BO$18 -> 0.06
B22: % of group revenue | C22: =IF(AND(ISNUMBER(C18),ISNUMBER(C61)),IFERROR(C18/C61,""),"") | D22: =IF(AND(ISNUMBER(D18),ISNUMBER(D61)),IFERROR(D18/D61,""),"") | E22: =IF(AND(ISNUMBER(E18),ISNUMBER(E61)),IFERROR(E18/E61,""),"") | F22: =IF(AND(ISNUMBER(F18),ISNUMBER(F61)),IFERROR(F18/F61,""),"") -> 0.18808777 | G22: =IF(AND(ISNUMBER(G18),ISNUMBER(G61)),IFERROR(G18/G61,""),"") -> 0.18526228 | H22: =IF(AND(ISNUMBER(H18),ISNUMBER(H61)),IFERROR(H18/H61,""),"") -> 0.20267417 | I22: =IF(AND(ISNUMBER(I18),ISNUMBER(I61)),IFERROR(I18/I61,""),"") -> 0.2139946 | J22: =IF(AND(ISNUMBER(J18),ISNUMBER(J61)),IFERROR(J18/J61,""),"") -> 0.22386962 | ... BC22: =IF(AND(ISNUMBER(BC18),ISNUMBER(BC61)),IFERROR(BC18/BC61,""),"") -> 0.26030905 | BF22: =IFERROR(AVERAGE(AY22,AZ22,BA22,BB22,BC22),"n/m") -> 0.26675409 | BG22: =IFERROR(AVERAGE(AJ22,AM22,AP22,AS22,AV22),"n/m") -> 0.27616879 | BH22: =IFERROR(AVERAGE(U22,X22,AA22,AD22,AG22,AJ22,AM22,AP22,AS22,AV22),"n/m") -> 0.24738038 | BI22: =IFERROR(AVERAGE(C22,D22,E22,F22,G22,H22,I22,L22,O22,R22,U22,X22,AA22,AD22,AG22,AJ22,AM22,AP22,AS22,AV22),"n/m") -> 0.2319047 | BL22: 2029E | BM22: =BN22+$BM$18 -> 0.105 | BN22: 0.085 | BO22: =BN22+$BO$18 -> 0.055
BL23: 2030E | BM23: =BN23+$BM$18 -> 0.1 | BN23: 0.08 | BO23: =BN23+$BO$18 -> 0.05
B24: Silk and Textiles | BD24: SILK AND TEXTILES — modelling logic | BL24: RTW_ccGrowth (Ready-to-wear and Accessories revenue y/y, constant FX) | BM24: 0.02 | BN24: Δ → | BO24: -0.03 | BP24: H1/26 +2.0% with a Q2 acceleration (women's AW26 collection); FY25 +6.1%, FY24 +15.4%.
B25: Revenue | F25: 227 | G25: 284 | H25: 347 | I25: 424.6 | J25: 201.7 | K25: =L25-J25 -> 252.2 | L25: 453.9 | M25: 216 | N25: =O25-M25 -> 266.3 | O25: 482.3 | P25: 250.6 | Q25: =R25-P25 -> 270.6 | R25: 521.2 | S25: 230.3 | T25: =U25-S25 -> 285 | U25: 515.3 | V25: 246.3 | W25: =X25-V25 -> 288 | X25: 534.3 | Y25: 249.4 | Z25: =AA25-Y25 -> 287.5 | AA25: 536.9 | AB25: 266.6 | AC25: =AD25-AB25 -> 325.9 | AD25: 592.5 | AE25: 165.2 | AF25: =AG25-AE25 -> 286.8 | AG25: 452 | AH25: 273.9 | AI25: =AJ25-AH25 -> 395.1 | AJ25: 669 | AK25: 372 | AL25: =AM25-AK25 -> 470 | AM25: 842 | AN25: 444 | AO25: =AP25-AN25 -> 488 | AP25: 932 | AQ25: 436 | AR25: =AS25-AQ25 -> 514 | AS25: 950 | AT25: 447 | AU25: =AV25-AT25 -> 517 | AV25: 964 | AW25: 469 | AX25: =AU25*(1+AX27+AX64) -> 542.85 | AY25: =AW25+AX25 -> 1011.85 | AZ25: =AY25*(1+AZ27+AZ64) -> 1072.561 | BA25: =AZ25*(1+BA27+BA64) -> 1136.9147 | BB25: =BA25*(1+BB27+BB64) -> 1199.445 | BC25: =BB25*(1+BC27+BC64) -> 1259.4172 | BD25: H2/26E: H2/25 × (1 + scenario constant-currency growth + H2/26E currency effect). 2027E+: prior year × (1 + scenario cc growth + currency effect). | BF25: =IFERROR((BC25/AV25)^(1/5)-1,"n/m") -> 0.054917552 | BG25: =IFERROR((AV25/AG25)^(1/5)-1,"n/m") -> 0.16355715 | BH25: =IFERROR((AV25/R25)^(1/10)-1,"n/m") -> 0.063425972 | BI25: =IFERROR((AV25/C25)^(1/19)-1,"n/m") -> n/m | BL25: H2/26E | BM25: =BN25+$BM$24 -> 0.06 | BN25: 0.04 | BO25: =BN25+$BO$24 -> 0.01
B26: Revenue y/y % (reported) | D26: =IF(AND(ISNUMBER(D25),ISNUMBER(C25)),IFERROR(D25/C25-1,""),"") | E26: =IF(AND(ISNUMBER(E25),ISNUMBER(D25)),IFERROR(E25/D25-1,""),"") | F26: =IF(AND(ISNUMBER(F25),ISNUMBER(E25)),IFERROR(F25/E25-1,""),"") | G26: =IF(AND(ISNUMBER(G25),ISNUMBER(F25)),IFERROR(G25/F25-1,""),"") -> 0.25110132 | H26: =IF(AND(ISNUMBER(H25),ISNUMBER(G25)),IFERROR(H25/G25-1,""),"") -> 0.22183099 | I26: =IF(AND(ISNUMBER(I25),ISNUMBER(H25)),IFERROR(I25/H25-1,""),"") -> 0.22363112 | L26: =IF(AND(ISNUMBER(L25),ISNUMBER(I25)),IFERROR(L25/I25-1,""),"") -> 0.069006123 | M26: =IF(AND(ISNUMBER(M25),ISNUMBER(J25)),IFERROR(M25/J25-1,""),"") -> 0.070897372 | N26: =IF(AND(ISNUMBER(N25),ISNUMBER(K25)),IFERROR(N25/K25-1,""),"") -> 0.05590801 | O26: =IF(AND(ISNUMBER(O25),ISNUMBER(L25)),IFERROR(O25/L25-1,""),"") -> 0.062568848 | P26: =IF(AND(ISNUMBER(P25),ISNUMBER(M25)),IFERROR(P25/M25-1,""),"") -> 0.16018519 | Q26: =IF(AND(ISNUMBER(Q25),ISNUMBER(N25)),IFERROR(Q25/N25-1,""),"") -> 0.016147202 | R26: =IF(AND(ISNUMBER(R25),ISNUMBER(O25)),IFERROR(R25/O25-1,""),"") -> 0.080655194 | S26: =IF(AND(ISNUMBER(S25),ISNUMBER(P25)),IFERROR(S25/P25-1,""),"") -> -0.081005587 | ... AY26: =IF(AND(ISNUMBER(AY25),ISNUMBER(AV25)),IFERROR(AY25/AV25-1,""),"") -> 0.049636929 | AZ26: =IF(AND(ISNUMBER(AZ25),ISNUMBER(AY25)),IFERROR(AZ25/AY25-1,""),"") -> 0.06 | BA26: =IF(AND(ISNUMBER(BA25),ISNUMBER(AZ25)),IFERROR(BA25/AZ25-1,""),"") -> 0.06 | BB26: =IF(AND(ISNUMBER(BB25),ISNUMBER(BA25)),IFERROR(BB25/BA25-1,""),"") -> 0.055 | BC26: =IF(AND(ISNUMBER(BC25),ISNUMBER(BB25)),IFERROR(BC25/BB25-1,""),"") -> 0.05 | BL26: 2027E | BM26: =BN26+$BM$24 -> 0.08 | BN26: 0.06 | BO26: =BN26+$BO$24 -> 0.03
B27: Revenue y/y % at constant exchange rates (company) | G27: 0.189 | H27: 0.226 | I27: 0.159 | J27: 0.129 | L27: 0.115 | M27: 0.113 | O27: 0.076 | P27: 0.046 | R27: -0.005 | S27: -0.069 | U27: -0.008 | V27: 0.058 | X27: 0.057 | Y27: 0.071 | AA27: 0.032 | AB27: 0.04 | AD27: 0.075 | AE27: -0.385 | AG27: -0.228 | AH27: 0.719 | AJ27: 0.491 | AK27: 0.29 | AM27: 0.203 | AN27: 0.224 | AP27: 0.156 | AQ27: 0.015 | AS27: 0.038 | AT27: 0.035 | AV27: 0.047 | AW27: 0.097 | AX27: =CHOOSE(MATCH($BD$2,{"Bull","Base","Bear"},0),$BM$31,$BN$31,$BO$31) -> 0.08 | AY27: =(AT25*(1+AW27)+AU25*(1+AX27))/AV25-1 -> 0.08788278 | AZ27: =CHOOSE(MATCH($BD$2,{"Bull","Base","Bear"},0),$BM$32,$BN$32,$BO$32) -> 0.06 | BA27: =CHOOSE(MATCH($BD$2,{"Bull","Base","Bear"},0),$BM$33,$BN$33,$BO$33) -> 0.06 | BB27: =CHOOSE(MATCH($BD$2,{"Bull","Base","Bear"},0),$BM$34,$BN$34,$BO$34) -> 0.055 | BC27: =CHOOSE(MATCH($BD$2,{"Bull","Base","Bear"},0),$BM$35,$BN$35,$BO$35) -> 0.05 | BD27: Scenario lever (SILK_ccGrowth, Bull/Base/Bear table →). 2026E = H1/26 actual and H2/26E growth weighted by 2025 halves. Company figures to one decimal (press releases). | BF27: =IFERROR(AVERAGE(AY27,AZ27,BA27,BB27,BC27),"n/m") -> 0.062576556 | BG27: =IFERROR(AVERAGE(AJ27,AM27,AP27,AS27,AV27),"n/m") -> 0.187 | BH27: =IFERROR(AVERAGE(U27,X27,AA27,AD27,AG27,AJ27,AM27,AP27,AS27,AV27),"n/m") -> 0.0863 | BI27: =IFERROR(AVERAGE(C27,D27,E27,F27,G27,H27,I27,L27,O27,R27,U27,X27,AA27,AD27,AG27,AJ27,AM27,AP27,AS27,AV27),"n/m") -> 0.1014375 | BL27: 2028E | BM27: =BN27+$BM$24 -> 0.08 | BN27: 0.06 | BO27: =BN27+$BO$24 -> 0.03
B28: Currency (and scope) effect on growth, pts (reported − constant FX) | C28: =IF(AND(ISNUMBER(C26),ISNUMBER(C27)),C26-C27,"") | D28: =IF(AND(ISNUMBER(D26),ISNUMBER(D27)),D26-D27,"") | E28: =IF(AND(ISNUMBER(E26),ISNUMBER(E27)),E26-E27,"") | F28: =IF(AND(ISNUMBER(F26),ISNUMBER(F27)),F26-F27,"") | G28: =IF(AND(ISNUMBER(G26),ISNUMBER(G27)),G26-G27,"") -> 0.062101322 | H28: =IF(AND(ISNUMBER(H26),ISNUMBER(H27)),H26-H27,"") -> -0.0041690141 | I28: =IF(AND(ISNUMBER(I26),ISNUMBER(I27)),I26-I27,"") -> 0.064631124 | J28: =IF(AND(ISNUMBER(J26),ISNUMBER(J27)),J26-J27,"") | ... AW28: =IF(AND(ISNUMBER(AW26),ISNUMBER(AW27)),AW26-AW27,"") -> -0.047782998 | AX28: =AX64 -> -0.03 | AY28: =AY26-AY27 -> -0.038245851 | AZ28: =AZ64 -> 0 | BA28: =BA64 -> 0 | BB28: =BB64 -> 0 | BC28: =BC64 -> 0 | BL28: 2029E | BM28: =BN28+$BM$24 -> 0.08 | BN28: 0.06 | BO28: =BN28+$BO$24 -> 0.03
B29: % of group revenue | C29: =IF(AND(ISNUMBER(C25),ISNUMBER(C61)),IFERROR(C25/C61,""),"") | D29: =IF(AND(ISNUMBER(D25),ISNUMBER(D61)),IFERROR(D25/D61,""),"") | E29: =IF(AND(ISNUMBER(E25),ISNUMBER(E61)),IFERROR(E25/E61,""),"") | F29: =IF(AND(ISNUMBER(F25),ISNUMBER(F61)),IFERROR(F25/F61,""),"") -> 0.11859979 | G29: =IF(AND(ISNUMBER(G25),ISNUMBER(G61)),IFERROR(G25/G61,""),"") -> 0.1182348 | H29: =IF(AND(ISNUMBER(H25),ISNUMBER(H61)),IFERROR(H25/H61,""),"") -> 0.12209711 | I29: =IF(AND(ISNUMBER(I25),ISNUMBER(I61)),IFERROR(I25/I61,""),"") -> 0.12186442 | J29: =IF(AND(ISNUMBER(J25),ISNUMBER(J61)),IFERROR(J25/J61,""),"") -> 0.11414181 | ... BC29: =IF(AND(ISNUMBER(BC25),ISNUMBER(BC61)),IFERROR(BC25/BC61,""),"") -> 0.05809982 | BF29: =IFERROR(AVERAGE(AY29,AZ29,BA29,BB29,BC29),"n/m") -> 0.059938706 | BG29: =IFERROR(AVERAGE(AJ29,AM29,AP29,AS29,AV29),"n/m") -> 0.067870551 | BH29: =IFERROR(AVERAGE(U29,X29,AA29,AD29,AG29,AJ29,AM29,AP29,AS29,AV29),"n/m") -> 0.078150238 | BI29: =IFERROR(AVERAGE(C29,D29,E29,F29,G29,H29,I29,L29,O29,R29,U29,X29,AA29,AD29,AG29,AJ29,AM29,AP29,AS29,AV29),"n/m") -> 0.094584996 | BL29: 2030E | BM29: =BN29+$BM$24 -> 0.075 | BN29: 0.055 | BO29: =BN29+$BO$24 -> 0.025
BL30: SILK_ccGrowth (Silk and Textiles revenue y/y, constant FX) | BM30: 0.02 | BN30: Δ → | BO30: -0.03 | BP30: H1/26 +9.7% (acceleration in Q2); FY25 +4.7%, FY24 +3.8%.
B31: Other Hermès sectors (Jewellery, Home / Art of Living & Tableware — Tableware folded in from 2014) | BD31: OTHER HERMÈS SECTORS — modelling logic | BL31: H2/26E | BM31: =BN31+$BM$30 -> 0.1 | BN31: 0.08 | BO31: =BN31+$BO$30 -> 0.05
B32: Revenue | F32: 116 | G32: 131 | H32: 160 | I32: 225.7 | J32: 123.6 | K32: =L32-J32 -> 154 | L32: 277.6 | M32: 124.5 | N32: =O32-M32 -> 156.4 | O32: 280.9 | P32: 154.9 | Q32: =R32-P32 -> 177 | R32: 331.9 | S32: 150.6 | T32: =U32-S32 -> 185.4 | U32: 336 | V32: 172.3 | W32: =X32-V32 -> 192.7 | X32: 365 | Y32: 201.7 | Z32: =AA32-Y32 -> 223 | AA32: 424.7 | AB32: 247.6 | AC32: =AD32-AB32 -> 277.3 | AD32: 524.9 | AE32: 239.2 | AF32: =AG32-AE32 -> 403.4 | AG32: 642.6 | AH32: 462.3 | AI32: =AJ32-AH32 -> 538.7 | AJ32: 1001 | AK32: 648 | AL32: =AM32-AK32 -> 723 | AM32: 1371 | AN32: 836 | AO32: =AP32-AN32 -> 817 | AP32: 1653 | AQ32: 967 | AR32: =AS32-AQ32 -> 942 | AS32: 1909 | AT32: 1056 | AU32: =AV32-AT32 -> 999 | AV32: 2055 | AW32: 1065 | AX32: =AU32*(1+AX34+AX64) -> 1028.97 | AY32: =AW32+AX32 -> 2093.97 | AZ32: =AY32*(1+AZ34+AZ64) -> 2261.4876 | BA32: =AZ32*(1+BA34+BA64) -> 2442.4066 | BB32: =BA32*(1+BB34+BB64) -> 2625.5871 | BC32: =BB32*(1+BC34+BC64) -> 2809.3782 | BD32: H2/26E: H2/25 × (1 + scenario constant-currency growth + H2/26E currency effect). 2027E+: prior year × (1 + scenario cc growth + currency effect). | BF32: =IFERROR((BC32/AV32)^(1/5)-1,"n/m") -> 0.064534342 | BG32: =IFERROR((AV32/AG32)^(1/5)-1,"n/m") -> 0.26175264 | BH32: =IFERROR((AV32/R32)^(1/10)-1,"n/m") -> 0.19999782 | BI32: =IFERROR((AV32/C32)^(1/19)-1,"n/m") -> n/m | BL32: 2027E | BM32: =BN32+$BM$30 -> 0.08 | BN32: 0.06 | BO32: =BN32+$BO$30 -> 0.03
B33: Revenue y/y % (reported) | D33: =IF(AND(ISNUMBER(D32),ISNUMBER(C32)),IFERROR(D32/C32-1,""),"") | E33: =IF(AND(ISNUMBER(E32),ISNUMBER(D32)),IFERROR(E32/D32-1,""),"") | F33: =IF(AND(ISNUMBER(F32),ISNUMBER(E32)),IFERROR(F32/E32-1,""),"") | G33: =IF(AND(ISNUMBER(G32),ISNUMBER(F32)),IFERROR(G32/F32-1,""),"") -> 0.12931034 | H33: =IF(AND(ISNUMBER(H32),ISNUMBER(G32)),IFERROR(H32/G32-1,""),"") -> 0.22137405 | I33: =IF(AND(ISNUMBER(I32),ISNUMBER(H32)),IFERROR(I32/H32-1,""),"") -> 0.410625 | L33: =IF(AND(ISNUMBER(L32),ISNUMBER(I32)),IFERROR(L32/I32-1,""),"") -> 0.22995126 | M33: =IF(AND(ISNUMBER(M32),ISNUMBER(J32)),IFERROR(M32/J32-1,""),"") -> 0.0072815534 | N33: =IF(AND(ISNUMBER(N32),ISNUMBER(K32)),IFERROR(N32/K32-1,""),"") -> 0.015584416 | O33: =IF(AND(ISNUMBER(O32),ISNUMBER(L32)),IFERROR(O32/L32-1,""),"") -> 0.011887608 | P33: =IF(AND(ISNUMBER(P32),ISNUMBER(M32)),IFERROR(P32/M32-1,""),"") -> 0.24417671 | Q33: =IF(AND(ISNUMBER(Q32),ISNUMBER(N32)),IFERROR(Q32/N32-1,""),"") -> 0.13171355 | R33: =IF(AND(ISNUMBER(R32),ISNUMBER(O32)),IFERROR(R32/O32-1,""),"") -> 0.18155927 | S33: =IF(AND(ISNUMBER(S32),ISNUMBER(P32)),IFERROR(S32/P32-1,""),"") -> -0.027759845 | ... AY33: =IF(AND(ISNUMBER(AY32),ISNUMBER(AV32)),IFERROR(AY32/AV32-1,""),"") -> 0.018963504 | AZ33: =IF(AND(ISNUMBER(AZ32),ISNUMBER(AY32)),IFERROR(AZ32/AY32-1,""),"") -> 0.08 | BA33: =IF(AND(ISNUMBER(BA32),ISNUMBER(AZ32)),IFERROR(BA32/AZ32-1,""),"") -> 0.08 | BB33: =IF(AND(ISNUMBER(BB32),ISNUMBER(BA32)),IFERROR(BB32/BA32-1,""),"") -> 0.075 | BC33: =IF(AND(ISNUMBER(BC32),ISNUMBER(BB32)),IFERROR(BC32/BB32-1,""),"") -> 0.07 | BL33: 2028E | BM33: =BN33+$BM$30 -> 0.08 | BN33: 0.06 | BO33: =BN33+$BO$30 -> 0.03
B34: Revenue y/y % at constant exchange rates (company) | G34: 0.075228359 | H34: 0.22459347 | I34: 0.35708799 | J34: 0.29684595 | L34: 0.27834669 | M34: 0.18 | O34: 0.151 | P34: 0.118 | R34: 0.085 | S34: -0.015 | U34: 0.016 | V34: 0.13 | X34: 0.105 | Y34: 0.241 | AA34: 0.196 | AB34: 0.194 | AD34: 0.204 | AE34: -0.042 | AG34: 0.239 | AH34: 1.004 | AJ34: 0.567 | AK34: 0.325 | AM34: 0.296 | AN34: 0.321 | AP34: 0.258 | AQ34: 0.187 | AS34: 0.171 | AT34: 0.103 | AV34: 0.112 | AW34: 0.054 | AX34: =CHOOSE(MATCH($BD$2,{"Bull","Base","Bear"},0),$BM$37,$BN$37,$BO$37) -> 0.06 | AY34: =(AT32*(1+AW34)+AU32*(1+AX34))/AV32-1 -> 0.056916788 | AZ34: =CHOOSE(MATCH($BD$2,{"Bull","Base","Bear"},0),$BM$38,$BN$38,$BO$38) -> 0.08 | BA34: =CHOOSE(MATCH($BD$2,{"Bull","Base","Bear"},0),$BM$39,$BN$39,$BO$39) -> 0.08 | BB34: =CHOOSE(MATCH($BD$2,{"Bull","Base","Bear"},0),$BM$40,$BN$40,$BO$40) -> 0.075 | BC34: =CHOOSE(MATCH($BD$2,{"Bull","Base","Bear"},0),$BM$41,$BN$41,$BO$41) -> 0.07 | BD34: Scenario lever (OTHER_HERMES_ccGrowth, Bull/Base/Bear table →). 2026E = H1/26 actual and H2/26E growth weighted by 2025 halves. Company figures to one decimal (press releases). | BF34: =IFERROR(AVERAGE(AY34,AZ34,BA34,BB34,BC34),"n/m") -> 0.072383358 | BG34: =IFERROR(AVERAGE(AJ34,AM34,AP34,AS34,AV34),"n/m") -> 0.2808 | BH34: =IFERROR(AVERAGE(U34,X34,AA34,AD34,AG34,AJ34,AM34,AP34,AS34,AV34),"n/m") -> 0.2164 | BI34: =IFERROR(AVERAGE(C34,D34,E34,F34,G34,H34,I34,L34,O34,R34,U34,X34,AA34,AD34,AG34,AJ34,AM34,AP34,AS34,AV34),"n/m") -> 0.20845353 | BL34: 2029E | BM34: =BN34+$BM$30 -> 0.075 | BN34: 0.055 | BO34: =BN34+$BO$30 -> 0.025
B35: Currency (and scope) effect on growth, pts (reported − constant FX) | C35: =IF(AND(ISNUMBER(C33),ISNUMBER(C34)),C33-C34,"") | D35: =IF(AND(ISNUMBER(D33),ISNUMBER(D34)),D33-D34,"") | E35: =IF(AND(ISNUMBER(E33),ISNUMBER(E34)),E33-E34,"") | F35: =IF(AND(ISNUMBER(F33),ISNUMBER(F34)),F33-F34,"") | G35: =IF(AND(ISNUMBER(G33),ISNUMBER(G34)),G33-G34,"") -> 0.054081986 | H35: =IF(AND(ISNUMBER(H33),ISNUMBER(H34)),H33-H34,"") -> -0.0032194223 | I35: =IF(AND(ISNUMBER(I33),ISNUMBER(I34)),I33-I34,"") -> 0.05353701 | J35: =IF(AND(ISNUMBER(J33),ISNUMBER(J34)),J33-J34,"") | ... AW35: =IF(AND(ISNUMBER(AW33),ISNUMBER(AW34)),AW33-AW34,"") -> -0.045477273 | AX35: =AX64 -> -0.03 | AY35: =AY33-AY34 -> -0.037953285 | AZ35: =AZ64 -> 0 | BA35: =BA64 -> 0 | BB35: =BB64 -> 0 | BC35: =BC64 -> 0 | BD35: 2014: Other Hermès sectors scope restated by the company (Tableware folded in, comparatives restated), so reported y/y vs 2013 as originally published is not like-for-like. | BL35: 2030E | BM35: =BN35+$BM$30 -> 0.07 | BN35: 0.05 | BO35: =BN35+$BO$30 -> 0.02
B36: % of group revenue | C36: =IF(AND(ISNUMBER(C32),ISNUMBER(C61)),IFERROR(C32/C61,""),"") | D36: =IF(AND(ISNUMBER(D32),ISNUMBER(D61)),IFERROR(D32/D61,""),"") | E36: =IF(AND(ISNUMBER(E32),ISNUMBER(E61)),IFERROR(E32/E61,""),"") | F36: =IF(AND(ISNUMBER(F32),ISNUMBER(F61)),IFERROR(F32/F61,""),"") -> 0.060606061 | G36: =IF(AND(ISNUMBER(G32),ISNUMBER(G61)),IFERROR(G32/G61,""),"") -> 0.054537885 | H36: =IF(AND(ISNUMBER(H32),ISNUMBER(H61)),IFERROR(H32/H61,""),"") -> 0.056298381 | I36: =IF(AND(ISNUMBER(I32),ISNUMBER(I61)),IFERROR(I32/I61,""),"") -> 0.064778141 | J36: =IF(AND(ISNUMBER(J32),ISNUMBER(J61)),IFERROR(J32/J61,""),"") -> 0.069945108 | ... BC36: =IF(AND(ISNUMBER(BC32),ISNUMBER(BC61)),IFERROR(BC32/BC61,""),"") -> 0.12960309 | BF36: =IFERROR(AVERAGE(AY36,AZ36,BA36,BB36,BC36),"n/m") -> 0.12874724 | BG36: =IFERROR(AVERAGE(AJ36,AM36,AP36,AS36,AV36),"n/m") -> 0.12140342 | BH36: =IFERROR(AVERAGE(U36,X36,AA36,AD36,AG36,AJ36,AM36,AP36,AS36,AV36),"n/m") -> 0.098539428 | BI36: =IFERROR(AVERAGE(C36,D36,E36,F36,G36,H36,I36,L36,O36,R36,U36,X36,AA36,AD36,AG36,AJ36,AM36,AP36,AS36,AV36),"n/m") -> 0.084253318 | BL36: OTHER_HERMES_ccGrowth (Other Hermès sectors revenue y/y, constant FX) | BM36: 0.02 | BN36: Δ → | BO36: -0.03 | BP36: Jewellery and Home: H1/26 +5.4%; FY25 +11.2%, FY24 +17.1%.
B37: Memo: Tableware (separate métier to 2013, as originally reported) | F37: 38 | G37: 44 | H37: 51 | I37: 60.5 | J37: 28.9 | K37: =L37-J37 -> 32.3 | L37: 61.2 | BL37: H2/26E | BM37: =BN37+$BM$36 -> 0.08 | BN37: 0.06 | BO37: =BN37+$BO$36 -> 0.03
BL38: 2027E | BM38: =BN38+$BM$36 -> 0.1 | BN38: 0.08 | BO38: =BN38+$BO$36 -> 0.05
B39: Perfume and Beauty (Perfumes to 2019; Beauty from 2020) | BD39: PERFUME AND BEAUTY — modelling logic | BL39: 2028E | BM39: =BN39+$BM$36 -> 0.1 | BN39: 0.08 | BO39: =BN39+$BO$36 -> 0.05
B40: Revenue | F40: 117 | G40: 138 | H40: 159 | I40: 184.1 | J40: 106.7 | K40: =L40-J40 -> 103 | L40: 209.7 | M40: 114.6 | N40: =O40-M40 -> 116.2 | O40: 230.8 | P40: 120.3 | Q40: =R40-P40 -> 121.1 | R40: 241.4 | S40: 124.6 | T40: =U40-S40 -> 137.3 | U40: 261.9 | V40: 134.4 | W40: =X40-V40 -> 153.1 | X40: 287.5 | Y40: 153.2 | Z40: =AA40-Y40 -> 158.5 | AA40: 311.7 | AB40: 158.7 | AC40: =AD40-AB40 -> 167.2 | AD40: 325.9 | AE40: 112.9 | AF40: =AG40-AE40 -> 150.3 | AG40: 263.2 | AH40: 184.1 | AI40: =AJ40-AH40 -> 200.9 | AJ40: 385 | AK40: 230 | AL40: =AM40-AK40 -> 218 | AM40: 448 | AN40: 249 | AO40: =AP40-AN40 -> 243 | AP40: 492 | AQ40: 259 | AR40: =AS40-AQ40 -> 276 | AS40: 535 | AT40: 248 | AU40: =AV40-AT40 -> 241 | AV40: 489 | AW40: 233 | AX40: =AU40*(1+AX42+AX64) -> 228.95 | AY40: =AW40+AX40 -> 461.95 | AZ40: =AY40*(1+AZ42+AZ64) -> 471.189 | BA40: =AZ40*(1+BA42+BA64) -> 485.32467 | BB40: =BA40*(1+BB42+BB64) -> 499.88441 | BC40: =BB40*(1+BC42+BC64) -> 514.88094 | BD40: H2/26E: H2/25 × (1 + scenario constant-currency growth + H2/26E currency effect). 2027E+: prior year × (1 + scenario cc growth + currency effect). | BF40: =IFERROR((BC40/AV40)^(1/5)-1,"n/m") -> 0.01036802 | BG40: =IFERROR((AV40/AG40)^(1/5)-1,"n/m") -> 0.13189097 | BH40: =IFERROR((AV40/R40)^(1/10)-1,"n/m") -> 0.073141918 | BI40: =IFERROR((AV40/C40)^(1/19)-1,"n/m") -> n/m | BL40: 2029E | BM40: =BN40+$BM$36 -> 0.095 | BN40: 0.075 | BO40: =BN40+$BO$36 -> 0.045
B41: Revenue y/y % (reported) | D41: =IF(AND(ISNUMBER(D40),ISNUMBER(C40)),IFERROR(D40/C40-1,""),"") | E41: =IF(AND(ISNUMBER(E40),ISNUMBER(D40)),IFERROR(E40/D40-1,""),"") | F41: =IF(AND(ISNUMBER(F40),ISNUMBER(E40)),IFERROR(F40/E40-1,""),"") | G41: =IF(AND(ISNUMBER(G40),ISNUMBER(F40)),IFERROR(G40/F40-1,""),"") -> 0.17948718 | H41: =IF(AND(ISNUMBER(H40),ISNUMBER(G40)),IFERROR(H40/G40-1,""),"") -> 0.15217391 | I41: =IF(AND(ISNUMBER(I40),ISNUMBER(H40)),IFERROR(I40/H40-1,""),"") -> 0.15786164 | L41: =IF(AND(ISNUMBER(L40),ISNUMBER(I40)),IFERROR(L40/I40-1,""),"") -> 0.13905486 | M41: =IF(AND(ISNUMBER(M40),ISNUMBER(J40)),IFERROR(M40/J40-1,""),"") -> 0.074039363 | N41: =IF(AND(ISNUMBER(N40),ISNUMBER(K40)),IFERROR(N40/K40-1,""),"") -> 0.12815534 | O41: =IF(AND(ISNUMBER(O40),ISNUMBER(L40)),IFERROR(O40/L40-1,""),"") -> 0.10061993 | P41: =IF(AND(ISNUMBER(P40),ISNUMBER(M40)),IFERROR(P40/M40-1,""),"") -> 0.04973822 | Q41: =IF(AND(ISNUMBER(Q40),ISNUMBER(N40)),IFERROR(Q40/N40-1,""),"") -> 0.042168675 | R41: =IF(AND(ISNUMBER(R40),ISNUMBER(O40)),IFERROR(R40/O40-1,""),"") -> 0.04592721 | S41: =IF(AND(ISNUMBER(S40),ISNUMBER(P40)),IFERROR(S40/P40-1,""),"") -> 0.035743973 | ... AY41: =IF(AND(ISNUMBER(AY40),ISNUMBER(AV40)),IFERROR(AY40/AV40-1,""),"") -> -0.055316973 | AZ41: =IF(AND(ISNUMBER(AZ40),ISNUMBER(AY40)),IFERROR(AZ40/AY40-1,""),"") -> 0.02 | BA41: =IF(AND(ISNUMBER(BA40),ISNUMBER(AZ40)),IFERROR(BA40/AZ40-1,""),"") -> 0.03 | BB41: =IF(AND(ISNUMBER(BB40),ISNUMBER(BA40)),IFERROR(BB40/BA40-1,""),"") -> 0.03 | BC41: =IF(AND(ISNUMBER(BC40),ISNUMBER(BB40)),IFERROR(BC40/BB40-1,""),"") -> 0.03 | BL41: 2030E | BM41: =BN41+$BM$36 -> 0.09 | BN41: 0.07 | BO41: =BN41+$BO$36 -> 0.04
B42: Revenue y/y % at constant exchange rates (company) | G42: 0.163 | H42: 0.157 | I42: 0.144 | J42: 0.199 | L42: 0.148 | M42: 0.08 | O42: 0.104 | P42: 0.036 | R42: 0.033 | S42: 0.037 | U42: 0.085 | V42: 0.077 | X42: 0.101 | Y42: 0.149 | AA42: 0.089 | AB42: 0.032 | AD42: 0.041 | AE42: -0.291 | AG42: -0.19 | AH42: 0.645 | AJ42: 0.465 | AK42: 0.233 | AM42: 0.15 | AN42: 0.095 | AP42: 0.117 | AQ42: 0.049 | AS42: 0.093 | AT42: -0.038 | AV42: -0.076 | AW42: -0.045 | AX42: =CHOOSE(MATCH($BD$2,{"Bull","Base","Bear"},0),$BM$43,$BN$43,$BO$43) -> -0.02 | AY42: =(AT40*(1+AW42)+AU40*(1+AX42))/AV40-1 -> -0.032678937 | AZ42: =CHOOSE(MATCH($BD$2,{"Bull","Base","Bear"},0),$BM$44,$BN$44,$BO$44) -> 0.02 | BA42: =CHOOSE(MATCH($BD$2,{"Bull","Base","Bear"},0),$BM$45,$BN$45,$BO$45) -> 0.03 | BB42: =CHOOSE(MATCH($BD$2,{"Bull","Base","Bear"},0),$BM$46,$BN$46,$BO$46) -> 0.03 | BC42: =CHOOSE(MATCH($BD$2,{"Bull","Base","Bear"},0),$BM$47,$BN$47,$BO$47) -> 0.03 | BD42: Scenario lever (PERFUME_ccGrowth, Bull/Base/Bear table →). 2026E = H1/26 actual and H2/26E growth weighted by 2025 halves. Company figures to one decimal (press releases). | BF42: =IFERROR(AVERAGE(AY42,AZ42,BA42,BB42,BC42),"n/m") -> 0.015464213 | BG42: =IFERROR(AVERAGE(AJ42,AM42,AP42,AS42,AV42),"n/m") -> 0.1498 | BH42: =IFERROR(AVERAGE(U42,X42,AA42,AD42,AG42,AJ42,AM42,AP42,AS42,AV42),"n/m") -> 0.0875 | BI42: =IFERROR(AVERAGE(C42,D42,E42,F42,G42,H42,I42,L42,O42,R42,U42,X42,AA42,AD42,AG42,AJ42,AM42,AP42,AS42,AV42),"n/m") -> 0.1015 | BL42: PERFUME_ccGrowth (Perfume and Beauty revenue y/y, constant FX) | BM42: 0.02 | BN42: Δ → | BO42: -0.03 | BP42: H1/26 −4.5%; FY25 −7.6%, FY24 +9.3%.
B43: Currency (and scope) effect on growth, pts (reported − constant FX) | C43: =IF(AND(ISNUMBER(C41),ISNUMBER(C42)),C41-C42,"") | D43: =IF(AND(ISNUMBER(D41),ISNUMBER(D42)),D41-D42,"") | E43: =IF(AND(ISNUMBER(E41),ISNUMBER(E42)),E41-E42,"") | F43: =IF(AND(ISNUMBER(F41),ISNUMBER(F42)),F41-F42,"") | G43: =IF(AND(ISNUMBER(G41),ISNUMBER(G42)),G41-G42,"") -> 0.016487179 | H43: =IF(AND(ISNUMBER(H41),ISNUMBER(H42)),H41-H42,"") -> -0.004826087 | I43: =IF(AND(ISNUMBER(I41),ISNUMBER(I42)),I41-I42,"") -> 0.013861635 | J43: =IF(AND(ISNUMBER(J41),ISNUMBER(J42)),J41-J42,"") | ... AW43: =IF(AND(ISNUMBER(AW41),ISNUMBER(AW42)),AW41-AW42,"") -> -0.015483871 | AX43: =AX64 -> -0.03 | AY43: =AY41-AY42 -> -0.022638037 | AZ43: =AZ64 -> 0 | BA43: =BA64 -> 0 | BB43: =BB64 -> 0 | BC43: =BC64 -> 0 | BL43: H2/26E | BM43: =BN43+$BM$42 -> 0 | BN43: -0.02 | BO43: =BN43+$BO$42 -> -0.05
B44: % of group revenue | C44: =IF(AND(ISNUMBER(C40),ISNUMBER(C61)),IFERROR(C40/C61,""),"") | D44: =IF(AND(ISNUMBER(D40),ISNUMBER(D61)),IFERROR(D40/D61,""),"") | E44: =IF(AND(ISNUMBER(E40),ISNUMBER(E61)),IFERROR(E40/E61,""),"") | F44: =IF(AND(ISNUMBER(F40),ISNUMBER(F61)),IFERROR(F40/F61,""),"") -> 0.061128527 | G44: =IF(AND(ISNUMBER(G40),ISNUMBER(G61)),IFERROR(G40/G61,""),"") -> 0.057452123 | H44: =IF(AND(ISNUMBER(H40),ISNUMBER(H61)),IFERROR(H40/H61,""),"") -> 0.055946517 | I44: =IF(AND(ISNUMBER(I40),ISNUMBER(I61)),IFERROR(I40/I61,""),"") -> 0.052838528 | J44: =IF(AND(ISNUMBER(J40),ISNUMBER(J61)),IFERROR(J40/J61,""),"") -> 0.060381416 | ... BC44: =IF(AND(ISNUMBER(BC40),ISNUMBER(BC61)),IFERROR(BC40/BC61,""),"") -> 0.023752645 | BF44: =IFERROR(AVERAGE(AY44,AZ44,BA44,BB44,BC44),"n/m") -> 0.025774445 | BG44: =IFERROR(AVERAGE(AJ44,AM44,AP44,AS44,AV44),"n/m") -> 0.036791158 | BH44: =IFERROR(AVERAGE(U44,X44,AA44,AD44,AG44,AJ44,AM44,AP44,AS44,AV44),"n/m") -> 0.042689363 | BI44: =IFERROR(AVERAGE(C44,D44,E44,F44,G44,H44,I44,L44,O44,R44,U44,X44,AA44,AD44,AG44,AJ44,AM44,AP44,AS44,AV44),"n/m") -> 0.04800056 | BL44: 2027E | BM44: =BN44+$BM$42 -> 0.04 | BN44: 0.02 | BO44: =BN44+$BO$42 -> -0.01
BL45: 2028E | BM45: =BN45+$BM$42 -> 0.05 | BN45: 0.03 | BO45: =BN45+$BO$42 -> 0
B46: Watches (La Montre Hermès) | BD46: WATCHES — modelling logic | BL46: 2029E | BM46: =BN46+$BM$42 -> 0.05 | BN46: 0.03 | BO46: =BN46+$BO$42 -> 0
B47: Revenue | F47: 87 | G47: 113 | H47: 139 | I47: 172.7 | J47: 74.9 | K47: =L47-J47 -> 92.3 | L47: 167.2 | M47: 67.2 | N47: =O47-M47 -> 80.9 | O47: 148.1 | P47: 75 | Q47: =R47-P47 -> 88.2 | R47: 163.2 | S47: 74.6 | T47: =U47-S47 -> 83.3 | U47: 157.9 | V47: 75 | W47: =X47-V47 -> 82.5 | X47: 157.5 | Y47: 77 | Z47: =AA47-Y47 -> 91.6 | AA47: 168.6 | AB47: 90.5 | AC47: =AD47-AB47 -> 102.9 | AD47: 193.4 | AE47: 74.2 | AF47: =AG47-AE47 -> 121.7 | AG47: 195.9 | AH47: 158.8 | AI47: =AJ47-AH47 -> 178.2 | AJ47: 337 | AK47: 262 | AL47: =AM47-AK47 -> 257 | AM47: 519 | AN47: 317 | AO47: =AP47-AN47 -> 294 | AP47: 611 | AQ47: 308 | AR47: =AS47-AQ47 -> 269 | AS47: 577 | AT47: 281 | AU47: =AV47-AT47 -> 268 | AV47: 549 | AW47: 269 | AX47: =AU47*(1+AX49+AX64) -> 268 | AY47: =AW47+AX47 -> 537 | AZ47: =AY47*(1+AZ49+AZ64) -> 563.85 | BA47: =AZ47*(1+BA49+BA64) -> 592.0425 | BB47: =BA47*(1+BB49+BB64) -> 621.64463 | BC47: =BB47*(1+BC49+BC64) -> 652.72686 | BD47: H2/26E: H2/25 × (1 + scenario constant-currency growth + H2/26E currency effect). 2027E+: prior year × (1 + scenario cc growth + currency effect). | BF47: =IFERROR((BC47/AV47)^(1/5)-1,"n/m") -> 0.03521803 | BG47: =IFERROR((AV47/AG47)^(1/5)-1,"n/m") -> 0.22887464 | BH47: =IFERROR((AV47/R47)^(1/10)-1,"n/m") -> 0.12897732 | BI47: =IFERROR((AV47/C47)^(1/19)-1,"n/m") -> n/m | BL47: 2030E | BM47: =BN47+$BM$42 -> 0.05 | BN47: 0.03 | BO47: =BN47+$BO$42 -> 0
B48: Revenue y/y % (reported) | D48: =IF(AND(ISNUMBER(D47),ISNUMBER(C47)),IFERROR(D47/C47-1,""),"") | E48: =IF(AND(ISNUMBER(E47),ISNUMBER(D47)),IFERROR(E47/D47-1,""),"") | F48: =IF(AND(ISNUMBER(F47),ISNUMBER(E47)),IFERROR(F47/E47-1,""),"") | G48: =IF(AND(ISNUMBER(G47),ISNUMBER(F47)),IFERROR(G47/F47-1,""),"") -> 0.29885057 | H48: =IF(AND(ISNUMBER(H47),ISNUMBER(G47)),IFERROR(H47/G47-1,""),"") -> 0.2300885 | I48: =IF(AND(ISNUMBER(I47),ISNUMBER(H47)),IFERROR(I47/H47-1,""),"") -> 0.24244604 | L48: =IF(AND(ISNUMBER(L47),ISNUMBER(I47)),IFERROR(L47/I47-1,""),"") -> -0.031847134 | M48: =IF(AND(ISNUMBER(M47),ISNUMBER(J47)),IFERROR(M47/J47-1,""),"") -> -0.10280374 | N48: =IF(AND(ISNUMBER(N47),ISNUMBER(K47)),IFERROR(N47/K47-1,""),"") -> -0.12351029 | O48: =IF(AND(ISNUMBER(O47),ISNUMBER(L47)),IFERROR(O47/L47-1,""),"") -> -0.11423445 | P48: =IF(AND(ISNUMBER(P47),ISNUMBER(M47)),IFERROR(P47/M47-1,""),"") -> 0.11607143 | Q48: =IF(AND(ISNUMBER(Q47),ISNUMBER(N47)),IFERROR(Q47/N47-1,""),"") -> 0.090234858 | R48: =IF(AND(ISNUMBER(R47),ISNUMBER(O47)),IFERROR(R47/O47-1,""),"") -> 0.10195814 | S48: =IF(AND(ISNUMBER(S47),ISNUMBER(P47)),IFERROR(S47/P47-1,""),"") -> -0.0053333333 | ... AY48: =IF(AND(ISNUMBER(AY47),ISNUMBER(AV47)),IFERROR(AY47/AV47-1,""),"") -> -0.021857923 | AZ48: =IF(AND(ISNUMBER(AZ47),ISNUMBER(AY47)),IFERROR(AZ47/AY47-1,""),"") -> 0.05 | BA48: =IF(AND(ISNUMBER(BA47),ISNUMBER(AZ47)),IFERROR(BA47/AZ47-1,""),"") -> 0.05 | BB48: =IF(AND(ISNUMBER(BB47),ISNUMBER(BA47)),IFERROR(BB47/BA47-1,""),"") -> 0.05 | BC48: =IF(AND(ISNUMBER(BC47),ISNUMBER(BB47)),IFERROR(BC47/BB47-1,""),"") -> 0.05 | BL48: WATCHES_ccGrowth (Watches revenue y/y, constant FX) | BM48: 0.02 | BN48: Δ → | BO48: -0.03 | BP48: H1/26 +0.2% with a solid Q2; FY25 −1.5%, FY24 −4.2%.
B49: Revenue y/y % at constant exchange rates (company) | G49: 0.229 | H49: 0.229 | I49: 0.174 | J49: -0.01 | L49: 0.01 | M49: -0.067 | O49: -0.106 | P49: -0.009 | R49: 0.001 | S49: 0.007 | U49: -0.032 | V49: -0.012 | X49: 0.014 | Y49: 0.09 | AA49: 0.099 | AB49: 0.142 | AD49: 0.116 | AE49: -0.185 | AG49: 0.023 | AH49: 1.206 | AJ49: 0.725 | AK49: 0.553 | AM49: 0.459 | AN49: 0.243 | AP49: 0.232 | AQ49: -0.002 | AS49: -0.042 | AT49: -0.079 | AV49: -0.015 | AW49: 0.002 | AX49: =CHOOSE(MATCH($BD$2,{"Bull","Base","Bear"},0),$BM$49,$BN$49,$BO$49) -> 0.03 | AY49: =(AT47*(1+AW49)+AU47*(1+AX49))/AV47-1 -> 0.015668488 | AZ49: =CHOOSE(MATCH($BD$2,{"Bull","Base","Bear"},0),$BM$50,$BN$50,$BO$50) -> 0.05 | BA49: =CHOOSE(MATCH($BD$2,{"Bull","Base","Bear"},0),$BM$51,$BN$51,$BO$51) -> 0.05 | BB49: =CHOOSE(MATCH($BD$2,{"Bull","Base","Bear"},0),$BM$52,$BN$52,$BO$52) -> 0.05 | BC49: =CHOOSE(MATCH($BD$2,{"Bull","Base","Bear"},0),$BM$53,$BN$53,$BO$53) -> 0.05 | BD49: Scenario lever (WATCHES_ccGrowth, Bull/Base/Bear table →). 2026E = H1/26 actual and H2/26E growth weighted by 2025 halves. Company figures to one decimal (press releases). | BF49: =IFERROR(AVERAGE(AY49,AZ49,BA49,BB49,BC49),"n/m") -> 0.043133698 | BG49: =IFERROR(AVERAGE(AJ49,AM49,AP49,AS49,AV49),"n/m") -> 0.2718 | BH49: =IFERROR(AVERAGE(U49,X49,AA49,AD49,AG49,AJ49,AM49,AP49,AS49,AV49),"n/m") -> 0.1579 | BI49: =IFERROR(AVERAGE(C49,D49,E49,F49,G49,H49,I49,L49,O49,R49,U49,X49,AA49,AD49,AG49,AJ49,AM49,AP49,AS49,AV49),"n/m") -> 0.13225 | BL49: H2/26E | BM49: =BN49+$BM$48 -> 0.05 | BN49: 0.03 | BO49: =BN49+$BO$48 -> 0
B50: Currency (and scope) effect on growth, pts (reported − constant FX) | C50: =IF(AND(ISNUMBER(C48),ISNUMBER(C49)),C48-C49,"") | D50: =IF(AND(ISNUMBER(D48),ISNUMBER(D49)),D48-D49,"") | E50: =IF(AND(ISNUMBER(E48),ISNUMBER(E49)),E48-E49,"") | F50: =IF(AND(ISNUMBER(F48),ISNUMBER(F49)),F48-F49,"") | G50: =IF(AND(ISNUMBER(G48),ISNUMBER(G49)),G48-G49,"") -> 0.069850575 | H50: =IF(AND(ISNUMBER(H48),ISNUMBER(H49)),H48-H49,"") -> 0.0010884956 | I50: =IF(AND(ISNUMBER(I48),ISNUMBER(I49)),I48-I49,"") -> 0.068446043 | J50: =IF(AND(ISNUMBER(J48),ISNUMBER(J49)),J48-J49,"") | ... AW50: =IF(AND(ISNUMBER(AW48),ISNUMBER(AW49)),AW48-AW49,"") -> -0.044704626 | AX50: =AX64 -> -0.03 | AY50: =AY48-AY49 -> -0.037526412 | AZ50: =AZ64 -> 0 | BA50: =BA64 -> 0 | BB50: =BB64 -> 0 | BC50: =BC64 -> 0 | BL50: 2027E | BM50: =BN50+$BM$48 -> 0.07 | BN50: 0.05 | BO50: =BN50+$BO$48 -> 0.02
B51: % of group revenue | C51: =IF(AND(ISNUMBER(C47),ISNUMBER(C61)),IFERROR(C47/C61,""),"") | D51: =IF(AND(ISNUMBER(D47),ISNUMBER(D61)),IFERROR(D47/D61,""),"") | E51: =IF(AND(ISNUMBER(E47),ISNUMBER(E61)),IFERROR(E47/E61,""),"") | F51: =IF(AND(ISNUMBER(F47),ISNUMBER(F61)),IFERROR(F47/F61,""),"") -> 0.045454545 | G51: =IF(AND(ISNUMBER(G47),ISNUMBER(G61)),IFERROR(G47/G61,""),"") -> 0.04704413 | H51: =IF(AND(ISNUMBER(H47),ISNUMBER(H61)),IFERROR(H47/H61,""),"") -> 0.048909219 | I51: =IF(AND(ISNUMBER(I47),ISNUMBER(I61)),IFERROR(I47/I61,""),"") -> 0.049566615 | J51: =IF(AND(ISNUMBER(J47),ISNUMBER(J61)),IFERROR(J47/J61,""),"") -> 0.04238583 | ... BC51: =IF(AND(ISNUMBER(BC47),ISNUMBER(BC61)),IFERROR(BC47/BC61,""),"") -> 0.030111795 | BF51: =IFERROR(AVERAGE(AY51,AZ51,BA51,BB51,BC51),"n/m") -> 0.031338227 | BG51: =IFERROR(AVERAGE(AJ51,AM51,AP51,AS51,AV51),"n/m") -> 0.040022492 | BH51: =IFERROR(AVERAGE(U51,X51,AA51,AD51,AG51,AJ51,AM51,AP51,AS51,AV51),"n/m") -> 0.034586391 | BI51: =IFERROR(AVERAGE(C51,D51,E51,F51,G51,H51,I51,L51,O51,R51,U51,X51,AA51,AD51,AG51,AJ51,AM51,AP51,AS51,AV51),"n/m") -> 0.038296298 | BL51: 2028E | BM51: =BN51+$BM$48 -> 0.07 | BN51: 0.05 | BO51: =BN51+$BO$48 -> 0.02
BL52: 2029E | BM52: =BN52+$BM$48 -> 0.07 | BN52: 0.05 | BO52: =BN52+$BO$48 -> 0.02
B53: Other products (John Lobb, Saint-Louis, Puiforcat, textile production for third parties) | BD53: OTHER PRODUCTS — modelling logic | BL53: 2030E | BM53: =BN53+$BM$48 -> 0.07 | BN53: 0.05 | BO53: =BN53+$BO$48 -> 0.02
B54: Revenue | F54: 71 | G54: 86 | H54: 113 | I54: 134.9 | J54: 84.7 | K54: =L54-J54 -> 84.9 | L54: 169.6 | M54: 103.3 | N54: =O54-M54 -> 97.5 | O54: 200.8 | P54: 97.1 | Q54: =R54-P54 -> 111.4 | R54: 208.5 | S54: 111.8 | T54: =U54-S54 -> 116.5 | U54: 228.3 | V54: 101.9 | W54: =X54-V54 -> 121.5 | X54: 223.4 | Y54: 109.8 | Z54: =AA54-Y54 -> 128.2 | AA54: 238 | AB54: 113.9 | AC54: =AD54-AB54 -> 144.3 | AD54: 258.2 | AE54: 79.3 | AF54: =AG54-AE54 -> 138.4 | AG54: 217.7 | AH54: 131.6 | AI54: =AJ54-AH54 -> 147.4 | AJ54: 279 | AK54: 146 | AL54: =AM54-AK54 -> 160 | AM54: 306 | AN54: 150 | AO54: =AP54-AN54 -> 163 | AP54: 313 | AQ54: 157 | AR54: =AS54-AQ54 -> 180 | AS54: 337 | AT54: 168 | AU54: =AV54-AT54 -> 181 | AV54: 349 | AW54: 168 | AX54: =AU54*(1+AX56+AX64) -> 181 | AY54: =AW54+AX54 -> 349 | AZ54: =AY54*(1+AZ56+AZ64) -> 362.96 | BA54: =AZ54*(1+BA56+BA64) -> 377.4784 | BB54: =BA54*(1+BB56+BB64) -> 392.57754 | BC54: =BB54*(1+BC56+BC64) -> 408.28064 | BD54: H2/26E: H2/25 × (1 + scenario constant-currency growth + H2/26E currency effect). 2027E+: prior year × (1 + scenario cc growth + currency effect). | BF54: =IFERROR((BC54/AV54)^(1/5)-1,"n/m") -> 0.031874004 | BG54: =IFERROR((AV54/AG54)^(1/5)-1,"n/m") -> 0.098989137 | BH54: =IFERROR((AV54/R54)^(1/10)-1,"n/m") -> 0.052863177 | BI54: =IFERROR((AV54/C54)^(1/19)-1,"n/m") -> n/m | BL54: OTHER_PRODUCTS_ccGrowth (Other products revenue y/y, constant FX) | BM54: 0.02 | BN54: Δ → | BO54: -0.03 | BP54: John Lobb, Saint-Louis, Puiforcat, textiles (Holding Textile Hermès): H1/26 +2.8%; FY25 +5.5%.
B55: Revenue y/y % (reported) | D55: =IF(AND(ISNUMBER(D54),ISNUMBER(C54)),IFERROR(D54/C54-1,""),"") | E55: =IF(AND(ISNUMBER(E54),ISNUMBER(D54)),IFERROR(E54/D54-1,""),"") | F55: =IF(AND(ISNUMBER(F54),ISNUMBER(E54)),IFERROR(F54/E54-1,""),"") | G55: =IF(AND(ISNUMBER(G54),ISNUMBER(F54)),IFERROR(G54/F54-1,""),"") -> 0.21126761 | H55: =IF(AND(ISNUMBER(H54),ISNUMBER(G54)),IFERROR(H54/G54-1,""),"") -> 0.31395349 | I55: =IF(AND(ISNUMBER(I54),ISNUMBER(H54)),IFERROR(I54/H54-1,""),"") -> 0.19380531 | L55: =IF(AND(ISNUMBER(L54),ISNUMBER(I54)),IFERROR(L54/I54-1,""),"") -> 0.25722758 | M55: =IF(AND(ISNUMBER(M54),ISNUMBER(J54)),IFERROR(M54/J54-1,""),"") -> 0.21959858 | N55: =IF(AND(ISNUMBER(N54),ISNUMBER(K54)),IFERROR(N54/K54-1,""),"") -> 0.14840989 | O55: =IF(AND(ISNUMBER(O54),ISNUMBER(L54)),IFERROR(O54/L54-1,""),"") -> 0.18396226 | P55: =IF(AND(ISNUMBER(P54),ISNUMBER(M54)),IFERROR(P54/M54-1,""),"") -> -0.060019361 | Q55: =IF(AND(ISNUMBER(Q54),ISNUMBER(N54)),IFERROR(Q54/N54-1,""),"") -> 0.1425641 | R55: =IF(AND(ISNUMBER(R54),ISNUMBER(O54)),IFERROR(R54/O54-1,""),"") -> 0.038346614 | S55: =IF(AND(ISNUMBER(S54),ISNUMBER(P54)),IFERROR(S54/P54-1,""),"") -> 0.15139032 | ... AY55: =IF(AND(ISNUMBER(AY54),ISNUMBER(AV54)),IFERROR(AY54/AV54-1,""),"") -> 0 | AZ55: =IF(AND(ISNUMBER(AZ54),ISNUMBER(AY54)),IFERROR(AZ54/AY54-1,""),"") -> 0.04 | BA55: =IF(AND(ISNUMBER(BA54),ISNUMBER(AZ54)),IFERROR(BA54/AZ54-1,""),"") -> 0.04 | BB55: =IF(AND(ISNUMBER(BB54),ISNUMBER(BA54)),IFERROR(BB54/BA54-1,""),"") -> 0.04 | BC55: =IF(AND(ISNUMBER(BC54),ISNUMBER(BB54)),IFERROR(BC54/BB54-1,""),"") -> 0.04 | BL55: H2/26E | BM55: =BN55+$BM$54 -> 0.05 | BN55: 0.03 | BO55: =BN55+$BO$54 -> 0
B56: Revenue y/y % at constant exchange rates (company) | G56: 0.188 | H56: 0.306 | I56: 0.167 | J56: 0.242 | L56: 0.29 | M56: 0.058 | O56: 0.007 | P56: -0.097 | R56: -0.002 | S56: 0.158 | U56: 0.101 | V56: -0.087 | X56: -0.009 | Y56: 0.103 | AA56: 0.079 | AB56: 0.024 | AD56: 0.07 | AE56: -0.308 | AG56: -0.153 | AH56: 0.692 | AJ56: 0.291 | AK56: 0.091 | AM56: 0.076 | AN56: 0.041 | AP56: 0.052 | AQ56: 0.066 | AS56: 0.087 | AT56: 0.075 | AV56: 0.055 | AW56: 0.028 | AX56: =CHOOSE(MATCH($BD$2,{"Bull","Base","Bear"},0),$BM$55,$BN$55,$BO$55) -> 0.03 | AY56: =(AT54*(1+AW56)+AU54*(1+AX56))/AV54-1 -> 0.029037249 | AZ56: =CHOOSE(MATCH($BD$2,{"Bull","Base","Bear"},0),$BM$56,$BN$56,$BO$56) -> 0.04 | BA56: =CHOOSE(MATCH($BD$2,{"Bull","Base","Bear"},0),$BM$57,$BN$57,$BO$57) -> 0.04 | BB56: =CHOOSE(MATCH($BD$2,{"Bull","Base","Bear"},0),$BM$58,$BN$58,$BO$58) -> 0.04 | BC56: =CHOOSE(MATCH($BD$2,{"Bull","Base","Bear"},0),$BM$59,$BN$59,$BO$59) -> 0.04 | BD56: Scenario lever (OTHER_PRODUCTS_ccGrowth, Bull/Base/Bear table →). 2026E = H1/26 actual and H2/26E growth weighted by 2025 halves. Company figures to one decimal (press releases). | BF56: =IFERROR(AVERAGE(AY56,AZ56,BA56,BB56,BC56),"n/m") -> 0.03780745 | BG56: =IFERROR(AVERAGE(AJ56,AM56,AP56,AS56,AV56),"n/m") -> 0.1122 | BH56: =IFERROR(AVERAGE(U56,X56,AA56,AD56,AG56,AJ56,AM56,AP56,AS56,AV56),"n/m") -> 0.0649 | BI56: =IFERROR(AVERAGE(C56,D56,E56,F56,G56,H56,I56,L56,O56,R56,U56,X56,AA56,AD56,AG56,AJ56,AM56,AP56,AS56,AV56),"n/m") -> 0.1003125 | BL56: 2027E | BM56: =BN56+$BM$54 -> 0.06 | BN56: 0.04 | BO56: =BN56+$BO$54 -> 0.01
B57: Currency (and scope) effect on growth, pts (reported − constant FX) | C57: =IF(AND(ISNUMBER(C55),ISNUMBER(C56)),C55-C56,"") | D57: =IF(AND(ISNUMBER(D55),ISNUMBER(D56)),D55-D56,"") | E57: =IF(AND(ISNUMBER(E55),ISNUMBER(E56)),E55-E56,"") | F57: =IF(AND(ISNUMBER(F55),ISNUMBER(F56)),F55-F56,"") | G57: =IF(AND(ISNUMBER(G55),ISNUMBER(G56)),G55-G56,"") -> 0.023267606 | H57: =IF(AND(ISNUMBER(H55),ISNUMBER(H56)),H55-H56,"") -> 0.0079534884 | I57: =IF(AND(ISNUMBER(I55),ISNUMBER(I56)),I55-I56,"") -> 0.02680531 | J57: =IF(AND(ISNUMBER(J55),ISNUMBER(J56)),J55-J56,"") | ... AW57: =IF(AND(ISNUMBER(AW55),ISNUMBER(AW56)),AW55-AW56,"") -> -0.028 | AX57: =AX64 -> -0.03 | AY57: =AY55-AY56 -> -0.029037249 | AZ57: =AZ64 -> 0 | BA57: =BA64 -> 0 | BB57: =BB64 -> 0 | BC57: =BC64 -> 0 | BL57: 2028E | BM57: =BN57+$BM$54 -> 0.06 | BN57: 0.04 | BO57: =BN57+$BO$54 -> 0.01
B58: % of group revenue | C58: =IF(AND(ISNUMBER(C54),ISNUMBER(C61)),IFERROR(C54/C61,""),"") | D58: =IF(AND(ISNUMBER(D54),ISNUMBER(D61)),IFERROR(D54/D61,""),"") | E58: =IF(AND(ISNUMBER(E54),ISNUMBER(E61)),IFERROR(E54/E61,""),"") | F58: =IF(AND(ISNUMBER(F54),ISNUMBER(F61)),IFERROR(F54/F61,""),"") -> 0.037095089 | G58: =IF(AND(ISNUMBER(G54),ISNUMBER(G61)),IFERROR(G54/G61,""),"") -> 0.035803497 | H58: =IF(AND(ISNUMBER(H54),ISNUMBER(H61)),IFERROR(H54/H61,""),"") -> 0.039760732 | I58: =IF(AND(ISNUMBER(I54),ISNUMBER(I61)),IFERROR(I54/I61,""),"") -> 0.03871764 | J58: =IF(AND(ISNUMBER(J54),ISNUMBER(J61)),IFERROR(J54/J61,""),"") -> 0.047931639 | ... BC58: =IF(AND(ISNUMBER(BC54),ISNUMBER(BC61)),IFERROR(BC54/BC61,""),"") -> 0.018834927 | BF58: =IFERROR(AVERAGE(AY58,AZ58,BA58,BB58,BC58),"n/m") -> 0.019990739 | BG58: =IFERROR(AVERAGE(AJ58,AM58,AP58,AS58,AV58),"n/m") -> 0.024955979 | BH58: =IFERROR(AVERAGE(U58,X58,AA58,AD58,AG58,AJ58,AM58,AP58,AS58,AV58),"n/m") -> 0.032039807 | BI58: =IFERROR(AVERAGE(C58,D58,E58,F58,G58,H58,I58,L58,O58,R58,U58,X58,AA58,AD58,AG58,AJ58,AM58,AP58,AS58,AV58),"n/m") -> 0.035809754 | BL58: 2029E | BM58: =BN58+$BM$54 -> 0.06 | BN58: 0.04 | BO58: =BN58+$BO$54 -> 0.01
BL59: 2030E | BM59: =BN59+$BM$54 -> 0.06 | BN59: 0.04 | BO59: =BN59+$BO$54 -> 0.01
B60: Group revenue (métier build) — constant-currency growth and currency effect | BD60: GROUP REVENUE — modelling logic | BL60: GM (gross margin %) | BM60: 0.005 | BN60: Δ → | BO60: -0.01 | BP60: Gross margin: 71.1% FY25 (H2/25 71.5%), 71.1% H1/26 (FX headwind offset by price increases).
B61: Revenue (métier build) | C61: =IF(ISNUMBER(C11),N(C11)+N(C18)+N(C25)+N(C32)+N(C40)+N(C47)+N(C54),"") | D61: =IF(ISNUMBER(D11),N(D11)+N(D18)+N(D25)+N(D32)+N(D40)+N(D47)+N(D54),"") | E61: =IF(ISNUMBER(E11),N(E11)+N(E18)+N(E25)+N(E32)+N(E40)+N(E47)+N(E54),"") | F61: =IF(ISNUMBER(F11),N(F11)+N(F18)+N(F25)+N(F32)+N(F40)+N(F47)+N(F54),"") -> 1914 | G61: =IF(ISNUMBER(G11),N(G11)+N(G18)+N(G25)+N(G32)+N(G40)+N(G47)+N(G54),"") -> 2402 | H61: =IF(ISNUMBER(H11),N(H11)+N(H18)+N(H25)+N(H32)+N(H40)+N(H47)+N(H54),"") -> 2842 | I61: =IF(ISNUMBER(I11),N(I11)+N(I18)+N(I25)+N(I32)+N(I40)+N(I47)+N(I54),"") -> 3484.2 | J61: =IF(ISNUMBER(J11),N(J11)+N(J18)+N(J25)+N(J32)+N(J40)+N(J47)+N(J54),"") -> 1767.1 | ... AW61: =IF(ISNUMBER(AW11),N(AW11)+N(AW18)+N(AW25)+N(AW32)+N(AW40)+N(AW47)+N(AW54),"") -> 8163 | AX61: =AX11+AX18+AX25+AX32+AX40+AX47+AX54 -> 8243.99 | AY61: =AY11+AY18+AY25+AY32+AY40+AY47+AY54 -> 16406.99 | AZ61: =AZ11+AZ18+AZ25+AZ32+AZ40+AZ47+AZ54 -> 17626.336 | BA61: =BA11+BA18+BA25+BA32+BA40+BA47+BA54 -> 18946.137 | BB61: =BB11+BB18+BB25+BB32+BB40+BB47+BB54 -> 20307.483 | BC61: =BC11+BC18+BC25+BC32+BC40+BC47+BC54 -> 21676.783 | BD61: Σ métier revenues. | BF61: =IFERROR((BC61/AV61)^(1/5)-1,"n/m") -> 0.062599341 | BG61: =IFERROR((AV61/AG61)^(1/5)-1,"n/m") -> 0.20153396 | BH61: =IFERROR((AV61/R61)^(1/10)-1,"n/m") -> 0.12699063 | BI61: =IFERROR((AV61/C61)^(1/19)-1,"n/m") -> n/m | BL61: H2/26E | BM61: =BN61+$BM$60 -> 0.718 | BN61: 0.713 | BO61: =BN61+$BO$60 -> 0.703
B62: Revenue y/y % (reported) | D62: =IF(AND(ISNUMBER(D61),ISNUMBER(C61)),IFERROR(D61/C61-1,""),"") | E62: =IF(AND(ISNUMBER(E61),ISNUMBER(D61)),IFERROR(E61/D61-1,""),"") | F62: =IF(AND(ISNUMBER(F61),ISNUMBER(E61)),IFERROR(F61/E61-1,""),"") | G62: =IF(AND(ISNUMBER(G61),ISNUMBER(F61)),IFERROR(G61/F61-1,""),"") -> 0.25496343 | H62: =IF(AND(ISNUMBER(H61),ISNUMBER(G61)),IFERROR(H61/G61-1,""),"") -> 0.18318068 | I62: =IF(AND(ISNUMBER(I61),ISNUMBER(H61)),IFERROR(I61/H61-1,""),"") -> 0.22596763 | L62: =IF(AND(ISNUMBER(L61),ISNUMBER(I61)),IFERROR(L61/I61-1,""),"") -> 0.077693588 | M62: =IF(AND(ISNUMBER(M61),ISNUMBER(J61)),IFERROR(M61/J61-1,""),"") -> 0.07911267 | N62: =IF(AND(ISNUMBER(N61),ISNUMBER(K61)),IFERROR(N61/K61-1,""),"") -> 0.11263709 | O62: =IF(AND(ISNUMBER(O61),ISNUMBER(L61)),IFERROR(O61/L61-1,""),"") -> 0.096860103 | P62: =IF(AND(ISNUMBER(P61),ISNUMBER(M61)),IFERROR(P61/M61-1,""),"") -> 0.20583145 | Q62: =IF(AND(ISNUMBER(Q61),ISNUMBER(N61)),IFERROR(Q61/N61-1,""),"") -> 0.14920649 | R62: =IF(AND(ISNUMBER(R61),ISNUMBER(O61)),IFERROR(R61/O61-1,""),"") -> 0.17542369 | S62: =IF(AND(ISNUMBER(S61),ISNUMBER(P61)),IFERROR(S61/P61-1,""),"") -> 0.061407324 | ... AY62: =IF(AND(ISNUMBER(AY61),ISNUMBER(AV61)),IFERROR(AY61/AV61-1,""),"") -> 0.025372789 | AZ62: =IF(AND(ISNUMBER(AZ61),ISNUMBER(AY61)),IFERROR(AZ61/AY61-1,""),"") -> 0.074318714 | BA62: =IF(AND(ISNUMBER(BA61),ISNUMBER(AZ61)),IFERROR(BA61/AZ61-1,""),"") -> 0.074876647 | BB62: =IF(AND(ISNUMBER(BB61),ISNUMBER(BA61)),IFERROR(BB61/BA61-1,""),"") -> 0.071853461 | BC62: =IF(AND(ISNUMBER(BC61),ISNUMBER(BB61)),IFERROR(BC61/BB61-1,""),"") -> 0.067428365 | BL62: 2027E | BM62: =BN62+$BM$60 -> 0.717 | BN62: 0.712 | BO62: =BN62+$BO$60 -> 0.702
B63: Revenue y/y % at constant exchange rates (company; forecast = Σ métiers) | G63: 0.189 | H63: 0.183 | I63: 0.164 | J63: 0.144 | L63: 0.13 | M63: 0.12 | O63: 0.111 | P63: 0.088 | R63: 0.081 | S63: 0.072 | U63: 0.074 | V63: 0.097 | X63: 0.086 | Y63: 0.112 | AA63: 0.104 | AB63: 0.12 | AD63: 0.124 | AE63: -0.249 | AG63: -0.06 | AH63: 0.767 | AJ63: 0.418 | AK63: 0.232 | AM63: 0.234 | AN63: 0.252 | AP63: 0.206 | AQ63: 0.151 | AS63: 0.147 | AT63: 0.081 | AV63: 0.089 | AW63: 0.061 | AX63: =(AU11*AX13+AU18*AX20+AU25*AX27+AU32*AX34+AU40*AX42+AU47*AX49+AU54*AX56)/(AU11+AU18+AU25+AU32+AU40+AU47+AU54) -> 0.064637299 | AY63: =(AV11*AY13+AV18*AY20+AV25*AY27+AV32*AY34+AV40*AY42+AV47*AY49+AV54*AY56)/(AV11+AV18+AV25+AV32+AV40+AV47+AV54) -> 0.062825011 | AZ63: =(AY11*AZ13+AY18*AZ20+AY25*AZ27+AY32*AZ34+AY40*AZ42+AY47*AZ49+AY54*AZ56)/(AY11+AY18+AY25+AY32+AY40+AY47+AY54) -> 0.074318714 | BA63: =(AZ11*BA13+AZ18*BA20+AZ25*BA27+AZ32*BA34+AZ40*BA42+AZ47*BA49+AZ54*BA56)/(AZ11+AZ18+AZ25+AZ32+AZ40+AZ47+AZ54) -> 0.074876647 | BB63: =(BA11*BB13+BA18*BB20+BA25*BB27+BA32*BB34+BA40*BB42+BA47*BB49+BA54*BB56)/(BA11+BA18+BA25+BA32+BA40+BA47+BA54) -> 0.071853461 | BC63: =(BB11*BC13+BB18*BC20+BB25*BC27+BB32*BC34+BB40*BC42+BB47*BC49+BB54*BC56)/(BB11+BB18+BB25+BB32+BB40+BB47+BB54) -> 0.067428365 | BD63: Hermès' headline growth measure. Forecast = prior-period-weighted average of métier cc growth. | BF63: =IFERROR(AVERAGE(AY63,AZ63,BA63,BB63,BC63),"n/m") -> 0.070260439 | BG63: =IFERROR(AVERAGE(AJ63,AM63,AP63,AS63,AV63),"n/m") -> 0.2188 | BH63: =IFERROR(AVERAGE(U63,X63,AA63,AD63,AG63,AJ63,AM63,AP63,AS63,AV63),"n/m") -> 0.1422 | BI63: =IFERROR(AVERAGE(C63,D63,E63,F63,G63,H63,I63,L63,O63,R63,U63,X63,AA63,AD63,AG63,AJ63,AM63,AP63,AS63,AV63),"n/m") -> 0.1425 | BL63: 2028E | BM63: =BN63+$BM$60 -> 0.718 | BN63: 0.713 | BO63: =BN63+$BO$60 -> 0.703
B64: Currency (and scope) effect, pts (reported − constant FX) | C64: =IF(AND(ISNUMBER(C62),ISNUMBER(C63)),C62-C63,"") | D64: =IF(AND(ISNUMBER(D62),ISNUMBER(D63)),D62-D63,"") | E64: =IF(AND(ISNUMBER(E62),ISNUMBER(E63)),E62-E63,"") | F64: =IF(AND(ISNUMBER(F62),ISNUMBER(F63)),F62-F63,"") | G64: =IF(AND(ISNUMBER(G62),ISNUMBER(G63)),G62-G63,"") -> 0.065963427 | H64: =IF(AND(ISNUMBER(H62),ISNUMBER(H63)),H62-H63,"") -> 0.00018068276 | I64: =IF(AND(ISNUMBER(I62),ISNUMBER(I63)),I62-I63,"") -> 0.061967628 | J64: =IF(AND(ISNUMBER(J62),ISNUMBER(J63)),J62-J63,"") | ... AW64: =IF(AND(ISNUMBER(AW62),ISNUMBER(AW63)),AW62-AW63,"") -> -0.044816756 | AX64: =CHOOSE(MATCH($BD$2,{"Bull","Base","Bear"},0),$BM$12,$BN$12,$BO$12) -> -0.03 | AY64: =AY62-AY63 -> -0.037452222 | AZ64: 0 | BA64: 0 | BB64: 0 | BC64: 0 | BD64: H2/26E: scenario point estimate (Bull / Base / Bear table →). 2027E+: no currency effect assumed (constant-currency growth = reported growth). H1/26: −4.5 pts (> €360m negative impact on revenue). | BL64: 2029E | BM64: =BN64+$BM$60 -> 0.719 | BN64: 0.714 | BO64: =BN64+$BO$60 -> 0.704
B65: Check: métier build vs consolidated revenue (should be 0; ±1 whole-€m rounding) | C65: =IF(AND(ISNUMBER(C61),ISNUMBER(C119)),ROUND(C61-C119,0),"") | D65: =IF(AND(ISNUMBER(D61),ISNUMBER(D119)),ROUND(D61-D119,0),"") | E65: =IF(AND(ISNUMBER(E61),ISNUMBER(E119)),ROUND(E61-E119,0),"") | F65: =IF(AND(ISNUMBER(F61),ISNUMBER(F119)),ROUND(F61-F119,0),"") -> 0 | G65: =IF(AND(ISNUMBER(G61),ISNUMBER(G119)),ROUND(G61-G119,0),"") -> 1 | H65: =IF(AND(ISNUMBER(H61),ISNUMBER(H119)),ROUND(H61-H119,0),"") -> 1 | I65: =IF(AND(ISNUMBER(I61),ISNUMBER(I119)),ROUND(I61-I119,0),"") -> 0 | J65: =IF(AND(ISNUMBER(J61),ISNUMBER(J119)),ROUND(J61-J119,0),"") -> 0 | ... AW65: =IF(AND(ISNUMBER(AW61),ISNUMBER(AW119)),ROUND(AW61-AW119,0),"") -> 0 | AX65: =ROUND(AX61-AX119,0) -> 0 | AY65: =ROUND(AY61-AY119,0) -> 0 | AZ65: =ROUND(AZ61-AZ119,0) -> 0 | BA65: =ROUND(BA61-BA119,0) -> 0 | BB65: =ROUND(BB61-BB119,0) -> 0 | BC65: =ROUND(BC61-BC119,0) -> 0 | BL65: 2030E | BM65: =BN65+$BM$60 -> 0.719 | BN65: 0.714 | BO65: =BN65+$BO$60 -> 0.704
B66: Quarterly revenue (memo; Hermès publishes revenue only for Q1 and Q3) | BL66: ROI_margin (recurring operating margin %) | BM66: 0.015 | BN66: Δ → | BO66: -0.025 | BP66: Recurring operating margin (Hermès KPI): 41.0% FY25 (H2/25 40.7%), 41.0% H1/26 (41.4% H1/25). H2/26E: H2/25 40.7% less the H1 y/y drift (−0.4 pt) and FX.
B67: Revenue — 1st quarter of the half (Q1 in H1 columns, Q3 in H2 columns) | M67: 943.5 | N67: 991 | P67: 1122.2 | Q67: 1143 | S67: 1190.7 | T67: 1256.7 | V67: 1351.7 | W67: 1337.1 | Y67: 1393.8 | Z67: 1462.5 | AB67: 1609.7 | AC67: 1727.9 | AE67: 1505.5 | AF67: 1800.3 | AH67: 2083.7 | AI67: 2367 | AK67: 2765 | AL67: 3136 | AN67: 3380 | AO67: 3365 | AQ67: 3805 | AR67: 3704 | AT67: 4129 | AU67: 3881 | AW67: 4070 | BL67: H2/26E | BM67: =BN67+$BM$66 -> 0.417 | BN67: 0.402 | BO67: =BN67+$BO$66 -> 0.377
B68: y/y % at constant exchange rates | P68: 0.08 | Q68: 0.079 | S68: 0.062 | T68: 0.088 | V68: 0.112 | W68: 0.113 | Y68: 0.108 | Z68: 0.096 | AB68: 0.116 | AC68: 0.15 | AE68: -0.077 | AF68: 0.069 | AH68: 0.437 | AI68: 0.312 | AK68: 0.271 | AL68: 0.243 | AN68: 0.23 | AO68: 0.156 | AQ68: 0.17 | AR68: 0.113 | AT68: 0.072 | AU68: 0.096 | AW68: 0.056 | BL68: 2027E | BM68: =BN68+$BM$66 -> 0.42 | BN68: 0.405 | BO68: =BN68+$BO$66 -> 0.38
B69: Revenue — 2nd quarter of the half (Q2 in H1 columns, Q4 in H2 columns) | M69: 963.4 | N69: 1221.2 | P69: 1177.2 | Q69: 1398.5 | S69: 1249.7 | T69: 1505.1 | V69: 1361.3 | W69: 1499.1 | Y69: 1459.6 | Z69: 1650.2 | AB69: 1674.5 | AC69: 1871.3 | AE69: 982.5 | AF69: 2101.1 | AH69: 2151.4 | AI69: 2380 | AK69: 2710 | AL69: 2991 | AN69: 3317 | AO69: 3364 | AQ69: 3699 | AR69: 3962 | AT69: 3905 | AU69: 4087 | AW69: 4094 | BL69: 2028E | BM69: =BN69+$BM$66 -> 0.423 | BN69: 0.408 | BO69: =BN69+$BO$66 -> 0.383
B70: y/y % at constant exchange rates | M70: 0.1 | P70: 0.097 | Q70: 0.072 | S70: 0.081 | T70: 0.066 | V70: 0.083 | W70: 0.046 | Y70: 0.116 | Z70: 0.096 | AB70: 0.123 | AC70: 0.107 | AE70: -0.415 | AF70: 0.156 | AH70: 1.271 | AI70: 0.11 | AK70: 0.195 | AL70: 0.229 | AN70: 0.275 | AO70: 0.175 | AQ70: 0.133 | AR70: 0.176 | AT70: 0.09 | AU70: 0.098 | AW70: 0.067 | BL70: 2029E | BM70: =BN70+$BM$66 -> 0.425 | BN70: 0.41 | BO70: =BN70+$BO$66 -> 0.385
B71: Check: quarters vs half-year revenue (should be 0; ±1 from whole-€m quarters) | J71: =IF(AND(ISNUMBER(J67),ISNUMBER(J69)),ROUND(J67+J69-J119,0),"") | K71: =IF(AND(ISNUMBER(K67),ISNUMBER(K69)),ROUND(K67+K69-K119,0),"") | M71: =IF(AND(ISNUMBER(M67),ISNUMBER(M69)),ROUND(M67+M69-M119,0),"") -> 0 | N71: =IF(AND(ISNUMBER(N67),ISNUMBER(N69)),ROUND(N67+N69-N119,0),"") -> 0 | P71: =IF(AND(ISNUMBER(P67),ISNUMBER(P69)),ROUND(P67+P69-P119,0),"") -> 0 | Q71: =IF(AND(ISNUMBER(Q67),ISNUMBER(Q69)),ROUND(Q67+Q69-Q119,0),"") -> 0 | S71: =IF(AND(ISNUMBER(S67),ISNUMBER(S69)),ROUND(S67+S69-S119,0),"") -> 0 | T71: =IF(AND(ISNUMBER(T67),ISNUMBER(T69)),ROUND(T67+T69-T119,0),"") -> 0 | V71: =IF(AND(ISNUMBER(V67),ISNUMBER(V69)),ROUND(V67+V69-V119,0),"") -> 0 | W71: =IF(AND(ISNUMBER(W67),ISNUMBER(W69)),ROUND(W67+W69-W119,0),"") -> 0 | Y71: =IF(AND(ISNUMBER(Y67),ISNUMBER(Y69)),ROUND(Y67+Y69-Y119,0),"") -> 0 | Z71: =IF(AND(ISNUMBER(Z67),ISNUMBER(Z69)),ROUND(Z67+Z69-Z119,0),"") -> 0 | AB71: =IF(AND(ISNUMBER(AB67),ISNUMBER(AB69)),ROUND(AB67+AB69-AB119,0),"") -> 0 | AC71: =IF(AND(ISNUMBER(AC67),ISNUMBER(AC69)),ROUND(AC67+AC69-AC119,0),"") -> 0 | AE71: =IF(AND(ISNUMBER(AE67),ISNUMBER(AE69)),ROUND(AE67+AE69-AE119,0),"") -> 0 | AF71: =IF(AND(ISNUMBER(AF67),ISNUMBER(AF69)),ROUND(AF67+AF69-AF119,0),"") -> 0 | AH71: =IF(AND(ISNUMBER(AH67),ISNUMBER(AH69)),ROUND(AH67+AH69-AH119,0),"") -> 0 | AI71: =IF(AND(ISNUMBER(AI67),ISNUMBER(AI69)),ROUND(AI67+AI69-AI119,0),"") -> 0 | AK71: =IF(AND(ISNUMBER(AK67),ISNUMBER(AK69)),ROUND(AK67+AK69-AK119,0),"") -> 0 | AL71: =IF(AND(ISNUMBER(AL67),ISNUMBER(AL69)),ROUND(AL67+AL69-AL119,0),"") -> 0 | AN71: =IF(AND(ISNUMBER(AN67),ISNUMBER(AN69)),ROUND(AN67+AN69-AN119,0),"") -> -1 | AO71: =IF(AND(ISNUMBER(AO67),ISNUMBER(AO69)),ROUND(AO67+AO69-AO119,0),"") -> 0 | AQ71: =IF(AND(ISNUMBER(AQ67),ISNUMBER(AQ69)),ROUND(AQ67+AQ69-AQ119,0),"") -> 0 | AR71: =IF(AND(ISNUMBER(AR67),ISNUMBER(AR69)),ROUND(AR67+AR69-AR119,0),"") -> 0 | AT71: =IF(AND(ISNUMBER(AT67),ISNUMBER(AT69)),ROUND(AT67+AT69-AT119,0),"") -> 0 | AU71: =IF(AND(ISNUMBER(AU67),ISNUMBER(AU69)),ROUND(AU67+AU69-AU119,0),"") -> 0 | AW71: =IF(AND(ISNUMBER(AW67),ISNUMBER(AW69)),ROUND(AW67+AW69-AW119,0),"") -> 1 | BL71: 2030E | BM71: =BN71+$BM$66 -> 0.425 | BN71: 0.41 | BO71: =BN71+$BO$66 -> 0.385
BL72: Buybacks (€m) | BM72: 300 | BN72: Δ → | BO72: -200 | BP72: Share buybacks (€m; H2/26E then 2027E+): H1/26 €160m (94,846 shares) for employee free-share plans; 2025 €8m net. Floor at 0.
B73: Revenue & recurring operating income by geographical area (IFRS 8 operating segments; memo) | BD73: GEOGRAPHY — historical disclosure (memo cross-check; not forecast) | BL73: H2/26E | BM73: =MAX(0,BN73+$BM$72) -> 350 | BN73: 50 | BO73: =MAX(0,BN73+$BO$72) -> 0
B74: Revenue — France | F74: 370.1 | G74: 437.2 | H74: 494.9 | I74: 555.5 | J74: 289.2 | K74: =L74-J74 -> 323.9 | L74: 613.1 | M74: 307.9 | N74: =O74-M74 -> 336 | O74: 643.9 | P74: 328.3 | Q74: =R74-P74 -> 355.5 | R74: 683.8 | S74: 352.3 | T74: =U74-S74 -> 366.9 | U74: 719.2 | V74: 360.7 | W74: =X74-V74 -> 394.2 | X74: 754.9 | Y74: 390.3 | Z74: =AA74-Y74 -> 411.9 | AA74: 802.2 | AB74: 405.8 | AC74: =AD74-AB74 -> 461.5 | AD74: 867.3 | AE74: 252.2 | AF74: =AG74-AE74 -> 367.4 | AG74: 619.6 | AH74: 341.2 | AI74: =AJ74-AH74 -> 496.8 | AJ74: 838 | AK74: 480 | AL74: =AM74-AK74 -> 584 | AM74: 1064 | AN74: 593 | AO74: =AP74-AN74 -> 681 | AP74: 1274 | AQ74: 680 | AR74: =AS74-AQ74 -> 767 | AS74: 1447 | AT74: 740 | AU74: =AV74-AT74 -> 835 | AV74: 1575 | AW74: 753 | BF74: =IFERROR((BC74/AV74)^(1/5)-1,"n/m") -> -1 | BG74: =IFERROR((AV74/AG74)^(1/5)-1,"n/m") -> 0.20512981 | BH74: =IFERROR((AV74/R74)^(1/10)-1,"n/m") -> 0.087014022 | BI74: =IFERROR((AV74/C74)^(1/19)-1,"n/m") -> n/m | BL74: 2027E | BM74: =MAX(0,BN74+$BM$72) -> 550 | BN74: 250 | BO74: =MAX(0,BN74+$BO$72) -> 50
B75: Revenue — Europe (excl. France) | F75: 385.4 | G75: 463.4 | H75: 559.7 | I75: 661.8 | J75: 346.9 | K75: =L75-J75 -> 390.1 | L75: 737 | M75: 370.8 | N75: =O75-M75 -> 429 | O75: 799.8 | P75: 406.7 | Q75: =R75-P75 -> 499.1 | R75: 905.8 | S75: 433.8 | T75: =U75-S75 -> 529.9 | U75: 963.7 | V75: 475.5 | W75: =X75-V75 -> 568.6 | X75: 1044.1 | Y75: 500.7 | Z75: =AA75-Y75 -> 605.8 | AA75: 1106.5 | AB75: 544.6 | AC75: =AD75-AB75 -> 657.3 | AD75: 1201.9 | AE75: 348.9 | AF75: =AG75-AE75 -> 604.5 | AG75: 953.4 | AH75: 521.9 | AI75: =AJ75-AH75 -> 781.1 | AJ75: 1303 | AK75: 696 | AL75: =AM75-AK75 -> 840 | AM75: 1536 | AN75: 836 | AO75: =AP75-AN75 -> 982 | AP75: 1818 | AQ75: 970 | AR75: =AS75-AQ75 -> 1177 | AS75: 2147 | AT75: 1088 | AU75: =AV75-AT75 -> 1274 | AV75: 2362 | AW75: 1165 | BF75: =IFERROR((BC75/AV75)^(1/5)-1,"n/m") -> -1 | BG75: =IFERROR((AV75/AG75)^(1/5)-1,"n/m") -> 0.19894966 | BH75: =IFERROR((AV75/R75)^(1/10)-1,"n/m") -> 0.10058796 | BI75: =IFERROR((AV75/C75)^(1/19)-1,"n/m") -> n/m | BL75: 2028E | BM75: =MAX(0,BN75+$BM$72) -> 550 | BN75: 250 | BO75: =MAX(0,BN75+$BO$72) -> 50
B76: Revenue — Japan | F76: 408.4 | G76: 453.2 | H76: 471.6 | I76: 545 | J76: 221.4 | K76: =L76-J76 -> 241.8 | L76: 463.2 | M76: 220.8 | N76: =O76-M76 -> 263.6 | O76: 484.4 | P76: 279.7 | Q76: =R76-P76 -> 320.5 | R76: 600.2 | S76: 329.8 | T76: =U76-S76 -> 394.3 | U76: 724.1 | V76: 348.7 | W76: =X76-V76 -> 367.9 | X76: 716.6 | Y76: 344.8 | Z76: =AA76-Y76 -> 403.5 | AA76: 748.3 | AB76: 400.6 | AC76: =AD76-AB76 -> 463.4 | AD76: 864 | AE76: 322.2 | AF76: =AG76-AE76 -> 511.7 | AG76: 833.9 | AH76: 469 | AI76: =AJ76-AH76 -> 508 | AJ76: 977 | AK76: 546 | AL76: =AM76-AK76 -> 555 | AM76: 1101 | AN76: 636 | AO76: =AP76-AN76 -> 624 | AP76: 1260 | AQ76: 693 | AR76: =AS76-AQ76 -> 744 | AS76: 1437 | AT76: 815 | AU76: =AV76-AT76 -> 776 | AV76: 1591 | AW76: 798 | BF76: =IFERROR((BC76/AV76)^(1/5)-1,"n/m") -> -1 | BG76: =IFERROR((AV76/AG76)^(1/5)-1,"n/m") -> 0.13791872 | BH76: =IFERROR((AV76/R76)^(1/10)-1,"n/m") -> 0.10239547 | BI76: =IFERROR((AV76/C76)^(1/19)-1,"n/m") -> n/m | BL76: 2029E | BM76: =MAX(0,BN76+$BM$72) -> 550 | BN76: 250 | BO76: =MAX(0,BN76+$BO$72) -> 50
B77: Revenue — Asia-Pacific (excl. Japan) | F77: 422.6 | G77: 630.9 | H77: 808 | I77: 1100.3 | J77: 591.2 | K77: =L77-J77 -> 656.9 | L77: 1248.1 | M77: 662.3 | N77: =O77-M77 -> 742.7 | O77: 1405 | P77: 842.2 | Q77: =R77-P77 -> 851.8 | R77: 1694 | S77: 856.1 | T77: =U77-S77 -> 921.7 | U77: 1777.8 | V77: 998.5 | W77: =X77-V77 -> 947.5 | X77: 1946 | Y77: 1072.8 | Z77: =AA77-Y77 -> 1069.6 | AA77: 2142.4 | AB77: 1299.3 | AC77: =AD77-AB77 -> 1290.3 | AD77: 2589.6 | AE77: 1183.7 | AF77: =AG77-AE77 -> 1731.7 | AG77: 2915.4 | AH77: 2153 | AI77: =AJ77-AH77 -> 2098 | AJ77: 4251 | AK77: 2665 | AL77: =AM77-AK77 -> 2891 | AM77: 5556 | AN77: 3297 | AO77: =AP77-AN77 -> 2976 | AP77: 6273 | AQ77: 3521 | AR77: =AS77-AQ77 -> 3127 | AS77: 6648 | AT77: 3574 | AU77: =AV77-AT77 -> 3128 | AV77: 6702 | AW77: 3533 | BF77: =IFERROR((BC77/AV77)^(1/5)-1,"n/m") -> -1 | BG77: =IFERROR((AV77/AG77)^(1/5)-1,"n/m") -> 0.18113967 | BH77: =IFERROR((AV77/R77)^(1/10)-1,"n/m") -> 0.14743767 | BI77: =IFERROR((AV77/C77)^(1/19)-1,"n/m") -> n/m | BL77: 2030E | BM77: =MAX(0,BN77+$BM$72) -> 550 | BN77: 250 | BO77: =MAX(0,BN77+$BO$72) -> 50
B78: Revenue — Americas | F78: 293.7 | G78: 384.7 | H78: 464.2 | I78: 568.9 | J78: 286.1 | K78: =L78-J78 -> 341.3 | L78: 627.4 | M78: 306.7 | N78: =O78-M78 -> 404.4 | O78: 711.1 | P78: 403.8 | Q78: =R78-P78 -> 480.3 | R78: 884.1 | S78: 431.6 | T78: =U78-S78 -> 509.2 | U78: 940.8 | V78: 482.4 | W78: =X78-V78 -> 513.4 | X78: 995.8 | Y78: 489.9 | Z78: =AA78-Y78 -> 568.7 | AA78: 1058.6 | AB78: 569.2 | AC78: =AD78-AB78 -> 671.5 | AD78: 1240.7 | AE78: 336.8 | AF78: =AG78-AE78 -> 622.2 | AG78: 959 | AH78: 667.9 | AI78: =AJ78-AH78 -> 790.1 | AJ78: 1458 | AK78: 982 | AL78: =AM78-AK78 -> 1156 | AM78: 2138 | AN78: 1185 | AO78: =AP78-AN78 -> 1317 | AP78: 2502 | AQ78: 1329 | AR78: =AS78-AQ78 -> 1536 | AS78: 2865 | AT78: 1455 | AU78: =AV78-AT78 -> 1620 | AV78: 3075 | AW78: 1585 | BF78: =IFERROR((BC78/AV78)^(1/5)-1,"n/m") -> -1 | BG78: =IFERROR((AV78/AG78)^(1/5)-1,"n/m") -> 0.26242418 | BH78: =IFERROR((AV78/R78)^(1/10)-1,"n/m") -> 0.13275079 | BI78: =IFERROR((AV78/C78)^(1/19)-1,"n/m") -> n/m | BL78: Exceptional dividends paid (€m) | BM78: 1000 | BN78: Δ → | BO78: 0 | BP78: Exceptional dividends paid (€m; 2026E then 2027E+): €10/share (~€1.05bn) paid in 2024 and 2025; none for FY25. Floor at 0.
B79: Revenue — Other (Middle East) | F79: 34.1 | G79: 31.3 | H79: 42.8 | I79: 52.6 | J79: 32.4 | K79: =L79-J79 -> 33.7 | L79: 66.1 | M79: 38.4 | N79: =O79-M79 -> 36.1 | O79: 74.5 | P79: 38.7 | Q79: =R79-P79 -> 34.5 | R79: 73.2 | S79: 36.7 | T79: =U79-S79 -> 40 | U79: 76.7 | V79: 47.2 | W79: =X79-V79 -> 44.6 | X79: 91.8 | Y79: 54.8 | Z79: =AA79-Y79 -> 53.3 | AA79: 108.1 | AB79: 64.6 | AC79: =AD79-AB79 -> 55.4 | AD79: 120 | AE79: 44.1 | AF79: =AG79-AE79 -> 64.1 | AG79: 108.2 | AH79: 82.3 | AI79: =AJ79-AH79 -> 73.7 | AJ79: 156 | AK79: 106 | AL79: =AM79-AK79 -> 101 | AM79: 207 | AN79: 151 | AO79: =AP79-AN79 -> 148 | AP79: 299 | AQ79: 311 | AR79: =AS79-AQ79 -> 316 | AS79: 627 | AT79: 362 | AU79: =AV79-AT79 -> 335 | AV79: 697 | AW79: 330 | BF79: =IFERROR((BC79/AV79)^(1/5)-1,"n/m") -> -1 | BG79: =IFERROR((AV79/AG79)^(1/5)-1,"n/m") -> 0.45144674 | BH79: =IFERROR((AV79/R79)^(1/10)-1,"n/m") -> 0.25277238 | BI79: =IFERROR((AV79/C79)^(1/19)-1,"n/m") -> n/m | BL79: 2026E | BM79: =MAX(0,BN79+$BM$78) -> 1000 | BN79: 0 | BO79: =MAX(0,BN79+$BO$78) -> 0
B80: Revenue — total of areas | C80: =IF(ISNUMBER(C74),N(C74)+N(C75)+N(C76)+N(C77)+N(C78)+N(C79),"") | D80: =IF(ISNUMBER(D74),N(D74)+N(D75)+N(D76)+N(D77)+N(D78)+N(D79),"") | E80: =IF(ISNUMBER(E74),N(E74)+N(E75)+N(E76)+N(E77)+N(E78)+N(E79),"") | F80: =IF(ISNUMBER(F74),N(F74)+N(F75)+N(F76)+N(F77)+N(F78)+N(F79),"") -> 1914.3 | G80: =IF(ISNUMBER(G74),N(G74)+N(G75)+N(G76)+N(G77)+N(G78)+N(G79),"") -> 2400.7 | H80: =IF(ISNUMBER(H74),N(H74)+N(H75)+N(H76)+N(H77)+N(H78)+N(H79),"") -> 2841.2 | I80: =IF(ISNUMBER(I74),N(I74)+N(I75)+N(I76)+N(I77)+N(I78)+N(I79),"") -> 3484.1 | J80: =IF(ISNUMBER(J74),N(J74)+N(J75)+N(J76)+N(J77)+N(J78)+N(J79),"") -> 1767.2 | ... AW80: =IF(ISNUMBER(AW74),N(AW74)+N(AW75)+N(AW76)+N(AW77)+N(AW78)+N(AW79),"") -> 8164 | BL80: 2027E | BM80: =MAX(0,BN80+$BM$78) -> 1000 | BN80: 0 | BO80: =MAX(0,BN80+$BO$78) -> 0
B81: Check: Σ areas vs consolidated revenue (should be 0; ±1 whole-€m rounding) | C81: =IF(AND(ISNUMBER(C80),ISNUMBER(C119)),ROUND(C80-C119,0),"") | D81: =IF(AND(ISNUMBER(D80),ISNUMBER(D119)),ROUND(D80-D119,0),"") | E81: =IF(AND(ISNUMBER(E80),ISNUMBER(E119)),ROUND(E80-E119,0),"") | F81: =IF(AND(ISNUMBER(F80),ISNUMBER(F119)),ROUND(F80-F119,0),"") -> 0 | G81: =IF(AND(ISNUMBER(G80),ISNUMBER(G119)),ROUND(G80-G119,0),"") -> 0 | H81: =IF(AND(ISNUMBER(H80),ISNUMBER(H119)),ROUND(H80-H119,0),"") -> 0 | I81: =IF(AND(ISNUMBER(I80),ISNUMBER(I119)),ROUND(I80-I119,0),"") -> 0 | J81: =IF(AND(ISNUMBER(J80),ISNUMBER(J119)),ROUND(J80-J119,0),"") -> 0 | ... AW81: =IF(AND(ISNUMBER(AW80),ISNUMBER(AW119)),ROUND(AW80-AW119,0),"") -> 1 | BL81: 2028E | BM81: =MAX(0,BN81+$BM$78) -> 1000 | BN81: 0 | BO81: =MAX(0,BN81+$BO$78) -> 0
B82: % of revenue — France | C82: =IF(AND(ISNUMBER(C74),ISNUMBER(C80)),IFERROR(C74/C80,""),"") | D82: =IF(AND(ISNUMBER(D74),ISNUMBER(D80)),IFERROR(D74/D80,""),"") | E82: =IF(AND(ISNUMBER(E74),ISNUMBER(E80)),IFERROR(E74/E80,""),"") | F82: =IF(AND(ISNUMBER(F74),ISNUMBER(F80)),IFERROR(F74/F80,""),"") -> 0.19333438 | G82: =IF(AND(ISNUMBER(G74),ISNUMBER(G80)),IFERROR(G74/G80,""),"") -> 0.18211355 | H82: =IF(AND(ISNUMBER(H74),ISNUMBER(H80)),IFERROR(H74/H80,""),"") -> 0.17418696 | I82: =IF(AND(ISNUMBER(I74),ISNUMBER(I80)),IFERROR(I74/I80,""),"") -> 0.15943859 | J82: =IF(AND(ISNUMBER(J74),ISNUMBER(J80)),IFERROR(J74/J80,""),"") -> 0.16364871 | ... AW82: =IF(AND(ISNUMBER(AW74),ISNUMBER(AW80)),IFERROR(AW74/AW80,""),"") -> 0.092234199 | BF82: =IFERROR(AVERAGE(AY82,AZ82,BA82,BB82,BC82),"n/m") -> n/m | BG82: =IFERROR(AVERAGE(AJ82,AM82,AP82,AS82,AV82),"n/m") -> 0.094738139 | BH82: =IFERROR(AVERAGE(U82,X82,AA82,AD82,AG82,AJ82,AM82,AP82,AS82,AV82),"n/m") -> 0.11054031 | BI82: =IFERROR(AVERAGE(C82,D82,E82,F82,G82,H82,I82,L82,O82,R82,U82,X82,AA82,AD82,AG82,AJ82,AM82,AP82,AS82,AV82),"n/m") -> 0.1338436 | BL82: 2029E | BM82: =MAX(0,BN82+$BM$78) -> 1000 | BN82: 0 | BO82: =MAX(0,BN82+$BO$78) -> 0
B83: % of revenue — Europe (excl. France) | C83: =IF(AND(ISNUMBER(C75),ISNUMBER(C80)),IFERROR(C75/C80,""),"") | D83: =IF(AND(ISNUMBER(D75),ISNUMBER(D80)),IFERROR(D75/D80,""),"") | E83: =IF(AND(ISNUMBER(E75),ISNUMBER(E80)),IFERROR(E75/E80,""),"") | F83: =IF(AND(ISNUMBER(F75),ISNUMBER(F80)),IFERROR(F75/F80,""),"") -> 0.20132686 | G83: =IF(AND(ISNUMBER(G75),ISNUMBER(G80)),IFERROR(G75/G80,""),"") -> 0.19302703 | H83: =IF(AND(ISNUMBER(H75),ISNUMBER(H80)),IFERROR(H75/H80,""),"") -> 0.19699423 | I83: =IF(AND(ISNUMBER(I75),ISNUMBER(I80)),IFERROR(I75/I80,""),"") -> 0.18994862 | J83: =IF(AND(ISNUMBER(J75),ISNUMBER(J80)),IFERROR(J75/J80,""),"") -> 0.19629923 | ... AW83: =IF(AND(ISNUMBER(AW75),ISNUMBER(AW80)),IFERROR(AW75/AW80,""),"") -> 0.14269966 | BF83: =IFERROR(AVERAGE(AY83,AZ83,BA83,BB83,BC83),"n/m") -> n/m | BG83: =IFERROR(AVERAGE(AJ83,AM83,AP83,AS83,AV83),"n/m") -> 0.14039564 | BH83: =IFERROR(AVERAGE(U83,X83,AA83,AD83,AG83,AJ83,AM83,AP83,AS83,AV83),"n/m") -> 0.15846605 | BI83: =IFERROR(AVERAGE(C83,D83,E83,F83,G83,H83,I83,L83,O83,R83,U83,X83,AA83,AD83,AG83,AJ83,AM83,AP83,AS83,AV83),"n/m") -> 0.17314869 | BL83: 2030E | BM83: =MAX(0,BN83+$BM$78) -> 1000 | BN83: 0 | BO83: =MAX(0,BN83+$BO$78) -> 0
B84: % of revenue — Japan | C84: =IF(AND(ISNUMBER(C76),ISNUMBER(C80)),IFERROR(C76/C80,""),"") | D84: =IF(AND(ISNUMBER(D76),ISNUMBER(D80)),IFERROR(D76/D80,""),"") | E84: =IF(AND(ISNUMBER(E76),ISNUMBER(E80)),IFERROR(E76/E80,""),"") | F84: =IF(AND(ISNUMBER(F76),ISNUMBER(F80)),IFERROR(F76/F80,""),"") -> 0.21334169 | G84: =IF(AND(ISNUMBER(G76),ISNUMBER(G80)),IFERROR(G76/G80,""),"") -> 0.18877827 | H84: =IF(AND(ISNUMBER(H76),ISNUMBER(H80)),IFERROR(H76/H80,""),"") -> 0.1659862 | I84: =IF(AND(ISNUMBER(I76),ISNUMBER(I80)),IFERROR(I76/I80,""),"") -> 0.1564249 | J84: =IF(AND(ISNUMBER(J76),ISNUMBER(J80)),IFERROR(J76/J80,""),"") -> 0.12528293 | ... AW84: =IF(AND(ISNUMBER(AW76),ISNUMBER(AW80)),IFERROR(AW76/AW80,""),"") -> 0.097746203 | BF84: =IFERROR(AVERAGE(AY84,AZ84,BA84,BB84,BC84),"n/m") -> n/m | BG84: =IFERROR(AVERAGE(AJ84,AM84,AP84,AS84,AV84),"n/m") -> 0.098330289 | BH84: =IFERROR(AVERAGE(U84,X84,AA84,AD84,AG84,AJ84,AM84,AP84,AS84,AV84),"n/m") -> 0.11414295 | BI84: =IFERROR(AVERAGE(C84,D84,E84,F84,G84,H84,I84,L84,O84,R84,U84,X84,AA84,AD84,AG84,AJ84,AM84,AP84,AS84,AV84),"n/m") -> 0.13122996 | BL84: Payout (ordinary DPS / recurring EPS) | BM84: 0.05 | BN84: Δ → | BO84: 0 | BP84: Ordinary DPS / recurring diluted EPS (2026E then 2027E+): FY25 €18.00 / €46.2 = 39%; FY24 €16.00 / €43.9 = 36%.
B85: % of revenue — Asia-Pacific (excl. Japan) | C85: =IF(AND(ISNUMBER(C77),ISNUMBER(C80)),IFERROR(C77/C80,""),"") | D85: =IF(AND(ISNUMBER(D77),ISNUMBER(D80)),IFERROR(D77/D80,""),"") | E85: =IF(AND(ISNUMBER(E77),ISNUMBER(E80)),IFERROR(E77/E80,""),"") | F85: =IF(AND(ISNUMBER(F77),ISNUMBER(F80)),IFERROR(F77/F80,""),"") -> 0.22075955 | G85: =IF(AND(ISNUMBER(G77),ISNUMBER(G80)),IFERROR(G77/G80,""),"") -> 0.26279835 | H85: =IF(AND(ISNUMBER(H77),ISNUMBER(H80)),IFERROR(H77/H80,""),"") -> 0.28438688 | I85: =IF(AND(ISNUMBER(I77),ISNUMBER(I80)),IFERROR(I77/I80,""),"") -> 0.31580609 | J85: =IF(AND(ISNUMBER(J77),ISNUMBER(J80)),IFERROR(J77/J80,""),"") -> 0.33454052 | ... AW85: =IF(AND(ISNUMBER(AW77),ISNUMBER(AW80)),IFERROR(AW77/AW80,""),"") -> 0.43275355 | BF85: =IFERROR(AVERAGE(AY85,AZ85,BA85,BB85,BC85),"n/m") -> n/m | BG85: =IFERROR(AVERAGE(AJ85,AM85,AP85,AS85,AV85),"n/m") -> 0.45527301 | BH85: =IFERROR(AVERAGE(U85,X85,AA85,AD85,AG85,AJ85,AM85,AP85,AS85,AV85),"n/m") -> 0.4160359 | BI85: =IFERROR(AVERAGE(C85,D85,E85,F85,G85,H85,I85,L85,O85,R85,U85,X85,AA85,AD85,AG85,AJ85,AM85,AP85,AS85,AV85),"n/m") -> 0.3686794 | BL85: 2026E | BM85: =BN85+$BM$84 -> 0.45 | BN85: 0.4 | BO85: =BN85+$BO$84 -> 0.4
B86: % of revenue — Americas | C86: =IF(AND(ISNUMBER(C78),ISNUMBER(C80)),IFERROR(C78/C80,""),"") | D86: =IF(AND(ISNUMBER(D78),ISNUMBER(D80)),IFERROR(D78/D80,""),"") | E86: =IF(AND(ISNUMBER(E78),ISNUMBER(E80)),IFERROR(E78/E80,""),"") | F86: =IF(AND(ISNUMBER(F78),ISNUMBER(F80)),IFERROR(F78/F80,""),"") -> 0.15342423 | G86: =IF(AND(ISNUMBER(G78),ISNUMBER(G80)),IFERROR(G78/G80,""),"") -> 0.16024493 | H86: =IF(AND(ISNUMBER(H78),ISNUMBER(H80)),IFERROR(H78/H80,""),"") -> 0.16338167 | I86: =IF(AND(ISNUMBER(I78),ISNUMBER(I80)),IFERROR(I78/I80,""),"") -> 0.16328464 | J86: =IF(AND(ISNUMBER(J78),ISNUMBER(J80)),IFERROR(J78/J80,""),"") -> 0.16189452 | ... AW86: =IF(AND(ISNUMBER(AW78),ISNUMBER(AW80)),IFERROR(AW78/AW80,""),"") -> 0.19414503 | BF86: =IFERROR(AVERAGE(AY86,AZ86,BA86,BB86,BC86),"n/m") -> n/m | BG86: =IFERROR(AVERAGE(AJ86,AM86,AP86,AS86,AV86),"n/m") -> 0.18279012 | BH86: =IFERROR(AVERAGE(U86,X86,AA86,AD86,AG86,AJ86,AM86,AP86,AS86,AV86),"n/m") -> 0.17820114 | BI86: =IFERROR(AVERAGE(C86,D86,E86,F86,G86,H86,I86,L86,O86,R86,U86,X86,AA86,AD86,AG86,AJ86,AM86,AP86,AS86,AV86),"n/m") -> 0.17321827 | BL86: 2027E | BM86: =BN86+$BM$84 -> 0.45 | BN86: 0.4 | BO86: =BN86+$BO$84 -> 0.4
B87: % of revenue — Other (Middle East) | C87: =IF(AND(ISNUMBER(C79),ISNUMBER(C80)),IFERROR(C79/C80,""),"") | D87: =IF(AND(ISNUMBER(D79),ISNUMBER(D80)),IFERROR(D79/D80,""),"") | E87: =IF(AND(ISNUMBER(E79),ISNUMBER(E80)),IFERROR(E79/E80,""),"") | F87: =IF(AND(ISNUMBER(F79),ISNUMBER(F80)),IFERROR(F79/F80,""),"") -> 0.0178133 | G87: =IF(AND(ISNUMBER(G79),ISNUMBER(G80)),IFERROR(G79/G80,""),"") -> 0.013037864 | H87: =IF(AND(ISNUMBER(H79),ISNUMBER(H80)),IFERROR(H79/H80,""),"") -> 0.015064057 | I87: =IF(AND(ISNUMBER(I79),ISNUMBER(I80)),IFERROR(I79/I80,""),"") -> 0.015097156 | J87: =IF(AND(ISNUMBER(J79),ISNUMBER(J80)),IFERROR(J79/J80,""),"") -> 0.018334088 | ... AW87: =IF(AND(ISNUMBER(AW79),ISNUMBER(AW80)),IFERROR(AW79/AW80,""),"") -> 0.040421362 | BF87: =IFERROR(AVERAGE(AY87,AZ87,BA87,BB87,BC87),"n/m") -> n/m | BG87: =IFERROR(AVERAGE(AJ87,AM87,AP87,AS87,AV87),"n/m") -> 0.028472803 | BH87: =IFERROR(AVERAGE(U87,X87,AA87,AD87,AG87,AJ87,AM87,AP87,AS87,AV87),"n/m") -> 0.022613648 | BI87: =IFERROR(AVERAGE(C87,D87,E87,F87,G87,H87,I87,L87,O87,R87,U87,X87,AA87,AD87,AG87,AJ87,AM87,AP87,AS87,AV87),"n/m") -> 0.019880076 | BL87: 2028E | BM87: =BN87+$BM$84 -> 0.45 | BN87: 0.4 | BO87: =BN87+$BO$84 -> 0.4
B88: y/y % at constant exchange rates — France | G88: 0.181 | H88: 0.132 | I88: 0.122 | J88: 0.13 | L88: 0.104 | M88: 0.065 | O88: 0.05 | P88: 0.066 | R88: 0.062 | S88: 0.073 | U88: 0.052 | V88: 0.024 | X88: 0.05 | Y88: 0.082 | AA88: 0.063 | AB88: 0.04 | AD88: 0.081 | AE88: -0.378 | AG88: -0.286 | AH88: 0.353 | AJ88: 0.352 | AK88: 0.407 | AM88: 0.269 | AN88: 0.235 | AP88: 0.198 | AQ88: 0.147 | AS88: 0.135 | AT88: 0.087 | AV88: 0.089 | AW88: 0.018 | BL88: 2029E | BM88: =BN88+$BM$84 -> 0.45 | BN88: 0.4 | BO88: =BN88+$BO$84 -> 0.4
B89: y/y % at constant exchange rates — Europe (excl. France) | G89: 0.179 | H89: 0.193 | I89: 0.166 | J89: 0.143 | L89: 0.129 | M89: 0.073 | O89: 0.086 | P89: 0.07 | R89: 0.108 | S89: 0.091 | U89: 0.092 | V89: 0.107 | X89: 0.096 | Y89: 0.074 | AA89: 0.075 | AB89: 0.088 | AD89: 0.081 | AE89: -0.362 | AG89: -0.2 | AH89: 0.518 | AJ89: 0.369 | AK89: 0.338 | AM89: 0.184 | AN89: 0.215 | AP89: 0.202 | AQ89: 0.177 | AS89: 0.189 | AT89: 0.126 | AV89: 0.113 | AW89: 0.088 | BL89: 2030E | BM89: =BN89+$BM$84 -> 0.45 | BN89: 0.4 | BO89: =BN89+$BO$84 -> 0.4
B90: y/y % at constant exchange rates — Japan | G90: -0.008 | H90: -0.007 | I90: 0.068 | J90: 0.08 | L90: 0.065 | M90: 0.113 | O90: 0.129 | P90: 0.205 | R90: 0.183 | S90: 0.1 | U90: 0.086 | V90: 0.034 | X90: 0.041 | Y90: 0.068 | AA90: 0.075 | AB90: 0.098 | AD90: 0.082 | AE90: -0.228 | AG90: -0.037 | AH90: 0.585 | AJ90: 0.249 | AK90: 0.204 | AM90: 0.197 | AN90: 0.26 | AP90: 0.257 | AQ90: 0.224 | AS90: 0.225 | AT90: 0.16 | AV90: 0.141 | AW90: 0.11
B91: y/y % at constant exchange rates — Asia-Pacific (excl. Japan) | G91: 0.38 | H91: 0.294 | I91: 0.254 | J91: 0.169 | L91: 0.164 | M91: 0.172 | O91: 0.131 | P91: 0.069 | R91: 0.051 | S91: 0.053 | U91: 0.071 | V91: 0.143 | X91: 0.113 | Y91: 0.149 | AA91: 0.137 | AB91: 0.177 | AD91: 0.178 | AE91: -0.091 | AG91: 0.144 | AH91: 0.865 | AJ91: 0.446 | AK91: 0.149 | AM91: 0.219 | AN91: 0.276 | AP91: 0.191 | AQ91: 0.099 | AS91: 0.074 | AT91: 0.03 | AV91: 0.049 | AW91: 0.024
B92: y/y % at constant exchange rates — Americas | G92: 0.241 | H92: 0.258 | I92: 0.14 | J92: 0.165 | L92: 0.142 | M92: 0.126 | O92: 0.145 | P92: 0.103 | R92: 0.068 | S92: 0.083 | U92: 0.072 | V92: 0.088 | X92: 0.077 | Y92: 0.124 | AA92: 0.115 | AB92: 0.098 | AD92: 0.12 | AE92: -0.417 | AG92: -0.205 | AH92: 1.151 | AJ92: 0.567 | AK92: 0.341 | AM92: 0.316 | AN92: 0.199 | AP92: 0.205 | AQ92: 0.126 | AS92: 0.155 | AT92: 0.117 | AV92: 0.124 | AW92: 0.153
B93: y/y % at constant exchange rates — Other (Middle East) | G93: -0.088 | H93: 0.359 | I93: 0.225 | J93: 0.223 | L93: 0.26 | M93: 0.186 | O93: 0.126 | P93: 0 | R93: -0.022 | S93: -0.049 | U93: 0.048 | V93: 0.286 | X93: 0.199 | Y93: 0.162 | AA93: 0.178 | AB93: 0.177 | AD93: 0.109 | AE93: -0.317 | AG93: -0.099 | AH93: 0.87 | AJ93: 0.446 | AK93: 0.28 | AM93: 0.315 | AN93: 0.424 | AP93: 0.44 | AQ93: 1.053 | AS93: 1.096 | AT93: 0.172 | AV93: 0.149 | AW93: -0.042
B94: Recurring operating income — France | F94: 95.2 | G94: 102 | H94: 139 | I94: 155.6 | J94: 102.8 | K94: =L94-J94 -> 105.2 | L94: 208 | M94: 99.9 | N94: =O94-M94 -> 119.1 | O94: 219 | P94: 110.6 | Q94: =R94-P94 -> 115.4 | R94: 226 | S94: 112.8 | T94: =U94-S94 -> 128.2 | U94: 241 | V94: 116.5 | W94: =X94-V94 -> 154.1 | X94: 270.6 | Y94: 117.6 | Z94: =AA94-Y94 -> 159.3 | AA94: 276.9 | AB94: 135.4 | AC94: =AD94-AB94 -> 177.3 | AD94: 312.7 | AE94: 39.4 | AF94: =AG94-AE94 -> 119.8 | AG94: 159.2 | AH94: 98.7 | AI94: =AJ94-AH94 -> 186.3 | AJ94: 285 | AK94: 183 | AL94: =AM94-AK94 -> 228 | AM94: 411 | AN94: 243 | AO94: =AP94-AN94 -> 269 | AP94: 512 | AQ94: 263 | AR94: =AS94-AQ94 -> 370 | AS94: 633 | AT94: 271 | AU94: =AV94-AT94 -> 444 | AV94: 715 | AW94: 273
B95: Recurring operating income — Europe (excl. France) | F95: 94.8 | G95: 110 | H95: 147.7 | I95: 188.7 | J95: 96.8 | K95: =L95-J95 -> 106 | L95: 202.8 | M95: 99.6 | N95: =O95-M95 -> 119.2 | O95: 218.8 | P95: 107 | Q95: =R95-P95 -> 131.3 | R95: 238.3 | S95: 113.3 | T95: =U95-S95 -> 139.9 | U95: 253.2 | V95: 143.6 | W95: =X95-V95 -> 150.9 | X95: 294.5 | Y95: 129 | Z95: =AA95-Y95 -> 177.8 | AA95: 306.8 | AB95: 142.8 | AC95: =AD95-AB95 -> 200.8 | AD95: 343.6 | AE95: 16.4 | AF95: =AG95-AE95 -> 179 | AG95: 195.4 | AH95: 126.2 | AI95: =AJ95-AH95 -> 245.8 | AJ95: 372 | AK95: 188 | AL95: =AM95-AK95 -> 249 | AM95: 437 | AN95: 275 | AO95: =AP95-AN95 -> 309 | AP95: 584 | AQ95: 313 | AR95: =AS95-AQ95 -> 406 | AS95: 719 | AT95: 353 | AU95: =AV95-AT95 -> 460 | AV95: 813 | AW95: 374
B96: Recurring operating income — Japan | F96: 122.6 | G96: 152 | H96: 163.6 | I96: 201.3 | J96: 84 | K96: =L96-J96 -> 94.1 | L96: 178.1 | M96: 81.9 | N96: =O96-M96 -> 67.4 | O96: 149.3 | P96: 100.6 | Q96: =R96-P96 -> 103.1 | R96: 203.7 | S96: 129.7 | T96: =U96-S96 -> 121.3 | U96: 251 | V96: 130.2 | W96: =X96-V96 -> 124.8 | X96: 255 | Y96: 131 | Z96: =AA96-Y96 -> 144.3 | AA96: 275.3 | AB96: 157.4 | AC96: =AD96-AB96 -> 161.1 | AD96: 318.5 | AE96: 80.2 | AF96: =AG96-AE96 -> 211.5 | AG96: 291.7 | AH96: 193.9 | AI96: =AJ96-AH96 -> 186.1 | AJ96: 380 | AK96: 219 | AL96: =AM96-AK96 -> 216 | AM96: 435 | AN96: 253 | AO96: =AP96-AN96 -> 252 | AP96: 505 | AQ96: 298 | AR96: =AS96-AQ96 -> 269 | AS96: 567 | AT96: 328 | AU96: =AV96-AT96 -> 297 | AV96: 625 | AW96: 333
B97: Recurring operating income — Asia-Pacific (excl. Japan) | F97: 144.4 | G97: 248.1 | H97: 336.5 | I97: 456.9 | J97: 234.1 | K97: =L97-J97 -> 256.2 | L97: 490.3 | M97: 275 | N97: =O97-M97 -> 292.4 | O97: 567.4 | P97: 342.5 | Q97: =R97-P97 -> 325.1 | R97: 667.6 | S97: 380.4 | T97: =U97-S97 -> 363.3 | U97: 743.7 | V97: 458.4 | W97: =X97-V97 -> 406.8 | X97: 865.2 | Y97: 499.1 | Z97: =AA97-Y97 -> 451 | AA97: 950.1 | AB97: 578.1 | AC97: =AD97-AB97 -> 501.8 | AD97: 1079.9 | AE97: 474.8 | AF97: =AG97-AE97 -> 814.8 | AG97: 1289.6 | AH97: 1107.9 | AI97: =AJ97-AH97 -> 872.1 | AJ97: 1980 | AK97: 1322 | AL97: =AM97-AK97 -> 1304 | AM97: 2626 | AN97: 1687 | AO97: =AP97-AN97 -> 1372 | AP97: 3059 | AQ97: 1730 | AR97: =AS97-AQ97 -> 936 | AS97: 2666 | AT97: 1724 | AU97: =AV97-AT97 -> 1037 | AV97: 2761 | AW97: 1653
B98: Recurring operating income — Americas | F98: 73.6 | G98: 115.3 | H98: 148.7 | I98: 181.1 | J98: 95.3 | K98: =L98-J98 -> 115.3 | L98: 210.6 | M98: 94.7 | N98: =O98-M98 -> 126.8 | O98: 221.5 | P98: 131.6 | Q98: =R98-P98 -> 147.3 | R98: 278.9 | S98: 139.6 | T98: =U98-S98 -> 157.8 | U98: 297.4 | V98: 157.5 | W98: =X98-V98 -> 193.4 | X98: 350.9 | Y98: 165.2 | Z98: =AA98-Y98 -> 214.4 | AA98: 379.6 | AB98: 190.2 | AC98: =AD98-AB98 -> 237.4 | AD98: 427.6 | AE98: 2.9 | AF98: =AG98-AE98 -> 225.7 | AG98: 228.6 | AH98: 262.7 | AI98: =AJ98-AH98 -> 257.3 | AJ98: 520 | AK98: 365 | AL98: =AM98-AK98 -> 372 | AM98: 737 | AN98: 448 | AO98: =AP98-AN98 -> 447 | AP98: 895 | AQ98: 492 | AR98: =AS98-AQ98 -> 523 | AS98: 1015 | AT98: 527 | AU98: =AV98-AT98 -> 572 | AV98: 1099 | AW98: 581
B99: Recurring operating income — Other (Middle East) | F99: 4.9 | G99: 3.1 | H99: 0.6 | I99: 3.2 | J99: 8.3 | K99: =L99-J99 -> 3.7 | L99: 12 | M99: 11.1 | N99: =O99-M99 -> 6.3 | O99: 17.4 | P99: 10 | Q99: =R99-P99 -> 4.8 | R99: 14.8 | S99: 8.2 | T99: =U99-S99 -> 5.9 | U99: 14.1 | V99: 7.5 | W99: =X99-V99 -> 5.2 | X99: 12.7 | Y99: 8.9 | Z99: =AA99-Y99 -> 4.3 | AA99: 13.2 | AB99: 14.5 | AC99: =AD99-AB99 -> 19.3 | AD99: 33.8 | AE99: 8.4 | AF99: =AG99-AE99 -> 16.2 | AG99: 24.6 | AH99: 26.8 | AI99: =AJ99-AH99 -> 17.2 | AJ99: 44 | AK99: 33 | AL99: =AM99-AK99 -> 25 | AM99: 58 | AN99: 44 | AO99: =AP99-AN99 -> 45 | AP99: 89 | AQ99: 108 | AR99: =AS99-AQ99 -> 110 | AS99: 218 | AT99: 149 | AU99: =AV99-AT99 -> 119 | AV99: 268 | AW99: 128
B100: Recurring operating income — Unallocated / Holding (free-share plans, central costs, internal billings) | F100: -72.5 | G100: -62.2 | H100: -50.9 | I100: -68.2 | J100: -37.2 | K100: =L100-J100 -> -46.5 | L100: -83.7 | M100: -40.7 | N100: =O100-M100 -> -53.3 | O100: -94 | P100: -54.2 | Q100: =R100-P100 -> -34.5 | R100: -88.7 | S100: -57.2 | T100: =U100-S100 -> -46.7 | U100: -103.9 | V100: -82.4 | W100: =X100-V100 -> -44.5 | X100: -126.9 | Y100: -66.3 | Z100: =AA100-Y100 -> -90.5 | AA100: -156.8 | AB100: -74.5 | AC100: =AD100-AB100 -> -102.8 | AD100: -177.3 | AE100: -87.4 | AF100: =AG100-AE100 -> -120.4 | AG100: -207.8 | AH100: -94.4 | AI100: =AJ100-AH100 -> 44.4 | AJ100: -50 | AK100: -4 | AL100: =AM100-AK100 -> -2 | AM100: -6 | AN100: -5 | AO100: =AP100-AN100 -> 11 | AP100: 6 | AQ100: -55 | AR100: =AS100-AQ100 -> 386 | AS100: 331 | AT100: -25 | AU100: =AV100-AT100 -> 314 | AV100: 289 | AW100: 9
B101: Recurring operating income — total of areas | C101: =IF(ISNUMBER(C94),N(C94)+N(C95)+N(C96)+N(C97)+N(C98)+N(C99)+N(C100),"") | D101: =IF(ISNUMBER(D94),N(D94)+N(D95)+N(D96)+N(D97)+N(D98)+N(D99)+N(D100),"") | E101: =IF(ISNUMBER(E94),N(E94)+N(E95)+N(E96)+N(E97)+N(E98)+N(E99)+N(E100),"") | F101: =IF(ISNUMBER(F94),N(F94)+N(F95)+N(F96)+N(F97)+N(F98)+N(F99)+N(F100),"") -> 463 | G101: =IF(ISNUMBER(G94),N(G94)+N(G95)+N(G96)+N(G97)+N(G98)+N(G99)+N(G100),"") -> 668.3 | H101: =IF(ISNUMBER(H94),N(H94)+N(H95)+N(H96)+N(H97)+N(H98)+N(H99)+N(H100),"") -> 885.2 | I101: =IF(ISNUMBER(I94),N(I94)+N(I95)+N(I96)+N(I97)+N(I98)+N(I99)+N(I100),"") -> 1118.6 | J101: =IF(ISNUMBER(J94),N(J94)+N(J95)+N(J96)+N(J97)+N(J98)+N(J99)+N(J100),"") -> 584.1 | ... AW101: =IF(ISNUMBER(AW94),N(AW94)+N(AW95)+N(AW96)+N(AW97)+N(AW98)+N(AW99)+N(AW100),"") -> 3351
...

Sheet Bull-Base-Bear
B2: Hermès International (RMS) — Bull / Base / Bear Case P&L Summary | J2: Share price (€): | K2: =Model!$AY$379 -> 1299.5
B3: Adjusted figures (Hermès APMs: recurring operating income, adjusted free cash flow, restated net cash; recurring net income / EPS and EBITDA = model bridges) · EUR millions · Live panel linked to Model — toggle scenario via Model!BD2. Bull and Bear panels are value snapshots generated from the Model with the switch set to each case. | J3: As of: | K3: =TODAY() -> 46299
B5: Scenario: | C5: =Model!$BD$2 -> Base | N5: Scenario: | O5: Bull | P5: Snapshot (values) — Model run with switch = Bull | Z5: Scenario: | AA5: Bear | AB5: Snapshot (values) — Model run with switch = Bear
B7: (EURm, except EPS and shares) | C7: 2025A | D7: 2026E | E7: 2027E | F7: 2028E | G7: 2029E | H7: 2030E | I7: 25-'30 CAGR | J7: LT Hist Avg | K7: LT Hist Min | L7: LT Hist Max | N7: (EURm, except EPS and shares) | O7: 2025A | P7: 2026E | Q7: 2027E | R7: 2028E | S7: 2029E | T7: 2030E | U7: 25-'30 CAGR | V7: LT Hist Avg | W7: LT Hist Min | X7: LT Hist Max | Z7: (EURm, except EPS and shares) | AA7: 2025A | AB7: 2026E | AC7: 2027E | AD7: 2028E | AE7: 2029E | AF7: 2030E | AG7: 25-'30 CAGR | AH7: LT Hist Avg | AI7: LT Hist Min | AJ7: LT Hist Max
B9: Revenue | C9: =Model!AV119 -> 16002 | D9: =Model!AY119 -> 16406.99 | E9: =Model!AZ119 -> 17626.336 | F9: =Model!BA119 -> 18946.137 | G9: =Model!BB119 -> 20307.483 | H9: =Model!BC119 -> 21676.783 | I9: =IFERROR((H9/C9)^(1/5)-1,"n/m") -> 0.062586059 | N9: Revenue | O9: 16002 | P9: 16646.03 | Q9: 18215.903 | R9: 19943.909 | S9: 21775.495 | T9: 23678.874 | U9: 0.081526977 | Z9: Revenue | AA9: 16002 | AB9: 16008.59 | AC9: 16718.335 | AD9: 17468.995 | AE9: 18200.61 | AF9: 18882.399 | AG9: 0.033657309
B10: Revenue y/y % | D10: =IFERROR(D9/C9-1,"") -> 0.025308711 | E10: =IFERROR(E9/D9-1,"") -> 0.074318714 | F10: =IFERROR(F9/E9-1,"") -> 0.074876647 | G10: =IFERROR(G9/F9-1,"") -> 0.071853461 | H10: =IFERROR(H9/G9-1,"") -> 0.067428365 | N10: Revenue y/y % | P10: 0.040246844 | Q10: 0.094309178 | R10: 0.094862444 | S10: 0.091836889 | T10: 0.087409224 | Z10: Revenue y/y % | AB10: 0.00041182352 | AC10: 0.044335241 | AD10: 0.04490044 | AE10: 0.041880774 | AF10: 0.03745965
B11: Revenue y/y % at constant exchange rates | C11: =Model!AV197 -> 0.089 | D11: =Model!AY197 -> 0.062825011 | E11: =Model!AZ197 -> 0.074318714 | F11: =Model!BA197 -> 0.074876647 | G11: =Model!BB197 -> 0.071853461 | H11: =Model!BC197 -> 0.067428365 | N11: Revenue y/y % at constant exchange rates | O11: 0.089 | P11: 0.072784388 | Q11: 0.094309178 | R11: 0.094862444 | S11: 0.091836889 | T11: 0.087409224 | Z11: Revenue y/y % at constant exchange rates | AA11: 0.089 | AB11: 0.047885945 | AC11: 0.044335241 | AD11: 0.04490044 | AE11: 0.041880774 | AF11: 0.03745965
B12: Recurring Operating Income | C12: =Model!AV124 -> 6569 | D12: =Model!AY124 -> 6664.084 | E12: =Model!AZ124 -> 7138.6662 | F12: =Model!BA124 -> 7730.024 | G12: =Model!BB124 -> 8326.068 | H12: =Model!BC124 -> 8887.4811 | I12: =IFERROR((H12/C12)^(1/5)-1,"n/m") -> 0.062321292 | N12: Recurring Operating Income | O12: 6569 | P12: 6887.4235 | Q12: 7650.6794 | R12: 8436.2733 | S12: 9254.5854 | T12: 10063.522 | U12: 0.089055828 | Z12: Recurring Operating Income | AA12: 6569 | AB12: 6307.7874 | AC12: 6352.9672 | AD12: 6690.6252 | AE12: 7007.235 | AF12: 7269.7235 | AG12: 0.020478189
B13: Recurring operating margin % | C13: =IFERROR(C12/C9,"") -> 0.41051119 | D13: =IFERROR(D12/D9,"") -> 0.40617347 | E13: =IFERROR(E12/E9,"") -> 0.405 | F13: =IFERROR(F12/F9,"") -> 0.408 | G13: =IFERROR(G12/G9,"") -> 0.41 | H13: =IFERROR(H12/H9,"") -> 0.41 | J13: =IFERROR(AVERAGE(Model!C203,Model!D203,Model!E203,Model!F203,Model!G203,Model!H203,Model!I203,Model!L203,Model!O203,Model!R203,Model!U203,Model!X203,Model!AA203,Model!AD203,Model!AG203,Model!AJ203,Model!AM203,Model!AP203,Model!AS203,Model!AV203),"") -> 0.32924659 | K13: =IFERROR(MIN(Model!C203,Model!D203,Model!E203,Model!F203,Model!G203,Model!H203,Model!I203,Model!L203,Model!O203,Model!R203,Model!U203,Model!X203,Model!AA203,Model!AD203,Model!AG203,Model!AJ203,Model!AM203,Model!AP203,Model!AS203,Model!AV203),"") -> 0.24181163 | L13: =IFERROR(MAX(Model!C203,Model!D203,Model!E203,Model!F203,Model!G203,Model!H203,Model!I203,Model!L203,Model!O203,Model!R203,Model!U203,Model!X203,Model!AA203,Model!AD203,Model!AG203,Model!AJ203,Model!AM203,Model!AP203,Model!AS203,Model!AV203),"") -> 0.42071945 | N13: Recurring operating margin % | O13: 0.41051119 | P13: 0.41375773 | Q13: 0.42 | R13: 0.423 | S13: 0.425 | T13: 0.425 | V13: 0.32924659 | W13: 0.24181163 | X13: 0.42071945 | Z13: Recurring operating margin % | AA13: 0.41051119 | AB13: 0.39402517 | AC13: 0.38 | AD13: 0.383 | AE13: 0.385 | AF13: 0.385 | AH13: 0.32924659 | AI13: 0.24181163 | AJ13: 0.42071945
B15: Operating Income (IFRS) | C15: =Model!AV127 -> 6569 | D15: =Model!AY127 -> 6664.084 | E15: =Model!AZ127 -> 7138.6662 | F15: =Model!BA127 -> 7730.024 | G15: =Model!BB127 -> 8326.068 | H15: =Model!BC127 -> 8887.4811 | I15: =IFERROR((H15/C15)^(1/5)-1,"n/m") -> 0.062321292 | N15: Operating Income (IFRS) | O15: 6569 | P15: 6887.4235 | Q15: 7650.6794 | R15: 8436.2733 | S15: 9254.5854 | T15: 10063.522 | U15: 0.089055828 | Z15: Operating Income (IFRS) | AA15: 6569 | AB15: 6307.7874 | AC15: 6352.9672 | AD15: 6690.6252 | AE15: 7007.235 | AF15: 7269.7235 | AG15: 0.020478189
B16: Operating income y/y % | D16: =IFERROR(D15/C15-1,"") -> 0.014474651 | E16: =IFERROR(E15/D15-1,"") -> 0.071214928 | F16: =IFERROR(F15/E15-1,"") -> 0.082838696 | G16: =IFERROR(G15/F15-1,"") -> 0.077107644 | H16: =IFERROR(H15/G15-1,"") -> 0.067428365 | N16: Operating income y/y % | P16: 0.048473666 | Q16: 0.11081879 | R16: 0.10268289 | S16: 0.096999239 | T16: 0.087409224 | Z16: Operating income y/y % | AB16: -0.039764434 | AC16: 0.0071625362 | AD16: 0.053149654 | AE16: 0.047321405 | AF16: 0.03745965
B17: Operating margin (IFRS) % | C17: =IFERROR(C15/C9,"") -> 0.41051119 | D17: =IFERROR(D15/D9,"") -> 0.40617347 | E17: =IFERROR(E15/E9,"") -> 0.405 | F17: =IFERROR(F15/F9,"") -> 0.408 | G17: =IFERROR(G15/G9,"") -> 0.41 | H17: =IFERROR(H15/H9,"") -> 0.41 | J17: =IFERROR(AVERAGE(Model!C205,Model!D205,Model!E205,Model!F205,Model!G205,Model!H205,Model!I205,Model!L205,Model!O205,Model!R205,Model!U205,Model!X205,Model!AA205,Model!AD205,Model!AG205,Model!AJ205,Model!AM205,Model!AP205,Model!AS205,Model!AV205),"") -> 0.33114958 | K17: =IFERROR(MIN(Model!C205,Model!D205,Model!E205,Model!F205,Model!G205,Model!H205,Model!I205,Model!L205,Model!O205,Model!R205,Model!U205,Model!X205,Model!AA205,Model!AD205,Model!AG205,Model!AJ205,Model!AM205,Model!AP205,Model!AS205,Model!AV205),"") -> 0.24181163 | L17: =IFERROR(MAX(Model!C205,Model!D205,Model!E205,Model!F205,Model!G205,Model!H205,Model!I205,Model!L205,Model!O205,Model!R205,Model!U205,Model!X205,Model!AA205,Model!AD205,Model!AG205,Model!AJ205,Model!AM205,Model!AP205,Model!AS205,Model!AV205),"") -> 0.42071945 | N17: Operating margin (IFRS) % | O17: 0.41051119 | P17: 0.41375773 | Q17: 0.42 | R17: 0.423 | S17: 0.425 | T17: 0.425 | V17: 0.33114958 | W17: 0.24181163 | X17: 0.42071945 | Z17: Operating margin (IFRS) % | AA17: 0.41051119 | AB17: 0.39402517 | AC17: 0.38 | AD17: 0.383 | AE17: 0.385 | AF17: 0.385 | AH17: 0.33114958 | AI17: 0.24181163 | AJ17: 0.42071945
B19: Recurring Net Income (attributable; excl. non-recurring & French exceptional contribution) | C19: =Model!AV187 -> 4855 | D19: =Model!AY187 -> 4959.7091 | E19: =Model!AZ187 -> 5292.0401 | F19: =Model!BA187 -> 5743.4712 | G19: =Model!BB187 -> 6203.7986 | H19: =Model!BC187 -> 6643.3671 | I19: =IFERROR((H19/C19)^(1/5)-1,"n/m") -> 0.064730767 | N19: Recurring Net Income (attributable; excl. non-recurring & French exceptional contribution) | O19: 4855 | P19: 5119.7654 | Q19: 5639.9582 | R19: 6210.8102 | S19: 6810.036 | T19: 7406.9707 | U19: 0.08815379 | Z19: Recurring Net Income (attributable; excl. non-recurring & French exceptional contribution) | AA19: 4855 | AB19: 4704.3692 | AC19: 4730.3208 | AD19: 4998.5459 | AE19: 5257.5688 | AF19: 5480.6251 | AG19: 0.024538237
B21: FDSO (m) | C21: =Model!AV148 -> 105.0367 | D21: =Model!AY148 -> 105.00298 | E21: =Model!AZ148 -> 104.93355 | F21: =Model!BA148 -> 104.83964 | G21: =Model!BB148 -> 104.7571 | H21: =Model!BC148 -> 104.68519 | I21: =IFERROR((H21/C21)^(1/5)-1,"n/m") -> -0.00067020514 | N21: FDSO (m) | O21: 105.0367 | P21: 105.00298 | Q21: 104.59482 | R21: 104.2922 | S21: 104.01462 | T21: 103.76043 | U21: -0.0024420426 | Z21: FDSO (m) | AA21: 105.0367 | AB21: 105.00298 | AC21: 105.04395 | AD21: 105.08916 | AE21: 105.13666 | AF21: 105.18627 | AG21: 0.00028463403
B23: Recurring EPS — Diluted (€) | C23: =Model!AV191 -> 46.221938 | D23: =Model!AY191 -> 47.233986 | E23: =Model!AZ191 -> 50.432298 | F23: =Model!BA191 -> 54.783395 | G23: =Model!BB191 -> 59.220794 | H23: =Model!BC191 -> 63.460427 | I23: =IFERROR((H23/C23)^(1/5)-1,"n/m") -> 0.065444833 | N23: Recurring EPS — Diluted (€) | O23: 46.221938 | P23: 48.758288 | Q23: 53.921967 | R23: 59.552009 | S23: 65.471911 | T23: 71.385311 | U23: 0.090817613 | Z23: Recurring EPS — Diluted (€) | AA23: 46.221938 | AB23: 44.802246 | AC23: 45.031827 | AD23: 47.564808 | AE23: 50.007001 | AF23: 52.103995 | AG23: 0.024246702
B24: EPS y/y % | D24: =IFERROR(D23/C23-1,"") -> 0.0218954 | E24: =IFERROR(E23/D23-1,"") -> 0.067712096 | F24: =IFERROR(F23/E23-1,"") -> 0.086276001 | G24: =IFERROR(G23/F23-1,"") -> 0.080998983 | H24: =IFERROR(H23/G23-1,"") -> 0.071590267 | N24: EPS y/y % | P24: 0.054873296 | Q24: 0.10590363 | R24: 0.10441091 | S24: 0.099407257 | T24: 0.090319658 | Z24: EPS y/y % | AB24: -0.03071468 | AC24: 0.0051243191 | AD24: 0.056248698 | AE24: 0.051344534 | AF24: 0.041933991
B26: P / E (x) — assumed (recurring EPS) | F26: 34 | G26: =F26 -> 34 | H26: =G26 -> 34 | N26: P / E (x) — assumed (recurring EPS) | R26: 42 | S26: =R26 -> 42 | T26: =S26 -> 42 | Z26: P / E (x) — assumed (recurring EPS) | AD26: 27 | AE26: =AD26 -> 27 | AF26: =AE26 -> 27
B27: Price Target (€) | F27: =F26*F23 -> 1862.6354 | G27: =G26*G23 -> 2013.507 | H27: =H26*H23 -> 2157.6545 | N27: Price Target (€) | R27: =R26*R23 -> 2501.1844 | S27: =S26*S23 -> 2749.8202 | T27: =T26*T23 -> 2998.1831 | Z27: Price Target (€) | AD27: =AD26*AD23 -> 1284.2498 | AE27: =AE26*AE23 -> 1350.189 | AF27: =AF26*AF23 -> 1406.8079
B28: Upside / (Downside) vs current | F28: =IFERROR(F27/$K$2-1,"") -> 0.43334777 | G28: =IFERROR(G27/$K$2-1,"") -> 0.54944748 | H28: =IFERROR(H27/$K$2-1,"") -> 0.66037284 | N28: Upside / (Downside) vs current | R28: =IFERROR(R27/$K$2-1,"") -> 0.92472826 | S28: =IFERROR(S27/$K$2-1,"") -> 1.1160602 | T28: =IFERROR(T27/$K$2-1,"") -> 1.3071821 | Z28: Upside / (Downside) vs current | AD28: =IFERROR(AD27/$K$2-1,"") -> -0.011735415 | AE28: =IFERROR(AE27/$K$2-1,"") -> 0.039006569 | AF28: =IFERROR(AF27/$K$2-1,"") -> 0.082576261
B29: IRR (to Dec-Y-1) | F29: =IFERROR((F27/$K$2)^(1/((DATE(2028-1,12,31)-$K$3)/365.25))-1,"") -> 0.33679536 | G29: =IFERROR((G27/$K$2)^(1/((DATE(2029-1,12,31)-$K$3)/365.25))-1,"") -> 0.2156633 | H29: =IFERROR((H27/$K$2)^(1/((DATE(2030-1,12,31)-$K$3)/365.25))-1,"") -> 0.16931314 | N29: IRR (to Dec-Y-1) | R29: =IFERROR((R27/$K$2)^(1/((DATE(2028-1,12,31)-$K$3)/365.25))-1,"") -> 0.69544856 | S29: =IFERROR((S27/$K$2)^(1/((DATE(2029-1,12,31)-$K$3)/365.25))-1,"") -> 0.39693423 | T29: =IFERROR((T27/$K$2)^(1/((DATE(2030-1,12,31)-$K$3)/365.25))-1,"") -> 0.2942151 | Z29: IRR (to Dec-Y-1) | AD29: =IFERROR((AD27/$K$2)^(1/((DATE(2028-1,12,31)-$K$3)/365.25))-1,"") -> -0.0094729698 | AE29: =IFERROR((AE27/$K$2)^(1/((DATE(2029-1,12,31)-$K$3)/365.25))-1,"") -> 0.017211524 | AF29: =IFERROR((AF27/$K$2)^(1/((DATE(2030-1,12,31)-$K$3)/365.25))-1,"") -> 0.024778581
B31: Adjusted Free Cash Flow | C31: =Model!AV239 -> 3881 | D31: =Model!AY239 -> 4263.1903 | E31: =Model!AZ239 -> 4623.7066 | F31: =Model!BA239 -> 5160.6671 | G31: =Model!BB239 -> 5627.1425 | H31: =Model!BC239 -> 6071.4717 | I31: =IFERROR((H31/C31)^(1/5)-1,"n/m") -> 0.093629123 | N31: Adjusted Free Cash Flow | O31: 3881 | P31: 4425.6071 | Q31: 4945.7078 | R31: 5567.5773 | S31: 6159.911 | T31: 6748.2488 | U31: 0.11699052 | Z31: Adjusted Free Cash Flow | AA31: 3881 | AB31: 4001.5519 | AC31: 4090.876 | AD31: 4501.4977 | AE31: 4781.842 | AF31: 5024.3371 | AG31: 0.052996739
B32: FCF % | C32: =IFERROR(C31/C9,"") -> 0.24253218 | D32: =IFERROR(D31/D9,"") -> 0.25983988 | E32: =IFERROR(E31/E9,"") -> 0.26231807 | F32: =IFERROR(F31/F9,"") -> 0.27238624 | G32: =IFERROR(G31/G9,"") -> 0.277097 | H32: =IFERROR(H31/H9,"") -> 0.28009099 | J32: =IFERROR(AVERAGE(Model!C244,Model!D244,Model!E244,Model!F244,Model!G244,Model!H244,Model!I244,Model!L244,Model!O244,Model!R244,Model!U244,Model!X244,Model!AA244,Model!AD244,Model!AG244,Model!AJ244,Model!AM244,Model!AP244,Model!AS244,Model!AV244),"") -> 0.21365323 | K32: =IFERROR(MIN(Model!C244,Model!D244,Model!E244,Model!F244,Model!G244,Model!H244,Model!I244,Model!L244,Model!O244,Model!R244,Model!U244,Model!X244,Model!AA244,Model!AD244,Model!AG244,Model!AJ244,Model!AM244,Model!AP244,Model!AS244,Model!AV244),"") -> 0.13566317 | L32: =IFERROR(MAX(Model!C244,Model!D244,Model!E244,Model!F244,Model!G244,Model!H244,Model!I244,Model!L244,Model!O244,Model!R244,Model!U244,Model!X244,Model!AA244,Model!AD244,Model!AG244,Model!AJ244,Model!AM244,Model!AP244,Model!AS244,Model!AV244),"") -> 0.29625919 | N32: FCF % | O32: 0.24253218 | P32: 0.26586562 | Q32: 0.27150494 | R32: 0.2791618 | S32: 0.28288271 | T32: 0.28499027 | V32: 0.21365323 | W32: 0.13566317 | X32: 0.29625919 | Z32: FCF % | AA32: 0.24253218 | AB32: 0.2499628 | AC32: 0.24469399 | AD32: 0.25768498 | AE32: 0.26272976 | AF32: 0.26608574 | AH32: 0.21365323 | AI32: 0.13566317 | AJ32: 0.29625919
B33: FCF / share (€) | C33: =IFERROR(C31/C21,"") -> 36.948989 | D33: =IFERROR(D31/D21,"") -> 40.600661 | E33: =IFERROR(E31/E21,"") -> 44.063186 | F33: =IFERROR(F31/F21,"") -> 49.22439 | G33: =IFERROR(G31/G21,"") -> 53.716097 | H33: =IFERROR(H31/H21,"") -> 57.997425 | N33: FCF / share (€) | O33: 36.948989 | P33: 42.147444 | Q33: 47.284446 | R33: 53.384406 | S33: 59.221588 | T33: 65.036822 | Z33: FCF / share (€) | AA33: 36.948989 | AB33: 38.108938 | AC33: 38.944425 | AD33: 42.835033 | AE33: 45.482158 | AF33: 47.766091
B34: FCF Yield (on PT) | F34: =IFERROR(F33/F$27,"") -> 0.026427281 | G34: =IFERROR(G33/G$27,"") -> 0.02667788 | H34: =IFERROR(H33/H$27,"") -> 0.026879848 | N34: FCF Yield (on PT) | R34: =IFERROR(R33/R$27,"") -> 0.021343651 | S34: =IFERROR(S33/S$27,"") -> 0.021536531 | T34: =IFERROR(T33/T$27,"") -> 0.021692078 | Z34: FCF Yield (on PT) | AD34: =IFERROR(AD33/AD$27,"") -> 0.033354128 | AE34: =IFERROR(AE33/AE$27,"") -> 0.033685771 | AF34: =IFERROR(AF33/AF$27,"") -> 0.033953529
B35: EBITDA (IFRS 16) | C35: =Model!AV171 -> 7495 | D35: =Model!AY171 -> 7661.5326 | E35: =Model!AZ171 -> 8217.0823 | F35: =Model!BA171 -> 8894.4554 | G35: =Model!BB171 -> 9579.8088 | H35: =Model!BC171 -> 10232.524 | I35: =IFERROR((H35/C35)^(1/5)-1,"n/m") -> 0.064246484 | N35: EBITDA (IFRS 16) | O35: 7495 | P35: 7893.7166 | Q35: 8752.541 | R35: 9642.9593 | S35: 10573.749 | T35: 11501.601 | U35: 0.089424988 | Z35: EBITDA (IFRS 16) | AA35: 7495 | AB35: 7290.4953 | AC35: 7395.0681 | AD35: 7792.0163 | AE35: 8166.1893 | AF35: 8483.4445 | AG35: 0.025085563
B36: EBITDA margin % | C36: =IFERROR(C35/C9,"") -> 0.46837895 | D36: =IFERROR(D35/D9,"") -> 0.46696759 | E36: =IFERROR(E35/E9,"") -> 0.46618209 | F36: =IFERROR(F35/F9,"") -> 0.46946009 | G36: =IFERROR(G35/G9,"") -> 0.47173787 | H36: =IFERROR(H35/H9,"") -> 0.47204991 | J36: =IFERROR(AVERAGE(Model!C204,Model!D204,Model!E204,Model!F204,Model!G204,Model!H204,Model!I204,Model!L204,Model!O204,Model!R204,Model!U204,Model!X204,Model!AA204,Model!AD204,Model!AG204,Model!AJ204,Model!AM204,Model!AP204,Model!AS204,Model!AV204),"") -> 0.39326349 | K36: =IFERROR(MIN(Model!C204,Model!D204,Model!E204,Model!F204,Model!G204,Model!H204,Model!I204,Model!L204,Model!O204,Model!R204,Model!U204,Model!X204,Model!AA204,Model!AD204,Model!AG204,Model!AJ204,Model!AM204,Model!AP204,Model!AS204,Model!AV204),"") -> 0.28595309 | L36: =IFERROR(MAX(Model!C204,Model!D204,Model!E204,Model!F204,Model!G204,Model!H204,Model!I204,Model!L204,Model!O204,Model!R204,Model!U204,Model!X204,Model!AA204,Model!AD204,Model!AG204,Model!AJ204,Model!AM204,Model!AP204,Model!AS204,Model!AV204),"") -> 0.47821554 | N36: EBITDA margin % | O36: 0.46837895 | P36: 0.47421016 | Q36: 0.48048899 | R36: 0.48350399 | S36: 0.48558018 | T36: 0.4857326 | V36: 0.39326349 | W36: 0.28595309 | X36: 0.47821554 | Z36: EBITDA margin % | AA36: 0.46837895 | AB36: 0.45541145 | AC36: 0.44233282 | AD36: 0.44604834 | AE36: 0.44867667 | AF36: 0.4492779 | AH36: 0.39326349 | AI36: 0.28595309 | AJ36: 0.47821554
B38: Net Debt (negative = net cash) | C38: =Model!AV372 -> -12773 | D38: =Model!AY372 -> -14747.19 | E38: =Model!AZ372 -> -17014.568 | F38: =Model!BA372 -> -19684.598 | G38: =Model!BB372 -> -22638.525 | H38: =Model!BC372 -> -25850.743 | N38: Net Debt (negative = net cash) | O38: -12773 | P38: -13609.607 | Q38: -14582.961 | R38: -15940.028 | S38: -17630.095 | T38: -19636.41 | Z38: Net Debt (negative = net cash) | AA38: -12773 | AB38: -14535.552 | AC38: -16574.154 | AD38: -19011.611 | AE38: -21620.979 | AF38: -24368.262
B39: Net Debt / EBITDA (x) | C39: =IFERROR(C38/C35,"") -> -1.7042028 | D39: =IFERROR(D38/D35,"") -> -1.9248355 | E39: =IFERROR(E38/E35,"") -> -2.0706337 | F39: =IFERROR(F38/F35,"") -> -2.2131314 | G39: =IFERROR(G38/G35,"") -> -2.36315 | H39: =IFERROR(H38/H35,"") -> -2.5263312 | N39: Net Debt / EBITDA (x) | O39: -1.7042028 | P39: -1.7241064 | Q39: -1.6661403 | R39: -1.6530225 | S39: -1.6673457 | T39: -1.7072762 | Z39: Net Debt / EBITDA (x) | AA39: -1.7042028 | AB39: -1.9937674 | AC39: -2.2412443 | AD39: -2.4398834 | AE39: -2.6476216 | AF39: -2.8724491
B41: ROIC | C41: =Model!AV351 -> 0.56005017 | D41: =Model!AY351 -> 0.52135649 | E41: =Model!AZ351 -> 0.4939499 | F41: =Model!BA351 -> 0.48481987 | G41: =Model!BB351 -> 0.47690758 | H41: =Model!BC351 -> 0.46788245 | J41: =IFERROR(AVERAGE(Model!C351,Model!D351,Model!E351,Model!F351,Model!G351,Model!H351,Model!I351,Model!L351,Model!O351,Model!R351,Model!U351,Model!X351,Model!AA351,Model!AD351,Model!AG351,Model!AJ351,Model!AM351,Model!AP351,Model!AS351,Model!AV351),"") -> 0.51955545 | K41: =IFERROR(MIN(Model!C351,Model!D351,Model!E351,Model!F351,Model!G351,Model!H351,Model!I351,Model!L351,Model!O351,Model!R351,Model!U351,Model!X351,Model!AA351,Model!AD351,Model!AG351,Model!AJ351,Model!AM351,Model!AP351,Model!AS351,Model!AV351),"") -> 0.2529689 | L41: =IFERROR(MAX(Model!C351,Model!D351,Model!E351,Model!F351,Model!G351,Model!H351,Model!I351,Model!L351,Model!O351,Model!R351,Model!U351,Model!X351,Model!AA351,Model!AD351,Model!AG351,Model!AJ351,Model!AM351,Model!AP351,Model!AS351,Model!AV351),"") -> 0.73200514 | N41: ROIC | O41: 0.56005017 | P41: 0.53897284 | Q41: 0.52687695 | R41: 0.52226192 | S41: 0.51852656 | T41: 0.51329395 | V41: 0.51955545 | W41: 0.2529689 | X41: 0.73200514 | Z41: ROIC | AA41: 0.56005017 | AB41: 0.49317615 | AC41: 0.44225992 | AD41: 0.42740684 | AE41: 0.41421831 | AF41: 0.40045195 | AH41: 0.51955545 | AI41: 0.2529689 | AJ41: 0.73200514
B42: RONTA | C42: =Model!AV364 -> 0.52877161 | D42: =Model!AY364 -> 0.4946952 | E42: =Model!AZ364 -> 0.47132623 | F42: =Model!BA364 -> 0.46460553 | G42: =Model!BB364 -> 0.45868199 | H42: =Model!BC364 -> 0.45139731 | J42: =IFERROR(AVERAGE(Model!C364,Model!D364,Model!E364,Model!F364,Model!G364,Model!H364,Model!I364,Model!L364,Model!O364,Model!R364,Model!U364,Model!X364,Model!AA364,Model!AD364,Model!AG364,Model!AJ364,Model!AM364,Model!AP364,Model!AS364,Model!AV364),"") -> 0.47015029 | K42: =IFERROR(MIN(Model!C364,Model!D364,Model!E364,Model!F364,Model!G364,Model!H364,Model!I364,Model!L364,Model!O364,Model!R364,Model!U364,Model!X364,Model!AA364,Model!AD364,Model!AG364,Model!AJ364,Model!AM364,Model!AP364,Model!AS364,Model!AV364),"") -> 0.23289532 | L42: =IFERROR(MAX(Model!C364,Model!D364,Model!E364,Model!F364,Model!G364,Model!H364,Model!I364,Model!L364,Model!O364,Model!R364,Model!U364,Model!X364,Model!AA364,Model!AD364,Model!AG364,Model!AJ364,Model!AM364,Model!AP364,Model!AS364,Model!AV364),"") -> 0.63300388 | N42: RONTA | O42: 0.52877161 | P42: 0.5114037 | Q42: 0.50285398 | R42: 0.50075687 | S42: 0.49912662 | T42: 0.49575284 | V42: 0.47015029 | W42: 0.23289532 | X42: 0.63300388 | Z42: RONTA | AA42: 0.52877161 | AB42: 0.46797079 | AC42: 0.42188613 | AD42: 0.40927005 | AE42: 0.39790155 | AF42: 0.3857128 | AH42: 0.47015029 | AI42: 0.23289532 | AJ42: 0.63300388
B44: Implied Market Cap (EURm) | F44: =F27*F21 -> 195278.02 | G44: =G27*G21 -> 210929.15 | H44: =H27*H21 -> 225874.48 | N44: Implied Market Cap (EURm) | R44: =R27*R21 -> 260854.03 | S44: =S27*S21 -> 286021.51 | T44: =T27*T21 -> 311092.77 | Z44: Implied Market Cap (EURm) | AD44: =AD27*AD21 -> 134960.74 | AE44: =AE27*AE21 -> 141954.36 | AF44: =AF27*AF21 -> 147976.88
B45: (+) Net Debt & NCI | F45: =F38+Model!BA383 -> -19678.598 | G45: =G38+Model!BB383 -> -22632.525 | H45: =H38+Model!BC383 -> -25844.743 | N45: (+) Net Debt & NCI | R45: =R38+Model!BA383 -> -15934.028 | S45: =S38+Model!BB383 -> -17624.095 | T45: =T38+Model!BC383 -> -19630.41 | Z45: (+) Net Debt & NCI | AD45: =AD38+Model!BA383 -> -19005.611 | AE45: =AE38+Model!BB383 -> -21614.979 | AF45: =AF38+Model!BC383 -> -24362.262
B46: Implied Enterprise Value (EURm) | F46: =F44+F45 -> 175599.42 | G46: =G44+G45 -> 188296.63 | H46: =H44+H45 -> 200029.74 | N46: Implied Enterprise Value (EURm) | R46: =R44+R45 -> 244920 | S46: =S44+S45 -> 268397.42 | T46: =T44+T45 -> 291462.36 | Z46: Implied Enterprise Value (EURm) | AD46: =AD44+AD45 -> 115955.13 | AE46: =AE44+AE45 -> 120339.38 | AF46: =AF44+AF45 -> 123614.61
B47: Implied EV / EBITDA (x) | F47: =IFERROR(F46/F35,"") -> 19.742571 | G47: =IFERROR(G46/G35,"") -> 19.655573 | H47: =IFERROR(H46/H35,"") -> 19.548427 | N47: Implied EV / EBITDA (x) | R47: =IFERROR(R46/R35,"") -> 25.398842 | S47: =IFERROR(S46/S35,"") -> 25.383374 | T47: =IFERROR(T46/T35,"") -> 25.341025 | Z47: Implied EV / EBITDA (x) | AD47: =IFERROR(AD46/AD35,"") -> 14.881274 | AE47: =IFERROR(AE46/AE35,"") -> 14.736296 | AF47: =IFERROR(AF46/AF35,"") -> 14.571276

Sheet DCF
B2: DCF VALUATION — HERMÈS INTERNATIONAL (RMS)
B4: 1. WACC BUILD
B5: Risk-free rate (EUR 10Y govt) | C5: 0.03 | D5: Assumption (~blend of 10Y Bund / OAT yields); update to market
B6: Equity risk premium | C6: 0.055 | D6: Euro-area implied ERP ~5–6% (Damodaran)
B7: Levered beta | C7: 0.9 | D7: Luxury peers (LVMH, Kering, Richemont, Prada) ~0.9–1.2; Hermès' pricing power and family-controlled shareholder base dampen cyclicality
B8: Cost of equity | C8: =C5+C7*C6 -> 0.0795
B9: Pre-tax cost of debt | C9: 0.035 | D9: No financial debt (net cash €12.9bn at 30-Jun-26); notional IG euro cost
B10: Tax rate | C10: 0.285 | D10: Model 2027E+ effective tax rate (excl. the French exceptional contribution)
B11: After-tax cost of debt | C11: =C9*(1-C10) -> 0.025025
B12: Target D/V | C12: 0 | D12: Net cash balance sheet; lease liabilities (~€2.3bn) treated as operating (ROU depreciation kept in EBIT)
B13: WACC | C13: =C8*(1-C12)+C11*C12 -> 0.0795
B15: Valuation date (live) | C15: =TODAY() -> 46299 | D15: Periods = (Dec-31-Year − today) / 365.25; cash flows assumed at year-end
B16: 2. UNLEVERED FREE CASH FLOW BUILD (EURm)
D17: 2026E | E17: 2027E | F17: 2028E | G17: 2029E | H17: 2030E | I17: 2031E | J17: 2032E | K17: 2033E | L17: 2034E | M17: 2035E | N17: Terminal
B18: Recurring operating income = adjusted EBIT (Model) | D18: =Model!AY124 -> 6664.084 | E18: =Model!AZ124 -> 7138.6662 | F18: =Model!BA124 -> 7730.024 | G18: =Model!BB124 -> 8326.068 | H18: =Model!BC124 -> 8887.4811 | I18: =H18*(1+I$31) -> 9509.6048 | J18: =I18*(1+J$31) -> 10115.842 | K18: =J18*(1+K$31) -> 10697.503 | L18: =K18*(1+L$31) -> 11245.75 | M18: =L18*(1+M$31) -> 11751.809
B19: y/y % | E19: =IFERROR(E18/D18-1,"") -> 0.071214928 | F19: =IFERROR(F18/E18-1,"") -> 0.082838696 | G19: =IFERROR(G18/F18-1,"") -> 0.077107644 | H19: =IFERROR(H18/G18-1,"") -> 0.067428365 | I19: =IFERROR(I18/H18-1,"") -> 0.07 | J19: =IFERROR(J18/I18-1,"") -> 0.06375 | K19: =IFERROR(K18/J18-1,"") -> 0.0575 | L19: =IFERROR(L18/K18-1,"") -> 0.05125 | M19: =IFERROR(M18/L18-1,"") -> 0.045
B20: (+) Non-recurring items (Model; nil in forecast) | D20: =Model!AY126 -> 0 | E20: =Model!AZ126 -> 0 | F20: =Model!BA126 -> 0 | G20: =Model!BB126 -> 0 | H20: =Model!BC126 -> 0 | I20: =H20*(1+I$31) -> 0 | J20: =I20*(1+J$31) -> 0 | K20: =J20*(1+K$31) -> 0 | L20: =K20*(1+L$31) -> 0 | M20: =L20*(1+M$31) -> 0
B21: × (1 − tax rate) | D21: =1-$C$10 -> 0.715 | E21: =1-$C$10 -> 0.715 | F21: =1-$C$10 -> 0.715 | G21: =1-$C$10 -> 0.715 | H21: =1-$C$10 -> 0.715 | I21: =1-$C$10 -> 0.715 | J21: =1-$C$10 -> 0.715 | K21: =1-$C$10 -> 0.715 | ... M21: =1-$C$10 -> 0.715
B22: NOPAT = (Adjusted EBIT + non-recurring) × (1 − t) | D22: =(D18+D20)*D21 -> 4764.82 | E22: =(E18+E20)*E21 -> 5104.1464 | F22: =(F18+F20)*F21 -> 5526.9672 | G22: =(G18+G20)*G21 -> 5953.1386 | H22: =(H18+H20)*H21 -> 6354.549 | I22: =(I18+I20)*I21 -> 6799.3674 | J22: =(J18+J20)*J21 -> 7232.8271 | K22: =(K18+K20)*K21 -> 7648.7147 | ... M22: =(M18+M20)*M21 -> 8402.5433
B23: plus D&A of PP&E and intangibles (ROU depreciation kept in EBIT as lease-cost proxy) | D23: =Model!AY144 -> 607.05863 | E23: =Model!AZ144 -> 652.17445 | F23: =Model!BA144 -> 701.00708 | G23: =Model!BB144 -> 751.37687 | H23: =Model!BC144 -> 802.04098 | I23: =H23*(1+I$31) -> 858.18385 | J23: =I23*(1+J$31) -> 912.89307 | K23: =J23*(1+K$31) -> 965.38442 | L23: =K23*(1+L$31) -> 1014.8604 | M23: =L23*(1+M$31) -> 1060.5291
B24: − Operating investments and acquisitions | D24: =D29+Model!AY219 -> -1198 | E24: =E29+Model!AZ219 -> -1233.8435 | F24: =F29+Model!BA219 -> -1288.3373 | G24: =G29+Model!BB219 -> -1340.2939 | H24: =H29+Model!BC219 -> -1387.3141 | I24: =I29 -> -1484.4261 | J24: =J29 -> -1579.0583 | K24: =K29 -> -1669.8541 | L24: =L29 -> -1755.4342 | M24: =M29 -> -1834.4287
B25: − Δ Working capital (CF statement) | D25: =Model!AY215 -> 79.61064 | E25: =Model!AZ215 -> -207.79354 | F25: =Model!BA215 -> -127.69377 | G25: =Model!BB215 -> -131.43529 | H25: =Model!BC215 -> -141.75562 | I25: =H25*(1+I$31) -> -151.67851 | J25: =I25*(1+J$31) -> -161.34801 | K25: =J25*(1+K$31) -> -170.62552 | L25: =K25*(1+L$31) -> -179.37008 | M25: =L25*(1+M$31) -> -187.44174
B26: Unlevered FCF | D26: =D22+D23+D24+D25 -> 4253.4893 | E26: =E22+E23+E24+E25 -> 4314.6837 | F26: =F22+F23+F24+F25 -> 4811.9432 | G26: =G22+G23+G24+G25 -> 5232.7863 | H26: =H22+H23+H24+H25 -> 5627.5203 | I26: =I22+I23+I24+I25 -> 6021.4467 | J26: =J22+J23+J24+J25 -> 6405.3139 | K26: =K22+K23+K24+K25 -> 6773.6194 | ... M26: =M22+M23+M24+M25 -> 7441.202 | N26: =M26*(1+$C$32) -> 7664.438
B27: y/y % | E27: =IFERROR(E26/D26-1,"") -> 0.014386871 | F27: =IFERROR(F26/E26-1,"") -> 0.11524818 | G27: =IFERROR(G26/F26-1,"") -> 0.087458047 | H27: =IFERROR(H26/G26-1,"") -> 0.07543475 | I27: =IFERROR(I26/H26-1,"") -> 0.07 | J27: =IFERROR(J26/I26-1,"") -> 0.06375 | K27: =IFERROR(K26/J26-1,"") -> 0.0575 | L27: =IFERROR(L26/K26-1,"") -> 0.05125 | M27: =IFERROR(M26/L26-1,"") -> 0.045
B28: Terminal Value (Gordon Growth) | N28: =N26/($C$13-$C$32) -> 154837.13
B29: memo: operating investments only (fade years carry no acquisitions) | D29: =Model!AY218 -> -1150 | E29: =Model!AZ218 -> -1233.8435 | F29: =Model!BA218 -> -1288.3373 | G29: =Model!BB218 -> -1340.2939 | H29: =Model!BC218 -> -1387.3141 | I29: =H29*(1+I$31) -> -1484.4261 | J29: =I29*(1+J$31) -> -1579.0583 | K29: =J29*(1+K$31) -> -1669.8541 | L29: =K29*(1+L$31) -> -1755.4342 | M29: =L29*(1+M$31) -> -1834.4287
B31: Fade-period growth (2031E–35E) | I31: 0.07 | J31: =I31+($M$31-$I$31)/(COLUMNS($I$31:$M$31)-1) -> 0.06375 | K31: =J31+($M$31-$I$31)/(COLUMNS($I$31:$M$31)-1) -> 0.0575 | L31: =K31+($M$31-$I$31)/(COLUMNS($I$31:$M$31)-1) -> 0.05125 | M31: 0.045
B32: Terminal growth rate | C32: 0.03
B34: Discount period (years) | D34: =(DATE(2026,12,31)-$C$15)/365.25 -> 0.24093087 | E34: =(DATE(2027,12,31)-$C$15)/365.25 -> 1.2402464 | F34: =(DATE(2028,12,31)-$C$15)/365.25 -> 2.2422998 | G34: =(DATE(2029,12,31)-$C$15)/365.25 -> 3.2416153 | H34: =(DATE(2030,12,31)-$C$15)/365.25 -> 4.2409309 | I34: =(DATE(2031,12,31)-$C$15)/365.25 -> 5.2402464 | J34: =(DATE(2032,12,31)-$C$15)/365.25 -> 6.2422998 | K34: =(DATE(2033,12,31)-$C$15)/365.25 -> 7.2416153 | L34: =(DATE(2034,12,31)-$C$15)/365.25 -> 8.2409309 | M34: =(DATE(2035,12,31)-$C$15)/365.25 -> 9.2402464 | N34: =M34 -> 9.2402464
B35: Discount factor | D35: =1/(1+$C$13)^D34 -> 0.98173808 | E35: =1/(1+$C$13)^E34 -> 0.9094854 | F35: =1/(1+$C$13)^F34 -> 0.84237383 | G35: =1/(1+$C$13)^G34 -> 0.7803779 | H35: =1/(1+$C$13)^H34 -> 0.72294466 | I35: =1/(1+$C$13)^I34 -> 0.66973832 | J35: =1/(1+$C$13)^J34 -> 0.62031785 | K35: =1/(1+$C$13)^K34 -> 0.5746645 | ... N35: =1/(1+$C$13)^N34 -> 0.49319034
B36: PV of UFCF | D36: =D26*D35 -> 4175.8125 | E36: =E26*E35 -> 3924.1418 | F36: =F26*F35 -> 4053.455 | G36: =G26*G35 -> 4083.5508 | H36: =H26*H35 -> 4068.3857 | I36: =I26*I35 -> 4032.7935 | J36: =J26*J35 -> 3973.3306 | K36: =K26*K35 -> 3892.5587 | ... M36: =M26*M35 -> 3669.9289 | N36: =N28*N35 -> 76364.177
D37: Recurring operating income expenses free-share plans and right-of-use depreciation (a proxy for lease payments, so lease liabilities are not deducted as debt below). 2026E UFCF is the full calendar year (H1/26 actual + H2/26E); the 2026E column is discounted to 31-Dec-26.
B39: Implied ROIC & incremental ROIC (EURm) | D39: =D17 -> 2026E | E39: =E17 -> 2027E | F39: =F17 -> 2028E | G39: =G17 -> 2029E | H39: =H17 -> 2030E | I39: =I17 -> 2031E | J39: =J17 -> 2032E | K39: =K17 -> 2033E | ... M39: =M17 -> 2035E
B40: NOPAT (row 22) | D40: =D22 -> 4764.82 | E40: =E22 -> 5104.1464 | F40: =F22 -> 5526.9672 | G40: =G22 -> 5953.1386 | H40: =H22 -> 6354.549 | I40: =I22 -> 6799.3674 | J40: =J22 -> 7232.8271 | K40: =K22 -> 7648.7147 | ... M40: =M22 -> 8402.5433
B41: Net investment = NOPAT − UFCF | D41: =D40-D26 -> 511.33073 | E41: =E40-E26 -> 789.46264 | F41: =F40-F26 -> 715.02402 | G41: =G40-G26 -> 720.35229 | H41: =H40-H26 -> 727.02876 | I41: =I40-I26 -> 777.92078 | J41: =J40-J26 -> 827.51323 | K41: =K40-K26 -> 875.09524 | ... M41: =M40-M26 -> 961.34134
B42: Opening invested capital | D42: =Model!AV349 -> 8385 | E42: =D43 -> 8896.3307 | F42: =E43 -> 9685.7934 | G42: =F43 -> 10400.817 | H42: =G43 -> 11121.17 | I42: =H43 -> 11848.198 | J42: =I43 -> 12626.119 | K42: =J43 -> 13453.632 | L42: =K43 -> 14328.728 | M42: =L43 -> 15248.672
B43: Closing invested capital | D43: =D42+D41 -> 8896.3307 | E43: =E42+E41 -> 9685.7934 | F43: =F42+F41 -> 10400.817 | G43: =G42+G41 -> 11121.17 | H43: =H42+H41 -> 11848.198 | I43: =I42+I41 -> 12626.119 | J43: =J42+J41 -> 13453.632 | K43: =K42+K41 -> 14328.728 | ... M43: =M42+M41 -> 16210.013
B44: Implied ROIC = NOPAT / opening IC | D44: =IFERROR(D40/D42,"") -> 0.56825522 | E44: =IFERROR(E40/E42,"") -> 0.57373613 | F44: =IFERROR(F40/F42,"") -> 0.57062617 | G44: =IFERROR(G40/G42,"") -> 0.57237219 | H44: =IFERROR(H40/H42,"") -> 0.57139215 | I44: =IFERROR(I40/I42,"") -> 0.57387353 | J44: =IFERROR(J40/J42,"") -> 0.57284641 | K44: =IFERROR(K40/K42,"") -> 0.56852413 | ... M44: =IFERROR(M40/M42,"") -> 0.55103445
B45: Reinvestment rate = net inv. / NOPAT | D45: =IFERROR(D41/D40,"") -> 0.10731375 | E45: =IFERROR(E41/E40,"") -> 0.15467085 | F45: =IFERROR(F41/F40,"") -> 0.12937005 | G45: =IFERROR(G41/G40,"") -> 0.12100378 | H45: =IFERROR(H41/H40,"") -> 0.11441076 | I45: =IFERROR(I41/I40,"") -> 0.11441076 | J45: =IFERROR(J41/J40,"") -> 0.11441076 | K45: =IFERROR(K41/K40,"") -> 0.11441076 | ... M45: =IFERROR(M41/M40,"") -> 0.11441076
B46: Incremental ROIC = Δ NOPAT / prior-yr net inv. | E46: =IFERROR((E40-D40)/D41,"") -> 0.66361417 | F46: =IFERROR((F40-E40)/E41,"") -> 0.53558054 | G46: =IFERROR((G40-F40)/F41,"") -> 0.59602392 | H46: =IFERROR((H40-G40)/G41,"") -> 0.55724179 | I46: =IFERROR((I40-H40)/H41,"") -> 0.61183058 | J46: =IFERROR((J40-I40)/I41,"") -> 0.55720285 | K46: =IFERROR((K40-J40)/J41,"") -> 0.50257512 | L46: =IFERROR((L40-K40)/K41,"") -> 0.44794739 | M46: =IFERROR((M40-L40)/L41,"") -> 0.39331966
B47: Cumulative incremental ROIC 2026E–35E | C47: =IFERROR((M40-D40)/SUM(D41:L41),"") -> 0.5299967
D48: Opening IC = Model 2025A invested capital (equity + lease liabilities − restated net cash), rolled forward with net investment. Hermès' book IC is small relative to NOPAT (ROIC > 60%).
B49: 3. VALUATION SUMMARY
B50: Sum of PV (explicit + fade) | C50: =SUM(D36:M36) -> 39664.848
B51: PV of Terminal Value | C51: =N36 -> 76364.177
B52: Enterprise Value | C52: =C50+C51 -> 116029.03
B53: Less: net debt (Model 2026E YE; negative = net cash) | C53: =Model!AY372 -> -14747.19
B54: Less: non-controlling interests (Model 2026E) | C54: =Model!AY383 -> 6
B55: Equity Value | C55: =C52-C53-C54 -> 130770.22
B56: Diluted shares (m, Model 2026E) | C56: =Model!AY148 -> 105.00298
B57: Implied share price (€) | C57: =C55/C56 -> 1245.3953
B58: Current share price (€) | C58: =Model!AY379 -> 1299.5
B59: Implied upside / (downside) | C59: =C57/C58-1 -> -0.041635002
B60: Required discount to DCF value for target IRR (discount closes over horizon; value compounds at WACC) | C60: =1-((1+C13)/(1+F60))^F61 -> 0.10460663 | E60: Target IRR | F60: 0.12
B61: Max entry price for target IRR (€) — % vs. current share price shown right | C61: =C57*(1-C60) -> 1115.1187 | D61: =C61/C58-1 -> -0.14188634 | E61: Years for discount to close | F61: 3
B64: 4. SENSITIVITY: IMPLIED PRICE (€) — WACC × Terminal Growth
B65: WACC step (across) | C65: 0.005
B66: Terminal growth step (down) | C66: 0.005
B67: g (down) / WACC | D67: =E67-$C$65 -> 0.0695 | E67: =F67-$C$65 -> 0.0745 | F67: =$C$13 -> 0.0795 | G67: =F67+$C$65 -> 0.0845 | H67: =G67+$C$65 -> 0.0895
B68: =B69-$C$66 -> 0.02 | D68: =IFERROR((SUMPRODUCT($D$26:$M$26/(1+D$67)^$D$34:$M$34)+($M$26*(1+$B68)/(D$67-$B68))/(1+D$67)^$M$34-$C$53-$C$54)/$C$56,"") -> 1319.8821 | E68: =IFERROR((SUMPRODUCT($D$26:$M$26/(1+E$67)^$D$34:$M$34)+($M$26*(1+$B68)/(E$67-$B68))/(1+E$67)^$M$34-$C$53-$C$54)/$C$56,"") -> 1209.223 | F68: =IFERROR((SUMPRODUCT($D$26:$M$26/(1+F$67)^$D$34:$M$34)+($M$26*(1+$B68)/(F$67-$B68))/(1+F$67)^$M$34-$C$53-$C$54)/$C$56,"") -> 1117.2931 | G68: =IFERROR((SUMPRODUCT($D$26:$M$26/(1+G$67)^$D$34:$M$34)+($M$26*(1+$B68)/(G$67-$B68))/(1+G$67)^$M$34-$C$53-$C$54)/$C$56,"") -> 1039.7324 | H68: =IFERROR((SUMPRODUCT($D$26:$M$26/(1+H$67)^$D$34:$M$34)+($M$26*(1+$B68)/(H$67-$B68))/(1+H$67)^$M$34-$C$53-$C$54)/$C$56,"") -> 973.43571
B69: =B70-$C$66 -> 0.025 | D69: =IFERROR((SUMPRODUCT($D$26:$M$26/(1+D$67)^$D$34:$M$34)+($M$26*(1+$B69)/(D$67-$B69))/(1+D$67)^$M$34-$C$53-$C$54)/$C$56,"") -> 1412.3497 | E69: =IFERROR((SUMPRODUCT($D$26:$M$26/(1+E$67)^$D$34:$M$34)+($M$26*(1+$B69)/(E$67-$B69))/(1+E$67)^$M$34-$C$53-$C$54)/$C$56,"") -> 1281.8773 | F69: =IFERROR((SUMPRODUCT($D$26:$M$26/(1+F$67)^$D$34:$M$34)+($M$26*(1+$B69)/(F$67-$B69))/(1+F$67)^$M$34-$C$53-$C$54)/$C$56,"") -> 1175.468 | G69: =IFERROR((SUMPRODUCT($D$26:$M$26/(1+G$67)^$D$34:$M$34)+($M$26*(1+$B69)/(G$67-$B69))/(1+G$67)^$M$34-$C$53-$C$54)/$C$56,"") -> 1087.0513 | H69: =IFERROR((SUMPRODUCT($D$26:$M$26/(1+H$67)^$D$34:$M$34)+($M$26*(1+$B69)/(H$67-$B69))/(1+H$67)^$M$34-$C$53-$C$54)/$C$56,"") -> 1012.4394
B70: =$C$32 -> 0.03 | D70: =IFERROR((SUMPRODUCT($D$26:$M$26/(1+D$67)^$D$34:$M$34)+($M$26*(1+$B70)/(D$67-$B70))/(1+D$67)^$M$34-$C$53-$C$54)/$C$56,"") -> 1528.2267 | E70: =IFERROR((SUMPRODUCT($D$26:$M$26/(1+E$67)^$D$34:$M$34)+($M$26*(1+$B70)/(E$67-$B70))/(1+E$67)^$M$34-$C$53-$C$54)/$C$56,"") -> 1370.8584 | F70: =IFERROR((SUMPRODUCT($D$26:$M$26/(1+F$67)^$D$34:$M$34)+($M$26*(1+$B70)/(F$67-$B70))/(1+F$67)^$M$34-$C$53-$C$54)/$C$56,"") -> 1245.3953 | G70: =IFERROR((SUMPRODUCT($D$26:$M$26/(1+G$67)^$D$34:$M$34)+($M$26*(1+$B70)/(G$67-$B70))/(1+G$67)^$M$34-$C$53-$C$54)/$C$56,"") -> 1143.0526 | H70: =IFERROR((SUMPRODUCT($D$26:$M$26/(1+H$67)^$D$34:$M$34)+($M$26*(1+$B70)/(H$67-$B70))/(1+H$67)^$M$34-$C$53-$C$54)/$C$56,"") -> 1057.9983
B71: =B70+$C$66 -> 0.035 | D71: =IFERROR((SUMPRODUCT($D$26:$M$26/(1+D$67)^$D$34:$M$34)+($M$26*(1+$B71)/(D$67-$B71))/(1+D$67)^$M$34-$C$53-$C$54)/$C$56,"") -> 1677.6914 | E71: =IFERROR((SUMPRODUCT($D$26:$M$26/(1+E$67)^$D$34:$M$34)+($M$26*(1+$B71)/(E$67-$B71))/(1+E$67)^$M$34-$C$53-$C$54)/$C$56,"") -> 1482.3663 | F71: =IFERROR((SUMPRODUCT($D$26:$M$26/(1+F$67)^$D$34:$M$34)+($M$26*(1+$B71)/(F$67-$B71))/(1+F$67)^$M$34-$C$53-$C$54)/$C$56,"") -> 1331.0367 | G71: =IFERROR((SUMPRODUCT($D$26:$M$26/(1+G$67)^$D$34:$M$34)+($M$26*(1+$B71)/(G$67-$B71))/(1+G$67)^$M$34-$C$53-$C$54)/$C$56,"") -> 1210.3672 | H71: =IFERROR((SUMPRODUCT($D$26:$M$26/(1+H$67)^$D$34:$M$34)+($M$26*(1+$B71)/(H$67-$B71))/(1+H$67)^$M$34-$C$53-$C$54)/$C$56,"") -> 1111.9166
B72: =B71+$C$66 -> 0.04 | D72: =IFERROR((SUMPRODUCT($D$26:$M$26/(1+D$67)^$D$34:$M$34)+($M$26*(1+$B72)/(D$67-$B72))/(1+D$67)^$M$34-$C$53-$C$54)/$C$56,"") -> 1877.822 | E72: =IFERROR((SUMPRODUCT($D$26:$M$26/(1+E$67)^$D$34:$M$34)+($M$26*(1+$B72)/(E$67-$B72))/(1+E$67)^$M$34-$C$53-$C$54)/$C$56,"") -> 1626.1954 | F72: =IFERROR((SUMPRODUCT($D$26:$M$26/(1+F$67)^$D$34:$M$34)+($M$26*(1+$B72)/(F$67-$B72))/(1+F$67)^$M$34-$C$53-$C$54)/$C$56,"") -> 1438.3594 | G72: =IFERROR((SUMPRODUCT($D$26:$M$26/(1+G$67)^$D$34:$M$34)+($M$26*(1+$B72)/(G$67-$B72))/(1+G$67)^$M$34-$C$53-$C$54)/$C$56,"") -> 1292.8087 | H72: =IFERROR((SUMPRODUCT($D$26:$M$26/(1+H$67)^$D$34:$M$34)+($M$26*(1+$B72)/(H$67-$B72))/(1+H$67)^$M$34-$C$53-$C$54)/$C$56,"") -> 1176.7275
B75: 5. REVERSE DCF
B76: To solve for the market-implied path: Data ▸ What-If Analysis ▸ Goal Seek — set C57 (implied price) to the current price (C58) by changing C32 (terminal growth) or the Model scenario levers (métier constant-currency growth, recurring operating margin).
B78: 6. MAUBOUSSIN EV / NOPAT — TWO-STAGE FRAMEWORK
B79: EV/NOPAT = 1/r + [g × (1 − r/ROIIC) / (r × (r − g))] × [1 − ((1+g)/(1+r))^N]
B80: Formula source: Mauboussin & Rappaport, "Expectations Investing" (2021); Counterpoint Global, "What Does a Price-Earnings Multiple Mean?" (2020).
B82: Input | C82: Value | D82: Rationale (Hermès characteristics)
B83: r (Cost of capital / WACC) | C83: =$C$13 -> 0.0795 | D83: Linked from Section 1 WACC build
B84: g (NOPAT growth, Stage 1) | C84: 0.08 | D84: Model recurring operating income CAGR 2025–30E: high-single-digit constant-currency growth, stable ~41% margin
B85: ROIIC (Return on incremental invested capital) | C85: 0.4 | D85: Capacity growth (leather workshops, stores) earns very high returns: ROIC > 60% on book IC; incremental capex ~7% of sales
B86: N (Years of value creation / CAP) | C86: 20 | D86: Scarcity-driven brand (waitlists, controlled capacity), 190-year heritage, family control (H51 ~66%), vertical integration in craftsmanship
B88: Calculation | C88: Value
B89: Steady-state component: 1 / r | C89: =1/C83 -> 12.578616
B90: Value-creation factor: 1 − r / ROIIC | C90: =1-C83/C85 -> 0.80125
B91: Growth multiplier: g × (1 − r/ROIIC) / (r × (r − g)) | C91: =C84*C90/(C83*(C83-C84)) -> -1612.5786
B92: Time decay: 1 − ((1+g)/(1+r))^N | C92: =1-((1+C84)/(1+C83))^C86 -> -0.0093044228
B93: PVGO component (growth value) | C93: =C91*C92 -> 15.004113
B94: Mauboussin EV / NOPAT (steady-state + PVGO) | C94: =C89+C93 -> 27.58273
B96: VALUATION — Applied to 2028E NOPAT | C96: EURm
B97: 2028E recurring operating income (Model) | C97: =Model!BA124 -> 7730.024
B98: (+) 2028E non-recurring items | C98: =Model!BA126 -> 0
B99: Tax rate (from WACC build) | C99: =$C$10 -> 0.285
B100: 2028E NOPAT = (ROI + non-recurring) × (1 − t) | C100: =(C97+C98)*(1-C99) -> 5526.9672
B101: × Mauboussin EV/NOPAT multiple | C101: =C94 -> 27.58273
B102: Implied Enterprise Value (2028E basis) | C102: =C100*C101 -> 152448.84
B103: Less: YE2027 net debt + NCI (Model) | C103: =Model!AZ372+Model!AZ383 -> -17008.568
B104: Implied Equity Value | C104: =C102-C103 -> 169457.41
B105: Diluted shares 2028E (m, Model) | C105: =Model!BA148 -> 104.83964
B106: Implied share price 2028 (€) | C106: =C104/C105 -> 1616.3487
B108: Current share price (€) | C108: =C58 -> 1299.5
B109: Implied upside / (downside) | C109: =C106/C108-1 -> 0.24382355
B111: MARKET-IMPLIED EV/NOPAT TODAY | C111: EURm
B112: Current market cap (spot × diluted shares) | C112: =C58*C56 -> 136451.37
B113: Plus: YE2026 net debt & NCI | C113: =C53+C54 -> -14741.19
B114: Implied Enterprise Value (today) | C114: =C112+C113 -> 121710.18
B115: Hermès' market-implied EV/NOPAT (on 2028E NOPAT) | C115: =C114/C100 -> 22.021151
B117: Multiple gap (Mauboussin − Market) | C117: =C94-C115 -> 5.5615787
...

Sheet Charts
B2: Hermès International — Historical Operating Performance (2009–2025)
B3: All historicals · EURm · Linked to Model. Growth decomposition = revenue growth at constant exchange rates (company-reported) and the currency / scope effect (reported − constant). EBITDA = recurring operating income + all D&A (IFRS 16 from 2019). Charts start in 2009, the first year with full financial statements (2006–08: key figures only).
C7: 2009 | D7: 2010 | E7: 2011 | F7: 2012 | G7: 2013 | H7: 2014 | I7: 2015 | J7: 2016 | K7: 2017 | L7: 2018 | M7: 2019 | N7: 2020 | O7: 2021 | P7: 2022 | Q7: 2023 | R7: 2024 | S7: 2025
B8: Constant-currency growth % | C8: =IFERROR(Model!F63+0,0) -> 0 | D8: =IFERROR(Model!G63+0,0) -> 0.189 | E8: =IFERROR(Model!H63+0,0) -> 0.183 | F8: =IFERROR(Model!I63+0,0) -> 0.164 | G8: =IFERROR(Model!L63+0,0) -> 0.13 | H8: =IFERROR(Model!O63+0,0) -> 0.111 | I8: =IFERROR(Model!R63+0,0) -> 0.081 | J8: =IFERROR(Model!U63+0,0) -> 0.074 | K8: =IFERROR(Model!X63+0,0) -> 0.086 | L8: =IFERROR(Model!AA63+0,0) -> 0.104 | M8: =IFERROR(Model!AD63+0,0) -> 0.124 | N8: =IFERROR(Model!AG63+0,0) -> -0.06 | O8: =IFERROR(Model!AJ63+0,0) -> 0.418 | P8: =IFERROR(Model!AM63+0,0) -> 0.234 | Q8: =IFERROR(Model!AP63+0,0) -> 0.206 | R8: =IFERROR(Model!AS63+0,0) -> 0.147 | S8: =IFERROR(Model!AV63+0,0) -> 0.089
B9: Currency / scope effect % | C9: =IFERROR(Model!F64+0,0) -> 0 | D9: =IFERROR(Model!G64+0,0) -> 0.065963427 | E9: =IFERROR(Model!H64+0,0) -> 0.00018068276 | F9: =IFERROR(Model!I64+0,0) -> 0.061967628 | G9: =IFERROR(Model!L64+0,0) -> -0.052306412 | H9: =IFERROR(Model!O64+0,0) -> -0.014139897 | I9: =IFERROR(Model!R64+0,0) -> 0.094423688 | J9: =IFERROR(Model!U64+0,0) -> 0.00059048563 | K9: =IFERROR(Model!X64+0,0) -> -0.019316674 | L9: =IFERROR(Model!AA64+0,0) -> -0.028852679 | M9: =IFERROR(Model!AD64+0,0) -> 0.029752032 | N9: =IFERROR(Model!AG64+0,0) -> -0.011752332 | O9: =IFERROR(Model!AJ64+0,0) -> -0.012412708 | P9: =IFERROR(Model!AM64+0,0) -> 0.057726979 | Q9: =IFERROR(Model!AP64+0,0) -> -0.048599776 | R9: =IFERROR(Model!AS64+0,0) -> -0.017186937 | S9: =IFERROR(Model!AV64+0,0) -> -0.034220831
C11: =C7 -> 2009 | D11: =D7 -> 2010 | E11: =E7 -> 2011 | F11: =F7 -> 2012 | G11: =G7 -> 2013 | H11: =H7 -> 2014 | I11: =I7 -> 2015 | J11: =J7 -> 2016 | ... S11: =S7 -> 2025
B12: EBITDA | C12: =IFERROR(Model!F171+0,0) -> 547.4 | D12: =IFERROR(Model!G171+0,0) -> 769.1 | E12: =IFERROR(Model!H171+0,0) -> 998.4 | F12: =IFERROR(Model!I171+0,0) -> 1238.8 | G12: =IFERROR(Model!L171+0,0) -> 1356.7 | H12: =IFERROR(Model!O171+0,0) -> 1467.9 | I12: =IFERROR(Model!R171+0,0) -> 1747.2 | J12: =IFERROR(Model!U171+0,0) -> 1928.6 | K12: =IFERROR(Model!X171+0,0) -> 2165 | L12: =IFERROR(Model!AA171+0,0) -> 2305 | M12: =IFERROR(Model!AD171+0,0) -> 2815 | N12: =IFERROR(Model!AG171+0,0) -> 2549.9 | O12: =IFERROR(Model!AJ171+0,0) -> 4159 | P12: =IFERROR(Model!AM171+0,0) -> 5427 | Q12: =IFERROR(Model!AP171+0,0) -> 6421 | R12: =IFERROR(Model!AS171+0,0) -> 6992 | S12: =IFERROR(Model!AV171+0,0) -> 7495
B13: Recurring Operating Income | C13: =Model!F124 -> 462.9 | D13: =Model!G124 -> 668.2 | E13: =Model!H124 -> 885.2 | F13: =Model!I124 -> 1118.7 | G13: =Model!L124 -> 1218.2 | H13: =Model!O124 -> 1299.3 | I13: =Model!R124 -> 1540.7 | J13: =Model!U124 -> 1696.5 | K13: =Model!X124 -> 1922 | L13: =Model!AA124 -> 2045 | M13: =Model!AD124 -> 2338.8 | N13: =Model!AG124 -> 1981.4 | O13: =Model!AJ124 -> 3531 | P13: =Model!AM124 -> 4697 | Q13: =Model!AP124 -> 5649 | R13: =Model!AS124 -> 6148 | S13: =Model!AV124 -> 6569
B14: EBITDA Margin % | C14: =IFERROR(Model!F204+0,NA()) -> 0.28595309 | D14: =IFERROR(Model!G204+0,NA()) -> 0.32035155 | E14: =IFERROR(Model!H204+0,NA()) -> 0.35140082 | F14: =IFERROR(Model!I204+0,NA()) -> 0.35555811 | G14: =IFERROR(Model!L204+0,NA()) -> 0.36132417 | H14: =IFERROR(Model!O204+0,NA()) -> 0.35640752 | I14: =IFERROR(Model!R204+0,NA()) -> 0.36091717 | J14: =IFERROR(Model!U204+0,NA()) -> 0.37072777 | K14: =IFERROR(Model!X204+0,NA()) -> 0.39014633 | L14: =IFERROR(Model!AA204+0,NA()) -> 0.38634954 | M14: =IFERROR(Model!AD204+0,NA()) -> 0.40895488 | N14: =IFERROR(Model!AG204+0,NA()) -> 0.39908286 | O14: =IFERROR(Model!AJ204+0,NA()) -> 0.46303719 | P14: =IFERROR(Model!AM204+0,NA()) -> 0.46776418 | Q14: =IFERROR(Model!AP204+0,NA()) -> 0.47821554 | R14: =IFERROR(Model!AS204+0,NA()) -> 0.46090969 | S14: =IFERROR(Model!AV204+0,NA()) -> 0.46837895
B15: Recurring Op. Margin % | C15: =Model!F203 -> 0.24181163 | D15: =Model!G203 -> 0.27832389 | E15: =Model!H203 -> 0.3115585 | F15: =Model!I203 -> 0.32108722 | G15: =Model!L203 -> 0.32443805 | H15: =Model!O203 -> 0.31547128 | I15: =Model!R203 -> 0.31826069 | J15: =Model!U203 -> 0.32611203 | K15: =Model!X203 -> 0.34635623 | L15: =Model!AA203 -> 0.34276998 | M15: =Model!AD203 -> 0.33977395 | N15: =Model!AG203 -> 0.31010737 | O15: =Model!AJ203 -> 0.39311957 | P15: =Model!AM203 -> 0.40484399 | Q15: =Model!AP203 -> 0.42071945 | R15: =Model!AS203 -> 0.40527357 | S15: =Model!AV203 -> 0.41051119
C17: =C7 -> 2009 | D17: =D7 -> 2010 | E17: =E7 -> 2011 | F17: =F7 -> 2012 | G17: =G7 -> 2013 | H17: =H7 -> 2014 | I17: =I7 -> 2015 | J17: =J7 -> 2016 | ... S17: =S7 -> 2025
B18: ROIC | C18: =IFERROR(Model!F351+0,NA()) -> 0.2529689 | D18: =IFERROR(Model!G351+0,NA()) -> 0.36525336 | E18: =IFERROR(Model!H351+0,NA()) -> 0.46780885 | F18: =IFERROR(Model!I351+0,NA()) -> 0.46643717 | G18: =IFERROR(Model!L351+0,NA()) -> 0.46439214 | H18: =IFERROR(Model!O351+0,NA()) -> 0.44144194 | I18: =IFERROR(Model!R351+0,NA()) -> 0.46318658 | J18: =IFERROR(Model!U351+0,NA()) -> 0.55155413 | K18: =IFERROR(Model!X351+0,NA()) -> 0.63217752 | L18: =IFERROR(Model!AA351+0,NA()) -> 0.72958105 | M18: =IFERROR(Model!AD351+0,NA()) -> 0.50391403 | N18: =IFERROR(Model!AG351+0,NA()) -> 0.331617 | O18: =IFERROR(Model!AJ351+0,NA()) -> 0.60394105 | P18: =IFERROR(Model!AM351+0,NA()) -> 0.73200514 | Q18: =IFERROR(Model!AP351+0,NA()) -> 0.67429528 | R18: =IFERROR(Model!AS351+0,NA()) -> 0.59181835 | S18: =IFERROR(Model!AV351+0,NA()) -> 0.56005017
B19: RONTA | C19: =IFERROR(Model!F364+0,NA()) -> 0.23289532 | D19: =IFERROR(Model!G364+0,NA()) -> 0.32321019 | E19: =IFERROR(Model!H364+0,NA()) -> 0.45804942 | F19: =IFERROR(Model!I364+0,NA()) -> 0.45961578 | G19: =IFERROR(Model!L364+0,NA()) -> 0.4418959 | H19: =IFERROR(Model!O364+0,NA()) -> 0.41245329 | I19: =IFERROR(Model!R364+0,NA()) -> 0.42751833 | J19: =IFERROR(Model!U364+0,NA()) -> 0.49458963 | K19: =IFERROR(Model!X364+0,NA()) -> 0.52517865 | L19: =IFERROR(Model!AA364+0,NA()) -> 0.59967779 | M19: =IFERROR(Model!AD364+0,NA()) -> 0.43763291 | N19: =IFERROR(Model!AG364+0,NA()) -> 0.30257598 | O19: =IFERROR(Model!AJ364+0,NA()) -> 0.53682201 | P19: =IFERROR(Model!AM364+0,NA()) -> 0.63300388 | Q19: =IFERROR(Model!AP364+0,NA()) -> 0.611058 | R19: =IFERROR(Model!AS364+0,NA()) -> 0.56760621 | S19: =IFERROR(Model!AV364+0,NA()) -> 0.52877161
B20: Recurring op. margin % | C20: =IFERROR(Model!F203+0,NA()) -> 0.24181163 | D20: =IFERROR(Model!G203+0,NA()) -> 0.27832389 | E20: =IFERROR(Model!H203+0,NA()) -> 0.3115585 | F20: =IFERROR(Model!I203+0,NA()) -> 0.32108722 | G20: =IFERROR(Model!L203+0,NA()) -> 0.32443805 | H20: =IFERROR(Model!O203+0,NA()) -> 0.31547128 | I20: =IFERROR(Model!R203+0,NA()) -> 0.31826069 | J20: =IFERROR(Model!U203+0,NA()) -> 0.32611203 | K20: =IFERROR(Model!X203+0,NA()) -> 0.34635623 | L20: =IFERROR(Model!AA203+0,NA()) -> 0.34276998 | M20: =IFERROR(Model!AD203+0,NA()) -> 0.33977395 | N20: =IFERROR(Model!AG203+0,NA()) -> 0.31010737 | O20: =IFERROR(Model!AJ203+0,NA()) -> 0.39311957 | P20: =IFERROR(Model!AM203+0,NA()) -> 0.40484399 | Q20: =IFERROR(Model!AP203+0,NA()) -> 0.42071945 | R20: =IFERROR(Model!AS203+0,NA()) -> 0.40527357 | S20: =IFERROR(Model!AV203+0,NA()) -> 0.41051119
B21: Adjusted FCF margin % | C21: =IFERROR(Model!F244+0,NA()) -> 0.13566317 | D21: =IFERROR(Model!G244+0,NA()) -> 0.21892702 | E21: =IFERROR(Model!H244+0,NA()) -> 0.19382655 | F21: =IFERROR(Model!I244+0,NA()) -> 0.14583393 | G21: =IFERROR(Model!L244+0,NA()) -> 0.18259295 | H21: =IFERROR(Model!O244+0,NA()) -> 0.16699849 | I21: =IFERROR(Model!R244+0,NA()) -> 0.19279075 | J21: =IFERROR(Model!U244+0,NA()) -> 0.23293991 | K21: =IFERROR(Model!X244+0,NA()) -> 0.24154833 | L21: =IFERROR(Model!AA244+0,NA()) -> 0.24255376 | M21: =IFERROR(Model!AD244+0,NA()) -> 0.20433216 | N21: =IFERROR(Model!AG244+0,NA()) -> 0.15577363 | O21: =IFERROR(Model!AJ244+0,NA()) -> 0.29625919 | P21: =IFERROR(Model!AM244+0,NA()) -> 0.29348388 | Q21: =IFERROR(Model!AP244+0,NA()) -> 0.23772995 | R21: =IFERROR(Model!AS244+0,NA()) -> 0.24831905 | S21: =IFERROR(Model!AV244+0,NA()) -> 0.24253218
