Workbook

Sheet Model
CF1: SCENARIO SWITCH ▼ (Bull / Base / Bear) — drives all scenario-linked forecast drivers
B2: Saia, Inc. (NASDAQ: SAIA) — 3-Statement Financial Model | CF2: Base
B3: US GAAP as reported · USD millions (per-share data in USD; LTL tonnage & shipments in thousands; yields in $/cwt) · Source: Saia Forms 10-K / 10-Q and Form 8-K earnings releases (Ex. 99.1), interim LTL operating-data 8-Ks and call transcripts (8-K Ex. 99.1), SEC EDGAR CIK 0001177702 (investor-relations releases are the same documents as filed on EDGAR); DOE diesel from carrier 10-Q/10-Ks (Knight-Swift, Heartland, Marten) and EIA.
B4: Basis notes: calendar fiscal year. Continuing operations — Jevic Transportation sold Jun-2006 (discontinued operations to 2010). The Connection (Nov-2006) and Madison Freight (Jan-2007) integrated 2007; Robart (2012) and LinkEx (2015, sold 2018) small. Per-share data split-adjusted for the 3-for-2 split (May-2013). LTL statistics: TL statistics shown separately to 2017; from Q1/18 weight-priced truckload included in LTL (tonnage/shipment basis change — use company-reported change memos for y/y). ASC 606 adopted 1-Jan-2018 (2017 as originally reported). FY2008 per 10-K (Q4/08 release pre-dated the $35.5m goodwill impairment). Saia publishes no EBITDA; Adjusted EBITDA is model-defined. Last reported quarter Q2/26; Q3/26E uses Jul–Aug interim data (8-K 3-Sep-26).
CH5: Forecast | CI5: Historical | CJ5: Historical | CK5: Historical
B6: (USDm) | C6: 2006 | D6: 2007 | E6: 2008 | F6: 2009 | G6: 2010 | H6: 2011 | I6: 2012 | J6: Q1/13 | K6: Q2/13 | L6: Q3/13 | M6: Q4/13 | N6: 2013 | O6: Q1/14 | P6: Q2/14 | Q6: Q3/14 | R6: Q4/14 | S6: 2014 | T6: Q1/15 | U6: Q2/15 | V6: Q3/15 | W6: Q4/15 | X6: 2015 | Y6: Q1/16 | Z6: Q2/16 | AA6: Q3/16 | AB6: Q4/16 | AC6: 2016 | AD6: Q1/17 | AE6: Q2/17 | AF6: Q3/17 | AG6: Q4/17 | AH6: 2017 | AI6: Q1/18 | AJ6: Q2/18 | AK6: Q3/18 | AL6: Q4/18 | AM6: 2018 | AN6: Q1/19 | AO6: Q2/19 | AP6: Q3/19 | AQ6: Q4/19 | AR6: 2019 | AS6: Q1/20 | AT6: Q2/20 | AU6: Q3/20 | AV6: Q4/20 | AW6: 2020 | AX6: Q1/21 | AY6: Q2/21 | AZ6: Q3/21 | BA6: Q4/21 | BB6: 2021 | BC6: Q1/22 | BD6: Q2/22 | BE6: Q3/22 | BF6: Q4/22 | BG6: 2022 | BH6: Q1/23 | BI6: Q2/23 | BJ6: Q3/23 | BK6: Q4/23 | BL6: 2023 | BM6: Q1/24 | BN6: Q2/24 | BO6: Q3/24 | BP6: Q4/24 | BQ6: 2024 | BR6: Q1/25 | BS6: Q2/25 | BT6: Q3/25 | BU6: Q4/25 | BV6: 2025 | BW6: Q1/26 | BX6: Q2/26 | BY6: Q3/26E | BZ6: Q4/26E | CA6: 2026E | CB6: 2027E | CC6: 2028E | CD6: 2029E | CE6: 2030E | CF6: Modelling Notes | CH6: 5Y CAGR | CI6: 5Y CAGR | CJ6: 10Y CAGR | CK6: 19Y CAGR
CH7: 25-'30 | CI7: 20-'25 | CJ7: 15-'25 | CK7: 06-'25
B8: LTL OPERATING BUILD — VOLUME (TONNAGE) × CORE YIELD (REV/CWT EX-FUEL) + FUEL SURCHARGE (DOE DIESEL × SURCHARGE TABLE × CAPTURE) → REVENUE | CF8: LTL BUILD — modelling logic (tonnage × rev/cwt ex-fuel = freight revenue; + fuel surcharge per cwt = all-in yield)
CN9: SCENARIO INPUT TABLE — driver assumptions per Bull / Base / Bear | CO9: Bull | CP9: Base | CQ9: Bear | CR9: Bull / Bear = Base + Δ (Δ inputs on each lever header). Outlook block = Bull / Base / Bear end-points of company guidance.
B10: LTL volume (Saia LTL; shipments & tonnage in thousands; basis: statistics exclude services not priced by weight — truckload volumes priced by weight included from Q1/18) | CF10: VOLUME — modelling logic
B11: Workdays | C11: 252 | D11: 253 | E11: 254 | F11: 253 | G11: 252 | H11: 253 | I11: 253 | J11: 63 | K11: 64 | L11: 64 | M11: 62 | N11: 253 | O11: 63 | P11: 64 | Q11: 64 | R11: 62 | S11: 253 | T11: 63 | U11: 64 | V11: 64 | W11: 62 | X11: 253 | Y11: 64 | Z11: 64 | AA11: 64 | AB11: 61 | AC11: 253 | AD11: 64 | AE11: 64 | AF11: 63 | AG11: 61 | AH11: 252 | AI11: 64 | AJ11: 64 | AK11: 63 | AL11: 62 | AM11: 253 | AN11: 63 | AO11: 64 | AP11: 64 | AQ11: 62 | AR11: 253 | AS11: 64 | AT11: 64 | AU11: 64 | AV11: 62 | AW11: 254 | AX11: 63 | AY11: 64 | AZ11: 64 | BA11: 61 | BB11: 252 | BC11: 64 | BD11: 64 | BE11: 64 | BF11: 61 | BG11: 253 | BH11: 64 | BI11: 64 | BJ11: 63 | BK11: 61 | BL11: 252 | BM11: 64 | BN11: 64 | BO11: 64 | BP11: 62 | BQ11: 254 | BR11: 63 | BS11: 64 | BT11: 64 | BU11: 62 | BV11: 253 | BW11: 63 | BX11: 64 | BY11: 64 | BZ11: 62 | CA11: =SUM(BW11,BX11,BY11,BZ11) -> 253 | CB11: 253 | CC11: 253 | CD11: 253 | CE11: 253 | CF11: Q3/26E 64 (= Q3/25); Q4/26E 62 (= Q4/25); 2027E+ 253 workdays (2025: 253). | CN11: FY26 outlook — Q4-25 call (10-Feb-26), Q2-26 release & call (30-Jul-26), Jul–Aug data (3-Sep-26) | CO11: Bull | CP11: Base | CQ11: Bear
B12: LTL tonnage per workday (000 tons) | C12: =IF(AND(ISNUMBER(C14),ISNUMBER(C11)),IFERROR(C14/C11,""),"") -> 13.730159 | D12: =IF(AND(ISNUMBER(D14),ISNUMBER(D11)),IFERROR(D14/D11,""),"") -> 14.996047 | E12: =IF(AND(ISNUMBER(E14),ISNUMBER(E11)),IFERROR(E14/E11,""),"") -> 14.551181 | F12: =IF(AND(ISNUMBER(F14),ISNUMBER(F11)),IFERROR(F14/F11,""),"") -> 13.73913 | G12: =IF(AND(ISNUMBER(G14),ISNUMBER(G11)),IFERROR(G14/G11,""),"") -> 14.138889 | H12: =IF(AND(ISNUMBER(H14),ISNUMBER(H11)),IFERROR(H14/H11,""),"") -> 14.581028 | I12: =IF(AND(ISNUMBER(I14),ISNUMBER(I11)),IFERROR(I14/I11,""),"") -> 14.545455 | J12: =IF(AND(ISNUMBER(J14),ISNUMBER(J11)),IFERROR(J14/J11,""),"") -> 14.222222 | ... BX12: =IF(AND(ISNUMBER(BX14),ISNUMBER(BX11)),IFERROR(BX14/BX11,""),"") -> 26.703125 | BY12: =BT12*(1+BY13) -> 26.753484 | BZ12: =BU12*(1+BZ13) -> 25.179516 | CA12: =IF(AND(ISNUMBER(CA14),ISNUMBER(CA11)),IFERROR(CA14/CA11,""),"") -> 25.673332 | CB12: =CA12*(1+CB13) -> 26.956999 | CC12: =CB12*(1+CC13) -> 28.170064 | CD12: =CC12*(1+CD13) -> 29.296866 | CE12: =CD12*(1+CE13) -> 30.322256 | CN12: FY26 operating-ratio improvement vs FY25 adjusted OR (bps) | CO12: 150 | CP12: 100 | CQ12: 50 | CR12: Guide 100–200 bps (Feb-26); Q2 call: 200 bps needs mid-single-digit shipment growth → Base = low end.
B13: LTL tonnage per workday y/y % | D13: =IF(AND(ISNUMBER(D12),ISNUMBER(C12)),IFERROR(D12/C12-1,""),"") -> 0.092197674 | E13: =IF(AND(ISNUMBER(E12),ISNUMBER(D12)),IFERROR(E12/D12-1,""),"") -> -0.029665572 | F13: =IF(AND(ISNUMBER(F12),ISNUMBER(E12)),IFERROR(F12/E12-1,""),"") -> -0.055806512 | G13: =IF(AND(ISNUMBER(G12),ISNUMBER(F12)),IFERROR(G12/F12-1,""),"") -> 0.029096343 | H13: =IF(AND(ISNUMBER(H12),ISNUMBER(G12)),IFERROR(H12/G12-1,""),"") -> 0.031271112 | I13: =IF(AND(ISNUMBER(I12),ISNUMBER(H12)),IFERROR(I12/H12-1,""),"") -> -0.0024396856 | N13: =IF(AND(ISNUMBER(N12),ISNUMBER(I12)),IFERROR(N12/I12-1,""),"") -> -0.0024456522 | O13: =IF(AND(ISNUMBER(O12),ISNUMBER(J12)),IFERROR(O12/J12-1,""),"") -> 0.056919643 | P13: =IF(AND(ISNUMBER(P12),ISNUMBER(K12)),IFERROR(P12/K12-1,""),"") -> 0.069109948 | Q13: =IF(AND(ISNUMBER(Q12),ISNUMBER(L12)),IFERROR(Q12/L12-1,""),"") -> 0.081545064 | R13: =IF(AND(ISNUMBER(R12),ISNUMBER(M12)),IFERROR(R12/M12-1,""),"") -> 0.042792793 | S13: =IF(AND(ISNUMBER(S12),ISNUMBER(N12)),IFERROR(S12/N12-1,""),"") -> 0.062925633 | T13: =IF(AND(ISNUMBER(T12),ISNUMBER(O12)),IFERROR(T12/O12-1,""),"") -> -0.066525871 | U13: =IF(AND(ISNUMBER(U12),ISNUMBER(P12)),IFERROR(U12/P12-1,""),"") -> -0.059745348 | ... BX13: =IF(AND(ISNUMBER(BX12),ISNUMBER(BS12)),IFERROR(BX12/BS12-1,""),"") -> 0.084390863 | BY13: =BY59 -> 0.083 | BZ13: =CHOOSE(MATCH($CF$2,{"Bull","Base","Bear"},0),$CO$16,$CP$16,$CQ$16) -> 0.07 | CA13: =IF(AND(ISNUMBER(CA12),ISNUMBER(BV12)),IFERROR(CA12/BV12-1,""),"") -> 0.054269274 | CB13: =CHOOSE(MATCH($CF$2,{"Bull","Base","Bear"},0),$CO$36,$CP$36,$CQ$36) -> 0.05 | CC13: =CHOOSE(MATCH($CF$2,{"Bull","Base","Bear"},0),$CO$37,$CP$37,$CQ$37) -> 0.045 | CD13: =CHOOSE(MATCH($CF$2,{"Bull","Base","Bear"},0),$CO$38,$CP$38,$CQ$38) -> 0.04 | CE13: =CHOOSE(MATCH($CF$2,{"Bull","Base","Bear"},0),$CO$39,$CP$39,$CQ$39) -> 0.035 | CF13: Q3/26E = Jul–Aug QTD +8.3% (8-K 3-Sep-26); Q4/26E and 2027E+ = scenario lever TON (Bull/Base/Bear). | CN13: Q3/26 OR sequential change vs Q2/26 86.9% (bps; + = worse) | CO13: 50 | CP13: 100 | CQ13: 150 | CR13: Q2-26 call: ~100 bps degradation (typical 150–200 bps), assuming fuel near late-July level.
B14: LTL tonnage (000 tons) | C14: 3460 | D14: 3794 | E14: 3696 | F14: 3476 | G14: 3563 | H14: 3689 | I14: 3680 | J14: 896 | K14: 955 | L14: 932 | M14: 888 | N14: 3671 | O14: 947 | P14: 1021 | Q14: 1008 | R14: 926 | S14: 3902 | T14: 884 | U14: 960 | V14: 940 | W14: 844 | X14: 3628 | Y14: 868 | Z14: 919 | AA14: 913 | AB14: 842 | AC14: 3541 | AD14: 885 | AE14: 984 | AF14: 931 | AG14: 912 | AH14: 3711 | AI14: 1199 | AJ14: 1278 | AK14: 1208 | AL14: 1115 | AM14: 4801 | AN14: 1139 | AO14: 1254 | AP14: 1263 | AQ14: 1164 | AR14: 4820 | AS14: 1203 | AT14: 1142 | AU14: 1263 | AV14: 1233 | AW14: 4842 | AX14: 1247 | AY14: 1406 | AZ14: 1402 | BA14: 1346 | BB14: 5401 | BC14: 1387 | BD14: 1446 | BE14: 1397 | BF14: 1243 | BG14: 5473 | BH14: 1311 | BI14: 1421 | BJ14: 1467 | BK14: 1345 | BL14: 5543 | BM14: 1392 | BN14: 1559 | BO14: 1605 | BP14: 1481 | BQ14: 6037 | BR14: 1545 | BS14: 1576 | BT14: 1581 | BU14: 1459 | BV14: 6161 | BW14: 1513 | BX14: 1709 | BY14: =BY12*BY11 -> 1712.223 | BZ14: =BZ12*BZ11 -> 1561.13 | CA14: =SUM(BW14,BX14,BY14,BZ14) -> 6495.353 | CB14: =CB12*CB11 -> 6820.1206 | CC14: =CC12*CC11 -> 7127.0261 | CD14: =CD12*CD11 -> 7412.1071 | CE14: =CE12*CE11 -> 7671.5309 | CH14: =IFERROR((CE14/BV14)^(1/5)-1,"n/m") -> 0.044831279 | CI14: =IFERROR((BV14/AW14)^(1/5)-1,"n/m") -> 0.049361883 | CJ14: =IFERROR((BV14/X14)^(1/10)-1,"n/m") -> 0.054382995 | CK14: =IFERROR((BV14/C14)^(1/19)-1,"n/m") -> 0.030832645 | CN14: FY26 net capital expenditures ($m) | CO14: 400 | CP14: 375 | CQ14: 350 | CR14: Guidance $350–400m (Q2-26 release); 1H/26 net capex $158.0m.
B15: LTL weight per shipment (lbs) | C15: 1120.4663 | D15: 1101.626 | E15: 1101.6393 | F15: 1081.5184 | G15: 1113.6115 | H15: 1137.3516 | I15: 1169.1819 | J15: 1179 | K15: 1163 | L15: 1159 | M15: 1191 | N15: 1172.8435 | O15: 1195 | P15: 1179 | Q15: 1165 | R15: 1159 | S15: 1174 | T15: 1147 | U15: 1141 | V15: 1134 | W15: 1125 | X15: 1137 | Y15: 1118 | Z15: 1121 | AA15: 1114 | AB15: 1118 | AC15: 1118 | AD15: 1101 | AE15: 1118 | AF15: 1120 | AG15: 1114 | AH15: 1113 | AI15: 1355 | AJ15: 1370 | AK15: 1357 | AL15: 1322 | AM15: 1352 | AN15: 1308 | AO15: 1298 | AP15: 1302 | AQ15: 1297 | AR15: 1301 | AS15: 1331 | AT15: 1309 | AU15: 1289 | AV15: 1327 | AW15: 1314 | AX15: 1366 | AY15: 1397 | AZ15: 1400 | BA15: 1426 | BB15: 1397 | BC15: 1414 | BD15: 1412 | BE15: 1431 | BF15: 1433 | BG15: 1422 | BH15: 1439 | BI15: 1443 | BJ15: 1360 | BK15: 1314 | BL15: 1386 | BM15: 1321 | BN15: 1340 | BO15: 1349 | BP15: 1362 | BQ15: 1343 | BR15: 1424 | BS15: 1394 | BT15: 1355 | BU15: 1348 | BV15: 1380 | BW15: 1380 | BX15: 1448 | BY15: =BT15*(1+BY16) -> 1452.56 | BZ15: =BU15*(1+BZ16) -> 1415.4 | CA15: =IFERROR(CA14*2000/CA17,"") -> 1424.9749 | CB15: =CA15*(1+CB16) -> 1439.2247 | CC15: =CB15*(1+CC16) -> 1446.4208 | CD15: =CC15*(1+CD16) -> 1446.4208 | CE15: =CD15*(1+CE16) -> 1446.4208 | CN15: Q4/26E DOE diesel ($/gal) | CO15: 6.25 | CP15: 6.25 | CQ15: 6.25 | CR15: Late-Sep-26 weekly DOE $6.38 (record $6.53 on 21-Sep); held near spot in all cases (fuel is a pass-through lever, not a scenario call).
B16: Weight per shipment y/y % | D16: =IF(AND(ISNUMBER(D15),ISNUMBER(C15)),IFERROR(D15/C15-1,""),"") -> -0.0168147 | E16: =IF(AND(ISNUMBER(E15),ISNUMBER(D15)),IFERROR(E15/D15-1,""),"") -> 1.2098482e-05 | F16: =IF(AND(ISNUMBER(F15),ISNUMBER(E15)),IFERROR(F15/E15-1,""),"") -> -0.018264586 | G16: =IF(AND(ISNUMBER(G15),ISNUMBER(F15)),IFERROR(G15/F15-1,""),"") -> 0.029674156 | H16: =IF(AND(ISNUMBER(H15),ISNUMBER(G15)),IFERROR(H15/G15-1,""),"") -> 0.021318139 | I16: =IF(AND(ISNUMBER(I15),ISNUMBER(H15)),IFERROR(I15/H15-1,""),"") -> 0.0279863 | N16: =IF(AND(ISNUMBER(N15),ISNUMBER(I15)),IFERROR(N15/I15-1,""),"") -> 0.0031317284 | O16: =IF(AND(ISNUMBER(O15),ISNUMBER(J15)),IFERROR(O15/J15-1,""),"") -> 0.013570823 | P16: =IF(AND(ISNUMBER(P15),ISNUMBER(K15)),IFERROR(P15/K15-1,""),"") -> 0.013757524 | Q16: =IF(AND(ISNUMBER(Q15),ISNUMBER(L15)),IFERROR(Q15/L15-1,""),"") -> 0.0051768766 | R16: =IF(AND(ISNUMBER(R15),ISNUMBER(M15)),IFERROR(R15/M15-1,""),"") -> -0.026868178 | S16: =IF(AND(ISNUMBER(S15),ISNUMBER(N15)),IFERROR(S15/N15-1,""),"") -> 0.00098610733 | T16: =IF(AND(ISNUMBER(T15),ISNUMBER(O15)),IFERROR(T15/O15-1,""),"") -> -0.040167364 | U16: =IF(AND(ISNUMBER(U15),ISNUMBER(P15)),IFERROR(U15/P15-1,""),"") -> -0.032230704 | ... BX16: =IF(AND(ISNUMBER(BX15),ISNUMBER(BS15)),IFERROR(BX15/BS15-1,""),"") -> 0.038737446 | BY16: =BY61 -> 0.072 | BZ16: =CHOOSE(MATCH($CF$2,{"Bull","Base","Bear"},0),$CO$19,$CP$19,$CQ$19) -> 0.05 | CA16: =IF(AND(ISNUMBER(CA15),ISNUMBER(BV15)),IFERROR(CA15/BV15-1,""),"") -> 0.032590536 | CB16: =CHOOSE(MATCH($CF$2,{"Bull","Base","Bear"},0),$CO$46,$CP$46,$CQ$46) -> 0.01 | CC16: =CHOOSE(MATCH($CF$2,{"Bull","Base","Bear"},0),$CO$47,$CP$47,$CQ$47) -> 0.005 | CD16: =CHOOSE(MATCH($CF$2,{"Bull","Base","Bear"},0),$CO$48,$CP$48,$CQ$48) -> 0 | CE16: =CHOOSE(MATCH($CF$2,{"Bull","Base","Bear"},0),$CO$49,$CP$49,$CQ$49) -> 0 | CF16: Q3/26E = QTD +7.2%; heavier mix (customer/industrial mix initiatives) lowers rev/cwt — see mix effect below. | CN16: Q4/26E LTL tonnage/workday y/y | CO16: 0.09 | CP16: 0.07 | CQ16: 0.05 | CR16: QTD Jul–Aug +8.3%; Aug +8.7%. Comparison eases (Q4/25 tonnage/day −1.5%).
B17: LTL shipments (000s) | C17: 6176 | D17: 6888 | E17: 6710 | F17: 6428 | G17: 6399 | H17: 6487 | I17: 6295 | J17: 1520 | K17: 1642 | L17: 1608 | M17: 1490 | N17: 6260 | O17: 1586 | P17: 1732 | Q17: 1730 | R17: 1597 | S17: 6646 | T17: 1542 | U17: 1683 | V17: 1658 | W17: 1499 | X17: 6381 | Y17: 1553 | Z17: 1639 | AA17: 1638 | AB17: 1506 | AC17: 6335 | AD17: 1607 | AE17: 1760 | AF17: 1662 | AG17: 1636 | AH17: 6666 | AI17: 1770 | AJ17: 1866 | AK17: 1780 | AL17: 1687 | AM17: 7103 | AN17: 1741 | AO17: 1933 | AP17: 1941 | AQ17: 1794 | AR17: 7409 | AS17: 1809 | AT17: 1745 | AU17: 1959 | AV17: 1859 | AW17: 7371 | AX17: 1826 | AY17: 2012 | AZ17: 2004 | BA17: 1888 | BB17: 7730 | BC17: 1962 | BD17: 2048 | BE17: 1954 | BF17: 1734 | BG17: 7697 | BH17: 1822 | BI17: 1970 | BJ17: 2158 | BK17: 2047 | BL17: 7997 | BM17: 2108 | BN17: 2327 | BO17: 2379 | BP17: 2174 | BQ17: 8988 | BR17: 2170 | BS17: 2261 | BT17: 2333 | BU17: 2164 | BV17: 8929 | BW17: 2192 | BX17: 2361 | BY17: =IFERROR(BY14*2000/BY15,"") -> 2357.5246 | BZ17: =IFERROR(BZ14*2000/BZ15,"") -> 2205.9206 | CA17: =SUM(BW17,BX17,BY17,BZ17) -> 9116.4452 | CB17: =IFERROR(CB14*2000/CB15,"") -> 9477.4926 | CC17: =IFERROR(CC14*2000/CC15,"") -> 9854.7062 | CD17: =IFERROR(CD14*2000/CD15,"") -> 10248.894 | CE17: =IFERROR(CE14*2000/CE15,"") -> 10607.606 | CF17: Forecast shipments = tonnage × 2,000 ÷ weight per shipment. | CH17: =IFERROR((CE17/BV17)^(1/5)-1,"n/m") -> 0.035053765 | CI17: =IFERROR((BV17/AW17)^(1/5)-1,"n/m") -> 0.039095065 | CJ17: =IFERROR((BV17/X17)^(1/10)-1,"n/m") -> 0.034168744 | CK17: =IFERROR((BV17/C17)^(1/19)-1,"n/m") -> 0.019591206 | CN17: Q3/26E core price y/y (before weight mix) | CO17: 0.04 | CP17: 0.035 | CQ17: 0.03 | CR17: 7.1% GRI (early Jul-26) + renewals +10.7%; core yield ~+3% in Q2 after mix.
B18: LTL shipments per workday (000s) | C18: =IF(AND(ISNUMBER(C17),ISNUMBER(C11)),IFERROR(C17/C11,""),"") -> 24.507937 | D18: =IF(AND(ISNUMBER(D17),ISNUMBER(D11)),IFERROR(D17/D11,""),"") -> 27.225296 | E18: =IF(AND(ISNUMBER(E17),ISNUMBER(E11)),IFERROR(E17/E11,""),"") -> 26.417323 | F18: =IF(AND(ISNUMBER(F17),ISNUMBER(F11)),IFERROR(F17/F11,""),"") -> 25.407115 | G18: =IF(AND(ISNUMBER(G17),ISNUMBER(G11)),IFERROR(G17/G11,""),"") -> 25.392857 | H18: =IF(AND(ISNUMBER(H17),ISNUMBER(H11)),IFERROR(H17/H11,""),"") -> 25.640316 | I18: =IF(AND(ISNUMBER(I17),ISNUMBER(I11)),IFERROR(I17/I11,""),"") -> 24.881423 | J18: =IF(AND(ISNUMBER(J17),ISNUMBER(J11)),IFERROR(J17/J11,""),"") -> 24.126984 | ... CE18: =IF(AND(ISNUMBER(CE17),ISNUMBER(CE11)),IFERROR(CE17/CE11,""),"") -> 41.927295 | CN18: Q4/26E core price y/y (before weight mix) | CO18: 0.05 | CP18: 0.04 | CQ18: 0.03
B19: LTL shipments per workday y/y % | D19: =IF(AND(ISNUMBER(D18),ISNUMBER(C18)),IFERROR(D18/C18-1,""),"") -> 0.11087673 | E19: =IF(AND(ISNUMBER(E18),ISNUMBER(D18)),IFERROR(E18/D18-1,""),"") -> -0.029677312 | F19: =IF(AND(ISNUMBER(F18),ISNUMBER(E18)),IFERROR(F18/E18-1,""),"") -> -0.03824037 | G19: =IF(AND(ISNUMBER(G18),ISNUMBER(F18)),IFERROR(G18/F18-1,""),"") -> -0.00056116099 | H19: =IF(AND(ISNUMBER(H18),ISNUMBER(G18)),IFERROR(H18/G18-1,""),"") -> 0.0097452233 | I19: =IF(AND(ISNUMBER(I18),ISNUMBER(H18)),IFERROR(I18/H18-1,""),"") -> -0.029597657 | N19: =IF(AND(ISNUMBER(N18),ISNUMBER(I18)),IFERROR(N18/I18-1,""),"") -> -0.0055599682 | O19: =IF(AND(ISNUMBER(O18),ISNUMBER(J18)),IFERROR(O18/J18-1,""),"") -> 0.043421053 | P19: =IF(AND(ISNUMBER(P18),ISNUMBER(K18)),IFERROR(P18/K18-1,""),"") -> 0.054811206 | Q19: =IF(AND(ISNUMBER(Q18),ISNUMBER(L18)),IFERROR(Q18/L18-1,""),"") -> 0.075870647 | R19: =IF(AND(ISNUMBER(R18),ISNUMBER(M18)),IFERROR(R18/M18-1,""),"") -> 0.071812081 | S19: =IF(AND(ISNUMBER(S18),ISNUMBER(N18)),IFERROR(S18/N18-1,""),"") -> 0.061661342 | T19: =IF(AND(ISNUMBER(T18),ISNUMBER(O18)),IFERROR(T18/O18-1,""),"") -> -0.027742749 | U19: =IF(AND(ISNUMBER(U18),ISNUMBER(P18)),IFERROR(U18/P18-1,""),"") -> -0.028290993 | ... CA19: =IF(AND(ISNUMBER(CA18),ISNUMBER(BV18)),IFERROR(CA18/BV18-1,""),"") -> 0.020992859 | CB19: =IF(AND(ISNUMBER(CB18),ISNUMBER(CA18)),IFERROR(CB18/CA18-1,""),"") -> 0.03960396 | CC19: =IF(AND(ISNUMBER(CC18),ISNUMBER(CB18)),IFERROR(CC18/CB18-1,""),"") -> 0.039800995 | CD19: =IF(AND(ISNUMBER(CD18),ISNUMBER(CC18)),IFERROR(CD18/CC18-1,""),"") -> 0.04 | CE19: =IF(AND(ISNUMBER(CE18),ISNUMBER(CD18)),IFERROR(CE18/CD18-1,""),"") -> 0.035 | CF19: Check vs QTD Jul–Aug shipments/workday +1.0% (8-K 3-Sep-26). | CN19: Q4/26E weight per shipment y/y | CO19: 0.05 | CP19: 0.05 | CQ19: 0.05 | CR19: QTD +7.2%; laps the start of the weight increase from Q4/25–Q1/26.
B20: Memo: company-reported LTL tonnage/workday change % (release, like-for-like basis) | J20: -0.020212893 | K20: -0.015463918 | L20: -0.0006127451 | M20: 0.028968714 | O20: 0.056919643 | P20: 0.069109948 | Q20: 0.081545064 | R20: 0.042792793 | S20: 0.063215259 | T20: -0.066525871 | U20: -0.059745348 | V20: -0.067460317 | W20: -0.088552916 | X20: -0.0702204 | Y20: -0.033441742 | Z20: -0.042708333 | AA20: -0.028723404 | AB20: 0.013984927 | AC20: -0.023980154 | AD20: 0.019585253 | AE20: 0.070729053 | AF20: 0.03590118 | AG20: 0.083135392 | AH20: 0.052167803 | AI20: 0.12265918 | AJ20: 0.076663858 | AK20: 0.072824156 | AL20: -0.0063259701 | AM20: 0.066226024 | AN20: -0.034962998 | AO20: -0.018779343 | AP20: 0.029193398 | AQ20: 0.043946188 | AR20: 0.0039575089 | AS20: 0.039686677 | AT20: -0.089314195 | AU20: 0 | AV20: 0.059278351 | AW20: 0.00060933773 | AX20: 0.053028804 | AY20: 0.23117338 | AZ20: 0.11005542 | BA20: 0.10954223 | BB20: 0.12430093 | BC20: 0.094890237 | BD20: 0.028449502 | BE20: -0.0035663338 | BF20: -0.076523031 | BG20: 0.0093256043 | BH20: -0.054794521 | BI20: -0.017289073 | BJ20: 0.066775744 | BK20: 0.082059533 | BL20: 0.016809068 | BM20: 0.061784897 | BN20: 0.097114708 | BO20: 0.076974693 | BP20: 0.083355318 | BQ20: 0.080545655 | BR20: 0.12753147 | BS20: 0.010904426 | BT20: -0.014953271 | BU20: -0.014854828 | BV20: 0.024573758 | BW20: -0.020711974 | BX20: 0.084390863 | CF20: From the prior-year column of each release (restated basis) — use for y/y across the Q1/18 statistics-basis change. | CN20: 2H/26 share repurchases ($m) | CO20: 50 | CP20: 0 | CQ20: 0 | CR20: No active programme (last buyback 2007); leverage-floor plug applies from 2027E.
B21: Memo: company-reported LTL shipments/workday change % | J21: -0.034317083 | K21: -0.0084541063 | L21: 0.0056385006 | M21: 0.016371078 | O21: 0.043421053 | P21: 0.054811206 | Q21: 0.075870647 | R21: 0.071812081 | S21: 0.061661342 | T21: -0.027742749 | U21: -0.028290993 | V21: -0.041618497 | W21: -0.061365059 | X21: -0.039873608 | Y21: -0.0086028696 | Z21: -0.026143791 | AA21: -0.012062726 | AB21: 0.021139776 | AC21: -0.0072089014 | AD21: 0.03477141 | AE21: 0.073825503 | AF21: 0.030757602 | AG21: 0.086321381 | AH21: 0.056425001 | AI21: 0.083894672 | AJ21: 0.043624161 | AK21: 0.053254438 | AL21: -0.0019300526 | AM21: 0.044269358 | AN21: -0.00077123128 | AO21: 0.035905681 | AP21: 0.073411166 | AQ21: 0.0634262 | AR21: 0.043080389 | AS21: 0.022822731 | AT21: -0.097258148 | AU21: 0.0092735703 | AV21: 0.036231884 | AW21: -0.0090457127 | AX21: 0.025419639 | AY21: 0.1530086 | AZ21: 0.022970904 | BA21: 0.032248962 | BB21: 0.057027433 | BC21: 0.057690991 | BD21: 0.017892644 | BE21: -0.0249501 | BF21: -0.081567797 | BG21: -0.0082047768 | BH21: -0.071355759 | BI21: -0.038085938 | BJ21: 0.12193141 | BK21: 0.1805075 | BL21: 0.043099146 | BM21: 0.15697036 | BN21: 0.18121827 | BO21: 0.085184488 | BP21: 0.044912303 | BQ21: 0.1150717 | BR21: 0.045751634 | BS21: -0.028362699 | BT21: -0.019335855 | BU21: -0.004599816 | BV21: -0.0026376847 | BW21: 0.010138249 | BX21: 0.044228218 | CN21: FY26 point estimates & model constants (all cases) | CO21: Bull | CP21: Base | CQ21: Bear
B22: LTL average length of haul (miles) | J22: 734 | K22: 743 | L22: 742 | M22: 746 | N22: 741.27188 | O22: 753 | P22: 759 | Q22: 766 | R22: 773 | S22: 763 | T22: 773 | U22: 778 | V22: 773 | W22: 775 | X22: 775 | Y22: 781 | Z22: 786 | AA22: 789 | AB22: 792 | AC22: 787 | AD22: 797 | AE22: 806 | AF22: 813 | AG22: 828 | AH22: 811 | AI22: 837 | AJ22: 837 | AK22: 835 | AL22: 837 | AM22: 837 | AN22: 831 | AO22: 841 | AP22: 842 | AQ22: 846 | AR22: 840 | AS22: 848 | AT22: 876 | AU22: 893 | AV22: 898 | AW22: 879 | AX22: 904 | AY22: 911 | AZ22: 915 | BA22: 924 | BB22: 913 | BC22: 915 | BD22: 910 | BE22: 897 | BF22: 892 | BG22: 904 | BH22: 892 | BI22: 892 | BJ22: 896 | BK22: 895 | BL22: 894 | BM22: 888 | BN22: 888 | BO22: 890 | BP22: 898 | BQ22: 891 | BR22: 905 | BS22: 893 | BT22: 894 | BU22: 897 | BV22: 897 | BW22: 890 | BX22: 888 | CN22: FY25 adjusted operating ratio (base for the FY26 improvement guide) | CP22: 0.896 | CR22: Q4-25 release: adjusted OR 89.6% (GAAP 89.1% incl. $14.5m net real-estate gain).
CN23: Q3/Q4-26E effective tax rate | CP23: 0.245 | CR23: 1H/26 24.3%; Q2/26 24.9%.
B24: LTL yield — core price (revenue per hundredweight excluding fuel surcharge) | CF24: CORE YIELD — modelling logic | CN24: Q3/Q4-26E D&A sequential growth | CP24: 0.01 | CR24: Q2/26 D&A $64.2m (+2.6% y/y).
B25: LTL revenue/cwt excl. fuel surcharge — as reported ($) | C25: 10.264416 | AS25: 15.78 | AT25: 16.01 | AU25: 16.61 | AV25: 16.57 | AW25: 16.27 | AX25: 16.68 | AY25: 16.92 | AZ25: 18.31 | BA25: 18.89 | BB25: 17.72 | BC25: 19.28 | BD25: 19.44 | BE25: 19.74 | BF25: 20.11 | BG25: 19.63 | BH25: 20.15 | BI25: 19.96 | BJ25: 21.39 | BK25: 22.47 | BL25: 20.99 | BM25: 22.26 | BN25: 21.69 | BO25: 21.75 | BP25: 21.96 | BQ25: 21.9 | BR25: 21.12 | BS25: 21.42 | BT25: 21.72 | BU25: 22.07 | BV25: 21.58 | BW25: 21.52 | BX25: 20.94 | CF25: Reported in releases 2006–Q3/07 and from 2020 (2020 from the prior-year columns of 2021 releases). | CN25: Fuel-surcharge table: base diesel price ($/gal) | CP25: 1.25 | CR25: Saia LTL fuel-surcharge table mechanics (published carrier-table summaries; saia.com not reachable from this environment — verify vs current Saia tariff).
B26: LTL revenue/cwt excl. fuel surcharge — model ($) | C26: =IF(ISNUMBER(C25),C25,IF(AND(ISNUMBER(C40),ISNUMBER(C43)),C40*(1-C43),"")) -> 10.264416 | D26: =IF(ISNUMBER(D25),D25,IF(AND(ISNUMBER(D40),ISNUMBER(D43)),D40*(1-D43),"")) | E26: =IF(ISNUMBER(E25),E25,IF(AND(ISNUMBER(E40),ISNUMBER(E43)),E40*(1-E43),"")) | F26: =IF(ISNUMBER(F25),F25,IF(AND(ISNUMBER(F40),ISNUMBER(F43)),F40*(1-F43),"")) | G26: =IF(ISNUMBER(G25),G25,IF(AND(ISNUMBER(G40),ISNUMBER(G43)),G40*(1-G43),"")) -> 10.288393 | H26: =IF(ISNUMBER(H25),H25,IF(AND(ISNUMBER(H40),ISNUMBER(H43)),H40*(1-H43),"")) -> 10.772551 | I26: =IF(ISNUMBER(I25),I25,IF(AND(ISNUMBER(I40),ISNUMBER(I43)),I40*(1-I43),"")) -> 11.425171 | J26: =IF(ISNUMBER(J25),J25,IF(AND(ISNUMBER(J40),ISNUMBER(J43)),J40*(1-J43),"")) -> 11.71268 | ... BX26: =IF(ISNUMBER(BX25),BX25,IF(AND(ISNUMBER(BX40),ISNUMBER(BX43)),BX40*(1-BX43),"")) -> 20.94 | BY26: =BT26*(1+BY27) -> 21.30732 | BZ26: =BU26*(1+BZ27) -> 22.125175 | CA26: =IFERROR(CA46*1000/(CA14*20),"") -> 21.456783 | CB26: =CA26*(1+CB27) -> 22.368696 | CC26: =CB26*(1+CC27) -> 23.403248 | CD26: =CC26*(1+CD27) -> 24.456394 | CE26: =CD26*(1+CE27) -> 25.556932 | CF26: Historical: reported where disclosed, else derived = all-in rev/cwt × (1 − company fuel-surcharge % of revenue) (≈ ±1% vs reported on overlap years). FORECAST CORE PRICE INPUT. | CH26: =IFERROR((CE26/BV26)^(1/5)-1,"n/m") -> 0.034407011 | CI26: =IFERROR((BV26/AW26)^(1/5)-1,"n/m") -> 0.058114772 | CJ26: =IFERROR((BV26/X26)^(1/10)-1,"n/m") -> 0.046994365 | CK26: =IFERROR((BV26/C26)^(1/19)-1,"n/m") -> 0.039884525 | CN26: Fuel-surcharge table: price step ($/gal) | CP26: 0.05
B27: Rev/cwt ex-fuel y/y % | D27: =IF(AND(ISNUMBER(D26),ISNUMBER(C26)),IFERROR(D26/C26-1,""),"") | E27: =IF(AND(ISNUMBER(E26),ISNUMBER(D26)),IFERROR(E26/D26-1,""),"") | F27: =IF(AND(ISNUMBER(F26),ISNUMBER(E26)),IFERROR(F26/E26-1,""),"") | G27: =IF(AND(ISNUMBER(G26),ISNUMBER(F26)),IFERROR(G26/F26-1,""),"") | H27: =IF(AND(ISNUMBER(H26),ISNUMBER(G26)),IFERROR(H26/G26-1,""),"") -> 0.047058669 | I27: =IF(AND(ISNUMBER(I26),ISNUMBER(H26)),IFERROR(I26/H26-1,""),"") -> 0.060581813 | N27: =IF(AND(ISNUMBER(N26),ISNUMBER(I26)),IFERROR(N26/I26-1,""),"") -> 0.043820315 | O27: =IF(AND(ISNUMBER(O26),ISNUMBER(J26)),IFERROR(O26/J26-1,""),"") -> 0.026988699 | P27: =IF(AND(ISNUMBER(P26),ISNUMBER(K26)),IFERROR(P26/K26-1,""),"") -> 0.044951879 | Q27: =IF(AND(ISNUMBER(Q26),ISNUMBER(L26)),IFERROR(Q26/L26-1,""),"") -> 0.043328748 | R27: =IF(AND(ISNUMBER(R26),ISNUMBER(M26)),IFERROR(R26/M26-1,""),"") -> 0.070823375 | S27: =IF(AND(ISNUMBER(S26),ISNUMBER(N26)),IFERROR(S26/N26-1,""),"") -> 0.046186663 | T27: =IF(AND(ISNUMBER(T26),ISNUMBER(O26)),IFERROR(T26/O26-1,""),"") -> 0.10097607 | U27: =IF(AND(ISNUMBER(U26),ISNUMBER(P26)),IFERROR(U26/P26-1,""),"") -> 0.097183887 | ... BX27: =IF(AND(ISNUMBER(BX26),ISNUMBER(BS26)),IFERROR(BX26/BS26-1,""),"") -> -0.022408964 | BY27: =BY28-BY16*BY29 -> -0.019 | BZ27: =BZ28-BZ16*BZ29 -> 0.0025 | CA27: =IF(AND(ISNUMBER(CA26),ISNUMBER(BV26)),IFERROR(CA26/BV26-1,""),"") -> -0.0057097919 | CB27: =CB28-CB16*CB29 -> 0.0425 | CC27: =CC28-CC16*CC29 -> 0.04625 | CD27: =CD28-CD16*CD29 -> 0.045 | CE27: =CE28-CE16*CE29 -> 0.045 | CF27: Forecast = core price (contract renewals + GRI) − weight-per-shipment mix effect × elasticity. | CN27: Fuel-surcharge table: surcharge increment per step | CP27: 0.005
B28: Core price y/y % before weight-mix (contract renewals, GRI) — input | BY28: =CHOOSE(MATCH($CF$2,{"Bull","Base","Bear"},0),$CO$17,$CP$17,$CQ$17) -> 0.035 | BZ28: =CHOOSE(MATCH($CF$2,{"Bull","Base","Bear"},0),$CO$18,$CP$18,$CQ$18) -> 0.04 | CB28: =CHOOSE(MATCH($CF$2,{"Bull","Base","Bear"},0),$CO$41,$CP$41,$CQ$41) -> 0.05 | CC28: =CHOOSE(MATCH($CF$2,{"Bull","Base","Bear"},0),$CO$42,$CP$42,$CQ$42) -> 0.05 | CD28: =CHOOSE(MATCH($CF$2,{"Bull","Base","Bear"},0),$CO$43,$CP$43,$CQ$43) -> 0.045 | CE28: =CHOOSE(MATCH($CF$2,{"Bull","Base","Bear"},0),$CO$44,$CP$44,$CQ$44) -> 0.045 | CF28: Q2-26 call: core yield ex-fuel ~+3% after mix; contractual renewals +10.7% (Q2/26); 7.1% GRI from early Jul-26. | CN28: Fuel pass-through into FOS (Δ fuel cost per $1 Δ surcharge revenue) | CP28: 0.31 | CR28: Calibrated: Q2/26 vs Q2/25 FOS +$37.1m vs revenue ex-fuel +6.5% and fuel-surcharge revenue +$94m.
B29: Weight-mix elasticity of rev/cwt (−Δ rev/cwt per +1% weight/shipment) | BY29: =$CP$29 -> 0.75 | BZ29: =$CP$29 -> 0.75 | CB29: =$CP$29 -> 0.75 | CC29: =$CP$29 -> 0.75 | CD29: =$CP$29 -> 0.75 | CE29: =$CP$29 -> 0.75 | CF29: Heavier shipments carry lower rev/cwt. Q2/26: weight +3.9%, rev/cwt ex-fuel −2.2% with ~+3% core → implied ~1.3x incl. LOH/LA mix; 0.75x assumed. | CN29: Weight-mix elasticity of rev/cwt | CP29: 0.75
B30: Memo: company-reported rev/cwt ex-fuel change % | AX30: 0.057034221 | AY30: 0.056839475 | AZ30: 0.10234798 | BA30: 0.14001207 | BB30: 0.089121082 | BC30: 0.1558753 | BD30: 0.14893617 | BE30: 0.078099399 | BF30: 0.064584436 | BG30: 0.10778781 | BH30: 0.045124481 | BI30: 0.026748971 | BJ30: 0.083586626 | BK30: 0.11735455 | BL30: 0.069281712 | BM30: 0.10471464 | BN30: 0.086673347 | BO30: 0.016830295 | BP30: -0.022696929 | BQ30: 0.043353978 | BR30: -0.051212938 | BS30: -0.012448133 | BT30: -0.0013793103 | BU30: 0.0050091075 | BV30: -0.014611872 | BW30: 0.018939394 | BX30: -0.022408964 | CN30: Minimum cash balance ($m) | CP30: 25 | CR30: Saia runs lean cash ($19.7m at YE25) with revolver as liquidity.
B31: LTL revenue/shipment excl. fuel surcharge ($) | C31: =IF(ISNUMBER(C26),IFERROR(C26*C15/100,""),"") -> 115.00933 | D31: =IF(ISNUMBER(D26),IFERROR(D26*D15/100,""),"") | E31: =IF(ISNUMBER(E26),IFERROR(E26*E15/100,""),"") | F31: =IF(ISNUMBER(F26),IFERROR(F26*F15/100,""),"") | G31: =IF(ISNUMBER(G26),IFERROR(G26*G15/100,""),"") -> 114.57272 | H31: =IF(ISNUMBER(H26),IFERROR(H26*H15/100,""),"") -> 122.52178 | I31: =IF(ISNUMBER(I26),IFERROR(I26*I15/100,""),"") -> 133.58103 | J31: =IF(ISNUMBER(J26),IFERROR(J26*J15/100,""),"") -> 138.0925 | ... BX31: =IF(ISNUMBER(BX26),IFERROR(BX26*BX15/100,""),"") -> 303.2112 | BY31: =IFERROR(BY26*BY15/100,"") -> 309.50161 | BZ31: =IFERROR(BZ26*BZ15/100,"") -> 313.15973 | CA31: =IFERROR(CA26*CA15/100,"") -> 305.75378 | CB31: =IFERROR(CB26*CB15/100,"") -> 321.93579 | CC31: =IFERROR(CC26*CC15/100,"") -> 338.50945 | CD31: =IFERROR(CD26*CD15/100,"") -> 353.74238 | CE31: =IFERROR(CE26*CE15/100,"") -> 369.66078 | CH31: =IFERROR((CE31/BV31)^(1/5)-1,"n/m") -> 0.044178077 | CI31: =IFERROR((BV31/AW31)^(1/5)-1,"n/m") -> 0.068536894 | CJ31: =IFERROR((BV31/X31)^(1/10)-1,"n/m") -> 0.067471297 | CK31: =IFERROR((BV31/C31)^(1/19)-1,"n/m") -> 0.051349797 | CN31: Share-price appreciation % p.a. (buyback pricing) | CP31: 0.07
B33: Fuel surcharge — DOE diesel × Saia fuel-surcharge table × capture ratio | CF33: FUEL SURCHARGE — modelling logic | CN33: Minimum net debt / Adjusted EBITDA (x) — buyback floor 2026E+ | CO33: 0.5 | CP33: 0 | CQ33: 0 | CR33: Saia is under-levered (net debt ~$16m at Q2/26); Base returns surplus cash only once net debt reaches zero; Bull re-levers to 0.5x.
B34: DOE U.S. on-highway diesel — average of weekly prices ($/gal) | C34: 2.705 | D34: 2.885 | E34: 3.803 | F34: 2.47 | G34: 2.99 | H34: 3.85 | I34: 3.97 | J34: 4.03 | K34: 3.87 | L34: 3.92 | M34: =4*N34-J34-K34-L34 -> 3.86 | N34: 3.92 | O34: 3.96 | P34: 3.94 | Q34: 3.83 | R34: =4*S34-O34-P34-Q34 -> 3.59 | S34: 3.83 | T34: 2.92 | U34: 2.85 | V34: 2.63 | W34: =4*X34-T34-U34-V34 -> 2.44 | X34: 2.71 | Y34: 2.07 | Z34: 2.3 | AA34: 2.38 | AB34: =4*AC34-Y34-Z34-AA34 -> 2.45 | AC34: 2.3 | AD34: 2.57 | AE34: 2.55 | AF34: 2.63 | AG34: =4*AH34-AD34-AE34-AF34 -> 2.85 | AH34: 2.65 | AI34: 3.02 | AJ34: 3.19 | AK34: 3.24 | AL34: =4*AM34-AI34-AJ34-AK34 -> 3.27 | AM34: 3.18 | AN34: 3.02 | AO34: 3.12 | AP34: 3.02 | AQ34: =4*AR34-AN34-AO34-AP34 -> 3.08 | AR34: 3.06 | AS34: 2.92 | AT34: 2.44 | AU34: 2.43 | AV34: =4*AW34-AS34-AT34-AU34 -> 2.45 | AW34: 2.56 | AX34: 2.91 | AY34: 3.21 | AZ34: 3.36 | BA34: =4*BB34-AX34-AY34-AZ34 -> 3.68 | BB34: 3.29 | BC34: 4.36 | BD34: 5.53 | BE34: 5.09 | BF34: =4*BG34-BC34-BD34-BE34 -> 5.06 | BG34: 5.01 | BH34: 4.4 | BI34: 3.94 | BJ34: 4.27 | BK34: =4*BL34-BH34-BI34-BJ34 -> 4.19 | BL34: 4.2 | BM34: 3.96 | BN34: 3.86 | BO34: 3.69 | BP34: =4*BQ34-BM34-BN34-BO34 -> 3.53 | BQ34: 3.76 | BR34: 3.63 | BS34: 3.56 | BT34: 3.76 | BU34: =4*BV34-BR34-BS34-BT34 -> 3.69 | BV34: 3.66 | BW34: 4.12 | BX34: 5.33 | BY34: 5.56 | BZ34: =CHOOSE(MATCH($CF$2,{"Bull","Base","Bear"},0),$CO$15,$CP$15,$CQ$15) -> 6.25 | CA34: =AVERAGE(BW34,BX34,BY34,BZ34) -> 5.315 | CB34: =CHOOSE(MATCH($CF$2,{"Bull","Base","Bear"},0),$CO$51,$CP$51,$CQ$51) -> 5.25 | CC34: =CHOOSE(MATCH($CF$2,{"Bull","Base","Bear"},0),$CO$52,$CP$52,$CQ$52) -> 4.75 | CD34: =CHOOSE(MATCH($CF$2,{"Bull","Base","Bear"},0),$CO$53,$CP$53,$CQ$53) -> 4.5 | CE34: =CHOOSE(MATCH($CF$2,{"Bull","Base","Bear"},0),$CO$54,$CP$54,$CQ$54) -> 4.5 | CF34: Q1–Q3 & FY per Knight-Swift 10-Qs/10-Ks (weekly DOE average; Heartland & Marten 10-Qs cross-check); Q4 = 4×FY − Q1–Q3. 2006–08 EIA annual averages. Q3/26 $5.56 = 13-week EIA average (Jul $4.955 matches Heartland 10-Q $4.96).
B35: Diesel y/y % | D35: =IF(AND(ISNUMBER(D34),ISNUMBER(C34)),IFERROR(D34/C34-1,""),"") -> 0.066543438 | E35: =IF(AND(ISNUMBER(E34),ISNUMBER(D34)),IFERROR(E34/D34-1,""),"") -> 0.31819757 | F35: =IF(AND(ISNUMBER(F34),ISNUMBER(E34)),IFERROR(F34/E34-1,""),"") -> -0.35051275 | G35: =IF(AND(ISNUMBER(G34),ISNUMBER(F34)),IFERROR(G34/F34-1,""),"") -> 0.21052632 | H35: =IF(AND(ISNUMBER(H34),ISNUMBER(G34)),IFERROR(H34/G34-1,""),"") -> 0.28762542 | I35: =IF(AND(ISNUMBER(I34),ISNUMBER(H34)),IFERROR(I34/H34-1,""),"") -> 0.031168831 | N35: =IF(AND(ISNUMBER(N34),ISNUMBER(I34)),IFERROR(N34/I34-1,""),"") -> -0.012594458 | O35: =IF(AND(ISNUMBER(O34),ISNUMBER(J34)),IFERROR(O34/J34-1,""),"") -> -0.017369727 | P35: =IF(AND(ISNUMBER(P34),ISNUMBER(K34)),IFERROR(P34/K34-1,""),"") -> 0.018087855 | Q35: =IF(AND(ISNUMBER(Q34),ISNUMBER(L34)),IFERROR(Q34/L34-1,""),"") -> -0.022959184 | R35: =IF(AND(ISNUMBER(R34),ISNUMBER(M34)),IFERROR(R34/M34-1,""),"") -> -0.069948187 | S35: =IF(AND(ISNUMBER(S34),ISNUMBER(N34)),IFERROR(S34/N34-1,""),"") -> -0.022959184 | T35: =IF(AND(ISNUMBER(T34),ISNUMBER(O34)),IFERROR(T34/O34-1,""),"") -> -0.26262626 | U35: =IF(AND(ISNUMBER(U34),ISNUMBER(P34)),IFERROR(U34/P34-1,""),"") -> -0.27664975 | ... CA35: =IF(AND(ISNUMBER(CA34),ISNUMBER(BV34)),IFERROR(CA34/BV34-1,""),"") -> 0.45218579 | CB35: =IF(AND(ISNUMBER(CB34),ISNUMBER(CA34)),IFERROR(CB34/CA34-1,""),"") -> -0.012229539 | CC35: =IF(AND(ISNUMBER(CC34),ISNUMBER(CB34)),IFERROR(CC34/CB34-1,""),"") -> -0.095238095 | CD35: =IF(AND(ISNUMBER(CD34),ISNUMBER(CC34)),IFERROR(CD34/CC34-1,""),"") -> -0.052631579 | CE35: =IF(AND(ISNUMBER(CE34),ISNUMBER(CD34)),IFERROR(CE34/CD34-1,""),"") -> 0 | CN35: TON (LTL tonnage per workday y/y) | CO35: 0.02 | CP35: Δ → | CQ35: -0.02 | CR35: Industrial recovery + density on the national network (33 terminals added since 2022; ~25% more doors).
B36: Fuel-surcharge table % at average diesel (Saia LTL table: base $/gal, +x% per step) | C36: =IF(ISNUMBER(C34),MAX(0,ROUNDDOWN((C34-$CP$25)/$CP$26,0)*$CP$27),"") -> 0.145 | D36: =IF(ISNUMBER(D34),MAX(0,ROUNDDOWN((D34-$CP$25)/$CP$26,0)*$CP$27),"") -> 0.16 | E36: =IF(ISNUMBER(E34),MAX(0,ROUNDDOWN((E34-$CP$25)/$CP$26,0)*$CP$27),"") -> 0.255 | F36: =IF(ISNUMBER(F34),MAX(0,ROUNDDOWN((F34-$CP$25)/$CP$26,0)*$CP$27),"") -> 0.12 | G36: =IF(ISNUMBER(G34),MAX(0,ROUNDDOWN((G34-$CP$25)/$CP$26,0)*$CP$27),"") -> 0.17 | H36: =IF(ISNUMBER(H34),MAX(0,ROUNDDOWN((H34-$CP$25)/$CP$26,0)*$CP$27),"") -> 0.26 | I36: =IF(ISNUMBER(I34),MAX(0,ROUNDDOWN((I34-$CP$25)/$CP$26,0)*$CP$27),"") -> 0.27 | J36: =IF(ISNUMBER(J34),MAX(0,ROUNDDOWN((J34-$CP$25)/$CP$26,0)*$CP$27),"") -> 0.275 | ... CE36: =IF(ISNUMBER(CE34),MAX(0,ROUNDDOWN((CE34-$CP$25)/$CP$26,0)*$CP$27),"") -> 0.325 | CF36: Table parameters in the scenario panel (current Saia LTL table: $1.25 base, +0.5% per $0.05). Saia revised its program 18-Jan-2016 (10-K); apply to 2016+ only. | CN36: 2027E | CO36: =CP36+$CO$35 -> 0.07 | CP36: 0.05 | CQ36: =CP36+$CQ$35 -> 0.03
B37: Effective fuel surcharge % of ex-fuel yield ((all-in ÷ ex-fuel rev/cwt) − 1) | C37: =IF(AND(ISNUMBER(C40),ISNUMBER(C26)),IFERROR(C40/C26-1,""),"") -> 0.14339708 | D37: =IF(AND(ISNUMBER(D40),ISNUMBER(D26)),IFERROR(D40/D26-1,""),"") | E37: =IF(AND(ISNUMBER(E40),ISNUMBER(E26)),IFERROR(E40/E26-1,""),"") | F37: =IF(AND(ISNUMBER(F40),ISNUMBER(F26)),IFERROR(F40/F26-1,""),"") | G37: =IF(AND(ISNUMBER(G40),ISNUMBER(G26)),IFERROR(G40/G26-1,""),"") -> 0.14155251 | H37: =IF(AND(ISNUMBER(H40),ISNUMBER(H26)),IFERROR(H40/H26-1,""),"") -> 0.20048019 | I37: =IF(AND(ISNUMBER(I40),ISNUMBER(I26)),IFERROR(I40/I26-1,""),"") -> 0.20918984 | J37: =IF(AND(ISNUMBER(J40),ISNUMBER(J26)),IFERROR(J40/J26-1,""),"") -> 0.21065375 | ... BX37: =IF(AND(ISNUMBER(BX40),ISNUMBER(BX26)),IFERROR(BX40/BX26-1,""),"") -> 0.29799427 | BY37: =BY36*BY38 -> 0.31877415 | BZ37: =BZ36*BZ38 -> 0.37066762 | CA37: =IFERROR(CA40/CA26-1,"") -> 0.29970179 | CB37: =CB36*CB38 -> 0.2965341 | CC37: =CC36*CC38 -> 0.25946733 | CD37: =CD36*CD38 -> 0.24093395 | CE37: =CE36*CE38 -> 0.24093395 | CN37: 2028E | CO37: =CP37+$CO$35 -> 0.065 | CP37: 0.045 | CQ37: =CP37+$CQ$35 -> 0.025
B38: Capture ratio (effective ÷ table) — discounts, minimum charges, accessorials not surcharged | C38: =IF(AND(ISNUMBER(C37),ISNUMBER(C36)),IFERROR(C37/C36,""),"") -> 0.98894536 | D38: =IF(AND(ISNUMBER(D37),ISNUMBER(D36)),IFERROR(D37/D36,""),"") | E38: =IF(AND(ISNUMBER(E37),ISNUMBER(E36)),IFERROR(E37/E36,""),"") | F38: =IF(AND(ISNUMBER(F37),ISNUMBER(F36)),IFERROR(F37/F36,""),"") | G38: =IF(AND(ISNUMBER(G37),ISNUMBER(G36)),IFERROR(G37/G36,""),"") -> 0.83266183 | H38: =IF(AND(ISNUMBER(H37),ISNUMBER(H36)),IFERROR(H37/H36,""),"") -> 0.77107766 | I38: =IF(AND(ISNUMBER(I37),ISNUMBER(I36)),IFERROR(I37/I36,""),"") -> 0.7747772 | J38: =IF(AND(ISNUMBER(J37),ISNUMBER(J36)),IFERROR(J37/J36,""),"") -> 0.76601365 | ... BX38: =IF(AND(ISNUMBER(BX37),ISNUMBER(BX36)),IFERROR(BX37/BX36,""),"") -> 0.73578832 | BY38: =AVERAGE($BT$38,$BU$38,$BW$38,$BX$38) -> 0.74133524 | BZ38: =AVERAGE($BT$38,$BU$38,$BW$38,$BX$38) -> 0.74133524 | CA38: =IFERROR(CA37/CA36,"") -> 0.74000441 | CB38: =AVERAGE($BT$38,$BU$38,$BW$38,$BX$38) -> 0.74133524 | CC38: =AVERAGE($BT$38,$BU$38,$BW$38,$BX$38) -> 0.74133524 | CD38: =AVERAGE($BT$38,$BU$38,$BW$38,$BX$38) -> 0.74133524 | CE38: =AVERAGE($BT$38,$BU$38,$BW$38,$BX$38) -> 0.74133524 | CF38: Forecast = trailing-4Q average (Q3/25–Q2/26 ≈ 0.74); stable 0.69–0.77 since 2022. | CH38: =IFERROR(AVERAGE(CA38,CB38,CC38,CD38,CE38),"n/m") -> 0.74106907 | CI38: =IFERROR(AVERAGE(BB38,BG38,BL38,BQ38,BV38),"n/m") -> 0.74371411 | CJ38: =IFERROR(AVERAGE(AC38,AH38,AM38,AR38,AW38,BB38,BG38,BL38,BQ38,BV38),"n/m") -> 0.8302333 | CK38: =IFERROR(AVERAGE(C38,D38,E38,F38,G38,H38,I38,N38,S38,X38,AC38,AH38,AM38,AR38,AW38,BB38,BG38,BL38,BQ38,BV38),"n/m") -> 0.83094904 | CN38: 2029E | CO38: =CP38+$CO$35 -> 0.06 | CP38: 0.04 | CQ38: =CP38+$CQ$35 -> 0.02
B39: Fuel surcharge per cwt ($) | C39: =IF(AND(ISNUMBER(C40),ISNUMBER(C26)),C40-C26,"") -> 1.4718873 | D39: =IF(AND(ISNUMBER(D40),ISNUMBER(D26)),D40-D26,"") | E39: =IF(AND(ISNUMBER(E40),ISNUMBER(E26)),E40-E26,"") | F39: =IF(AND(ISNUMBER(F40),ISNUMBER(F26)),F40-F26,"") | G39: =IF(AND(ISNUMBER(G40),ISNUMBER(G26)),G40-G26,"") -> 1.4563478 | H39: =IF(AND(ISNUMBER(H40),ISNUMBER(H26)),H40-H26,"") -> 2.159683 | I39: =IF(AND(ISNUMBER(I40),ISNUMBER(I26)),I40-I26,"") -> 2.3900298 | J39: =IF(AND(ISNUMBER(J40),ISNUMBER(J26)),J40-J26,"") -> 2.46732 | ... BX39: =IF(AND(ISNUMBER(BX40),ISNUMBER(BX26)),BX40-BX26,"") -> 6.24 | BY39: =BY26*BY37 -> 6.7922229 | BZ39: =BZ26*BZ37 -> 8.2010859 | CA39: =IFERROR(CA47*1000/(CA14*20),"") -> 6.4306361 | CB39: =CB26*CB37 -> 6.633081 | CC39: =CC26*CC37 -> 6.0723784 | CD39: =CD26*CD37 -> 5.8923757 | CE39: =CE26*CE37 -> 6.1575326 | CN39: 2030E | CO39: =CP39+$CO$35 -> 0.055 | CP39: 0.035 | CQ39: =CP39+$CQ$35 -> 0.015
B40: LTL revenue/cwt incl. fuel surcharge ($) | C40: 11.736303 | D40: 11.983026 | E40: 12.946897 | F40: 11.420377 | G40: 11.74474 | H40: 12.932234 | I40: 13.815201 | J40: 14.18 | K40: 14.16 | L40: 14.54 | M40: 14.46 | N40: 14.333925 | O40: 14.51 | P40: 14.85 | Q40: 15.17 | R40: 15.33 | S40: 14.96 | T40: 15.17 | U40: 15.42 | V40: 15.51 | W40: 15.66 | X40: 15.44 | Y40: 15.49 | Z40: 15.73 | AA40: 16.08 | AB40: 16.45 | AC40: 15.93 | AD40: 16.68 | AE40: 16.89 | AF40: 17.36 | AG40: 17.89 | AH40: 17.2 | AI40: 15.92 | AJ40: 16.44 | AK40: 17.2 | AL40: 17.72 | AM40: 16.8 | AN40: 17.61 | AO40: 18.05 | AP40: 18.12 | AQ40: 18.38 | AR40: 18.05 | AS40: 18.16 | AT40: 17.95 | AU40: 18.59 | AV40: 18.6 | AW40: 18.33 | AX40: 19.18 | AY40: 19.84 | AZ40: 21.36 | BA40: 22.24 | BB40: 20.68 | BC40: 23.29 | BD40: 25.05 | BE40: 25.1 | BF40: 25.42 | BG40: 24.7 | BH40: 24.63 | BI40: 23.85 | BJ40: 25.87 | BK40: 27.21 | BL40: 25.38 | BM40: 26.51 | BN40: 25.75 | BO40: 25.64 | BP40: 25.73 | BQ40: 25.89 | BR40: 24.97 | BS40: 25.2 | BT40: 25.76 | BU40: 26.13 | BV40: 25.5 | BW40: 25.93 | BX40: 27.18 | BY40: =BY26+BY39 -> 28.099543 | BZ40: =BZ26+BZ39 -> 30.326261 | CA40: =IFERROR(CA48*1000/(CA14*20),"") -> 27.887419 | CB40: =CB26+CB39 -> 29.001777 | CC40: =CC26+CC39 -> 29.475627 | CD40: =CD26+CD39 -> 30.34877 | CE40: =CE26+CE39 -> 31.714465 | CF40: All-in yield = core yield + fuel surcharge per cwt; drives LTL revenue. | CH40: =IFERROR((CE40/BV40)^(1/5)-1,"n/m") -> 0.044584172 | CI40: =IFERROR((BV40/AW40)^(1/5)-1,"n/m") -> 0.068256498 | CJ40: =IFERROR((BV40/X40)^(1/10)-1,"n/m") -> 0.051451605 | CK40: =IFERROR((BV40/C40)^(1/19)-1,"n/m") -> 0.041687152 | CN40: PRICE (core rev/cwt ex-fuel y/y, before weight mix) | CO40: 0.015 | CP40: Δ → | CQ40: -0.015 | CR40: National-network service premium; pricing ahead of cost inflation (mgmt).
B41: Rev/cwt incl. fuel y/y % | D41: =IF(AND(ISNUMBER(D40),ISNUMBER(C40)),IFERROR(D40/C40-1,""),"") -> 0.021022153 | E41: =IF(AND(ISNUMBER(E40),ISNUMBER(D40)),IFERROR(E40/D40-1,""),"") -> 0.080436346 | F41: =IF(AND(ISNUMBER(F40),ISNUMBER(E40)),IFERROR(F40/E40-1,""),"") -> -0.11790623 | G41: =IF(AND(ISNUMBER(G40),ISNUMBER(F40)),IFERROR(G40/F40-1,""),"") -> 0.028402173 | H41: =IF(AND(ISNUMBER(H40),ISNUMBER(G40)),IFERROR(H40/G40-1,""),"") -> 0.10110852 | I41: =IF(AND(ISNUMBER(I40),ISNUMBER(H40)),IFERROR(I40/H40-1,""),"") -> 0.068276482 | N41: =IF(AND(ISNUMBER(N40),ISNUMBER(I40)),IFERROR(N40/I40-1,""),"") -> 0.037547356 | O41: =IF(AND(ISNUMBER(O40),ISNUMBER(J40)),IFERROR(O40/J40-1,""),"") -> 0.023272214 | P41: =IF(AND(ISNUMBER(P40),ISNUMBER(K40)),IFERROR(P40/K40-1,""),"") -> 0.048728814 | Q41: =IF(AND(ISNUMBER(Q40),ISNUMBER(L40)),IFERROR(Q40/L40-1,""),"") -> 0.043328748 | R41: =IF(AND(ISNUMBER(R40),ISNUMBER(M40)),IFERROR(R40/M40-1,""),"") -> 0.060165975 | S41: =IF(AND(ISNUMBER(S40),ISNUMBER(N40)),IFERROR(S40/N40-1,""),"") -> 0.043677822 | T41: =IF(AND(ISNUMBER(T40),ISNUMBER(O40)),IFERROR(T40/O40-1,""),"") -> 0.045485872 | U41: =IF(AND(ISNUMBER(U40),ISNUMBER(P40)),IFERROR(U40/P40-1,""),"") -> 0.038383838 | ... CA41: =IF(AND(ISNUMBER(CA40),ISNUMBER(BV40)),IFERROR(CA40/BV40-1,""),"") -> 0.093624266 | CB41: =IF(AND(ISNUMBER(CB40),ISNUMBER(CA40)),IFERROR(CB40/CA40-1,""),"") -> 0.039959172 | CC41: =IF(AND(ISNUMBER(CC40),ISNUMBER(CB40)),IFERROR(CC40/CB40-1,""),"") -> 0.016338639 | CD41: =IF(AND(ISNUMBER(CD40),ISNUMBER(CC40)),IFERROR(CD40/CC40-1,""),"") -> 0.02962256 | CE41: =IF(AND(ISNUMBER(CE40),ISNUMBER(CD40)),IFERROR(CE40/CD40-1,""),"") -> 0.045 | CN41: 2027E | CO41: =CP41+$CO$40 -> 0.065 | CP41: 0.05 | CQ41: =CP41+$CQ$40 -> 0.035
B42: LTL revenue/shipment incl. fuel surcharge ($) | J42: 167.25 | K42: 164.68 | L42: 168.43 | M42: 172.22 | O42: 173.28 | P42: 175.09 | Q42: 176.71 | R42: 177.72 | S42: 175.71 | T42: 174.12 | U42: 176.02 | V42: 175.77 | W42: 176.23 | X42: 175.55 | Y42: 173.2 | Z42: 176.45 | AA42: 179.17 | AB42: 183.91 | AC42: 178.13 | AD42: 183.68 | AE42: 188.78 | AF42: 194.36 | AG42: 199.39 | AH42: 191.55 | AI42: 215.79 | AJ42: 225.24 | AK42: 233.38 | AL42: 234.33 | AM42: 227.08 | AN42: 230.43 | AO42: 234.33 | AP42: 235.87 | AQ42: 238.45 | AR42: 234.81 | AS42: 241.61 | AT42: 235.08 | AU42: 239.6 | AV42: 246.88 | AW42: 240.86 | AX42: 261.96 | AY42: 277.24 | AZ42: 299.02 | BA42: 317.04 | BB42: 289 | BC42: 329.3 | BD42: 353.75 | BE42: 359.04 | BF42: 364.44 | BG42: 351.27 | BH42: 354.37 | BI42: 344.08 | BJ42: 351.64 | BK42: 357.5 | BL42: 351.9 | BM42: 350.18 | BN42: 345.07 | BO42: 345.93 | BP42: 350.51 | BQ42: 347.81 | BR42: 355.48 | BS42: 351.36 | BT42: 349.07 | BU42: 352.27 | BV42: 351.99 | BW42: 357.93 | BX42: 393.56 | BY42: =IFERROR(BY40*BY15/100,"") -> 408.16272 | BZ42: =IFERROR(BZ40*BZ15/100,"") -> 429.2379 | CA42: =IFERROR(CA40*CA15/100,"") -> 397.38873 | CB42: =IFERROR(CB40*CB15/100,"") -> 417.40073 | CC42: =IFERROR(CC40*CC15/100,"") -> 426.3416 | CD42: =IFERROR(CD40*CD15/100,"") -> 438.97093 | CE42: =IFERROR(CE40*CE15/100,"") -> 458.72462 | CH42: =IFERROR((CE42/BV42)^(1/5)-1,"n/m") -> 0.054397444 | CI42: =IFERROR((BV42/AW42)^(1/5)-1,"n/m") -> 0.078830283 | CJ42: =IFERROR((BV42/X42)^(1/10)-1,"n/m") -> 0.072044836 | CK42: =IFERROR((BV42/C42)^(1/19)-1,"n/m") -> n/m | CN42: 2028E | CO42: =CP42+$CO$40 -> 0.065 | CP42: 0.05 | CQ42: =CP42+$CQ$40 -> 0.035
B43: Fuel surcharge revenue % of total operating revenue (company: 10-K/10-Q MD&A; Q4 derived) | C43: 0.119 | G43: 0.124 | H43: 0.167 | I43: 0.173 | J43: 0.174 | K43: 0.167 | L43: 0.167 | M43: =IFERROR((N43*N81-J43*J81-K43*K81-L43*L81)/M81,"") -> 0.16421989 | N43: 0.168 | O43: 0.171 | P43: 0.17 | Q43: 0.167 | R43: =IFERROR((S43*S81-O43*O81-P43*P81-Q43*Q81)/R81,"") -> 0.15581815 | S43: 0.166 | T43: 0.127 | U43: 0.123 | V43: 0.114 | W43: =IFERROR((X43*X81-T43*T81-U43*U81-V43*V81)/W81,"") -> 0.10337216 | X43: 0.117 | Y43: 0.087 | Z43: 0.097 | AA43: 0.102 | AB43: =IFERROR((AC43*AC81-Y43*Y81-Z43*Z81-AA43*AA81)/AB81,"") -> 0.10138641 | AC43: 0.097 | AD43: 0.109 | AE43: 0.111 | AF43: 0.113 | AG43: =IFERROR((AH43*AH81-AD43*AD81-AE43*AE81-AF43*AF81)/AG81,"") -> 0.12642243 | AH43: 0.115 | AI43: 0.13 | AJ43: 0.138 | AK43: 0.138 | AL43: =IFERROR((AM43*AM81-AI43*AI81-AJ43*AJ81-AK43*AK81)/AL81,"") -> 0.13759371 | AM43: 0.136 | AN43: 0.129 | AO43: 0.132 | AP43: 0.128 | AQ43: =IFERROR((AR43*AR81-AN43*AN81-AO43*AO81-AP43*AP81)/AQ81,"") -> 0.13094789 | AR43: 0.13 | AS43: 0.128 | AT43: 0.106 | AU43: 0.104 | AV43: =IFERROR((AW43*AW81-AS43*AS81-AT43*AT81-AU43*AU81)/AV81,"") -> 0.10653279 | AW43: 0.111 | AX43: 0.129 | AY43: 0.144 | AZ43: 0.139 | BA43: =IFERROR((BB43*BB81-AX43*AX81-AY43*AY81-AZ43*AZ81)/BA81,"") -> 0.14592418 | BB43: 0.14 | BC43: 0.168 | BD43: 0.217 | BE43: 0.205 | BF43: =IFERROR((BG43*BG81-BC43*BC81-BD43*BD81-BE43*BE81)/BF81,"") -> 0.20311812 | BG43: 0.199 | BH43: 0.178 | BI43: 0.159 | BJ43: 0.169 | BK43: =IFERROR((BL43*BL81-BH43*BH81-BI43*BI81-BJ43*BJ81)/BK81,"") -> 0.17033319 | BL43: 0.169 | BM43: 0.157 | BN43: 0.154 | BO43: 0.148 | BP43: =IFERROR((BQ43*BQ81-BM43*BM81-BN43*BN81-BO43*BO81)/BP81,"") -> 0.14126411 | BQ43: 0.15 | BR43: 0.151 | BS43: 0.146 | BT43: 0.152 | BU43: =IFERROR((BV43*BV81-BR43*BR81-BS43*BS81-BT43*BT81)/BU81,"") -> 0.15101474 | BV43: 0.15 | BW43: 0.165 | BX43: 0.223 | BY43: =IFERROR(BY54/BY81,"") -> 0.24172005 | BZ43: =IFERROR(BZ54/BZ81,"") -> 0.27042852 | CA43: =IFERROR(CA54/CA81,"") -> 0.22790802 | CB43: =IFERROR(CB54/CB81,"") -> 0.22871292 | CC43: =IFERROR(CC54/CC81,"") -> 0.20601355 | CD43: =IFERROR(CD54/CD81,"") -> 0.19415534 | CE43: =IFERROR(CE54/CE81,"") -> 0.19415534 | CF43: Q2/26: 22.3% (14.6% Q2/25). Q4 = (FY% × FY revenue − Σ Q1–Q3) ÷ Q4 revenue. | CH43: =IFERROR(AVERAGE(CA43,CB43,CC43,CD43,CE43),"n/m") -> 0.21018903 | CI43: =IFERROR(AVERAGE(BB43,BG43,BL43,BQ43,BV43),"n/m") -> 0.1616 | CJ43: =IFERROR(AVERAGE(AC43,AH43,AM43,AR43,AW43,BB43,BG43,BL43,BQ43,BV43),"n/m") -> 0.1397 | CK43: =IFERROR(AVERAGE(C43,D43,E43,F43,G43,H43,I43,N43,S43,X43,AC43,AH43,AM43,AR43,AW43,BB43,BG43,BL43,BQ43,BV43),"n/m") -> 0.143 | CN43: 2029E | CO43: =CP43+$CO$40 -> 0.06 | CP43: 0.045 | CQ43: =CP43+$CQ$40 -> 0.03
CN44: 2030E | CO44: =CP44+$CO$40 -> 0.06 | CP44: 0.045 | CQ44: =CP44+$CQ$40 -> 0.03
B45: Revenue build (tonnage × yield) | CF45: REVENUE — modelling logic | CN45: WPS (weight per shipment y/y) | CO45: 0 | CP45: Δ → | CQ45: 0 | CR45: Mix normalises after the 2026 weight step-up.
B46: LTL revenue excl. fuel surcharge (tonnage × 20 × rev/cwt ex-fuel) | C46: =IF(AND(ISNUMBER(C14),ISNUMBER(C26)),C14*20*C26/1000,"") -> 710.2976 | D46: =IF(AND(ISNUMBER(D14),ISNUMBER(D26)),D14*20*D26/1000,"") | E46: =IF(AND(ISNUMBER(E14),ISNUMBER(E26)),E14*20*E26/1000,"") | F46: =IF(AND(ISNUMBER(F14),ISNUMBER(F26)),F14*20*F26/1000,"") | G46: =IF(AND(ISNUMBER(G14),ISNUMBER(G26)),G14*20*G26/1000,"") -> 733.15086 | H46: =IF(AND(ISNUMBER(H14),ISNUMBER(H26)),H14*20*H26/1000,"") -> 794.79879 | I46: =IF(AND(ISNUMBER(I14),ISNUMBER(I26)),I14*20*I26/1000,"") -> 840.89261 | J46: =IF(AND(ISNUMBER(J14),ISNUMBER(J26)),J14*20*J26/1000,"") -> 209.89123 | ... BX46: =IF(AND(ISNUMBER(BX14),ISNUMBER(BX26)),BX14*20*BX26/1000,"") -> 715.7292 | BY46: =BY14*20*BY26/1000 -> 729.65767 | BZ46: =BZ14*20*BZ26/1000 -> 690.80549 | CA46: =SUM(BW46,BX46,BY46,BZ46) -> 2787.3876 | CB46: =CB14*20*CB26/1000 -> 3051.1441 | CC46: =CC14*20*CC26/1000 -> 3335.9112 | CD46: =CD14*20*CD26/1000 -> 3625.4683 | CE46: =CE14*20*CE26/1000 -> 3921.2159 | CF46: Freight (core) revenue = f(tonnage, rev/cwt ex-fuel). | CN46: 2027E | CO46: =CP46+$CO$45 -> 0.01 | CP46: 0.01 | CQ46: =CP46+$CQ$45 -> 0.01
B47: LTL fuel surcharge revenue (tonnage × 20 × fuel surcharge/cwt) | C47: =IF(AND(ISNUMBER(C14),ISNUMBER(C39)),C14*20*C39/1000,"") -> 101.8546 | D47: =IF(AND(ISNUMBER(D14),ISNUMBER(D39)),D14*20*D39/1000,"") | E47: =IF(AND(ISNUMBER(E14),ISNUMBER(E39)),E14*20*E39/1000,"") | F47: =IF(AND(ISNUMBER(F14),ISNUMBER(F39)),F14*20*F39/1000,"") | G47: =IF(AND(ISNUMBER(G14),ISNUMBER(G39)),G14*20*G39/1000,"") -> 103.77934 | H47: =IF(AND(ISNUMBER(H14),ISNUMBER(H39)),H14*20*H39/1000,"") -> 159.34141 | I47: =IF(AND(ISNUMBER(I14),ISNUMBER(I39)),I14*20*I39/1000,"") -> 175.90619 | J47: =IF(AND(ISNUMBER(J14),ISNUMBER(J39)),J14*20*J39/1000,"") -> 44.214374 | ... BX47: =IF(AND(ISNUMBER(BX14),ISNUMBER(BX39)),BX14*20*BX39/1000,"") -> 213.2832 | BY47: =BY14*20*BY39/1000 -> 232.596 | BZ47: =BZ14*20*BZ39/1000 -> 256.05923 | CA47: =SUM(BW47,BX47,BY47,BZ47) -> 835.38503 | CB47: =CB14*20*CB39/1000 -> 904.76826 | CC47: =CC14*20*CC39/1000 -> 865.55998 | CD47: =CD14*20*CD39/1000 -> 873.4984 | CE47: =CE14*20*CE39/1000 -> 944.75404 | CN47: 2028E | CO47: =CP47+$CO$45 -> 0.005 | CP47: 0.005 | CQ47: =CP47+$CQ$45 -> 0.005
B48: LTL revenue (tonnage × 20 × rev/cwt incl. fuel) | C48: =IF(AND(ISNUMBER(C14),ISNUMBER(C40)),C14*20*C40/1000,"") -> 812.1522 | D48: =IF(AND(ISNUMBER(D14),ISNUMBER(D40)),D14*20*D40/1000,"") -> 909.272 | E48: =IF(AND(ISNUMBER(E14),ISNUMBER(E40)),E14*20*E40/1000,"") -> 957.0346 | F48: =IF(AND(ISNUMBER(F14),ISNUMBER(F40)),F14*20*F40/1000,"") -> 793.9446 | G48: =IF(AND(ISNUMBER(G14),ISNUMBER(G40)),G14*20*G40/1000,"") -> 836.9302 | H48: =IF(AND(ISNUMBER(H14),ISNUMBER(H40)),H14*20*H40/1000,"") -> 954.1402 | I48: =IF(AND(ISNUMBER(I14),ISNUMBER(I40)),I14*20*I40/1000,"") -> 1016.7988 | J48: =IF(AND(ISNUMBER(J14),ISNUMBER(J40)),J14*20*J40/1000,"") -> 254.1056 | ... BX48: =IF(AND(ISNUMBER(BX14),ISNUMBER(BX40)),BX14*20*BX40/1000,"") -> 929.0124 | BY48: =BY46+BY47 -> 962.25367 | BZ48: =BZ46+BZ47 -> 946.86471 | CA48: =SUM(BW48,BX48,BY48,BZ48) -> 3622.7726 | CB48: =CB46+CB47 -> 3955.9124 | CC48: =CC46+CC47 -> 4201.4712 | CD48: =CD46+CD47 -> 4498.9667 | CE48: =CE46+CE47 -> 4865.9699 | CH48: =IFERROR((CE48/BV48)^(1/5)-1,"n/m") -> 0.091414217 | CI48: =IFERROR((BV48/AW48)^(1/5)-1,"n/m") -> 0.12098765 | CJ48: =IFERROR((BV48/X48)^(1/10)-1,"n/m") -> 0.10863269 | CK48: =IFERROR((BV48/C48)^(1/19)-1,"n/m") -> 0.073805123 | CN48: 2029E | CO48: =CP48+$CO$45 -> 0 | CP48: 0 | CQ48: =CP48+$CQ$45 -> 0
B49: Other revenue (non-weight-priced TL/logistics; revenue-recognition adjustment & other) | C49: =IF(ISNUMBER(C48),C81-C48,"") -> 62.5858 | D49: =IF(ISNUMBER(D48),D81-D48,"") -> 66.851 | E49: =IF(ISNUMBER(E48),E81-E48,"") -> 73.3864 | F49: =IF(ISNUMBER(F48),F81-F48,"") -> 55.1964 | G49: =IF(ISNUMBER(G48),G81-G48,"") -> 65.7298 | H49: =IF(ISNUMBER(H48),H81-H48,"") -> 76.0838 | I49: =IF(ISNUMBER(I48),I81-I48,"") -> 81.8802 | J49: =IF(ISNUMBER(J48),J81-J48,"") -> 19.6894 | ... BX49: =IF(ISNUMBER(BX48),BX81-BX48,"") -> 27.4816 | BY49: =BY48*BY50 -> 29.667229 | BZ49: =BZ48*BZ50 -> 34.123835 | CA49: =SUM(BW49,BX49,BY49,BZ49) -> 112.85686 | CB49: =CB48*CB50 -> 123.23486 | CC49: =CC48*CC50 -> 130.88452 | CD49: =CD48*CD50 -> 140.15212 | CE49: =CE48*CE50 -> 151.58503 | CN49: 2030E | CO49: =CP49+$CO$45 -> 0 | CP49: 0 | CQ49: =CP49+$CQ$45 -> 0
B50: Other revenue % of LTL revenue | C50: =IF(ISNUMBER(C49),IFERROR(C49/C48,""),"") -> 0.077061664 | D50: =IF(ISNUMBER(D49),IFERROR(D49/D48,""),"") -> 0.073521455 | E50: =IF(ISNUMBER(E49),IFERROR(E49/E48,""),"") -> 0.076681031 | F50: =IF(ISNUMBER(F49),IFERROR(F49/F48,""),"") -> 0.069521727 | G50: =IF(ISNUMBER(G49),IFERROR(G49/G48,""),"") -> 0.078536776 | H50: =IF(ISNUMBER(H49),IFERROR(H49/H48,""),"") -> 0.079740692 | I50: =IF(ISNUMBER(I49),IFERROR(I49/I48,""),"") -> 0.080527436 | J50: =IF(ISNUMBER(J49),IFERROR(J49/J48,""),"") -> 0.077485109 | ... BX50: =IF(ISNUMBER(BX49),IFERROR(BX49/BX48,""),"") -> 0.029581521 | BY50: =BT50 -> 0.030830986 | BZ50: =BU50 -> 0.036038765 | CA50: =IFERROR(CA49/CA48,"") -> 0.03115207 | CB50: =$CA$50 -> 0.03115207 | CC50: =$CA$50 -> 0.03115207 | CD50: =$CA$50 -> 0.03115207 | CE50: =$CA$50 -> 0.03115207 | CF50: Forecast: prior-year quarter (Q3/Q4-26E); 2027E+ at 2026E level. TL statistics folded into LTL from Q1/18 (step-down in this ratio). | CN50: DSL (DOE diesel, $/gal) | CO50: 0 | CP50: Δ → | CQ50: 0 | CR50: Mean-reversion from the 2026 spike (2023–25 avg $3.9); flat across cases — flex here to stress fuel.
B51: Total operating revenue (LTL build) | C51: =IF(ISNUMBER(C48),C48+C49,"") -> 874.738 | D51: =IF(ISNUMBER(D48),D48+D49,"") -> 976.123 | E51: =IF(ISNUMBER(E48),E48+E49,"") -> 1030.421 | F51: =IF(ISNUMBER(F48),F48+F49,"") -> 849.141 | G51: =IF(ISNUMBER(G48),G48+G49,"") -> 902.66 | H51: =IF(ISNUMBER(H48),H48+H49,"") -> 1030.224 | I51: =IF(ISNUMBER(I48),I48+I49,"") -> 1098.679 | J51: =IF(ISNUMBER(J48),J48+J49,"") -> 273.795 | ... BX51: =IF(ISNUMBER(BX48),BX48+BX49,"") -> 956.494 | BY51: =BY48+BY49 -> 991.9209 | BZ51: =BZ48+BZ49 -> 980.98855 | CA51: =CA48+CA49 -> 3735.6295 | CB51: =CB48+CB49 -> 4079.1472 | CC51: =CC48+CC49 -> 4332.3557 | CD51: =CD48+CD49 -> 4639.1188 | CE51: =CE48+CE49 -> 5017.5549 | CN51: 2027E | CO51: =CP51+$CO$50 -> 5.25 | CP51: 5.25 | CQ51: =CP51+$CQ$50 -> 5.25
B52: Revenue y/y % | D52: =IF(AND(ISNUMBER(D81),ISNUMBER(C81)),IFERROR(D81/C81-1,""),"") -> 0.11590328 | E52: =IF(AND(ISNUMBER(E81),ISNUMBER(D81)),IFERROR(E81/D81-1,""),"") -> 0.055626186 | F52: =IF(AND(ISNUMBER(F81),ISNUMBER(E81)),IFERROR(F81/E81-1,""),"") -> -0.17592809 | G52: =IF(AND(ISNUMBER(G81),ISNUMBER(F81)),IFERROR(G81/F81-1,""),"") -> 0.063027224 | H52: =IF(AND(ISNUMBER(H81),ISNUMBER(G81)),IFERROR(H81/G81-1,""),"") -> 0.1413201 | I52: =IF(AND(ISNUMBER(I81),ISNUMBER(H81)),IFERROR(I81/H81-1,""),"") -> 0.066446715 | N52: =IF(AND(ISNUMBER(N81),ISNUMBER(I81)),IFERROR(N81/I81-1,""),"") -> 0.036785085 | O52: =IF(AND(ISNUMBER(O81),ISNUMBER(J81)),IFERROR(O81/J81-1,""),"") -> 0.094724155 | P52: =IF(AND(ISNUMBER(P81),ISNUMBER(K81)),IFERROR(P81/K81-1,""),"") -> 0.12934915 | Q52: =IF(AND(ISNUMBER(Q81),ISNUMBER(L81)),IFERROR(Q81/L81-1,""),"") -> 0.13462555 | R52: =IF(AND(ISNUMBER(R81),ISNUMBER(M81)),IFERROR(R81/M81-1,""),"") -> 0.10725 | S52: =IF(AND(ISNUMBER(S81),ISNUMBER(N81)),IFERROR(S81/N81-1,""),"") -> 0.11695874 | T52: =IF(AND(ISNUMBER(T81),ISNUMBER(O81)),IFERROR(T81/O81-1,""),"") -> -0.022380142 | U52: =IF(AND(ISNUMBER(U81),ISNUMBER(P81)),IFERROR(U81/P81-1,""),"") -> -0.020941347 | ... BX52: =IF(AND(ISNUMBER(BX81),ISNUMBER(BS81)),IFERROR(BX81/BS81-1,""),"") -> 0.17057452 | BY52: =IF(AND(ISNUMBER(BY51),ISNUMBER(BT51)),IFERROR(BY51/BT51-1,""),"") -> 0.18135889 | BZ52: =IF(AND(ISNUMBER(BZ51),ISNUMBER(BU51)),IFERROR(BZ51/BU51-1,""),"") -> 0.24183311 | CA52: =IF(AND(ISNUMBER(CA51),ISNUMBER(BV51)),IFERROR(CA51/BV51-1,""),"") -> 0.155009 | CB52: =IF(AND(ISNUMBER(CB51),ISNUMBER(CA51)),IFERROR(CB51/CA51-1,""),"") -> 0.091957131 | CC52: =IF(AND(ISNUMBER(CC51),ISNUMBER(CB51)),IFERROR(CC51/CB51-1,""),"") -> 0.062073878 | CD52: =IF(AND(ISNUMBER(CD51),ISNUMBER(CC51)),IFERROR(CD51/CC51-1,""),"") -> 0.070807463 | CE52: =IF(AND(ISNUMBER(CE51),ISNUMBER(CD51)),IFERROR(CE51/CD51-1,""),"") -> 0.081575 | CN52: 2028E | CO52: =CP52+$CO$50 -> 4.75 | CP52: 4.75 | CQ52: =CP52+$CQ$50 -> 4.75
B53: Check: LTL build vs reported operating revenue (should be 0) | C53: =IF(ISNUMBER(C51),ROUND(C51-C81,1),"") -> 0 | D53: =IF(ISNUMBER(D51),ROUND(D51-D81,1),"") -> 0 | E53: =IF(ISNUMBER(E51),ROUND(E51-E81,1),"") -> 0 | F53: =IF(ISNUMBER(F51),ROUND(F51-F81,1),"") -> 0 | G53: =IF(ISNUMBER(G51),ROUND(G51-G81,1),"") -> 0 | H53: =IF(ISNUMBER(H51),ROUND(H51-H81,1),"") -> 0 | I53: =IF(ISNUMBER(I51),ROUND(I51-I81,1),"") -> 0 | J53: =IF(ISNUMBER(J51),ROUND(J51-J81,1),"") -> 0 | ... BX53: =IF(ISNUMBER(BX51),ROUND(BX51-BX81,1),"") -> 0 | BY53: =ROUND(BY51-BY81,1) -> 0 | BZ53: =ROUND(BZ51-BZ81,1) -> 0 | CA53: =ROUND(CA51-CA81,1) -> 0 | CB53: =ROUND(CB51-CB81,1) -> 0 | CC53: =ROUND(CC51-CC81,1) -> 0 | CD53: =ROUND(CD51-CD81,1) -> 0 | CE53: =ROUND(CE51-CE81,1) -> 0 | CN53: 2029E | CO53: =CP53+$CO$50 -> 4.5 | CP53: 4.5 | CQ53: =CP53+$CQ$50 -> 4.5
B54: Memo: total fuel surcharge revenue (company % × revenue; forecast = LTL surcharge grossed up for other revenue) | C54: =IF(ISNUMBER(C43),C43*C81,"") -> 104.09382 | D54: =IF(ISNUMBER(D43),D43*D81,"") | E54: =IF(ISNUMBER(E43),E43*E81,"") | F54: =IF(ISNUMBER(F43),F43*F81,"") | G54: =IF(ISNUMBER(G43),G43*G81,"") -> 111.92984 | H54: =IF(ISNUMBER(H43),H43*H81,"") -> 172.04741 | I54: =IF(ISNUMBER(I43),I43*I81,"") -> 190.07147 | J54: =IF(ISNUMBER(J43),J43*J81,"") -> 47.64033 | ... BX54: =IF(ISNUMBER(BX43),BX43*BX81,"") -> 213.29816 | BY54: =BY47*(1+BY50) -> 239.76717 | BZ54: =BZ47*(1+BZ50) -> 265.28728 | CA54: =SUM(BW54,BX54,BY54,BZ54) -> 851.3799 | CB54: =CB47*(1+CB50) -> 932.95366 | CC54: =CC47*(1+CC50) -> 892.52397 | CD54: =CD47*(1+CD50) -> 900.70969 | CE54: =CE47*(1+CE50) -> 974.18508 | CN54: 2030E | CO54: =CP54+$CO$50 -> 4.5 | CP54: 4.5 | CQ54: =CP54+$CQ$50 -> 4.5
B55: Memo: operating revenue excl. fuel surcharge | C55: =IF(ISNUMBER(C54),C81-C54,"") -> 770.64418 | D55: =IF(ISNUMBER(D54),D81-D54,"") | E55: =IF(ISNUMBER(E54),E81-E54,"") | F55: =IF(ISNUMBER(F54),F81-F54,"") | G55: =IF(ISNUMBER(G54),G81-G54,"") -> 790.73016 | H55: =IF(ISNUMBER(H54),H81-H54,"") -> 858.17659 | I55: =IF(ISNUMBER(I54),I81-I54,"") -> 908.60753 | J55: =IF(ISNUMBER(J54),J81-J54,"") -> 226.15467 | ... BX55: =IF(ISNUMBER(BX54),BX81-BX54,"") -> 743.19584 | BY55: =BY81-BY54 -> 752.15373 | BZ55: =BZ81-BZ54 -> 715.70127 | CA55: =CA81-CA54 -> 2884.2495 | CB55: =CB81-CB54 -> 3146.1936 | CC55: =CC81-CC54 -> 3439.8317 | CD55: =CD81-CD54 -> 3738.4091 | CE55: =CE81-CE54 -> 4043.3699 | CN55: SWB (salaries, wages & benefits per shipment y/y) | CO55: -0.01 | CP55: Δ → | CQ55: 0.01 | CR55: Wage inflation ~3–4% p.a. less density/productivity (20–25% spare network capacity per mgmt; linehaul optimisation, technology).
B56: Memo: revenue excl. fuel surcharge y/y % | D56: =IF(AND(ISNUMBER(D55),ISNUMBER(C55)),IFERROR(D55/C55-1,""),"") | E56: =IF(AND(ISNUMBER(E55),ISNUMBER(D55)),IFERROR(E55/D55-1,""),"") | F56: =IF(AND(ISNUMBER(F55),ISNUMBER(E55)),IFERROR(F55/E55-1,""),"") | G56: =IF(AND(ISNUMBER(G55),ISNUMBER(F55)),IFERROR(G55/F55-1,""),"") | H56: =IF(AND(ISNUMBER(H55),ISNUMBER(G55)),IFERROR(H55/G55-1,""),"") -> 0.085296395 | I56: =IF(AND(ISNUMBER(I55),ISNUMBER(H55)),IFERROR(I55/H55-1,""),"") -> 0.058765226 | N56: =IF(AND(ISNUMBER(N55),ISNUMBER(I55)),IFERROR(N55/I55-1,""),"") -> 0.043053435 | O56: =IF(AND(ISNUMBER(O55),ISNUMBER(J55)),IFERROR(O55/J55-1,""),"") -> 0.098700151 | P56: =IF(AND(ISNUMBER(P55),ISNUMBER(K55)),IFERROR(P55/K55-1,""),"") -> 0.12528187 | Q56: =IF(AND(ISNUMBER(Q55),ISNUMBER(L55)),IFERROR(Q55/L55-1,""),"") -> 0.13462555 | R56: =IF(AND(ISNUMBER(R55),ISNUMBER(M55)),IFERROR(R55/M55-1,""),"") -> 0.11838072 | S56: =IF(AND(ISNUMBER(S55),ISNUMBER(N55)),IFERROR(S55/N55-1,""),"") -> 0.11964374 | T56: =IF(AND(ISNUMBER(T55),ISNUMBER(O55)),IFERROR(T55/O55-1,""),"") -> 0.029508005 | U56: =IF(AND(ISNUMBER(U55),ISNUMBER(P55)),IFERROR(U55/P55-1,""),"") -> 0.034499324 | ... CA56: =IF(AND(ISNUMBER(CA55),ISNUMBER(BV55)),IFERROR(CA55/BV55-1,""),"") -> 0.049144931 | CB56: =IF(AND(ISNUMBER(CB55),ISNUMBER(CA55)),IFERROR(CB55/CA55-1,""),"") -> 0.090818775 | CC56: =IF(AND(ISNUMBER(CC55),ISNUMBER(CB55)),IFERROR(CC55/CB55-1,""),"") -> 0.09333125 | CD56: =IF(AND(ISNUMBER(CD55),ISNUMBER(CC55)),IFERROR(CD55/CC55-1,""),"") -> 0.0868 | CE56: =IF(AND(ISNUMBER(CE55),ISNUMBER(CD55)),IFERROR(CE55/CD55-1,""),"") -> 0.081575 | CN56: 2027E | CO56: =CP56+$CO$55 -> 0.015 | CP56: 0.025 | CQ56: =CP56+$CQ$55 -> 0.035
CN57: 2028E | CO57: =CP57+$CO$55 -> 0.015 | CP57: 0.025 | CQ57: =CP57+$CQ$55 -> 0.035
B58: Q3/26E–Q4/26E outlook calibration (Jul–Aug interim LTL data; Q2-26 call operating-ratio guidance) | CF58: OUTLOOK CALIBRATION — Q3/Q4-26E | CN58: 2029E | CO58: =CP58+$CO$55 -> 0.02 | CP58: 0.03 | CQ58: =CP58+$CQ$55 -> 0.04
B59: Memo: Jul–Aug QTD LTL tonnage/workday y/y (8-K 3-Sep-2026) | BY59: 0.083 | CN59: 2030E | CO59: =CP59+$CO$55 -> 0.02 | CP59: 0.03 | CQ59: =CP59+$CQ$55 -> 0.04
B60: Memo: Jul–Aug QTD LTL shipments/workday y/y | BY60: 0.01 | CN60: CAPEX (gross capex % of revenue) | CO60: 0 | CP60: Δ → | CQ60: 0 | CR60: 2024 33% / 2025 17.6% (network build-out); FY26 guide ≈10% of revenue; 11–12% thereafter (fleet + selective real estate).
B61: Memo: Jul–Aug QTD LTL weight/shipment y/y | BY61: 0.072 | CN61: 2027E | CO61: =CP61+$CO$60 -> 0.11 | CP61: 0.11 | CQ61: =CP61+$CQ$60 -> 0.11
B62: Operating-ratio target: Q3/26E = Q2/26 OR + guided sequential change; Q4/26E solves FY26 target; 2026E = FY25 adj. OR − guided improvement | BY62: =$BX$94+CHOOSE(MATCH($CF$2,{"Bull","Base","Bear"},0),$CO$13,$CP$13,$CQ$13)/10000 -> 0.87909275 | BZ62: =($CA$62*$CA$81-$BW$92-$BX$92-$BY$92)/$BZ$81 -> 0.88387904 | CA62: =$CP$22-CHOOSE(MATCH($CF$2,{"Bull","Base","Bear"},0),$CO$12,$CP$12,$CQ$12)/10000 -> 0.886 | CF62: Q2-26 call: Q3 OR ~100 bps worse than Q2 (vs 150–200 bps typical), assuming fuel near late-Jul levels. Feb-26: FY26 OR improvement 100–200 bps (200 needs mid-single-digit shipment growth). | CN62: 2028E | CO62: =CP62+$CO$60 -> 0.11 | CP62: 0.11 | CQ62: =CP62+$CQ$60 -> 0.11
CN63: 2029E | CO63: =CP63+$CO$60 -> 0.12 | CP63: 0.12 | CQ63: =CP63+$CQ$60 -> 0.12
B64: OPERATING COST BUILD → OPERATING RATIO (drivers for each reported expense line) | CF64: COST BUILD — modelling logic | CN64: 2030E | CO64: =CP64+$CO$60 -> 0.12 | CP64: 0.12 | CQ64: =CP64+$CQ$60 -> 0.12
B66: Salaries, wages & benefits per shipment ($) | C66: =IF(ISNUMBER(C17),IFERROR(C82*1000/C17,""),"") -> 76.74158 | D66: =IF(ISNUMBER(D17),IFERROR(D82*1000/D17,""),"") -> 76.161295 | E66: =IF(ISNUMBER(E17),IFERROR(E82*1000/E17,""),"") -> 80.157526 | F66: =IF(ISNUMBER(F17),IFERROR(F82*1000/F17,""),"") -> 75.680305 | G66: =IF(ISNUMBER(G17),IFERROR(G82*1000/G17,""),"") -> 75.198781 | H66: =IF(ISNUMBER(H17),IFERROR(H82*1000/H17,""),"") -> 79.231848 | I66: =IF(ISNUMBER(I17),IFERROR(I82*1000/I17,""),"") -> 86.855441 | J66: =IF(ISNUMBER(J17),IFERROR(J82*1000/J17,""),"") -> 90.035526 | ... BX66: =IF(ISNUMBER(BX17),IFERROR(BX82*1000/BX17,""),"") -> 183.98348 | BY66: =IFERROR(BY82*1000/BY17,"") -> 196.29552 | BZ66: =IFERROR(BZ82*1000/BZ17,"") -> 204.773 | CA66: =IFERROR(CA82*1000/CA17,"") -> 191.1014 | CB66: =CA66*(1+CB67) -> 195.87894 | CC66: =CB66*(1+CC67) -> 200.77591 | CD66: =CC66*(1+CD67) -> 206.79919 | CE66: =CD66*(1+CE67) -> 213.00317 | CH66: =IFERROR((CE66/BV66)^(1/5)-1,"n/m") -> 0.037809733 | CI66: =IFERROR((BV66/AW66)^(1/5)-1,"n/m") -> 0.062468467 | CJ66: =IFERROR((BV66/X66)^(1/10)-1,"n/m") -> 0.053537304 | CK66: =IFERROR((BV66/C66)^(1/19)-1,"n/m") -> 0.044943912
B67: SWB per shipment y/y % | D67: =IF(AND(ISNUMBER(D66),ISNUMBER(C66)),IFERROR(D66/C66-1,""),"") -> -0.0075615501 | E67: =IF(AND(ISNUMBER(E66),ISNUMBER(D66)),IFERROR(E66/D66-1,""),"") -> 0.052470629 | F67: =IF(AND(ISNUMBER(F66),ISNUMBER(E66)),IFERROR(F66/E66-1,""),"") -> -0.055855281 | G67: =IF(AND(ISNUMBER(G66),ISNUMBER(F66)),IFERROR(G66/F66-1,""),"") -> -0.0063626046 | H67: =IF(AND(ISNUMBER(H66),ISNUMBER(G66)),IFERROR(H66/G66-1,""),"") -> 0.053632083 | I67: =IF(AND(ISNUMBER(I66),ISNUMBER(H66)),IFERROR(I66/H66-1,""),"") -> 0.096218789 | N67: =IF(AND(ISNUMBER(N66),ISNUMBER(I66)),IFERROR(N66/I66-1,""),"") -> 0.052917314 | O67: =IF(AND(ISNUMBER(O66),ISNUMBER(J66)),IFERROR(O66/J66-1,""),"") -> 0.052001718 | P67: =IF(AND(ISNUMBER(P66),ISNUMBER(K66)),IFERROR(P66/K66-1,""),"") -> 0.052459041 | Q67: =IF(AND(ISNUMBER(Q66),ISNUMBER(L66)),IFERROR(Q66/L66-1,""),"") -> 0.049670737 | R67: =IF(AND(ISNUMBER(R66),ISNUMBER(M66)),IFERROR(R66/M66-1,""),"") -> 0.055018296 | S67: =IF(AND(ISNUMBER(S66),ISNUMBER(N66)),IFERROR(S66/N66-1,""),"") -> 0.052396097 | T67: =IF(AND(ISNUMBER(T66),ISNUMBER(O66)),IFERROR(T66/O66-1,""),"") -> 0.079933018 | U67: =IF(AND(ISNUMBER(U66),ISNUMBER(P66)),IFERROR(U66/P66-1,""),"") -> 0.095029046 | ... CA67: =IF(AND(ISNUMBER(CA66),ISNUMBER(BV66)),IFERROR(CA66/BV66-1,""),"") -> 0.080106346 | CB67: =CHOOSE(MATCH($CF$2,{"Bull","Base","Bear"},0),$CO$56,$CP$56,$CQ$56) -> 0.025 | CC67: =CHOOSE(MATCH($CF$2,{"Bull","Base","Bear"},0),$CO$57,$CP$57,$CQ$57) -> 0.025 | CD67: =CHOOSE(MATCH($CF$2,{"Bull","Base","Bear"},0),$CO$58,$CP$58,$CQ$58) -> 0.03 | CE67: =CHOOSE(MATCH($CF$2,{"Bull","Base","Bear"},0),$CO$59,$CP$59,$CQ$59) -> 0.03 | CF67: 2027E+: scenario lever SWB (wage inflation − productivity). Saia moved its annual wage increase from Oct to Jul (Jul-26).
B68: SWB per shipment before outlook calibration (prior-year quarter × (1 + Q2/26 y/y)) | BY68: =BT66*(1+$BX$67) -> 182.90385 | BZ68: =BU66*(1+$BX$67) -> 195.93221
B69: Outlook calibration: implied Δ SWB/shipment vs run-rate (solves OR target) | BY69: =IFERROR(BY66/BY68-1,"") -> 0.073216958 | BZ69: =IFERROR(BZ66/BZ68-1,"") -> 0.04512168 | CF69: SWB is the balancing line in Q3/Q4-26E so the OR meets guidance; shown as a % shift vs run-rate for reasonableness.
B70: Purchased transportation % of revenue | C70: =IF(AND(ISNUMBER(C83),ISNUMBER(C81)),IFERROR(C83/C81,""),"") -> 0.080057114 | D70: =IF(AND(ISNUMBER(D83),ISNUMBER(D81)),IFERROR(D83/D81,""),"") -> 0.077985049 | E70: =IF(AND(ISNUMBER(E83),ISNUMBER(E81)),IFERROR(E83/E81,""),"") -> 0.076145575 | F70: =IF(AND(ISNUMBER(F83),ISNUMBER(F81)),IFERROR(F83/F81,""),"") -> 0.076227623 | G70: =IF(AND(ISNUMBER(G83),ISNUMBER(G81)),IFERROR(G83/G81,""),"") -> 0.089578579 | H70: =IF(AND(ISNUMBER(H83),ISNUMBER(H81)),IFERROR(H83/H81,""),"") -> 0.084601989 | I70: =IF(AND(ISNUMBER(I83),ISNUMBER(I81)),IFERROR(I83/I81,""),"") -> 0.067827819 | J70: =IF(AND(ISNUMBER(J83),ISNUMBER(J81)),IFERROR(J83/J81,""),"") -> 0.061253858 | ... BX70: =IF(AND(ISNUMBER(BX83),ISNUMBER(BX81)),IFERROR(BX83/BX81,""),"") -> 0.088845304 | BY70: =$BX$70 -> 0.088845304 | BZ70: =$BX$70 -> 0.088845304 | CA70: =IF(AND(ISNUMBER(CA83),ISNUMBER(CA81)),IFERROR(CA83/CA81,""),"") -> 0.086890775 | CB70: 0.08 | CC70: 0.08 | CD70: 0.08 | CE70: 0.08 | CF70: Q3/Q4-26E at Q2/26 8.9% (rail/truck PT miles 15.4%; diesel embedded in PT rates). 2027E+ 8.0% input as diesel normalises. | CH70: =IFERROR(AVERAGE(CA70,CB70,CC70,CD70,CE70),"n/m") -> 0.081378155 | CI70: =IFERROR(AVERAGE(BB70,BG70,BL70,BQ70,BV70),"n/m") -> 0.09031303 | CJ70: =IFERROR(AVERAGE(AC70,AH70,AM70,AR70,AW70,BB70,BG70,BL70,BQ70,BV70),"n/m") -> 0.078214298 | CK70: =IFERROR(AVERAGE(C70,D70,E70,F70,G70,H70,I70,N70,S70,X70,AC70,AH70,AM70,AR70,AW70,BB70,BG70,BL70,BQ70,BV70),"n/m") -> 0.076736827
B71: Fuel pass-through: Δ fuel cost in FOS per $1 of Δ fuel-surcharge revenue | BY71: =$CP$28 -> 0.31 | BZ71: =$CP$28 -> 0.31 | CB71: =$CP$28 -> 0.31 | CC71: =$CP$28 -> 0.31 | CD71: =$CP$28 -> 0.31 | CE71: =$CP$28 -> 0.31 | CF71: FOS forecast = prior-year FOS × (1 + revenue ex-fuel growth) + pass-through × (Δ fuel-surcharge revenue beyond volume). 0.31 calibrated on Q2/26 vs Q2/25.
B72: Fuel, operating expenses & supplies % of revenue | C72: =IF(AND(ISNUMBER(C84),ISNUMBER(C81)),IFERROR(C84/C81,""),"") -> 0.21561428 | D72: =IF(AND(ISNUMBER(D84),ISNUMBER(D81)),IFERROR(D84/D81,""),"") -> 0.2327555 | E72: =IF(AND(ISNUMBER(E84),ISNUMBER(E81)),IFERROR(E84/E81,""),"") -> 0.27150359 | F72: =IF(AND(ISNUMBER(F84),ISNUMBER(F81)),IFERROR(F84/F81,""),"") -> 0.23212635 | G72: =IF(AND(ISNUMBER(G84),ISNUMBER(G81)),IFERROR(G84/G81,""),"") -> 0.25898013 | H72: =IF(AND(ISNUMBER(H84),ISNUMBER(H81)),IFERROR(H84/H81,""),"") -> 0.2849225 | I72: =IF(AND(ISNUMBER(I84),ISNUMBER(I81)),IFERROR(I84/I81,""),"") -> 0.28049685 | J72: =IF(AND(ISNUMBER(J84),ISNUMBER(J81)),IFERROR(J84/J81,""),"") -> 0.28854435 | ... CE72: =IF(AND(ISNUMBER(CE84),ISNUMBER(CE81)),IFERROR(CE84/CE81,""),"") -> 0.20830888 | CH72: =IFERROR(AVERAGE(CA72,CB72,CC72,CD72,CE72),"n/m") -> 0.2103322 | CI72: =IFERROR(AVERAGE(BB72,BG72,BL72,BQ72,BV72),"n/m") -> 0.19221354 | CJ72: =IFERROR(AVERAGE(AC72,AH72,AM72,AR72,AW72,BB72,BG72,BL72,BQ72,BV72),"n/m") -> 0.18956388 | CK72: =IFERROR(AVERAGE(C72,D72,E72,F72,G72,H72,I72,N72,S72,X72,AC72,AH72,AM72,AR72,AW72,BB72,BG72,BL72,BQ72,BV72),"n/m") -> 0.22012131
B73: Operating taxes & licenses % of revenue excl. fuel surcharge | C73: =IF(ISNUMBER(C55),IFERROR(C85/C55,""),"") -> 0.037440106 | D73: =IF(ISNUMBER(D55),IFERROR(D85/D55,""),"") | E73: =IF(ISNUMBER(E55),IFERROR(E85/E55,""),"") | F73: =IF(ISNUMBER(F55),IFERROR(F85/F55,""),"") | G73: =IF(ISNUMBER(G55),IFERROR(G85/G55,""),"") -> 0.046768167 | H73: =IF(ISNUMBER(H55),IFERROR(H85/H55,""),"") -> 0.04454561 | I73: =IF(ISNUMBER(I55),IFERROR(I85/I55,""),"") -> 0.042133703 | J73: =IF(ISNUMBER(J55),IFERROR(J85/J55,""),"") -> 0.042355968 | ... BX73: =IF(ISNUMBER(BX55),IFERROR(BX85/BX55,""),"") -> 0.030191235 | BY73: =BT73 -> 0.029306839 | BZ73: =BU73 -> 0.030968112 | CA73: =IFERROR(CA85/CA55,"") -> 0.030814659 | CB73: =$CA$73 -> 0.030814659 | CC73: =$CA$73 -> 0.030814659 | CD73: =$CA$73 -> 0.030814659 | CE73: =$CA$73 -> 0.030814659
B74: Claims & insurance % of revenue | C74: =IF(AND(ISNUMBER(C86),ISNUMBER(C81)),IFERROR(C86/C81,""),"") -> 0.032111329 | D74: =IF(AND(ISNUMBER(D86),ISNUMBER(D81)),IFERROR(D86/D81,""),"") -> 0.037653042 | E74: =IF(AND(ISNUMBER(E86),ISNUMBER(E81)),IFERROR(E86/E81,""),"") -> 0.031889878 | F74: =IF(AND(ISNUMBER(F86),ISNUMBER(F81)),IFERROR(F86/F81,""),"") -> 0.035108421 | G74: =IF(AND(ISNUMBER(G86),ISNUMBER(G81)),IFERROR(G86/G81,""),"") -> 0.024228392 | H74: =IF(AND(ISNUMBER(H86),ISNUMBER(H81)),IFERROR(H86/H81,""),"") -> 0.031126241 | I74: =IF(AND(ISNUMBER(I86),ISNUMBER(I81)),IFERROR(I86/I81,""),"") -> 0.022492466 | J74: =IF(AND(ISNUMBER(J86),ISNUMBER(J81)),IFERROR(J86/J81,""),"") -> 0.020434997 | ... BX74: =IF(AND(ISNUMBER(BX86),ISNUMBER(BX81)),IFERROR(BX86/BX81,""),"") -> 0.02551924 | BY74: =($BW$86+$BX$86)/($BW$81+$BX$81) -> 0.02683977 | BZ74: =($BW$86+$BX$86)/($BW$81+$BX$81) -> 0.02683977 | CA74: =IF(AND(ISNUMBER(CA86),ISNUMBER(CA81)),IFERROR(CA86/CA81,""),"") -> 0.02683977 | CB74: =$CA$74 -> 0.02683977 | CC74: =$CA$74 -> 0.02683977 | CD74: =$CA$74 -> 0.02683977 | CE74: =$CA$74 -> 0.02683977 | CF74: Q3/Q4-26E at the 1H/26 ratio (record cargo claims ratio 0.3% in Q2/26). | CH74: =IFERROR(AVERAGE(CA74,CB74,CC74,CD74,CE74),"n/m") -> 0.02683977 | CI74: =IFERROR(AVERAGE(BB74,BG74,BL74,BQ74,BV74),"n/m") -> 0.024710982 | CJ74: =IFERROR(AVERAGE(AC74,AH74,AM74,AR74,AW74,BB74,BG74,BL74,BQ74,BV74),"n/m") -> 0.02576795 | CK74: =IFERROR(AVERAGE(C74,D74,E74,F74,G74,H74,I74,N74,S74,X74,AC74,AH74,AM74,AR74,AW74,BB74,BG74,BL74,BQ74,BV74),"n/m") -> 0.027308163
B75: D&A % of opening net property & equipment | D75: =IF(ISNUMBER(C237),IFERROR(D87/C237,""),"") -> 0.12287506 | E75: =IF(ISNUMBER(D237),IFERROR(E87/D237,""),"") -> 0.11090321 | F75: =IF(ISNUMBER(E237),IFERROR(F87/E237,""),"") -> 0.11057273 | G75: =IF(ISNUMBER(F237),IFERROR(G87/F237,""),"") -> 0.11182274 | H75: =IF(ISNUMBER(G237),IFERROR(H87/G237,""),"") -> 0.12813039 | I75: =IF(ISNUMBER(H237),IFERROR(I87/H237,""),"") -> 0.14789416 | N75: =IF(ISNUMBER(I237),IFERROR(N87/I237,""),"") -> 0.14255856 | S75: =IF(ISNUMBER(N237),IFERROR(S87/N237,""),"") -> 0.13655356 | X75: =IF(ISNUMBER(S237),IFERROR(X87/S237,""),"") -> 0.13443884 | AC75: =IF(ISNUMBER(X237),IFERROR(AC87/X237,""),"") -> 0.14140017 | AH75: =IF(ISNUMBER(AC237),IFERROR(AH87/AC237,""),"") -> 0.1441802 | AM75: =IF(ISNUMBER(AH237),IFERROR(AM87/AH237,""),"") -> 0.13883634 | AR75: =IF(ISNUMBER(AM237),IFERROR(AR87/AM237,""),"") -> 0.13340119 | AW75: =IF(ISNUMBER(AR237),IFERROR(AW87/AR237,""),"") -> 0.12792621 | BB75: =IF(ISNUMBER(AW237),IFERROR(BB87/AW237,""),"") -> 0.12473295 | BG75: =IF(ISNUMBER(BB237),IFERROR(BG87/BB237,""),"") -> 0.1227713 | BL75: =IF(ISNUMBER(BG237),IFERROR(BL87/BG237,""),"") -> 0.12062767 | BQ75: =IF(ISNUMBER(BL237),IFERROR(BQ87/BL237,""),"") -> 0.11915389 | BV75: =IF(ISNUMBER(BQ237),IFERROR(BV87/BQ237,""),"") -> 0.097215221 | CA75: =IFERROR(CA87/BV237,"") -> 0.0902367 | CB75: =$BV$75 -> 0.097215221 | CC75: =$BV$75 -> 0.097215221 | CD75: =$BV$75 -> 0.097215221 | CE75: =$BV$75 -> 0.097215221 | CF75: 2027E+ D&A = opening net PP&E × FY25 rate (links capex to depreciation). Q3/Q4-26E = prior quarter × (1 + sequential growth input). | CH75: =IFERROR(AVERAGE(CA75,CB75,CC75,CD75,CE75),"n/m") -> 0.095819516 | CI75: =IFERROR(AVERAGE(BB75,BG75,BL75,BQ75,BV75),"n/m") -> 0.11690021 | CJ75: =IFERROR(AVERAGE(AC75,AH75,AM75,AR75,AW75,BB75,BG75,BL75,BQ75,BV75),"n/m") -> 0.12702451 | CK75: =IFERROR(AVERAGE(C75,D75,E75,F75,G75,H75,I75,N75,S75,X75,AC75,AH75,AM75,AR75,AW75,BB75,BG75,BL75,BQ75,BV75),"n/m") -> 0.1271576
B76: Memo: operating cost per shipment ($) | C76: =IF(ISNUMBER(C17),IFERROR(C92*1000/C17,""),"") -> 133.54016 | D76: =IF(ISNUMBER(D17),IFERROR(D92*1000/D17,""),"") -> 136.17233 | E76: =IF(ISNUMBER(E17),IFERROR(E92*1000/E17,""),"") -> 155.03308 | F76: =IF(ISNUMBER(F17),IFERROR(F92*1000/F17,""),"") -> 132.67486 | G76: =IF(ISNUMBER(G17),IFERROR(G92*1000/G17,""),"") -> 139.17175 | H76: =IF(ISNUMBER(H17),IFERROR(H92*1000/H17,""),"") -> 154.4748 | I76: =IF(ISNUMBER(I17),IFERROR(I92*1000/I17,""),"") -> 165.20175 | J76: =IF(ISNUMBER(J17),IFERROR(J92*1000/J17,""),"") -> 170.56776 | ... BX76: =IF(ISNUMBER(BX17),IFERROR(BX92*1000/BX17,""),"") -> 352.08895 | BY76: =IFERROR(BY92*1000/BY17,"") -> 369.87544 | BZ76: =IFERROR(BZ92*1000/BZ17,"") -> 393.06729 | CA76: =IFERROR(CA92*1000/CA17,"") -> 363.05463 | CB76: =IFERROR(CB92*1000/CB17,"") -> 374.31196 | CC76: =IFERROR(CC92*1000/CC17,"") -> 381.80488 | CD76: =IFERROR(CD92*1000/CD17,"") -> 392.17969 | CE76: =IFERROR(CE92*1000/CE17,"") -> 406.38803 | CH76: =IFERROR((CE76/BV76)^(1/5)-1,"n/m") -> 0.047146292 | CI76: =IFERROR((BV76/AW76)^(1/5)-1,"n/m") -> 0.076983609 | CJ76: =IFERROR((BV76/X76)^(1/10)-1,"n/m") -> 0.061744757 | CK76: =IFERROR((BV76/C76)^(1/19)-1,"n/m") -> 0.047546417
B77: Memo: cost per shipment y/y % | D77: =IF(AND(ISNUMBER(D76),ISNUMBER(C76)),IFERROR(D76/C76-1,""),"") -> 0.019710725 | E77: =IF(AND(ISNUMBER(E76),ISNUMBER(D76)),IFERROR(E76/D76-1,""),"") -> 0.13850653 | F77: =IF(AND(ISNUMBER(F76),ISNUMBER(E76)),IFERROR(F76/E76-1,""),"") -> -0.14421583 | G77: =IF(AND(ISNUMBER(G76),ISNUMBER(F76)),IFERROR(G76/F76-1,""),"") -> 0.048968475 | H77: =IF(AND(ISNUMBER(H76),ISNUMBER(G76)),IFERROR(H76/G76-1,""),"") -> 0.10995802 | I77: =IF(AND(ISNUMBER(I76),ISNUMBER(H76)),IFERROR(I76/H76-1,""),"") -> 0.069441436 | N77: =IF(AND(ISNUMBER(N76),ISNUMBER(I76)),IFERROR(N76/I76-1,""),"") -> 0.029505081 | O77: =IF(AND(ISNUMBER(O76),ISNUMBER(J76)),IFERROR(O76/J76-1,""),"") -> 0.051672716 | P77: =IF(AND(ISNUMBER(P76),ISNUMBER(K76)),IFERROR(P76/K76-1,""),"") -> 0.083079534 | Q77: =IF(AND(ISNUMBER(Q76),ISNUMBER(L76)),IFERROR(Q76/L76-1,""),"") -> 0.046861074 | R77: =IF(AND(ISNUMBER(R76),ISNUMBER(M76)),IFERROR(R76/M76-1,""),"") -> 0.01790713 | S77: =IF(AND(ISNUMBER(S76),ISNUMBER(N76)),IFERROR(S76/N76-1,""),"") -> 0.049811012 | T77: =IF(AND(ISNUMBER(T76),ISNUMBER(O76)),IFERROR(T76/O76-1,""),"") -> -0.017415428 | U77: =IF(AND(ISNUMBER(U76),ISNUMBER(P76)),IFERROR(U76/P76-1,""),"") -> -0.022595612 | ... CA77: =IF(AND(ISNUMBER(CA76),ISNUMBER(BV76)),IFERROR(CA76/BV76-1,""),"") -> 0.12478074 | CB77: =IF(AND(ISNUMBER(CB76),ISNUMBER(CA76)),IFERROR(CB76/CA76-1,""),"") -> 0.031007239 | CC77: =IF(AND(ISNUMBER(CC76),ISNUMBER(CB76)),IFERROR(CC76/CB76-1,""),"") -> 0.020017852 | CD77: =IF(AND(ISNUMBER(CD76),ISNUMBER(CC76)),IFERROR(CD76/CC76-1,""),"") -> 0.027173066 | CE77: =IF(AND(ISNUMBER(CE76),ISNUMBER(CD76)),IFERROR(CE76/CD76-1,""),"") -> 0.036229169
B78: Stock-based compensation % of revenue | C78: =IF(AND(ISNUMBER(C109),ISNUMBER(C81)),IFERROR(C109/C81,""),"") -> 0.00073279085 | D78: =IF(AND(ISNUMBER(D109),ISNUMBER(D81)),IFERROR(D109/D81,""),"") -> 0.0010521215 | E78: =IF(AND(ISNUMBER(E109),ISNUMBER(E81)),IFERROR(E109/E81,""),"") -> 0.0017119216 | F78: =IF(AND(ISNUMBER(F109),ISNUMBER(F81)),IFERROR(F109/F81,""),"") -> 0.0021621851 | G78: =IF(AND(ISNUMBER(G109),ISNUMBER(G81)),IFERROR(G109/G81,""),"") -> 0.0020960273 | H78: =IF(AND(ISNUMBER(H109),ISNUMBER(H81)),IFERROR(H109/H81,""),"") -> 0.0017423395 | I78: =IF(AND(ISNUMBER(I109),ISNUMBER(I81)),IFERROR(I109/I81,""),"") -> 0.0024456643 | J78: =IF(AND(ISNUMBER(J109),ISNUMBER(J81)),IFERROR(J109/J81,""),"") -> 0.0026497927 | ... BX78: =IF(AND(ISNUMBER(BX109),ISNUMBER(BX81)),IFERROR(BX109/BX81,""),"") -> 0.0045144036 | BY78: =($BW$109+$BX$109)/($BW$81+$BX$81) -> 0.0046626804 | BZ78: =($BW$109+$BX$109)/($BW$81+$BX$81) -> 0.0046626804 | CA78: =IF(AND(ISNUMBER(CA109),ISNUMBER(CA81)),IFERROR(CA109/CA81,""),"") -> 0.0046626804 | CB78: =$CA$78 -> 0.0046626804 | CC78: =$CA$78 -> 0.0046626804 | CD78: =$CA$78 -> 0.0046626804 | CE78: =$CA$78 -> 0.0046626804
B80: CONDENSED CONSOLIDATED STATEMENTS OF OPERATIONS (US GAAP; continuing operations; Jevic = discontinued from Q2/06) | CF80: CONSOLIDATED IS — forecast logic
B81: Operating revenue | C81: 874.738 | D81: 976.123 | E81: 1030.421 | F81: 849.141 | G81: 902.66 | H81: 1030.224 | I81: 1098.679 | J81: 273.795 | K81: 292.557 | L81: 293.087 | M81: 279.655 | N81: 1139.094 | O81: 299.73 | P81: 330.399 | Q81: 332.544 | R81: 309.648 | S81: 1272.321 | T81: 293.022 | U81: 323.48 | V81: 317.199 | W81: 287.61 | X81: 1221.311 | Y81: 289.911 | Z81: 311.905 | AA81: 316.442 | AB81: 300.223 | AC81: 1218.481 | AD81: 317.037 | AE81: 358.16 | AF81: 350.062 | AG81: 353.251 | AH81: 1378.51 | AI81: 392.805 | AJ81: 428.732 | AK81: 425.562 | AL81: 406.75 | AM81: 1653.849 | AN81: 410.584 | AO81: 464.195 | AP81: 468.891 | AQ81: 443.065 | AR81: 1786.735 | AS81: 446.396 | AT81: 418.114 | AU81: 481.374 | AV81: 476.482 | AW81: 1822.366 | AX81: 484.074 | AY81: 571.333 | AZ81: 616.216 | BA81: 617.081 | BB81: 2288.704 | BC81: 661.216 | BD81: 745.554 | BE81: 729.561 | BF81: 655.726 | BG81: 2792.057 | BH81: 660.535 | BI81: 694.622 | BJ81: 775.144 | BK81: 751.132 | BL81: 2881.433 | BM81: 754.775 | BN81: 823.244 | BO81: 842.103 | BP81: 788.952 | BQ81: 3209.074 | BR81: 787.575 | BS81: 817.115 | BT81: 839.644 | BU81: 789.952 | BV81: 3234.286 | BW81: 806.226 | BX81: 956.494 | BY81: =BY51 -> 991.9209 | BZ81: =BZ51 -> 980.98855 | CA81: =SUM(BW81,BX81,BY81,BZ81) -> 3735.6295 | CB81: =CB51 -> 4079.1472 | CC81: =CC51 -> 4332.3557 | CD81: =CD51 -> 4639.1188 | CE81: =CE51 -> 5017.5549 | CF81: Forecast linked to the LTL build. | CH81: =IFERROR((CE81/BV81)^(1/5)-1,"n/m") -> 0.091799128 | CI81: =IFERROR((BV81/AW81)^(1/5)-1,"n/m") -> 0.12157563 | CJ81: =IFERROR((BV81/X81)^(1/10)-1,"n/m") -> 0.10228834 | CK81: =IFERROR((BV81/C81)^(1/19)-1,"n/m") -> 0.071246698
B82: Salaries, wages & employees' benefits | C82: 473.956 | D82: 524.599 | E82: 537.857 | F82: 486.473 | G82: 481.197 | H82: 513.977 | I82: 546.755 | J82: 136.854 | K82: 144.309 | L82: 147.305 | M82: 144.019 | N82: 572.487 | O82: 150.222 | P82: 160.204 | Q82: 166.353 | R82: 162.854 | S82: 639.633 | T82: 157.729 | U82: 170.465 | V82: 177.623 | W82: 164.356 | X82: 670.173 | Y82: 170.266 | Z82: 175.924 | AA82: 178.687 | AB82: 171.169 | AC82: 696.046 | AD82: 180.903 | AE82: 196.388 | AF82: 194.92 | AG82: 194.579 | AH82: 766.79 | AI82: 211.124 | AJ82: 220.406 | AK82: 224.635 | AL82: 216.557 | AM82: 872.722 | AN82: 220.352 | AO82: 237.689 | AP82: 250.162 | AQ82: 239.708 | AR82: 947.911 | AS82: 238.645 | AT82: 224.277 | AU82: 252.092 | AV82: 248.246 | AW82: 963.26 | AX82: 244.437 | AY82: 268.786 | AZ82: 277.087 | BA82: 273.393 | BB82: 1063.703 | BC82: 289.463 | BD82: 295.052 | BE82: 297.247 | BF82: 287.777 | BG82: 1169.539 | BH82: 298.956 | BI82: 311.888 | BJ82: 344.605 | BK82: 345.831 | BL82: 1301.28 | BM82: 341.713 | BN82: 372.24 | BO82: 398.134 | BP82: 375.76 | BQ82: 1487.847 | BR82: 389.256 | BS82: 390.975 | BT82: 401.058 | BU82: 398.504 | BV82: 1579.793 | BW82: 393.296 | BX82: 434.385 | BY82: =BY62*BY81-(BY83+BY84+BY85+BY86+BY87+BY88) -> 462.77152 | BZ82: =BZ62*BZ81-(BZ83+BZ84+BZ85+BZ86+BZ87+BZ88) -> 451.71298 | CA82: =SUM(BW82,BX82,BY82,BZ82) -> 1742.1655 | CB82: =CB17*CB66/1000 -> 1856.4412 | CC82: =CC17*CC66/1000 -> 1978.5876 | CD82: =CD17*CD66/1000 -> 2119.4631 | CE82: =CE17*CE66/1000 -> 2259.4536 | CF82: Q3/Q4-26E: balancing line to the OR target. 2027E+: shipments × SWB per shipment.
B83: Purchased transportation | C83: 70.029 | D83: 76.123 | E83: 78.462 | F83: 64.728 | G83: 80.859 | H83: 87.159 | I83: 74.521 | J83: 16.771 | K83: 19.338 | L83: 18.914 | M83: 17.952 | N83: 72.975 | O83: 21.991 | P83: 27.926 | Q83: 27.479 | R83: 22.214 | S83: 99.61 | T83: 17.714 | U83: 20.184 | V83: 19.314 | W83: 13.399 | X83: 70.611 | Y83: 12.467 | Z83: 14.315 | AA83: 15.657 | AB83: 13.89 | AC83: 56.329 | AD83: 14.775 | AE83: 22.363 | AF83: 23.074 | AG83: 21.27 | AH83: 81.482 | AI83: 29.916 | AJ83: 34.113 | AK83: 31.216 | AL83: 28.659 | AM83: 123.904 | AN83: 28.418 | AO83: 34.154 | AP83: 35.843 | AQ83: 31.565 | AR83: 129.98 | AS83: 30.059 | AT83: 26.406 | AU83: 40.053 | AV83: 44.851 | AW83: 141.369 | AX83: 45.031 | AY83: 62.481 | AZ83: 72.193 | BA83: 70.005 | BB83: 249.71 | BC83: 78.248 | BD83: 91.819 | BE83: 85.452 | BF83: 60.377 | BG83: 315.896 | BH83: 46.727 | BI83: 49.771 | BJ83: 76.746 | BK83: 65.444 | BL83: 238.688 | BM83: 52.507 | BN83: 61.047 | BO83: 65.584 | BP83: 58.168 | BQ83: 237.306 | BR83: 59.849 | BS83: 57.699 | BT83: 59.329 | BU83: 57.718 | BV83: 234.595 | BW83: 64.328 | BX83: 84.98 | BY83: =BY81*BY70 -> 88.127514 | BZ83: =BZ81*BZ70 -> 87.156226 | CA83: =SUM(BW83,BX83,BY83,BZ83) -> 324.59174 | CB83: =CB81*CB70 -> 326.33178 | CC83: =CC81*CC70 -> 346.58846 | CD83: =CD81*CD70 -> 371.12951 | CE83: =CE81*CE70 -> 401.40439
B84: Fuel, operating expenses & supplies | C84: 188.606 | D84: 227.198 | E84: 279.763 | F84: 197.108 | G84: 233.771 | H84: 293.534 | I84: 308.176 | J84: 79.002 | K84: 78.154 | L84: 75.803 | M84: 73.405 | N84: 306.364 | O84: 79.959 | P84: 81.276 | Q84: 80.206 | R84: 73.347 | S84: 314.788 | T84: 67.145 | U84: 69.165 | V84: 65.122 | W84: 59.955 | X84: 261.387 | Y84: 54.04 | Z84: 59.026 | AA84: 59.345 | AB84: 57.953 | AC84: 230.364 | AD84: 63.99 | AE84: 66.092 | AF84: 66.679 | AG84: 71.329 | AH84: 268.09 | AI84: 78.794 | AJ84: 84.745 | AK84: 81.643 | AL84: 79.818 | AM84: 325 | AN84: 83.543 | AO84: 85.328 | AP84: 84.259 | AQ84: 86.926 | AR84: 340.056 | AS84: 82.899 | AT84: 65.902 | AU84: 74.106 | AV84: 76.327 | AW84: 299.234 | AX84: 84.901 | AY84: 90.664 | AZ84: 98.834 | BA84: 107.505 | BB84: 381.904 | BC84: 122.771 | BD84: 145.53 | BE84: 145.461 | BF84: 144.694 | BG84: 558.456 | BH84: 141.625 | BI84: 133.49 | BJ84: 144.282 | BK84: 144.291 | BL84: 563.688 | BM84: 156.325 | BN84: 160.877 | BO84: 158.733 | BP84: 153.467 | BQ84: 629.402 | BR84: 166.671 | BS84: 161.634 | BT84: 165.727 | BU84: 160.676 | BV84: 654.708 | BW84: 173.489 | BX84: 198.743 | BY84: =BT84*(BY55/BT55)+BY71*(BY54-BT54*(BY55/BT55)) -> 207.60245 | BZ84: =BU84*(BZ55/BU55)+BZ71*(BZ54-BU54*(BZ55/BU55)) -> 214.24156 | CA84: =SUM(BW84,BX84,BY84,BZ84) -> 794.07601 | CB84: =CA84*(CB55/CA55)+CB71*(CB54-CA54*(CB55/CA55)) -> 867.51129 | CC84: =CB84*(CC55/CB55)+CC71*(CC54-CB54*(CC55/CB55)) -> 908.95114 | CD84: =CC84*(CD55/CC55)+CD71*(CD54-CC54*(CD55/CC55)) -> 966.36964 | CE84: =CD84*(CE55/CD55)+CE71*(CE54-CD54*(CE55/CD55)) -> 1045.2012
B85: Operating taxes & licenses | C85: 28.853 | D85: 34.474 | E85: 35.356 | F85: 35.465 | G85: 36.981 | H85: 38.228 | I85: 38.283 | J85: 9.579 | K85: 9.33 | L85: 9.074 | M85: 8.53 | N85: 36.513 | O85: 8.975 | P85: 8.993 | Q85: 9.033 | R85: 9.027 | S85: 36.028 | T85: 9.096 | U85: 9.411 | V85: 9.258 | W85: 9.238 | X85: 37.003 | Y85: 10.04 | Z85: 10.126 | AA85: 10.061 | AB85: 9.798 | AC85: 40.025 | AD85: 10.582 | AE85: 10.875 | AF85: 10.631 | AG85: 11.242 | AH85: 43.33 | AI85: 12.15 | AJ85: 12.794 | AK85: 12.366 | AL85: 12.779 | AM85: 50.089 | AN85: 13.202 | AO85: 13.529 | AP85: 13.634 | AQ85: 14.032 | AR85: 54.397 | AS85: 14.396 | AT85: 13.743 | AU85: 14.061 | AV85: 14.094 | AW85: 56.294 | AX85: 14.338 | AY85: 14.559 | AZ85: 14.572 | BA85: 15.626 | BB85: 59.095 | BC85: 16.573 | BD85: 15.979 | BE85: 16.261 | BF85: 15.011 | BG85: 63.824 | BH85: 17.065 | BI85: 17.457 | BJ85: 17.018 | BK85: 18.002 | BL85: 69.542 | BM85: 19.766 | BN85: 19.693 | BO85: 19.942 | BP85: 20.727 | BQ85: 80.128 | BR85: 20.437 | BS85: 22.014 | BT85: 20.867 | BU85: 20.769 | BV85: 84.087 | BW85: 22.232 | BX85: 22.438 | BY85: =BY55*BY73 -> 22.043248 | BZ85: =BZ55*BZ73 -> 22.163917 | CA85: =SUM(BW85,BX85,BY85,BZ85) -> 88.877165 | CB85: =CB55*CB73 -> 96.948881 | CC85: =CC55*CC73 -> 105.99724 | CD85: =CD55*CD73 -> 115.1978 | CE85: =CE55*CE73 -> 124.59506
B86: Claims & insurance | C86: 28.089 | D86: 36.754 | E86: 32.86 | F86: 29.812 | G86: 21.87 | H86: 32.067 | I86: 24.712 | J86: 5.595 | K86: 5.883 | L86: 6.607 | M86: 7.409 | N86: 25.494 | O86: 9.518 | P86: 14.177 | Q86: 6.956 | R86: 6.912 | S86: 37.563 | T86: 4.837 | U86: 6.361 | V86: 9.146 | W86: 6.488 | X86: 26.832 | Y86: 8.081 | Z86: 10.88 | AA86: 9.988 | AB86: 10.676 | AC86: 39.625 | AD86: 9.049 | AE86: 10.426 | AF86: 8.535 | AG86: 9.152 | AH86: 37.162 | AI86: 10.191 | AJ86: 9.91 | AK86: 9.985 | AL86: 8.339 | AM86: 38.425 | AN86: 9.53 | AO86: 13.156 | AP86: 7.85 | AQ86: 12.537 | AR86: 43.073 | AS86: 10.421 | AT86: 18.293 | AU86: 11.938 | AV86: 9.109 | AW86: 49.761 | AX86: 11.48 | AY86: 17.328 | AZ86: 15.518 | BA86: 17.019 | BB86: 61.345 | BC86: 10.736 | BD86: 14.216 | BE86: 15.988 | BF86: 15.661 | BG86: 56.601 | BH86: 14.059 | BI86: 16.956 | BJ86: 18.024 | BK86: 18.945 | BL86: 67.984 | BM86: 17.463 | BN86: 18.828 | BO86: 19.274 | BP86: 22.084 | BQ86: 77.649 | BR86: 21.545 | BS86: 22.826 | BT86: 23.614 | BU86: 24.803 | BV86: 92.788 | BW86: 22.902 | BX86: 24.409 | BY86: =BY81*BY74 -> 26.622929 | BZ86: =BZ81*BZ74 -> 26.329507 | CA86: =SUM(BW86,BX86,BY86,BZ86) -> 100.26344 | CB86: =CB81*CB74 -> 109.48337 | CC86: =CC81*CC74 -> 116.27943 | CD86: =CD81*CD74 -> 124.51288 | CE86: =CE81*CE74 -> 134.67002
B87: Depreciation & amortization | C87: 32.55 | D87: 38.685 | E87: 40.898 | F87: 39.342 | G87: 36.159 | H87: 37.278 | I87: 47.985 | J87: 11.634 | K87: 12.386 | L87: 13.745 | M87: 13.799 | N87: 51.564 | O87: 13.841 | P87: 15.087 | Q87: 15.336 | R87: 14.758 | S87: 59.022 | T87: 15.199 | U87: 16.561 | V87: 16.765 | W87: 16.495 | X87: 65.02 | Y87: 17.243 | Z87: 19.74 | AA87: 19.927 | AB87: 19.33 | AC87: 76.24 | AD87: 20.087 | AE87: 22.182 | AF87: 22.338 | AG87: 22.495 | AH87: 87.102 | AI87: 23.03 | AJ87: 25.241 | AK87: 26.694 | AL87: 27.188 | AM87: 102.153 | AN87: 26.782 | AO87: 29.143 | AP87: 31.333 | AQ87: 31.877 | AR87: 119.135 | AS87: 32.59 | AT87: 33.664 | AU87: 34.224 | AV87: 34.177 | AW87: 134.655 | AX87: 35.372 | AY87: 34.659 | AZ87: 35.742 | BA87: 35.927 | BB87: 141.7 | BC87: 39.952 | BD87: 36.944 | BE87: 40.682 | BF87: 39.625 | BG87: 157.203 | BH87: 42.88 | BI87: 44.658 | BJ87: 45.618 | BK87: 45.689 | BL87: 178.845 | BM87: 48.849 | BN87: 52.536 | BO87: 54.656 | BP87: 54.064 | BQ87: 210.105 | BR87: 59.043 | BS87: 62.546 | BT87: 64.037 | BU87: 62.947 | BV87: 248.573 | BW87: 62.19 | BX87: 64.181 | BY87: =BX87*(1+$CP$24) -> 64.82281 | BZ87: =BY87*(1+$CP$24) -> 65.471038 | CA87: =SUM(BW87,BX87,BY87,BZ87) -> 256.66485 | CB87: =CA237*CB75 -> 290.82226 | CC87: =CB237*CC75 -> 306.17098 | CD87: =CC237*CD75 -> 322.73531 | CE87: =CD237*CE75 -> 345.47968
B88: Other operating (gains) losses, net (property disposals; Q3/25 incl. $16.4m terminal-sale gain & $1.9m impairment) | C88: -1.416 | D88: -2.305 | E88: -0.435 | F88: -0.094 | G88: -0.277 | H88: -0.165 | I88: -0.487 | J88: -0.172 | K88: -0.102 | L88: -0.296 | M88: -0.151 | N88: -0.721 | O88: -0.007 | P88: -0.005 | Q88: 0.032 | R88: -0.036 | S88: -0.016 | T88: 0.069 | U88: 0.052 | V88: 0.126 | W88: 0.063 | X88: 0.31 | Y88: 0.19 | Z88: 0.173 | AA88: 0.133 | AB88: 0.22 | AC88: 0.716 | AD88: 0.132 | AE88: 0.116 | AF88: -0.717 | AG88: 0.286 | AH88: -0.183 | AI88: 0.021 | AJ88: -0.042 | AK88: 0.326 | AL88: 0.074 | AM88: 0.379 | AN88: 0.126 | AO88: 0.03 | AP88: 0.451 | AQ88: -1.01 | AR88: -0.403 | AS88: -1.39 | AT88: 0.148 | AU88: -0.316 | AV88: -0.97 | AW88: -2.528 | AX88: -0.199 | AY88: -0.069 | AZ88: -3.847 | BA88: 0.221 | BB88: -3.894 | BC88: 0.024 | BD88: 0.021 | BE88: 0.115 | BF88: -0.11 | BG88: 0.05 | BH88: 0.08 | BI88: 0.147 | BJ88: 0.416 | BK88: 0.267 | BL88: 0.91 | BM88: 0.24 | BN88: 0.43 | BO88: 0.609 | BP88: 3.198 | BQ88: 4.477 | BR88: 0.606 | BS88: 0.022 | BT88: -13.598 | BU88: 0.512 | BV88: -12.458 | BW88: 0.983 | BX88: 2.146 | BY88: 0 | BZ88: 0 | CA88: =SUM(BW88,BX88,BY88,BZ88) -> 3.129 | CB88: 0 | CC88: 0 | CD88: 0 | CE88: 0
B89: Restructuring charges (2006: Jevic separation / HQ) | C89: 2.587 | D89: 0
B90: Integration charges (The Connection, Madison Freight; 2006–07) | C90: 1.49 | D90: 2.427 | E90: 0
B91: Goodwill impairment charge (Q4/08) | E91: 35.511 | F91: 0
B92: Total operating expenses | C92: =C82+C83+C84+C85+C86+C87+N(C88)+N(C89)+N(C90)+N(C91) -> 824.744 | D92: =D82+D83+D84+D85+D86+D87+N(D88)+N(D89)+N(D90)+N(D91) -> 937.955 | E92: =E82+E83+E84+E85+E86+E87+N(E88)+N(E89)+N(E90)+N(E91) -> 1040.272 | F92: =F82+F83+F84+F85+F86+F87+N(F88)+N(F89)+N(F90)+N(F91) -> 852.834 | G92: =G82+G83+G84+G85+G86+G87+N(G88)+N(G89)+N(G90)+N(G91) -> 890.56 | H92: =H82+H83+H84+H85+H86+H87+N(H88)+N(H89)+N(H90)+N(H91) -> 1002.078 | I92: =I82+I83+I84+I85+I86+I87+N(I88)+N(I89)+N(I90)+N(I91) -> 1039.945 | J92: =J82+J83+J84+J85+J86+J87+N(J88)+N(J89)+N(J90)+N(J91) -> 259.263 | ... BX92: =BX82+BX83+BX84+BX85+BX86+BX87+N(BX88)+N(BX89)+N(BX90)+N(BX91) -> 831.282 | BY92: =BY82+BY83+BY84+BY85+BY86+BY87+N(BY88) -> 871.99047 | BZ92: =BZ82+BZ83+BZ84+BZ85+BZ86+BZ87+N(BZ88) -> 867.07522 | CA92: =CA82+CA83+CA84+CA85+CA86+CA87+N(CA88) -> 3309.7677 | CB92: =CB82+CB83+CB84+CB85+CB86+CB87+N(CB88) -> 3547.5388 | CC92: =CC82+CC83+CC84+CC85+CC86+CC87+N(CC88) -> 3762.5749 | CD92: =CD82+CD83+CD84+CD85+CD86+CD87+N(CD88) -> 4019.4082 | CE92: =CE82+CE83+CE84+CE85+CE86+CE87+N(CE88) -> 4310.804
B93: Operating income | C93: =C81-C92 -> 49.994 | D93: =D81-D92 -> 38.168 | E93: =E81-E92 -> -9.851 | F93: =F81-F92 -> -3.693 | G93: =G81-G92 -> 12.1 | H93: =H81-H92 -> 28.146 | I93: =I81-I92 -> 58.734 | J93: =J81-J92 -> 14.532 | ... CE93: =CE81-CE92 -> 706.75092 | CH93: =IFERROR((CE93/BV93)^(1/5)-1,"n/m") -> 0.14946408 | CI93: =IFERROR((BV93/AW93)^(1/5)-1,"n/m") -> 0.14326948 | CJ93: =IFERROR((BV93/X93)^(1/10)-1,"n/m") -> 0.14621675 | CK93: =IFERROR((BV93/C93)^(1/19)-1,"n/m") -> 0.10821702
B94: Operating ratio (GAAP) % | C94: =IF(AND(ISNUMBER(C92),ISNUMBER(C81)),IFERROR(C92/C81,""),"") -> 0.94284689 | D94: =IF(AND(ISNUMBER(D92),ISNUMBER(D81)),IFERROR(D92/D81,""),"") -> 0.96089837 | E94: =IF(AND(ISNUMBER(E92),ISNUMBER(E81)),IFERROR(E92/E81,""),"") -> 1.0095602 | F94: =IF(AND(ISNUMBER(F92),ISNUMBER(F81)),IFERROR(F92/F81,""),"") -> 1.0043491 | G94: =IF(AND(ISNUMBER(G92),ISNUMBER(G81)),IFERROR(G92/G81,""),"") -> 0.98659517 | H94: =IF(AND(ISNUMBER(H92),ISNUMBER(H81)),IFERROR(H92/H81,""),"") -> 0.97267973 | I94: =IF(AND(ISNUMBER(I92),ISNUMBER(I81)),IFERROR(I92/I81,""),"") -> 0.94654126 | J94: =IF(AND(ISNUMBER(J92),ISNUMBER(J81)),IFERROR(J92/J81,""),"") -> 0.94692379 | ... CE94: =IF(AND(ISNUMBER(CE92),ISNUMBER(CE81)),IFERROR(CE92/CE81,""),"") -> 0.85914436 | CH94: =IFERROR(AVERAGE(CA94,CB94,CC94,CD94,CE94),"n/m") -> 0.86994394 | CI94: =IFERROR(AVERAGE(BB94,BG94,BL94,BQ94,BV94),"n/m") -> 0.85321965 | CJ94: =IFERROR(AVERAGE(AC94,AH94,AM94,AR94,AW94,BB94,BG94,BL94,BQ94,BV94),"n/m") -> 0.88627168 | CK94: =IFERROR(AVERAGE(C94,D94,E94,F94,G94,H94,I94,N94,S94,X94,AC94,AH94,AM94,AR94,AW94,BB94,BG94,BL94,BQ94,BV94),"n/m") -> 0.9239917
B95: Memo: operating ratio as reported (release) | J95: 0.947 | K95: 0.92 | L95: 0.925 | M95: 0.947 | O95: 0.949 | P95: 0.931 | Q95: 0.918 | R95: 0.934 | S95: 0.933 | T95: 0.928 | U95: 0.903 | V95: 0.937 | W95: 0.939 | X95: 0.926 | Y95: 0.939 | Z95: 0.93 | AA95: 0.928 | AB95: 0.943 | AC95: 0.935 | AD95: 0.945 | AE95: 0.917 | AF95: 0.93 | AG95: 0.935 | AH95: 0.931 | AI95: 0.93 | AJ95: 0.903 | AK95: 0.909 | AL95: 0.918 | AM95: 0.915 | AN95: 0.93 | AO95: 0.89 | AP95: 0.903 | AQ95: 0.938 | AR95: 0.915 | AS95: 0.913 | AT95: 0.915 | AU95: 0.885 | AV95: 0.894 | AW95: 0.901 | AX95: 0.899 | AY95: 0.855 | AZ95: 0.828 | BA95: 0.842 | BB95: 0.854 | BC95: 0.844 | BD95: 0.804 | BE95: 0.824 | BF95: 0.859 | BG95: 0.831 | BH95: 0.85 | BI95: 0.827 | BJ95: 0.834 | BK95: 0.85 | BL95: 0.84 | BM95: 0.844 | BN95: 0.833 | BO95: 0.851 | BP95: 0.871 | BQ95: 0.85 | BR95: 0.911 | BS95: 0.878 | BT95: 0.859 | BU95: 0.919 | BV95: 0.891 | BW95: 0.917 | BX95: 0.869
B96: Check: model operating income vs reported (should be 0) | C96: =ROUND(C93-49.994,1) -> 0 | D96: =ROUND(D93-38.168,1) -> 0 | E96: =ROUND(E93--9.851,1) -> 0 | F96: =ROUND(F93--3.693,1) -> 0 | G96: =ROUND(G93-12.1,1) -> 0 | H96: =ROUND(H93-28.146,1) -> 0 | I96: =ROUND(I93-58.734,1) -> 0 | J96: =ROUND(J93-14.532,1) -> 0 | K96: =ROUND(K93-23.259,1) -> 0 | L96: =ROUND(L93-21.935,1) -> 0 | M96: =ROUND(M93-14.692,1) -> 0 | N96: =ROUND(N93-74.418,1) -> 0 | O96: =ROUND(O93-15.231,1) -> 0 | P96: =ROUND(P93-22.741,1) -> 0 | Q96: =ROUND(Q93-27.149,1) -> 0 | R96: =ROUND(R93-20.572,1) -> 0 | S96: =ROUND(S93-85.693,1) -> 0 | T96: =ROUND(T93-21.233,1) -> 0 | U96: =ROUND(U93-31.281,1) -> 0 | V96: =ROUND(V93-19.845,1) -> 0 | W96: =ROUND(W93-17.616,1) -> 0 | X96: =ROUND(X93-89.975,1) -> 0 | Y96: =ROUND(Y93-17.584,1) -> 0 | Z96: =ROUND(Z93-21.721,1) -> 0 | AA96: =ROUND(AA93-22.644,1) -> 0 | AB96: =ROUND(AB93-17.187,1) -> 0 | AC96: =ROUND(AC93-79.136,1) -> 0 | AD96: =ROUND(AD93-17.519,1) -> 0 | AE96: =ROUND(AE93-29.718,1) -> 0 | AF96: =ROUND(AF93-24.602,1) -> 0 | AG96: =ROUND(AG93-22.898,1) -> 0 | AH96: =ROUND(AH93-94.737,1) -> 0 | AI96: =ROUND(AI93-27.579,1) -> 0 | AJ96: =ROUND(AJ93-41.565,1) -> 0 | AK96: =ROUND(AK93-38.697,1) -> 0 | AL96: =ROUND(AL93-33.336,1) -> 0 | AM96: =ROUND(AM93-141.177,1) -> 0 | AN96: =ROUND(AN93-28.631,1) -> 0 | AO96: =ROUND(AO93-51.166,1) -> 0 | AP96: =ROUND(AP93-45.359,1) -> 0 | AQ96: =ROUND(AQ93-27.43,1) -> 0 | AR96: =ROUND(AR93-152.586,1) -> 0 | AS96: =ROUND(AS93-38.776,1) -> 0 | AT96: =ROUND(AT93-35.681,1) -> 0 | AU96: =ROUND(AU93-55.216,1) -> 0 | AV96: =ROUND(AV93-50.648,1) -> 0 | AW96: =ROUND(AW93-180.321,1) -> 0 | AX96: =ROUND(AX93-48.714,1) -> 0 | AY96: =ROUND(AY93-82.925,1) -> 0 | AZ96: =ROUND(AZ93-106.117,1) -> 0 | BA96: =ROUND(BA93-97.385,1) -> 0 | BB96: =ROUND(BB93-335.141,1) -> 0 | BC96: =ROUND(BC93-103.449,1) -> 0 | BD96: =ROUND(BD93-145.993,1) -> 0 | BE96: =ROUND(BE93-128.355,1) -> 0 | BF96: =ROUND(BF93-92.691,1) -> 0 | BG96: =ROUND(BG93-470.488,1) -> 0 | BH96: =ROUND(BH93-99.143,1) -> 0 | BI96: =ROUND(BI93-120.255,1) -> 0 | BJ96: =ROUND(BJ93-128.435,1) -> 0 | BK96: =ROUND(BK93-112.663,1) -> 0 | BL96: =ROUND(BL93-460.496,1) -> 0 | BM96: =ROUND(BM93-117.912,1) -> 0 | BN96: =ROUND(BN93-137.593,1) -> 0 | BO96: =ROUND(BO93-125.171,1) -> 0 | BP96: =ROUND(BP93-101.484,1) -> 0 | BQ96: =ROUND(BQ93-482.16,1) -> 0 | BR96: =ROUND(BR93-70.168,1) -> 0 | BS96: =ROUND(BS93-99.399,1) -> 0 | BT96: =ROUND(BT93-118.61,1) -> 0 | BU96: =ROUND(BU93-64.023,1) -> 0 | BV96: =ROUND(BV93-352.2,1) -> 0 | BW96: =ROUND(BW93-66.806,1) -> 0 | BX96: =ROUND(BX93-125.212,1) -> 0
B97: Interest expense | C97: 9.288 | D97: 10.135 | E97: 12.441 | F97: 12.156 | G97: 10.602 | H97: 10.468 | I97: 7.807 | J97: 1.528 | K97: 1.618 | L97: 1.76 | M97: 1.584 | N97: 6.49 | O97: 1.316 | P97: 1.177 | Q97: 1.064 | R97: 1.007 | S97: 4.564 | T97: 1.019 | U97: 1.074 | V97: 1.033 | W97: 0.981 | X97: 4.107 | Y97: 0.963 | Z97: 1.264 | AA97: 1.183 | AB97: 0.984 | AC97: 4.394 | AD97: 0.911 | AE97: 1.538 | AF97: 1.313 | AG97: 1.289 | AH97: 5.051 | AI97: 1.226 | AJ97: 1.454 | AK97: 1.41 | AL97: 1.328 | AM97: 5.418 | AN97: 1.383 | AO97: 1.903 | AP97: 1.868 | AQ97: 1.534 | AR97: 6.688 | AS97: 1.402 | AT97: 1.594 | AU97: 1.174 | AV97: 1.007 | AW97: 5.177 | AX97: 0.852 | AY97: 0.834 | AZ97: 0.777 | BA97: 0.749 | BB97: 3.212 | BC97: 0.692 | BD97: 0.668 | BE97: 0.581 | BF97: 0.67 | BG97: 2.611 | BH97: 0.688 | BI97: 0.458 | BJ97: 0.454 | BK97: 0.935 | BL97: 2.535 | BM97: 0.542 | BN97: 2.412 | BO97: 2.997 | BP97: 2.979 | BQ97: 8.93 | BR97: 4.285 | BS97: 4.742 | BT97: 4.483 | BU97: 2.934 | BV97: 16.444 | BW97: 2.574 | BX97: 2.048 | BY97: =$BX$278*$CB$285/4+$CB$287/4 -> 1.8225 | BZ97: =$BX$278*$CB$285/4+$CB$287/4 -> 1.8225 | CA97: =SUM(BW97,BX97,BY97,BZ97) -> 8.267 | CB97: =CA278*CB285+CA281*CB286+CB287 -> 7.29 | CC97: =CB278*CC285+CB281*CC286+CC287 -> 7.29 | CD97: =CC278*CD285+CC281*CD286+CD287 -> 7.29 | CE97: =CD278*CE285+CD281*CE286+CE287 -> 7.29 | CF97: Q3/Q4-26E: $100m 6.09% Prudential notes ($1.52m/qtr) + ~$0.3m/qtr unused-commitment & LC fees (revolver undrawn at 30-Jun-26). 2027E+: opening balances × rates.
B98: Interest income | BI98: -0.487 | BJ98: -2.423 | BK98: -3.158 | BL98: -6.208 | BM98: -0.755 | BN98: -0.11 | BO98: -0.045 | BP98: -0.139 | BQ98: -1.049 | BR98: -0.039 | BS98: -0.034 | BT98: -0.044 | BU98: -0.034 | BV98: -0.151 | BW98: -0.063 | BX98: -0.317 | BY98: =-$BX$231*$CB$288/4 -> -0.630105 | BZ98: =-$BX$231*$CB$288/4 -> -0.630105 | CA98: =SUM(BW98,BX98,BY98,BZ98) -> -1.64021 | CB98: =-CA231*CB288 -> -4.6373563 | CC98: =-CB231*CC288 -> -3.00372 | CD98: =-CC231*CD288 -> -3.00372 | CE98: =-CD231*CE288 -> -3.00372
B99: Other, net (incl. deferred-compensation trust / COLI marks) | C99: -1.267 | D99: -0.358 | E99: 0.419 | F99: -0.208 | G99: -0.435 | H99: -0.052 | I99: -0.212 | J99: -0.066 | K99: -0.029 | L99: -0.085 | M99: -0.037 | N99: -0.217 | O99: -0.03 | P99: -0.035 | Q99: 0.016 | R99: -0.05 | S99: -0.099 | T99: -0.051 | U99: -0.014 | V99: 0.046 | W99: -0.076 | X99: -0.095 | Y99: -0.007 | Z99: -0.036 | AA99: -0.104 | AB99: -0.03 | AC99: -0.177 | AD99: 0.098 | AE99: 0.09 | AF99: -0.131 | AG99: -0.149 | AH99: -0.092 | AI99: -0.103 | AJ99: -0.142 | AK99: -0.139 | AL99: 0.31 | AM99: -0.074 | AN99: -0.334 | AO99: -0.14 | AP99: -0.02 | AQ99: -0.26 | AR99: -0.754 | AS99: 0.547 | AT99: -0.751 | AU99: -0.391 | AV99: -0.539 | AW99: -1.134 | AX99: -0.131 | AY99: -0.43 | AZ99: 0.014 | BA99: -0.297 | BB99: -0.844 | BC99: 0.235 | BD99: 0.769 | BE99: 0.068 | BF99: -1.243 | BG99: -0.171 | BH99: -0.643 | BI99: -0.99 | BJ99: 0.157 | BK99: -0.722 | BL99: -2.058 | BM99: -0.788 | BN99: -0.326 | BO99: -0.46 | BP99: -0.155 | BQ99: -1.729 | BR99: 0.357 | BS99: -0.873 | BT99: -0.654 | BU99: -0.312 | BV99: -1.482 | BW99: -0.74 | BX99: -1.994 | BY99: =($BW$99+$BX$99)/2 -> -1.367 | BZ99: =($BW$99+$BX$99)/2 -> -1.367 | CA99: =SUM(BW99,BX99,BY99,BZ99) -> -5.468 | CB99: 0 | CC99: 0 | CD99: 0 | CE99: 0
B100: Nonoperating (income) expenses, net | C100: =C97+N(C98)+C99 -> 8.021 | D100: =D97+N(D98)+D99 -> 9.777 | E100: =E97+N(E98)+E99 -> 12.86 | F100: =F97+N(F98)+F99 -> 11.948 | G100: =G97+N(G98)+G99 -> 10.167 | H100: =H97+N(H98)+H99 -> 10.416 | I100: =I97+N(I98)+I99 -> 7.595 | J100: =J97+N(J98)+J99 -> 1.462 | ... CE100: =CE97+N(CE98)+CE99 -> 4.28628
B101: Income before income taxes | C101: =C93-C100 -> 41.973 | D101: =D93-D100 -> 28.391 | E101: =E93-E100 -> -22.711 | F101: =F93-F100 -> -15.641 | G101: =G93-G100 -> 1.933 | H101: =H93-H100 -> 17.73 | I101: =I93-I100 -> 51.139 | J101: =J93-J100 -> 13.07 | ... CE101: =CE93-CE100 -> 702.46464 | CH101: =IFERROR((CE101/BV101)^(1/5)-1,"n/m") -> 0.15797374 | CI101: =IFERROR((BV101/AW101)^(1/5)-1,"n/m") -> 0.13864033 | CJ101: =IFERROR((BV101/X101)^(1/10)-1,"n/m") -> 0.14652079 | CK101: =IFERROR((BV101/C101)^(1/19)-1,"n/m") -> 0.11593795
B102: Income tax expense (benefit) | C102: 16.1 | D102: 11.306 | E102: -3.022 | F102: -6.605 | G102: -0.024 | H102: 6.357 | I102: 19.091 | J102: 3.915 | K102: 8.17 | L102: 7.352 | M102: 5.081 | N102: 24.518 | O102: 5.369 | P102: 8.031 | Q102: 9.791 | R102: 6.046 | S102: 29.237 | T102: 7.66 | U102: 10.974 | V102: 6.989 | W102: 5.324 | X102: 30.947 | Y102: 6.053 | Z102: 7.218 | AA102: 7.739 | AB102: 5.885 | AC102: 26.895 | AD102: 5.123 | AE102: 10.487 | AF102: 9.013 | AG102: -26.001 | AH102: -1.378 | AI102: 5.331 | AJ102: 9.972 | AK102: 9.231 | AL102: 6.318 | AM102: 30.852 | AN102: 5.323 | AO102: 12.33 | AP102: 10.543 | AQ102: 4.737 | AR102: 32.933 | AS102: 8.716 | AT102: 6.384 | AU102: 12.894 | AV102: 9.944 | AW102: 37.938 | AX102: 10.702 | AY102: 20.047 | AZ102: 25.617 | BA102: 23.172 | BB102: 79.538 | BC102: 23.098 | BD102: 35.311 | BE102: 29.815 | BF102: 22.402 | BG102: 110.626 | BH102: 23.001 | BI102: 29.955 | BJ102: 32.034 | BK102: 26.38 | BL102: 111.37 | BM102: 28.218 | BN102: 33.098 | BO102: 29.931 | BP102: 22.696 | BQ102: 113.943 | BR102: 15.755 | BS102: 24.173 | BT102: 28.509 | BU102: 13.916 | BV102: 82.353 | BW102: 15.166 | BX102: 31.215 | BY102: =BY101*BY103 -> 29.425733 | BZ102: =BZ101*BZ103 -> 27.951544 | CA102: =SUM(BW102,BX102,BY102,BZ102) -> 103.75828 | CB102: =CB101*CB103 -> 129.59417 | CC102: =CC101*CC103 -> 138.54616 | CD102: =CD101*CD103 -> 150.77896 | CE102: =CE101*CE103 -> 172.10384
B103: Effective tax rate | C103: =IF(AND(ISNUMBER(C102),ISNUMBER(C101)),IFERROR(C102/C101,""),"") -> 0.38357992 | D103: =IF(AND(ISNUMBER(D102),ISNUMBER(D101)),IFERROR(D102/D101,""),"") -> 0.39822479 | E103: =IF(AND(ISNUMBER(E102),ISNUMBER(E101)),IFERROR(E102/E101,""),"") -> 0.13306327 | F103: =IF(AND(ISNUMBER(F102),ISNUMBER(F101)),IFERROR(F102/F101,""),"") -> 0.42228758 | G103: =IF(AND(ISNUMBER(G102),ISNUMBER(G101)),IFERROR(G102/G101,""),"") -> -0.012415934 | H103: =IF(AND(ISNUMBER(H102),ISNUMBER(H101)),IFERROR(H102/H101,""),"") -> 0.35854484 | I103: =IF(AND(ISNUMBER(I102),ISNUMBER(I101)),IFERROR(I102/I101,""),"") -> 0.37331586 | J103: =IF(AND(ISNUMBER(J102),ISNUMBER(J101)),IFERROR(J102/J101,""),"") -> 0.29954093 | ... BX103: =IF(AND(ISNUMBER(BX102),ISNUMBER(BX101)),IFERROR(BX102/BX101,""),"") -> 0.24877466 | BY103: =$CP$23 -> 0.245 | BZ103: =$CP$23 -> 0.245 | CA103: =IF(AND(ISNUMBER(CA102),ISNUMBER(CA101)),IFERROR(CA102/CA101,""),"") -> 0.24430787 | CB103: 0.245 | CC103: 0.245 | CD103: 0.245 | CE103: 0.245 | CF103: Q3/Q4-26E at 24.5% (1H/26 24.3%); 2027E+ 24.5% input. FY17 includes the $34m Tax Act benefit. | CH103: =IFERROR(AVERAGE(CA103,CB103,CC103,CD103,CE103),"n/m") -> 0.24486157 | CI103: =IFERROR(AVERAGE(BB103,BG103,BL103,BQ103,BV103),"n/m") -> 0.23954163 | CJ103: =IFERROR(AVERAGE(AC103,AH103,AM103,AR103,AW103,BB103,BG103,BL103,BQ103,BV103),"n/m") -> 0.22082612 | CK103: =IFERROR(AVERAGE(C103,D103,E103,F103,G103,H103,I103,N103,S103,X103,AC103,AH103,AM103,AR103,AW103,BB103,BG103,BL103,BQ103,BV103),"n/m") -> 0.26722972
...

Sheet Bull-Base-Bear
B2: Saia, Inc. (SAIA) — Bull / Base / Bear Case P&L Summary | J2: Share price ($): | K2: =Model!$CA$322 -> 350
B3: Adjusted figures (company definition: adjusted operating income / adjusted operating ratio / adjusted diluted EPS; Adjusted EBITDA model-defined — Saia does not publish EBITDA) · USD millions · Live panel linked to Model — toggle scenario via Model!CF2. Bull and Bear panels are value snapshots generated from the Model with the switch set to each case. | J3: As of: | K3: =TODAY() -> 46300
B5: Scenario: | C5: =Model!$CF$2 -> Base | N5: Scenario: | O5: Bull | P5: Snapshot (values) — Model run with switch = Bull | Z5: Scenario: | AA5: Bear | AB5: Snapshot (values) — Model run with switch = Bear
B7: (USDm, except EPS and shares) | C7: 2025A | D7: 2026E | E7: 2027E | F7: 2028E | G7: 2029E | H7: 2030E | I7: 25-'30 CAGR | J7: LT Hist Avg | K7: LT Hist Min | L7: LT Hist Max | N7: (USDm, except EPS and shares) | O7: 2025A | P7: 2026E | Q7: 2027E | R7: 2028E | S7: 2029E | T7: 2030E | U7: 25-'30 CAGR | V7: LT Hist Avg | W7: LT Hist Min | X7: LT Hist Max | Z7: (USDm, except EPS and shares) | AA7: 2025A | AB7: 2026E | AC7: 2027E | AD7: 2028E | AE7: 2029E | AF7: 2030E | AG7: 25-'30 CAGR | AH7: LT Hist Avg | AI7: LT Hist Min | AJ7: LT Hist Max
B9: Revenues | C9: =Model!BV81 -> 3234.286 | D9: =Model!CA81 -> 3735.6295 | E9: =Model!CB81 -> 4079.1472 | F9: =Model!CC81 -> 4332.3557 | G9: =Model!CD81 -> 4639.1188 | H9: =Model!CE81 -> 5017.5549 | I9: =IFERROR((H9/C9)^(1/5)-1,"n/m") -> 0.091799128 | N9: Revenues | O9: 3234.286 | P9: 3768.9897 | Q9: 4252.5829 | R9: 4668.9913 | S9: 5168.8813 | T9: 5780.36 | U9: 0.12314362 | Z9: Revenues | AA9: 3234.286 | AB9: 3702.635 | AC9: 3910.6378 | AD9: 4015.4885 | AE9: 4156.5934 | AF9: 4345.5105 | AG9: 0.060846327
B10: Revenues y/y % | D10: =IFERROR(D9/C9-1,"") -> 0.155009 | E10: =IFERROR(E9/D9-1,"") -> 0.091957131 | F10: =IFERROR(F9/E9-1,"") -> 0.062073878 | G10: =IFERROR(G9/F9-1,"") -> 0.070807463 | H10: =IFERROR(H9/G9-1,"") -> 0.081575 | N10: Revenues y/y % | P10: 0.16532356 | Q10: 0.12830846 | R10: 0.097918939 | S10: 0.10706594 | T10: 0.1183 | Z10: Revenues y/y % | AB10: 0.14480755 | AC10: 0.056176948 | AD10: 0.026811662 | AE10: 0.035140155 | AF10: 0.04545
B11: LTL tonnage per workday y/y % | C11: =Model!BV168 -> 0.024573758 | D11: =Model!CA168 -> 0.054269274 | E11: =Model!CB168 -> 0.05 | F11: =Model!CC168 -> 0.045 | G11: =Model!CD168 -> 0.04 | H11: =Model!CE168 -> 0.035 | N11: LTL tonnage per workday y/y % | O11: 0.024573758 | P11: 0.059005519 | Q11: 0.07 | R11: 0.065 | S11: 0.06 | T11: 0.055 | Z11: LTL tonnage per workday y/y % | AA11: 0.024573758 | AB11: 0.04953303 | AC11: 0.03 | AD11: 0.025 | AE11: 0.02 | AF11: 0.015
B12: Adjusted EBITDA (model; Saia does not publish EBITDA) | C12: =Model!BV145 -> 587.752 | D12: =Model!CA145 -> 687.99461 | E12: =Model!CB145 -> 822.4307 | F12: =Model!CC145 -> 875.95179 | G12: =Model!CD145 -> 942.44591 | H12: =Model!CE145 -> 1052.2306 | I12: =IFERROR((H12/C12)^(1/5)-1,"n/m") -> 0.12352661 | N12: Adjusted EBITDA (model; Saia does not publish EBITDA) | O12: 587.752 | P12: 710.64262 | Q12: 920.66701 | R12: 1062.716 | S12: 1234.428 | T12: 1472.3368 | U12: 0.20160744 | Z12: Adjusted EBITDA (model; Saia does not publish EBITDA) | AA12: 587.752 | AB12: 665.72007 | AC12: 728.28877 | AD12: 703.54621 | AE12: 683.13335 | AF12: 693.2699 | AG12: 0.033574166
B13: Adjusted EBITDA margin % | C13: =IFERROR(C12/C9,"") -> 0.18172543 | D13: =IFERROR(D12/D9,"") -> 0.184171 | E13: =IFERROR(E12/E9,"") -> 0.20161829 | F13: =IFERROR(F12/F9,"") -> 0.20218834 | G13: =IFERROR(G12/G9,"") -> 0.20315192 | H13: =IFERROR(H12/H9,"") -> 0.20970983 | J13: =IFERROR(AVERAGE(Model!C146,Model!D146,Model!E146,Model!F146,Model!G146,Model!H146,Model!I146,Model!N146,Model!S146,Model!X146,Model!AC146,Model!AH146,Model!AM146,Model!AR146,Model!AW146,Model!BB146,Model!BG146,Model!BL146,Model!BQ146,Model!BV146),"n/m") -> 0.13127442 | K13: =IFERROR(MIN(Model!C146,Model!D146,Model!E146,Model!F146,Model!G146,Model!H146,Model!I146,Model!N146,Model!S146,Model!X146,Model!AC146,Model!AH146,Model!AM146,Model!AR146,Model!AW146,Model!BB146,Model!BG146,Model!BL146,Model!BQ146,Model!BV146),"n/m") -> 0.027742154 | L13: =IFERROR(MAX(Model!C146,Model!D146,Model!E146,Model!F146,Model!G146,Model!H146,Model!I146,Model!N146,Model!S146,Model!X146,Model!AC146,Model!AH146,Model!AM146,Model!AR146,Model!AW146,Model!BB146,Model!BG146,Model!BL146,Model!BQ146,Model!BV146),"n/m") -> 0.22487435 | N13: Adjusted EBITDA margin % | O13: 0.18172543 | P13: 0.1885499 | Q13: 0.21649596 | R13: 0.22761148 | S13: 0.23881917 | T13: 0.25471368 | V13: 0.13127442 | W13: 0.027742154 | X13: 0.22487435 | Z13: Adjusted EBITDA margin % | AA13: 0.18172543 | AB13: 0.1797963 | AC13: 0.18623274 | AD13: 0.17520813 | AE13: 0.16434933 | AF13: 0.15953704 | AH13: 0.13127442 | AI13: 0.027742154 | AJ13: 0.22487435
B15: Operating Income (GAAP) | C15: =Model!BV93 -> 352.2 | D15: =Model!CA93 -> 425.86176 | E15: =Model!CB93 -> 531.60843 | F15: =Model!CC93 -> 569.78081 | G15: =Model!CD93 -> 619.7106 | H15: =Model!CE93 -> 706.75092 | I15: =IFERROR((H15/C15)^(1/5)-1,"n/m") -> 0.14946408 | N15: Operating Income (GAAP) | O15: 352.2 | P15: 448.50977 | Q15: 627.41437 | R15: 752.49627 | S15: 904.4376 | T15: 1114.1272 | U15: 0.25900973 | Z15: Operating Income (GAAP) | AA15: 352.2 | AB15: 403.58722 | AC15: 439.89689 | AD15: 401.37133 | AE15: 367.39413 | AF15: 359.73524 | AG15: 0.0042428019
B16: Operating income y/y % | D16: =IFERROR(D15/C15-1,"") -> 0.20914752 | E16: =IFERROR(E15/D15-1,"") -> 0.24831221 | F16: =IFERROR(F15/E15-1,"") -> 0.071805432 | G16: =IFERROR(G15/F15-1,"") -> 0.08762983 | H16: =IFERROR(H15/G15-1,"") -> 0.14045317 | N16: Operating income y/y % | P16: 0.27345193 | Q16: 0.39888673 | R16: 0.19936091 | S16: 0.2019164 | T16: 0.23184532 | Z16: Operating income y/y % | AB16: 0.14590352 | AC16: 0.08996734 | AD16: -0.087578619 | AE16: -0.084652769 | AF16: -0.020846515
B17: Operating margin (GAAP) % (= 1 − operating ratio) | C17: =IFERROR(C15/C9,"") -> 0.10889575 | D17: =IFERROR(D15/D9,"") -> 0.114 | E17: =IFERROR(E15/E9,"") -> 0.13032342 | F17: =IFERROR(F15/F9,"") -> 0.13151755 | G17: =IFERROR(G15/G9,"") -> 0.13358369 | H17: =IFERROR(H15/H9,"") -> 0.14085564 | J17: =IFERROR(AVERAGE(Model!C179,Model!D179,Model!E179,Model!F179,Model!G179,Model!H179,Model!I179,Model!N179,Model!S179,Model!X179,Model!AC179,Model!AH179,Model!AM179,Model!AR179,Model!AW179,Model!BB179,Model!BG179,Model!BL179,Model!BQ179,Model!BV179),"n/m") -> 0.076008299 | K17: =IFERROR(MIN(Model!C179,Model!D179,Model!E179,Model!F179,Model!G179,Model!H179,Model!I179,Model!N179,Model!S179,Model!X179,Model!AC179,Model!AH179,Model!AM179,Model!AR179,Model!AW179,Model!BB179,Model!BG179,Model!BL179,Model!BQ179,Model!BV179),"n/m") -> -0.0095601701 | L17: =IFERROR(MAX(Model!C179,Model!D179,Model!E179,Model!F179,Model!G179,Model!H179,Model!I179,Model!N179,Model!S179,Model!X179,Model!AC179,Model!AH179,Model!AM179,Model!AR179,Model!AW179,Model!BB179,Model!BG179,Model!BL179,Model!BQ179,Model!BV179),"n/m") -> 0.16850945 | N17: Operating margin (GAAP) % (= 1 − operating ratio) | O17: 0.10889575 | P17: 0.119 | Q17: 0.14753724 | R17: 0.16116891 | S17: 0.17497744 | T17: 0.19274357 | V17: 0.076008299 | W17: -0.0095601701 | X17: 0.16850945 | Z17: Operating margin (GAAP) % (= 1 − operating ratio) | AA17: 0.10889575 | AB17: 0.109 | AC17: 0.11248725 | AD17: 0.099955791 | AE17: 0.088388279 | AF17: 0.082783195 | AH17: 0.076008299 | AI17: -0.0095601701 | AJ17: 0.16850945
B19: Adjusted Net Income (company definition) | C19: =Model!BV160 -> 244.02303 | D19: =Model!CA160 -> 320.94469 | E19: =Model!CB160 -> 399.36162 | F19: =Model!CC160 -> 426.94837 | G19: =Model!CD160 -> 464.64536 | H19: =Model!CE160 -> 530.3608 | I19: =IFERROR((H19/C19)^(1/5)-1,"n/m") -> 0.16796041 | N19: Adjusted Net Income (company definition) | O19: 244.02303 | P19: 338.04394 | Q19: 470.38677 | R19: 547.20116 | S19: 658.96757 | T19: 813.71807 | U19: 0.27235597 | Z19: Adjusted Net Income (company definition) | AA19: 244.02303 | AB19: 304.12741 | AC19: 330.30189 | AD19: 299.79921 | AE19: 274.14643 | AF19: 268.36397 | AG19: 0.019198274
B21: FDSO (m) | C21: =Model!BV112 -> 26.786 | D21: =Model!CA112 -> 26.8265 | E21: =Model!CB112 -> 26.356755 | F21: =Model!CC112 -> 25.599894 | G21: =Model!CD112 -> 24.962205 | H21: =Model!CE112 -> 24.346859 | I21: =IFERROR((H21/C21)^(1/5)-1,"n/m") -> -0.018914142 | N21: FDSO (m) | O21: 26.786 | P21: 26.8265 | Q21: 25.605316 | R21: 24.039405 | S21: 22.931296 | T21: 21.678441 | U21: -0.04142955 | Z21: FDSO (m) | AA21: 26.786 | AB21: 26.8265 | AC21: 26.415293 | AD21: 25.841668 | AE21: 25.501501 | AF21: 25.28488 | AG21: -0.011468284
B23: Adjusted EPS — Diluted ($) | C23: =Model!BV162 -> 9.1100958 | D23: =Model!CA162 -> 11.963718 | E23: =Model!CB162 -> 15.152155 | F23: =Model!CC162 -> 16.67774 | G23: =Model!CD162 -> 18.613955 | H23: =Model!CE162 -> 21.783541 | I23: =IFERROR((H23/C23)^(1/5)-1,"n/m") -> 0.19047727 | N23: Adjusted EPS — Diluted ($) | O23: 9.1100958 | P23: 12.60112 | Q23: 18.370668 | R23: 22.762674 | S23: 28.736604 | T23: 37.53582 | U23: 0.32734737 | Z23: Adjusted EPS — Diluted ($) | AA23: 9.1100958 | AB23: 11.336828 | AC23: 12.504192 | AD23: 11.601388 | AE23: 10.750208 | AF23: 10.613614 | AG23: 0.031022331
B24: EPS y/y % | D24: =IFERROR(D23/C23-1,"") -> 0.31323739 | E24: =IFERROR(E23/D23-1,"") -> 0.26650879 | F24: =IFERROR(F23/E23-1,"") -> 0.10068439 | G24: =IFERROR(G23/F23-1,"") -> 0.11609576 | H24: =IFERROR(H23/G23-1,"") -> 0.1702801 | N24: EPS y/y % | P24: 0.38320388 | Q24: 0.45785999 | R24: 0.2390771 | S24: 0.26244408 | T24: 0.3062024 | Z24: EPS y/y % | AB24: 0.24442467 | AC24: 0.10297093 | AD24: -0.072200111 | AE24: -0.073368802 | AF24: -0.012706115
B26: P / E (x) — assumed (adjusted EPS) | G26: 26 | H26: 26 | N26: P / E (x) — assumed (adjusted EPS) | S26: 30 | T26: 30 | Z26: P / E (x) — assumed (adjusted EPS) | AD26: 20 | AE26: 20 | AF26: 20
B27: Price Target ($) | G27: =G26*G23 -> 483.96283 | H27: =H26*H23 -> 566.37206 | N27: Price Target ($) | S27: =S26*S23 -> 862.09811 | T27: =T26*T23 -> 1126.0746 | Z27: Price Target ($) | AD27: =AD26*AD23 -> 232.02775 | AE27: =AE26*AE23 -> 215.00415 | AF27: =AF26*AF23 -> 212.27229
B28: Upside / (Downside) vs current | G28: =IFERROR(G27/$K$2-1,"") -> 0.38275093 | H28: =IFERROR(H27/$K$2-1,"") -> 0.6182059 | N28: Upside / (Downside) vs current | S28: =IFERROR(S27/$K$2-1,"") -> 1.4631374 | T28: =IFERROR(T27/$K$2-1,"") -> 2.217356 | Z28: Upside / (Downside) vs current | AD28: =IFERROR(AD27/$K$2-1,"") -> -0.33706357 | AE28: =IFERROR(AE27/$K$2-1,"") -> -0.38570242 | AF28: =IFERROR(AF27/$K$2-1,"") -> -0.39350775
B29: IRR (to Dec-Y-1) | G29: =IFERROR((G27/$K$2)^(1/((DATE(2029-1,12,31)-$K$3)/365.25))-1,"") -> 0.15569814 | H29: =IFERROR((H27/$K$2)^(1/((DATE(2030-1,12,31)-$K$3)/365.25))-1,"") -> 0.16021629 | N29: IRR (to Dec-Y-1) | S29: =IFERROR((S27/$K$2)^(1/((DATE(2029-1,12,31)-$K$3)/365.25))-1,"") -> 0.4955671 | T29: =IFERROR((T27/$K$2)^(1/((DATE(2030-1,12,31)-$K$3)/365.25))-1,"") -> 0.43446454 | Z29: IRR (to Dec-Y-1) | AD29: =IFERROR((AD27/$K$2)^(1/((DATE(2028-1,12,31)-$K$3)/365.25))-1,"") -> -0.28264215 | AE29: =IFERROR((AE27/$K$2)^(1/((DATE(2029-1,12,31)-$K$3)/365.25))-1,"") -> -0.19553385 | AF29: =IFERROR((AF27/$K$2)^(1/((DATE(2030-1,12,31)-$K$3)/365.25))-1,"") -> -0.1430657
B31: Free Cash Flow | C31: =Model!BV211 -> 27.334 | D31: =Model!CA211 -> 200.73254 | E31: =Model!CB211 -> 274.03499 | F31: =Model!CC211 -> 297.49462 | G31: =Model!CD211 -> 273.1689 | H31: =Model!CE211 -> 319.37689 | I31: =IFERROR((H31/C31)^(1/5)-1,"n/m") -> 0.63500867 | N31: Free Cash Flow | O31: 27.334 | P31: 192.96946 | Q31: 327.29232 | R31: 387.13093 | S31: 418.80561 | T31: 537.67641 | U31: 0.81452752 | Z31: Free Cash Flow | AA31: 27.334 | AB31: 208.78913 | AC31: 222.13319 | AD31: 197.55789 | AE31: 124.96823 | AF31: 112.09775 | AG31: 0.32610753
B32: FCF % | C32: =IFERROR(C31/C9,"") -> 0.0084513243 | D32: =IFERROR(D31/D9,"") -> 0.053734597 | E32: =IFERROR(E31/E9,"") -> 0.06717948 | F32: =IFERROR(F31/F9,"") -> 0.068668097 | G32: =IFERROR(G31/G9,"") -> 0.058883791 | H32: =IFERROR(H31/H9,"") -> 0.063651897 | J32: =IFERROR(AVERAGE(Model!C213,Model!D213,Model!E213,Model!F213,Model!G213,Model!H213,Model!I213,Model!N213,Model!S213,Model!X213,Model!AC213,Model!AH213,Model!AM213,Model!AR213,Model!AW213,Model!BB213,Model!BG213,Model!BL213,Model!BQ213,Model!BV213),"n/m") -> 0.0044078847 | K32: =IFERROR(MIN(Model!C213,Model!D213,Model!E213,Model!F213,Model!G213,Model!H213,Model!I213,Model!N213,Model!S213,Model!X213,Model!AC213,Model!AH213,Model!AM213,Model!AR213,Model!AW213,Model!BB213,Model!BG213,Model!BL213,Model!BQ213,Model!BV213),"n/m") -> -0.14329835 | L32: =IFERROR(MAX(Model!C213,Model!D213,Model!E213,Model!F213,Model!G213,Model!H213,Model!I213,Model!N213,Model!S213,Model!X213,Model!AC213,Model!AH213,Model!AM213,Model!AR213,Model!AW213,Model!BB213,Model!BG213,Model!BL213,Model!BQ213,Model!BV213),"n/m") -> 0.052921088 | N32: FCF % | O32: 0.0084513243 | P32: 0.051199254 | Q32: 0.076963184 | R32: 0.082915324 | S32: 0.081024419 | T32: 0.093017808 | V32: 0.0044078847 | W32: -0.14329835 | X32: 0.052921088 | Z32: FCF % | AA32: 0.0084513243 | AB32: 0.056389336 | AC32: 0.056802293 | AD32: 0.049198968 | AE32: 0.030065061 | AF32: 0.025796221 | AH32: 0.0044078847 | AI32: -0.14329835 | AJ32: 0.052921088
B33: FCF / share ($) | C33: =IFERROR(C31/C21,"") -> 1.0204584 | D33: =IFERROR(D31/D21,"") -> 7.4826214 | E33: =IFERROR(E31/E21,"") -> 10.397144 | F33: =IFERROR(F31/F21,"") -> 11.620932 | G33: =IFERROR(G31/G21,"") -> 10.9433 | H33: =IFERROR(H31/H21,"") -> 13.117786 | N33: FCF / share ($) | O33: 1.0204584 | P33: 7.1932403 | Q33: 12.782202 | R33: 16.104014 | S33: 18.263495 | T33: 24.802356 | Z33: FCF / share ($) | AA33: 1.0204584 | AB33: 7.7829434 | AC33: 8.4092648 | AD33: 7.6449355 | AE33: 4.9004266 | AF33: 4.4333906
B34: FCF Yield (on PT) | F34: =IFERROR(F33/F$27,"") | G34: =IFERROR(G33/G$27,"") -> 0.022611861 | H34: =IFERROR(H33/H$27,"") -> 0.023161075 | N34: FCF Yield (on PT) | R34: =IFERROR(R33/R$27,"") | S34: =IFERROR(S33/S$27,"") -> 0.021184938 | T34: =IFERROR(T33/T$27,"") -> 0.0220255 | Z34: FCF Yield (on PT) | AD34: =IFERROR(AD33/AD$27,"") -> 0.032948367 | AE34: =IFERROR(AE33/AE$27,"") -> 0.022792242 | AF34: =IFERROR(AF33/AF$27,"") -> 0.020885395
B35: Adjusted Operating Income (company definition) | C35: =Model!BV130 -> 337.697 | D35: =Model!CA130 -> 425.86176 | E35: =Model!CB130 -> 531.60843 | F35: =Model!CC130 -> 569.78081 | G35: =Model!CD130 -> 619.7106 | H35: =Model!CE130 -> 706.75092 | I35: =IFERROR((H35/C35)^(1/5)-1,"n/m") -> 0.15917188 | N35: Adjusted Operating Income (company definition) | O35: 337.697 | P35: 448.50977 | Q35: 627.41437 | R35: 752.49627 | S35: 904.4376 | T35: 1114.1272 | U35: 0.26964269 | Z35: Adjusted Operating Income (company definition) | AA35: 337.697 | AB35: 403.58722 | AC35: 439.89689 | AD35: 401.37133 | AE35: 367.39413 | AF35: 359.73524 | AG35: 0.012724129
B36: Adjusted operating ratio % | C36: =IFERROR(1-C35/C9,"") -> 0.89558839 | D36: =IFERROR(1-D35/D9,"") -> 0.886 | E36: =IFERROR(1-E35/E9,"") -> 0.86967658 | F36: =IFERROR(1-F35/F9,"") -> 0.86848245 | G36: =IFERROR(1-G35/G9,"") -> 0.86641631 | H36: =IFERROR(1-H35/H9,"") -> 0.85914436 | J36: =IFERROR(AVERAGE(Model!C131,Model!D131,Model!E131,Model!F131,Model!G131,Model!H131,Model!I131,Model!N131,Model!S131,Model!X131,Model!AC131,Model!AH131,Model!AM131,Model!AR131,Model!AW131,Model!BB131,Model!BG131,Model!BL131,Model!BQ131,Model!BV131),"n/m") -> 0.9229529 | K36: =IFERROR(MIN(Model!C131,Model!D131,Model!E131,Model!F131,Model!G131,Model!H131,Model!I131,Model!N131,Model!S131,Model!X131,Model!AC131,Model!AH131,Model!AM131,Model!AR131,Model!AW131,Model!BB131,Model!BG131,Model!BL131,Model!BQ131,Model!BV131),"n/m") -> 0.83149055 | L36: =IFERROR(MAX(Model!C131,Model!D131,Model!E131,Model!F131,Model!G131,Model!H131,Model!I131,Model!N131,Model!S131,Model!X131,Model!AC131,Model!AH131,Model!AM131,Model!AR131,Model!AW131,Model!BB131,Model!BG131,Model!BL131,Model!BQ131,Model!BV131),"n/m") -> 1.0188343 | N36: Adjusted operating ratio % | O36: 0.89558839 | P36: 0.881 | Q36: 0.85246276 | R36: 0.83883109 | S36: 0.82502256 | T36: 0.80725643 | V36: 0.9229529 | W36: 0.83149055 | X36: 1.0188343 | Z36: Adjusted operating ratio % | AA36: 0.89558839 | AB36: 0.891 | AC36: 0.88751275 | AD36: 0.90004421 | AE36: 0.91161172 | AF36: 0.91721681 | AH36: 0.9229529 | AI36: 0.83149055 | AJ36: 1.0188343
B38: Net Debt | C38: =Model!BV301 -> 144.26 | D38: =Model!CA301 -> -54.454544 | E38: =Model!CB301 -> 0 | F38: =Model!CC301 -> 0 | G38: =Model!CD301 -> 0 | H38: =Model!CE301 -> 0 | N38: Net Debt | O38: 144.26 | P38: 3.3085392 | Q38: 460.3335 | R38: 531.35801 | S38: 617.21398 | T38: 736.16838 | Z38: Net Debt | AA38: 144.26 | AB38: -62.511132 | AC38: 0 | AD38: 0 | AE38: 0 | AF38: 0
B39: Net Debt / Adjusted EBITDA (x) | C39: =IFERROR(C38/C12,"") -> 0.24544366 | D39: =IFERROR(D38/D12,"") -> -0.079149667 | E39: =IFERROR(E38/E12,"") -> 0 | F39: =IFERROR(F38/F12,"") -> 0 | G39: =IFERROR(G38/G12,"") -> 0 | H39: =IFERROR(H38/H12,"") -> 0 | N39: Net Debt / Adjusted EBITDA (x) | O39: 0.24544366 | P39: 0.0046557005 | Q39: 0.5 | R39: 0.5 | S39: 0.5 | T39: 0.5 | Z39: Net Debt / Adjusted EBITDA (x) | AA39: 0.24544366 | AB39: -0.093900026 | AC39: 0 | AD39: 0 | AE39: 0 | AF39: 0
B41: ROIC | C41: =Model!BV302 -> 0.094192852 | D41: =Model!CA302 -> 0.11403766 | E41: =Model!CB302 -> 0.13367073 | F41: =Model!CC302 -> 0.13646736 | G41: =Model!CD302 -> 0.13902718 | H41: =Model!CE302 -> 0.14823063 | J41: =IFERROR(AVERAGE(Model!C302,Model!D302,Model!E302,Model!F302,Model!G302,Model!H302,Model!I302,Model!N302,Model!S302,Model!X302,Model!AC302,Model!AH302,Model!AM302,Model!AR302,Model!AW302,Model!BB302,Model!BG302,Model!BL302,Model!BQ302,Model!BV302),"n/m") -> 0.11659755 | K41: =IFERROR(MIN(Model!C302,Model!D302,Model!E302,Model!F302,Model!G302,Model!H302,Model!I302,Model!N302,Model!S302,Model!X302,Model!AC302,Model!AH302,Model!AM302,Model!AR302,Model!AW302,Model!BB302,Model!BG302,Model!BL302,Model!BQ302,Model!BV302),"n/m") -> -0.033356226 | L41: =IFERROR(MAX(Model!C302,Model!D302,Model!E302,Model!F302,Model!G302,Model!H302,Model!I302,Model!N302,Model!S302,Model!X302,Model!AC302,Model!AH302,Model!AM302,Model!AR302,Model!AW302,Model!BB302,Model!BG302,Model!BL302,Model!BQ302,Model!BV302),"n/m") -> 0.25258344 | N41: ROIC | O41: 0.094192852 | P41: 0.11897853 | Q41: 0.15550303 | R41: 0.1759983 | S41: 0.19552849 | T41: 0.22163212 | V41: 0.11659755 | W41: -0.033356226 | X41: 0.25258344 | Z41: ROIC | AA41: 0.094192852 | AB41: 0.10910945 | AC41: 0.1122162 | AD41: 0.09836806 | AE41: 0.08536985 | AF41: 0.079282763 | AH41: 0.11659755 | AI41: -0.033356226 | AJ41: 0.25258344
B42: RONTA | C42: =Model!BV313 -> 0.080054342 | D42: =Model!CA313 -> 0.091918126 | E42: =Model!CB313 -> 0.10916102 | F42: =Model!CC313 -> 0.11123655 | G42: =Model!CD313 -> 0.11340933 | H42: =Model!CE313 -> 0.12093503 | J42: =IFERROR(AVERAGE(Model!C313,Model!D313,Model!E313,Model!F313,Model!G313,Model!H313,Model!I313,Model!N313,Model!S313,Model!X313,Model!AC313,Model!AH313,Model!AM313,Model!AR313,Model!AW313,Model!BB313,Model!BG313,Model!BL313,Model!BQ313,Model!BV313),"n/m") -> 0.092559354 | K42: =IFERROR(MIN(Model!C313,Model!D313,Model!E313,Model!F313,Model!G313,Model!H313,Model!I313,Model!N313,Model!S313,Model!X313,Model!AC313,Model!AH313,Model!AM313,Model!AR313,Model!AW313,Model!BB313,Model!BG313,Model!BL313,Model!BQ313,Model!BV313),"n/m") -> -0.026043915 | L42: =IFERROR(MAX(Model!C313,Model!D313,Model!E313,Model!F313,Model!G313,Model!H313,Model!I313,Model!N313,Model!S313,Model!X313,Model!AC313,Model!AH313,Model!AM313,Model!AR313,Model!AW313,Model!BB313,Model!BG313,Model!BL313,Model!BQ313,Model!BV313),"n/m") -> 0.18767042 | N42: RONTA | O42: 0.080054342 | P42: 0.097568627 | Q42: 0.12952832 | R42: 0.14591815 | S42: 0.16168012 | T42: 0.18256734 | V42: 0.092559354 | W42: -0.026043915 | X42: 0.18767042 | Z42: RONTA | AA42: 0.080054342 | AB42: 0.08765932 | AC42: 0.091687409 | AD42: 0.080376863 | AE42: 0.069967793 | AF42: 0.065173304 | AH42: 0.092559354 | AI42: -0.026043915 | AJ42: 0.18767042
B44: Implied Market Cap (USDm) | F44: =F27*F21 -> 0 | G44: =G27*G21 -> 12080.779 | H44: =H27*H21 -> 13789.381 | N44: Implied Market Cap (USDm) | R44: =R27*R21 -> 0 | S44: =S27*S21 -> 19769.027 | T44: =T27*T21 -> 24411.542 | Z44: Implied Market Cap (USDm) | AD44: =AD27*AD21 -> 5995.9842 | AE44: =AE27*AE21 -> 5482.9286 | AF44: =AF27*AF21 -> 5367.2794
B45: (+) Net Debt | F45: =F38 -> 0 | G45: =G38 -> 0 | H45: =H38 -> 0 | N45: (+) Net Debt | R45: =R38 -> 531.35801 | S45: =S38 -> 617.21398 | T45: =T38 -> 736.16838 | Z45: (+) Net Debt | AD45: =AD38 -> 0 | AE45: =AE38 -> 0 | AF45: =AF38 -> 0
B46: Implied Enterprise Value (USDm) | F46: =F44+F45 -> 0 | G46: =G44+G45 -> 12080.779 | H46: =H44+H45 -> 13789.381 | N46: Implied Enterprise Value (USDm) | R46: =R44+R45 -> 531.35801 | S46: =S44+S45 -> 20386.241 | T46: =T44+T45 -> 25147.711 | Z46: Implied Enterprise Value (USDm) | AD46: =AD44+AD45 -> 5995.9842 | AE46: =AE44+AE45 -> 5482.9286 | AF46: =AF44+AF45 -> 5367.2794
B47: Implied EV / Adjusted EBITDA (x) | F47: =IFERROR(F46/F12,"") -> 0 | G47: =IFERROR(G46/G12,"") -> 12.818539 | H47: =IFERROR(H46/H12,"") -> 13.104904 | N47: Implied EV / Adjusted EBITDA (x) | R47: =IFERROR(R46/R12,"") -> 0.5 | S47: =IFERROR(S46/S12,"") -> 16.514727 | T47: =IFERROR(T46/T12,"") -> 17.080135 | Z47: Implied EV / Adjusted EBITDA (x) | AD47: =IFERROR(AD46/AD12,"") -> 8.5225165 | AE47: =IFERROR(AE46/AE12,"") -> 8.0261468 | AF47: =IFERROR(AF46/AF12,"") -> 7.7419766

Sheet DCF
B2: DCF VALUATION — SAIA, INC. (SAIA)
B4: 1. WACC BUILD
B5: Risk-free rate (US 10Y govt) | C5: 0.055 | D5: Assumption (~US 10Y Treasury yield); update to market
B6: Equity risk premium | C6: 0.05 | D6: US implied ERP ~4.5–5.5% (Damodaran)
B7: Levered beta | C7: 1.3 | D7: LTL peers (ODFL ~1.1, XPO ~1.9, ArcBest ~1.6); SAIA 5Y monthly ~1.3–1.6 — industrial-cycle and fuel sensitivity, partly offset by pricing discipline; update to market
B8: Cost of equity | C8: =C5+C7*C6 -> 0.12
B9: Pre-tax cost of debt | C9: 0.0609 | D9: Unrated; $100m 6.09% senior notes (PGIM shelf, May-2024) and SOFR + 1.25–2.00% revolver — marginal cost ~6%
B10: Tax rate | C10: =Model!$CB$103 -> 0.245 | D10: Model 2027E+ effective tax rate
B11: After-tax cost of debt | C11: =C9*(1-C10) -> 0.0459795
B12: Target D/V | C12: 0.05 | D12: Net debt ~nil (YE2026E) vs ~$9.3bn market cap ($350 × ~26.7m shares); revolver/lease capacity — 5% debt weight
B13: WACC | C13: =C8*(1-C12)+C11*C12 -> 0.11629897
B15: Valuation date (live) | C15: =TODAY() -> 46300 | D15: Periods = (Dec-31-Year − today) / 365.25; cash flows assumed at year-end
B16: 2. UNLEVERED FREE CASH FLOW BUILD (USDm)
D17: 2026E | E17: 2027E | F17: 2028E | G17: 2029E | H17: 2030E | I17: 2031E | J17: 2032E | K17: 2033E | L17: 2034E | M17: 2035E | N17: Terminal | P17: CAGR 26–30E | Q17: CAGR 26–35E
B18: Adjusted EBIT (Model; Adjusted EBITDA − D&A) | D18: =Model!CA150 -> 431.32976 | E18: =Model!CB150 -> 531.60843 | F18: =Model!CC150 -> 569.78081 | G18: =Model!CD150 -> 619.7106 | H18: =Model!CE150 -> 706.75092 | I18: =H18*(1+I$31) -> 749.15597 | J18: =I18*(1+J$31) -> 792.23244 | K18: =J18*(1+K$31) -> 835.80523 | L18: =K18*(1+L$31) -> 879.685 | M18: =L18*(1+M$31) -> 923.66925 | P18: =IFERROR(($H18/$D18)^(1/(VALUE(LEFT($H$17,4))-VALUE(LEFT($D$17,4))))-1,"n/m") -> 0.13139496 | Q18: =IFERROR(($M18/$D18)^(1/(VALUE(LEFT($M$17,4))-VALUE(LEFT($D$17,4))))-1,"n/m") -> 0.088291481
B19: y/y % | E19: =IFERROR(E18/D18-1,"") -> 0.23248726 | F19: =IFERROR(F18/E18-1,"") -> 0.071805432 | G19: =IFERROR(G18/F18-1,"") -> 0.08762983 | H19: =IFERROR(H18/G18-1,"") -> 0.14045317 | I19: =IFERROR(I18/H18-1,"") -> 0.06 | J19: =IFERROR(J18/I18-1,"") -> 0.0575 | K19: =IFERROR(K18/J18-1,"") -> 0.055 | L19: =IFERROR(L18/K18-1,"") -> 0.0525 | M19: =IFERROR(M18/L18-1,"") -> 0.05
B20: (−) Adjusting items excluded from Adjusted EBIT (cash; none forecast) | D20: =-Model!CA129 -> 0 | E20: =-Model!CB129 -> 0 | F20: =-Model!CC129 -> 0 | G20: =-Model!CD129 -> 0 | H20: =-Model!CE129 -> 0 | I20: =H20*(1+I$31) -> 0 | J20: =I20*(1+J$31) -> 0 | K20: =J20*(1+K$31) -> 0 | L20: =K20*(1+L$31) -> 0 | M20: =L20*(1+M$31) -> 0
B21: × (1 − tax rate) | D21: =1-$C$10 -> 0.755 | E21: =1-$C$10 -> 0.755 | F21: =1-$C$10 -> 0.755 | G21: =1-$C$10 -> 0.755 | H21: =1-$C$10 -> 0.755 | I21: =1-$C$10 -> 0.755 | J21: =1-$C$10 -> 0.755 | K21: =1-$C$10 -> 0.755 | ... M21: =1-$C$10 -> 0.755
B22: NOPAT = (Adjusted EBIT − adjusting items) × (1 − t) | D22: =(D18+D20)*D21 -> 325.65397 | E22: =(E18+E20)*E21 -> 401.36437 | F22: =(F18+F20)*F21 -> 430.18451 | G22: =(G18+G20)*G21 -> 467.8815 | H22: =(H18+H20)*H21 -> 533.59694 | I22: =(I18+I20)*I21 -> 565.61276 | J22: =(J18+J20)*J21 -> 598.13549 | K22: =(K18+K20)*K21 -> 631.03295 | ... M22: =(M18+M20)*M21 -> 697.37028
B23: plus depreciation & amortization | D23: =Model!CA87 -> 256.66485 | E23: =Model!CB87 -> 290.82226 | F23: =Model!CC87 -> 306.17098 | G23: =Model!CD87 -> 322.73531 | H23: =Model!CE87 -> 345.47968 | I23: =H23*(1+I$31) -> 366.20846 | J23: =I23*(1+J$31) -> 387.26544 | K23: =J23*(1+K$31) -> 408.56504 | L23: =K23*(1+L$31) -> 430.01471 | M23: =L23*(1+M$31) -> 451.51544
B24: − Net capex (gross capex − disposal proceeds) and acquisitions | D24: =D29 -> -375 | E24: =E29+Model!CB194 -> -448.70619 | F24: =F29+Model!CC194 -> -476.55913 | G24: =G29+Model!CD194 -> -556.69426 | H24: =H29+Model!CE194 -> -602.10659 | I24: =I29 -> -638.23299 | J24: =J29 -> -674.93138 | K24: =K29 -> -712.05261 | L24: =L29 -> -749.43537 | M24: =M29 -> -786.90714
B25: − Δ Working capital (CF statement) | D25: =Model!CA191 -> -58.441499 | E25: =Model!CB191 -> -18.861005 | F25: =Model!CC191 -> -13.902531 | G25: =Model!CD191 -> -16.842974 | H25: =Model!CE191 -> -20.778214 | I25: =H25*(1+I$31) -> -22.024907 | J25: =I25*(1+J$31) -> -23.291339 | K25: =J25*(1+K$31) -> -24.572362 | L25: =K25*(1+L$31) -> -25.862411 | M25: =L25*(1+M$31) -> -27.155532
B26: Unlevered FCF | D26: =D22+D23+D24+D25 -> 148.87732 | E26: =E22+E23+E24+E25 -> 224.61943 | F26: =F22+F23+F24+F25 -> 245.89383 | G26: =G22+G23+G24+G25 -> 217.07958 | H26: =H22+H23+H24+H25 -> 256.19181 | I26: =I22+I23+I24+I25 -> 271.56332 | J26: =J22+J23+J24+J25 -> 287.17821 | K26: =K22+K23+K24+K25 -> 302.97302 | ... M26: =M22+M23+M24+M25 -> 334.82305 | N26: =M26*(1+$C$32) -> 348.21598 | P26: =IFERROR(($H26/$D26)^(1/(VALUE(LEFT($H$17,4))-VALUE(LEFT($D$17,4))))-1,"n/m") -> 0.14533934 | Q26: =IFERROR(($M26/$D26)^(1/(VALUE(LEFT($M$17,4))-VALUE(LEFT($D$17,4))))-1,"n/m") -> 0.094232594
B27: y/y % | E27: =IFERROR(E26/D26-1,"") -> 0.50875524 | F27: =IFERROR(F26/E26-1,"") -> 0.094713104 | G27: =IFERROR(G26/F26-1,"") -> -0.1171817 | H27: =IFERROR(H26/G26-1,"") -> 0.18017465 | I27: =IFERROR(I26/H26-1,"") -> 0.06 | J27: =IFERROR(J26/I26-1,"") -> 0.0575 | K27: =IFERROR(K26/J26-1,"") -> 0.055 | L27: =IFERROR(L26/K26-1,"") -> 0.0525 | M27: =IFERROR(M26/L26-1,"") -> 0.05
B28: Terminal Value (Gordon Growth) | N28: =N26/($C$13-$C$32) -> 4563.8356
B29: memo: net capex (gross capex + disposal proceeds; fade years carry no acquisitions) | D29: =Model!CA193+Model!CA195 -> -375 | E29: =Model!CB193+Model!CB195 -> -448.70619 | F29: =Model!CC193+Model!CC195 -> -476.55913 | G29: =Model!CD193+Model!CD195 -> -556.69426 | H29: =Model!CE193+Model!CE195 -> -602.10659 | I29: =H29*(1+I$31) -> -638.23299 | J29: =I29*(1+J$31) -> -674.93138 | K29: =J29*(1+K$31) -> -712.05261 | L29: =K29*(1+L$31) -> -749.43537 | M29: =L29*(1+M$31) -> -786.90714
B31: Fade-period growth (2031E–35E) | I31: 0.06 | J31: =I31+($M$31-$I$31)/(COLUMNS($I$31:$M$31)-1) -> 0.0575 | K31: =J31+($M$31-$I$31)/(COLUMNS($I$31:$M$31)-1) -> 0.055 | L31: =K31+($M$31-$I$31)/(COLUMNS($I$31:$M$31)-1) -> 0.0525 | M31: 0.05
B32: Terminal growth rate | C32: 0.04
B34: Discount period (years) | D34: =(DATE(2026,12,31)-$C$15)/365.25 -> 0.23819302 | E34: =(DATE(2027,12,31)-$C$15)/365.25 -> 1.2375086 | F34: =(DATE(2028,12,31)-$C$15)/365.25 -> 2.2395619 | G34: =(DATE(2029,12,31)-$C$15)/365.25 -> 3.2388775 | H34: =(DATE(2030,12,31)-$C$15)/365.25 -> 4.238193 | I34: =(DATE(2031,12,31)-$C$15)/365.25 -> 5.2375086 | J34: =(DATE(2032,12,31)-$C$15)/365.25 -> 6.2395619 | K34: =(DATE(2033,12,31)-$C$15)/365.25 -> 7.2388775 | L34: =(DATE(2034,12,31)-$C$15)/365.25 -> 8.238193 | M34: =(DATE(2035,12,31)-$C$15)/365.25 -> 9.2375086 | N34: =M34 -> 9.2375086
B35: Discount factor | D35: =1/(1+$C$13)^D34 -> 0.9741347 | E35: =1/(1+$C$13)^E34 -> 0.87271249 | F35: =1/(1+$C$13)^F34 -> 0.7816144 | G35: =1/(1+$C$13)^G34 -> 0.70023648 | H35: =1/(1+$C$13)^H34 -> 0.62733123 | I35: =1/(1+$C$13)^I34 -> 0.56201653 | J35: =1/(1+$C$13)^J34 -> 0.50335044 | K35: =1/(1+$C$13)^K34 -> 0.45094401 | ... N35: =1/(1+$C$13)^N34 -> 0.361932
B36: PV of UFCF | D36: =D26*D35 -> 145.02656 | E36: =E26*E35 -> 196.02818 | F36: =F26*F35 -> 192.19416 | G36: =G26*G35 -> 152.00704 | H36: =H26*H35 -> 160.71713 | I36: =I26*I35 -> 152.62308 | J36: =J26*J35 -> 144.55128 | K36: =K26*K35 -> 136.62387 | ... M36: =M26*M35 -> 121.18318 | N36: =N28*N35 -> 1651.7981
D37: Saia's adjusted EBIT deducts all D&A (terminal and fleet depreciation; added back in row 23) and expenses stock-based compensation. Saia publishes no EBITDA; adjusting items (terminal-sale gains, impairments) are non-recurring and not forecast. Operating-lease costs (terminals, equipment) sit inside operating income. Fuel surcharge is a pass-through modelled from DOE diesel; the explicit forecast assumes diesel normalises from the 2026 spike (Model DSL lever).
B39: Implied ROIC & incremental ROIC (USDm) | D39: =D17 -> 2026E | E39: =E17 -> 2027E | F39: =F17 -> 2028E | G39: =G17 -> 2029E | H39: =H17 -> 2030E | I39: =I17 -> 2031E | J39: =J17 -> 2032E | K39: =K17 -> 2033E | ... M39: =M17 -> 2035E | N39: Terminal
B40: NOPAT (row 22) | D40: =D22 -> 325.65397 | E40: =E22 -> 401.36437 | F40: =F22 -> 430.18451 | G40: =G22 -> 467.8815 | H40: =H22 -> 533.59694 | I40: =I22 -> 565.61276 | J40: =J22 -> 598.13549 | K40: =K22 -> 631.03295 | ... M40: =M22 -> 697.37028 | N40: =M40*(1+$C$32) -> 725.2651
B41: Net investment = NOPAT − UFCF | D41: =D40-D26 -> 176.77665 | E41: =E40-E26 -> 176.74494 | F41: =F40-F26 -> 184.29067 | G41: =G40-G26 -> 250.80193 | H41: =H40-H26 -> 277.40513 | I41: =I40-I26 -> 294.04944 | J41: =J40-J26 -> 310.95728 | K41: =K40-K26 -> 328.05993 | ... N41: =N40-N26 -> 377.04912
B42: Opening invested capital | D42: =Model!BV300 -> 2721.959 | E42: =D43 -> 2898.7357 | F42: =E43 -> 3075.4806 | G42: =F43 -> 3259.7713 | H42: =G43 -> 3510.5732 | I42: =H43 -> 3787.9783 | J42: =I43 -> 4082.0278 | K42: =J43 -> 4392.985 | L42: =K43 -> 4721.045 | ... N42: =M43 -> 5428.8753
B43: Closing invested capital | D43: =D42+D41 -> 2898.7357 | E43: =E42+E41 -> 3075.4806 | F43: =F42+F41 -> 3259.7713 | G43: =G42+G41 -> 3510.5732 | H43: =H42+H41 -> 3787.9783 | I43: =I42+I41 -> 4082.0278 | J43: =J42+J41 -> 4392.985 | K43: =K42+K41 -> 4721.045 | ... M43: =M42+M41 -> 5428.8753
B44: Implied ROIC = NOPAT / opening IC | D44: =IFERROR(D40/D42,"") -> 0.11963956 | E44: =IFERROR(E40/E42,"") -> 0.13846187 | F44: =IFERROR(F40/F42,"") -> 0.13987554 | G44: =IFERROR(G40/G42,"") -> 0.143532 | H44: =IFERROR(H40/H42,"") -> 0.1519971 | I44: =IFERROR(I40/I42,"") -> 0.14931785 | J44: =IFERROR(J40/J42,"") -> 0.14652901 | K44: =IFERROR(K40/K42,"") -> 0.14364559 | ... N44: =IFERROR(N40/N42,"") -> 0.13359399
B45: Reinvestment rate = net inv. / NOPAT | D45: =IFERROR(D41/D40,"") -> 0.54283586 | E45: =IFERROR(E41/E40,"") -> 0.44036031 | F45: =IFERROR(F41/F40,"") -> 0.42839914 | G45: =IFERROR(G41/G40,"") -> 0.53603727 | H45: =IFERROR(H41/H40,"") -> 0.51987766 | I45: =IFERROR(I41/I40,"") -> 0.51987766 | J45: =IFERROR(J41/J40,"") -> 0.51987766 | K45: =IFERROR(K41/K40,"") -> 0.51987766 | ... N45: =IFERROR(N41/N40,"") -> 0.51987766
B46: Incremental ROIC = Δ NOPAT / prior-yr net inv. | E46: =IFERROR((E40-D40)/D41,"") -> 0.4282828 | F46: =IFERROR((F40-E40)/E41,"") -> 0.16306064 | G46: =IFERROR((G40-F40)/F41,"") -> 0.20455183 | H46: =IFERROR((H40-G40)/G41,"") -> 0.26202127 | I46: =IFERROR((I40-H40)/H41,"") -> 0.11541177 | J46: =IFERROR((J40-I40)/I41,"") -> 0.11060295 | K46: =IFERROR((K40-J40)/J41,"") -> 0.10579412 | L46: =IFERROR((L40-K40)/K41,"") -> 0.1009853 | M46: =IFERROR((M40-L40)/L41,"") -> 0.096176474 | N46: =IFERROR($C$32/N45,"") -> 0.076941179
B47: Cumulative incremental ROIC 2026E–35E | C47: =IFERROR((M40-D40)/SUM(D41:L41),"") -> 0.15855708
D48: Opening IC = Model 2025A book IC (equity + net debt), rolled forward with DCF net investment (net capex + M&A − D&A + ΔWC). Terminal incremental ROIC = g ÷ reinvestment rate. Cumulative = (NOPAT 2035E − 2026E) / Σ net investment 2026E–34E.
B49: 3. VALUATION SUMMARY
B50: Sum of PV (explicit + fade) | C50: =SUM(D36:M36) -> 1529.7797
B51: PV of Terminal Value | C51: =N36 -> 1651.7981
B52: Enterprise Value | C52: =C50+C51 -> 3181.5778
B53: Less: net debt (Model 2026E year end) | C53: =Model!CA301 -> -54.454544
B54: Less: non-controlling interests (none) | C54: 0
B55: Equity Value | C55: =C52-C53-C54 -> 3236.0324
B56: Diluted shares (m, Model 2026E period end) | C56: =Model!CA323 -> 26.76865
B57: Implied share price ($) | C57: =C55/C56 -> 120.88889
B58: Current share price ($) | C58: =Model!CA322 -> 350
B59: Implied upside / (downside) | C59: =C57/C58-1 -> -0.65460317
B60: Required discount to DCF value for target IRR (discount closes over horizon; value compounds at WACC) | C60: =1-((1+C13)/(1+F60))^F61 -> 0.085364494 | E60: Target IRR | F60: 0.15
B61: Max entry price for target IRR ($) — % vs. current share price shown right | C61: =C57*(1-C60) -> 110.56927 | D61: =C61/C58-1 -> -0.6840878 | E61: Years for discount to close | F61: 3
B64: 4. SENSITIVITY: IMPLIED PRICE ($) — WACC × Terminal Growth
B65: WACC step (across) | C65: 0.005
B66: Terminal growth step (down) | C66: 0.005
B67: g (down) / WACC | D67: =E67-$C$65 -> 0.10629898 | E67: =F67-$C$65 -> 0.11129897 | F67: =$C$13 -> 0.11629897 | G67: =F67+$C$65 -> 0.12129898 | H67: =G67+$C$65 -> 0.12629898
B68: =B69-$C$66 -> 0.03 | D68: =IFERROR((SUMPRODUCT($D$26:$M$26/(1+D$67)^$D$34:$M$34)+($M$26*(1+$B68)/(D$67-$B68))/(1+D$67)^$M$34-$C$53-$C$54)/$C$56,"") -> 127.92702 | E68: =IFERROR((SUMPRODUCT($D$26:$M$26/(1+E$67)^$D$34:$M$34)+($M$26*(1+$B68)/(E$67-$B68))/(1+E$67)^$M$34-$C$53-$C$54)/$C$56,"") -> 120.11367 | F68: =IFERROR((SUMPRODUCT($D$26:$M$26/(1+F$67)^$D$34:$M$34)+($M$26*(1+$B68)/(F$67-$B68))/(1+F$67)^$M$34-$C$53-$C$54)/$C$56,"") -> 113.214 | G68: =IFERROR((SUMPRODUCT($D$26:$M$26/(1+G$67)^$D$34:$M$34)+($M$26*(1+$B68)/(G$67-$B68))/(1+G$67)^$M$34-$C$53-$C$54)/$C$56,"") -> 107.07761 | H68: =IFERROR((SUMPRODUCT($D$26:$M$26/(1+H$67)^$D$34:$M$34)+($M$26*(1+$B68)/(H$67-$B68))/(1+H$67)^$M$34-$C$53-$C$54)/$C$56,"") -> 101.58535
B69: =B70-$C$66 -> 0.035 | D69: =IFERROR((SUMPRODUCT($D$26:$M$26/(1+D$67)^$D$34:$M$34)+($M$26*(1+$B69)/(D$67-$B69))/(1+D$67)^$M$34-$C$53-$C$54)/$C$56,"") -> 132.92917 | E69: =IFERROR((SUMPRODUCT($D$26:$M$26/(1+E$67)^$D$34:$M$34)+($M$26*(1+$B69)/(E$67-$B69))/(1+E$67)^$M$34-$C$53-$C$54)/$C$56,"") -> 124.34058 | F69: =IFERROR((SUMPRODUCT($D$26:$M$26/(1+F$67)^$D$34:$M$34)+($M$26*(1+$B69)/(F$67-$B69))/(1+F$67)^$M$34-$C$53-$C$54)/$C$56,"") -> 116.81544 | G69: =IFERROR((SUMPRODUCT($D$26:$M$26/(1+G$67)^$D$34:$M$34)+($M$26*(1+$B69)/(G$67-$B69))/(1+G$67)^$M$34-$C$53-$C$54)/$C$56,"") -> 110.16866 | H69: =IFERROR((SUMPRODUCT($D$26:$M$26/(1+H$67)^$D$34:$M$34)+($M$26*(1+$B69)/(H$67-$B69))/(1+H$67)^$M$34-$C$53-$C$54)/$C$56,"") -> 104.25573
B70: =$C$32 -> 0.04 | D70: =IFERROR((SUMPRODUCT($D$26:$M$26/(1+D$67)^$D$34:$M$34)+($M$26*(1+$B70)/(D$67-$B70))/(1+D$67)^$M$34-$C$53-$C$54)/$C$56,"") -> 138.6858 | E70: =IFERROR((SUMPRODUCT($D$26:$M$26/(1+E$67)^$D$34:$M$34)+($M$26*(1+$B70)/(E$67-$B70))/(1+E$67)^$M$34-$C$53-$C$54)/$C$56,"") -> 129.16032 | F70: =IFERROR((SUMPRODUCT($D$26:$M$26/(1+F$67)^$D$34:$M$34)+($M$26*(1+$B70)/(F$67-$B70))/(1+F$67)^$M$34-$C$53-$C$54)/$C$56,"") -> 120.88889 | G70: =IFERROR((SUMPRODUCT($D$26:$M$26/(1+G$67)^$D$34:$M$34)+($M$26*(1+$B70)/(G$67-$B70))/(1+G$67)^$M$34-$C$53-$C$54)/$C$56,"") -> 113.63993 | H70: =IFERROR((SUMPRODUCT($D$26:$M$26/(1+H$67)^$D$34:$M$34)+($M$26*(1+$B70)/(H$67-$B70))/(1+H$67)^$M$34-$C$53-$C$54)/$C$56,"") -> 107.23555
B71: =B70+$C$66 -> 0.045 | D71: =IFERROR((SUMPRODUCT($D$26:$M$26/(1+D$67)^$D$34:$M$34)+($M$26*(1+$B71)/(D$67-$B71))/(1+D$67)^$M$34-$C$53-$C$54)/$C$56,"") -> 145.38154 | E71: =IFERROR((SUMPRODUCT($D$26:$M$26/(1+E$67)^$D$34:$M$34)+($M$26*(1+$B71)/(E$67-$B71))/(1+E$67)^$M$34-$C$53-$C$54)/$C$56,"") -> 134.70704 | F71: =IFERROR((SUMPRODUCT($D$26:$M$26/(1+F$67)^$D$34:$M$34)+($M$26*(1+$B71)/(F$67-$B71))/(1+F$67)^$M$34-$C$53-$C$54)/$C$56,"") -> 125.53366 | G71: =IFERROR((SUMPRODUCT($D$26:$M$26/(1+G$67)^$D$34:$M$34)+($M$26*(1+$B71)/(G$67-$B71))/(1+G$67)^$M$34-$C$53-$C$54)/$C$56,"") -> 117.56615 | H71: =IFERROR((SUMPRODUCT($D$26:$M$26/(1+H$67)^$D$34:$M$34)+($M$26*(1+$B71)/(H$67-$B71))/(1+H$67)^$M$34-$C$53-$C$54)/$C$56,"") -> 110.58189
B72: =B71+$C$66 -> 0.05 | D72: =IFERROR((SUMPRODUCT($D$26:$M$26/(1+D$67)^$D$34:$M$34)+($M$26*(1+$B72)/(D$67-$B72))/(1+D$67)^$M$34-$C$53-$C$54)/$C$56,"") -> 153.2666 | E72: =IFERROR((SUMPRODUCT($D$26:$M$26/(1+E$67)^$D$34:$M$34)+($M$26*(1+$B72)/(E$67-$B72))/(1+E$67)^$M$34-$C$53-$C$54)/$C$56,"") -> 141.15863 | F72: =IFERROR((SUMPRODUCT($D$26:$M$26/(1+F$67)^$D$34:$M$34)+($M$26*(1+$B72)/(F$67-$B72))/(1+F$67)^$M$34-$C$53-$C$54)/$C$56,"") -> 130.87901 | G72: =IFERROR((SUMPRODUCT($D$26:$M$26/(1+G$67)^$D$34:$M$34)+($M$26*(1+$B72)/(G$67-$B72))/(1+G$67)^$M$34-$C$53-$C$54)/$C$56,"") -> 122.04303 | H72: =IFERROR((SUMPRODUCT($D$26:$M$26/(1+H$67)^$D$34:$M$34)+($M$26*(1+$B72)/(H$67-$B72))/(1+H$67)^$M$34-$C$53-$C$54)/$C$56,"") -> 114.36682
B75: 5. REVERSE DCF
B76: To solve for the market-implied path: Data ▸ What-If Analysis ▸ Goal Seek — set C57 (implied price) to the current price (C58) by changing C32 (terminal growth) or the Model scenario levers (LTL tonnage, core price, SWB per shipment, diesel, capex).
B78: 6. MAUBOUSSIN EV / NOPAT — TWO-STAGE FRAMEWORK
B79: EV/NOPAT = 1/r + [g × (1 − r/ROIIC) / (r × (r − g))] × [1 − ((1+g)/(1+r))^N]
B80: Formula source: Mauboussin & Rappaport, "Expectations Investing" (2021); Counterpoint Global, "What Does a Price-Earnings Multiple Mean?" (2020).
B82: Input | C82: Value | D82: Rationale (Saia characteristics)
B83: r (Cost of capital / WACC) | C83: =$C$13 -> 0.11629897 | D83: Linked from Section 1 WACC build
B84: g (NOPAT growth, Stage 1) | C84: 0.1 | D84: Model Adjusted EBIT CAGR 2026–30E: tonnage growth on a national network with 20–25% spare capacity + ~5% core pricing, partly offset by fuel normalisation → ~10% NOPAT growth
B85: ROIIC (Return on incremental invested capital) | C85: 0.16 | D85: LTL density economics: incremental tonnage on owned terminals/doors earns high returns (2021–23 ROIC 21–25%); the 2024–25 terminal build earned less while volumes were soft
B86: N (Years of value creation / CAP) | C86: 12 | D86: Owned terminal network (218 terminals; ~1bn real-estate investment since 2022) is hard to replicate; LTL industry consolidation (Yellow exit 2023) supports pricing; competitive (ODFL, XPO, FedEx Freight)
B88: Calculation | C88: Value
B89: Steady-state component: 1 / r | C89: =1/C83 -> 8.5985281
B90: Value-creation factor: 1 − r / ROIIC | C90: =1-C83/C85 -> 0.27313141
B91: Growth multiplier: g × (1 − r/ROIIC) / (r × (r − g)) | C91: =C84*C90/(C83*(C83-C84)) -> 14.409054
B92: Time decay: 1 − ((1+g)/(1+r))^N | C92: =1-((1+C84)/(1+C83))^C86 -> 0.16180337
B93: PVGO component (growth value) | C93: =C91*C92 -> 2.3314335
B94: Mauboussin EV / NOPAT (steady-state + PVGO) | C94: =C89+C93 -> 10.929962
B96: VALUATION — Applied to 2028E NOPAT | C96: USDm
B97: 2028E Adjusted EBIT (Model) | C97: =Model!CC150 -> 569.78081
B98: (−) 2028E adjusting items | C98: =-Model!CC129 -> 0
B99: Tax rate (from WACC build) | C99: =$C$10 -> 0.245
B100: 2028E NOPAT = (Adj. EBIT − adjusting items) × (1 − t) | C100: =(C97+C98)*(1-C99) -> 430.18451
B101: × Mauboussin EV/NOPAT multiple | C101: =C94 -> 10.929962
B102: Implied Enterprise Value (2028E basis) | C102: =C100*C101 -> 4701.9001
B103: Less: YE2027 net debt (Model) | C103: =Model!CB301 -> 0
B104: Implied Equity Value | C104: =C102-C103 -> 4701.9001
B105: Diluted shares 2028E (m, Model) | C105: =Model!CC323 -> 25.254928
B106: Implied share price 2028 ($) | C106: =C104/C105 -> 186.17753
B108: Current share price ($) | C108: =C58 -> 350
B109: Implied upside / (downside) | C109: =C106/C108-1 -> -0.46806419
B111: MARKET-IMPLIED EV/NOPAT TODAY | C111: USDm
B112: Current market cap (spot × diluted shares) | C112: =C58*C56 -> 9369.0275
B113: Plus: YE2026 net debt | C113: =C53+C54 -> -54.454544
B114: Implied Enterprise Value (today) | C114: =C112+C113 -> 9314.573
B115: SAIA's market-implied EV/NOPAT (on 2028E NOPAT) | C115: =C114/C100 -> 21.652507
B117: Multiple gap (Mauboussin − Market) | C117: =C94-C115 -> -10.722545
...

Sheet Charts
B2: Saia, Inc. — Historical Operating Performance (2006–2025)
B3: All historicals · USDm · Linked to Model. Volume / price = LTL tonnage per workday y/y (company-reported like-for-like change where available, else model) and LTL revenue/cwt ex-fuel y/y (derived from the company fuel-surcharge % where not reported; n/a 2007–09). Adjusted EBITDA model-defined (Saia publishes adjusted OI/OR only).
C7: 2006 | D7: 2007 | E7: 2008 | F7: 2009 | G7: 2010 | H7: 2011 | I7: 2012 | J7: 2013 | K7: 2014 | L7: 2015 | M7: 2016 | N7: 2017 | O7: 2018 | P7: 2019 | Q7: 2020 | R7: 2021 | S7: 2022 | T7: 2023 | U7: 2024 | V7: 2025
B8: LTL tonnage/workday % | C8: =IFERROR(Model!C20+0,IFERROR(Model!C13+0,0)) -> 0 | D8: =IFERROR(Model!D20+0,IFERROR(Model!D13+0,0)) -> 0 | E8: =IFERROR(Model!E20+0,IFERROR(Model!E13+0,0)) -> 0 | F8: =IFERROR(Model!F20+0,IFERROR(Model!F13+0,0)) -> 0 | G8: =IFERROR(Model!G20+0,IFERROR(Model!G13+0,0)) -> 0 | H8: =IFERROR(Model!H20+0,IFERROR(Model!H13+0,0)) -> 0 | I8: =IFERROR(Model!I20+0,IFERROR(Model!I13+0,0)) -> 0 | J8: =IFERROR(Model!N20+0,IFERROR(Model!N13+0,0)) -> 0 | K8: =IFERROR(Model!S20+0,IFERROR(Model!S13+0,0)) -> 0.063215259 | L8: =IFERROR(Model!X20+0,IFERROR(Model!X13+0,0)) -> -0.0702204 | M8: =IFERROR(Model!AC20+0,IFERROR(Model!AC13+0,0)) -> -0.023980154 | N8: =IFERROR(Model!AH20+0,IFERROR(Model!AH13+0,0)) -> 0.052167803 | O8: =IFERROR(Model!AM20+0,IFERROR(Model!AM13+0,0)) -> 0.066226024 | P8: =IFERROR(Model!AR20+0,IFERROR(Model!AR13+0,0)) -> 0.0039575089 | Q8: =IFERROR(Model!AW20+0,IFERROR(Model!AW13+0,0)) -> 0.00060933773 | R8: =IFERROR(Model!BB20+0,IFERROR(Model!BB13+0,0)) -> 0.12430093 | S8: =IFERROR(Model!BG20+0,IFERROR(Model!BG13+0,0)) -> 0.0093256043 | T8: =IFERROR(Model!BL20+0,IFERROR(Model!BL13+0,0)) -> 0.016809068 | U8: =IFERROR(Model!BQ20+0,IFERROR(Model!BQ13+0,0)) -> 0.080545655 | V8: =IFERROR(Model!BV20+0,IFERROR(Model!BV13+0,0)) -> 0.024573758
B9: LTL rev/cwt ex-fuel % | C9: =IFERROR(Model!C27+0,IFERROR(Model!C30+0,0)) -> 0 | D9: =IFERROR(Model!D27+0,IFERROR(Model!D30+0,0)) -> 0 | E9: =IFERROR(Model!E27+0,IFERROR(Model!E30+0,0)) -> 0 | F9: =IFERROR(Model!F27+0,IFERROR(Model!F30+0,0)) -> 0 | G9: =IFERROR(Model!G27+0,IFERROR(Model!G30+0,0)) -> 0 | H9: =IFERROR(Model!H27+0,IFERROR(Model!H30+0,0)) -> 0.047058669 | I9: =IFERROR(Model!I27+0,IFERROR(Model!I30+0,0)) -> 0.060581813 | J9: =IFERROR(Model!N27+0,IFERROR(Model!N30+0,0)) -> 0.043820315 | K9: =IFERROR(Model!S27+0,IFERROR(Model!S30+0,0)) -> 0.046186663 | L9: =IFERROR(Model!X27+0,IFERROR(Model!X30+0,0)) -> 0.092723682 | M9: =IFERROR(Model!AC27+0,IFERROR(Model!AC30+0,0)) -> 0.055104624 | N9: =IFERROR(Model!AH27+0,IFERROR(Model!AH30+0,0)) -> 0.058201058 | O9: =IFERROR(Model!AM27+0,IFERROR(Model!AM30+0,0)) -> -0.046432795 | P9: =IFERROR(Model!AR27+0,IFERROR(Model!AR30+0,0)) -> 0.081865906 | Q9: =IFERROR(Model!AW27+0,IFERROR(Model!AW30+0,0)) -> 0.03607476 | R9: =IFERROR(Model!BB27+0,IFERROR(Model!BB30+0,0)) -> 0.089121082 | S9: =IFERROR(Model!BG27+0,IFERROR(Model!BG30+0,0)) -> 0.10778781 | T9: =IFERROR(Model!BL27+0,IFERROR(Model!BL30+0,0)) -> 0.069281712 | U9: =IFERROR(Model!BQ27+0,IFERROR(Model!BQ30+0,0)) -> 0.043353978 | V9: =IFERROR(Model!BV27+0,IFERROR(Model!BV30+0,0)) -> -0.014611872
C11: =C7 -> 2006 | D11: =D7 -> 2007 | E11: =E7 -> 2008 | F11: =F7 -> 2009 | G11: =G7 -> 2010 | H11: =H7 -> 2011 | I11: =I7 -> 2012 | J11: =J7 -> 2013 | ... V11: =V7 -> 2025
B12: Adjusted EBITDA (model) | C12: =Model!C145 -> 87.888 | D12: =Model!D145 -> 79.638 | E12: =Model!E145 -> 66.139 | F12: =Model!F145 -> 23.557 | G12: =Model!G145 -> 48.694 | H12: =Model!H145 -> 65.476 | I12: =Model!I145 -> 106.931 | J12: =Model!N145 -> 126.199 | K12: =Model!S145 -> 144.814 | L12: =Model!X145 -> 155.09 | M12: =Model!AC145 -> 155.553 | N12: =Model!AH145 -> 181.931 | O12: =Model!AM145 -> 243.404 | P12: =Model!AR145 -> 272.475 | Q12: =Model!AW145 -> 316.11 | R12: =Model!BB145 -> 473.418 | S12: =Model!BG145 -> 627.862 | T12: =Model!BL145 -> 641.399 | U12: =Model!BQ145 -> 693.994 | V12: =Model!BV145 -> 587.752
B13: Operating Income (GAAP) | C13: =Model!C93 -> 49.994 | D13: =Model!D93 -> 38.168 | E13: =Model!E93 -> -9.851 | F13: =Model!F93 -> -3.693 | G13: =Model!G93 -> 12.1 | H13: =Model!H93 -> 28.146 | I13: =Model!I93 -> 58.734 | J13: =Model!N93 -> 74.418 | K13: =Model!S93 -> 85.693 | L13: =Model!X93 -> 89.975 | M13: =Model!AC93 -> 79.136 | N13: =Model!AH93 -> 94.737 | O13: =Model!AM93 -> 141.177 | P13: =Model!AR93 -> 152.586 | Q13: =Model!AW93 -> 180.321 | R13: =Model!BB93 -> 335.141 | S13: =Model!BG93 -> 470.488 | T13: =Model!BL93 -> 460.496 | U13: =Model!BQ93 -> 482.16 | V13: =Model!BV93 -> 352.2
B14: Adj. EBITDA Margin % | C14: =Model!C146 -> 0.10047351 | D14: =Model!D146 -> 0.08158603 | E14: =Model!E146 -> 0.064186386 | F14: =Model!F146 -> 0.027742154 | G14: =Model!G146 -> 0.053945007 | H14: =Model!H146 -> 0.06355511 | I14: =Model!I146 -> 0.097326881 | J14: =Model!N146 -> 0.11078893 | K14: =Model!S146 -> 0.11381876 | L14: =Model!X146 -> 0.12698649 | M14: =Model!AC146 -> 0.12766141 | N14: =Model!AH146 -> 0.13197655 | O14: =Model!AM146 -> 0.14717426 | P14: =Model!AR146 -> 0.15249883 | Q14: =Model!AW146 -> 0.17346131 | R14: =Model!BB146 -> 0.20684982 | S14: =Model!BG146 -> 0.22487435 | T14: =Model!BL146 -> 0.22259723 | U14: =Model!BQ146 -> 0.21625989 | V14: =Model!BV146 -> 0.18172543
B15: GAAP Op. Margin % | C15: =Model!C179 -> 0.057153113 | D15: =Model!D179 -> 0.03910163 | E15: =Model!E179 -> -0.0095601701 | F15: =Model!F179 -> -0.004349101 | G15: =Model!G179 -> 0.013404826 | H15: =Model!H179 -> 0.027320272 | I15: =Model!I179 -> 0.053458745 | J15: =Model!N179 -> 0.065330868 | K15: =Model!S179 -> 0.067351714 | L15: =Model!X179 -> 0.073670834 | M15: =Model!AC179 -> 0.064946437 | N15: =Model!AH179 -> 0.068724202 | O15: =Model!AM179 -> 0.08536269 | P15: =Model!AR179 -> 0.085399346 | Q15: =Model!AW179 -> 0.098948839 | R15: =Model!BB179 -> 0.14643265 | S15: =Model!BG179 -> 0.16850945 | T15: =Model!BL179 -> 0.15981493 | U15: =Model!BQ179 -> 0.15024895 | V15: =Model!BV179 -> 0.10889575
C17: =C7 -> 2006 | D17: =D7 -> 2007 | E17: =E7 -> 2008 | F17: =F7 -> 2009 | G17: =G7 -> 2010 | H17: =H7 -> 2011 | I17: =I7 -> 2012 | J17: =J7 -> 2013 | ... V17: =V7 -> 2025
B18: ROIC | C18: =IFERROR(Model!C302+0,NA()) -> 0.11277632 | D18: =IFERROR(Model!D302+0,NA()) -> 0.067180332 | E18: =IFERROR(Model!E302+0,NA()) -> 0.073247243 | F18: =IFERROR(Model!F302+0,NA()) -> -0.033356226 | G18: =IFERROR(Model!G302+0,NA()) -> 0.039858705 | H18: =IFERROR(Model!H302+0,NA()) -> 0.062191206 | I18: =IFERROR(Model!I302+0,NA()) -> 0.11730763 | J18: =IFERROR(Model!N302+0,NA()) -> 0.12524233 | K18: =IFERROR(Model!S302+0,NA()) -> 0.12323934 | L18: =IFERROR(Model!X302+0,NA()) -> 0.11604625 | M18: =IFERROR(Model!AC302+0,NA()) -> 0.091548286 | N18: =IFERROR(Model!AH302+0,NA()) -> 0.113409 | O18: =IFERROR(Model!AM302+0,NA()) -> 0.13369813 | P18: =IFERROR(Model!AR302+0,NA()) -> 0.12497804 | Q18: =IFERROR(Model!AW302+0,NA()) -> 0.14141911 | R18: =IFERROR(Model!BB302+0,NA()) -> 0.21683836 | S18: =IFERROR(Model!BG302+0,NA()) -> 0.25258344 | T18: =IFERROR(Model!BL302+0,NA()) -> 0.21185966 | U18: =IFERROR(Model!BQ302+0,NA()) -> 0.14769098 | V18: =IFERROR(Model!BV302+0,NA()) -> 0.094192852
B19: RONTA | C19: =IFERROR(Model!C313+0,NA()) -> 0.091669119 | D19: =IFERROR(Model!D313+0,NA()) -> 0.055151617 | E19: =IFERROR(Model!E313+0,NA()) -> 0.053937828 | F19: =IFERROR(Model!F313+0,NA()) -> -0.026043915 | G19: =IFERROR(Model!G313+0,NA()) -> 0.029308813 | H19: =IFERROR(Model!H313+0,NA()) -> 0.048534142 | I19: =IFERROR(Model!I313+0,NA()) -> 0.092228874 | J19: =IFERROR(Model!N313+0,NA()) -> 0.098909622 | K19: =IFERROR(Model!S313+0,NA()) -> 0.097171928 | L19: =IFERROR(Model!X313+0,NA()) -> 0.096034894 | M19: =IFERROR(Model!AC313+0,NA()) -> 0.075634507 | N19: =IFERROR(Model!AH313+0,NA()) -> 0.098959087 | O19: =IFERROR(Model!AM313+0,NA()) -> 0.1158267 | P19: =IFERROR(Model!AR313+0,NA()) -> 0.099597861 | Q19: =IFERROR(Model!AW313+0,NA()) -> 0.1100819 | R19: =IFERROR(Model!BB313+0,NA()) -> 0.1635667 | S19: =IFERROR(Model!BG313+0,NA()) -> 0.18767042 | T19: =IFERROR(Model!BL313+0,NA()) -> 0.15497829 | U19: =IFERROR(Model!BQ313+0,NA()) -> 0.12791436 | V19: =IFERROR(Model!BV313+0,NA()) -> 0.080054342
B20: Adj. EBITDA margin % | C20: =IFERROR(Model!C146+0,NA()) -> 0.10047351 | D20: =IFERROR(Model!D146+0,NA()) -> 0.08158603 | E20: =IFERROR(Model!E146+0,NA()) -> 0.064186386 | F20: =IFERROR(Model!F146+0,NA()) -> 0.027742154 | G20: =IFERROR(Model!G146+0,NA()) -> 0.053945007 | H20: =IFERROR(Model!H146+0,NA()) -> 0.06355511 | I20: =IFERROR(Model!I146+0,NA()) -> 0.097326881 | J20: =IFERROR(Model!N146+0,NA()) -> 0.11078893 | K20: =IFERROR(Model!S146+0,NA()) -> 0.11381876 | L20: =IFERROR(Model!X146+0,NA()) -> 0.12698649 | M20: =IFERROR(Model!AC146+0,NA()) -> 0.12766141 | N20: =IFERROR(Model!AH146+0,NA()) -> 0.13197655 | O20: =IFERROR(Model!AM146+0,NA()) -> 0.14717426 | P20: =IFERROR(Model!AR146+0,NA()) -> 0.15249883 | Q20: =IFERROR(Model!AW146+0,NA()) -> 0.17346131 | R20: =IFERROR(Model!BB146+0,NA()) -> 0.20684982 | S20: =IFERROR(Model!BG146+0,NA()) -> 0.22487435 | T20: =IFERROR(Model!BL146+0,NA()) -> 0.22259723 | U20: =IFERROR(Model!BQ146+0,NA()) -> 0.21625989 | V20: =IFERROR(Model!BV146+0,NA()) -> 0.18172543
B21: FCF margin % | C21: =IFERROR(Model!C213+0,NA()) -> -0.019546424 | D21: =IFERROR(Model!D213+0,NA()) -> -0.050418851 | E21: =IFERROR(Model!E213+0,NA()) -> 0.052921088 | F21: =IFERROR(Model!F213+0,NA()) -> 0.0067444629 | G21: =IFERROR(Model!G213+0,NA()) -> 0.021681475 | H21: =IFERROR(Model!H213+0,NA()) -> -0.012279854 | I21: =IFERROR(Model!I213+0,NA()) -> 0.013247727 | J21: =IFERROR(Model!N213+0,NA()) -> -0.02198765 | K21: =IFERROR(Model!S213+0,NA()) -> 0.0034739661 | L21: =IFERROR(Model!X213+0,NA()) -> 0.046028407 | M21: =IFERROR(Model!AC213+0,NA()) -> 0.021675348 | N21: =IFERROR(Model!AH213+0,NA()) -> -0.020928394 | O21: =IFERROR(Model!AM213+0,NA()) -> 0.019810757 | P21: =IFERROR(Model!AR213+0,NA()) -> -0.008271512 | Q21: =IFERROR(Model!AW213+0,NA()) -> 0.042803147 | R21: =IFERROR(Model!BB213+0,NA()) -> 0.042314777 | S21: =IFERROR(Model!BG213+0,NA()) -> 0.037820503 | T21: =IFERROR(Model!BL213+0,NA()) -> 0.047915742 | U21: =IFERROR(Model!BQ213+0,NA()) -> -0.14329835 | V21: =IFERROR(Model!BV213+0,NA()) -> 0.0084513243
