Workbook

Sheet Model
CC1: SCENARIO SWITCH ▼ (Bull / Base / Bear) — drives all scenario-linked forecast drivers
B2: S&P Global Inc. (NYSE: SPGI) — 3-Statement Financial Model | CC2: Base
B3: US GAAP · USD millions (per-share data in USD; shares in millions) · Fiscal years ended 31 December · Source: S&P Global Forms 10-K / 10-Q, Form 8-K earnings releases (Ex. 99.1), the 8-K / 8-K/A of 2 / 6-Jul-2026 (Mobility spin-off, pro forma and recast) and deal / financing 8-Ks, SEC EDGAR (CIK 64040; McGraw Hill Financial 2013–16, The McGraw-Hill Companies before); XBRL company facts; investor-relations releases are the same documents as filed on EDGAR
B4: Basis notes: hybrid recast — FY2010–11 continuing operations (McGraw-Hill Education sold Mar-2013); FY2012–2024 as originally reported; 2025 and 1H-26 pro forma excluding Mobility (spun off 1-Jul-2026 as Mobility Global, NYSE: MBGL). Divisions: Ratings, Indices (S&P DJI JV with CME 73/27 from Jul-2012), Energy (C&C / Platts / Commodity Insights), Market Intelligence (Capital IQ; SNL Sep-2015). IHS Markit merger 28-Feb-2022; Engineering Solutions sold May-2023; OSTTRA stake sold Q4-2025. Q3–Q4/26E calibrated to FY26 guidance (28-Jul-2026).
CE5: Forecast | CF5: Historical | CG5: Historical | CH5: Historical
B6: (USDm) | C6: 2010 | D6: 2011 | E6: 2012 | F6: Q1/13 | G6: Q2/13 | H6: Q3/13 | I6: Q4/13 | J6: 2013 | K6: Q1/14 | L6: Q2/14 | M6: Q3/14 | N6: Q4/14 | O6: 2014 | P6: Q1/15 | Q6: Q2/15 | R6: Q3/15 | S6: Q4/15 | T6: 2015 | U6: Q1/16 | V6: Q2/16 | W6: Q3/16 | X6: Q4/16 | Y6: 2016 | Z6: Q1/17 | AA6: Q2/17 | AB6: Q3/17 | AC6: Q4/17 | AD6: 2017 | AE6: Q1/18 | AF6: Q2/18 | AG6: Q3/18 | AH6: Q4/18 | AI6: 2018 | AJ6: Q1/19 | AK6: Q2/19 | AL6: Q3/19 | AM6: Q4/19 | AN6: 2019 | AO6: Q1/20 | AP6: Q2/20 | AQ6: Q3/20 | AR6: Q4/20 | AS6: 2020 | AT6: Q1/21 | AU6: Q2/21 | AV6: Q3/21 | AW6: Q4/21 | AX6: 2021 | AY6: Q1/22 | AZ6: Q2/22 | BA6: Q3/22 | BB6: Q4/22 | BC6: 2022 | BD6: Q1/23 | BE6: Q2/23 | BF6: Q3/23 | BG6: Q4/23 | BH6: 2023 | BI6: Q1/24 | BJ6: Q2/24 | BK6: Q3/24 | BL6: Q4/24 | BM6: 2024 | BN6: Q1/25 | BO6: Q2/25 | BP6: Q3/25 | BQ6: Q4/25 | BR6: 2025 | BS6: Q1/26 | BT6: Q2/26 | BU6: Q3/26E | BV6: Q4/26E | BW6: 2026E | BX6: 2027E | BY6: 2028E | BZ6: 2029E | CA6: 2030E | CB6: 2031E | CC6: Modelling Notes | CE6: 5Y CAGR | CF6: 5Y CAGR | CG6: 10Y CAGR | CH6: 15Y CAGR
CE7: 26-'31 | CF7: 20-'25 | CG7: 15-'25 | CH7: 10-'25
B8: DIVISION P&L — RATINGS · INDICES · ENERGY · MARKET INTELLIGENCE (revenue by type × adjusted operating margin) | CC8: DIVISION BUILD — modelling logic (revenue by type → division revenue → division adjusted OP at the adjusted margin → − adjusted corporate unallocated + adjusted equity income = adjusted OP → GAAP P&L)
CK9: SCENARIO INPUT TABLE — driver assumptions per Bull / Base / Bear | CL9: Bull | CM9: Base | CN9: Bear | CO9: Bull / Bear = Base + Δ (Δ inputs on each block header). Outlook block = high / mid / low end of the FY26 guidance ranges.
B10: S&P Global Ratings (credit ratings, research & analytics; Crisil) — "S&P Ratings" 2010–15 | CC10: RATINGS — modelling logic
B11: Transaction revenue (new issuance: bonds, bank loans, structured finance) | D11: 651 | E11: 903 | F11: 264 | G11: 287 | H11: 227 | I11: 257 | J11: 1035 | K11: 245 | L11: 327 | M11: 269 | N11: 288 | O11: 1129 | P11: 289 | Q11: 329 | R11: 244 | S11: 247 | T11: 1109 | U11: 225 | V11: 343 | W11: 299 | X11: 311 | Y11: 1178 | Z11: 373 | AA11: 394 | AB11: 372 | AC11: 401 | AD11: 1540 | AE11: 368 | AF11: 397 | AG11: 328 | AH11: 283 | AI11: 1377 | AJ11: 331 | AK11: 429 | AL11: 402 | AM11: 429 | AN11: 1577 | AO11: 432 | AP11: 624 | AQ11: 490 | AR11: 430 | AS11: 1977 | AT11: 582 | AU11: 615 | AV11: 551 | AW11: 504 | AX11: 2253 | AZ11: 344 | BA11: 244 | BB11: 249 | BD11: 379 | BE11: 383 | BF11: 326 | BG11: 338 | BH11: 1425 | BI11: 582 | BJ11: 626 | BK11: 597 | BL11: 521 | BM11: 2326 | BN11: 620 | BO11: 597 | BP11: 668 | BQ11: 585 | BR11: 2470 | BS11: 712 | BT11: 746 | BU11: =BP11*(1+BU12) -> 749.42934 | BV11: =BQ11*(1+BV12) -> 656.31162 | BW11: =SUM(BS11:BV11) -> 2863.741 | BX11: =BW11*(1+BX12) -> 2949.6532 | BY11: =BX11*(1+BY12) -> 3126.6324 | BZ11: =BY11*(1+BZ12) -> 3314.2303 | CA11: =BZ11*(1+CA12) -> 3479.9418 | CB11: =CA11*(1+CB12) -> 3653.9389 | CC11: Revenue by type (release revenue-information exhibit; 10-K / 10-Q revenue note). Q3–Q4/26E: prior-year quarter × (1 + growth). 2027E+: prior year × (1 + scenario lever). | CE11: =IFERROR((CB11/BW11)^(1/5)-1,"n/m") -> 0.049942488 | CF11: =IFERROR((BR11/AS11)^(1/5)-1,"n/m") -> 0.045533751 | CG11: =IFERROR((BR11/T11)^(1/10)-1,"n/m") -> 0.08336934 | CH11: =IFERROR((BR11/C11)^(1/15)-1,"n/m") -> n/m | CK11: FY26 guidance — Q2-26 release (28-Jul-2026), continuing operations excl. Mobility | CL11: High | CM11: Mid | CN11: Low | CO11: Revenue +5.9–7.9% (organic cc +6–8%) on FY2025 pro forma revenue $13,589m; adjusted EPS $17.50–17.75; GAAP EPS $16.35–16.60; adjusted margin +35–60 bp (+75–100 bp ex OSTTRA); deal amortization ~$785m; corporate unallocated $185–195m adjusted; interest $365–385m GAAP / $390–410m adjusted; tax 22–23%; capex $190–210m; >$7bn of 2026 buybacks. Source: SEC EDGAR 8-K Ex. 99.1 (no unverified guidance used).
B12: y/y % | D12: =IF(AND(ISNUMBER(D11),ISNUMBER(C11)),IFERROR(D11/C11-1,""),"") | E12: =IF(AND(ISNUMBER(E11),ISNUMBER(D11)),IFERROR(E11/D11-1,""),"") -> 0.38709677 | J12: =IF(AND(ISNUMBER(J11),ISNUMBER(E11)),IFERROR(J11/E11-1,""),"") -> 0.1461794 | K12: =IF(AND(ISNUMBER(K11),ISNUMBER(F11)),IFERROR(K11/F11-1,""),"") -> -0.071969697 | L12: =IF(AND(ISNUMBER(L11),ISNUMBER(G11)),IFERROR(L11/G11-1,""),"") -> 0.13937282 | M12: =IF(AND(ISNUMBER(M11),ISNUMBER(H11)),IFERROR(M11/H11-1,""),"") -> 0.18502203 | N12: =IF(AND(ISNUMBER(N11),ISNUMBER(I11)),IFERROR(N11/I11-1,""),"") -> 0.12062257 | O12: =IF(AND(ISNUMBER(O11),ISNUMBER(J11)),IFERROR(O11/J11-1,""),"") -> 0.090821256 | P12: =IF(AND(ISNUMBER(P11),ISNUMBER(K11)),IFERROR(P11/K11-1,""),"") -> 0.17959184 | Q12: =IF(AND(ISNUMBER(Q11),ISNUMBER(L11)),IFERROR(Q11/L11-1,""),"") -> 0.006116208 | ... BT12: =IF(AND(ISNUMBER(BT11),ISNUMBER(BO11)),IFERROR(BT11/BO11-1,""),"") -> 0.24958124 | BU12: =$BW$13+$BW$149 -> 0.12190021 | BV12: =$BW$13+$BW$149 -> 0.12190021 | BW12: =IF(AND(ISNUMBER(BW11),ISNUMBER(BR11)),IFERROR(BW11/BR11-1,""),"") -> 0.1594093 | BX12: =CHOOSE(MATCH($CC$2,{"Bull","Base","Bear"},0),$CL$35,$CM$35,$CN$35) -> 0.03 | BY12: =CHOOSE(MATCH($CC$2,{"Bull","Base","Bear"},0),$CL$36,$CM$36,$CN$36) -> 0.06 | BZ12: =CHOOSE(MATCH($CC$2,{"Bull","Base","Bear"},0),$CL$37,$CM$37,$CN$37) -> 0.06 | CA12: =CHOOSE(MATCH($CC$2,{"Bull","Base","Bear"},0),$CL$38,$CM$38,$CN$38) -> 0.05 | CB12: =CHOOSE(MATCH($CC$2,{"Bull","Base","Bear"},0),$CL$39,$CM$39,$CN$39) -> 0.05 | CC12: Q3–Q4/26E: 1H-26 y/y growth of the line + revenue-guidance calibration Δ (Group block). 2027E–2031E: scenario lever. | CK12: FY26 revenue growth (vs FY2025 pro forma) | CL12: 0.079 | CM12: 0.069 | CN12: 0.059 | CO12: Guided +5.9–7.9%. Drives the Q3–Q4/26E revenue calibration.
B13: Q3–Q4/26E growth before revenue calibration (1H-26 y/y) | BW13: =IFERROR(SUM(BS11:BT11)/SUM(BN11:BO11)-1,0) -> 0.19802794 | CK13: FY26 adjusted diluted EPS ($) | CL13: 17.75 | CM13: 17.625 | CN13: 17.5 | CO13: Guided $17.50–17.75. Drives the margin calibration.
B14: Non-transaction revenue (surveillance, frequent-issuer programs, Crisil & other) | D14: 1116 | E14: 1131 | F14: 297 | G14: 312 | H14: 313 | I14: 317 | J14: 1239 | K14: 324 | L14: 337 | M14: 335 | N14: 330 | O14: 1326 | P14: 317 | Q14: 329 | R14: 343 | S14: 331 | T14: 1319 | U14: 327 | V14: 339 | W14: 343 | X14: 347 | Y14: 1357 | Z14: 341 | AA14: 353 | AB14: 367 | AC14: 388 | AD14: 1448 | AE14: 380 | AF14: 378 | AG14: 372 | AH14: 378 | AI14: 1506 | AJ14: 365 | AK14: 372 | AL14: 387 | AM14: 391 | AN14: 1529 | AO14: 393 | AP14: 382 | AQ14: 404 | AR14: 451 | AS14: 1629 | AT14: 435 | AU14: 458 | AV14: 466 | AW14: 485 | AX14: 1844 | AZ14: 452 | BA14: 437 | BB14: 456 | BD14: 445 | BE14: 468 | BF14: 493 | BG14: 500 | BH14: 1907 | BI14: 480 | BJ14: 509 | BK14: 513 | BL14: 541 | BM14: 2044 | BN14: 529 | BO14: 551 | BP14: 572 | BQ14: 602 | BR14: 2254 | BS14: 590 | BT14: 593 | BU14: =BP14*(1+BU15) -> 583.00679 | BV14: =BQ14*(1+BV15) -> 613.58407 | BW14: =SUM(BS14:BV14) -> 2379.5909 | BX14: =BW14*(1+BX15) -> 2546.1622 | BY14: =BX14*(1+BY15) -> 2724.3936 | BZ14: =BY14*(1+BZ15) -> 2887.8572 | CA14: =BZ14*(1+CA15) -> 3061.1286 | CB14: =CA14*(1+CB15) -> 3244.7963 | CE14: =IFERROR((CB14/BW14)^(1/5)-1,"n/m") -> 0.063988736 | CF14: =IFERROR((BR14/AS14)^(1/5)-1,"n/m") -> 0.067103552 | CG14: =IFERROR((BR14/T14)^(1/10)-1,"n/m") -> 0.055044825 | CH14: =IFERROR((BR14/C14)^(1/15)-1,"n/m") -> n/m | CK14: FY26 GAAP diluted EPS, continuing ($) — memo | CL14: 16.6 | CM14: 16.475 | CN14: 16.35 | CO14: Guided $16.35–16.60 (information row).
B15: y/y % | D15: =IF(AND(ISNUMBER(D14),ISNUMBER(C14)),IFERROR(D14/C14-1,""),"") | E15: =IF(AND(ISNUMBER(E14),ISNUMBER(D14)),IFERROR(E14/D14-1,""),"") -> 0.01344086 | J15: =IF(AND(ISNUMBER(J14),ISNUMBER(E14)),IFERROR(J14/E14-1,""),"") -> 0.095490716 | K15: =IF(AND(ISNUMBER(K14),ISNUMBER(F14)),IFERROR(K14/F14-1,""),"") -> 0.090909091 | L15: =IF(AND(ISNUMBER(L14),ISNUMBER(G14)),IFERROR(L14/G14-1,""),"") -> 0.080128205 | M15: =IF(AND(ISNUMBER(M14),ISNUMBER(H14)),IFERROR(M14/H14-1,""),"") -> 0.07028754 | N15: =IF(AND(ISNUMBER(N14),ISNUMBER(I14)),IFERROR(N14/I14-1,""),"") -> 0.041009464 | O15: =IF(AND(ISNUMBER(O14),ISNUMBER(J14)),IFERROR(O14/J14-1,""),"") -> 0.070217918 | P15: =IF(AND(ISNUMBER(P14),ISNUMBER(K14)),IFERROR(P14/K14-1,""),"") -> -0.021604938 | Q15: =IF(AND(ISNUMBER(Q14),ISNUMBER(L14)),IFERROR(Q14/L14-1,""),"") -> -0.023738872 | ... BT15: =IF(AND(ISNUMBER(BT14),ISNUMBER(BO14)),IFERROR(BT14/BO14-1,""),"") -> 0.076225045 | BU15: =$BW$16+$BW$149 -> 0.019242642 | BV15: =$BW$16+$BW$149 -> 0.019242642 | BW15: =IF(AND(ISNUMBER(BW14),ISNUMBER(BR14)),IFERROR(BW14/BR14-1,""),"") -> 0.055719105 | BX15: =CHOOSE(MATCH($CC$2,{"Bull","Base","Bear"},0),$CL$41,$CM$41,$CN$41) -> 0.07 | BY15: =CHOOSE(MATCH($CC$2,{"Bull","Base","Bear"},0),$CL$42,$CM$42,$CN$42) -> 0.07 | BZ15: =CHOOSE(MATCH($CC$2,{"Bull","Base","Bear"},0),$CL$43,$CM$43,$CN$43) -> 0.06 | CA15: =CHOOSE(MATCH($CC$2,{"Bull","Base","Bear"},0),$CL$44,$CM$44,$CN$44) -> 0.06 | CB15: =CHOOSE(MATCH($CC$2,{"Bull","Base","Bear"},0),$CL$45,$CM$45,$CN$45) -> 0.06 | CK15: FY26 adjusted margin expansion (bp) — memo | CL15: 60 | CM15: 47.5 | CN15: 35 | CO15: Guided +35–60 bp vs FY2025 pro forma 51.3% (information row).
B16: Q3–Q4/26E growth before revenue calibration (1H-26 y/y) | BW16: =IFERROR(SUM(BS14:BT14)/SUM(BN14:BO14)-1,0) -> 0.09537037 | CK16: FY26 organic constant-currency growth — memo | CL16: 0.08 | CM16: 0.07 | CN16: 0.06 | CO16: Guided +6–8% (information row).
B17: Not split by type (history only: periods without a revenue-by-type table on this basis) | C17: =IF(ISNUMBER(C21),C21-(N(C11)+N(C14)),"") -> 1695 | D17: =IF(ISNUMBER(D21),D21-(N(D11)+N(D14)),"") -> 0 | E17: =IF(ISNUMBER(E21),E21-(N(E11)+N(E14)),"") -> 0 | F17: =IF(ISNUMBER(F21),F21-(N(F11)+N(F14)),"") -> 0 | G17: =IF(ISNUMBER(G21),G21-(N(G11)+N(G14)),"") -> 0 | H17: =IF(ISNUMBER(H21),H21-(N(H11)+N(H14)),"") -> 0 | I17: =IF(ISNUMBER(I21),I21-(N(I11)+N(I14)),"") -> 0 | J17: =IF(ISNUMBER(J21),J21-(N(J11)+N(J14)),"") -> 0 | ... BT17: =IF(ISNUMBER(BT21),BT21-(N(BT11)+N(BT14)),"") -> 0 | CK17: 2H-26 share repurchases ($m) | CL17: 6000 | CM17: 5750 | CN17: 5500 | CO17: 1H-26 $1,500m (ASRs at $426.70 and $414.76); company expects >$7bn for 2026 → 2H ≥ $5.5bn (assumption by case).
B18: Ratings — division revenue | C18: =IF(ISNUMBER(C21),N(C11)+N(C14)+N(C17),"") -> 1695 | D18: =IF(ISNUMBER(D21),N(D11)+N(D14)+N(D17),"") -> 1767 | E18: =IF(ISNUMBER(E21),N(E11)+N(E14)+N(E17),"") -> 2034 | F18: =IF(ISNUMBER(F21),N(F11)+N(F14)+N(F17),"") -> 561 | G18: =IF(ISNUMBER(G21),N(G11)+N(G14)+N(G17),"") -> 599 | H18: =IF(ISNUMBER(H21),N(H11)+N(H14)+N(H17),"") -> 540 | I18: =IF(ISNUMBER(I21),N(I11)+N(I14)+N(I17),"") -> 574 | J18: =IF(ISNUMBER(J21),N(J11)+N(J14)+N(J17),"") -> 2274 | ... BT18: =IF(ISNUMBER(BT21),N(BT11)+N(BT14)+N(BT17),"") -> 1339 | BU18: =BU11+BU14 -> 1332.4361 | BV18: =BV11+BV14 -> 1269.8957 | BW18: =BW11+BW14 -> 5243.3318 | BX18: =BX11+BX14 -> 5495.8154 | BY18: =BY11+BY14 -> 5851.026 | BZ18: =BZ11+BZ14 -> 6202.0875 | CA18: =CA11+CA14 -> 6541.0705 | CB18: =CB11+CB14 -> 6898.7353 | CC18: History: division revenue as reported (Σ revenue types + any unsplit remainder). | CE18: =IFERROR((CB18/BW18)^(1/5)-1,"n/m") -> 0.056409815 | CF18: =IFERROR((BR18/AS18)^(1/5)-1,"n/m") -> 0.055496587 | CG18: =IFERROR((BR18/T18)^(1/10)-1,"n/m") -> 0.068823812 | CH18: =IFERROR((BR18/C18)^(1/15)-1,"n/m") -> 0.07072024
B19: Division revenue y/y % | D19: =IF(AND(ISNUMBER(D18),ISNUMBER(C18)),IFERROR(D18/C18-1,""),"") -> 0.042477876 | E19: =IF(AND(ISNUMBER(E18),ISNUMBER(D18)),IFERROR(E18/D18-1,""),"") -> 0.15110357 | J19: =IF(AND(ISNUMBER(J18),ISNUMBER(E18)),IFERROR(J18/E18-1,""),"") -> 0.1179941 | K19: =IF(AND(ISNUMBER(K18),ISNUMBER(F18)),IFERROR(K18/F18-1,""),"") -> 0.01426025 | L19: =IF(AND(ISNUMBER(L18),ISNUMBER(G18)),IFERROR(L18/G18-1,""),"") -> 0.10851419 | M19: =IF(AND(ISNUMBER(M18),ISNUMBER(H18)),IFERROR(M18/H18-1,""),"") -> 0.11851852 | N19: =IF(AND(ISNUMBER(N18),ISNUMBER(I18)),IFERROR(N18/I18-1,""),"") -> 0.076655052 | O19: =IF(AND(ISNUMBER(O18),ISNUMBER(J18)),IFERROR(O18/J18-1,""),"") -> 0.079595427 | P19: =IF(AND(ISNUMBER(P18),ISNUMBER(K18)),IFERROR(P18/K18-1,""),"") -> 0.065026362 | Q19: =IF(AND(ISNUMBER(Q18),ISNUMBER(L18)),IFERROR(Q18/L18-1,""),"") -> -0.0090361446 | ... BW19: =IF(AND(ISNUMBER(BW18),ISNUMBER(BR18)),IFERROR(BW18/BR18-1,""),"") -> 0.10993476 | BX19: =IF(AND(ISNUMBER(BX18),ISNUMBER(BW18)),IFERROR(BX18/BW18-1,""),"") -> 0.048153273 | BY19: =IF(AND(ISNUMBER(BY18),ISNUMBER(BX18)),IFERROR(BY18/BX18-1,""),"") -> 0.064632911 | BZ19: =IF(AND(ISNUMBER(BZ18),ISNUMBER(BY18)),IFERROR(BZ18/BY18-1,""),"") -> 0.06 | CA19: =IF(AND(ISNUMBER(CA18),ISNUMBER(BZ18)),IFERROR(CA18/BZ18-1,""),"") -> 0.054656266 | CB19: =IF(AND(ISNUMBER(CB18),ISNUMBER(CA18)),IFERROR(CB18/CA18-1,""),"") -> 0.054679859 | CK19: Q3/26E–Q4/26E point estimates (all cases; per quarter unless stated)
B20: % of total revenue | C20: =IF(AND(ISNUMBER(C18),ISNUMBER(C138)),IFERROR(C18/C138,""),"") -> 0.4657873 | D20: =IF(AND(ISNUMBER(D18),ISNUMBER(D138)),IFERROR(D18/D138,""),"") -> 0.44688923 | E20: =IF(AND(ISNUMBER(E18),ISNUMBER(E138)),IFERROR(E18/E138,""),"") -> 0.45707865 | F20: =IF(AND(ISNUMBER(F18),ISNUMBER(F138)),IFERROR(F18/F138,""),"") -> 0.47502117 | G20: =IF(AND(ISNUMBER(G18),ISNUMBER(G138)),IFERROR(G18/G138,""),"") -> 0.4792 | H20: =IF(AND(ISNUMBER(H18),ISNUMBER(H138)),IFERROR(H18/H138,""),"") -> 0.45226131 | I20: =IF(AND(ISNUMBER(I18),ISNUMBER(I138)),IFERROR(I18/I138,""),"") -> 0.4592 | J20: =IF(AND(ISNUMBER(J18),ISNUMBER(J138)),IFERROR(J18/J138,""),"") -> 0.46646154 | ... CB20: =IF(AND(ISNUMBER(CB18),ISNUMBER(CB138)),IFERROR(CB18/CB138,""),"") -> 0.34421387 | CE20: =IFERROR(AVERAGE(BX20,BY20,BZ20,CA20,CB20),"n/m") -> 0.3507719 | CF20: =IFERROR(AVERAGE(AX20,BC20,BH20,BM20,BR20),"n/m") -> 0.33768169 | CG20: =IFERROR(AVERAGE(Y20,AD20,AI20,AN20,AS20,AX20,BC20,BH20,BM20,BR20),"n/m") -> 0.40379233 | CH20: =IFERROR(AVERAGE(C20,D20,E20,J20,O20,T20,Y20,AD20,AI20,AN20,AS20,AX20,BC20,BH20,BM20,BR20),"n/m") -> 0.42607342 | CK20: Adjusted corporate unallocated expense ($m / quarter) | CM20: 54 | CO20: FY26 guided $185–195m adjusted; 1H $82m → (190 − 82) ÷ 2.
B21: Memo: Ratings revenue as reported (segment exhibit; 2025+ adjusted as recast) | C21: 1695 | D21: 1767 | E21: 2034 | F21: 561 | G21: 599 | H21: 540 | I21: 574 | J21: 2274 | K21: 569 | L21: 664 | M21: 604 | N21: 618 | O21: 2455 | P21: 606 | Q21: 658 | R21: 587 | S21: 578 | T21: 2428 | U21: 552 | V21: 682 | W21: 642 | X21: 658 | Y21: 2535 | Z21: 714 | AA21: 747 | AB21: 739 | AC21: 789 | AD21: 2988 | AE21: 748 | AF21: 775 | AG21: 700 | AH21: 661 | AI21: 2883 | AJ21: 696 | AK21: 801 | AL21: 789 | AM21: 820 | AN21: 3106 | AO21: 825 | AP21: 1006 | AQ21: 894 | AR21: 881 | AS21: 3606 | AT21: 1017 | AU21: 1073 | AV21: 1017 | AW21: 989 | AX21: 4097 | AY21: 868 | AZ21: 796 | BA21: 681 | BB21: 705 | BC21: 3050 | BD21: 824 | BE21: 851 | BF21: 819 | BG21: 838 | BH21: 3332 | BI21: 1062 | BJ21: 1135 | BK21: 1110 | BL21: 1062 | BM21: 4370 | BN21: 1149 | BO21: 1148 | BP21: 1240 | BQ21: 1187 | BR21: 4724 | BS21: 1302 | BT21: 1339 | CK21: Deal-related amortization ($m / quarter) | CM21: 193 | CO21: FY26 guided ~$785m; 1H $399m → (785 − 399) ÷ 2.
B22: Check: revenue types vs division revenue (should be 0; ±1 rounding) | C22: =IF(AND(ISNUMBER(C11),ISNUMBER(C21)),IF(ABS(C18-C21)<=1.01,0,ROUND(C18-C21,0)),"") | D22: =IF(AND(ISNUMBER(D11),ISNUMBER(D21)),IF(ABS(D18-D21)<=1.01,0,ROUND(D18-D21,0)),"") -> 0 | E22: =IF(AND(ISNUMBER(E11),ISNUMBER(E21)),IF(ABS(E18-E21)<=1.01,0,ROUND(E18-E21,0)),"") -> 0 | F22: =IF(AND(ISNUMBER(F11),ISNUMBER(F21)),IF(ABS(F18-F21)<=1.01,0,ROUND(F18-F21,0)),"") -> 0 | G22: =IF(AND(ISNUMBER(G11),ISNUMBER(G21)),IF(ABS(G18-G21)<=1.01,0,ROUND(G18-G21,0)),"") -> 0 | H22: =IF(AND(ISNUMBER(H11),ISNUMBER(H21)),IF(ABS(H18-H21)<=1.01,0,ROUND(H18-H21,0)),"") -> 0 | I22: =IF(AND(ISNUMBER(I11),ISNUMBER(I21)),IF(ABS(I18-I21)<=1.01,0,ROUND(I18-I21,0)),"") -> 0 | J22: =IF(AND(ISNUMBER(J11),ISNUMBER(J21)),IF(ABS(J18-J21)<=1.01,0,ROUND(J18-J21,0)),"") -> 0 | ... BT22: =IF(AND(ISNUMBER(BT11),ISNUMBER(BT21)),IF(ABS(BT18-BT21)<=1.01,0,ROUND(BT18-BT21,0)),"") -> 0 | CK22: Interest expense, net — GAAP ($m / quarter) | CM22: 98 | CO22: FY26 guided $365–385m GAAP; 1H $179m → (375 − 179) ÷ 2.
B23: Ratings — adjusted operating profit | D23: 728 | E23: 865 | F23: 259 | G23: 277 | H23: 227 | I23: 231 | J23: 993 | K23: 240 | L23: 308 | M23: 266 | N23: 261 | O23: 1074 | P23: 285 | Q23: 329 | R23: 280 | S23: 252 | T23: 1146 | U23: 252 | V23: 369 | W23: 330 | X23: 313 | Y23: 1263 | Z23: 379 | AA23: 398 | AB23: 392 | AC23: 439 | AD23: 1608 | AE23: 408 | AF23: 443 | AG23: 396 | AH23: 367 | AI23: 1614 | AJ23: 364 | AK23: 467 | AL23: 472 | AM23: 473 | AN23: 1776 | AO23: 521 | AP23: 695 | AQ23: 552 | AR23: 481 | AS23: 2249 | AT23: 686 | AU23: 731 | AV23: 645 | AW23: 570 | AX23: 2632 | AY23: 518 | AZ23: 473 | BA23: 381 | BB23: 338 | BC23: 1710 | BD23: 480 | BE23: 491 | BF23: 464 | BG23: 447 | BH23: 1882 | BI23: 687 | BJ23: 747 | BK23: 684 | BL23: 634 | BM23: 2753 | BN23: 759 | BO23: 750 | BP23: 831 | BQ23: 735 | BR23: 3076 | BS23: 878 | BT23: 917 | BU23: =BU18*BU24 -> 889.37827 | BV23: =BV18*BV24 -> 782.92834 | BW23: =SUM(BS23:BV23) -> 3467.3066 | BX23: =BX18*BX24 -> 3654.7173 | BY23: =BY18*BY24 -> 3920.1874 | BZ23: =BZ18*BZ24 -> 4155.3986 | CA23: =CA18*CA24 -> 4382.5172 | CB23: =CB18*CB24 -> 4622.1526 | CC23: Division adjusted OP (company non-GAAP: OP + non-GAAP adjustments + deal-related amortization). 2025+: pro forma recast basis. Forecast = revenue × adjusted margin. | CE23: =IFERROR((CB23/BW23)^(1/5)-1,"n/m") -> 0.05918155 | CF23: =IFERROR((BR23/AS23)^(1/5)-1,"n/m") -> 0.064631655 | CG23: =IFERROR((BR23/T23)^(1/10)-1,"n/m") -> 0.10377403 | CH23: =IFERROR((BR23/C23)^(1/15)-1,"n/m") -> n/m | CK23: Premium amortization benefit in interest ($m / quarter) | CM23: 6 | CO23: IHS Markit notes fair-value premium: $6m a quarter (adjusted interest = GAAP + $6m).
B24: Adjusted operating margin % | C24: =IF(AND(ISNUMBER(C23),ISNUMBER(C18)),IFERROR(C23/C18,""),"") | D24: =IF(AND(ISNUMBER(D23),ISNUMBER(D18)),IFERROR(D23/D18,""),"") -> 0.41199774 | E24: =IF(AND(ISNUMBER(E23),ISNUMBER(E18)),IFERROR(E23/E18,""),"") -> 0.4252704 | F24: =IF(AND(ISNUMBER(F23),ISNUMBER(F18)),IFERROR(F23/F18,""),"") -> 0.46167558 | G24: =IF(AND(ISNUMBER(G23),ISNUMBER(G18)),IFERROR(G23/G18,""),"") -> 0.4624374 | H24: =IF(AND(ISNUMBER(H23),ISNUMBER(H18)),IFERROR(H23/H18,""),"") -> 0.42037037 | I24: =IF(AND(ISNUMBER(I23),ISNUMBER(I18)),IFERROR(I23/I18,""),"") -> 0.40243902 | J24: =IF(AND(ISNUMBER(J23),ISNUMBER(J18)),IFERROR(J23/J18,""),"") -> 0.43667546 | ... BT24: =IF(AND(ISNUMBER(BT23),ISNUMBER(BT18)),IFERROR(BT23/BT18,""),"") -> 0.68483943 | BU24: =BU25+$BW$159 -> 0.66748285 | BV24: =BV25+$BW$159 -> 0.61652965 | BW24: =IF(AND(ISNUMBER(BW23),ISNUMBER(BW18)),IFERROR(BW23/BW18,""),"") -> 0.66127926 | BX24: =CHOOSE(MATCH($CC$2,{"Bull","Base","Bear"},0),$CL$77,$CM$77,$CN$77) -> 0.665 | BY24: =CHOOSE(MATCH($CC$2,{"Bull","Base","Bear"},0),$CL$78,$CM$78,$CN$78) -> 0.67 | BZ24: =CHOOSE(MATCH($CC$2,{"Bull","Base","Bear"},0),$CL$79,$CM$79,$CN$79) -> 0.67 | CA24: =CHOOSE(MATCH($CC$2,{"Bull","Base","Bear"},0),$CL$80,$CM$80,$CN$80) -> 0.67 | CB24: =CHOOSE(MATCH($CC$2,{"Bull","Base","Bear"},0),$CL$81,$CM$81,$CN$81) -> 0.67 | CC24: Q3–Q4/26E: margin before calibration + adjusted-EPS-guidance calibration Δ (Group block). 2027E+: scenario lever. | CE24: =IFERROR(AVERAGE(BX24,BY24,BZ24,CA24,CB24),"n/m") -> 0.669 | CF24: =IFERROR(AVERAGE(AX24,BC24,BH24,BM24,BR24),"n/m") -> 0.60980463 | CG24: =IFERROR(AVERAGE(Y24,AD24,AI24,AN24,AS24,AX24,BC24,BH24,BM24,BR24),"n/m") -> 0.58407134 | CH24: =IFERROR(AVERAGE(C24,D24,E24,J24,O24,T24,Y24,AD24,AI24,AN24,AS24,AX24,BC24,BH24,BM24,BR24),"n/m") -> 0.53494166 | CK24: Other income, net ($m / quarter) | CM24: 3 | CO24: 1H-26 $6m (pension income).
B25: Q3–Q4/26E margin before EPS calibration (prior-year quarter + 1H-26 y/y drift) | BU25: =BP24+IFERROR(SUM(BS23:BT23)/SUM(BS18:BT18)-SUM(BN23:BO23)/SUM(BN18:BO18),0) -> 0.69288424 | BV25: =BQ24+IFERROR(SUM(BS23:BT23)/SUM(BS18:BT18)-SUM(BN23:BO23)/SUM(BN18:BO18),0) -> 0.64193104 | CK25: Depreciation ($m / quarter) | CM25: 29 | CO25: 1H-26 $56m continuing.
B26: Incremental adjusted margin (Δ adjusted OP / Δ revenue) | D26: =IFERROR((D23-C23)/(D18-C18),"") -> 10.111111 | E26: =IFERROR((E23-D23)/(E18-D18),"") -> 0.51310861 | J26: =IFERROR((J23-E23)/(J18-E18),"") -> 0.53333333 | K26: =IFERROR((K23-F23)/(K18-F18),"") -> -2.375 | L26: =IFERROR((L23-G23)/(L18-G18),"") -> 0.47692308 | M26: =IFERROR((M23-H23)/(M18-H18),"") -> 0.609375 | N26: =IFERROR((N23-I23)/(N18-I18),"") -> 0.68181818 | O26: =IFERROR((O23-J23)/(O18-J18),"") -> 0.44751381 | P26: =IFERROR((P23-K23)/(P18-K18),"") -> 1.2162162 | Q26: =IFERROR((Q23-L23)/(Q18-L18),"") -> -3.5 | ... BW26: =IFERROR((BW23-BR23)/(BW18-BR18),"") -> 0.7534809 | BX26: =IFERROR((BX23-BW23)/(BX18-BW18),"") -> 0.74226861 | BY26: =IFERROR((BY23-BX23)/(BY18-BX18),"") -> 0.74735997 | BZ26: =IFERROR((BZ23-BY23)/(BZ18-BY18),"") -> 0.67 | CA26: =IFERROR((CA23-BZ23)/(CA18-BZ18),"") -> 0.67 | CB26: =IFERROR((CB23-CA23)/(CB18-CA18),"") -> 0.67 | CK26: Severance & restructuring ($m / quarter) | CM26: 15 | CO26: Assumption (1H-26 continuing ~$45m).
B27: Memo: Ratings — operating profit (GAAP, as reported) | C27: 762 | D27: 720 | E27: 849 | F27: 259 | G27: 277 | H27: 243 | I27: 221 | J27: 1000 | K27: 240 | L27: 308 | M27: 183 | N27: -1313 | O27: -583 | P27: 291 | Q27: 361 | R27: 194 | S27: 232 | T27: 1078 | U27: 262 | V27: 396 | W27: 346 | X27: 258 | Y27: 1262 | Z27: 376 | AA27: 397 | AB27: 376 | AC27: 374 | AD27: 1524 | AE27: 408 | AF27: 369 | AG27: 395 | AH27: 357 | AI27: 1530 | AJ27: 363 | AK27: 455 | AL27: 472 | AM27: 473 | AN27: 1763 | AO27: 520 | AP27: 693 | AQ27: 544 | AR27: 465 | AS27: 2223 | AT27: 681 | AU27: 729 | AV27: 644 | AW27: 575 | AX27: 2629 | AY27: 511 | AZ27: 464 | BA27: 377 | BB27: 320 | BC27: 1672 | BD27: 477 | BE27: 486 | BF27: 459 | BG27: 442 | BH27: 1864 | BI27: 679 | BJ27: 725 | BK27: 676 | BL27: 627 | BM27: 2707 | CK27: Disposition / separation costs ($m / quarter) | CM27: 10 | CO27: Assumption: residual Mobility separation and geoscience / EDM disposition costs.
CK28: Gain on geoscience portfolio sale (Q4/26E; negative = gain) | CM28: -250 | CO28: Assumption implied by the guidance: GAAP vs adjusted margin guidance leaves ~$210m of net 2H gains after amortization, and the EPS bridge includes −$1.20 of divestiture gains ($0.60 booked in 1H).
B29: S&P Dow Jones Indices (73% / 27% JV with CME Group from Jul-2012; S&P DJ Indices to 2015) | CC29: INDICES (S&P DOW JONES INDICES) — modelling logic | CK29: Tax rate (GAAP & adjusted) | CM29: 0.225 | CO29: FY26 guided 22–23%.
B30: Asset-linked fees (ETFs, mutual funds, insurance products) | U30: 86 | V30: 92 | W30: 100 | X30: 104 | Y30: 381 | Z30: 108 | AA30: 114 | AB30: 118 | AC30: 121 | AD30: 461 | AE30: 131 | AF30: 135 | AG30: 131 | AH30: 126 | AI30: 522 | AJ30: 143 | AK30: 159 | AL30: 152 | AM30: 159 | AN30: 613 | AO30: 159 | AP30: 153 | AQ30: 156 | AR30: 179 | AS30: 647 | AT30: 183 | AU30: 195 | AV30: 211 | AW30: 210 | AX30: 800 | AZ30: 214 | BA30: 210 | BB30: 220 | BD30: 210 | BE30: 211 | BF30: 218 | BG30: 221 | BH30: 859 | BI30: 244 | BJ30: 245 | BK30: 266 | BL30: 291 | BM30: 1046 | BN30: 288 | BO30: 286 | BP30: 303 | BQ30: 329 | BR30: 1206 | BS30: 339 | BT30: 348 | BU30: =BP30*(1+BU31) -> 339.58312 | BV30: =BQ30*(1+BV31) -> 368.72227 | BW30: =SUM(BS30:BV30) -> 1395.3054 | BX30: =BW30*(1+BX31) -> 1534.8359 | BY30: =BX30*(1+BY31) -> 1672.9712 | BZ30: =BY30*(1+BZ31) -> 1823.5386 | CA30: =BZ30*(1+CA31) -> 1969.4217 | CB30: =CA30*(1+CB31) -> 2126.9754 | CE30: =IFERROR((CB30/BW30)^(1/5)-1,"n/m") -> 0.087974304 | CF30: =IFERROR((BR30/AS30)^(1/5)-1,"n/m") -> 0.13263142 | CG30: =IFERROR((BR30/T30)^(1/10)-1,"n/m") -> n/m | CH30: =IFERROR((BR30/C30)^(1/15)-1,"n/m") -> n/m | CK30: 2H-26 capital expenditures ($m) | CM30: 135 | CO30: FY26 guided $190–210m; 1H $65m.
B31: y/y % | D31: =IF(AND(ISNUMBER(D30),ISNUMBER(C30)),IFERROR(D30/C30-1,""),"") | E31: =IF(AND(ISNUMBER(E30),ISNUMBER(D30)),IFERROR(E30/D30-1,""),"") | J31: =IF(AND(ISNUMBER(J30),ISNUMBER(E30)),IFERROR(J30/E30-1,""),"") | K31: =IF(AND(ISNUMBER(K30),ISNUMBER(F30)),IFERROR(K30/F30-1,""),"") | L31: =IF(AND(ISNUMBER(L30),ISNUMBER(G30)),IFERROR(L30/G30-1,""),"") | M31: =IF(AND(ISNUMBER(M30),ISNUMBER(H30)),IFERROR(M30/H30-1,""),"") | N31: =IF(AND(ISNUMBER(N30),ISNUMBER(I30)),IFERROR(N30/I30-1,""),"") | O31: =IF(AND(ISNUMBER(O30),ISNUMBER(J30)),IFERROR(O30/J30-1,""),"") | P31: =IF(AND(ISNUMBER(P30),ISNUMBER(K30)),IFERROR(P30/K30-1,""),"") | Q31: =IF(AND(ISNUMBER(Q30),ISNUMBER(L30)),IFERROR(Q30/L30-1,""),"") | ... BT31: =IF(AND(ISNUMBER(BT30),ISNUMBER(BO30)),IFERROR(BT30/BO30-1,""),"") -> 0.21678322 | BU31: =$BW$32+$BW$149 -> 0.12073638 | BV31: =$BW$32+$BW$149 -> 0.12073638 | BW31: =IF(AND(ISNUMBER(BW30),ISNUMBER(BR30)),IFERROR(BW30/BR30-1,""),"") -> 0.15696965 | BX31: =CHOOSE(MATCH($CC$2,{"Bull","Base","Bear"},0),$CL$47,$CM$47,$CN$47) -> 0.1 | BY31: =CHOOSE(MATCH($CC$2,{"Bull","Base","Bear"},0),$CL$48,$CM$48,$CN$48) -> 0.09 | BZ31: =CHOOSE(MATCH($CC$2,{"Bull","Base","Bear"},0),$CL$49,$CM$49,$CN$49) -> 0.09 | CA31: =CHOOSE(MATCH($CC$2,{"Bull","Base","Bear"},0),$CL$50,$CM$50,$CN$50) -> 0.08 | CB31: =CHOOSE(MATCH($CC$2,{"Bull","Base","Bear"},0),$CL$51,$CM$51,$CN$51) -> 0.08
B32: Q3–Q4/26E growth before revenue calibration (1H-26 y/y) | BW32: =IFERROR(SUM(BS30:BT30)/SUM(BN30:BO30)-1,0) -> 0.19686411 | CK32: Target net debt / adjusted EBITDA (x) — buyback plug 2027E+ | CL32: 1.75 | CM32: 1.5 | CN32: 1.25 | CO32: Assumption: net debt / adjusted EBITDA target for 2027E+ buybacks. Model YE2026E ~1.4x after the $7bn+ 2026 buybacks; S&P Global has historically returned ~85% of adjusted FCF and kept leverage near 2x gross. Bull = more buybacks (higher target).
B33: Exchange-traded derivatives (sales usage-based royalties) | D33: 252 | E33: 301 | F33: 90 | G33: 97 | H33: 99 | I33: 103 | J33: 390 | K33: 111 | L33: 105 | M33: 114 | N33: 111 | O33: 441 | P33: 114 | Q33: 118 | R33: 124 | S33: 119 | T33: 475 | U33: 33 | V33: 29 | W33: 31 | X33: 30 | Y33: 125 | Z33: 32 | AA33: 33 | AB33: 33 | AC33: 34 | AD33: 131 | AE33: 50 | AF33: 38 | AG33: 33 | AH33: 48 | AI33: 171 | AJ33: 34 | AK33: 36 | AL33: 38 | AM33: 31 | AN33: 140 | AO33: 54 | AP33: 44 | AQ33: 35 | AR33: 32 | AS33: 165 | AT33: 41 | AU33: 35 | AV33: 40 | AW33: 42 | AX33: 158 | AZ33: 57 | BA33: 55 | BB33: 56 | BD33: 65 | BE33: 67 | BF33: 66 | BG33: 68 | BH33: 267 | BI33: 73 | BJ33: 70 | BK33: 76 | BL33: 71 | BM33: 290 | BN33: 81 | BO33: 80 | BP33: 77 | BQ33: 85 | BR33: 324 | BS33: 96 | BT33: 99 | BU33: =BP33*(1+BU34) -> 87.399035 | BV33: =BQ33*(1+BV34) -> 96.479454 | BW33: =SUM(BS33:BV33) -> 378.87849 | BX33: =BW33*(1+BX34) -> 397.82241 | BY33: =BX33*(1+BY34) -> 417.71353 | BZ33: =BY33*(1+BZ34) -> 438.59921 | CA33: =BZ33*(1+CA34) -> 460.52917 | CB33: =CA33*(1+CB34) -> 483.55563 | CE33: =IFERROR((CB33/BW33)^(1/5)-1,"n/m") -> 0.05 | CF33: =IFERROR((BR33/AS33)^(1/5)-1,"n/m") -> 0.14449056 | CG33: =IFERROR((BR33/T33)^(1/10)-1,"n/m") -> -0.037534569 | CH33: =IFERROR((BR33/C33)^(1/15)-1,"n/m") -> n/m
B34: y/y % | D34: =IF(AND(ISNUMBER(D33),ISNUMBER(C33)),IFERROR(D33/C33-1,""),"") | E34: =IF(AND(ISNUMBER(E33),ISNUMBER(D33)),IFERROR(E33/D33-1,""),"") -> 0.19444444 | J34: =IF(AND(ISNUMBER(J33),ISNUMBER(E33)),IFERROR(J33/E33-1,""),"") -> 0.29568106 | K34: =IF(AND(ISNUMBER(K33),ISNUMBER(F33)),IFERROR(K33/F33-1,""),"") -> 0.23333333 | L34: =IF(AND(ISNUMBER(L33),ISNUMBER(G33)),IFERROR(L33/G33-1,""),"") -> 0.082474227 | M34: =IF(AND(ISNUMBER(M33),ISNUMBER(H33)),IFERROR(M33/H33-1,""),"") -> 0.15151515 | N34: =IF(AND(ISNUMBER(N33),ISNUMBER(I33)),IFERROR(N33/I33-1,""),"") -> 0.077669903 | O34: =IF(AND(ISNUMBER(O33),ISNUMBER(J33)),IFERROR(O33/J33-1,""),"") -> 0.13076923 | P34: =IF(AND(ISNUMBER(P33),ISNUMBER(K33)),IFERROR(P33/K33-1,""),"") -> 0.027027027 | Q34: =IF(AND(ISNUMBER(Q33),ISNUMBER(L33)),IFERROR(Q33/L33-1,""),"") -> 0.12380952 | ... BT34: =IF(AND(ISNUMBER(BT33),ISNUMBER(BO33)),IFERROR(BT33/BO33-1,""),"") -> 0.2375 | BU34: =$BW$35+$BW$149 -> 0.1350524 | BV34: =$BW$35+$BW$149 -> 0.1350524 | BW34: =IF(AND(ISNUMBER(BW33),ISNUMBER(BR33)),IFERROR(BW33/BR33-1,""),"") -> 0.16937805 | BX34: =CHOOSE(MATCH($CC$2,{"Bull","Base","Bear"},0),$CL$53,$CM$53,$CN$53) -> 0.05 | BY34: =CHOOSE(MATCH($CC$2,{"Bull","Base","Bear"},0),$CL$54,$CM$54,$CN$54) -> 0.05 | BZ34: =CHOOSE(MATCH($CC$2,{"Bull","Base","Bear"},0),$CL$55,$CM$55,$CN$55) -> 0.05 | CA34: =CHOOSE(MATCH($CC$2,{"Bull","Base","Bear"},0),$CL$56,$CM$56,$CN$56) -> 0.05 | CB34: =CHOOSE(MATCH($CC$2,{"Bull","Base","Bear"},0),$CL$57,$CM$57,$CN$57) -> 0.05 | CK34: RAT_TR (Ratings transaction revenue y/y) | CL34: 0.04 | CM34: Δ → | CN34: -0.08 | CO34: 1H-26 +20% (record issuance, refinancing walls); FY2020–25 range −27% to +25% (cyclical). 2027E normalisation after two strong years.
B35: Q3–Q4/26E growth before revenue calibration (1H-26 y/y) | BW35: =IFERROR(SUM(BS33:BT33)/SUM(BN33:BO33)-1,0) -> 0.21118012 | CK35: 2027E | CL35: =CM35+$CL$34 -> 0.07 | CM35: 0.03 | CN35: =CM35+$CN$34 -> -0.05
B36: Data & custom subscriptions | D36: 71 | E36: 87 | F36: 25 | G36: 26 | H36: 25 | I36: 27 | J36: 103 | K36: 26 | L36: 28 | M36: 29 | N36: 29 | O36: 111 | P36: 29 | Q36: 30 | R36: 32 | S36: 32 | T36: 122 | U36: 32 | V36: 32 | W36: 33 | X36: 37 | Y36: 133 | Z36: 31 | AA36: 37 | AB36: 36 | AC36: 36 | AD36: 141 | AE36: 33 | AF36: 36 | AG36: 41 | AH36: 41 | AI36: 144 | AJ36: 40 | AK36: 40 | AL36: 42 | AM36: 43 | AN36: 165 | AO36: 46 | AP36: 43 | AQ36: 43 | AR36: 46 | AS36: 177 | AT36: 46 | AU36: 48 | AV36: 47 | AW36: 51 | AX36: 191 | AZ36: 67 | BA36: 69 | BB36: 68 | BD36: 66 | BE36: 70 | BF36: 70 | BG36: 71 | BH36: 277 | BI36: 70 | BJ36: 74 | BK36: 74 | BL36: 74 | BM36: 292 | BN36: 76 | BO36: 80 | BP36: 82 | BQ36: 84 | BR36: 320 | BS36: 84 | BT36: 87 | BU36: =BP36*(1+BU37) -> 83.642142 | BV36: =BQ36*(1+BV37) -> 85.682194 | BW36: =SUM(BS36:BV36) -> 340.32434 | BX36: =BW36*(1+BX37) -> 367.55028 | BY36: =BX36*(1+BY37) -> 396.95431 | BZ36: =BY36*(1+BZ37) -> 424.74111 | CA36: =BZ36*(1+CA37) -> 454.47298 | CB36: =CA36*(1+CB37) -> 486.28609 | CE36: =IFERROR((CB36/BW36)^(1/5)-1,"n/m") -> 0.073988841 | CF36: =IFERROR((BR36/AS36)^(1/5)-1,"n/m") -> 0.12573286 | CG36: =IFERROR((BR36/T36)^(1/10)-1,"n/m") -> 0.10123249 | CH36: =IFERROR((BR36/C36)^(1/15)-1,"n/m") -> n/m | CK36: 2028E | CL36: =CM36+$CL$34 -> 0.1 | CM36: 0.06 | CN36: =CM36+$CN$34 -> -0.02
B37: y/y % | D37: =IF(AND(ISNUMBER(D36),ISNUMBER(C36)),IFERROR(D36/C36-1,""),"") | E37: =IF(AND(ISNUMBER(E36),ISNUMBER(D36)),IFERROR(E36/D36-1,""),"") -> 0.22535211 | J37: =IF(AND(ISNUMBER(J36),ISNUMBER(E36)),IFERROR(J36/E36-1,""),"") -> 0.18390805 | K37: =IF(AND(ISNUMBER(K36),ISNUMBER(F36)),IFERROR(K36/F36-1,""),"") -> 0.04 | L37: =IF(AND(ISNUMBER(L36),ISNUMBER(G36)),IFERROR(L36/G36-1,""),"") -> 0.076923077 | M37: =IF(AND(ISNUMBER(M36),ISNUMBER(H36)),IFERROR(M36/H36-1,""),"") -> 0.16 | N37: =IF(AND(ISNUMBER(N36),ISNUMBER(I36)),IFERROR(N36/I36-1,""),"") -> 0.074074074 | O37: =IF(AND(ISNUMBER(O36),ISNUMBER(J36)),IFERROR(O36/J36-1,""),"") -> 0.077669903 | P37: =IF(AND(ISNUMBER(P36),ISNUMBER(K36)),IFERROR(P36/K36-1,""),"") -> 0.11538462 | Q37: =IF(AND(ISNUMBER(Q36),ISNUMBER(L36)),IFERROR(Q36/L36-1,""),"") -> 0.071428571 | ... BT37: =IF(AND(ISNUMBER(BT36),ISNUMBER(BO36)),IFERROR(BT36/BO36-1,""),"") -> 0.0875 | BU37: =$BW$38+$BW$149 -> 0.020026118 | BV37: =$BW$38+$BW$149 -> 0.020026118 | BW37: =IF(AND(ISNUMBER(BW36),ISNUMBER(BR36)),IFERROR(BW36/BR36-1,""),"") -> 0.063513549 | BX37: =CHOOSE(MATCH($CC$2,{"Bull","Base","Bear"},0),$CL$59,$CM$59,$CN$59) -> 0.08 | BY37: =CHOOSE(MATCH($CC$2,{"Bull","Base","Bear"},0),$CL$60,$CM$60,$CN$60) -> 0.08 | BZ37: =CHOOSE(MATCH($CC$2,{"Bull","Base","Bear"},0),$CL$61,$CM$61,$CN$61) -> 0.07 | CA37: =CHOOSE(MATCH($CC$2,{"Bull","Base","Bear"},0),$CL$62,$CM$62,$CN$62) -> 0.07 | CB37: =CHOOSE(MATCH($CC$2,{"Bull","Base","Bear"},0),$CL$63,$CM$63,$CN$63) -> 0.07 | CK37: 2029E | CL37: =CM37+$CL$34 -> 0.1 | CM37: 0.06 | CN37: =CM37+$CN$34 -> -0.02
B38: Q3–Q4/26E growth before revenue calibration (1H-26 y/y) | BW38: =IFERROR(SUM(BS36:BT36)/SUM(BN36:BO36)-1,0) -> 0.096153846 | CK38: 2030E | CL38: =CM38+$CL$34 -> 0.09 | CM38: 0.05 | CN38: =CM38+$CN$34 -> -0.03
B39: Not split by type (history only: periods without a revenue-by-type table on this basis) | C39: =IF(ISNUMBER(C43),C43-(N(C30)+N(C33)+N(C36)),"") -> 273 | D39: =IF(ISNUMBER(D43),D43-(N(D30)+N(D33)+N(D36)),"") -> 0 | E39: =IF(ISNUMBER(E43),E43-(N(E30)+N(E33)+N(E36)),"") -> 0 | F39: =IF(ISNUMBER(F43),F43-(N(F30)+N(F33)+N(F36)),"") -> 0 | G39: =IF(ISNUMBER(G43),G43-(N(G30)+N(G33)+N(G36)),"") -> 0 | H39: =IF(ISNUMBER(H43),H43-(N(H30)+N(H33)+N(H36)),"") -> 0 | I39: =IF(ISNUMBER(I43),I43-(N(I30)+N(I33)+N(I36)),"") -> 0 | J39: =IF(ISNUMBER(J43),J43-(N(J30)+N(J33)+N(J36)),"") -> 0 | ... BT39: =IF(ISNUMBER(BT43),BT43-(N(BT30)+N(BT33)+N(BT36)),"") -> 0 | CK39: 2031E | CL39: =CM39+$CL$34 -> 0.09 | CM39: 0.05 | CN39: =CM39+$CN$34 -> -0.03
B40: Indices (S&P Dow Jones Indices) — division revenue | C40: =IF(ISNUMBER(C43),N(C30)+N(C33)+N(C36)+N(C39),"") -> 273 | D40: =IF(ISNUMBER(D43),N(D30)+N(D33)+N(D36)+N(D39),"") -> 323 | E40: =IF(ISNUMBER(E43),N(E30)+N(E33)+N(E36)+N(E39),"") -> 388 | F40: =IF(ISNUMBER(F43),N(F30)+N(F33)+N(F36)+N(F39),"") -> 115 | G40: =IF(ISNUMBER(G43),N(G30)+N(G33)+N(G36)+N(G39),"") -> 123 | H40: =IF(ISNUMBER(H43),N(H30)+N(H33)+N(H36)+N(H39),"") -> 124 | I40: =IF(ISNUMBER(I43),N(I30)+N(I33)+N(I36)+N(I39),"") -> 130 | J40: =IF(ISNUMBER(J43),N(J30)+N(J33)+N(J36)+N(J39),"") -> 493 | ... BT40: =IF(ISNUMBER(BT43),N(BT30)+N(BT33)+N(BT36)+N(BT39),"") -> 534 | BU40: =BU30+BU33+BU36 -> 510.6243 | BV40: =BV30+BV33+BV36 -> 550.88392 | BW40: =BW30+BW33+BW36 -> 2114.5082 | BX40: =BX30+BX33+BX36 -> 2300.2086 | BY40: =BY30+BY33+BY36 -> 2487.639 | BZ40: =BZ30+BZ33+BZ36 -> 2686.8789 | CA40: =CA30+CA33+CA36 -> 2884.4238 | CB40: =CB30+CB33+CB36 -> 3096.8171 | CE40: =IFERROR((CB40/BW40)^(1/5)-1,"n/m") -> 0.079297662 | CF40: =IFERROR((BR40/AS40)^(1/5)-1,"n/m") -> 0.133431 | CG40: =IFERROR((BR40/T40)^(1/10)-1,"n/m") -> 0.11974657 | CH40: =IFERROR((BR40/C40)^(1/15)-1,"n/m") -> 0.13605826 | CK40: RAT_NT (Ratings non-transaction revenue y/y) | CL40: 0.02 | CM40: Δ → | CN40: -0.03 | CO40: 1H-26 +10%; surveillance and frequent-issuer fees, Crisil; price.
B41: Division revenue y/y % | D41: =IF(AND(ISNUMBER(D40),ISNUMBER(C40)),IFERROR(D40/C40-1,""),"") -> 0.18315018 | E41: =IF(AND(ISNUMBER(E40),ISNUMBER(D40)),IFERROR(E40/D40-1,""),"") -> 0.20123839 | J41: =IF(AND(ISNUMBER(J40),ISNUMBER(E40)),IFERROR(J40/E40-1,""),"") -> 0.27061856 | K41: =IF(AND(ISNUMBER(K40),ISNUMBER(F40)),IFERROR(K40/F40-1,""),"") -> 0.19130435 | L41: =IF(AND(ISNUMBER(L40),ISNUMBER(G40)),IFERROR(L40/G40-1,""),"") -> 0.081300813 | M41: =IF(AND(ISNUMBER(M40),ISNUMBER(H40)),IFERROR(M40/H40-1,""),"") -> 0.15322581 | N41: =IF(AND(ISNUMBER(N40),ISNUMBER(I40)),IFERROR(N40/I40-1,""),"") -> 0.076923077 | O41: =IF(AND(ISNUMBER(O40),ISNUMBER(J40)),IFERROR(O40/J40-1,""),"") -> 0.11967546 | P41: =IF(AND(ISNUMBER(P40),ISNUMBER(K40)),IFERROR(P40/K40-1,""),"") -> 0.04379562 | Q41: =IF(AND(ISNUMBER(Q40),ISNUMBER(L40)),IFERROR(Q40/L40-1,""),"") -> 0.11278195 | ... BW41: =IF(AND(ISNUMBER(BW40),ISNUMBER(BR40)),IFERROR(BW40/BR40-1,""),"") -> 0.14297742 | BX41: =IF(AND(ISNUMBER(BX40),ISNUMBER(BW40)),IFERROR(BX40/BW40-1,""),"") -> 0.087822033 | BY41: =IF(AND(ISNUMBER(BY40),ISNUMBER(BX40)),IFERROR(BY40/BX40-1,""),"") -> 0.081484077 | BZ41: =IF(AND(ISNUMBER(BZ40),ISNUMBER(BY40)),IFERROR(BZ40/BY40-1,""),"") -> 0.08009196 | CA41: =IF(AND(ISNUMBER(CA40),ISNUMBER(BZ40)),IFERROR(CA40/BZ40-1,""),"") -> 0.07352208 | CB41: =IF(AND(ISNUMBER(CB40),ISNUMBER(CA40)),IFERROR(CB40/CA40-1,""),"") -> 0.073634568 | CK41: 2027E | CL41: =CM41+$CL$40 -> 0.09 | CM41: 0.07 | CN41: =CM41+$CN$40 -> 0.04
B42: % of total revenue | C42: =IF(AND(ISNUMBER(C40),ISNUMBER(C138)),IFERROR(C40/C138,""),"") -> 0.07502061 | D42: =IF(AND(ISNUMBER(D40),ISNUMBER(D138)),IFERROR(D40/D138,""),"") -> 0.081689428 | E42: =IF(AND(ISNUMBER(E40),ISNUMBER(E138)),IFERROR(E40/E138,""),"") -> 0.087191011 | F42: =IF(AND(ISNUMBER(F40),ISNUMBER(F138)),IFERROR(F40/F138,""),"") -> 0.097375106 | G42: =IF(AND(ISNUMBER(G40),ISNUMBER(G138)),IFERROR(G40/G138,""),"") -> 0.0984 | H42: =IF(AND(ISNUMBER(H40),ISNUMBER(H138)),IFERROR(H40/H138,""),"") -> 0.1038526 | I42: =IF(AND(ISNUMBER(I40),ISNUMBER(I138)),IFERROR(I40/I138,""),"") -> 0.104 | J42: =IF(AND(ISNUMBER(J40),ISNUMBER(J138)),IFERROR(J40/J138,""),"") -> 0.10112821 | ... CB42: =IF(AND(ISNUMBER(CB40),ISNUMBER(CB138)),IFERROR(CB40/CB138,""),"") -> 0.15451635 | CE42: =IFERROR(AVERAGE(BX42,BY42,BZ42,CA42,CB42),"n/m") -> 0.15196287 | CF42: =IFERROR(AVERAGE(AX42,BC42,BH42,BM42,BR42),"n/m") -> 0.12424606 | CG42: =IFERROR(AVERAGE(Y42,AD42,AI42,AN42,AS42,AX42,BC42,BH42,BM42,BR42),"n/m") -> 0.12586837 | CH42: =IFERROR(AVERAGE(C42,D42,E42,J42,O42,T42,Y42,AD42,AI42,AN42,AS42,AX42,BC42,BH42,BM42,BR42),"n/m") -> 0.11408526 | CK42: 2028E | CL42: =CM42+$CL$40 -> 0.09 | CM42: 0.07 | CN42: =CM42+$CN$40 -> 0.04
B43: Memo: Indices (S&P Dow Jones Indices) revenue as reported (segment exhibit; 2025+ adjusted as recast) | C43: 273 | D43: 323 | E43: 388 | F43: 115 | G43: 123 | H43: 124 | I43: 130 | J43: 493 | K43: 137 | L43: 133 | M43: 143 | N43: 140 | O43: 552 | P43: 143 | Q43: 148 | R43: 156 | S43: 151 | T43: 597 | U43: 151 | V43: 153 | W43: 164 | X43: 171 | Y43: 639 | Z43: 171 | AA43: 184 | AB43: 187 | AC43: 191 | AD43: 733 | AE43: 214 | AF43: 209 | AG43: 205 | AH43: 215 | AI43: 837 | AJ43: 217 | AK43: 235 | AL43: 232 | AM43: 233 | AN43: 918 | AO43: 259 | AP43: 240 | AQ43: 234 | AR43: 257 | AS43: 989 | AT43: 270 | AU43: 278 | AV43: 298 | AW43: 303 | AX43: 1149 | AY43: 322 | AZ43: 339 | BA43: 334 | BB43: 344 | BC43: 1339 | BD43: 341 | BE43: 348 | BF43: 354 | BG43: 360 | BH43: 1403 | BI43: 387 | BJ43: 389 | BK43: 416 | BL43: 436 | BM43: 1628 | BN43: 445 | BO43: 446 | BP43: 462 | BQ43: 498 | BR43: 1850 | BS43: 519 | BT43: 534 | CK43: 2029E | CL43: =CM43+$CL$40 -> 0.08 | CM43: 0.06 | CN43: =CM43+$CN$40 -> 0.03
B44: Check: revenue types vs division revenue (should be 0; ±1 rounding) | C44: =IF(AND(ISNUMBER(C30),ISNUMBER(C43)),IF(ABS(C40-C43)<=1.01,0,ROUND(C40-C43,0)),"") | D44: =IF(AND(ISNUMBER(D30),ISNUMBER(D43)),IF(ABS(D40-D43)<=1.01,0,ROUND(D40-D43,0)),"") | E44: =IF(AND(ISNUMBER(E30),ISNUMBER(E43)),IF(ABS(E40-E43)<=1.01,0,ROUND(E40-E43,0)),"") | F44: =IF(AND(ISNUMBER(F30),ISNUMBER(F43)),IF(ABS(F40-F43)<=1.01,0,ROUND(F40-F43,0)),"") | G44: =IF(AND(ISNUMBER(G30),ISNUMBER(G43)),IF(ABS(G40-G43)<=1.01,0,ROUND(G40-G43,0)),"") | H44: =IF(AND(ISNUMBER(H30),ISNUMBER(H43)),IF(ABS(H40-H43)<=1.01,0,ROUND(H40-H43,0)),"") | I44: =IF(AND(ISNUMBER(I30),ISNUMBER(I43)),IF(ABS(I40-I43)<=1.01,0,ROUND(I40-I43,0)),"") | J44: =IF(AND(ISNUMBER(J30),ISNUMBER(J43)),IF(ABS(J40-J43)<=1.01,0,ROUND(J40-J43,0)),"") | ... BT44: =IF(AND(ISNUMBER(BT30),ISNUMBER(BT43)),IF(ABS(BT40-BT43)<=1.01,0,ROUND(BT40-BT43,0)),"") -> 0 | CK44: 2030E | CL44: =CM44+$CL$40 -> 0.08 | CM44: 0.06 | CN44: =CM44+$CN$40 -> 0.03
B45: Indices (S&P Dow Jones Indices) — adjusted operating profit | D45: 189 | E45: 234 | F45: 67 | G45: 80 | H45: 80 | I45: 50 | J45: 278 | K45: 91 | L45: 82 | M45: 91 | N45: 87 | O45: 351 | P45: 95 | Q45: 96 | R45: 106 | S45: 94 | T45: 392 | U45: 102 | V45: 101 | W45: 108 | X45: 105 | Y45: 417 | Z45: 116 | AA45: 120 | AB45: 120 | AC45: 122 | AD45: 478 | AE45: 149 | AF45: 138 | AG45: 136 | AH45: 144 | AI45: 568 | AJ45: 151 | AK45: 164 | AL45: 163 | AM45: 158 | AN45: 635 | AO45: 183 | AP45: 172 | AQ45: 153 | AR45: 176 | AS45: 684 | AT45: 192 | AU45: 198 | AV45: 214 | AW45: 199 | AX45: 803 | AY45: 230 | AZ45: 243 | BA45: 234 | BB45: 214 | BC45: 921 | BD45: 245 | BE45: 238 | BF45: 246 | BG45: 238 | BH45: 967 | BI45: 282 | BJ45: 275 | BK45: 292 | BL45: 296 | BM45: 1145 | BN45: 321 | BO45: 315 | BP45: 325 | BQ45: 340 | BR45: 1301 | BS45: 379 | BT45: 382 | BU45: =BU40*BU46 -> 350.77548 | BV45: =BV40*BV46 -> 367.01091 | BW45: =SUM(BS45:BV45) -> 1478.7864 | BX45: =BX40*BX46 -> 1644.6492 | BY45: =BY40*BY46 -> 1791.1001 | BZ45: =BZ40*BZ46 -> 1934.5528 | CA45: =CA40*CA46 -> 2091.2073 | CB45: =CB40*CB46 -> 2245.1924 | CE45: =IFERROR((CB45/BW45)^(1/5)-1,"n/m") -> 0.08710032 | CF45: =IFERROR((BR45/AS45)^(1/5)-1,"n/m") -> 0.13721935 | CG45: =IFERROR((BR45/T45)^(1/10)-1,"n/m") -> 0.12745476 | CH45: =IFERROR((BR45/C45)^(1/15)-1,"n/m") -> n/m | CK45: 2031E | CL45: =CM45+$CL$40 -> 0.08 | CM45: 0.06 | CN45: =CM45+$CN$40 -> 0.03
B46: Adjusted operating margin % | C46: =IF(AND(ISNUMBER(C45),ISNUMBER(C40)),IFERROR(C45/C40,""),"") | D46: =IF(AND(ISNUMBER(D45),ISNUMBER(D40)),IFERROR(D45/D40,""),"") -> 0.58513932 | E46: =IF(AND(ISNUMBER(E45),ISNUMBER(E40)),IFERROR(E45/E40,""),"") -> 0.60309278 | F46: =IF(AND(ISNUMBER(F45),ISNUMBER(F40)),IFERROR(F45/F40,""),"") -> 0.5826087 | G46: =IF(AND(ISNUMBER(G45),ISNUMBER(G40)),IFERROR(G45/G40,""),"") -> 0.6504065 | H46: =IF(AND(ISNUMBER(H45),ISNUMBER(H40)),IFERROR(H45/H40,""),"") -> 0.64516129 | I46: =IF(AND(ISNUMBER(I45),ISNUMBER(I40)),IFERROR(I45/I40,""),"") -> 0.38461538 | J46: =IF(AND(ISNUMBER(J45),ISNUMBER(J40)),IFERROR(J45/J40,""),"") -> 0.56389452 | ... BT46: =IF(AND(ISNUMBER(BT45),ISNUMBER(BT40)),IFERROR(BT45/BT40,""),"") -> 0.71535581 | BU46: =BU47+$BW$159 -> 0.68695415 | BV46: =BV47+$BW$159 -> 0.66622187 | BW46: =IF(AND(ISNUMBER(BW45),ISNUMBER(BW40)),IFERROR(BW45/BW40,""),"") -> 0.6993524 | BX46: =CHOOSE(MATCH($CC$2,{"Bull","Base","Bear"},0),$CL$83,$CM$83,$CN$83) -> 0.715 | BY46: =CHOOSE(MATCH($CC$2,{"Bull","Base","Bear"},0),$CL$84,$CM$84,$CN$84) -> 0.72 | BZ46: =CHOOSE(MATCH($CC$2,{"Bull","Base","Bear"},0),$CL$85,$CM$85,$CN$85) -> 0.72 | CA46: =CHOOSE(MATCH($CC$2,{"Bull","Base","Bear"},0),$CL$86,$CM$86,$CN$86) -> 0.725 | CB46: =CHOOSE(MATCH($CC$2,{"Bull","Base","Bear"},0),$CL$87,$CM$87,$CN$87) -> 0.725 | CE46: =IFERROR(AVERAGE(BX46,BY46,BZ46,CA46,CB46),"n/m") -> 0.721 | CF46: =IFERROR(AVERAGE(AX46,BC46,BH46,BM46,BR46),"n/m") -> 0.69649857 | CG46: =IFERROR(AVERAGE(Y46,AD46,AI46,AN46,AS46,AX46,BC46,BH46,BM46,BR46),"n/m") -> 0.68491325 | CH46: =IFERROR(AVERAGE(C46,D46,E46,J46,O46,T46,Y46,AD46,AI46,AN46,AS46,AX46,BC46,BH46,BM46,BR46),"n/m") -> 0.65958301 | CK46: IDX_ALF (Indices asset-linked fees y/y) | CL46: 0.05 | CM46: Δ → | CN46: -0.12 | CO46: 1H-26 +20% (equity-market levels and ETF inflows); market-driven (Bear = equity drawdown).
B47: Q3–Q4/26E margin before EPS calibration (prior-year quarter + 1H-26 y/y drift) | BU47: =BP46+IFERROR(SUM(BS45:BT45)/SUM(BS40:BT40)-SUM(BN45:BO45)/SUM(BN40:BO40),0) -> 0.71235555 | BV47: =BQ46+IFERROR(SUM(BS45:BT45)/SUM(BS40:BT40)-SUM(BN45:BO45)/SUM(BN40:BO40),0) -> 0.69162327 | CK47: 2027E | CL47: =CM47+$CL$46 -> 0.15 | CM47: 0.1 | CN47: =CM47+$CN$46 -> -0.02
B48: Incremental adjusted margin (Δ adjusted OP / Δ revenue) | D48: =IFERROR((D45-C45)/(D40-C40),"") -> 3.78 | E48: =IFERROR((E45-D45)/(E40-D40),"") -> 0.69230769 | J48: =IFERROR((J45-E45)/(J40-E40),"") -> 0.41904762 | K48: =IFERROR((K45-F45)/(K40-F40),"") -> 1.0909091 | L48: =IFERROR((L45-G45)/(L40-G40),"") -> 0.2 | M48: =IFERROR((M45-H45)/(M40-H40),"") -> 0.57894737 | N48: =IFERROR((N45-I45)/(N40-I40),"") -> 3.7 | O48: =IFERROR((O45-J45)/(O40-J40),"") -> 1.2372881 | P48: =IFERROR((P45-K45)/(P40-K40),"") -> 0.66666667 | Q48: =IFERROR((Q45-L45)/(Q40-L40),"") -> 0.93333333 | ... BW48: =IFERROR((BW45-BR45)/(BW40-BR40),"") -> 0.67213941 | BX48: =IFERROR((BX45-BW45)/(BX40-BW40),"") -> 0.89317396 | BY48: =IFERROR((BY45-BX45)/(BY40-BX40),"") -> 0.78136168 | BZ48: =IFERROR((BZ45-BY45)/(BZ40-BY40),"") -> 0.72 | CA48: =IFERROR((CA45-BZ45)/(CA40-BZ40),"") -> 0.79300678 | CB48: =IFERROR((CB45-CA45)/(CB40-CA40),"") -> 0.725 | CK48: 2028E | CL48: =CM48+$CL$46 -> 0.14 | CM48: 0.09 | CN48: =CM48+$CN$46 -> -0.03
B49: Memo: Indices (S&P Dow Jones Indices) — operating profit (GAAP, as reported) | C49: 144 | D49: 189 | E49: 212 | F49: 67 | G49: 80 | H49: 80 | I49: 50 | J49: 278 | K49: 91 | L49: 82 | M49: 86 | N49: 87 | O49: 347 | P49: 95 | Q49: 96 | R49: 106 | S49: 94 | T49: 392 | U49: 101 | V49: 100 | W49: 107 | X49: 104 | Y49: 412 | Z49: 115 | AA49: 119 | AB49: 119 | AC49: 119 | AD49: 471 | AE49: 147 | AF49: 136 | AG49: 134 | AH49: 143 | AI49: 563 | AJ49: 149 | AK49: 162 | AL49: 161 | AM49: 157 | AN49: 630 | AO49: 182 | AP49: 171 | AQ49: 151 | AR49: 163 | AS49: 666 | AT49: 191 | AU49: 196 | AV49: 213 | AW49: 199 | AX49: 798 | AY49: 224 | AZ49: 270 | BA49: 239 | BB49: 195 | BC49: 927 | BD49: 238 | BE49: 226 | BF49: 235 | BG49: 227 | BH49: 925 | BI49: 272 | BJ49: 263 | BK49: 282 | BL49: 287 | BM49: 1103 | CK49: 2029E | CL49: =CM49+$CL$46 -> 0.14 | CM49: 0.09 | CN49: =CM49+$CN$46 -> -0.03
CK50: 2030E | CL50: =CM50+$CL$46 -> 0.13 | CM50: 0.08 | CN50: =CM50+$CN$46 -> -0.04
B51: S&P Global Energy — Commodities & Commercial 2010–15 (incl. J.D. Power, Aviation Week, McGraw-Hill Construction while owned); Platts 2018–21; Commodity Insights 2022–25; Energy (recast with 451 Research and Maritime & Trade) from 2025 | CC51: ENERGY (COMMODITY INSIGHTS / PLATTS) — modelling logic | CK51: 2031E | CL51: =CM51+$CL$46 -> 0.13 | CM51: 0.08 | CN51: =CM51+$CN$46 -> -0.04
B52: Subscription | D52: 562 | E52: 622 | F52: 163 | G52: 161 | H52: 164 | I52: 168 | J52: 656 | K52: 173 | L52: 173 | M52: 145 | N52: 148 | O52: 576 | P52: 149 | Q52: 154 | R52: 165 | S52: 172 | T52: 641 | U52: 172 | V52: 175 | W52: 172 | AE52: 181 | AF52: 188 | AG52: 188 | AH52: 193 | AI52: 750 | AJ52: 191 | AK52: 195 | AL52: 194 | AM52: 195 | AN52: 774 | AO52: 197 | AP52: 201 | AQ52: 205 | AR52: 207 | AS52: 809 | AT52: 208 | AU52: 217 | AV52: 220 | AW52: 226 | AX52: 871 | AZ52: 386 | BA52: 394 | BB52: 404 | BD52: 409 | BE52: 420 | BF52: 432 | BG52: 446 | BH52: 1707 | BI52: 450 | BJ52: 459 | BK52: 478 | BL52: 486 | BM52: 1873 | BN52: 533 | BO52: 548 | BP52: 556 | BQ52: 572 | BR52: 2209 | BS52: 556 | BT52: 569 | BU52: =BP52*(1+BU53) -> 536.30388 | BV52: =BQ52*(1+BV53) -> 551.73709 | BW52: =SUM(BS52:BV52) -> 2213.041 | BX52: =BW52*(1+BX53) -> 2345.8234 | BY52: =BX52*(1+BY53) -> 2486.5728 | BZ52: =BY52*(1+BZ53) -> 2635.7672 | CA52: =BZ52*(1+CA53) -> 2793.9132 | CB52: =CA52*(1+CB53) -> 2961.548 | CK52: IDX_ETD (Indices exchange-traded derivatives y/y) | CL52: 0.04 | CM52: Δ → | CN52: -0.08 | CO52: 1H-26 +20%; volatility-driven volumes.
B53: y/y % | D53: =IF(AND(ISNUMBER(D52),ISNUMBER(C52)),IFERROR(D52/C52-1,""),"") | E53: =IF(AND(ISNUMBER(E52),ISNUMBER(D52)),IFERROR(E52/D52-1,""),"") -> 0.10676157 | J53: =IF(AND(ISNUMBER(J52),ISNUMBER(E52)),IFERROR(J52/E52-1,""),"") -> 0.054662379 | K53: =IF(AND(ISNUMBER(K52),ISNUMBER(F52)),IFERROR(K52/F52-1,""),"") -> 0.061349693 | L53: =IF(AND(ISNUMBER(L52),ISNUMBER(G52)),IFERROR(L52/G52-1,""),"") -> 0.074534161 | M53: =IF(AND(ISNUMBER(M52),ISNUMBER(H52)),IFERROR(M52/H52-1,""),"") -> -0.11585366 | N53: =IF(AND(ISNUMBER(N52),ISNUMBER(I52)),IFERROR(N52/I52-1,""),"") -> -0.11904762 | O53: =IF(AND(ISNUMBER(O52),ISNUMBER(J52)),IFERROR(O52/J52-1,""),"") -> -0.12195122 | P53: =IF(AND(ISNUMBER(P52),ISNUMBER(K52)),IFERROR(P52/K52-1,""),"") -> -0.13872832 | Q53: =IF(AND(ISNUMBER(Q52),ISNUMBER(L52)),IFERROR(Q52/L52-1,""),"") -> -0.10982659 | ... BT53: =IF(AND(ISNUMBER(BT52),ISNUMBER(BO52)),IFERROR(BT52/BO52-1,""),"") -> 0.038321168 | BU53: =$BW$54+$BW$149 -> -0.035424675 | BV53: =$BW$54+$BW$149 -> -0.035424675 | BW53: =IF(AND(ISNUMBER(BW52),ISNUMBER(BR52)),IFERROR(BW52/BR52-1,""),"") -> 0.0018293193 | BX53: =CHOOSE(MATCH($CC$2,{"Bull","Base","Bear"},0),$CL$65,$CM$65,$CN$65) -> 0.06 | BY53: =CHOOSE(MATCH($CC$2,{"Bull","Base","Bear"},0),$CL$66,$CM$66,$CN$66) -> 0.06 | BZ53: =CHOOSE(MATCH($CC$2,{"Bull","Base","Bear"},0),$CL$67,$CM$67,$CN$67) -> 0.06 | CA53: =CHOOSE(MATCH($CC$2,{"Bull","Base","Bear"},0),$CL$68,$CM$68,$CN$68) -> 0.06 | CB53: =CHOOSE(MATCH($CC$2,{"Bull","Base","Bear"},0),$CL$69,$CM$69,$CN$69) -> 0.06 | CK53: 2027E | CL53: =CM53+$CL$52 -> 0.09 | CM53: 0.05 | CN53: =CM53+$CN$52 -> -0.03
B54: Q3–Q4/26E growth before revenue calibration (1H-26 y/y) | BW54: =IFERROR(SUM(BS52:BT52)/SUM(BN52:BO52)-1,0) -> 0.040703053 | CK54: 2028E | CL54: =CM54+$CL$52 -> 0.09 | CM54: 0.05 | CN54: =CM54+$CN$52 -> -0.03
B55: Non-subscription / transaction (incl. CERAWeek conference) | D55: 334 | E55: 351 | F55: 73 | G55: 98 | H55: 91 | I55: 96 | J55: 358 | K55: 78 | L55: 90 | M55: 82 | N55: 88 | O55: 317 | P55: 76 | Q55: 80 | R55: 83 | S55: 92 | T55: 330 | U55: 82 | V55: 80 | W55: 57 | AE55: 2 | AF55: 4 | AG55: 2 | AH55: 3 | AI55: 11 | AJ55: 2 | AK55: 3 | AL55: 2 | AM55: 3 | AN55: 10 | AO55: 1 | AP55: 1 | AQ55: 2 | AR55: 2 | AS55: 7 | AT55: 1 | AU55: 3 | AV55: 2 | AW55: 7 | AX55: 13 | AZ55: 26 | BA55: 21 | BB55: 31 | BD55: 80 | BE55: 24 | BF55: 26 | BG55: 28 | BH55: 158 | BI55: 83 | BJ55: 31 | BK55: 18 | BL55: 33 | BM55: 166 | BN55: 118 | BO55: 29 | BP55: 22 | BQ55: 27 | BR55: 196 | BS55: 131 | BT55: 27 | BU55: =BP55*(1+BU56) -> 21.971448 | BV55: =BQ55*(1+BV56) -> 26.96496 | BW55: =SUM(BS55:BV55) -> 206.93641 | BX55: =BW55*(1+BX56) -> 219.35259 | BY55: =BX55*(1+BY56) -> 232.51375 | BZ55: =BY55*(1+BZ56) -> 246.46457 | CA55: =BZ55*(1+CA56) -> 261.25245 | CB55: =CA55*(1+CB56) -> 276.92759 | CK55: 2029E | CL55: =CM55+$CL$52 -> 0.09 | CM55: 0.05 | CN55: =CM55+$CN$52 -> -0.03
B56: y/y % | D56: =IF(AND(ISNUMBER(D55),ISNUMBER(C55)),IFERROR(D55/C55-1,""),"") | E56: =IF(AND(ISNUMBER(E55),ISNUMBER(D55)),IFERROR(E55/D55-1,""),"") -> 0.050898204 | J56: =IF(AND(ISNUMBER(J55),ISNUMBER(E55)),IFERROR(J55/E55-1,""),"") -> 0.01994302 | K56: =IF(AND(ISNUMBER(K55),ISNUMBER(F55)),IFERROR(K55/F55-1,""),"") -> 0.068493151 | L56: =IF(AND(ISNUMBER(L55),ISNUMBER(G55)),IFERROR(L55/G55-1,""),"") -> -0.081632653 | M56: =IF(AND(ISNUMBER(M55),ISNUMBER(H55)),IFERROR(M55/H55-1,""),"") -> -0.098901099 | N56: =IF(AND(ISNUMBER(N55),ISNUMBER(I55)),IFERROR(N55/I55-1,""),"") -> -0.083333333 | O56: =IF(AND(ISNUMBER(O55),ISNUMBER(J55)),IFERROR(O55/J55-1,""),"") -> -0.11452514 | P56: =IF(AND(ISNUMBER(P55),ISNUMBER(K55)),IFERROR(P55/K55-1,""),"") -> -0.025641026 | Q56: =IF(AND(ISNUMBER(Q55),ISNUMBER(L55)),IFERROR(Q55/L55-1,""),"") -> -0.11111111 | ... BT56: =IF(AND(ISNUMBER(BT55),ISNUMBER(BO55)),IFERROR(BT55/BO55-1,""),"") -> -0.068965517 | BU56: =$BW$57+$BW$149 -> -0.0012977959 | BV56: =$BW$57+$BW$149 -> -0.0012977959 | BW56: =IF(AND(ISNUMBER(BW55),ISNUMBER(BR55)),IFERROR(BW55/BR55-1,""),"") -> 0.055798 | BX56: =CHOOSE(MATCH($CC$2,{"Bull","Base","Bear"},0),$CL$65,$CM$65,$CN$65) -> 0.06 | BY56: =CHOOSE(MATCH($CC$2,{"Bull","Base","Bear"},0),$CL$66,$CM$66,$CN$66) -> 0.06 | BZ56: =CHOOSE(MATCH($CC$2,{"Bull","Base","Bear"},0),$CL$67,$CM$67,$CN$67) -> 0.06 | CA56: =CHOOSE(MATCH($CC$2,{"Bull","Base","Bear"},0),$CL$68,$CM$68,$CN$68) -> 0.06 | CB56: =CHOOSE(MATCH($CC$2,{"Bull","Base","Bear"},0),$CL$69,$CM$69,$CN$69) -> 0.06 | CK56: 2030E | CL56: =CM56+$CL$52 -> 0.09 | CM56: 0.05 | CN56: =CM56+$CN$52 -> -0.03
B57: Q3–Q4/26E growth before revenue calibration (1H-26 y/y) | BW57: =IFERROR(SUM(BS55:BT55)/SUM(BN55:BO55)-1,0) -> 0.074829932 | CK57: 2031E | CL57: =CM57+$CL$52 -> 0.09 | CM57: 0.05 | CN57: =CM57+$CN$52 -> -0.03
B58: Sales usage-based royalties | AE58: 13 | AF58: 13 | AG58: 14 | AH58: 14 | AI58: 54 | AJ58: 14 | AK58: 15 | AL58: 16 | AM58: 15 | AN58: 60 | AO58: 17 | AP58: 15 | AQ58: 15 | AR58: 14 | AS58: 62 | AT58: 16 | AU58: 16 | AV58: 17 | AW58: 16 | AX58: 66 | AZ58: 15 | BA58: 17 | BB58: 16 | BD58: 19 | BE58: 18 | BF58: 21 | BG58: 23 | BH58: 81 | BI58: 26 | BJ58: 26 | BK58: 26 | BL58: 26 | BM58: 103 | BN58: 29 | BO58: 30 | BP58: 31 | BQ58: 30 | BR58: 120 | BS58: 37 | BT58: 27 | BU58: =BP58*(1+BU59) -> 31.267159 | BV58: =BQ58*(1+BV59) -> 30.258541 | BW58: =SUM(BS58:BV58) -> 125.5257 | BX58: =BW58*(1+BX59) -> 133.05724 | BY58: =BX58*(1+BY59) -> 141.04068 | BZ58: =BY58*(1+BZ59) -> 149.50312 | CA58: =BZ58*(1+CA59) -> 158.4733 | CB58: =CA58*(1+CB59) -> 167.9817 | CK58: IDX_SUB (Indices data & custom subscriptions y/y) | CL58: 0.02 | CM58: Δ → | CN58: -0.03 | CO58: 1H-26 +10%; FY2023–25 +7–10%.
B59: y/y % | D59: =IF(AND(ISNUMBER(D58),ISNUMBER(C58)),IFERROR(D58/C58-1,""),"") | E59: =IF(AND(ISNUMBER(E58),ISNUMBER(D58)),IFERROR(E58/D58-1,""),"") | J59: =IF(AND(ISNUMBER(J58),ISNUMBER(E58)),IFERROR(J58/E58-1,""),"") | K59: =IF(AND(ISNUMBER(K58),ISNUMBER(F58)),IFERROR(K58/F58-1,""),"") | L59: =IF(AND(ISNUMBER(L58),ISNUMBER(G58)),IFERROR(L58/G58-1,""),"") | M59: =IF(AND(ISNUMBER(M58),ISNUMBER(H58)),IFERROR(M58/H58-1,""),"") | N59: =IF(AND(ISNUMBER(N58),ISNUMBER(I58)),IFERROR(N58/I58-1,""),"") | O59: =IF(AND(ISNUMBER(O58),ISNUMBER(J58)),IFERROR(O58/J58-1,""),"") | P59: =IF(AND(ISNUMBER(P58),ISNUMBER(K58)),IFERROR(P58/K58-1,""),"") | Q59: =IF(AND(ISNUMBER(Q58),ISNUMBER(L58)),IFERROR(Q58/L58-1,""),"") | ... BT59: =IF(AND(ISNUMBER(BT58),ISNUMBER(BO58)),IFERROR(BT58/BO58-1,""),"") -> -0.1 | BU59: =$BW$60+$BW$149 -> 0.0086180348 | BV59: =$BW$60+$BW$149 -> 0.0086180348 | BW59: =IF(AND(ISNUMBER(BW58),ISNUMBER(BR58)),IFERROR(BW58/BR58-1,""),"") -> 0.046047501 | BX59: =CHOOSE(MATCH($CC$2,{"Bull","Base","Bear"},0),$CL$65,$CM$65,$CN$65) -> 0.06 | BY59: =CHOOSE(MATCH($CC$2,{"Bull","Base","Bear"},0),$CL$66,$CM$66,$CN$66) -> 0.06 | BZ59: =CHOOSE(MATCH($CC$2,{"Bull","Base","Bear"},0),$CL$67,$CM$67,$CN$67) -> 0.06 | CA59: =CHOOSE(MATCH($CC$2,{"Bull","Base","Bear"},0),$CL$68,$CM$68,$CN$68) -> 0.06 | CB59: =CHOOSE(MATCH($CC$2,{"Bull","Base","Bear"},0),$CL$69,$CM$69,$CN$69) -> 0.06 | CK59: 2027E | CL59: =CM59+$CL$58 -> 0.1 | CM59: 0.08 | CN59: =CM59+$CN$58 -> 0.05
B60: Q3–Q4/26E growth before revenue calibration (1H-26 y/y) | BW60: =IFERROR(SUM(BS58:BT58)/SUM(BN58:BO58)-1,0) -> 0.084745763 | CK60: 2028E | CL60: =CM60+$CL$58 -> 0.1 | CM60: 0.08 | CN60: =CM60+$CN$58 -> 0.05
B61: Not split by type (history only: periods without a revenue-by-type table on this basis) | C61: =IF(ISNUMBER(C65),C65-(N(C52)+N(C55)+N(C58)),"") -> 811 | D61: =IF(ISNUMBER(D65),D65-(N(D52)+N(D55)+N(D58)),"") -> 0 | E61: =IF(ISNUMBER(E65),E65-(N(E52)+N(E55)+N(E58)),"") -> 0 | F61: =IF(ISNUMBER(F65),F65-(N(F52)+N(F55)+N(F58)),"") -> 0 | G61: =IF(ISNUMBER(G65),G65-(N(G52)+N(G55)+N(G58)),"") -> 0 | H61: =IF(ISNUMBER(H65),H65-(N(H52)+N(H55)+N(H58)),"") -> 0 | I61: =IF(ISNUMBER(I65),I65-(N(I52)+N(I55)+N(I58)),"") -> 0 | J61: =IF(ISNUMBER(J65),J65-(N(J52)+N(J55)+N(J58)),"") -> 0 | ... BT61: =IF(ISNUMBER(BT65),BT65-(N(BT52)+N(BT55)+N(BT58)),"") -> 0 | CK61: 2029E | CL61: =CM61+$CL$58 -> 0.09 | CM61: 0.07 | CN61: =CM61+$CN$58 -> 0.04
B62: Energy (Commodity Insights / Platts) — division revenue | C62: =IF(ISNUMBER(C65),N(C52)+N(C55)+N(C58)+N(C61),"") -> 811 | D62: =IF(ISNUMBER(D65),N(D52)+N(D55)+N(D58)+N(D61),"") -> 896 | E62: =IF(ISNUMBER(E65),N(E52)+N(E55)+N(E58)+N(E61),"") -> 973 | F62: =IF(ISNUMBER(F65),N(F52)+N(F55)+N(F58)+N(F61),"") -> 236 | G62: =IF(ISNUMBER(G65),N(G52)+N(G55)+N(G58)+N(G61),"") -> 259 | H62: =IF(ISNUMBER(H65),N(H52)+N(H55)+N(H58)+N(H61),"") -> 255 | I62: =IF(ISNUMBER(I65),N(I52)+N(I55)+N(I58)+N(I61),"") -> 264 | J62: =IF(ISNUMBER(J65),N(J52)+N(J55)+N(J58)+N(J61),"") -> 1014 | ... BT62: =IF(ISNUMBER(BT65),N(BT52)+N(BT55)+N(BT58)+N(BT61),"") -> 623 | BU62: =BU52+BU55+BU58 -> 589.54249 | BV62: =BV52+BV55+BV58 -> 608.96059 | BW62: =BW52+BW55+BW58 -> 2545.5031 | BX62: =BX52+BX55+BX58 -> 2698.2333 | BY62: =BY52+BY55+BY58 -> 2860.1273 | BZ62: =BZ52+BZ55+BZ58 -> 3031.7349 | CA62: =CA52+CA55+CA58 -> 3213.639 | CB62: =CB52+CB55+CB58 -> 3406.4573 | CE62: =IFERROR((CB62/BW62)^(1/5)-1,"n/m") -> 0.06 | CF62: =IFERROR((BR62/AS62)^(1/5)-1,"n/m") -> 0.23524576 | CG62: =IFERROR((BR62/T62)^(1/10)-1,"n/m") -> 0.10028252 | CH62: =IFERROR((BR62/C62)^(1/15)-1,"n/m") -> 0.07865535 | CK62: 2030E | CL62: =CM62+$CL$58 -> 0.09 | CM62: 0.07 | CN62: =CM62+$CN$58 -> 0.04
B63: Division revenue y/y % | D63: =IF(AND(ISNUMBER(D62),ISNUMBER(C62)),IFERROR(D62/C62-1,""),"") -> 0.10480888 | E63: =IF(AND(ISNUMBER(E62),ISNUMBER(D62)),IFERROR(E62/D62-1,""),"") -> 0.0859375 | J63: =IF(AND(ISNUMBER(J62),ISNUMBER(E62)),IFERROR(J62/E62-1,""),"") -> 0.042137718 | K63: =IF(AND(ISNUMBER(K62),ISNUMBER(F62)),IFERROR(K62/F62-1,""),"") -> 0.063559322 | L63: =IF(AND(ISNUMBER(L62),ISNUMBER(G62)),IFERROR(L62/G62-1,""),"") -> 0.015444015 | M63: =IF(AND(ISNUMBER(M62),ISNUMBER(H62)),IFERROR(M62/H62-1,""),"") -> -0.10980392 | N63: =IF(AND(ISNUMBER(N62),ISNUMBER(I62)),IFERROR(N62/I62-1,""),"") -> -0.10606061 | O63: =IF(AND(ISNUMBER(O62),ISNUMBER(J62)),IFERROR(O62/J62-1,""),"") -> -0.11932939 | P63: =IF(AND(ISNUMBER(P62),ISNUMBER(K62)),IFERROR(P62/K62-1,""),"") -> -0.10358566 | Q63: =IF(AND(ISNUMBER(Q62),ISNUMBER(L62)),IFERROR(Q62/L62-1,""),"") -> -0.11026616 | ... BW63: =IF(AND(ISNUMBER(BW62),ISNUMBER(BR62)),IFERROR(BW62/BR62-1,""),"") -> 0.0081200295 | BX63: =IF(AND(ISNUMBER(BX62),ISNUMBER(BW62)),IFERROR(BX62/BW62-1,""),"") -> 0.06 | BY63: =IF(AND(ISNUMBER(BY62),ISNUMBER(BX62)),IFERROR(BY62/BX62-1,""),"") -> 0.06 | BZ63: =IF(AND(ISNUMBER(BZ62),ISNUMBER(BY62)),IFERROR(BZ62/BY62-1,""),"") -> 0.06 | CA63: =IF(AND(ISNUMBER(CA62),ISNUMBER(BZ62)),IFERROR(CA62/BZ62-1,""),"") -> 0.06 | CB63: =IF(AND(ISNUMBER(CB62),ISNUMBER(CA62)),IFERROR(CB62/CA62-1,""),"") -> 0.06 | CK63: 2031E | CL63: =CM63+$CL$58 -> 0.09 | CM63: 0.07 | CN63: =CM63+$CN$58 -> 0.04
B64: % of total revenue | C64: =IF(AND(ISNUMBER(C62),ISNUMBER(C138)),IFERROR(C62/C138,""),"") -> 0.22286342 | D64: =IF(AND(ISNUMBER(D62),ISNUMBER(D138)),IFERROR(D62/D138,""),"") -> 0.22660597 | E64: =IF(AND(ISNUMBER(E62),ISNUMBER(E138)),IFERROR(E62/E138,""),"") -> 0.21865169 | F64: =IF(AND(ISNUMBER(F62),ISNUMBER(F138)),IFERROR(F62/F138,""),"") -> 0.19983065 | G64: =IF(AND(ISNUMBER(G62),ISNUMBER(G138)),IFERROR(G62/G138,""),"") -> 0.2072 | H64: =IF(AND(ISNUMBER(H62),ISNUMBER(H138)),IFERROR(H62/H138,""),"") -> 0.21356784 | I64: =IF(AND(ISNUMBER(I62),ISNUMBER(I138)),IFERROR(I62/I138,""),"") -> 0.2112 | J64: =IF(AND(ISNUMBER(J62),ISNUMBER(J138)),IFERROR(J62/J138,""),"") -> 0.208 | ... CB64: =IF(AND(ISNUMBER(CB62),ISNUMBER(CB138)),IFERROR(CB62/CB138,""),"") -> 0.16996592 | CE64: =IFERROR(AVERAGE(BX64,BY64,BZ64,CA64,CB64),"n/m") -> 0.17213166 | CF64: =IFERROR(AVERAGE(AX64,BC64,BH64,BM64,BR64),"n/m") -> 0.15149817 | CG64: =IFERROR(AVERAGE(Y64,AD64,AI64,AN64,AS64,AX64,BC64,BH64,BM64,BR64),"n/m") -> 0.13851246 | CH64: =IFERROR(AVERAGE(C64,D64,E64,J64,O64,T64,Y64,AD64,AI64,AN64,AS64,AX64,BC64,BH64,BM64,BR64),"n/m") -> 0.1638001 | CK64: EN (Energy revenue y/y, all types) | CL64: 0.02 | CM64: Δ → | CN64: -0.04 | CO64: 1H-26 +5% recast (2026 includes the geoscience sale in 2H); Platts / CERA, CERAWeek; subscription growth ~4–7%.
B65: Memo: Energy (Commodity Insights / Platts) revenue as reported (segment exhibit; 2025+ adjusted as recast) | C65: 811 | D65: 896 | E65: 973 | F65: 236 | G65: 259 | H65: 255 | I65: 264 | J65: 1014 | K65: 251 | L65: 263 | M65: 227 | N65: 236 | O65: 893 | P65: 225 | Q65: 234 | R65: 248 | S65: 264 | T65: 971 | U65: 254 | V65: 255 | W65: 229 | X65: 188 | Y65: 712 | Z65: 191 | AA65: 192 | AB65: 193 | AC65: 197 | AD65: 774 | AE65: 196 | AF65: 205 | AG65: 204 | AH65: 210 | AI65: 815 | AJ65: 207 | AK65: 213 | AL65: 212 | AM65: 213 | AN65: 844 | AO65: 215 | AP65: 217 | AQ65: 222 | AR65: 223 | AS65: 878 | AT65: 225 | AU65: 236 | AV65: 239 | AW65: 249 | AX65: 950 | AY65: 363 | AZ65: 438 | BA65: 432 | BB65: 451 | BC65: 1685 | BD65: 508 | BE65: 462 | BF65: 479 | BG65: 497 | BH65: 1946 | BI65: 559 | BJ65: 516 | BK65: 522 | BL65: 545 | BM65: 2142 | BN65: 680 | BO65: 607 | BP65: 609 | BQ65: 629 | BR65: 2525 | BS65: 724 | BT65: 623 | CK65: 2027E | CL65: =CM65+$CL$64 -> 0.08 | CM65: 0.06 | CN65: =CM65+$CN$64 -> 0.02
B66: Check: revenue types vs division revenue (should be 0; ±1 rounding) | C66: =IF(AND(ISNUMBER(C52),ISNUMBER(C65)),IF(ABS(C62-C65)<=1.01,0,ROUND(C62-C65,0)),"") | D66: =IF(AND(ISNUMBER(D52),ISNUMBER(D65)),IF(ABS(D62-D65)<=1.01,0,ROUND(D62-D65,0)),"") -> 0 | E66: =IF(AND(ISNUMBER(E52),ISNUMBER(E65)),IF(ABS(E62-E65)<=1.01,0,ROUND(E62-E65,0)),"") -> 0 | F66: =IF(AND(ISNUMBER(F52),ISNUMBER(F65)),IF(ABS(F62-F65)<=1.01,0,ROUND(F62-F65,0)),"") -> 0 | G66: =IF(AND(ISNUMBER(G52),ISNUMBER(G65)),IF(ABS(G62-G65)<=1.01,0,ROUND(G62-G65,0)),"") -> 0 | H66: =IF(AND(ISNUMBER(H52),ISNUMBER(H65)),IF(ABS(H62-H65)<=1.01,0,ROUND(H62-H65,0)),"") -> 0 | I66: =IF(AND(ISNUMBER(I52),ISNUMBER(I65)),IF(ABS(I62-I65)<=1.01,0,ROUND(I62-I65,0)),"") -> 0 | J66: =IF(AND(ISNUMBER(J52),ISNUMBER(J65)),IF(ABS(J62-J65)<=1.01,0,ROUND(J62-J65,0)),"") -> 0 | ... BT66: =IF(AND(ISNUMBER(BT52),ISNUMBER(BT65)),IF(ABS(BT62-BT65)<=1.01,0,ROUND(BT62-BT65,0)),"") -> 0 | CK66: 2028E | CL66: =CM66+$CL$64 -> 0.08 | CM66: 0.06 | CN66: =CM66+$CN$64 -> 0.02
B67: Energy (Commodity Insights / Platts) — adjusted operating profit | D67: 186 | E67: 260 | F67: 62 | G67: 83 | H67: 82 | I67: 84 | J67: 310 | K67: 76 | L67: 83 | M67: 83 | N67: 76 | O67: 306 | P67: 85 | Q67: 88 | R67: 93 | S67: 92 | T67: 358 | U67: 107 | V67: 98 | W67: 94 | AE67: 95 | AF67: 102 | AG67: 102 | AH67: 101 | AI67: 401 | AJ67: 98 | AK67: 111 | AL67: 107 | AM67: 107 | AN67: 424 | AO67: 114 | AP67: 127 | AQ67: 124 | AR67: 115 | AS67: 480 | AT67: 131 | AU67: 136 | AV67: 130 | AW67: 125 | AX67: 523 | AY67: 180 | AZ67: 188 | BA67: 198 | BB67: 201 | BC67: 767 | BD67: 234 | BE67: 211 | BF67: 232 | BG67: 220 | BH67: 897 | BI67: 264 | BJ67: 244 | BK67: 250 | BL67: 245 | BM67: 1003 | BN67: 322 | BO67: 284 | BP67: 281 | BQ67: 272 | BR67: 1159 | BS67: 348 | BT67: 296 | BU67: =BU62*BU68 -> 261.31339 | BV67: =BV62*BV68 -> 252.27291 | BW67: =SUM(BS67:BV67) -> 1157.5863 | BX67: =BX62*BX68 -> 1281.6608 | BY67: =BY62*BY68 -> 1372.8611 | BZ67: =BZ62*BZ68 -> 1470.3914 | CA67: =CA62*CA68 -> 1574.6831 | CB67: =CB62*CB68 -> 1669.1641 | CE67: =IFERROR((CB67/BW67)^(1/5)-1,"n/m") -> 0.075942668 | CF67: =IFERROR((BR67/AS67)^(1/5)-1,"n/m") -> 0.19280222 | CG67: =IFERROR((BR67/T67)^(1/10)-1,"n/m") -> 0.12465687 | CH67: =IFERROR((BR67/C67)^(1/15)-1,"n/m") -> n/m | CK67: 2029E | CL67: =CM67+$CL$64 -> 0.08 | CM67: 0.06 | CN67: =CM67+$CN$64 -> 0.02
B68: Adjusted operating margin % | C68: =IF(AND(ISNUMBER(C67),ISNUMBER(C62)),IFERROR(C67/C62,""),"") | D68: =IF(AND(ISNUMBER(D67),ISNUMBER(D62)),IFERROR(D67/D62,""),"") -> 0.20758929 | E68: =IF(AND(ISNUMBER(E67),ISNUMBER(E62)),IFERROR(E67/E62,""),"") -> 0.2672148 | F68: =IF(AND(ISNUMBER(F67),ISNUMBER(F62)),IFERROR(F67/F62,""),"") -> 0.26271186 | G68: =IF(AND(ISNUMBER(G67),ISNUMBER(G62)),IFERROR(G67/G62,""),"") -> 0.32046332 | H68: =IF(AND(ISNUMBER(H67),ISNUMBER(H62)),IFERROR(H67/H62,""),"") -> 0.32156863 | I68: =IF(AND(ISNUMBER(I67),ISNUMBER(I62)),IFERROR(I67/I62,""),"") -> 0.31818182 | J68: =IF(AND(ISNUMBER(J67),ISNUMBER(J62)),IFERROR(J67/J62,""),"") -> 0.30571992 | ... BT68: =IF(AND(ISNUMBER(BT67),ISNUMBER(BT62)),IFERROR(BT67/BT62,""),"") -> 0.47512039 | BU68: =BU69+$BW$159 -> 0.44324777 | BV68: =BV69+$BW$159 -> 0.41426805 | BW68: =IF(AND(ISNUMBER(BW67),ISNUMBER(BW62)),IFERROR(BW67/BW62,""),"") -> 0.45475738 | BX68: =CHOOSE(MATCH($CC$2,{"Bull","Base","Bear"},0),$CL$89,$CM$89,$CN$89) -> 0.475 | BY68: =CHOOSE(MATCH($CC$2,{"Bull","Base","Bear"},0),$CL$90,$CM$90,$CN$90) -> 0.48 | BZ68: =CHOOSE(MATCH($CC$2,{"Bull","Base","Bear"},0),$CL$91,$CM$91,$CN$91) -> 0.485 | CA68: =CHOOSE(MATCH($CC$2,{"Bull","Base","Bear"},0),$CL$92,$CM$92,$CN$92) -> 0.49 | CB68: =CHOOSE(MATCH($CC$2,{"Bull","Base","Bear"},0),$CL$93,$CM$93,$CN$93) -> 0.49 | CE68: =IFERROR(AVERAGE(BX68,BY68,BZ68,CA68,CB68),"n/m") -> 0.484 | CF68: =IFERROR(AVERAGE(AX68,BC68,BH68,BM68,BR68),"n/m") -> 0.47878572 | CG68: =IFERROR(AVERAGE(Y68,AD68,AI68,AN68,AS68,AX68,BC68,BH68,BM68,BR68),"n/m") -> 0.49187748 | CH68: =IFERROR(AVERAGE(C68,D68,E68,J68,O68,T68,Y68,AD68,AI68,AN68,AS68,AX68,BC68,BH68,BM68,BR68),"n/m") -> 0.41745393 | CK68: 2030E | CL68: =CM68+$CL$64 -> 0.08 | CM68: 0.06 | CN68: =CM68+$CN$64 -> 0.02
B69: Q3–Q4/26E margin before EPS calibration (prior-year quarter + 1H-26 y/y drift) | BU69: =BP68+IFERROR(SUM(BS67:BT67)/SUM(BS62:BT62)-SUM(BN67:BO67)/SUM(BN62:BO62),0) -> 0.46864916 | BV69: =BQ68+IFERROR(SUM(BS67:BT67)/SUM(BS62:BT62)-SUM(BN67:BO67)/SUM(BN62:BO62),0) -> 0.43966944 | CK69: 2031E | CL69: =CM69+$CL$64 -> 0.08 | CM69: 0.06 | CN69: =CM69+$CN$64 -> 0.02
B70: Incremental adjusted margin (Δ adjusted OP / Δ revenue) | D70: =IFERROR((D67-C67)/(D62-C62),"") -> 2.1882353 | E70: =IFERROR((E67-D67)/(E62-D62),"") -> 0.96103896 | J70: =IFERROR((J67-E67)/(J62-E62),"") -> 1.2195122 | K70: =IFERROR((K67-F67)/(K62-F62),"") -> 0.93333333 | L70: =IFERROR((L67-G67)/(L62-G62),"") -> 0 | M70: =IFERROR((M67-H67)/(M62-H62),"") -> -0.035714286 | N70: =IFERROR((N67-I67)/(N62-I62),"") -> 0.28571429 | O70: =IFERROR((O67-J67)/(O62-J62),"") -> 0.033057851 | P70: =IFERROR((P67-K67)/(P62-K62),"") -> -0.34615385 | Q70: =IFERROR((Q67-L67)/(Q62-L62),"") -> -0.17241379 | ... BW70: =IFERROR((BW67-BR67)/(BW62-BR62),"") -> -0.068950416 | BX70: =IFERROR((BX67-BW67)/(BX62-BW62),"") -> 0.81237703 | BY70: =IFERROR((BY67-BX67)/(BY62-BX62),"") -> 0.56333333 | BZ70: =IFERROR((BZ67-BY67)/(BZ62-BY62),"") -> 0.56833333 | CA70: =IFERROR((CA67-BZ67)/(CA62-BZ62),"") -> 0.57333333 | CB70: =IFERROR((CB67-CA67)/(CB62-CA62),"") -> 0.49 | CK70: MI (Market Intelligence revenue y/y, all types) | CL70: 0.02 | CM70: Δ → | CN70: -0.04 | CO70: 1H-26 +7% recast (+6% organic cc); With Intelligence (Nov-2025) in the base; EDM / thinkFolio sold Q1-26.
B71: Memo: Energy (Commodity Insights / Platts) — operating profit (GAAP, as reported) | C71: 153 | D71: 180 | E71: 248 | F71: 62 | G71: 83 | H71: 91 | I71: 76 | J71: 311 | K71: 76 | L71: 83 | M71: 71 | N71: 72 | O71: 290 | P71: 85 | Q71: 87 | R71: 93 | S71: 92 | T71: 357 | U71: 102 | V71: 93 | W71: 812 | AE71: 90 | AF71: 98 | AG71: 98 | AH71: 97 | AI71: 383 | AJ71: 94 | AK71: 107 | AL71: 132 | AM71: 105 | AN71: 438 | AO71: 112 | AP71: 124 | AQ71: 121 | AR71: 100 | AS71: 458 | AT71: 129 | AU71: 135 | AV71: 128 | AW71: 125 | AX71: 517 | AY71: 158 | AZ71: 141 | BA71: 141 | BB71: 150 | BC71: 591 | BD71: 187 | BE71: 156 | BF71: 184 | BG71: 177 | BH71: 704 | BI71: 226 | BJ71: 206 | BK71: 211 | BL71: 202 | BM71: 845 | CK71: 2027E | CL71: =CM71+$CL$70 -> 0.08 | CM71: 0.06 | CN71: =CM71+$CN$70 -> 0.02
CK72: 2028E | CL72: =CM72+$CL$70 -> 0.085 | CM72: 0.065 | CN72: =CM72+$CN$70 -> 0.025
B73: S&P Global Market Intelligence — S&P Capital IQ 2010–15; Market Intelligence (SNL from Sep-2015) 2018+; incl. IHS Markit financial services from Mar-2022; recast 2025+ (451 Research / Maritime & Trade to Energy) | CC73: MARKET INTELLIGENCE — modelling logic | CK73: 2029E | CL73: =CM73+$CL$70 -> 0.085 | CM73: 0.065 | CN73: =CM73+$CN$70 -> 0.025
B74: Subscription | D74: 922 | E74: 1014 | F74: 260 | G74: 260 | H74: 265 | I74: 270 | J74: 1056 | K74: 274 | L74: 278 | M74: 283 | N74: 286 | O74: 1118 | P74: 287 | Q74: 292 | R74: 322 | S74: 370 | T74: 1270 | U74: 375 | V74: 382 | W74: 394 | AE74: 424 | AF74: 431 | AG74: 451 | AH74: 464 | AI74: 1773 | AJ74: 467 | AK74: 471 | AL74: 477 | AM74: 488 | AN74: 1904 | AO74: 505 | AP74: 503 | AQ74: 517 | AR74: 526 | AS74: 2050 | AT74: 527 | AU74: 540 | AV74: 557 | AW74: 568 | AX74: 2191 | AZ74: 856 | BA74: 862 | BB74: 876 | BD74: 890 | BE74: 910 | BF74: 932 | BG74: 953 | BH74: 3685 | BI74: 947 | BJ74: 965 | BK74: 981 | BL74: 989 | BM74: 3882 | BN74: 945 | BO74: 969 | BP74: 986 | BQ74: 1013 | BR74: 3913 | BS74: 1001 | BT74: 1025 | BU74: =BP74*(1+BU75) -> 968.63503 | BV74: =BQ74*(1+BV75) -> 995.15952 | BW74: =SUM(BS74:BV74) -> 3989.7945 | BX74: =BW74*(1+BX75) -> 4229.1822 | BY74: =BX74*(1+BY75) -> 4504.0791 | BZ74: =BY74*(1+BZ75) -> 4796.8442 | CA74: =BZ74*(1+CA75) -> 5108.6391 | CB74: =CA74*(1+CB75) -> 5440.7006 | CK74: 2030E | CL74: =CM74+$CL$70 -> 0.085 | CM74: 0.065 | CN74: =CM74+$CN$70 -> 0.025
B75: y/y % | D75: =IF(AND(ISNUMBER(D74),ISNUMBER(C74)),IFERROR(D74/C74-1,""),"") | E75: =IF(AND(ISNUMBER(E74),ISNUMBER(D74)),IFERROR(E74/D74-1,""),"") -> 0.09978308 | J75: =IF(AND(ISNUMBER(J74),ISNUMBER(E74)),IFERROR(J74/E74-1,""),"") -> 0.041420118 | K75: =IF(AND(ISNUMBER(K74),ISNUMBER(F74)),IFERROR(K74/F74-1,""),"") -> 0.053846154 | L75: =IF(AND(ISNUMBER(L74),ISNUMBER(G74)),IFERROR(L74/G74-1,""),"") -> 0.069230769 | M75: =IF(AND(ISNUMBER(M74),ISNUMBER(H74)),IFERROR(M74/H74-1,""),"") -> 0.067924528 | N75: =IF(AND(ISNUMBER(N74),ISNUMBER(I74)),IFERROR(N74/I74-1,""),"") -> 0.059259259 | O75: =IF(AND(ISNUMBER(O74),ISNUMBER(J74)),IFERROR(O74/J74-1,""),"") -> 0.058712121 | P75: =IF(AND(ISNUMBER(P74),ISNUMBER(K74)),IFERROR(P74/K74-1,""),"") -> 0.047445255 | Q75: =IF(AND(ISNUMBER(Q74),ISNUMBER(L74)),IFERROR(Q74/L74-1,""),"") -> 0.050359712 | ... BT75: =IF(AND(ISNUMBER(BT74),ISNUMBER(BO74)),IFERROR(BT74/BO74-1,""),"") -> 0.057791538 | BU75: =$BW$76+$BW$149 -> -0.017611531 | BV75: =$BW$76+$BW$149 -> -0.017611531 | BW75: =IF(AND(ISNUMBER(BW74),ISNUMBER(BR74)),IFERROR(BW74/BR74-1,""),"") -> 0.019625492 | BX75: =CHOOSE(MATCH($CC$2,{"Bull","Base","Bear"},0),$CL$71,$CM$71,$CN$71) -> 0.06 | BY75: =CHOOSE(MATCH($CC$2,{"Bull","Base","Bear"},0),$CL$72,$CM$72,$CN$72) -> 0.065 | BZ75: =CHOOSE(MATCH($CC$2,{"Bull","Base","Bear"},0),$CL$73,$CM$73,$CN$73) -> 0.065 | CA75: =CHOOSE(MATCH($CC$2,{"Bull","Base","Bear"},0),$CL$74,$CM$74,$CN$74) -> 0.065 | CB75: =CHOOSE(MATCH($CC$2,{"Bull","Base","Bear"},0),$CL$75,$CM$75,$CN$75) -> 0.065 | CK75: 2031E | CL75: =CM75+$CL$70 -> 0.085 | CM75: 0.065 | CN75: =CM75+$CN$70 -> 0.025
B76: Q3–Q4/26E growth before revenue calibration (1H-26 y/y) | BW76: =IFERROR(SUM(BS74:BT74)/SUM(BN74:BO74)-1,0) -> 0.058516196 | CK76: RAT_M (Ratings adjusted margin) | CL76: 0.01 | CM76: Δ → | CN76: -0.03 | CO76: FY2025 65.1%, 1H-26 68.0%; operating leverage on issuance.
B77: Non-subscription / transaction | D77: 109 | E77: 110 | F77: 28 | G77: 27 | H77: 28 | I77: 31 | J77: 114 | K77: 27 | L77: 29 | M77: 28 | N77: 32 | O77: 119 | P77: 33 | Q77: 32 | R77: 34 | S77: 35 | T77: 135 | U77: 32 | V77: 34 | W77: 35 | AE77: 8 | AF77: 11 | AG77: 8 | AH77: 9 | AI77: 40 | AJ77: 10 | AK77: 12 | AL77: 10 | AM77: 14 | AN77: 45 | AO77: 13 | AP77: 13 | AQ77: 13 | AR77: 16 | AS77: 55 | AT77: 12 | AU77: 15 | AV77: 13 | AW77: 16 | AX77: 56 | AZ77: 42 | BA77: 40 | BB77: 52 | BD77: 56 | BE77: 39 | BF77: 42 | BG77: 50 | BH77: 187 | BI77: 54 | BJ77: 43 | BK77: 39 | BL77: 48 | BM77: 184 | BN77: 36 | BO77: 38 | BP77: 39 | BQ77: 41 | BR77: 154 | BS77: 54 | BT77: 37 | BU77: =BP77*(1+BU78) -> 44.990478 | BV77: =BQ77*(1+BV78) -> 47.297682 | BW77: =SUM(BS77:BV77) -> 183.28816 | BX77: =BW77*(1+BX78) -> 194.28545 | BY77: =BX77*(1+BY78) -> 206.914 | BZ77: =BY77*(1+BZ78) -> 220.36341 | CA77: =BZ77*(1+CA78) -> 234.68704 | CB77: =CA77*(1+CB78) -> 249.94169 | CK77: 2027E | CL77: =CM77+$CL$76 -> 0.675 | CM77: 0.665 | CN77: =CM77+$CN$76 -> 0.635
B78: y/y % | D78: =IF(AND(ISNUMBER(D77),ISNUMBER(C77)),IFERROR(D77/C77-1,""),"") | E78: =IF(AND(ISNUMBER(E77),ISNUMBER(D77)),IFERROR(E77/D77-1,""),"") -> 0.0091743119 | J78: =IF(AND(ISNUMBER(J77),ISNUMBER(E77)),IFERROR(J77/E77-1,""),"") -> 0.036363636 | K78: =IF(AND(ISNUMBER(K77),ISNUMBER(F77)),IFERROR(K77/F77-1,""),"") -> -0.035714286 | L78: =IF(AND(ISNUMBER(L77),ISNUMBER(G77)),IFERROR(L77/G77-1,""),"") -> 0.074074074 | M78: =IF(AND(ISNUMBER(M77),ISNUMBER(H77)),IFERROR(M77/H77-1,""),"") -> 0 | N78: =IF(AND(ISNUMBER(N77),ISNUMBER(I77)),IFERROR(N77/I77-1,""),"") -> 0.032258065 | O78: =IF(AND(ISNUMBER(O77),ISNUMBER(J77)),IFERROR(O77/J77-1,""),"") -> 0.043859649 | P78: =IF(AND(ISNUMBER(P77),ISNUMBER(K77)),IFERROR(P77/K77-1,""),"") -> 0.22222222 | Q78: =IF(AND(ISNUMBER(Q77),ISNUMBER(L77)),IFERROR(Q77/L77-1,""),"") -> 0.10344828 | ... BT78: =IF(AND(ISNUMBER(BT77),ISNUMBER(BO77)),IFERROR(BT77/BO77-1,""),"") -> -0.026315789 | BU78: =$BW$79+$BW$149 -> 0.153602 | BV78: =$BW$79+$BW$149 -> 0.153602 | BW78: =IF(AND(ISNUMBER(BW77),ISNUMBER(BR77)),IFERROR(BW77/BR77-1,""),"") -> 0.19018286 | BX78: =CHOOSE(MATCH($CC$2,{"Bull","Base","Bear"},0),$CL$71,$CM$71,$CN$71) -> 0.06 | BY78: =CHOOSE(MATCH($CC$2,{"Bull","Base","Bear"},0),$CL$72,$CM$72,$CN$72) -> 0.065 | BZ78: =CHOOSE(MATCH($CC$2,{"Bull","Base","Bear"},0),$CL$73,$CM$73,$CN$73) -> 0.065 | CA78: =CHOOSE(MATCH($CC$2,{"Bull","Base","Bear"},0),$CL$74,$CM$74,$CN$74) -> 0.065 | CB78: =CHOOSE(MATCH($CC$2,{"Bull","Base","Bear"},0),$CL$75,$CM$75,$CN$75) -> 0.065 | CK78: 2028E | CL78: =CM78+$CL$76 -> 0.68 | CM78: 0.67 | CN78: =CM78+$CN$76 -> 0.64
B79: Q3–Q4/26E growth before revenue calibration (1H-26 y/y) | BW79: =IFERROR(SUM(BS77:BT77)/SUM(BN77:BO77)-1,0) -> 0.22972973 | CK79: 2029E | CL79: =CM79+$CL$76 -> 0.68 | CM79: 0.67 | CN79: =CM79+$CN$76 -> 0.64
B80: Recurring variable | AZ80: 121 | BA80: 115 | BB80: 109 | BD80: 125 | BE80: 130 | BF80: 125 | BG80: 124 | BH80: 504 | BI80: 141 | BJ80: 147 | BK80: 142 | BL80: 149 | BM80: 579 | BN80: 150 | BO80: 158 | BP80: 158 | BQ80: 157 | BR80: 623 | BS80: 169 | BT80: 173 | BU80: =BP80*(1+BU81) -> 163.41338 | BV80: =BQ80*(1+BV81) -> 162.37912 | BW80: =SUM(BS80:BV80) -> 667.79249 | BX80: =BW80*(1+BX81) -> 707.86004 | BY80: =BX80*(1+BY81) -> 753.87095 | BZ80: =BY80*(1+BZ81) -> 802.87256 | CA80: =BZ80*(1+CA81) -> 855.05927 | CB80: =CA80*(1+CB81) -> 910.63813 | CK80: 2030E | CL80: =CM80+$CL$76 -> 0.68 | CM80: 0.67 | CN80: =CM80+$CN$76 -> 0.64
B81: y/y % | D81: =IF(AND(ISNUMBER(D80),ISNUMBER(C80)),IFERROR(D80/C80-1,""),"") | E81: =IF(AND(ISNUMBER(E80),ISNUMBER(D80)),IFERROR(E80/D80-1,""),"") | J81: =IF(AND(ISNUMBER(J80),ISNUMBER(E80)),IFERROR(J80/E80-1,""),"") | K81: =IF(AND(ISNUMBER(K80),ISNUMBER(F80)),IFERROR(K80/F80-1,""),"") | L81: =IF(AND(ISNUMBER(L80),ISNUMBER(G80)),IFERROR(L80/G80-1,""),"") | M81: =IF(AND(ISNUMBER(M80),ISNUMBER(H80)),IFERROR(M80/H80-1,""),"") | N81: =IF(AND(ISNUMBER(N80),ISNUMBER(I80)),IFERROR(N80/I80-1,""),"") | O81: =IF(AND(ISNUMBER(O80),ISNUMBER(J80)),IFERROR(O80/J80-1,""),"") | P81: =IF(AND(ISNUMBER(P80),ISNUMBER(K80)),IFERROR(P80/K80-1,""),"") | Q81: =IF(AND(ISNUMBER(Q80),ISNUMBER(L80)),IFERROR(Q80/L80-1,""),"") | ... BT81: =IF(AND(ISNUMBER(BT80),ISNUMBER(BO80)),IFERROR(BT80/BO80-1,""),"") -> 0.094936709 | BU81: =$BW$82+$BW$149 -> 0.034261883 | BV81: =$BW$82+$BW$149 -> 0.034261883 | BW81: =IF(AND(ISNUMBER(BW80),ISNUMBER(BR80)),IFERROR(BW80/BR80-1,""),"") -> 0.071898063 | BX81: =CHOOSE(MATCH($CC$2,{"Bull","Base","Bear"},0),$CL$71,$CM$71,$CN$71) -> 0.06 | BY81: =CHOOSE(MATCH($CC$2,{"Bull","Base","Bear"},0),$CL$72,$CM$72,$CN$72) -> 0.065 | BZ81: =CHOOSE(MATCH($CC$2,{"Bull","Base","Bear"},0),$CL$73,$CM$73,$CN$73) -> 0.065 | CA81: =CHOOSE(MATCH($CC$2,{"Bull","Base","Bear"},0),$CL$74,$CM$74,$CN$74) -> 0.065 | CB81: =CHOOSE(MATCH($CC$2,{"Bull","Base","Bear"},0),$CL$75,$CM$75,$CN$75) -> 0.065 | CK81: 2031E | CL81: =CM81+$CL$76 -> 0.68 | CM81: 0.67 | CN81: =CM81+$CN$76 -> 0.64
B82: Q3–Q4/26E growth before revenue calibration (1H-26 y/y) | BW82: =IFERROR(SUM(BS80:BT80)/SUM(BN80:BO80)-1,0) -> 0.11038961 | CK82: IDX_M (Indices adjusted margin) | CL82: 0.005 | CM82: Δ → | CN82: -0.02 | CO82: FY2025 70.3%, 1H-26 72.2%.
B83: Not split by type (history only: periods without a revenue-by-type table on this basis) | C83: =IF(ISNUMBER(C87),C87-(N(C74)+N(C77)+N(C80)),"") -> 916 | D83: =IF(ISNUMBER(D87),D87-(N(D74)+N(D77)+N(D80)),"") -> 0 | E83: =IF(ISNUMBER(E87),E87-(N(E74)+N(E77)+N(E80)),"") -> 0 | F83: =IF(ISNUMBER(F87),F87-(N(F74)+N(F77)+N(F80)),"") -> 0 | G83: =IF(ISNUMBER(G87),G87-(N(G74)+N(G77)+N(G80)),"") -> 0 | H83: =IF(ISNUMBER(H87),H87-(N(H74)+N(H77)+N(H80)),"") -> 0 | I83: =IF(ISNUMBER(I87),I87-(N(I74)+N(I77)+N(I80)),"") -> 0 | J83: =IF(ISNUMBER(J87),J87-(N(J74)+N(J77)+N(J80)),"") -> 0 | ... BT83: =IF(ISNUMBER(BT87),BT87-(N(BT74)+N(BT77)+N(BT80)),"") -> 0 | CK83: 2027E | CL83: =CM83+$CL$82 -> 0.72 | CM83: 0.715 | CN83: =CM83+$CN$82 -> 0.695
B84: Market Intelligence — division revenue | C84: =IF(ISNUMBER(C87),N(C74)+N(C77)+N(C80)+N(C83),"") -> 916 | D84: =IF(ISNUMBER(D87),N(D74)+N(D77)+N(D80)+N(D83),"") -> 1031 | E84: =IF(ISNUMBER(E87),N(E74)+N(E77)+N(E80)+N(E83),"") -> 1124 | F84: =IF(ISNUMBER(F87),N(F74)+N(F77)+N(F80)+N(F83),"") -> 288 | G84: =IF(ISNUMBER(G87),N(G74)+N(G77)+N(G80)+N(G83),"") -> 287 | H84: =IF(ISNUMBER(H87),N(H74)+N(H77)+N(H80)+N(H83),"") -> 293 | I84: =IF(ISNUMBER(I87),N(I74)+N(I77)+N(I80)+N(I83),"") -> 301 | J84: =IF(ISNUMBER(J87),N(J74)+N(J77)+N(J80)+N(J83),"") -> 1170 | ... BT84: =IF(ISNUMBER(BT87),N(BT74)+N(BT77)+N(BT80)+N(BT83),"") -> 1235 | BU84: =BU74+BU77+BU80 -> 1177.0389 | BV84: =BV74+BV77+BV80 -> 1204.8363 | BW84: =BW74+BW77+BW80 -> 4840.8752 | BX84: =BX74+BX77+BX80 -> 5131.3277 | BY84: =BY74+BY77+BY80 -> 5464.864 | BZ84: =BZ74+BZ77+BZ80 -> 5820.0802 | CA84: =CA74+CA77+CA80 -> 6198.3854 | CB84: =CB74+CB77+CB80 -> 6601.2804 | CE84: =IFERROR((CB84/BW84)^(1/5)-1,"n/m") -> 0.063998117 | CF84: =IFERROR((BR84/AS84)^(1/5)-1,"n/m") -> 0.1736616 | CG84: =IFERROR((BR84/T84)^(1/10)-1,"n/m") -> 0.12810533 | CH84: =IFERROR((BR84/C84)^(1/15)-1,"n/m") -> 0.11502642 | CK84: 2028E | CL84: =CM84+$CL$82 -> 0.725 | CM84: 0.72 | CN84: =CM84+$CN$82 -> 0.7
B85: Division revenue y/y % | D85: =IF(AND(ISNUMBER(D84),ISNUMBER(C84)),IFERROR(D84/C84-1,""),"") -> 0.12554585 | E85: =IF(AND(ISNUMBER(E84),ISNUMBER(D84)),IFERROR(E84/D84-1,""),"") -> 0.090203686 | J85: =IF(AND(ISNUMBER(J84),ISNUMBER(E84)),IFERROR(J84/E84-1,""),"") -> 0.040925267 | K85: =IF(AND(ISNUMBER(K84),ISNUMBER(F84)),IFERROR(K84/F84-1,""),"") -> 0.045138889 | L85: =IF(AND(ISNUMBER(L84),ISNUMBER(G84)),IFERROR(L84/G84-1,""),"") -> 0.069686411 | M85: =IF(AND(ISNUMBER(M84),ISNUMBER(H84)),IFERROR(M84/H84-1,""),"") -> 0.061433447 | N85: =IF(AND(ISNUMBER(N84),ISNUMBER(I84)),IFERROR(N84/I84-1,""),"") -> 0.056478405 | O85: =IF(AND(ISNUMBER(O84),ISNUMBER(J84)),IFERROR(O84/J84-1,""),"") -> 0.057264957 | P85: =IF(AND(ISNUMBER(P84),ISNUMBER(K84)),IFERROR(P84/K84-1,""),"") -> 0.063122924 | Q85: =IF(AND(ISNUMBER(Q84),ISNUMBER(L84)),IFERROR(Q84/L84-1,""),"") -> 0.055374593 | ... BW85: =IF(AND(ISNUMBER(BW84),ISNUMBER(BR84)),IFERROR(BW84/BR84-1,""),"") -> 0.032169553 | BX85: =IF(AND(ISNUMBER(BX84),ISNUMBER(BW84)),IFERROR(BX84/BW84-1,""),"") -> 0.06 | BY85: =IF(AND(ISNUMBER(BY84),ISNUMBER(BX84)),IFERROR(BY84/BX84-1,""),"") -> 0.065 | BZ85: =IF(AND(ISNUMBER(BZ84),ISNUMBER(BY84)),IFERROR(BZ84/BY84-1,""),"") -> 0.065 | CA85: =IF(AND(ISNUMBER(CA84),ISNUMBER(BZ84)),IFERROR(CA84/BZ84-1,""),"") -> 0.065 | CB85: =IF(AND(ISNUMBER(CB84),ISNUMBER(CA84)),IFERROR(CB84/CA84-1,""),"") -> 0.065 | CK85: 2029E | CL85: =CM85+$CL$82 -> 0.725 | CM85: 0.72 | CN85: =CM85+$CN$82 -> 0.7
B86: % of total revenue | C86: =IF(AND(ISNUMBER(C84),ISNUMBER(C138)),IFERROR(C84/C138,""),"") -> 0.2517175 | D86: =IF(AND(ISNUMBER(D84),ISNUMBER(D138)),IFERROR(D84/D138,""),"") -> 0.26074861 | E86: =IF(AND(ISNUMBER(E84),ISNUMBER(E138)),IFERROR(E84/E138,""),"") -> 0.25258427 | F86: =IF(AND(ISNUMBER(F84),ISNUMBER(F138)),IFERROR(F84/F138,""),"") -> 0.24386113 | G86: =IF(AND(ISNUMBER(G84),ISNUMBER(G138)),IFERROR(G84/G138,""),"") -> 0.2296 | H86: =IF(AND(ISNUMBER(H84),ISNUMBER(H138)),IFERROR(H84/H138,""),"") -> 0.24539363 | I86: =IF(AND(ISNUMBER(I84),ISNUMBER(I138)),IFERROR(I84/I138,""),"") -> 0.2408 | J86: =IF(AND(ISNUMBER(J84),ISNUMBER(J138)),IFERROR(J84/J138,""),"") -> 0.24 | ... CB86: =IF(AND(ISNUMBER(CB84),ISNUMBER(CB138)),IFERROR(CB84/CB138,""),"") -> 0.3293723 | CE86: =IFERROR(AVERAGE(BX86,BY86,BZ86,CA86,CB86),"n/m") -> 0.33042975 | CF86: =IFERROR(AVERAGE(AX86,BC86,BH86,BM86,BR86),"n/m") -> 0.3267783 | CG86: =IFERROR(AVERAGE(Y86,AD86,AI86,AN86,AS86,AX86,BC86,BH86,BM86,BR86),"n/m") -> 0.30720352 | CH86: =IFERROR(AVERAGE(C86,D86,E86,J86,O86,T86,Y86,AD86,AI86,AN86,AS86,AX86,BC86,BH86,BM86,BR86),"n/m") -> 0.28665208 | CK86: 2030E | CL86: =CM86+$CL$82 -> 0.73 | CM86: 0.725 | CN86: =CM86+$CN$82 -> 0.705
B87: Memo: Market Intelligence revenue as reported (segment exhibit; 2025+ adjusted as recast) | C87: 916 | D87: 1031 | E87: 1124 | F87: 288 | G87: 287 | H87: 293 | I87: 301 | J87: 1170 | K87: 301 | L87: 307 | M87: 311 | N87: 318 | O87: 1237 | P87: 320 | Q87: 324 | R87: 356 | S87: 405 | T87: 1405 | U87: 407 | V87: 416 | W87: 429 | X87: 407 | Y87: 1659 | Z87: 402 | AA87: 414 | AB87: 422 | AC87: 440 | AD87: 1678 | AE87: 437 | AF87: 447 | AG87: 464 | AH87: 478 | AI87: 1833 | AJ87: 482 | AK87: 487 | AL87: 488 | AM87: 502 | AN87: 1959 | AO87: 519 | AP87: 516 | AQ87: 530 | AR87: 542 | AS87: 2106 | AT87: 539 | AU87: 555 | AV87: 570 | AW87: 584 | AX87: 2247 | AY87: 727 | AZ87: 1030 | BA87: 1016 | BB87: 1037 | BC87: 3811 | BD87: 1071 | BE87: 1079 | BF87: 1099 | BG87: 1127 | BH87: 4376 | BI87: 1142 | BJ87: 1155 | BK87: 1162 | BL87: 1186 | BM87: 4645 | BN87: 1131 | BO87: 1165 | BP87: 1183 | BQ87: 1211 | BR87: 4690 | BS87: 1224 | BT87: 1235 | CK87: 2031E | CL87: =CM87+$CL$82 -> 0.73 | CM87: 0.725 | CN87: =CM87+$CN$82 -> 0.705
B88: Check: revenue types vs division revenue (should be 0; ±1 rounding) | C88: =IF(AND(ISNUMBER(C74),ISNUMBER(C87)),IF(ABS(C84-C87)<=1.01,0,ROUND(C84-C87,0)),"") | D88: =IF(AND(ISNUMBER(D74),ISNUMBER(D87)),IF(ABS(D84-D87)<=1.01,0,ROUND(D84-D87,0)),"") -> 0 | E88: =IF(AND(ISNUMBER(E74),ISNUMBER(E87)),IF(ABS(E84-E87)<=1.01,0,ROUND(E84-E87,0)),"") -> 0 | F88: =IF(AND(ISNUMBER(F74),ISNUMBER(F87)),IF(ABS(F84-F87)<=1.01,0,ROUND(F84-F87,0)),"") -> 0 | G88: =IF(AND(ISNUMBER(G74),ISNUMBER(G87)),IF(ABS(G84-G87)<=1.01,0,ROUND(G84-G87,0)),"") -> 0 | H88: =IF(AND(ISNUMBER(H74),ISNUMBER(H87)),IF(ABS(H84-H87)<=1.01,0,ROUND(H84-H87,0)),"") -> 0 | I88: =IF(AND(ISNUMBER(I74),ISNUMBER(I87)),IF(ABS(I84-I87)<=1.01,0,ROUND(I84-I87,0)),"") -> 0 | J88: =IF(AND(ISNUMBER(J74),ISNUMBER(J87)),IF(ABS(J84-J87)<=1.01,0,ROUND(J84-J87,0)),"") -> 0 | ... BT88: =IF(AND(ISNUMBER(BT74),ISNUMBER(BT87)),IF(ABS(BT84-BT87)<=1.01,0,ROUND(BT84-BT87,0)),"") -> 0 | CK88: CI_M (Energy adjusted margin) | CL88: 0.01 | CM88: Δ → | CN88: -0.02 | CO88: FY2025 recast 45.9%, 1H-26 47.8%.
B89: Market Intelligence — adjusted operating profit | D89: 214 | E89: 228 | F89: 56 | G89: 55 | H89: 59 | I89: 54 | J89: 224 | K89: 53 | L89: 54 | M89: 68 | N89: 62 | O89: 237 | P89: 63 | Q89: 74 | R89: 85 | S89: 75 | T89: 297 | U89: 123 | V89: 118 | W89: 135 | AE89: 129 | AF89: 146 | AG89: 168 | AH89: 184 | AI89: 625 | AJ89: 163 | AK89: 167 | AL89: 167 | AM89: 172 | AN89: 670 | AO89: 160 | AP89: 177 | AQ89: 179 | AR89: 166 | AS89: 683 | AT89: 181 | AU89: 196 | AV89: 203 | AW89: 191 | AX89: 771 | AY89: 229 | AZ89: 336 | BA89: 345 | BB89: 326 | BC89: 1236 | BD89: 343 | BE89: 349 | BF89: 366 | BG89: 386 | BH89: 1443 | BI89: 373 | BJ89: 380 | BK89: 371 | BL89: 387 | BM89: 1512 | BN89: 352 | BO89: 405 | BP89: 416 | BQ89: 377 | BR89: 1549 | BS89: 402 | BT89: 445 | BU89: =BU84*BU90 -> 401.36095 | BV89: =BV84*BV90 -> 362.24211 | BW89: =SUM(BS89:BV89) -> 1610.6031 | BX89: =BX84*BX90 -> 1795.9647 | BY89: =BY84*BY90 -> 1940.0267 | BZ89: =BZ84*BZ90 -> 2095.2289 | CA89: =CA84*CA90 -> 2262.4107 | CB89: =CB84*CB90 -> 2442.4738 | CE89: =IFERROR((CB89/BW89)^(1/5)-1,"n/m") -> 0.086846666 | CF89: =IFERROR((BR89/AS89)^(1/5)-1,"n/m") -> 0.17794806 | CG89: =IFERROR((BR89/T89)^(1/10)-1,"n/m") -> 0.17958569 | CH89: =IFERROR((BR89/C89)^(1/15)-1,"n/m") -> n/m | CK89: 2027E | CL89: =CM89+$CL$88 -> 0.485 | CM89: 0.475 | CN89: =CM89+$CN$88 -> 0.455
B90: Adjusted operating margin % | C90: =IF(AND(ISNUMBER(C89),ISNUMBER(C84)),IFERROR(C89/C84,""),"") | D90: =IF(AND(ISNUMBER(D89),ISNUMBER(D84)),IFERROR(D89/D84,""),"") -> 0.20756547 | E90: =IF(AND(ISNUMBER(E89),ISNUMBER(E84)),IFERROR(E89/E84,""),"") -> 0.20284698 | F90: =IF(AND(ISNUMBER(F89),ISNUMBER(F84)),IFERROR(F89/F84,""),"") -> 0.19444444 | G90: =IF(AND(ISNUMBER(G89),ISNUMBER(G84)),IFERROR(G89/G84,""),"") -> 0.19163763 | H90: =IF(AND(ISNUMBER(H89),ISNUMBER(H84)),IFERROR(H89/H84,""),"") -> 0.20136519 | I90: =IF(AND(ISNUMBER(I89),ISNUMBER(I84)),IFERROR(I89/I84,""),"") -> 0.17940199 | J90: =IF(AND(ISNUMBER(J89),ISNUMBER(J84)),IFERROR(J89/J84,""),"") -> 0.19145299 | ... BT90: =IF(AND(ISNUMBER(BT89),ISNUMBER(BT84)),IFERROR(BT89/BT84,""),"") -> 0.36032389 | BU90: =BU91+$BW$159 -> 0.34099209 | BV90: =BV91+$BW$159 -> 0.3006567 | BW90: =IF(AND(ISNUMBER(BW89),ISNUMBER(BW84)),IFERROR(BW89/BW84,""),"") -> 0.33270906 | BX90: =CHOOSE(MATCH($CC$2,{"Bull","Base","Bear"},0),$CL$95,$CM$95,$CN$95) -> 0.35 | BY90: =CHOOSE(MATCH($CC$2,{"Bull","Base","Bear"},0),$CL$96,$CM$96,$CN$96) -> 0.355 | BZ90: =CHOOSE(MATCH($CC$2,{"Bull","Base","Bear"},0),$CL$97,$CM$97,$CN$97) -> 0.36 | CA90: =CHOOSE(MATCH($CC$2,{"Bull","Base","Bear"},0),$CL$98,$CM$98,$CN$98) -> 0.365 | CB90: =CHOOSE(MATCH($CC$2,{"Bull","Base","Bear"},0),$CL$99,$CM$99,$CN$99) -> 0.37 | CE90: =IFERROR(AVERAGE(BX90,BY90,BZ90,CA90,CB90),"n/m") -> 0.36 | CF90: =IFERROR(AVERAGE(AX90,BC90,BH90,BM90,BR90),"n/m") -> 0.33059804 | CG90: =IFERROR(AVERAGE(Y90,AD90,AI90,AN90,AS90,AX90,BC90,BH90,BM90,BR90),"n/m") -> 0.3325355 | CH90: =IFERROR(AVERAGE(C90,D90,E90,J90,O90,T90,Y90,AD90,AI90,AN90,AS90,AX90,BC90,BH90,BM90,BR90),"n/m") -> 0.28193307 | CK90: 2028E | CL90: =CM90+$CL$88 -> 0.49 | CM90: 0.48 | CN90: =CM90+$CN$88 -> 0.46
B91: Q3–Q4/26E margin before EPS calibration (prior-year quarter + 1H-26 y/y drift) | BU91: =BP90+IFERROR(SUM(BS89:BT89)/SUM(BS84:BT84)-SUM(BN89:BO89)/SUM(BN84:BO84),0) -> 0.36639348 | BV91: =BQ90+IFERROR(SUM(BS89:BT89)/SUM(BS84:BT84)-SUM(BN89:BO89)/SUM(BN84:BO84),0) -> 0.32605809 | CK91: 2029E | CL91: =CM91+$CL$88 -> 0.495 | CM91: 0.485 | CN91: =CM91+$CN$88 -> 0.465
B92: Incremental adjusted margin (Δ adjusted OP / Δ revenue) | D92: =IFERROR((D89-C89)/(D84-C84),"") -> 1.8608696 | E92: =IFERROR((E89-D89)/(E84-D84),"") -> 0.15053763 | J92: =IFERROR((J89-E89)/(J84-E84),"") -> -0.086956522 | K92: =IFERROR((K89-F89)/(K84-F84),"") -> -0.23076923 | L92: =IFERROR((L89-G89)/(L84-G84),"") -> -0.05 | M92: =IFERROR((M89-H89)/(M84-H84),"") -> 0.5 | N92: =IFERROR((N89-I89)/(N84-I84),"") -> 0.47058824 | O92: =IFERROR((O89-J89)/(O84-J84),"") -> 0.19402985 | P92: =IFERROR((P89-K89)/(P84-K84),"") -> 0.52631579 | Q92: =IFERROR((Q89-L89)/(Q84-L84),"") -> 1.1764706 | ... BW92: =IFERROR((BW89-BR89)/(BW84-BR84),"") -> 0.40830473 | BX92: =IFERROR((BX89-BW89)/(BX84-BW84),"") -> 0.63818226 | BY92: =IFERROR((BY89-BX89)/(BY84-BX84),"") -> 0.43192308 | BZ92: =IFERROR((BZ89-BY89)/(BZ84-BY84),"") -> 0.43692308 | CA92: =IFERROR((CA89-BZ89)/(CA84-BZ84),"") -> 0.44192308 | CB92: =IFERROR((CB89-CA89)/(CB84-CA84),"") -> 0.44692308 | CK92: 2030E | CL92: =CM92+$CL$88 -> 0.5 | CM92: 0.49 | CN92: =CM92+$CN$88 -> 0.47
B93: Memo: Market Intelligence — operating profit (GAAP, as reported) | C93: 171 | D93: 214 | E93: 208 | F93: 56 | G93: 55 | H93: 54 | I93: 46 | J93: 211 | K93: 53 | L93: 54 | M93: 64 | N93: 56 | O93: 228 | P93: 63 | Q93: 63 | R93: 53 | S93: 50 | T93: 228 | U93: 81 | V93: 93 | W93: 112 | AE93: 112 | AF93: 128 | AG93: 148 | AH93: 161 | AI93: 545 | AJ93: 145 | AK93: 147 | AL93: 171 | AM93: 145 | AN93: 607 | AO93: 147 | AP93: 159 | AQ93: 164 | AR93: 120 | AS93: 589 | AT93: 166 | AU93: 180 | AV93: 187 | AW93: 169 | AX93: 703 | AY93: 1489 | AZ93: 702 | BA93: 174 | BB93: 122 | BC93: 2488 | BD93: 229 | BE93: 176 | BF93: 195 | BG93: 115 | BH93: 714 | BI93: 189 | BJ93: 230 | BK93: 230 | BL93: 226 | BM93: 875 | CK93: 2031E | CL93: =CM93+$CL$88 -> 0.5 | CM93: 0.49 | CN93: =CM93+$CN$88 -> 0.47
CK94: MI_M (Market Intelligence adjusted margin) | CL94: 0.01 | CM94: Δ → | CN94: -0.02 | CO94: FY2025 recast 33.0%, 1H-26 34.4%; new operating model (Jul-2026).
B95: Spun-off, divested & legacy divisions (history only; not in the forecast) | CC95: LEGACY — Mobility (Mar-2022 to Jun-2026; spun off as Mobility Global, 1-Jul-2026), Engineering Solutions (Mar-2022 to May-2023, sold to KKR), combined MCI 2016–17 | CK95: 2027E | CL95: =CM95+$CL$94 -> 0.36 | CM95: 0.35 | CN95: =CM95+$CN$94 -> 0.33
B96: Mobility (spun off 1-Jul-2026; 2025+ pro forma excludes it) — revenue | AY96: 115 | AZ96: 337 | BA96: 346 | BB96: 345 | BC96: 1142 | BD96: 358 | BE96: 369 | BF96: 379 | BG96: 377 | BH96: 1484 | BI96: 386 | BJ96: 400 | BK96: 412 | BL96: 411 | BM96: 1609 | BU96: =0 -> 0 | BV96: =0 -> 0 | BW96: =SUM(BS96:BV96) -> 0 | BX96: =0 -> 0 | BY96: =0 -> 0 | BZ96: =0 -> 0 | CA96: =0 -> 0 | CB96: =0 -> 0 | CK96: 2028E | CL96: =CM96+$CL$94 -> 0.365 | CM96: 0.355 | CN96: =CM96+$CN$94 -> 0.335
B97: Mobility (spun off 1-Jul-2026; 2025+ pro forma excludes it) — adjusted OP | AY97: 43 | AZ97: 141 | BA97: 146 | BB97: 117 | BC97: 447 | BD97: 140 | BE97: 149 | BF97: 160 | BG97: 127 | BH97: 576 | BI97: 147 | BJ97: 164 | BK97: 174 | BL97: 143 | BM97: 627 | BU97: =0 -> 0 | BV97: =0 -> 0 | BW97: =SUM(BS97:BV97) -> 0 | BX97: =0 -> 0 | BY97: =0 -> 0 | BZ97: =0 -> 0 | CA97: =0 -> 0 | CB97: =0 -> 0 | CK97: 2029E | CL97: =CM97+$CL$94 -> 0.37 | CM97: 0.36 | CN97: =CM97+$CN$94 -> 0.34
B98: Memo: operating profit (GAAP) | AY98: 18 | AZ98: 58 | BA98: 90 | BB98: 48 | BC98: 213 | BD98: 64 | BE98: 68 | BF98: 80 | BG98: 46 | BH98: 260 | BI98: 70 | BJ98: 80 | BK98: 97 | BL98: 65 | BM98: 312 | CK98: 2030E | CL98: =CM98+$CL$94 -> 0.375 | CM98: 0.365 | CN98: =CM98+$CN$94 -> 0.345
B99: Engineering Solutions (sold 2-May-2023) — revenue | AY99: 33 | AZ99: 96 | BA99: 95 | BB99: 99 | BC99: 323 | BD99: 100 | BE99: 33 | BF99: 0 | BG99: 0 | BH99: 133 | BI99: 0 | BJ99: 0 | BK99: 0 | BL99: 0 | BM99: 0 | BU99: =0 -> 0 | BV99: =0 -> 0 | BW99: =SUM(BS99:BV99) -> 0 | BX99: =0 -> 0 | BY99: =0 -> 0 | BZ99: =0 -> 0 | CA99: =0 -> 0 | CB99: =0 -> 0 | CK99: 2031E | CL99: =CM99+$CL$94 -> 0.38 | CM99: 0.37 | CN99: =CM99+$CN$94 -> 0.35
B100: Engineering Solutions (sold 2-May-2023) — adjusted OP | AY100: 6 | AZ100: 17 | BA100: 17 | BB100: 15 | BC100: 55 | BD100: 16 | BE100: 4 | BF100: 0 | BG100: 0 | BH100: 20 | BI100: 0 | BJ100: 0 | BK100: 0 | BL100: 0 | BM100: 0 | BU100: =0 -> 0 | BV100: =0 -> 0 | BW100: =SUM(BS100:BV100) -> 0 | BX100: =0 -> 0 | BY100: =0 -> 0 | BZ100: =0 -> 0 | CA100: =0 -> 0 | CB100: =0 -> 0 | CK100: M&A_spend (bolt-on acquisitions, $m) | CL100: 500 | CM100: Δ → | CN100: -500 | CO100: Assumption: bolt-ons (With Intelligence ~$1.8bn in 2025, Visible Alpha 2024, small deals 2026). Base $500m p.a.
...

Sheet Bull-Base-Bear
B2: S&P Global Inc. (SPGI) — Bull / Base / Bear Case P&L Summary | J2: Share price ($): | K2: =Model!$BX$488 -> 415
B3: Adjusted figures (company definitions: adjusted operating profit, adjusted diluted EPS; adjusted EBITDA = model definition) · USD millions · continuing operations excluding Mobility · Live panel linked to Model — toggle scenario via Model!CC2. Bull and Bear panels are value snapshots generated from the Model with the switch set to each case. FY2026E = 1H actual (pro forma) + 2H calibrated to the FY26 guidance (revenue +5.9–7.9%, adjusted EPS $17.50–17.75). | J3: As of: | K3: =TODAY() -> 2026-10-12 00:00:00
B5: Scenario: | C5: =Model!$CC$2 -> Base | N5: Scenario: | O5: Bull | P5: Snapshot (values) — Model run with switch = Bull | Z5: Scenario: | AA5: Bear | AB5: Snapshot (values) — Model run with switch = Bear
B7: (USDm, except EPS and shares) | C7: 2026E | D7: 2027E | E7: 2028E | F7: 2029E | G7: 2030E | H7: 2031E | I7: 26-'31 CAGR | J7: LT Hist Avg | K7: LT Hist Min | L7: LT Hist Max | N7: (USDm, except EPS and shares) | O7: 2026E | P7: 2027E | Q7: 2028E | R7: 2029E | S7: 2030E | T7: 2031E | U7: 26-'31 CAGR | V7: LT Hist Avg | W7: LT Hist Min | X7: LT Hist Max | Z7: (USDm, except EPS and shares) | AA7: 2026E | AB7: 2027E | AC7: 2028E | AD7: 2029E | AE7: 2030E | AF7: 2031E | AG7: 26-'31 CAGR | AH7: LT Hist Avg | AI7: LT Hist Min | AJ7: LT Hist Max
B9: Revenue | C9: =Model!BW187 -> 14526.641 | D9: =Model!BX187 -> 15426.203 | E9: =Model!BY187 -> 16516.783 | F9: =Model!BZ187 -> 17650.843 | G9: =Model!CA187 -> 18809.309 | H9: =Model!CB187 -> 20042.002 | I9: =IFERROR((H9/C9)^(1/5)-1,"n/m") -> 0.066486056 | N9: Revenue | O9: 14662.531 | P9: 16002.395 | Q9: 17634.634 | R9: 19390.16 | S9: 21253.108 | T9: 23285.507 | U9: 0.096921005 | Z9: Revenue | AA9: 14390.751 | AB9: 14462.943 | AC9: 14641.292 | AD9: 14801.812 | AE9: 14933.161 | AF9: 15076.307 | AG9: 0.0093512033
B10: Revenue y/y % | D10: =IFERROR(D9/C9-1,"") -> 0.061924987 | E10: =IFERROR(E9/D9-1,"") -> 0.070696602 | F10: =IFERROR(F9/E9-1,"") -> 0.068661054 | G10: =IFERROR(G9/F9-1,"") -> 0.065632328 | H10: =IFERROR(H9/G9-1,"") -> 0.065536358 | N10: Revenue y/y % | P10: 0.091380163 | Q10: 0.10199963 | R10: 0.09954992 | S10: 0.096076989 | T10: 0.095628321 | Z10: Revenue y/y % | AB10: 0.0050165488 | AC10: 0.01233143 | AD10: 0.010963549 | AE10: 0.0088738142 | AF10: 0.0095858261
B11: Ratings revenue y/y % | C11: =Model!BW293 -> 0.10993476 | D11: =Model!BX293 -> 0.048153273 | E11: =Model!BY293 -> 0.064632911 | F11: =Model!BZ293 -> 0.06 | G11: =Model!CA293 -> 0.054656266 | H11: =Model!CB293 -> 0.054679859 | N11: Ratings revenue y/y % | O11: 0.11988131 | P11: 0.079081947 | Q11: 0.095413082 | R11: 0.090871496 | S11: 0.085481235 | T11: 0.085504053 | Z11: Ratings revenue y/y % | AA11: 0.099988221 | AB11: -0.0091794629 | AC11: 0.0085644453 | AD11: 0.0045456329 | AE11: 0.00020111902 | AF11: 0.0011008976
B12: Adjusted EBITDA (model) | C12: =Model!BW256 -> 7638.2824 | D12: =Model!BX256 -> 8309.2359 | E12: =Model!BY256 -> 8971.2164 | F12: =Model!BZ256 -> 9618.8125 | G12: =Model!CA256 -> 10291.886 | H12: =Model!CB256 -> 10979.397 | I12: =IFERROR((H12/C12)^(1/5)-1,"n/m") -> 0.075267583 | N12: Adjusted EBITDA (model) | O12: 7685.4478 | P12: 8775.4755 | Q12: 9750.4731 | R12: 10758.294 | S12: 11844.687 | T12: 13000.836 | U12: 0.11086279 | Z12: Adjusted EBITDA (model) | AA12: 7591.0685 | AB12: 7422.4785 | AC12: 7564.1227 | AD12: 7658.9854 | AE12: 7745.2453 | AF12: 7816.0513 | AG12: 0.0058585176
B13: Adjusted EBITDA margin % | C13: =IFERROR(C12/C9,"") -> 0.52581201 | D13: =IFERROR(D12/D9,"") -> 0.53864427 | E13: =IFERROR(E12/E9,"") -> 0.5431576 | F13: =IFERROR(F12/F9,"") -> 0.54494919 | G13: =IFERROR(G12/G9,"") -> 0.54716983 | H13: =IFERROR(H12/H9,"") -> 0.54781934 | J13: =IFERROR(AVERAGE(Model!C257,Model!D257,Model!E257,Model!J257,Model!O257,Model!T257,Model!Y257,Model!AD257,Model!AI257,Model!AN257,Model!AS257,Model!AX257,Model!BC257,Model!BH257,Model!BM257,Model!BR257),"") -> 0.44171145 | K13: =IFERROR(MIN(Model!C257,Model!D257,Model!E257,Model!J257,Model!O257,Model!T257,Model!Y257,Model!AD257,Model!AI257,Model!AN257,Model!AS257,Model!AX257,Model!BC257,Model!BH257,Model!BM257,Model!BR257),"") -> 0.30273141 | L13: =IFERROR(MAX(Model!C257,Model!D257,Model!E257,Model!J257,Model!O257,Model!T257,Model!Y257,Model!AD257,Model!AI257,Model!AN257,Model!AS257,Model!AX257,Model!BC257,Model!BH257,Model!BM257,Model!BR257),"") -> 0.56201037 | N13: Adjusted EBITDA margin % | O13: 0.52415561 | P13: 0.54838512 | Q13: 0.55291611 | R13: 0.55483264 | S13: 0.55731549 | T13: 0.55832306 | V13: 0.44171145 | W13: 0.30273141 | X13: 0.56201037 | Z13: Adjusted EBITDA margin % | AA13: 0.52749634 | AB13: 0.51320665 | AC13: 0.51662947 | AD13: 0.51743566 | AE13: 0.51866082 | AF13: 0.51843274 | AH13: 0.44171145 | AI13: 0.30273141 | AJ13: 0.56201037
B15: Operating profit (GAAP) | C15: =Model!BW196 -> 7057.2824 | D15: =Model!BX196 -> 7338.9929 | E15: =Model!BY196 -> 7998.5821 | F15: =Model!BZ196 -> 8651.4391 | G15: =Model!CA196 -> 9329.5785 | H15: =Model!CB196 -> 10020.561 | I15: =IFERROR((H15/C15)^(1/5)-1,"n/m") -> 0.072632385 | N15: Operating profit (GAAP) | O15: 7104.4478 | P15: 7784.7897 | Q15: 8741.3961 | R15: 9737.8392 | S15: 10811.995 | T15: 11953.552 | U15: 0.10966868 | Z15: Operating profit (GAAP) | AA15: 7010.0685 | AB15: 6475.7749 | AC15: 6633.9924 | AD15: 6753.5709 | AE15: 6864.78 | AF15: 6959.4408 | AG15: -0.0014486186
B16: Operating profit y/y % | D16: =IFERROR(D15/C15-1,"") -> 0.039917713 | E16: =IFERROR(E15/D15-1,"") -> 0.089874614 | F16: =IFERROR(F15/E15-1,"") -> 0.081621591 | G16: =IFERROR(G15/F15-1,"") -> 0.078384578 | H16: =IFERROR(H15/G15-1,"") -> 0.074063596 | N16: Operating profit y/y % | P16: 0.095762811 | Q16: 0.12288146 | R16: 0.11399131 | S16: 0.1103074 | T16: 0.10558243 | Z16: Operating profit y/y % | AB16: -0.07621803 | AC16: 0.024432212 | AD16: 0.018025119 | AE16: 0.016466713 | AF16: 0.013789342
B17: Operating margin (GAAP) % | C17: =IFERROR(C15/C9,"") -> 0.48581653 | D17: =IFERROR(D15/D9,"") -> 0.4757485 | E17: =IFERROR(E15/E9,"") -> 0.48426997 | F17: =IFERROR(F15/F9,"") -> 0.49014311 | G17: =IFERROR(G15/G9,"") -> 0.49600858 | H17: =IFERROR(H15/H9,"") -> 0.49997802 | J17: =IFERROR(AVERAGE(Model!C305,Model!D305,Model!E305,Model!J305,Model!O305,Model!T305,Model!Y305,Model!AD305,Model!AI305,Model!AN305,Model!AS305,Model!AX305,Model!BC305,Model!BH305,Model!BM305,Model!BR305),"") -> 0.37837768 | K17: =IFERROR(MIN(Model!C305,Model!D305,Model!E305,Model!J305,Model!O305,Model!T305,Model!Y305,Model!AD305,Model!AI305,Model!AN305,Model!AS305,Model!AX305,Model!BC305,Model!BH305,Model!BM305,Model!BR305),"") -> 0.022371808 | L17: =IFERROR(MAX(Model!C305,Model!D305,Model!E305,Model!J305,Model!O305,Model!T305,Model!Y305,Model!AD305,Model!AI305,Model!AN305,Model!AS305,Model!AX305,Model!BC305,Model!BH305,Model!BM305,Model!BR305),"") -> 0.59512454 | N17: Operating margin (GAAP) % | O17: 0.4845308 | P17: 0.48647652 | Q17: 0.49569479 | R17: 0.5022052 | S17: 0.50872535 | T17: 0.51334727 | V17: 0.37837768 | W17: 0.022371808 | X17: 0.59512454 | Z17: Operating margin (GAAP) % | AA17: 0.48712319 | AB17: 0.44774946 | AC17: 0.45310158 | AD17: 0.45626649 | AE17: 0.4597004 | AF17: 0.46161442 | AH17: 0.37837768 | AI17: 0.022371808 | AJ17: 0.59512454
B19: Adjusted Net Income | C19: =Model!BW270 -> 5151.1027 | D19: =Model!BX270 -> 5547.5621 | E19: =Model!BY270 -> 6003.5561 | F19: =Model!BZ270 -> 6405.5589 | G19: =Model!CA270 -> 6837.1597 | H19: =Model!CB270 -> 7283.3796 | I19: =IFERROR((H19/C19)^(1/5)-1,"n/m") -> 0.071732864 | N19: Adjusted Net Income | O19: 5184.9621 | P19: 5873.2227 | Q19: 6457.3802 | R19: 7094.3457 | S19: 7782.3107 | T19: 8519.3999 | U19: 0.10441598 | Z19: Adjusted Net Income | AA19: 5117.2056 | AB19: 4929.6586 | AC19: 5108.0194 | AD19: 5163.0276 | AE19: 5222.4277 | AF19: 5277.3579 | AG19: 0.0061824454
B21: FDSO (m) | C21: =Model!BW217 -> 292.26114 | D21: =Model!BX217 -> 277.39309 | E21: =Model!BY217 -> 267.67227 | F21: =Model!BZ217 -> 257.00028 | G21: =Model!CA217 -> 246.40775 | H21: =Model!CB217 -> 235.85994 | I21: =IFERROR((H21/C21)^(1/5)-1,"n/m") -> -0.041975488 | N21: FDSO (m) | O21: 292.11054 | P21: 273.83687 | Q21: 260.30007 | R21: 247.63317 | S21: 234.50842 | T21: 220.90521 | U21: -0.054347125 | Z21: FDSO (m) | AA21: 292.41175 | AB21: 281.71338 | AC21: 277.24308 | AD21: 269.92768 | AE21: 263.2582 | AF21: 257.14783 | AG21: -0.02537486
B23: Adjusted EPS — Diluted ($) | C23: =Model!BW274 -> 17.625 | D23: =Model!BX274 -> 19.99892 | E23: =Model!BY274 -> 22.428756 | F23: =Model!BZ274 -> 24.924327 | G23: =Model!CA274 -> 27.747341 | H23: =Model!CB274 -> 30.880105 | I23: =IFERROR((H23/C23)^(1/5)-1,"n/m") -> 0.11869044 | N23: Adjusted EPS — Diluted ($) | O23: 17.75 | P23: 21.447889 | Q23: 24.807448 | R23: 28.648608 | S23: 33.185634 | T23: 38.565861 | U23: 0.1678873 | Z23: Adjusted EPS — Diluted ($) | AA23: 17.5 | AB23: 17.498844 | AC23: 18.424335 | AD23: 19.127448 | AE23: 19.837664 | AF23: 20.522661 | AG23: 0.032378916
B24: EPS y/y % | D24: =IFERROR(D23/C23-1,"") -> 0.13469048 | E24: =IFERROR(E23/D23-1,"") -> 0.12149837 | F24: =IFERROR(F23/E23-1,"") -> 0.11126658 | G24: =IFERROR(G23/F23-1,"") -> 0.11326339 | H24: =IFERROR(H23/G23-1,"") -> 0.11290322 | N24: EPS y/y % | P24: 0.20833175 | Q24: 0.15663821 | R24: 0.15483901 | S24: 0.15836811 | T24: 0.16212519 | Z24: EPS y/y % | AB24: -6.6046231e-05 | AC24: 0.052888692 | AD24: 0.038162169 | AE24: 0.037130733 | AF24: 0.034530152
B26: P / E (x) — assumed (adjusted EPS) | F26: 26 | G26: 26 | H26: 26 | N26: P / E (x) — assumed (adjusted EPS) | R26: 30 | S26: 30 | T26: 30 | Z26: P / E (x) — assumed (adjusted EPS) | AD26: 20 | AE26: 20 | AF26: 20
B27: Price Target ($) | F27: =F26*F23 -> 648.0325 | G27: =G26*G23 -> 721.43085 | H27: =H26*H23 -> 802.88272 | N27: Price Target ($) | R27: =R26*R23 -> 859.45824 | S27: =S26*S23 -> 995.56902 | T27: =T26*T23 -> 1156.9758 | Z27: Price Target ($) | AD27: =AD26*AD23 -> 382.54896 | AE27: =AE26*AE23 -> 396.75328 | AF27: =AF26*AF23 -> 410.45323
B28: Upside / (Downside) vs current | F28: =IFERROR(F27/$K$2-1,"") -> 0.56152409 | G28: =IFERROR(G27/$K$2-1,"") -> 0.7383876 | H28: =IFERROR(H27/$K$2-1,"") -> 0.93465715 | N28: Upside / (Downside) vs current | R28: =IFERROR(R27/$K$2-1,"") -> 1.0709837 | S28: =IFERROR(S27/$K$2-1,"") -> 1.3989615 | T28: =IFERROR(T27/$K$2-1,"") -> 1.7878936 | Z28: Upside / (Downside) vs current | AD28: =IFERROR(AD27/$K$2-1,"") -> -0.078195289 | AE28: =IFERROR(AE27/$K$2-1,"") -> -0.043968004 | AF28: =IFERROR(AF27/$K$2-1,"") -> -0.010956073
B29: IRR (to 31-Dec of Y-1) | F29: =IFERROR((F27/$K$2)^(1/((DATE(2029-1,12,31)-$K$3)/365.25))-1,"") -> 0.22227381 | G29: =IFERROR((G27/$K$2)^(1/((DATE(2030-1,12,31)-$K$3)/365.25))-1,"") -> 0.18737077 | H29: =IFERROR((H27/$K$2)^(1/((DATE(2031-1,12,31)-$K$3)/365.25))-1,"") -> 0.16931437 | N29: IRR (to 31-Dec of Y-1) | R29: =IFERROR((R27/$K$2)^(1/((DATE(2029-1,12,31)-$K$3)/365.25))-1,"") -> 0.38802237 | S29: =IFERROR((S27/$K$2)^(1/((DATE(2030-1,12,31)-$K$3)/365.25))-1,"") -> 0.31229112 | T29: =IFERROR((T27/$K$2)^(1/((DATE(2031-1,12,31)-$K$3)/365.25))-1,"") -> 0.27508751 | Z29: IRR (to 31-Dec of Y-1) | AD29: =IFERROR((AD27/$K$2)^(1/((DATE(2029-1,12,31)-$K$3)/365.25))-1,"") -> -0.036005769 | AE29: =IFERROR((AE27/$K$2)^(1/((DATE(2030-1,12,31)-$K$3)/365.25))-1,"") -> -0.013868129 | AF29: =IFERROR((AF27/$K$2)^(1/((DATE(2031-1,12,31)-$K$3)/365.25))-1,"") -> -0.0026077482
B31: Free Cash Flow | C31: =Model!BW339 -> 5183.0146 | D31: =Model!BX339 -> 5846.5256 | E31: =Model!BY339 -> 6355.8976 | F31: =Model!BZ339 -> 6772.4646 | G31: =Model!CA339 -> 7213.9573 | H31: =Model!CB339 -> 7683.3266 | I31: =IFERROR((H31/C31)^(1/5)-1,"n/m") -> 0.081915572 | N31: Free Cash Flow | O31: 5251.2058 | P31: 6280.4455 | Q31: 6949.463 | R31: 7627.5096 | S31: 8353.1917 | T31: 9144.911 | U31: 0.11733676 | Z31: Free Cash Flow | AA31: 5114.7858 | AB31: 5020.2501 | AC31: 5222.4508 | AD31: 5268.068 | AE31: 5315.0361 | AF31: 5368.1808 | AG31: 0.0097176268
B32: FCF % | C32: =IFERROR(C31/C9,"") -> 0.35679374 | D32: =IFERROR(D31/D9,"") -> 0.37899965 | E32: =IFERROR(E31/E9,"") -> 0.3848145 | F32: =IFERROR(F31/F9,"") -> 0.38369072 | G32: =IFERROR(G31/G9,"") -> 0.38353123 | H32: =IFERROR(H31/H9,"") -> 0.38336122 | J32: =IFERROR(AVERAGE(Model!C343,Model!D343,Model!E343,Model!J343,Model!O343,Model!T343,Model!Y343,Model!AD343,Model!AI343,Model!AN343,Model!AS343,Model!AX343,Model!BC343,Model!BH343,Model!BM343,Model!BR343),"") -> 0.26407735 | K32: =IFERROR(MIN(Model!C343,Model!D343,Model!E343,Model!J343,Model!O343,Model!T343,Model!Y343,Model!AD343,Model!AI343,Model!AN343,Model!AS343,Model!AX343,Model!BC343,Model!BH343,Model!BM343,Model!BR343),"") -> -0.0090344438 | L32: =IFERROR(MAX(Model!C343,Model!D343,Model!E343,Model!J343,Model!O343,Model!T343,Model!Y343,Model!AD343,Model!AI343,Model!AN343,Model!AS343,Model!AX343,Model!BC343,Model!BH343,Model!BM343,Model!BR343),"") -> 0.44302607 | N32: FCF % | O32: 0.35813775 | P32: 0.39246909 | Q32: 0.39408037 | R32: 0.39337012 | S32: 0.39303388 | T32: 0.39272973 | V32: 0.26407735 | W32: -0.0090344438 | X32: 0.44302607 | Z32: FCF % | AA32: 0.35542174 | AB32: 0.34711124 | AC32: 0.35669331 | AD32: 0.35590696 | AE32: 0.35592171 | AF32: 0.35606735 | AH32: 0.26407735 | AI32: -0.0090344438 | AJ32: 0.44302607
B33: FCF / share ($) | C33: =IFERROR(C31/C21,"") -> 17.73419 | D33: =IFERROR(D31/D21,"") -> 21.076681 | E33: =IFERROR(E31/E21,"") -> 23.745073 | F33: =IFERROR(F31/F21,"") -> 26.351974 | G33: =IFERROR(G31/G21,"") -> 29.276504 | H33: =IFERROR(H31/H21,"") -> 32.575801 | N33: FCF / share ($) | O33: 17.976776 | P33: 22.934989 | Q33: 26.697892 | R33: 30.801647 | S33: 35.620007 | T33: 41.397443 | Z33: FCF / share ($) | AA33: 17.491725 | AB33: 17.820417 | AC33: 18.837083 | AD33: 19.51659 | AE33: 20.189442 | AF33: 20.875855
B34: FCF Yield (on PT) | F34: =IFERROR(F33/F$27,"") -> 0.040664587 | G34: =IFERROR(G33/G$27,"") -> 0.040581164 | H34: =IFERROR(H33/H$27,"") -> 0.040573549 | N34: FCF Yield (on PT) | R34: =IFERROR(R33/R$27,"") -> 0.035838445 | S34: =IFERROR(S33/S$27,"") -> 0.035778541 | T34: =IFERROR(T33/T$27,"") -> 0.035780732 | Z34: FCF Yield (on PT) | AD34: =IFERROR(AD33/AD$27,"") -> 0.051017236 | AE34: =IFERROR(AE33/AE$27,"") -> 0.050886641 | AF34: =IFERROR(AF33/AF$27,"") -> 0.050860497
B35: Adjusted EBITDA (leverage basis) | C35: =Model!BW256 -> 7638.2824 | D35: =Model!BX256 -> 8309.2359 | E35: =Model!BY256 -> 8971.2164 | F35: =Model!BZ256 -> 9618.8125 | G35: =Model!CA256 -> 10291.886 | H35: =Model!CB256 -> 10979.397 | I35: =IFERROR((H35/C35)^(1/5)-1,"n/m") -> 0.075267583 | N35: Adjusted EBITDA (leverage basis) | O35: 7685.4478 | P35: 8775.4755 | Q35: 9750.4731 | R35: 10758.294 | S35: 11844.687 | T35: 13000.836 | U35: 0.11086279 | Z35: Adjusted EBITDA (leverage basis) | AA35: 7591.0685 | AB35: 7422.4785 | AC35: 7564.1227 | AD35: 7658.9854 | AE35: 7745.2453 | AF35: 7816.0513 | AG35: 0.0058585176
B36: Adjusted EBITDA % of revenue | C36: =IFERROR(C35/C9,"") -> 0.52581201 | D36: =IFERROR(D35/D9,"") -> 0.53864427 | E36: =IFERROR(E35/E9,"") -> 0.5431576 | F36: =IFERROR(F35/F9,"") -> 0.54494919 | G36: =IFERROR(G35/G9,"") -> 0.54716983 | H36: =IFERROR(H35/H9,"") -> 0.54781934 | J36: =IFERROR(AVERAGE(Model!C304,Model!D304,Model!E304,Model!J304,Model!O304,Model!T304,Model!Y304,Model!AD304,Model!AI304,Model!AN304,Model!AS304,Model!AX304,Model!BC304,Model!BH304,Model!BM304,Model!BR304),"") -> 0.44171145 | K36: =IFERROR(MIN(Model!C304,Model!D304,Model!E304,Model!J304,Model!O304,Model!T304,Model!Y304,Model!AD304,Model!AI304,Model!AN304,Model!AS304,Model!AX304,Model!BC304,Model!BH304,Model!BM304,Model!BR304),"") -> 0.30273141 | L36: =IFERROR(MAX(Model!C304,Model!D304,Model!E304,Model!J304,Model!O304,Model!T304,Model!Y304,Model!AD304,Model!AI304,Model!AN304,Model!AS304,Model!AX304,Model!BC304,Model!BH304,Model!BM304,Model!BR304),"") -> 0.56201037 | N36: Adjusted EBITDA % of revenue | O36: 0.52415561 | P36: 0.54838512 | Q36: 0.55291611 | R36: 0.55483264 | S36: 0.55731549 | T36: 0.55832306 | V36: 0.44171145 | W36: 0.30273141 | X36: 0.56201037 | Z36: Adjusted EBITDA % of revenue | AA36: 0.52749634 | AB36: 0.51320665 | AC36: 0.51662947 | AD36: 0.51743566 | AE36: 0.51866082 | AF36: 0.51843274 | AH36: 0.44171145 | AI36: 0.30273141 | AJ36: 0.56201037
B38: Net Debt | C38: =Model!BW482 -> 12314.897 | D38: =Model!BX482 -> 12463.854 | E38: =Model!BY482 -> 13456.825 | F38: =Model!BZ482 -> 14428.219 | G38: =Model!CA482 -> 15437.829 | H38: =Model!CB482 -> 16469.095 | N38: Net Debt | O38: 12496.706 | P38: 15357.082 | Q38: 17063.328 | R38: 18827.014 | S38: 20728.201 | T38: 22751.463 | Z38: Net Debt | AA38: 12133.126 | AB38: 9278.0981 | AC38: 9455.1534 | AD38: 9573.7318 | AE38: 9681.5566 | AF38: 9770.0641
B39: Net Debt / Adjusted EBITDA (x) | C39: =IFERROR(C38/C35,"") -> 1.61226 | D39: =IFERROR(D38/D35,"") -> 1.5 | E39: =IFERROR(E38/E35,"") -> 1.5 | F39: =IFERROR(F38/F35,"") -> 1.5 | G39: =IFERROR(G38/G35,"") -> 1.5 | H39: =IFERROR(H38/H35,"") -> 1.5 | N39: Net Debt / Adjusted EBITDA (x) | O39: 1.6260219 | P39: 1.75 | Q39: 1.75 | R39: 1.75 | S39: 1.75 | T39: 1.75 | Z39: Net Debt / Adjusted EBITDA (x) | AA39: 1.5983423 | AB39: 1.25 | AC39: 1.25 | AD39: 1.25 | AE39: 1.25 | AF39: 1.25
B40: Share repurchases ($m; FY2026E = 2H) | D40: =Model!BX353 -> 4348.8769 | E40: =Model!BY353 -> 5682.1616 | F40: =Model!BZ353 -> 6067.0503 | G40: =Model!CA353 -> 6537.9356 | H40: =Model!CB353 -> 7022.0685 | N40: Share repurchases ($m; FY2026E = 2H) | P40: 6996.6706 | Q40: 6516.85 | R40: 7251.3727 | S40: 8118.2654 | T40: 9041.504 | AB40: 1016.1625 | AC40: 4198.4145 | AD40: 4159.9658 | AE40: 4167.6586 | AF40: 4170.3272
B41: Implied avg buyback price ($) | D41: =Model!BX352 -> 448.2 | E41: =Model!BY352 -> 484.056 | F41: =Model!BZ352 -> 522.78048 | G41: =Model!CA352 -> 564.60292 | H41: =Model!CB352 -> 609.77115 | N41: Implied avg buyback price ($) | P41: 448.2 | Q41: 484.056 | R41: 522.78048 | S41: 564.60292 | T41: 609.77115 | AB41: 448.2 | AC41: 484.056 | AD41: 522.78048 | AE41: 564.60292 | AF41: 609.77115
B42: Shares repurchased (m) | D42: =Model!BX354 -> 9.7029828 | E42: =Model!BY354 -> 11.738645 | F42: =Model!BZ354 -> 11.60535 | G42: =Model!CA354 -> 11.579706 | H42: =Model!CB354 -> 11.515908 | N42: Shares repurchased (m) | P42: 15.610599 | Q42: 13.463008 | R42: 13.870779 | S42: 14.378717 | T42: 14.8277 | AB42: 2.2672077 | AC42: 8.6734067 | AD42: 7.9573856 | AE42: 7.3815747 | AF42: 6.8391678
B44: ROIC | C44: =Model!BW465 -> 0.16235083 | D44: =Model!BX465 -> 0.18036487 | E44: =Model!BY465 -> 0.19645952 | F44: =Model!BZ465 -> 0.212428 | G44: =Model!CA465 -> 0.22912833 | H44: =Model!CB465 -> 0.24638904 | J44: =IFERROR(AVERAGE(Model!C465,Model!D465,Model!E465,Model!J465,Model!O465,Model!T465,Model!Y465,Model!AD465,Model!AI465,Model!AN465,Model!AS465,Model!AX465,Model!BC465,Model!BH465,Model!BM465,Model!BR465),"") -> 0.4313108 | K44: =IFERROR(MIN(Model!C465,Model!D465,Model!E465,Model!J465,Model!O465,Model!T465,Model!Y465,Model!AD465,Model!AI465,Model!AN465,Model!AS465,Model!AX465,Model!BC465,Model!BH465,Model!BM465,Model!BR465),"") -> -0.21665383 | L44: =IFERROR(MAX(Model!C465,Model!D465,Model!E465,Model!J465,Model!O465,Model!T465,Model!Y465,Model!AD465,Model!AI465,Model!AN465,Model!AS465,Model!AX465,Model!BC465,Model!BH465,Model!BM465,Model!BR465),"") -> 1.0746325 | N44: ROIC | O44: 0.16354826 | P44: 0.18847906 | Q44: 0.20920422 | R44: 0.23066584 | S44: 0.25386309 | T44: 0.27873661 | V44: 0.4313108 | W44: -0.21665383 | X44: 1.0746325 | Z44: ROIC | AA44: 0.16115466 | AB44: 0.16228985 | AC44: 0.16808642 | AD44: 0.17283526 | AE44: 0.17735407 | AF44: 0.18151091 | AH44: 0.4313108 | AI44: -0.21665383 | AJ44: 1.0746325
B45: ROE | C45: =Model!BW480 -> 0.27462507 | D45: =Model!BX480 -> 0.28289916 | E45: =Model!BY480 -> 0.33409368 | F45: =Model!BZ480 -> 0.39007873 | G45: =Model!CA480 -> 0.45931668 | H45: =Model!CB480 -> 0.54488411 | J45: =IFERROR(AVERAGE(Model!C480,Model!D480,Model!E480,Model!J480,Model!O480,Model!T480,Model!Y480,Model!AD480,Model!AI480,Model!AN480,Model!AS480,Model!AX480,Model!BC480,Model!BH480,Model!BM480,Model!BR480),"") -> 1.9109924 | K45: =IFERROR(MIN(Model!C480,Model!D480,Model!E480,Model!J480,Model!O480,Model!T480,Model!Y480,Model!AD480,Model!AI480,Model!AN480,Model!AS480,Model!AX480,Model!BC480,Model!BH480,Model!BM480,Model!BR480),"") -> -0.23565574 | L45: =IFERROR(MAX(Model!C480,Model!D480,Model!E480,Model!J480,Model!O480,Model!T480,Model!Y480,Model!AD480,Model!AI480,Model!AN480,Model!AS480,Model!AX480,Model!BC480,Model!BH480,Model!BM480,Model!BR480),"") -> 5.9587629 | N45: ROE | O45: 0.27993964 | P45: 0.35258063 | Q45: 0.44052529 | R45: 0.56228669 | S45: 0.74370032 | T45: 1.0394065 | V45: 1.9109924 | W45: -0.23565574 | X45: 5.9587629 | Z45: ROE | AA45: 0.26943679 | AB45: 0.21219107 | AC45: 0.22991477 | AD45: 0.24163182 | AE45: 0.25378257 | AF45: 0.26581689 | AH45: 1.9109924 | AI45: -0.23565574 | AJ45: 5.9587629
B47: Implied Market Cap (USDm) | F47: =F27*F21 -> 166544.53 | G47: =G27*G21 -> 177766.15 | H47: =H27*H21 -> 189367.87 | N47: Implied Market Cap (USDm) | R47: =R27*R21 -> 212830.37 | S47: =S27*S21 -> 233469.32 | T47: =T27*T21 -> 255582 | Z47: Implied Market Cap (USDm) | AD47: =AD27*AD21 -> 103260.55 | AE47: =AE27*AE21 -> 104448.55 | AF47: =AF27*AF21 -> 105547.16
B48: (+) Net Debt & NCI | F48: =F38+Model!BZ492 -> 19567.219 | G48: =G38+Model!CA492 -> 20576.829 | H48: =H38+Model!CB492 -> 21608.095 | N48: (+) Net Debt & NCI | R48: =R38+Model!BZ492 -> 23966.014 | S48: =S38+Model!CA492 -> 25867.201 | T48: =T38+Model!CB492 -> 27890.463 | Z48: (+) Net Debt & NCI | AD48: =AD38+Model!BZ492 -> 14712.732 | AE48: =AE38+Model!CA492 -> 14820.557 | AF48: =AF38+Model!CB492 -> 14909.064
B49: Implied Enterprise Value (USDm) | F49: =F47+F48 -> 186111.75 | G49: =G47+G48 -> 198342.98 | H49: =H47+H48 -> 210975.97 | N49: Implied Enterprise Value (USDm) | R49: =R47+R48 -> 236796.38 | S49: =S47+S48 -> 259336.52 | T49: =T47+T48 -> 283472.46 | Z49: Implied Enterprise Value (USDm) | AD49: =AD47+AD48 -> 117973.28 | AE49: =AE47+AE48 -> 119269.11 | AF49: =AF47+AF48 -> 120456.22
B50: Implied EV / Adjusted EBITDA (x) | F50: =IFERROR(F49/F35,"") -> 19.348724 | G50: =IFERROR(G49/G35,"") -> 19.271781 | H50: =IFERROR(H49/H35,"") -> 19.215625 | N50: Implied EV / Adjusted EBITDA (x) | R50: =IFERROR(R49/R35,"") -> 22.010589 | S50: =IFERROR(S49/S35,"") -> 21.894756 | T50: =IFERROR(T49/T35,"") -> 21.804172 | Z50: Implied EV / Adjusted EBITDA (x) | AD50: =IFERROR(AD49/AD35,"") -> 15.403252 | AE50: =IFERROR(AE49/AE35,"") -> 15.39901 | AF50: =IFERROR(AF49/AF35,"") -> 15.411391

Sheet DCF
B2: DCF VALUATION — S&P GLOBAL INC. (SPGI)
B4: 1. WACC BUILD
B5: Risk-free rate (US 10Y govt) | C5: 0.0425 | D5: Assumption (~US 10Y Treasury yield, Oct-2026; government rate sources not reachable from the build environment); update to market
B6: Equity risk premium | C6: 0.05 | D6: Assumption: US implied ERP ~4.5–5.5%
B7: Levered beta | C7: 1 | D7: Assumption: information-services / benchmark peers (MCO, MSCI, ICE, CME, VRSK, FDS) ~0.9–1.1; Ratings issuance and Indices asset-linked fees are market-sensitive, subscriptions defensive
B8: Cost of equity | C8: =C5+C7*C6 -> 0.0925
B9: Pre-tax cost of debt | C9: 0.05 | D9: Recent issues: $600m 4.25% 2031 and $400m 4.80% 2035 notes (Dec-2025); A-rated issuer; pre-tax cost of new debt ~5% (assumption)
B10: Tax rate | C10: 0.225 | D10: Model 2027E+ effective tax rate (FY26 guidance 22–23%)
B11: After-tax cost of debt | C11: =C9*(1-C10) -> 0.03875
B12: Target D/V | C12: 0.1 | D12: Net debt ~$12bn at YE2026E (after >$7bn of 2026 buybacks) vs ~$118bn market cap ($415 × ~283m diluted shares); ~1.6x adjusted EBITDA; plus ~$5bn redeemable NCI
B13: WACC | C13: =C8*(1-C12)+C11*C12 -> 0.087125
B15: Valuation date (live) | C15: =TODAY() -> 2026-10-12 00:00:00 | D15: Periods = (31-Dec of the year − today) / 365.25; cash flows assumed at year end; FY2026E (Q4 under way at the valuation date) is the base year — its cash flow is in YE2026E net debt
B16: 2. UNLEVERED FREE CASH FLOW BUILD (USDm)
D17: 2027E | E17: 2028E | F17: 2029E | G17: 2030E | H17: 2031E | I17: 2032E | J17: 2033E | K17: 2034E | L17: 2035E | M17: 2036E | N17: Terminal | P17: CAGR 27–31E | Q17: CAGR 27–36E
B18: Adj. EBITA (before deal amortization) less severance, acquisition, disposition & legal cash costs | D18: =Model!BX260-Model!BX262 -> 8135.8263 | E18: =Model!BY260-Model!BY262 -> 8789.0821 | F18: =Model!BZ260-Model!BZ262 -> 9427.6058 | G18: =Model!CA260-Model!CA262 -> 10091.412 | H18: =Model!CB260-Model!CB262 -> 10769.061 | I18: =H18*(1+I$26) -> 11522.895 | J18: =I18*(1+J$26) -> 12271.883 | K18: =J18*(1+K$26) -> 13008.196 | L18: =K18*(1+L$26) -> 13723.647 | M18: =L18*(1+M$26) -> 14409.829 | P18: =(H18/D18)^(1/(COLUMNS(D18:H18)-1))-1 -> 0.072615427 | Q18: =(M18/D18)^(1/(COLUMNS(D18:M18)-1))-1 -> 0.065575262
B19: × (1 − tax rate) | D19: =1-$C$10 -> 0.775 | E19: =1-$C$10 -> 0.775 | F19: =1-$C$10 -> 0.775 | G19: =1-$C$10 -> 0.775 | H19: =1-$C$10 -> 0.775 | I19: =1-$C$10 -> 0.775 | J19: =1-$C$10 -> 0.775 | K19: =1-$C$10 -> 0.775 | ... M19: =1-$C$10 -> 0.775
B20: NOPAT | D20: =D18*D19 -> 6305.2654 | E20: =E18*E19 -> 6811.5386 | F20: =F18*F19 -> 7306.3945 | G20: =G18*G19 -> 7820.8442 | H20: =H18*H19 -> 8346.022 | I20: =I18*I19 -> 8930.2435 | J20: =J18*J19 -> 9510.7094 | K20: =K18*K19 -> 10081.352 | ... M20: =M18*M19 -> 11167.618
B21: plus depreciation (deal-related amortization is not deducted above, so it is not added back) | D21: =Model!BX168 -> 123.40962 | E21: =Model!BY168 -> 132.13427 | F21: =Model!BZ168 -> 141.20674 | G21: =Model!CA168 -> 150.47447 | H21: =Model!CB168 -> 160.33602 | I21: =H21*(1+I$26) -> 171.55954 | J21: =I21*(1+J$26) -> 182.71091 | K21: =J21*(1+K$26) -> 193.67357 | L21: =K21*(1+L$26) -> 204.32561 | M21: =L21*(1+M$26) -> 214.54189
B22: − Capex and acquisitions (bolt-ons; M&A lever 2027E–31E) | D22: =Model!BX320+Model!BX321 -> -715.96684 | E22: =Model!BY320+Model!BY321 -> -731.23496 | F22: =Model!BZ320+Model!BZ321 -> -747.1118 | G22: =Model!CA320+Model!CA321 -> -763.33032 | H22: =Model!CB320+Model!CB321 -> -780.58803 | I22: =Model!CB320*(1+I$26) -> -300.2292 | J22: =I22*(1+J$26) -> -319.74409 | K22: =J22*(1+K$26) -> -338.92874 | L22: =K22*(1+L$26) -> -357.56982 | M22: =L22*(1+M$26) -> -375.44831
B23: − Δ Working capital (CF statement) | D23: =Model!BX318 -> 227.26881 | E23: =Model!BY318 -> 275.52835 | F23: =Model!BZ318 -> 286.5132 | G23: =Model!CA318 -> 292.67927 | H23: =Model!CB318 -> 311.43244 | I23: =H23*(1+I$26) -> 333.23271 | J23: =I23*(1+J$26) -> 354.89283 | K23: =J23*(1+K$26) -> 376.1864 | L23: =K23*(1+L$26) -> 396.87666 | M23: =L23*(1+M$26) -> 416.72049
B24: Unlevered FCF | D24: =D20+D21+D22+D23 -> 5939.977 | E24: =E20+E21+E22+E23 -> 6487.9663 | F24: =F20+F21+F22+F23 -> 6987.0026 | G24: =G20+G21+G22+G23 -> 7500.6676 | H24: =H20+H21+H22+H23 -> 8037.2024 | I24: =I20+I21+I22+I23 -> 9134.8066 | J24: =J20+J21+J22+J23 -> 9728.569 | K24: =K20+K21+K22+K23 -> 10312.283 | ... M24: =M20+M21+M22+M23 -> 11423.432 | N24: =M24*(1+$C$27) -> 11880.369 | P24: =(H24/D24)^(1/(COLUMNS(D24:H24)-1))-1 -> 0.078524553 | Q24: =(M24/D24)^(1/(COLUMNS(D24:M24)-1))-1 -> 0.075367408
B25: Terminal Value (Gordon Growth) | N25: =N24/($C$13-$C$27) -> 252103.32
B26: Fade-period growth (2032E–36E; 7.0% → 5.0% linear) | I26: 0.07 | J26: =I26+($M$26-$I$26)/4 -> 0.065 | K26: =J26+($M$26-$I$26)/4 -> 0.06 | L26: =K26+($M$26-$I$26)/4 -> 0.055 | M26: 0.05
B27: Terminal growth rate | C27: 0.04
B29: Discount period (years) | D29: =(DATE(2027,12,31)-$C$15)/365.25 -> 1.2183436 | E29: =(DATE(2028,12,31)-$C$15)/365.25 -> 2.220397 | F29: =(DATE(2029,12,31)-$C$15)/365.25 -> 3.2197125 | G29: =(DATE(2030,12,31)-$C$15)/365.25 -> 4.2190281 | H29: =(DATE(2031,12,31)-$C$15)/365.25 -> 5.2183436 | I29: =(DATE(2032,12,31)-$C$15)/365.25 -> 6.220397 | J29: =(DATE(2033,12,31)-$C$15)/365.25 -> 7.2197125 | K29: =(DATE(2034,12,31)-$C$15)/365.25 -> 8.2190281 | L29: =(DATE(2035,12,31)-$C$15)/365.25 -> 9.2183436 | M29: =(DATE(2036,12,31)-$C$15)/365.25 -> 10.220397 | N29: =M29 -> 10.220397
B30: Discount factor | D30: =1/(1+$C$13)^D29 -> 0.9032316 | E30: =1/(1+$C$13)^E29 -> 0.83070179 | F30: =1/(1+$C$13)^F29 -> 0.7641709 | G30: =1/(1+$C$13)^G29 -> 0.70296846 | H30: =1/(1+$C$13)^H29 -> 0.64666773 | I30: =1/(1+$C$13)^I29 -> 0.59474009 | J30: =1/(1+$C$13)^J29 -> 0.54710737 | K30: =1/(1+$C$13)^K29 -> 0.50328955 | ... N30: =1/(1+$C$13)^N29 -> 0.42580355
B31: PV of UFCF | D31: =D24*D30 -> 5365.1749 | E31: =E24*E30 -> 5389.5652 | F31: =F24*F30 -> 5339.2641 | G31: =G24*G30 -> 5272.7328 | H31: =H24*H30 -> 5197.3995 | I31: =I24*I30 -> 5432.8357 | J31: =J24*J30 -> 5322.5718 | K31: =K24*K30 -> 5190.0643 | ... M31: =M24*M30 -> 4864.1378 | N31: =N25*N30 -> 107346.49
D32: S&P Global's adjusted operating profit excludes deal-related amortization (IHS Markit and other acquired intangibles) but is after stock-based compensation, which the company does not adjust out. NOPAT therefore taxes adjusted EBITA (before acquired-intangible amortization) less the cash severance, acquisition, disposition and legal costs the company adds back (row 18), and adds back depreciation only (row 21). Row 22 includes bolt-on acquisitions in 2027E–31E; the fade period and terminal value assume no new acquisitions. Redeemable NCI (CME Group 27% of S&P DJI) and other NCI are deducted in the EV bridge. Mobility (spun off 1-Jul-2026) is excluded throughout.
B33: IMPLIED ROIC — invested capital roll-forward (USDm)
B34: Opening invested capital | D34: =Model!BW462 -> 35209.934 | E34: =D38 -> 35575.222 | F34: =E38 -> 35898.794 | G34: =F38 -> 36218.186 | H34: =G38 -> 36538.363 | I34: =H38 -> 36847.182 | J34: =I38 -> 36642.619 | K34: =J38 -> 36424.76 | L34: =K38 -> 36193.829 | M34: =L38 -> 35950.196
B35: plus Capex and acquisitions | D35: =-D22 -> 715.96684 | E35: =-E22 -> 731.23496 | F35: =-F22 -> 747.1118 | G35: =-G22 -> 763.33032 | H35: =-H22 -> 780.58803 | I35: =-I22 -> 300.2292 | J35: =-J22 -> 319.74409 | K35: =-K22 -> 338.92874 | ... M35: =-M22 -> 375.44831
B36: less DD&A | D36: =-D21 -> -123.40962 | E36: =-E21 -> -132.13427 | F36: =-F21 -> -141.20674 | G36: =-G21 -> -150.47447 | H36: =-H21 -> -160.33602 | I36: =-I21 -> -171.55954 | J36: =-J21 -> -182.71091 | K36: =-K21 -> -193.67357 | ... M36: =-M21 -> -214.54189
B37: plus Δ Working capital investment | D37: =-D23 -> -227.26881 | E37: =-E23 -> -275.52835 | F37: =-F23 -> -286.5132 | G37: =-G23 -> -292.67927 | H37: =-H23 -> -311.43244 | I37: =-I23 -> -333.23271 | J37: =-J23 -> -354.89283 | K37: =-K23 -> -376.1864 | ... M37: =-M23 -> -416.72049
B38: Closing invested capital | D38: =SUM(D34:D37) -> 35575.222 | E38: =SUM(E34:E37) -> 35898.794 | F38: =SUM(F34:F37) -> 36218.186 | G38: =SUM(G34:G37) -> 36538.363 | H38: =SUM(H34:H37) -> 36847.182 | I38: =SUM(I34:I37) -> 36642.619 | J38: =SUM(J34:J37) -> 36424.76 | K38: =SUM(K34:K37) -> 36193.829 | ... M38: =SUM(M34:M37) -> 35694.382
B39: NOPAT (row 20) | D39: =D20 -> 6305.2654 | E39: =E20 -> 6811.5386 | F39: =F20 -> 7306.3945 | G39: =G20 -> 7820.8442 | H39: =H20 -> 8346.022 | I39: =I20 -> 8930.2435 | J39: =J20 -> 9510.7094 | K39: =K20 -> 10081.352 | ... M39: =M20 -> 11167.618
B40: Implied ROIC (NOPAT / avg. invested capital) | D40: =IFERROR(D39/AVERAGE(D34,D38),"") -> 0.17815219 | E40: =IFERROR(E39/AVERAGE(E34,E38),"") -> 0.19060181 | F40: =IFERROR(F39/AVERAGE(F34,F38),"") -> 0.20262619 | G40: =IFERROR(G39/AVERAGE(G34,G38),"") -> 0.21498667 | H40: =IFERROR(H39/AVERAGE(H34,H38),"") -> 0.22745684 | I40: =IFERROR(I39/AVERAGE(I34,I38),"") -> 0.24303354 | J40: =IFERROR(J39/AVERAGE(J34,J38),"") -> 0.2603271 | K40: =IFERROR(K39/AVERAGE(K34,K38),"") -> 0.2776521 | ... M40: =IFERROR(M39/AVERAGE(M34,M38),"") -> 0.31175053
B41: Reinvestment rate (net investment / NOPAT) | D41: =IFERROR(SUM(D35:D37)/D39,"") -> 0.057933868 | E41: =IFERROR(SUM(E35:E37)/E39,"") -> 0.047503562 | F41: =IFERROR(SUM(F35:F37)/F39,"") -> 0.043714017 | G41: =IFERROR(SUM(G35:G37)/G39,"") -> 0.040938877 | H41: =IFERROR(SUM(H35:H37)/H39,"") -> 0.037002009 | I41: =IFERROR(SUM(I35:I37)/I39,"") -> -0.022906772 | J41: =IFERROR(SUM(J35:J37)/J39,"") -> -0.022906772 | K41: =IFERROR(SUM(K35:K37)/K39,"") -> -0.022906772 | ... M41: =IFERROR(SUM(M35:M37)/M39,"") -> -0.022906772
B42: Implied terminal RONIC (g / reinvestment rate) | N42: =IFERROR($C$27/M41,"") -> -1.7462085
D43: Opening IC = Model FY2026E book IC (equity incl. redeemable NCI + net debt at 31-Dec-2026E, after the Mobility spin-off), rolled forward with capex + M&A − depreciation + ΔWC.
B44: 3. VALUATION SUMMARY
B45: Sum of PV (explicit + fade) | C45: =SUM(D31:M31) -> 52410.73
B46: PV of Terminal Value | C46: =N31 -> 107346.49
B47: Enterprise Value | C47: =C45+C46 -> 159757.22
B48: Less: Net debt + redeemable & other NCI (Model FY2026E year end) | C48: =Model!BW482+Model!BW492 -> 17453.897 | D48: Net debt at 31-Dec-2026E (after the >$7bn 2026 buybacks) plus redeemable NCI (CME 27% of S&P DJI, carrying value) and other NCI; FY2026E cash flow is not double counted.
B49: Equity Value | C49: =C47-C48 -> 142303.32
B50: Diluted shares (m, Model FY2026E period end) | C50: =Model!BW489 -> 281.54458
B51: Implied share price ($) | C51: =C49/C50 -> 505.43797
B52: Current share price ($) | C52: =Model!BW488 -> 415
B53: Implied upside / (downside) | C53: =C51/C52-1 -> 0.21792283
B54: Required discount to DCF value for target IRR | C54: =1-((1+C13)/(1+H54))^H55 -> 0.15521746 | D54: vs. current | E54: Target IRR | H54: 0.15
B55: Max entry price for target IRR ($) | C55: =C51*(1-C54) -> 426.98517 | D55: =C55/C52-1 -> 0.028879938 | E55: Years for discount to close | H55: 3
B58: 4. SENSITIVITY: IMPLIED PRICE ($) — WACC × Terminal Growth
D60: WACC →
B61: Terminal growth ↓ | D61: =F61-0.01 -> 0.077125 | E61: =F61-0.005 -> 0.082125 | F61: =$C$13 -> 0.087125 | G61: =F61+0.005 -> 0.092125 | H61: =F61+0.01 -> 0.097125
B62: =B64-0.01 -> 0.03 | D62: {=IFERROR((SUMPRODUCT($D$24:$M$24/(1+D$61)^$D$29:$M$29)+($M$24*(1+$B62)/(D$61-$B62))/(1+D$61)^$M$29-$C$48)/$C$50,"")} -> 549.21991 | E62: {=IFERROR((SUMPRODUCT($D$24:$M$24/(1+E$61)^$D$29:$M$29)+($M$24*(1+$B62)/(E$61-$B62))/(1+E$61)^$M$29-$C$48)/$C$50,"")} -> 486.94789 | F62: {=IFERROR((SUMPRODUCT($D$24:$M$24/(1+F$61)^$D$29:$M$29)+($M$24*(1+$B62)/(F$61-$B62))/(1+F$61)^$M$29-$C$48)/$C$50,"")} -> 435.66928 | G62: {=IFERROR((SUMPRODUCT($D$24:$M$24/(1+G$61)^$D$29:$M$29)+($M$24*(1+$B62)/(G$61-$B62))/(1+G$61)^$M$29-$C$48)/$C$50,"")} -> 392.72657 | H62: {=IFERROR((SUMPRODUCT($D$24:$M$24/(1+H$61)^$D$29:$M$29)+($M$24*(1+$B62)/(H$61-$B62))/(1+H$61)^$M$29-$C$48)/$C$50,"")} -> 356.25419
B63: =B64-0.005 -> 0.035 | D63: {=IFERROR((SUMPRODUCT($D$24:$M$24/(1+D$61)^$D$29:$M$29)+($M$24*(1+$B63)/(D$61-$B63))/(1+D$61)^$M$29-$C$48)/$C$50,"")} -> 600.7335 | E63: {=IFERROR((SUMPRODUCT($D$24:$M$24/(1+E$61)^$D$29:$M$29)+($M$24*(1+$B63)/(E$61-$B63))/(1+E$61)^$M$29-$C$48)/$C$50,"")} -> 526.83848 | F63: {=IFERROR((SUMPRODUCT($D$24:$M$24/(1+F$61)^$D$29:$M$29)+($M$24*(1+$B63)/(F$61-$B63))/(1+F$61)^$M$29-$C$48)/$C$50,"")} -> 467.20741 | G63: {=IFERROR((SUMPRODUCT($D$24:$M$24/(1+G$61)^$D$29:$M$29)+($M$24*(1+$B63)/(G$61-$B63))/(1+G$61)^$M$29-$C$48)/$C$50,"")} -> 418.0919 | H63: {=IFERROR((SUMPRODUCT($D$24:$M$24/(1+H$61)^$D$29:$M$29)+($M$24*(1+$B63)/(H$61-$B63))/(1+H$61)^$M$29-$C$48)/$C$50,"")} -> 376.95043
B64: =$C$27 -> 0.04 | D64: {=IFERROR((SUMPRODUCT($D$24:$M$24/(1+D$61)^$D$29:$M$29)+($M$24*(1+$B64)/(D$61-$B64))/(1+D$61)^$M$29-$C$48)/$C$50,"")} -> 666.12281 | E64: {=IFERROR((SUMPRODUCT($D$24:$M$24/(1+E$61)^$D$29:$M$29)+($M$24*(1+$B64)/(E$61-$B64))/(1+E$61)^$M$29-$C$48)/$C$50,"")} -> 576.19865 | F64: {=IFERROR((SUMPRODUCT($D$24:$M$24/(1+F$61)^$D$29:$M$29)+($M$24*(1+$B64)/(F$61-$B64))/(1+F$61)^$M$29-$C$48)/$C$50,"")} -> 505.43797 | G64: {=IFERROR((SUMPRODUCT($D$24:$M$24/(1+G$61)^$D$29:$M$29)+($M$24*(1+$B64)/(G$61-$B64))/(1+G$61)^$M$29-$C$48)/$C$50,"")} -> 448.32349 | H64: {=IFERROR((SUMPRODUCT($D$24:$M$24/(1+H$61)^$D$29:$M$29)+($M$24*(1+$B64)/(H$61-$B64))/(1+H$61)^$M$29-$C$48)/$C$50,"")} -> 401.26964
B65: =B64+0.005 -> 0.045 | D65: {=IFERROR((SUMPRODUCT($D$24:$M$24/(1+D$61)^$D$29:$M$29)+($M$24*(1+$B65)/(D$61-$B65))/(1+D$61)^$M$29-$C$48)/$C$50,"")} -> 751.86676 | E65: {=IFERROR((SUMPRODUCT($D$24:$M$24/(1+E$61)^$D$29:$M$29)+($M$24*(1+$B65)/(E$61-$B65))/(1+E$61)^$M$29-$C$48)/$C$50,"")} -> 638.85448 | F65: {=IFERROR((SUMPRODUCT($D$24:$M$24/(1+F$61)^$D$29:$M$29)+($M$24*(1+$B65)/(F$61-$B65))/(1+F$61)^$M$29-$C$48)/$C$50,"")} -> 552.74405 | G65: {=IFERROR((SUMPRODUCT($D$24:$M$24/(1+G$61)^$D$29:$M$29)+($M$24*(1+$B65)/(G$61-$B65))/(1+G$61)^$M$29-$C$48)/$C$50,"")} -> 484.97026 | H65: {=IFERROR((SUMPRODUCT($D$24:$M$24/(1+H$61)^$D$29:$M$29)+($M$24*(1+$B65)/(H$61-$B65))/(1+H$61)^$M$29-$C$48)/$C$50,"")} -> 430.25441
B66: =B64+0.01 -> 0.05 | D66: {=IFERROR((SUMPRODUCT($D$24:$M$24/(1+D$61)^$D$29:$M$29)+($M$24*(1+$B66)/(D$61-$B66))/(1+D$61)^$M$29-$C$48)/$C$50,"")} -> 869.22139 | E66: {=IFERROR((SUMPRODUCT($D$24:$M$24/(1+E$61)^$D$29:$M$29)+($M$24*(1+$B66)/(E$61-$B66))/(1+E$61)^$M$29-$C$48)/$C$50,"")} -> 721.01408 | F66: {=IFERROR((SUMPRODUCT($D$24:$M$24/(1+F$61)^$D$29:$M$29)+($M$24*(1+$B66)/(F$61-$B66))/(1+F$61)^$M$29-$C$48)/$C$50,"")} -> 612.7925 | G66: {=IFERROR((SUMPRODUCT($D$24:$M$24/(1+G$61)^$D$29:$M$29)+($M$24*(1+$B66)/(G$61-$B66))/(1+G$61)^$M$29-$C$48)/$C$50,"")} -> 530.31656 | H66: {=IFERROR((SUMPRODUCT($D$24:$M$24/(1+H$61)^$D$29:$M$29)+($M$24*(1+$B66)/(H$61-$B66))/(1+H$61)^$M$29-$C$48)/$C$50,"")} -> 465.38979
B69: 5. REVERSE DCF
B70: To solve for the market-implied path: Data ▸ What-If Analysis ▸ Goal Seek — set C51 to the current price (C52) by changing C27 (terminal growth) or the fade-period growth inputs (I26:M26).
B72: 6. MAUBOUSSIN EV / NOPAT — TWO-STAGE FRAMEWORK
B73: EV/NOPAT = 1/r + [g × (1 − r/ROIIC) / (r × (r − g))] × [1 − ((1+g)/(1+r))^N]
B74: Formula source: Mauboussin & Rappaport, "Expectations Investing" (2021); Counterpoint Global, "What Does a Price-Earnings Multiple Mean?" (2020).
B76: Input | C76: Value | D76: Rationale (S&P Global characteristics)
B77: r (Cost of capital / WACC) | C77: =$C$13 -> 0.087125 | D77: Linked from Section 1 WACC build
B78: g (NOPAT growth, Stage 1) | C78: 0.09 | D78: Model adjusted EBITA CAGR 2026–31E: mid / high-single-digit revenue growth with modest margin expansion and the M&A lever → ~8–9% NOPAT growth
B79: ROIIC (Return on incremental invested capital) | C79: 0.3 | D79: Benchmarks (S&P 500 index licensing, Platts price assessments) and ratings are franchise assets with very high incremental returns; reported ROIC is depressed by the $31bn IHS Markit goodwill, so incremental (not average) returns matter
B80: N (Years of value creation / CAP) | C80: 20 | D80: Regulatory-licensed ratings duopoly, embedded benchmarks and data networks give a long competitive-advantage period; risks are issuance cyclicality, passive-fee compression and AI-driven disruption of data / workflow products
B82: Calculation | C82: Value
B83: Steady-state component: 1 / r | C83: =1/C77 -> 11.477762
B84: Value-creation factor: 1 − r / ROIIC | C84: =1-C77/C79 -> 0.70958333
B85: Growth multiplier: g × (1 − r/ROIIC) / (r × (r − g)) | C85: =C78*C84/(C77*(C77-C78)) -> -254.95602
B86: Time decay: 1 − ((1+g)/(1+r))^N | C86: =1-((1+C78)/(1+C77))^C80 -> -0.054241959
B87: PVGO component (growth value) | C87: =C85*C86 -> 13.829314
B88: Mauboussin EV / NOPAT (steady-state + PVGO) | C88: =C83+C87 -> 25.307076
B90: VALUATION — Applied to FY2029E NOPAT | C90: USDm
B91: FY2029E Adj. EBITA less severance / acquisition / disposition / legal costs | C91: =Model!BZ260-Model!BZ262 -> 9427.6058
B92: Tax rate (from WACC build) | C92: =$C$10 -> 0.225
B93: FY2029E NOPAT | C93: =C91*(1-C92) -> 7306.3945
B94: × Mauboussin EV/NOPAT multiple | C94: =C88 -> 25.307076
B95: Implied Enterprise Value (FY2029E basis) | C95: =C93*C94 -> 184903.48
B96: Less: FY2028E year-end net debt + NCI (Model) | C96: =Model!BY482+Model!BY492 -> 18595.825
B97: Implied Equity Value | C97: =C95-C96 -> 166307.66
B98: Diluted shares FY2029E (m, Model) | C98: =Model!BZ489 -> 251.6976
B99: Implied share price FY2029 ($) | C99: =C97/C98 -> 660.7439
B101: Current share price ($) | C101: =C52 -> 415
B102: Implied upside / (downside) | C102: =C99/C101-1 -> 0.59215398
B104: MARKET-IMPLIED EV/NOPAT TODAY | C104: USDm
B105: Current market cap (spot × diluted shares) | C105: =C52*C50 -> 116841
B106: Plus: FY2026E year-end net debt + NCI | C106: =C48 -> 17453.897
B107: Implied Enterprise Value (today) | C107: =C105+C106 -> 134294.9
B108: SPGI market-implied EV/NOPAT (on FY2029E NOPAT) | C108: =C107/C93 -> 18.380461
B110: Multiple gap (Mauboussin − Market) | C110: =C88-C108 -> 6.9266151
B111: Implied re-rating headroom | C111: =C88/C108-1 -> 0.37684665

Sheet Charts
B2: S&P Global Inc. — Operating Performance (FY2012–FY2025) and Model Forecast (FY2026E–FY2031E)
B3: USDm · fiscal years ended 31 December · Linked to Model. Bars = contribution of Ratings and of the other divisions (Indices, Energy, Market Intelligence) to total revenue growth (pp); FY2022 includes the IHS Markit merger; FY2025+ excludes Mobility. Adjusted EBITDA = model definition (adjusted OP + depreciation); ROIC on adjusted EBITA.
C7: 2012 | D7: 2013 | E7: 2014 | F7: 2015 | G7: 2016 | H7: 2017 | I7: 2018 | J7: 2019 | K7: 2020 | L7: 2021 | M7: 2022 | N7: 2023 | O7: 2024 | P7: 2025 | Q7: 2026E | R7: 2027E | S7: 2028E | T7: 2029E | U7: 2030E | V7: 2031E
B8: Ratings contribution to growth (pp) | C8: =IFERROR(Model!E118+0,0) -> 0.067526555 | D8: =IFERROR(Model!J118+0,0) -> 0.053932584 | E8: =IFERROR(Model!O118+0,0) -> 0.037128205 | F8: =IFERROR(Model!T118+0,0) -> -0.0053454761 | G8: =IFERROR(Model!Y118+0,0) -> 0.020139281 | H8: =IFERROR(Model!AD118+0,0) -> 0.080021198 | I8: =IFERROR(Model!AI118+0,0) -> -0.017318159 | J8: =IFERROR(Model!AN118+0,0) -> 0.035634388 | K8: =IFERROR(Model!AS118+0,0) -> 0.074638006 | L8: =IFERROR(Model!AX118+0,0) -> 0.065976888 | M8: =IFERROR(Model!BC118+0,0) -> -0.12619019 | N8: =IFERROR(Model!BH118+0,0) -> 0.025221358 | O8: =IFERROR(Model!BM118+0,0) -> 0.083059934 | P8: =IFERROR(Model!BR118+0,0) -> 0.024915541 | Q8: =IFERROR(Model!BW118+0,0) -> 0.038217074 | R8: =IFERROR(Model!BX118+0,0) -> 0.017380728 | S8: =IFERROR(Model!BY118+0,0) -> 0.023026441 | T8: =IFERROR(Model!BZ118+0,0) -> 0.021254838 | U8: =IFERROR(Model!CA118+0,0) -> 0.019204916 | V8: =IFERROR(Model!CB118+0,0) -> 0.019015308
B9: Indices, Energy & MI contribution (pp) | C9: =IFERROR(Model!E119+0,0)+IFERROR(Model!E120+0,0)+IFERROR(Model!E121+0,0) -> 0.059433485 | D9: =IFERROR(Model!J119+0,0)+IFERROR(Model!J120+0,0)+IFERROR(Model!J121+0,0) -> 0.043146067 | E9: =IFERROR(Model!O119+0,0)+IFERROR(Model!O120+0,0)+IFERROR(Model!O121+0,0) -> 0.001025641 | F9: =IFERROR(Model!T119+0,0)+IFERROR(Model!T120+0,0)+IFERROR(Model!T121+0,0) -> 0.057612354 | G9: =IFERROR(Model!Y119+0,0)+IFERROR(Model!Y120+0,0)+IFERROR(Model!Y121+0,0) -> 0.0069640504 | H9: =IFERROR(Model!AD119+0,0)+IFERROR(Model!AD120+0,0)+IFERROR(Model!AD121+0,0) -> 0.030913266 | I9: =IFERROR(Model!AI119+0,0)+IFERROR(Model!AI120+0,0)+IFERROR(Model!AI121+0,0) -> 0.049480455 | J9: =IFERROR(Model!AN119+0,0)+IFERROR(Model!AN120+0,0)+IFERROR(Model!AN121+0,0) -> 0.037711729 | K9: =IFERROR(Model!AS119+0,0)+IFERROR(Model!AS120+0,0)+IFERROR(Model!AS121+0,0) -> 0.037617555 | L9: =IFERROR(Model!AX119+0,0)+IFERROR(Model!AX120+0,0)+IFERROR(Model!AX121+0,0) -> 0.050120935 | M9: =IFERROR(Model!BC119+0,0)+IFERROR(Model!BC120+0,0)+IFERROR(Model!BC121+0,0) -> 0.29998795 | N9: =IFERROR(Model!BH119+0,0)+IFERROR(Model!BH120+0,0)+IFERROR(Model!BH121+0,0) -> 0.07959932 | O9: =IFERROR(Model!BM119+0,0)+IFERROR(Model!BM120+0,0)+IFERROR(Model!BM121+0,0) -> 0.055213251 | P9: =IFERROR(Model!BR119+0,0)+IFERROR(Model!BR120+0,0)+IFERROR(Model!BR121+0,0) -> 0.045748874 | Q9: =IFERROR(Model!BW119+0,0)+IFERROR(Model!BW120+0,0)+IFERROR(Model!BW121+0,0) -> 0.032076422 | R9: =IFERROR(Model!BX119+0,0)+IFERROR(Model!BX120+0,0)+IFERROR(Model!BX121+0,0) -> 0.043291708 | S9: =IFERROR(Model!BY119+0,0)+IFERROR(Model!BY120+0,0)+IFERROR(Model!BY121+0,0) -> 0.044266283 | T9: =IFERROR(Model!BZ119+0,0)+IFERROR(Model!BZ120+0,0)+IFERROR(Model!BZ121+0,0) -> 0.043959146 | U9: =IFERROR(Model!CA119+0,0)+IFERROR(Model!CA120+0,0)+IFERROR(Model!CA121+0,0) -> 0.042930201 | V9: =IFERROR(Model!CB119+0,0)+IFERROR(Model!CB120+0,0)+IFERROR(Model!CB121+0,0) -> 0.042963125
C11: =C7 -> 2012 | D11: =D7 -> 2013 | E11: =E7 -> 2014 | F11: =F7 -> 2015 | G11: =G7 -> 2016 | H11: =H7 -> 2017 | I11: =I7 -> 2018 | J11: =J7 -> 2019 | ... V11: =V7 -> 2031E
B12: Adjusted EBITDA | C12: =Model!E256 -> 1459 | D12: =Model!J256 -> 1688 | E12: =Model!O256 -> 1901 | F12: =Model!T256 -> 2143 | G12: =Model!Y256 -> 2516 | H12: =Model!AD256 -> 2939 | I12: =Model!AI256 -> 3136 | J12: =Model!AN256 -> 3442 | K12: =Model!AS256 -> 4050 | L12: =Model!AX256 -> 4663 | M12: =Model!BC256 -> 5240 | N12: =Model!BH256 -> 5833 | O12: =Model!BM256 -> 7054 | P12: =Model!BR256 -> 7070 | Q12: =Model!BW256 -> 7638.2824 | R12: =Model!BX256 -> 8309.2359 | S12: =Model!BY256 -> 8971.2164 | T12: =Model!BZ256 -> 9618.8125 | U12: =Model!CA256 -> 10291.886 | V12: =Model!CB256 -> 10979.397
B13: Operating profit (GAAP) | C13: =Model!E196 -> 1211 | D13: =Model!J196 -> 1405 | E13: =Model!O196 -> 113 | F13: =Model!T196 -> 1917 | G13: =Model!Y196 -> 3369 | H13: =Model!AD196 -> 2610 | I13: =Model!AI196 -> 2790 | J13: =Model!AN196 -> 3226 | K13: =Model!AS196 -> 3617 | L13: =Model!AX196 -> 4221 | M13: =Model!BC196 -> 4944 | N13: =Model!BH196 -> 4020 | O13: =Model!BM196 -> 5580 | P13: =Model!BR196 -> 6140 | Q13: =Model!BW196 -> 7057.2824 | R13: =Model!BX196 -> 7338.9929 | S13: =Model!BY196 -> 7998.5821 | T13: =Model!BZ196 -> 8651.4391 | U13: =Model!CA196 -> 9329.5785 | V13: =Model!CB196 -> 10020.561
B14: Adj. EBITDA Margin % | C14: =Model!E304 -> 0.32786517 | D14: =Model!J304 -> 0.34625641 | E14: =Model!O304 -> 0.37636112 | F14: =Model!T304 -> 0.40335027 | G14: =Model!Y304 -> 0.44444444 | H14: =Model!AD304 -> 0.48474353 | I14: =Model!AI304 -> 0.50111857 | J14: =Model!AN304 -> 0.51380803 | K14: =Model!AS304 -> 0.54420855 | L14: =Model!AX304 -> 0.56201037 | M14: =Model!BC304 -> 0.46865218 | N14: =Model!BH304 -> 0.46675202 | O14: =Model!BM304 -> 0.49648086 | P14: =Model!BR304 -> 0.52027375 | Q14: =Model!BW304 -> 0.52581201 | R14: =Model!BX304 -> 0.53864427 | S14: =Model!BY304 -> 0.5431576 | T14: =Model!BZ304 -> 0.54494919 | U14: =Model!CA304 -> 0.54716983 | V14: =Model!CB304 -> 0.54781934
B15: Operating Margin % | C15: =Model!E305 -> 0.27213483 | D15: =Model!J305 -> 0.28820513 | E15: =Model!O305 -> 0.022371808 | F15: =Model!T305 -> 0.3608131 | G15: =Model!Y305 -> 0.59512454 | H15: =Model!AD305 -> 0.43047996 | I15: =Model!AI305 -> 0.44582934 | J15: =Model!AN305 -> 0.48156441 | K15: =Model!AS305 -> 0.48602526 | L15: =Model!AX305 -> 0.5087381 | M15: =Model!BC305 -> 0.4421787 | N15: =Model!BH305 -> 0.3216772 | O15: =Model!BM305 -> 0.39273649 | P15: =Model!BR305 -> 0.45183604 | Q15: =Model!BW305 -> 0.48581653 | R15: =Model!BX305 -> 0.4757485 | S15: =Model!BY305 -> 0.48426997 | T15: =Model!BZ305 -> 0.49014311 | U15: =Model!CA305 -> 0.49600858 | V15: =Model!CB305 -> 0.49997802
C17: =C7 -> 2012 | D17: =D7 -> 2013 | E17: =E7 -> 2014 | F17: =F7 -> 2015 | G17: =G7 -> 2016 | H17: =H7 -> 2017 | I17: =I7 -> 2018 | J17: =J7 -> 2019 | ... V17: =V7 -> 2031E
B18: ROIC | C18: =IFERROR(Model!E465+0,NA()) -> 0.34707245 | D18: =IFERROR(Model!J465+0,NA()) -> 0.68420792 | E18: =IFERROR(Model!O465+0,NA()) -> -0.21665383 | F18: =IFERROR(Model!T465+0,NA()) -> 0.40439539 | G18: =IFERROR(Model!Y465+0,NA()) -> 0.54931308 | H18: =IFERROR(Model!AD465+0,NA()) -> 0.67453965 | I18: =IFERROR(Model!AI465+0,NA()) -> 0.57250069 | J18: =IFERROR(Model!AN465+0,NA()) -> 0.67033181 | K18: =IFERROR(Model!AS465+0,NA()) -> 0.90686179 | L18: =IFERROR(Model!AX465+0,NA()) -> 1.0746325 | M18: =IFERROR(Model!BC465+0,NA()) -> 0.067222917 | N18: =IFERROR(Model!BH465+0,NA()) -> 0.086006058 | O18: =IFERROR(Model!BM465+0,NA()) -> 0.11030173 | P18: =IFERROR(Model!BR465+0,NA()) -> 0.10761897 | Q18: =IFERROR(Model!BW465+0,NA()) -> 0.16235083 | R18: =IFERROR(Model!BX465+0,NA()) -> 0.18036487 | S18: =IFERROR(Model!BY465+0,NA()) -> 0.19645952 | T18: =IFERROR(Model!BZ465+0,NA()) -> 0.212428 | U18: =IFERROR(Model!CA465+0,NA()) -> 0.22912833 | V18: =IFERROR(Model!CB465+0,NA()) -> 0.24638904
B19: ROE (RONTA n/m: negative net tangible assets) | C19: =IFERROR(Model!E480+0,NA()) -> 0.56975228 | D19: =IFERROR(Model!J480+0,NA()) -> 1.057648 | E19: =IFERROR(Model!O480+0,NA()) -> -0.23565574 | F19: =IFERROR(Model!T480+0,NA()) -> 5.9587629 | G19: =IFERROR(Model!Y480+0,NA()) -> 3.24 | H19: =IFERROR(Model!AD480+0,NA()) -> 2.1040788 | I19: =IFERROR(Model!AI480+0,NA()) -> 3.1178344 | J19: =IFERROR(Model!AN480+0,NA()) -> 4.4321503 | K19: =IFERROR(Model!AS480+0,NA()) -> 4.5952849 | L19: =IFERROR(Model!AX480+0,NA()) -> 1.488189 | M19: =IFERROR(Model!BC480+0,NA()) -> 0.089260196 | N19: =IFERROR(Model!BH480+0,NA()) -> 0.076783626 | O19: =IFERROR(Model!BM480+0,NA()) -> 0.11616756 | P19: =IFERROR(Model!BR480+0,NA()) -> 0.14363736 | Q19: =IFERROR(Model!BW480+0,NA()) -> 0.27462507 | R19: =IFERROR(Model!BX480+0,NA()) -> 0.28289916 | S19: =IFERROR(Model!BY480+0,NA()) -> 0.33409368 | T19: =IFERROR(Model!BZ480+0,NA()) -> 0.39007873 | U19: =IFERROR(Model!CA480+0,NA()) -> 0.45931668 | V19: =IFERROR(Model!CB480+0,NA()) -> 0.54488411
B20: Adj. EBITDA margin % | C20: =IFERROR(Model!E304+0,NA()) -> 0.32786517 | D20: =IFERROR(Model!J304+0,NA()) -> 0.34625641 | E20: =IFERROR(Model!O304+0,NA()) -> 0.37636112 | F20: =IFERROR(Model!T304+0,NA()) -> 0.40335027 | G20: =IFERROR(Model!Y304+0,NA()) -> 0.44444444 | H20: =IFERROR(Model!AD304+0,NA()) -> 0.48474353 | I20: =IFERROR(Model!AI304+0,NA()) -> 0.50111857 | J20: =IFERROR(Model!AN304+0,NA()) -> 0.51380803 | K20: =IFERROR(Model!AS304+0,NA()) -> 0.54420855 | L20: =IFERROR(Model!AX304+0,NA()) -> 0.56201037 | M20: =IFERROR(Model!BC304+0,NA()) -> 0.46865218 | N20: =IFERROR(Model!BH304+0,NA()) -> 0.46675202 | O20: =IFERROR(Model!BM304+0,NA()) -> 0.49648086 | P20: =IFERROR(Model!BR304+0,NA()) -> 0.52027375 | Q20: =IFERROR(Model!BW304+0,NA()) -> 0.52581201 | R20: =IFERROR(Model!BX304+0,NA()) -> 0.53864427 | S20: =IFERROR(Model!BY304+0,NA()) -> 0.5431576 | T20: =IFERROR(Model!BZ304+0,NA()) -> 0.54494919 | U20: =IFERROR(Model!CA304+0,NA()) -> 0.54716983 | V20: =IFERROR(Model!CB304+0,NA()) -> 0.54781934
B21: FCF margin % | C21: =IFERROR(Model!E343+0,NA()) -> 0.14067416 | D21: =IFERROR(Model!J343+0,NA()) -> 0.128 | E21: =IFERROR(Model!O343+0,NA()) -> 0.20451396 | F21: =IFERROR(Model!T343+0,NA()) -> -0.0090344438 | G21: =IFERROR(Model!Y343+0,NA()) -> 0.21780604 | H21: =IFERROR(Model!AD343+0,NA()) -> 0.2939139 | I21: =IFERROR(Model!AI343+0,NA()) -> 0.28715244 | J21: =IFERROR(Model!AN343+0,NA()) -> 0.375877 | K21: =IFERROR(Model!AS343+0,NA()) -> 0.44302607 | L21: =IFERROR(Model!AX343+0,NA()) -> 0.40207304 | M21: =IFERROR(Model!BC343+0,NA()) -> 0.20069761 | N21: =IFERROR(Model!BH343+0,NA()) -> 0.26302313 | O21: =IFERROR(Model!BM343+0,NA()) -> 0.37148086 | P21: =IFERROR(Model!BR343+0,NA()) -> 0.37787917 | Q21: =IFERROR(Model!BW343+0,NA()) -> 0.35679374 | R21: =IFERROR(Model!BX343+0,NA()) -> 0.37899965 | S21: =IFERROR(Model!BY343+0,NA()) -> 0.3848145 | T21: =IFERROR(Model!BZ343+0,NA()) -> 0.38369072 | U21: =IFERROR(Model!CA343+0,NA()) -> 0.38353123 | V21: =IFERROR(Model!CB343+0,NA()) -> 0.38336122
