Workbook

Sheet Model
AU1: SCENARIO SWITCH ▼ (Bull / Base / Bear) — drives all scenario-linked forecast drivers
B2: STERIS plc (NYSE: STE) — 3-Statement Financial Model | AU2: Base
B3: US GAAP as reported · USD millions (per-share data in USD; shares in millions) · Fiscal years ended 31 March (2027 = Apr-2026 – Mar-2027) · Source: STERIS Forms 10-K / 10-Q and Form 8-K earnings releases (Ex. 99.1), SEC EDGAR (STERIS Corp CIK 815065 to FY2015; STERIS plc (UK) CIK 1624899 FY2016–19; STERIS plc (Ireland) CIK 1757898 from FY2019); investor-relations releases at steris-ir.com are the same documents as filed on EDGAR
B4: Basis notes: FY2012–FY2022 as originally reported; FY2023 onward continuing operations (Dental, acquired with Cantel Jun-2021, sold Sep-2024, recast in the Q4 FY24 and FY25 releases) — originally reported adjusted EPS rebuilt and checked in memo rows. Segments: Healthcare, Applied Sterilization Technologies (AST), Life Sciences (+ Dental FY2022). Acquisitions: Synergy Health Nov-15, Cantel Jun-21, BD surgical instrumentation Aug-23. Q2/27E–Q4/27E calibrated to FY27 revenue-growth and adjusted-EPS guidance.
AW5: Forecast | AX5: Historical | AY5: Historical | AZ5: Historical
B6: (USDm) | C6: 2012 | D6: 2013 | E6: 2014 | F6: 2015 | G6: 2016 | H6: 2017 | I6: 2018 | J6: 2019 | K6: 2020 | L6: 2021 | M6: Q1/22 | N6: Q2/22 | O6: Q3/22 | P6: Q4/22 | Q6: 2022 | R6: Q1/23 | S6: Q2/23 | T6: Q3/23 | U6: Q4/23 | V6: 2023 | W6: Q1/24 | X6: Q2/24 | Y6: Q3/24 | Z6: Q4/24 | AA6: 2024 | AB6: Q1/25 | AC6: Q2/25 | AD6: Q3/25 | AE6: Q4/25 | AF6: 2025 | AG6: Q1/26 | AH6: Q2/26 | AI6: Q3/26 | AJ6: Q4/26 | AK6: 2026 | AL6: Q1/27 | AM6: Q2/27E | AN6: Q3/27E | AO6: Q4/27E | AP6: 2027E | AQ6: 2028E | AR6: 2029E | AS6: 2030E | AT6: 2031E | AU6: Modelling Notes | AW6: 5Y CAGR | AX6: 5Y CAGR | AY6: 10Y CAGR | AZ6: 14Y CAGR
AW7: 26-'31 | AX7: 21-'26 | AY7: 16-'26 | AZ7: 12-'26
B8: SEGMENT P&L — HEALTHCARE · AST · LIFE SCIENCES (revenue by type × segment operating margin) | AU8: SEGMENT BUILD — modelling logic (capital / consumables / service revenue by segment → segment operating income at the segment margin → + corporate = adjusted operating income → GAAP P&L)
BC9: SCENARIO INPUT TABLE — driver assumptions per Bull / Base / Bear | BD9: Bull | BE9: Base | BF9: Bear | BG9: Bull / Bear = Base + Δ (Δ inputs on each block header). Outlook block = high / mid / low end of the FY27 guidance ranges.
B10: Healthcare (infection prevention consumables, sterilizers & washers, surgical tables / lights / OR integration, endoscopy (Cantel), repair & instrument services) | AU10: HEALTHCARE — modelling logic
B11: Capital equipment revenue | C11: 545.596 | D11: 521.806 | E11: 515.38 | F11: 517.007 | G11: 524.992 | H11: 547.5425 | I11: 527.402 | J11: 568.811 | K11: 592.436 | L11: 588.864 | M11: 150.89 | N11: 202.405 | O11: 217.214 | P11: 211.996 | Q11: 782.505 | R11: 179.134 | S11: 212.484 | T11: 227.226 | U11: 277.746 | V11: 896.59 | W11: 238.099 | X11: 254.905 | Y11: 266.838 | Z11: 331.695 | AA11: 1091.537 | AB11: 214.639 | AC11: 249.732 | AD11: 254.804 | AE11: 318.025 | AF11: 1037.2 | AG11: 227.3 | AH11: 259.4 | AI11: 272.1 | AJ11: 337.1 | AK11: 1095.9 | AL11: 230.5 | AM11: =AH11*(1+AM12) | AN11: =AI11*(1+AN12) | AO11: =AJ11*(1+AO12) | AP11: =SUM(AL11,AM11,AN11,AO11) | AQ11: =AP11*(1+AQ12) | AR11: =AQ11*(1+AR12) | AS11: =AR11*(1+AS12) | AT11: =AS11*(1+AT12) | AU11: Revenue by type as published (release "Unaudited Supplemental Financial Data"). Q2–Q4/27E: prior-year quarter × (1 + growth). 2028E+: prior year × (1 + scenario lever). | AW11: =IFERROR((AT11/AK11)^(1/5)-1,"n/m") | AX11: =IFERROR((AK11/L11)^(1/5)-1,"n/m") | AY11: =IFERROR((AK11/G11)^(1/10)-1,"n/m") | AZ11: =IFERROR((AK11/C11)^(1/14)-1,"n/m") | BC11: FY27 outlook — Q4 FY26 release (11-May-26), reiterated 5-Aug-26 | BD11: High | BE11: Mid | BF11: Low | BG11: As-reported revenue growth 7–8% (incl. Healthcare tuck-ins, slightly favourable FX); constant-currency organic 6–7%; adjusted EPS $11.10–11.30 (+9–11% vs $10.17); ~25% tax rate; capex ~$450m (raised from $375m in Aug-26); free cash flow ~$800m (from $850m).
B12: y/y % | D12: =IF(AND(ISNUMBER(D11),ISNUMBER(C11)),IFERROR(D11/C11-1,""),"") | E12: =IF(AND(ISNUMBER(E11),ISNUMBER(D11)),IFERROR(E11/D11-1,""),"") | F12: =IF(AND(ISNUMBER(F11),ISNUMBER(E11)),IFERROR(F11/E11-1,""),"") | G12: =IF(AND(ISNUMBER(G11),ISNUMBER(F11)),IFERROR(G11/F11-1,""),"") | H12: =IF(AND(ISNUMBER(H11),ISNUMBER(G11)),IFERROR(H11/G11-1,""),"") | I12: =IF(AND(ISNUMBER(I11),ISNUMBER(H11)),IFERROR(I11/H11-1,""),"") | J12: =IF(AND(ISNUMBER(J11),ISNUMBER(I11)),IFERROR(J11/I11-1,""),"") | K12: =IF(AND(ISNUMBER(K11),ISNUMBER(J11)),IFERROR(K11/J11-1,""),"") | L12: =IF(AND(ISNUMBER(L11),ISNUMBER(K11)),IFERROR(L11/K11-1,""),"") | Q12: =IF(AND(ISNUMBER(Q11),ISNUMBER(L11)),IFERROR(Q11/L11-1,""),"") | R12: =IF(AND(ISNUMBER(R11),ISNUMBER(M11)),IFERROR(R11/M11-1,""),"") | S12: =IF(AND(ISNUMBER(S11),ISNUMBER(N11)),IFERROR(S11/N11-1,""),"") | T12: =IF(AND(ISNUMBER(T11),ISNUMBER(O11)),IFERROR(T11/O11-1,""),"") | U12: =IF(AND(ISNUMBER(U11),ISNUMBER(P11)),IFERROR(U11/P11-1,""),"") | V12: =IF(AND(ISNUMBER(V11),ISNUMBER(Q11)),IFERROR(V11/Q11-1,""),"") | W12: =IF(AND(ISNUMBER(W11),ISNUMBER(R11)),IFERROR(W11/R11-1,""),"") | X12: =IF(AND(ISNUMBER(X11),ISNUMBER(S11)),IFERROR(X11/S11-1,""),"") | ... AL12: =IF(AND(ISNUMBER(AL11),ISNUMBER(AG11)),IFERROR(AL11/AG11-1,""),"") | AM12: =AM13+$AM$127 | AN12: =AN13+$AM$127 | AO12: =AO13+$AM$127 | AP12: =IF(AND(ISNUMBER(AP11),ISNUMBER(AK11)),IFERROR(AP11/AK11-1,""),"") | AQ12: =CHOOSE(MATCH($AU$2,{"Bull","Base","Bear"},0),$BD$30,$BE$30,$BF$30) | AR12: =CHOOSE(MATCH($AU$2,{"Bull","Base","Bear"},0),$BD$31,$BE$31,$BF$31) | AS12: =CHOOSE(MATCH($AU$2,{"Bull","Base","Bear"},0),$BD$32,$BE$32,$BF$32) | AT12: =CHOOSE(MATCH($AU$2,{"Bull","Base","Bear"},0),$BD$33,$BE$33,$BF$33) | AU12: Q2–Q4/27E: Q1/27 y/y growth of the line + revenue-outlook calibration Δ (Group block). 2028E–2031E: scenario lever (Bull/Base/Bear table →). | BC12: FY27 revenue growth, as reported | BD12: 0.08 | BE12: 0.075 | BF12: 0.07 | BG12: Guided 7–8%. Drives the Q2–Q4/27E revenue calibration.
B13: Q2–Q4/27E growth before revenue calibration (Q1/27 y/y) | AM13: =IFERROR(AL11/AG11-1,0) | AN13: =IFERROR(AL11/AG11-1,0) | AO13: =IFERROR(AL11/AG11-1,0) | BC13: FY27 constant-currency organic growth — memo | BD13: 0.07 | BE13: 0.065 | BF13: 0.06 | BG13: Guided 6–7% (memo; compare the growth-bridge row).
B14: Consumables revenue | C14: 229.504 | D14: 278.15 | E14: 325.703 | F14: 359.49 | G14: 381.477 | H14: 402.50063 | I14: 412.495 | J14: 414.969 | K14: 454.518 | L14: 510.946 | M14: 206.692 | N14: 270.089 | O14: 273.75 | P14: 254.074 | Q14: 1004.605 | R14: 252.032 | S14: 246.05 | T14: 259.81 | U14: 292.424 | V14: 1050.316 | W14: 280.281 | X14: 306.025 | Y14: 329.435 | Z14: 332.683 | AA14: 1248.424 | AB14: 343.354 | AC14: 341.707 | AD14: 358.233 | AE14: 352.737 | AF14: 1396.031 | AG14: 358.9 | AH14: 374.2 | AI14: 387.1 | AJ14: 376.4 | AK14: 1496.6 | AL14: 391.9 | AM14: =AH14*(1+AM15) | AN14: =AI14*(1+AN15) | AO14: =AJ14*(1+AO15) | AP14: =SUM(AL14,AM14,AN14,AO14) | AQ14: =AP14*(1+AQ15) | AR14: =AQ14*(1+AR15) | AS14: =AR14*(1+AS15) | AT14: =AS14*(1+AT15) | AW14: =IFERROR((AT14/AK14)^(1/5)-1,"n/m") | AX14: =IFERROR((AK14/L14)^(1/5)-1,"n/m") | AY14: =IFERROR((AK14/G14)^(1/10)-1,"n/m") | AZ14: =IFERROR((AK14/C14)^(1/14)-1,"n/m") | BC14: FY27 adjusted EPS ($) | BD14: 11.3 | BE14: 11.2 | BF14: 11.1 | BG14: Guided $11.10–11.30. Drives the Q2–Q4/27E segment-margin calibration.
B15: y/y % | D15: =IF(AND(ISNUMBER(D14),ISNUMBER(C14)),IFERROR(D14/C14-1,""),"") | E15: =IF(AND(ISNUMBER(E14),ISNUMBER(D14)),IFERROR(E14/D14-1,""),"") | F15: =IF(AND(ISNUMBER(F14),ISNUMBER(E14)),IFERROR(F14/E14-1,""),"") | G15: =IF(AND(ISNUMBER(G14),ISNUMBER(F14)),IFERROR(G14/F14-1,""),"") | H15: =IF(AND(ISNUMBER(H14),ISNUMBER(G14)),IFERROR(H14/G14-1,""),"") | I15: =IF(AND(ISNUMBER(I14),ISNUMBER(H14)),IFERROR(I14/H14-1,""),"") | J15: =IF(AND(ISNUMBER(J14),ISNUMBER(I14)),IFERROR(J14/I14-1,""),"") | K15: =IF(AND(ISNUMBER(K14),ISNUMBER(J14)),IFERROR(K14/J14-1,""),"") | L15: =IF(AND(ISNUMBER(L14),ISNUMBER(K14)),IFERROR(L14/K14-1,""),"") | Q15: =IF(AND(ISNUMBER(Q14),ISNUMBER(L14)),IFERROR(Q14/L14-1,""),"") | R15: =IF(AND(ISNUMBER(R14),ISNUMBER(M14)),IFERROR(R14/M14-1,""),"") | S15: =IF(AND(ISNUMBER(S14),ISNUMBER(N14)),IFERROR(S14/N14-1,""),"") | T15: =IF(AND(ISNUMBER(T14),ISNUMBER(O14)),IFERROR(T14/O14-1,""),"") | U15: =IF(AND(ISNUMBER(U14),ISNUMBER(P14)),IFERROR(U14/P14-1,""),"") | V15: =IF(AND(ISNUMBER(V14),ISNUMBER(Q14)),IFERROR(V14/Q14-1,""),"") | W15: =IF(AND(ISNUMBER(W14),ISNUMBER(R14)),IFERROR(W14/R14-1,""),"") | X15: =IF(AND(ISNUMBER(X14),ISNUMBER(S14)),IFERROR(X14/S14-1,""),"") | ... AL15: =IF(AND(ISNUMBER(AL14),ISNUMBER(AG14)),IFERROR(AL14/AG14-1,""),"") | AM15: =AM16+$AM$127 | AN15: =AN16+$AM$127 | AO15: =AO16+$AM$127 | AP15: =IF(AND(ISNUMBER(AP14),ISNUMBER(AK14)),IFERROR(AP14/AK14-1,""),"") | AQ15: =CHOOSE(MATCH($AU$2,{"Bull","Base","Bear"},0),$BD$35,$BE$35,$BF$35) | AR15: =CHOOSE(MATCH($AU$2,{"Bull","Base","Bear"},0),$BD$36,$BE$36,$BF$36) | AS15: =CHOOSE(MATCH($AU$2,{"Bull","Base","Bear"},0),$BD$37,$BE$37,$BF$37) | AT15: =CHOOSE(MATCH($AU$2,{"Bull","Base","Bear"},0),$BD$38,$BE$38,$BF$38) | BC15: FY27 GAAP diluted EPS, continuing ($) — memo | BD15: 9.12 | BE15: 9.02 | BF15: 8.92 | BG15: Guided $8.92–9.12 (amortization $2.08, acquisition $0.01, restructuring $0.07, other $0.02 per share); memo, not forced.
B16: Q2–Q4/27E growth before revenue calibration (Q1/27 y/y) | AM16: =IFERROR(AL14/AG14-1,0) | AN16: =IFERROR(AL14/AG14-1,0) | AO16: =IFERROR(AL14/AG14-1,0) | BC16: Q2–Q4/27E share repurchases ($m) | BD16: 400 | BE16: 300 | BF16: 200 | BG16: Q1/27 $115.5m; $900m left on the $1.0bn May-2026 authorization.
B17: Service revenue | C17: 238.002 | D17: 274.834 | E17: 338.968 | F17: 515.377 | G17: 723.549 | H17: 871.00987 | I17: 805.222 | J17: 864.705 | K17: 939.855 | L17: 854.245 | M17: 245.235 | N17: 271.64 | O17: 268.711 | P17: 272.771 | Q17: 1058.357 | R17: 267.36 | S17: 274.279 | T17: 282.108 | U17: 314.478 | V17: 1138.225 | W17: 300.494 | X17: 309.126 | Y17: 319.954 | Z17: 343.484 | AA17: 1273.058 | AB17: 343.228 | AC17: 352.791 | AD17: 363.007 | AE17: 386.414 | AF17: 1445.44 | AG17: 388.5 | AH17: 400.1 | AI17: 404.7 | AJ17: 422.8 | AK17: 1616 | AL17: 425.9 | AM17: =AH17*(1+AM18) | AN17: =AI17*(1+AN18) | AO17: =AJ17*(1+AO18) | AP17: =SUM(AL17,AM17,AN17,AO17) | AQ17: =AP17*(1+AQ18) | AR17: =AQ17*(1+AR18) | AS17: =AR17*(1+AS18) | AT17: =AS17*(1+AT18) | AW17: =IFERROR((AT17/AK17)^(1/5)-1,"n/m") | AX17: =IFERROR((AK17/L17)^(1/5)-1,"n/m") | AY17: =IFERROR((AK17/G17)^(1/10)-1,"n/m") | AZ17: =IFERROR((AK17/C17)^(1/14)-1,"n/m")
B18: y/y % | D18: =IF(AND(ISNUMBER(D17),ISNUMBER(C17)),IFERROR(D17/C17-1,""),"") | E18: =IF(AND(ISNUMBER(E17),ISNUMBER(D17)),IFERROR(E17/D17-1,""),"") | F18: =IF(AND(ISNUMBER(F17),ISNUMBER(E17)),IFERROR(F17/E17-1,""),"") | G18: =IF(AND(ISNUMBER(G17),ISNUMBER(F17)),IFERROR(G17/F17-1,""),"") | H18: =IF(AND(ISNUMBER(H17),ISNUMBER(G17)),IFERROR(H17/G17-1,""),"") | I18: =IF(AND(ISNUMBER(I17),ISNUMBER(H17)),IFERROR(I17/H17-1,""),"") | J18: =IF(AND(ISNUMBER(J17),ISNUMBER(I17)),IFERROR(J17/I17-1,""),"") | K18: =IF(AND(ISNUMBER(K17),ISNUMBER(J17)),IFERROR(K17/J17-1,""),"") | L18: =IF(AND(ISNUMBER(L17),ISNUMBER(K17)),IFERROR(L17/K17-1,""),"") | Q18: =IF(AND(ISNUMBER(Q17),ISNUMBER(L17)),IFERROR(Q17/L17-1,""),"") | R18: =IF(AND(ISNUMBER(R17),ISNUMBER(M17)),IFERROR(R17/M17-1,""),"") | S18: =IF(AND(ISNUMBER(S17),ISNUMBER(N17)),IFERROR(S17/N17-1,""),"") | T18: =IF(AND(ISNUMBER(T17),ISNUMBER(O17)),IFERROR(T17/O17-1,""),"") | U18: =IF(AND(ISNUMBER(U17),ISNUMBER(P17)),IFERROR(U17/P17-1,""),"") | V18: =IF(AND(ISNUMBER(V17),ISNUMBER(Q17)),IFERROR(V17/Q17-1,""),"") | W18: =IF(AND(ISNUMBER(W17),ISNUMBER(R17)),IFERROR(W17/R17-1,""),"") | X18: =IF(AND(ISNUMBER(X17),ISNUMBER(S17)),IFERROR(X17/S17-1,""),"") | ... AL18: =IF(AND(ISNUMBER(AL17),ISNUMBER(AG17)),IFERROR(AL17/AG17-1,""),"") | AM18: =AM19+$AM$127 | AN18: =AN19+$AM$127 | AO18: =AO19+$AM$127 | AP18: =IF(AND(ISNUMBER(AP17),ISNUMBER(AK17)),IFERROR(AP17/AK17-1,""),"") | AQ18: =CHOOSE(MATCH($AU$2,{"Bull","Base","Bear"},0),$BD$40,$BE$40,$BF$40) | AR18: =CHOOSE(MATCH($AU$2,{"Bull","Base","Bear"},0),$BD$41,$BE$41,$BF$41) | AS18: =CHOOSE(MATCH($AU$2,{"Bull","Base","Bear"},0),$BD$42,$BE$42,$BF$42) | AT18: =CHOOSE(MATCH($AU$2,{"Bull","Base","Bear"},0),$BD$43,$BE$43,$BF$43) | BC18: FY27 point estimates (all cases)
B19: Q2–Q4/27E growth before revenue calibration (Q1/27 y/y) | AM19: =IFERROR(AL17/AG17-1,0) | AN19: =IFERROR(AL17/AG17-1,0) | AO19: =IFERROR(AL17/AG17-1,0) | BC19: Interest expense ($m) | BE19: 63 | BG19: Not guided; FY26 $60.7m, Q1/27 $15.8m; Feb-2027 private-placement maturity refinanced on the revolver.
B20: Healthcare — revenue | C20: =IF(ISNUMBER(C11),C11+C14+C17,"") | D20: =IF(ISNUMBER(D11),D11+D14+D17,"") | E20: =IF(ISNUMBER(E11),E11+E14+E17,"") | F20: =IF(ISNUMBER(F11),F11+F14+F17,"") | G20: =IF(ISNUMBER(G11),G11+G14+G17,"") | H20: =IF(ISNUMBER(H11),H11+H14+H17,"") | I20: =IF(ISNUMBER(I11),I11+I14+I17,"") | J20: =IF(ISNUMBER(J11),J11+J14+J17,"") | ... AT20: =IF(ISNUMBER(AT11),AT11+AT14+AT17,"") | AW20: =IFERROR((AT20/AK20)^(1/5)-1,"n/m") | AX20: =IFERROR((AK20/L20)^(1/5)-1,"n/m") | AY20: =IFERROR((AK20/G20)^(1/10)-1,"n/m") | AZ20: =IFERROR((AK20/C20)^(1/14)-1,"n/m") | BC20: Other non-operating (income) expense, net ($m) | BE20: -10 | BG20: Interest & miscellaneous income (Q1/27 −$3.1m) net of other items.
B21: Revenue y/y % | D21: =IF(AND(ISNUMBER(D20),ISNUMBER(C20)),IFERROR(D20/C20-1,""),"") | E21: =IF(AND(ISNUMBER(E20),ISNUMBER(D20)),IFERROR(E20/D20-1,""),"") | F21: =IF(AND(ISNUMBER(F20),ISNUMBER(E20)),IFERROR(F20/E20-1,""),"") | G21: =IF(AND(ISNUMBER(G20),ISNUMBER(F20)),IFERROR(G20/F20-1,""),"") | H21: =IF(AND(ISNUMBER(H20),ISNUMBER(G20)),IFERROR(H20/G20-1,""),"") | I21: =IF(AND(ISNUMBER(I20),ISNUMBER(H20)),IFERROR(I20/H20-1,""),"") | J21: =IF(AND(ISNUMBER(J20),ISNUMBER(I20)),IFERROR(J20/I20-1,""),"") | K21: =IF(AND(ISNUMBER(K20),ISNUMBER(J20)),IFERROR(K20/J20-1,""),"") | L21: =IF(AND(ISNUMBER(L20),ISNUMBER(K20)),IFERROR(L20/K20-1,""),"") | Q21: =IF(AND(ISNUMBER(Q20),ISNUMBER(L20)),IFERROR(Q20/L20-1,""),"") | R21: =IF(AND(ISNUMBER(R20),ISNUMBER(M20)),IFERROR(R20/M20-1,""),"") | S21: =IF(AND(ISNUMBER(S20),ISNUMBER(N20)),IFERROR(S20/N20-1,""),"") | T21: =IF(AND(ISNUMBER(T20),ISNUMBER(O20)),IFERROR(T20/O20-1,""),"") | U21: =IF(AND(ISNUMBER(U20),ISNUMBER(P20)),IFERROR(U20/P20-1,""),"") | V21: =IF(AND(ISNUMBER(V20),ISNUMBER(Q20)),IFERROR(V20/Q20-1,""),"") | W21: =IF(AND(ISNUMBER(W20),ISNUMBER(R20)),IFERROR(W20/R20-1,""),"") | X21: =IF(AND(ISNUMBER(X20),ISNUMBER(S20)),IFERROR(X20/S20-1,""),"") | ... AP21: =IF(AND(ISNUMBER(AP20),ISNUMBER(AK20)),IFERROR(AP20/AK20-1,""),"") | AQ21: =IF(AND(ISNUMBER(AQ20),ISNUMBER(AP20)),IFERROR(AQ20/AP20-1,""),"") | AR21: =IF(AND(ISNUMBER(AR20),ISNUMBER(AQ20)),IFERROR(AR20/AQ20-1,""),"") | AS21: =IF(AND(ISNUMBER(AS20),ISNUMBER(AR20)),IFERROR(AS20/AR20-1,""),"") | AT21: =IF(AND(ISNUMBER(AT20),ISNUMBER(AS20)),IFERROR(AT20/AS20-1,""),"") | BC21: Amortization of acquired intangibles ($m) | BE21: 262 | BG21: Q1/27 $65.3m; 10-K schedule $253.1m + FY27 tuck-ins; FY27 outlook $2.08 per share after tax.
B22: % of total revenue | C22: =IF(AND(ISNUMBER(C20),ISNUMBER(C117)),IFERROR(C20/C117,""),"") | D22: =IF(AND(ISNUMBER(D20),ISNUMBER(D117)),IFERROR(D20/D117,""),"") | E22: =IF(AND(ISNUMBER(E20),ISNUMBER(E117)),IFERROR(E20/E117,""),"") | F22: =IF(AND(ISNUMBER(F20),ISNUMBER(F117)),IFERROR(F20/F117,""),"") | G22: =IF(AND(ISNUMBER(G20),ISNUMBER(G117)),IFERROR(G20/G117,""),"") | H22: =IF(AND(ISNUMBER(H20),ISNUMBER(H117)),IFERROR(H20/H117,""),"") | I22: =IF(AND(ISNUMBER(I20),ISNUMBER(I117)),IFERROR(I20/I117,""),"") | J22: =IF(AND(ISNUMBER(J20),ISNUMBER(J117)),IFERROR(J20/J117,""),"") | ... AT22: =IF(AND(ISNUMBER(AT20),ISNUMBER(AT117)),IFERROR(AT20/AT117,""),"") | BC22: Depreciation & other amortization ($m) | BE22: 238 | BG22: Q1/27 $58.5m (D&A $123.8m − amortization $65.3m); rising with capex.
B23: Recurring (consumables + service) % of segment revenue | C23: =IF(ISNUMBER(C14),IFERROR((C14+C17)/C20,""),"") | D23: =IF(ISNUMBER(D14),IFERROR((D14+D17)/D20,""),"") | E23: =IF(ISNUMBER(E14),IFERROR((E14+E17)/E20,""),"") | F23: =IF(ISNUMBER(F14),IFERROR((F14+F17)/F20,""),"") | G23: =IF(ISNUMBER(G14),IFERROR((G14+G17)/G20,""),"") | H23: =IF(ISNUMBER(H14),IFERROR((H14+H17)/H20,""),"") | I23: =IF(ISNUMBER(I14),IFERROR((I14+I17)/I20,""),"") | J23: =IF(ISNUMBER(J14),IFERROR((J14+J17)/J20,""),"") | ... AT23: =IF(ISNUMBER(AT14),IFERROR((AT14+AT17)/AT20,""),"") | BC23: Tax rate (GAAP & adjusted) | BE23: 0.25 | BG23: FY27 outlook ~25% (Q1/27 GAAP 26.5%, adjusted 25.9%).
B24: Memo: Healthcare revenue as published (segment data) | C24: 1013.102 | D24: 1074.79 | E24: 1180.051 | F24: 1391.874 | G24: 1630.018 | H24: 1821.053 | I24: 1745.119 | J24: 1848.485 | K24: 1986.809 | L24: 1954.055 | M24: 602.817 | N24: 744.134 | O24: 759.675 | P24: 738.841 | Q24: 2845.467 | R24: 698.526 | S24: 732.813 | T24: 769.144 | U24: 884.648 | V24: 3085.131 | W24: 818.874 | X24: 870.056 | Y24: 916.227 | Z24: 1007.862 | AA24: 3613.019 | AB24: 901.221 | AC24: 944.23 | AD24: 976.044 | AE24: 1057.176 | AF24: 3878.671 | AG24: 974.7 | AH24: 1033.8 | AI24: 1063.8 | AJ24: 1136.3 | AK24: 4208.6 | AL24: 1048.3 | BC24: Capital expenditures ($m) | BE24: 450 | BG24: FY27 outlook ~$450m (Q1/27 release), incl. the North Carolina chemistries and Mentor, OH plants.
B25: Check: revenue by type vs segment revenue (should be 0) | C25: =IF(AND(ISNUMBER(C20),ISNUMBER(C24)),IF(ABS(C20-C24)<=0.15,0,ROUND(C20-C24,1)),"") | D25: =IF(AND(ISNUMBER(D20),ISNUMBER(D24)),IF(ABS(D20-D24)<=0.15,0,ROUND(D20-D24,1)),"") | E25: =IF(AND(ISNUMBER(E20),ISNUMBER(E24)),IF(ABS(E20-E24)<=0.15,0,ROUND(E20-E24,1)),"") | F25: =IF(AND(ISNUMBER(F20),ISNUMBER(F24)),IF(ABS(F20-F24)<=0.15,0,ROUND(F20-F24,1)),"") | G25: =IF(AND(ISNUMBER(G20),ISNUMBER(G24)),IF(ABS(G20-G24)<=0.15,0,ROUND(G20-G24,1)),"") | H25: =IF(AND(ISNUMBER(H20),ISNUMBER(H24)),IF(ABS(H20-H24)<=0.15,0,ROUND(H20-H24,1)),"") | I25: =IF(AND(ISNUMBER(I20),ISNUMBER(I24)),IF(ABS(I20-I24)<=0.15,0,ROUND(I20-I24,1)),"") | J25: =IF(AND(ISNUMBER(J20),ISNUMBER(J24)),IF(ABS(J20-J24)<=0.15,0,ROUND(J20-J24,1)),"") | ... AL25: =IF(AND(ISNUMBER(AL20),ISNUMBER(AL24)),IF(ABS(AL20-AL24)<=0.15,0,ROUND(AL20-AL24,1)),"") | BC25: Free cash flow outlook ($m) — memo | BE25: 800 | BG25: FY27 outlook ~$800m (CFO ~$1,250m − capex ~$450m).
B26: Segment operating income (adjusted basis) | C26: 127.849 | D26: 128.767 | E26: 149.842 | F26: 185.108 | G26: 205.46 | H26: 237.972 | I26: 250.705 | J26: 387.906 | K26: 420.636 | L26: 427.089 | M26: 136.16 | N26: 160.39 | O26: 169.267 | P26: 160.281 | Q26: 626.098 | R26: 156.497 | S26: 165.337 | T26: 175.399 | U26: 208.787 | V26: 706.02 | W26: 198.182 | X26: 204.054 | Y26: 223.898 | Z26: 245.224 | AA26: 871.358 | AB26: 216.887 | AC26: 228.006 | AD26: 246.917 | AE26: 279.711 | AF26: 971.521 | AG26: 235.5 | AH26: 259.5 | AI26: 258.1 | AJ26: 283.2 | AK26: 1036.4 | AL26: 260.2 | AM26: =AM20*AM27 | AN26: =AN20*AN27 | AO26: =AO20*AO27 | AP26: =SUM(AL26,AM26,AN26,AO26) | AQ26: =AQ20*AQ27 | AR26: =AR20*AR27 | AS26: =AS20*AS27 | AT26: =AT20*AT27 | AU26: Segment income before adjustments (company measure; FY2012–15: adjusted segment operating income from the release reconciliations). Forecast = revenue × segment margin. | AW26: =IFERROR((AT26/AK26)^(1/5)-1,"n/m") | AX26: =IFERROR((AK26/L26)^(1/5)-1,"n/m") | AY26: =IFERROR((AK26/G26)^(1/10)-1,"n/m") | AZ26: =IFERROR((AK26/C26)^(1/14)-1,"n/m")
B27: Segment operating margin % | C27: =IF(AND(ISNUMBER(C26),ISNUMBER(C20)),IFERROR(C26/C20,""),"") | D27: =IF(AND(ISNUMBER(D26),ISNUMBER(D20)),IFERROR(D26/D20,""),"") | E27: =IF(AND(ISNUMBER(E26),ISNUMBER(E20)),IFERROR(E26/E20,""),"") | F27: =IF(AND(ISNUMBER(F26),ISNUMBER(F20)),IFERROR(F26/F20,""),"") | G27: =IF(AND(ISNUMBER(G26),ISNUMBER(G20)),IFERROR(G26/G20,""),"") | H27: =IF(AND(ISNUMBER(H26),ISNUMBER(H20)),IFERROR(H26/H20,""),"") | I27: =IF(AND(ISNUMBER(I26),ISNUMBER(I20)),IFERROR(I26/I20,""),"") | J27: =IF(AND(ISNUMBER(J26),ISNUMBER(J20)),IFERROR(J26/J20,""),"") | ... AL27: =IF(AND(ISNUMBER(AL26),ISNUMBER(AL20)),IFERROR(AL26/AL20,""),"") | AM27: =AM28+$AM$134 | AN27: =AN28+$AM$134 | AO27: =AO28+$AM$134 | AP27: =IF(AND(ISNUMBER(AP26),ISNUMBER(AP20)),IFERROR(AP26/AP20,""),"") | AQ27: =CHOOSE(MATCH($AU$2,{"Bull","Base","Bear"},0),$BD$70,$BE$70,$BF$70) | AR27: =CHOOSE(MATCH($AU$2,{"Bull","Base","Bear"},0),$BD$71,$BE$71,$BF$71) | AS27: =CHOOSE(MATCH($AU$2,{"Bull","Base","Bear"},0),$BD$72,$BE$72,$BF$72) | AT27: =CHOOSE(MATCH($AU$2,{"Bull","Base","Bear"},0),$BD$73,$BE$73,$BF$73) | AU27: Q2–Q4/27E: margin before calibration + adjusted-EPS-outlook calibration Δ (Group block). 2028E+: scenario lever. | AW27: =IFERROR(AVERAGE(AP27,AQ27,AR27,AS27,AT27),"n/m") | AX27: =IFERROR(AVERAGE(Q27,V27,AA27,AF27,AK27),"n/m") | AY27: =IFERROR(AVERAGE(H27,I27,J27,K27,L27,Q27,V27,AA27,AF27,AK27),"n/m") | AZ27: =IFERROR(AVERAGE(C27,D27,E27,F27,G27,H27,I27,J27,K27,L27,Q27,V27,AA27,AF27,AK27),"n/m") | BC27: Maximum net debt / adjusted EBITDA before buybacks (x) — buyback floor 2028E+ | BD27: 1 | BE27: 0.75 | BF27: 0.5 | BG27: Net debt $1.41bn at 30-Jun-26 ≈ 0.9x adjusted EBITDA (model definition). Target = leverage up to which surplus cash is returned via buybacks; below it free cash flow is held / repays the revolver. Bull = more buybacks (higher target).
B28: Q2–Q4/27E margin before EPS-outlook calibration (prior-year quarter + Q1/27 y/y drift) | AM28: =AH27+IFERROR(AL26/AL20-AG26/AG20,0) | AN28: =AI27+IFERROR(AL26/AL20-AG26/AG20,0) | AO28: =AJ27+IFERROR(AL26/AL20-AG26/AG20,0)
B29: Incremental segment margin (Δ operating income / Δ revenue) | D29: =IFERROR((D26-C26)/(D20-C20),"") | E29: =IFERROR((E26-D26)/(E20-D20),"") | F29: =IFERROR((F26-E26)/(F20-E20),"") | G29: =IFERROR((G26-F26)/(G20-F20),"") | H29: =IFERROR((H26-G26)/(H20-G20),"") | I29: =IFERROR((I26-H26)/(I20-H20),"") | J29: =IFERROR((J26-I26)/(J20-I20),"") | K29: =IFERROR((K26-J26)/(K20-J20),"") | L29: =IFERROR((L26-K26)/(L20-K20),"") | Q29: =IFERROR((Q26-L26)/(Q20-L20),"") | R29: =IFERROR((R26-M26)/(R20-M20),"") | S29: =IFERROR((S26-N26)/(S20-N20),"") | T29: =IFERROR((T26-O26)/(T20-O20),"") | U29: =IFERROR((U26-P26)/(U20-P20),"") | V29: =IFERROR((V26-Q26)/(V20-Q20),"") | W29: =IFERROR((W26-R26)/(W20-R20),"") | X29: =IFERROR((X26-S26)/(X20-S20),"") | ... AP29: =IFERROR((AP26-AK26)/(AP20-AK20),"") | AQ29: =IFERROR((AQ26-AP26)/(AQ20-AP20),"") | AR29: =IFERROR((AR26-AQ26)/(AR20-AQ20),"") | AS29: =IFERROR((AS26-AR26)/(AS20-AR20),"") | AT29: =IFERROR((AT26-AS26)/(AT20-AS20),"") | BC29: HC_CAP (Healthcare capital equipment y/y) | BD29: 0.02 | BE29: Δ → | BF29: -0.04 | BG29: Hospital capex cycle (sterilizers, washers, OR tables / lights, integration); backlog $444m at 30-Jun-26 (+10% y/y).
BC30: 2028E | BD30: =BE30+$BD$29 | BE30: 0.045 | BF30: =BE30+$BF$29
B31: Applied Sterilization Technologies (contract EO / gamma / E-beam / X-ray sterilization and lab testing; "Isomedix" to FY2015) | AU31: APPLIED STERILIZATION TECHNOLOGIES (AST) — modelling logic | BC31: 2029E | BD31: =BE31+$BD$29 | BE31: 0.04 | BF31: =BE31+$BF$29
B32: Service (contract sterilization & lab testing) revenue | C32: 164.257 | D32: 179.55 | E32: 194.183 | F32: 205.675 | G32: 310.12 | H32: 458.231 | I32: 513.287 | J32: 555.127 | K32: 627.147 | L32: 685.912 | M32: 208.902 | N32: 204.892 | O32: 216.298 | P32: 222.88 | Q32: 852.972 | R32: 220.911 | S32: 232.358 | T32: 222.014 | U32: 227.469 | V32: 887.971 | W32: 232.225 | X32: 233.299 | Y32: 229.69 | Z32: 244.247 | AA32: 939.461 | AB32: 248.715 | AC32: 247.932 | AD32: 253.14 | AE32: 257.84 | AF32: 1007.627 | AG32: 279.6 | AH32: 279.4 | AI32: 276.4 | AJ32: 283.1 | AK32: 1118.5 | AL32: 296.3 | AM32: =AH32*(1+AM33) | AN32: =AI32*(1+AN33) | AO32: =AJ32*(1+AO33) | AP32: =SUM(AL32,AM32,AN32,AO32) | AQ32: =AP32*(1+AQ33) | AR32: =AQ32*(1+AR33) | AS32: =AR32*(1+AS33) | AT32: =AS32*(1+AT33) | AU32: Revenue by type as published (release "Unaudited Supplemental Financial Data"). Q2–Q4/27E: prior-year quarter × (1 + growth). 2028E+: prior year × (1 + scenario lever). | AW32: =IFERROR((AT32/AK32)^(1/5)-1,"n/m") | AX32: =IFERROR((AK32/L32)^(1/5)-1,"n/m") | AY32: =IFERROR((AK32/G32)^(1/10)-1,"n/m") | AZ32: =IFERROR((AK32/C32)^(1/14)-1,"n/m") | BC32: 2030E | BD32: =BE32+$BD$29 | BE32: 0.04 | BF32: =BE32+$BF$29
B33: y/y % | D33: =IF(AND(ISNUMBER(D32),ISNUMBER(C32)),IFERROR(D32/C32-1,""),"") | E33: =IF(AND(ISNUMBER(E32),ISNUMBER(D32)),IFERROR(E32/D32-1,""),"") | F33: =IF(AND(ISNUMBER(F32),ISNUMBER(E32)),IFERROR(F32/E32-1,""),"") | G33: =IF(AND(ISNUMBER(G32),ISNUMBER(F32)),IFERROR(G32/F32-1,""),"") | H33: =IF(AND(ISNUMBER(H32),ISNUMBER(G32)),IFERROR(H32/G32-1,""),"") | I33: =IF(AND(ISNUMBER(I32),ISNUMBER(H32)),IFERROR(I32/H32-1,""),"") | J33: =IF(AND(ISNUMBER(J32),ISNUMBER(I32)),IFERROR(J32/I32-1,""),"") | K33: =IF(AND(ISNUMBER(K32),ISNUMBER(J32)),IFERROR(K32/J32-1,""),"") | L33: =IF(AND(ISNUMBER(L32),ISNUMBER(K32)),IFERROR(L32/K32-1,""),"") | Q33: =IF(AND(ISNUMBER(Q32),ISNUMBER(L32)),IFERROR(Q32/L32-1,""),"") | R33: =IF(AND(ISNUMBER(R32),ISNUMBER(M32)),IFERROR(R32/M32-1,""),"") | S33: =IF(AND(ISNUMBER(S32),ISNUMBER(N32)),IFERROR(S32/N32-1,""),"") | T33: =IF(AND(ISNUMBER(T32),ISNUMBER(O32)),IFERROR(T32/O32-1,""),"") | U33: =IF(AND(ISNUMBER(U32),ISNUMBER(P32)),IFERROR(U32/P32-1,""),"") | V33: =IF(AND(ISNUMBER(V32),ISNUMBER(Q32)),IFERROR(V32/Q32-1,""),"") | W33: =IF(AND(ISNUMBER(W32),ISNUMBER(R32)),IFERROR(W32/R32-1,""),"") | X33: =IF(AND(ISNUMBER(X32),ISNUMBER(S32)),IFERROR(X32/S32-1,""),"") | ... AL33: =IF(AND(ISNUMBER(AL32),ISNUMBER(AG32)),IFERROR(AL32/AG32-1,""),"") | AM33: =AM34+$AM$127 | AN33: =AN34+$AM$127 | AO33: =AO34+$AM$127 | AP33: =IF(AND(ISNUMBER(AP32),ISNUMBER(AK32)),IFERROR(AP32/AK32-1,""),"") | AQ33: =CHOOSE(MATCH($AU$2,{"Bull","Base","Bear"},0),$BD$45,$BE$45,$BF$45) | AR33: =CHOOSE(MATCH($AU$2,{"Bull","Base","Bear"},0),$BD$46,$BE$46,$BF$46) | AS33: =CHOOSE(MATCH($AU$2,{"Bull","Base","Bear"},0),$BD$47,$BE$47,$BF$47) | AT33: =CHOOSE(MATCH($AU$2,{"Bull","Base","Bear"},0),$BD$48,$BE$48,$BF$48) | AU33: Q2–Q4/27E: Q1/27 y/y growth of the line + revenue-outlook calibration Δ (Group block). 2028E–2031E: scenario lever (Bull/Base/Bear table →). | BC33: 2031E | BD33: =BE33+$BD$29 | BE33: 0.04 | BF33: =BE33+$BF$29
B34: Q2–Q4/27E growth before revenue calibration (Q1/27 y/y) | AM34: =IFERROR(AL32/AG32-1,0) | AN34: =IFERROR(AL32/AG32-1,0) | AO34: =IFERROR(AL32/AG32-1,0) | BC34: HC_CONS (Healthcare consumables y/y) | BD34: 0.015 | BE34: Δ → | BF34: -0.03 | BG34: Procedure volumes (US surgical procedures +MSD), endoscopy consumables (Cantel), share gains, price.
B35: Capital equipment revenue | C35: 0 | D35: 0 | E35: 0 | F35: 0 | G35: 0 | H35: 0 | I35: 0 | J35: 0 | K35: 0 | L35: 0 | M35: 0 | N35: 0 | O35: 0 | P35: 0 | Q35: 0 | R35: 0 | S35: 0 | T35: 0 | U35: 11.679 | V35: 26.46 | W35: 0.874 | X35: 1.754 | Y35: 5.241 | Z35: 6.65 | AA35: 14.519 | AB35: 1.088 | AC35: 8.805 | AD35: 5.004 | AE35: 16.049 | AF35: 30.946 | AG35: 1.6 | AH35: 2.1 | AI35: 10.2 | AJ35: 6.1 | AK35: 20 | AL35: 1.4 | AM35: =AH35*(1+AM36) | AN35: =AI35*(1+AN36) | AO35: =AJ35*(1+AO36) | AP35: =SUM(AL35,AM35,AN35,AO35) | AQ35: =AP35*(1+AQ36) | AR35: =AQ35*(1+AR36) | AS35: =AR35*(1+AS36) | AT35: =AS35*(1+AT36) | BC35: 2028E | BD35: =BE35+$BD$34 | BE35: 0.065 | BF35: =BE35+$BF$34
B36: y/y % | D36: =IF(AND(ISNUMBER(D35),ISNUMBER(C35)),IFERROR(D35/C35-1,""),"") | E36: =IF(AND(ISNUMBER(E35),ISNUMBER(D35)),IFERROR(E35/D35-1,""),"") | F36: =IF(AND(ISNUMBER(F35),ISNUMBER(E35)),IFERROR(F35/E35-1,""),"") | G36: =IF(AND(ISNUMBER(G35),ISNUMBER(F35)),IFERROR(G35/F35-1,""),"") | H36: =IF(AND(ISNUMBER(H35),ISNUMBER(G35)),IFERROR(H35/G35-1,""),"") | I36: =IF(AND(ISNUMBER(I35),ISNUMBER(H35)),IFERROR(I35/H35-1,""),"") | J36: =IF(AND(ISNUMBER(J35),ISNUMBER(I35)),IFERROR(J35/I35-1,""),"") | K36: =IF(AND(ISNUMBER(K35),ISNUMBER(J35)),IFERROR(K35/J35-1,""),"") | L36: =IF(AND(ISNUMBER(L35),ISNUMBER(K35)),IFERROR(L35/K35-1,""),"") | Q36: =IF(AND(ISNUMBER(Q35),ISNUMBER(L35)),IFERROR(Q35/L35-1,""),"") | R36: =IF(AND(ISNUMBER(R35),ISNUMBER(M35)),IFERROR(R35/M35-1,""),"") | S36: =IF(AND(ISNUMBER(S35),ISNUMBER(N35)),IFERROR(S35/N35-1,""),"") | T36: =IF(AND(ISNUMBER(T35),ISNUMBER(O35)),IFERROR(T35/O35-1,""),"") | U36: =IF(AND(ISNUMBER(U35),ISNUMBER(P35)),IFERROR(U35/P35-1,""),"") | V36: =IF(AND(ISNUMBER(V35),ISNUMBER(Q35)),IFERROR(V35/Q35-1,""),"") | W36: =IF(AND(ISNUMBER(W35),ISNUMBER(R35)),IFERROR(W35/R35-1,""),"") | X36: =IF(AND(ISNUMBER(X35),ISNUMBER(S35)),IFERROR(X35/S35-1,""),"") | ... AL36: =IF(AND(ISNUMBER(AL35),ISNUMBER(AG35)),IFERROR(AL35/AG35-1,""),"") | AM36: =AM37+$AM$127 | AN36: =AN37+$AM$127 | AO36: =AO37+$AM$127 | AP36: =IF(AND(ISNUMBER(AP35),ISNUMBER(AK35)),IFERROR(AP35/AK35-1,""),"") | AQ36: =CHOOSE(MATCH($AU$2,{"Bull","Base","Bear"},0),$BD$50,$BE$50,$BF$50) | AR36: =CHOOSE(MATCH($AU$2,{"Bull","Base","Bear"},0),$BD$51,$BE$51,$BF$51) | AS36: =CHOOSE(MATCH($AU$2,{"Bull","Base","Bear"},0),$BD$52,$BE$52,$BF$52) | AT36: =CHOOSE(MATCH($AU$2,{"Bull","Base","Bear"},0),$BD$53,$BE$53,$BF$53) | BC36: 2029E | BD36: =BE36+$BD$34 | BE36: 0.065 | BF36: =BE36+$BF$34
B37: Q2–Q4/27E growth before revenue calibration (Q1/27 y/y) | AM37: =IFERROR(AL35/AG35-1,0) | AN37: =IFERROR(AL35/AG35-1,0) | AO37: =IFERROR(AL35/AG35-1,0) | BC37: 2030E | BD37: =BE37+$BD$34 | BE37: 0.06 | BF37: =BE37+$BF$34
B38: Applied Sterilization Technologies (AST) — revenue | C38: =IF(ISNUMBER(C32),C32+C35,"") | D38: =IF(ISNUMBER(D32),D32+D35,"") | E38: =IF(ISNUMBER(E32),E32+E35,"") | F38: =IF(ISNUMBER(F32),F32+F35,"") | G38: =IF(ISNUMBER(G32),G32+G35,"") | H38: =IF(ISNUMBER(H32),H32+H35,"") | I38: =IF(ISNUMBER(I32),I32+I35,"") | J38: =IF(ISNUMBER(J32),J32+J35,"") | ... AT38: =IF(ISNUMBER(AT32),AT32+AT35,"") | AW38: =IFERROR((AT38/AK38)^(1/5)-1,"n/m") | AX38: =IFERROR((AK38/L38)^(1/5)-1,"n/m") | AY38: =IFERROR((AK38/G38)^(1/10)-1,"n/m") | AZ38: =IFERROR((AK38/C38)^(1/14)-1,"n/m") | BC38: 2031E | BD38: =BE38+$BD$34 | BE38: 0.06 | BF38: =BE38+$BF$34
B39: Revenue y/y % | D39: =IF(AND(ISNUMBER(D38),ISNUMBER(C38)),IFERROR(D38/C38-1,""),"") | E39: =IF(AND(ISNUMBER(E38),ISNUMBER(D38)),IFERROR(E38/D38-1,""),"") | F39: =IF(AND(ISNUMBER(F38),ISNUMBER(E38)),IFERROR(F38/E38-1,""),"") | G39: =IF(AND(ISNUMBER(G38),ISNUMBER(F38)),IFERROR(G38/F38-1,""),"") | H39: =IF(AND(ISNUMBER(H38),ISNUMBER(G38)),IFERROR(H38/G38-1,""),"") | I39: =IF(AND(ISNUMBER(I38),ISNUMBER(H38)),IFERROR(I38/H38-1,""),"") | J39: =IF(AND(ISNUMBER(J38),ISNUMBER(I38)),IFERROR(J38/I38-1,""),"") | K39: =IF(AND(ISNUMBER(K38),ISNUMBER(J38)),IFERROR(K38/J38-1,""),"") | L39: =IF(AND(ISNUMBER(L38),ISNUMBER(K38)),IFERROR(L38/K38-1,""),"") | Q39: =IF(AND(ISNUMBER(Q38),ISNUMBER(L38)),IFERROR(Q38/L38-1,""),"") | R39: =IF(AND(ISNUMBER(R38),ISNUMBER(M38)),IFERROR(R38/M38-1,""),"") | S39: =IF(AND(ISNUMBER(S38),ISNUMBER(N38)),IFERROR(S38/N38-1,""),"") | T39: =IF(AND(ISNUMBER(T38),ISNUMBER(O38)),IFERROR(T38/O38-1,""),"") | U39: =IF(AND(ISNUMBER(U38),ISNUMBER(P38)),IFERROR(U38/P38-1,""),"") | V39: =IF(AND(ISNUMBER(V38),ISNUMBER(Q38)),IFERROR(V38/Q38-1,""),"") | W39: =IF(AND(ISNUMBER(W38),ISNUMBER(R38)),IFERROR(W38/R38-1,""),"") | X39: =IF(AND(ISNUMBER(X38),ISNUMBER(S38)),IFERROR(X38/S38-1,""),"") | ... AP39: =IF(AND(ISNUMBER(AP38),ISNUMBER(AK38)),IFERROR(AP38/AK38-1,""),"") | AQ39: =IF(AND(ISNUMBER(AQ38),ISNUMBER(AP38)),IFERROR(AQ38/AP38-1,""),"") | AR39: =IF(AND(ISNUMBER(AR38),ISNUMBER(AQ38)),IFERROR(AR38/AQ38-1,""),"") | AS39: =IF(AND(ISNUMBER(AS38),ISNUMBER(AR38)),IFERROR(AS38/AR38-1,""),"") | AT39: =IF(AND(ISNUMBER(AT38),ISNUMBER(AS38)),IFERROR(AT38/AS38-1,""),"") | BC39: HC_SERV (Healthcare service y/y) | BD39: 0.015 | BE39: Δ → | BF39: -0.03 | BG39: Equipment service contracts, instrument repair (BD instruments, Aug-23), outsourced reprocessing; FY26 +12%.
B40: % of total revenue | C40: =IF(AND(ISNUMBER(C38),ISNUMBER(C117)),IFERROR(C38/C117,""),"") | D40: =IF(AND(ISNUMBER(D38),ISNUMBER(D117)),IFERROR(D38/D117,""),"") | E40: =IF(AND(ISNUMBER(E38),ISNUMBER(E117)),IFERROR(E38/E117,""),"") | F40: =IF(AND(ISNUMBER(F38),ISNUMBER(F117)),IFERROR(F38/F117,""),"") | G40: =IF(AND(ISNUMBER(G38),ISNUMBER(G117)),IFERROR(G38/G117,""),"") | H40: =IF(AND(ISNUMBER(H38),ISNUMBER(H117)),IFERROR(H38/H117,""),"") | I40: =IF(AND(ISNUMBER(I38),ISNUMBER(I117)),IFERROR(I38/I117,""),"") | J40: =IF(AND(ISNUMBER(J38),ISNUMBER(J117)),IFERROR(J38/J117,""),"") | ... AT40: =IF(AND(ISNUMBER(AT38),ISNUMBER(AT117)),IFERROR(AT38/AT117,""),"") | BC40: 2028E | BD40: =BE40+$BD$39 | BE40: 0.085 | BF40: =BE40+$BF$39
B41: Memo: Applied Sterilization Technologies (AST) revenue as published (segment data) | C41: 164.257 | D41: 179.55 | E41: 194.183 | F41: 205.675 | G41: 310.12 | H41: 458.231 | I41: 513.287 | J41: 555.127 | K41: 627.147 | L41: 685.912 | M41: 208.902 | N41: 204.892 | O41: 216.298 | P41: 222.88 | Q41: 852.972 | R41: 220.911 | S41: 232.358 | T41: 222.014 | U41: 239.148 | V41: 914.431 | W41: 233.099 | X41: 235.053 | Y41: 234.931 | Z41: 250.897 | AA41: 953.98 | AB41: 249.803 | AC41: 256.737 | AD41: 258.144 | AE41: 273.889 | AF41: 1038.573 | AG41: 281.2 | AH41: 281.5 | AI41: 286.6 | AJ41: 289.2 | AK41: 1138.5 | AL41: 297.6 | BC41: 2029E | BD41: =BE41+$BD$39 | BE41: 0.08 | BF41: =BE41+$BF$39
B42: Check: revenue by type vs segment revenue (should be 0) | C42: =IF(AND(ISNUMBER(C38),ISNUMBER(C41)),IF(ABS(C38-C41)<=0.15,0,ROUND(C38-C41,1)),"") | D42: =IF(AND(ISNUMBER(D38),ISNUMBER(D41)),IF(ABS(D38-D41)<=0.15,0,ROUND(D38-D41,1)),"") | E42: =IF(AND(ISNUMBER(E38),ISNUMBER(E41)),IF(ABS(E38-E41)<=0.15,0,ROUND(E38-E41,1)),"") | F42: =IF(AND(ISNUMBER(F38),ISNUMBER(F41)),IF(ABS(F38-F41)<=0.15,0,ROUND(F38-F41,1)),"") | G42: =IF(AND(ISNUMBER(G38),ISNUMBER(G41)),IF(ABS(G38-G41)<=0.15,0,ROUND(G38-G41,1)),"") | H42: =IF(AND(ISNUMBER(H38),ISNUMBER(H41)),IF(ABS(H38-H41)<=0.15,0,ROUND(H38-H41,1)),"") | I42: =IF(AND(ISNUMBER(I38),ISNUMBER(I41)),IF(ABS(I38-I41)<=0.15,0,ROUND(I38-I41,1)),"") | J42: =IF(AND(ISNUMBER(J38),ISNUMBER(J41)),IF(ABS(J38-J41)<=0.15,0,ROUND(J38-J41,1)),"") | ... AL42: =IF(AND(ISNUMBER(AL38),ISNUMBER(AL41)),IF(ABS(AL38-AL41)<=0.15,0,ROUND(AL38-AL41,1)),"") | BC42: 2030E | BD42: =BE42+$BD$39 | BE42: 0.075 | BF42: =BE42+$BF$39
B43: Segment operating income (adjusted basis) | C43: 47.596 | D43: 51.455 | E43: 57.598 | F43: 59.471 | G43: 99.224 | H43: 156.01 | I43: 173.375 | J43: 221.828 | K43: 270.917 | L43: 310.648 | M43: 101.927 | N43: 99.789 | O43: 101.343 | P43: 107.042 | Q43: 410.101 | R43: 109.315 | S43: 110.384 | T43: 103.539 | U43: 105.782 | V43: 429.02 | W43: 109.59 | X43: 110.783 | Y43: 105.156 | Z43: 114.215 | AA43: 439.744 | AB43: 117.714 | AC43: 109.902 | AD43: 115.758 | AE43: 122.202 | AF43: 465.576 | AG43: 136.7 | AH43: 127.6 | AI43: 129.2 | AJ43: 131.1 | AK43: 524.7 | AL43: 142.9 | AM43: =AM38*AM44 | AN43: =AN38*AN44 | AO43: =AO38*AO44 | AP43: =SUM(AL43,AM43,AN43,AO43) | AQ43: =AQ38*AQ44 | AR43: =AR38*AR44 | AS43: =AS38*AS44 | AT43: =AT38*AT44 | AW43: =IFERROR((AT43/AK43)^(1/5)-1,"n/m") | AX43: =IFERROR((AK43/L43)^(1/5)-1,"n/m") | AY43: =IFERROR((AK43/G43)^(1/10)-1,"n/m") | AZ43: =IFERROR((AK43/C43)^(1/14)-1,"n/m") | BC43: 2031E | BD43: =BE43+$BD$39 | BE43: 0.07 | BF43: =BE43+$BF$39
B44: Segment operating margin % | C44: =IF(AND(ISNUMBER(C43),ISNUMBER(C38)),IFERROR(C43/C38,""),"") | D44: =IF(AND(ISNUMBER(D43),ISNUMBER(D38)),IFERROR(D43/D38,""),"") | E44: =IF(AND(ISNUMBER(E43),ISNUMBER(E38)),IFERROR(E43/E38,""),"") | F44: =IF(AND(ISNUMBER(F43),ISNUMBER(F38)),IFERROR(F43/F38,""),"") | G44: =IF(AND(ISNUMBER(G43),ISNUMBER(G38)),IFERROR(G43/G38,""),"") | H44: =IF(AND(ISNUMBER(H43),ISNUMBER(H38)),IFERROR(H43/H38,""),"") | I44: =IF(AND(ISNUMBER(I43),ISNUMBER(I38)),IFERROR(I43/I38,""),"") | J44: =IF(AND(ISNUMBER(J43),ISNUMBER(J38)),IFERROR(J43/J38,""),"") | ... AL44: =IF(AND(ISNUMBER(AL43),ISNUMBER(AL38)),IFERROR(AL43/AL38,""),"") | AM44: =AM45+$AM$134 | AN44: =AN45+$AM$134 | AO44: =AO45+$AM$134 | AP44: =IF(AND(ISNUMBER(AP43),ISNUMBER(AP38)),IFERROR(AP43/AP38,""),"") | AQ44: =CHOOSE(MATCH($AU$2,{"Bull","Base","Bear"},0),$BD$75,$BE$75,$BF$75) | AR44: =CHOOSE(MATCH($AU$2,{"Bull","Base","Bear"},0),$BD$76,$BE$76,$BF$76) | AS44: =CHOOSE(MATCH($AU$2,{"Bull","Base","Bear"},0),$BD$77,$BE$77,$BF$77) | AT44: =CHOOSE(MATCH($AU$2,{"Bull","Base","Bear"},0),$BD$78,$BE$78,$BF$78) | AW44: =IFERROR(AVERAGE(AP44,AQ44,AR44,AS44,AT44),"n/m") | AX44: =IFERROR(AVERAGE(Q44,V44,AA44,AF44,AK44),"n/m") | AY44: =IFERROR(AVERAGE(H44,I44,J44,K44,L44,Q44,V44,AA44,AF44,AK44),"n/m") | AZ44: =IFERROR(AVERAGE(C44,D44,E44,F44,G44,H44,I44,J44,K44,L44,Q44,V44,AA44,AF44,AK44),"n/m") | BC44: AST_SERV (AST contract sterilization & lab y/y) | BD44: 0.02 | BE44: Δ → | BF44: -0.04 | BG44: Med-device volumes (bioprocessing recovery), price; EO / gamma / X-ray capacity adds. FY26 +11%.
B45: Q2–Q4/27E margin before EPS-outlook calibration (prior-year quarter + Q1/27 y/y drift) | AM45: =AH44+IFERROR(AL43/AL38-AG43/AG38,0) | AN45: =AI44+IFERROR(AL43/AL38-AG43/AG38,0) | AO45: =AJ44+IFERROR(AL43/AL38-AG43/AG38,0) | BC45: 2028E | BD45: =BE45+$BD$44 | BE45: 0.08 | BF45: =BE45+$BF$44
B46: Incremental segment margin (Δ operating income / Δ revenue) | D46: =IFERROR((D43-C43)/(D38-C38),"") | E46: =IFERROR((E43-D43)/(E38-D38),"") | F46: =IFERROR((F43-E43)/(F38-E38),"") | G46: =IFERROR((G43-F43)/(G38-F38),"") | H46: =IFERROR((H43-G43)/(H38-G38),"") | I46: =IFERROR((I43-H43)/(I38-H38),"") | J46: =IFERROR((J43-I43)/(J38-I38),"") | K46: =IFERROR((K43-J43)/(K38-J38),"") | L46: =IFERROR((L43-K43)/(L38-K38),"") | Q46: =IFERROR((Q43-L43)/(Q38-L38),"") | R46: =IFERROR((R43-M43)/(R38-M38),"") | S46: =IFERROR((S43-N43)/(S38-N38),"") | T46: =IFERROR((T43-O43)/(T38-O38),"") | U46: =IFERROR((U43-P43)/(U38-P38),"") | V46: =IFERROR((V43-Q43)/(V38-Q38),"") | W46: =IFERROR((W43-R43)/(W38-R38),"") | X46: =IFERROR((X43-S43)/(X38-S38),"") | ... AP46: =IFERROR((AP43-AK43)/(AP38-AK38),"") | AQ46: =IFERROR((AQ43-AP43)/(AQ38-AP38),"") | AR46: =IFERROR((AR43-AQ43)/(AR38-AQ38),"") | AS46: =IFERROR((AS43-AR43)/(AS38-AR38),"") | AT46: =IFERROR((AT43-AS43)/(AT38-AS38),"") | BC46: 2029E | BD46: =BE46+$BD$44 | BE46: 0.08 | BF46: =BE46+$BF$44
BC47: 2030E | BD47: =BE47+$BD$44 | BE47: 0.075 | BF47: =BE47+$BF$44
B48: Life Sciences (barrier & cleaning consumables, sterilizers / washers for pharma & biotech, service) | AU48: LIFE SCIENCES — modelling logic | BC48: 2031E | BD48: =BE48+$BD$44 | BE48: 0.075 | BF48: =BE48+$BF$44
B49: Capital equipment revenue | C49: 81.281 | D49: 91.572 | E49: 88.199 | F49: 80.802 | G49: 84.843 | H49: 83.662544 | I49: 100.555 | J49: 102.714 | K49: 112.747 | L49: 128.356 | M49: 32.745 | N49: 34.186 | O49: 30.412 | P49: 44.938 | Q49: 142.281 | R49: 40.499 | S49: 30.015 | T49: 28.581 | U49: 48.325 | V49: 147.42 | W49: 30.991 | X49: 35.438 | Y49: 44.836 | Z49: 44.255 | AA49: 155.52 | AB49: 26.476 | AC49: 23.012 | AD49: 31.063 | AE49: 36.983 | AF49: 117.534 | AG49: 26.6 | AH49: 31.9 | AI49: 33.3 | AJ49: 43.9 | AK49: 135.7 | AL49: 31.3 | AM49: =AH49*(1+AM50) | AN49: =AI49*(1+AN50) | AO49: =AJ49*(1+AO50) | AP49: =SUM(AL49,AM49,AN49,AO49) | AQ49: =AP49*(1+AQ50) | AR49: =AQ49*(1+AR50) | AS49: =AR49*(1+AS50) | AT49: =AS49*(1+AT50) | AU49: Revenue by type as published (release "Unaudited Supplemental Financial Data"). Q2–Q4/27E: prior-year quarter × (1 + growth). 2028E+: prior year × (1 + scenario lever). | AW49: =IFERROR((AT49/AK49)^(1/5)-1,"n/m") | AX49: =IFERROR((AK49/L49)^(1/5)-1,"n/m") | AY49: =IFERROR((AK49/G49)^(1/10)-1,"n/m") | AZ49: =IFERROR((AK49/C49)^(1/14)-1,"n/m") | BC49: AST_CAP (AST capital equipment y/y) | BD49: 0 | BE49: Δ → | BF49: -0.1 | BG49: Lumpy X-ray / E-beam system sales (~$20–30m p.a.).
B50: y/y % | D50: =IF(AND(ISNUMBER(D49),ISNUMBER(C49)),IFERROR(D49/C49-1,""),"") | E50: =IF(AND(ISNUMBER(E49),ISNUMBER(D49)),IFERROR(E49/D49-1,""),"") | F50: =IF(AND(ISNUMBER(F49),ISNUMBER(E49)),IFERROR(F49/E49-1,""),"") | G50: =IF(AND(ISNUMBER(G49),ISNUMBER(F49)),IFERROR(G49/F49-1,""),"") | H50: =IF(AND(ISNUMBER(H49),ISNUMBER(G49)),IFERROR(H49/G49-1,""),"") | I50: =IF(AND(ISNUMBER(I49),ISNUMBER(H49)),IFERROR(I49/H49-1,""),"") | J50: =IF(AND(ISNUMBER(J49),ISNUMBER(I49)),IFERROR(J49/I49-1,""),"") | K50: =IF(AND(ISNUMBER(K49),ISNUMBER(J49)),IFERROR(K49/J49-1,""),"") | L50: =IF(AND(ISNUMBER(L49),ISNUMBER(K49)),IFERROR(L49/K49-1,""),"") | Q50: =IF(AND(ISNUMBER(Q49),ISNUMBER(L49)),IFERROR(Q49/L49-1,""),"") | R50: =IF(AND(ISNUMBER(R49),ISNUMBER(M49)),IFERROR(R49/M49-1,""),"") | S50: =IF(AND(ISNUMBER(S49),ISNUMBER(N49)),IFERROR(S49/N49-1,""),"") | T50: =IF(AND(ISNUMBER(T49),ISNUMBER(O49)),IFERROR(T49/O49-1,""),"") | U50: =IF(AND(ISNUMBER(U49),ISNUMBER(P49)),IFERROR(U49/P49-1,""),"") | V50: =IF(AND(ISNUMBER(V49),ISNUMBER(Q49)),IFERROR(V49/Q49-1,""),"") | W50: =IF(AND(ISNUMBER(W49),ISNUMBER(R49)),IFERROR(W49/R49-1,""),"") | X50: =IF(AND(ISNUMBER(X49),ISNUMBER(S49)),IFERROR(X49/S49-1,""),"") | ... AL50: =IF(AND(ISNUMBER(AL49),ISNUMBER(AG49)),IFERROR(AL49/AG49-1,""),"") | AM50: =AM51+$AM$127 | AN50: =AN51+$AM$127 | AO50: =AO51+$AM$127 | AP50: =IF(AND(ISNUMBER(AP49),ISNUMBER(AK49)),IFERROR(AP49/AK49-1,""),"") | AQ50: =CHOOSE(MATCH($AU$2,{"Bull","Base","Bear"},0),$BD$55,$BE$55,$BF$55) | AR50: =CHOOSE(MATCH($AU$2,{"Bull","Base","Bear"},0),$BD$56,$BE$56,$BF$56) | AS50: =CHOOSE(MATCH($AU$2,{"Bull","Base","Bear"},0),$BD$57,$BE$57,$BF$57) | AT50: =CHOOSE(MATCH($AU$2,{"Bull","Base","Bear"},0),$BD$58,$BE$58,$BF$58) | AU50: Q2–Q4/27E: Q1/27 y/y growth of the line + revenue-outlook calibration Δ (Group block). 2028E–2031E: scenario lever (Bull/Base/Bear table →). | BC50: 2028E | BD50: =BE50+$BD$49 | BE50: 0 | BF50: =BE50+$BF$49
B51: Q2–Q4/27E growth before revenue calibration (Q1/27 y/y) | AM51: =IFERROR(AL49/AG49-1,0) | AN51: =IFERROR(AL49/AG49-1,0) | AO51: =IFERROR(AL49/AG49-1,0) | BC51: 2029E | BD51: =BE51+$BD$49 | BE51: 0 | BF51: =BE51+$BF$49
B52: Consumables revenue | C52: 71.666 | D52: 75.834 | E52: 82.18 | F52: 90.506 | G52: 121.032 | H52: 142.45093 | I52: 150.656 | J52: 161.78 | K52: 185.904 | L52: 215.005 | M52: 56.536 | N52: 61.748 | O52: 61.096 | P52: 59.985 | Q52: 239.365 | R52: 59.557 | S52: 57.42 | T52: 55.61 | U52: 68.527 | V52: 241.114 | W52: 61.698 | X52: 59.409 | Y52: 60.072 | Z52: 70.401 | AA52: 251.58 | AB52: 69.818 | AC52: 72.125 | AD52: 68.676 | AE52: 76.037 | AF52: 286.656 | AG52: 75.3 | AH52: 77.2 | AI52: 75.9 | AJ52: 79.9 | AK52: 308.3 | AL52: 81.5 | AM52: =AH52*(1+AM53) | AN52: =AI52*(1+AN53) | AO52: =AJ52*(1+AO53) | AP52: =SUM(AL52,AM52,AN52,AO52) | AQ52: =AP52*(1+AQ53) | AR52: =AQ52*(1+AR53) | AS52: =AR52*(1+AS53) | AT52: =AS52*(1+AT53) | AW52: =IFERROR((AT52/AK52)^(1/5)-1,"n/m") | AX52: =IFERROR((AK52/L52)^(1/5)-1,"n/m") | AY52: =IFERROR((AK52/G52)^(1/10)-1,"n/m") | AZ52: =IFERROR((AK52/C52)^(1/14)-1,"n/m") | BC52: 2030E | BD52: =BE52+$BD$49 | BE52: 0 | BF52: =BE52+$BF$49
B53: y/y % | D53: =IF(AND(ISNUMBER(D52),ISNUMBER(C52)),IFERROR(D52/C52-1,""),"") | E53: =IF(AND(ISNUMBER(E52),ISNUMBER(D52)),IFERROR(E52/D52-1,""),"") | F53: =IF(AND(ISNUMBER(F52),ISNUMBER(E52)),IFERROR(F52/E52-1,""),"") | G53: =IF(AND(ISNUMBER(G52),ISNUMBER(F52)),IFERROR(G52/F52-1,""),"") | H53: =IF(AND(ISNUMBER(H52),ISNUMBER(G52)),IFERROR(H52/G52-1,""),"") | I53: =IF(AND(ISNUMBER(I52),ISNUMBER(H52)),IFERROR(I52/H52-1,""),"") | J53: =IF(AND(ISNUMBER(J52),ISNUMBER(I52)),IFERROR(J52/I52-1,""),"") | K53: =IF(AND(ISNUMBER(K52),ISNUMBER(J52)),IFERROR(K52/J52-1,""),"") | L53: =IF(AND(ISNUMBER(L52),ISNUMBER(K52)),IFERROR(L52/K52-1,""),"") | Q53: =IF(AND(ISNUMBER(Q52),ISNUMBER(L52)),IFERROR(Q52/L52-1,""),"") | R53: =IF(AND(ISNUMBER(R52),ISNUMBER(M52)),IFERROR(R52/M52-1,""),"") | S53: =IF(AND(ISNUMBER(S52),ISNUMBER(N52)),IFERROR(S52/N52-1,""),"") | T53: =IF(AND(ISNUMBER(T52),ISNUMBER(O52)),IFERROR(T52/O52-1,""),"") | U53: =IF(AND(ISNUMBER(U52),ISNUMBER(P52)),IFERROR(U52/P52-1,""),"") | V53: =IF(AND(ISNUMBER(V52),ISNUMBER(Q52)),IFERROR(V52/Q52-1,""),"") | W53: =IF(AND(ISNUMBER(W52),ISNUMBER(R52)),IFERROR(W52/R52-1,""),"") | X53: =IF(AND(ISNUMBER(X52),ISNUMBER(S52)),IFERROR(X52/S52-1,""),"") | ... AL53: =IF(AND(ISNUMBER(AL52),ISNUMBER(AG52)),IFERROR(AL52/AG52-1,""),"") | AM53: =AM54+$AM$127 | AN53: =AN54+$AM$127 | AO53: =AO54+$AM$127 | AP53: =IF(AND(ISNUMBER(AP52),ISNUMBER(AK52)),IFERROR(AP52/AK52-1,""),"") | AQ53: =CHOOSE(MATCH($AU$2,{"Bull","Base","Bear"},0),$BD$60,$BE$60,$BF$60) | AR53: =CHOOSE(MATCH($AU$2,{"Bull","Base","Bear"},0),$BD$61,$BE$61,$BF$61) | AS53: =CHOOSE(MATCH($AU$2,{"Bull","Base","Bear"},0),$BD$62,$BE$62,$BF$62) | AT53: =CHOOSE(MATCH($AU$2,{"Bull","Base","Bear"},0),$BD$63,$BE$63,$BF$63) | BC53: 2031E | BD53: =BE53+$BD$49 | BE53: 0 | BF53: =BE53+$BF$49
B54: Q2–Q4/27E growth before revenue calibration (Q1/27 y/y) | AM54: =IFERROR(AL52/AG52-1,0) | AN54: =IFERROR(AL52/AG52-1,0) | AO54: =IFERROR(AL52/AG52-1,0) | BC54: LS_CAP (Life Sciences capital equipment y/y) | BD54: 0.03 | BE54: Δ → | BF54: -0.05 | BG54: Pharma / biopharma capital (backlog $110m).
B55: Service revenue | C55: 73.711 | D55: 77.015 | E55: 75.743 | F55: 79.537 | G55: 90.095 | H55: 101.16252 | I55: 110.379 | J55: 114.064 | K55: 118.288 | L55: 124.191 | M55: 32.19 | N55: 36.393 | O55: 36.4 | P55: 38.335 | Q55: 143.318 | R55: 32.151 | S55: 38.333 | T55: 37.082 | U55: 40.604 | V55: 148.17 | W55: 38.724 | X55: 38.248 | Y55: 41.658 | Z55: 45.972 | AA55: 164.602 | AB55: 32.184 | AC55: 32.808 | AD55: 36.643 | AE55: 36.446 | AF55: 138.081 | AG55: 33.3 | AH55: 35.8 | AI55: 36.5 | AJ55: 39.2 | AK55: 144.8 | AL55: 34 | AM55: =AH55*(1+AM56) | AN55: =AI55*(1+AN56) | AO55: =AJ55*(1+AO56) | AP55: =SUM(AL55,AM55,AN55,AO55) | AQ55: =AP55*(1+AQ56) | AR55: =AQ55*(1+AR56) | AS55: =AR55*(1+AS56) | AT55: =AS55*(1+AT56) | AW55: =IFERROR((AT55/AK55)^(1/5)-1,"n/m") | AX55: =IFERROR((AK55/L55)^(1/5)-1,"n/m") | AY55: =IFERROR((AK55/G55)^(1/10)-1,"n/m") | AZ55: =IFERROR((AK55/C55)^(1/14)-1,"n/m") | BC55: 2028E | BD55: =BE55+$BD$54 | BE55: 0.04 | BF55: =BE55+$BF$54
B56: y/y % | D56: =IF(AND(ISNUMBER(D55),ISNUMBER(C55)),IFERROR(D55/C55-1,""),"") | E56: =IF(AND(ISNUMBER(E55),ISNUMBER(D55)),IFERROR(E55/D55-1,""),"") | F56: =IF(AND(ISNUMBER(F55),ISNUMBER(E55)),IFERROR(F55/E55-1,""),"") | G56: =IF(AND(ISNUMBER(G55),ISNUMBER(F55)),IFERROR(G55/F55-1,""),"") | H56: =IF(AND(ISNUMBER(H55),ISNUMBER(G55)),IFERROR(H55/G55-1,""),"") | I56: =IF(AND(ISNUMBER(I55),ISNUMBER(H55)),IFERROR(I55/H55-1,""),"") | J56: =IF(AND(ISNUMBER(J55),ISNUMBER(I55)),IFERROR(J55/I55-1,""),"") | K56: =IF(AND(ISNUMBER(K55),ISNUMBER(J55)),IFERROR(K55/J55-1,""),"") | L56: =IF(AND(ISNUMBER(L55),ISNUMBER(K55)),IFERROR(L55/K55-1,""),"") | Q56: =IF(AND(ISNUMBER(Q55),ISNUMBER(L55)),IFERROR(Q55/L55-1,""),"") | R56: =IF(AND(ISNUMBER(R55),ISNUMBER(M55)),IFERROR(R55/M55-1,""),"") | S56: =IF(AND(ISNUMBER(S55),ISNUMBER(N55)),IFERROR(S55/N55-1,""),"") | T56: =IF(AND(ISNUMBER(T55),ISNUMBER(O55)),IFERROR(T55/O55-1,""),"") | U56: =IF(AND(ISNUMBER(U55),ISNUMBER(P55)),IFERROR(U55/P55-1,""),"") | V56: =IF(AND(ISNUMBER(V55),ISNUMBER(Q55)),IFERROR(V55/Q55-1,""),"") | W56: =IF(AND(ISNUMBER(W55),ISNUMBER(R55)),IFERROR(W55/R55-1,""),"") | X56: =IF(AND(ISNUMBER(X55),ISNUMBER(S55)),IFERROR(X55/S55-1,""),"") | ... AL56: =IF(AND(ISNUMBER(AL55),ISNUMBER(AG55)),IFERROR(AL55/AG55-1,""),"") | AM56: =AM57+$AM$127 | AN56: =AN57+$AM$127 | AO56: =AO57+$AM$127 | AP56: =IF(AND(ISNUMBER(AP55),ISNUMBER(AK55)),IFERROR(AP55/AK55-1,""),"") | AQ56: =CHOOSE(MATCH($AU$2,{"Bull","Base","Bear"},0),$BD$65,$BE$65,$BF$65) | AR56: =CHOOSE(MATCH($AU$2,{"Bull","Base","Bear"},0),$BD$66,$BE$66,$BF$66) | AS56: =CHOOSE(MATCH($AU$2,{"Bull","Base","Bear"},0),$BD$67,$BE$67,$BF$67) | AT56: =CHOOSE(MATCH($AU$2,{"Bull","Base","Bear"},0),$BD$68,$BE$68,$BF$68) | BC56: 2029E | BD56: =BE56+$BD$54 | BE56: 0.04 | BF56: =BE56+$BF$54
B57: Q2–Q4/27E growth before revenue calibration (Q1/27 y/y) | AM57: =IFERROR(AL55/AG55-1,0) | AN57: =IFERROR(AL55/AG55-1,0) | AO57: =IFERROR(AL55/AG55-1,0) | BC57: 2030E | BD57: =BE57+$BD$54 | BE57: 0.04 | BF57: =BE57+$BF$54
B58: Life Sciences — revenue | C58: =IF(ISNUMBER(C49),C49+C52+C55,"") | D58: =IF(ISNUMBER(D49),D49+D52+D55,"") | E58: =IF(ISNUMBER(E49),E49+E52+E55,"") | F58: =IF(ISNUMBER(F49),F49+F52+F55,"") | G58: =IF(ISNUMBER(G49),G49+G52+G55,"") | H58: =IF(ISNUMBER(H49),H49+H52+H55,"") | I58: =IF(ISNUMBER(I49),I49+I52+I55,"") | J58: =IF(ISNUMBER(J49),J49+J52+J55,"") | ... AT58: =IF(ISNUMBER(AT49),AT49+AT52+AT55,"") | AW58: =IFERROR((AT58/AK58)^(1/5)-1,"n/m") | AX58: =IFERROR((AK58/L58)^(1/5)-1,"n/m") | AY58: =IFERROR((AK58/G58)^(1/10)-1,"n/m") | AZ58: =IFERROR((AK58/C58)^(1/14)-1,"n/m") | BC58: 2031E | BD58: =BE58+$BD$54 | BE58: 0.04 | BF58: =BE58+$BF$54
B59: Revenue y/y % | D59: =IF(AND(ISNUMBER(D58),ISNUMBER(C58)),IFERROR(D58/C58-1,""),"") | E59: =IF(AND(ISNUMBER(E58),ISNUMBER(D58)),IFERROR(E58/D58-1,""),"") | F59: =IF(AND(ISNUMBER(F58),ISNUMBER(E58)),IFERROR(F58/E58-1,""),"") | G59: =IF(AND(ISNUMBER(G58),ISNUMBER(F58)),IFERROR(G58/F58-1,""),"") | H59: =IF(AND(ISNUMBER(H58),ISNUMBER(G58)),IFERROR(H58/G58-1,""),"") | I59: =IF(AND(ISNUMBER(I58),ISNUMBER(H58)),IFERROR(I58/H58-1,""),"") | J59: =IF(AND(ISNUMBER(J58),ISNUMBER(I58)),IFERROR(J58/I58-1,""),"") | K59: =IF(AND(ISNUMBER(K58),ISNUMBER(J58)),IFERROR(K58/J58-1,""),"") | L59: =IF(AND(ISNUMBER(L58),ISNUMBER(K58)),IFERROR(L58/K58-1,""),"") | Q59: =IF(AND(ISNUMBER(Q58),ISNUMBER(L58)),IFERROR(Q58/L58-1,""),"") | R59: =IF(AND(ISNUMBER(R58),ISNUMBER(M58)),IFERROR(R58/M58-1,""),"") | S59: =IF(AND(ISNUMBER(S58),ISNUMBER(N58)),IFERROR(S58/N58-1,""),"") | T59: =IF(AND(ISNUMBER(T58),ISNUMBER(O58)),IFERROR(T58/O58-1,""),"") | U59: =IF(AND(ISNUMBER(U58),ISNUMBER(P58)),IFERROR(U58/P58-1,""),"") | V59: =IF(AND(ISNUMBER(V58),ISNUMBER(Q58)),IFERROR(V58/Q58-1,""),"") | W59: =IF(AND(ISNUMBER(W58),ISNUMBER(R58)),IFERROR(W58/R58-1,""),"") | X59: =IF(AND(ISNUMBER(X58),ISNUMBER(S58)),IFERROR(X58/S58-1,""),"") | ... AP59: =IF(AND(ISNUMBER(AP58),ISNUMBER(AK58)),IFERROR(AP58/AK58-1,""),"") | AQ59: =IF(AND(ISNUMBER(AQ58),ISNUMBER(AP58)),IFERROR(AQ58/AP58-1,""),"") | AR59: =IF(AND(ISNUMBER(AR58),ISNUMBER(AQ58)),IFERROR(AR58/AQ58-1,""),"") | AS59: =IF(AND(ISNUMBER(AS58),ISNUMBER(AR58)),IFERROR(AS58/AR58-1,""),"") | AT59: =IF(AND(ISNUMBER(AT58),ISNUMBER(AS58)),IFERROR(AT58/AS58-1,""),"") | BC59: LS_CONS (Life Sciences consumables y/y) | BD59: 0.015 | BE59: Δ → | BF59: -0.03 | BG59: Barrier & cleaning chemistries for pharma manufacturing.
B60: % of total revenue | C60: =IF(AND(ISNUMBER(C58),ISNUMBER(C117)),IFERROR(C58/C117,""),"") | D60: =IF(AND(ISNUMBER(D58),ISNUMBER(D117)),IFERROR(D58/D117,""),"") | E60: =IF(AND(ISNUMBER(E58),ISNUMBER(E117)),IFERROR(E58/E117,""),"") | F60: =IF(AND(ISNUMBER(F58),ISNUMBER(F117)),IFERROR(F58/F117,""),"") | G60: =IF(AND(ISNUMBER(G58),ISNUMBER(G117)),IFERROR(G58/G117,""),"") | H60: =IF(AND(ISNUMBER(H58),ISNUMBER(H117)),IFERROR(H58/H117,""),"") | I60: =IF(AND(ISNUMBER(I58),ISNUMBER(I117)),IFERROR(I58/I117,""),"") | J60: =IF(AND(ISNUMBER(J58),ISNUMBER(J117)),IFERROR(J58/J117,""),"") | ... AT60: =IF(AND(ISNUMBER(AT58),ISNUMBER(AT117)),IFERROR(AT58/AT117,""),"") | BC60: 2028E | BD60: =BE60+$BD$59 | BE60: 0.06 | BF60: =BE60+$BF$59
B61: Recurring (consumables + service) % of segment revenue | C61: =IF(ISNUMBER(C52),IFERROR((C52+C55)/C58,""),"") | D61: =IF(ISNUMBER(D52),IFERROR((D52+D55)/D58,""),"") | E61: =IF(ISNUMBER(E52),IFERROR((E52+E55)/E58,""),"") | F61: =IF(ISNUMBER(F52),IFERROR((F52+F55)/F58,""),"") | G61: =IF(ISNUMBER(G52),IFERROR((G52+G55)/G58,""),"") | H61: =IF(ISNUMBER(H52),IFERROR((H52+H55)/H58,""),"") | I61: =IF(ISNUMBER(I52),IFERROR((I52+I55)/I58,""),"") | J61: =IF(ISNUMBER(J52),IFERROR((J52+J55)/J58,""),"") | ... AT61: =IF(ISNUMBER(AT52),IFERROR((AT52+AT55)/AT58,""),"") | BC61: 2029E | BD61: =BE61+$BD$59 | BE61: 0.06 | BF61: =BE61+$BF$59
B62: Memo: Life Sciences revenue as published (segment data) | C62: 226.658 | D62: 244.421 | E62: 246.122 | F62: 250.845 | G62: 295.97 | H62: 327.276 | I62: 361.59 | J62: 378.558 | K62: 416.939 | L62: 467.552 | M62: 121.471 | N62: 132.327 | O62: 127.908 | P62: 143.258 | Q62: 524.964 | R62: 132.207 | S62: 125.768 | T62: 121.273 | U62: 157.456 | V62: 536.704 | W62: 131.413 | X62: 133.095 | Y62: 146.566 | Z62: 160.628 | AA62: 571.702 | AB62: 128.478 | AC62: 127.945 | AD62: 136.382 | AE62: 149.466 | AF62: 542.271 | AG62: 135.2 | AH62: 145 | AI62: 145.8 | AJ62: 162.9 | AK62: 588.8 | AL62: 146.7 | BC62: 2030E | BD62: =BE62+$BD$59 | BE62: 0.06 | BF62: =BE62+$BF$59
B63: Check: revenue by type vs segment revenue (should be 0) | C63: =IF(AND(ISNUMBER(C58),ISNUMBER(C62)),IF(ABS(C58-C62)<=0.15,0,ROUND(C58-C62,1)),"") | D63: =IF(AND(ISNUMBER(D58),ISNUMBER(D62)),IF(ABS(D58-D62)<=0.15,0,ROUND(D58-D62,1)),"") | E63: =IF(AND(ISNUMBER(E58),ISNUMBER(E62)),IF(ABS(E58-E62)<=0.15,0,ROUND(E58-E62,1)),"") | F63: =IF(AND(ISNUMBER(F58),ISNUMBER(F62)),IF(ABS(F58-F62)<=0.15,0,ROUND(F58-F62,1)),"") | G63: =IF(AND(ISNUMBER(G58),ISNUMBER(G62)),IF(ABS(G58-G62)<=0.15,0,ROUND(G58-G62,1)),"") | H63: =IF(AND(ISNUMBER(H58),ISNUMBER(H62)),IF(ABS(H58-H62)<=0.15,0,ROUND(H58-H62,1)),"") | I63: =IF(AND(ISNUMBER(I58),ISNUMBER(I62)),IF(ABS(I58-I62)<=0.15,0,ROUND(I58-I62,1)),"") | J63: =IF(AND(ISNUMBER(J58),ISNUMBER(J62)),IF(ABS(J58-J62)<=0.15,0,ROUND(J58-J62,1)),"") | ... AL63: =IF(AND(ISNUMBER(AL58),ISNUMBER(AL62)),IF(ABS(AL58-AL62)<=0.15,0,ROUND(AL58-AL62,1)),"") | BC63: 2031E | BD63: =BE63+$BD$59 | BE63: 0.06 | BF63: =BE63+$BF$59
B64: Segment operating income (adjusted basis) | C64: 41.633 | D64: 47.453 | E64: 50.772 | F64: 56.094 | G64: 85.466 | H64: 96.983 | I64: 106.737 | J64: 132.129 | K64: 144.088 | L64: 180.796 | M64: 49.088 | N64: 57.519 | O64: 52.032 | P64: 57.549 | Q64: 216.188 | R64: 55.305 | S64: 48.619 | T64: 45.249 | U64: 61.052 | V64: 210.225 | W64: 49.841 | X64: 50.284 | Y64: 56.738 | Z64: 64.486 | AA64: 221.349 | AB64: 52.584 | AC64: 53.7 | AD64: 58.133 | AE64: 65.024 | AF64: 229.441 | AG64: 58.7 | AH64: 59.9 | AI64: 61.8 | AJ64: 70.6 | AK64: 251 | AL64: 61.8 | AM64: =AM58*AM65 | AN64: =AN58*AN65 | AO64: =AO58*AO65 | AP64: =SUM(AL64,AM64,AN64,AO64) | AQ64: =AQ58*AQ65 | AR64: =AR58*AR65 | AS64: =AS58*AS65 | AT64: =AT58*AT65 | AW64: =IFERROR((AT64/AK64)^(1/5)-1,"n/m") | AX64: =IFERROR((AK64/L64)^(1/5)-1,"n/m") | AY64: =IFERROR((AK64/G64)^(1/10)-1,"n/m") | AZ64: =IFERROR((AK64/C64)^(1/14)-1,"n/m") | BC64: LS_SERV (Life Sciences service y/y) | BD64: 0.01 | BE64: Δ → | BF64: -0.03 | BG64: Installed-base service (CECS divested Q4 FY24).
B65: Segment operating margin % | C65: =IF(AND(ISNUMBER(C64),ISNUMBER(C58)),IFERROR(C64/C58,""),"") | D65: =IF(AND(ISNUMBER(D64),ISNUMBER(D58)),IFERROR(D64/D58,""),"") | E65: =IF(AND(ISNUMBER(E64),ISNUMBER(E58)),IFERROR(E64/E58,""),"") | F65: =IF(AND(ISNUMBER(F64),ISNUMBER(F58)),IFERROR(F64/F58,""),"") | G65: =IF(AND(ISNUMBER(G64),ISNUMBER(G58)),IFERROR(G64/G58,""),"") | H65: =IF(AND(ISNUMBER(H64),ISNUMBER(H58)),IFERROR(H64/H58,""),"") | I65: =IF(AND(ISNUMBER(I64),ISNUMBER(I58)),IFERROR(I64/I58,""),"") | J65: =IF(AND(ISNUMBER(J64),ISNUMBER(J58)),IFERROR(J64/J58,""),"") | ... AL65: =IF(AND(ISNUMBER(AL64),ISNUMBER(AL58)),IFERROR(AL64/AL58,""),"") | AM65: =AM66+$AM$134 | AN65: =AN66+$AM$134 | AO65: =AO66+$AM$134 | AP65: =IF(AND(ISNUMBER(AP64),ISNUMBER(AP58)),IFERROR(AP64/AP58,""),"") | AQ65: =CHOOSE(MATCH($AU$2,{"Bull","Base","Bear"},0),$BD$80,$BE$80,$BF$80) | AR65: =CHOOSE(MATCH($AU$2,{"Bull","Base","Bear"},0),$BD$81,$BE$81,$BF$81) | AS65: =CHOOSE(MATCH($AU$2,{"Bull","Base","Bear"},0),$BD$82,$BE$82,$BF$82) | AT65: =CHOOSE(MATCH($AU$2,{"Bull","Base","Bear"},0),$BD$83,$BE$83,$BF$83) | AW65: =IFERROR(AVERAGE(AP65,AQ65,AR65,AS65,AT65),"n/m") | AX65: =IFERROR(AVERAGE(Q65,V65,AA65,AF65,AK65),"n/m") | AY65: =IFERROR(AVERAGE(H65,I65,J65,K65,L65,Q65,V65,AA65,AF65,AK65),"n/m") | AZ65: =IFERROR(AVERAGE(C65,D65,E65,F65,G65,H65,I65,J65,K65,L65,Q65,V65,AA65,AF65,AK65),"n/m") | BC65: 2028E | BD65: =BE65+$BD$64 | BE65: 0.04 | BF65: =BE65+$BF$64
B66: Q2–Q4/27E margin before EPS-outlook calibration (prior-year quarter + Q1/27 y/y drift) | AM66: =AH65+IFERROR(AL64/AL58-AG64/AG58,0) | AN66: =AI65+IFERROR(AL64/AL58-AG64/AG58,0) | AO66: =AJ65+IFERROR(AL64/AL58-AG64/AG58,0) | BC66: 2029E | BD66: =BE66+$BD$64 | BE66: 0.04 | BF66: =BE66+$BF$64
B67: Incremental segment margin (Δ operating income / Δ revenue) | D67: =IFERROR((D64-C64)/(D58-C58),"") | E67: =IFERROR((E64-D64)/(E58-D58),"") | F67: =IFERROR((F64-E64)/(F58-E58),"") | G67: =IFERROR((G64-F64)/(G58-F58),"") | H67: =IFERROR((H64-G64)/(H58-G58),"") | I67: =IFERROR((I64-H64)/(I58-H58),"") | J67: =IFERROR((J64-I64)/(J58-I58),"") | K67: =IFERROR((K64-J64)/(K58-J58),"") | L67: =IFERROR((L64-K64)/(L58-K58),"") | Q67: =IFERROR((Q64-L64)/(Q58-L58),"") | R67: =IFERROR((R64-M64)/(R58-M58),"") | S67: =IFERROR((S64-N64)/(S58-N58),"") | T67: =IFERROR((T64-O64)/(T58-O58),"") | U67: =IFERROR((U64-P64)/(U58-P58),"") | V67: =IFERROR((V64-Q64)/(V58-Q58),"") | W67: =IFERROR((W64-R64)/(W58-R58),"") | X67: =IFERROR((X64-S64)/(X58-S58),"") | ... AP67: =IFERROR((AP64-AK64)/(AP58-AK58),"") | AQ67: =IFERROR((AQ64-AP64)/(AQ58-AP58),"") | AR67: =IFERROR((AR64-AQ64)/(AR58-AQ58),"") | AS67: =IFERROR((AS64-AR64)/(AS58-AR58),"") | AT67: =IFERROR((AT64-AS64)/(AT58-AS58),"") | BC67: 2030E | BD67: =BE67+$BD$64 | BE67: 0.04 | BF67: =BE67+$BF$64
BC68: 2031E | BD68: =BE68+$BD$64 | BE68: 0.04 | BF68: =BE68+$BF$64
B69: Dental (Cantel, Jun-2021 – Sep-2024) — discontinued operations from the Q4 FY24 release; FY2023+ on the restated basis | AU69: DENTAL / OTHER — as originally reported in FY2022 (sold to Peak Rock Capital, 9-Sep-2024) | BC69: HC_M (Healthcare segment operating margin) | BD69: 0.01 | BE69: Δ → | BF69: -0.02 | BG69: FY26 24.6%; FY27E ~24.8% (calibrated to the EPS outlook). Volume / price / productivity vs tariffs and inflation (~+30 bps p.a.).
B70: Dental revenue (FY2022 as reported; discontinued from FY2023 restated) | C70: 0 | D70: 0 | E70: 0 | F70: 0 | G70: 0 | H70: 0 | I70: 0 | J70: 0 | K70: 0 | L70: 0 | M70: 35.232 | N70: 115.632 | O70: 105.09 | P70: 105.707 | Q70: 361.661 | R70: 0 | S70: 0 | T70: 0 | U70: 0 | V70: 0 | W70: 0 | X70: 0 | Y70: 0 | Z70: 0 | AA70: 0 | AB70: 0 | AC70: 0 | AD70: 0 | AE70: 0 | AF70: 0 | AG70: 0 | AH70: 0 | AI70: 0 | AJ70: 0 | AK70: 0 | AL70: 0 | AM70: =0 | AN70: =0 | AO70: =0 | AP70: =SUM(AL70,AM70,AN70,AO70) | AQ70: =0 | AR70: =0 | AS70: =0 | AT70: =0 | BC70: 2028E | BD70: =BE70+$BD$69 | BE70: 0.251 | BF70: =BE70+$BF$69
B71: Dental segment operating income | C71: 0 | D71: 0 | E71: 0 | F71: 0 | G71: 0 | H71: 0 | I71: 0 | J71: 0 | K71: 0 | L71: 0 | M71: 10.119 | N71: 32.392 | O71: 23.096 | P71: 18.834 | Q71: 84.441 | R71: 0 | S71: 0 | T71: 0 | U71: 0 | V71: 0 | W71: 0 | X71: 0 | Y71: 0 | Z71: 0 | AA71: 0 | AB71: 0 | AC71: 0 | AD71: 0 | AE71: 0 | AF71: 0 | AG71: 0 | AH71: 0 | AI71: 0 | AJ71: 0 | AK71: 0 | AL71: 0 | AM71: =0 | AN71: =0 | AO71: =0 | AP71: =SUM(AL71,AM71,AN71,AO71) | AQ71: =0 | AR71: =0 | AS71: =0 | AT71: =0 | BC71: 2029E | BD71: =BE71+$BD$69 | BE71: 0.254 | BF71: =BE71+$BF$69
B72: Corporate & other revenue (Defense & Industrial, FY2012–17) | C72: 2.793 | D72: 3.141 | E72: 1.896 | F72: 1.869 | G72: 2.656 | H72: 6.196 | I72: 0 | J72: 0 | K72: 0 | L72: 0 | M72: 0 | N72: 0 | O72: 0 | P72: 0 | Q72: 0 | R72: 0 | S72: 0 | T72: 0 | U72: 0 | V72: 0 | W72: 0 | X72: 0 | Y72: 0 | Z72: 0 | AA72: 0 | AB72: 0 | AC72: 0 | AD72: 0 | AE72: 0 | AF72: 0 | AG72: 0 | AH72: 0 | AI72: 0 | AJ72: 0 | AK72: 0 | AL72: 0 | AM72: =0 | AN72: =0 | AO72: =0 | AP72: =SUM(AL72,AM72,AN72,AO72) | AQ72: =0 | AR72: =0 | AS72: =0 | AT72: =0 | BC72: 2030E | BD72: =BE72+$BD$69 | BE72: 0.257 | BF72: =BE72+$BF$69
BC73: 2031E | BD73: =BE73+$BD$69 | BE73: 0.26 | BF73: =BE73+$BF$69
B74: Corporate costs (adjusted basis; reported separately from FY2019 — partially allocated to segments before) | AU74: CORPORATE — public-company, corporate functions, shared distribution & R&D, legacy pension; tariff refunds (FY27) | BC74: AST_M (AST segment operating margin) | BD74: 0.01 | BE74: Δ → | BF74: -0.02 | BG74: FY26 46.1%; high fixed-cost network — operating leverage on volume.
B75: Corporate operating loss (adjusted) | C75: -8.655 | D75: -7.932 | E75: -8.142 | F75: -9.541 | G75: -11.488 | H75: -14.433 | I75: -17.439 | J75: -184.9 | K75: -207.015 | L75: -219.153 | M75: -75.06 | N75: -71.552 | O75: -55.849 | P75: -57.598 | Q75: -260.059 | R75: -75.77 | S75: -67.452 | T75: -53.145 | U75: -68.607 | V75: -264.974 | W75: -91.873 | X75: -87.02 | Y75: -81.559 | Z75: -88.044 | AA75: -348.497 | AB75: -101.748 | AC75: -97.129 | AD75: -100.843 | AE75: -99.314 | AF75: -399.033 | AG75: -114 | AH75: -109.9 | AI75: -106 | AJ75: -100 | AK75: -430.1 | AL75: -110.1 | AM75: =AH75*(1+AM76) | AN75: =AI75*(1+AN76) | AO75: =AJ75*(1+AO76) | AP75: =SUM(AL75,AM75,AN75,AO75) | AQ75: =AQ159*AQ77 | AR75: =AR159*AR77 | AS75: =AS159*AS77 | AT75: =AT159*AT77 | AU75: FY2012–15: plug = adjusted operating income − adjusted segment operating income. Q2–Q4/27E: prior-year quarter × (1 + Q1/27 y/y). 2028E+: % of revenue. | BC75: 2028E | BD75: =BE75+$BD$74 | BE75: 0.453 | BF75: =BE75+$BF$74
B76: Corporate cost y/y % | D76: =IF(AND(ISNUMBER(D75),ISNUMBER(C75)),IFERROR(D75/C75-1,""),"") | E76: =IF(AND(ISNUMBER(E75),ISNUMBER(D75)),IFERROR(E75/D75-1,""),"") | F76: =IF(AND(ISNUMBER(F75),ISNUMBER(E75)),IFERROR(F75/E75-1,""),"") | G76: =IF(AND(ISNUMBER(G75),ISNUMBER(F75)),IFERROR(G75/F75-1,""),"") | H76: =IF(AND(ISNUMBER(H75),ISNUMBER(G75)),IFERROR(H75/G75-1,""),"") | I76: =IF(AND(ISNUMBER(I75),ISNUMBER(H75)),IFERROR(I75/H75-1,""),"") | J76: =IF(AND(ISNUMBER(J75),ISNUMBER(I75)),IFERROR(J75/I75-1,""),"") | K76: =IF(AND(ISNUMBER(K75),ISNUMBER(J75)),IFERROR(K75/J75-1,""),"") | L76: =IF(AND(ISNUMBER(L75),ISNUMBER(K75)),IFERROR(L75/K75-1,""),"") | Q76: =IF(AND(ISNUMBER(Q75),ISNUMBER(L75)),IFERROR(Q75/L75-1,""),"") | R76: =IF(AND(ISNUMBER(R75),ISNUMBER(M75)),IFERROR(R75/M75-1,""),"") | S76: =IF(AND(ISNUMBER(S75),ISNUMBER(N75)),IFERROR(S75/N75-1,""),"") | T76: =IF(AND(ISNUMBER(T75),ISNUMBER(O75)),IFERROR(T75/O75-1,""),"") | U76: =IF(AND(ISNUMBER(U75),ISNUMBER(P75)),IFERROR(U75/P75-1,""),"") | V76: =IF(AND(ISNUMBER(V75),ISNUMBER(Q75)),IFERROR(V75/Q75-1,""),"") | W76: =IF(AND(ISNUMBER(W75),ISNUMBER(R75)),IFERROR(W75/R75-1,""),"") | X76: =IF(AND(ISNUMBER(X75),ISNUMBER(S75)),IFERROR(X75/S75-1,""),"") | ... AL76: =IF(AND(ISNUMBER(AL75),ISNUMBER(AG75)),IFERROR(AL75/AG75-1,""),"") | AM76: =IFERROR(AL75/AG75-1,0) | AN76: =IFERROR(AL75/AG75-1,0) | AO76: =IFERROR(AL75/AG75-1,0) | AP76: =IF(AND(ISNUMBER(AP75),ISNUMBER(AK75)),IFERROR(AP75/AK75-1,""),"") | AQ76: =IF(AND(ISNUMBER(AQ75),ISNUMBER(AP75)),IFERROR(AQ75/AP75-1,""),"") | AR76: =IF(AND(ISNUMBER(AR75),ISNUMBER(AQ75)),IFERROR(AR75/AQ75-1,""),"") | AS76: =IF(AND(ISNUMBER(AS75),ISNUMBER(AR75)),IFERROR(AS75/AR75-1,""),"") | AT76: =IF(AND(ISNUMBER(AT75),ISNUMBER(AS75)),IFERROR(AT75/AS75-1,""),"") | BC76: 2029E | BD76: =BE76+$BD$74 | BE76: 0.456 | BF76: =BE76+$BF$74
B77: Corporate cost % of revenue | C77: =IF(AND(ISNUMBER(C75),ISNUMBER(C159)),IFERROR(C75/C159,""),"") | D77: =IF(AND(ISNUMBER(D75),ISNUMBER(D159)),IFERROR(D75/D159,""),"") | E77: =IF(AND(ISNUMBER(E75),ISNUMBER(E159)),IFERROR(E75/E159,""),"") | F77: =IF(AND(ISNUMBER(F75),ISNUMBER(F159)),IFERROR(F75/F159,""),"") | G77: =IF(AND(ISNUMBER(G75),ISNUMBER(G159)),IFERROR(G75/G159,""),"") | H77: =IF(AND(ISNUMBER(H75),ISNUMBER(H159)),IFERROR(H75/H159,""),"") | I77: =IF(AND(ISNUMBER(I75),ISNUMBER(I159)),IFERROR(I75/I159,""),"") | J77: =IF(AND(ISNUMBER(J75),ISNUMBER(J159)),IFERROR(J75/J159,""),"") | ... AP77: =IF(AND(ISNUMBER(AP75),ISNUMBER(AP159)),IFERROR(AP75/AP159,""),"") | AQ77: -0.071 | AR77: -0.071 | AS77: -0.071 | AT77: -0.071 | AW77: =IFERROR(AVERAGE(AP77,AQ77,AR77,AS77,AT77),"n/m") | AX77: =IFERROR(AVERAGE(Q77,V77,AA77,AF77,AK77),"n/m") | AY77: =IFERROR(AVERAGE(H77,I77,J77,K77,L77,Q77,V77,AA77,AF77,AK77),"n/m") | AZ77: =IFERROR(AVERAGE(C77,D77,E77,F77,G77,H77,I77,J77,K77,L77,Q77,V77,AA77,AF77,AK77),"n/m") | BC77: 2030E | BD77: =BE77+$BD$74 | BE77: 0.459 | BF77: =BE77+$BF$74
BC78: 2031E | BD78: =BE78+$BD$74 | BE78: 0.462 | BF78: =BE78+$BF$74
B79: Revenue by type (all segments; recurring = consumables + service) | AU79: MIX — outputs | BC79: LS_M (Life Sciences segment operating margin) | BD79: 0.01 | BE79: Δ → | BF79: -0.02 | BG79: FY26 42.6%; FY27E calibrated ~40.8%.
B80: Capital equipment revenue | C80: =IF(ISNUMBER(C11),C11+C35+C49,"") | D80: =IF(ISNUMBER(D11),D11+D35+D49,"") | E80: =IF(ISNUMBER(E11),E11+E35+E49,"") | F80: =IF(ISNUMBER(F11),F11+F35+F49,"") | G80: =IF(ISNUMBER(G11),G11+G35+G49,"") | H80: =IF(ISNUMBER(H11),H11+H35+H49,"") | I80: =IF(ISNUMBER(I11),I11+I35+I49,"") | J80: =IF(ISNUMBER(J11),J11+J35+J49,"") | ... AT80: =IF(ISNUMBER(AT11),AT11+AT35+AT49,"") | AW80: =IFERROR((AT80/AK80)^(1/5)-1,"n/m") | AX80: =IFERROR((AK80/L80)^(1/5)-1,"n/m") | AY80: =IFERROR((AK80/G80)^(1/10)-1,"n/m") | AZ80: =IFERROR((AK80/C80)^(1/14)-1,"n/m") | BC80: 2028E | BD80: =BE80+$BD$79 | BE80: 0.413 | BF80: =BE80+$BF$79
B81: Consumables revenue | C81: =IF(ISNUMBER(C14),C14+C52,"") | D81: =IF(ISNUMBER(D14),D14+D52,"") | E81: =IF(ISNUMBER(E14),E14+E52,"") | F81: =IF(ISNUMBER(F14),F14+F52,"") | G81: =IF(ISNUMBER(G14),G14+G52,"") | H81: =IF(ISNUMBER(H14),H14+H52,"") | I81: =IF(ISNUMBER(I14),I14+I52,"") | J81: =IF(ISNUMBER(J14),J14+J52,"") | ... AT81: =IF(ISNUMBER(AT14),AT14+AT52,"") | AW81: =IFERROR((AT81/AK81)^(1/5)-1,"n/m") | AX81: =IFERROR((AK81/L81)^(1/5)-1,"n/m") | AY81: =IFERROR((AK81/G81)^(1/10)-1,"n/m") | AZ81: =IFERROR((AK81/C81)^(1/14)-1,"n/m") | BC81: 2029E | BD81: =BE81+$BD$79 | BE81: 0.416 | BF81: =BE81+$BF$79
B82: Service revenue | C82: =IF(ISNUMBER(C17),C17+C32+C55,"") | D82: =IF(ISNUMBER(D17),D17+D32+D55,"") | E82: =IF(ISNUMBER(E17),E17+E32+E55,"") | F82: =IF(ISNUMBER(F17),F17+F32+F55,"") | G82: =IF(ISNUMBER(G17),G17+G32+G55,"") | H82: =IF(ISNUMBER(H17),H17+H32+H55,"") | I82: =IF(ISNUMBER(I17),I17+I32+I55,"") | J82: =IF(ISNUMBER(J17),J17+J32+J55,"") | ... AT82: =IF(ISNUMBER(AT17),AT17+AT32+AT55,"") | AW82: =IFERROR((AT82/AK82)^(1/5)-1,"n/m") | AX82: =IFERROR((AK82/L82)^(1/5)-1,"n/m") | AY82: =IFERROR((AK82/G82)^(1/10)-1,"n/m") | AZ82: =IFERROR((AK82/C82)^(1/14)-1,"n/m") | BC82: 2030E | BD82: =BE82+$BD$79 | BE82: 0.419 | BF82: =BE82+$BF$79
B83: Recurring revenue % of total | C83: =IF(ISNUMBER(C81),IFERROR((C81+C82)/C117,""),"") | D83: =IF(ISNUMBER(D81),IFERROR((D81+D82)/D117,""),"") | E83: =IF(ISNUMBER(E81),IFERROR((E81+E82)/E117,""),"") | F83: =IF(ISNUMBER(F81),IFERROR((F81+F82)/F117,""),"") | G83: =IF(ISNUMBER(G81),IFERROR((G81+G82)/G117,""),"") | H83: =IF(ISNUMBER(H81),IFERROR((H81+H82)/H117,""),"") | I83: =IF(ISNUMBER(I81),IFERROR((I81+I82)/I117,""),"") | J83: =IF(ISNUMBER(J81),IFERROR((J81+J82)/J117,""),"") | ... AT83: =IF(ISNUMBER(AT81),IFERROR((AT81+AT82)/AT117,""),"") | AW83: =IFERROR(AVERAGE(AP83,AQ83,AR83,AS83,AT83),"n/m") | AX83: =IFERROR(AVERAGE(Q83,V83,AA83,AF83,AK83),"n/m") | AY83: =IFERROR(AVERAGE(H83,I83,J83,K83,L83,Q83,V83,AA83,AF83,AK83),"n/m") | AZ83: =IFERROR(AVERAGE(C83,D83,E83,F83,G83,H83,I83,J83,K83,L83,Q83,V83,AA83,AF83,AK83),"n/m") | BC83: 2031E | BD83: =BE83+$BD$79 | BE83: 0.422 | BF83: =BE83+$BF$79
B84: Capital equipment y/y % | D84: =IF(AND(ISNUMBER(D80),ISNUMBER(C80)),IFERROR(D80/C80-1,""),"") | E84: =IF(AND(ISNUMBER(E80),ISNUMBER(D80)),IFERROR(E80/D80-1,""),"") | F84: =IF(AND(ISNUMBER(F80),ISNUMBER(E80)),IFERROR(F80/E80-1,""),"") | G84: =IF(AND(ISNUMBER(G80),ISNUMBER(F80)),IFERROR(G80/F80-1,""),"") | H84: =IF(AND(ISNUMBER(H80),ISNUMBER(G80)),IFERROR(H80/G80-1,""),"") | I84: =IF(AND(ISNUMBER(I80),ISNUMBER(H80)),IFERROR(I80/H80-1,""),"") | J84: =IF(AND(ISNUMBER(J80),ISNUMBER(I80)),IFERROR(J80/I80-1,""),"") | K84: =IF(AND(ISNUMBER(K80),ISNUMBER(J80)),IFERROR(K80/J80-1,""),"") | L84: =IF(AND(ISNUMBER(L80),ISNUMBER(K80)),IFERROR(L80/K80-1,""),"") | Q84: =IF(AND(ISNUMBER(Q80),ISNUMBER(L80)),IFERROR(Q80/L80-1,""),"") | R84: =IF(AND(ISNUMBER(R80),ISNUMBER(M80)),IFERROR(R80/M80-1,""),"") | S84: =IF(AND(ISNUMBER(S80),ISNUMBER(N80)),IFERROR(S80/N80-1,""),"") | T84: =IF(AND(ISNUMBER(T80),ISNUMBER(O80)),IFERROR(T80/O80-1,""),"") | U84: =IF(AND(ISNUMBER(U80),ISNUMBER(P80)),IFERROR(U80/P80-1,""),"") | V84: =IF(AND(ISNUMBER(V80),ISNUMBER(Q80)),IFERROR(V80/Q80-1,""),"") | W84: =IF(AND(ISNUMBER(W80),ISNUMBER(R80)),IFERROR(W80/R80-1,""),"") | X84: =IF(AND(ISNUMBER(X80),ISNUMBER(S80)),IFERROR(X80/S80-1,""),"") | ... AP84: =IF(AND(ISNUMBER(AP80),ISNUMBER(AK80)),IFERROR(AP80/AK80-1,""),"") | AQ84: =IF(AND(ISNUMBER(AQ80),ISNUMBER(AP80)),IFERROR(AQ80/AP80-1,""),"") | AR84: =IF(AND(ISNUMBER(AR80),ISNUMBER(AQ80)),IFERROR(AR80/AQ80-1,""),"") | AS84: =IF(AND(ISNUMBER(AS80),ISNUMBER(AR80)),IFERROR(AS80/AR80-1,""),"") | AT84: =IF(AND(ISNUMBER(AT80),ISNUMBER(AS80)),IFERROR(AT80/AS80-1,""),"") | BC84: M&A_spend (tuck-in acquisitions, $m) | BD84: 150 | BE84: Δ → | BF84: -150 | BG84: STERIS spent $16–55m p.a. on tuck-ins (FY25–Q1/27) besides BD instruments ($540m, FY24) and Cantel ($4.6bn incl. debt, FY22). Base $150m p.a.
B85: Recurring revenue y/y % | D85: =IFERROR((D81+D82)/(C81+C82)-1,"") | E85: =IFERROR((E81+E82)/(D81+D82)-1,"") | F85: =IFERROR((F81+F82)/(E81+E82)-1,"") | G85: =IFERROR((G81+G82)/(F81+F82)-1,"") | H85: =IFERROR((H81+H82)/(G81+G82)-1,"") | I85: =IFERROR((I81+I82)/(H81+H82)-1,"") | J85: =IFERROR((J81+J82)/(I81+I82)-1,"") | K85: =IFERROR((K81+K82)/(J81+J82)-1,"") | L85: =IFERROR((L81+L82)/(K81+K82)-1,"") | Q85: =IFERROR((Q81+Q82)/(L81+L82)-1,"") | R85: =IFERROR((R81+R82)/(M81+M82)-1,"") | S85: =IFERROR((S81+S82)/(N81+N82)-1,"") | T85: =IFERROR((T81+T82)/(O81+O82)-1,"") | U85: =IFERROR((U81+U82)/(P81+P82)-1,"") | V85: =IFERROR((V81+V82)/(Q81+Q82)-1,"") | W85: =IFERROR((W81+W82)/(R81+R82)-1,"") | X85: =IFERROR((X81+X82)/(S81+S82)-1,"") | ... AP85: =IFERROR((AP81+AP82)/(AK81+AK82)-1,"") | AQ85: =IFERROR((AQ81+AQ82)/(AP81+AP82)-1,"") | AR85: =IFERROR((AR81+AR82)/(AQ81+AQ82)-1,"") | AS85: =IFERROR((AS81+AS82)/(AR81+AR82)-1,"") | AT85: =IFERROR((AT81+AT82)/(AS81+AS82)-1,"") | BC85: 2028E | BD85: =MAX(0,BE85+$BD$84) | BE85: 150 | BF85: =MAX(0,BE85+$BF$84)
BC86: 2029E | BD86: =MAX(0,BE86+$BD$84) | BE86: 150 | BF86: =MAX(0,BE86+$BF$84)
B87: Revenue growth bridge — as reported → organic → constant-currency organic (company definitions; table published from FY2017) | AU87: ORGANIC — acquisitions organic from the 13th month; divestitures removed from the prior-year base; FX at prior-year rates | BC87: 2030E | BD87: =MAX(0,BE87+$BD$84) | BE87: 150 | BF87: =MAX(0,BE87+$BF$84)
B88: Revenue (as presented in the bridge; FY2023 – Q3 FY24 incl. Dental) | H88: 2612.756 | I88: 2619.996 | J88: 2782.17 | K88: 3030.895 | L88: 3107.519 | M88: 968.422 | N88: 1196.985 | O88: 1208.971 | P88: 1210.686 | Q88: 4585.064 | R88: 1156.491 | S88: 1200.517 | T88: 1215.994 | U88: 1384.837 | V88: 4957.839 | W88: 1284.542 | X88: 1342.36 | Y88: 1395.645 | Z88: 1419.387 | AA88: 5138.701 | AB88: 1279.502 | AC88: 1328.912 | AD88: 1370.57 | AE88: 1480.531 | AF88: 5459.515 | AG88: 1391.1 | AH88: 1460.3 | AI88: 1496.2 | AJ88: 1588.4 | AK88: 5935.9 | AL88: 1492.7 | AM88: =AM159 | AN88: =AN159 | AO88: =AO159 | AP88: =SUM(AL88,AM88,AN88,AO88) | AQ88: =AQ159 | AR88: =AR159 | AS88: =AS159 | AT88: =AT159 | BC88: 2031E | BD88: =MAX(0,BE88+$BD$84) | BE88: 150 | BF88: =MAX(0,BE88+$BF$84)
B89: Prior-year revenue (as presented in the bridge) | H89: 2238.764 | I89: 2612.756 | J89: 2619.996 | K89: 2782.17 | L89: 3030.895 | M89: 668.932 | N89: 756.132 | O89: 808.924 | P89: 873.531 | Q89: 3107.519 | R89: 968.422 | S89: 1196.985 | T89: 1208.971 | U89: 1210.686 | V89: 4585.064 | W89: 1156.491 | X89: 1200.517 | Y89: 1215.994 | Z89: 1281.252 | AA89: 4536.266 | AB89: 1183.386 | AC89: 1238.204 | AD89: 1297.724 | AE89: 1419.387 | AF89: 5138.701 | AG89: 1279.5 | AH89: 1328.9 | AI89: 1370.6 | AJ89: 1480.5 | AK89: 5459.5 | AL89: 1391.1 | AM89: =AH159 | AN89: =AI159 | AO89: =AJ159 | AP89: =SUM(AL89,AM89,AN89,AO89) | AQ89: =AP159 | AR89: =AQ159 | AS89: =AR159 | AT89: =AS159
B90: Impact of acquisitions ($m) | H90: 378.379 | I90: 7.432 | J90: 0 | K90: 0 | L90: 48.928 | M90: 141.341 | N90: 346.073 | O90: 332.746 | P90: 253.225 | Q90: 1073.099 | R90: 166.209 | S90: 0 | T90: 0 | U90: 0 | V90: 166.209 | W90: 0 | X90: 28.948 | Y90: 45.342 | Z90: 44.995 | AA90: 119.285 | AB90: 40.976 | AC90: 11.397 | AD90: 0 | AE90: 0 | AF90: 52.373 | AG90: 0 | AH90: 0 | AI90: 0 | AJ90: 2.4 | AK90: 2.4 | AL90: 6.9 | AM90: 7 | AN90: 7 | AO90: 7 | AP90: =SUM(AL90,AM90,AN90,AO90) | AQ90: =AQ107 | AR90: =AR107 | AS90: =AS107 | AT90: =AT107 | AU90: Q2–Q4/27E input: Healthcare tuck-ins not in the prior-year quarter (Q1/27 impact of acquisitions $6.9m).
B91: Impact of divestitures (prior-year revenue removed, $m) | H91: -85.466 | I91: -143.011 | J91: -25.907 | K91: -4.485 | L91: 0 | M91: 0 | N91: 0 | O91: 0 | P91: 0 | Q91: 0 | R91: -14.753 | S91: -45.047 | T91: -47.334 | U91: 0 | V91: -107.133 | W91: 0 | X91: 0 | Y91: 0 | Z91: 0 | AA91: 0 | AB91: -7.881 | AC91: -8.918 | AD91: -7.84 | AE91: -9.958 | AF91: -34.598 | AG91: 0 | AH91: 0 | AI91: 0 | AJ91: 0 | AK91: 0 | AL91: 0 | AM91: =0 | AN91: =0 | AO91: =0 | AP91: =SUM(AL91,AM91,AN91,AO91) | AQ91: =0 | AR91: =0 | AS91: =0 | AT91: =0
B92: Impact of foreign currency ($m) | H92: -25.296 | I92: 20.077 | J92: -9.719 | K92: -20.362 | L92: 24.046 | M92: 18.103 | N92: 6.383 | O92: -2.427 | P92: -10.356 | Q92: 11.651 | R92: -23.85 | S92: -36.512 | T92: -31.065 | U92: -18.023 | V92: -109.45 | W92: -0.583 | X92: 13.506 | Y92: 12.396 | Z92: 4.062 | AA92: 27.654 | AB92: -2.876 | AC92: 2.057 | AD92: 0.389 | AE92: -11.652 | AF92: -12.082 | AG92: 11.8 | AH92: 12.7 | AI92: 18.4 | AJ92: 31.5 | AK92: 74.4 | AL92: 8.4 | AM92: 7 | AN92: 7 | AO92: 6 | AP92: =SUM(AL92,AM92,AN92,AO92) | AQ92: 0 | AR92: 0 | AS92: 0 | AT92: 0 | AU92: Q2–Q4/27E: slightly favourable currency (FY27 outlook: as-reported growth 7–8% vs constant-currency organic 6–7%, incl. tuck-ins).
B93: Revenue growth as reported % | H93: 0.167 | I93: 0.003 | J93: 0.062 | K93: 0.089 | L93: 0.025 | M93: 0.448 | N93: 0.583 | O93: 0.495 | P93: 0.386 | Q93: 0.475 | R93: 0.194 | S93: 0.003 | T93: 0.006 | U93: 0.144 | V93: 0.081 | W93: 0.111 | X93: 0.118 | Y93: 0.148 | Z93: 0.108 | AA93: 0.133 | AB93: 0.081 | AC93: 0.073 | AD93: 0.056 | AE93: 0.043 | AF93: 0.062 | AG93: 0.087 | AH93: 0.099 | AI93: 0.092 | AJ93: 0.073 | AK93: 0.087 | AL93: 0.073 | AM93: =IFERROR(AM88/AM89-1,"") | AN93: =IFERROR(AN88/AN89-1,"") | AO93: =IFERROR(AO88/AO89-1,"") | AP93: =IFERROR(AP88/AP89-1,"") | AQ93: =IFERROR(AQ88/AQ89-1,"") | AR93: =IFERROR(AR88/AR89-1,"") | AS93: =IFERROR(AS88/AS89-1,"") | AT93: =IFERROR(AT88/AT89-1,"")
B94: Organic growth % (published) | H94: 0.038 | I94: 0.058 | J94: 0.073 | K94: 0.091 | L94: 0.009 | M94: 0.236 | N94: 0.125 | O94: 0.083 | P94: 0.096 | Q94: 0.13 | R94: 0.038 | S94: 0.042 | T94: 0.047 | U94: 0.144 | V94: 0.07 | W94: 0.111 | X94: 0.094 | Y94: 0.11 | Z94: 0.073 | AA94: 0.107 | AB94: 0.054 | AC94: 0.072 | AD94: 0.063 | AE94: 0.05 | AF94: 0.059 | AG94: 0.087 | AH94: 0.099 | AI94: 0.092 | AJ94: 0.071 | AK94: 0.087 | AL94: 0.068 | AM94: =IFERROR((AM88-AM90)/(AM89+AM91)-1,"") | AN94: =IFERROR((AN88-AN90)/(AN89+AN91)-1,"") | AO94: =IFERROR((AO88-AO90)/(AO89+AO91)-1,"") | AP94: =IFERROR((AP88-AP90)/(AP89+AP91)-1,"") | AQ94: =IFERROR((AQ88-AQ90)/(AQ89+AQ91)-1,"") | AR94: =IFERROR((AR88-AR90)/(AR89+AR91)-1,"") | AS94: =IFERROR((AS88-AS90)/(AS89+AS91)-1,"") | AT94: =IFERROR((AT88-AT90)/(AT89+AT91)-1,"") | AW94: =IFERROR(AVERAGE(AP94,AQ94,AR94,AS94,AT94),"n/m") | AX94: =IFERROR(AVERAGE(Q94,V94,AA94,AF94,AK94),"n/m") | AY94: =IFERROR(AVERAGE(H94,I94,J94,K94,L94,Q94,V94,AA94,AF94,AK94),"n/m") | AZ94: =IFERROR(AVERAGE(C94,D94,E94,F94,G94,H94,I94,J94,K94,L94,Q94,V94,AA94,AF94,AK94),"n/m")
B95: Constant-currency organic growth % (published) | H95: 0.049 | I95: 0.05 | J95: 0.076 | K95: 0.098 | L95: 0.001 | M95: 0.209 | N95: 0.117 | O95: 0.086 | P95: 0.108 | Q95: 0.126 | R95: 0.063 | S95: 0.074 | T95: 0.074 | U95: 0.159 | V95: 0.094 | W95: 0.111 | X95: 0.083 | Y95: 0.1 | Z95: 0.07 | AA95: 0.1 | AB95: 0.056 | AC95: 0.07 | AD95: 0.062 | AE95: 0.059 | AF95: 0.062 | AG95: 0.078 | AH95: 0.089 | AI95: 0.078 | AJ95: 0.05 | AK95: 0.073 | AL95: 0.062 | AM95: =IFERROR((AM88-AM90-AM92)/(AM89+AM91)-1,"") | AN95: =IFERROR((AN88-AN90-AN92)/(AN89+AN91)-1,"") | AO95: =IFERROR((AO88-AO90-AO92)/(AO89+AO91)-1,"") | AP95: =IFERROR((AP88-AP90-AP92)/(AP89+AP91)-1,"") | AQ95: =IFERROR((AQ88-AQ90-AQ92)/(AQ89+AQ91)-1,"") | AR95: =IFERROR((AR88-AR90-AR92)/(AR89+AR91)-1,"") | AS95: =IFERROR((AS88-AS90-AS92)/(AS89+AS91)-1,"") | AT95: =IFERROR((AT88-AT90-AT92)/(AT89+AT91)-1,"") | AU95: STERIS's headline growth KPI and guidance metric (FY27 outlook 6–7%). Historical as published; forecast = (revenue − acquisitions − FX) ÷ prior-year revenue − 1. | AW95: =IFERROR(AVERAGE(AP95,AQ95,AR95,AS95,AT95),"n/m") | AX95: =IFERROR(AVERAGE(Q95,V95,AA95,AF95,AK95),"n/m") | AY95: =IFERROR(AVERAGE(H95,I95,J95,K95,L95,Q95,V95,AA95,AF95,AK95),"n/m") | AZ95: =IFERROR(AVERAGE(C95,D95,E95,F95,G95,H95,I95,J95,K95,L95,Q95,V95,AA95,AF95,AK95),"n/m")
B96: Check: published CC organic growth vs (revenue − acquisitions − FX) ÷ (prior-year revenue + divestitures) − 1 (should be 0.0%) | C96: =IF(ISNUMBER(C95),IF(ABS((C88-C90-C92)/(C89+C91)-1-C95)<0.0015,0,ROUND((C88-C90-C92)/(C89+C91)-1-C95,3)),"n/p") | D96: =IF(ISNUMBER(D95),IF(ABS((D88-D90-D92)/(D89+D91)-1-D95)<0.0015,0,ROUND((D88-D90-D92)/(D89+D91)-1-D95,3)),"n/p") | E96: =IF(ISNUMBER(E95),IF(ABS((E88-E90-E92)/(E89+E91)-1-E95)<0.0015,0,ROUND((E88-E90-E92)/(E89+E91)-1-E95,3)),"n/p") | F96: =IF(ISNUMBER(F95),IF(ABS((F88-F90-F92)/(F89+F91)-1-F95)<0.0015,0,ROUND((F88-F90-F92)/(F89+F91)-1-F95,3)),"n/p") | G96: =IF(ISNUMBER(G95),IF(ABS((G88-G90-G92)/(G89+G91)-1-G95)<0.0015,0,ROUND((G88-G90-G92)/(G89+G91)-1-G95,3)),"n/p") | H96: =IF(ISNUMBER(H95),IF(ABS((H88-H90-H92)/(H89+H91)-1-H95)<0.0015,0,ROUND((H88-H90-H92)/(H89+H91)-1-H95,3)),"n/p") | I96: =IF(ISNUMBER(I95),IF(ABS((I88-I90-I92)/(I89+I91)-1-I95)<0.0015,0,ROUND((I88-I90-I92)/(I89+I91)-1-I95,3)),"n/p") | J96: =IF(ISNUMBER(J95),IF(ABS((J88-J90-J92)/(J89+J91)-1-J95)<0.0015,0,ROUND((J88-J90-J92)/(J89+J91)-1-J95,3)),"n/p") | ... AL96: =IF(ISNUMBER(AL95),IF(ABS((AL88-AL90-AL92)/(AL89+AL91)-1-AL95)<0.0015,0,ROUND((AL88-AL90-AL92)/(AL89+AL91)-1-AL95,3)),"n/p")
B97: Healthcare — constant-currency organic growth % (published) | L97: -0.044 | M97: 0.249 | N97: 0.103 | O97: 0.053 | P97: 0.069 | Q97: 0.11 | R97: 0.037 | S97: 0.069 | T97: 0.097 | U97: 0.21 | V97: 0.108 | W97: 0.175 | X97: 0.139 | Y97: 0.124 | Z97: 0.085 | AA97: 0.128 | AB97: 0.052 | AC97: 0.071 | AD97: 0.065 | AE97: 0.056 | AF97: 0.061 | AG97: 0.076 | AH97: 0.09 | AI97: 0.082 | AJ97: 0.057 | AK97: 0.076 | AL97: 0.064
B98: Applied Sterilization Technologies (AST) — constant-currency organic growth % (published) | H98: 0.07 | I98: 0.065 | J98: 0.086 | K98: 0.145 | L98: 0.074 | M98: 0.271 | N98: 0.188 | O98: 0.179 | P98: 0.215 | Q98: 0.212 | R98: 0.103 | S98: 0.194 | T98: 0.074 | U98: 0.098 | V98: 0.116 | W98: 0.051 | X98: -0.01 | Y98: 0.04 | Z98: 0.046 | AA98: 0.032 | AB98: 0.077 | AC98: 0.087 | AD98: 0.095 | AE98: 0.103 | AF98: 0.091 | AG98: 0.102 | AH98: 0.074 | AI98: 0.079 | AJ98: 0.016 | AK98: 0.067 | AL98: 0.047
B99: Life Sciences — constant-currency organic growth % (published) | H99: 0.043 | I99: 0.089 | J99: 0.051 | K99: 0.11 | L99: 0.108 | M99: -0.008 | N99: 0.069 | O99: 0.094 | P99: 0.121 | Q99: 0.069 | R99: 0.098 | S99: 0 | T99: -0.006 | U99: 0.113 | V99: 0.053 | W99: -0.006 | X99: 0.046 | Y99: 0.197 | Z99: 0.016 | AA99: 0.058 | AB99: 0.043 | AC99: 0.03 | AD99: -0.015 | AE99: 0.001 | AF99: 0.013 | AG99: 0.042 | AH99: 0.117 | AI99: 0.05 | AJ99: 0.062 | AK99: 0.067 | AL99: 0.079
B101: Future acquisitions (M&A lever — Healthcare / Life Sciences tuck-ins, unallocated; deals closed from 2028E) | AU101: M&A LEVER — acquired revenue = spend ÷ EV/sales; mid-year convention
...

Sheet Bull-Base-Bear
B2: STERIS plc (STE) — Bull / Base / Bear Case P&L Summary | J2: Share price ($): | K2: =Model!$AP$446
B3: Adjusted figures (company definitions: adjusted income from operations, adjusted EPS from continuing operations; adjusted EBITDA = model definition) · USD millions · fiscal years ended 31 March · Live panel linked to Model — toggle scenario via Model!AU2. Bull and Bear panels are value snapshots generated from the Model with the switch set to each case. FY2027E calibrated to the FY27 outlook (revenue growth 7–8%, adjusted EPS $11.10–11.30). | J3: As of: | K3: =TODAY()
B5: Scenario: | C5: =Model!$AU$2 | N5: Scenario: | O5: Bull | P5: Snapshot (values) — Model run with switch = Bull | Z5: Scenario: | AA5: Bear | AB5: Snapshot (values) — Model run with switch = Bear
B7: (USDm, except EPS and shares) | C7: 2026A | D7: 2027E | E7: 2028E | F7: 2029E | G7: 2030E | H7: 2031E | I7: 26-'31 CAGR | J7: LT Hist Avg | K7: LT Hist Min | L7: LT Hist Max | N7: (USDm, except EPS and shares) | O7: 2026A | P7: 2027E | Q7: 2028E | R7: 2029E | S7: 2030E | T7: 2031E | U7: 26-'31 CAGR | V7: LT Hist Avg | W7: LT Hist Min | X7: LT Hist Max | Z7: (USDm, except EPS and shares) | AA7: 2026A | AB7: 2027E | AC7: 2028E | AD7: 2029E | AE7: 2030E | AF7: 2031E | AG7: 26-'31 CAGR | AH7: LT Hist Avg | AI7: LT Hist Min | AJ7: LT Hist Max
B9: Revenues | C9: =Model!AK159 | D9: =Model!AP159 | E9: =Model!AQ159 | F9: =Model!AR159 | G9: =Model!AS159 | H9: =Model!AT159 | I9: =IFERROR((H9/C9)^(1/5)-1,"n/m") | N9: Revenues | O9: 5935.9 | P9: 6410.672 | Q9: 6994.7344 | R9: 7652.2817 | S9: 8335.993 | T9: 9061.4375 | U9: 0.088283649 | Z9: Revenues | AA9: 5935.9 | AB9: 6351.313 | AC9: 6566.8389 | AD9: 6777.1349 | AE9: 6971.6932 | AF9: 7163.6121 | AG9: 0.038314926
B10: Revenues y/y % | D10: =IFERROR(D9/C9-1,"") | E10: =IFERROR(E9/D9-1,"") | F10: =IFERROR(F9/E9-1,"") | G10: =IFERROR(G9/F9-1,"") | H10: =IFERROR(H9/G9-1,"") | N10: Revenues y/y % | P10: 0.079983153 | Q10: 0.091107832 | R10: 0.094006043 | S10: 0.089347376 | T10: 0.087025557 | Z10: Revenues y/y % | AB10: 0.069983153 | AC10: 0.033934071 | AD10: 0.03202393 | AE10: 0.028708043 | AF10: 0.027528309
B11: Constant-currency organic growth % | C11: =Model!AK267 | D11: =Model!AP267 | E11: =Model!AQ267 | F11: =Model!AR267 | G11: =Model!AS267 | H11: =Model!AT267 | N11: Constant-currency organic growth % | O11: 0.073 | P11: 0.070480458 | Q11: 0.085258211 | R11: 0.077386398 | S11: 0.063350228 | T11: 0.052745373 | Z11: Constant-currency organic growth % | AA11: 0.073 | AB11: 0.060480627 | AC11: 0.033934071 | AD11: 0.03202393 | AE11: 0.028708043 | AF11: 0.027528309
B12: Adjusted EBITDA (model) | C12: =Model!AK233 | D12: =Model!AP233 | E12: =Model!AQ233 | F12: =Model!AR233 | G12: =Model!AS233 | H12: =Model!AT233 | I12: =IFERROR((H12/C12)^(1/5)-1,"n/m") | N12: Adjusted EBITDA (model) | O12: 1603.4 | P12: 1760.7702 | Q12: 1974.0376 | R12: 2185.1419 | S12: 2408.7475 | T12: 2641.276 | U12: 0.10497991 | Z12: Adjusted EBITDA (model) | AA12: 1603.4 | AB12: 1740.1169 | AC12: 1657.3536 | AD12: 1737.3821 | AE12: 1815.0427 | AF12: 1886.9437 | AG12: 0.033102497
B13: Adjusted EBITDA margin % | C13: =IFERROR(C12/C9,"") | D13: =IFERROR(D12/D9,"") | E13: =IFERROR(E12/E9,"") | F13: =IFERROR(F12/F9,"") | G13: =IFERROR(G12/G9,"") | H13: =IFERROR(H12/H9,"") | J13: =IFERROR(AVERAGE(Model!C234,Model!D234,Model!E234,Model!F234,Model!G234,Model!H234,Model!I234,Model!J234,Model!K234,Model!L234,Model!Q234,Model!V234,Model!AA234,Model!AF234,Model!AK234),"") | K13: =IFERROR(MIN(Model!C234,Model!D234,Model!E234,Model!F234,Model!G234,Model!H234,Model!I234,Model!J234,Model!K234,Model!L234,Model!Q234,Model!V234,Model!AA234,Model!AF234,Model!AK234),"") | L13: =IFERROR(MAX(Model!C234,Model!D234,Model!E234,Model!F234,Model!G234,Model!H234,Model!I234,Model!J234,Model!K234,Model!L234,Model!Q234,Model!V234,Model!AA234,Model!AF234,Model!AK234),"") | N13: Adjusted EBITDA margin % | O13: 0.27011911 | P13: 0.27466234 | Q13: 0.28221767 | R13: 0.2855543 | S13: 0.28895747 | T13: 0.29148532 | V13: 0.24082676 | W13: 0.1839674 | X13: 0.30351681 | Z13: Adjusted EBITDA margin % | AA13: 0.27011911 | AB13: 0.27397751 | AC13: 0.25238225 | AD13: 0.25635938 | AE13: 0.2603446 | AF13: 0.26340673 | AH13: 0.24082676 | AI13: 0.1839674 | AJ13: 0.30351681
B15: Income from Operations (GAAP) | C15: =Model!AK167 | D15: =Model!AP167 | E15: =Model!AQ167 | F15: =Model!AR167 | G15: =Model!AS167 | H15: =Model!AT167 | I15: =IFERROR((H15/C15)^(1/5)-1,"n/m") | N15: Income from Operations (GAAP) | O15: 1101.8 | P15: 1241.2702 | Q15: 1415.2877 | R15: 1579.153 | S15: 1764.2578 | T15: 1995.4685 | U15: 0.12612973 | Z15: Income from Operations (GAAP) | AA15: 1101.8 | AB15: 1220.6169 | AC15: 1129.1137 | AD15: 1196.2738 | AE15: 1272.3749 | AF15: 1380.7992 | AG15: 0.046177923
B16: Income from operations y/y % | D16: =IFERROR(D15/C15-1,"") | E16: =IFERROR(E15/D15-1,"") | F16: =IFERROR(F15/E15-1,"") | G16: =IFERROR(G15/F15-1,"") | H16: =IFERROR(H15/G15-1,"") | N16: Income from operations y/y % | P16: 0.12658391 | Q16: 0.14019315 | R16: 0.11578227 | S16: 0.11721778 | T16: 0.13105272 | Z16: Income from operations y/y % | AB16: 0.10783891 | AC16: -0.074964713 | AD16: 0.059480378 | AE16: 0.06361513 | AF16: 0.085214066
B17: Operating margin (GAAP) % | C17: =IFERROR(C15/C9,"") | D17: =IFERROR(D15/D9,"") | E17: =IFERROR(E15/E9,"") | F17: =IFERROR(F15/F9,"") | G17: =IFERROR(G15/G9,"") | H17: =IFERROR(H15/H9,"") | J17: =IFERROR(AVERAGE(Model!C280,Model!D280,Model!E280,Model!F280,Model!G280,Model!H280,Model!I280,Model!J280,Model!K280,Model!L280,Model!Q280,Model!V280,Model!AA280,Model!AF280,Model!AK280),"") | K17: =IFERROR(MIN(Model!C280,Model!D280,Model!E280,Model!F280,Model!G280,Model!H280,Model!I280,Model!J280,Model!K280,Model!L280,Model!Q280,Model!V280,Model!AA280,Model!AF280,Model!AK280),"") | L17: =IFERROR(MAX(Model!C280,Model!D280,Model!E280,Model!F280,Model!G280,Model!H280,Model!I280,Model!J280,Model!K280,Model!L280,Model!Q280,Model!V280,Model!AA280,Model!AF280,Model!AK280),"") | N17: Operating margin (GAAP) % | O17: 0.18561633 | P17: 0.19362559 | Q17: 0.20233616 | R17: 0.20636367 | S17: 0.21164338 | T17: 0.22021545 | V17: 0.14546743 | W17: 0.087109167 | X17: 0.18561633 | Z17: Operating margin (GAAP) % | AA17: 0.18561633 | AB17: 0.1921834 | AC17: 0.17194174 | AD17: 0.17651616 | AE17: 0.18250587 | AF17: 0.19275181 | AH17: 0.14546743 | AI17: 0.087109167 | AJ17: 0.18561633
B19: Adjusted Net Income (continuing operations) | C19: =Model!AK247 | D19: =Model!AP247 | E19: =Model!AQ247 | F19: =Model!AR247 | G19: =Model!AS247 | H19: =Model!AT247 | I19: =IFERROR((H19/C19)^(1/5)-1,"n/m") | N19: Adjusted Net Income (continuing operations) | O19: 1003.4 | P19: 1098.0276 | Q19: 1239.0793 | R19: 1347.2467 | S19: 1478.9598 | T19: 1621.8764 | U19: 0.10080079 | Z19: Adjusted Net Income (continuing operations) | AA19: 1003.4 | AB19: 1082.5377 | AC19: 1017.3202 | AD19: 1072.5505 | AE19: 1119.6926 | AF19: 1165.8014 | AG19: 0.030457533
B21: FDSO (m) | C21: =Model!AK186 | D21: =Model!AP186 | E21: =Model!AQ186 | F21: =Model!AR186 | G21: =Model!AS186 | H21: =Model!AT186 | I21: =IFERROR((H21/C21)^(1/5)-1,"n/m") | N21: FDSO (m) | O21: 98.7 | P21: 97.170585 | Q21: 93.664059 | R21: 89.662347 | S21: 86.378991 | T21: 82.823099 | U21: -0.034467571 | Z21: FDSO (m) | AA21: 98.7 | AB21: 97.525918 | AC21: 96.461294 | AD21: 94.503358 | AE21: 91.775088 | AF21: 89.099853 | AG21: -0.020257456
B23: Adjusted EPS — Diluted ($) | C23: =Model!AK251 | D23: =Model!AP251 | E23: =Model!AQ251 | F23: =Model!AR251 | G23: =Model!AS251 | H23: =Model!AT251 | I23: =IFERROR((H23/C23)^(1/5)-1,"n/m") | N23: Adjusted EPS — Diluted ($) | O23: 10.16616 | P23: 11.3 | Q23: 13.228972 | R23: 15.02578 | S23: 17.121754 | T23: 19.582417 | U23: 0.14009717 | Z23: Adjusted EPS — Diluted ($) | AA23: 10.16616 | AB23: 11.1 | AC23: 10.546409 | AD23: 11.349337 | AE23: 12.200398 | AF23: 13.084213 | AG23: 0.051763588
B24: EPS y/y % | D24: =IFERROR(D23/C23-1,"") | E24: =IFERROR(E23/D23-1,"") | F24: =IFERROR(F23/E23-1,"") | G24: =IFERROR(G23/F23-1,"") | H24: =IFERROR(H23/G23-1,"") | N24: EPS y/y % | P24: 0.1115308 | Q24: 0.17070553 | R24: 0.13582369 | S24: 0.13949185 | T24: 0.14371557 | Z24: EPS y/y % | AB24: 0.091857684 | AC24: -0.049873069 | AD24: 0.076132861 | AE24: 0.074987713 | AF24: 0.072441473
B26: P / E (x) — assumed (adjusted EPS) | G26: 22 | H26: 22 | N26: P / E (x) — assumed (adjusted EPS) | S26: 25 | T26: 25 | Z26: P / E (x) — assumed (adjusted EPS) | AD26: 17 | AE26: 17 | AF26: 17
B27: Price Target ($) | G27: =G26*G23 | H27: =H26*H23 | N27: Price Target ($) | S27: =S26*S23 | T27: =T26*T23 | Z27: Price Target ($) | AD27: =AD26*AD23 | AE27: =AE26*AE23 | AF27: =AF26*AF23
B28: Upside / (Downside) vs current | G28: =IFERROR(G27/$K$2-1,"") | H28: =IFERROR(H27/$K$2-1,"") | N28: Upside / (Downside) vs current | S28: =IFERROR(S27/$K$2-1,"") | T28: =IFERROR(T27/$K$2-1,"") | Z28: Upside / (Downside) vs current | AD28: =IFERROR(AD27/$K$2-1,"") | AE28: =IFERROR(AE27/$K$2-1,"") | AF28: =IFERROR(AF27/$K$2-1,"")
B29: IRR (to 31-Mar of Y-1) | G29: =IFERROR((G27/$K$2)^(1/((DATE(2030-1,3,31)-$K$3)/365.25))-1,"") | H29: =IFERROR((H27/$K$2)^(1/((DATE(2031-1,3,31)-$K$3)/365.25))-1,"") | N29: IRR (to 31-Mar of Y-1) | S29: =IFERROR((S27/$K$2)^(1/((DATE(2030-1,3,31)-$K$3)/365.25))-1,"") | T29: =IFERROR((T27/$K$2)^(1/((DATE(2031-1,3,31)-$K$3)/365.25))-1,"") | Z29: IRR (to 31-Mar of Y-1) | AD29: =IFERROR((AD27/$K$2)^(1/((DATE(2029-1,3,31)-$K$3)/365.25))-1,"") | AE29: =IFERROR((AE27/$K$2)^(1/((DATE(2030-1,3,31)-$K$3)/365.25))-1,"") | AF29: =IFERROR((AF27/$K$2)^(1/((DATE(2031-1,3,31)-$K$3)/365.25))-1,"")
B31: Free Cash Flow | C31: =Model!AK313 | D31: =Model!AP313 | E31: =Model!AQ313 | F31: =Model!AR313 | G31: =Model!AS313 | H31: =Model!AT313 | I31: =IFERROR((H31/C31)^(1/5)-1,"n/m") | N31: Free Cash Flow | O31: 982.9 | P31: 951.34806 | Q31: 1072.3173 | R31: 1187.3799 | S31: 1339.8636 | T31: 1484.994 | U31: 0.086033131 | Z31: Free Cash Flow | AA31: 982.9 | AB31: 942.05652 | AC31: 887.15355 | AD31: 976.55899 | AE31: 1048.6575 | AF31: 1102.8561 | AG31: 0.023297469
B32: FCF % | C32: =IFERROR(C31/C9,"") | D32: =IFERROR(D31/D9,"") | E32: =IFERROR(E31/E9,"") | F32: =IFERROR(F31/F9,"") | G32: =IFERROR(G31/G9,"") | H32: =IFERROR(H31/H9,"") | J32: =IFERROR(AVERAGE(Model!C317,Model!D317,Model!E317,Model!F317,Model!G317,Model!H317,Model!I317,Model!J317,Model!K317,Model!L317,Model!Q317,Model!V317,Model!AA317,Model!AF317,Model!AK317),"") | K32: =IFERROR(MIN(Model!C317,Model!D317,Model!E317,Model!F317,Model!G317,Model!H317,Model!I317,Model!J317,Model!K317,Model!L317,Model!Q317,Model!V317,Model!AA317,Model!AF317,Model!AK317),"") | L32: =IFERROR(MAX(Model!C317,Model!D317,Model!E317,Model!F317,Model!G317,Model!H317,Model!I317,Model!J317,Model!K317,Model!L317,Model!Q317,Model!V317,Model!AA317,Model!AF317,Model!AK317),"") | N32: FCF % | O32: 0.16558567 | P32: 0.14840068 | Q32: 0.1533035 | R32: 0.15516678 | S32: 0.16073233 | T32: 0.16388062 | V32: 0.10617638 | W32: 0.057671108 | X32: 0.16558567 | Z32: FCF % | AA32: 0.16558567 | AB32: 0.14832469 | AC32: 0.13509598 | AD32: 0.14409614 | AE32: 0.15041648 | AF32: 0.15395251 | AH32: 0.10617638 | AI32: 0.057671108 | AJ32: 0.16558567
B33: FCF / share ($) | C33: =IFERROR(C31/C21,"") | D33: =IFERROR(D31/D21,"") | E33: =IFERROR(E31/E21,"") | F33: =IFERROR(F31/F21,"") | G33: =IFERROR(G31/G21,"") | H33: =IFERROR(H31/H21,"") | N33: FCF / share ($) | O33: 9.95846 | P33: 9.7904943 | Q33: 11.448546 | R33: 13.242793 | S33: 15.511452 | T33: 17.929709 | Z33: FCF / share ($) | AA33: 9.95846 | AB33: 9.6595504 | AC33: 9.19699 | AD33: 10.33359 | AE33: 11.426385 | AF33: 12.377754
B34: FCF Yield (on PT) | F34: =IFERROR(F33/F$27,"") | G34: =IFERROR(G33/G$27,"") | H34: =IFERROR(H33/H$27,"") | N34: FCF Yield (on PT) | R34: =IFERROR(R33/R$27,"") | S34: =IFERROR(S33/S$27,"") | T34: =IFERROR(T33/T$27,"") | Z34: FCF Yield (on PT) | AD34: =IFERROR(AD33/AD$27,"") | AE34: =IFERROR(AE33/AE$27,"") | AF34: =IFERROR(AF33/AF$27,"")
B35: Adjusted EBITDA (leverage basis) | C35: =Model!AK233 | D35: =Model!AP233 | E35: =Model!AQ233 | F35: =Model!AR233 | G35: =Model!AS233 | H35: =Model!AT233 | I35: =IFERROR((H35/C35)^(1/5)-1,"n/m") | N35: Adjusted EBITDA (leverage basis) | O35: 1603.4 | P35: 1760.7702 | Q35: 1974.0376 | R35: 2185.1419 | S35: 2408.7475 | T35: 2641.276 | U35: 0.10497991 | Z35: Adjusted EBITDA (leverage basis) | AA35: 1603.4 | AB35: 1740.1169 | AC35: 1657.3536 | AD35: 1737.3821 | AE35: 1815.0427 | AF35: 1886.9437 | AG35: 0.033102497
B36: Adjusted EBITDA % of revenues | C36: =IFERROR(C35/C9,"") | D36: =IFERROR(D35/D9,"") | E36: =IFERROR(E35/E9,"") | F36: =IFERROR(F35/F9,"") | G36: =IFERROR(G35/G9,"") | H36: =IFERROR(H35/H9,"") | J36: =IFERROR(AVERAGE(Model!C279,Model!D279,Model!E279,Model!F279,Model!G279,Model!H279,Model!I279,Model!J279,Model!K279,Model!L279,Model!Q279,Model!V279,Model!AA279,Model!AF279,Model!AK279),"") | K36: =IFERROR(MIN(Model!C279,Model!D279,Model!E279,Model!F279,Model!G279,Model!H279,Model!I279,Model!J279,Model!K279,Model!L279,Model!Q279,Model!V279,Model!AA279,Model!AF279,Model!AK279),"") | L36: =IFERROR(MAX(Model!C279,Model!D279,Model!E279,Model!F279,Model!G279,Model!H279,Model!I279,Model!J279,Model!K279,Model!L279,Model!Q279,Model!V279,Model!AA279,Model!AF279,Model!AK279),"") | N36: Adjusted EBITDA % of revenues | O36: 0.27011911 | P36: 0.27466234 | Q36: 0.28221767 | R36: 0.2855543 | S36: 0.28895747 | T36: 0.29148532 | V36: 0.24082676 | W36: 0.1839674 | X36: 0.30351681 | Z36: Adjusted EBITDA % of revenues | AA36: 0.27011911 | AB36: 0.27397751 | AC36: 0.25238225 | AD36: 0.25635938 | AE36: 0.2603446 | AF36: 0.26340673 | AH36: 0.24082676 | AI36: 0.1839674 | AJ36: 0.30351681
B38: Net Debt | C38: =Model!AK441 | D38: =Model!AP441 | E38: =Model!AQ441 | F38: =Model!AR441 | G38: =Model!AS441 | H38: =Model!AT441 | N38: Net Debt | O38: 1492.1 | P38: 1315.7778 | Q38: 1974.0376 | R38: 2185.1419 | S38: 2408.7475 | T38: 2641.276 | Z38: Net Debt | AA38: 1492.1 | AB38: 1125.9648 | AC38: 828.6768 | AD38: 868.69105 | AE38: 907.52134 | AF38: 943.47184
B39: Net Debt / Adjusted EBITDA (x) | C39: =IFERROR(C38/C35,"") | D39: =IFERROR(D38/D35,"") | E39: =IFERROR(E38/E35,"") | F39: =IFERROR(F38/F35,"") | G39: =IFERROR(G38/G35,"") | H39: =IFERROR(H38/H35,"") | N39: Net Debt / Adjusted EBITDA (x) | O39: 0.93058501 | P39: 0.74727403 | Q39: 1 | R39: 1 | S39: 1 | T39: 1 | Z39: Net Debt / Adjusted EBITDA (x) | AA39: 0.93058501 | AB39: 0.64706273 | AC39: 0.5 | AD39: 0.5 | AE39: 0.5 | AF39: 0.5
B40: Share repurchases ($m; FY2027E = Q2–Q4) | D40: =Model!AP327 | E40: =Model!AQ327 | F40: =Model!AR327 | G40: =Model!AS327 | H40: =Model!AT327 | N40: Share repurchases ($m; FY2027E = Q2–Q4) | P40: 400 | Q40: 1181.1906 | R40: 842.40897 | S40: 995.73688 | T40: 1139.1076 | AB40: 200 | AC40: 337.90017 | AD40: 746.83922 | AE40: 803.77176 | AF40: 840.6538
B41: Implied avg buyback price ($) | D41: =Model!AP326 | E41: =Model!AQ326 | F41: =Model!AR326 | G41: =Model!AS326 | H41: =Model!AT326 | N41: Implied avg buyback price ($) | P41: 211.07 | Q41: 227.9556 | R41: 246.19205 | S41: 265.88741 | T41: 287.1584 | AB41: 211.07 | AC41: 227.9556 | AD41: 246.19205 | AE41: 265.88741 | AF41: 287.1584
B42: Shares repurchased (m) | D42: =Model!AP328 | E42: =Model!AQ328 | F42: =Model!AR328 | G42: =Model!AS328 | H42: =Model!AT328 | N42: Shares repurchased (m) | P42: 1.8951059 | Q42: 5.1816695 | R42: 3.4217554 | S42: 3.7449568 | T42: 3.9668266 | AB42: 0.94755294 | AC42: 1.482307 | AD42: 3.0335635 | AE42: 3.0229779 | AF42: 2.9274915
B44: ROIC | C44: =Model!AK424 | D44: =Model!AP424 | E44: =Model!AQ424 | F44: =Model!AR424 | G44: =Model!AS424 | H44: =Model!AT424 | J44: =IFERROR(AVERAGE(Model!C424,Model!D424,Model!E424,Model!F424,Model!G424,Model!H424,Model!I424,Model!J424,Model!K424,Model!L424,Model!Q424,Model!V424,Model!AA424,Model!AF424,Model!AK424),"") | K44: =IFERROR(MIN(Model!C424,Model!D424,Model!E424,Model!F424,Model!G424,Model!H424,Model!I424,Model!J424,Model!K424,Model!L424,Model!Q424,Model!V424,Model!AA424,Model!AF424,Model!AK424),"") | L44: =IFERROR(MAX(Model!C424,Model!D424,Model!E424,Model!F424,Model!G424,Model!H424,Model!I424,Model!J424,Model!K424,Model!L424,Model!Q424,Model!V424,Model!AA424,Model!AF424,Model!AK424),"") | N44: ROIC | O44: 0.097170795 | P44: 0.10837716 | Q44: 0.12001866 | R44: 0.12918558 | S44: 0.13902153 | T44: 0.1510531 | V44: 0.091989474 | W44: 0.054499159 | X44: 0.15241455 | Z44: ROIC | AA44: 0.097170795 | AB44: 0.10667352 | AC44: 0.099440824 | AD44: 0.10571324 | AE44: 0.11229345 | AF44: 0.1210534 | AH44: 0.091989474 | AI44: 0.054499159 | AJ44: 0.15241455
B45: RONTA | C45: =Model!AK435 | D45: =Model!AP435 | E45: =Model!AQ435 | F45: =Model!AR435 | G45: =Model!AS435 | H45: =Model!AT435 | J45: =IFERROR(AVERAGE(Model!C435,Model!D435,Model!E435,Model!F435,Model!G435,Model!H435,Model!I435,Model!J435,Model!K435,Model!L435,Model!Q435,Model!V435,Model!AA435,Model!AF435,Model!AK435),"") | K45: =IFERROR(MIN(Model!C435,Model!D435,Model!E435,Model!F435,Model!G435,Model!H435,Model!I435,Model!J435,Model!K435,Model!L435,Model!Q435,Model!V435,Model!AA435,Model!AF435,Model!AK435),"") | L45: =IFERROR(MAX(Model!C435,Model!D435,Model!E435,Model!F435,Model!G435,Model!H435,Model!I435,Model!J435,Model!K435,Model!L435,Model!Q435,Model!V435,Model!AA435,Model!AF435,Model!AK435),"") | N45: RONTA | O45: 0.21670461 | P45: 0.22597362 | Q45: 0.24609346 | R45: 0.25707133 | S45: 0.26900777 | T45: 0.28507103 | V45: 0.19710919 | W45: 0.14256772 | X45: 0.23560522 | Z45: RONTA | AA45: 0.21670461 | AB45: 0.21289481 | AC45: 0.18235993 | AD45: 0.19166323 | AE45: 0.19645644 | AF45: 0.20940405 | AH45: 0.19710919 | AI45: 0.14256772 | AJ45: 0.23560522
B47: Implied Market Cap (USDm) | F47: =F27*F21 | G47: =G27*G21 | H47: =H27*H21 | N47: Implied Market Cap (USDm) | R47: =R27*R21 | S47: =S27*S21 | T47: =T27*T21 | Z47: Implied Market Cap (USDm) | AD47: =AD27*AD21 | AE47: =AE27*AE21 | AF47: =AF27*AF21
B48: (+) Net Debt & NCI | F48: =F38+Model!AR357 | G48: =G38+Model!AS357 | H48: =H38+Model!AT357 | N48: (+) Net Debt & NCI | R48: =R38+Model!AR357 | S48: =S38+Model!AS357 | T48: =T38+Model!AT357 | Z48: (+) Net Debt & NCI | AD48: =AD38+Model!AR357 | AE48: =AE38+Model!AS357 | AF48: =AF38+Model!AT357
B49: Implied Enterprise Value (USDm) | F49: =F47+F48 | G49: =G47+G48 | H49: =H47+H48 | N49: Implied Enterprise Value (USDm) | R49: =R47+R48 | S49: =S47+S48 | T49: =T47+T48 | Z49: Implied Enterprise Value (USDm) | AD49: =AD47+AD48 | AE49: =AE47+AE48 | AF49: =AF47+AF48
B50: Implied EV / Adjusted EBITDA (x) | F50: =IFERROR(F49/F35,"") | G50: =IFERROR(G49/G35,"") | H50: =IFERROR(H49/H35,"") | N50: Implied EV / Adjusted EBITDA (x) | R50: =IFERROR(R49/R35,"") | S50: =IFERROR(S49/S35,"") | T50: =IFERROR(T49/T35,"") | Z50: Implied EV / Adjusted EBITDA (x) | AD50: =IFERROR(AD49/AD35,"") | AE50: =IFERROR(AE49/AE35,"") | AF50: =IFERROR(AF49/AF35,"")

Sheet DCF
B2: DCF VALUATION — STERIS PLC (STE)
B4: 1. WACC BUILD
B5: Risk-free rate (US 10Y govt) | C5: 0.045 | D5: Assumption (~US 10Y Treasury yield, Oct-2026); update to market
B6: Equity risk premium | C6: 0.05 | D6: US implied ERP ~4.5–5.5% (Damodaran)
B7: Levered beta | C7: 0.85 | D7: Medtech / infection-prevention peers (Ecolab, Getinge, Cantel pre-deal, Sotera Health) ~0.7–1.0; ~75% recurring consumables & service revenue dampens cyclicality
B8: Cost of equity | C8: =C5+C7*C6
B9: Pre-tax cost of debt | C9: 0.05 | D9: Investment grade (BBB+ / Baa1); 2.70% 2031 and 3.75% 2051 public notes; marginal cost ~5%
B10: Tax rate | C10: 0.25 | D10: Model FY2027E+ effective tax rate (FY27 outlook ~25%)
B11: After-tax cost of debt | C11: =C9*(1-C10)
B12: Target D/V | C12: 0.08 | D12: Net debt ~$1.4bn at 30-Jun-2026 vs ~$20.6bn market cap ($211.07 × ~98m diluted shares); ~0.9x adjusted EBITDA
B13: WACC | C13: =C8*(1-C12)+C11*C12
B15: Valuation date (live) | C15: =TODAY() | D15: Periods = (31-Mar of fiscal year − today) / 365.25; cash flows assumed at fiscal year-end (31 March)
B16: 2. UNLEVERED FREE CASH FLOW BUILD (USDm)
D17: 2027E | E17: 2028E | F17: 2029E | G17: 2030E | H17: 2031E | I17: 2032E | J17: 2033E | K17: 2034E | L17: 2035E | M17: 2036E | N17: Terminal | P17: CAGR 26–30E | Q17: CAGR 26–35E
B18: Adj. EBIT less acquisition, integration & restructuring costs | D18: =Model!AP238-Model!AP240 | E18: =Model!AQ238-Model!AQ240 | F18: =Model!AR238-Model!AR240 | G18: =Model!AS238-Model!AS240 | H18: =Model!AT238-Model!AT240 | I18: =H18*(1+I$26) | J18: =I18*(1+J$26) | K18: =J18*(1+K$26) | L18: =K18*(1+L$26) | M18: =L18*(1+M$26) | P18: =(H18/D18)^(1/(COLUMNS(D18:H18)-1))-1 | Q18: =(M18/D18)^(1/(COLUMNS(D18:M18)-1))-1
B19: × (1 − tax rate) | D19: =1-$C$10 | E19: =1-$C$10 | F19: =1-$C$10 | G19: =1-$C$10 | H19: =1-$C$10 | I19: =1-$C$10 | J19: =1-$C$10 | K19: =1-$C$10 | ... M19: =1-$C$10
B20: NOPAT | D20: =D18*D19 | E20: =E18*E19 | F20: =F18*F19 | G20: =G18*G19 | H20: =H18*H19 | I20: =I18*I19 | J20: =J18*J19 | K20: =K18*K19 | ... M20: =M18*M19
B21: plus DD&A (total, incl. acquired-intangible amortization) | D21: =Model!AP182 | E21: =Model!AQ182 | F21: =Model!AR182 | G21: =Model!AS182 | H21: =Model!AT182 | I21: =H21*(1+I$26) | J21: =I21*(1+J$26) | K21: =J21*(1+K$26) | L21: =K21*(1+L$26) | M21: =L21*(1+M$26)
B22: − Capex (PP&E & intangibles) and acquisitions (tuck-ins; M&A lever 2028E–31E) | D22: =Model!AP294+Model!AP296 | E22: =Model!AQ294+Model!AQ296 | F22: =Model!AR294+Model!AR296 | G22: =Model!AS294+Model!AS296 | H22: =Model!AT294+Model!AT296 | I22: =Model!AT294*(1+I$26) | J22: =I22*(1+J$26) | K22: =J22*(1+K$26) | L22: =K22*(1+L$26) | M22: =L22*(1+M$26)
B23: − Δ Working capital (CF statement) | D23: =Model!AP292 | E23: =Model!AQ292 | F23: =Model!AR292 | G23: =Model!AS292 | H23: =Model!AT292 | I23: =H23*(1+I$26) | J23: =I23*(1+J$26) | K23: =J23*(1+K$26) | L23: =K23*(1+L$26) | M23: =L23*(1+M$26)
B24: Unlevered FCF | D24: =D20+D21+D22+D23 | E24: =E20+E21+E22+E23 | F24: =F20+F21+F22+F23 | G24: =G20+G21+G22+G23 | H24: =H20+H21+H22+H23 | I24: =I20+I21+I22+I23 | J24: =J20+J21+J22+J23 | K24: =K20+K21+K22+K23 | ... M24: =M20+M21+M22+M23 | N24: =M24*(1+$C$27) | P24: =(H24/D24)^(1/(COLUMNS(D24:H24)-1))-1 | Q24: =(M24/D24)^(1/(COLUMNS(D24:M24)-1))-1
B25: Terminal Value (Gordon Growth) | N25: =N24/($C$13-$C$27)
B26: Fade-period growth (2032E–36E; 6.0% → 4.5% linear) | I26: 0.06 | J26: =I26+($M$26-$I$26)/4 | K26: =J26+($M$26-$I$26)/4 | L26: =K26+($M$26-$I$26)/4 | M26: 0.045
B27: Terminal growth rate | C27: 0.035
B29: Discount period (years) | D29: =(DATE(2027,3,31)-$C$15)/365.25 | E29: =(DATE(2028,3,31)-$C$15)/365.25 | F29: =(DATE(2029,3,31)-$C$15)/365.25 | G29: =(DATE(2030,3,31)-$C$15)/365.25 | H29: =(DATE(2031,3,31)-$C$15)/365.25 | I29: =(DATE(2032,3,31)-$C$15)/365.25 | J29: =(DATE(2033,3,31)-$C$15)/365.25 | K29: =(DATE(2034,3,31)-$C$15)/365.25 | L29: =(DATE(2035,3,31)-$C$15)/365.25 | M29: =(DATE(2036,3,31)-$C$15)/365.25 | N29: =M29
B30: Discount factor | D30: =1/(1+$C$13)^D29 | E30: =1/(1+$C$13)^E29 | F30: =1/(1+$C$13)^F29 | G30: =1/(1+$C$13)^G29 | H30: =1/(1+$C$13)^H29 | I30: =1/(1+$C$13)^I29 | J30: =1/(1+$C$13)^J29 | K30: =1/(1+$C$13)^K29 | ... N30: =1/(1+$C$13)^N29
B31: PV of UFCF | D31: =D24*D30 | E31: =E24*E30 | F31: =F24*F30 | G31: =G24*G30 | H31: =H24*H30 | I31: =I24*I30 | J31: =J24*J30 | K31: =K24*K30 | ... M31: =M24*M30 | N31: =N25*N30
D32: STERIS's adjusted operating income excludes acquired-intangible amortization (~$262m in FY27E) but expenses share-based compensation; Adjusted EBIT here deducts all D&A (non-cash, added back in row 21). Acquisition & integration and restructuring charges (cash; adjusted out by the company, incl. the FY27–30 North Carolina Center-of-Excellence plan) are deducted inside row 18. Row 22 includes tuck-in acquisitions in FY2027E–31E; the fade period and terminal value assume no new acquisitions. Dental (sold Sep-2024) is excluded throughout (continuing operations).
B33: IMPLIED ROIC — invested capital roll-forward (USDm)
B34: Opening invested capital | D34: =Model!AK421 | E34: =D38 | F34: =E38 | G34: =F38 | H34: =G38 | I34: =H38 | J34: =I38 | K34: =J38 | L34: =K38 | M34: =L38
B35: plus Capex and acquisitions | D35: =-D22 | E35: =-E22 | F35: =-F22 | G35: =-G22 | H35: =-H22 | I35: =-I22 | J35: =-J22 | K35: =-K22 | ... M35: =-M22
B36: less DD&A | D36: =-D21 | E36: =-E21 | F36: =-F21 | G36: =-G21 | H36: =-H21 | I36: =-I21 | J36: =-J21 | K36: =-K21 | ... M36: =-M21
B37: plus Δ Working capital investment | D37: =-D23 | E37: =-E23 | F37: =-F23 | G37: =-G23 | H37: =-H23 | I37: =-I23 | J37: =-J23 | K37: =-K23 | ... M37: =-M23
B38: Closing invested capital | D38: =SUM(D34:D37) | E38: =SUM(E34:E37) | F38: =SUM(F34:F37) | G38: =SUM(G34:G37) | H38: =SUM(H34:H37) | I38: =SUM(I34:I37) | J38: =SUM(J34:J37) | K38: =SUM(K34:K37) | ... M38: =SUM(M34:M37)
B39: NOPAT (row 20) | D39: =D20 | E39: =E20 | F39: =F20 | G39: =G20 | H39: =H20 | I39: =I20 | J39: =J20 | K39: =K20 | ... M39: =M20
B40: Implied ROIC (NOPAT / avg. invested capital) | D40: =IFERROR(D39/AVERAGE(D34,D38),"") | E40: =IFERROR(E39/AVERAGE(E34,E38),"") | F40: =IFERROR(F39/AVERAGE(F34,F38),"") | G40: =IFERROR(G39/AVERAGE(G34,G38),"") | H40: =IFERROR(H39/AVERAGE(H34,H38),"") | I40: =IFERROR(I39/AVERAGE(I34,I38),"") | J40: =IFERROR(J39/AVERAGE(J34,J38),"") | K40: =IFERROR(K39/AVERAGE(K34,K38),"") | ... M40: =IFERROR(M39/AVERAGE(M34,M38),"")
B41: Reinvestment rate (net investment / NOPAT) | D41: =IFERROR(SUM(D35:D37)/D39,"") | E41: =IFERROR(SUM(E35:E37)/E39,"") | F41: =IFERROR(SUM(F35:F37)/F39,"") | G41: =IFERROR(SUM(G35:G37)/G39,"") | H41: =IFERROR(SUM(H35:H37)/H39,"") | I41: =IFERROR(SUM(I35:I37)/I39,"") | J41: =IFERROR(SUM(J35:J37)/J39,"") | K41: =IFERROR(SUM(K35:K37)/K39,"") | ... M41: =IFERROR(SUM(M35:M37)/M39,"")
B42: Implied terminal RONIC (g / reinvestment rate) | N42: =IFERROR($C$27/M41,"")
D43: Opening IC = Model FY2026A book IC (total equity incl. NCI + net debt), rolled forward with capex + M&A − DD&A + ΔWC.
B44: 3. VALUATION SUMMARY
B45: Sum of PV (explicit + fade) | C45: =SUM(D31:M31)
B46: PV of Terminal Value | C46: =N31
B47: Enterprise Value | C47: =C45+C46
B48: Less: Net debt + NCI (Model FY2027E year end, 31-Mar-2027) | C48: =Model!AP441+Model!AP357 | D48: STE: noncontrolling interests (~$14m) deducted alongside net debt.
B49: Equity Value | C49: =C47-C48
B50: Diluted shares (m, Model FY2027E period end) | C50: =Model!AP447
B51: Implied share price ($) | C51: =C49/C50
B52: Current share price ($) | C52: =Model!AP446
B53: Implied upside / (downside) | C53: =C51/C52-1
B54: Required discount to DCF value for target IRR | C54: =1-((1+C13)/(1+H54))^H55 | D54: vs. current | E54: Target IRR | H54: 0.15
B55: Max entry price for target IRR ($) | C55: =C51*(1-C54) | D55: =C55/C52-1 | E55: Years for discount to close | H55: 3
B58: 4. SENSITIVITY: IMPLIED PRICE ($) — WACC × Terminal Growth
D60: WACC →
B61: Terminal growth ↓ | D61: =F61-0.01 | E61: =F61-0.005 | F61: =$C$13 | G61: =F61+0.005 | H61: =F61+0.01
B62: =B64-0.01 | D62: {=IFERROR((SUMPRODUCT($D$24:$M$24/(1+D$61)^$D$29:$M$29)+($M$24*(1+$B62)/(D$61-$B62))/(1+D$61)^$M$29-$C$48)/$C$50,"")} | E62: {=IFERROR((SUMPRODUCT($D$24:$M$24/(1+E$61)^$D$29:$M$29)+($M$24*(1+$B62)/(E$61-$B62))/(1+E$61)^$M$29-$C$48)/$C$50,"")} | F62: {=IFERROR((SUMPRODUCT($D$24:$M$24/(1+F$61)^$D$29:$M$29)+($M$24*(1+$B62)/(F$61-$B62))/(1+F$61)^$M$29-$C$48)/$C$50,"")} | G62: {=IFERROR((SUMPRODUCT($D$24:$M$24/(1+G$61)^$D$29:$M$29)+($M$24*(1+$B62)/(G$61-$B62))/(1+G$61)^$M$29-$C$48)/$C$50,"")} | H62: {=IFERROR((SUMPRODUCT($D$24:$M$24/(1+H$61)^$D$29:$M$29)+($M$24*(1+$B62)/(H$61-$B62))/(1+H$61)^$M$29-$C$48)/$C$50,"")}
B63: =B64-0.005 | D63: {=IFERROR((SUMPRODUCT($D$24:$M$24/(1+D$61)^$D$29:$M$29)+($M$24*(1+$B63)/(D$61-$B63))/(1+D$61)^$M$29-$C$48)/$C$50,"")} | E63: {=IFERROR((SUMPRODUCT($D$24:$M$24/(1+E$61)^$D$29:$M$29)+($M$24*(1+$B63)/(E$61-$B63))/(1+E$61)^$M$29-$C$48)/$C$50,"")} | F63: {=IFERROR((SUMPRODUCT($D$24:$M$24/(1+F$61)^$D$29:$M$29)+($M$24*(1+$B63)/(F$61-$B63))/(1+F$61)^$M$29-$C$48)/$C$50,"")} | G63: {=IFERROR((SUMPRODUCT($D$24:$M$24/(1+G$61)^$D$29:$M$29)+($M$24*(1+$B63)/(G$61-$B63))/(1+G$61)^$M$29-$C$48)/$C$50,"")} | H63: {=IFERROR((SUMPRODUCT($D$24:$M$24/(1+H$61)^$D$29:$M$29)+($M$24*(1+$B63)/(H$61-$B63))/(1+H$61)^$M$29-$C$48)/$C$50,"")}
B64: =$C$27 | D64: {=IFERROR((SUMPRODUCT($D$24:$M$24/(1+D$61)^$D$29:$M$29)+($M$24*(1+$B64)/(D$61-$B64))/(1+D$61)^$M$29-$C$48)/$C$50,"")} | E64: {=IFERROR((SUMPRODUCT($D$24:$M$24/(1+E$61)^$D$29:$M$29)+($M$24*(1+$B64)/(E$61-$B64))/(1+E$61)^$M$29-$C$48)/$C$50,"")} | F64: {=IFERROR((SUMPRODUCT($D$24:$M$24/(1+F$61)^$D$29:$M$29)+($M$24*(1+$B64)/(F$61-$B64))/(1+F$61)^$M$29-$C$48)/$C$50,"")} | G64: {=IFERROR((SUMPRODUCT($D$24:$M$24/(1+G$61)^$D$29:$M$29)+($M$24*(1+$B64)/(G$61-$B64))/(1+G$61)^$M$29-$C$48)/$C$50,"")} | H64: {=IFERROR((SUMPRODUCT($D$24:$M$24/(1+H$61)^$D$29:$M$29)+($M$24*(1+$B64)/(H$61-$B64))/(1+H$61)^$M$29-$C$48)/$C$50,"")}
B65: =B64+0.005 | D65: {=IFERROR((SUMPRODUCT($D$24:$M$24/(1+D$61)^$D$29:$M$29)+($M$24*(1+$B65)/(D$61-$B65))/(1+D$61)^$M$29-$C$48)/$C$50,"")} | E65: {=IFERROR((SUMPRODUCT($D$24:$M$24/(1+E$61)^$D$29:$M$29)+($M$24*(1+$B65)/(E$61-$B65))/(1+E$61)^$M$29-$C$48)/$C$50,"")} | F65: {=IFERROR((SUMPRODUCT($D$24:$M$24/(1+F$61)^$D$29:$M$29)+($M$24*(1+$B65)/(F$61-$B65))/(1+F$61)^$M$29-$C$48)/$C$50,"")} | G65: {=IFERROR((SUMPRODUCT($D$24:$M$24/(1+G$61)^$D$29:$M$29)+($M$24*(1+$B65)/(G$61-$B65))/(1+G$61)^$M$29-$C$48)/$C$50,"")} | H65: {=IFERROR((SUMPRODUCT($D$24:$M$24/(1+H$61)^$D$29:$M$29)+($M$24*(1+$B65)/(H$61-$B65))/(1+H$61)^$M$29-$C$48)/$C$50,"")}
B66: =B64+0.01 | D66: {=IFERROR((SUMPRODUCT($D$24:$M$24/(1+D$61)^$D$29:$M$29)+($M$24*(1+$B66)/(D$61-$B66))/(1+D$61)^$M$29-$C$48)/$C$50,"")} | E66: {=IFERROR((SUMPRODUCT($D$24:$M$24/(1+E$61)^$D$29:$M$29)+($M$24*(1+$B66)/(E$61-$B66))/(1+E$61)^$M$29-$C$48)/$C$50,"")} | F66: {=IFERROR((SUMPRODUCT($D$24:$M$24/(1+F$61)^$D$29:$M$29)+($M$24*(1+$B66)/(F$61-$B66))/(1+F$61)^$M$29-$C$48)/$C$50,"")} | G66: {=IFERROR((SUMPRODUCT($D$24:$M$24/(1+G$61)^$D$29:$M$29)+($M$24*(1+$B66)/(G$61-$B66))/(1+G$61)^$M$29-$C$48)/$C$50,"")} | H66: {=IFERROR((SUMPRODUCT($D$24:$M$24/(1+H$61)^$D$29:$M$29)+($M$24*(1+$B66)/(H$61-$B66))/(1+H$61)^$M$29-$C$48)/$C$50,"")}
B69: 5. REVERSE DCF
B70: To solve for the market-implied path: Data ▸ What-If Analysis ▸ Goal Seek — set C51 to the current price (C52) by changing C27 (terminal growth) or the fade-period growth inputs (I26:M26).
B72: 6. MAUBOUSSIN EV / NOPAT — TWO-STAGE FRAMEWORK
B73: EV/NOPAT = 1/r + [g × (1 − r/ROIIC) / (r × (r − g))] × [1 − ((1+g)/(1+r))^N]
B74: Formula source: Mauboussin & Rappaport, "Expectations Investing" (2021); Counterpoint Global, "What Does a Price-Earnings Multiple Mean?" (2020).
B76: Input | C76: Value | D76: Rationale (STERIS characteristics)
B77: r (Cost of capital / WACC) | C77: =$C$13 | D77: Linked from Section 1 WACC build
B78: g (NOPAT growth, Stage 1) | C78: 0.08 | D78: Model adjusted EBIT CAGR FY2027–31E: mid-to-high single-digit revenue growth (procedures, service, AST capacity), ~50 bps p.a. margin expansion and buybacks → ~8% NOPAT growth
B79: ROIIC (Return on incremental invested capital) | C79: 0.18 | D79: Razor / razor-blade installed base (sterilizers, washers, endoscope reprocessors) drives consumables & service at high incremental returns; AST sterilization network earns ~45% segment margins on capacity adds; acquisitions (Synergy, Cantel) earn ~7–9% after tax
B80: N (Years of value creation / CAP) | C80: 15 | D80: Regulated, validated sterilization processes and hospital standardization create high switching costs; ~75% recurring revenue; EO regulatory and litigation exposure is the main risk to the CAP
B82: Calculation | C82: Value
B83: Steady-state component: 1 / r | C83: =1/C77
B84: Value-creation factor: 1 − r / ROIIC | C84: =1-C77/C79
B85: Growth multiplier: g × (1 − r/ROIIC) / (r × (r − g)) | C85: =C78*C84/(C77*(C77-C78))
B86: Time decay: 1 − ((1+g)/(1+r))^N | C86: =1-((1+C78)/(1+C77))^C80
B87: PVGO component (growth value) | C87: =C85*C86
B88: Mauboussin EV / NOPAT (steady-state + PVGO) | C88: =C83+C87
B90: VALUATION — Applied to FY2029E NOPAT | C90: USDm
B91: FY2029E Adj. EBIT less acquisition, integration & restructuring costs | C91: =Model!AR238-Model!AR240
B92: Tax rate (from WACC build) | C92: =$C$10
B93: FY2029E NOPAT | C93: =C91*(1-C92)
B94: × Mauboussin EV/NOPAT multiple | C94: =C88
B95: Implied Enterprise Value (FY2029E basis) | C95: =C93*C94
B96: Less: FY2028E year-end net debt + NCI (Model) | C96: =Model!AQ441+Model!AQ357
B97: Implied Equity Value | C97: =C95-C96
B98: Diluted shares FY2029E (m, Model) | C98: =Model!AR447
B99: Implied share price FY2029 ($) | C99: =C97/C98
B101: Current share price ($) | C101: =C52
B102: Implied upside / (downside) | C102: =C99/C101-1
B104: MARKET-IMPLIED EV/NOPAT TODAY | C104: USDm
B105: Current market cap (spot × diluted shares) | C105: =C52*C50
B106: Plus: FY2027E year-end net debt + NCI | C106: =C48
B107: Implied Enterprise Value (today) | C107: =C105+C106
B108: STE market-implied EV/NOPAT (on FY2029E NOPAT) | C108: =C107/C93
B110: Multiple gap (Mauboussin − Market) | C110: =C88-C108
B111: Implied re-rating headroom | C111: =C88/C108-1

Sheet Charts
B2: STERIS plc — Operating Performance (FY2012–FY2026) and Model Forecast (FY2027E–FY2031E)
B3: USDm · fiscal years ended 31 March · Linked to Model. Bars = constant-currency organic growth vs acquisitions, divestitures & FX (published bridge from FY2017; earlier years: total growth shown as organic). Adjusted EBITDA = model definition (adjusted operating income + depreciation & other amortization). ROIC / RONTA on adjusted EBIT (full-cost).
C7: 2012 | D7: 2013 | E7: 2014 | F7: 2015 | G7: 2016 | H7: 2017 | I7: 2018 | J7: 2019 | K7: 2020 | L7: 2021 | M7: 2022 | N7: 2023 | O7: 2024 | P7: 2025 | Q7: 2026 | R7: 2027E | S7: 2028E | T7: 2029E | U7: 2030E | V7: 2031E
B8: CC organic growth % | C8: =IFERROR(Model!C95+0,IFERROR(Model!C266+0,0)) | D8: =IFERROR(Model!D95+0,IFERROR(Model!D266+0,0)) | E8: =IFERROR(Model!E95+0,IFERROR(Model!E266+0,0)) | F8: =IFERROR(Model!F95+0,IFERROR(Model!F266+0,0)) | G8: =IFERROR(Model!G95+0,IFERROR(Model!G266+0,0)) | H8: =IFERROR(Model!H95+0,IFERROR(Model!H266+0,0)) | I8: =IFERROR(Model!I95+0,IFERROR(Model!I266+0,0)) | J8: =IFERROR(Model!J95+0,IFERROR(Model!J266+0,0)) | ... L8: =IFERROR(Model!L95+0,IFERROR(Model!L266+0,0)) | M8: =IFERROR(Model!Q95+0,IFERROR(Model!Q266+0,0)) | N8: =IFERROR(Model!V95+0,IFERROR(Model!V266+0,0)) | O8: =IFERROR(Model!AA95+0,IFERROR(Model!AA266+0,0)) | P8: =IFERROR(Model!AF95+0,IFERROR(Model!AF266+0,0)) | Q8: =IFERROR(Model!AK95+0,IFERROR(Model!AK266+0,0)) | R8: =IFERROR(Model!AP95+0,IFERROR(Model!AP266+0,0)) | S8: =IFERROR(Model!AQ95+0,IFERROR(Model!AQ266+0,0)) | T8: =IFERROR(Model!AR95+0,IFERROR(Model!AR266+0,0)) | U8: =IFERROR(Model!AS95+0,IFERROR(Model!AS266+0,0)) | V8: =IFERROR(Model!AT95+0,IFERROR(Model!AT266+0,0))
B9: Acquisitions, divestitures & FX % | C9: =IFERROR(Model!C266-Model!C95,0) | D9: =IFERROR(Model!D266-Model!D95,0) | E9: =IFERROR(Model!E266-Model!E95,0) | F9: =IFERROR(Model!F266-Model!F95,0) | G9: =IFERROR(Model!G266-Model!G95,0) | H9: =IFERROR(Model!H266-Model!H95,0) | I9: =IFERROR(Model!I266-Model!I95,0) | J9: =IFERROR(Model!J266-Model!J95,0) | ... L9: =IFERROR(Model!L266-Model!L95,0) | M9: =IFERROR(Model!Q266-Model!Q95,0) | N9: =IFERROR(Model!V266-Model!V95,0) | O9: =IFERROR(Model!AA266-Model!AA95,0) | P9: =IFERROR(Model!AF266-Model!AF95,0) | Q9: =IFERROR(Model!AK266-Model!AK95,0) | R9: =IFERROR(Model!AP266-Model!AP95,0) | S9: =IFERROR(Model!AQ266-Model!AQ95,0) | T9: =IFERROR(Model!AR266-Model!AR95,0) | U9: =IFERROR(Model!AS266-Model!AS95,0) | V9: =IFERROR(Model!AT266-Model!AT95,0)
C11: =C7 | D11: =D7 | E11: =E7 | F11: =F7 | G11: =G7 | H11: =H7 | I11: =I7 | J11: =J7 | ... V11: =V7
B12: Adjusted EBITDA | C12: =Model!C233 | D12: =Model!D233 | E12: =Model!E233 | F12: =Model!F233 | G12: =Model!G233 | H12: =Model!H233 | I12: =Model!I233 | J12: =Model!J233 | ... L12: =Model!L233 | M12: =Model!Q233 | N12: =Model!V233 | O12: =Model!AA233 | P12: =Model!AF233 | Q12: =Model!AK233 | R12: =Model!AP233 | S12: =Model!AQ233 | T12: =Model!AR233 | U12: =Model!AS233 | V12: =Model!AT233
B13: Income from Operations (GAAP) | C13: =Model!C167 | D13: =Model!D167 | E13: =Model!E167 | F13: =Model!F167 | G13: =Model!G167 | H13: =Model!H167 | I13: =Model!I167 | J13: =Model!J167 | ... L13: =Model!L167 | M13: =Model!Q167 | N13: =Model!V167 | O13: =Model!AA167 | P13: =Model!AF167 | Q13: =Model!AK167 | R13: =Model!AP167 | S13: =Model!AQ167 | T13: =Model!AR167 | U13: =Model!AS167 | V13: =Model!AT167
B14: Adj. EBITDA Margin % | C14: =Model!C279 | D14: =Model!D279 | E14: =Model!E279 | F14: =Model!F279 | G14: =Model!G279 | H14: =Model!H279 | I14: =Model!I279 | J14: =Model!J279 | ... L14: =Model!L279 | M14: =Model!Q279 | N14: =Model!V279 | O14: =Model!AA279 | P14: =Model!AF279 | Q14: =Model!AK279 | R14: =Model!AP279 | S14: =Model!AQ279 | T14: =Model!AR279 | U14: =Model!AS279 | V14: =Model!AT279
B15: GAAP Op. Margin % | C15: =Model!C280 | D15: =Model!D280 | E15: =Model!E280 | F15: =Model!F280 | G15: =Model!G280 | H15: =Model!H280 | I15: =Model!I280 | J15: =Model!J280 | ... L15: =Model!L280 | M15: =Model!Q280 | N15: =Model!V280 | O15: =Model!AA280 | P15: =Model!AF280 | Q15: =Model!AK280 | R15: =Model!AP280 | S15: =Model!AQ280 | T15: =Model!AR280 | U15: =Model!AS280 | V15: =Model!AT280
C17: =C7 | D17: =D7 | E17: =E7 | F17: =F7 | G17: =G7 | H17: =H7 | I17: =I7 | J17: =J7 | ... V17: =V7
B18: ROIC | C18: =IFERROR(Model!C424+0,NA()) | D18: =IFERROR(Model!D424+0,NA()) | E18: =IFERROR(Model!E424+0,NA()) | F18: =IFERROR(Model!F424+0,NA()) | G18: =IFERROR(Model!G424+0,NA()) | H18: =IFERROR(Model!H424+0,NA()) | I18: =IFERROR(Model!I424+0,NA()) | J18: =IFERROR(Model!J424+0,NA()) | ... L18: =IFERROR(Model!L424+0,NA()) | M18: =IFERROR(Model!Q424+0,NA()) | N18: =IFERROR(Model!V424+0,NA()) | O18: =IFERROR(Model!AA424+0,NA()) | P18: =IFERROR(Model!AF424+0,NA()) | Q18: =IFERROR(Model!AK424+0,NA()) | R18: =IFERROR(Model!AP424+0,NA()) | S18: =IFERROR(Model!AQ424+0,NA()) | T18: =IFERROR(Model!AR424+0,NA()) | U18: =IFERROR(Model!AS424+0,NA()) | V18: =IFERROR(Model!AT424+0,NA())
B19: RONTA | C19: =IFERROR(Model!C435+0,NA()) | D19: =IFERROR(Model!D435+0,NA()) | E19: =IFERROR(Model!E435+0,NA()) | F19: =IFERROR(Model!F435+0,NA()) | G19: =IFERROR(Model!G435+0,NA()) | H19: =IFERROR(Model!H435+0,NA()) | I19: =IFERROR(Model!I435+0,NA()) | J19: =IFERROR(Model!J435+0,NA()) | ... L19: =IFERROR(Model!L435+0,NA()) | M19: =IFERROR(Model!Q435+0,NA()) | N19: =IFERROR(Model!V435+0,NA()) | O19: =IFERROR(Model!AA435+0,NA()) | P19: =IFERROR(Model!AF435+0,NA()) | Q19: =IFERROR(Model!AK435+0,NA()) | R19: =IFERROR(Model!AP435+0,NA()) | S19: =IFERROR(Model!AQ435+0,NA()) | T19: =IFERROR(Model!AR435+0,NA()) | U19: =IFERROR(Model!AS435+0,NA()) | V19: =IFERROR(Model!AT435+0,NA())
B20: Adj. EBITDA margin % | C20: =IFERROR(Model!C279+0,NA()) | D20: =IFERROR(Model!D279+0,NA()) | E20: =IFERROR(Model!E279+0,NA()) | F20: =IFERROR(Model!F279+0,NA()) | G20: =IFERROR(Model!G279+0,NA()) | H20: =IFERROR(Model!H279+0,NA()) | I20: =IFERROR(Model!I279+0,NA()) | J20: =IFERROR(Model!J279+0,NA()) | ... L20: =IFERROR(Model!L279+0,NA()) | M20: =IFERROR(Model!Q279+0,NA()) | N20: =IFERROR(Model!V279+0,NA()) | O20: =IFERROR(Model!AA279+0,NA()) | P20: =IFERROR(Model!AF279+0,NA()) | Q20: =IFERROR(Model!AK279+0,NA()) | R20: =IFERROR(Model!AP279+0,NA()) | S20: =IFERROR(Model!AQ279+0,NA()) | T20: =IFERROR(Model!AR279+0,NA()) | U20: =IFERROR(Model!AS279+0,NA()) | V20: =IFERROR(Model!AT279+0,NA())
B21: FCF margin % | C21: =IFERROR(Model!C317+0,NA()) | D21: =IFERROR(Model!D317+0,NA()) | E21: =IFERROR(Model!E317+0,NA()) | F21: =IFERROR(Model!F317+0,NA()) | G21: =IFERROR(Model!G317+0,NA()) | H21: =IFERROR(Model!H317+0,NA()) | I21: =IFERROR(Model!I317+0,NA()) | J21: =IFERROR(Model!J317+0,NA()) | ... L21: =IFERROR(Model!L317+0,NA()) | M21: =IFERROR(Model!Q317+0,NA()) | N21: =IFERROR(Model!V317+0,NA()) | O21: =IFERROR(Model!AA317+0,NA()) | P21: =IFERROR(Model!AF317+0,NA()) | Q21: =IFERROR(Model!AK317+0,NA()) | R21: =IFERROR(Model!AP317+0,NA()) | S21: =IFERROR(Model!AQ317+0,NA()) | T21: =IFERROR(Model!AR317+0,NA()) | U21: =IFERROR(Model!AS317+0,NA()) | V21: =IFERROR(Model!AT317+0,NA())
