Workbook

Sheet Model
CF1: SCENARIO SWITCH ▼ (Bull / Base / Bear) — drives all scenario-linked forecast drivers
B2: Thermo Fisher Scientific Inc. (NYSE: TMO) — 3-Statement Financial Model | CF2: Base
B3: US GAAP as reported · USD millions (per-share data in USD; shares in millions) · Source: Thermo Fisher Forms 10-K / 10-Q and Form 8-K quarterly earnings releases (Ex. 99.1), deal 8-Ks (Solventum P&F Sep-2025, Clario Oct-2025 / Mar-2026, notes offerings Oct-2025 / Dec-2025 / Feb-2026), SEC EDGAR CIK 0000097745 (investor-relations releases are the same documents as filed on EDGAR); FY26 guidance per the Q2-26 earnings call (23-Jul-2026; guidance is given on the call, not in the release)
B4: Basis notes: calendar fiscal year (fiscal quarters end on the Saturday nearest quarter-end). Thermo Electron merged with Fisher Scientific on 9-Nov-2006 (FY2006 includes Fisher for ~7 weeks; reported in USD thousands, converted). All periods as originally reported (no recasts). Segments: Analytical Technologies + Laboratory Products & Services (2006–Q2/11), + Specialty Diagnostics (Q3/11–2013); four segments from Q1/14 (Life Technologies, Feb-2014): Life Sciences Solutions, Analytical Instruments, Specialty Diagnostics, Laboratory Products & Services → Laboratory Products & Biopharma Services from Q4/21 (PPD, Dec-2021). Segment income = adjusted operating income (company definition). Recent portfolio: Olink Jul-2024 (LSS); Solventum Purification & Filtration 1-Sep-2025 (LSS); Clario 24-Mar-2026 (LPBS; in FY26 guidance); microbiology (SD; FY25 revenues $645m) sold to Astorg in Q3/26 (closing date per input).
CH5: Forecast | CI5: Historical | CJ5: Historical | CK5: Historical
B6: (USDm) | C6: 2006 | D6: 2007 | E6: 2008 | F6: 2009 | G6: 2010 | H6: 2011 | I6: 2012 | J6: Q1/13 | K6: Q2/13 | L6: Q3/13 | M6: Q4/13 | N6: 2013 | O6: Q1/14 | P6: Q2/14 | Q6: Q3/14 | R6: Q4/14 | S6: 2014 | T6: Q1/15 | U6: Q2/15 | V6: Q3/15 | W6: Q4/15 | X6: 2015 | Y6: Q1/16 | Z6: Q2/16 | AA6: Q3/16 | AB6: Q4/16 | AC6: 2016 | AD6: Q1/17 | AE6: Q2/17 | AF6: Q3/17 | AG6: Q4/17 | AH6: 2017 | AI6: Q1/18 | AJ6: Q2/18 | AK6: Q3/18 | AL6: Q4/18 | AM6: 2018 | AN6: Q1/19 | AO6: Q2/19 | AP6: Q3/19 | AQ6: Q4/19 | AR6: 2019 | AS6: Q1/20 | AT6: Q2/20 | AU6: Q3/20 | AV6: Q4/20 | AW6: 2020 | AX6: Q1/21 | AY6: Q2/21 | AZ6: Q3/21 | BA6: Q4/21 | BB6: 2021 | BC6: Q1/22 | BD6: Q2/22 | BE6: Q3/22 | BF6: Q4/22 | BG6: 2022 | BH6: Q1/23 | BI6: Q2/23 | BJ6: Q3/23 | BK6: Q4/23 | BL6: 2023 | BM6: Q1/24 | BN6: Q2/24 | BO6: Q3/24 | BP6: Q4/24 | BQ6: 2024 | BR6: Q1/25 | BS6: Q2/25 | BT6: Q3/25 | BU6: Q4/25 | BV6: 2025 | BW6: Q1/26 | BX6: Q2/26 | BY6: Q3/26E | BZ6: Q4/26E | CA6: 2026E | CB6: 2027E | CC6: 2028E | CD6: 2029E | CE6: 2030E | CF6: Modelling Notes | CH6: 5Y CAGR | CI6: 5Y CAGR | CJ6: 10Y CAGR | CK6: 19Y CAGR
CH7: 25-'30 | CI7: 20-'25 | CJ7: 15-'25 | CK7: 06-'25
B8: SEGMENT P&L — LIFE SCIENCES SOLUTIONS · ANALYTICAL INSTRUMENTS · SPECIALTY DIAGNOSTICS · LAB PRODUCTS & BIOPHARMA SERVICES (organic + M&A + FX build) | CF8: SEGMENT BUILD — modelling logic (prior-year revenues × (1 + organic + acquisitions/divestitures + FX) → segment income margin → adjusted operating income)
B9: Life Sciences Solutions (bioproduction, biosciences, genetic sciences; Olink Jul-24, Solventum Purification & Filtration Sep-25) — from Q1/14 | CF9: LIFE SCIENCES SOLUTIONS — modelling logic | CN9: SCENARIO INPUT TABLE — driver assumptions per Bull / Base / Bear | CO9: Bull | CP9: Base | CQ9: Bear | CR9: Bull / Bear = Base + Δ (Δ inputs on each lever header). Outlook block = high / mid / low end of the FY26 ranges.
B10: Revenues | O10: 835.5 | P10: 1103.1 | Q10: 1071.9 | R10: 1185.2 | S10: 4195.7 | T10: 1019.9 | U10: 1129.3 | V10: 1080.4 | W10: 1209.8 | X10: 4439.4 | Y10: 1133 | Z10: 1277.6 | AA10: 1231.5 | AB10: 1336 | AC10: 4978.1 | AD10: 1363.5 | AE10: 1404.6 | AF10: 1382 | AG10: 1578 | AH10: 5728 | AI10: 1499 | AJ10: 1569 | AK10: 1504 | AL10: 1697 | AM10: 6269 | AN10: 1607 | AO10: 1710 | AP10: 1701 | AQ10: 1838 | AR10: 6856 | AS10: 1774 | AT10: 2602 | AU10: 3424 | AV10: 4368 | AW10: 12168 | AX10: 4203 | AY10: 3557 | AZ10: 3721 | BA10: 4150 | BB10: 15631 | BC10: 4231 | BD10: 3292 | BE10: 2962 | BF10: 3046 | BG10: 13532 | BH10: 2612 | BI10: 2463 | BJ10: 2433 | BK10: 2469 | BL10: 9977 | BM10: 2285 | BN10: 2355 | BO10: 2387 | BP10: 2604 | BQ10: 9631 | BR10: 2341 | BS10: 2499 | BT10: 2588 | BU10: 2946 | BV10: 10374 | BW10: 2636 | BX10: 2815 | BY10: =BT10*(1+BY11) -> 2771.2594 | BZ10: =BU10*(1+BZ11) -> 2987.8785 | CA10: =SUM(BW10,BX10,BY10,BZ10) -> 11210.138 | CB10: =CA10*(1+CB11) -> 11882.746 | CC10: =CB10*(1+CC11) -> 12655.125 | CD10: =CC10*(1+CD11) -> 13540.983 | CE10: =CD10*(1+CE11) -> 14488.852 | CF10: Q3/26E–Q4/26E: prior-year quarter × (1 + organic + acquisitions/divestitures + FX). 2026E = sum of quarters. 2027E+: prior year × (1 + organic (scenario lever) + M&A + FX). | CH10: =IFERROR((CE10/BV10)^(1/5)-1,"n/m") -> 0.069098075 | CI10: =IFERROR((BV10/AW10)^(1/5)-1,"n/m") -> -0.031397895 | CJ10: =IFERROR((BV10/X10)^(1/10)-1,"n/m") -> 0.088584626 | CK10: =IFERROR((BV10/C10)^(1/19)-1,"n/m") -> n/m
B11: Revenues y/y % (reported) | D11: =IF(AND(ISNUMBER(D10),ISNUMBER(C10)),IFERROR(D10/C10-1,""),"") | E11: =IF(AND(ISNUMBER(E10),ISNUMBER(D10)),IFERROR(E10/D10-1,""),"") | F11: =IF(AND(ISNUMBER(F10),ISNUMBER(E10)),IFERROR(F10/E10-1,""),"") | G11: =IF(AND(ISNUMBER(G10),ISNUMBER(F10)),IFERROR(G10/F10-1,""),"") | H11: =IF(AND(ISNUMBER(H10),ISNUMBER(G10)),IFERROR(H10/G10-1,""),"") | I11: =IF(AND(ISNUMBER(I10),ISNUMBER(H10)),IFERROR(I10/H10-1,""),"") | N11: =IF(AND(ISNUMBER(N10),ISNUMBER(I10)),IFERROR(N10/I10-1,""),"") | O11: =IF(AND(ISNUMBER(O10),ISNUMBER(J10)),IFERROR(O10/J10-1,""),"") | P11: =IF(AND(ISNUMBER(P10),ISNUMBER(K10)),IFERROR(P10/K10-1,""),"") | Q11: =IF(AND(ISNUMBER(Q10),ISNUMBER(L10)),IFERROR(Q10/L10-1,""),"") | R11: =IF(AND(ISNUMBER(R10),ISNUMBER(M10)),IFERROR(R10/M10-1,""),"") | S11: =IF(AND(ISNUMBER(S10),ISNUMBER(N10)),IFERROR(S10/N10-1,""),"") | T11: =IF(AND(ISNUMBER(T10),ISNUMBER(O10)),IFERROR(T10/O10-1,""),"") -> 0.22070616 | U11: =IF(AND(ISNUMBER(U10),ISNUMBER(P10)),IFERROR(U10/P10-1,""),"") -> 0.023751246 | ... BX11: =IF(AND(ISNUMBER(BX10),ISNUMBER(BS10)),IFERROR(BX10/BS10-1,""),"") -> 0.12645058 | BY11: =BY12+BY13+BY14 -> 0.070811197 | BZ11: =BZ12+BZ13+BZ14 -> 0.01421537 | CA11: =IFERROR(CA10/BV10-1,"") -> 0.08059937 | CB11: =CB12+CB13+CB14 -> 0.06 | CC11: =CC12+CC13+CC14 -> 0.065 | CD11: =CD12+CD13+CD14 -> 0.07 | CE11: =CE12+CE13+CE14 -> 0.07 | CN11: FY26 outlook — Q2-26 earnings call (23-Jul-2026); revenue & margin drive the Q3/Q4-26E calibration | CO11: High | CP11: Mid | CQ11: Low | CR11: Guidance given on the earnings call (not in the Form 8-K release). Bull = high end, Base = mid-point, Bear = low end.
B12: of which: organic growth % (company-reported; forecast driver) | BB12: 0.23 | BC12: -0.01 | BD12: -0.05 | BE12: -0.17 | BG12: -0.12 | BH12: -0.37 | BI12: -0.25 | BJ12: -0.19 | BL12: -0.26 | BM12: -0.12 | BN12: -0.03 | BO12: -0.04 | BQ12: -0.04 | BR12: 0.02 | BS12: 0.04 | BT12: 0.05 | BV12: 0.03 | BW12: 0.01 | BX12: 0.03 | BY12: =$BX12+BY117 -> 0.02171537 | BZ12: =$BX12+BZ117 -> 0.02171537 | CB12: =CHOOSE(MATCH($CF$2,{"Bull","Base","Bear"},0),$CO$30,$CP$30,$CQ$30) -> 0.06 | CC12: =CHOOSE(MATCH($CF$2,{"Bull","Base","Bear"},0),$CO$31,$CP$31,$CQ$31) -> 0.065 | CD12: =CHOOSE(MATCH($CF$2,{"Bull","Base","Bear"},0),$CO$32,$CP$32,$CQ$32) -> 0.07 | CE12: =CHOOSE(MATCH($CF$2,{"Bull","Base","Bear"},0),$CO$33,$CP$33,$CQ$33) -> 0.07 | CF12: Q3/Q4-26E: Q2/26 segment organic growth + revenue-outlook calibration Δ (Group block). 2027E–2030E: scenario lever LSS_org (Bull / Base / Bear table →). Bioproduction (pharma/biotech) recovery; FY25 +3%, Q2/26 +3%. | CN12: FY26 revenues ($m) | CO12: 48100 | CP12: 47750 | CQ12: 47400 | CR12: Raised to $47.4–48.1bn (from $47.3–48.1bn in April); 6–8% reported growth.
B13: of which: acquisitions / divestitures % | BB13: 0.03 | BC13: 0.03 | BD13: 0.01 | BE13: 0.01 | BG13: 0.01 | BH13: 0 | BI13: 0 | BJ13: 0 | BL13: 0 | BM13: 0 | BN13: 0 | BO13: 0.02 | BQ13: 0.01 | BR13: 0.02 | BS13: 0.01 | BT13: 0.03 | BV13: 0.03 | BW13: 0.09 | BX13: 0.09 | BY13: =$CA$71*2/BT10 -> 0.054095827 | BZ13: 0 | CB13: 0 | CC13: 0 | CD13: 0 | CE13: 0 | CF13: Q3/26E: Solventum P&F (closed 1-Sep-2025) was in Q3/25 for one month → +2 months of run-rate (input row in portfolio block) ÷ Q3/25 LSS revenues; Q4/26E 0% (anniversaried). 2027E+: 0% (future M&A modelled unallocated below). | CN13: FY26 adjusted operating margin | CO13: 0.236 | CP13: 0.235 | CQ13: 0.234 | CR13: ~80bp expansion on FY25 22.7% (mid-point); ±10bp for the ends.
B14: of which: currency translation % | BB14: 0.02 | BC14: -0.02 | BD14: -0.03 | BE14: -0.04 | BG14: -0.03 | BH14: -0.02 | BI14: 0 | BJ14: 0.01 | BL14: 0 | BM14: 0 | BN14: -0.01 | BO14: 0 | BQ14: 0 | BR14: -0.01 | BS14: 0.01 | BT14: 0.01 | BV14: 0.01 | BW14: 0.03 | BX14: 0.01 | BY14: =BY113 -> -0.005 | BZ14: =BZ113 -> -0.0075 | CB14: =CB113 -> 0 | CC14: =CC113 -> 0 | CD14: =CD113 -> 0 | CE14: =CE113 -> 0 | CF14: Linked to the FX assumption row (Group block). | CN14: FY26 adjusted EPS ($) | CO14: 25.33 | CP14: 25.13 | CQ14: 24.93 | CR14: Raised to $24.93–25.33 (+9–11%); memo — EPS is an output of the model.
B15: Segment income (= segment adjusted operating income) | O15: 244.6 | P15: 299.1 | Q15: 306.3 | R15: 364.9 | S15: 1214.9 | T15: 298.7 | U15: 323.5 | V15: 332.7 | W15: 382 | X15: 1336.9 | Y15: 330 | Z15: 369.6 | AA15: 370.1 | AB15: 445 | AC15: 1514.7 | AD15: 433.9 | AE15: 448.1 | AF15: 453 | AG15: 561 | AH15: 1896 | AI15: 517 | AJ15: 522 | AK15: 495 | AL15: 624 | AM15: 2158 | AN15: 561 | AO15: 609 | AP15: 586 | AQ15: 690 | AR15: 2446 | AS15: 675 | AT15: 1234 | AU15: 1879 | AV15: 2321 | AW15: 6109 | AX15: 2279 | AY15: 1718 | AZ15: 1821 | BA15: 1999 | BB15: 7817 | BC15: 2176 | BD15: 1327 | BE15: 1039 | BF15: 1040 | BG15: 5582 | BH15: 836 | BI15: 817 | BJ15: 872 | BK15: 895 | BL15: 3420 | BM15: 840 | BN15: 865 | BO15: 845 | BP15: 952 | BQ15: 3503 | BR15: 834 | BS15: 919 | BT15: 968 | BU15: 1046 | BV15: 3768 | BW15: 954 | BX15: 1041 | BY15: =BY10*BY17 -> 1074.9417 | BZ15: =BZ10*BZ17 -> 1102.2671 | CA15: =SUM(BW15,BX15,BY15,BZ15) -> 4172.2088 | CB15: =CB10*CB17 -> 4467.9125 | CC15: =CC10*CC17 -> 4808.9474 | CD15: =CD10*CD17 -> 5199.7376 | CE15: =CE10*CE17 -> 5621.6746 | CH15: =IFERROR((CE15/BV15)^(1/5)-1,"n/m") -> 0.083305536 | CI15: =IFERROR((BV15/AW15)^(1/5)-1,"n/m") -> -0.092120617 | CJ15: =IFERROR((BV15/X15)^(1/10)-1,"n/m") -> 0.10917787 | CK15: =IFERROR((BV15/C15)^(1/19)-1,"n/m") -> n/m | CN15: FY26 free cash flow ($m) | CO15: 7400 | CP15: 7150 | CQ15: 6900 | CR15: $6.9–7.4bn (memo).
B16: Segment margin before outlook calibration % (Q3/Q4-26E helper) | BY16: =BT17+(BW15+BX15)/(BW10+BX10)-(BR15+BS15)/(BR10+BS10) -> 0.37783181 | BZ16: =BU17+(BW15+BX15)/(BW10+BX10)-(BR15+BS15)/(BR10+BS10) -> 0.35885551 | CF16: Q3/Q4-26E: prior-year quarter margin + (1H/26 − 1H/25 margin drift). | CN16: FY26 net capital expenditures ($m) | CO16: 2100 | CP16: 2000 | CQ16: 1900 | CR16: $1.9–2.1bn net capex; Bull = high end (growth capacity), Bear = low end.
B17: Segment income margin % | C17: =IF(AND(ISNUMBER(C15),ISNUMBER(C10)),C15/C10,"") | D17: =IF(AND(ISNUMBER(D15),ISNUMBER(D10)),D15/D10,"") | E17: =IF(AND(ISNUMBER(E15),ISNUMBER(E10)),E15/E10,"") | F17: =IF(AND(ISNUMBER(F15),ISNUMBER(F10)),F15/F10,"") | G17: =IF(AND(ISNUMBER(G15),ISNUMBER(G10)),G15/G10,"") | H17: =IF(AND(ISNUMBER(H15),ISNUMBER(H10)),H15/H10,"") | I17: =IF(AND(ISNUMBER(I15),ISNUMBER(I10)),I15/I10,"") | J17: =IF(AND(ISNUMBER(J15),ISNUMBER(J10)),J15/J10,"") | ... BX17: =IF(AND(ISNUMBER(BX15),ISNUMBER(BX10)),BX15/BX10,"") -> 0.36980462 | BY17: =BY16+BY122 -> 0.38788925 | BZ17: =BZ16+BZ122 -> 0.36891295 | CA17: =IFERROR(CA15/CA10,"") -> 0.37218176 | CB17: =CHOOSE(MATCH($CF$2,{"Bull","Base","Bear"},0),$CO$50,$CP$50,$CQ$50) -> 0.376 | CC17: =CHOOSE(MATCH($CF$2,{"Bull","Base","Bear"},0),$CO$51,$CP$51,$CQ$51) -> 0.38 | CD17: =CHOOSE(MATCH($CF$2,{"Bull","Base","Bear"},0),$CO$52,$CP$52,$CQ$52) -> 0.384 | CE17: =CHOOSE(MATCH($CF$2,{"Bull","Base","Bear"},0),$CO$53,$CP$53,$CQ$53) -> 0.388 | CF17: Q3/Q4-26E: pre-calibration margin + outlook calibration Δ (adjusted operating margin guidance). 2027E+: scenario lever LSS_m. FY25 36.3% (Solventum P&F dilution); bioproduction mix and productivity drive expansion. | CN17: FY26 point estimates (all cases)
B18: Incremental segment margin (Δ income ÷ Δ revenues) | D18: =IF(AND(ISNUMBER(D15),ISNUMBER(C15)),IFERROR((D15-C15)/(D10-C10),""),"") | E18: =IF(AND(ISNUMBER(E15),ISNUMBER(D15)),IFERROR((E15-D15)/(E10-D10),""),"") | F18: =IF(AND(ISNUMBER(F15),ISNUMBER(E15)),IFERROR((F15-E15)/(F10-E10),""),"") | G18: =IF(AND(ISNUMBER(G15),ISNUMBER(F15)),IFERROR((G15-F15)/(G10-F10),""),"") | H18: =IF(AND(ISNUMBER(H15),ISNUMBER(G15)),IFERROR((H15-G15)/(H10-G10),""),"") | I18: =IF(AND(ISNUMBER(I15),ISNUMBER(H15)),IFERROR((I15-H15)/(I10-H10),""),"") | N18: =IF(AND(ISNUMBER(N15),ISNUMBER(I15)),IFERROR((N15-I15)/(N10-I10),""),"") | O18: =IF(AND(ISNUMBER(O15),ISNUMBER(J15)),IFERROR((O15-J15)/(O10-J10),""),"") | P18: =IF(AND(ISNUMBER(P15),ISNUMBER(K15)),IFERROR((P15-K15)/(P10-K10),""),"") | Q18: =IF(AND(ISNUMBER(Q15),ISNUMBER(L15)),IFERROR((Q15-L15)/(Q10-L10),""),"") | R18: =IF(AND(ISNUMBER(R15),ISNUMBER(M15)),IFERROR((R15-M15)/(R10-M10),""),"") | S18: =IF(AND(ISNUMBER(S15),ISNUMBER(N15)),IFERROR((S15-N15)/(S10-N10),""),"") | T18: =IF(AND(ISNUMBER(T15),ISNUMBER(O15)),IFERROR((T15-O15)/(T10-O10),""),"") -> 0.29338395 | U18: =IF(AND(ISNUMBER(U15),ISNUMBER(P15)),IFERROR((U15-P15)/(U10-P10),""),"") -> 0.93129771 | ... BX18: =IF(AND(ISNUMBER(BX15),ISNUMBER(BS15)),IFERROR((BX15-BS15)/(BX10-BS10),""),"") -> 0.38607595 | BY18: =IFERROR((BY15-BT15)/(BY10-BT10),"") -> 0.58355388 | BZ18: =IFERROR((BZ15-BU15)/(BZ10-BU10),"") -> 1.3435795 | CA18: =IFERROR((CA15-BV15)/(CA10-BV10),"") -> 0.48342362 | CB18: =IFERROR((CB15-CA15)/(CB10-CA10),"") -> 0.4396374 | CC18: =IFERROR((CC15-CB15)/(CC10-CB10),"") -> 0.44153846 | CD18: =IFERROR((CD15-CC15)/(CD10-CC10),"") -> 0.44114286 | CE18: =IFERROR((CE15-CD15)/(CE10-CD10),"") -> 0.44514286 | CN18: Organic revenue growth (memo) | CP18: 0.04 | CR18: ~4% (raised from 3–4%).
B19: Segment income y/y % | D19: =IF(AND(ISNUMBER(D15),ISNUMBER(C15)),IFERROR(D15/C15-1,""),"") | E19: =IF(AND(ISNUMBER(E15),ISNUMBER(D15)),IFERROR(E15/D15-1,""),"") | F19: =IF(AND(ISNUMBER(F15),ISNUMBER(E15)),IFERROR(F15/E15-1,""),"") | G19: =IF(AND(ISNUMBER(G15),ISNUMBER(F15)),IFERROR(G15/F15-1,""),"") | H19: =IF(AND(ISNUMBER(H15),ISNUMBER(G15)),IFERROR(H15/G15-1,""),"") | I19: =IF(AND(ISNUMBER(I15),ISNUMBER(H15)),IFERROR(I15/H15-1,""),"") | N19: =IF(AND(ISNUMBER(N15),ISNUMBER(I15)),IFERROR(N15/I15-1,""),"") | O19: =IF(AND(ISNUMBER(O15),ISNUMBER(J15)),IFERROR(O15/J15-1,""),"") | P19: =IF(AND(ISNUMBER(P15),ISNUMBER(K15)),IFERROR(P15/K15-1,""),"") | Q19: =IF(AND(ISNUMBER(Q15),ISNUMBER(L15)),IFERROR(Q15/L15-1,""),"") | R19: =IF(AND(ISNUMBER(R15),ISNUMBER(M15)),IFERROR(R15/M15-1,""),"") | S19: =IF(AND(ISNUMBER(S15),ISNUMBER(N15)),IFERROR(S15/N15-1,""),"") | T19: =IF(AND(ISNUMBER(T15),ISNUMBER(O15)),IFERROR(T15/O15-1,""),"") -> 0.22117743 | U19: =IF(AND(ISNUMBER(U15),ISNUMBER(P15)),IFERROR(U15/P15-1,""),"") -> 0.081578068 | ... BX19: =IF(AND(ISNUMBER(BX15),ISNUMBER(BS15)),IFERROR(BX15/BS15-1,""),"") -> 0.13275299 | BY19: =IFERROR(BY15/BT15-1,"") -> 0.11047698 | BZ19: =IFERROR(BZ15/BU15-1,"") -> 0.05379261 | CA19: =IFERROR(CA15/BV15-1,"") -> 0.1072741 | CB19: =IFERROR(CB15/CA15-1,"") -> 0.07087463 | CC19: =IFERROR(CC15/CB15-1,"") -> 0.076329787 | CD19: =IFERROR(CD15/CC15-1,"") -> 0.081263158 | CE19: =IFERROR(CE15/CD15-1,"") -> 0.081145833 | CN19: Revenue contribution from acquisitions ($m, memo) | CP19: 1600 | CR19: Clario + Solventum P&F stub; $0.32 adjusted EPS.
CN20: Net interest expense ($m) | CP20: 660 | CR20: ~$660m (Q2-26 call); drives Q3/Q4-26E interest income.
B21: Analytical Instruments (chromatography & mass spectrometry, electron microscopy, chemical analysis) — from Q1/14 | CF21: ANALYTICAL INSTRUMENTS — modelling logic | CN21: Adjusted tax rate | CP21: 0.115 | CR21: 11.5% (Q2-26 call).
B22: Revenues | O22: 769.9 | P22: 793.4 | Q22: 786.5 | R22: 902.4 | S22: 3252.2 | T22: 727.4 | U22: 777 | V22: 778.5 | W22: 925.3 | X22: 3208.2 | Y22: 759.3 | Z22: 793.9 | AA22: 898 | AB22: 1217 | AC22: 3668.2 | AD22: 1052 | AE22: 1165.8 | AF22: 1189.6 | AG22: 1414 | AH22: 4821 | AI22: 1257 | AJ22: 1311 | AK22: 1333 | AL22: 1568 | AM22: 5469 | AN22: 1322 | AO22: 1324 | AP22: 1358 | AQ22: 1518 | AR22: 5522 | AS22: 1101 | AT22: 1051 | AU22: 1336 | AV22: 1636 | AW22: 5124 | AX22: 1387 | AY22: 1481 | AZ22: 1476 | BA22: 1725 | BB22: 6069 | BC22: 1518 | BD22: 1607 | BE22: 1621 | BF22: 1878 | BG22: 6624 | BH22: 1723 | BI22: 1749 | BJ22: 1754 | BK22: 2037 | BL22: 7263 | BM22: 1687 | BN22: 1782 | BO22: 1808 | BP22: 2186 | BQ22: 7463 | BR22: 1718 | BS22: 1728 | BT22: 1893 | BU22: 2215 | BV22: 7554 | BW22: 1716 | BX22: 1847 | BY22: =BT22*(1+BY23) -> 2000.3622 | BZ22: =BU22*(1+BZ23) -> 2335.087 | CA22: =SUM(BW22,BX22,BY22,BZ22) -> 7898.4492 | CB22: =CA22*(1+CB23) -> 8293.3717 | CC22: =CB22*(1+CC23) -> 8749.5071 | CD22: =CC22*(1+CD23) -> 9230.73 | CE22: =CD22*(1+CE23) -> 9738.4202 | CH22: =IFERROR((CE22/BV22)^(1/5)-1,"n/m") -> 0.052112804 | CI22: =IFERROR((BV22/AW22)^(1/5)-1,"n/m") -> 0.080720954 | CJ22: =IFERROR((BV22/X22)^(1/10)-1,"n/m") -> 0.089410495 | CK22: =IFERROR((BV22/C22)^(1/19)-1,"n/m") -> n/m | CN22: Dividends ($m, memo) | CP22: 700 | CR22: ~$700m.
B23: Revenues y/y % (reported) | D23: =IF(AND(ISNUMBER(D22),ISNUMBER(C22)),IFERROR(D22/C22-1,""),"") | E23: =IF(AND(ISNUMBER(E22),ISNUMBER(D22)),IFERROR(E22/D22-1,""),"") | F23: =IF(AND(ISNUMBER(F22),ISNUMBER(E22)),IFERROR(F22/E22-1,""),"") | G23: =IF(AND(ISNUMBER(G22),ISNUMBER(F22)),IFERROR(G22/F22-1,""),"") | H23: =IF(AND(ISNUMBER(H22),ISNUMBER(G22)),IFERROR(H22/G22-1,""),"") | I23: =IF(AND(ISNUMBER(I22),ISNUMBER(H22)),IFERROR(I22/H22-1,""),"") | N23: =IF(AND(ISNUMBER(N22),ISNUMBER(I22)),IFERROR(N22/I22-1,""),"") | O23: =IF(AND(ISNUMBER(O22),ISNUMBER(J22)),IFERROR(O22/J22-1,""),"") | P23: =IF(AND(ISNUMBER(P22),ISNUMBER(K22)),IFERROR(P22/K22-1,""),"") | Q23: =IF(AND(ISNUMBER(Q22),ISNUMBER(L22)),IFERROR(Q22/L22-1,""),"") | R23: =IF(AND(ISNUMBER(R22),ISNUMBER(M22)),IFERROR(R22/M22-1,""),"") | S23: =IF(AND(ISNUMBER(S22),ISNUMBER(N22)),IFERROR(S22/N22-1,""),"") | T23: =IF(AND(ISNUMBER(T22),ISNUMBER(O22)),IFERROR(T22/O22-1,""),"") -> -0.055201974 | U23: =IF(AND(ISNUMBER(U22),ISNUMBER(P22)),IFERROR(U22/P22-1,""),"") -> -0.020670532 | ... BX23: =IF(AND(ISNUMBER(BX22),ISNUMBER(BS22)),IFERROR(BX22/BS22-1,""),"") -> 0.068865741 | BY23: =BY24+BY25+BY26 -> 0.05671537 | BZ23: =BZ24+BZ25+BZ26 -> 0.05421537 | CA23: =IFERROR(CA22/BV22-1,"") -> 0.045598258 | CB23: =CB24+CB25+CB26 -> 0.05 | CC23: =CC24+CC25+CC26 -> 0.055 | CD23: =CD24+CD25+CD26 -> 0.055 | CE23: =CE24+CE25+CE26 -> 0.055 | CN23: Share repurchases FY26 plan ($m, memo) | CP23: 4000 | CR23: $4.0bn — fully executed in 1H/26 ($3.0bn Q1, $1.0bn Q2).
B24: of which: organic growth % (company-reported; forecast driver) | BB24: 0.17 | BC24: 0.12 | BD24: 0.13 | BE24: 0.16 | BG24: 0.14 | BH24: 0.17 | BI24: 0.1 | BJ24: 0.08 | BL24: 0.1 | BM24: -0.01 | BN24: 0.03 | BO24: 0.03 | BQ24: 0.03 | BR24: 0.03 | BS24: -0.04 | BT24: 0.04 | BV24: 0 | BW24: -0.02 | BX24: 0.07 | BY24: =$BX24+BY117 -> 0.06171537 | BZ24: =$BX24+BZ117 -> 0.06171537 | CB24: =CHOOSE(MATCH($CF$2,{"Bull","Base","Bear"},0),$CO$35,$CP$35,$CQ$35) -> 0.05 | CC24: =CHOOSE(MATCH($CF$2,{"Bull","Base","Bear"},0),$CO$36,$CP$36,$CQ$36) -> 0.055 | CD24: =CHOOSE(MATCH($CF$2,{"Bull","Base","Bear"},0),$CO$37,$CP$37,$CQ$37) -> 0.055 | CE24: =CHOOSE(MATCH($CF$2,{"Bull","Base","Bear"},0),$CO$38,$CP$38,$CQ$38) -> 0.055 | CF24: Q3/Q4-26E: Q2/26 segment organic growth + revenue-outlook calibration Δ (Group block). 2027E–2030E: scenario lever AI_org (Bull / Base / Bear table →). Electron microscopy, chromatography & MS (pharma, semis, academic); FY25 0%, Q2/26 +7%. | CN24: 2H/26 share repurchases ($m) | CO24: 1000 | CP24: 0 | CQ24: 0 | CR24: Plan completed in 1H; Bull assumes an incremental $1bn in 2H.
B25: of which: acquisitions / divestitures % | BB25: 0 | BC25: 0 | BD25: 0 | BE25: 0 | BG25: 0 | BH25: 0 | BI25: 0 | BJ25: 0 | BL25: 0 | BM25: 0 | BN25: 0 | BO25: 0 | BQ25: 0 | BR25: 0 | BS25: 0 | BT25: 0 | BV25: 0 | BW25: 0 | BX25: 0 | BY25: 0 | BZ25: 0 | CB25: 0 | CC25: 0 | CD25: 0 | CE25: 0 | CF25: Two small proteomics-software acquisitions in 2026 (not material; Q1–Q2/26 contribution 0%). Forecast 0%.
B26: of which: currency translation % | BB26: 0.02 | BC26: -0.02 | BD26: -0.04 | BE26: -0.06 | BG26: -0.05 | BH26: -0.03 | BI26: -0.01 | BJ26: 0.01 | BL26: -0.01 | BM26: -0.01 | BN26: -0.01 | BO26: 0 | BQ26: -0.01 | BR26: -0.01 | BS26: 0.01 | BT26: 0.01 | BV26: 0.01 | BW26: 0.02 | BX26: 0 | BY26: =BY113 -> -0.005 | BZ26: =BZ113 -> -0.0075 | CB26: =CB113 -> 0 | CC26: =CC113 -> 0 | CD26: =CD113 -> 0 | CE26: =CE113 -> 0 | CN26: Capital allocation 2027E+
B27: Segment income (= segment adjusted operating income) | O27: 130.9 | P27: 130.4 | Q27: 137.8 | R27: 182 | S27: 581.1 | T27: 121.7 | U27: 139.6 | V27: 146.5 | W27: 205 | X27: 612.8 | Y27: 111.7 | Z27: 144.9 | AA27: 190.1 | AB27: 298.5 | AC27: 745.2 | AD27: 191.8 | AE27: 232.6 | AF27: 256.6 | AG27: 346 | AH27: 1027 | AI27: 246 | AJ27: 291 | AK27: 294 | AL27: 416 | AM27: 1247 | AN27: 282 | AO27: 286 | AP27: 311 | AQ27: 394 | AR27: 1273 | AS27: 171 | AT27: 135 | AU27: 171 | AV27: 331 | AW27: 808 | AX27: 272 | AY27: 280 | AZ27: 264 | BA27: 381 | BB27: 1197 | BC27: 301 | BD27: 344 | BE27: 386 | BF27: 476 | BG27: 1507 | BH27: 421 | BI27: 432 | BJ27: 468 | BK27: 587 | BL27: 1908 | BM27: 400 | BN27: 439 | BO27: 451 | BP27: 666 | BQ27: 1955 | BR27: 399 | BS27: 325 | BT27: 429 | BU27: 583 | BV27: 1736 | BW27: 355 | BX27: 424 | BY27: =BY22*BY29 -> 490.52713 | BZ27: =BZ22*BZ29 -> 658.02793 | CA27: =SUM(BW27,BX27,BY27,BZ27) -> 1927.5551 | CB27: =CB22*CB29 -> 2073.3429 | CC27: =CC22*CC29 -> 2231.1243 | CD27: =CD22*CD29 -> 2399.9898 | CE27: =CE22*CE29 -> 2580.6814 | CH27: =IFERROR((CE27/BV27)^(1/5)-1,"n/m") -> 0.082522502 | CI27: =IFERROR((BV27/AW27)^(1/5)-1,"n/m") -> 0.16527297 | CJ27: =IFERROR((BV27/X27)^(1/10)-1,"n/m") -> 0.10974474 | CK27: =IFERROR((BV27/C27)^(1/19)-1,"n/m") -> n/m | CN27: Minimum net debt / adjusted EBITDA (x) — buyback floor 2027E+ | CO27: 2.75 | CP27: 2.5 | CQ27: 2.25 | CR27: TMO: 3.5x after Clario (Q1-26 call), deleveraging to ~2.5x by YE26 in the model; TMO has run ~2.5–3.0x between large deals (A-/A3 ratings).
B28: Segment margin before outlook calibration % (Q3/Q4-26E helper) | BY28: =BT29+(BW27+BX27)/(BW22+BX22)-(BR27+BS27)/(BR22+BS22) -> 0.23516172 | BZ28: =BU29+(BW27+BX27)/(BW22+BX22)-(BR27+BS27)/(BR22+BS22) -> 0.27174273 | CF28: Q3/Q4-26E: prior-year quarter margin + (1H/26 − 1H/25 margin drift).
B29: Segment income margin % | C29: =IF(AND(ISNUMBER(C27),ISNUMBER(C22)),C27/C22,"") | D29: =IF(AND(ISNUMBER(D27),ISNUMBER(D22)),D27/D22,"") | E29: =IF(AND(ISNUMBER(E27),ISNUMBER(E22)),E27/E22,"") | F29: =IF(AND(ISNUMBER(F27),ISNUMBER(F22)),F27/F22,"") | G29: =IF(AND(ISNUMBER(G27),ISNUMBER(G22)),G27/G22,"") | H29: =IF(AND(ISNUMBER(H27),ISNUMBER(H22)),H27/H22,"") | I29: =IF(AND(ISNUMBER(I27),ISNUMBER(I22)),I27/I22,"") | J29: =IF(AND(ISNUMBER(J27),ISNUMBER(J22)),J27/J22,"") | ... BX29: =IF(AND(ISNUMBER(BX27),ISNUMBER(BX22)),BX27/BX22,"") -> 0.22956145 | BY29: =BY28+BY122 -> 0.24521916 | BZ29: =BZ28+BZ122 -> 0.28180017 | CA29: =IFERROR(CA27/CA22,"") -> 0.24404222 | CB29: =CHOOSE(MATCH($CF$2,{"Bull","Base","Bear"},0),$CO$55,$CP$55,$CQ$55) -> 0.25 | CC29: =CHOOSE(MATCH($CF$2,{"Bull","Base","Bear"},0),$CO$56,$CP$56,$CQ$56) -> 0.255 | CD29: =CHOOSE(MATCH($CF$2,{"Bull","Base","Bear"},0),$CO$57,$CP$57,$CQ$57) -> 0.26 | CE29: =CHOOSE(MATCH($CF$2,{"Bull","Base","Bear"},0),$CO$58,$CP$58,$CQ$58) -> 0.265 | CF29: Q3/Q4-26E: pre-calibration margin + outlook calibration Δ (adjusted operating margin guidance). 2027E+: scenario lever AI_m. FY25 23.0% (tariffs, FX); recovery toward ~26% with volume leverage. | CN29: LSS_org (Life Sciences Solutions organic growth) | CO29: 0.02 | CP29: Δ → | CQ29: -0.02 | CR29: Bioproduction recovery, proteomics (Olink), cell & gene therapy; FY25 +3%, Q2/26 +3%.
B30: Incremental segment margin (Δ income ÷ Δ revenues) | D30: =IF(AND(ISNUMBER(D27),ISNUMBER(C27)),IFERROR((D27-C27)/(D22-C22),""),"") | E30: =IF(AND(ISNUMBER(E27),ISNUMBER(D27)),IFERROR((E27-D27)/(E22-D22),""),"") | F30: =IF(AND(ISNUMBER(F27),ISNUMBER(E27)),IFERROR((F27-E27)/(F22-E22),""),"") | G30: =IF(AND(ISNUMBER(G27),ISNUMBER(F27)),IFERROR((G27-F27)/(G22-F22),""),"") | H30: =IF(AND(ISNUMBER(H27),ISNUMBER(G27)),IFERROR((H27-G27)/(H22-G22),""),"") | I30: =IF(AND(ISNUMBER(I27),ISNUMBER(H27)),IFERROR((I27-H27)/(I22-H22),""),"") | N30: =IF(AND(ISNUMBER(N27),ISNUMBER(I27)),IFERROR((N27-I27)/(N22-I22),""),"") | O30: =IF(AND(ISNUMBER(O27),ISNUMBER(J27)),IFERROR((O27-J27)/(O22-J22),""),"") | P30: =IF(AND(ISNUMBER(P27),ISNUMBER(K27)),IFERROR((P27-K27)/(P22-K22),""),"") | Q30: =IF(AND(ISNUMBER(Q27),ISNUMBER(L27)),IFERROR((Q27-L27)/(Q22-L22),""),"") | R30: =IF(AND(ISNUMBER(R27),ISNUMBER(M27)),IFERROR((R27-M27)/(R22-M22),""),"") | S30: =IF(AND(ISNUMBER(S27),ISNUMBER(N27)),IFERROR((S27-N27)/(S22-N22),""),"") | T30: =IF(AND(ISNUMBER(T27),ISNUMBER(O27)),IFERROR((T27-O27)/(T22-O22),""),"") -> 0.21647059 | U30: =IF(AND(ISNUMBER(U27),ISNUMBER(P27)),IFERROR((U27-P27)/(U22-P22),""),"") -> -0.56097561 | ... BX30: =IF(AND(ISNUMBER(BX27),ISNUMBER(BS27)),IFERROR((BX27-BS27)/(BX22-BS22),""),"") -> 0.83193277 | BY30: =IFERROR((BY27-BT27)/(BY22-BT22),"") -> 0.57308007 | BZ30: =IFERROR((BZ27-BU27)/(BZ22-BU22),"") -> 0.62477953 | CA30: =IFERROR((CA27-BV27)/(CA22-BV22),"") -> 0.55611985 | CB30: =IFERROR((CB27-CA27)/(CB22-CA22),"") -> 0.36915567 | CC30: =IFERROR((CC27-CB27)/(CC22-CB22),"") -> 0.34590909 | CD30: =IFERROR((CD27-CC27)/(CD22-CC22),"") -> 0.35090909 | CE30: =IFERROR((CE27-CD27)/(CE22-CD22),"") -> 0.35590909 | CN30: 2027E | CO30: =CP30+$CO$29 -> 0.08 | CP30: 0.06 | CQ30: =CP30+$CQ$29 -> 0.04
B31: Segment income y/y % | D31: =IF(AND(ISNUMBER(D27),ISNUMBER(C27)),IFERROR(D27/C27-1,""),"") | E31: =IF(AND(ISNUMBER(E27),ISNUMBER(D27)),IFERROR(E27/D27-1,""),"") | F31: =IF(AND(ISNUMBER(F27),ISNUMBER(E27)),IFERROR(F27/E27-1,""),"") | G31: =IF(AND(ISNUMBER(G27),ISNUMBER(F27)),IFERROR(G27/F27-1,""),"") | H31: =IF(AND(ISNUMBER(H27),ISNUMBER(G27)),IFERROR(H27/G27-1,""),"") | I31: =IF(AND(ISNUMBER(I27),ISNUMBER(H27)),IFERROR(I27/H27-1,""),"") | N31: =IF(AND(ISNUMBER(N27),ISNUMBER(I27)),IFERROR(N27/I27-1,""),"") | O31: =IF(AND(ISNUMBER(O27),ISNUMBER(J27)),IFERROR(O27/J27-1,""),"") | P31: =IF(AND(ISNUMBER(P27),ISNUMBER(K27)),IFERROR(P27/K27-1,""),"") | Q31: =IF(AND(ISNUMBER(Q27),ISNUMBER(L27)),IFERROR(Q27/L27-1,""),"") | R31: =IF(AND(ISNUMBER(R27),ISNUMBER(M27)),IFERROR(R27/M27-1,""),"") | S31: =IF(AND(ISNUMBER(S27),ISNUMBER(N27)),IFERROR(S27/N27-1,""),"") | T31: =IF(AND(ISNUMBER(T27),ISNUMBER(O27)),IFERROR(T27/O27-1,""),"") -> -0.070282659 | U31: =IF(AND(ISNUMBER(U27),ISNUMBER(P27)),IFERROR(U27/P27-1,""),"") -> 0.070552147 | ... BX31: =IF(AND(ISNUMBER(BX27),ISNUMBER(BS27)),IFERROR(BX27/BS27-1,""),"") -> 0.30461538 | BY31: =IFERROR(BY27/BT27-1,"") -> 0.14341989 | BZ31: =IFERROR(BZ27/BU27-1,"") -> 0.12869284 | CA31: =IFERROR(CA27/BV27-1,"") -> 0.11034278 | CB31: =IFERROR(CB27/CA27-1,"") -> 0.075633567 | CC31: =IFERROR(CC27/CB27-1,"") -> 0.0761 | CD31: =IFERROR(CD27/CC27-1,"") -> 0.075686275 | CE31: =IFERROR(CE27/CD27-1,"") -> 0.075288462 | CN31: 2028E | CO31: =CP31+$CO$29 -> 0.085 | CP31: 0.065 | CQ31: =CP31+$CQ$29 -> 0.045
CN32: 2029E | CO32: =CP32+$CO$29 -> 0.09 | CP32: 0.07 | CQ32: =CP32+$CQ$29 -> 0.05
B33: Specialty Diagnostics (clinical & immunodiagnostics, transplant, healthcare market channel; microbiology sold Q3/26) — from Q1/14 | CF33: SPECIALTY DIAGNOSTICS — modelling logic | CN33: 2030E | CO33: =CP33+$CO$29 -> 0.09 | CP33: 0.07 | CQ33: =CP33+$CQ$29 -> 0.05
B34: Revenues | O34: 813.7 | P34: 855.1 | Q34: 811.8 | R34: 863 | S34: 3343.6 | T34: 785.2 | U34: 817.1 | V34: 776.9 | W34: 864.7 | X34: 3243.9 | Y34: 854.6 | Z34: 851.3 | AA34: 798.9 | AB34: 834.4 | AC34: 3339.2 | AD34: 866.4 | AE34: 861.8 | AF34: 843.7 | AG34: 914 | AH34: 3486 | AI34: 947 | AJ34: 932 | AK34: 894 | AL34: 951 | AM34: 3724 | AN34: 957 | AO34: 943 | AP34: 879 | AQ34: 939 | AR34: 3718 | AS34: 958 | AT34: 988 | AU34: 1430 | AV34: 1967 | AW34: 5343 | AX34: 1615 | AY34: 1235 | AZ34: 1362 | BA34: 1447 | BB34: 5659 | BC34: 1482 | BD34: 1101 | BE34: 1065 | BF34: 1115 | BG34: 4763 | BH34: 1108 | BI34: 1109 | BJ34: 1083 | BK34: 1105 | BL34: 4405 | BM34: 1109 | BN34: 1117 | BO34: 1129 | BP34: 1157 | BQ34: 4512 | BR34: 1148 | BS34: 1134 | BT34: 1174 | BU34: 1220 | BV34: 4676 | BW34: 1142 | BX34: 1205 | BY34: =BT34*(1+BY35) -> 1170.8181 | BZ34: =BU34*(1+BZ35) -> 1089.7428 | CA34: =SUM(BW34,BX34,BY34,BZ34) -> 4607.5609 | CB34: =CA34*(1+CB35) -> 4373.1868 | CC34: =CB34*(1+CC35) -> 4591.8462 | CD34: =CC34*(1+CD35) -> 4821.4385 | CE34: =CD34*(1+CE35) -> 5062.5104 | CH34: =IFERROR((CE34/BV34)^(1/5)-1,"n/m") -> 0.016010709 | CI34: =IFERROR((BV34/AW34)^(1/5)-1,"n/m") -> -0.026316376 | CJ34: =IFERROR((BV34/X34)^(1/10)-1,"n/m") -> 0.037243458 | CK34: =IFERROR((BV34/C34)^(1/19)-1,"n/m") -> n/m | CN34: AI_org (Analytical Instruments organic growth) | CO34: 0.025 | CP34: Δ → | CQ34: -0.025 | CR34: Mass spectrometry & electron microscopy cycle (pharma, semis, academic/government funding risk).
B35: Revenues y/y % (reported) | D35: =IF(AND(ISNUMBER(D34),ISNUMBER(C34)),IFERROR(D34/C34-1,""),"") | E35: =IF(AND(ISNUMBER(E34),ISNUMBER(D34)),IFERROR(E34/D34-1,""),"") | F35: =IF(AND(ISNUMBER(F34),ISNUMBER(E34)),IFERROR(F34/E34-1,""),"") | G35: =IF(AND(ISNUMBER(G34),ISNUMBER(F34)),IFERROR(G34/F34-1,""),"") | H35: =IF(AND(ISNUMBER(H34),ISNUMBER(G34)),IFERROR(H34/G34-1,""),"") | I35: =IF(AND(ISNUMBER(I34),ISNUMBER(H34)),IFERROR(I34/H34-1,""),"") | N35: =IF(AND(ISNUMBER(N34),ISNUMBER(I34)),IFERROR(N34/I34-1,""),"") | O35: =IF(AND(ISNUMBER(O34),ISNUMBER(J34)),IFERROR(O34/J34-1,""),"") | P35: =IF(AND(ISNUMBER(P34),ISNUMBER(K34)),IFERROR(P34/K34-1,""),"") | Q35: =IF(AND(ISNUMBER(Q34),ISNUMBER(L34)),IFERROR(Q34/L34-1,""),"") | R35: =IF(AND(ISNUMBER(R34),ISNUMBER(M34)),IFERROR(R34/M34-1,""),"") | S35: =IF(AND(ISNUMBER(S34),ISNUMBER(N34)),IFERROR(S34/N34-1,""),"") | T35: =IF(AND(ISNUMBER(T34),ISNUMBER(O34)),IFERROR(T34/O34-1,""),"") -> -0.035025194 | U35: =IF(AND(ISNUMBER(U34),ISNUMBER(P34)),IFERROR(U34/P34-1,""),"") -> -0.044439247 | ... BX35: =IF(AND(ISNUMBER(BX34),ISNUMBER(BS34)),IFERROR(BX34/BS34-1,""),"") -> 0.062610229 | BY35: =BY36+BY37+BY38 -> -0.0027102806 | BZ35: =BZ36+BZ37+BZ38 -> -0.10676824 | CA35: =IFERROR(CA34/BV34-1,"") -> -0.014636253 | CB35: =CB36+CB37+CB38 -> -0.050867271 | CC35: =CC36+CC37+CC38 -> 0.05 | CD35: =CD36+CD37+CD38 -> 0.05 | CE35: =CE36+CE37+CE38 -> 0.05 | CN35: 2027E | CO35: =CP35+$CO$34 -> 0.075 | CP35: 0.05 | CQ35: =CP35+$CQ$34 -> 0.025
B36: of which: organic growth % (company-reported; forecast driver) | BB36: 0.05 | BC36: -0.07 | BD36: -0.08 | BE36: -0.19 | BG36: -0.13 | BH36: -0.28 | BI36: -0.05 | BJ36: -0.06 | BL36: -0.13 | BM36: 0 | BN36: 0.01 | BO36: 0.04 | BQ36: 0.03 | BR36: 0.04 | BS36: 0 | BT36: 0.02 | BV36: 0.02 | BW36: -0.03 | BX36: 0.05 | BY36: =$BX36+BY117 -> 0.04171537 | BZ36: =$BX36+BZ117 -> 0.04171537 | CB36: =CHOOSE(MATCH($CF$2,{"Bull","Base","Bear"},0),$CO$40,$CP$40,$CQ$40) -> 0.045 | CC36: =CHOOSE(MATCH($CF$2,{"Bull","Base","Bear"},0),$CO$41,$CP$41,$CQ$41) -> 0.05 | CD36: =CHOOSE(MATCH($CF$2,{"Bull","Base","Bear"},0),$CO$42,$CP$42,$CQ$42) -> 0.05 | CE36: =CHOOSE(MATCH($CF$2,{"Bull","Base","Bear"},0),$CO$43,$CP$43,$CQ$43) -> 0.05 | CF36: Q3/Q4-26E: Q2/26 segment organic growth + revenue-outlook calibration Δ (Group block). 2027E–2030E: scenario lever SD_org (Bull / Base / Bear table →). Clinical diagnostics, healthcare channel; FY25 +2%, Q2/26 +5%. | CN36: 2028E | CO36: =CP36+$CO$34 -> 0.08 | CP36: 0.055 | CQ36: =CP36+$CQ$34 -> 0.03
B37: of which: acquisitions / divestitures % | BB37: 0 | BC37: 0 | BD37: 0 | BE37: 0 | BG37: 0 | BH37: 0.04 | BI37: 0.06 | BJ37: 0.06 | BL37: 0.05 | BM37: 0 | BN37: 0 | BO37: 0 | BQ37: 0 | BR37: 0 | BS37: 0 | BT37: 0 | BV37: 0 | BW37: 0 | BX37: 0 | BY37: =BY80/BT34 -> -0.039425651 | BZ37: =BZ80/BU34 -> -0.14098361 | CB37: =-CA78/CA34 -> -0.095867271 | CC37: 0 | CD37: 0 | CE37: 0 | CF37: Q3/Q4-26E: microbiology revenues removed vs prior-year quarter (closing-date input) ÷ prior-year SD revenues. 2027E: removal of the 2026E Jan–Aug microbiology stub ÷ 2026E SD revenues. | CN37: 2029E | CO37: =CP37+$CO$34 -> 0.08 | CP37: 0.055 | CQ37: =CP37+$CQ$34 -> 0.03
B38: of which: currency translation % | BB38: 0.01 | BC38: -0.01 | BD38: -0.03 | BE38: -0.03 | BG38: -0.03 | BH38: -0.01 | BI38: 0 | BJ38: 0.01 | BL38: 0 | BM38: 0 | BN38: -0.01 | BO38: 0 | BQ38: 0 | BR38: -0.01 | BS38: 0.01 | BT38: 0.02 | BV38: 0.01 | BW38: 0.03 | BX38: 0.01 | BY38: =BY113 -> -0.005 | BZ38: =BZ113 -> -0.0075 | CB38: =CB113 -> 0 | CC38: =CC113 -> 0 | CD38: =CD113 -> 0 | CE38: =CE113 -> 0 | CN38: 2030E | CO38: =CP38+$CO$34 -> 0.08 | CP38: 0.055 | CQ38: =CP38+$CQ$34 -> 0.03
B39: Segment income (= segment adjusted operating income) | O39: 221 | P39: 236.4 | Q39: 224.3 | R39: 234.3 | S39: 916 | T39: 214.1 | U39: 227.2 | V39: 204.9 | W39: 226.7 | X39: 872.9 | Y39: 230.1 | Z39: 237.9 | AA39: 214.4 | AB39: 227.4 | AC39: 909.8 | AD39: 233.9 | AE39: 235 | AF39: 218.8 | AG39: 242 | AH39: 930 | AI39: 243 | AJ39: 253 | AK39: 223 | AL39: 233 | AM39: 952 | AN39: 242 | AO39: 242 | AP39: 223 | AQ39: 223 | AR39: 930 | AS39: 236 | AT39: 214 | AU39: 398 | AV39: 520 | AW39: 1368 | AX39: 428 | AY39: 245 | AZ39: 310 | BA39: 297 | BB39: 1280 | BC39: 353 | BD39: 243 | BE39: 220 | BF39: 208 | BG39: 1024 | BH39: 280 | BI39: 297 | BJ39: 283 | BK39: 264 | BL39: 1124 | BM39: 294 | BN39: 299 | BO39: 293 | BP39: 273 | BQ39: 1159 | BR39: 304 | BS39: 306 | BT39: 321 | BU39: 324 | BV39: 1256 | BW39: 313 | BX39: 334 | BY39: =BY34*BY41 -> 341.69545 | BZ39: =BZ34*BZ41 -> 309.4792 | CA39: =SUM(BW39,BX39,BY39,BZ39) -> 1298.1747 | CB39: =CB34*CB41 -> 1250.7314 | CC39: =CC34*CC41 -> 1331.6354 | CD39: =CD34*CD41 -> 1417.5029 | CE39: =CE34*CE41 -> 1508.6281 | CH39: =IFERROR((CE39/BV39)^(1/5)-1,"n/m") -> 0.037333757 | CI39: =IFERROR((BV39/AW39)^(1/5)-1,"n/m") -> -0.016938454 | CJ39: =IFERROR((BV39/X39)^(1/10)-1,"n/m") -> 0.037056731 | CK39: =IFERROR((BV39/C39)^(1/19)-1,"n/m") -> n/m | CN39: SD_org (Specialty Diagnostics organic growth) | CO39: 0.015 | CP39: Δ → | CQ39: -0.015 | CR39: Clinical/immunodiagnostics, transplant; ex-microbiology.
B40: Segment margin before outlook calibration % (Q3/Q4-26E helper) | BY40: =BT41+(BW39+BX39)/(BW34+BX34)-(BR39+BS39)/(BR34+BS34) -> 0.28178588 | BZ40: =BU41+(BW39+BX39)/(BW34+BX34)-(BR39+BS39)/(BR34+BS34) -> 0.27393546 | CF40: Q3/Q4-26E: prior-year quarter margin + (1H/26 − 1H/25 margin drift). | CN40: 2027E | CO40: =CP40+$CO$39 -> 0.06 | CP40: 0.045 | CQ40: =CP40+$CQ$39 -> 0.03
B41: Segment income margin % | C41: =IF(AND(ISNUMBER(C39),ISNUMBER(C34)),C39/C34,"") | D41: =IF(AND(ISNUMBER(D39),ISNUMBER(D34)),D39/D34,"") | E41: =IF(AND(ISNUMBER(E39),ISNUMBER(E34)),E39/E34,"") | F41: =IF(AND(ISNUMBER(F39),ISNUMBER(F34)),F39/F34,"") | G41: =IF(AND(ISNUMBER(G39),ISNUMBER(G34)),G39/G34,"") | H41: =IF(AND(ISNUMBER(H39),ISNUMBER(H34)),H39/H34,"") | I41: =IF(AND(ISNUMBER(I39),ISNUMBER(I34)),I39/I34,"") | J41: =IF(AND(ISNUMBER(J39),ISNUMBER(J34)),J39/J34,"") | ... BX41: =IF(AND(ISNUMBER(BX39),ISNUMBER(BX34)),BX39/BX34,"") -> 0.27717842 | BY41: =BY40+BY122 -> 0.29184332 | BZ41: =BZ40+BZ122 -> 0.2839929 | CA41: =IFERROR(CA39/CA34,"") -> 0.28174878 | CB41: =CHOOSE(MATCH($CF$2,{"Bull","Base","Bear"},0),$CO$60,$CP$60,$CQ$60) -> 0.286 | CC41: =CHOOSE(MATCH($CF$2,{"Bull","Base","Bear"},0),$CO$61,$CP$61,$CQ$61) -> 0.29 | CD41: =CHOOSE(MATCH($CF$2,{"Bull","Base","Bear"},0),$CO$62,$CP$62,$CQ$62) -> 0.294 | CE41: =CHOOSE(MATCH($CF$2,{"Bull","Base","Bear"},0),$CO$63,$CP$63,$CQ$63) -> 0.298 | CF41: Q3/Q4-26E: pre-calibration margin + outlook calibration Δ (adjusted operating margin guidance). 2027E+: scenario lever SD_m. FY25 26.9%; microbiology exit is margin-neutral to slightly accretive. | CN41: 2028E | CO41: =CP41+$CO$39 -> 0.065 | CP41: 0.05 | CQ41: =CP41+$CQ$39 -> 0.035
B42: Incremental segment margin (Δ income ÷ Δ revenues) | D42: =IF(AND(ISNUMBER(D39),ISNUMBER(C39)),IFERROR((D39-C39)/(D34-C34),""),"") | E42: =IF(AND(ISNUMBER(E39),ISNUMBER(D39)),IFERROR((E39-D39)/(E34-D34),""),"") | F42: =IF(AND(ISNUMBER(F39),ISNUMBER(E39)),IFERROR((F39-E39)/(F34-E34),""),"") | G42: =IF(AND(ISNUMBER(G39),ISNUMBER(F39)),IFERROR((G39-F39)/(G34-F34),""),"") | H42: =IF(AND(ISNUMBER(H39),ISNUMBER(G39)),IFERROR((H39-G39)/(H34-G34),""),"") | I42: =IF(AND(ISNUMBER(I39),ISNUMBER(H39)),IFERROR((I39-H39)/(I34-H34),""),"") | N42: =IF(AND(ISNUMBER(N39),ISNUMBER(I39)),IFERROR((N39-I39)/(N34-I34),""),"") | O42: =IF(AND(ISNUMBER(O39),ISNUMBER(J39)),IFERROR((O39-J39)/(O34-J34),""),"") | P42: =IF(AND(ISNUMBER(P39),ISNUMBER(K39)),IFERROR((P39-K39)/(P34-K34),""),"") | Q42: =IF(AND(ISNUMBER(Q39),ISNUMBER(L39)),IFERROR((Q39-L39)/(Q34-L34),""),"") | R42: =IF(AND(ISNUMBER(R39),ISNUMBER(M39)),IFERROR((R39-M39)/(R34-M34),""),"") | S42: =IF(AND(ISNUMBER(S39),ISNUMBER(N39)),IFERROR((S39-N39)/(S34-N34),""),"") | T42: =IF(AND(ISNUMBER(T39),ISNUMBER(O39)),IFERROR((T39-O39)/(T34-O34),""),"") -> 0.24210526 | U42: =IF(AND(ISNUMBER(U39),ISNUMBER(P39)),IFERROR((U39-P39)/(U34-P34),""),"") -> 0.24210526 | ... BX42: =IF(AND(ISNUMBER(BX39),ISNUMBER(BS39)),IFERROR((BX39-BS39)/(BX34-BS34),""),"") -> 0.3943662 | BY42: =IFERROR((BY39-BT39)/(BY34-BT34),"") -> -6.5041794 | BZ42: =IFERROR((BZ39-BU39)/(BZ34-BU34),"") -> 0.11147784 | CA42: =IFERROR((CA39-BV39)/(CA34-BV34),"") -> -0.61623607 | CB42: =IFERROR((CB39-CA39)/(CB34-CA34),"") -> 0.20242522 | CC42: =IFERROR((CC39-CB39)/(CC34-CB34),"") -> 0.37 | CD42: =IFERROR((CD39-CC39)/(CD34-CC34),"") -> 0.374 | CE42: =IFERROR((CE39-CD39)/(CE34-CD34),"") -> 0.378 | CN42: 2029E | CO42: =CP42+$CO$39 -> 0.065 | CP42: 0.05 | CQ42: =CP42+$CQ$39 -> 0.035
B43: Segment income y/y % | D43: =IF(AND(ISNUMBER(D39),ISNUMBER(C39)),IFERROR(D39/C39-1,""),"") | E43: =IF(AND(ISNUMBER(E39),ISNUMBER(D39)),IFERROR(E39/D39-1,""),"") | F43: =IF(AND(ISNUMBER(F39),ISNUMBER(E39)),IFERROR(F39/E39-1,""),"") | G43: =IF(AND(ISNUMBER(G39),ISNUMBER(F39)),IFERROR(G39/F39-1,""),"") | H43: =IF(AND(ISNUMBER(H39),ISNUMBER(G39)),IFERROR(H39/G39-1,""),"") | I43: =IF(AND(ISNUMBER(I39),ISNUMBER(H39)),IFERROR(I39/H39-1,""),"") | N43: =IF(AND(ISNUMBER(N39),ISNUMBER(I39)),IFERROR(N39/I39-1,""),"") | O43: =IF(AND(ISNUMBER(O39),ISNUMBER(J39)),IFERROR(O39/J39-1,""),"") | P43: =IF(AND(ISNUMBER(P39),ISNUMBER(K39)),IFERROR(P39/K39-1,""),"") | Q43: =IF(AND(ISNUMBER(Q39),ISNUMBER(L39)),IFERROR(Q39/L39-1,""),"") | R43: =IF(AND(ISNUMBER(R39),ISNUMBER(M39)),IFERROR(R39/M39-1,""),"") | S43: =IF(AND(ISNUMBER(S39),ISNUMBER(N39)),IFERROR(S39/N39-1,""),"") | T43: =IF(AND(ISNUMBER(T39),ISNUMBER(O39)),IFERROR(T39/O39-1,""),"") -> -0.031221719 | U43: =IF(AND(ISNUMBER(U39),ISNUMBER(P39)),IFERROR(U39/P39-1,""),"") -> -0.03891709 | ... BX43: =IF(AND(ISNUMBER(BX39),ISNUMBER(BS39)),IFERROR(BX39/BS39-1,""),"") -> 0.091503268 | BY43: =IFERROR(BY39/BT39-1,"") -> 0.064471806 | BZ43: =IFERROR(BZ39/BU39-1,"") -> -0.044817273 | CA43: =IFERROR(CA39/BV39-1,"") -> 0.033578546 | CB43: =IFERROR(CB39/CA39-1,"") -> -0.036546098 | CC43: =IFERROR(CC39/CB39-1,"") -> 0.064685315 | CD43: =IFERROR(CD39/CC39-1,"") -> 0.064482759 | CE43: =IFERROR(CE39/CD39-1,"") -> 0.064285714 | CN43: 2030E | CO43: =CP43+$CO$39 -> 0.065 | CP43: 0.05 | CQ43: =CP43+$CQ$39 -> 0.035
CN44: LPBS_org (Lab Products & Biopharma Services organic growth) | CO44: 0.02 | CP44: Δ → | CQ44: -0.02 | CR44: Research & safety channel, pharma services (CDMO), clinical research (PPD + Clario).
B45: Laboratory Products & Biopharma Services (lab products, research & safety channel, pharma services, clinical research — PPD Dec-21, Clario Mar-26) — from Q1/14 | CF45: LABORATORY PRODUCTS AND BIOPHARMA SERVICES — modelling logic | CN45: 2027E | CO45: =CP45+$CO$44 -> 0.075 | CP45: 0.055 | CQ45: =CP45+$CQ$44 -> 0.035
B46: Revenues | O46: 1590.5 | P46: 1699.4 | Q46: 1628.7 | R46: 1682.9 | S46: 6601.5 | T46: 1513.4 | U46: 1693.3 | V46: 1638.2 | W46: 1816.6 | X46: 6661.5 | Y46: 1724.6 | Z46: 1802.2 | AA46: 1746.2 | AB46: 1757 | AC46: 7030 | AD46: 1699 | AE46: 1792.5 | AF46: 1933 | AG46: 2401 | AH46: 7825 | AI46: 2413 | AJ46: 2550 | AK46: 2470 | AL46: 2602 | AM46: 10035 | AN46: 2513 | AO46: 2633 | AP46: 2619 | AQ46: 2834 | AR46: 10599 | AS46: 2730 | AT46: 2787 | AU46: 3112 | AV46: 3616 | AW46: 12245 | AX46: 3597 | AY46: 3583 | AZ46: 3487 | BA46: 4195 | BB46: 14862 | BC46: 5442 | BD46: 5537 | BE46: 5585 | BF46: 5947 | BG46: 22511 | BH46: 5763 | BI46: 5831 | BJ46: 5728 | BK46: 5719 | BL46: 23041 | BM46: 5723 | BN46: 5758 | BO46: 5740 | BP46: 5936 | BQ46: 23157 | BR46: 5640 | BS46: 5995 | BT46: 5970 | BU46: 6379 | BV46: 23984 | BW46: 6036 | BX46: 6693 | BY46: =BT46*(1+BY47) -> 6549.1908 | BZ46: =BU46*(1+BZ47) -> 6957.2598 | CA46: =SUM(BW46,BX46,BY46,BZ46) -> 26235.451 | CB46: =CA46*(1+CB47) -> 28032.049 | CC46: =CB46*(1+CC47) -> 29713.972 | CD46: =CC46*(1+CD47) -> 31496.81 | CE46: =CD46*(1+CE47) -> 33386.618 | CH46: =IFERROR((CE46/BV46)^(1/5)-1,"n/m") -> 0.068390859 | CI46: =IFERROR((BV46/AW46)^(1/5)-1,"n/m") -> 0.14391187 | CJ46: =IFERROR((BV46/X46)^(1/10)-1,"n/m") -> 0.13667147 | CK46: =IFERROR((BV46/C46)^(1/19)-1,"n/m") -> n/m | CN46: 2028E | CO46: =CP46+$CO$44 -> 0.08 | CP46: 0.06 | CQ46: =CP46+$CQ$44 -> 0.04
B47: Revenues y/y % (reported) | D47: =IF(AND(ISNUMBER(D46),ISNUMBER(C46)),IFERROR(D46/C46-1,""),"") | E47: =IF(AND(ISNUMBER(E46),ISNUMBER(D46)),IFERROR(E46/D46-1,""),"") | F47: =IF(AND(ISNUMBER(F46),ISNUMBER(E46)),IFERROR(F46/E46-1,""),"") | G47: =IF(AND(ISNUMBER(G46),ISNUMBER(F46)),IFERROR(G46/F46-1,""),"") | H47: =IF(AND(ISNUMBER(H46),ISNUMBER(G46)),IFERROR(H46/G46-1,""),"") | I47: =IF(AND(ISNUMBER(I46),ISNUMBER(H46)),IFERROR(I46/H46-1,""),"") | N47: =IF(AND(ISNUMBER(N46),ISNUMBER(I46)),IFERROR(N46/I46-1,""),"") | O47: =IF(AND(ISNUMBER(O46),ISNUMBER(J46)),IFERROR(O46/J46-1,""),"") | P47: =IF(AND(ISNUMBER(P46),ISNUMBER(K46)),IFERROR(P46/K46-1,""),"") | Q47: =IF(AND(ISNUMBER(Q46),ISNUMBER(L46)),IFERROR(Q46/L46-1,""),"") | R47: =IF(AND(ISNUMBER(R46),ISNUMBER(M46)),IFERROR(R46/M46-1,""),"") | S47: =IF(AND(ISNUMBER(S46),ISNUMBER(N46)),IFERROR(S46/N46-1,""),"") | T47: =IF(AND(ISNUMBER(T46),ISNUMBER(O46)),IFERROR(T46/O46-1,""),"") -> -0.048475322 | U47: =IF(AND(ISNUMBER(U46),ISNUMBER(P46)),IFERROR(U46/P46-1,""),"") -> -0.0035895022 | ... BX47: =IF(AND(ISNUMBER(BX46),ISNUMBER(BS46)),IFERROR(BX46/BS46-1,""),"") -> 0.11643036 | BY47: =BY48+BY49+BY50 -> 0.097016878 | BZ47: =BZ48+BZ49+BZ50 -> 0.090650548 | CA47: =IFERROR(CA46/BV46-1,"") -> 0.093873024 | CB47: =CB48+CB49+CB50 -> 0.068479784 | CC47: =CC48+CC49+CC50 -> 0.06 | CD47: =CD48+CD49+CD50 -> 0.06 | CE47: =CE48+CE49+CE50 -> 0.06 | CN47: 2029E | CO47: =CP47+$CO$44 -> 0.08 | CP47: 0.06 | CQ47: =CP47+$CQ$44 -> 0.04
B48: of which: organic growth % (company-reported; forecast driver) | BB48: 0.15 | BC48: 0.06 | BD48: 0.1 | BE48: 0.12 | BG48: 0.1 | BH48: 0.07 | BI48: 0.05 | BJ48: 0.01 | BL48: 0.02 | BM48: -0.01 | BN48: -0.01 | BO48: 0 | BQ48: 0 | BR48: -0.01 | BS48: 0.03 | BT48: 0.03 | BV48: 0.03 | BW48: 0.04 | BX48: 0.05 | BY48: =$BX48+BY117 -> 0.04171537 | BZ48: =$BX48+BZ117 -> 0.04171537 | CB48: =CHOOSE(MATCH($CF$2,{"Bull","Base","Bear"},0),$CO$45,$CP$45,$CQ$45) -> 0.055 | CC48: =CHOOSE(MATCH($CF$2,{"Bull","Base","Bear"},0),$CO$46,$CP$46,$CQ$46) -> 0.06 | CD48: =CHOOSE(MATCH($CF$2,{"Bull","Base","Bear"},0),$CO$47,$CP$47,$CQ$47) -> 0.06 | CE48: =CHOOSE(MATCH($CF$2,{"Bull","Base","Bear"},0),$CO$48,$CP$48,$CQ$48) -> 0.06 | CF48: Q3/Q4-26E: Q2/26 segment organic growth + revenue-outlook calibration Δ (Group block). 2027E–2030E: scenario lever LPBS_org (Bull / Base / Bear table →). Research & safety channel, pharma services, clinical research; FY25 +3%, Q2/26 +5%. | CN48: 2030E | CO48: =CP48+$CO$44 -> 0.08 | CP48: 0.06 | CQ48: =CP48+$CQ$44 -> 0.04
B49: of which: acquisitions / divestitures % | BB49: 0.05 | BC49: 0.47 | BD49: 0.48 | BE49: 0.53 | BG49: 0.45 | BH49: 0 | BI49: 0 | BJ49: 0 | BL49: 0 | BM49: 0 | BN49: 0 | BO49: 0 | BQ49: 0 | BR49: 0 | BS49: 0 | BT49: 0 | BV49: 0 | BW49: 0.01 | BX49: 0.06 | BY49: =$CA$72/4/BT46 -> 0.060301508 | BZ49: =$CA$72/4/BU46 -> 0.056435178 | CB49: =$CA$72*(1+$CA$73)*83/365/CA46 -> 0.013479784 | CC49: 0 | CD49: 0 | CE49: 0 | CF49: Q3/Q4-26E: Clario (closed 24-Mar-2026) full quarter = run-rate ÷ 4 ÷ prior-year LPBS revenues (Q2/26 actual: +6%). 2027E: Clario 1-Jan–24-Mar stub (83 days, grown at HSD) ÷ 2026E LPBS revenues. | CN49: LSS_m (Life Sciences Solutions segment margin) | CO49: 0.015 | CP49: Δ → | CQ49: -0.015 | CR49: FY25 36.3%; 2026E ~37.2% (1H/26 36.6%); +40bp p.a. (bioproduction mix, productivity).
B50: of which: currency translation % | BB50: 0.02 | BC50: -0.02 | BD50: -0.04 | BE50: -0.05 | BG50: -0.03 | BH50: -0.01 | BI50: 0 | BJ50: 0.01 | BL50: 0 | BM50: 0 | BN50: 0 | BO50: 0 | BQ50: 0 | BR50: -0.01 | BS50: 0.01 | BT50: 0.01 | BV50: 0.01 | BW50: 0.02 | BX50: 0.01 | BY50: =BY113 -> -0.005 | BZ50: =BZ113 -> -0.0075 | CB50: =CB113 -> 0 | CC50: =CC113 -> 0 | CD50: =CD113 -> 0 | CE50: =CE113 -> 0 | CN50: 2027E | CO50: =CP50+$CO$49 -> 0.391 | CP50: 0.376 | CQ50: =CP50+$CQ$49 -> 0.361
B51: Segment income (= segment adjusted operating income) | O51: 234 | P51: 257.7 | Q51: 246.6 | R51: 244.5 | S51: 982.8 | T51: 222.1 | U51: 260 | V51: 249.6 | W51: 267.4 | X51: 999.1 | Y51: 258.2 | Z51: 279.8 | AA51: 257.9 | AB51: 256.2 | AC51: 1052.1 | AD51: 216.2 | AE51: 246.7 | AF51: 243.4 | AG51: 301 | AH51: 1007 | AI51: 280 | AJ51: 337 | AK51: 299 | AL51: 342 | AM51: 1258 | AN51: 285 | AO51: 345 | AP51: 303 | AQ51: 391 | AR51: 1324 | AS51: 295 | AT51: 281 | AU51: 355 | AV51: 340 | AW51: 1271 | AX51: 531 | AY51: 446 | AZ51: 383 | BA51: 484 | BB51: 1844 | BC51: 620 | BD51: 691 | BE51: 725 | BF51: 836 | BG51: 2872 | BH51: 793 | BI51: 824 | BJ51: 937 | BK51: 804 | BL51: 3358 | BM51: 744 | BN51: 745 | BO51: 773 | BP51: 828 | BQ51: 3090 | BR51: 731 | BS51: 825 | BT51: 868 | BU51: 925 | BV51: 3350 | BW51: 778 | BX51: 936 | BY51: =BY46*BY53 -> 1024.0957 | BZ51: =BZ46*BZ53 -> 1085.2158 | CA51: =SUM(BW51,BX51,BY51,BZ51) -> 3823.3115 | CB51: =CB46*CB53 -> 4204.8073 | CC51: =CC46*CC53 -> 4575.9516 | CD51: =CD46*CD53 -> 4976.496 | CE51: =CE46*CE53 -> 5408.6322 | CH51: =IFERROR((CE51/BV51)^(1/5)-1,"n/m") -> 0.10054683 | CI51: =IFERROR((BV51/AW51)^(1/5)-1,"n/m") -> 0.21389145 | CJ51: =IFERROR((BV51/X51)^(1/10)-1,"n/m") -> 0.1286092 | CK51: =IFERROR((BV51/C51)^(1/19)-1,"n/m") -> n/m | CN51: 2028E | CO51: =CP51+$CO$49 -> 0.395 | CP51: 0.38 | CQ51: =CP51+$CQ$49 -> 0.365
B52: Segment margin before outlook calibration % (Q3/Q4-26E helper) | BY52: =BT53+(BW51+BX51)/(BW46+BX46)-(BR51+BS51)/(BR46+BS46) -> 0.14631237 | BZ52: =BU53+(BW51+BX51)/(BW46+BX46)-(BR51+BS51)/(BR46+BS46) -> 0.14592579 | CF52: Q3/Q4-26E: prior-year quarter margin + (1H/26 − 1H/25 margin drift). | CN52: 2029E | CO52: =CP52+$CO$49 -> 0.399 | CP52: 0.384 | CQ52: =CP52+$CQ$49 -> 0.369
B53: Segment income margin % | C53: =IF(AND(ISNUMBER(C51),ISNUMBER(C46)),C51/C46,"") | D53: =IF(AND(ISNUMBER(D51),ISNUMBER(D46)),D51/D46,"") | E53: =IF(AND(ISNUMBER(E51),ISNUMBER(E46)),E51/E46,"") | F53: =IF(AND(ISNUMBER(F51),ISNUMBER(F46)),F51/F46,"") | G53: =IF(AND(ISNUMBER(G51),ISNUMBER(G46)),G51/G46,"") | H53: =IF(AND(ISNUMBER(H51),ISNUMBER(H46)),H51/H46,"") | I53: =IF(AND(ISNUMBER(I51),ISNUMBER(I46)),I51/I46,"") | J53: =IF(AND(ISNUMBER(J51),ISNUMBER(J46)),J51/J46,"") | ... BX53: =IF(AND(ISNUMBER(BX51),ISNUMBER(BX46)),BX51/BX46,"") -> 0.1398476 | BY53: =BY52+BY122 -> 0.1563698 | BZ53: =BZ52+BZ122 -> 0.15598322 | CA53: =IFERROR(CA51/CA46,"") -> 0.14573073 | CB53: =CHOOSE(MATCH($CF$2,{"Bull","Base","Bear"},0),$CO$65,$CP$65,$CQ$65) -> 0.15 | CC53: =CHOOSE(MATCH($CF$2,{"Bull","Base","Bear"},0),$CO$66,$CP$66,$CQ$66) -> 0.154 | CD53: =CHOOSE(MATCH($CF$2,{"Bull","Base","Bear"},0),$CO$67,$CP$67,$CQ$67) -> 0.158 | CE53: =CHOOSE(MATCH($CF$2,{"Bull","Base","Bear"},0),$CO$68,$CP$68,$CQ$68) -> 0.162 | CF53: Q3/Q4-26E: pre-calibration margin + outlook calibration Δ (adjusted operating margin guidance). 2027E+: scenario lever LPBS_m. FY25 14.0%; Clario (software/data, accretive) and pharma services productivity. | CN53: 2030E | CO53: =CP53+$CO$49 -> 0.403 | CP53: 0.388 | CQ53: =CP53+$CQ$49 -> 0.373
B54: Incremental segment margin (Δ income ÷ Δ revenues) | D54: =IF(AND(ISNUMBER(D51),ISNUMBER(C51)),IFERROR((D51-C51)/(D46-C46),""),"") | E54: =IF(AND(ISNUMBER(E51),ISNUMBER(D51)),IFERROR((E51-D51)/(E46-D46),""),"") | F54: =IF(AND(ISNUMBER(F51),ISNUMBER(E51)),IFERROR((F51-E51)/(F46-E46),""),"") | G54: =IF(AND(ISNUMBER(G51),ISNUMBER(F51)),IFERROR((G51-F51)/(G46-F46),""),"") | H54: =IF(AND(ISNUMBER(H51),ISNUMBER(G51)),IFERROR((H51-G51)/(H46-G46),""),"") | I54: =IF(AND(ISNUMBER(I51),ISNUMBER(H51)),IFERROR((I51-H51)/(I46-H46),""),"") | N54: =IF(AND(ISNUMBER(N51),ISNUMBER(I51)),IFERROR((N51-I51)/(N46-I46),""),"") | O54: =IF(AND(ISNUMBER(O51),ISNUMBER(J51)),IFERROR((O51-J51)/(O46-J46),""),"") | P54: =IF(AND(ISNUMBER(P51),ISNUMBER(K51)),IFERROR((P51-K51)/(P46-K46),""),"") | Q54: =IF(AND(ISNUMBER(Q51),ISNUMBER(L51)),IFERROR((Q51-L51)/(Q46-L46),""),"") | R54: =IF(AND(ISNUMBER(R51),ISNUMBER(M51)),IFERROR((R51-M51)/(R46-M46),""),"") | S54: =IF(AND(ISNUMBER(S51),ISNUMBER(N51)),IFERROR((S51-N51)/(S46-N46),""),"") | T54: =IF(AND(ISNUMBER(T51),ISNUMBER(O51)),IFERROR((T51-O51)/(T46-O46),""),"") -> 0.15434501 | U54: =IF(AND(ISNUMBER(U51),ISNUMBER(P51)),IFERROR((U51-P51)/(U46-P46),""),"") -> -0.37704918 | ... BX54: =IF(AND(ISNUMBER(BX51),ISNUMBER(BS51)),IFERROR((BX51-BS51)/(BX46-BS46),""),"") -> 0.15902579 | BY54: =IFERROR((BY51-BT51)/(BY46-BT46),"") -> 0.2695065 | BZ54: =IFERROR((BZ51-BU51)/(BZ46-BU46),"") -> 0.27706544 | CA54: =IFERROR((CA51-BV51)/(CA46-BV46),"") -> 0.21022513 | CB54: =IFERROR((CB51-CA51)/(CB46-CA46),"") -> 0.21234344 | CC54: =IFERROR((CC51-CB51)/(CC46-CB46),"") -> 0.22066667 | CD54: =IFERROR((CD51-CC51)/(CD46-CC46),"") -> 0.22466667 | CE54: =IFERROR((CE51-CD51)/(CE46-CD46),"") -> 0.22866667 | CN54: AI_m (Analytical Instruments segment margin) | CO54: 0.015 | CP54: Δ → | CQ54: -0.015 | CR54: FY25 23.0% (tariffs); 2026E ~24.4%; 2024 26.2%.
B55: Segment income y/y % | D55: =IF(AND(ISNUMBER(D51),ISNUMBER(C51)),IFERROR(D51/C51-1,""),"") | E55: =IF(AND(ISNUMBER(E51),ISNUMBER(D51)),IFERROR(E51/D51-1,""),"") | F55: =IF(AND(ISNUMBER(F51),ISNUMBER(E51)),IFERROR(F51/E51-1,""),"") | G55: =IF(AND(ISNUMBER(G51),ISNUMBER(F51)),IFERROR(G51/F51-1,""),"") | H55: =IF(AND(ISNUMBER(H51),ISNUMBER(G51)),IFERROR(H51/G51-1,""),"") | I55: =IF(AND(ISNUMBER(I51),ISNUMBER(H51)),IFERROR(I51/H51-1,""),"") | N55: =IF(AND(ISNUMBER(N51),ISNUMBER(I51)),IFERROR(N51/I51-1,""),"") | O55: =IF(AND(ISNUMBER(O51),ISNUMBER(J51)),IFERROR(O51/J51-1,""),"") | P55: =IF(AND(ISNUMBER(P51),ISNUMBER(K51)),IFERROR(P51/K51-1,""),"") | Q55: =IF(AND(ISNUMBER(Q51),ISNUMBER(L51)),IFERROR(Q51/L51-1,""),"") | R55: =IF(AND(ISNUMBER(R51),ISNUMBER(M51)),IFERROR(R51/M51-1,""),"") | S55: =IF(AND(ISNUMBER(S51),ISNUMBER(N51)),IFERROR(S51/N51-1,""),"") | T55: =IF(AND(ISNUMBER(T51),ISNUMBER(O51)),IFERROR(T51/O51-1,""),"") -> -0.050854701 | U55: =IF(AND(ISNUMBER(U51),ISNUMBER(P51)),IFERROR(U51/P51-1,""),"") -> 0.0089251067 | ... BX55: =IF(AND(ISNUMBER(BX51),ISNUMBER(BS51)),IFERROR(BX51/BS51-1,""),"") -> 0.13454545 | BY55: =IFERROR(BY51/BT51-1,"") -> 0.17983373 | BZ55: =IFERROR(BZ51/BU51-1,"") -> 0.17320629 | CA55: =IFERROR(CA51/BV51-1,"") -> 0.14128701 | CB55: =IFERROR(CB51/CA51-1,"") -> 0.099781511 | CC55: =IFERROR(CC51/CB51-1,"") -> 0.088266667 | CD55: =IFERROR(CD51/CC51-1,"") -> 0.087532468 | CE55: =IFERROR(CE51/CD51-1,"") -> 0.086835443 | CN55: 2027E | CO55: =CP55+$CO$54 -> 0.265 | CP55: 0.25 | CQ55: =CP55+$CQ$54 -> 0.235
CN56: 2028E | CO56: =CP56+$CO$54 -> 0.27 | CP56: 0.255 | CQ56: =CP56+$CQ$54 -> 0.24
B57: Legacy segment structure — as originally reported, 2006–2013 (not recast) | CF57: LEGACY SEGMENTS — historical disclosure only (not forecast) | CN57: 2029E | CO57: =CP57+$CO$54 -> 0.275 | CP57: 0.26 | CQ57: =CP57+$CQ$54 -> 0.245
B58: Analytical Technologies — revenues (2006–2013) | C58: 2425.821 | D58: 4256 | E58: 4471.2 | F58: 4153.9 | G58: 4611.8 | H58: 3845.4 | I58: 4123.7 | J58: 977.8 | K58: 1006.5 | L58: 996.6 | M58: 1144.2 | N58: 4125.1 | CN58: 2030E | CO58: =CP58+$CO$54 -> 0.28 | CP58: 0.265 | CQ58: =CP58+$CQ$54 -> 0.25
B59: Specialty Diagnostics — revenues (three-segment structure, Q3/11–2013) | H59: 2465.8 | I59: 2962.3 | J59: 805.6 | K59: 793.6 | L59: 759.2 | M59: 833.3 | N59: 3191.7 | CN59: SD_m (Specialty Diagnostics segment margin) | CO59: 0.01 | CP59: Δ → | CQ59: -0.01 | CR59: FY25 26.9%; 2026E ~28.2%.
B60: Laboratory Products and Services — revenues (legacy structure, 2006–2013) | C60: 1406.637 | D60: 5842.2 | E60: 6453.3 | F60: 6426.6 | G60: 6693 | H60: 5935.4 | I60: 5990 | J60: 1544.3 | K60: 1583.2 | L60: 1582.1 | M60: 1640.9 | N60: 6350.5 | CN60: 2027E | CO60: =CP60+$CO$59 -> 0.296 | CP60: 0.286 | CQ60: =CP60+$CQ$59 -> 0.276
B61: Analytical Technologies — segment operating income | C61: 383.64 | D61: 843.1 | E61: 957.1 | F61: 837.3 | G61: 984.2 | H61: 720 | I61: 772.7 | J61: 176.1 | K61: 177.9 | L61: 180.4 | M61: 233.4 | N61: 767.8 | CN61: 2028E | CO61: =CP61+$CO$59 -> 0.3 | CP61: 0.29 | CQ61: =CP61+$CQ$59 -> 0.28
B62: Specialty Diagnostics — segment operating income (Q3/11–2013) | H62: 597 | I62: 761.2 | J62: 221.7 | K62: 216.9 | L62: 203.7 | M62: 224.4 | N62: 866.7 | CN62: 2029E | CO62: =CP62+$CO$59 -> 0.304 | CP62: 0.294 | CQ62: =CP62+$CQ$59 -> 0.284
B63: Laboratory Products and Services — segment operating income (legacy) | C63: 189.229 | D63: 793.8 | E63: 912 | F63: 877.6 | G63: 931.8 | H63: 810.8 | I63: 846 | J63: 217.3 | K63: 229 | L63: 235.3 | M63: 236.4 | N63: 918 | CN63: 2030E | CO63: =CP63+$CO$59 -> 0.308 | CP63: 0.298 | CQ63: =CP63+$CQ$59 -> 0.288
B64: Other — segment operating income (2006) | C64: 0 | CN64: LPBS_m (Lab Products & Biopharma Services segment margin) | CO64: 0.01 | CP64: Δ → | CQ64: -0.01 | CR64: FY25 14.0%; 2026E ~14.6%; Clario (software/data) accretive.
CN65: 2027E | CO65: =CP65+$CO$64 -> 0.16 | CP65: 0.15 | CQ65: =CP65+$CQ$64 -> 0.14
B66: Eliminations (intersegment revenues) | CF66: ELIMINATIONS — modelling logic | CN66: 2028E | CO66: =CP66+$CO$64 -> 0.164 | CP66: 0.154 | CQ66: =CP66+$CQ$64 -> 0.144
B67: Eliminations | C67: -40.841 | D67: -351.8 | E67: -426.5 | F67: -470.8 | G67: -516.1 | H67: -520.7 | I67: -566.1 | J67: -136.2 | K67: -143.2 | L67: -146.1 | M67: -151.5 | N67: -577 | O67: -106.1 | P67: -129.1 | Q67: -127.5 | R67: -140.7 | S67: -503.4 | T67: -127.1 | U67: -145.8 | V67: -150.8 | W67: -163.9 | X67: -587.6 | Y67: -176.7 | Z67: -189.8 | AA67: -183.7 | AB67: -191.2 | AC67: -741.4 | AD67: -215.9 | AE67: -234.7 | AF67: -232.1 | AG67: -260 | AH67: -942 | AI67: -263 | AJ67: -284 | AK67: -281 | AL67: -311 | AM67: -1139 | AN67: -274 | AO67: -294 | AP67: -285 | AQ67: -300 | AR67: -1153 | AS67: -333 | AT67: -511 | AU67: -781 | AV67: -1037 | AW67: -2662 | AX67: -896 | AY67: -583 | AZ67: -716 | BA67: -815 | BB67: -3010 | BC67: -855 | BD67: -567 | BE67: -556 | BF67: -536 | BG67: -2515 | BH67: -496 | BI67: -465 | BJ67: -424 | BK67: -444 | BL67: -1829 | BM67: -460 | BN67: -470 | BO67: -467 | BP67: -487 | BQ67: -1885 | BR67: -482 | BS67: -501 | BT67: -503 | BU67: -546 | BV67: -2033 | BW67: -524 | BX67: -565 | BY67: =-BY68*(BY10+BY22+BY34+BY46) -> -540.49808 | BZ67: =-BZ68*(BZ10+BZ22+BZ34+BZ46) -> -572.10052 | CA67: =SUM(BW67,BX67,BY67,BZ67) -> -2201.5986 | CB67: =-CB68*(CB10+CB22+CB34+CB46) -> -2317.5041 | CC67: =-CC68*(CC10+CC22+CC34+CC46) -> -2455.4179 | CD67: =-CD68*(CD10+CD22+CD34+CD46) -> -2604.3686 | CE67: =-CE68*(CE10+CE22+CE34+CE46) -> -2762.4397 | CF67: Forecast: − eliminations % × Σ segment revenues. | CN67: 2029E | CO67: =CP67+$CO$64 -> 0.168 | CP67: 0.158 | CQ67: =CP67+$CQ$64 -> 0.148
B68: Eliminations % of gross segment revenues | C68: =IFERROR(-C67/(N(C10)+N(C22)+N(C34)+N(C46)+N(C58)+N(C59)+N(C60)),"") -> 0.010656607 | D68: =IFERROR(-D67/(N(D10)+N(D22)+N(D34)+N(D46)+N(D58)+N(D59)+N(D60)),"") -> 0.034837892 | E68: =IFERROR(-E67/(N(E10)+N(E22)+N(E34)+N(E46)+N(E58)+N(E59)+N(E60)),"") -> 0.039040688 | F68: =IFERROR(-F67/(N(F10)+N(F22)+N(F34)+N(F46)+N(F58)+N(F59)+N(F60)),"") -> 0.044496952 | G68: =IFERROR(-G67/(N(G10)+N(G22)+N(G34)+N(G46)+N(G58)+N(G59)+N(G60)),"") -> 0.045653174 | H68: =IFERROR(-H67/(N(H10)+N(H22)+N(H34)+N(H46)+N(H58)+N(H59)+N(H60)),"") -> 0.042517923 | I68: =IFERROR(-I67/(N(I10)+N(I22)+N(I34)+N(I46)+N(I58)+N(I59)+N(I60)),"") -> 0.043293056 | J68: =IFERROR(-J67/(N(J10)+N(J22)+N(J34)+N(J46)+N(J58)+N(J59)+N(J60)),"") -> 0.04092917 | ... BX68: =IFERROR(-BX67/(N(BX10)+N(BX22)+N(BX34)+N(BX46)+N(BX58)+N(BX59)+N(BX60)),"") -> 0.044984076 | BY68: =BT68 -> 0.043268817 | BZ68: =BU68 -> 0.042789969 | CA68: =IFERROR(-CA67/(N(CA10)+N(CA22)+N(CA34)+N(CA46)+N(CA58)+N(CA59)+N(CA60)),"") -> 0.044074637 | CB68: =$CA$68 -> 0.044074637 | CC68: =$CA$68 -> 0.044074637 | CD68: =$CA$68 -> 0.044074637 | CE68: =$CA$68 -> 0.044074637 | CF68: Prior-year quarter (Q3/Q4-26E); 2026E level held flat 2027E+. | CN68: 2030E | CO68: =CP68+$CO$64 -> 0.172 | CP68: 0.162 | CQ68: =CP68+$CQ$64 -> 0.152
CN69: M&A_spend (bolt-on acquisitions, $m) | CO69: 3000 | CP69: Δ → | CQ69: -3000 | CR69: Base: ~$4bn p.a. bolt-ons after the Clario deleveraging; Bull +$3bn, Bear −$3bn.
B70: Portfolio changes — Solventum P&F (LSS, 1-Sep-2025) · Clario (LPBS, 24-Mar-2026) · Microbiology divestiture (SD, Q3/26) | CF70: PORTFOLIO CHANGES — inputs feeding segment acquisitions/divestitures %, the gain on sale and the 2026E balance sheet | CN70: 2027E | CO70: =CP70+$CO$69 -> 7000 | CP70: 4000 | CQ70: =CP70+$CQ$69 -> 1000
B71: Solventum Purification & Filtration — revenues per month (run-rate, USDm) | CA71: 70 | CF71: ≈ 9% acquisition contribution to LSS in Q1/26 (10-Q) × Q1/25 LSS revenues ÷ 3 months (≈ $1.0bn annual; 2025 deal ~$4.1bn). | CN71: 2028E | CO71: =CP71+$CO$69 -> 7000 | CP71: 4000 | CQ71: =CP71+$CQ$69 -> 1000
B72: Clario — annual revenue run-rate (USDm) | CA72: 1440 | CF72: Q2/26 LPBS acquisition contribution +6% (10-Q) × Q2/25 LPBS revenues × 4. Company: HSD growth, accretive to adjusted operating margin; ~$0.45 adjusted EPS in year 1 ($0.32 in 2026 guidance). | CN72: 2029E | CO72: =CP72+$CO$69 -> 7000 | CP72: 4000 | CQ72: =CP72+$CQ$69 -> 1000
B73: Clario — revenue growth % (high-single-digit, per company) | CA73: 0.08 | CN73: 2030E | CO73: =CP73+$CO$69 -> 7000 | CP73: 4000 | CQ73: =CP73+$CQ$69 -> 1000
B74: Clario — adjusted EBITDA margin % (assumption; pro forma leverage only) | CA74: 0.3
B75: Memo: Clario purchase price, preliminary (USDm; cash $5,806m + debt settled $3,180m + payable + earn-out FV − cash) | CA75: 9098
B76: Memo: Clario acquired intangibles (CR $2,510m/20y · technology $844m/7y · trade names $19m/3y · backlog $423m/6y) | CA76: =2510+844+19+423 -> 3796
B77: Clario — intangible amortization p.a. (straight-line over weighted-average lives) | CA77: =2510/20+844/7+19/3+423/6 -> 322.90476 | CF77: Not in the FY2025 10-K amortization schedule (deal closed after year-end); added to the forecast amortization schedule.
B78: Microbiology — revenues (SD; 10-Q/10-K revenue disaggregation; FY25 $645m) | BL78: 618 | BQ78: 633 | BR78: 152 | BS78: 159 | BT78: 162 | BU78: 172 | BV78: 645 | BW78: 160 | BX78: 166 | BY78: =BT78*BY79/91 -> 115.71429 | BZ78: =BU78*BZ79/91 -> 0 | CA78: =SUM(BW78,BX78,BY78,BZ78) -> 441.71429
B79: Microbiology — days owned in fiscal quarter (closing assumed 31-Aug-2026; Q3 = 91 days) | BY79: 65 | BZ79: 0 | CF79: Input: fiscal Q3/26 = 28-Jun to 26-Sep-2026; closing assumed 31-Aug-2026 → 65 days owned. Change if the closing date differs.
B80: Microbiology — revenues removed vs prior-year quarter | BY80: =BY78-BT78 -> -46.285714 | BZ80: =BZ78-BU78 -> -172
B81: Microbiology — cash proceeds (USDm) | CA81: 1025
B82: Microbiology — seller note received (USDm; other assets) | CA82: 50
B83: Microbiology — assets held for sale at 27-Jun-2026 (current $228m + long-term $760m) | CA83: =228+760 -> 988
B84: Microbiology — liabilities held for sale at 27-Jun-2026 (current $71m + long-term $45m) | CA84: =71+45 -> 116
B85: Microbiology — pre-tax gain on sale (in restructuring & other; excluded from adjusted results) | BY85: =$CA$81+$CA$82-$CA$83+$CA$84 -> 203 | BZ85: 0 | CA85: =SUM(BW85,BX85,BY85,BZ85) -> 203 | CF85: Proceeds − net assets held for sale (selling costs ignored). TMO books gains/losses on business sales in "restructuring and other costs (income)", excluded from adjusted OI/EPS.
B87: Future acquisitions (M&A lever — bolt-ons, unallocated to segments; deals closed from 2027E) | CF87: M&A LEVER — acquired revenues = spend ÷ EV/revenues; mid-year convention
B88: Acquisition spend (USDm, scenario) | CA88: 0 | CB88: =MAX(0,CHOOSE(MATCH($CF$2,{"Bull","Base","Bear"},0),$CO$70,$CP$70,$CQ$70)) -> 4000 | CC88: =MAX(0,CHOOSE(MATCH($CF$2,{"Bull","Base","Bear"},0),$CO$71,$CP$71,$CQ$71)) -> 4000 | CD88: =MAX(0,CHOOSE(MATCH($CF$2,{"Bull","Base","Bear"},0),$CO$72,$CP$72,$CQ$72)) -> 4000 | CE88: =MAX(0,CHOOSE(MATCH($CF$2,{"Bull","Base","Bear"},0),$CO$73,$CP$73,$CQ$73)) -> 4000 | CF88: Scenario lever M&A_spend. TMO deployed $0.7–17bn p.a. on acquisitions in 2014–2026 (Life Technologies, FEI, Patheon, PPD, Olink, Solventum P&F, Clario); 2026 investor framework ~2/3 of capital deployment to M&A.
B89: Purchase multiple — EV / revenues (x) | CA89: 0 | CB89: 5 | CC89: =CB89 -> 5 | CD89: =CC89 -> 5 | CE89: =CD89 -> 5 | CF89: Life-science tools / services deals: ~4–7x revenues (Clario ~7x, Solventum P&F ~4x, Olink ~6x).
B90: Annualised revenues acquired in the year | CA90: 0 | CB90: =IFERROR(CB88/CB89,0) -> 800 | CC90: =IFERROR(CC88/CC89,0) -> 800 | CD90: =IFERROR(CD88/CD89,0) -> 800 | CE90: =IFERROR(CE88/CE89,0) -> 800
B91: Growth of acquired businesses after acquisition % | CA91: 0 | CB91: 0.06 | CC91: =CB91 -> 0.06 | CD91: =CC91 -> 0.06 | CE91: =CD91 -> 0.06
B92: Run-rate revenues of businesses acquired (year end) | CA92: 0 | CB92: =CA92*(1+CB91)+CB90 -> 800 | CC92: =CB92*(1+CC91)+CC90 -> 1648 | CD92: =CC92*(1+CD91)+CD90 -> 2546.88 | CE92: =CD92*(1+CE91)+CE90 -> 3499.6928
B93: Revenues from future acquisitions | CA93: 0 | CB93: =CA92*(1+CB91)+0.5*CB90 -> 400 | CC93: =CB92*(1+CC91)+0.5*CC90 -> 1248 | CD93: =CC92*(1+CD91)+0.5*CD90 -> 2146.88 | CE93: =CD92*(1+CE91)+0.5*CE90 -> 3099.6928 | CF93: Mid-year convention: deals close evenly through the year (half a year of revenues in year 1).
B94: Segment income margin of acquired businesses % (before amortization) | CA94: 0 | CB94: 0.22 | CC94: =CB94 -> 0.22 | CD94: =CC94 -> 0.22 | CE94: =CD94 -> 0.22
B95: Segment income (adjusted OI) from future acquisitions | CA95: 0 | CB95: =CB93*CB94 -> 88 | CC95: =CC93*CC94 -> 274.56 | CD95: =CD93*CD94 -> 472.3136 | CE95: =CE93*CE94 -> 681.93242
B96: PP&E % of spend | CA96: 0 | CB96: 0.05 | CC96: =CB96 -> 0.05 | CD96: =CC96 -> 0.05 | CE96: =CD96 -> 0.05
B97: Acquired intangibles % of spend | CA97: 0 | CB97: 0.4 | CC97: =CB97 -> 0.4 | CD97: =CC97 -> 0.4 | CE97: =CD97 -> 0.4 | CF97: Clario: 42% of purchase price to intangibles; Solventum P&F: 40%. Balance to goodwill (and 5% PP&E).
B98: Intangible amortization life (years) | CA98: 0 | CB98: 14 | CC98: =CB98 -> 14 | CD98: =CC98 -> 14 | CE98: =CD98 -> 14
B99: Cumulative acquired intangibles (gross) | CA99: 0 | CB99: =CA99+CB88*CB97 -> 1600 | CC99: =CB99+CC88*CC97 -> 3200 | CD99: =CC99+CD88*CD97 -> 4800 | CE99: =CD99+CE88*CE97 -> 6400
B100: Amortization of future-acquisition intangibles | CA100: 0 | CB100: =(CA99+0.5*CB88*CB97)/CB98 -> 57.142857 | CC100: =(CB99+0.5*CC88*CC97)/CC98 -> 171.42857 | CD100: =(CC99+0.5*CD88*CD97)/CD98 -> 285.71429 | CE100: =(CD99+0.5*CE88*CE97)/CE98 -> 400
B102: Group Total — revenues & segment income (= adjusted operating income, TMO's primary non-GAAP profit measure) | CF102: GROUP TOTAL (CONSOLIDATED) — modelling logic
...

Sheet Bull-Base-Bear
B2: Thermo Fisher Scientific (TMO) — Bull / Base / Bear Case P&L Summary | J2: Share price ($): | K2: =Model!$CA$400 -> 676.76
B3: Adjusted figures (company current definitions: adjusted operating income = Σ segment income; adjusted EPS excludes amortization, restructuring, step-up, transaction costs, investment gains/losses, equity-method results and their tax effects). Adjusted EBITDA is a model memo (adjusted OI + depreciation). | J3: As of: | K3: =TODAY() -> 46301
B5: Scenario: | C5: =Model!$CF$2 -> Base | N5: Scenario: | O5: Bull | P5: Snapshot (values) — Model run with switch = Bull | Z5: Scenario: | AA5: Bear | AB5: Snapshot (values) — Model run with switch = Bear
B7: (USDm, except EPS and shares) | C7: 2025A | D7: 2026E | E7: 2027E | F7: 2028E | G7: 2029E | H7: 2030E | I7: 25-'30 CAGR | J7: LT Hist Avg | K7: LT Hist Min | L7: LT Hist Max | N7: (USDm, except EPS and shares) | O7: 2025A | P7: 2026E | Q7: 2027E | R7: 2028E | S7: 2029E | T7: 2030E | U7: 25-'30 CAGR | V7: LT Hist Avg | W7: LT Hist Min | X7: LT Hist Max | Z7: (USDm, except EPS and shares) | AA7: 2025A | AB7: 2026E | AC7: 2027E | AD7: 2028E | AE7: 2029E | AF7: 2030E | AG7: 25-'30 CAGR | AH7: LT Hist Avg | AI7: LT Hist Min | AJ7: LT Hist Max
B9: Revenues | C9: =Model!BV136 -> 44556 | D9: =Model!CA136 -> 47750 | E9: =Model!CB136 -> 50663.849 | F9: =Model!CC136 -> 54503.032 | G9: =Model!CD136 -> 58632.473 | H9: =Model!CE136 -> 63013.654 | I9: =IFERROR((H9/C9)^(1/5)-1,"n/m") -> 0.071780113 | N9: Revenues | O9: 44556 | P9: 48100 | Q9: 52310.71 | R9: 57917.618 | S9: 64007.429 | T9: 70559.902 | U9: 0.096302376 | Z9: Revenues | AA9: 44556 | AB9: 47400 | AC9: 49031.235 | AD9: 51158.613 | AE9: 53432.598 | AF9: 55804.704 | AG9: 0.046051155
B10: Revenues y/y % | D10: =IFERROR(D9/C9-1,"") -> 0.07168507 | E10: =IFERROR(E9/D9-1,"") -> 0.06102302 | F10: =IFERROR(F9/E9-1,"") -> 0.075777551 | G10: =IFERROR(G9/F9-1,"") -> 0.075765353 | H10: =IFERROR(H9/G9-1,"") -> 0.074722778 | N10: Revenues y/y % | P10: 0.079540354 | Q10: 0.087540738 | R10: 0.10718472 | S10: 0.10514609 | T10: 0.10237051 | Z10: Revenues y/y % | AB10: 0.063829787 | AC10: 0.034414239 | AD10: 0.043388228 | AE10: 0.04444969 | AF10: 0.044394374
B11: Organic revenue growth % | C11: =Model!BV222 -> 0.02 | D11: =Model!CA222 -> 0.036947268 | E11: =Model!CB222 -> 0.054409085 | F11: =Model!CC222 -> 0.059509617 | G11: =Model!CD222 -> 0.060662089 | H11: =Model!CE222 -> 0.060694565 | N11: Organic revenue growth % | O11: 0.02 | P11: 0.044797641 | Q11: 0.074737937 | R11: 0.079884748 | S11: 0.081042132 | T11: 0.081079157 | Z11: Organic revenue growth % | AA11: 0.02 | AB11: 0.029096894 | AC11: 0.034080566 | AD11: 0.039144289 | AE11: 0.040302871 | AF11: 0.040341584
B12: Adjusted Operating Income (company definition = Σ segment income) | C12: =Model!BV186 -> 10110 | D12: =Model!CA186 -> 11219.25 | E12: =Model!CB186 -> 12084.794 | F12: =Model!CC186 -> 13222.219 | G12: =Model!CD186 -> 14466.04 | H12: =Model!CE186 -> 15801.549 | I12: =IFERROR((H12/C12)^(1/5)-1,"n/m") -> 0.093426763 | N12: Adjusted Operating Income (company definition = Σ segment income) | O12: 10110 | P12: 11349.6 | Q12: 13117.614 | R12: 14727.588 | S12: 16506.317 | T12: 18445.243 | U12: 0.12778586 | Z12: Adjusted Operating Income (company definition = Σ segment income) | AA12: 10110 | AB12: 11089.6 | AC12: 11089.177 | AD12: 11795.666 | AE12: 12562.148 | AF12: 13370.847 | AG12: 0.057502871
B13: Adjusted operating margin % | C13: =IFERROR(C12/C9,"") -> 0.22690547 | D13: =IFERROR(D12/D9,"") -> 0.23495812 | E13: =IFERROR(E12/E9,"") -> 0.23852894 | F13: =IFERROR(F12/F9,"") -> 0.24259602 | G13: =IFERROR(G12/G9,"") -> 0.24672403 | H13: =IFERROR(H12/H9,"") -> 0.25076388 | J13: =IFERROR(AVERAGE(Model!C187,Model!D187,Model!E187,Model!F187,Model!G187,Model!H187,Model!I187,Model!N187,Model!S187,Model!X187,Model!AC187,Model!AH187,Model!AM187,Model!AR187,Model!AW187,Model!BB187,Model!BG187,Model!BL187,Model!BQ187,Model!BV187),"") -> 0.21578386 | K13: =IFERROR(MIN(Model!C187,Model!D187,Model!E187,Model!F187,Model!G187,Model!H187,Model!I187,Model!N187,Model!S187,Model!X187,Model!AC187,Model!AH187,Model!AM187,Model!AR187,Model!AW187,Model!BB187,Model!BG187,Model!BL187,Model!BQ187,Model!BV187),"") -> 0.15108831 | L13: =IFERROR(MAX(Model!C187,Model!D187,Model!E187,Model!F187,Model!G187,Model!H187,Model!I187,Model!N187,Model!S187,Model!X187,Model!AC187,Model!AH187,Model!AM187,Model!AR187,Model!AW187,Model!BB187,Model!BG187,Model!BL187,Model!BQ187,Model!BV187),"") -> 0.30955599 | N13: Adjusted operating margin % | O13: 0.22690547 | P13: 0.23595842 | Q13: 0.25076345 | R13: 0.2542851 | S13: 0.25788126 | T13: 0.26141254 | V13: 0.21578386 | W13: 0.15108831 | X13: 0.30955599 | Z13: Adjusted operating margin % | AA13: 0.22690547 | AB13: 0.23395781 | AC13: 0.22616557 | AD13: 0.23057048 | AE13: 0.23510269 | AF13: 0.23960072 | AH13: 0.21578386 | AI13: 0.15108831 | AJ13: 0.30955599
B15: Operating Income (GAAP) | C15: =Model!BV145 -> 7747 | D15: =Model!CA145 -> 8999.25 | E15: =Model!CB145 -> 9622.7635 | F15: =Model!CC145 -> 10677.867 | G15: =Model!CD145 -> 11903.503 | H15: =Model!CE145 -> 13396.895 | I15: =IFERROR((H15/C15)^(1/5)-1,"n/m") -> 0.11576857 | N15: Operating Income (GAAP) | O15: 7747 | P15: 9129.6 | Q15: 10602.845 | R15: 12034.177 | S15: 13697.244 | T15: 15695.312 | U15: 0.15166795 | Z15: Operating Income (GAAP) | AA15: 7747 | AB15: 8869.6 | AC15: 8679.7995 | AD15: 9399.9526 | AE15: 10245.095 | AF15: 11309.448 | AG15: 0.078602862
B16: Operating income y/y % | D16: =IFERROR(D15/C15-1,"") -> 0.16164322 | E16: =IFERROR(E15/D15-1,"") -> 0.06928505 | F16: =IFERROR(F15/E15-1,"") -> 0.10964664 | G16: =IFERROR(G15/F15-1,"") -> 0.1147828 | H16: =IFERROR(H15/G15-1,"") -> 0.12545826 | N16: Operating income y/y % | P16: 0.17846908 | Q16: 0.16137015 | R16: 0.13499511 | S16: 0.13819532 | T16: 0.14587374 | Z16: Operating income y/y % | AB16: 0.14490771 | AC16: -0.021398993 | AD16: 0.082968865 | AE16: 0.089909266 | AF16: 0.10388896
B17: Operating margin (GAAP) % | C17: =IFERROR(C15/C9,"") -> 0.17387108 | D17: =IFERROR(D15/D9,"") -> 0.18846597 | E17: =IFERROR(E15/E9,"") -> 0.18993353 | F17: =IFERROR(F15/F9,"") -> 0.19591327 | G17: =IFERROR(G15/G9,"") -> 0.20301894 | H17: =IFERROR(H15/H9,"") -> 0.21260305 | J17: =IFERROR(AVERAGE(Model!C232,Model!D232,Model!E232,Model!F232,Model!G232,Model!H232,Model!I232,Model!N232,Model!S232,Model!X232,Model!AC232,Model!AH232,Model!AM232,Model!AR232,Model!AW232,Model!BB232,Model!BG232,Model!BL232,Model!BQ232,Model!BV232),"") -> 0.14680256 | K17: =IFERROR(MIN(Model!C232,Model!D232,Model!E232,Model!F232,Model!G232,Model!H232,Model!I232,Model!N232,Model!S232,Model!X232,Model!AC232,Model!AH232,Model!AM232,Model!AR232,Model!AW232,Model!BB232,Model!BG232,Model!BL232,Model!BQ232,Model!BV232),"") -> 0.063814199 | L17: =IFERROR(MAX(Model!C232,Model!D232,Model!E232,Model!F232,Model!G232,Model!H232,Model!I232,Model!N232,Model!S232,Model!X232,Model!AC232,Model!AH232,Model!AM232,Model!AR232,Model!AW232,Model!BB232,Model!BG232,Model!BL232,Model!BQ232,Model!BV232),"") -> 0.25574456 | N17: Operating margin (GAAP) % | O17: 0.17387108 | P17: 0.18980457 | Q17: 0.20268975 | R17: 0.20778094 | S17: 0.2139946 | T17: 0.22243954 | V17: 0.14680256 | W17: 0.063814199 | X17: 0.25574456 | Z17: Operating margin (GAAP) % | AA17: 0.17387108 | AB17: 0.18712236 | AC17: 0.17702592 | AD17: 0.18374135 | AE17: 0.19173867 | AF17: 0.20266119 | AH17: 0.14680256 | AI17: 0.063814199 | AJ17: 0.25574456
B19: Adjusted Net Income (attributable to Thermo Fisher) | C19: =Model!BV208 -> 8643 | D19: =Model!CA208 -> 9339.0063 | E19: =Model!CB208 -> 9852.7203 | F19: =Model!CC208 -> 10740.276 | G19: =Model!CD208 -> 11629.419 | H19: =Model!CE208 -> 12644.413 | I19: =IFERROR((H19/C19)^(1/5)-1,"n/m") -> 0.079063083 | N19: Adjusted Net Income (attributable to Thermo Fisher) | O19: 8643 | P19: 9454.366 | Q19: 10738.523 | R19: 11857.727 | S19: 13131.769 | T19: 14595.657 | U19: 0.11048278 | Z19: Adjusted Net Income (attributable to Thermo Fisher) | AA19: 8643 | AB19: 9224.266 | AC19: 8968.8775 | AD19: 9666.6821 | AE19: 10188.812 | AF19: 10798.643 | AG19: 0.045540684
B21: FDSO (m) | C21: =Model!BV168 -> 378 | D21: =Model!CA168 -> 371.5 | E21: =Model!CB168 -> 369.02823 | F21: =Model!CC168 -> 362.73221 | G21: =Model!CD168 -> 354.3372 | H21: =Model!CE168 -> 345.47198 | I21: =IFERROR((H21/C21)^(1/5)-1,"n/m") -> -0.017835558 | N21: FDSO (m) | O21: 378 | P21: 371.13059 | Q21: 365.31447 | R21: 357.04429 | S21: 348.8342 | T21: 339.48383 | U21: -0.021264236 | Z21: FDSO (m) | AA21: 378 | AB21: 371.5 | AC21: 371.51965 | AD21: 367.20295 | AE21: 358.09206 | AF21: 349.10621 | AG21: -0.015777804
B23: Adjusted EPS — Diluted ($) | C23: =Model!BV212 -> 22.865079 | D23: =Model!CA212 -> 25.138644 | E23: =Model!CB212 -> 26.699096 | F23: =Model!CC212 -> 29.609382 | G23: =Model!CD212 -> 32.820202 | H23: =Model!CE212 -> 36.600402 | I23: =IFERROR((H23/C23)^(1/5)-1,"n/m") -> 0.098658266 | N23: Adjusted EPS — Diluted ($) | O23: 22.865079 | P23: 25.474499 | Q23: 29.395285 | R23: 33.210801 | S23: 37.644729 | T23: 42.993675 | U23: 0.13460938 | Z23: Adjusted EPS — Diluted ($) | AA23: 22.865079 | AB23: 24.829787 | AC23: 24.141058 | AD23: 26.325175 | AE23: 28.453053 | AF23: 30.932258 | AG23: 0.062301467
B24: EPS y/y % | D24: =IFERROR(D23/C23-1,"") -> 0.099433928 | E24: =IFERROR(E23/D23-1,"") -> 0.062073838 | F24: =IFERROR(F23/E23-1,"") -> 0.10900317 | G24: =IFERROR(G23/F23-1,"") -> 0.10843928 | H24: =IFERROR(H23/G23-1,"") -> 0.11517904 | N24: EPS y/y % | P24: 0.11412249 | Q24: 0.15391023 | R24: 0.12980026 | S24: 0.13350861 | T24: 0.14209016 | Z24: EPS y/y % | AB24: 0.085926139 | AC24: -0.027738022 | AD24: 0.090473128 | AE24: 0.080830528 | AF24: 0.087133171
B26: P / E (x) — assumed (adjusted EPS) | G26: 26 | H26: 26 | N26: P / E (x) — assumed (adjusted EPS) | S26: 30 | T26: 30 | Z26: P / E (x) — assumed (adjusted EPS) | AD26: 21 | AE26: 21 | AF26: 21
B27: Price Target ($) | G27: =G26*G23 -> 853.32526 | H27: =H26*H23 -> 951.61044 | N27: Price Target ($) | S27: =S26*S23 -> 1129.3419 | T27: =T26*T23 -> 1289.8102 | Z27: Price Target ($) | AD27: =AD26*AD23 -> 552.82868 | AE27: =AE26*AE23 -> 597.51411 | AF27: =AF26*AF23 -> 649.57741
B28: Upside / (Downside) vs current | G28: =IFERROR(G27/$K$2-1,"") -> 0.26089789 | H28: =IFERROR(H27/$K$2-1,"") -> 0.4061269 | N28: Upside / (Downside) vs current | S28: =IFERROR(S27/$K$2-1,"") -> 0.66874797 | T28: =IFERROR(T27/$K$2-1,"") -> 0.90586064 | Z28: Upside / (Downside) vs current | AD28: =IFERROR(AD27/$K$2-1,"") -> -0.18312448 | AE28: =IFERROR(AE27/$K$2-1,"") -> -0.117096 | AF28: =IFERROR(AF27/$K$2-1,"") -> -0.040165771
B29: IRR (to Dec-Y-1) | G29: =IFERROR((G27/$K$2)^(1/((DATE(2029-1,12,31)-$K$3)/365.25))-1,"") -> 0.10920089 | H29: =IFERROR((H27/$K$2)^(1/((DATE(2030-1,12,31)-$K$3)/365.25))-1,"") -> 0.11106912 | N29: IRR (to Dec-Y-1) | S29: =IFERROR((S27/$K$2)^(1/((DATE(2029-1,12,31)-$K$3)/365.25))-1,"") -> 0.25725261 | T29: =IFERROR((T27/$K$2)^(1/((DATE(2030-1,12,31)-$K$3)/365.25))-1,"") -> 0.22053716 | Z29: IRR (to Dec-Y-1) | AD29: =IFERROR((AD27/$K$2)^(1/((DATE(2028-1,12,31)-$K$3)/365.25))-1,"") -> -0.15109723 | AE29: =IFERROR((AE27/$K$2)^(1/((DATE(2029-1,12,31)-$K$3)/365.25))-1,"") -> -0.054155044 | AF29: =IFERROR((AF27/$K$2)^(1/((DATE(2030-1,12,31)-$K$3)/365.25))-1,"") -> -0.012587876
B31: Free Cash Flow (company definition) | C31: =Model!BV267 -> 6337 | D31: =Model!CA267 -> 7150 | E31: =Model!CB267 -> 8636.7828 | F31: =Model!CC267 -> 9350.0011 | G31: =Model!CD267 -> 10147.883 | H31: =Model!CE267 -> 11080.678 | I31: =IFERROR((H31/C31)^(1/5)-1,"n/m") -> 0.11824387 | N31: Free Cash Flow (company definition) | O31: 6337 | P31: 7400 | Q31: 9326.1093 | R31: 10181.811 | S31: 11310.361 | T31: 12632.681 | U31: 0.14794839 | Z31: Free Cash Flow (company definition) | AA31: 6337 | AB31: 6900 | AC31: 7947.3248 | AD31: 8553.6565 | AE31: 9030.853 | AF31: 9608.1037 | AG31: 0.086802917
B32: FCF % | C32: =IFERROR(C31/C9,"") -> 0.14222551 | D32: =IFERROR(D31/D9,"") -> 0.14973822 | E32: =IFERROR(E31/E9,"") -> 0.1704723 | F32: =IFERROR(F31/F9,"") -> 0.17155011 | G32: =IFERROR(G31/G9,"") -> 0.17307616 | H32: =IFERROR(H31/H9,"") -> 0.17584567 | J32: =IFERROR(AVERAGE(Model!C273,Model!D273,Model!E273,Model!F273,Model!G273,Model!H273,Model!I273,Model!N273,Model!S273,Model!X273,Model!AC273,Model!AH273,Model!AM273,Model!AR273,Model!AW273,Model!BB273,Model!BG273,Model!BL273,Model!BQ273,Model!BV273),"") -> 0.14630846 | K32: =IFERROR(MIN(Model!C273,Model!D273,Model!E273,Model!F273,Model!G273,Model!H273,Model!I273,Model!N273,Model!S273,Model!X273,Model!AC273,Model!AH273,Model!AM273,Model!AR273,Model!AW273,Model!BB273,Model!BG273,Model!BL273,Model!BQ273,Model!BV273),"") -> 0.088748415 | L32: =IFERROR(MAX(Model!C273,Model!D273,Model!E273,Model!F273,Model!G273,Model!H273,Model!I273,Model!N273,Model!S273,Model!X273,Model!AC273,Model!AH273,Model!AM273,Model!AR273,Model!AW273,Model!BB273,Model!BG273,Model!BL273,Model!BQ273,Model!BV273),"") -> 0.21177603 | N32: FCF % | O32: 0.14222551 | P32: 0.15384615 | Q32: 0.17828298 | R32: 0.17579816 | S32: 0.17670388 | T32: 0.17903484 | V32: 0.14630846 | W32: 0.088748415 | X32: 0.21177603 | Z32: FCF % | AA32: 0.14222551 | AB32: 0.14556962 | AC32: 0.16208698 | AD32: 0.16719876 | AE32: 0.16901392 | AF32: 0.17217372 | AH32: 0.14630846 | AI32: 0.088748415 | AJ32: 0.21177603
B33: FCF / share ($) | C33: =IFERROR(C31/C21,"") -> 16.76455 | D33: =IFERROR(D31/D21,"") -> 19.246299 | E33: =IFERROR(E31/E21,"") -> 23.404125 | F33: =IFERROR(F31/F21,"") -> 25.776595 | G33: =IFERROR(G31/G21,"") -> 28.639057 | H33: =IFERROR(H31/H21,"") -> 32.074028 | N33: FCF / share ($) | O33: 16.76455 | P33: 19.939073 | Q33: 25.52899 | R33: 28.51694 | S33: 32.423316 | T33: 37.211437 | Z33: FCF / share ($) | AA33: 16.76455 | AB33: 18.573351 | AC33: 21.391398 | AD33: 23.294084 | AE33: 25.219362 | AF33: 27.522007
B34: FCF Yield (on PT) | F34: =IFERROR(F33/F$27,"") | G34: =IFERROR(G33/G$27,"") -> 0.033561712 | H34: =IFERROR(H33/H$27,"") -> 0.033704998 | N34: FCF Yield (on PT) | R34: =IFERROR(R33/R$27,"") | S34: =IFERROR(S33/S$27,"") -> 0.028709921 | T34: =IFERROR(T33/T$27,"") -> 0.028850319 | Z34: FCF Yield (on PT) | AD34: =IFERROR(AD33/AD$27,"") -> 0.042136172 | AE34: =IFERROR(AE33/AE$27,"") -> 0.042207139 | AF34: =IFERROR(AF33/AF$27,"") -> 0.042369096
B35: Adjusted EBITDA — model (2026E pro forma incl. Clario full year) | C35: =Model!BV195 -> 11160 | D35: =Model!CA195 -> 12639.955 | E35: =Model!CB195 -> 13452.718 | F35: =Model!CC195 -> 14693.801 | G35: =Model!CD195 -> 16049.117 | H35: =Model!CE195 -> 17502.917 | I35: =IFERROR((H35/C35)^(1/5)-1,"n/m") -> 0.094181203 | N35: Adjusted EBITDA — model (2026E pro forma incl. Clario full year) | O35: 11160 | P35: 12779.999 | Q35: 14530.003 | R35: 16291.363 | S35: 18234.517 | T35: 20350.36 | U35: 0.12766884 | Z35: Adjusted EBITDA — model (2026E pro forma incl. Clario full year) | AA35: 11160 | AB35: 12500.611 | AC35: 12413.021 | AD35: 13176.949 | AE35: 14004.828 | AF35: 14877.574 | AG35: 0.059189306
B36: Adjusted EBITDA (pro forma) % of revenues | C36: =IFERROR(C35/C9,"") -> 0.25047132 | D36: =IFERROR(D35/D9,"") -> 0.2647111 | E36: =IFERROR(E35/E9,"") -> 0.26552894 | F36: =IFERROR(F35/F9,"") -> 0.26959602 | G36: =IFERROR(G35/G9,"") -> 0.27372403 | H36: =IFERROR(H35/H9,"") -> 0.27776388 | J36: =IFERROR(AVERAGE(Model!C230,Model!D230,Model!E230,Model!F230,Model!G230,Model!H230,Model!I230,Model!N230,Model!S230,Model!X230,Model!AC230,Model!AH230,Model!AM230,Model!AR230,Model!AW230,Model!BB230,Model!BG230,Model!BL230,Model!BQ230,Model!BV230),"") -> 0.23656039 | K36: =IFERROR(MIN(Model!C230,Model!D230,Model!E230,Model!F230,Model!G230,Model!H230,Model!I230,Model!N230,Model!S230,Model!X230,Model!AC230,Model!AH230,Model!AM230,Model!AR230,Model!AW230,Model!BB230,Model!BG230,Model!BL230,Model!BQ230,Model!BV230),"") -> 0.16953611 | L36: =IFERROR(MAX(Model!C230,Model!D230,Model!E230,Model!F230,Model!G230,Model!H230,Model!I230,Model!N230,Model!S230,Model!X230,Model!AC230,Model!AH230,Model!AM230,Model!AR230,Model!AW230,Model!BB230,Model!BG230,Model!BL230,Model!BQ230,Model!BV230),"") -> 0.33074902 | N36: Adjusted EBITDA (pro forma) % of revenues | O36: 0.25047132 | P36: 0.26569645 | Q36: 0.27776345 | R36: 0.2812851 | S36: 0.28488126 | T36: 0.28841254 | V36: 0.23656039 | W36: 0.16953611 | X36: 0.33074902 | Z36: Adjusted EBITDA (pro forma) % of revenues | AA36: 0.25047132 | AB36: 0.26372598 | AC36: 0.25316557 | AD36: 0.25757048 | AE36: 0.26210269 | AF36: 0.26660072 | AH36: 0.23656039 | AI36: 0.16953611 | AJ36: 0.33074902
B38: Net Debt | C38: =Model!BV395 -> 29280 | D38: =Model!CA395 -> 33162.74 | E38: =Model!CB395 -> 33631.795 | F38: =Model!CC395 -> 36734.501 | G38: =Model!CD395 -> 40122.792 | H38: =Model!CE395 -> 43757.293 | N38: Net Debt | O38: 29280 | P38: 33912.046 | Q38: 39957.508 | R38: 44801.249 | S38: 50144.922 | T38: 55963.491 | Z38: Net Debt | AA38: 29280 | AB38: 33412.74 | AC38: 27929.297 | AD38: 29648.135 | AE38: 31510.863 | AF38: 33474.542
B39: Net Debt / Adjusted EBITDA (x) | C39: =IFERROR(C38/C35,"") -> 2.6236559 | D39: =IFERROR(D38/D35,"") -> 2.6236438 | E39: =IFERROR(E38/E35,"") -> 2.5 | F39: =IFERROR(F38/F35,"") -> 2.5 | G39: =IFERROR(G38/G35,"") -> 2.5 | H39: =IFERROR(H38/H35,"") -> 2.5 | N39: Net Debt / Adjusted EBITDA (x) | O39: 2.6236559 | P39: 2.6535249 | Q39: 2.75 | R39: 2.75 | S39: 2.75 | T39: 2.75 | Z39: Net Debt / Adjusted EBITDA (x) | AA39: 2.6236559 | AB39: 2.6728885 | AC39: 2.25 | AD39: 2.25 | AE39: 2.25 | AF39: 2.25
B40: Share repurchases ($m; 2026E = 2H only) | D40: =Model!CA282 -> 0 | E40: =Model!CB282 -> 4340.1667 | F40: =Model!CC282 -> 7620.5645 | G40: =Model!CD282 -> 8641.22 | H40: =Model!CE282 -> 9754.5019 | N40: Share repurchases ($m; 2026E = 2H only) | P40: 1000 | Q40: 7608.9565 | R40: 7206.9433 | S40: 8772.6585 | T40: 10505.931 | Z40: Share repurchases ($m; 2026E = 2H only) | AB40: 0 | AC40: 698.21008 | AD40: 8429.0169 | AE40: 8988.7218 | AF40: 9601.3311
B41: Implied avg buyback price ($) | D41: =Model!CA281 -> 676.76 | E41: =Model!CB281 -> 730.9008 | F41: =Model!CC281 -> 789.37286 | G41: =Model!CD281 -> 852.52269 | H41: =Model!CE281 -> 920.72451 | N41: Implied avg buyback price ($) | P41: 676.76 | Q41: 730.9008 | R41: 789.37286 | S41: 852.52269 | T41: 920.72451 | Z41: Implied avg buyback price ($) | AB41: 676.76 | AC41: 730.9008 | AD41: 789.37286 | AE41: 852.52269 | AF41: 920.72451
B42: Shares repurchased (m) | D42: =Model!CA283 -> 0 | E42: =Model!CB283 -> 5.9381064 | F42: =Model!CC283 -> 9.6539478 | G42: =Model!CD283 -> 10.136059 | H42: =Model!CE283 -> 10.594376 | N42: Shares repurchased (m) | P42: 1.4776287 | Q42: 10.410382 | R42: 9.1299608 | S42: 10.290235 | T42: 11.410504 | Z42: Shares repurchased (m) | AB42: 0 | AC42: 0.95527339 | AD42: 10.678118 | AE42: 10.543675 | AF42: 10.428017
B44: ROIC | C44: =Model!BV378 -> 0.1093851 | D44: =Model!CA378 -> 0.11052175 | E44: =Model!CB378 -> 0.11351232 | F44: =Model!CC378 -> 0.11869908 | G44: =Model!CD378 -> 0.12417051 | H44: =Model!CE378 -> 0.13032961 | J44: =IFERROR(AVERAGE(Model!C378,Model!D378,Model!E378,Model!F378,Model!G378,Model!H378,Model!I378,Model!N378,Model!S378,Model!X378,Model!AC378,Model!AH378,Model!AM378,Model!AR378,Model!AW378,Model!BB378,Model!BG378,Model!BL378,Model!BQ378,Model!BV378),"") -> 0.10315893 | K44: =IFERROR(MIN(Model!C378,Model!D378,Model!E378,Model!F378,Model!G378,Model!H378,Model!I378,Model!N378,Model!S378,Model!X378,Model!AC378,Model!AH378,Model!AM378,Model!AR378,Model!AW378,Model!BB378,Model!BG378,Model!BL378,Model!BQ378,Model!BV378),"") -> 0.02583209 | L44: =IFERROR(MAX(Model!C378,Model!D378,Model!E378,Model!F378,Model!G378,Model!H378,Model!I378,Model!N378,Model!S378,Model!X378,Model!AC378,Model!AH378,Model!AM378,Model!AR378,Model!AW378,Model!BB378,Model!BG378,Model!BL378,Model!BQ378,Model!BV378),"") -> 0.17845579 | N44: ROIC | O44: 0.1093851 | P44: 0.11196706 | Q44: 0.11934829 | R44: 0.12427485 | S44: 0.12964836 | T44: 0.13591464 | V44: 0.10315893 | W44: 0.02583209 | X44: 0.17845579 | Z44: ROIC | AA44: 0.1093851 | AB44: 0.1090868 | AC44: 0.10764358 | AD44: 0.11310421 | AE44: 0.11882589 | AF44: 0.1251519 | AH44: 0.10315893 | AI44: 0.02583209 | AJ44: 0.17845579
B45: RONTA | C45: =Model!BV389 -> 0.27050992 | D45: =Model!CA389 -> 0.30308514 | E45: =Model!CB389 -> 0.31555186 | F45: =Model!CC389 -> 0.36006871 | G45: =Model!CD389 -> 0.39430808 | H45: =Model!CE389 -> 0.40853439 | J45: =IFERROR(AVERAGE(Model!C389,Model!D389,Model!E389,Model!F389,Model!G389,Model!H389,Model!I389,Model!N389,Model!S389,Model!X389,Model!AC389,Model!AH389,Model!AM389,Model!AR389,Model!AW389,Model!BB389,Model!BG389,Model!BL389,Model!BQ389,Model!BV389),"") -> 0.36499146 | K45: =IFERROR(MIN(Model!C389,Model!D389,Model!E389,Model!F389,Model!G389,Model!H389,Model!I389,Model!N389,Model!S389,Model!X389,Model!AC389,Model!AH389,Model!AM389,Model!AR389,Model!AW389,Model!BB389,Model!BG389,Model!BL389,Model!BQ389,Model!BV389),"") -> 0.11537017 | L45: =IFERROR(MAX(Model!C389,Model!D389,Model!E389,Model!F389,Model!G389,Model!H389,Model!I389,Model!N389,Model!S389,Model!X389,Model!AC389,Model!AH389,Model!AM389,Model!AR389,Model!AW389,Model!BB389,Model!BG389,Model!BL389,Model!BQ389,Model!BV389),"") -> 0.51854284 | N45: RONTA | O45: 0.27050992 | P45: 0.31505577 | Q45: 0.39848042 | R45: 0.41651392 | S45: 0.43430005 | T45: 0.45392158 | V45: 0.36499146 | W45: 0.11537017 | X45: 0.51854284 | Z45: RONTA | AA45: 0.27050992 | AB45: 0.30066479 | AC45: 0.24900081 | AD45: 0.26756699 | AE45: 0.28861018 | AF45: 0.31346925 | AH45: 0.36499146 | AI45: 0.11537017 | AJ45: 0.51854284
B47: Implied Market Cap (USDm) | F47: =F27*F21 -> 0 | G47: =G27*G21 -> 302364.88 | H47: =H27*H21 -> 328754.75 | N47: Implied Market Cap (USDm) | S47: =S27*S21 -> 393953.07 | T47: =T27*T21 -> 437869.72 | Z47: Implied Market Cap (USDm) | AD47: =AD27*AD21 -> 203000.32 | AE47: =AE27*AE21 -> 213965.06 | AF47: =AF27*AF21 -> 226771.51
B48: (+) Net Debt & NCI | F48: =F38+Model!CC404 -> 36912.501 | G48: =G38+Model!CD404 -> 40320.792 | H48: =H38+Model!CE404 -> 43975.293 | N48: (+) Net Debt & NCI | S48: =S38+198 -> 50342.922 | T48: =T38+218 -> 56181.491 | Z48: (+) Net Debt & NCI | AD48: =AD38+178 -> 29826.135 | AE48: =AE38+198 -> 31708.863 | AF48: =AF38+218 -> 33692.542
B49: Implied Enterprise Value (USDm) | F49: =F47+F48 -> 36912.501 | G49: =G47+G48 -> 342685.68 | H49: =H47+H48 -> 372730.04 | N49: Implied Enterprise Value (USDm) | S49: =S47+S48 -> 444295.99 | T49: =T47+T48 -> 494051.21 | Z49: Implied Enterprise Value (USDm) | AD49: =AD47+AD48 -> 232826.46 | AE49: =AE47+AE48 -> 245673.92 | AF49: =AF47+AF48 -> 260464.05
B50: Implied EV / Adjusted EBITDA (x) | F50: =IFERROR(F49/F35,"") -> 2.512114 | G50: =IFERROR(G49/G35,"") -> 21.352308 | H50: =IFERROR(H49/H35,"") -> 21.295309 | N50: Implied EV / Adjusted EBITDA (x) | S50: =IFERROR(S49/S35,"") -> 24.365657 | T50: =IFERROR(T49/T35,"") -> 24.277271 | Z50: Implied EV / Adjusted EBITDA (x) | AD50: =IFERROR(AD49/AD35,"") -> 17.669224 | AE50: =IFERROR(AE49/AE35,"") -> 17.542088 | AF50: =IFERROR(AF49/AF35,"") -> 17.507158

Sheet DCF
B2: DCF VALUATION — THERMO FISHER SCIENTIFIC (TMO)
B4: 1. WACC BUILD
B5: Risk-free rate (US 10Y govt) | C5: 0.055 | D5: Assumption (~US 10Y Treasury yield, consistent with the other models in this set); update to market
B6: Equity risk premium | C6: 0.05 | D6: US implied ERP ~4.5–5.5% (Damodaran)
B7: Levered beta | C7: 0.9 | D7: Life-science tools & services peers (DHR, A, WAT, IQV, ILMN) ~0.8–1.1; recurring consumables/services (~80% of revenues) dampen cyclicality
B8: Cost of equity | C8: =C5+C7*C6 -> 0.1
B9: Pre-tax cost of debt | C9: 0.05 | D9: Single-A (A-/A3); 2025–26 USD notes priced at 4.20%–5.55% (Feb-2026: 4.215% 2031 → 5.546% 2046); marginal cost ~5.0%
B10: Tax rate | C10: 0.13 | D10: Model 2029E–30E adjusted tax rate (cash-tax proxy; FY26 guidance 11.5%)
B11: After-tax cost of debt | C11: =C9*(1-C10) -> 0.0435
B12: Target D/V | C12: 0.15 | D12: Net debt ~$33bn at YE2026E vs ~$250bn market cap ($676.76 × ~370m shares); 2.6x net debt / adjusted EBITDA
B13: WACC | C13: =C8*(1-C12)+C11*C12 -> 0.091525
B15: Valuation date (live) | C15: =TODAY() -> 46301 | D15: Periods = (Dec-31-Year − today) / 365.25; cash flows assumed at year-end
B16: 2. UNLEVERED FREE CASH FLOW BUILD (USDm)
D17: 2026E | E17: 2027E | F17: 2028E | G17: 2029E | H17: 2030E | I17: 2031E | J17: 2032E | K17: 2033E | L17: 2034E | M17: 2035E | N17: Terminal | P17: CAGR 26–30E | Q17: CAGR 26–35E
B18: Adj. EBIT less restructuring, transaction & integration costs | D18: =Model!CA196-Model!CA181-(Model!CA143+N(Model!CA85)) -> 10763.25 | E18: =Model!CB196-Model!CB181-(Model!CB143+N(Model!CB85)) -> 11660.811 | F18: =Model!CC196-Model!CC181-(Model!CC143+N(Model!CC85)) -> 12795.2 | G18: =Model!CD196-Model!CD181-(Model!CD143+N(Model!CD85)) -> 14014.245 | H18: =Model!CE196-Model!CE181-(Model!CE143+N(Model!CE85)) -> 15323.467 | I18: =H18*(1+I$26) -> 16396.109 | J18: =I18*(1+J$26) -> 17461.857 | K18: =J18*(1+K$26) -> 18509.568 | L18: =K18*(1+L$26) -> 19527.594 | M18: =L18*(1+M$26) -> 20503.974 | P18: =(H18/D18)^(1/(COLUMNS(D18:H18)-1))-1 -> 0.092328842 | Q18: =(M18/D18)^(1/(COLUMNS(D18:M18)-1))-1 -> 0.074235255
B19: × (1 − tax rate) | D19: =1-$C$10 -> 0.87 | E19: =1-$C$10 -> 0.87 | F19: =1-$C$10 -> 0.87 | G19: =1-$C$10 -> 0.87 | H19: =1-$C$10 -> 0.87 | I19: =1-$C$10 -> 0.87 | J19: =1-$C$10 -> 0.87 | K19: =1-$C$10 -> 0.87 | ... M19: =1-$C$10 -> 0.87
B20: NOPAT | D20: =D18*D19 -> 9364.0275 | E20: =E18*E19 -> 10144.906 | F20: =F18*F19 -> 11131.824 | G20: =G18*G19 -> 12192.393 | H20: =H18*H19 -> 13331.416 | I20: =I18*I19 -> 14264.615 | J20: =J18*J19 -> 15191.815 | K20: =K18*K19 -> 16103.324 | ... M20: =M18*M19 -> 17838.457
B21: plus depreciation (acquired-intangible amortization already excluded from adjusted EBIT) | D21: =Model!CA126 -> 1322.4695 | E21: =Model!CB126 -> 1367.9239 | F21: =Model!CC126 -> 1471.5819 | G21: =Model!CD126 -> 1583.0768 | H21: =Model!CE126 -> 1701.3687 | I21: =H21*(1+I$26) -> 1820.4645 | J21: =I21*(1+J$26) -> 1938.7947 | K21: =J21*(1+K$26) -> 2055.1223 | L21: =K21*(1+L$26) -> 2168.1541 | M21: =L21*(1+M$26) -> 2276.5618
B22: − Capex (PP&E) and acquisitions (M&A 2027E–30E) | D22: =Model!CA248 -> -2000 | E22: =Model!CB248+Model!CB250 -> -6127.8817 | F22: =Model!CC248+Model!CC250 -> -6289.1273 | G22: =Model!CD248+Model!CD250 -> -6462.5639 | H22: =Model!CE248+Model!CE250 -> -6646.5735 | I22: =Model!CE248*(1+I$26) -> -2831.8336 | J22: =I22*(1+J$26) -> -3015.9028 | K22: =J22*(1+K$26) -> -3196.857 | L22: =K22*(1+L$26) -> -3372.6841 | M22: =L22*(1+M$26) -> -3541.3183
B23: − Δ Working capital (CF statement) | D23: =Model!CA245 -> -758.19247 | E23: =Model!CB245 -> -376.65811 | F23: =Model!CC245 -> -514.7134 | G23: =Model!CD245 -> -553.62799 | H23: =Model!CE245 -> -587.37837 | I23: =H23*(1+I$26) -> -628.49486 | J23: =I23*(1+J$26) -> -669.34702 | K23: =J23*(1+K$26) -> -709.50785 | L23: =K23*(1+L$26) -> -748.53078 | M23: =L23*(1+M$26) -> -785.95732
B24: Unlevered FCF | D24: =D20+D21+D22+D23 -> 7928.3045 | E24: =E20+E21+E22+E23 -> 5008.2898 | F24: =F20+F21+F22+F23 -> 5799.5656 | G24: =G20+G21+G22+G23 -> 6759.2781 | H24: =H20+H21+H22+H23 -> 7798.8329 | I24: =I20+I21+I22+I23 -> 12624.751 | J24: =J20+J21+J22+J23 -> 13445.36 | K24: =K20+K21+K22+K23 -> 14252.082 | ... M24: =M20+M21+M22+M23 -> 15787.743 | N24: =M24*(1+$C$27) -> 16340.314 | P24: =(H24/D24)^(1/(COLUMNS(D24:H24)-1))-1 -> -0.0041078181 | Q24: =(M24/D24)^(1/(COLUMNS(D24:M24)-1))-1 -> 0.079537538
B25: Terminal Value (Gordon Growth) | N25: =N24/($C$13-$C$27) -> 289081.19
B26: Fade-period growth (2031E–35E; 7% → 5% linear) | I26: 0.07 | J26: =I26+($M$26-$I$26)/4 -> 0.065 | K26: =J26+($M$26-$I$26)/4 -> 0.06 | L26: =K26+($M$26-$I$26)/4 -> 0.055 | M26: 0.05
B27: Terminal growth rate | C27: 0.035
B29: Discount period (years) | D29: =(DATE(2026,12,31)-$C$15)/365.25 -> 0.23545517 | E29: =(DATE(2027,12,31)-$C$15)/365.25 -> 1.2347707 | F29: =(DATE(2028,12,31)-$C$15)/365.25 -> 2.2368241 | G29: =(DATE(2029,12,31)-$C$15)/365.25 -> 3.2361396 | H29: =(DATE(2030,12,31)-$C$15)/365.25 -> 4.2354552 | I29: =(DATE(2031,12,31)-$C$15)/365.25 -> 5.2347707 | J29: =(DATE(2032,12,31)-$C$15)/365.25 -> 6.2368241 | K29: =(DATE(2033,12,31)-$C$15)/365.25 -> 7.2361396 | L29: =(DATE(2034,12,31)-$C$15)/365.25 -> 8.2354552 | M29: =(DATE(2035,12,31)-$C$15)/365.25 -> 9.2347707 | N29: =M29 -> 9.2347707
B30: Discount factor | D30: =1/(1+$C$13)^D29 -> 0.97959097 | E30: =1/(1+$C$13)^E29 -> 0.8975055 | F30: =1/(1+$C$13)^F29 -> 0.82210129 | G30: =1/(1+$C$13)^G29 -> 0.75321278 | H30: =1/(1+$C$13)^H29 -> 0.69009682 | I30: =1/(1+$C$13)^I29 -> 0.6322697 | J30: =1/(1+$C$13)^J29 -> 0.57914936 | K30: =1/(1+$C$13)^K29 -> 0.53061916 | ... N30: =1/(1+$C$13)^N29 -> 0.44541785
B31: PV of UFCF | D31: =D24*D30 -> 7766.4955 | E31: =E24*E30 -> 4494.9676 | F31: =F24*F30 -> 4767.8304 | G31: =G24*G30 -> 5091.1746 | H31: =H24*H30 -> 5381.9498 | I31: =I24*I30 -> 7982.2476 | J31: =J24*J30 -> 7786.8717 | K31: =K24*K30 -> 7562.4276 | ... M31: =M24*M30 -> 7032.1428 | N31: =N25*N30 -> 128761.92
D32: TMO's adjusted operating income expenses stock-based compensation and depreciation and excludes amortization of acquired intangibles (non-cash), so only depreciation is added back. Restructuring, transaction and integration costs are deducted as cash costs (the 2026E microbiology gain is excluded). Clario (closed 24-Mar-2026, $8.9bn) and the microbiology proceeds sit in YE2026E net debt, not in UFCF; acquisition spend from the M&A lever is deducted in 2027E–30E; the fade period and terminal value assume no new acquisitions.
B33: IMPLIED ROIC — invested capital roll-forward (USDm)
B34: Opening invested capital | D34: =Model!BV375+Model!CA75 -> 91914 | E34: =D38 -> 93349.723 | F34: =E38 -> 98486.339 | G34: =F38 -> 103818.6 | H34: =G38 -> 109251.71 | I34: =H38 -> 114784.3 | J34: =I38 -> 116424.16 | K34: =J38 -> 118170.62 | L34: =K38 -> 120021.86 | M34: =L38 -> 121974.92
B35: plus Capex and acquisitions | D35: =-D22 -> 2000 | E35: =-E22 -> 6127.8817 | F35: =-F22 -> 6289.1273 | G35: =-G22 -> 6462.5639 | H35: =-H22 -> 6646.5735 | I35: =-I22 -> 2831.8336 | J35: =-J22 -> 3015.9028 | K35: =-K22 -> 3196.857 | ... M35: =-M22 -> 3541.3183
B36: less DD&A | D36: =-D21 -> -1322.4695 | E36: =-E21 -> -1367.9239 | F36: =-F21 -> -1471.5819 | G36: =-G21 -> -1583.0768 | H36: =-H21 -> -1701.3687 | I36: =-I21 -> -1820.4645 | J36: =-J21 -> -1938.7947 | K36: =-K21 -> -2055.1223 | ... M36: =-M21 -> -2276.5618
B37: plus Δ Working capital investment | D37: =-D23 -> 758.19247 | E37: =-E23 -> 376.65811 | F37: =-F23 -> 514.7134 | G37: =-G23 -> 553.62799 | H37: =-H23 -> 587.37837 | I37: =-I23 -> 628.49486 | J37: =-J23 -> 669.34702 | K37: =-K23 -> 709.50785 | ... M37: =-M23 -> 785.95732
B38: Closing invested capital | D38: =SUM(D34:D37) -> 93349.723 | E38: =SUM(E34:E37) -> 98486.339 | F38: =SUM(F34:F37) -> 103818.6 | G38: =SUM(G34:G37) -> 109251.71 | H38: =SUM(H34:H37) -> 114784.3 | I38: =SUM(I34:I37) -> 116424.16 | J38: =SUM(J34:J37) -> 118170.62 | K38: =SUM(K34:K37) -> 120021.86 | ... M38: =SUM(M34:M37) -> 124025.63
B39: NOPAT (row 20) | D39: =D20 -> 9364.0275 | E39: =E20 -> 10144.906 | F39: =F20 -> 11131.824 | G39: =G20 -> 12192.393 | H39: =H20 -> 13331.416 | I39: =I20 -> 14264.615 | J39: =J20 -> 15191.815 | K39: =K20 -> 16103.324 | ... M39: =M20 -> 17838.457
B40: Implied ROIC (NOPAT / avg. invested capital) | D40: =IFERROR(D39/AVERAGE(D34,D38),"") -> 0.10108862 | E40: =IFERROR(E39/AVERAGE(E34,E38),"") -> 0.10576641 | F40: =IFERROR(F39/AVERAGE(F34,F38),"") -> 0.11004995 | G40: =IFERROR(G39/AVERAGE(G34,G38),"") -> 0.11444479 | H40: =IFERROR(H39/AVERAGE(H34,H38),"") -> 0.11901137 | I40: =IFERROR(I39/AVERAGE(I34,I38),"") -> 0.12339181 | J40: =IFERROR(J39/AVERAGE(J34,J38),"") -> 0.12951538 | K40: =IFERROR(K39/AVERAGE(K34,K38),"") -> 0.1352127 | ... M40: =IFERROR(M39/AVERAGE(M34,M38),"") -> 0.14502778
B41: Reinvestment rate (net investment / NOPAT) | D41: =IFERROR(SUM(D35:D37)/D39,"") -> 0.15332323 | E41: =IFERROR(SUM(E35:E37)/E39,"") -> 0.50632465 | F41: =IFERROR(SUM(F35:F37)/F39,"") -> 0.47901033 | G41: =IFERROR(SUM(G35:G37)/G39,"") -> 0.44561515 | H41: =IFERROR(SUM(H35:H37)/H39,"") -> 0.41500341 | I41: =IFERROR(SUM(I35:I37)/I39,"") -> 0.11496027 | J41: =IFERROR(SUM(J35:J37)/J39,"") -> 0.11496027 | K41: =IFERROR(SUM(K35:K37)/K39,"") -> 0.11496027 | ... M41: =IFERROR(SUM(M35:M37)/M39,"") -> 0.11496027
B42: Implied terminal RONIC (g / reinvestment rate) | N42: =IFERROR($C$27/M41,"") -> 0.30445301
D43: Opening IC = Model 2025A book IC (equity incl. NCI + net debt) + Clario purchase price ($9.1bn), rolled forward with capex + M&A − depreciation + ΔWC.
B44: 3. VALUATION SUMMARY
B45: Sum of PV (explicit + fade) | C45: =SUM(D31:M31) -> 65175.917
B46: PV of Terminal Value | C46: =N31 -> 128761.92
B47: Enterprise Value | C47: =C45+C46 -> 193937.84
B48: Less: Net debt + NCI incl. redeemable NCI (Model 2026E YE) | C48: =Model!CA395+Model!CA404 -> 33300.74 | D48: TMO-specific: noncontrolling interests (~$0.2bn) and redeemable NCI (~$0.1bn) deducted alongside net debt; YE2026E net debt includes Clario and the microbiology proceeds.
B49: Equity Value | C49: =C47-C48 -> 160637.1
B50: Diluted shares (m, Model 2026E YE) | C50: =Model!CA401 -> 370.24729
B51: Implied share price ($) | C51: =C49/C50 -> 433.86436
B52: Current share price ($) | C52: =Model!CA400 -> 676.76
B53: Implied upside / (downside) | C53: =C51/C52-1 -> -0.35890957
B54: Required discount to DCF value for target IRR | C54: =1-((1+C13)/(1+H54))^H55 -> 0.14491844 | D54: vs. current | E54: Target IRR | H54: 0.15
B55: Max entry price for target IRR ($) | C55: =C51*(1-C54) -> 370.98941 | D55: =C55/C52-1 -> -0.4518154 | E55: Years for discount to close | H55: 3
B58: 4. SENSITIVITY: IMPLIED PRICE ($) — WACC × Terminal Growth
D60: WACC →
B61: Terminal growth ↓ | D61: =F61-0.01 -> 0.081525 | E61: =F61-0.005 -> 0.086525 | F61: =$C$13 -> 0.091525 | G61: =F61+0.005 -> 0.096525 | H61: =F61+0.01 -> 0.101525
B62: =B64-0.01 -> 0.025 | D62: {=IFERROR((SUMPRODUCT($D$24:$M$24/(1+D$61)^$D$29:$M$29)+($M$24*(1+$B62)/(D$61-$B62))/(1+D$61)^$M$29-$C$48)/$C$50,"")} -> 469.4559 | E62: {=IFERROR((SUMPRODUCT($D$24:$M$24/(1+E$61)^$D$29:$M$29)+($M$24*(1+$B62)/(E$61-$B62))/(1+E$61)^$M$29-$C$48)/$C$50,"")} -> 420.34388 | F62: {=IFERROR((SUMPRODUCT($D$24:$M$24/(1+F$61)^$D$29:$M$29)+($M$24*(1+$B62)/(F$61-$B62))/(1+F$61)^$M$29-$C$48)/$C$50,"")} -> 378.73232 | G62: {=IFERROR((SUMPRODUCT($D$24:$M$24/(1+G$61)^$D$29:$M$29)+($M$24*(1+$B62)/(G$61-$B62))/(1+G$61)^$M$29-$C$48)/$C$50,"")} -> 343.04472 | H62: {=IFERROR((SUMPRODUCT($D$24:$M$24/(1+H$61)^$D$29:$M$29)+($M$24*(1+$B62)/(H$61-$B62))/(1+H$61)^$M$29-$C$48)/$C$50,"")} -> 312.11672
B63: =B64-0.005 -> 0.03 | D63: {=IFERROR((SUMPRODUCT($D$24:$M$24/(1+D$61)^$D$29:$M$29)+($M$24*(1+$B63)/(D$61-$B63))/(1+D$61)^$M$29-$C$48)/$C$50,"")} -> 507.84928 | E63: {=IFERROR((SUMPRODUCT($D$24:$M$24/(1+E$61)^$D$29:$M$29)+($M$24*(1+$B63)/(E$61-$B63))/(1+E$61)^$M$29-$C$48)/$C$50,"")} -> 451.29862 | F63: {=IFERROR((SUMPRODUCT($D$24:$M$24/(1+F$61)^$D$29:$M$29)+($M$24*(1+$B63)/(F$61-$B63))/(1+F$61)^$M$29-$C$48)/$C$50,"")} -> 404.05811 | G63: {=IFERROR((SUMPRODUCT($D$24:$M$24/(1+G$61)^$D$29:$M$29)+($M$24*(1+$B63)/(G$61-$B63))/(1+G$61)^$M$29-$C$48)/$C$50,"")} -> 364.02503 | H63: {=IFERROR((SUMPRODUCT($D$24:$M$24/(1+H$61)^$D$29:$M$29)+($M$24*(1+$B63)/(H$61-$B63))/(1+H$61)^$M$29-$C$48)/$C$50,"")} -> 329.68475
B64: =$C$27 -> 0.035 | D64: {=IFERROR((SUMPRODUCT($D$24:$M$24/(1+D$61)^$D$29:$M$29)+($M$24*(1+$B64)/(D$61-$B64))/(1+D$61)^$M$29-$C$48)/$C$50,"")} -> 554.49486 | E64: {=IFERROR((SUMPRODUCT($D$24:$M$24/(1+E$61)^$D$29:$M$29)+($M$24*(1+$B64)/(E$61-$B64))/(1+E$61)^$M$29-$C$48)/$C$50,"")} -> 488.26107 | F64: {=IFERROR((SUMPRODUCT($D$24:$M$24/(1+F$61)^$D$29:$M$29)+($M$24*(1+$B64)/(F$61-$B64))/(1+F$61)^$M$29-$C$48)/$C$50,"")} -> 433.86436 | G64: {=IFERROR((SUMPRODUCT($D$24:$M$24/(1+G$61)^$D$29:$M$29)+($M$24*(1+$B64)/(G$61-$B64))/(1+G$61)^$M$29-$C$48)/$C$50,"")} -> 388.41539 | H64: {=IFERROR((SUMPRODUCT($D$24:$M$24/(1+H$61)^$D$29:$M$29)+($M$24*(1+$B64)/(H$61-$B64))/(1+H$61)^$M$29-$C$48)/$C$50,"")} -> 349.89359
B65: =B64+0.005 -> 0.04 | D65: {=IFERROR((SUMPRODUCT($D$24:$M$24/(1+D$61)^$D$29:$M$29)+($M$24*(1+$B65)/(D$61-$B65))/(1+D$61)^$M$29-$C$48)/$C$50,"")} -> 612.37357 | E65: {=IFERROR((SUMPRODUCT($D$24:$M$24/(1+E$61)^$D$29:$M$29)+($M$24*(1+$B65)/(E$61-$B65))/(1+E$61)^$M$29-$C$48)/$C$50,"")} -> 533.16816 | F65: {=IFERROR((SUMPRODUCT($D$24:$M$24/(1+F$61)^$D$29:$M$29)+($M$24*(1+$B65)/(F$61-$B65))/(1+F$61)^$M$29-$C$48)/$C$50,"")} -> 469.45542 | G65: {=IFERROR((SUMPRODUCT($D$24:$M$24/(1+G$61)^$D$29:$M$29)+($M$24*(1+$B65)/(G$61-$B65))/(1+G$61)^$M$29-$C$48)/$C$50,"")} -> 417.12072 | H65: {=IFERROR((SUMPRODUCT($D$24:$M$24/(1+H$61)^$D$29:$M$29)+($M$24*(1+$B65)/(H$61-$B65))/(1+H$61)^$M$29-$C$48)/$C$50,"")} -> 373.3871
B66: =B64+0.01 -> 0.045 | D66: {=IFERROR((SUMPRODUCT($D$24:$M$24/(1+D$61)^$D$29:$M$29)+($M$24*(1+$B66)/(D$61-$B66))/(1+D$61)^$M$29-$C$48)/$C$50,"")} -> 686.09862 | E66: {=IFERROR((SUMPRODUCT($D$24:$M$24/(1+E$61)^$D$29:$M$29)+($M$24*(1+$B66)/(E$61-$B66))/(1+E$61)^$M$29-$C$48)/$C$50,"")} -> 588.88973 | F66: {=IFERROR((SUMPRODUCT($D$24:$M$24/(1+F$61)^$D$29:$M$29)+($M$24*(1+$B66)/(F$61-$B66))/(1+F$61)^$M$29-$C$48)/$C$50,"")} -> 512.69636 | G66: {=IFERROR((SUMPRODUCT($D$24:$M$24/(1+G$61)^$D$29:$M$29)+($M$24*(1+$B66)/(G$61-$B66))/(1+G$61)^$M$29-$C$48)/$C$50,"")} -> 451.39719 | H66: {=IFERROR((SUMPRODUCT($D$24:$M$24/(1+H$61)^$D$29:$M$29)+($M$24*(1+$B66)/(H$61-$B66))/(1+H$61)^$M$29-$C$48)/$C$50,"")} -> 401.0369
B69: 5. REVERSE DCF
B70: To solve for the market-implied path: Data ▸ What-If Analysis ▸ Goal Seek — set C51 to the current price (C52) by changing C27 (terminal growth) or the fade-period growth inputs (I26:M26).
B72: 6. MAUBOUSSIN EV / NOPAT — TWO-STAGE FRAMEWORK
B73: EV/NOPAT = 1/r + [g × (1 − r/ROIIC) / (r × (r − g))] × [1 − ((1+g)/(1+r))^N]
B74: Formula source: Mauboussin & Rappaport, "Expectations Investing" (2021); Counterpoint Global, "What Does a Price-Earnings Multiple Mean?" (2020).
B76: Input | C76: Value | D76: Rationale (Thermo Fisher characteristics)
B77: r (Cost of capital / WACC) | C77: =$C$13 -> 0.091525 | D77: Linked from Section 1 WACC build
B78: g (NOPAT growth, Stage 1) | C78: 0.09 | D78: Model adjusted EBIT CAGR 2026–30E (~9%): ~6% organic growth, 40–50bp p.a. margin expansion and bolt-on M&A → ~9% NOPAT growth
B79: ROIIC (Return on incremental invested capital) | C79: 0.14 | D79: Organic reinvestment (capex ~4% of revenues, R&D ~3%) earns high returns; acquired growth earns ~7–9% after tax on purchase price (Clario ~7x revenues) → blended ~14%
B80: N (Years of value creation / CAP) | C80: 15 | D80: Scale leader in life-science tools & services (~$48bn revenues), ~80% recurring revenues, unmatched channel (Fisher) and PPI productivity system; long runway in biopharma outsourcing
B82: Calculation | C82: Value
B83: Steady-state component: 1 / r | C83: =1/C77 -> 10.925977
B84: Value-creation factor: 1 − r / ROIIC | C84: =1-C77/C79 -> 0.34625
B85: Growth multiplier: g × (1 − r/ROIIC) / (r × (r − g)) | C85: =C78*C84/(C77*(C77-C78)) -> 223.26606
B86: Time decay: 1 − ((1+g)/(1+r))^N | C86: =1-((1+C78)/(1+C77))^C80 -> 0.020753197
B87: PVGO component (growth value) | C87: =C85*C86 -> 4.6334846
B88: Mauboussin EV / NOPAT (steady-state + PVGO) | C88: =C83+C87 -> 15.559461
B90: VALUATION — Applied to 2028E NOPAT | C90: USDm
B91: 2028E Adj. EBIT less restructuring, transaction & integration costs | C91: =Model!CC196-Model!CC181-Model!CC143 -> 12795.2
B92: Tax rate (from WACC build) | C92: =$C$10 -> 0.13
B93: 2028E NOPAT | C93: =C91*(1-C92) -> 11131.824
B94: × Mauboussin EV/NOPAT multiple | C94: =C88 -> 15.559461
B95: Implied Enterprise Value (2028E basis) | C95: =C93*C94 -> 173205.19
B96: Less: YE2027 net debt + NCI (Model) | C96: =Model!CB395+Model!CB404 -> 33789.795
B97: Implied Equity Value | C97: =C95-C96 -> 139415.39
B98: Diluted shares 2028E (m, Model) | C98: =Model!CC401 -> 358.65523
B99: Implied share price 2028 ($) | C99: =C97/C98 -> 388.71702
B101: Current share price ($) | C101: =C52 -> 676.76
B102: Implied upside / (downside) | C102: =C99/C101-1 -> -0.42562057
B104: MARKET-IMPLIED EV/NOPAT TODAY | C104: USDm
B105: Current market cap (spot × diluted shares) | C105: =C52*C50 -> 250568.55
B106: Plus: YE2026 net debt + NCI | C106: =C48 -> 33300.74
B107: Implied Enterprise Value (today) | C107: =C105+C106 -> 283869.29
B108: TMO market-implied EV/NOPAT (on 2028E NOPAT) | C108: =C107/C93 -> 25.500698
B110: Multiple gap (Mauboussin − Market) | C110: =C88-C108 -> -9.9412369
B111: Implied re-rating headroom | C111: =C88/C108-1 -> -0.38984176

Sheet Charts
B2: Thermo Fisher Scientific — Historical Operating Performance (2006–2025)
B3: All historicals · USDm · Linked to Model. Revenue growth drivers = company-reported organic growth, acquisitions/divestitures and currency translation (consolidated; not disclosed on a consistent basis before 2012). Adjusted operating income = company definition (Σ segment income).
C7: 2006 | D7: 2007 | E7: 2008 | F7: 2009 | G7: 2010 | H7: 2011 | I7: 2012 | J7: 2013 | K7: 2014 | L7: 2015 | M7: 2016 | N7: 2017 | O7: 2018 | P7: 2019 | Q7: 2020 | R7: 2021 | S7: 2022 | T7: 2023 | U7: 2024 | V7: 2025
B8: Organic growth % | C8: =IFERROR(Model!C109+0,0) -> 0 | D8: =IFERROR(Model!D109+0,0) -> 0 | E8: =IFERROR(Model!E109+0,0) -> 0 | F8: =IFERROR(Model!F109+0,0) -> 0 | G8: =IFERROR(Model!G109+0,0) -> 0 | H8: =IFERROR(Model!H109+0,0) -> 0 | I8: =IFERROR(Model!I109+0,0) -> 0.04 | J8: =IFERROR(Model!N109+0,0) -> 0.03 | K8: =IFERROR(Model!S109+0,0) -> 0.04 | L8: =IFERROR(Model!X109+0,0) -> 0.05 | M8: =IFERROR(Model!AC109+0,0) -> 0.04 | N8: =IFERROR(Model!AH109+0,0) -> 0.05 | O8: =IFERROR(Model!AM109+0,0) -> 0.08 | P8: =IFERROR(Model!AR109+0,0) -> 0.06 | Q8: =IFERROR(Model!AW109+0,0) -> 0.25 | R8: =IFERROR(Model!BB109+0,0) -> 0.17 | S8: =IFERROR(Model!BG109+0,0) -> 0 | T8: =IFERROR(Model!BL109+0,0) -> -0.05 | U8: =IFERROR(Model!BQ109+0,0) -> 0 | V8: =IFERROR(Model!BV109+0,0) -> 0.02
B9: Acquisitions / divestitures % | C9: =IFERROR(Model!C110+0,0) -> 0 | D9: =IFERROR(Model!D110+0,0) -> 0 | E9: =IFERROR(Model!E110+0,0) -> 0 | F9: =IFERROR(Model!F110+0,0) -> 0 | G9: =IFERROR(Model!G110+0,0) -> 0 | H9: =IFERROR(Model!H110+0,0) -> 0 | I9: =IFERROR(Model!I110+0,0) -> 0 | J9: =IFERROR(Model!N110+0,0) -> 0.02 | K9: =IFERROR(Model!S110+0,0) -> 0.25 | L9: =IFERROR(Model!X110+0,0) -> 0.01 | M9: =IFERROR(Model!AC110+0,0) -> 0.04 | N9: =IFERROR(Model!AH110+0,0) -> 0.09 | O9: =IFERROR(Model!AM110+0,0) -> 0.07 | P9: =IFERROR(Model!AR110+0,0) -> 0 | Q9: =IFERROR(Model!AW110+0,0) -> 0 | R9: =IFERROR(Model!BB110+0,0) -> 0.02 | S9: =IFERROR(Model!BG110+0,0) -> 0.18 | T9: =IFERROR(Model!BL110+0,0) -> 0.01 | U9: =IFERROR(Model!BQ110+0,0) -> 0 | V9: =IFERROR(Model!BV110+0,0) -> 0.01
B10: Currency translation % | C10: =IFERROR(Model!C111+0,0) -> 0 | D10: =IFERROR(Model!D111+0,0) -> 0 | E10: =IFERROR(Model!E111+0,0) -> 0 | F10: =IFERROR(Model!F111+0,0) -> 0 | G10: =IFERROR(Model!G111+0,0) -> 0 | H10: =IFERROR(Model!H111+0,0) -> 0 | I10: =IFERROR(Model!I111+0,0) -> -0.02 | J10: =IFERROR(Model!N111+0,0) -> 0 | K10: =IFERROR(Model!S111+0,0) -> 0 | L10: =IFERROR(Model!X111+0,0) -> -0.06 | M10: =IFERROR(Model!AC111+0,0) -> -0.01 | N10: =IFERROR(Model!AH111+0,0) -> 0 | O10: =IFERROR(Model!AM111+0,0) -> 0.01 | P10: =IFERROR(Model!AR111+0,0) -> -0.02 | Q10: =IFERROR(Model!AW111+0,0) -> 0.01 | R10: =IFERROR(Model!BB111+0,0) -> 0.02 | S10: =IFERROR(Model!BG111+0,0) -> -0.03 | T10: =IFERROR(Model!BL111+0,0) -> 0 | U10: =IFERROR(Model!BQ111+0,0) -> 0 | V10: =IFERROR(Model!BV111+0,0) -> 0.01
C11: =C7 -> 2006 | D11: =D7 -> 2007 | E11: =E7 -> 2008 | F11: =F7 -> 2009 | G11: =G7 -> 2010 | H11: =H7 -> 2011 | I11: =I7 -> 2012 | J11: =J7 -> 2013 | ... V11: =V7 -> 2025
B12: Adjusted operating income | C12: =Model!C186 -> 572.869 | D12: =Model!D186 -> 1636.9 | E12: =Model!E186 -> 1869.1 | F12: =Model!F186 -> 1714.9 | G12: =Model!G186 -> 1916 | H12: =Model!H186 -> 2127.8 | I12: =Model!I186 -> 2379.9 | J12: =Model!N186 -> 2552.5 | K12: =Model!S186 -> 3694.8 | L12: =Model!X186 -> 3821.7 | M12: =Model!AC186 -> 4221.8 | N12: =Model!AH186 -> 4860 | O12: =Model!AM186 -> 5615 | P12: =Model!AR186 -> 5973 | Q12: =Model!AW186 -> 9556 | R12: =Model!BB186 -> 12138 | S12: =Model!BG186 -> 10985 | T12: =Model!BL186 -> 9810 | U12: =Model!BQ186 -> 9707 | V12: =Model!BV186 -> 10110
B13: Operating income (GAAP) | C13: =Model!C145 -> 241.959 | D13: =Model!D145 -> 974.4 | E13: =Model!E145 -> 1229.4 | F13: =Model!F145 -> 1048.9 | G13: =Model!G145 -> 1264.9 | H13: =Model!H145 -> 1245.2 | I13: =Model!I145 -> 1482.1 | J13: =Model!N145 -> 1609.6 | K13: =Model!S145 -> 2503 | L13: =Model!X145 -> 2336.2 | M13: =Model!AC145 -> 2449.2 | N13: =Model!AH145 -> 2968 | O13: =Model!AM145 -> 3783 | P13: =Model!AR145 -> 4594 | Q13: =Model!AW145 -> 7794 | R13: =Model!BB145 -> 10028 | S13: =Model!BG145 -> 8393 | T13: =Model!BL145 -> 6859 | U13: =Model!BQ145 -> 7337 | V13: =Model!BV145 -> 7747
B14: Adj. operating margin % | C14: =Model!C187 -> 0.15108831 | D14: =Model!D187 -> 0.16794919 | E14: =Model!E187 -> 0.17804344 | F14: =Model!F187 -> 0.16962917 | G14: =Model!G187 -> 0.17759322 | H14: =Model!H187 -> 0.18146155 | I14: =Model!I187 -> 0.19024133 | J14: =Model!N187 -> 0.19499171 | K14: =Model!S187 -> 0.21876184 | L14: =Model!X187 -> 0.22526436 | M14: =Model!AC187 -> 0.23102643 | N14: =Model!AH187 -> 0.23233579 | O14: =Model!AM187 -> 0.23051975 | P14: =Model!AR187 -> 0.23385013 | Q14: =Model!AW187 -> 0.29660438 | R14: =Model!BB187 -> 0.30955599 | S14: =Model!BG187 -> 0.24457308 | T14: =Model!BL187 -> 0.22890076 | U14: =Model!BQ187 -> 0.22638121 | V14: =Model!BV187 -> 0.22690547
B15: GAAP op. margin % | C15: =Model!C147 -> 0.063814199 | D15: =Model!D147 -> 0.099975376 | E15: =Model!E147 -> 0.11710802 | F15: =Model!F147 -> 0.10375184 | G15: =Model!G147 -> 0.11724304 | H15: =Model!H147 -> 0.10619228 | I15: =Model!I147 -> 0.11847417 | J15: =Model!N147 -> 0.12296128 | K15: =Model!S147 -> 0.14819771 | L15: =Model!X147 -> 0.1377038 | M15: =Model!AC147 -> 0.13402575 | N15: =Model!AH147 -> 0.14188737 | O15: =Model!AM147 -> 0.15530832 | P15: =Model!AR147 -> 0.17986062 | Q15: =Model!AW147 -> 0.24191446 | R15: =Model!BB147 -> 0.25574456 | S15: =Model!BG147 -> 0.18686408 | T15: =Model!BL147 -> 0.16004387 | U15: =Model!BQ147 -> 0.1711094 | V15: =Model!BV147 -> 0.17387108
C17: =C7 -> 2006 | D17: =D7 -> 2007 | E17: =E7 -> 2008 | F17: =F7 -> 2009 | G17: =G7 -> 2010 | H17: =H7 -> 2011 | I17: =I7 -> 2012 | J17: =J7 -> 2013 | ... V17: =V7 -> 2025
B18: ROIC | C18: =IFERROR(Model!C378+0,NA()) -> 0.02583209 | D18: =IFERROR(Model!D378+0,NA()) -> 0.077538468 | E18: =IFERROR(Model!E378+0,NA()) -> 0.091644539 | F18: =IFERROR(Model!F378+0,NA()) -> 0.085480968 | G18: =IFERROR(Model!G378+0,NA()) -> 0.091628291 | H18: =IFERROR(Model!H378+0,NA()) -> 0.081760611 | I18: =IFERROR(Model!I378+0,NA()) -> 0.091180731 | J18: =IFERROR(Model!N378+0,NA()) -> 0.10120817 | K18: =IFERROR(Model!S378+0,NA()) -> 0.093573781 | L18: =IFERROR(Model!X378+0,NA()) -> 0.098538808 | M18: =IFERROR(Model!AC378+0,NA()) -> 0.097302557 | N18: =IFERROR(Model!AH378+0,NA()) -> 0.093760905 | O18: =IFERROR(Model!AM378+0,NA()) -> 0.11126051 | P18: =IFERROR(Model!AR378+0,NA()) -> 0.11799351 | Q18: =IFERROR(Model!AW378+0,NA()) -> 0.17845579 | R18: =IFERROR(Model!BB378+0,NA()) -> 0.14529515 | S18: =IFERROR(Model!BG378+0,NA()) -> 0.13624616 | T18: =IFERROR(Model!BL378+0,NA()) -> 0.11983862 | U18: =IFERROR(Model!BQ378+0,NA()) -> 0.11525394 | V18: =IFERROR(Model!BV378+0,NA()) -> 0.1093851
B19: RONTA | C19: =IFERROR(Model!C389+0,NA()) -> 0.11537017 | D19: =IFERROR(Model!D389+0,NA()) -> 0.34782322 | E19: =IFERROR(Model!E389+0,NA()) -> 0.32227416 | F19: =IFERROR(Model!F389+0,NA()) -> 0.28812534 | G19: =IFERROR(Model!G389+0,NA()) -> 0.34211405 | H19: =IFERROR(Model!H389+0,NA()) -> 0.33005197 | I19: =IFERROR(Model!I389+0,NA()) -> 0.39240701 | J19: =IFERROR(Model!N389+0,NA()) -> 0.21404652 | K19: =IFERROR(Model!S389+0,NA()) -> 0.48641336 | L19: =IFERROR(Model!X389+0,NA()) -> 0.51815547 | M19: =IFERROR(Model!AC389+0,NA()) -> 0.51854284 | N19: =IFERROR(Model!AH389+0,NA()) -> 0.43339185 | O19: =IFERROR(Model!AM389+0,NA()) -> 0.45378655 | P19: =IFERROR(Model!AR389+0,NA()) -> 0.4107152 | Q19: =IFERROR(Model!AW389+0,NA()) -> 0.36177283 | R19: =IFERROR(Model!BB389+0,NA()) -> 0.47246741 | S19: =IFERROR(Model!BG389+0,NA()) -> 0.35226946 | T19: =IFERROR(Model!BL389+0,NA()) -> 0.31954364 | U19: =IFERROR(Model!BQ389+0,NA()) -> 0.3500482 | V19: =IFERROR(Model!BV389+0,NA()) -> 0.27050992
B20: Adj. operating margin % | C20: =IFERROR(Model!C187+0,NA()) -> 0.15108831 | D20: =IFERROR(Model!D187+0,NA()) -> 0.16794919 | E20: =IFERROR(Model!E187+0,NA()) -> 0.17804344 | F20: =IFERROR(Model!F187+0,NA()) -> 0.16962917 | G20: =IFERROR(Model!G187+0,NA()) -> 0.17759322 | H20: =IFERROR(Model!H187+0,NA()) -> 0.18146155 | I20: =IFERROR(Model!I187+0,NA()) -> 0.19024133 | J20: =IFERROR(Model!N187+0,NA()) -> 0.19499171 | K20: =IFERROR(Model!S187+0,NA()) -> 0.21876184 | L20: =IFERROR(Model!X187+0,NA()) -> 0.22526436 | M20: =IFERROR(Model!AC187+0,NA()) -> 0.23102643 | N20: =IFERROR(Model!AH187+0,NA()) -> 0.23233579 | O20: =IFERROR(Model!AM187+0,NA()) -> 0.23051975 | P20: =IFERROR(Model!AR187+0,NA()) -> 0.23385013 | Q20: =IFERROR(Model!AW187+0,NA()) -> 0.29660438 | R20: =IFERROR(Model!BB187+0,NA()) -> 0.30955599 | S20: =IFERROR(Model!BG187+0,NA()) -> 0.24457308 | T20: =IFERROR(Model!BL187+0,NA()) -> 0.22890076 | U20: =IFERROR(Model!BQ187+0,NA()) -> 0.22638121 | V20: =IFERROR(Model!BV187+0,NA()) -> 0.22690547
B21: FCF margin % | C21: =IFERROR(Model!C273+0,NA()) -> 0.088748415 | D21: =IFERROR(Model!D273+0,NA()) -> 0.13634778 | E21: =IFERROR(Model!E273+0,NA()) -> 0.11171652 | F21: =IFERROR(Model!F273+0,NA()) -> 0.14502903 | G21: =IFERROR(Model!G273+0,NA()) -> 0.11523168 | H21: =IFERROR(Model!H273+0,NA()) -> 0.12110797 | I21: =IFERROR(Model!I273+0,NA()) -> 0.14113622 | J21: =IFERROR(Model!N273+0,NA()) -> 0.13398471 | K21: =IFERROR(Model!S273+0,NA()) -> 0.13295756 | L21: =IFERROR(Model!X273+0,NA()) -> 0.14269042 | M21: =IFERROR(Model!AC273+0,NA()) -> 0.14994993 | N21: =IFERROR(Model!AH273+0,NA()) -> 0.16755904 | O21: =IFERROR(Model!AM273+0,NA()) -> 0.15744314 | P21: =IFERROR(Model!AR273+0,NA()) -> 0.15985436 | Q21: =IFERROR(Model!AW273+0,NA()) -> 0.21177603 | R21: =IFERROR(Model!BB273+0,NA()) -> 0.17954146 | S21: =IFERROR(Model!BG273+0,NA()) -> 0.15440276 | T21: =IFERROR(Model!BL273+0,NA()) -> 0.16366055 | U21: =IFERROR(Model!BQ273+0,NA()) -> 0.17080622 | V21: =IFERROR(Model!BV273+0,NA()) -> 0.14222551
