Workbook

Sheet Model
BB1: SCENARIO SWITCH ▼ (Bull / Base / Bear) — drives all scenario-linked forecast drivers
B2: Uber Technologies, Inc. (NYSE: UBER) — 3-Statement Financial Model | BB2: Base
B3: US GAAP as reported · USD millions (per-share data in USD; Gross Bookings in USD millions; MAPCs, trips and shares in millions) · Source: Uber Form S-1 (Apr-2019), Forms 10-K / 10-Q and Form 8-K earnings releases (Ex. 99.1), Jan-2026 recast 8-K, deal 8-Ks (Delivery Hero 16-Jul-2026; term loan 6-Aug-2026; € notes 15-Sep-2026), SEC EDGAR CIK 0001543151 (investor.uber.com releases are the same documents as filed on EDGAR)
B4: Basis notes: calendar fiscal year. IPO 10-May-2019 (pre-IPO EPS on pre-conversion common shares). 2018–19 revenue as originally reported (2020 10-K restated FY18/FY19 for excess Driver payments; no operating-income impact). Interest income shown separately for all periods (2026 presentation). Segments: Core Platform / Other Bets (2016–Q2/19) → Rides / Eats / Freight / Other Bets / ATG (Q3/19) → Mobility / Delivery / Freight (2020+); segment measure Segment Adjusted EBITDA to Q4/25, Segment Operating Income from Q1/26 (recast to Q1/24). Uber China discontinued 2016; Postmates Dec-2020; ATG sold Jan-2021; Transplace Nov-2021; Trendyol Go Jun-2025; Delivery Hero (BCA 16-Jul-2026) modelled as consolidated from an assumed 1-Oct-2027 closing (switch in scenario table) — excluded from company outlook.
BD5: Forecast | BE5: Historical | BF5: Historical | BG5: Historical
B6: (USDm) | C6: 2016 | D6: 2017 | E6: Q1/18 | F6: Q2/18 | G6: Q3/18 | H6: Q4/18 | I6: 2018 | J6: Q1/19 | K6: Q2/19 | L6: Q3/19 | M6: Q4/19 | N6: 2019 | O6: Q1/20 | P6: Q2/20 | Q6: Q3/20 | R6: Q4/20 | S6: 2020 | T6: Q1/21 | U6: Q2/21 | V6: Q3/21 | W6: Q4/21 | X6: 2021 | Y6: Q1/22 | Z6: Q2/22 | AA6: Q3/22 | AB6: Q4/22 | AC6: 2022 | AD6: Q1/23 | AE6: Q2/23 | AF6: Q3/23 | AG6: Q4/23 | AH6: 2023 | AI6: Q1/24 | AJ6: Q2/24 | AK6: Q3/24 | AL6: Q4/24 | AM6: 2024 | AN6: Q1/25 | AO6: Q2/25 | AP6: Q3/25 | AQ6: Q4/25 | AR6: 2025 | AS6: Q1/26 | AT6: Q2/26 | AU6: Q3/26E | AV6: Q4/26E | AW6: 2026E | AX6: 2027E | AY6: 2028E | AZ6: 2029E | BA6: 2030E | BB6: Modelling Notes | BD6: 5Y CAGR | BE6: 5Y CAGR | BF6: 7Y CAGR | BG6: 9Y CAGR
BD7: 25-'30 | BE7: 20-'25 | BF7: 18-'25 | BG7: 16-'25
B8: PLATFORM & SEGMENT BUILD — MOBILITY · DELIVERY · FREIGHT (Gross Bookings → revenue → Segment Operating Income → Non-GAAP Operating Income → Adjusted EBITDA) | BB8: PLATFORM & SEGMENT BUILD — modelling logic (Gross Bookings × take rate → revenue; Segment Operating Income = GB × margin, incremental margin on ΔGB from 2027E)
BJ9: SCENARIO INPUT TABLE — driver assumptions per Bull / Base / Bear | BK9: Bull | BL9: Base | BM9: Bear | BN9: Bull / Bear = Base + Δ (Δ inputs on each block header). Outlook block = high / mid / low end of the Q3-26 ranges.
B10: Platform key metrics (company-reported; Uber standalone — Delivery Hero metrics not added) | BB10: PLATFORM KPIs — trips = Gross Bookings ÷ GB per trip; MAPCs = trips ÷ (monthly frequency × months)
B11: Monthly Active Platform Consumers — MAPCs (m; quarter = monthly average; FY = Q4) | C11: 45 | D11: 68 | E11: 70 | F11: 76 | G11: 82 | H11: 91 | I11: 91 | J11: 93 | K11: 99 | L11: 103 | M11: 111 | N11: 111 | O11: 103 | P11: 55 | Q11: 78 | R11: 93 | S11: 93 | T11: 98 | U11: 101 | V11: 109 | W11: 118 | X11: 118 | Y11: 115 | Z11: 122 | AA11: 124 | AB11: 131 | AC11: 131 | AD11: 130 | AE11: 137 | AF11: 142 | AG11: 150 | AH11: 150 | AI11: 149 | AJ11: 156 | AK11: 161 | AL11: 171 | AM11: 171 | AN11: 170 | AO11: 180 | AP11: 189 | AQ11: 202 | AR11: 202 | AS11: 199 | AT11: 208 | AU11: =AU13/(AU15*3) | AV11: =AV13/(AV15*3) | AW11: =AV11 | AX11: =AW11*(AX13/AW13)/(AX15/AW15) | AY11: =AX11*(AY13/AX13)/(AY15/AX15) | AZ11: =AY11*(AZ13/AY13)/(AZ15/AY15) | BA11: =AZ11*(BA13/AZ13)/(BA15/AZ15) | BB11: Q3/Q4-26E: trips ÷ (frequency × 3). 2027E+: grows with trips ÷ frequency (Q4 basis). | BD11: =IFERROR((BA11/AR11)^(1/5)-1,"") | BE11: =IFERROR((AR11/S11)^(1/5)-1,"") | BF11: =IFERROR((AR11/I11)^(1/7)-1,"") | BG11: =IFERROR((AR11/C11)^(1/9)-1,"") | BJ11: Q3-26 outlook — Q2-26 release (5-Aug-26); Uber standalone, excludes Delivery Hero | BK11: High | BL11: Mid | BM11: Low | BN11: Uber guides one quarter ahead: Gross Bookings and Non-GAAP EPS (with an Adjusted EBITDA translation).
B12: MAPCs y/y % | D12: =IF(AND(ISNUMBER(D11),ISNUMBER(C11)),IFERROR(D11/C11-1,""),"") | I12: =IF(AND(ISNUMBER(I11),ISNUMBER(D11)),IFERROR(I11/D11-1,""),"") | J12: =IF(AND(ISNUMBER(J11),ISNUMBER(E11)),IFERROR(J11/E11-1,""),"") | K12: =IF(AND(ISNUMBER(K11),ISNUMBER(F11)),IFERROR(K11/F11-1,""),"") | L12: =IF(AND(ISNUMBER(L11),ISNUMBER(G11)),IFERROR(L11/G11-1,""),"") | M12: =IF(AND(ISNUMBER(M11),ISNUMBER(H11)),IFERROR(M11/H11-1,""),"") | N12: =IF(AND(ISNUMBER(N11),ISNUMBER(I11)),IFERROR(N11/I11-1,""),"") | O12: =IF(AND(ISNUMBER(O11),ISNUMBER(J11)),IFERROR(O11/J11-1,""),"") | P12: =IF(AND(ISNUMBER(P11),ISNUMBER(K11)),IFERROR(P11/K11-1,""),"") | ... AT12: =IF(AND(ISNUMBER(AT11),ISNUMBER(AO11)),IFERROR(AT11/AO11-1,""),"") | AU12: =IFERROR(AU11/AP11-1,"") | AV12: =IFERROR(AV11/AQ11-1,"") | AW12: =IFERROR(AW11/AR11-1,"") | AX12: =IFERROR(AX11/AW11-1,"") | AY12: =IFERROR(AY11/AX11-1,"") | AZ12: =IFERROR(AZ11/AY11-1,"") | BA12: =IFERROR(BA11/AZ11-1,"") | BJ12: Q3-26 Gross Bookings ($m) | BK12: 60250 | BL12: 59250 | BM12: 58250 | BN12: +18–22% y/y constant currency; ~1pp FX headwind.
B13: Trips (m) | C13: 1818 | D13: 3736 | E13: 1136 | F13: 1242 | G13: 1348 | H13: 1493 | I13: 5220 | J13: 1550 | K13: 1677 | L13: 1770 | M13: 1907 | N13: 6904 | O13: 1661 | P13: 737 | Q13: 1184 | R13: 1443 | S13: 5025 | T13: 1447 | U13: 1511 | V13: 1641 | W13: 1769 | X13: 6368 | Y13: 1713 | Z13: 1872 | AA13: 1953 | AB13: 2104 | AC13: 7642 | AD13: 2124 | AE13: 2282 | AF13: 2441 | AG13: 2601 | AH13: 9448 | AI13: 2572 | AJ13: 2765 | AK13: 2868 | AL13: 3068 | AM13: 11273 | AN13: 3036 | AO13: 3268 | AP13: 3512 | AQ13: 3751 | AR13: 13567 | AS13: 3643 | AT13: 3867 | AU13: =AU19/AU17 | AV13: =AV19/AV17 | AW13: =SUM(AS13,AT13,AU13,AV13) | AX13: =AX19/AX17 | AY13: =AY19/AY17 | AZ13: =AZ19/AZ17 | BA13: =BA19/BA17 | BD13: =IFERROR((BA13/AR13)^(1/5)-1,"") | BE13: =IFERROR((AR13/S13)^(1/5)-1,"") | BF13: =IFERROR((AR13/I13)^(1/7)-1,"") | BG13: =IFERROR((AR13/C13)^(1/9)-1,"") | BJ13: Q3-26 Adjusted EBITDA translation ($m) | BK13: 2960 | BL13: 2910 | BM13: 2860 | BN13: Drives the Q3/Q4-26E segment-margin calibration.
B14: Trips y/y % | D14: =IF(AND(ISNUMBER(D13),ISNUMBER(C13)),IFERROR(D13/C13-1,""),"") | I14: =IF(AND(ISNUMBER(I13),ISNUMBER(D13)),IFERROR(I13/D13-1,""),"") | J14: =IF(AND(ISNUMBER(J13),ISNUMBER(E13)),IFERROR(J13/E13-1,""),"") | K14: =IF(AND(ISNUMBER(K13),ISNUMBER(F13)),IFERROR(K13/F13-1,""),"") | L14: =IF(AND(ISNUMBER(L13),ISNUMBER(G13)),IFERROR(L13/G13-1,""),"") | M14: =IF(AND(ISNUMBER(M13),ISNUMBER(H13)),IFERROR(M13/H13-1,""),"") | N14: =IF(AND(ISNUMBER(N13),ISNUMBER(I13)),IFERROR(N13/I13-1,""),"") | O14: =IF(AND(ISNUMBER(O13),ISNUMBER(J13)),IFERROR(O13/J13-1,""),"") | P14: =IF(AND(ISNUMBER(P13),ISNUMBER(K13)),IFERROR(P13/K13-1,""),"") | ... AT14: =IF(AND(ISNUMBER(AT13),ISNUMBER(AO13)),IFERROR(AT13/AO13-1,""),"") | AU14: =IFERROR(AU13/AP13-1,"") | AV14: =IFERROR(AV13/AQ13-1,"") | AW14: =IFERROR(AW13/AR13-1,"") | AX14: =IFERROR(AX13/AW13-1,"") | AY14: =IFERROR(AY13/AX13-1,"") | AZ14: =IFERROR(AZ13/AY13-1,"") | BA14: =IFERROR(BA13/AZ13-1,"") | BJ14: Q3-26 Non-GAAP EPS ($) | BK14: 0.88 | BL14: 0.86 | BM14: 0.84 | BN14: +28–35% y/y (memo; compared with the model).
B15: Monthly trips per MAPC (x) | E15: =IFERROR(E13/E11/3,"") | F15: =IFERROR(F13/F11/3,"") | G15: =IFERROR(G13/G11/3,"") | H15: =IFERROR(H13/H11/3,"") | I15: =IFERROR(I13/AVERAGE(E11,F11,G11,H11)/12,"") | J15: =IFERROR(J13/J11/3,"") | K15: =IFERROR(K13/K11/3,"") | L15: =IFERROR(L13/L11/3,"") | M15: =IFERROR(M13/M11/3,"") | N15: =IFERROR(N13/AVERAGE(J11,K11,L11,M11)/12,"") | O15: =IFERROR(O13/O11/3,"") | P15: =IFERROR(P13/P11/3,"") | Q15: =IFERROR(Q13/Q11/3,"") | R15: =IFERROR(R13/R11/3,"") | S15: =IFERROR(S13/AVERAGE(O11,P11,Q11,R11)/12,"") | T15: =IFERROR(T13/T11/3,"") | U15: =IFERROR(U13/U11/3,"") | V15: =IFERROR(V13/V11/3,"") | W15: =IFERROR(W13/W11/3,"") | X15: =IFERROR(X13/AVERAGE(T11,U11,V11,W11)/12,"") | Y15: =IFERROR(Y13/Y11/3,"") | Z15: =IFERROR(Z13/Z11/3,"") | AA15: =IFERROR(AA13/AA11/3,"") | AB15: =IFERROR(AB13/AB11/3,"") | AC15: =IFERROR(AC13/AVERAGE(Y11,Z11,AA11,AB11)/12,"") | AD15: =IFERROR(AD13/AD11/3,"") | AE15: =IFERROR(AE13/AE11/3,"") | AF15: =IFERROR(AF13/AF11/3,"") | AG15: =IFERROR(AG13/AG11/3,"") | AH15: =IFERROR(AH13/AVERAGE(AD11,AE11,AF11,AG11)/12,"") | AI15: =IFERROR(AI13/AI11/3,"") | AJ15: =IFERROR(AJ13/AJ11/3,"") | AK15: =IFERROR(AK13/AK11/3,"") | AL15: =IFERROR(AL13/AL11/3,"") | AM15: =IFERROR(AM13/AVERAGE(AI11,AJ11,AK11,AL11)/12,"") | AN15: =IFERROR(AN13/AN11/3,"") | AO15: =IFERROR(AO13/AO11/3,"") | AP15: =IFERROR(AP13/AP11/3,"") | AQ15: =IFERROR(AQ13/AQ11/3,"") | AR15: =IFERROR(AR13/AVERAGE(AN11,AO11,AP11,AQ11)/12,"") | AS15: =IFERROR(AS13/AS11/3,"") | AT15: =IFERROR(AT13/AT11/3,"") | AU15: =AP15*($AT$15/$AO$15) | AV15: =AQ15*($AT$15/$AO$15) | AW15: =IFERROR(AW13/AVERAGE(AS11,AT11,AU11,AV11)/12,"") | AX15: =AW15*(1+AX16) | AY15: =AX15*(1+AY16) | AZ15: =AY15*(1+AZ16) | BA15: =AZ15*(1+BA16) | BB15: Q3/Q4-26E: prior-year quarter × Q2/26 y/y change. 2027E+: prior year × (1 + frequency growth input). | BJ15: Point estimates, switches & capital allocation
B16: Monthly trips per MAPC y/y % | D16: =IF(AND(ISNUMBER(D15),ISNUMBER(C15)),IFERROR(D15/C15-1,""),"") | I16: =IF(AND(ISNUMBER(I15),ISNUMBER(D15)),IFERROR(I15/D15-1,""),"") | J16: =IF(AND(ISNUMBER(J15),ISNUMBER(E15)),IFERROR(J15/E15-1,""),"") | K16: =IF(AND(ISNUMBER(K15),ISNUMBER(F15)),IFERROR(K15/F15-1,""),"") | L16: =IF(AND(ISNUMBER(L15),ISNUMBER(G15)),IFERROR(L15/G15-1,""),"") | M16: =IF(AND(ISNUMBER(M15),ISNUMBER(H15)),IFERROR(M15/H15-1,""),"") | N16: =IF(AND(ISNUMBER(N15),ISNUMBER(I15)),IFERROR(N15/I15-1,""),"") | O16: =IF(AND(ISNUMBER(O15),ISNUMBER(J15)),IFERROR(O15/J15-1,""),"") | P16: =IF(AND(ISNUMBER(P15),ISNUMBER(K15)),IFERROR(P15/K15-1,""),"") | ... AT16: =IF(AND(ISNUMBER(AT15),ISNUMBER(AO15)),IFERROR(AT15/AO15-1,""),"") | AU16: =IFERROR(AU15/AP15-1,"") | AV16: =IFERROR(AV15/AQ15-1,"") | AW16: =IFERROR(AW15/AR15-1,"") | AX16: 0.015 | AY16: 0.015 | AZ16: 0.015 | BA16: 0.015 | BB16: 2027E+ input: +1.5% p.a. (Q2/26 +2%; cross-platform users and Uber One membership lift engagement). | BJ16: Q3/Q4-26E tax rate (Non-GAAP & GAAP) | BK16: =BL16 | BL16: 0.24 | BM16: =BL16 | BN16: 1H/26 Non-GAAP ETR 24%.
B17: Gross Bookings per trip ($) | C17: =IF(AND(ISNUMBER(C19),ISNUMBER(C13)),IFERROR(C19/C13,""),"") | D17: =IF(AND(ISNUMBER(D19),ISNUMBER(D13)),IFERROR(D19/D13,""),"") | E17: =IF(AND(ISNUMBER(E19),ISNUMBER(E13)),IFERROR(E19/E13,""),"") | F17: =IF(AND(ISNUMBER(F19),ISNUMBER(F13)),IFERROR(F19/F13,""),"") | G17: =IF(AND(ISNUMBER(G19),ISNUMBER(G13)),IFERROR(G19/G13,""),"") | H17: =IF(AND(ISNUMBER(H19),ISNUMBER(H13)),IFERROR(H19/H13,""),"") | I17: =IF(AND(ISNUMBER(I19),ISNUMBER(I13)),IFERROR(I19/I13,""),"") | J17: =IF(AND(ISNUMBER(J19),ISNUMBER(J13)),IFERROR(J19/J13,""),"") | ... AT17: =IF(AND(ISNUMBER(AT19),ISNUMBER(AT13)),IFERROR(AT19/AT13,""),"") | AU17: =AP17*($AT$17/$AO$17) | AV17: =AQ17*($AT$17/$AO$17) | AW17: =IFERROR(AW19/AW13,"") | AX17: =AW17*(1+AX18) | AY17: =AX17*(1+AY18) | AZ17: =AY17*(1+AZ18) | BA17: =AZ17*(1+BA18) | BJ17: USD per EUR (deal-implied) | BK17: =BL17 | BL17: =14800/(314*41.5) | BM17: =BL17 | BN17: $14.8bn equity value ÷ (314m shares × €41.50) = 1.136.
B18: Gross Bookings per trip y/y % | D18: =IF(AND(ISNUMBER(D17),ISNUMBER(C17)),IFERROR(D17/C17-1,""),"") | I18: =IF(AND(ISNUMBER(I17),ISNUMBER(D17)),IFERROR(I17/D17-1,""),"") | J18: =IF(AND(ISNUMBER(J17),ISNUMBER(E17)),IFERROR(J17/E17-1,""),"") | K18: =IF(AND(ISNUMBER(K17),ISNUMBER(F17)),IFERROR(K17/F17-1,""),"") | L18: =IF(AND(ISNUMBER(L17),ISNUMBER(G17)),IFERROR(L17/G17-1,""),"") | M18: =IF(AND(ISNUMBER(M17),ISNUMBER(H17)),IFERROR(M17/H17-1,""),"") | N18: =IF(AND(ISNUMBER(N17),ISNUMBER(I17)),IFERROR(N17/I17-1,""),"") | O18: =IF(AND(ISNUMBER(O17),ISNUMBER(J17)),IFERROR(O17/J17-1,""),"") | P18: =IF(AND(ISNUMBER(P17),ISNUMBER(K17)),IFERROR(P17/K17-1,""),"") | ... AT18: =IF(AND(ISNUMBER(AT17),ISNUMBER(AO17)),IFERROR(AT17/AO17-1,""),"") | AU18: =IFERROR(AU17/AP17-1,"") | AV18: =IFERROR(AV17/AQ17-1,"") | AW18: =IFERROR(AW17/AR17-1,"") | AX18: 0.02 | AY18: 0.02 | AZ18: 0.02 | BA18: 0.02 | BB18: 2027E+ input: +2.0% p.a. (pricing / mix; Q2/26 +4.9% incl. FX). | BJ18: 2H/26 share repurchases ($m) | BK18: 3000 | BL18: 1500 | BM18: 500 | BN18: 1H/26 $3.5bn (Q1 $3.0bn, Q2 $0.5bn after the Delivery Hero announcement).
B19: Gross Bookings — Uber standalone (Mobility + Delivery + Freight + Other Bets) | C19: =N(C24)+N(C36)+N(C48)+N(C55)+N(C58) | D19: =N(D24)+N(D36)+N(D48)+N(D55)+N(D58) | E19: =N(E24)+N(E36)+N(E48)+N(E55)+N(E58) | F19: =N(F24)+N(F36)+N(F48)+N(F55)+N(F58) | G19: =N(G24)+N(G36)+N(G48)+N(G55)+N(G58) | H19: =N(H24)+N(H36)+N(H48)+N(H55)+N(H58) | I19: =N(I24)+N(I36)+N(I48)+N(I55)+N(I58) | J19: =N(J24)+N(J36)+N(J48)+N(J55)+N(J58) | ... AT19: =N(AT24)+N(AT36)+N(AT48)+N(AT55)+N(AT58) | AU19: =N(AU24)+N(AU36)+N(AU48) | AV19: =N(AV24)+N(AV36)+N(AV48) | AW19: =N(AW24)+N(AW36)+N(AW48) | AX19: =N(AX24)+N(AX36)+N(AX48) | AY19: =N(AY24)+N(AY36)+N(AY48) | AZ19: =N(AZ24)+N(AZ36)+N(AZ48) | BA19: =N(BA24)+N(BA36)+N(BA48) | BD19: =IFERROR((BA19/AR19)^(1/5)-1,"") | BE19: =IFERROR((AR19/S19)^(1/5)-1,"") | BF19: =IFERROR((AR19/I19)^(1/7)-1,"") | BG19: =IFERROR((AR19/C19)^(1/9)-1,"") | BJ19: Delivery Hero consolidation switch (1 = on, 0 = Uber standalone) | BK19: =BL19 | BL19: 1 | BM19: =BL19 | BN19: All scenarios. 0 removes the deal (no consolidation, no consideration).
B20: Gross Bookings y/y % (reported) | D20: =IF(AND(ISNUMBER(D19),ISNUMBER(C19)),IFERROR(D19/C19-1,""),"") | I20: =IF(AND(ISNUMBER(I19),ISNUMBER(D19)),IFERROR(I19/D19-1,""),"") | J20: =IF(AND(ISNUMBER(J19),ISNUMBER(E19)),IFERROR(J19/E19-1,""),"") | K20: =IF(AND(ISNUMBER(K19),ISNUMBER(F19)),IFERROR(K19/F19-1,""),"") | L20: =IF(AND(ISNUMBER(L19),ISNUMBER(G19)),IFERROR(L19/G19-1,""),"") | M20: =IF(AND(ISNUMBER(M19),ISNUMBER(H19)),IFERROR(M19/H19-1,""),"") | N20: =IF(AND(ISNUMBER(N19),ISNUMBER(I19)),IFERROR(N19/I19-1,""),"") | O20: =IF(AND(ISNUMBER(O19),ISNUMBER(J19)),IFERROR(O19/J19-1,""),"") | P20: =IF(AND(ISNUMBER(P19),ISNUMBER(K19)),IFERROR(P19/K19-1,""),"") | ... AT20: =IF(AND(ISNUMBER(AT19),ISNUMBER(AO19)),IFERROR(AT19/AO19-1,""),"") | AU20: =IFERROR(AU19/AP19-1,"") | AV20: =IFERROR(AV19/AQ19-1,"") | AW20: =IFERROR(AW19/AR19-1,"") | AX20: =IFERROR(AX19/AW19-1,"") | AY20: =IFERROR(AY19/AX19-1,"") | AZ20: =IFERROR(AZ19/AY19-1,"") | BA20: =IFERROR(BA19/AZ19-1,"") | BJ20: Delivery Hero: Uber ownership after the offer | BK20: =BL20 | BL20: 0.75 | BM20: =BL20 | BN20: Committed ~53% incl. Prosus; assumes ~half of the free float tenders.
B21: Memo: Gross Bookings y/y % at constant currency (company) | J21: 0.41 | K21: 0.37 | L21: 0.32 | M21: 0.3 | N21: 0.35 | O21: 0.1 | P21: -0.32 | Q21: -0.08 | R21: -0.04 | S21: -0.09 | T21: 0.22 | U21: 1.04 | V21: 0.53 | W21: 0.5 | X21: 0.53 | Y21: 0.39 | Z21: 0.36 | AA21: 0.32 | AB21: 0.26 | AC21: 0.33 | AD21: 0.22 | AE21: 0.18 | AF21: 0.2 | AG21: 0.21 | AH21: 0.2 | AI21: 0.21 | AJ21: 0.21 | AK21: 0.2 | AL21: 0.21 | AM21: 0.21 | AN21: 0.18 | AO21: 0.18 | AP21: 0.21 | AQ21: 0.22 | AR21: 0.2 | AS21: 0.21 | AT21: 0.22 | BJ21: Delivery Hero run-rate synergies ($m) | BK21: =BL21 | BL21: 1200 | BM21: =BL21 | BN21: Deck: annualised synergies of over $1.2bn within 18 months of closing.
BJ22: Minimum net debt / Adjusted EBITDA (x) — buyback floor 2027E+ | BK22: 0.5 | BL22: 0.25 | BM22: 0 | BN22: Uber: gross leverage < 2x, investment grade.
B23: Mobility (ride-hailing incl. Moto, Reserve, Uber for Business, AV partnerships; "Rides" 2019; Core Platform ridesharing 2016–18) | BB23: MOBILITY — modelling logic | BJ23: Minimum share repurchases % of FCF — 2027E+ | BK23: 0.75 | BL23: 0.5 | BM23: 0.25 | BN23: Uber returned ~67% of FY25 FCF ($6.5bn of $9.8bn).
B24: Gross Bookings | D24: 31384 | E24: 9380 | F24: 10166 | G24: 10488 | H24: 11479 | I24: 41513 | J24: 11446 | K24: 12188 | L24: 12554 | M24: 13512 | O24: 10874 | P24: 3046 | Q24: 5905 | R24: 6789 | T24: 6773 | U24: 8640 | V24: 9883 | W24: 11340 | Y24: 10723 | Z24: 13364 | AA24: 13684 | AB24: 14894 | AD24: 14981 | AE24: 16728 | AF24: 17903 | AG24: 19285 | AI24: 18670 | AJ24: 20554 | AK24: 21002 | AL24: 22798 | AN24: 21182 | AO24: 23762 | AP24: 25111 | AQ24: 27442 | AS24: 26394 | AT24: 28988 | AU24: =AP24*(1+AU25) | AV24: =AQ24*(1+AV25) | AW24: =SUM(AS24,AT24,AU24,AV24) | AX24: =AW24*(1+AX25) | AY24: =AX24*(1+AY25) | AZ24: =AY24*(1+AZ25) | BA24: =AZ24*(1+BA25) | BB24: Q3/Q4-26E: prior-year quarter × (1 + y/y growth). 2027E+: prior year × (1 + scenario lever MOB_GB). | BD24: =IFERROR((BA24/AR24)^(1/5)-1,"") | BE24: =IFERROR((AR24/S24)^(1/5)-1,"") | BF24: =IFERROR((AR24/I24)^(1/7)-1,"") | BG24: =IFERROR((AR24/C24)^(1/9)-1,"")
B25: Gross Bookings y/y % | D25: =IF(AND(ISNUMBER(D24),ISNUMBER(C24)),IFERROR(D24/C24-1,""),"") | I25: =IF(AND(ISNUMBER(I24),ISNUMBER(D24)),IFERROR(I24/D24-1,""),"") | J25: =IF(AND(ISNUMBER(J24),ISNUMBER(E24)),IFERROR(J24/E24-1,""),"") | K25: =IF(AND(ISNUMBER(K24),ISNUMBER(F24)),IFERROR(K24/F24-1,""),"") | L25: =IF(AND(ISNUMBER(L24),ISNUMBER(G24)),IFERROR(L24/G24-1,""),"") | M25: =IF(AND(ISNUMBER(M24),ISNUMBER(H24)),IFERROR(M24/H24-1,""),"") | N25: =IF(AND(ISNUMBER(N24),ISNUMBER(I24)),IFERROR(N24/I24-1,""),"") | O25: =IF(AND(ISNUMBER(O24),ISNUMBER(J24)),IFERROR(O24/J24-1,""),"") | P25: =IF(AND(ISNUMBER(P24),ISNUMBER(K24)),IFERROR(P24/K24-1,""),"") | ... AT25: =IF(AND(ISNUMBER(AT24),ISNUMBER(AO24)),IFERROR(AT24/AO24-1,""),"") | AU25: =$AT$25+$AU$114 | AV25: =$AT$25+$AU$114 | AW25: =IFERROR(AW24/AR24-1,"") | AX25: =CHOOSE(MATCH($BB$2,{"Bull","Base","Bear"},0),$BK$26,$BL$26,$BM$26) | AY25: =CHOOSE(MATCH($BB$2,{"Bull","Base","Bear"},0),$BK$27,$BL$27,$BM$27) | AZ25: =CHOOSE(MATCH($BB$2,{"Bull","Base","Bear"},0),$BK$28,$BL$28,$BM$28) | BA25: =CHOOSE(MATCH($BB$2,{"Bull","Base","Bear"},0),$BK$29,$BL$29,$BM$29) | BB25: Q3/Q4-26E: Q2/26 y/y + outlook calibration Δ (Group block). 2027E–30E: scenario lever MOB_GB (table →). | BJ25: MOB_GB (Mobility Gross Bookings y/y) | BK25: 0.03 | BL25: Δ → | BM25: -0.03 | BN25: FY25 +17%; Q2/26 +22% (+20% cc). AV partnerships, Moto, Reserve, new markets vs maturing US.
B26: Memo: Gross Bookings y/y % at constant currency (company) | L26: 0.22 | M26: 0.2 | O26: -0.03 | P26: -0.73 | Q26: -0.5 | R26: -0.47 | T26: -0.36 | U26: 1.74 | V26: 0.63 | W26: 0.67 | Y26: 0.62 | Z26: 0.57 | AA26: 0.45 | AB26: 0.37 | AD26: 0.43 | AE26: 0.28 | AF26: 0.3 | AG26: 0.28 | AI26: 0.26 | AJ26: 0.27 | AK26: 0.24 | AL26: 0.24 | AN26: 0.2 | AO26: 0.18 | AP26: 0.19 | AQ26: 0.19 | AS26: 0.2 | AT26: 0.2 | BJ26: 2027E | BK26: =BL26+$BK$25 | BL26: 0.16 | BM26: =BL26+$BM$25
B27: Revenue | C27: 3535 | D27: 6888 | E27: 2180 | F27: 2291 | G27: 2425 | H27: 2400 | I27: 9437 | J27: 2418 | K27: 2376 | L27: 2895 | M27: 3056 | N27: 10745 | O27: 2467 | P27: 787 | Q27: 1364 | R27: 1471 | T27: 853 | U27: 1618 | V27: 2205 | W27: 2278 | Y27: 2518 | Z27: 3553 | AA27: 3822 | AB27: 4136 | AD27: 4330 | AE27: 4894 | AF27: 5071 | AG27: 5537 | AI27: 5633 | AJ27: 6134 | AK27: 6409 | AL27: 6911 | AN27: 6496 | AO27: 7288 | AP27: 7682 | AQ27: 8204 | AS27: 6798 | AT27: 7363 | AU27: =AU24*AU29 | AV27: =AV24*AV29 | AW27: =SUM(AS27,AT27,AU27,AV27) | AX27: =AX24*AX29 | AY27: =AY24*AY29 | AZ27: =AZ24*AZ29 | BA27: =BA24*BA29 | BD27: =IFERROR((BA27/AR27)^(1/5)-1,"") | BE27: =IFERROR((AR27/S27)^(1/5)-1,"") | BF27: =IFERROR((AR27/I27)^(1/7)-1,"") | BG27: =IFERROR((AR27/C27)^(1/9)-1,"") | BJ27: 2028E | BK27: =BL27+$BK$25 | BL27: 0.15 | BM27: =BL27+$BM$25
B28: Revenue y/y % | D28: =IF(AND(ISNUMBER(D27),ISNUMBER(C27)),IFERROR(D27/C27-1,""),"") | I28: =IF(AND(ISNUMBER(I27),ISNUMBER(D27)),IFERROR(I27/D27-1,""),"") | J28: =IF(AND(ISNUMBER(J27),ISNUMBER(E27)),IFERROR(J27/E27-1,""),"") | K28: =IF(AND(ISNUMBER(K27),ISNUMBER(F27)),IFERROR(K27/F27-1,""),"") | L28: =IF(AND(ISNUMBER(L27),ISNUMBER(G27)),IFERROR(L27/G27-1,""),"") | M28: =IF(AND(ISNUMBER(M27),ISNUMBER(H27)),IFERROR(M27/H27-1,""),"") | N28: =IF(AND(ISNUMBER(N27),ISNUMBER(I27)),IFERROR(N27/I27-1,""),"") | O28: =IF(AND(ISNUMBER(O27),ISNUMBER(J27)),IFERROR(O27/J27-1,""),"") | P28: =IF(AND(ISNUMBER(P27),ISNUMBER(K27)),IFERROR(P27/K27-1,""),"") | ... AT28: =IF(AND(ISNUMBER(AT27),ISNUMBER(AO27)),IFERROR(AT27/AO27-1,""),"") | AU28: =IFERROR(AU27/AP27-1,"") | AV28: =IFERROR(AV27/AQ27-1,"") | AW28: =IFERROR(AW27/AR27-1,"") | AX28: =IFERROR(AX27/AW27-1,"") | AY28: =IFERROR(AY27/AX27-1,"") | AZ28: =IFERROR(AZ27/AY27-1,"") | BA28: =IFERROR(BA27/AZ27-1,"") | BJ28: 2029E | BK28: =BL28+$BK$25 | BL28: 0.14 | BM28: =BL28+$BM$25
B29: Take rate — revenue ÷ Gross Bookings % | C29: =IF(AND(ISNUMBER(C27),ISNUMBER(C24)),IFERROR(C27/C24,""),"") | D29: =IF(AND(ISNUMBER(D27),ISNUMBER(D24)),IFERROR(D27/D24,""),"") | E29: =IF(AND(ISNUMBER(E27),ISNUMBER(E24)),IFERROR(E27/E24,""),"") | F29: =IF(AND(ISNUMBER(F27),ISNUMBER(F24)),IFERROR(F27/F24,""),"") | G29: =IF(AND(ISNUMBER(G27),ISNUMBER(G24)),IFERROR(G27/G24,""),"") | H29: =IF(AND(ISNUMBER(H27),ISNUMBER(H24)),IFERROR(H27/H24,""),"") | I29: =IF(AND(ISNUMBER(I27),ISNUMBER(I24)),IFERROR(I27/I24,""),"") | J29: =IF(AND(ISNUMBER(J27),ISNUMBER(J24)),IFERROR(J27/J24,""),"") | ... AT29: =IF(AND(ISNUMBER(AT27),ISNUMBER(AT24)),IFERROR(AT27/AT24,""),"") | AU29: =AP29*($AT$29/$AO$29) | AV29: =AQ29*($AT$29/$AO$29) | AW29: =IF(AND(ISNUMBER(AW27),ISNUMBER(AW24)),IFERROR(AW27/AW24,""),"") | AX29: =AW29 | AY29: =AX29 | AZ29: =AY29 | BA29: =AZ29 | BB29: Q3/Q4-26E: prior-year quarter × (Q2/26 ÷ Q2/25 take rate) — carries the 2026 business-model changes. 2027E+: held at 2026E. | BJ29: 2030E | BK29: =BL29+$BK$25 | BL29: 0.13 | BM29: =BL29+$BM$25
B30: Segment Operating Income (2026 measure; recast from Q1/24) | AI30: 1310 | AJ30: 1392 | AK30: 1514 | AL30: 1608 | AM30: 5824 | AN30: 1587 | AO30: 1729 | AP30: 1864 | AQ30: 2027 | AR30: 7207 | AS30: 2029 | AT30: 2215 | AU30: =AU24*AU32 | AV30: =AV24*AV32 | AW30: =SUM(AS30,AT30,AU30,AV30) | AX30: =AW30+(AX24-AW24)*AX33 | AY30: =AX30+(AY24-AX24)*AY33 | AZ30: =AY30+(AZ24-AY24)*AZ33 | BA30: =AZ30+(BA24-AZ24)*BA33 | BB30: 2027E+: prior-year Segment OI + Δ Gross Bookings × incremental margin (scenario lever MOB_INC). 2026E = sum of quarters.
B31: Segment OI % of GB before outlook calibration (Q3/Q4-26E helper) | AU31: =AP32+($AS$30+$AT$30)/($AS$24+$AT$24)-($AN$30+$AO$30)/($AN$24+$AO$24) | AV31: =AQ32+($AS$30+$AT$30)/($AS$24+$AT$24)-($AN$30+$AO$30)/($AN$24+$AO$24) | BB31: Q3/Q4-26E: prior-year quarter margin + (1H/26 − 1H/25 margin drift). | BJ31: DEL_GB (Delivery Gross Bookings y/y) | BK31: 0.03 | BL31: Δ → | BM31: -0.03 | BN31: FY25 +22%; Q2/26 +26% (incl. Trendyol Go). Grocery & retail, advertising, Uber One.
B32: Segment Operating Income % of Gross Bookings | C32: =IF(AND(ISNUMBER(C30),ISNUMBER(C24)),IFERROR(C30/C24,""),"") | D32: =IF(AND(ISNUMBER(D30),ISNUMBER(D24)),IFERROR(D30/D24,""),"") | E32: =IF(AND(ISNUMBER(E30),ISNUMBER(E24)),IFERROR(E30/E24,""),"") | F32: =IF(AND(ISNUMBER(F30),ISNUMBER(F24)),IFERROR(F30/F24,""),"") | G32: =IF(AND(ISNUMBER(G30),ISNUMBER(G24)),IFERROR(G30/G24,""),"") | H32: =IF(AND(ISNUMBER(H30),ISNUMBER(H24)),IFERROR(H30/H24,""),"") | I32: =IF(AND(ISNUMBER(I30),ISNUMBER(I24)),IFERROR(I30/I24,""),"") | J32: =IF(AND(ISNUMBER(J30),ISNUMBER(J24)),IFERROR(J30/J24,""),"") | ... AT32: =IF(AND(ISNUMBER(AT30),ISNUMBER(AT24)),IFERROR(AT30/AT24,""),"") | AU32: =AU31+$AU$117 | AV32: =AV31+$AU$117 | AW32: =IF(AND(ISNUMBER(AW30),ISNUMBER(AW24)),IFERROR(AW30/AW24,""),"") | AX32: =IF(AND(ISNUMBER(AX30),ISNUMBER(AX24)),IFERROR(AX30/AX24,""),"") | AY32: =IF(AND(ISNUMBER(AY30),ISNUMBER(AY24)),IFERROR(AY30/AY24,""),"") | AZ32: =IF(AND(ISNUMBER(AZ30),ISNUMBER(AZ24)),IFERROR(AZ30/AZ24,""),"") | BA32: =IF(AND(ISNUMBER(BA30),ISNUMBER(BA24)),IFERROR(BA30/BA24,""),"") | BB32: Q3/Q4-26E: margin before calibration + outlook calibration Δ (Group block). 2027E+: output. | BJ32: 2027E | BK32: =BL32+$BK$31 | BL32: 0.16 | BM32: =BL32+$BM$31
B33: Incremental Segment OI margin on Δ Gross Bookings (y/y) % | D33: =IF(AND(ISNUMBER(D30),ISNUMBER(C30)),IFERROR((D30-C30)/(D24-C24),""),"") | I33: =IF(AND(ISNUMBER(I30),ISNUMBER(D30)),IFERROR((I30-D30)/(I24-D24),""),"") | J33: =IF(AND(ISNUMBER(J30),ISNUMBER(E30)),IFERROR((J30-E30)/(J24-E24),""),"") | K33: =IF(AND(ISNUMBER(K30),ISNUMBER(F30)),IFERROR((K30-F30)/(K24-F24),""),"") | L33: =IF(AND(ISNUMBER(L30),ISNUMBER(G30)),IFERROR((L30-G30)/(L24-G24),""),"") | M33: =IF(AND(ISNUMBER(M30),ISNUMBER(H30)),IFERROR((M30-H30)/(M24-H24),""),"") | N33: =IF(AND(ISNUMBER(N30),ISNUMBER(I30)),IFERROR((N30-I30)/(N24-I24),""),"") | O33: =IF(AND(ISNUMBER(O30),ISNUMBER(J30)),IFERROR((O30-J30)/(O24-J24),""),"") | P33: =IF(AND(ISNUMBER(P30),ISNUMBER(K30)),IFERROR((P30-K30)/(P24-K24),""),"") | ... AT33: =IF(AND(ISNUMBER(AT30),ISNUMBER(AO30)),IFERROR((AT30-AO30)/(AT24-AO24),""),"") | AU33: =IFERROR((AU30-AP30)/(AU24-AP24),"") | AV33: =IFERROR((AV30-AQ30)/(AV24-AQ24),"") | AW33: =IFERROR((AW30-AR30)/(AW24-AR24),"") | AX33: =CHOOSE(MATCH($BB$2,{"Bull","Base","Bear"},0),$BK$38,$BL$38,$BM$38) | AY33: =CHOOSE(MATCH($BB$2,{"Bull","Base","Bear"},0),$BK$39,$BL$39,$BM$39) | AZ33: =CHOOSE(MATCH($BB$2,{"Bull","Base","Bear"},0),$BK$40,$BL$40,$BM$40) | BA33: =CHOOSE(MATCH($BB$2,{"Bull","Base","Bear"},0),$BK$41,$BL$41,$BM$41) | BB33: FY25 9.6% (ΔSOI $1.38bn ÷ ΔGB $14.5bn). 2027E+: scenario lever MOB_INC. | BJ33: 2028E | BK33: =BL33+$BK$31 | BL33: 0.15 | BM33: =BL33+$BM$31
BJ34: 2029E | BK34: =BL34+$BK$31 | BL34: 0.14 | BM34: =BL34+$BM$31
B35: Delivery (Uber Eats incl. Grocery & Retail, Postmates from Dec-20, Cornershop, Drizly (closed 2024), Trendyol Go from Jun-25; "Eats" 2019) | BB35: DELIVERY — modelling logic (same mechanics as Mobility) | BJ35: 2030E | BK35: =BL35+$BK$31 | BL35: 0.13 | BM35: =BL35+$BM$31
B36: Gross Bookings | D36: 2958 | E36: 1473 | F36: 1774 | G36: 2111 | H36: 2561 | I36: 7919 | J36: 3071 | K36: 3386 | L36: 3658 | M36: 4374 | O36: 4683 | P36: 6961 | Q36: 8550 | R36: 10050 | T36: 12461 | U36: 12912 | V36: 12828 | W36: 13444 | Y36: 13903 | Z36: 13876 | AA36: 13684 | AB36: 14315 | AD36: 15026 | AE36: 15595 | AF36: 16094 | AG36: 17011 | AI36: 17699 | AJ36: 18126 | AK36: 18663 | AL36: 20126 | AN36: 20377 | AO36: 21734 | AP36: 23322 | AQ36: 25431 | AS36: 25992 | AT36: 27463 | AU36: =AP36*(1+AU37) | AV36: =AQ36*(1+AV37) | AW36: =SUM(AS36,AT36,AU36,AV36) | AX36: =AW36*(1+AX37) | AY36: =AX36*(1+AY37) | AZ36: =AY36*(1+AZ37) | BA36: =AZ36*(1+BA37) | BB36: Q3/Q4-26E: prior-year quarter × (1 + y/y growth). 2027E+: scenario lever DEL_GB. | BD36: =IFERROR((BA36/AR36)^(1/5)-1,"") | BE36: =IFERROR((AR36/S36)^(1/5)-1,"") | BF36: =IFERROR((AR36/I36)^(1/7)-1,"") | BG36: =IFERROR((AR36/C36)^(1/9)-1,"")
B37: Gross Bookings y/y % | D37: =IF(AND(ISNUMBER(D36),ISNUMBER(C36)),IFERROR(D36/C36-1,""),"") | I37: =IF(AND(ISNUMBER(I36),ISNUMBER(D36)),IFERROR(I36/D36-1,""),"") | J37: =IF(AND(ISNUMBER(J36),ISNUMBER(E36)),IFERROR(J36/E36-1,""),"") | K37: =IF(AND(ISNUMBER(K36),ISNUMBER(F36)),IFERROR(K36/F36-1,""),"") | L37: =IF(AND(ISNUMBER(L36),ISNUMBER(G36)),IFERROR(L36/G36-1,""),"") | M37: =IF(AND(ISNUMBER(M36),ISNUMBER(H36)),IFERROR(M36/H36-1,""),"") | N37: =IF(AND(ISNUMBER(N36),ISNUMBER(I36)),IFERROR(N36/I36-1,""),"") | O37: =IF(AND(ISNUMBER(O36),ISNUMBER(J36)),IFERROR(O36/J36-1,""),"") | P37: =IF(AND(ISNUMBER(P36),ISNUMBER(K36)),IFERROR(P36/K36-1,""),"") | ... AT37: =IF(AND(ISNUMBER(AT36),ISNUMBER(AO36)),IFERROR(AT36/AO36-1,""),"") | AU37: =$AT$37+$AU$114 | AV37: =$AT$37+$AU$114 | AW37: =IFERROR(AW36/AR36-1,"") | AX37: =CHOOSE(MATCH($BB$2,{"Bull","Base","Bear"},0),$BK$32,$BL$32,$BM$32) | AY37: =CHOOSE(MATCH($BB$2,{"Bull","Base","Bear"},0),$BK$33,$BL$33,$BM$33) | AZ37: =CHOOSE(MATCH($BB$2,{"Bull","Base","Bear"},0),$BK$34,$BL$34,$BM$34) | BA37: =CHOOSE(MATCH($BB$2,{"Bull","Base","Bear"},0),$BK$35,$BL$35,$BM$35) | BB37: Q2/26 +26% includes Trendyol Go (anniversaries Jun-26); calibration Δ brings Q3/26E to the outlook end-point. | BJ37: MOB_INC (Mobility incremental Segment OI margin on ΔGB) | BK37: 0.015 | BL37: Δ → | BM37: -0.015 | BN37: FY25 9.6%; Q2/26 y/y 9.3%. Segment OI margin 7.4% of GB (FY25).
B38: Memo: Gross Bookings y/y % at constant currency (company) | L38: 0.77 | M38: 0.73 | O38: 0.54 | P38: 1.13 | Q38: 1.35 | R38: 1.28 | T38: 1.57 | U38: 0.75 | V38: 0.46 | W38: 0.33 | Y38: 0.15 | Z38: 0.12 | AA38: 0.13 | AB38: 0.14 | AD38: 0.12 | AE38: 0.14 | AF38: 0.16 | AG38: 0.17 | AI38: 0.17 | AJ38: 0.17 | AK38: 0.17 | AL38: 0.18 | AN38: 0.18 | AO38: 0.2 | AP38: 0.24 | AQ38: 0.26 | AS38: 0.23 | AT38: 0.25 | BJ38: 2027E | BK38: =BL38+$BK$37 | BL38: 0.095 | BM38: =BL38+$BM$37
B39: Revenue | C39: 103 | D39: 587 | E39: 283 | F39: 346 | G39: 394 | H39: 437 | I39: 1460 | J39: 536 | K39: 595 | L39: 645 | M39: 734 | N39: 2510 | O39: 527 | P39: 886 | Q39: 1136 | R39: 1356 | T39: 1741 | U39: 1963 | V39: 2238 | W39: 2420 | Y39: 2512 | Z39: 2688 | AA39: 2770 | AB39: 2931 | AD39: 3093 | AE39: 3057 | AF39: 2935 | AG39: 3119 | AI39: 3214 | AJ39: 3293 | AK39: 3470 | AL39: 3773 | AN39: 3777 | AO39: 4102 | AP39: 4477 | AQ39: 4892 | AS39: 5068 | AT39: 5245 | AU39: =AU36*AU41 | AV39: =AV36*AV41 | AW39: =SUM(AS39,AT39,AU39,AV39) | AX39: =AX36*AX41 | AY39: =AY36*AY41 | AZ39: =AZ36*AZ41 | BA39: =BA36*BA41 | BD39: =IFERROR((BA39/AR39)^(1/5)-1,"") | BE39: =IFERROR((AR39/S39)^(1/5)-1,"") | BF39: =IFERROR((AR39/I39)^(1/7)-1,"") | BG39: =IFERROR((AR39/C39)^(1/9)-1,"") | BJ39: 2028E | BK39: =BL39+$BK$37 | BL39: 0.095 | BM39: =BL39+$BM$37
B40: Revenue y/y % | D40: =IF(AND(ISNUMBER(D39),ISNUMBER(C39)),IFERROR(D39/C39-1,""),"") | I40: =IF(AND(ISNUMBER(I39),ISNUMBER(D39)),IFERROR(I39/D39-1,""),"") | J40: =IF(AND(ISNUMBER(J39),ISNUMBER(E39)),IFERROR(J39/E39-1,""),"") | K40: =IF(AND(ISNUMBER(K39),ISNUMBER(F39)),IFERROR(K39/F39-1,""),"") | L40: =IF(AND(ISNUMBER(L39),ISNUMBER(G39)),IFERROR(L39/G39-1,""),"") | M40: =IF(AND(ISNUMBER(M39),ISNUMBER(H39)),IFERROR(M39/H39-1,""),"") | N40: =IF(AND(ISNUMBER(N39),ISNUMBER(I39)),IFERROR(N39/I39-1,""),"") | O40: =IF(AND(ISNUMBER(O39),ISNUMBER(J39)),IFERROR(O39/J39-1,""),"") | P40: =IF(AND(ISNUMBER(P39),ISNUMBER(K39)),IFERROR(P39/K39-1,""),"") | ... AT40: =IF(AND(ISNUMBER(AT39),ISNUMBER(AO39)),IFERROR(AT39/AO39-1,""),"") | AU40: =IFERROR(AU39/AP39-1,"") | AV40: =IFERROR(AV39/AQ39-1,"") | AW40: =IFERROR(AW39/AR39-1,"") | AX40: =IFERROR(AX39/AW39-1,"") | AY40: =IFERROR(AY39/AX39-1,"") | AZ40: =IFERROR(AZ39/AY39-1,"") | BA40: =IFERROR(BA39/AZ39-1,"") | BJ40: 2029E | BK40: =BL40+$BK$37 | BL40: 0.09 | BM40: =BL40+$BM$37
B41: Take rate — revenue ÷ Gross Bookings % | C41: =IF(AND(ISNUMBER(C39),ISNUMBER(C36)),IFERROR(C39/C36,""),"") | D41: =IF(AND(ISNUMBER(D39),ISNUMBER(D36)),IFERROR(D39/D36,""),"") | E41: =IF(AND(ISNUMBER(E39),ISNUMBER(E36)),IFERROR(E39/E36,""),"") | F41: =IF(AND(ISNUMBER(F39),ISNUMBER(F36)),IFERROR(F39/F36,""),"") | G41: =IF(AND(ISNUMBER(G39),ISNUMBER(G36)),IFERROR(G39/G36,""),"") | H41: =IF(AND(ISNUMBER(H39),ISNUMBER(H36)),IFERROR(H39/H36,""),"") | I41: =IF(AND(ISNUMBER(I39),ISNUMBER(I36)),IFERROR(I39/I36,""),"") | J41: =IF(AND(ISNUMBER(J39),ISNUMBER(J36)),IFERROR(J39/J36,""),"") | ... AT41: =IF(AND(ISNUMBER(AT39),ISNUMBER(AT36)),IFERROR(AT39/AT36,""),"") | AU41: =AP41*($AT$41/$AO$41) | AV41: =AQ41*($AT$41/$AO$41) | AW41: =IF(AND(ISNUMBER(AW39),ISNUMBER(AW36)),IFERROR(AW39/AW36,""),"") | AX41: =AW41 | AY41: =AX41 | AZ41: =AY41 | BA41: =AZ41 | BJ41: 2030E | BK41: =BL41+$BK$37 | BL41: 0.09 | BM41: =BL41+$BM$37
B42: Segment Operating Income (2026 measure; recast from Q1/24) | AI42: 428 | AJ42: 514 | AK42: 544 | AL42: 639 | AM42: 2125 | AN42: 671 | AO42: 766 | AP42: 811 | AQ42: 905 | AR42: 3153 | AS42: 961 | AT42: 1055 | AU42: =AU36*AU44 | AV42: =AV36*AV44 | AW42: =SUM(AS42,AT42,AU42,AV42) | AX42: =AW42+(AX36-AW36)*AX45 | AY42: =AX42+(AY36-AX36)*AY45 | AZ42: =AY42+(AZ36-AY36)*AZ45 | BA42: =AZ42+(BA36-AZ36)*BA45
B43: Segment OI % of GB before outlook calibration (Q3/Q4-26E helper) | AU43: =AP44+($AS$42+$AT$42)/($AS$36+$AT$36)-($AN$42+$AO$42)/($AN$36+$AO$36) | AV43: =AQ44+($AS$42+$AT$42)/($AS$36+$AT$36)-($AN$42+$AO$42)/($AN$36+$AO$36) | BJ43: DEL_INC (Delivery incremental Segment OI margin on ΔGB) | BK43: 0.015 | BL43: Δ → | BM43: -0.015 | BN43: FY25 6.3%; Q2/26 y/y 5.0%. Segment OI margin 3.5% of GB (FY25).
B44: Segment Operating Income % of Gross Bookings | C44: =IF(AND(ISNUMBER(C42),ISNUMBER(C36)),IFERROR(C42/C36,""),"") | D44: =IF(AND(ISNUMBER(D42),ISNUMBER(D36)),IFERROR(D42/D36,""),"") | E44: =IF(AND(ISNUMBER(E42),ISNUMBER(E36)),IFERROR(E42/E36,""),"") | F44: =IF(AND(ISNUMBER(F42),ISNUMBER(F36)),IFERROR(F42/F36,""),"") | G44: =IF(AND(ISNUMBER(G42),ISNUMBER(G36)),IFERROR(G42/G36,""),"") | H44: =IF(AND(ISNUMBER(H42),ISNUMBER(H36)),IFERROR(H42/H36,""),"") | I44: =IF(AND(ISNUMBER(I42),ISNUMBER(I36)),IFERROR(I42/I36,""),"") | J44: =IF(AND(ISNUMBER(J42),ISNUMBER(J36)),IFERROR(J42/J36,""),"") | ... AT44: =IF(AND(ISNUMBER(AT42),ISNUMBER(AT36)),IFERROR(AT42/AT36,""),"") | AU44: =AU43+$AU$117 | AV44: =AV43+$AU$117 | AW44: =IF(AND(ISNUMBER(AW42),ISNUMBER(AW36)),IFERROR(AW42/AW36,""),"") | AX44: =IF(AND(ISNUMBER(AX42),ISNUMBER(AX36)),IFERROR(AX42/AX36,""),"") | AY44: =IF(AND(ISNUMBER(AY42),ISNUMBER(AY36)),IFERROR(AY42/AY36,""),"") | AZ44: =IF(AND(ISNUMBER(AZ42),ISNUMBER(AZ36)),IFERROR(AZ42/AZ36,""),"") | BA44: =IF(AND(ISNUMBER(BA42),ISNUMBER(BA36)),IFERROR(BA42/BA36,""),"") | BJ44: 2027E | BK44: =BL44+$BK$43 | BL44: 0.06 | BM44: =BL44+$BM$43
B45: Incremental Segment OI margin on Δ Gross Bookings (y/y) % | D45: =IF(AND(ISNUMBER(D42),ISNUMBER(C42)),IFERROR((D42-C42)/(D36-C36),""),"") | I45: =IF(AND(ISNUMBER(I42),ISNUMBER(D42)),IFERROR((I42-D42)/(I36-D36),""),"") | J45: =IF(AND(ISNUMBER(J42),ISNUMBER(E42)),IFERROR((J42-E42)/(J36-E36),""),"") | K45: =IF(AND(ISNUMBER(K42),ISNUMBER(F42)),IFERROR((K42-F42)/(K36-F36),""),"") | L45: =IF(AND(ISNUMBER(L42),ISNUMBER(G42)),IFERROR((L42-G42)/(L36-G36),""),"") | M45: =IF(AND(ISNUMBER(M42),ISNUMBER(H42)),IFERROR((M42-H42)/(M36-H36),""),"") | N45: =IF(AND(ISNUMBER(N42),ISNUMBER(I42)),IFERROR((N42-I42)/(N36-I36),""),"") | O45: =IF(AND(ISNUMBER(O42),ISNUMBER(J42)),IFERROR((O42-J42)/(O36-J36),""),"") | P45: =IF(AND(ISNUMBER(P42),ISNUMBER(K42)),IFERROR((P42-K42)/(P36-K36),""),"") | ... AT45: =IF(AND(ISNUMBER(AT42),ISNUMBER(AO42)),IFERROR((AT42-AO42)/(AT36-AO36),""),"") | AU45: =IFERROR((AU42-AP42)/(AU36-AP36),"") | AV45: =IFERROR((AV42-AQ42)/(AV36-AQ36),"") | AW45: =IFERROR((AW42-AR42)/(AW36-AR36),"") | AX45: =CHOOSE(MATCH($BB$2,{"Bull","Base","Bear"},0),$BK$44,$BL$44,$BM$44) | AY45: =CHOOSE(MATCH($BB$2,{"Bull","Base","Bear"},0),$BK$45,$BL$45,$BM$45) | AZ45: =CHOOSE(MATCH($BB$2,{"Bull","Base","Bear"},0),$BK$46,$BL$46,$BM$46) | BA45: =CHOOSE(MATCH($BB$2,{"Bull","Base","Bear"},0),$BK$47,$BL$47,$BM$47) | BB45: FY25 6.3% (advertising, Uber One, grocery scale). 2027E+: scenario lever DEL_INC. | BJ45: 2028E | BK45: =BL45+$BK$43 | BL45: 0.06 | BM45: =BL45+$BM$43
BJ46: 2029E | BK46: =BL46+$BK$43 | BL46: 0.06 | BM46: =BL46+$BM$43
B47: Freight (Uber Freight brokerage & managed transportation; Transplace from Nov-21; Gross Bookings = revenue) | BB47: FREIGHT — modelling logic | BJ47: 2030E | BK47: =BL47+$BK$43 | BL47: 0.06 | BM47: =BL47+$BM$43
B48: Gross Bookings (= revenue) | G48: 123 | H48: 126 | J48: 128 | K48: 167 | L48: 223 | M48: 219 | O48: 198 | P48: 212 | Q48: 290 | R48: 313 | T48: 302 | U48: 348 | V48: 402 | W48: 1082 | Y48: 1823 | Z48: 1838 | AA48: 1751 | AB48: 1540 | AD48: 1401 | AE48: 1278 | AF48: 1284 | AG48: 1279 | AI48: 1282 | AJ48: 1272 | AK48: 1308 | AL48: 1273 | AN48: 1259 | AO48: 1260 | AP48: 1307 | AQ48: 1267 | AS48: 1334 | AT48: 1571 | AU48: =AP48*(1+AU49) | AV48: =AQ48*(1+AV49) | AW48: =SUM(AS48,AT48,AU48,AV48) | AX48: =AW48*(1+AX49) | AY48: =AX48*(1+AY49) | AZ48: =AY48*(1+AZ49) | BA48: =AZ48*(1+BA49) | BD48: =IFERROR((BA48/AR48)^(1/5)-1,"") | BE48: =IFERROR((AR48/S48)^(1/5)-1,"") | BF48: =IFERROR((AR48/I48)^(1/7)-1,"") | BG48: =IFERROR((AR48/C48)^(1/9)-1,"")
B49: Gross Bookings y/y % | D49: =IF(AND(ISNUMBER(D48),ISNUMBER(C48)),IFERROR(D48/C48-1,""),"") | I49: =IF(AND(ISNUMBER(I48),ISNUMBER(D48)),IFERROR(I48/D48-1,""),"") | J49: =IF(AND(ISNUMBER(J48),ISNUMBER(E48)),IFERROR(J48/E48-1,""),"") | K49: =IF(AND(ISNUMBER(K48),ISNUMBER(F48)),IFERROR(K48/F48-1,""),"") | L49: =IF(AND(ISNUMBER(L48),ISNUMBER(G48)),IFERROR(L48/G48-1,""),"") | M49: =IF(AND(ISNUMBER(M48),ISNUMBER(H48)),IFERROR(M48/H48-1,""),"") | N49: =IF(AND(ISNUMBER(N48),ISNUMBER(I48)),IFERROR(N48/I48-1,""),"") | O49: =IF(AND(ISNUMBER(O48),ISNUMBER(J48)),IFERROR(O48/J48-1,""),"") | P49: =IF(AND(ISNUMBER(P48),ISNUMBER(K48)),IFERROR(P48/K48-1,""),"") | ... AT49: =IF(AND(ISNUMBER(AT48),ISNUMBER(AO48)),IFERROR(AT48/AO48-1,""),"") | AU49: =$AT$49 | AV49: =$AT$49 | AW49: =IFERROR(AW48/AR48-1,"") | AX49: =CHOOSE(MATCH($BB$2,{"Bull","Base","Bear"},0),$BK$50,$BL$50,$BM$50) | AY49: =CHOOSE(MATCH($BB$2,{"Bull","Base","Bear"},0),$BK$51,$BL$51,$BM$51) | AZ49: =CHOOSE(MATCH($BB$2,{"Bull","Base","Bear"},0),$BK$52,$BL$52,$BM$52) | BA49: =CHOOSE(MATCH($BB$2,{"Bull","Base","Bear"},0),$BK$53,$BL$53,$BM$53) | BB49: Q3/Q4-26E: Q2/26 y/y (not calibrated). 2027E+: scenario lever FRT_GR. | BJ49: FRT_GR (Freight revenue y/y) | BK49: 0.04 | BL49: Δ → | BM49: -0.04 | BN49: FY25 −1%; Q2/26 +25% (freight-cycle recovery, acquisitions).
B50: Revenue | G50: 122 | H50: 125 | J50: 127 | K50: 167 | L50: 218 | M50: 219 | O50: 199 | P50: 211 | Q50: 288 | R50: 313 | T50: 301 | U50: 348 | V50: 402 | W50: 1080 | Y50: 1824 | Z50: 1832 | AA50: 1751 | AB50: 1540 | AD50: 1400 | AE50: 1279 | AF50: 1286 | AG50: 1280 | AI50: 1284 | AJ50: 1273 | AK50: 1309 | AL50: 1275 | AN50: 1260 | AO50: 1261 | AP50: 1308 | AQ50: 1270 | AS50: 1337 | AT50: 1583 | AU50: =AU48 | AV50: =AV48 | AW50: =SUM(AS50,AT50,AU50,AV50) | AX50: =AX48 | AY50: =AY48 | AZ50: =AZ48 | BA50: =BA48 | BJ50: 2027E | BK50: =BL50+$BK$49 | BL50: 0.08 | BM50: =BL50+$BM$49
B51: Segment Operating Income (2026 measure; recast from Q1/24) | AI51: -42 | AJ51: -33 | AK51: -39 | AL51: -41 | AM51: -155 | AN51: -25 | AO51: -26 | AP51: -40 | AQ51: -18 | AR51: -109 | AS51: -30 | AT51: -24 | AU51: =AU50*AU52 | AV51: =AV50*AV52 | AW51: =SUM(AS51,AT51,AU51,AV51) | AX51: =AX50*AX52 | AY51: =AY50*AY52 | AZ51: =AZ50*AZ52 | BA51: =BA50*BA52 | BJ51: 2028E | BK51: =BL51+$BK$49 | BL51: 0.07 | BM51: =BL51+$BM$49
B52: Segment Operating Income % of revenue | C52: =IF(AND(ISNUMBER(C51),ISNUMBER(C50)),IFERROR(C51/C50,""),"") | D52: =IF(AND(ISNUMBER(D51),ISNUMBER(D50)),IFERROR(D51/D50,""),"") | E52: =IF(AND(ISNUMBER(E51),ISNUMBER(E50)),IFERROR(E51/E50,""),"") | F52: =IF(AND(ISNUMBER(F51),ISNUMBER(F50)),IFERROR(F51/F50,""),"") | G52: =IF(AND(ISNUMBER(G51),ISNUMBER(G50)),IFERROR(G51/G50,""),"") | H52: =IF(AND(ISNUMBER(H51),ISNUMBER(H50)),IFERROR(H51/H50,""),"") | I52: =IF(AND(ISNUMBER(I51),ISNUMBER(I50)),IFERROR(I51/I50,""),"") | J52: =IF(AND(ISNUMBER(J51),ISNUMBER(J50)),IFERROR(J51/J50,""),"") | ... AT52: =IF(AND(ISNUMBER(AT51),ISNUMBER(AT50)),IFERROR(AT51/AT50,""),"") | AU52: =AP52+($AS$51+$AT$51)/($AS$50+$AT$50)-($AN$51+$AO$51)/($AN$50+$AO$50) | AV52: =AQ52+($AS$51+$AT$51)/($AS$50+$AT$50)-($AN$51+$AO$51)/($AN$50+$AO$50) | AW52: =IF(AND(ISNUMBER(AW51),ISNUMBER(AW50)),IFERROR(AW51/AW50,""),"") | AX52: =CHOOSE(MATCH($BB$2,{"Bull","Base","Bear"},0),$BK$56,$BL$56,$BM$56) | AY52: =CHOOSE(MATCH($BB$2,{"Bull","Base","Bear"},0),$BK$57,$BL$57,$BM$57) | AZ52: =CHOOSE(MATCH($BB$2,{"Bull","Base","Bear"},0),$BK$58,$BL$58,$BM$58) | BA52: =CHOOSE(MATCH($BB$2,{"Bull","Base","Bear"},0),$BK$59,$BL$59,$BM$59) | BB52: Q3/Q4-26E: prior-year quarter + 1H drift. 2027E+: scenario lever FRT_M (freight-cycle recovery). | BJ52: 2029E | BK52: =BL52+$BK$49 | BL52: 0.06 | BM52: =BL52+$BM$49
BJ53: 2030E | BK53: =BL53+$BK$49 | BL53: 0.05 | BM53: =BL53+$BM$49
B54: Other Bets, ATG & items not allocated to segments (legacy 2016–2020) | BB54: LEGACY — historical only; JUMP to Lime (May-20), ATG to Aurora (Jan-21), Other Bets wound down 2020
B55: Other Bets — Gross Bookings (JUMP, Transit, other; to Q2/20) | D55: 67 | E55: 40 | F55: 72 | G55: 3 | H55: 3 | I55: 367 | J55: 4 | K55: 15 | L55: 30 | M55: 26 | O55: 21 | P55: 5 | Q55: 0 | R55: 0 | BJ55: FRT_M (Freight Segment OI % of revenue) | BK55: 0.01 | BL55: Δ → | BM55: -0.01 | BN55: FY25 −2.1%; 1H/26 −1.9%.
B56: Other Bets — revenue | C56: 1 | D56: 67 | E56: 40 | F56: 71 | G56: 3 | H56: 12 | I56: 373 | J56: 18 | K56: 28 | L56: 38 | M56: 35 | O56: 30 | P56: 4 | Q56: 0 | R56: 0 | BJ56: 2027E | BK56: =BL56+$BK$55 | BL56: -0.01 | BM56: =BL56+$BM$55
B57: ATG & Other Technology Programs — revenue (to Q4/20) | G57: 0 | H57: 0 | J57: 0 | K57: 0 | L57: 17 | M57: 25 | O57: 25 | P57: 25 | Q57: 25 | R57: 25 | BJ57: 2028E | BK57: =BL57+$BK$55 | BL57: -0.005 | BM57: =BL57+$BM$55
B58: Gross Bookings not split by segment (2016 annual; S-1 segment split quarterly from 2017) | C58: 19236 | N58: 65001 | S58: 57897 | X58: 90415 | AC58: 115395 | AH58: 137865 | AM58: 162773 | AR58: 193454 | BJ58: 2029E | BK58: =BL58+$BK$55 | BL58: 0 | BM58: =BL58+$BM$55
B59: Revenue not allocated to segments (Core Platform other revenue 2016–18, Freight within Other Bets to Q2/18, Q4/18–19 rounding) | C59: 206 | D59: 390 | E59: 81 | F59: 60 | N59: 892 | S59: 11139 | T59: 8 | X59: 17455 | AC59: 31877 | AH59: 37281 | AM59: 43978 | AR59: 52017 | BJ59: 2030E | BK59: =BL59+$BK$55 | BL59: 0.005 | BM59: =BL59+$BM$55
B61: Delivery Hero — acquired perimeter (Baemin, talabat, PedidosYa, foodpanda Asia, Glovo ex-SSW markets, HungerStation) — consolidated from assumed closing 1-Oct-2027; switch in scenario table | BB61: DELIVERY HERO — modelling logic (BCA 16-Jul-2026, €41.50/share cash tender; closing expected 2H/27; NOT in company outlook) | BJ61: DH_GR (Delivery Hero Gross Bookings y/y) | BK61: 0.03 | BL61: Δ → | BM61: -0.03 | BN61: Acquired perimeter ~high-single / low-double-digit growth (talabat +28% cc 2025; Baemin slower).
B62: Memo: 2025 Gross Bookings — acquired perimeter (GMV proxy; EUR at 1.12) | AR62: 42000 | BJ62: 2027E | BK62: =BL62+$BK$61 | BL62: 0.1 | BM62: =BL62+$BM$61
B63: Memo: 2025 Adjusted EBITDA — acquired perimeter (IFRS) | AR63: 1100 | BJ63: 2028E | BK63: =BL63+$BK$61 | BL63: 0.1 | BM63: =BL63+$BM$61
B64: Days consolidated in period (× consolidation switch) | AX64: =92*$BL$19 | AY64: =365*$BL$19 | AZ64: =365*$BL$19 | BA64: =365*$BL$19 | BB64: Assumed closing 1-Oct-2027 (company: "second half of 2027"; long-stop 10-May-2028). Switch = 0 shows Uber standalone. | BJ64: 2029E | BK64: =BL64+$BK$61 | BL64: 0.09 | BM64: =BL64+$BM$61
B65: Annual Gross Bookings run-rate (standalone basis) | AW65: =AR62*(1+AW66) | AX65: =AW65*(1+AX66) | AY65: =AX65*(1+AY66) | AZ65: =AY65*(1+AZ66) | BA65: =AZ65*(1+BA66) | BJ65: 2030E | BK65: =BL65+$BK$61 | BL65: 0.09 | BM65: =BL65+$BM$61
B66: Gross Bookings growth y/y % | AW66: 0.1 | AX66: =CHOOSE(MATCH($BB$2,{"Bull","Base","Bear"},0),$BK$62,$BL$62,$BM$62) | AY66: =CHOOSE(MATCH($BB$2,{"Bull","Base","Bear"},0),$BK$63,$BL$63,$BM$63) | AZ66: =CHOOSE(MATCH($BB$2,{"Bull","Base","Bear"},0),$BK$64,$BL$64,$BM$64) | BA66: =CHOOSE(MATCH($BB$2,{"Bull","Base","Bear"},0),$BK$65,$BL$65,$BM$65) | BB66: 2026E input +10% (talabat ~+28%, Baemin low growth). 2027E+: scenario lever DH_GR.
B67: Gross Bookings (consolidated from closing) | AX67: =AX65*AX64/365 | AY67: =AY65*AY64/365 | AZ67: =AZ65*AZ64/365 | BA67: =BA65*BA64/365 | BJ67: DH_M (Delivery Hero standalone Adj. EBITDA % of GB) | BK67: 0.005 | BL67: Δ → | BM67: -0.005 | BN67: 2025 IFRS 2.6%; US GAAP ~2.3% (deck-implied ~$1.2bn 2027E standalone).
B68: Revenue ÷ Gross Bookings % (assumption) | AX68: 0.24 | AY68: =AX68 | AZ68: =AY68 | BA68: =AZ68 | BB68: Assumption ~24%: Delivery Hero reports IFRS revenue / GMV in the mid-20s% (own delivery, Dmarts); not verifiable from EDGAR — refine on the offer document. | BJ68: 2027E | BK68: =BL68+$BK$67 | BL68: 0.023 | BM68: =BL68+$BM$67
B69: Revenue (consolidated) | AX69: =AX67*AX68 | AY69: =AY67*AY68 | AZ69: =AZ67*AZ68 | BA69: =BA67*BA68 | BJ69: 2028E | BK69: =BL69+$BK$67 | BL69: 0.026 | BM69: =BL69+$BM$67
B70: Standalone Adjusted EBITDA % of Gross Bookings (US GAAP basis, before synergies) | AX70: =CHOOSE(MATCH($BB$2,{"Bull","Base","Bear"},0),$BK$68,$BL$68,$BM$68) | AY70: =CHOOSE(MATCH($BB$2,{"Bull","Base","Bear"},0),$BK$69,$BL$69,$BM$69) | AZ70: =CHOOSE(MATCH($BB$2,{"Bull","Base","Bear"},0),$BK$70,$BL$70,$BM$70) | BA70: =CHOOSE(MATCH($BB$2,{"Bull","Base","Bear"},0),$BK$71,$BL$71,$BM$71) | BB70: 2025 IFRS 2.6% ($1.1bn / $42bn); US GAAP lower (leases expensed). Deck: ~8x EV / 2027E Adj. EBITDA incl. >$1.2bn synergies ⇒ ~$1.2bn standalone 2027E. Lever DH_M. | BJ70: 2029E | BK70: =BL70+$BK$67 | BL70: 0.029 | BM70: =BL70+$BM$67
B71: (+) Synergies realised (>$1.2bn annualised within 18 months of closing) | AX71: =$BL$21*MIN(1,MAX(0,CHOOSE(MATCH($BB$2,{"Bull","Base","Bear"},0),$BK$74,$BL$74,$BM$74)))*AX64/365 | AY71: =$BL$21*MIN(1,MAX(0,CHOOSE(MATCH($BB$2,{"Bull","Base","Bear"},0),$BK$75,$BL$75,$BM$75)))*AY64/365 | AZ71: =$BL$21*MIN(1,MAX(0,CHOOSE(MATCH($BB$2,{"Bull","Base","Bear"},0),$BK$76,$BL$76,$BM$76)))*AZ64/365 | BA71: =$BL$21*MIN(1,MAX(0,CHOOSE(MATCH($BB$2,{"Bull","Base","Bear"},0),$BK$77,$BL$77,$BM$77)))*BA64/365 | BB71: Deck slide 11: annualised synergies of over $1.2bn within 18 months of closing. Realisation % per scenario lever DH_SYN. | BJ71: 2030E | BK71: =BL71+$BK$67 | BL71: 0.032 | BM71: =BL71+$BM$67
B72: Adjusted EBITDA contribution | AX72: =AX67*AX70+AX71 | AY72: =AY67*AY70+AY71 | AZ72: =AZ67*AZ70+AZ71 | BA72: =BA67*BA70+BA71
B73: Adjusted EBITDA % of Gross Bookings | AX73: =IFERROR(AX72/AX67,"") | AY73: =IFERROR(AY72/AY67,"") | AZ73: =IFERROR(AZ72/AZ67,"") | BA73: =IFERROR(BA72/BA67,"") | BJ73: DH_SYN (synergy realisation % of run-rate) | BK73: 0.25 | BL73: Δ → | BM73: -0.25 | BN73: Run-rate within 18 months of closing (Q4/27 close → full run-rate 2029E). Capped at 100%.
B74: D&A excl. purchase accounting % of Gross Bookings (assumption) | AX74: 0.008 | AY74: =AX74 | AZ74: =AY74 | BA74: =AZ74 | BJ74: 2027E | BK74: =BL74+$BK$73 | BL74: 0.1 | BM74: =BL74+$BM$73
B75: (−) D&A excl. purchase accounting | AX75: =AX67*AX74 | AY75: =AY67*AY74 | AZ75: =AZ67*AZ74 | BA75: =BA67*BA74 | BJ75: 2028E | BK75: =BL75+$BK$73 | BL75: 0.6 | BM75: =BL75+$BM$73
B76: Stock-based compensation % of Gross Bookings (assumption) | AX76: 0.002 | AY76: =AX76 | AZ76: =AY76 | BA76: =AZ76 | BJ76: 2029E | BK76: =BL76+$BK$73 | BL76: 1 | BM76: =BL76+$BM$73
B77: (−) Stock-based compensation | AX77: =AX67*AX76 | AY77: =AY67*AY76 | AZ77: =AZ67*AZ76 | BA77: =BA67*BA76 | BJ77: 2030E | BK77: =BL77+$BK$73 | BL77: 1 | BM77: =BL77+$BM$73
B78: Segment Operating Income (Delivery Hero) | AX78: =AX72-AX75-AX77 | AY78: =AY72-AY75-AY77 | AZ78: =AZ72-AZ75-AZ77 | BA78: =BA72-BA75-BA77
B79: Memo: amortization of acquired DH intangibles (PPA; excluded from Non-GAAP) | AX79: =IFERROR($AX$392/$AX$393*AX64/365,0) | AY79: =IFERROR($AX$392/$AX$393*AY64/365,0) | AZ79: =IFERROR($AX$392/$AX$393*AZ64/365,0) | BA79: =IFERROR($AX$392/$AX$393*BA64/365,0) | BJ79: MA (bolt-on acquisitions, $m) | BK79: 1000 | BL79: Δ → | BM79: -1000 | BN79: Base: no bolt-ons while integrating Delivery Hero (2027–28E), $1bn p.a. thereafter. Floored at 0.
B80: Memo: net income attributable to Delivery Hero minority holders (NCI) | AX80: =(1-$AX$384)*(AX78-AX79)*(1-AX163) | AY80: =(1-$AX$384)*(AY78-AY79)*(1-AY163) | AZ80: =(1-$AX$384)*(AZ78-AZ79)*(1-AZ163) | BA80: =(1-$AX$384)*(BA78-BA79)*(1-BA163) | BB80: (1 − Uber ownership) × (DH Segment OI − PPA amortization) × (1 − tax). Simplified: DH interest sits in Uber group debt. | BJ80: 2027E | BK80: =BL80+$BK$79 | BL80: 0 | BM80: =BL80+$BM$79
BJ81: 2028E | BK81: =BL81+$BK$79 | BL81: 0 | BM81: =BL81+$BM$79
B82: Future acquisitions (M&A lever — bolt-ons, unallocated; deals close mid-year) | BB82: M&A LEVER — acquired revenue = spend ÷ EV/revenue; mid-year convention | BJ82: 2029E | BK82: =BL82+$BK$79 | BL82: 1000 | BM82: =BL82+$BM$79
B83: Acquisition spend (USDm, scenario) | AW83: 0 | AX83: =MAX(0,CHOOSE(MATCH($BB$2,{"Bull","Base","Bear"},0),$BK$80,$BL$80,$BM$80)) | AY83: =MAX(0,CHOOSE(MATCH($BB$2,{"Bull","Base","Bear"},0),$BK$81,$BL$81,$BM$81)) | AZ83: =MAX(0,CHOOSE(MATCH($BB$2,{"Bull","Base","Bear"},0),$BK$82,$BL$82,$BM$82)) | BA83: =MAX(0,CHOOSE(MATCH($BB$2,{"Bull","Base","Bear"},0),$BK$83,$BL$83,$BM$83)) | BB83: Scenario lever MA. Uber deployed $0.1–2.7bn p.a. on acquisitions 2020–25 (Careem, Postmates, Transplace, Drizly, Trendyol Go) plus Delivery Hero (2027). | BJ83: 2030E | BK83: =BL83+$BK$79 | BL83: 1000 | BM83: =BL83+$BM$79
B84: Purchase multiple — EV / revenue (x) | AW84: 0 | AX84: 2.5 | AY84: 2.5 | AZ84: 2.5 | BA84: 2.5
B85: Annualised revenue acquired in the year | AW85: 0 | AX85: =IFERROR(AX83/AX84,0) | AY85: =IFERROR(AY83/AY84,0) | AZ85: =IFERROR(AZ83/AZ84,0) | BA85: =IFERROR(BA83/BA84,0)
B86: Growth of acquired businesses after acquisition % | AW86: 0 | AX86: 0.1 | AY86: 0.1 | AZ86: 0.1 | BA86: 0.1
B87: Run-rate revenue of businesses acquired (year end) | AW87: 0 | AX87: =AW87*(1+AX86)+AX85 | AY87: =AX87*(1+AY86)+AY85 | AZ87: =AY87*(1+AZ86)+AZ85 | BA87: =AZ87*(1+BA86)+BA85
B88: Revenue from future acquisitions | AW88: 0 | AX88: =AW87*(1+AX86)+0.5*AX85 | AY88: =AX87*(1+AY86)+0.5*AY85 | AZ88: =AY87*(1+AZ86)+0.5*AZ85 | BA88: =AZ87*(1+BA86)+0.5*BA85
B89: Segment OI margin of acquired businesses % of revenue | AW89: 0 | AX89: 0.05 | AY89: 0.05 | AZ89: 0.05 | BA89: 0.05
B90: Segment Operating Income from future acquisitions | AW90: 0 | AX90: =AX88*AX89 | AY90: =AY88*AY89 | AZ90: =AZ88*AZ89 | BA90: =BA88*BA89
B91: D&A of acquired businesses % of revenue (excl. intangibles) | AW91: 0 | AX91: 0.02 | AY91: 0.02 | AZ91: 0.02 | BA91: 0.02
B92: D&A from future acquisitions | AW92: 0 | AX92: =AX88*AX91 | AY92: =AY88*AY91 | AZ92: =AZ88*AZ91 | BA92: =BA88*BA91
B93: Acquired intangibles % of spend | AW93: 0 | AX93: 0.25 | AY93: 0.25 | AZ93: 0.25 | BA93: 0.25
B94: Intangible amortization life (years) | AW94: 0 | AX94: 8 | AY94: 8 | AZ94: 8 | BA94: 8
B95: Cumulative acquired intangibles (gross) | AW95: 0 | AX95: =AW95+AX83*AX93 | AY95: =AX95+AY83*AY93 | AZ95: =AY95+AZ83*AZ93 | BA95: =AZ95+BA83*BA93
B96: Amortization of future-acquisition intangibles (excluded from Non-GAAP) | AW96: 0 | AX96: =(AW95+0.5*AX83*AX93)/AX94 | AY96: =(AX95+0.5*AY83*AY93)/AY94 | AZ96: =(AY95+0.5*AZ83*AZ93)/AZ94 | BA96: =(AZ95+0.5*BA83*BA93)/BA94
B98: Group total → Non-GAAP Operating Income → outlook calibration | BB98: GROUP TOTAL (CONSOLIDATED) — modelling logic
B99: Gross Bookings — total (incl. Delivery Hero from closing) | C99: =C19 | D99: =D19 | E99: =E19 | F99: =F19 | G99: =G19 | H99: =H19 | I99: =I19 | J99: =J19 | ... AT99: =AT19 | AU99: =AU19+N(AU67) | AV99: =AV19+N(AV67) | AW99: =AW19+N(AW67) | AX99: =AX19+N(AX67) | AY99: =AY19+N(AY67) | AZ99: =AZ19+N(AZ67) | BA99: =BA19+N(BA67) | BD99: =IFERROR((BA99/AR99)^(1/5)-1,"") | BE99: =IFERROR((AR99/S99)^(1/5)-1,"") | BF99: =IFERROR((AR99/I99)^(1/7)-1,"") | BG99: =IFERROR((AR99/C99)^(1/9)-1,"")
B100: Gross Bookings y/y % | D100: =IF(AND(ISNUMBER(D99),ISNUMBER(C99)),IFERROR(D99/C99-1,""),"") | I100: =IF(AND(ISNUMBER(I99),ISNUMBER(D99)),IFERROR(I99/D99-1,""),"") | J100: =IF(AND(ISNUMBER(J99),ISNUMBER(E99)),IFERROR(J99/E99-1,""),"") | K100: =IF(AND(ISNUMBER(K99),ISNUMBER(F99)),IFERROR(K99/F99-1,""),"") | L100: =IF(AND(ISNUMBER(L99),ISNUMBER(G99)),IFERROR(L99/G99-1,""),"") | M100: =IF(AND(ISNUMBER(M99),ISNUMBER(H99)),IFERROR(M99/H99-1,""),"") | N100: =IF(AND(ISNUMBER(N99),ISNUMBER(I99)),IFERROR(N99/I99-1,""),"") | O100: =IF(AND(ISNUMBER(O99),ISNUMBER(J99)),IFERROR(O99/J99-1,""),"") | P100: =IF(AND(ISNUMBER(P99),ISNUMBER(K99)),IFERROR(P99/K99-1,""),"") | ... AT100: =IF(AND(ISNUMBER(AT99),ISNUMBER(AO99)),IFERROR(AT99/AO99-1,""),"") | AU100: =IFERROR(AU99/AP99-1,"") | AV100: =IFERROR(AV99/AQ99-1,"") | AW100: =IFERROR(AW99/AR99-1,"") | AX100: =IFERROR(AX99/AW99-1,"") | AY100: =IFERROR(AY99/AX99-1,"") | AZ100: =IFERROR(AZ99/AY99-1,"") | BA100: =IFERROR(BA99/AZ99-1,"")
B101: Revenue (segment build) | C101: =N(C27)+N(C39)+N(C50)+N(C56)+N(C57)+N(C59) | D101: =N(D27)+N(D39)+N(D50)+N(D56)+N(D57)+N(D59) | E101: =N(E27)+N(E39)+N(E50)+N(E56)+N(E57)+N(E59) | F101: =N(F27)+N(F39)+N(F50)+N(F56)+N(F57)+N(F59) | G101: =N(G27)+N(G39)+N(G50)+N(G56)+N(G57)+N(G59) | H101: =N(H27)+N(H39)+N(H50)+N(H56)+N(H57)+N(H59) | I101: =N(I27)+N(I39)+N(I50)+N(I56)+N(I57)+N(I59) | J101: =N(J27)+N(J39)+N(J50)+N(J56)+N(J57)+N(J59) | ... AT101: =N(AT27)+N(AT39)+N(AT50)+N(AT56)+N(AT57)+N(AT59) | AU101: =N(AU27)+N(AU39)+N(AU50)+N(AU69)+N(AU88) | AV101: =N(AV27)+N(AV39)+N(AV50)+N(AV69)+N(AV88) | AW101: =N(AW27)+N(AW39)+N(AW50)+N(AW69)+N(AW88) | AX101: =N(AX27)+N(AX39)+N(AX50)+N(AX69)+N(AX88) | AY101: =N(AY27)+N(AY39)+N(AY50)+N(AY69)+N(AY88) | AZ101: =N(AZ27)+N(AZ39)+N(AZ50)+N(AZ69)+N(AZ88) | BA101: =N(BA27)+N(BA39)+N(BA50)+N(BA69)+N(BA88)
B102: Revenue ÷ Gross Bookings % (group take rate) | C102: =IF(AND(ISNUMBER(C101),ISNUMBER(C99)),IFERROR(C101/C99,""),"") | D102: =IF(AND(ISNUMBER(D101),ISNUMBER(D99)),IFERROR(D101/D99,""),"") | E102: =IF(AND(ISNUMBER(E101),ISNUMBER(E99)),IFERROR(E101/E99,""),"") | F102: =IF(AND(ISNUMBER(F101),ISNUMBER(F99)),IFERROR(F101/F99,""),"") | G102: =IF(AND(ISNUMBER(G101),ISNUMBER(G99)),IFERROR(G101/G99,""),"") | H102: =IF(AND(ISNUMBER(H101),ISNUMBER(H99)),IFERROR(H101/H99,""),"") | I102: =IF(AND(ISNUMBER(I101),ISNUMBER(I99)),IFERROR(I101/I99,""),"") | J102: =IF(AND(ISNUMBER(J101),ISNUMBER(J99)),IFERROR(J101/J99,""),"") | ... AT102: =IF(AND(ISNUMBER(AT101),ISNUMBER(AT99)),IFERROR(AT101/AT99,""),"") | AU102: =IFERROR(AU101/AU99,"") | AV102: =IFERROR(AV101/AV99,"") | AW102: =IFERROR(AW101/AW99,"") | AX102: =IFERROR(AX101/AX99,"") | AY102: =IFERROR(AY101/AY99,"") | AZ102: =IFERROR(AZ101/AZ99,"") | BA102: =IFERROR(BA101/BA99,"")
...

Sheet Bull-Base-Bear
B2: Uber Technologies (UBER) — Bull / Base / Bear Case P&L Summary | J2: Share price ($): | K2: =Model!$AW$463
B3: Adjusted figures (company definitions: Adjusted EBITDA; Non-GAAP OI / Net Income / EPS from Q1/26, recast to Q1/24). Base block links live to the Model (switch = Model scenario cell); Bull / Bear blocks are value snapshots of the Model run with the switch set to Bull / Bear. 2027E+ include Delivery Hero from 1-Oct-2027. | J3: As of: | K3: =TODAY()
B5: Scenario: | C5: =Model!$BB$2 | N5: Scenario: | O5: Bull | P5: Snapshot (values) — Model run with switch = Bull | Z5: Scenario: | AA5: Bear | AB5: Snapshot (values) — Model run with switch = Bear
B7: (USDm, except EPS and shares) | C7: 2025A | D7: 2026E | E7: 2027E | F7: 2028E | G7: 2029E | H7: 2030E | I7: 25-'30 CAGR | J7: LT Hist Avg | K7: LT Hist Min | L7: LT Hist Max | N7: (USDm, except EPS and shares) | O7: 2025A | P7: 2026E | Q7: 2027E | R7: 2028E | S7: 2029E | T7: 2030E | U7: 25-'30 CAGR | V7: LT Hist Avg | W7: LT Hist Min | X7: LT Hist Max | Z7: (USDm, except EPS and shares) | AA7: 2025A | AB7: 2026E | AC7: 2027E | AD7: 2028E | AE7: 2029E | AF7: 2030E | AG7: 25-'30 CAGR | AH7: LT Hist Avg | AI7: LT Hist Min | AJ7: LT Hist Max
B9: Gross Bookings | C9: =Model!AR99 | D9: =Model!AW99 | E9: =Model!AX99 | F9: =Model!AY99 | G9: =Model!AZ99 | H9: =Model!BA99 | I9: =IFERROR((H9/C9)^(1/5)-1,"n/m") | N9: Gross Bookings | O9: 193454 | P9: 237564.77 | Q9: 295432.85 | R9: 391596.82 | S9: 454686.55 | T9: 524208.22 | U9: 0.22063333 | Z9: Gross Bookings | AA9: 193454 | AB9: 233381.42 | AC9: 275630.8 | AD9: 347073.29 | AE9: 382017.16 | AF9: 417374.89 | AG9: 0.1662448
B10: Gross Bookings y/y % | D10: =IFERROR(D9/C9-1,"") | E10: =IFERROR(E9/D9-1,"") | F10: =IFERROR(F9/E9-1,"") | G10: =IFERROR(G9/F9-1,"") | H10: =IFERROR(H9/G9-1,"") | N10: Gross Bookings y/y % | P10: 0.22801684 | Q10: 0.24358863 | R10: 0.32550198 | S10: 0.16110889 | T10: 0.15290021 | Z10: Gross Bookings y/y % | AB10: 0.20639234 | AC10: 0.18103143 | AD10: 0.25919632 | AE10: 0.10068154 | AF10: 0.092555357
B11: Revenue | C11: =Model!AR148 | D11: =Model!AW148 | E11: =Model!AX148 | F11: =Model!AY148 | G11: =Model!AZ148 | H11: =Model!BA148 | I11: =IFERROR((H11/C11)^(1/5)-1,"n/m") | N11: Revenue | O11: 52017 | P11: 57939.362 | Q11: 71860.094 | R11: 95151.25 | S11: 110662.16 | T11: 127909.07 | U11: 0.19715727 | Z11: Revenue | AA11: 52017 | AB11: 57004.602 | AC11: 66838.379 | AD11: 83632.065 | AE11: 91607.39 | AF11: 99628.616 | AG11: 0.13880079
B12: Revenue y/y % | D12: =IFERROR(D11/C11-1,"") | E12: =IFERROR(E11/D11-1,"") | F12: =IFERROR(F11/E11-1,"") | G12: =IFERROR(G11/F11-1,"") | H12: =IFERROR(H11/G11-1,"") | N12: Revenue y/y % | P12: 0.11385436 | Q12: 0.2402638 | R12: 0.32411809 | S12: 0.16301316 | T12: 0.15585194 | Z12: Revenue y/y % | AB12: 0.095884067 | AC12: 0.17250848 | AD12: 0.25125814 | AE12: 0.095362041 | AF12: 0.087560907
B13: Adjusted EBITDA | C13: =Model!AR203 | D13: =Model!AW203 | E13: =Model!AX203 | F13: =Model!AY203 | G13: =Model!AZ203 | H13: =Model!BA203 | I13: =IFERROR((H13/C13)^(1/5)-1,"n/m") | N13: Adjusted EBITDA | O13: 8730 | P13: 11573.84 | Q13: 16038.224 | R13: 22860.194 | S13: 28311.308 | T13: 34189.508 | U13: 0.31394057 | Z13: Adjusted EBITDA | AA13: 8730 | AB13: 11364.412 | AC13: 13362.215 | AD13: 16507.039 | AE13: 19043.191 | AF13: 21156.048 | AG13: 0.1936694
B14: Adjusted EBITDA % of Gross Bookings | C14: =IFERROR(C13/C9,"") | D14: =IFERROR(D13/D9,"") | E14: =IFERROR(E13/E9,"") | F14: =IFERROR(F13/F9,"") | G14: =IFERROR(G13/G9,"") | H14: =IFERROR(H13/H9,"") | J14: =IFERROR(AVERAGE(Model!C254,Model!D254,Model!I254,Model!N254,Model!S254,Model!X254,Model!AC254,Model!AH254,Model!AM254,Model!AR254),"") | K14: =IFERROR(MIN(Model!C254,Model!D254,Model!I254,Model!N254,Model!S254,Model!X254,Model!AC254,Model!AH254,Model!AM254,Model!AR254),"") | L14: =IFERROR(MAX(Model!C254,Model!D254,Model!I254,Model!N254,Model!S254,Model!X254,Model!AC254,Model!AH254,Model!AM254,Model!AR254),"") | N14: Adjusted EBITDA % of Gross Bookings | O14: 0.045127007 | P14: 0.04871867 | Q14: 0.054287205 | R14: 0.058376864 | S14: 0.06226555 | T14: 0.065221235 | V14: =IFERROR(AVERAGE(Model!C254,Model!D254,Model!I254,Model!N254,Model!S254,Model!X254,Model!AC254,Model!AH254,Model!AM254,Model!AR254),"") | W14: =IFERROR(MIN(Model!C254,Model!D254,Model!I254,Model!N254,Model!S254,Model!X254,Model!AC254,Model!AH254,Model!AM254,Model!AR254),"") | X14: =IFERROR(MAX(Model!C254,Model!D254,Model!I254,Model!N254,Model!S254,Model!X254,Model!AC254,Model!AH254,Model!AM254,Model!AR254),"") | Z14: Adjusted EBITDA % of Gross Bookings | AA14: 0.045127007 | AB14: 0.048694585 | AC14: 0.048478671 | AD14: 0.047560672 | AE14: 0.049849047 | AF14: 0.050688359 | AH14: =IFERROR(AVERAGE(Model!C254,Model!D254,Model!I254,Model!N254,Model!S254,Model!X254,Model!AC254,Model!AH254,Model!AM254,Model!AR254),"") | AI14: =IFERROR(MIN(Model!C254,Model!D254,Model!I254,Model!N254,Model!S254,Model!X254,Model!AC254,Model!AH254,Model!AM254,Model!AR254),"") | AJ14: =IFERROR(MAX(Model!C254,Model!D254,Model!I254,Model!N254,Model!S254,Model!X254,Model!AC254,Model!AH254,Model!AM254,Model!AR254),"")
B16: Income from Operations (GAAP) | C16: =Model!AR157 | D16: =Model!AW157 | E16: =Model!AX157 | F16: =Model!AY157 | G16: =Model!AZ157 | H16: =Model!BA157 | I16: =IFERROR((H16/C16)^(1/5)-1,"n/m") | N16: Income from Operations (GAAP) | O16: 5565 | P16: 8151.2705 | Q16: 11595.291 | R16: 16971.072 | S16: 21950.001 | T16: 27061.4 | U16: 0.37207237 | Z16: Income from Operations (GAAP) | AA16: 5565 | AB16: 7976.7159 | AC16: 9183.4686 | AD16: 11217.63 | AE16: 13675.335 | AF16: 15497.259 | AG16: 0.22732037
B17: Income from operations y/y % | D17: =IFERROR(D16/C16-1,"") | E17: =IFERROR(E16/D16-1,"") | F17: =IFERROR(F16/E16-1,"") | G17: =IFERROR(G16/F16-1,"") | H17: =IFERROR(H16/G16-1,"") | N17: Income from operations y/y % | P17: 0.46473863 | Q17: 0.42251337 | R17: 0.46361757 | S17: 0.29337738 | T17: 0.23286558 | Z17: Income from operations y/y % | AB17: 0.43337213 | AC17: 0.1512844 | AD17: 0.22150255 | AE17: 0.21909307 | AF17: 0.13322697
B18: Operating margin (GAAP) % of revenue | C18: =IFERROR(C16/C11,"") | D18: =IFERROR(D16/D11,"") | E18: =IFERROR(E16/E11,"") | F18: =IFERROR(F16/F11,"") | G18: =IFERROR(G16/G11,"") | H18: =IFERROR(H16/H11,"") | J18: =IFERROR(AVERAGE(Model!C258,Model!D258,Model!I258,Model!N258,Model!S258,Model!X258,Model!AC258,Model!AH258,Model!AM258,Model!AR258),"") | K18: =IFERROR(MIN(Model!C258,Model!D258,Model!I258,Model!N258,Model!S258,Model!X258,Model!AC258,Model!AH258,Model!AM258,Model!AR258),"") | L18: =IFERROR(MAX(Model!C258,Model!D258,Model!I258,Model!N258,Model!S258,Model!X258,Model!AC258,Model!AH258,Model!AM258,Model!AR258),"") | N18: Operating margin (GAAP) % of revenue | O18: 0.10698426 | P18: 0.14068623 | Q18: 0.16135926 | R18: 0.1783589 | S18: 0.19835146 | T18: 0.21156749 | V18: =IFERROR(AVERAGE(Model!C258,Model!D258,Model!I258,Model!N258,Model!S258,Model!X258,Model!AC258,Model!AH258,Model!AM258,Model!AR258),"") | W18: =IFERROR(MIN(Model!C258,Model!D258,Model!I258,Model!N258,Model!S258,Model!X258,Model!AC258,Model!AH258,Model!AM258,Model!AR258),"") | X18: =IFERROR(MAX(Model!C258,Model!D258,Model!I258,Model!N258,Model!S258,Model!X258,Model!AC258,Model!AH258,Model!AM258,Model!AR258),"") | Z18: Operating margin (GAAP) % of revenue | AA18: 0.10698426 | AB18: 0.13993109 | AC18: 0.13739814 | AD18: 0.13413073 | AE18: 0.14928201 | AF18: 0.15555028 | AH18: =IFERROR(AVERAGE(Model!C258,Model!D258,Model!I258,Model!N258,Model!S258,Model!X258,Model!AC258,Model!AH258,Model!AM258,Model!AR258),"") | AI18: =IFERROR(MIN(Model!C258,Model!D258,Model!I258,Model!N258,Model!S258,Model!X258,Model!AC258,Model!AH258,Model!AM258,Model!AR258),"") | AJ18: =IFERROR(MAX(Model!C258,Model!D258,Model!I258,Model!N258,Model!S258,Model!X258,Model!AC258,Model!AH258,Model!AM258,Model!AR258),"")
B20: Non-GAAP Net Income (attributable to common) | C20: =Model!AR234 | D20: =Model!AW234 | E20: =Model!AX234 | F20: =Model!AY234 | G20: =Model!AZ234 | H20: =Model!BA234 | I20: =IFERROR((H20/C20)^(1/5)-1,"n/m") | N20: Non-GAAP Net Income (attributable to common) | O20: 5200 | P20: 6827.3247 | Q20: 9672.5073 | R20: 13677.707 | S20: 17155.551 | T20: 20876.899 | U20: 0.32048213 | Z20: Non-GAAP Net Income (attributable to common) | AA20: 5200 | AB20: 6694.6632 | AC20: 7931.3536 | AD20: 9750.3077 | AE20: 11337.929 | AF20: 12640.498 | AG20: 0.19440653
B22: FDSO (m) | C22: =Model!AR175 | D22: =Model!AW175 | E22: =Model!AX175 | F22: =Model!AY175 | G22: =Model!AZ175 | H22: =Model!BA175 | I22: =IFERROR((H22/C22)^(1/5)-1,"n/m") | N22: FDSO (m) | O22: 2119.689 | P22: 2051.7167 | Q22: 1978.3392 | R22: 1821.9269 | S22: 1599.4638 | T22: 1346.9585 | U22: -0.086693777 | Z22: FDSO (m) | AA22: 2119.689 | AB22: 2060.5232 | AC22: 2068.1671 | AD22: 2013.7433 | AE22: 1888.4147 | AF22: 1747.5016 | AG22: -0.037880349
B24: Non-GAAP EPS — Diluted ($) | C24: =Model!AR236 | D24: =Model!AW236 | E24: =Model!AX236 | F24: =Model!AY236 | G24: =Model!AZ236 | H24: =Model!BA236 | I24: =IFERROR((H24/C24)^(1/5)-1,"n/m") | N24: Non-GAAP EPS — Diluted ($) | O24: 2.4531901 | P24: 3.3276158 | Q24: 4.8892058 | R24: 7.5072753 | S24: 10.725814 | T24: 15.499288 | U24: 0.44582627 | Z24: Non-GAAP EPS — Diluted ($) | AA24: 2.4531901 | AB24: 3.2490113 | AC24: 3.8349676 | AD24: 4.8418822 | AE24: 6.0039401 | AF24: 7.233469 | AG24: 0.24143243
B25: EPS y/y % | D25: =IFERROR(D24/C24-1,"") | E25: =IFERROR(E24/D24-1,"") | F25: =IFERROR(F24/E24-1,"") | G25: =IFERROR(G24/F24-1,"") | H25: =IFERROR(H24/G24-1,"") | N25: EPS y/y % | P25: 0.35644433 | Q25: 0.46928195 | R25: 0.53547952 | S25: 0.4287226 | T25: 0.44504541 | Z25: EPS y/y % | AB25: 0.32440261 | AC25: 0.18034909 | AD25: 0.26256145 | AE25: 0.24000128 | AF25: 0.20478699
B27: P / E (x) — assumed (Non-GAAP EPS) | G27: 24 | H27: 24 | N27: P / E (x) — assumed (Non-GAAP EPS) | S27: 28 | T27: 28 | Z27: P / E (x) — assumed (Non-GAAP EPS) | AE27: 18 | AF27: 18
B28: Price Target ($) | G28: =G27*G24 | H28: =H27*H24 | N28: Price Target ($) | S28: =S27*S24 | T28: =T27*T24 | Z28: Price Target ($) | AE28: =AE27*AE24 | AF28: =AF27*AF24
B29: Upside / (Downside) vs current | G29: =IFERROR(G28/$K$2-1,"") | H29: =IFERROR(H28/$K$2-1,"") | N29: Upside / (Downside) vs current | S29: =IFERROR(S28/$K$2-1,"") | T29: =IFERROR(T28/$K$2-1,"") | Z29: Upside / (Downside) vs current | AE29: =IFERROR(AE28/$K$2-1,"") | AF29: =IFERROR(AF28/$K$2-1,"")
B30: IRR (to Dec-Y-1) | G30: =IFERROR((G28/$K$2)^(1/((DATE(2029-1,12,31)-$K$3)/365.25))-1,"") | H30: =IFERROR((H28/$K$2)^(1/((DATE(2030-1,12,31)-$K$3)/365.25))-1,"") | N30: IRR (to Dec-Y-1) | S30: =IFERROR((S28/$K$2)^(1/((DATE(2029-1,12,31)-$K$3)/365.25))-1,"") | T30: =IFERROR((T28/$K$2)^(1/((DATE(2030-1,12,31)-$K$3)/365.25))-1,"") | Z30: IRR (to Dec-Y-1) | AE30: =IFERROR((AE28/$K$2)^(1/((DATE(2029-1,12,31)-$K$3)/365.25))-1,"") | AF30: =IFERROR((AF28/$K$2)^(1/((DATE(2030-1,12,31)-$K$3)/365.25))-1,"")
B32: Free Cash Flow | C32: =Model!AR293 | D32: =Model!AW293 | E32: =Model!AX293 | F32: =Model!AY293 | G32: =Model!AZ293 | H32: =Model!BA293 | I32: =IFERROR((H32/C32)^(1/5)-1,"n/m") | N32: Free Cash Flow | O32: 9763 | P32: 11717.565 | Q32: 15485.048 | R32: 21065.219 | S32: 25830.601 | T32: 30688.424 | U32: 0.2574139 | Z32: Free Cash Flow | AA32: 9763 | AB32: 11236.122 | AC32: 12354.391 | AD32: 14943.689 | AE32: 17157.685 | AF32: 18775.391 | AG32: 0.1397278
B33: FCF % of revenue | C33: =IFERROR(C32/C11,"") | D33: =IFERROR(D32/D11,"") | E33: =IFERROR(E32/E11,"") | F33: =IFERROR(F32/F11,"") | G33: =IFERROR(G32/G11,"") | H33: =IFERROR(H32/H11,"") | J33: =IFERROR(AVERAGE(Model!C298,Model!D298,Model!I298,Model!N298,Model!S298,Model!X298,Model!AC298,Model!AH298,Model!AM298,Model!AR298),"") | K33: =IFERROR(MIN(Model!C298,Model!D298,Model!I298,Model!N298,Model!S298,Model!X298,Model!AC298,Model!AH298,Model!AM298,Model!AR298),"") | L33: =IFERROR(MAX(Model!C298,Model!D298,Model!I298,Model!N298,Model!S298,Model!X298,Model!AC298,Model!AH298,Model!AM298,Model!AR298),"") | N33: FCF % of revenue | O33: 0.18768864 | P33: 0.20223842 | Q33: 0.21548884 | R33: 0.22138667 | S33: 0.23341856 | T33: 0.23992375 | V33: =IFERROR(AVERAGE(Model!C298,Model!D298,Model!I298,Model!N298,Model!S298,Model!X298,Model!AC298,Model!AH298,Model!AM298,Model!AR298),"") | W33: =IFERROR(MIN(Model!C298,Model!D298,Model!I298,Model!N298,Model!S298,Model!X298,Model!AC298,Model!AH298,Model!AM298,Model!AR298),"") | X33: =IFERROR(MAX(Model!C298,Model!D298,Model!I298,Model!N298,Model!S298,Model!X298,Model!AC298,Model!AH298,Model!AM298,Model!AR298),"") | Z33: FCF % of revenue | AA33: 0.18768864 | AB33: 0.19710904 | AC33: 0.18483978 | AD33: 0.17868373 | AE33: 0.18729586 | AF33: 0.1884538 | AH33: =IFERROR(AVERAGE(Model!C298,Model!D298,Model!I298,Model!N298,Model!S298,Model!X298,Model!AC298,Model!AH298,Model!AM298,Model!AR298),"") | AI33: =IFERROR(MIN(Model!C298,Model!D298,Model!I298,Model!N298,Model!S298,Model!X298,Model!AC298,Model!AH298,Model!AM298,Model!AR298),"") | AJ33: =IFERROR(MAX(Model!C298,Model!D298,Model!I298,Model!N298,Model!S298,Model!X298,Model!AC298,Model!AH298,Model!AM298,Model!AR298),"")
B34: FCF / share ($) | C34: =IFERROR(C32/C22,"") | D34: =IFERROR(D32/D22,"") | E34: =IFERROR(E32/E22,"") | F34: =IFERROR(F32/F22,"") | G34: =IFERROR(G32/G22,"") | H34: =IFERROR(H32/H22,"") | N34: FCF / share ($) | O34: 4.6058644 | P34: 5.7111029 | Q34: 7.827297 | R34: 11.562055 | S34: 16.149538 | T34: 22.783495 | Z34: FCF / share ($) | AA34: 4.6058644 | AB34: 5.4530434 | AC34: 5.9735943 | AD34: 7.4208513 | AE34: 9.0857613 | AF34: 10.744134
B35: FCF Yield (on PT) | G35: =IFERROR(G34/G$28,"") | H35: =IFERROR(H34/H$28,"") | N35: FCF Yield (on PT) | S35: =IFERROR(S34/S$28,"") | T35: =IFERROR(T34/T$28,"") | Z35: FCF Yield (on PT) | AE35: =IFERROR(AE34/AE$28,"") | AF35: =IFERROR(AF34/AF$28,"")
B36: Adjusted EBITDA — pro forma (2027E incl. Delivery Hero full year) | C36: =Model!AR216 | D36: =Model!AW216 | E36: =Model!AX216 | F36: =Model!AY216 | G36: =Model!AZ216 | H36: =Model!BA216 | I36: =IFERROR((H36/C36)^(1/5)-1,"n/m") | N36: Adjusted EBITDA — pro forma (2027E incl. Delivery Hero full year) | O36: 8730 | P36: 11573.84 | Q36: 17131.546 | R36: 22860.194 | S36: 28311.308 | T36: 34189.508 | U36: 0.31394057 | Z36: Adjusted EBITDA — pro forma (2027E incl. Delivery Hero full year) | AA36: 8730 | AB36: 11364.412 | AC36: 14027.745 | AD36: 16507.039 | AE36: 19043.191 | AF36: 21156.048 | AG36: 0.1936694
B37: Adjusted EBITDA (pro forma) % of Gross Bookings | C37: =IFERROR(C36/C9,"") | D37: =IFERROR(D36/D9,"") | E37: =IFERROR(E36/E9,"") | F37: =IFERROR(F36/F9,"") | G37: =IFERROR(G36/G9,"") | H37: =IFERROR(H36/H9,"") | J37: =IFERROR(AVERAGE(Model!C254,Model!D254,Model!I254,Model!N254,Model!S254,Model!X254,Model!AC254,Model!AH254,Model!AM254,Model!AR254),"") | K37: =IFERROR(MIN(Model!C254,Model!D254,Model!I254,Model!N254,Model!S254,Model!X254,Model!AC254,Model!AH254,Model!AM254,Model!AR254),"") | L37: =IFERROR(MAX(Model!C254,Model!D254,Model!I254,Model!N254,Model!S254,Model!X254,Model!AC254,Model!AH254,Model!AM254,Model!AR254),"") | N37: Adjusted EBITDA (pro forma) % of Gross Bookings | O37: 0.045127007 | P37: 0.04871867 | Q37: 0.057987953 | R37: 0.058376864 | S37: 0.06226555 | T37: 0.065221235 | V37: =IFERROR(AVERAGE(Model!C254,Model!D254,Model!I254,Model!N254,Model!S254,Model!X254,Model!AC254,Model!AH254,Model!AM254,Model!AR254),"") | W37: =IFERROR(MIN(Model!C254,Model!D254,Model!I254,Model!N254,Model!S254,Model!X254,Model!AC254,Model!AH254,Model!AM254,Model!AR254),"") | X37: =IFERROR(MAX(Model!C254,Model!D254,Model!I254,Model!N254,Model!S254,Model!X254,Model!AC254,Model!AH254,Model!AM254,Model!AR254),"") | Z37: Adjusted EBITDA (pro forma) % of Gross Bookings | AA37: 0.045127007 | AB37: 0.048694585 | AC37: 0.050893243 | AD37: 0.047560672 | AE37: 0.049849047 | AF37: 0.050688359 | AH37: =IFERROR(AVERAGE(Model!C254,Model!D254,Model!I254,Model!N254,Model!S254,Model!X254,Model!AC254,Model!AH254,Model!AM254,Model!AR254),"") | AI37: =IFERROR(MIN(Model!C254,Model!D254,Model!I254,Model!N254,Model!S254,Model!X254,Model!AC254,Model!AH254,Model!AM254,Model!AR254),"") | AJ37: =IFERROR(MAX(Model!C254,Model!D254,Model!I254,Model!N254,Model!S254,Model!X254,Model!AC254,Model!AH254,Model!AM254,Model!AR254),"")
B39: Net Debt | C39: =Model!AR457 | D39: =Model!AW457 | E39: =Model!AX457 | F39: =Model!AY457 | G39: =Model!AZ457 | H39: =Model!BA457 | N39: Net Debt | O39: 2888 | P39: 3461.935 | Q39: 10512.193 | R39: 11430.097 | S39: 14155.654 | T39: 17094.754 | Z39: Net Debt | AA39: 2888 | AB39: 1443.3776 | AC39: 2099.1044 | AD39: 0 | AE39: 0 | AF39: 0
B40: Net Debt / Adjusted EBITDA (x) | C40: =IFERROR(C39/C36,"") | D40: =IFERROR(D39/D36,"") | E40: =IFERROR(E39/E36,"") | F40: =IFERROR(F39/F36,"") | G40: =IFERROR(G39/G36,"") | H40: =IFERROR(H39/H36,"") | N40: Net Debt / Adjusted EBITDA (x) | O40: 0.33081329 | P40: 0.29911724 | Q40: 0.61361613 | R40: 0.5 | S40: 0.5 | T40: 0.5 | Z40: Net Debt / Adjusted EBITDA (x) | AA40: 0.33081329 | AB40: 0.12700856 | AC40: 0.14963947 | AD40: 0 | AE40: 0 | AF40: 0
B41: Share repurchases ($m) | D41: =Model!AW307 | E41: =Model!AX307 | F41: =Model!AY307 | G41: =Model!AZ307 | H41: =Model!BA307 | N41: Share repurchases ($m) | P41: 3000 | Q41: 11613.786 | R41: 20958.123 | S41: 26531.158 | T41: 31602.523 | Z41: Share repurchases ($m) | AB41: 500 | AC41: 3088.5977 | AD41: 12819.585 | AE41: 17132.685 | AF41: 18750.391
B42: Implied avg buyback price ($) | D42: =Model!AW306 | E42: =Model!AX306 | F42: =Model!AY306 | G42: =Model!AZ306 | H42: =Model!BA306 | N42: Implied avg buyback price ($) | P42: 70.97 | Q42: 78.067 | R42: 85.8737 | S42: 94.46107 | T42: 103.90718 | Z42: Implied avg buyback price ($) | AB42: 70.97 | AC42: 78.067 | AD42: 85.8737 | AE42: 94.46107 | AF42: 103.90718
B43: Shares repurchased (m) | D43: =Model!AW308 | E43: =Model!AX308 | F43: =Model!AY308 | G43: =Model!AZ308 | H43: =Model!BA308 | N43: Shares repurchased (m) | P43: 42.271382 | Q43: 148.76691 | R43: 244.05753 | S43: 280.8687 | T43: 304.14187 | Z43: Shares repurchased (m) | AB43: 7.0452304 | AC43: 39.563423 | AD43: 149.28418 | AE43: 181.37297 | AF43: 180.45328
B45: ROIC | C45: =Model!AR439 | D45: =Model!AW439 | E45: =Model!AX439 | F45: =Model!AY439 | G45: =Model!AZ439 | H45: =Model!BA439 | J45: =IFERROR(AVERAGE(Model!C439,Model!D439,Model!I439,Model!N439,Model!S439,Model!X439,Model!AC439,Model!AH439,Model!AM439,Model!AR439),"") | K45: =IFERROR(MIN(Model!C439,Model!D439,Model!I439,Model!N439,Model!S439,Model!X439,Model!AC439,Model!AH439,Model!AM439,Model!AR439),"") | L45: =IFERROR(MAX(Model!C439,Model!D439,Model!I439,Model!N439,Model!S439,Model!X439,Model!AC439,Model!AH439,Model!AM439,Model!AR439),"") | N45: ROIC | O45: 0.23404352 | P45: 0.32169111 | Q45: 0.27396728 | R45: 0.45066618 | S45: 0.64243908 | T45: 0.93091451 | V45: =IFERROR(AVERAGE(Model!C439,Model!D439,Model!I439,Model!N439,Model!S439,Model!X439,Model!AC439,Model!AH439,Model!AM439,Model!AR439),"") | W45: =IFERROR(MIN(Model!C439,Model!D439,Model!I439,Model!N439,Model!S439,Model!X439,Model!AC439,Model!AH439,Model!AM439,Model!AR439),"") | X45: =IFERROR(MAX(Model!C439,Model!D439,Model!I439,Model!N439,Model!S439,Model!X439,Model!AC439,Model!AH439,Model!AM439,Model!AR439),"") | Z45: ROIC | AA45: 0.23404352 | AB45: 0.31078051 | AC45: 0.21869229 | AD45: 0.29902898 | AE45: 0.39412127 | AF45: 0.50537003 | AH45: =IFERROR(AVERAGE(Model!C439,Model!D439,Model!I439,Model!N439,Model!S439,Model!X439,Model!AC439,Model!AH439,Model!AM439,Model!AR439),"") | AI45: =IFERROR(MIN(Model!C439,Model!D439,Model!I439,Model!N439,Model!S439,Model!X439,Model!AC439,Model!AH439,Model!AM439,Model!AR439),"") | AJ45: =IFERROR(MAX(Model!C439,Model!D439,Model!I439,Model!N439,Model!S439,Model!X439,Model!AC439,Model!AH439,Model!AM439,Model!AR439),"")
B46: RONTA | C46: =Model!AR451 | D46: =Model!AW451 | E46: =Model!AX451 | F46: =Model!AY451 | G46: =Model!AZ451 | H46: =Model!BA451 | J46: =IFERROR(AVERAGE(Model!C451,Model!D451,Model!I451,Model!N451,Model!S451,Model!X451,Model!AC451,Model!AH451,Model!AM451,Model!AR451),"") | K46: =IFERROR(MIN(Model!C451,Model!D451,Model!I451,Model!N451,Model!S451,Model!X451,Model!AC451,Model!AH451,Model!AM451,Model!AR451),"") | L46: =IFERROR(MAX(Model!C451,Model!D451,Model!I451,Model!N451,Model!S451,Model!X451,Model!AC451,Model!AH451,Model!AM451,Model!AR451),"") | N46: RONTA | O46: 0.26370514 | P46: 0.26246115 | Q46: 0.55033979 | R46: 0.90785394 | S46: 1.3508575 | T46: 2.0890918 | V46: =IFERROR(AVERAGE(Model!C451,Model!D451,Model!I451,Model!N451,Model!S451,Model!X451,Model!AC451,Model!AH451,Model!AM451,Model!AR451),"") | W46: =IFERROR(MIN(Model!C451,Model!D451,Model!I451,Model!N451,Model!S451,Model!X451,Model!AC451,Model!AH451,Model!AM451,Model!AR451),"") | X46: =IFERROR(MAX(Model!C451,Model!D451,Model!I451,Model!N451,Model!S451,Model!X451,Model!AC451,Model!AH451,Model!AM451,Model!AR451),"") | Z46: RONTA | AA46: 0.26370514 | AB46: 0.23771316 | AC46: 0.29881507 | AD46: 0.35931699 | AE46: 0.44587591 | AF46: 0.53213183 | AH46: =IFERROR(AVERAGE(Model!C451,Model!D451,Model!I451,Model!N451,Model!S451,Model!X451,Model!AC451,Model!AH451,Model!AM451,Model!AR451),"") | AI46: =IFERROR(MIN(Model!C451,Model!D451,Model!I451,Model!N451,Model!S451,Model!X451,Model!AC451,Model!AH451,Model!AM451,Model!AR451),"") | AJ46: =IFERROR(MAX(Model!C451,Model!D451,Model!I451,Model!N451,Model!S451,Model!X451,Model!AC451,Model!AH451,Model!AM451,Model!AR451),"")
B48: Implied Market Cap (USDm) | G48: =G28*G22 | H48: =H28*H22 | N48: Implied Market Cap (USDm) | S48: =S28*S22 | T48: =T28*T22 | Z48: Implied Market Cap (USDm) | AE48: =AE28*AE22 | AF48: =AF28*AF22
B49: (+) Net Debt & NCI, (−) equity investments | G49: =G39+Model!AZ467+Model!AZ468 | H49: =H39+Model!BA467+Model!BA468 | N49: (+) Net Debt & NCI, (−) equity investments | S49: =S39+Model!AZ467+Model!AZ468 | T49: =T39+Model!BA467+Model!BA468 | Z49: (+) Net Debt & NCI, (−) equity investments | AE49: =AE39+Model!AZ467+Model!AZ468 | AF49: =AF39+Model!BA467+Model!BA468
B50: Implied Enterprise Value (USDm) | G50: =G48+G49 | H50: =H48+H49 | N50: Implied Enterprise Value (USDm) | S50: =S48+S49 | T50: =T48+T49 | Z50: Implied Enterprise Value (USDm) | AE50: =AE48+AE49 | AF50: =AF48+AF49
B51: Implied EV / Adjusted EBITDA (x) | G51: =IFERROR(G50/G36,"") | H51: =IFERROR(H50/H36,"") | N51: Implied EV / Adjusted EBITDA (x) | S51: =IFERROR(S50/S36,"") | T51: =IFERROR(T50/T36,"") | Z51: Implied EV / Adjusted EBITDA (x) | AE51: =IFERROR(AE50/AE36,"") | AF51: =IFERROR(AF50/AF36,"")

Sheet DCF
B2: DCF VALUATION — UBER TECHNOLOGIES (UBER)
B4: 1. WACC BUILD
B5: Risk-free rate (US 10Y govt) | C5: 0.055 | D5: Assumption (~US 10Y Treasury yield); same as the MLM model — update to market
B6: Equity risk premium | C6: 0.05 | D6: US implied ERP ~4.5–5.5% (Damodaran)
B7: Levered beta | C7: 1.2 | D7: Platform / internet peers (DoorDash, Lyft, Grab, Delivery Hero) ~1.1–1.4; Uber 5Y regression ~1.3
B8: Cost of equity | C8: =C5+C7*C6
B9: Pre-tax cost of debt | C9: 0.05 | D9: Investment grade (BBB / Baa2); Sep-2026 € notes 3.75%–5.25% (4.44% blended); $ notes 4.15%–5.35%
B10: Tax rate | C10: 0.24 | D10: Model 2027E+ effective / Non-GAAP tax rate
B11: After-tax cost of debt | C11: =C9*(1-C10)
B12: Target D/V | C12: 0.1 | D12: Gross debt ~$21bn at YE2027E (post Delivery Hero) vs ~$145bn market cap ($70.97 × ~2.04bn shares)
B13: WACC | C13: =C8*(1-C12)+C11*C12
B15: Valuation date (live) | C15: =TODAY() | D15: Periods = (Dec-31-Year − today) / 365.25; cash flows assumed at year-end
B16: 2. UNLEVERED FREE CASH FLOW BUILD (USDm)
D17: 2026E | E17: 2027E | F17: 2028E | G17: 2029E | H17: 2030E | I17: 2031E | J17: 2032E | K17: 2033E | L17: 2034E | M17: 2035E | N17: Terminal
B18: Adj. EBIT (Non-GAAP OI) less cash adjusting items (legal / regulatory reserves, acquisition & restructuring costs) | D18: =Model!AW212-Model!AW194-Model!AW196-Model!AW199 | E18: =Model!AX212-Model!AX194-Model!AX196-Model!AX199 | F18: =Model!AY212-Model!AY194-Model!AY196-Model!AY199 | G18: =Model!AZ212-Model!AZ194-Model!AZ196-Model!AZ199 | H18: =Model!BA212-Model!BA194-Model!BA196-Model!BA199 | I18: =H18*(1+I$26) | J18: =I18*(1+J$26) | K18: =J18*(1+K$26) | L18: =K18*(1+L$26) | M18: =L18*(1+M$26)
B19: × (1 − tax rate) | D19: =1-$C$10 | E19: =1-$C$10 | F19: =1-$C$10 | G19: =1-$C$10 | H19: =1-$C$10 | I19: =1-$C$10 | J19: =1-$C$10 | K19: =1-$C$10 | ... M19: =1-$C$10
B20: NOPAT | D20: =D18*D19 | E20: =E18*E19 | F20: =F18*F19 | G20: =G18*G19 | H20: =H18*H19 | I20: =I18*I19 | J20: =J18*J19 | K20: =K18*K19 | ... M20: =M18*M19
B21: plus D&A excl. amortization of acquired intangibles (Non-GAAP OI is after SBC) | D21: =Model!AW155-Model!AW172 | E21: =Model!AX155-Model!AX172 | F21: =Model!AY155-Model!AY172 | G21: =Model!AZ155-Model!AZ172 | H21: =Model!BA155-Model!BA172 | I21: =H21*(1+I$26) | J21: =I21*(1+J$26) | K21: =J21*(1+K$26) | L21: =K21*(1+L$26) | M21: =L21*(1+M$26)
B22: − Capex and acquisitions (Delivery Hero 2027E; M&A lever 2029E–30E) | D22: =Model!AW273 | E22: =Model!AX273+Model!AX274 | F22: =Model!AY273+Model!AY274 | G22: =Model!AZ273+Model!AZ274 | H22: =Model!BA273+Model!BA274 | I22: =Model!BA273*(1+I$26) | J22: =I22*(1+J$26) | K22: =J22*(1+K$26) | L22: =K22*(1+L$26) | M22: =L22*(1+M$26)
B23: − Δ Working capital (CF statement 2026–30E; fade/terminal = −NWC × growth: negative NWC releases cash as the platform grows) | D23: =Model!AW270 | E23: =Model!AX270 | F23: =Model!AY270 | G23: =Model!AZ270 | H23: =Model!BA270 | I23: =-Model!BA373*(1+I$26)*I$26 | J23: =-Model!BA373*(1+$I$26)*(1+$J$26)*J$26 | K23: =-Model!BA373*(1+$I$26)*(1+$J$26)*(1+$K$26)*K$26 | L23: =-Model!BA373*(1+$I$26)*(1+$J$26)*(1+$K$26)*(1+$L$26)*L$26 | M23: =-Model!BA373*(1+$I$26)*(1+$J$26)*(1+$K$26)*(1+$L$26)*(1+$M$26)*M$26 | N23: =-Model!BA373*(1+$I$26)*(1+$J$26)*(1+$K$26)*(1+$L$26)*(1+$M$26) | O23: ← |NWC| at 2035E (terminal ΔWC = |NWC| × g)
B24: Unlevered FCF | D24: =D20+D21+D22+D23 | E24: =E20+E21+E22+E23 | F24: =F20+F21+F22+F23 | G24: =G20+G21+G22+G23 | H24: =H20+H21+H22+H23 | I24: =I20+I21+I22+I23 | J24: =J20+J21+J22+J23 | K24: =K20+K21+K22+K23 | ... M24: =M20+M21+M22+M23 | N24: =(M20+M21+M22+N23*$C$27)*(1+$C$27)
B25: Terminal Value (Gordon Growth) | N25: =N24/($C$13-$C$27)
B26: Fade-period growth (2031E–35E; 12% → 6% linear) | I26: 0.12 | J26: =I26+($M$26-$I$26)/4 | K26: =J26+($M$26-$I$26)/4 | L26: =K26+($M$26-$I$26)/4 | M26: 0.06
B27: Terminal growth rate | C27: 0.04
B29: Discount period (years) | D29: =(DATE(2026,12,31)-$C$15)/365.25 | E29: =(DATE(2027,12,31)-$C$15)/365.25 | F29: =(DATE(2028,12,31)-$C$15)/365.25 | G29: =(DATE(2029,12,31)-$C$15)/365.25 | H29: =(DATE(2030,12,31)-$C$15)/365.25 | I29: =(DATE(2031,12,31)-$C$15)/365.25 | J29: =(DATE(2032,12,31)-$C$15)/365.25 | K29: =(DATE(2033,12,31)-$C$15)/365.25 | L29: =(DATE(2034,12,31)-$C$15)/365.25 | M29: =(DATE(2035,12,31)-$C$15)/365.25 | N29: =M29
B30: Discount factor | D30: =1/(1+$C$13)^D29 | E30: =1/(1+$C$13)^E29 | F30: =1/(1+$C$13)^F29 | G30: =1/(1+$C$13)^G29 | H30: =1/(1+$C$13)^H29 | I30: =1/(1+$C$13)^I29 | J30: =1/(1+$C$13)^J29 | K30: =1/(1+$C$13)^K29 | ... N30: =1/(1+$C$13)^N29
B31: PV of UFCF | D31: =D24*D30 | E31: =E24*E30 | F31: =F24*F30 | G31: =G24*G30 | H31: =H24*H30 | I31: =I24*I30 | J31: =J24*J30 | K31: =K24*K30 | ... M31: =M24*M30 | N31: =N25*N30
D32: Uber's Non-GAAP Operating Income is after stock-based compensation (treated as a real cost); acquired-intangible amortization is added back only via D&A excl. amortization.
B33: IMPLIED ROIC — invested capital roll-forward (USDm)
B34: Opening invested capital | D34: =Model!AR435 | E34: =D38 | F34: =E38 | G34: =F38 | H34: =G38 | I34: =H38 | J34: =I38 | K34: =J38 | L34: =K38 | M34: =L38
B35: plus Capex and acquisitions | D35: =-D22 | E35: =-E22 | F35: =-F22 | G35: =-G22 | H35: =-H22 | I35: =-I22 | J35: =-J22 | K35: =-K22 | ... M35: =-M22
B36: less D&A | D36: =-D21 | E36: =-E21 | F36: =-F21 | G36: =-G21 | H36: =-H21 | I36: =-I21 | J36: =-J21 | K36: =-K21 | ... M36: =-M21
B37: plus Δ Working capital investment | D37: =-D23 | E37: =-E23 | F37: =-F23 | G37: =-G23 | H37: =-H23 | I37: =-I23 | J37: =-J23 | K37: =-K23 | ... M37: =-M23
B38: Closing invested capital | D38: =SUM(D34:D37) | E38: =SUM(E34:E37) | F38: =SUM(F34:F37) | G38: =SUM(G34:G37) | H38: =SUM(H34:H37) | I38: =SUM(I34:I37) | J38: =SUM(J34:J37) | K38: =SUM(K34:K37) | ... M38: =SUM(M34:M37)
B39: NOPAT (row 20) | D39: =D20 | E39: =E20 | F39: =F20 | G39: =G20 | H39: =H20 | I39: =I20 | J39: =J20 | K39: =K20 | ... M39: =M20
B40: Implied ROIC (NOPAT / avg. invested capital) | D40: =IFERROR(D39/AVERAGE(D34,D38),"") | E40: =IFERROR(E39/AVERAGE(E34,E38),"") | F40: =IFERROR(F39/AVERAGE(F34,F38),"") | G40: =IFERROR(G39/AVERAGE(G34,G38),"") | H40: =IFERROR(H39/AVERAGE(H34,H38),"") | I40: =IFERROR(I39/AVERAGE(I34,I38),"") | J40: =IFERROR(J39/AVERAGE(J34,J38),"") | K40: =IFERROR(K39/AVERAGE(K34,K38),"") | ... M40: =IFERROR(M39/AVERAGE(M34,M38),"")
B41: Reinvestment rate (net investment / NOPAT) | D41: =IFERROR(SUM(D35:D37)/D39,"") | E41: =IFERROR(SUM(E35:E37)/E39,"") | F41: =IFERROR(SUM(F35:F37)/F39,"") | G41: =IFERROR(SUM(G35:G37)/G39,"") | H41: =IFERROR(SUM(H35:H37)/H39,"") | I41: =IFERROR(SUM(I35:I37)/I39,"") | J41: =IFERROR(SUM(J35:J37)/J39,"") | K41: =IFERROR(SUM(K35:K37)/K39,"") | ... M41: =IFERROR(SUM(M35:M37)/M39,"")
B42: Implied terminal RONIC (g / reinvestment rate) | N42: =IFERROR($C$27/M41,"")
D43: Opening IC = Model 2025A invested capital (equity incl. NCI + net debt − non-operating investments). Negative working capital (insurance float, Driver / Merchant payables) keeps IC small — ROIC is very high by construction.
B44: 3. VALUATION SUMMARY
B45: Sum of PV (explicit + fade) | C45: =SUM(D31:M31)
B46: PV of Terminal Value | C46: =N31
B47: Enterprise Value — operations | C47: =C45+C46
B48: Less: Net debt + NCI (Model 2026E YE) and Delivery Hero minorities at offer value | C48: =Model!AW457+Model!AW467+N(Model!AX388) | D48: Delivery Hero cash consideration sits in 2027E UFCF (acquisitions) and 100% of its cash flows are consolidated, so the DH minorities (NCI at offer value) are deducted.
B49: Plus: equity investments at carrying value (excl. the Delivery Hero stake, consolidated in 2027E) | C49: =Model!AW326+Model!AW327-Model!AX386*(N(Model!AX64)>0) | D49: Didi, Aurora, Grab, Lime and other stakes at 30-Jun-26 carrying value less the Aurora shares sold in Sep-26 (user choice: added at carrying value).
B50: Equity Value | C50: =C47-C48+C49
B51: Diluted shares (m, Model 2026E) | C51: =Model!AW464
B52: Implied share price ($) | C52: =C50/C51
B53: Current share price ($) | C53: =Model!AW463
B54: Implied upside / (downside) | C54: =C52/C53-1
B55: Required discount to DCF value for target IRR | C55: =1-((1+C13)/(1+H55))^H56 | D55: vs. current | E55: Target IRR | H55: 0.15
B56: Max entry price for target IRR ($) | C56: =C52*(1-C55) | D56: =C56/C53-1 | E56: Years for discount to close | H56: 3
B59: 4. SENSITIVITY: IMPLIED PRICE ($) — WACC × Terminal Growth
D61: WACC →
B62: Terminal growth ↓ | D62: =$F$62-0.01 | E62: =$F$62-0.005 | F62: =$C$13 | G62: =$F$62+0.005 | H62: =$F$62+0.01
B63: =$B$65-0.01 | D63: =IFERROR((SUMPRODUCT($D$24:$M$24/(1+D$62)^$D$29:$M$29)+(($M$20+$M$21+$M$22+$N$23*$B63)*(1+$B63)/(D$62-$B63))/(1+D$62)^$M$29-$C$48+$C$49)/$C$51,"") | E63: =IFERROR((SUMPRODUCT($D$24:$M$24/(1+E$62)^$D$29:$M$29)+(($M$20+$M$21+$M$22+$N$23*$B63)*(1+$B63)/(E$62-$B63))/(1+E$62)^$M$29-$C$48+$C$49)/$C$51,"") | F63: =IFERROR((SUMPRODUCT($D$24:$M$24/(1+F$62)^$D$29:$M$29)+(($M$20+$M$21+$M$22+$N$23*$B63)*(1+$B63)/(F$62-$B63))/(1+F$62)^$M$29-$C$48+$C$49)/$C$51,"") | G63: =IFERROR((SUMPRODUCT($D$24:$M$24/(1+G$62)^$D$29:$M$29)+(($M$20+$M$21+$M$22+$N$23*$B63)*(1+$B63)/(G$62-$B63))/(1+G$62)^$M$29-$C$48+$C$49)/$C$51,"") | H63: =IFERROR((SUMPRODUCT($D$24:$M$24/(1+H$62)^$D$29:$M$29)+(($M$20+$M$21+$M$22+$N$23*$B63)*(1+$B63)/(H$62-$B63))/(1+H$62)^$M$29-$C$48+$C$49)/$C$51,"")
B64: =$B$65-0.005 | D64: =IFERROR((SUMPRODUCT($D$24:$M$24/(1+D$62)^$D$29:$M$29)+(($M$20+$M$21+$M$22+$N$23*$B64)*(1+$B64)/(D$62-$B64))/(1+D$62)^$M$29-$C$48+$C$49)/$C$51,"") | E64: =IFERROR((SUMPRODUCT($D$24:$M$24/(1+E$62)^$D$29:$M$29)+(($M$20+$M$21+$M$22+$N$23*$B64)*(1+$B64)/(E$62-$B64))/(1+E$62)^$M$29-$C$48+$C$49)/$C$51,"") | F64: =IFERROR((SUMPRODUCT($D$24:$M$24/(1+F$62)^$D$29:$M$29)+(($M$20+$M$21+$M$22+$N$23*$B64)*(1+$B64)/(F$62-$B64))/(1+F$62)^$M$29-$C$48+$C$49)/$C$51,"") | G64: =IFERROR((SUMPRODUCT($D$24:$M$24/(1+G$62)^$D$29:$M$29)+(($M$20+$M$21+$M$22+$N$23*$B64)*(1+$B64)/(G$62-$B64))/(1+G$62)^$M$29-$C$48+$C$49)/$C$51,"") | H64: =IFERROR((SUMPRODUCT($D$24:$M$24/(1+H$62)^$D$29:$M$29)+(($M$20+$M$21+$M$22+$N$23*$B64)*(1+$B64)/(H$62-$B64))/(1+H$62)^$M$29-$C$48+$C$49)/$C$51,"")
B65: =$C$27 | D65: =IFERROR((SUMPRODUCT($D$24:$M$24/(1+D$62)^$D$29:$M$29)+(($M$20+$M$21+$M$22+$N$23*$B65)*(1+$B65)/(D$62-$B65))/(1+D$62)^$M$29-$C$48+$C$49)/$C$51,"") | E65: =IFERROR((SUMPRODUCT($D$24:$M$24/(1+E$62)^$D$29:$M$29)+(($M$20+$M$21+$M$22+$N$23*$B65)*(1+$B65)/(E$62-$B65))/(1+E$62)^$M$29-$C$48+$C$49)/$C$51,"") | F65: =IFERROR((SUMPRODUCT($D$24:$M$24/(1+F$62)^$D$29:$M$29)+(($M$20+$M$21+$M$22+$N$23*$B65)*(1+$B65)/(F$62-$B65))/(1+F$62)^$M$29-$C$48+$C$49)/$C$51,"") | G65: =IFERROR((SUMPRODUCT($D$24:$M$24/(1+G$62)^$D$29:$M$29)+(($M$20+$M$21+$M$22+$N$23*$B65)*(1+$B65)/(G$62-$B65))/(1+G$62)^$M$29-$C$48+$C$49)/$C$51,"") | H65: =IFERROR((SUMPRODUCT($D$24:$M$24/(1+H$62)^$D$29:$M$29)+(($M$20+$M$21+$M$22+$N$23*$B65)*(1+$B65)/(H$62-$B65))/(1+H$62)^$M$29-$C$48+$C$49)/$C$51,"")
B66: =$B$65+0.005 | D66: =IFERROR((SUMPRODUCT($D$24:$M$24/(1+D$62)^$D$29:$M$29)+(($M$20+$M$21+$M$22+$N$23*$B66)*(1+$B66)/(D$62-$B66))/(1+D$62)^$M$29-$C$48+$C$49)/$C$51,"") | E66: =IFERROR((SUMPRODUCT($D$24:$M$24/(1+E$62)^$D$29:$M$29)+(($M$20+$M$21+$M$22+$N$23*$B66)*(1+$B66)/(E$62-$B66))/(1+E$62)^$M$29-$C$48+$C$49)/$C$51,"") | F66: =IFERROR((SUMPRODUCT($D$24:$M$24/(1+F$62)^$D$29:$M$29)+(($M$20+$M$21+$M$22+$N$23*$B66)*(1+$B66)/(F$62-$B66))/(1+F$62)^$M$29-$C$48+$C$49)/$C$51,"") | G66: =IFERROR((SUMPRODUCT($D$24:$M$24/(1+G$62)^$D$29:$M$29)+(($M$20+$M$21+$M$22+$N$23*$B66)*(1+$B66)/(G$62-$B66))/(1+G$62)^$M$29-$C$48+$C$49)/$C$51,"") | H66: =IFERROR((SUMPRODUCT($D$24:$M$24/(1+H$62)^$D$29:$M$29)+(($M$20+$M$21+$M$22+$N$23*$B66)*(1+$B66)/(H$62-$B66))/(1+H$62)^$M$29-$C$48+$C$49)/$C$51,"")
B67: =$B$65+0.01 | D67: =IFERROR((SUMPRODUCT($D$24:$M$24/(1+D$62)^$D$29:$M$29)+(($M$20+$M$21+$M$22+$N$23*$B67)*(1+$B67)/(D$62-$B67))/(1+D$62)^$M$29-$C$48+$C$49)/$C$51,"") | E67: =IFERROR((SUMPRODUCT($D$24:$M$24/(1+E$62)^$D$29:$M$29)+(($M$20+$M$21+$M$22+$N$23*$B67)*(1+$B67)/(E$62-$B67))/(1+E$62)^$M$29-$C$48+$C$49)/$C$51,"") | F67: =IFERROR((SUMPRODUCT($D$24:$M$24/(1+F$62)^$D$29:$M$29)+(($M$20+$M$21+$M$22+$N$23*$B67)*(1+$B67)/(F$62-$B67))/(1+F$62)^$M$29-$C$48+$C$49)/$C$51,"") | G67: =IFERROR((SUMPRODUCT($D$24:$M$24/(1+G$62)^$D$29:$M$29)+(($M$20+$M$21+$M$22+$N$23*$B67)*(1+$B67)/(G$62-$B67))/(1+G$62)^$M$29-$C$48+$C$49)/$C$51,"") | H67: =IFERROR((SUMPRODUCT($D$24:$M$24/(1+H$62)^$D$29:$M$29)+(($M$20+$M$21+$M$22+$N$23*$B67)*(1+$B67)/(H$62-$B67))/(1+H$62)^$M$29-$C$48+$C$49)/$C$51,"")
B70: 5. REVERSE DCF
B71: To solve for the market-implied path: Data ▸ What-If Analysis ▸ Goal Seek — set C52 to the current price (C53) by changing the fade growth (I26) or Model scenario levers.
B73: 6. MAUBOUSSIN EV / NOPAT — TWO-STAGE FRAMEWORK
B74: EV/NOPAT = 1/r + [g × (1 − r/ROIIC) / (r × (r − g))] × [1 − ((1+g)/(1+r))^N]
B75: Formula source: Mauboussin & Rappaport, "Expectations Investing" (2021); Counterpoint Global value-driver framework.
B77: Input | C77: Value | D77: Rationale (Uber characteristics)
B78: r (Cost of capital / WACC) | C78: =$C$13 | D78: Linked from Section 1 WACC build
B79: g (NOPAT growth, Stage 1) | C79: 0.15 | D79: Model Adjusted EBIT CAGR 2026–30E ~25% (incl. Delivery Hero); organic mid-teens Gross Bookings growth with operating leverage
B80: ROIIC (Return on incremental invested capital) | C80: 0.35 | D80: Asset-light marketplace with negative working capital; acquisitions (Delivery Hero, ~$19bn EV) dilute incremental returns
B81: N (Years of value creation / CAP) | C81: 15 | D81: Two-sided network scale (MAPCs 208m, cross-platform users), Uber One; AV disintermediation risk caps the horizon
B83: Calculation | C83: Value
B84: Steady-state component: 1 / r | C84: =1/C78
B85: Value-creation factor: 1 − r / ROIIC | C85: =1-C78/C80
B86: Growth multiplier: g × (1 − r/ROIIC) / (r × (r − g)) | C86: =C79*C85/(C78*(C78-C79))
B87: Time decay: 1 − ((1+g)/(1+r))^N | C87: =1-((1+C79)/(1+C78))^C81
B88: PVGO component (growth value) | C88: =C86*C87
B89: Mauboussin EV / NOPAT (steady-state + PVGO) | C89: =C84+C88
B91: VALUATION — Applied to 2028E NOPAT | C91: USDm
B92: 2028E Adj. EBIT less cash adjusting items | C92: =F18
B93: Tax rate (from WACC build) | C93: =$C$10
B94: 2028E NOPAT | C94: =C92*(1-C93)
B95: × Mauboussin EV/NOPAT multiple | C95: =C89
B96: Implied Enterprise Value (2028E basis) | C96: =C94*C95
B97: Less: YE2027 net debt + NCI (Model), plus equity investments | C97: =Model!AX457+Model!AX467-(Model!AX326+Model!AX327)
B98: Implied Equity Value | C98: =C96-C97
B99: Diluted shares 2028E (m, Model) | C99: =Model!AY464
B100: Implied share price 2028 ($) | C100: =C98/C99
B102: Current share price ($) | C102: =C53
B103: Implied upside / (downside) | C103: =C100/C102-1
B105: MARKET-IMPLIED EV/NOPAT TODAY | C105: USDm
B106: Current market cap (spot × diluted shares) | C106: =C53*C51
B107: Plus: YE2026 net debt & NCI, less equity investments | C107: =C48-C49
B108: Implied Enterprise Value (today) | C108: =C106+C107
B109: Uber market-implied EV/NOPAT (on 2028E NOPAT) | C109: =C108/C94
B111: Multiple gap (Mauboussin − Market) | C111: =C89-C109
B112: Implied re-rating headroom | C112: =C89/C109-1

Sheet Charts
B2: Uber Technologies — Historical Operating Performance (2016–2025)
B3: All historicals · USDm · Linked to Model. Volume / price = trips y/y and Gross Bookings per trip y/y. Adjusted EBITDA as reconciled by the company; returns not meaningful (n/m → gap) in loss-making years.
C7: 2016 | D7: 2017 | E7: 2018 | F7: 2019 | G7: 2020 | H7: 2021 | I7: 2022 | J7: 2023 | K7: 2024 | L7: 2025
B8: Trips y/y % (volume) | C8: =IFERROR(Model!C14+0,0) | D8: =IFERROR(Model!D14+0,0) | E8: =IFERROR(Model!I14+0,0) | F8: =IFERROR(Model!N14+0,0) | G8: =IFERROR(Model!S14+0,0) | H8: =IFERROR(Model!X14+0,0) | I8: =IFERROR(Model!AC14+0,0) | J8: =IFERROR(Model!AH14+0,0) | K8: =IFERROR(Model!AM14+0,0) | L8: =IFERROR(Model!AR14+0,0)
B9: Gross Bookings per trip y/y % (price / mix) | C9: =IFERROR(Model!C18+0,0) | D9: =IFERROR(Model!D18+0,0) | E9: =IFERROR(Model!I18+0,0) | F9: =IFERROR(Model!N18+0,0) | G9: =IFERROR(Model!S18+0,0) | H9: =IFERROR(Model!X18+0,0) | I9: =IFERROR(Model!AC18+0,0) | J9: =IFERROR(Model!AH18+0,0) | K9: =IFERROR(Model!AM18+0,0) | L9: =IFERROR(Model!AR18+0,0)
C11: =C7 | D11: =D7 | E11: =E7 | F11: =F7 | G11: =G7 | H11: =H7 | I11: =I7 | J11: =J7 | ... L11: =L7
B12: Adjusted EBITDA | C12: =Model!C203 | D12: =Model!D203 | E12: =Model!I203 | F12: =Model!N203 | G12: =Model!S203 | H12: =Model!X203 | I12: =Model!AC203 | J12: =Model!AH203 | K12: =Model!AM203 | L12: =Model!AR203
B13: Income from Operations (GAAP) | C13: =Model!C157 | D13: =Model!D157 | E13: =Model!I157 | F13: =Model!N157 | G13: =Model!S157 | H13: =Model!X157 | I13: =Model!AC157 | J13: =Model!AH157 | K13: =Model!AM157 | L13: =Model!AR157
B14: Adj. EBITDA % of Gross Bookings | C14: =Model!C254 | D14: =Model!D254 | E14: =Model!I254 | F14: =Model!N254 | G14: =Model!S254 | H14: =Model!X254 | I14: =Model!AC254 | J14: =Model!AH254 | K14: =Model!AM254 | L14: =Model!AR254
B15: GAAP Op. Margin % (revenue) | C15: =Model!C258 | D15: =Model!D258 | E15: =Model!I258 | F15: =Model!N258 | G15: =Model!S258 | H15: =Model!X258 | I15: =Model!AC258 | J15: =Model!AH258 | K15: =Model!AM258 | L15: =Model!AR258
C17: =C7 | D17: =D7 | E17: =E7 | F17: =F7 | G17: =G7 | H17: =H7 | I17: =I7 | J17: =J7 | ... L17: =L7
B18: ROIC | C18: =IFERROR(Model!C439+0,NA()) | D18: =IFERROR(Model!D439+0,NA()) | E18: =IFERROR(Model!I439+0,NA()) | F18: =IFERROR(Model!N439+0,NA()) | G18: =IFERROR(Model!S439+0,NA()) | H18: =IFERROR(Model!X439+0,NA()) | I18: =IFERROR(Model!AC439+0,NA()) | J18: =IFERROR(Model!AH439+0,NA()) | K18: =IFERROR(Model!AM439+0,NA()) | L18: =IFERROR(Model!AR439+0,NA())
B19: RONTA | C19: =IFERROR(Model!C451+0,NA()) | D19: =IFERROR(Model!D451+0,NA()) | E19: =IFERROR(Model!I451+0,NA()) | F19: =IFERROR(Model!N451+0,NA()) | G19: =IFERROR(Model!S451+0,NA()) | H19: =IFERROR(Model!X451+0,NA()) | I19: =IFERROR(Model!AC451+0,NA()) | J19: =IFERROR(Model!AH451+0,NA()) | K19: =IFERROR(Model!AM451+0,NA()) | L19: =IFERROR(Model!AR451+0,NA())
B20: Adj. EBITDA % of Gross Bookings | C20: =IFERROR(Model!C254+0,NA()) | D20: =IFERROR(Model!D254+0,NA()) | E20: =IFERROR(Model!I254+0,NA()) | F20: =IFERROR(Model!N254+0,NA()) | G20: =IFERROR(Model!S254+0,NA()) | H20: =IFERROR(Model!X254+0,NA()) | I20: =IFERROR(Model!AC254+0,NA()) | J20: =IFERROR(Model!AH254+0,NA()) | K20: =IFERROR(Model!AM254+0,NA()) | L20: =IFERROR(Model!AR254+0,NA())
B21: FCF margin % (revenue) | C21: =IFERROR(Model!C298+0,NA()) | D21: =IFERROR(Model!D298+0,NA()) | E21: =IFERROR(Model!I298+0,NA()) | F21: =IFERROR(Model!N298+0,NA()) | G21: =IFERROR(Model!S298+0,NA()) | H21: =IFERROR(Model!X298+0,NA()) | I21: =IFERROR(Model!AC298+0,NA()) | J21: =IFERROR(Model!AH298+0,NA()) | K21: =IFERROR(Model!AM298+0,NA()) | L21: =IFERROR(Model!AR298+0,NA())
