Workbook

Sheet Model
CE1: SCENARIO SWITCH ▼ (Bull / Base / Bear) — drives all scenario-linked forecast drivers
B2: Visa Inc. (NYSE: V) — 3-Statement Financial Model | CE2: Base
B3: US GAAP as reported · USD millions (per-share data in USD; shares in millions, as-converted class A) · Fiscal years ended 30 September (2026 = Oct-2025 – Sep-2026) · Source: Visa Forms 10-K / 10-Q and Form 8-K earnings releases (Item 2.02, Ex. 99.1), SEC EDGAR (CIK 0001403161); XBRL company facts (cross-checks, dividends); releases on investor.visa.com are the same documents as filed on EDGAR · Q4 FY26 outlook: earnings call only (not on EDGAR) — UNVERIFIED
B4: Basis notes: as originally reported. IPO 19-Mar-2008 (reorganization Oct-2007; FY2008 first Visa Inc. 10-K year). 4-for-1 split Mar-2015 (per-share ÷4, shares ×4 before). One reportable segment; revenue by category; client incentives deducted from gross revenue. ASC 606 from FY2019; ASU 2016-18 restricted cash in the cash flow from FY2019. Visa Europe acquired 21-Jun-2016. Non-GAAP definitions per period (flag rows). Q4/26E calibrated to the Q4 FY26 call outlook (UNVERIFIED).
CG5: Forecast | CH5: Historical | CI5: Historical | CJ5: Historical
B6: (USDm) | C6: 2008 | D6: 2009 | E6: 2010 | F6: 2011 | G6: 2012 | H6: Q1/13 | I6: Q2/13 | J6: Q3/13 | K6: Q4/13 | L6: 2013 | M6: Q1/14 | N6: Q2/14 | O6: Q3/14 | P6: Q4/14 | Q6: 2014 | R6: Q1/15 | S6: Q2/15 | T6: Q3/15 | U6: Q4/15 | V6: 2015 | W6: Q1/16 | X6: Q2/16 | Y6: Q3/16 | Z6: Q4/16 | AA6: 2016 | AB6: Q1/17 | AC6: Q2/17 | AD6: Q3/17 | AE6: Q4/17 | AF6: 2017 | AG6: Q1/18 | AH6: Q2/18 | AI6: Q3/18 | AJ6: Q4/18 | AK6: 2018 | AL6: Q1/19 | AM6: Q2/19 | AN6: Q3/19 | AO6: Q4/19 | AP6: 2019 | AQ6: Q1/20 | AR6: Q2/20 | AS6: Q3/20 | AT6: Q4/20 | AU6: 2020 | AV6: Q1/21 | AW6: Q2/21 | AX6: Q3/21 | AY6: Q4/21 | AZ6: 2021 | BA6: Q1/22 | BB6: Q2/22 | BC6: Q3/22 | BD6: Q4/22 | BE6: 2022 | BF6: Q1/23 | BG6: Q2/23 | BH6: Q3/23 | BI6: Q4/23 | BJ6: 2023 | BK6: Q1/24 | BL6: Q2/24 | BM6: Q3/24 | BN6: Q4/24 | BO6: 2024 | BP6: Q1/25 | BQ6: Q2/25 | BR6: Q3/25 | BS6: Q4/25 | BT6: 2025 | BU6: Q1/26 | BV6: Q2/26 | BW6: Q3/26 | BX6: Q4/26E | BY6: 2026E | BZ6: 2027E | CA6: 2028E | CB6: 2029E | CC6: 2030E | CD6: 2031E | CE6: Modelling Notes | CG6: 5Y CAGR | CH6: 5Y CAGR | CI6: 10Y CAGR | CJ6: 17Y CAGR
CG7: 26-'31 | CH7: 20-'25 | CI7: 15-'25 | CJ7: 08-'25
B8: NET REVENUE BUILD — PAYMENTS VOLUME × YIELD · PROCESSED TRANSACTIONS × YIELD · CROSS-BORDER · CLIENT INCENTIVES | CE8: REVENUE BUILD — modelling logic (operating drivers → gross revenue by category → client incentives → net revenue; Visa reports one segment)
CM9: SCENARIO INPUT TABLE — driver assumptions per Bull / Base / Bear | CN9: Bull | CO9: Base | CP9: Bear | CQ9: Bull / Bear = Base + Δ (Δ inputs on each block header). Outlook block = high / mid / low end of the Q4 FY26 outlook (UNVERIFIED — call only).
B10: Operating drivers — Visa-branded payments volume and processed transactions (10-Q / 10-K MD&A) | CE10: KPIs — service revenue in a quarter is assessed on the PRIOR quarter's nominal payments volume; data processing revenue on processed transactions
B11: Nominal payments volume ($bn; the calendar quarter driving the period's service revenue) | D11: 2679 | E11: 3037 | F11: 3530 | G11: 3899 | H11: 1008 | I11: 1074 | J11: 1025 | K11: 1091 | L11: 4197 | M11: 1104 | N11: 1164 | O11: 1108 | P11: 1191 | Q11: 4567 | R11: 1217 | S11: 1245 | T11: 1168 | U11: 1254 | V11: 4884 | W11: 1265 | X11: 1305 | Y11: 1253 | Z11: 1828 | AA11: 5651 | AB11: 1858 | AC11: 1802 | AD11: 1734 | AE11: 1867 | AF11: 7265 | AG11: 1930 | AH11: 2033 | AI11: 1998 | AJ11: 2101 | AK11: 8063 | AL11: 2112 | AM11: 2197 | AN11: 2085 | AO11: 2228 | AP11: 8619 | AQ11: 2270 | AR11: 2361 | AS11: 2130 | AT11: 1955 | AU11: 8713 | AV11: 2349 | AW11: 2475 | AX11: 2423 | AY11: 2720 | AZ11: 9968 | BA11: 2784 | BB11: 2963 | BC11: 2775 | BD11: 2942 | BE11: 11464 | BF11: 2929 | BG11: 3018 | BH11: 2957 | BI11: 3166 | BJ11: 12074 | BK11: 3198 | BL11: 3280 | BM11: 3172 | BN11: 3328 | BO11: 12984 | BP11: 3410 | BQ11: 3524 | BR11: 3344 | BS11: 3617 | BT11: 13894 | BU11: 3732 | BV11: 3868 | BW11: 3728 | BX11: =BS11*(1+BX12) -> 4014.87 | BY11: =SUM(BU11:BX11) -> 15342.87 | BZ11: =BY11*(1+BZ12) -> 16647.014 | CA11: =BZ11*(1+CA12) -> 17978.775 | CB11: =CA11*(1+CB12) -> 19417.077 | CC11: =CB11*(1+CC12) -> 20873.358 | CD11: =CC11*(1+CD12) -> 22438.86 | CE11: 10-Q / 10-K "Total nominal payments volume" (three / twelve months ended one quarter before the fiscal period; Q4 = twelve months − nine months). Forecast = prior year × (1 + growth). | CG11: =IFERROR((CD11/BY11)^(1/5)-1,"n/m") -> 0.078993518 | CH11: =IFERROR((BT11/AU11)^(1/5)-1,"n/m") -> 0.097821966 | CI11: =IFERROR((BT11/V11)^(1/10)-1,"n/m") -> 0.11021007 | CJ11: =IFERROR((BT11/C11)^(1/17)-1,"n/m") -> n/m | CM11: Q4 FY26 outlook — Q3 FY26 earnings call (28-Jul-2026) — UNVERIFIED | CN11: High | CO11: Mid | CP11: Low | CQ11: UNVERIFIED (earnings call, not on EDGAR): Visa has given its outlook only on the call since FY2020 (the 8-K release has none); figures from secondary summaries found by web search. Q4 FY26: adjusted net revenue growth similar to Q3 (+14% nominal); non-GAAP EPS growth at the low end of mid-teens; adjusted opex growth low double digits; FY26 tax rate 18.0–18.25%, non-GAAP non-operating expense ~$165m.
B12: y/y % | D12: =IF(AND(ISNUMBER(D11),ISNUMBER(C11)),IFERROR(D11/C11-1,""),"") | E12: =IF(AND(ISNUMBER(E11),ISNUMBER(D11)),IFERROR(E11/D11-1,""),"") -> 0.13363195 | F12: =IF(AND(ISNUMBER(F11),ISNUMBER(E11)),IFERROR(F11/E11-1,""),"") -> 0.16233125 | G12: =IF(AND(ISNUMBER(G11),ISNUMBER(F11)),IFERROR(G11/F11-1,""),"") -> 0.10453258 | L12: =IF(AND(ISNUMBER(L11),ISNUMBER(G11)),IFERROR(L11/G11-1,""),"") -> 0.076429854 | M12: =IF(AND(ISNUMBER(M11),ISNUMBER(H11)),IFERROR(M11/H11-1,""),"") -> 0.095238095 | N12: =IF(AND(ISNUMBER(N11),ISNUMBER(I11)),IFERROR(N11/I11-1,""),"") -> 0.083798883 | O12: =IF(AND(ISNUMBER(O11),ISNUMBER(J11)),IFERROR(O11/J11-1,""),"") -> 0.08097561 | P12: =IF(AND(ISNUMBER(P11),ISNUMBER(K11)),IFERROR(P11/K11-1,""),"") -> 0.091659028 | Q12: =IF(AND(ISNUMBER(Q11),ISNUMBER(L11)),IFERROR(Q11/L11-1,""),"") -> 0.088158208 | R12: =IF(AND(ISNUMBER(R11),ISNUMBER(M11)),IFERROR(R11/M11-1,""),"") -> 0.10235507 | S12: =IF(AND(ISNUMBER(S11),ISNUMBER(N11)),IFERROR(S11/N11-1,""),"") -> 0.069587629 | ... BW12: =IF(AND(ISNUMBER(BW11),ISNUMBER(BR11)),IFERROR(BW11/BR11-1,""),"") -> 0.11483254 | BX12: =$CO$17 -> 0.11 | BY12: =IF(AND(ISNUMBER(BY11),ISNUMBER(BT11)),IFERROR(BY11/BT11-1,""),"") -> 0.10428026 | BZ12: =CHOOSE(MATCH($CE$2,{"Bull","Base","Bear"},0),$CN$29,$CO$29,$CP$29) -> 0.085 | CA12: =CHOOSE(MATCH($CE$2,{"Bull","Base","Bear"},0),$CN$30,$CO$30,$CP$30) -> 0.08 | CB12: =CHOOSE(MATCH($CE$2,{"Bull","Base","Bear"},0),$CN$31,$CO$31,$CP$31) -> 0.08 | CC12: =CHOOSE(MATCH($CE$2,{"Bull","Base","Bear"},0),$CN$32,$CO$32,$CP$32) -> 0.075 | CD12: =CHOOSE(MATCH($CE$2,{"Bull","Base","Bear"},0),$CN$33,$CO$33,$CP$33) -> 0.075 | CE12: Q4/26E: published — Q3 FY26 release: payments volume for the quarter ended 30-Jun-2026 +11% nominal (drives Q4 service revenue). 2027E+: scenario lever. | CM12: Q4/26E net revenue growth y/y (UNVERIFIED) | CN12: 0.14 | CO12: 0.13 | CP12: 0.12 | CQ12: Q4 FY26 adjusted net revenue growth 'similar to Q3' (Q3: +14% nominal, +13% constant dollar) - UNVERIFIED. Model end-points high / mid / low = 14% / 13% / 12% on Q4 FY25 net revenue $10,724m.
B13: of which U.S. ($bn) | D13: 1621 | E13: 1752 | F13: 1961 | G13: 2066 | H13: 521 | I13: 545 | J13: 530 | K13: 571 | L13: 2166 | M13: 575 | N13: 591 | O13: 575 | P13: 628 | Q13: 2369 | R13: 632 | S13: 651 | T13: 628 | U13: 683 | V13: 2594 | W13: 693 | X13: 714 | Y13: 695 | Z13: 749 | AA13: 2851 | AB13: 768 | AC13: 804 | AD13: 776 | AE13: 839 | AF13: 3187 | AG13: 836 | AH13: 881 | AI13: 854 | AJ13: 927 | AK13: 3499 | AL13: 945 | AM13: 979 | AN13: 930 | AO13: 1020 | AP13: 3875 | AQ13: 1023 | AR13: 1057 | AS13: 983 | AT13: 950 | AU13: 4009 | AV13: 1097 | AW13: 1140 | AX13: 1157 | AY13: 1332 | AZ13: 4725 | BA13: 1325 | BB13: 1394 | BC13: 1337 | BD13: 1489 | BE13: 5546 | BF13: 1480 | BG13: 1522 | BH13: 1470 | BI13: 1572 | BJ13: 6045 | BK13: 1569 | BL13: 1603 | BM13: 1561 | BN13: 1653 | BO13: 6387 | BP13: 1649 | BQ13: 1720 | BR13: 1654 | BS13: 1764 | BT13: 6788 | BU13: 1775 | BV13: 1835 | BW13: 1788 | CM13: Q4/26E non-GAAP EPS growth y/y (UNVERIFIED) | CN13: 0.15 | CO13: 0.14 | CP13: 0.13 | CQ13: Q4 FY26 non-GAAP EPS growth 'low end of mid-teens' - UNVERIFIED. End-points 15% / 14% / 13% on Q4 FY25 non-GAAP EPS $2.98.
B14: of which international ($bn) | D14: 1058 | E14: 1285 | F14: 1569 | G14: 1833 | H14: 487 | I14: 529 | J14: 495 | K14: 519 | L14: 2030 | M14: 529 | N14: 573 | O14: 533 | P14: 563 | Q14: 2198 | R14: 585 | S14: 594 | T14: 540 | U14: 571 | V14: 2290 | W14: 572 | X14: 591 | Y14: 558 | Z14: 1079 | AA14: 2800 | AB14: 1091 | AC14: 999 | AD14: 958 | AE14: 1028 | AF14: 4078 | AG14: 1094 | AH14: 1152 | AI14: 1143 | AJ14: 1172 | AK14: 4562 | AL14: 1167 | AM14: 1218 | AN14: 1155 | AO14: 1208 | AP14: 4744 | AQ14: 1247 | AR14: 1304 | AS14: 1147 | AT14: 1005 | AU14: 4704 | AV14: 1252 | AW14: 1335 | AX14: 1266 | AY14: 1388 | AZ14: 5243 | BA14: 1458 | BB14: 1568 | BC14: 1438 | BD14: 1453 | BE14: 5918 | BF14: 1449 | BG14: 1495 | BH14: 1487 | BI14: 1594 | BJ14: 6029 | BK14: 1629 | BL14: 1677 | BM14: 1611 | BN14: 1674 | BO14: 6597 | BP14: 1760 | BQ14: 1803 | BR14: 1690 | BS14: 1853 | BT14: 7106 | BU14: 1957 | BV14: 2033 | BW14: 1940 | CM14: Q4/26E share repurchases ($m) | CN14: 6000 | CO14: 5000 | CP14: 4000 | CQ14: Q3 FY26 $4.8bn (14.5m shares at $330.71); 9M FY26 $16.5bn; $28.4bn authorization remaining at 30-Jun-2026 (10-Q). Scenario input.
B15: International % of payments volume | C15: =IF(ISNUMBER(C14),IFERROR(C14/C11,""),"") | D15: =IF(ISNUMBER(D14),IFERROR(D14/D11,""),"") -> 0.39492348 | E15: =IF(ISNUMBER(E14),IFERROR(E14/E11,""),"") -> 0.42311492 | F15: =IF(ISNUMBER(F14),IFERROR(F14/F11,""),"") -> 0.44447592 | G15: =IF(ISNUMBER(G14),IFERROR(G14/G11,""),"") -> 0.47012054 | H15: =IF(ISNUMBER(H14),IFERROR(H14/H11,""),"") -> 0.48313492 | I15: =IF(ISNUMBER(I14),IFERROR(I14/I11,""),"") -> 0.49255121 | J15: =IF(ISNUMBER(J14),IFERROR(J14/J11,""),"") -> 0.48292683 | ... CD15: =IF(ISNUMBER(CD14),IFERROR(CD14/CD11,""),"") | CG15: =IFERROR(AVERAGE(BZ15,CA15,CB15,CC15,CD15),"n/m") -> n/m | CH15: =IFERROR(AVERAGE(AZ15,BE15,BJ15,BO15,BT15),"n/m") -> 0.51221519 | CI15: =IFERROR(AVERAGE(AA15,AF15,AK15,AP15,AU15,AZ15,BE15,BJ15,BO15,BT15),"n/m") -> 0.5273974 | CJ15: =IFERROR(AVERAGE(C15,D15,E15,F15,G15,L15,Q15,V15,AA15,AF15,AK15,AP15,AU15,AZ15,BE15,BJ15,BO15,BT15),"n/m") -> 0.49649673
B16: Processed transactions (millions) | E16: 45411 | G16: 53324 | H16: 14159 | I16: 13850 | J16: 14972 | K16: 15491 | L16: 58472 | M16: 15985 | N16: 15354 | O16: 16662 | P16: 16943 | Q16: 64944 | R16: 17599 | S16: 16980 | T16: 18024 | U16: 18364 | V16: 70968 | W16: 18986 | X16: 18475 | Y16: 19778 | Z16: 25921 | AA16: 83159 | AB16: 27329 | AC16: 26256 | AD16: 28450 | AE16: 29180 | AF16: 111215 | AG16: 30508 | AH16: 29321 | AI16: 31728 | AJ16: 32763 | AK16: 124320 | AL16: 33931 | AM16: 32544 | AN16: 35428 | AO16: 36425 | AP16: 138329 | AQ16: 37775 | AR16: 34941 | AS16: 30676 | AT16: 37448 | AU16: 140839 | AV16: 39213 | AW16: 37644 | AX16: 42561 | AY16: 45315 | AZ16: 164733 | BA16: 47558 | BB16: 44807 | BC16: 49279 | BD16: 50885 | BE16: 192530 | BF16: 52512 | BG16: 50069 | BH16: 54034 | BI16: 55964 | BJ16: 212579 | BK16: 57472 | BL16: 55456 | BM16: 59318 | BN16: 61511 | BO16: 233758 | BP16: 63797 | BQ16: 60651 | BR16: 65443 | BS16: 67654 | BT16: 257545 | BU16: 69400 | BV16: 66086 | BW16: 71662 | BX16: =BS16*(1+BX17) -> 73802.291 | BY16: =SUM(BU16:BX16) -> 280950.29 | BZ16: =BY16*(1+BZ17) -> 306235.82 | CA16: =BZ16*(1+CA17) -> 333797.04 | CB16: =CA16*(1+CB17) -> 362169.79 | CC16: =CB16*(1+CC17) -> 391143.37 | CD16: =CC16*(1+CD17) -> 422434.84 | CE16: 10-Q / 10-K "Visa processed transactions" (current period; Q4 = fiscal year − nine months). Forecast = prior year × (1 + growth). | CG16: =IFERROR((CD16/BY16)^(1/5)-1,"n/m") -> 0.084990783 | CH16: =IFERROR((BT16/AU16)^(1/5)-1,"n/m") -> 0.12830377 | CI16: =IFERROR((BT16/V16)^(1/10)-1,"n/m") -> 0.13757242 | CJ16: =IFERROR((BT16/C16)^(1/17)-1,"n/m") -> n/m | CM16: Q4/26E and FY26 point estimates (all cases)
B17: y/y % | D17: =IF(AND(ISNUMBER(D16),ISNUMBER(C16)),IFERROR(D16/C16-1,""),"") | E17: =IF(AND(ISNUMBER(E16),ISNUMBER(D16)),IFERROR(E16/D16-1,""),"") | F17: =IF(AND(ISNUMBER(F16),ISNUMBER(E16)),IFERROR(F16/E16-1,""),"") | G17: =IF(AND(ISNUMBER(G16),ISNUMBER(F16)),IFERROR(G16/F16-1,""),"") | L17: =IF(AND(ISNUMBER(L16),ISNUMBER(G16)),IFERROR(L16/G16-1,""),"") -> 0.096541895 | M17: =IF(AND(ISNUMBER(M16),ISNUMBER(H16)),IFERROR(M16/H16-1,""),"") -> 0.12896391 | N17: =IF(AND(ISNUMBER(N16),ISNUMBER(I16)),IFERROR(N16/I16-1,""),"") -> 0.10859206 | O17: =IF(AND(ISNUMBER(O16),ISNUMBER(J16)),IFERROR(O16/J16-1,""),"") -> 0.11287737 | P17: =IF(AND(ISNUMBER(P16),ISNUMBER(K16)),IFERROR(P16/K16-1,""),"") -> 0.093731844 | Q17: =IF(AND(ISNUMBER(Q16),ISNUMBER(L16)),IFERROR(Q16/L16-1,""),"") -> 0.11068546 | R17: =IF(AND(ISNUMBER(R16),ISNUMBER(M16)),IFERROR(R16/M16-1,""),"") -> 0.10096966 | S17: =IF(AND(ISNUMBER(S16),ISNUMBER(N16)),IFERROR(S16/N16-1,""),"") -> 0.10590074 | ... BW17: =IF(AND(ISNUMBER(BW16),ISNUMBER(BR16)),IFERROR(BW16/BR16-1,""),"") -> 0.095029262 | BX17: =IFERROR(SUM(BU16:BW16)/SUM(BP16:BR16)-1,0) -> 0.090878451 | BY17: =IF(AND(ISNUMBER(BY16),ISNUMBER(BT16)),IFERROR(BY16/BT16-1,""),"") -> 0.090878451 | BZ17: =CHOOSE(MATCH($CE$2,{"Bull","Base","Bear"},0),$CN$35,$CO$35,$CP$35) -> 0.09 | CA17: =CHOOSE(MATCH($CE$2,{"Bull","Base","Bear"},0),$CN$36,$CO$36,$CP$36) -> 0.09 | CB17: =CHOOSE(MATCH($CE$2,{"Bull","Base","Bear"},0),$CN$37,$CO$37,$CP$37) -> 0.085 | CC17: =CHOOSE(MATCH($CE$2,{"Bull","Base","Bear"},0),$CN$38,$CO$38,$CP$38) -> 0.08 | CD17: =CHOOSE(MATCH($CE$2,{"Bull","Base","Bear"},0),$CN$39,$CO$39,$CP$39) -> 0.08 | CE17: Q4/26E: 9M FY26 y/y (+9%). 2027E+: scenario lever. | CM17: Q4/26E nominal payments volume growth (quarter ended 30-Jun-2026; published) | CO17: 0.11 | CQ17: Q3 FY26 release (8-K 28-Jul-2026, Ex. 99.1) 'Key business drivers': payments volume growth for the quarter ended 30-Jun-2026 +11% nominal (+10% constant). Service revenue in Q4 FY26 is based on this quarter's volume (company: service revenue is assessed on prior-quarter payments volume).
CM18: Q4/26E interest expense ($m) | CO18: 195 | CQ18: Q3 FY26 $194m; $24.1bn debt incl. $1.5bn commercial paper; no notes mature in Q4.
B19: Gross revenue by category → client incentives → net revenue | CE19: REVENUE CATEGORIES — company presentation (service, data processing, international transaction, other; less client incentives) | CM19: Q4/26E investment income & other ($m) | CO19: 114 | CQ19: UNVERIFIED (earnings call, not on EDGAR): FY26 non-GAAP non-operating expense ~$165m; 9M $84m → Q4 −$81m = interest $195m − $114m investment income. Q3 FY26 non-GAAP $159m.
B20: Service revenue | C20: 3061 | D20: 3174 | E20: 3497 | F20: 4261 | G20: 4872 | H20: 1300 | I20: 1369 | J20: 1298 | K20: 1385 | L20: 5352 | M20: 1419 | N20: 1462 | O20: 1417 | P20: 1499 | Q20: 5797 | R20: 1538 | S20: 1577 | T20: 1550 | U20: 1637 | V20: 6302 | W20: 1645 | X20: 1699 | Y20: 1635 | Z20: 1768 | AA20: 6747 | AB20: 1918 | AC20: 1993 | AD20: 1948 | AE20: 2116 | AF20: 7975 | AG20: 2146 | AH20: 2253 | AI20: 2196 | AJ20: 2323 | AK20: 8918 | AL20: 2342 | AM20: 2417 | AN20: 2405 | AO20: 2536 | AP20: 9700 | AQ20: 2555 | AR20: 2623 | AS20: 2409 | AT20: 2217 | AU20: 9804 | AV20: 2677 | AW20: 2845 | AX20: 2828 | AY20: 3125 | AZ20: 11475 | BA20: 3193 | BB20: 3521 | BC20: 3189 | BD20: 3458 | BE20: 13361 | BF20: 3511 | BG20: 3771 | BH20: 3668 | BI20: 3876 | BJ20: 14826 | BK20: 3915 | BL20: 4033 | BM20: 3967 | BN20: 4199 | BO20: 16114 | BP20: 4208 | BQ20: 4399 | BR20: 4330 | BS20: 4602 | BT20: 17539 | BU20: 4760 | BV20: 4981 | BW20: 4922 | BX20: =BX11*1000*BX21 -> 5118.9905 | BY20: =SUM(BU20:BX20) -> 19781.99 | BZ20: =BZ11*1000*BZ21 -> 21678.094 | CA20: =CA11*1000*CA21 -> 23646.465 | CB20: =CB11*1000*CB21 -> 25665.873 | CC20: =CC11*1000*CC21 -> 27728.768 | CD20: =CD11*1000*CD21 -> 29957.468 | CE20: Forecast = nominal payments volume ($bn × 1,000) × service yield. | CG20: =IFERROR((CD20/BY20)^(1/5)-1,"n/m") -> 0.08654326 | CH20: =IFERROR((BT20/AU20)^(1/5)-1,"n/m") -> 0.12336349 | CI20: =IFERROR((BT20/V20)^(1/10)-1,"n/m") -> 0.10777776 | CJ20: =IFERROR((BT20/C20)^(1/17)-1,"n/m") -> 0.10814492 | CM20: Q4/26E non-GAAP tax rate | CO20: 0.19 | CQ20: UNVERIFIED (earnings call, not on EDGAR): FY26 18.0–18.25% with 9M FY26 non-GAAP 17.8% implies ~19% in Q4 (Q3 18.4%).
B21: Service yield (% of nominal payments volume) | C21: =IF(AND(ISNUMBER(C20),ISNUMBER(C11)),IFERROR(C20/(C11*1000),""),"") | D21: =IF(AND(ISNUMBER(D20),ISNUMBER(D11)),IFERROR(D20/(D11*1000),""),"") -> 0.0011847704 | E21: =IF(AND(ISNUMBER(E20),ISNUMBER(E11)),IFERROR(E20/(E11*1000),""),"") -> 0.0011514653 | F21: =IF(AND(ISNUMBER(F20),ISNUMBER(F11)),IFERROR(F20/(F11*1000),""),"") -> 0.0012070822 | G21: =IF(AND(ISNUMBER(G20),ISNUMBER(G11)),IFERROR(G20/(G11*1000),""),"") -> 0.0012495512 | H21: =IF(AND(ISNUMBER(H20),ISNUMBER(H11)),IFERROR(H20/(H11*1000),""),"") -> 0.0012896825 | I21: =IF(AND(ISNUMBER(I20),ISNUMBER(I11)),IFERROR(I20/(I11*1000),""),"") -> 0.0012746741 | J21: =IF(AND(ISNUMBER(J20),ISNUMBER(J11)),IFERROR(J20/(J11*1000),""),"") -> 0.0012663415 | ... BW21: =IF(AND(ISNUMBER(BW20),ISNUMBER(BW11)),IFERROR(BW20/(BW11*1000),""),"") -> 0.001320279 | BX21: =BS21*(1+BX22+$BX$50) -> 0.0012750078 | BY21: =IF(AND(ISNUMBER(BY20),ISNUMBER(BY11)),IFERROR(BY20/(BY11*1000),""),"") -> 0.0012893279 | BZ21: =BY21*(1+CHOOSE(MATCH($CE$2,{"Bull","Base","Bear"},0),$CN$41,$CO$41,$CP$41)) -> 0.0013022212 | CA21: =BZ21*(1+CHOOSE(MATCH($CE$2,{"Bull","Base","Bear"},0),$CN$42,$CO$42,$CP$42)) -> 0.0013152434 | CB21: =CA21*(1+CHOOSE(MATCH($CE$2,{"Bull","Base","Bear"},0),$CN$43,$CO$43,$CP$43)) -> 0.0013218196 | CC21: =CB21*(1+CHOOSE(MATCH($CE$2,{"Bull","Base","Bear"},0),$CN$44,$CO$44,$CP$44)) -> 0.0013284287 | CD21: =CC21*(1+CHOOSE(MATCH($CE$2,{"Bull","Base","Bear"},0),$CN$45,$CO$45,$CP$45)) -> 0.0013350709 | CE21: Q4/26E: prior-year quarter × (1 + 9M FY26 y/y yield change + revenue calibration Δ). 2027E+: prior year × (1 + scenario yield change: pricing, mix, card benefits). | CG21: =IFERROR(AVERAGE(BZ21,CA21,CB21,CC21,CD21),"n/m") -> 0.0013205568 | CH21: =IFERROR(AVERAGE(AZ21,BE21,BJ21,BO21,BT21),"n/m") -> 0.0012095991 | CI21: =IFERROR(AVERAGE(AA21,AF21,AK21,AP21,AU21,AZ21,BE21,BJ21,BO21,BT21),"n/m") -> 0.0011696348 | CJ21: =IFERROR(AVERAGE(C21,D21,E21,F21,G21,L21,Q21,V21,AA21,AF21,AK21,AP21,AU21,AZ21,BE21,BJ21,BO21,BT21),"n/m") -> 0.0011955337 | CM21: Q4/26E litigation provision ($m; adjusted out) | CO21: 0 | CQ21: Not forecast (assumption): covered-litigation provisions are funded through the escrow / class B conversion-rate mechanism.
B22: Q4/26E yield change before calibration (9M FY26 y/y) | BX22: =IFERROR((SUM(BU20:BW20)/SUM(BU11:BW11))/(SUM(BP20:BR20)/SUM(BP11:BR11))-1,0) -> 0.028358707 | CE22: Trend input: 9M FY26 service yield ÷ 9M FY25 service yield − 1 (formula on actuals). | CM22: Q4/26E amortization of acquired intangibles ($m; adjusted out) | CO22: 64 | CQ22: Q3 FY26 $64m (Featurespace, Pismo, Tink).
B23: Service revenue y/y % | D23: =IF(AND(ISNUMBER(D20),ISNUMBER(C20)),IFERROR(D20/C20-1,""),"") -> 0.036916041 | E23: =IF(AND(ISNUMBER(E20),ISNUMBER(D20)),IFERROR(E20/D20-1,""),"") -> 0.10176434 | F23: =IF(AND(ISNUMBER(F20),ISNUMBER(E20)),IFERROR(F20/E20-1,""),"") -> 0.21847298 | G23: =IF(AND(ISNUMBER(G20),ISNUMBER(F20)),IFERROR(G20/F20-1,""),"") -> 0.14339357 | L23: =IF(AND(ISNUMBER(L20),ISNUMBER(G20)),IFERROR(L20/G20-1,""),"") -> 0.098522167 | M23: =IF(AND(ISNUMBER(M20),ISNUMBER(H20)),IFERROR(M20/H20-1,""),"") -> 0.091538462 | N23: =IF(AND(ISNUMBER(N20),ISNUMBER(I20)),IFERROR(N20/I20-1,""),"") -> 0.067932798 | O23: =IF(AND(ISNUMBER(O20),ISNUMBER(J20)),IFERROR(O20/J20-1,""),"") -> 0.091679507 | P23: =IF(AND(ISNUMBER(P20),ISNUMBER(K20)),IFERROR(P20/K20-1,""),"") -> 0.082310469 | Q23: =IF(AND(ISNUMBER(Q20),ISNUMBER(L20)),IFERROR(Q20/L20-1,""),"") -> 0.083146487 | R23: =IF(AND(ISNUMBER(R20),ISNUMBER(M20)),IFERROR(R20/M20-1,""),"") -> 0.083861875 | S23: =IF(AND(ISNUMBER(S20),ISNUMBER(N20)),IFERROR(S20/N20-1,""),"") -> 0.078659371 | ... BY23: =IF(AND(ISNUMBER(BY20),ISNUMBER(BT20)),IFERROR(BY20/BT20-1,""),"") -> 0.12788588 | BZ23: =IF(AND(ISNUMBER(BZ20),ISNUMBER(BY20)),IFERROR(BZ20/BY20-1,""),"") -> 0.09585 | CA23: =IF(AND(ISNUMBER(CA20),ISNUMBER(BZ20)),IFERROR(CA20/BZ20-1,""),"") -> 0.0908 | CB23: =IF(AND(ISNUMBER(CB20),ISNUMBER(CA20)),IFERROR(CB20/CA20-1,""),"") -> 0.0854 | CC23: =IF(AND(ISNUMBER(CC20),ISNUMBER(CB20)),IFERROR(CC20/CB20-1,""),"") -> 0.080375 | CD23: =IF(AND(ISNUMBER(CD20),ISNUMBER(CC20)),IFERROR(CD20/CC20-1,""),"") -> 0.080375 | CM23: Q4/26E acquisition-related costs ($m; adjusted out) | CO23: 15 | CQ23: Q3 FY26 $14m.
B24: Data processing revenue | C24: 2073 | D24: 2430 | E24: 3125 | F24: 3478 | G24: 3975 | H24: 1115 | I24: 1150 | J24: 1191 | K24: 1186 | L24: 4642 | M24: 1264 | N24: 1234 | O24: 1321 | P24: 1348 | Q24: 5167 | R24: 1383 | S24: 1340 | T24: 1400 | U24: 1429 | V24: 5552 | W24: 1479 | X24: 1473 | Y24: 1541 | Z24: 1779 | AA24: 6272 | AB24: 1892 | AC24: 1843 | AD24: 1984 | AE24: 2067 | AF24: 7786 | AG24: 2147 | AH24: 2127 | AI24: 2359 | AJ24: 2394 | AK24: 9027 | AL24: 2470 | AM24: 2432 | AN24: 2662 | AO24: 2769 | AP24: 10333 | AQ24: 2864 | AR24: 2711 | AS24: 2525 | AT24: 2875 | AU24: 10975 | AV24: 3033 | AW24: 2996 | AX24: 3327 | AY24: 3436 | AZ24: 12792 | BA24: 3614 | BB24: 3480 | BC24: 3579 | BD24: 3765 | BE24: 14438 | BF24: 3827 | BG24: 3819 | BH24: 4105 | BI24: 4256 | BJ24: 16007 | BK24: 4356 | BL24: 4259 | BM24: 4489 | BN24: 4610 | BO24: 17714 | BP24: 4745 | BQ24: 4701 | BR24: 5153 | BS24: 5394 | BT24: 19993 | BU24: 5544 | BV24: 5543 | BW24: 6042 | BX24: =BX16*BX25 -> 6174.316 | BY24: =SUM(BU24:BX24) -> 23303.316 | BZ24: =BZ16*BZ25 -> 26035.63 | CA24: =CA16*CA25 -> 28946.413 | CB24: =CB16*CB25 -> 32034.996 | CC24: =CC16*CC25 -> 35116.762 | CD24: =CD16*CD25 -> 38494.995 | CE24: Forecast = processed transactions (m) × data processing revenue per transaction ($). | CG24: =IFERROR((CD24/BY24)^(1/5)-1,"n/m") -> 0.10559816 | CH24: =IFERROR((BT24/AU24)^(1/5)-1,"n/m") -> 0.12744324 | CI24: =IFERROR((BT24/V24)^(1/10)-1,"n/m") -> 0.13669212 | CJ24: =IFERROR((BT24/C24)^(1/17)-1,"n/m") -> 0.14261191 | CM24: FY26 purchases of property, equipment & technology ($m) | CO24: 1600 | CQ24: 9M FY26 $1,178m; FY25 $1,482m (3.7% of net revenue). Not guided (assumption).
B25: Data processing revenue per processed transaction ($) | C25: =IF(AND(ISNUMBER(C24),ISNUMBER(C16)),IFERROR(C24/C16,""),"") | D25: =IF(AND(ISNUMBER(D24),ISNUMBER(D16)),IFERROR(D24/D16,""),"") | E25: =IF(AND(ISNUMBER(E24),ISNUMBER(E16)),IFERROR(E24/E16,""),"") -> 0.068815926 | F25: =IF(AND(ISNUMBER(F24),ISNUMBER(F16)),IFERROR(F24/F16,""),"") | G25: =IF(AND(ISNUMBER(G24),ISNUMBER(G16)),IFERROR(G24/G16,""),"") -> 0.074544295 | H25: =IF(AND(ISNUMBER(H24),ISNUMBER(H16)),IFERROR(H24/H16,""),"") -> 0.078748499 | I25: =IF(AND(ISNUMBER(I24),ISNUMBER(I16)),IFERROR(I24/I16,""),"") -> 0.083032491 | J25: =IF(AND(ISNUMBER(J24),ISNUMBER(J16)),IFERROR(J24/J16,""),"") -> 0.079548491 | ... BW25: =IF(AND(ISNUMBER(BW24),ISNUMBER(BW16)),IFERROR(BW24/BW16,""),"") -> 0.084312467 | BX25: =BS25*(1+BX26+$BX$50) -> 0.083660222 | BY25: =IF(AND(ISNUMBER(BY24),ISNUMBER(BY16)),IFERROR(BY24/BY16,""),"") -> 0.082944623 | BZ25: =BY25*(1+CHOOSE(MATCH($CE$2,{"Bull","Base","Bear"},0),$CN$47,$CO$47,$CP$47)) -> 0.085018239 | CA25: =BZ25*(1+CHOOSE(MATCH($CE$2,{"Bull","Base","Bear"},0),$CN$48,$CO$48,$CP$48)) -> 0.086718604 | CB25: =CA25*(1+CHOOSE(MATCH($CE$2,{"Bull","Base","Bear"},0),$CN$49,$CO$49,$CP$49)) -> 0.088452976 | CC25: =CB25*(1+CHOOSE(MATCH($CE$2,{"Bull","Base","Bear"},0),$CN$50,$CO$50,$CP$50)) -> 0.08977977 | CD25: =CC25*(1+CHOOSE(MATCH($CE$2,{"Bull","Base","Bear"},0),$CN$51,$CO$51,$CP$51)) -> 0.091126467 | CE25: Q4/26E: prior-year quarter × (1 + 9M FY26 y/y change + calibration Δ). 2027E+: scenario (pricing, value-added services, cross-border mix).
B26: Q4/26E change before calibration (9M FY26 y/y) | BX26: =IFERROR((SUM(BU24:BW24)/SUM(BU16:BW16))/(SUM(BP24:BR24)/SUM(BP16:BR16))-1,0) -> 0.075554788 | CE26: Trend input: 9M FY26 ÷ 9M FY25 data processing revenue per transaction − 1 (formula on actuals). | CM26: Maximum net debt / adjusted EBITDA before buybacks (x) — buyback floor 2027E+ | CN26: 0.5 | CO26: 0.35 | CP26: 0.25 | CQ26: Net debt (debt − cash − investment securities) $9.9bn at 30-Jun-2026 ≈ 0.3x adjusted EBITDA (model definition). Visa returns most free cash flow via buybacks and dividends; target = leverage up to which surplus cash is returned (assumption; Visa states no leverage target). Bull = more buybacks.
B27: Data processing revenue y/y % | D27: =IF(AND(ISNUMBER(D24),ISNUMBER(C24)),IFERROR(D24/C24-1,""),"") -> 0.17221418 | E27: =IF(AND(ISNUMBER(E24),ISNUMBER(D24)),IFERROR(E24/D24-1,""),"") -> 0.28600823 | F27: =IF(AND(ISNUMBER(F24),ISNUMBER(E24)),IFERROR(F24/E24-1,""),"") -> 0.11296 | G27: =IF(AND(ISNUMBER(G24),ISNUMBER(F24)),IFERROR(G24/F24-1,""),"") -> 0.14289822 | L27: =IF(AND(ISNUMBER(L24),ISNUMBER(G24)),IFERROR(L24/G24-1,""),"") -> 0.16779874 | M27: =IF(AND(ISNUMBER(M24),ISNUMBER(H24)),IFERROR(M24/H24-1,""),"") -> 0.13363229 | N27: =IF(AND(ISNUMBER(N24),ISNUMBER(I24)),IFERROR(N24/I24-1,""),"") -> 0.073043478 | O27: =IF(AND(ISNUMBER(O24),ISNUMBER(J24)),IFERROR(O24/J24-1,""),"") -> 0.10915197 | P27: =IF(AND(ISNUMBER(P24),ISNUMBER(K24)),IFERROR(P24/K24-1,""),"") -> 0.13659359 | Q27: =IF(AND(ISNUMBER(Q24),ISNUMBER(L24)),IFERROR(Q24/L24-1,""),"") -> 0.1130978 | R27: =IF(AND(ISNUMBER(R24),ISNUMBER(M24)),IFERROR(R24/M24-1,""),"") -> 0.09414557 | S27: =IF(AND(ISNUMBER(S24),ISNUMBER(N24)),IFERROR(S24/N24-1,""),"") -> 0.085899514 | ... BY27: =IF(AND(ISNUMBER(BY24),ISNUMBER(BT24)),IFERROR(BY24/BT24-1,""),"") -> 0.16557375 | BZ27: =IF(AND(ISNUMBER(BZ24),ISNUMBER(BY24)),IFERROR(BZ24/BY24-1,""),"") -> 0.11725 | CA27: =IF(AND(ISNUMBER(CA24),ISNUMBER(BZ24)),IFERROR(CA24/BZ24-1,""),"") -> 0.1118 | CB27: =IF(AND(ISNUMBER(CB24),ISNUMBER(CA24)),IFERROR(CB24/CA24-1,""),"") -> 0.1067 | CC27: =IF(AND(ISNUMBER(CC24),ISNUMBER(CB24)),IFERROR(CC24/CB24-1,""),"") -> 0.0962 | CD27: =IF(AND(ISNUMBER(CD24),ISNUMBER(CC24)),IFERROR(CD24/CC24-1,""),"") -> 0.0962
B28: International transaction revenue | C28: 1721 | D28: 1916 | E28: 2290 | F28: 2674 | G28: 3025 | H28: 805 | I28: 831 | J28: 854 | K28: 899 | L28: 3389 | M28: 891 | N28: 871 | O28: 860 | P28: 938 | Q28: 3560 | R28: 970 | S28: 964 | T28: 1039 | U28: 1091 | V28: 4064 | W28: 1031 | X28: 1045 | Y28: 1084 | Z28: 1489 | AA28: 4649 | AB28: 1489 | AC28: 1469 | AD28: 1571 | AE28: 1792 | AF28: 6321 | AG28: 1666 | AH28: 1752 | AI28: 1830 | AJ28: 1963 | AK28: 7211 | AL28: 1851 | AM28: 1796 | AN28: 1977 | AO28: 2180 | AP28: 7804 | AQ28: 2018 | AR28: 1833 | AS28: 1102 | AT28: 1346 | AU28: 6299 | AV28: 1451 | AW28: 1488 | AX28: 1696 | AY28: 1895 | AZ28: 6530 | BA28: 2174 | BB28: 2208 | BC28: 2560 | BD28: 2873 | BE28: 9815 | BF28: 2797 | BG28: 2749 | BH28: 2920 | BI28: 3172 | BJ28: 11638 | BK28: 3019 | BL28: 2984 | BM28: 3194 | BN28: 3468 | BO28: 12665 | BP28: 3442 | BQ28: 3291 | BR28: 3633 | BS28: 3800 | BT28: 14166 | BU28: 3652 | BV28: 3631 | BW28: 3853 | BX28: =BS28*(1+BX29) -> 3982.518 | BY28: =SUM(BU28:BX28) -> 15118.518 | BZ28: =BY28*(1+BZ29) -> 16630.37 | CA28: =BZ28*(1+CA29) -> 18293.407 | CB28: =CA28*(1+CB29) -> 19939.813 | CC28: =CB28*(1+CC29) -> 21734.397 | CD28: =CC28*(1+CD29) -> 23473.148 | CE28: Driven by cross-border volume (excl. intra-Europe) and currency volatility. Q4/26E: prior-year quarter × (1 + 9M FY26 y/y + calibration Δ). 2027E+: scenario growth. | CG28: =IFERROR((CD28/BY28)^(1/5)-1,"n/m") -> 0.091974318 | CH28: =IFERROR((BT28/AU28)^(1/5)-1,"n/m") -> 0.17596698 | CI28: =IFERROR((BT28/V28)^(1/10)-1,"n/m") -> 0.13299855 | CJ28: =IFERROR((BT28/C28)^(1/17)-1,"n/m") -> 0.13201182 | CM28: PV (nominal payments volume y/y) | CN28: 0.02 | CO28: Δ → | CP28: -0.03 | CQ28: FY2023–25 +5–7.5% (FY2025 +7.0%); 9M FY26 +10.2% nominal (FX tailwind ~1pt). Consumer spending + cash digitisation; U.S. ~48% of volume.
B29: y/y % | D29: =IF(AND(ISNUMBER(D28),ISNUMBER(C28)),IFERROR(D28/C28-1,""),"") -> 0.11330622 | E29: =IF(AND(ISNUMBER(E28),ISNUMBER(D28)),IFERROR(E28/D28-1,""),"") -> 0.19519833 | F29: =IF(AND(ISNUMBER(F28),ISNUMBER(E28)),IFERROR(F28/E28-1,""),"") -> 0.16768559 | G29: =IF(AND(ISNUMBER(G28),ISNUMBER(F28)),IFERROR(G28/F28-1,""),"") -> 0.13126402 | L29: =IF(AND(ISNUMBER(L28),ISNUMBER(G28)),IFERROR(L28/G28-1,""),"") -> 0.12033058 | M29: =IF(AND(ISNUMBER(M28),ISNUMBER(H28)),IFERROR(M28/H28-1,""),"") -> 0.1068323 | N29: =IF(AND(ISNUMBER(N28),ISNUMBER(I28)),IFERROR(N28/I28-1,""),"") -> 0.048134777 | O29: =IF(AND(ISNUMBER(O28),ISNUMBER(J28)),IFERROR(O28/J28-1,""),"") -> 0.0070257611 | P29: =IF(AND(ISNUMBER(P28),ISNUMBER(K28)),IFERROR(P28/K28-1,""),"") -> 0.043381535 | Q29: =IF(AND(ISNUMBER(Q28),ISNUMBER(L28)),IFERROR(Q28/L28-1,""),"") -> 0.050457362 | R29: =IF(AND(ISNUMBER(R28),ISNUMBER(M28)),IFERROR(R28/M28-1,""),"") -> 0.088664422 | S29: =IF(AND(ISNUMBER(S28),ISNUMBER(N28)),IFERROR(S28/N28-1,""),"") -> 0.10677382 | ... BW29: =IF(AND(ISNUMBER(BW28),ISNUMBER(BR28)),IFERROR(BW28/BR28-1,""),"") -> 0.060556014 | BX29: =BX30+$BX$50 -> 0.048031055 | BY29: =IF(AND(ISNUMBER(BY28),ISNUMBER(BT28)),IFERROR(BY28/BT28-1,""),"") -> 0.06723973 | BZ29: =CHOOSE(MATCH($CE$2,{"Bull","Base","Bear"},0),$CN$53,$CO$53,$CP$53) -> 0.1 | CA29: =CHOOSE(MATCH($CE$2,{"Bull","Base","Bear"},0),$CN$54,$CO$54,$CP$54) -> 0.1 | CB29: =CHOOSE(MATCH($CE$2,{"Bull","Base","Bear"},0),$CN$55,$CO$55,$CP$55) -> 0.09 | CC29: =CHOOSE(MATCH($CE$2,{"Bull","Base","Bear"},0),$CN$56,$CO$56,$CP$56) -> 0.09 | CD29: =CHOOSE(MATCH($CE$2,{"Bull","Base","Bear"},0),$CN$57,$CO$57,$CP$57) -> 0.08 | CM29: 2027E | CN29: =CO29+$CN$28 -> 0.105 | CO29: 0.085 | CP29: =CO29+$CP$28 -> 0.055
B30: Q4/26E growth before calibration (9M FY26 y/y) | BX30: =IFERROR(SUM(BU28:BW28)/SUM(BP28:BR28)-1,0) -> 0.074281304 | CE30: Trend input: 9M FY26 ÷ 9M FY25 international transaction revenue − 1. | CM30: 2028E | CN30: =CO30+$CN$28 -> 0.1 | CO30: 0.08 | CP30: =CO30+$CP$28 -> 0.05
B31: Other revenue (value-added services, licensing, marketing services) | C31: 569 | D31: 625 | E31: 713 | F31: 655 | G31: 704 | H31: 179 | I31: 175 | J31: 179 | K31: 183 | L31: 716 | M31: 180 | N31: 183 | O31: 195 | P31: 212 | Q31: 770 | R31: 204 | S31: 204 | T31: 199 | U31: 216 | V31: 823 | W31: 198 | X31: 198 | Y31: 209 | Z31: 218 | AA31: 823 | AB31: 203 | AC31: 203 | AD31: 209 | AE31: 226 | AF31: 841 | AG31: 229 | AH31: 230 | AI31: 229 | AJ31: 256 | AK31: 944 | AL31: 299 | AM31: 327 | AN31: 342 | AO31: 345 | AP31: 1313 | AQ31: 365 | AR31: 392 | AS31: 314 | AT31: 361 | AU31: 1432 | AV31: 384 | AW31: 392 | AX31: 409 | AY31: 490 | AZ31: 1675 | BA31: 449 | BB31: 474 | BC31: 517 | BD31: 551 | BE31: 1991 | BF31: 587 | BG31: 551 | BH31: 597 | BI31: 744 | BJ31: 2479 | BK31: 692 | BL31: 756 | BM31: 780 | BN31: 969 | BO31: 3197 | BP31: 912 | BQ31: 937 | BR31: 1028 | BS31: 1176 | BT31: 4053 | BU31: 1214 | BV31: 1320 | BW31: 1496 | BX31: =BS31*(1+BX32) -> 1616.429 | BY31: =SUM(BU31:BX31) -> 5646.429 | BZ31: =BY31*(1+BZ32) -> 6888.6434 | CA31: =BZ31*(1+CA32) -> 8128.5992 | CB31: =CA31*(1+CB32) -> 9429.175 | CC31: =CB31*(1+CC32) -> 10749.26 | CD31: =CC31*(1+CD32) -> 12146.663 | CE31: Value-added services, consulting, marketing services, licensing. Q4/26E: prior-year quarter × (1 + 9M FY26 y/y + calibration Δ). 2027E+: scenario growth. | CG31: =IFERROR((CD31/BY31)^(1/5)-1,"n/m") -> 0.16556534 | CH31: =IFERROR((BT31/AU31)^(1/5)-1,"n/m") -> 0.23130805 | CI31: =IFERROR((BT31/V31)^(1/10)-1,"n/m") -> 0.17283705 | CJ31: =IFERROR((BT31/C31)^(1/17)-1,"n/m") -> 0.12242344 | CM31: 2029E | CN31: =CO31+$CN$28 -> 0.1 | CO31: 0.08 | CP31: =CO31+$CP$28 -> 0.05
B32: y/y % | D32: =IF(AND(ISNUMBER(D31),ISNUMBER(C31)),IFERROR(D31/C31-1,""),"") -> 0.098418278 | E32: =IF(AND(ISNUMBER(E31),ISNUMBER(D31)),IFERROR(E31/D31-1,""),"") -> 0.1408 | F32: =IF(AND(ISNUMBER(F31),ISNUMBER(E31)),IFERROR(F31/E31-1,""),"") -> -0.081346424 | G32: =IF(AND(ISNUMBER(G31),ISNUMBER(F31)),IFERROR(G31/F31-1,""),"") -> 0.07480916 | L32: =IF(AND(ISNUMBER(L31),ISNUMBER(G31)),IFERROR(L31/G31-1,""),"") -> 0.017045455 | M32: =IF(AND(ISNUMBER(M31),ISNUMBER(H31)),IFERROR(M31/H31-1,""),"") -> 0.0055865922 | N32: =IF(AND(ISNUMBER(N31),ISNUMBER(I31)),IFERROR(N31/I31-1,""),"") -> 0.045714286 | O32: =IF(AND(ISNUMBER(O31),ISNUMBER(J31)),IFERROR(O31/J31-1,""),"") -> 0.089385475 | P32: =IF(AND(ISNUMBER(P31),ISNUMBER(K31)),IFERROR(P31/K31-1,""),"") -> 0.15846995 | Q32: =IF(AND(ISNUMBER(Q31),ISNUMBER(L31)),IFERROR(Q31/L31-1,""),"") -> 0.075418994 | R32: =IF(AND(ISNUMBER(R31),ISNUMBER(M31)),IFERROR(R31/M31-1,""),"") -> 0.13333333 | S32: =IF(AND(ISNUMBER(S31),ISNUMBER(N31)),IFERROR(S31/N31-1,""),"") -> 0.1147541 | ... BW32: =IF(AND(ISNUMBER(BW31),ISNUMBER(BR31)),IFERROR(BW31/BR31-1,""),"") -> 0.45525292 | BX32: =BX33+$BX$50 -> 0.37451444 | BY32: =IF(AND(ISNUMBER(BY31),ISNUMBER(BT31)),IFERROR(BY31/BT31-1,""),"") -> 0.39314803 | BZ32: =CHOOSE(MATCH($CE$2,{"Bull","Base","Bear"},0),$CN$59,$CO$59,$CP$59) -> 0.22 | CA32: =CHOOSE(MATCH($CE$2,{"Bull","Base","Bear"},0),$CN$60,$CO$60,$CP$60) -> 0.18 | CB32: =CHOOSE(MATCH($CE$2,{"Bull","Base","Bear"},0),$CN$61,$CO$61,$CP$61) -> 0.16 | CC32: =CHOOSE(MATCH($CE$2,{"Bull","Base","Bear"},0),$CN$62,$CO$62,$CP$62) -> 0.14 | CD32: =CHOOSE(MATCH($CE$2,{"Bull","Base","Bear"},0),$CN$63,$CO$63,$CP$63) -> 0.13 | CM32: 2030E | CN32: =CO32+$CN$28 -> 0.095 | CO32: 0.075 | CP32: =CO32+$CP$28 -> 0.045
B33: Q4/26E growth before calibration (9M FY26 y/y) | BX33: =IFERROR(SUM(BU31:BW31)/SUM(BP31:BR31)-1,0) -> 0.40076469 | CE33: Trend input: 9M FY26 ÷ 9M FY25 other revenue − 1. | CM33: 2031E | CN33: =CO33+$CN$28 -> 0.095 | CO33: 0.075 | CP33: =CO33+$CP$28 -> 0.045
B34: Gross revenue | C34: =IF(ISNUMBER(C20),C20+C24+C28+C31,"") -> 7424 | D34: =IF(ISNUMBER(D20),D20+D24+D28+D31,"") -> 8145 | E34: =IF(ISNUMBER(E20),E20+E24+E28+E31,"") -> 9625 | F34: =IF(ISNUMBER(F20),F20+F24+F28+F31,"") -> 11068 | G34: =IF(ISNUMBER(G20),G20+G24+G28+G31,"") -> 12576 | H34: =IF(ISNUMBER(H20),H20+H24+H28+H31,"") -> 3399 | I34: =IF(ISNUMBER(I20),I20+I24+I28+I31,"") -> 3525 | J34: =IF(ISNUMBER(J20),J20+J24+J28+J31,"") -> 3522 | ... CD34: =IF(ISNUMBER(CD20),CD20+CD24+CD28+CD31,"") -> 104072.27 | CG34: =IFERROR((CD34/BY34)^(1/5)-1,"n/m") -> 0.10264188 | CH34: =IFERROR((BT34/AU34)^(1/5)-1,"n/m") -> 0.14353928 | CI34: =IFERROR((BT34/V34)^(1/10)-1,"n/m") -> 0.12783905 | CJ34: =IFERROR((BT34/C34)^(1/17)-1,"n/m") -> 0.12591796 | CM34: PTX (processed transactions y/y) | CN34: 0.02 | CO34: Δ → | CP34: -0.03 | CQ34: FY2023–25 +10–10.4%; 9M FY26 +9.1%. Tap-to-pay, e-commerce, new flows.
B35: Gross revenue y/y % | D35: =IF(AND(ISNUMBER(D34),ISNUMBER(C34)),IFERROR(D34/C34-1,""),"") -> 0.097117457 | E35: =IF(AND(ISNUMBER(E34),ISNUMBER(D34)),IFERROR(E34/D34-1,""),"") -> 0.18170657 | F35: =IF(AND(ISNUMBER(F34),ISNUMBER(E34)),IFERROR(F34/E34-1,""),"") -> 0.14992208 | G35: =IF(AND(ISNUMBER(G34),ISNUMBER(F34)),IFERROR(G34/F34-1,""),"") -> 0.13624864 | L35: =IF(AND(ISNUMBER(L34),ISNUMBER(G34)),IFERROR(L34/G34-1,""),"") -> 0.12110369 | M35: =IF(AND(ISNUMBER(M34),ISNUMBER(H34)),IFERROR(M34/H34-1,""),"") -> 0.10444248 | N35: =IF(AND(ISNUMBER(N34),ISNUMBER(I34)),IFERROR(N34/I34-1,""),"") -> 0.063829787 | O35: =IF(AND(ISNUMBER(O34),ISNUMBER(J34)),IFERROR(O34/J34-1,""),"") -> 0.076944918 | P35: =IF(AND(ISNUMBER(P34),ISNUMBER(K34)),IFERROR(P34/K34-1,""),"") -> 0.094169176 | Q35: =IF(AND(ISNUMBER(Q34),ISNUMBER(L34)),IFERROR(Q34/L34-1,""),"") -> 0.084757784 | R35: =IF(AND(ISNUMBER(R34),ISNUMBER(M34)),IFERROR(R34/M34-1,""),"") -> 0.090836441 | S35: =IF(AND(ISNUMBER(S34),ISNUMBER(N34)),IFERROR(S34/N34-1,""),"") -> 0.089333333 | ... BY35: =IF(AND(ISNUMBER(BY34),ISNUMBER(BT34)),IFERROR(BY34/BT34-1,""),"") -> 0.14527548 | BZ35: =IF(AND(ISNUMBER(BZ34),ISNUMBER(BY34)),IFERROR(BZ34/BY34-1,""),"") -> 0.11562184 | CA35: =IF(AND(ISNUMBER(CA34),ISNUMBER(BZ34)),IFERROR(CA34/BZ34-1,""),"") -> 0.10924959 | CB35: =IF(AND(ISNUMBER(CB34),ISNUMBER(CA34)),IFERROR(CB34/CA34-1,""),"") -> 0.10194248 | CC35: =IF(AND(ISNUMBER(CC34),ISNUMBER(CB34)),IFERROR(CC34/CB34-1,""),"") -> 0.094858647 | CD35: =IF(AND(ISNUMBER(CD34),ISNUMBER(CC34)),IFERROR(CD34/CC34-1,""),"") -> 0.0917147 | CM35: 2027E | CN35: =CO35+$CN$34 -> 0.11 | CO35: 0.09 | CP35: =CO35+$CP$34 -> 0.06
B36: Client incentives (deducted from gross revenue) | C36: 1161 | D36: 1234 | E36: 1560 | F36: 1880 | G36: 2155 | H36: 553 | I36: 567 | J36: 521 | K36: 680 | L36: 2321 | M36: 599 | N36: 587 | O36: 638 | P36: 768 | Q36: 2592 | R36: 713 | S36: 676 | T36: 670 | U36: 802 | V36: 2861 | W36: 788 | X36: 789 | Y36: 839 | Z36: 993 | AA36: 3409 | AB36: 1041 | AC36: 1031 | AD36: 1147 | AE36: 1346 | AF36: 4565 | AG36: 1326 | AH36: 1289 | AI36: 1374 | AJ36: 1502 | AK36: 5491 | AL36: 1456 | AM36: 1478 | AN36: 1546 | AO36: 1693 | AP36: 6173 | AQ36: 1748 | AR36: 1705 | AS36: 1513 | AT36: 1698 | AU36: 6664 | AV36: 1858 | AW36: 1992 | AX36: 2130 | AY36: 2387 | AZ36: 8367 | BA36: 2371 | BB36: 2494 | BC36: 2570 | BD36: 2860 | BE36: 10295 | BF36: 2786 | BG36: 2905 | BH36: 3167 | BI36: 3439 | BJ36: 12297 | BK36: 3348 | BL36: 3257 | BM36: 3530 | BN36: 3629 | BO36: 13764 | BP36: 3797 | BQ36: 3734 | BR36: 3972 | BS36: 4248 | BT36: 15751 | BU36: 4269 | BV36: 4245 | BW36: 4680 | BX36: =BX34*BX37 -> 4774.1335 | BY36: =SUM(BU36:BX36) -> 17968.133 | BZ36: =BZ34*BZ37 -> 20586.261 | CA36: =CA34*CA37 -> 22993.331 | CB36: =CB34*CB37 -> 25511.468 | CC36: =CC34*CC37 -> 28122.11 | CD36: =CD34*CD37 -> 30909.465 | CE36: Contra-revenue: incentives to financial-institution clients and merchants ("volume and support incentives" to FY2012). | CG36: =IFERROR((CD36/BY36)^(1/5)-1,"n/m") -> 0.11459658 | CH36: =IFERROR((BT36/AU36)^(1/5)-1,"n/m") -> 0.18772153 | CI36: =IFERROR((BT36/V36)^(1/10)-1,"n/m") -> 0.18598454 | CJ36: =IFERROR((BT36/C36)^(1/17)-1,"n/m") -> 0.16577901 | CM36: 2028E | CN36: =CO36+$CN$34 -> 0.11 | CO36: 0.09 | CP36: =CO36+$CP$34 -> 0.06
B37: Client incentives % of gross revenue | C37: =IF(AND(ISNUMBER(C36),ISNUMBER(C34)),IFERROR(C36/C34,""),"") -> 0.1563847 | D37: =IF(AND(ISNUMBER(D36),ISNUMBER(D34)),IFERROR(D36/D34,""),"") -> 0.15150399 | E37: =IF(AND(ISNUMBER(E36),ISNUMBER(E34)),IFERROR(E36/E34,""),"") -> 0.16207792 | F37: =IF(AND(ISNUMBER(F36),ISNUMBER(F34)),IFERROR(F36/F34,""),"") -> 0.16985905 | G37: =IF(AND(ISNUMBER(G36),ISNUMBER(G34)),IFERROR(G36/G34,""),"") -> 0.17135814 | H37: =IF(AND(ISNUMBER(H36),ISNUMBER(H34)),IFERROR(H36/H34,""),"") -> 0.16269491 | I37: =IF(AND(ISNUMBER(I36),ISNUMBER(I34)),IFERROR(I36/I34,""),"") -> 0.16085106 | J37: =IF(AND(ISNUMBER(J36),ISNUMBER(J34)),IFERROR(J36/J34,""),"") -> 0.14792731 | ... BW37: =IF(AND(ISNUMBER(BW36),ISNUMBER(BW34)),IFERROR(BW36/BW34,""),"") -> 0.28688776 | BX37: =BS37+IFERROR(SUM(BU36:BW36)/SUM(BU34:BW34)-SUM(BP36:BR36)/SUM(BP34:BR34),0) -> 0.28262265 | BY37: =IF(AND(ISNUMBER(BY36),ISNUMBER(BY34)),IFERROR(BY36/BY34,""),"") -> 0.28141053 | BZ37: =CHOOSE(MATCH($CE$2,{"Bull","Base","Bear"},0),$CN$65,$CO$65,$CP$65) -> 0.289 | CA37: =CHOOSE(MATCH($CE$2,{"Bull","Base","Bear"},0),$CN$66,$CO$66,$CP$66) -> 0.291 | CB37: =CHOOSE(MATCH($CE$2,{"Bull","Base","Bear"},0),$CN$67,$CO$67,$CP$67) -> 0.293 | CC37: =CHOOSE(MATCH($CE$2,{"Bull","Base","Bear"},0),$CN$68,$CO$68,$CP$68) -> 0.295 | CD37: =CHOOSE(MATCH($CE$2,{"Bull","Base","Bear"},0),$CN$69,$CO$69,$CP$69) -> 0.297 | CE37: Q4/26E: prior-year quarter + 9M FY26 y/y drift. 2027E+: scenario lever (renewals; FY2025 28.0%). | CG37: =IFERROR(AVERAGE(BZ37,CA37,CB37,CC37,CD37),"n/m") -> 0.293 | CH37: =IFERROR(AVERAGE(AZ37,BE37,BJ37,BO37,BT37),"n/m") -> 0.27014043 | CI37: =IFERROR(AVERAGE(AA37,AF37,AK37,AP37,AU37,AZ37,BE37,BJ37,BO37,BT37),"n/m") -> 0.23900995 | CJ37: =IFERROR(AVERAGE(C37,D37,E37,F37,G37,L37,Q37,V37,AA37,AF37,AK37,AP37,AU37,AZ37,BE37,BJ37,BO37,BT37),"n/m") -> 0.2059045 | CM37: 2029E | CN37: =CO37+$CN$34 -> 0.105 | CO37: 0.085 | CP37: =CO37+$CP$34 -> 0.055
B38: Revenue from future acquisitions (M&A lever) | BX38: =N(BX78) -> 0 | BY38: =N(BY78) -> 0 | BZ38: =N(BZ78) -> 62.5 | CA38: =N(CA78) -> 206.25 | CB38: =N(CB78) -> 371.5625 | CC38: =N(CC78) -> 561.67188 | CD38: =N(CD78) -> 780.29766 | CM38: 2030E | CN38: =CO38+$CN$34 -> 0.1 | CO38: 0.08 | CP38: =CO38+$CP$34 -> 0.05
B39: Net revenue (build) | C39: =IF(ISNUMBER(C34),C34-C36,C113) -> 6263 | D39: =IF(ISNUMBER(D34),D34-D36,D113) -> 6911 | E39: =IF(ISNUMBER(E34),E34-E36,E113) -> 8065 | F39: =IF(ISNUMBER(F34),F34-F36,F113) -> 9188 | G39: =IF(ISNUMBER(G34),G34-G36,G113) -> 10421 | H39: =IF(ISNUMBER(H34),H34-H36,H113) -> 2846 | I39: =IF(ISNUMBER(I34),I34-I36,I113) -> 2958 | J39: =IF(ISNUMBER(J34),J34-J36,J113) -> 3001 | ... BW39: =IF(ISNUMBER(BW34),BW34-BW36,BW113) -> 11633 | BX39: =BX34-BX36+BX38 -> 12118.12 | BY39: =SUM(BU39:BX39) -> 45882.12 | BZ39: =BZ34-BZ36+BZ38 -> 50708.976 | CA39: =CA34-CA36+CA38 -> 56227.803 | CB39: =CB34-CB36+CB38 -> 61929.952 | CC39: =CC34-CC36+CC38 -> 67768.748 | CD39: =CD34-CD36+CD38 -> 73943.106 | CE39: Gross revenue − client incentives (+ future acquisitions from 2027E). Drives the income statement. | CG39: =IFERROR((CD39/BY39)^(1/5)-1,"n/m") -> 0.10014731 | CH39: =IFERROR((BT39/AU39)^(1/5)-1,"n/m") -> 0.12859368 | CI39: =IFERROR((BT39/V39)^(1/10)-1,"n/m") -> 0.11164739 | CJ39: =IFERROR((BT39/C39)^(1/17)-1,"n/m") -> 0.11524239 | CM39: 2031E | CN39: =CO39+$CN$34 -> 0.1 | CO39: 0.08 | CP39: =CO39+$CP$34 -> 0.05
B40: Net revenue y/y % | D40: =IF(AND(ISNUMBER(D39),ISNUMBER(C39)),IFERROR(D39/C39-1,""),"") -> 0.10346479 | E40: =IF(AND(ISNUMBER(E39),ISNUMBER(D39)),IFERROR(E39/D39-1,""),"") -> 0.16698018 | F40: =IF(AND(ISNUMBER(F39),ISNUMBER(E39)),IFERROR(F39/E39-1,""),"") -> 0.13924365 | G40: =IF(AND(ISNUMBER(G39),ISNUMBER(F39)),IFERROR(G39/F39-1,""),"") -> 0.13419678 | L40: =IF(AND(ISNUMBER(L39),ISNUMBER(G39)),IFERROR(L39/G39-1,""),"") -> 0.13021783 | M40: =IF(AND(ISNUMBER(M39),ISNUMBER(H39)),IFERROR(M39/H39-1,""),"") -> 0.10857344 | N40: =IF(AND(ISNUMBER(N39),ISNUMBER(I39)),IFERROR(N39/I39-1,""),"") -> 0.069303584 | O40: =IF(AND(ISNUMBER(O39),ISNUMBER(J39)),IFERROR(O39/J39-1,""),"") -> 0.051316228 | P40: =IF(AND(ISNUMBER(P39),ISNUMBER(K39)),IFERROR(P39/K39-1,""),"") -> 0.086108308 | Q40: =IF(AND(ISNUMBER(Q39),ISNUMBER(L39)),IFERROR(Q39/L39-1,""),"") -> 0.07845135 | R40: =IF(AND(ISNUMBER(R39),ISNUMBER(M39)),IFERROR(R39/M39-1,""),"") -> 0.071949287 | S40: =IF(AND(ISNUMBER(S39),ISNUMBER(N39)),IFERROR(S39/N39-1,""),"") -> 0.077774265 | ... BY40: =IF(AND(ISNUMBER(BY39),ISNUMBER(BT39)),IFERROR(BY39/BT39-1,""),"") -> 0.147053 | BZ40: =IF(AND(ISNUMBER(BZ39),ISNUMBER(BY39)),IFERROR(BZ39/BY39-1,""),"") -> 0.10520125 | CA40: =IF(AND(ISNUMBER(CA39),ISNUMBER(BZ39)),IFERROR(CA39/BZ39-1,""),"") -> 0.10883333 | CB40: =IF(AND(ISNUMBER(CB39),ISNUMBER(CA39)),IFERROR(CB39/CA39-1,""),"") -> 0.10141155 | CC40: =IF(AND(ISNUMBER(CC39),ISNUMBER(CB39)),IFERROR(CC39/CB39-1,""),"") -> 0.094280657 | CD40: =IF(AND(ISNUMBER(CD39),ISNUMBER(CC39)),IFERROR(CD39/CC39-1,""),"") -> 0.091109224 | CM40: SVC_YLD (service yield change y/y) | CN40: 0.01 | CO40: Δ → | CP40: -0.015 | CQ40: Service revenue ÷ prior-quarter payments volume: FY2021–25 +1.1% to +5.4% a year (pricing, card benefits); 9M FY26 +2.8%.
B41: Check: build vs reported net revenue (should be 0) | C41: =IF(ISNUMBER(C39),IF(ABS(C39-C113)<=0.6,0,ROUND(C39-C113,1)),"") -> 0 | D41: =IF(ISNUMBER(D39),IF(ABS(D39-D113)<=0.6,0,ROUND(D39-D113,1)),"") -> 0 | E41: =IF(ISNUMBER(E39),IF(ABS(E39-E113)<=0.6,0,ROUND(E39-E113,1)),"") -> 0 | F41: =IF(ISNUMBER(F39),IF(ABS(F39-F113)<=0.6,0,ROUND(F39-F113,1)),"") -> 0 | G41: =IF(ISNUMBER(G39),IF(ABS(G39-G113)<=0.6,0,ROUND(G39-G113,1)),"") -> 0 | H41: =IF(ISNUMBER(H39),IF(ABS(H39-H113)<=0.6,0,ROUND(H39-H113,1)),"") -> 0 | I41: =IF(ISNUMBER(I39),IF(ABS(I39-I113)<=0.6,0,ROUND(I39-I113,1)),"") -> 0 | J41: =IF(ISNUMBER(J39),IF(ABS(J39-J113)<=0.6,0,ROUND(J39-J113,1)),"") -> 0 | ... BW41: =IF(ISNUMBER(BW39),IF(ABS(BW39-BW113)<=0.6,0,ROUND(BW39-BW113,1)),"") -> 0 | CM41: 2027E | CN41: =CO41+$CN$40 -> 0.02 | CO41: 0.01 | CP41: =CO41+$CP$40 -> -0.005
B42: Net revenue yield (net revenue ÷ nominal payments volume) | C42: =IF(AND(ISNUMBER(C39),ISNUMBER(C11)),IFERROR(C39/(C11*1000),""),"") | D42: =IF(AND(ISNUMBER(D39),ISNUMBER(D11)),IFERROR(D39/(D11*1000),""),"") -> 0.0025796939 | E42: =IF(AND(ISNUMBER(E39),ISNUMBER(E11)),IFERROR(E39/(E11*1000),""),"") -> 0.0026555812 | F42: =IF(AND(ISNUMBER(F39),ISNUMBER(F11)),IFERROR(F39/(F11*1000),""),"") -> 0.0026028329 | G42: =IF(AND(ISNUMBER(G39),ISNUMBER(G11)),IFERROR(G39/(G11*1000),""),"") -> 0.0026727366 | H42: =IF(AND(ISNUMBER(H39),ISNUMBER(H11)),IFERROR(H39/(H11*1000),""),"") -> 0.0028234127 | I42: =IF(AND(ISNUMBER(I39),ISNUMBER(I11)),IFERROR(I39/(I11*1000),""),"") -> 0.0027541899 | J42: =IF(AND(ISNUMBER(J39),ISNUMBER(J11)),IFERROR(J39/(J11*1000),""),"") -> 0.0029278049 | ... CD42: =IF(AND(ISNUMBER(CD39),ISNUMBER(CD11)),IFERROR(CD39/(CD11*1000),""),"") -> 0.0032953148 | CG42: =IFERROR(AVERAGE(BZ42,CA42,CB42,CC42,CD42),"n/m") -> 0.0031810041 | CH42: =IFERROR(AVERAGE(AZ42,BE42,BJ42,BO42,BT42),"n/m") -> 0.0026650456 | CI42: =IFERROR(AVERAGE(AA42,AF42,AK42,AP42,AU42,AZ42,BE42,BJ42,BO42,BT42),"n/m") -> 0.0026250185 | CJ42: =IFERROR(AVERAGE(C42,D42,E42,F42,G42,L42,Q42,V42,AA42,AF42,AK42,AP42,AU42,AZ42,BE42,BJ42,BO42,BT42),"n/m") -> 0.0026582653 | CM42: 2028E | CN42: =CO42+$CN$40 -> 0.02 | CO42: 0.01 | CP42: =CO42+$CP$40 -> -0.005
B43: Net revenue growth decomposition — payments volume y/y (pp) | D43: =IFERROR(D11/C11-1,"") | E43: =IFERROR(E11/D11-1,"") -> 0.13363195 | F43: =IFERROR(F11/E11-1,"") -> 0.16233125 | G43: =IFERROR(G11/F11-1,"") -> 0.10453258 | L43: =IFERROR(L11/G11-1,"") -> 0.076429854 | M43: =IFERROR(M11/H11-1,"") -> 0.095238095 | N43: =IFERROR(N11/I11-1,"") -> 0.083798883 | O43: =IFERROR(O11/J11-1,"") -> 0.08097561 | P43: =IFERROR(P11/K11-1,"") -> 0.091659028 | Q43: =IFERROR(Q11/L11-1,"") -> 0.088158208 | R43: =IFERROR(R11/M11-1,"") -> 0.10235507 | S43: =IFERROR(S11/N11-1,"") -> 0.069587629 | ... BY43: =IFERROR(BY11/BT11-1,"") -> 0.10428026 | BZ43: =IFERROR(BZ11/BY11-1,"") -> 0.085 | CA43: =IFERROR(CA11/BZ11-1,"") -> 0.08 | CB43: =IFERROR(CB11/CA11-1,"") -> 0.08 | CC43: =IFERROR(CC11/CB11-1,"") -> 0.075 | CD43: =IFERROR(CD11/CC11-1,"") -> 0.075 | CM43: 2029E | CN43: =CO43+$CN$40 -> 0.015 | CO43: 0.005 | CP43: =CO43+$CP$40 -> -0.01
B44: Net revenue growth decomposition — net revenue yield y/y (pp) | D44: =IFERROR((D39/C39)/(D11/C11)-1,"") | E44: =IFERROR((E39/D39)/(E11/D11)-1,"") -> 0.029417153 | F44: =IFERROR((F39/E39)/(F11/E11)-1,"") -> -0.019863187 | G44: =IFERROR((G39/F39)/(G11/F11)-1,"") -> 0.026856791 | L44: =IFERROR((L39/G39)/(L11/G11)-1,"") -> 0.049968863 | M44: =IFERROR((M39/H39)/(M11/H11)-1,"") -> 0.012175746 | N44: =IFERROR((N39/I39)/(N11/I11)-1,"") -> -0.013374529 | O44: =IFERROR((O39/J39)/(O11/J11)-1,"") -> -0.027437605 | P44: =IFERROR((P39/K39)/(P11/K11)-1,"") -> -0.0050846649 | Q44: =IFERROR((Q39/L39)/(Q11/L11)-1,"") -> -0.0089204476 | R44: =IFERROR((R39/M39)/(R11/M11)-1,"") -> -0.02758257 | S44: =IFERROR((S39/N39)/(S11/N11)-1,"") -> 0.0076540116 | ... BY44: =IFERROR((BY39/BT39)/(BY11/BT11)-1,"") -> 0.038733586 | BZ44: =IFERROR((BZ39/BY39)/(BZ11/BY11)-1,"") -> 0.01861866 | CA44: =IFERROR((CA39/BZ39)/(CA11/BZ11)-1,"") -> 0.02669753 | CB44: =IFERROR((CB39/CA39)/(CB11/CA11)-1,"") -> 0.019825508 | CC44: =IFERROR((CC39/CB39)/(CC11/CB11)-1,"") -> 0.017935494 | CD44: =IFERROR((CD39/CC39)/(CD11/CC11)-1,"") -> 0.014985325 | CM44: 2030E | CN44: =CO44+$CN$40 -> 0.015 | CO44: 0.005 | CP44: =CO44+$CP$40 -> -0.01
CM45: 2031E | CN45: =CO45+$CN$40 -> 0.015 | CO45: 0.005 | CP45: =CO45+$CP$40 -> -0.01
B46: Q4/26E calibration — net revenue and non-GAAP EPS to the Q4 FY26 outlook (UNVERIFIED: given on the call, not filed on EDGAR) | CE46: CALIBRATION — Visa guides on the earnings call only (no outlook in the 8-K release since FY2020); end-points are labelled unverified | CM46: DP_RPT (data processing revenue per transaction, y/y) | CN46: 0.015 | CO46: Δ → | CP46: -0.02 | CQ46: FY2021–25 −3.4% to +2.4%; 9M FY26 +7.5% (pricing, value-added services, cross-border mix).
B47: Memo: Q4/26E net revenue end-point = Q4/25 × (1 + outlook growth, active scenario) | BX47: =BS113*(1+CHOOSE(MATCH($CE$2,{"Bull","Base","Bear"},0),$CN$12,$CO$12,$CP$12)) -> 12118.12 | CE47: Q4 FY26 adjusted net revenue growth 'similar to Q3' (Q3: +14% nominal, +13% constant dollar) - UNVERIFIED. Model end-points high / mid / low = 14% / 13% / 12% on Q4 FY25 net revenue $10,724m. Drives the Q4/26E revenue calibration. | CM47: 2027E | CN47: =CO47+$CN$46 -> 0.04 | CO47: 0.025 | CP47: =CO47+$CP$46 -> 0.005
B48: Net revenue before calibration (Q4/26E helper) | BX48: =(BX11*1000*BS21*(1+BX22)+BX16*BS25*(1+BX26)+BS28*(1+BX30)+BS31*(1+BX33))*(1-BX37) -> 12418.827 | CM48: 2028E | CN48: =CO48+$CN$46 -> 0.035 | CO48: 0.02 | CP48: =CO48+$CP$46 -> 0
B49: Net revenue sensitivity to +1.00 of the calibration Δ (Q4/26E helper) | BX49: =(BX11*1000*BS21+BX16*BS25+BS28+BS31)*(1-BX37) -> 11455.382 | CM49: 2029E | CN49: =CO49+$CN$46 -> 0.035 | CO49: 0.02 | CP49: =CO49+$CP$46 -> 0
B50: Calibration Δ: uniform shift in service yield, data processing yield, international and other revenue growth (Q4/26E) | BX50: =(BX47-BX48)/BX49 -> -0.026250249 | CE50: Closed-form solve (no goal-seek): Δ = (end-point − pre-calibration) ÷ sensitivity. Payments volume is published, so the Δ falls on yields and growth rates. | CM50: 2030E | CN50: =CO50+$CN$46 -> 0.03 | CO50: 0.015 | CP50: =CO50+$CP$46 -> -0.005
B51: Check: Q4/26E net revenue vs outlook end-point (should be 0) | BX51: =ROUND(BX39-BX47,1) -> 0 | CM51: 2031E | CN51: =CO51+$CN$46 -> 0.03 | CO51: 0.015 | CP51: =CO51+$CP$46 -> -0.005
B52: Memo: implied FY26 net revenue growth (information; see the unverified full-year commentary) | BY52: =BY40 -> 0.147053 | CM52: ITR (international transaction revenue y/y) | CN52: 0.03 | CO52: Δ → | CP52: -0.06 | CQ52: FY2023–25 +8.8% to +18.6% (travel recovery to FY23); 9M FY26 +7.4% (lower currency volatility). Cross-border volume ex intra-Europe growth low-teens.
CM53: 2027E | CN53: =CO53+$CN$52 -> 0.13 | CO53: 0.1 | CP53: =CO53+$CP$52 -> 0.04
B54: Operating expenses (non-GAAP, company definition) → adjusted operating income | CE54: OPEX — non-GAAP operating expenses exclude the company's adjusting items (litigation provisions, acquired-intangible amortization, acquisition costs, severance …) | CM54: 2028E | CN54: =CO54+$CN$52 -> 0.13 | CO54: 0.1 | CP54: =CO54+$CP$52 -> 0.04
B55: Adjusted operating expenses (GAAP operating expenses − operating adjusting items) | C55: =IF(ISNUMBER(C123),C123-C159,"") -> 3366 | D55: =IF(ISNUMBER(D123),D123-D159,"") -> 3238 | E55: =IF(ISNUMBER(E123),E123-E159,"") -> 3476 | F55: =IF(ISNUMBER(F123),F123-F159,"") -> 3732 | G55: =IF(ISNUMBER(G123),G123-G159,"") -> 4184 | H55: =IF(ISNUMBER(H123),H123-H159,"") -> 1046 | I55: =IF(ISNUMBER(I123),I123-I159,"") -> 1098 | J55: =IF(ISNUMBER(J123),J123-J159,"") -> 1173 | ... BW55: =IF(ISNUMBER(BW123),BW123-BW159,"") -> 3878 | BX55: =BS55*(1+BX57+$BX$67) -> 4132.0316 | BY55: =SUM(BU55:BX55) -> 15000.032 | BZ55: =BZ39*(1-BZ61) -> 16480.417 | CA55: =CA39*(1-CA61) -> 18161.58 | CB55: =CB39*(1-CB61) -> 19817.585 | CC55: =CC39*(1-CC61) -> 21685.999 | CD55: =CD39*(1-CD61) -> 23513.908 | CE55: Q4/26E: prior-year quarter × (1 + 9M FY26 y/y + EPS calibration Δ). 2027E+: net revenue × (1 − adjusted operating margin lever). | CG55: =IFERROR((CD55/BY55)^(1/5)-1,"n/m") -> 0.094073571 | CH55: =IFERROR((BT55/AU55)^(1/5)-1,"n/m") -> 0.1087602 | CI55: =IFERROR((BT55/V55)^(1/10)-1,"n/m") -> 0.10359702 | CJ55: =IFERROR((BT55/C55)^(1/17)-1,"n/m") -> 0.082265896 | CM55: 2029E | CN55: =CO55+$CN$52 -> 0.12 | CO55: 0.09 | CP55: =CO55+$CP$52 -> 0.03
B56: y/y % | D56: =IF(AND(ISNUMBER(D55),ISNUMBER(C55)),IFERROR(D55/C55-1,""),"") -> -0.038027332 | E56: =IF(AND(ISNUMBER(E55),ISNUMBER(D55)),IFERROR(E55/D55-1,""),"") -> 0.073502162 | F56: =IF(AND(ISNUMBER(F55),ISNUMBER(E55)),IFERROR(F55/E55-1,""),"") -> 0.073647871 | G56: =IF(AND(ISNUMBER(G55),ISNUMBER(F55)),IFERROR(G55/F55-1,""),"") -> 0.12111468 | L56: =IF(AND(ISNUMBER(L55),ISNUMBER(G55)),IFERROR(L55/G55-1,""),"") -> 0.084847036 | M56: =IF(AND(ISNUMBER(M55),ISNUMBER(H55)),IFERROR(M55/H55-1,""),"") -> 0.030592734 | N56: =IF(AND(ISNUMBER(N55),ISNUMBER(I55)),IFERROR(N55/I55-1,""),"") -> 0.015482696 | O56: =IF(AND(ISNUMBER(O55),ISNUMBER(J55)),IFERROR(O55/J55-1,""),"") -> -0.032395567 | P56: =IF(AND(ISNUMBER(P55),ISNUMBER(K55)),IFERROR(P55/K55-1,""),"") -> 0.004091653 | Q56: =IF(AND(ISNUMBER(Q55),ISNUMBER(L55)),IFERROR(Q55/L55-1,""),"") -> 0.0035250055 | R56: =IF(AND(ISNUMBER(R55),ISNUMBER(M55)),IFERROR(R55/M55-1,""),"") -> 0.06122449 | S56: =IF(AND(ISNUMBER(S55),ISNUMBER(N55)),IFERROR(S55/N55-1,""),"") -> 0.011659193 | ... BY56: =IF(AND(ISNUMBER(BY55),ISNUMBER(BT55)),IFERROR(BY55/BT55-1,""),"") -> 0.16225257 | BZ56: =IF(AND(ISNUMBER(BZ55),ISNUMBER(BY55)),IFERROR(BZ55/BY55-1,""),"") -> 0.098692169 | CA56: =IF(AND(ISNUMBER(CA55),ISNUMBER(BZ55)),IFERROR(CA55/BZ55-1,""),"") -> 0.10200974 | CB56: =IF(AND(ISNUMBER(CB55),ISNUMBER(CA55)),IFERROR(CB55/CA55-1,""),"") -> 0.09118172 | CC56: =IF(AND(ISNUMBER(CC55),ISNUMBER(CB55)),IFERROR(CC55/CB55-1,""),"") -> 0.094280657 | CD56: =IF(AND(ISNUMBER(CD55),ISNUMBER(CC55)),IFERROR(CD55/CC55-1,""),"") -> 0.084289792 | CM56: 2030E | CN56: =CO56+$CN$52 -> 0.12 | CO56: 0.09 | CP56: =CO56+$CP$52 -> 0.03
B57: Q4/26E growth before EPS calibration (9M FY26 y/y) | BX57: =IFERROR(SUM(BU55:BW55)/SUM(BP55:BR55)-1,0) -> 0.16923077 | CE57: Trend input: 9M FY26 ÷ 9M FY25 non-GAAP operating expenses − 1 (incl. FIFA World Cup / Olympics marketing). | CM57: 2031E | CN57: =CO57+$CN$52 -> 0.11 | CO57: 0.08 | CP57: =CO57+$CP$52 -> 0.02
B58: Company-published non-GAAP operating expenses | C58: 3366 | D58: 3238 | G58: 4184 | P58: 1227 | Q58: 4555 | V58: 4816 | Y58: 1173 | Z58: 1526 | AA58: 5060 | AC58: 1477 | AF58: 6022 | AI58: 1755 | AJ58: 1833 | AK58: 6860 | AO58: 2032 | AP58: 7606 | AQ58: 2025 | AR58: 1914 | AS58: 1821 | AT58: 1942 | AU58: 7702 | AV58: 1828 | AW58: 1978 | AX58: 2048 | AY58: 2223 | AZ58: 8077 | BA58: 2115 | BB58: 2287 | BC58: 2353 | BD58: 2632 | BE58: 9387 | BF58: 2439 | BG58: 2581 | BH58: 2578 | BI58: 2883 | BJ58: 10481 | BK58: 2619 | BL58: 2871 | BM58: 2927 | BN58: 3192 | BO58: 11609 | BP58: 2917 | BQ58: 3071 | BR58: 3307 | BS58: 3611 | BT58: 12906 | BU58: 3391 | BV58: 3599 | BW58: 3878 | CM58: OTH (other revenue y/y: value-added services, consulting, marketing) | CN58: 0.05 | CO58: Δ → | CP58: -0.08 | CQ58: FY2023–25 +24.5% to +29.0%; 9M FY26 +40.1% (consulting, marketing services incl. FIFA World Cup 2026, Milano Cortina 2026).
B59: Check: model vs company-published non-GAAP operating expenses (should be 0) | C59: =IF(ISNUMBER(C58),IF(ABS(C55-C58)<=1.01,0,ROUND(C55-C58,1)),"n/p") -> 0 | D59: =IF(ISNUMBER(D58),IF(ABS(D55-D58)<=1.01,0,ROUND(D55-D58,1)),"n/p") -> 0 | E59: =IF(ISNUMBER(E58),IF(ABS(E55-E58)<=1.01,0,ROUND(E55-E58,1)),"n/p") -> n/p | F59: =IF(ISNUMBER(F58),IF(ABS(F55-F58)<=1.01,0,ROUND(F55-F58,1)),"n/p") -> n/p | G59: =IF(ISNUMBER(G58),IF(ABS(G55-G58)<=1.01,0,ROUND(G55-G58,1)),"n/p") -> 0 | H59: =IF(ISNUMBER(H58),IF(ABS(H55-H58)<=1.01,0,ROUND(H55-H58,1)),"n/p") -> n/p | I59: =IF(ISNUMBER(I58),IF(ABS(I55-I58)<=1.01,0,ROUND(I55-I58,1)),"n/p") -> n/p | J59: =IF(ISNUMBER(J58),IF(ABS(J55-J58)<=1.01,0,ROUND(J55-J58,1)),"n/p") -> n/p | ... BW59: =IF(ISNUMBER(BW58),IF(ABS(BW55-BW58)<=1.01,0,ROUND(BW55-BW58,1)),"n/p") -> 0 | CM59: 2027E | CN59: =CO59+$CN$58 -> 0.27 | CO59: 0.22 | CP59: =CO59+$CP$58 -> 0.14
B60: Adjusted operating income (net revenue − non-GAAP operating expenses) | C60: =IF(ISNUMBER(C55),C39-C55,"") -> 2897 | D60: =IF(ISNUMBER(D55),D39-D55,"") -> 3673 | E60: =IF(ISNUMBER(E55),E39-E55,"") -> 4589 | F60: =IF(ISNUMBER(F55),F39-F55,"") -> 5456 | G60: =IF(ISNUMBER(G55),G39-G55,"") -> 6237 | H60: =IF(ISNUMBER(H55),H39-H55,"") -> 1800 | I60: =IF(ISNUMBER(I55),I39-I55,"") -> 1860 | J60: =IF(ISNUMBER(J55),J39-J55,"") -> 1828 | ... CD60: =IF(ISNUMBER(CD55),CD39-CD55,"") -> 50429.198 | CG60: =IFERROR((CD60/BY60)^(1/5)-1,"n/m") -> 0.1030497 | CH60: =IFERROR((BT60/AU60)^(1/5)-1,"n/m") -> 0.13883335 | CI60: =IFERROR((BT60/V60)^(1/10)-1,"n/m") -> 0.11572027 | CJ60: =IFERROR((BT60/C60)^(1/17)-1,"n/m") -> 0.14054707 | CM60: 2028E | CN60: =CO60+$CN$58 -> 0.23 | CO60: 0.18 | CP60: =CO60+$CP$58 -> 0.1
B61: Adjusted operating margin % | C61: =IF(AND(ISNUMBER(C60),ISNUMBER(C39)),IFERROR(C60/C39,""),"") -> 0.46255788 | D61: =IF(AND(ISNUMBER(D60),ISNUMBER(D39)),IFERROR(D60/D39,""),"") -> 0.53147157 | E61: =IF(AND(ISNUMBER(E60),ISNUMBER(E39)),IFERROR(E60/E39,""),"") -> 0.56900186 | F61: =IF(AND(ISNUMBER(F60),ISNUMBER(F39)),IFERROR(F60/F39,""),"") -> 0.59381802 | G61: =IF(AND(ISNUMBER(G60),ISNUMBER(G39)),IFERROR(G60/G39,""),"") -> 0.59850302 | H61: =IF(AND(ISNUMBER(H60),ISNUMBER(H39)),IFERROR(H60/H39,""),"") -> 0.63246662 | I61: =IF(AND(ISNUMBER(I60),ISNUMBER(I39)),IFERROR(I60/I39,""),"") -> 0.62880325 | J61: =IF(AND(ISNUMBER(J60),ISNUMBER(J39)),IFERROR(J60/J39,""),"") -> 0.60913029 | ... BY61: =IF(AND(ISNUMBER(BY60),ISNUMBER(BY39)),IFERROR(BY60/BY39,""),"") -> 0.67307457 | BZ61: =CHOOSE(MATCH($CE$2,{"Bull","Base","Bear"},0),$CN$71,$CO$71,$CP$71) -> 0.675 | CA61: =CHOOSE(MATCH($CE$2,{"Bull","Base","Bear"},0),$CN$72,$CO$72,$CP$72) -> 0.677 | CB61: =CHOOSE(MATCH($CE$2,{"Bull","Base","Bear"},0),$CN$73,$CO$73,$CP$73) -> 0.68 | CC61: =CHOOSE(MATCH($CE$2,{"Bull","Base","Bear"},0),$CN$74,$CO$74,$CP$74) -> 0.68 | CD61: =CHOOSE(MATCH($CE$2,{"Bull","Base","Bear"},0),$CN$75,$CO$75,$CP$75) -> 0.682 | CE61: 2027E+: scenario lever (FY2025 adjusted operating margin 67.4%; FY2019 68.5%). | CG61: =IFERROR(AVERAGE(BZ61,CA61,CB61,CC61,CD61),"n/m") -> 0.6788 | CH61: =IFERROR(AVERAGE(AZ61,BE61,BJ61,BO61,BT61),"n/m") -> 0.6755781 | CI61: =IFERROR(AVERAGE(AA61,AF61,AK61,AP61,AU61,AZ61,BE61,BJ61,BO61,BT61),"n/m") -> 0.66979101 | CJ61: =IFERROR(AVERAGE(C61,D61,E61,F61,G61,L61,Q61,V61,AA61,AF61,AK61,AP61,AU61,AZ61,BE61,BJ61,BO61,BT61),"n/m") -> 0.63123911 | CM61: 2029E | CN61: =CO61+$CN$58 -> 0.21 | CO61: 0.16 | CP61: =CO61+$CP$58 -> 0.08
B62: Adjusted operating income y/y % | D62: =IF(AND(ISNUMBER(D60),ISNUMBER(C60)),IFERROR(D60/C60-1,""),"") -> 0.26786331 | E62: =IF(AND(ISNUMBER(E60),ISNUMBER(D60)),IFERROR(E60/D60-1,""),"") -> 0.24938742 | F62: =IF(AND(ISNUMBER(F60),ISNUMBER(E60)),IFERROR(F60/E60-1,""),"") -> 0.18893005 | G62: =IF(AND(ISNUMBER(G60),ISNUMBER(F60)),IFERROR(G60/F60-1,""),"") -> 0.14314516 | L62: =IF(AND(ISNUMBER(L60),ISNUMBER(G60)),IFERROR(L60/G60-1,""),"") -> 0.16065416 | M62: =IF(AND(ISNUMBER(M60),ISNUMBER(H60)),IFERROR(M60/H60-1,""),"") -> 0.15388889 | N62: =IF(AND(ISNUMBER(N60),ISNUMBER(I60)),IFERROR(N60/I60-1,""),"") -> 0.10107527 | O62: =IF(AND(ISNUMBER(O60),ISNUMBER(J60)),IFERROR(O60/J60-1,""),"") -> 0.10503282 | P62: =IF(AND(ISNUMBER(P60),ISNUMBER(K60)),IFERROR(P60/K60-1,""),"") -> 0.14334666 | Q62: =IF(AND(ISNUMBER(Q60),ISNUMBER(L60)),IFERROR(Q60/L60-1,""),"") -> 0.12543169 | R62: =IF(AND(ISNUMBER(R60),ISNUMBER(M60)),IFERROR(R60/M60-1,""),"") -> 0.077515648 | S62: =IF(AND(ISNUMBER(S60),ISNUMBER(N60)),IFERROR(S60/N60-1,""),"") -> 0.11376953 | ... BY62: =IF(AND(ISNUMBER(BY60),ISNUMBER(BT60)),IFERROR(BY60/BT60-1,""),"") -> 0.13981281 | BZ62: =IF(AND(ISNUMBER(BZ60),ISNUMBER(BY60)),IFERROR(BZ60/BY60-1,""),"") -> 0.10836283 | CA62: =IF(AND(ISNUMBER(CA60),ISNUMBER(BZ60)),IFERROR(CA60/BZ60-1,""),"") -> 0.11211876 | CB62: =IF(AND(ISNUMBER(CB60),ISNUMBER(CA60)),IFERROR(CB60/CA60-1,""),"") -> 0.10629225 | CC62: =IF(AND(ISNUMBER(CC60),ISNUMBER(CB60)),IFERROR(CC60/CB60-1,""),"") -> 0.094280657 | CD62: =IF(AND(ISNUMBER(CD60),ISNUMBER(CC60)),IFERROR(CD60/CC60-1,""),"") -> 0.094318369 | CM62: 2030E | CN62: =CO62+$CN$58 -> 0.19 | CO62: 0.14 | CP62: =CO62+$CP$58 -> 0.06
B63: Incremental adjusted operating margin (Δ adjusted OI / Δ net revenue) | D63: =IFERROR((D60-C60)/(D39-C39),"") -> 1.1975309 | E63: =IFERROR((E60-D60)/(E39-D39),"") -> 0.79376083 | F63: =IFERROR((F60-E60)/(F39-E39),"") -> 0.77203918 | G63: =IFERROR((G60-F60)/(G39-F39),"") -> 0.63341444 | L63: =IFERROR((L60-G60)/(L39-G39),"") -> 0.73839352 | M63: =IFERROR((M60-H60)/(M39-H39),"") -> 0.89644013 | N63: =IFERROR((N60-I60)/(N39-I39),"") -> 0.91707317 | O63: =IFERROR((O60-J60)/(O39-J39),"") -> 1.2467532 | P63: =IFERROR((P60-K60)/(P39-K39),"") -> 0.98046875 | Q63: =IFERROR((Q60-L60)/(Q39-L39),"") -> 0.98268398 | R63: =IFERROR((R60-M60)/(R39-M39),"") -> 0.7092511 | S63: =IFERROR((S60-N60)/(S39-N39),"") -> 0.94715447 | ... BY63: =IFERROR((BY60-BT60)/(BY39-BT39),"") -> 0.64400053 | BZ63: =IFERROR((BZ60-BY60)/(BZ39-BY39),"") -> 0.69330231 | CA63: =IFERROR((CA60-BZ60)/(CA39-BZ39),"") -> 0.69537672 | CB63: =IFERROR((CB60-CA60)/(CB39-CA39),"") -> 0.70958243 | CC63: =IFERROR((CC60-CB60)/(CC39-CB39),"") -> 0.68 | CD63: =IFERROR((CD60-CC60)/(CD39-CC39),"") -> 0.70395167 | CM63: 2031E | CN63: =CO63+$CN$58 -> 0.18 | CO63: 0.13 | CP63: =CO63+$CP$58 -> 0.05
B64: Memo: Q4/26E non-GAAP EPS end-point = Q4/25 × (1 + outlook growth, active scenario) ($) | BX64: =BS192*(1+CHOOSE(MATCH($CE$2,{"Bull","Base","Bear"},0),$CN$13,$CO$13,$CP$13)) -> 3.3972 | CE64: Q4 FY26 non-GAAP EPS growth 'low end of mid-teens' - UNVERIFIED. End-points 15% / 14% / 13% on Q4 FY25 non-GAAP EPS $2.98. Drives the Q4/26E operating-expense calibration. | CM64: CI (client incentives % of gross revenue) | CN64: -0.005 | CO64: Δ → | CP64: 0.01 | CQ64: FY2017 19.9% → FY2025 28.3% (renewals, competition for issuers); Q3 FY26 28.7%. Base +0.2pt a year.
B65: Adjusted net income required (Q4/26E diluted shares × EPS end-point) | BX65: =BX64*BX190 -> 6403.1216 | CM65: 2027E | CN65: =CO65+$CN$64 -> 0.284 | CO65: 0.289 | CP65: =CO65+$CP$64 -> 0.299
B66: Adjusted operating income required (NI ÷ (1 − adjusted tax rate) − adjusted non-operating income) | BX66: =BX65/(1-BX197)-(BX129-BX128) -> 7986.0884 | CM66: 2028E | CN66: =CO66+$CN$64 -> 0.286 | CO66: 0.291 | CP66: =CO66+$CP$64 -> 0.301
B67: Calibration Δ: shift in adjusted operating-expense growth (Q4/26E) | BX67: =(BX39-BX66)/BS55-1-BX57 -> -0.024940653 | CE67: Solves Q4/26E adjusted opex so that non-GAAP EPS = the end-point for the active scenario. | CM67: 2029E | CN67: =CO67+$CN$64 -> 0.288 | CO67: 0.293 | CP67: =CO67+$CP$64 -> 0.303
B68: Check: Q4/26E non-GAAP EPS vs outlook end-point (should be 0.00) | BX68: =ROUND(BX191-BX64,2) -> 0 | CM68: 2030E | CN68: =CO68+$CN$64 -> 0.29 | CO68: 0.295 | CP68: =CO68+$CP$64 -> 0.305
B69: Memo: implied FY26 non-GAAP EPS growth (information; call commentary "low end of mid-teens", UNVERIFIED) | BY69: =BY194 -> 0.15032826 | CM69: 2031E | CN69: =CO69+$CN$64 -> 0.292 | CO69: 0.297 | CP69: =CO69+$CP$64 -> 0.307
B70: Memo: Q4/26E adjusted operating-expense growth (information; call commentary "low double digits", UNVERIFIED) | BX70: =BX56 -> 0.14429012 | CM70: AOM (adjusted operating margin) | CN70: 0.01 | CO70: Δ → | CP70: -0.02 | CQ70: Non-GAAP: FY2018–25 66.5–68.0% (FY2025 67.7%, FY2020 64.7%); 9M FY26 67.8% with marketing for the FIFA World Cup 2026. Base flat-to-slightly-up.
CM71: 2027E | CN71: =CO71+$CN$70 -> 0.685 | CO71: 0.675 | CP71: =CO71+$CP$70 -> 0.655
B72: Future acquisitions (M&A lever — value-added services / new flows bolt-ons; deals closed from 2027E) | CE72: M&A LEVER — acquired revenue = spend ÷ EV/sales; mid-year convention | CM72: 2028E | CN72: =CO72+$CN$70 -> 0.687 | CO72: 0.677 | CP72: =CO72+$CP$70 -> 0.657
B73: Acquisition spend (USDm, scenario) | BY73: 0 | BZ73: =MAX(0,CHOOSE(MATCH($CE$2,{"Bull","Base","Bear"},0),$CN$77,$CO$77,$CP$77)) -> 1000 | CA73: =MAX(0,CHOOSE(MATCH($CE$2,{"Bull","Base","Bear"},0),$CN$78,$CO$78,$CP$78)) -> 1000 | CB73: =MAX(0,CHOOSE(MATCH($CE$2,{"Bull","Base","Bear"},0),$CN$79,$CO$79,$CP$79)) -> 1000 | CC73: =MAX(0,CHOOSE(MATCH($CE$2,{"Bull","Base","Bear"},0),$CN$80,$CO$80,$CP$80)) -> 1000 | CD73: =MAX(0,CHOOSE(MATCH($CE$2,{"Bull","Base","Bear"},0),$CN$81,$CO$81,$CP$81)) -> 1000 | CE73: Scenario lever M&A_spend (Base $1.0bn p.a.). Funded from cash (debt schedule). | CM73: 2029E | CN73: =CO73+$CN$70 -> 0.69 | CO73: 0.68 | CP73: =CO73+$CP$70 -> 0.66
B74: Purchase multiple — EV / sales (x) | BY74: 0 | BZ74: 8 | CA74: 8 | CB74: 8 | CC74: 8 | CD74: 8 | CE74: Fintech / software targets (Tink, Pismo, Featurespace, Currencycloud): prices not split by revenue in the filings; 8.0x EV/sales input (assumption). | CM74: 2030E | CN74: =CO74+$CN$70 -> 0.69 | CO74: 0.68 | CP74: =CO74+$CP$70 -> 0.66
B75: Annualised revenue acquired in the year | BY75: 0 | BZ75: =IFERROR(BZ73/BZ74,0) -> 125 | CA75: =IFERROR(CA73/CA74,0) -> 125 | CB75: =IFERROR(CB73/CB74,0) -> 125 | CC75: =IFERROR(CC73/CC74,0) -> 125 | CD75: =IFERROR(CD73/CD74,0) -> 125 | CE75: Spend ÷ EV/sales. | CM75: 2031E | CN75: =CO75+$CN$70 -> 0.692 | CO75: 0.682 | CP75: =CO75+$CP$70 -> 0.662
B76: Growth of acquired businesses after acquisition % | BY76: 0 | BZ76: 0.15 | CA76: 0.15 | CB76: 0.15 | CC76: 0.15 | CD76: 0.15 | CE76: Assumption: acquired fintech / value-added-services revenue grows 15% a year. | CM76: M&A_spend (acquisitions, $m) | CN76: 1000 | CO76: Δ → | CP76: -1000 | CQ76: Visa spent ~$0.9bn (Featurespace, FY25), ~$1.0bn (Pismo, FY24), ~$2.0bn (Tink, FY23), $0.7bn (9M FY26). Base $1.0bn p.a. (assumption).
B77: Run-rate revenue of businesses acquired (year end) | BY77: 0 | BZ77: =BY77*(1+BZ76)+BZ75 -> 125 | CA77: =BZ77*(1+CA76)+CA75 -> 268.75 | CB77: =CA77*(1+CB76)+CB75 -> 434.0625 | CC77: =CB77*(1+CC76)+CC75 -> 624.17188 | CD77: =CC77*(1+CD76)+CD75 -> 842.79766 | CE77: Prior run-rate × (1 + growth) + revenue acquired in the year. | CM77: 2027E | CN77: =MAX(0,CO77+$CN$76) -> 2000 | CO77: 1000 | CP77: =MAX(0,CO77+$CP$76) -> 0
B78: Revenue from future acquisitions | BY78: 0 | BZ78: =BY77*(1+BZ76)+0.5*BZ75 -> 62.5 | CA78: =BZ77*(1+CA76)+0.5*CA75 -> 206.25 | CB78: =CA77*(1+CB76)+0.5*CB75 -> 371.5625 | CC78: =CB77*(1+CC76)+0.5*CC75 -> 561.67188 | CD78: =CC77*(1+CD76)+0.5*CD75 -> 780.29766 | CE78: Mid-year convention. | CM78: 2028E | CN78: =MAX(0,CO78+$CN$76) -> 2000 | CO78: 1000 | CP78: =MAX(0,CO78+$CP$76) -> 0
B79: Adjusted operating margin of acquired businesses % | BY79: 0 | BZ79: 0 | CA79: 0 | CB79: 0 | CC79: 0 | CD79: 0 | CE79: Assumption: acquired businesses break even at the adjusted operating level (already inside the group margin lever). | CM79: 2029E | CN79: =MAX(0,CO79+$CN$76) -> 2000 | CO79: 1000 | CP79: =MAX(0,CO79+$CP$76) -> 0
B80: PP&E (technology) % of spend | BY80: 0 | BZ80: 0.05 | CA80: 0.05 | CB80: 0.05 | CC80: 0.05 | CD80: 0.05 | CE80: Assumption: 5% of consideration to PP&E / technology. | CM80: 2030E | CN80: =MAX(0,CO80+$CN$76) -> 2000 | CO80: 1000 | CP80: =MAX(0,CO80+$CP$76) -> 0
B81: Acquired intangibles % of spend | BY81: 0 | BZ81: 0.25 | CA81: 0.25 | CB81: 0.25 | CC81: 0.25 | CD81: 0.25 | CE81: Assumption: technology and customer relationships ~25% of consideration, the remainder goodwill (Visa's FY22–25 deals were mostly goodwill). | CM81: 2031E | CN81: =MAX(0,CO81+$CN$76) -> 2000 | CO81: 1000 | CP81: =MAX(0,CO81+$CP$76) -> 0
B82: Intangible amortization life (years) | BY82: 0 | BZ82: 7 | CA82: 7 | CB82: 7 | CC82: 7 | CD82: 7 | CE82: Assumption: 7-year life for acquired technology and customer relationships.
B83: Cumulative acquired intangibles (gross) | BY83: 0 | BZ83: =BY83+BZ73*BZ81 -> 250 | CA83: =BZ83+CA73*CA81 -> 500 | CB83: =CA83+CB73*CB81 -> 750 | CC83: =CB83+CC73*CC81 -> 1000 | CD83: =CC83+CD73*CD81 -> 1250 | CE83: Running total of acquired intangibles (gross).
B84: Amortization of future-acquisition intangibles (non-GAAP item) | BY84: 0 | BZ84: =IFERROR((BY83+0.5*BZ73*BZ81)/BZ82,0) -> 17.857143 | CA84: =IFERROR((BZ83+0.5*CA73*CA81)/CA82,0) -> 53.571429 | CB84: =IFERROR((CA83+0.5*CB73*CB81)/CB82,0) -> 89.285714 | CC84: =IFERROR((CB83+0.5*CC73*CC81)/CC82,0) -> 125 | CD84: =IFERROR((CC83+0.5*CD73*CD81)/CD82,0) -> 160.71429 | CE84: Cumulative acquired intangibles (+ half the year's additions) ÷ life; added to the non-GAAP amortization item.
B86: Cost drivers, D&A, share-based compensation & adjusting items | CE86: COST DRIVERS — expense lines are allocated from adjusted opex by the 9M FY26 mix; adjusting items are added back on their GAAP line
B87: Personnel (ex adjusting items) % of adjusted operating expenses | C87: =IF(ISNUMBER(C55),IFERROR((N(C115)-N(C104))/C55,""),"") -> 0.31461676 | D87: =IF(ISNUMBER(D55),IFERROR((N(D115)-N(D104))/D55,""),"") -> 0.33230389 | E87: =IF(ISNUMBER(E55),IFERROR((N(E115)-N(E104))/E55,""),"") -> 0.35155351 | F87: =IF(ISNUMBER(F55),IFERROR((N(F115)-N(F104))/F55,""),"") -> 0.39094319 | G87: =IF(ISNUMBER(G55),IFERROR((N(G115)-N(G104))/G55,""),"") -> 0.4125239 | H87: =IF(ISNUMBER(H55),IFERROR((N(H115)-N(H104))/H55,""),"") -> 0.43403442 | I87: =IF(ISNUMBER(I55),IFERROR((N(I115)-N(I104))/I55,""),"") -> 0.44262295 | J87: =IF(ISNUMBER(J55),IFERROR((N(J115)-N(J104))/J55,""),"") -> 0.42028986 | ... BW87: =IF(ISNUMBER(BW55),IFERROR((N(BW115)-N(BW104))/BW55,""),"") -> 0.48865395 | BX87: =IFERROR((SUM(BU115:BW115)-SUM(BU104:BW104))/SUM(BU55:BW55),0) -> 0.50607287 | BY87: =$BX$87 -> 0.50607287 | BZ87: =$BX$87 -> 0.50607287 | CA87: =$BX$87 -> 0.50607287 | CB87: =$BX$87 -> 0.50607287 | CC87: =$BX$87 -> 0.50607287 | CD87: =$BX$87 -> 0.50607287 | CE87: History: (GAAP line − adjusting items recorded on it) ÷ adjusted opex. Forecast: 9M FY26 mix, held.
B88: Marketing (ex adjusting items) % of adjusted operating expenses | C88: =IF(ISNUMBER(C55),IFERROR((N(C116))/C55,""),"") -> 0.30184195 | D88: =IF(ISNUMBER(D55),IFERROR((N(D116))/D55,""),"") -> 0.28350834 | E88: =IF(ISNUMBER(E55),IFERROR((N(E116))/E55,""),"") -> 0.27733026 | F88: =IF(ISNUMBER(F55),IFERROR((N(F116))/F55,""),"") -> 0.23311897 | G88: =IF(ISNUMBER(G55),IFERROR((N(G116))/G55,""),"") -> 0.20865201 | H88: =IF(ISNUMBER(H55),IFERROR((N(H116))/H55,""),"") -> 0.18451243 | I88: =IF(ISNUMBER(I55),IFERROR((N(I116))/I55,""),"") -> 0.17759563 | J88: =IF(ISNUMBER(J55),IFERROR((N(J116))/J55,""),"") -> 0.21483376 | ... BW88: =IF(ISNUMBER(BW55),IFERROR((N(BW116))/BW55,""),"") -> 0.16735431 | BX88: =IFERROR((SUM(BU116:BW116))/SUM(BU55:BW55),0) -> 0.14758925 | BY88: =$BX$88 -> 0.14758925 | BZ88: =$BX$88 -> 0.14758925 | CA88: =$BX$88 -> 0.14758925 | CB88: =$BX$88 -> 0.14758925 | CC88: =$BX$88 -> 0.14758925 | CD88: =$BX$88 -> 0.14758925
B89: Network and processing (ex adjusting items) % of adjusted operating expenses | C89: =IF(ISNUMBER(C55),IFERROR((N(C117))/C55,""),"") -> 0.10071301 | D89: =IF(ISNUMBER(D55),IFERROR((N(D117))/D55,""),"") -> 0.12137122 | E89: =IF(ISNUMBER(E55),IFERROR((N(E117))/E55,""),"") -> 0.12226697 | F89: =IF(ISNUMBER(F55),IFERROR((N(F117))/F55,""),"") -> 0.095659164 | G89: =IF(ISNUMBER(G55),IFERROR((N(G117))/G55,""),"") -> 0.098948375 | H89: =IF(ISNUMBER(H55),IFERROR((N(H117))/H55,""),"") -> 0.10516252 | I89: =IF(ISNUMBER(I55),IFERROR((N(I117))/I55,""),"") -> 0.10837887 | J89: =IF(ISNUMBER(J55),IFERROR((N(J117))/J55,""),"") -> 0.099744246 | ... BW89: =IF(ISNUMBER(BW55),IFERROR((N(BW117))/BW55,""),"") -> 0.072202166 | BX89: =IFERROR((SUM(BU117:BW117))/SUM(BU55:BW55),0) -> 0.071126242 | BY89: =$BX$89 -> 0.071126242 | BZ89: =$BX$89 -> 0.071126242 | CA89: =$BX$89 -> 0.071126242 | CB89: =$BX$89 -> 0.071126242 | CC89: =$BX$89 -> 0.071126242 | CD89: =$BX$89 -> 0.071126242
B90: Professional fees (ex adjusting items) % of adjusted operating expenses | C90: =IF(ISNUMBER(C55),IFERROR((N(C118))/C55,""),"") -> 0.13012478 | D90: =IF(ISNUMBER(D55),IFERROR((N(D118))/D55,""),"") -> 0.10901791 | E90: =IF(ISNUMBER(E55),IFERROR((N(E118))/E55,""),"") -> 0.082278481 | F90: =IF(ISNUMBER(F55),IFERROR((N(F118))/F55,""),"") -> 0.090300107 | G90: =IF(ISNUMBER(G55),IFERROR((N(G118))/G55,""),"") -> 0.092017208 | H90: =IF(ISNUMBER(H55),IFERROR((N(H118))/H55,""),"") -> 0.084130019 | I90: =IF(ISNUMBER(I55),IFERROR((N(I118))/I55,""),"") -> 0.08287796 | J90: =IF(ISNUMBER(J55),IFERROR((N(J118))/J55,""),"") -> 0.087809037 | ... BW90: =IF(ISNUMBER(BW55),IFERROR((N(BW118))/BW55,""),"") -> 0.06343476 | BX90: =IFERROR((SUM(BU118:BW118))/SUM(BU55:BW55),0) -> 0.063673169 | BY90: =$BX$90 -> 0.063673169 | BZ90: =$BX$90 -> 0.063673169 | CA90: =$BX$90 -> 0.063673169 | CB90: =$BX$90 -> 0.063673169 | CC90: =$BX$90 -> 0.063673169 | CD90: =$BX$90 -> 0.063673169
B91: Depreciation and amortization (ex adjusting items) % of adjusted operating expenses | C91: =IF(ISNUMBER(C55),IFERROR((N(C119)-N(C100))/C55,""),"") -> 0.050207962 | D91: =IF(ISNUMBER(D55),IFERROR((N(D119)-N(D100))/D55,""),"") -> 0.048795553 | E91: =IF(ISNUMBER(E55),IFERROR((N(E119)-N(E100))/E55,""),"") -> 0.076237054 | F91: =IF(ISNUMBER(F55),IFERROR((N(F119)-N(F100))/F55,""),"") -> 0.077170418 | G91: =IF(ISNUMBER(G55),IFERROR((N(G119)-N(G100))/G55,""),"") -> 0.07958891 | H91: =IF(ISNUMBER(H55),IFERROR((N(H119)-N(H100))/H55,""),"") -> 0.087954111 | I91: =IF(ISNUMBER(I55),IFERROR((N(I119)-N(I100))/I55,""),"") -> 0.089253188 | J91: =IF(ISNUMBER(J55),IFERROR((N(J119)-N(J100))/J55,""),"") -> 0.086104007 | ... BW91: =IF(ISNUMBER(BW55),IFERROR((N(BW119)-N(BW100))/BW55,""),"") -> 0.078133058 | BX91: =IFERROR((SUM(BU119:BW119)-SUM(BU100:BW100))/SUM(BU55:BW55),0) -> 0.078947368 | BY91: =$BX$91 -> 0.078947368 | BZ91: =$BX$91 -> 0.078947368 | CA91: =$BX$91 -> 0.078947368 | CB91: =$BX$91 -> 0.078947368 | CC91: =$BX$91 -> 0.078947368 | CD91: =$BX$91 -> 0.078947368
B92: General and administrative (ex adjusting items) % of adjusted operating expenses | C92: =IF(ISNUMBER(C55),IFERROR((N(C120)-N(C102))/C55,""),"") -> 0.098633393 | D92: =IF(ISNUMBER(D55),IFERROR((N(D120)-N(D102))/D55,""),"") -> 0.10438542 | E92: =IF(ISNUMBER(E55),IFERROR((N(E120)-N(E102))/E55,""),"") -> 0.10327963 | F92: =IF(ISNUMBER(F55),IFERROR((N(F120)-N(F102))/F55,""),"") -> 0.11093248 | G92: =IF(ISNUMBER(G55),IFERROR((N(G120)-N(G102))/G55,""),"") -> 0.10779159 | H92: =IF(ISNUMBER(H55),IFERROR((N(H120)-N(H102))/H55,""),"") -> 0.10133843 | I92: =IF(ISNUMBER(I55),IFERROR((N(I120)-N(I102))/I55,""),"") -> 0.098360656 | J92: =IF(ISNUMBER(J55),IFERROR((N(J120)-N(J102))/J55,""),"") -> 0.092071611 | ... BW92: =IF(ISNUMBER(BW55),IFERROR((N(BW120)-N(BW102))/BW55,""),"") -> 0.12609593 | BX92: =IFERROR((SUM(BU120:BW120)-SUM(BU102:BW102))/SUM(BU55:BW55),0) -> 0.12937063 | BY92: =$BX$92 -> 0.12937063 | BZ92: =$BX$92 -> 0.12937063 | CA92: =$BX$92 -> 0.12937063 | CB92: =$BX$92 -> 0.12937063 | CC92: =$BX$92 -> 0.12937063 | CD92: =$BX$92 -> 0.12937063
B93: Litigation provision (ex adjusting items) % of adjusted operating expenses | C93: =IF(ISNUMBER(C55),IFERROR((N(C121)-N(C99))/C55,""),"") -> 0.0038621509 | D93: =IF(ISNUMBER(D55),IFERROR((N(D121)-N(D99))/D55,""),"") -> 0.00061766523 | E93: =IF(ISNUMBER(E55),IFERROR((N(E121)-N(E99))/E55,""),"") -> -0.012945915 | F93: =IF(ISNUMBER(F55),IFERROR((N(F121)-N(F99))/F55,""),"") -> 0.0018756699 | G93: =IF(ISNUMBER(G55),IFERROR((N(G121)-N(G99))/G55,""),"") -> 0.00047801147 | H93: =IF(ISNUMBER(H55),IFERROR((N(H121)-N(H99))/H55,""),"") -> 0.0028680688 | I93: =IF(ISNUMBER(I55),IFERROR((N(I121)-N(I99))/I55,""),"") -> 0.00091074681 | J93: =IF(ISNUMBER(J55),IFERROR((N(J121)-N(J99))/J55,""),"") -> -0.00085251492 | ... BW93: =IF(ISNUMBER(BW55),IFERROR((N(BW121)-N(BW99))/BW55,""),"") -> 0.0041258381 | BX93: =IFERROR((SUM(BU121:BW121)-SUM(BU99:BW99))/SUM(BU55:BW55),0) -> 0.0032204637 | BY93: =$BX$93 -> 0.0032204637 | BZ93: =$BX$93 -> 0.0032204637 | CA93: =$BX$93 -> 0.0032204637 | CB93: =$BX$93 -> 0.0032204637 | CC93: =$BX$93 -> 0.0032204637 | CD93: =$BX$93 -> 0.0032204637
B94: Check: expense-line mix sums to 100% (should be 0) | BX94: =ROUND(BX87+BX88+BX89+BX90+BX91+BX92+BX93-1,4) -> 0 | BY94: =ROUND(BY87+BY88+BY89+BY90+BY91+BY92+BY93-1,4) -> 0 | BZ94: =ROUND(BZ87+BZ88+BZ89+BZ90+BZ91+BZ92+BZ93-1,4) -> 0 | CA94: =ROUND(CA87+CA88+CA89+CA90+CA91+CA92+CA93-1,4) -> 0 | CB94: =ROUND(CB87+CB88+CB89+CB90+CB91+CB92+CB93-1,4) -> 0 | CC94: =ROUND(CC87+CC88+CC89+CC90+CC91+CC92+CC93-1,4) -> 0 | CD94: =ROUND(CD87+CD88+CD89+CD90+CD91+CD92+CD93-1,4) -> 0
B95: Depreciation & amortization (GAAP) % of net revenue | C95: =IF(AND(ISNUMBER(C119),ISNUMBER(C113)),IFERROR(C119/C113,""),"") -> 0.03784129 | D95: =IF(AND(ISNUMBER(D119),ISNUMBER(D113)),IFERROR(D119/D113,""),"") -> 0.03270149 | E95: =IF(AND(ISNUMBER(E119),ISNUMBER(E113)),IFERROR(E119/E113,""),"") -> 0.032858029 | F95: =IF(AND(ISNUMBER(F119),ISNUMBER(F113)),IFERROR(F119/F113,""),"") -> 0.031345233 | G95: =IF(AND(ISNUMBER(G119),ISNUMBER(G113)),IFERROR(G119/G113,""),"") -> 0.031954707 | H95: =IF(AND(ISNUMBER(H119),ISNUMBER(H113)),IFERROR(H119/H113,""),"") -> 0.032326072 | I95: =IF(AND(ISNUMBER(I119),ISNUMBER(I113)),IFERROR(I119/I113,""),"") -> 0.033130494 | J95: =IF(AND(ISNUMBER(J119),ISNUMBER(J113)),IFERROR(J119/J113,""),"") -> 0.033655448 | ... CD95: =IF(AND(ISNUMBER(CD119),ISNUMBER(CD113)),IFERROR(CD119/CD113,""),"") -> 0.028360662 | CG95: =IFERROR(AVERAGE(BZ95,CA95,CB95,CC95,CD95),"n/m") -> 0.029319213 | CH95: =IFERROR(AVERAGE(AZ95,BE95,BJ95,BO95,BT95),"n/m") -> 0.030178106 | CI95: =IFERROR(AVERAGE(AA95,AF95,AK95,AP95,AU95,AZ95,BE95,BJ95,BO95,BT95),"n/m") -> 0.030786574 | CJ95: =IFERROR(AVERAGE(C95,D95,E95,F95,G95,L95,Q95,V95,AA95,AF95,AK95,AP95,AU95,AZ95,BE95,BJ95,BO95,BT95),"n/m") -> 0.032117264
B96: Share-based compensation (cash-flow statement) | C96: 74 | D96: 115 | E96: 131 | F96: 154 | G96: 147 | H96: 48 | I96: 50 | J96: 41 | K96: 40 | L96: 179 | M96: 45 | N96: 44 | O96: 41 | P96: 42 | Q96: 172 | R96: 45 | S96: 48 | T96: 46 | U96: 48 | V96: 187 | W96: 39 | X96: 58 | Y96: 55 | Z96: 69 | AA96: 221 | AB96: 45 | AC96: 71 | AD96: 67 | AE96: 52 | AF96: 235 | AG96: 68 | AH96: 85 | AI96: 89 | AJ96: 85 | AK96: 327 | AL96: 100 | AM96: 111 | AN96: 110 | AO96: 86 | AP96: 407 | AQ96: 116 | AR96: 99 | AS96: 107 | AT96: 94 | AU96: 416 | AV96: 122 | AW96: 153 | AX96: 159 | AY96: 108 | AZ96: 542 | BA96: 128 | BB96: 190 | BC96: 152 | BD96: 132 | BE96: 602 | BF96: 177 | BG96: 223 | BH96: 191 | BI96: 174 | BJ96: 765 | BK96: 209 | BL96: 242 | BM96: 211 | BN96: 188 | BO96: 850 | BP96: 224 | BQ96: 259 | BR96: 223 | BS96: 191 | BT96: 897 | BU96: 231 | BV96: 275 | BW96: 222 | BX96: =BS96*(1+IFERROR(SUM(BU96:BW96)/SUM(BP96:BR96)-1,0)) -> 196.95184 | BY96: =SUM(BU96:BX96) -> 924.95184 | BZ96: =BZ113*BZ97 -> 1166.3065 | CA96: =CA113*CA97 -> 1293.2395 | CB96: =CB113*CB97 -> 1424.3889 | CC96: =CC113*CC97 -> 1558.6812 | CD96: =CD113*CD97 -> 1700.6914 | CE96: Q4/26E: prior-year quarter × 9M FY26 y/y; 2027E+: % of net revenue. Visa does not adjust out share-based compensation. | CG96: =IFERROR((CD96/BY96)^(1/5)-1,"n/m") -> 0.12953913 | CH96: =IFERROR((BT96/AU96)^(1/5)-1,"n/m") -> 0.16611081 | CI96: =IFERROR((BT96/V96)^(1/10)-1,"n/m") -> 0.16975547 | CJ96: =IFERROR((BT96/C96)^(1/17)-1,"n/m") -> 0.15808081
B97: Share-based compensation % of net revenue | C97: =IF(AND(ISNUMBER(C96),ISNUMBER(C113)),IFERROR(C96/C113,""),"") -> 0.011815424 | D97: =IF(AND(ISNUMBER(D96),ISNUMBER(D113)),IFERROR(D96/D113,""),"") -> 0.016640139 | E97: =IF(AND(ISNUMBER(E96),ISNUMBER(E113)),IFERROR(E96/E113,""),"") -> 0.016243025 | F97: =IF(AND(ISNUMBER(F96),ISNUMBER(F113)),IFERROR(F96/F113,""),"") -> 0.016760993 | G97: =IF(AND(ISNUMBER(G96),ISNUMBER(G113)),IFERROR(G96/G113,""),"") -> 0.014106132 | H97: =IF(AND(ISNUMBER(H96),ISNUMBER(H113)),IFERROR(H96/H113,""),"") -> 0.016865777 | I97: =IF(AND(ISNUMBER(I96),ISNUMBER(I113)),IFERROR(I96/I113,""),"") -> 0.016903313 | J97: =IF(AND(ISNUMBER(J96),ISNUMBER(J113)),IFERROR(J96/J113,""),"") -> 0.013662113 | ... BY97: =IF(AND(ISNUMBER(BY96),ISNUMBER(BY113)),IFERROR(BY96/BY113,""),"") -> 0.020159309 | BZ97: 0.023 | CA97: 0.023 | CB97: 0.023 | CC97: 0.023 | CD97: 0.023 | CE97: Input 2.3% of net revenue (FY2021–25 2.1–2.4%). | CG97: =IFERROR(AVERAGE(BZ97,CA97,CB97,CC97,CD97),"n/m") -> 0.023 | CH97: =IFERROR(AVERAGE(AZ97,BE97,BJ97,BO97,BT97),"n/m") -> 0.022507388 | CI97: =IFERROR(AVERAGE(AA97,AF97,AK97,AP97,AU97,AZ97,BE97,BJ97,BO97,BT97),"n/m") -> 0.019261374 | CJ97: =IFERROR(AVERAGE(C97,D97,E97,F97,G97,L97,Q97,V97,AA97,AF97,AK97,AP97,AU97,AZ97,BE97,BJ97,BO97,BT97),"n/m") -> 0.017243948
B98: Operating adjusting items (pre-tax, excluded from non-GAAP by the company; forecast inputs):
B99: Litigation provision (U.S. covered litigation, VE territory and other significant matters) | C99: 1457 | D99: 0 | E99: 0 | F99: 0 | G99: 4098 | H99: 0 | I99: 0 | J99: 0 | K99: 0 | L99: 0 | M99: 0 | N99: 0 | O99: 0 | P99: 450 | Q99: 450 | R99: 0 | S99: 0 | T99: 0 | U99: 0 | V99: 0 | W99: 0 | X99: 0 | Y99: 0 | Z99: 0 | AA99: 0 | AB99: 0 | AC99: 0 | AD99: 0 | AE99: 0 | AF99: 0 | AG99: 0 | AH99: 0 | AI99: 600 | AJ99: 0 | AK99: 600 | AL99: 0 | AM99: 0 | AN99: 0 | AO99: 370 | AP99: 370 | AQ99: 0 | AR99: 0 | AS99: 0 | AT99: 0 | AU99: 0 | AV99: 0 | AW99: 0 | AX99: 0 | AY99: 0 | AZ99: 0 | BA99: 145 | BB99: 0 | BC99: 716 | BD99: 0 | BE99: 861 | BF99: 341 | BG99: 0 | BH99: 456 | BI99: 109 | BJ99: 906 | BK99: 0 | BL99: 424 | BM99: 10 | BN99: 0 | BO99: 434 | BP99: 27 | BQ99: 992 | BR99: 615 | BS99: 899 | BT99: 2533 | BU99: 707 | BV99: 311 | BW99: 237 | BX99: =$CO$21 -> 0 | BY99: =SUM(BU99:BX99) -> 1255 | BZ99: 0 | CA99: 0 | CB99: 0 | CC99: 0 | CD99: 0 | CE99: U.S. retrospective responsibility plan: covered litigation is paid from the U.S. litigation escrow ($888m at 30-Jun-2026; $875m deposited 9M FY26), funded by reducing the class B conversion rate (an as-converted share reduction with no P&L effect). VE territory covered losses are recovered through series B / C preferred conversion-rate adjustments. Litigation provisions are excluded from non-GAAP results; the forecast assumes no further provisions or escrow deposits (assumption).
B100: Amortization of acquired intangible assets (inside D&A) | C100: 68 | D100: 68 | E100: 0 | F100: 0 | G100: 0 | H100: 0 | I100: 0 | J100: 0 | K100: 0 | L100: 0 | M100: 0 | N100: 0 | O100: 0 | P100: 0 | Q100: 0 | R100: 0 | S100: 0 | T100: 0 | U100: 0 | V100: 0 | W100: 0 | X100: 0 | Y100: 0 | Z100: 0 | AA100: 0 | AB100: 0 | AC100: 0 | AD100: 0 | AE100: 0 | AF100: 0 | AG100: 0 | AH100: 0 | AI100: 0 | AJ100: 0 | AK100: 0 | AL100: 0 | AM100: 0 | AN100: 0 | AO100: 0 | AP100: 0 | AQ100: 11 | AR100: 11 | AS100: 13 | AT100: 11 | AU100: 46 | AV100: 12 | AW100: 13 | AX100: 13 | AY100: 13 | AZ100: 51 | BA100: 13 | BB100: 20 | BC100: 44 | BD100: 43 | BE100: 120 | BF100: 43 | BG100: 46 | BH100: 41 | BI100: 46 | BJ100: 176 | BK100: 40 | BL100: 43 | BM100: 48 | BN100: 47 | BO100: 178 | BP100: 46 | BQ100: 64 | BR100: 54 | BS100: 54 | BT100: 218 | BU100: 54 | BV100: 50 | BW100: 64 | BX100: =$CO$22 -> 64 | BY100: =SUM(BU100:BX100) -> 232 | BZ100: =BZ101+N(BZ84) -> 247.85714 | CA100: =CA101+N(CA84) -> 243.57143 | CB100: =CB101+N(CB84) -> 239.28571 | CC100: =CC101+N(CC84) -> 235 | CD100: =CD101+N(CD84) -> 240.71429 | CE100: FY2025 10-K Notes 7-8: estimated amortization of finite-lived intangibles (customer relationships) $63m / $62m / $43m / $29m / $10m (FY26-30) and of technology (capitalized software and acquired technology, inside D&A) $802m / $640m / $509m / $355m / $174m. The non-GAAP item 'amortization of acquired intangible assets' ($232m FY25; $168m 9M FY26) covers acquired technology + customer relationships. Forecast item: $64m Q4/26E (Q3 run-rate), then $230m / $190m / $150m / $110m / $80m FY27-31 (assumption, declining with the 10-K schedules) + future-acquisition amortization.
B101: Amortization schedule — acquired intangibles held at 30-Jun-2026 (assumption from the 10-K schedules) | BZ101: 230 | CA101: 190 | CB101: 150 | CC101: 110 | CD101: 80 | CE101: Assumption: acquired-intangible amortization declining with the FY2025 10-K technology and customer-relationship schedules ($230m FY27 → $80m FY31).
...

Sheet Bull-Base-Bear
B2: Visa Inc. (V) — Bull / Base / Bear Case P&L Summary | J2: Share price ($): | K2: =Model!$BZ$375 -> 389
B3: Non-GAAP figures (company definitions: non-GAAP operating expenses, net income and EPS; adjusted EBITDA is a model definition) · USD millions · fiscal years ended 30 September · Live panel linked to Model — toggle scenario via Model!CE2. Bull and Bear panels are value snapshots generated from the Model with the switch set to each case. FY2026E = Q1–Q3 actual + Q4 calibrated to the Q4 FY26 call outlook (UNVERIFIED: net revenue growth ~13%, non-GAAP EPS growth ~14%). | J3: As of: | K3: =TODAY() -> 2026-10-12 00:00:00
B5: Scenario: | C5: =Model!$CE$2 -> Base | N5: Scenario: | O5: Bull | P5: Snapshot (values) — Model run with switch = Bull | Z5: Scenario: | AA5: Bear | AB5: Snapshot (values) — Model run with switch = Bear
B7: (USDm, except EPS and shares) | C7: 2026E | D7: 2027E | E7: 2028E | F7: 2029E | G7: 2030E | H7: 2031E | I7: 26-'31 CAGR | J7: LT Hist Avg | K7: LT Hist Min | L7: LT Hist Max | N7: (USDm, except EPS and shares) | O7: 2026E | P7: 2027E | Q7: 2028E | R7: 2029E | S7: 2030E | T7: 2031E | U7: 26-'31 CAGR | V7: LT Hist Avg | W7: LT Hist Min | X7: LT Hist Max | Z7: (USDm, except EPS and shares) | AA7: 2026E | AB7: 2027E | AC7: 2028E | AD7: 2029E | AE7: 2030E | AF7: 2031E | AG7: 26-'31 CAGR | AH7: LT Hist Avg | AI7: LT Hist Min | AJ7: LT Hist Max
B9: Net revenue | C9: =Model!BY113 -> 45882.12 | D9: =Model!BZ113 -> 50708.976 | E9: =Model!CA113 -> 56227.803 | F9: =Model!CB113 -> 61929.952 | G9: =Model!CC113 -> 67768.748 | H9: =Model!CD113 -> 73943.106 | I9: =IFERROR((H9/C9)^(1/5)-1,"n/m") -> 0.10014731 | N9: Net revenue | O9: 45989.36 | P9: 52839.919 | Q9: 60562.227 | R9: 68948.124 | S9: 77986.378 | T9: 87953.949 | U9: 0.13846477 | Z9: Net revenue | AA9: 45774.88 | AB9: 47382.295 | AC9: 49821.447 | AD9: 52016.294 | AE9: 53937.241 | AF9: 55756.837 | AG9: 0.040241517
B10: Net revenue y/y % | D10: =IFERROR(D9/C9-1,"") -> 0.10520125 | E10: =IFERROR(E9/D9-1,"") -> 0.10883333 | F10: =IFERROR(F9/E9-1,"") -> 0.10141155 | G10: =IFERROR(G9/F9-1,"") -> 0.094280657 | H10: =IFERROR(H9/G9-1,"") -> 0.091109224 | N10: Net revenue y/y % | P10: 0.14895966 | Q10: 0.14614534 | R10: 0.13846744 | S10: 0.13108775 | T10: 0.12781169 | Z10: Net revenue y/y % | AB10: 0.035115656 | AC10: 0.051478129 | AD10: 0.044054262 | AE10: 0.036929715 | AF10: 0.033735434
B11: Nominal payments volume y/y % | C11: =Model!BY202 -> 0.10428026 | D11: =Model!BZ202 -> 0.085 | E11: =Model!CA202 -> 0.08 | F11: =Model!CB202 -> 0.08 | G11: =Model!CC202 -> 0.075 | H11: =Model!CD202 -> 0.075 | N11: Nominal payments volume y/y % | O11: 0.10428026 | P11: 0.105 | Q11: 0.1 | R11: 0.1 | S11: 0.095 | T11: 0.095 | Z11: Nominal payments volume y/y % | AA11: 0.10428026 | AB11: 0.055 | AC11: 0.05 | AD11: 0.05 | AE11: 0.045 | AF11: 0.045
B12: Adjusted EBITDA (model) | C12: =Model!BY174 -> 32066.301 | D12: =Model!BZ174 -> 35529.645 | E12: =Model!CA174 -> 39500.032 | F12: =Model!CB174 -> 43676.913 | G12: =Model!CC174 -> 47794.801 | H12: =Model!CD174 -> 52285.56 | I12: =IFERROR((H12/C12)^(1/5)-1,"n/m") -> 0.10272337 | N12: Adjusted EBITDA (model) | O12: 32133.627 | P12: 37509.39 | Q12: 43102.775 | R12: 49261.62 | S12: 55719.215 | T12: 63002.802 | U12: 0.14414225 | Z12: Adjusted EBITDA (model) | AA12: 31998.888 | AB12: 32325.947 | AC12: 34081.803 | AD12: 35726.981 | AE12: 37046.368 | AF12: 38398.853 | AG12: 0.037138301
B13: Adjusted EBITDA margin % | C13: =IFERROR(C12/C9,"") -> 0.69888448 | D13: =IFERROR(D12/D9,"") -> 0.70065789 | E13: =IFERROR(E12/E9,"") -> 0.7025 | F13: =IFERROR(F12/F9,"") -> 0.70526316 | G13: =IFERROR(G12/G9,"") -> 0.70526316 | H13: =IFERROR(H12/H9,"") -> 0.70710526 | J13: =IFERROR(AVERAGE(Model!C175,Model!D175,Model!E175,Model!F175,Model!G175,Model!L175,Model!Q175,Model!V175,Model!AA175,Model!AF175,Model!AK175,Model!AP175,Model!AU175,Model!AZ175,Model!BE175,Model!BJ175,Model!BO175,Model!BT175),"") -> 0.66087513 | K13: =IFERROR(MIN(Model!C175,Model!D175,Model!E175,Model!F175,Model!G175,Model!L175,Model!Q175,Model!V175,Model!AA175,Model!AF175,Model!AK175,Model!AP175,Model!AU175,Model!AZ175,Model!BE175,Model!BJ175,Model!BO175,Model!BT175),"") -> 0.48954175 | L13: =IFERROR(MAX(Model!C175,Model!D175,Model!E175,Model!F175,Model!G175,Model!L175,Model!Q175,Model!V175,Model!AA175,Model!AF175,Model!AK175,Model!AP175,Model!AU175,Model!AZ175,Model!BE175,Model!BJ175,Model!BO175,Model!BT175),"") -> 0.70501535 | N13: Adjusted EBITDA margin % | O13: 0.69871873 | P13: 0.70986842 | Q13: 0.71171053 | R13: 0.71447368 | S13: 0.71447368 | T13: 0.71631579 | V13: 0.66087513 | W13: 0.48954175 | X13: 0.70501535 | Z13: Adjusted EBITDA margin % | AA13: 0.69904909 | AB13: 0.68223684 | AC13: 0.68407895 | AD13: 0.68684211 | AE13: 0.68684211 | AF13: 0.68868421 | AH13: 0.66087513 | AI13: 0.48954175 | AJ13: 0.70501535
B15: Operating income (GAAP) | C15: =Model!BY125 -> 28755.088 | D15: =Model!BZ125 -> 33890.702 | E15: =Model!CA125 -> 37732.651 | F15: =Model!CB125 -> 41783.081 | G15: =Model!CC125 -> 45757.749 | H15: =Model!CD125 -> 50098.484 | I15: =IFERROR((H15/C15)^(1/5)-1,"n/m") -> 0.11743424 | N15: Operating income (GAAP) | O15: 28818.993 | P15: 35809.63 | Q15: 41189.107 | R15: 47125.634 | S15: 53330.601 | T15: 60342.704 | U15: 0.15928227 | Z15: Operating income (GAAP) | AA15: 28691.089 | AB15: 30745.403 | AC15: 32482.691 | AD15: 34120.754 | AE15: 35428.579 | AF15: 36771.026 | AG15: 0.050876652
B16: Operating income y/y % | D16: =IFERROR(D15/C15-1,"") -> 0.17859842 | E16: =IFERROR(E15/D15-1,"") -> 0.11336294 | F16: =IFERROR(F15/E15-1,"") -> 0.1073455 | G16: =IFERROR(G15/F15-1,"") -> 0.095126238 | H16: =IFERROR(H15/G15-1,"") -> 0.094863395 | N16: Operating income y/y % | P16: 0.24257049 | Q16: 0.15022431 | R16: 0.14412856 | S16: 0.13166862 | T16: 0.13148367 | Z16: Operating income y/y % | AB16: 0.07160112 | AC16: 0.056505598 | AD16: 0.05042881 | AE16: 0.03832931 | AF16: 0.037891647
B17: Operating margin (GAAP) % | C17: =IFERROR(C15/C9,"") -> 0.62671665 | D17: =IFERROR(D15/D9,"") -> 0.66833733 | E17: =IFERROR(E15/E9,"") -> 0.6710675 | F17: =IFERROR(F15/F9,"") -> 0.67468293 | G17: =IFERROR(G15/G9,"") -> 0.67520428 | H17: =IFERROR(H15/H9,"") -> 0.67752745 | J17: =IFERROR(AVERAGE(Model!C213,Model!D213,Model!E213,Model!F213,Model!G213,Model!L213,Model!Q213,Model!V213,Model!AA213,Model!AF213,Model!AK213,Model!AP213,Model!AU213,Model!AZ213,Model!BE213,Model!BJ213,Model!BO213,Model!BT213),"") -> 0.56987512 | K17: =IFERROR(MIN(Model!C213,Model!D213,Model!E213,Model!F213,Model!G213,Model!L213,Model!Q213,Model!V213,Model!AA213,Model!AF213,Model!AK213,Model!AP213,Model!AU213,Model!AZ213,Model!BE213,Model!BJ213,Model!BO213,Model!BT213),"") -> 0.19671084 | L17: =IFERROR(MAX(Model!C213,Model!D213,Model!E213,Model!F213,Model!G213,Model!L213,Model!Q213,Model!V213,Model!AA213,Model!AF213,Model!AK213,Model!AP213,Model!AU213,Model!AZ213,Model!BE213,Model!BJ213,Model!BO213,Model!BT213),"") -> 0.66150997 | N17: Operating margin (GAAP) % | O17: 0.6266448 | P17: 0.67770032 | Q17: 0.68011216 | R17: 0.68349407 | S17: 0.68384508 | T17: 0.68607157 | V17: 0.56987512 | W17: 0.19671084 | X17: 0.66150997 | Z17: Operating margin (GAAP) % | AA17: 0.62678677 | AB17: 0.64887957 | AC17: 0.65198208 | AD17: 0.6559628 | AE17: 0.65684819 | AF17: 0.6594891 | AH17: 0.56987512 | AI17: 0.19671084 | AJ17: 0.66150997
B19: Non-GAAP Net Income | C19: =Model!BY188 -> 25165.122 | D19: =Model!BZ188 -> 27790.377 | E19: =Model!CA188 -> 30765.502 | F19: =Model!CB188 -> 33985.558 | G19: =Model!CC188 -> 37157.922 | H19: =Model!CD188 -> 40637.42 | I19: =IFERROR((H19/C19)^(1/5)-1,"n/m") -> 0.10058964 | N19: Non-GAAP Net Income | O19: 25216.884 | P19: 29365.451 | Q19: 33454.915 | R19: 38197.67 | S19: 43166.741 | T19: 48797.152 | U19: 0.14114441 | Z19: Non-GAAP Net Income | AA19: 25113.282 | AB19: 25210.934 | AC19: 26548.426 | AD19: 27805.751 | AE19: 28810.143 | AF19: 29851.35 | AG19: 0.03517101
B21: FDSO (m) | C21: =Model!BY143 -> 1907.9558 | D21: =Model!BZ143 -> 1850.3694 | E21: =Model!CA143 -> 1795.395 | F21: =Model!CB143 -> 1741.6677 | G21: =Model!CC143 -> 1686.7594 | H21: =Model!CD143 -> 1630.9967 | I21: =IFERROR((H21/C21)^(1/5)-1,"n/m") -> -0.030881348 | N21: FDSO (m) | O21: 1907.6345 | P21: 1840.6566 | Q21: 1774.982 | R21: 1712.5414 | S21: 1645.7367 | T21: 1574.7309 | U21: -0.037629642 | Z21: FDSO (m) | AA21: 1908.2772 | AB21: 1858.9698 | AC21: 1814.7865 | AD21: 1772.449 | AE21: 1732.5423 | AF21: 1695.2973 | AG21: -0.023390638
B23: Adjusted EPS — Diluted ($) | C23: =Model!BY191 -> 13.189573 | D23: =Model!BZ191 -> 15.018827 | E23: =Model!CA191 -> 17.135785 | F23: =Model!CB191 -> 19.513227 | G23: =Model!CC191 -> 22.029177 | H23: =Model!CD191 -> 24.915698 | I23: =IFERROR((H23/C23)^(1/5)-1,"n/m") -> 0.13566036 | N23: Adjusted EPS — Diluted ($) | O23: 13.218929 | P23: 15.953792 | Q23: 18.84803 | R23: 22.304669 | S23: 26.229433 | T23: 30.987613 | U23: 0.1857643 | Z23: Adjusted EPS — Diluted ($) | AA23: 13.160186 | AB23: 13.561777 | AC23: 14.628953 | AD23: 15.687758 | AE23: 16.628825 | AF23: 17.608328 | AG23: 0.05996425
B24: EPS y/y % | D24: =IFERROR(D23/C23-1,"") -> 0.13868943 | E24: =IFERROR(E23/D23-1,"") -> 0.14095364 | F24: =IFERROR(F23/E23-1,"") -> 0.13874136 | G24: =IFERROR(G23/F23-1,"") -> 0.12893558 | H24: =IFERROR(H23/G23-1,"") -> 0.13103174 | N24: EPS y/y % | P24: 0.2068899 | Q24: 0.18141384 | R24: 0.18339523 | S24: 0.17596153 | T24: 0.18140613 | Z24: EPS y/y % | AB24: 0.030515611 | AC24: 0.078689973 | AD24: 0.07237736 | AE24: 0.059987383 | AF24: 0.05890388
B26: P / E (x) — assumed (adjusted EPS) | G26: 30 | H26: 30 | N26: P / E (x) — assumed (adjusted EPS) | S26: 33 | T26: 33 | Z26: P / E (x) — assumed (adjusted EPS) | AD26: 25 | AE26: 25 | AF26: 25
B27: Price Target ($) | G27: =G26*G23 -> 660.8753 | H27: =H26*H23 -> 747.47094 | N27: Price Target ($) | S27: =S26*S23 -> 865.57129 | T27: =T26*T23 -> 1022.5912 | Z27: Price Target ($) | AD27: =AD26*AD23 -> 392.19395 | AE27: =AE26*AE23 -> 415.72064 | AF27: =AF26*AF23 -> 440.20819
B28: Upside / (Downside) vs current | G28: =IFERROR(G27/$K$2-1,"") -> 0.69890822 | H28: =IFERROR(H27/$K$2-1,"") -> 0.92151912 | N28: Upside / (Downside) vs current | S28: =IFERROR(S27/$K$2-1,"") -> 1.225119 | T28: =IFERROR(T27/$K$2-1,"") -> 1.6287692 | Z28: Upside / (Downside) vs current | AD28: =IFERROR(AD27/$K$2-1,"") -> 0.0082106622 | AE28: =IFERROR(AE27/$K$2-1,"") -> 0.068690581 | AF28: =IFERROR(AF27/$K$2-1,"") -> 0.1316406
B29: IRR (to 30-Sep of Y-1) | G29: =IFERROR((G27/$K$2)^(1/((DATE(2030-1,9,30)-$K$3)/365.25))-1,"") -> 0.19551477 | H29: =IFERROR((H27/$K$2)^(1/((DATE(2031-1,9,30)-$K$3)/365.25))-1,"") -> 0.17895827 | N29: IRR (to 30-Sep of Y-1) | S29: =IFERROR((S27/$K$2)^(1/((DATE(2030-1,9,30)-$K$3)/365.25))-1,"") -> 0.30930087 | T29: =IFERROR((T27/$K$2)^(1/((DATE(2031-1,9,30)-$K$3)/365.25))-1,"") -> 0.27587218 | Z29: IRR (to 30-Sep of Y-1) | AD29: =IFERROR((AD27/$K$2)^(1/((DATE(2029-1,9,30)-$K$3)/365.25))-1,"") -> 0.0041626031 | AE29: =IFERROR((AE27/$K$2)^(1/((DATE(2030-1,9,30)-$K$3)/365.25))-1,"") -> 0.02263717 | AF29: =IFERROR((AF27/$K$2)^(1/((DATE(2031-1,9,30)-$K$3)/365.25))-1,"") -> 0.031664124
B31: Free Cash Flow | C31: =Model!BY242 -> 22759.817 | D31: =Model!BZ242 -> 28437.461 | E31: =Model!CA242 -> 31549.776 | F31: =Model!CB242 -> 34894.544 | G31: =Model!CC242 -> 38148.748 | H31: =Model!CD242 -> 41712.272 | I31: =IFERROR((H31/C31)^(1/5)-1,"n/m") -> 0.12880524 | N31: Free Cash Flow | O31: 22819.076 | P31: 30051.416 | Q31: 34314.75 | R31: 39239.357 | S31: 44351.772 | T31: 50135.606 | U31: 0.17049521 | Z31: Free Cash Flow | AA31: 22700.489 | AB31: 25792.857 | AC31: 27228.798 | AD31: 28540.036 | AE31: 29555.131 | AF31: 30605.14 | AG31: 0.061577812
B32: FCF % | C32: =IFERROR(C31/C9,"") -> 0.49604981 | D32: =IFERROR(D31/D9,"") -> 0.56079739 | E32: =IFERROR(E31/E9,"") -> 0.56110632 | F32: =IFERROR(F31/F9,"") -> 0.56345182 | G32: =IFERROR(G31/G9,"") -> 0.56292538 | H32: =IFERROR(H31/H9,"") -> 0.56411306 | J32: =IFERROR(AVERAGE(Model!C244,Model!D244,Model!E244,Model!F244,Model!G244,Model!L244,Model!Q244,Model!V244,Model!AA244,Model!AF244,Model!AK244,Model!AP244,Model!AU244,Model!AZ244,Model!BE244,Model!BJ244,Model!BO244,Model!BT244),"") -> 0.42190106 | K32: =IFERROR(MIN(Model!C244,Model!D244,Model!E244,Model!F244,Model!G244,Model!L244,Model!Q244,Model!V244,Model!AA244,Model!AF244,Model!AK244,Model!AP244,Model!AU244,Model!AZ244,Model!BE244,Model!BJ244,Model!BO244,Model!BT244),"") -> 0.018521475 | L32: =IFERROR(MAX(Model!C244,Model!D244,Model!E244,Model!F244,Model!G244,Model!L244,Model!Q244,Model!V244,Model!AA244,Model!AF244,Model!AK244,Model!AP244,Model!AU244,Model!AZ244,Model!BE244,Model!BJ244,Model!BO244,Model!BT244),"") -> 0.60999659 | N32: FCF % | O32: 0.49618164 | P32: 0.56872563 | Q32: 0.56660317 | R32: 0.56911421 | S32: 0.56871178 | T32: 0.57002109 | V32: 0.42190106 | W32: 0.018521475 | X32: 0.60999659 | Z32: FCF % | AA32: 0.49591585 | AB32: 0.54435644 | AC32: 0.54652764 | AD32: 0.54867492 | AE32: 0.54795408 | AF32: 0.54890381 | AH32: 0.42190106 | AI32: 0.018521475 | AJ32: 0.60999659
B33: FCF / share ($) | C33: =IFERROR(C31/C21,"") -> 11.928902 | D33: =IFERROR(D31/D21,"") -> 15.368532 | E33: =IFERROR(E31/E21,"") -> 17.57261 | F33: =IFERROR(F31/F21,"") -> 20.035133 | G33: =IFERROR(G31/G21,"") -> 22.616591 | H33: =IFERROR(H31/H21,"") -> 25.574713 | N33: FCF / share ($) | O33: 11.961975 | P33: 16.326466 | Q33: 19.332449 | R33: 22.912939 | S33: 26.949494 | T33: 31.83757 | Z33: FCF / share ($) | AA33: 11.895803 | AB33: 13.874813 | AC33: 15.003857 | AD33: 16.102035 | AE33: 17.058823 | AF33: 18.052964
B34: FCF Yield (on PT) | F34: =IFERROR(F33/F$27,"") | G34: =IFERROR(G33/G$27,"") -> 0.034222176 | H34: =IFERROR(H33/H$27,"") -> 0.034214993 | N34: FCF Yield (on PT) | R34: =IFERROR(R33/R$27,"") | S34: =IFERROR(S33/S$27,"") -> 0.031134922 | T34: =IFERROR(T33/T$27,"") -> 0.03113421 | Z34: FCF Yield (on PT) | AD34: =IFERROR(AD33/AD$27,"") -> 0.041056307 | AE34: =IFERROR(AE33/AE$27,"") -> 0.041034342 | AF34: =IFERROR(AF33/AF$27,"") -> 0.041010058
B35: Adjusted EBITDA (leverage basis) | C35: =Model!BY174 -> 32066.301 | D35: =Model!BZ174 -> 35529.645 | E35: =Model!CA174 -> 39500.032 | F35: =Model!CB174 -> 43676.913 | G35: =Model!CC174 -> 47794.801 | H35: =Model!CD174 -> 52285.56 | I35: =IFERROR((H35/C35)^(1/5)-1,"n/m") -> 0.10272337 | N35: Adjusted EBITDA (leverage basis) | O35: 32133.627 | P35: 37509.39 | Q35: 43102.775 | R35: 49261.62 | S35: 55719.215 | T35: 63002.802 | U35: 0.14414225 | Z35: Adjusted EBITDA (leverage basis) | AA35: 31998.888 | AB35: 32325.947 | AC35: 34081.803 | AD35: 35726.981 | AE35: 37046.368 | AF35: 38398.853 | AG35: 0.037138301
B36: Adjusted EBITDA % of net revenue | C36: =IFERROR(C35/C9,"") -> 0.69888448 | D36: =IFERROR(D35/D9,"") -> 0.70065789 | E36: =IFERROR(E35/E9,"") -> 0.7025 | F36: =IFERROR(F35/F9,"") -> 0.70526316 | G36: =IFERROR(G35/G9,"") -> 0.70526316 | H36: =IFERROR(H35/H9,"") -> 0.70710526 | J36: =IFERROR(AVERAGE(Model!C212,Model!D212,Model!E212,Model!F212,Model!G212,Model!L212,Model!Q212,Model!V212,Model!AA212,Model!AF212,Model!AK212,Model!AP212,Model!AU212,Model!AZ212,Model!BE212,Model!BJ212,Model!BO212,Model!BT212),"") -> 0.66087513 | K36: =IFERROR(MIN(Model!C212,Model!D212,Model!E212,Model!F212,Model!G212,Model!L212,Model!Q212,Model!V212,Model!AA212,Model!AF212,Model!AK212,Model!AP212,Model!AU212,Model!AZ212,Model!BE212,Model!BJ212,Model!BO212,Model!BT212),"") -> 0.48954175 | L36: =IFERROR(MAX(Model!C212,Model!D212,Model!E212,Model!F212,Model!G212,Model!L212,Model!Q212,Model!V212,Model!AA212,Model!AF212,Model!AK212,Model!AP212,Model!AU212,Model!AZ212,Model!BE212,Model!BJ212,Model!BO212,Model!BT212),"") -> 0.70501535 | N36: Adjusted EBITDA % of net revenue | O36: 0.69871873 | P36: 0.70986842 | Q36: 0.71171053 | R36: 0.71447368 | S36: 0.71447368 | T36: 0.71631579 | V36: 0.66087513 | W36: 0.48954175 | X36: 0.70501535 | Z36: Adjusted EBITDA % of net revenue | AA36: 0.69904909 | AB36: 0.68223684 | AC36: 0.68407895 | AD36: 0.68684211 | AE36: 0.68684211 | AF36: 0.68868421 | AH36: 0.66087513 | AI36: 0.48954175 | AJ36: 0.70501535
B38: Net Debt | C38: =Model!BY369 -> 8583.0146 | D38: =Model!BZ369 -> 12435.376 | E38: =Model!CA369 -> 13825.011 | F38: =Model!CB369 -> 15286.92 | G38: =Model!CC369 -> 16728.18 | H38: =Model!CD369 -> 18299.946 | N38: Net Debt | O38: 9522.8942 | P38: 18754.695 | Q38: 21551.387 | R38: 24630.81 | S38: 27859.608 | T38: 31501.401 | Z38: Net Debt | AA38: 7643.2041 | AB38: 8081.4868 | AC38: 8520.4507 | AD38: 8931.7452 | AE38: 9261.592 | AF38: 9599.7133
B39: Net Debt / Adjusted EBITDA (x) | C39: =IFERROR(C38/C35,"") -> 0.26766463 | D39: =IFERROR(D38/D35,"") -> 0.35 | E39: =IFERROR(E38/E35,"") -> 0.35 | F39: =IFERROR(F38/F35,"") -> 0.35 | G39: =IFERROR(G38/G35,"") -> 0.35 | H39: =IFERROR(H38/H35,"") -> 0.35 | N39: Net Debt / Adjusted EBITDA (x) | O39: 0.29635292 | P39: 0.5 | Q39: 0.5 | R39: 0.5 | S39: 0.5 | T39: 0.5 | Z39: Net Debt / Adjusted EBITDA (x) | AA39: 0.23885842 | AB39: 0.25 | AC39: 0.25 | AD39: 0.25 | AE39: 0.25 | AF39: 0.25
B40: Share repurchases ($m; FY2026E = Q4) | D40: =Model!BZ254 -> 25650.127 | E40: =Model!CA254 -> 25814.757 | F40: =Model!CB254 -> 28695.998 | G40: =Model!CC254 -> 31360.381 | H40: =Model!CD254 -> 34447.835 | N40: Share repurchases ($m; FY2026E = Q4) | P40: 31651.237 | Q40: 29043.451 | R40: 33748.581 | S40: 38495.509 | T40: 44166.789 | AB40: 20583.728 | AC40: 21493.924 | AD40: 22199.935 | AE40: 22497.593 | AF40: 22851.276
B41: Implied avg buyback price ($) | D41: =Model!BZ253 -> 420.12 | E41: =Model!CA253 -> 453.7296 | F41: =Model!CB253 -> 490.02797 | G41: =Model!CC253 -> 529.23021 | H41: =Model!CD253 -> 571.56862 | N41: Implied avg buyback price ($) | P41: 420.12 | Q41: 453.7296 | R41: 490.02797 | S41: 529.23021 | T41: 571.56862 | AB41: 420.12 | AC41: 453.7296 | AD41: 490.02797 | AE41: 529.23021 | AF41: 571.56862
B42: Shares repurchased (m) | D42: =Model!BZ255 -> 61.054286 | E42: =Model!CA255 -> 56.894584 | F42: =Model!CB255 -> 58.559919 | G42: =Model!CC255 -> 59.256598 | H42: =Model!CD255 -> 60.268941 | N42: Shares repurchased (m) | P42: 75.338564 | Q42: 64.010482 | R42: 68.870724 | S42: 72.738684 | T42: 77.272943 | AB42: 48.994878 | AC42: 47.371659 | AD42: 45.303404 | AE42: 42.510032 | AF42: 39.979934
B44: ROIC | C44: =Model!BY352 -> 0.57024299 | D44: =Model!BZ352 -> 0.6116478 | E44: =Model!CA352 -> 0.66269594 | F44: =Model!CB352 -> 0.7145087 | G44: =Model!CC352 -> 0.76155552 | H44: =Model!CD352 -> 0.81123259 | J44: =IFERROR(AVERAGE(Model!C352,Model!D352,Model!E352,Model!F352,Model!G352,Model!L352,Model!Q352,Model!V352,Model!AA352,Model!AF352,Model!AK352,Model!AP352,Model!AU352,Model!AZ352,Model!BE352,Model!BJ352,Model!BO352,Model!BT352),"") -> 0.28729563 | K44: =IFERROR(MIN(Model!C352,Model!D352,Model!E352,Model!F352,Model!G352,Model!L352,Model!Q352,Model!V352,Model!AA352,Model!AF352,Model!AK352,Model!AP352,Model!AU352,Model!AZ352,Model!BE352,Model!BJ352,Model!BO352,Model!BT352),"") -> 0.099335857 | L44: =IFERROR(MAX(Model!C352,Model!D352,Model!E352,Model!F352,Model!G352,Model!L352,Model!Q352,Model!V352,Model!AA352,Model!AF352,Model!AK352,Model!AP352,Model!AU352,Model!AZ352,Model!BE352,Model!BJ352,Model!BO352,Model!BT352),"") -> 0.51356067 | N44: ROIC | O44: 0.57151582 | P44: 0.63325109 | Q44: 0.69509648 | R44: 0.76077032 | S44: 0.82456016 | T44: 0.89447709 | V44: 0.28729563 | W44: 0.099335857 | X44: 0.51356067 | Z44: ROIC | AA44: 0.56896894 | AB44: 0.5665662 | AC44: 0.59500315 | AD44: 0.62090054 | AE44: 0.63956812 | AF44: 0.65773262 | AH44: 0.28729563 | AI44: 0.099335857 | AJ44: 0.51356067
B45: RONTA | C45: =Model!BY363 -> 1.5185878 | D45: =Model!BZ363 -> 1.6684165 | E45: =Model!CA363 -> 1.8316609 | F45: =Model!CB363 -> 2.0009388 | G45: =Model!CC363 -> 2.1576028 | H45: =Model!CD363 -> 2.3201719 | J45: =IFERROR(AVERAGE(Model!C363,Model!D363,Model!E363,Model!F363,Model!G363,Model!L363,Model!Q363,Model!V363,Model!AA363,Model!AF363,Model!AK363,Model!AP363,Model!AU363,Model!AZ363,Model!BE363,Model!BJ363,Model!BO363,Model!BT363),"") -> 0.57814785 | K45: =IFERROR(MIN(Model!C363,Model!D363,Model!E363,Model!F363,Model!G363,Model!L363,Model!Q363,Model!V363,Model!AA363,Model!AF363,Model!AK363,Model!AP363,Model!AU363,Model!AZ363,Model!BE363,Model!BJ363,Model!BO363,Model!BT363),"") -> 0.24654247 | L45: =IFERROR(MAX(Model!C363,Model!D363,Model!E363,Model!F363,Model!G363,Model!L363,Model!Q363,Model!V363,Model!AA363,Model!AF363,Model!AK363,Model!AP363,Model!AU363,Model!AZ363,Model!BE363,Model!BJ363,Model!BO363,Model!BT363),"") -> 0.97804216 | N45: RONTA | O45: 1.5403006 | P45: 1.7626594 | Q45: 1.9981684 | R45: 2.2575182 | S45: 2.5203969 | T45: 2.8080677 | V45: 0.57814785 | W45: 0.24654247 | X45: 0.97804216 | Z45: RONTA | AA45: 1.4333372 | AB45: 1.4531029 | AC45: 1.5561442 | AD45: 1.6377999 | AE45: 1.674183 | AF45: 1.7059617 | AH45: 0.57814785 | AI45: 0.24654247 | AJ45: 0.97804216
B47: Implied Market Cap (USDm) | F47: =F27*F21 -> 0 | G47: =G27*G21 -> 1114737.6 | H47: =H27*H21 -> 1219122.6 | N47: Implied Market Cap (USDm) | R47: =R27*R21 -> 0 | S47: =S27*S21 -> 1424502.5 | T47: =T27*T21 -> 1610306 | Z47: Implied Market Cap (USDm) | AD47: =AD27*AD21 -> 695143.76 | AE47: =AE27*AE21 -> 720253.57 | AF47: =AF27*AF21 -> 746283.76
B48: (+) Net Debt & NCI | F48: =F38+Model!CB287 -> 15286.92 | G48: =G38+Model!CC287 -> 16728.18 | H48: =H38+Model!CD287 -> 18299.946 | N48: (+) Net Debt & NCI | R48: =R38+Model!CB287 -> 24630.81 | S48: =S38+Model!CC287 -> 27859.608 | T48: =T38+Model!CD287 -> 31501.401 | Z48: (+) Net Debt & NCI | AD48: =AD38+Model!CB287 -> 8931.7452 | AE48: =AE38+Model!CC287 -> 9261.592 | AF48: =AF38+Model!CD287 -> 9599.7133
B49: Implied Enterprise Value (USDm) | F49: =F47+F48 -> 15286.92 | G49: =G47+G48 -> 1131465.8 | H49: =H47+H48 -> 1237422.6 | N49: Implied Enterprise Value (USDm) | R49: =R47+R48 -> 24630.81 | S49: =S47+S48 -> 1452362.1 | T49: =T47+T48 -> 1641807.4 | Z49: Implied Enterprise Value (USDm) | AD49: =AD47+AD48 -> 704075.51 | AE49: =AE47+AE48 -> 729515.16 | AF49: =AF47+AF48 -> 755883.47
B50: Implied EV / Adjusted EBITDA (x) | F50: =IFERROR(F49/F35,"") -> 0.35 | G50: =IFERROR(G49/G35,"") -> 23.673408 | H50: =IFERROR(H49/H35,"") -> 23.666622 | N50: Implied EV / Adjusted EBITDA (x) | R50: =IFERROR(R49/R35,"") -> 0.5 | S50: =IFERROR(S49/S35,"") -> 26.065731 | T50: =IFERROR(T49/T35,"") -> 26.059276 | Z50: Implied EV / Adjusted EBITDA (x) | AD50: =IFERROR(AD49/AD35,"") -> 19.707109 | AE50: =IFERROR(AE49/AE35,"") -> 19.691948 | AF50: =IFERROR(AF49/AF35,"") -> 19.685053

Sheet DCF
B2: DCF VALUATION — VISA INC. (V)
B4: 1. WACC BUILD
B5: Risk-free rate (US 10Y govt) | C5: 0.0425 | D5: Assumption (~US 10Y Treasury yield, Oct-2026; government rate sources not reachable from the build environment); update to market
B6: Equity risk premium | C6: 0.05 | D6: Assumption: US implied ERP ~4.5–5.5%
B7: Levered beta | C7: 0.95 | D7: Assumption: payment networks / processors (MA, AXP, PYPL, FI) ~0.9–1.2; Visa's volume-linked revenue is defensive (no credit risk; ~48% U.S. volume)
B8: Cost of equity | C8: =C5+C7*C6 -> 0.09
B9: Pre-tax cost of debt | C9: 0.045 | D9: Feb-2026 senior notes at 3.80–4.70% (10-Q Note 6); commercial paper 3.77% at 30-Jun-2026; AA- / Aa3-type credit
B10: Tax rate | C10: 0.185 | D10: Model FY2027E+ non-GAAP effective tax rate (FY2025 17.7%; FY26 18.0–18.25% call commentary, unverified)
B11: After-tax cost of debt | C11: =C9*(1-C10) -> 0.036675
B12: Target D/V | C12: 0.03 | D12: Net debt ~$9.9bn at 30-Jun-2026 vs ~$735bn market cap ($389 × ~1,890m as-converted shares); ~0.3x adjusted EBITDA
B13: WACC | C13: =C8*(1-C12)+C11*C12 -> 0.08840025
B15: Valuation date (live) | C15: =TODAY() -> 2026-10-12 00:00:00 | D15: Periods = (30-Sep of fiscal year − today) / 365.25; cash flows assumed at fiscal year-end (30 September); FY2026E (ended 30-Sep-2026) is the base year
B16: 2. UNLEVERED FREE CASH FLOW BUILD (USDm)
D17: 2027E | E17: 2028E | F17: 2029E | G17: 2030E | H17: 2031E | I17: 2032E | J17: 2033E | K17: 2034E | L17: 2035E | M17: 2036E | N17: Terminal | P17: CAGR 27–31E | Q17: CAGR 27–36E
B18: Adj. EBIT (full-cost) less acquisition and severance / restructuring costs | D18: =Model!BZ179-Model!BZ181 -> 33890.702 | E18: =Model!CA179-Model!CA181 -> 37732.651 | F18: =Model!CB179-Model!CB181 -> 41783.081 | G18: =Model!CC179-Model!CC181 -> 45757.749 | H18: =Model!CD179-Model!CD181 -> 50098.484 | I18: =H18*(1+I$26) -> 54607.348 | J18: =I18*(1+J$26) -> 59112.454 | K18: =J18*(1+K$26) -> 63545.888 | L18: =K18*(1+L$26) -> 67835.235 | M18: =L18*(1+M$26) -> 71905.35 | P18: =(H18/D18)^(1/(COLUMNS(D18:H18)-1))-1 -> 0.10264574 | Q18: =(M18/D18)^(1/(COLUMNS(D18:M18)-1))-1 -> 0.087170974
B19: × (1 − tax rate) | D19: =1-$C$10 -> 0.815 | E19: =1-$C$10 -> 0.815 | F19: =1-$C$10 -> 0.815 | G19: =1-$C$10 -> 0.815 | H19: =1-$C$10 -> 0.815 | I19: =1-$C$10 -> 0.815 | J19: =1-$C$10 -> 0.815 | K19: =1-$C$10 -> 0.815 | ... M19: =1-$C$10 -> 0.815
B20: NOPAT | D20: =D18*D19 -> 27620.922 | E20: =E18*E19 -> 30752.111 | F20: =F18*F19 -> 34053.211 | G20: =G18*G19 -> 37292.565 | H20: =H18*H19 -> 40830.265 | I20: =I18*I19 -> 44504.988 | J20: =J18*J19 -> 48176.65 | K20: =K18*K19 -> 51789.899 | ... M20: =M18*M19 -> 58602.86
B21: plus D&A (incl. amortization of acquired intangibles) | D21: =Model!BZ140 -> 1548.9427 | E21: =Model!CA140 -> 1677.3804 | F21: =Model!CB140 -> 1803.8319 | G21: =Model!CC140 -> 1947.0526 | H21: =Model!CD140 -> 2097.0754 | I21: =H21*(1+I$26) -> 2285.8122 | J21: =I21*(1+J$26) -> 2474.3917 | K21: =J21*(1+K$26) -> 2659.9711 | L21: =K21*(1+L$26) -> 2839.5191 | M21: =L21*(1+M$26) -> 3009.8903
B22: − Capex (property, equipment & technology) and acquisitions (M&A lever 2027E–31E) | D22: =Model!BZ226+Model!BZ227 -> -2876.2321 | E22: =Model!CA226+Model!CA227 -> -3024.2009 | F22: =Model!CB226+Model!CB227 -> -3167.5483 | G22: =Model!CC226+Model!CC227 -> -3371.9062 | H22: =Model!CD226+Model!CD227 -> -3588.0087 | I22: =Model!CD226*(1+I$26) -> -2820.9295 | J22: =I22*(1+J$26) -> -3053.6562 | K22: =J22*(1+K$26) -> -3282.6804 | L22: =K22*(1+L$26) -> -3504.2613 | M22: =L22*(1+M$26) -> -3714.517
B23: − Δ Working capital (CF statement) | D23: =Model!BZ224 -> 183.42054 | E23: =Model!CA224 -> 209.71542 | F23: =Model!CB224 -> 216.68165 | G23: =Model!CC224 -> 221.87427 | H23: =Model!CD224 -> 234.62561 | I23: =H23*(1+I$26) -> 255.74191 | J23: =I23*(1+J$26) -> 276.84062 | K23: =J23*(1+K$26) -> 297.60367 | L23: =K23*(1+L$26) -> 317.69191 | M23: =L23*(1+M$26) -> 336.75343
B24: Unlevered FCF | D24: =D20+D21+D22+D23 -> 26477.053 | E24: =E20+E21+E22+E23 -> 29615.006 | F24: =F20+F21+F22+F23 -> 32906.177 | G24: =G20+G21+G22+G23 -> 36089.586 | H24: =H20+H21+H22+H23 -> 39573.957 | I24: =I20+I21+I22+I23 -> 44225.613 | J24: =J20+J21+J22+J23 -> 47874.226 | K24: =K20+K21+K22+K23 -> 51464.793 | ... M24: =M20+M21+M22+M23 -> 58234.987 | N24: =M24*(1+$C$27) -> 60564.386 | P24: =(H24/D24)^(1/(COLUMNS(D24:H24)-1))-1 -> 0.10569401 | Q24: =(M24/D24)^(1/(COLUMNS(D24:M24)-1))-1 -> 0.091528114
B25: Terminal Value (Gordon Growth) | N25: =N24/($C$13-$C$27) -> 1251323.8
B26: Fade-period growth (2032E–36E; 9.0% → 6.0% linear) | I26: 0.09 | J26: =I26+($M$26-$I$26)/4 -> 0.0825 | K26: =J26+($M$26-$I$26)/4 -> 0.075 | L26: =K26+($M$26-$I$26)/4 -> 0.0675 | M26: 0.06
B27: Terminal growth rate | C27: 0.04
B29: Discount period (years) | D29: =(DATE(2027,9,30)-$C$15)/365.25 -> 0.96646133 | E29: =(DATE(2028,9,30)-$C$15)/365.25 -> 1.9685147 | F29: =(DATE(2029,9,30)-$C$15)/365.25 -> 2.9678303 | G29: =(DATE(2030,9,30)-$C$15)/365.25 -> 3.9671458 | H29: =(DATE(2031,9,30)-$C$15)/365.25 -> 4.9664613 | I29: =(DATE(2032,9,30)-$C$15)/365.25 -> 5.9685147 | J29: =(DATE(2033,9,30)-$C$15)/365.25 -> 6.9678303 | K29: =(DATE(2034,9,30)-$C$15)/365.25 -> 7.9671458 | L29: =(DATE(2035,9,30)-$C$15)/365.25 -> 8.9664613 | M29: =(DATE(2036,9,30)-$C$15)/365.25 -> 9.9685147 | N29: =M29 -> 9.9685147
B30: Discount factor | D30: =1/(1+$C$13)^D29 -> 0.92139364 | E30: =1/(1+$C$13)^E29 -> 0.84641049 | F30: =1/(1+$C$13)^F29 -> 0.77770982 | G30: =1/(1+$C$13)^G29 -> 0.71458539 | H30: =1/(1+$C$13)^H29 -> 0.65658458 | I30: =1/(1+$C$13)^I29 -> 0.60315163 | J30: =1/(1+$C$13)^J29 -> 0.55419557 | K30: =1/(1+$C$13)^K29 -> 0.50921314 | ... N30: =1/(1+$C$13)^N29 -> 0.4298055
B31: PV of UFCF | D31: =D24*D30 -> 24395.788 | E31: =E24*E30 -> 25066.451 | F31: =F24*F30 -> 25591.457 | G31: =G24*G30 -> 25789.091 | H31: =H24*H30 -> 25983.65 | I31: =I24*I30 -> 26674.75 | J31: =J24*J30 -> 26531.684 | K31: =K24*K30 -> 26206.549 | ... M31: =M24*M30 -> 25029.718 | N31: =N25*N30 -> 537825.87
D32: NOPAT starts from adjusted EBIT on a full-cost basis: non-GAAP operating income less amortization of acquired intangibles, after share-based compensation (Visa does not adjust it out), less acquisition and severance / restructuring costs (cash; adjusted out by the company). Litigation provisions for U.S. covered litigation are excluded: they are funded from the litigation escrow through class B conversion-rate reductions (an as-converted share reduction, captured in the share count). D&A is added back in row 21. Row 22 includes acquisitions in FY2027E–31E; the fade period and terminal value assume none. Client-incentive prepayments run through working capital (row 23).
B33: IMPLIED ROIC — invested capital roll-forward (USDm)
B34: Opening invested capital | D34: =Model!BY349 -> 44034.266 | E34: =D38 -> 45178.135 | F34: =E38 -> 46315.24 | G34: =F38 -> 47462.275 | H34: =G38 -> 48665.255 | I34: =H38 -> 49921.562 | J34: =I38 -> 50200.938 | K34: =J38 -> 50503.361 | L34: =K38 -> 50828.467 | M34: =L38 -> 51175.517
B35: plus Capex and acquisitions | D35: =-D22 -> 2876.2321 | E35: =-E22 -> 3024.2009 | F35: =-F22 -> 3167.5483 | G35: =-G22 -> 3371.9062 | H35: =-H22 -> 3588.0087 | I35: =-I22 -> 2820.9295 | J35: =-J22 -> 3053.6562 | K35: =-K22 -> 3282.6804 | ... M35: =-M22 -> 3714.517
B36: less DD&A | D36: =-D21 -> -1548.9427 | E36: =-E21 -> -1677.3804 | F36: =-F21 -> -1803.8319 | G36: =-G21 -> -1947.0526 | H36: =-H21 -> -2097.0754 | I36: =-I21 -> -2285.8122 | J36: =-J21 -> -2474.3917 | K36: =-K21 -> -2659.9711 | ... M36: =-M21 -> -3009.8903
B37: plus Δ Working capital investment | D37: =-D23 -> -183.42054 | E37: =-E23 -> -209.71542 | F37: =-F23 -> -216.68165 | G37: =-G23 -> -221.87427 | H37: =-H23 -> -234.62561 | I37: =-I23 -> -255.74191 | J37: =-J23 -> -276.84062 | K37: =-K23 -> -297.60367 | ... M37: =-M23 -> -336.75343
B38: Closing invested capital | D38: =SUM(D34:D37) -> 45178.135 | E38: =SUM(E34:E37) -> 46315.24 | F38: =SUM(F34:F37) -> 47462.275 | G38: =SUM(G34:G37) -> 48665.255 | H38: =SUM(H34:H37) -> 49921.562 | I38: =SUM(I34:I37) -> 50200.938 | J38: =SUM(J34:J37) -> 50503.361 | K38: =SUM(K34:K37) -> 50828.467 | ... M38: =SUM(M34:M37) -> 51543.391
B39: NOPAT (row 20) | D39: =D20 -> 27620.922 | E39: =E20 -> 30752.111 | F39: =F20 -> 34053.211 | G39: =G20 -> 37292.565 | H39: =H20 -> 40830.265 | I39: =I20 -> 44504.988 | J39: =J20 -> 48176.65 | K39: =K20 -> 51789.899 | ... M39: =M20 -> 58602.86
B40: Implied ROIC (NOPAT / avg. invested capital) | D40: =IFERROR(D39/AVERAGE(D34,D38),"") -> 0.61921709 | E40: =IFERROR(E39/AVERAGE(E34,E38),"") -> 0.67222595 | F40: =IFERROR(F39/AVERAGE(F34,F38),"") -> 0.72625535 | G40: =IFERROR(G39/AVERAGE(G34,G38),"") -> 0.77589771 | H40: =IFERROR(H39/AVERAGE(H34,H38),"") -> 0.82831084 | I40: =IFERROR(I39/AVERAGE(I34,I38),"") -> 0.88901073 | J40: =IFERROR(J39/AVERAGE(J34,J38),"") -> 0.95679431 | K40: =IFERROR(K39/AVERAGE(K34,K38),"") -> 1.0221842 | ... M40: =IFERROR(M39/AVERAGE(M34,M38),"") -> 1.1410335
B41: Reinvestment rate (net investment / NOPAT) | D41: =IFERROR(SUM(D35:D37)/D39,"") -> 0.041413131 | E41: =IFERROR(SUM(E35:E37)/E39,"") -> 0.036976489 | F41: =IFERROR(SUM(F35:F37)/F39,"") -> 0.033683602 | G41: =IFERROR(SUM(G35:G37)/G39,"") -> 0.032257886 | H41: =IFERROR(SUM(H35:H37)/H39,"") -> 0.030769031 | I41: =IFERROR(SUM(I35:I37)/I39,"") -> 0.0062773947 | J41: =IFERROR(SUM(J35:J37)/J39,"") -> 0.0062773947 | K41: =IFERROR(SUM(K35:K37)/K39,"") -> 0.0062773947 | ... M41: =IFERROR(SUM(M35:M37)/M39,"") -> 0.0062773947
B42: Implied terminal RONIC (g / reinvestment rate) | N42: =IFERROR($C$27/M41,"") -> 6.3720703
D43: Opening IC = Model FY2026E book IC (equity + net debt at 30-Sep-2026), rolled forward with capex + M&A − D&A + ΔWC. Book IC includes ~$27bn of Visa Europe intangibles.
B44: 3. VALUATION SUMMARY
B45: Sum of PV (explicit + fade) | C45: =SUM(D31:M31) -> 256973.94
B46: PV of Terminal Value | C46: =N31 -> 537825.87
B47: Enterprise Value | C47: =C45+C46 -> 794799.81
B48: Less: Net debt + NCI (Model FY2026E year end, 30-Sep-2026) | C48: =Model!BY369+Model!BY287 -> 8583.0146 | D48: Visa: no noncontrolling interests; preferred stock (series A / B / C) is included in the as-converted share count, not deducted. Net debt = debt − cash − investment securities at the base-year end (≈ valuation date), so FY2027E+ cash flows are not double counted.
B49: Equity Value | C49: =C47-C48 -> 786216.79
B50: Diluted as-converted shares (m, Model FY2026E period end) | C50: =Model!BY376 -> 1878.8965
B51: Implied share price ($) | C51: =C49/C50 -> 418.44603
B52: Current share price ($) | C52: =Model!BY375 -> 389
B53: Implied upside / (downside) | C53: =C51/C52-1 -> 0.075696733
B54: Required discount to DCF value for target IRR | C54: =1-((1+C13)/(1+H54))^H55 -> 0.15224106 | D54: vs. current | E54: Target IRR | H54: 0.15
B55: Max entry price for target IRR ($) | C55: =C51*(1-C54) -> 354.74136 | D55: =C55/C52-1 -> -0.08806848 | E55: Years for discount to close | H55: 3
B58: 4. SENSITIVITY: IMPLIED PRICE ($) — WACC × Terminal Growth
D60: WACC →
B61: Terminal growth ↓ | D61: =F61-0.01 -> 0.07840025 | E61: =F61-0.005 -> 0.08340025 | F61: =$C$13 -> 0.08840025 | G61: =F61+0.005 -> 0.09340025 | H61: =F61+0.01 -> 0.09840025
B62: =B64-0.01 -> 0.03 | D62: {=IFERROR((SUMPRODUCT($D$24:$M$24/(1+D$61)^$D$29:$M$29)+($M$24*(1+$B62)/(D$61-$B62))/(1+D$61)^$M$29-$C$48)/$C$50,"")} -> 450.18685 | E62: {=IFERROR((SUMPRODUCT($D$24:$M$24/(1+E$61)^$D$29:$M$29)+($M$24*(1+$B62)/(E$61-$B62))/(1+E$61)^$M$29-$C$48)/$C$50,"")} -> 404.73745 | F62: {=IFERROR((SUMPRODUCT($D$24:$M$24/(1+F$61)^$D$29:$M$29)+($M$24*(1+$B62)/(F$61-$B62))/(1+F$61)^$M$29-$C$48)/$C$50,"")} -> 367.15051 | G62: {=IFERROR((SUMPRODUCT($D$24:$M$24/(1+G$61)^$D$29:$M$29)+($M$24*(1+$B62)/(G$61-$B62))/(1+G$61)^$M$29-$C$48)/$C$50,"")} -> 335.56305 | H62: {=IFERROR((SUMPRODUCT($D$24:$M$24/(1+H$61)^$D$29:$M$29)+($M$24*(1+$B62)/(H$61-$B62))/(1+H$61)^$M$29-$C$48)/$C$50,"")} -> 308.65692
B63: =B64-0.005 -> 0.035 | D63: {=IFERROR((SUMPRODUCT($D$24:$M$24/(1+D$61)^$D$29:$M$29)+($M$24*(1+$B63)/(D$61-$B63))/(1+D$61)^$M$29-$C$48)/$C$50,"")} -> 487.67755 | E63: {=IFERROR((SUMPRODUCT($D$24:$M$24/(1+E$61)^$D$29:$M$29)+($M$24*(1+$B63)/(E$61-$B63))/(1+E$61)^$M$29-$C$48)/$C$50,"")} -> 433.96923 | F63: {=IFERROR((SUMPRODUCT($D$24:$M$24/(1+F$61)^$D$29:$M$29)+($M$24*(1+$B63)/(F$61-$B63))/(1+F$61)^$M$29-$C$48)/$C$50,"")} -> 390.39681 | G63: {=IFERROR((SUMPRODUCT($D$24:$M$24/(1+G$61)^$D$29:$M$29)+($M$24*(1+$B63)/(G$61-$B63))/(1+G$61)^$M$29-$C$48)/$C$50,"")} -> 354.35422 | H63: {=IFERROR((SUMPRODUCT($D$24:$M$24/(1+H$61)^$D$29:$M$29)+($M$24*(1+$B63)/(H$61-$B63))/(1+H$61)^$M$29-$C$48)/$C$50,"")} -> 324.05761
B64: =$C$27 -> 0.04 | D64: {=IFERROR((SUMPRODUCT($D$24:$M$24/(1+D$61)^$D$29:$M$29)+($M$24*(1+$B64)/(D$61-$B64))/(1+D$61)^$M$29-$C$48)/$C$50,"")} -> 534.93139 | E64: {=IFERROR((SUMPRODUCT($D$24:$M$24/(1+E$61)^$D$29:$M$29)+($M$24*(1+$B64)/(E$61-$B64))/(1+E$61)^$M$29-$C$48)/$C$50,"")} -> 469.93639 | F64: {=IFERROR((SUMPRODUCT($D$24:$M$24/(1+F$61)^$D$29:$M$29)+($M$24*(1+$B64)/(F$61-$B64))/(1+F$61)^$M$29-$C$48)/$C$50,"")} -> 418.44603 | G64: {=IFERROR((SUMPRODUCT($D$24:$M$24/(1+G$61)^$D$29:$M$29)+($M$24*(1+$B64)/(G$61-$B64))/(1+G$61)^$M$29-$C$48)/$C$50,"")} -> 376.66432 | H64: {=IFERROR((SUMPRODUCT($D$24:$M$24/(1+H$61)^$D$29:$M$29)+($M$24*(1+$B64)/(H$61-$B64))/(1+H$61)^$M$29-$C$48)/$C$50,"")} -> 342.09539
B65: =B64+0.005 -> 0.045 | D65: {=IFERROR((SUMPRODUCT($D$24:$M$24/(1+D$61)^$D$29:$M$29)+($M$24*(1+$B65)/(D$61-$B65))/(1+D$61)^$M$29-$C$48)/$C$50,"")} -> 596.33298 | E65: {=IFERROR((SUMPRODUCT($D$24:$M$24/(1+E$61)^$D$29:$M$29)+($M$24*(1+$B65)/(E$61-$B65))/(1+E$61)^$M$29-$C$48)/$C$50,"")} -> 515.26995 | F65: {=IFERROR((SUMPRODUCT($D$24:$M$24/(1+F$61)^$D$29:$M$29)+($M$24*(1+$B65)/(F$61-$B65))/(1+F$61)^$M$29-$C$48)/$C$50,"")} -> 452.95817 | G65: {=IFERROR((SUMPRODUCT($D$24:$M$24/(1+G$61)^$D$29:$M$29)+($M$24*(1+$B65)/(G$61-$B65))/(1+G$61)^$M$29-$C$48)/$C$50,"")} -> 403.58393 | H65: {=IFERROR((SUMPRODUCT($D$24:$M$24/(1+H$61)^$D$29:$M$29)+($M$24*(1+$B65)/(H$61-$B65))/(1+H$61)^$M$29-$C$48)/$C$50,"")} -> 363.51103
B66: =B64+0.01 -> 0.05 | D66: {=IFERROR((SUMPRODUCT($D$24:$M$24/(1+D$61)^$D$29:$M$29)+($M$24*(1+$B66)/(D$61-$B66))/(1+D$61)^$M$29-$C$48)/$C$50,"")} -> 679.35466 | E66: {=IFERROR((SUMPRODUCT($D$24:$M$24/(1+E$61)^$D$29:$M$29)+($M$24*(1+$B66)/(E$61-$B66))/(1+E$61)^$M$29-$C$48)/$C$50,"")} -> 574.17633 | F66: {=IFERROR((SUMPRODUCT($D$24:$M$24/(1+F$61)^$D$29:$M$29)+($M$24*(1+$B66)/(F$61-$B66))/(1+F$61)^$M$29-$C$48)/$C$50,"")} -> 496.45779 | G66: {=IFERROR((SUMPRODUCT($D$24:$M$24/(1+G$61)^$D$29:$M$29)+($M$24*(1+$B66)/(G$61-$B66))/(1+G$61)^$M$29-$C$48)/$C$50,"")} -> 436.70617 | H66: {=IFERROR((SUMPRODUCT($D$24:$M$24/(1+H$61)^$D$29:$M$29)+($M$24*(1+$B66)/(H$61-$B66))/(1+H$61)^$M$29-$C$48)/$C$50,"")} -> 389.35135
B69: 5. REVERSE DCF
B70: To solve for the market-implied path: Data ▸ What-If Analysis ▸ Goal Seek — set C51 to the current price (C52) by changing C27 (terminal growth) or the fade-period growth inputs (I26:M26).
B72: 6. MAUBOUSSIN EV / NOPAT — TWO-STAGE FRAMEWORK
B73: EV/NOPAT = 1/r + [g × (1 − r/ROIIC) / (r × (r − g))] × [1 − ((1+g)/(1+r))^N]
B74: Formula source: Mauboussin & Rappaport, "Expectations Investing" (2021); Counterpoint Global, "What Does a Price-Earnings Multiple Mean?" (2020).
B76: Input | C76: Value | D76: Rationale (Visa characteristics)
B77: r (Cost of capital / WACC) | C77: =$C$13 -> 0.08840025 | D77: Linked from Section 1 WACC build
B78: g (NOPAT growth, Stage 1) | C78: 0.11 | D78: Model non-GAAP operating income CAGR FY2026–31E: ~9–10% net revenue growth (payments volume ~8%, value-added services, pricing) at a stable ~68% margin
B79: ROIIC (Return on incremental invested capital) | C79: 0.4 | D79: Two-sided network with near-zero marginal cost per transaction: incremental returns far above WACC; book IC inflated by Visa Europe intangibles (bought back a perpetual licence)
B80: N (Years of value creation / CAP) | C80: 20 | D80: Network effects (4.9bn+ credentials, 150m+ merchant locations), brand and acceptance sustain a long competitive-advantage period; risks are regulation (interchange, routing) and A2A / real-time payment rails
B82: Calculation | C82: Value
B83: Steady-state component: 1 / r | C83: =1/C77 -> 11.312185
B84: Value-creation factor: 1 − r / ROIIC | C84: =1-C77/C79 -> 0.77899938
B85: Growth multiplier: g × (1 − r/ROIIC) / (r × (r − g)) | C85: =C78*C84/(C77*(C77-C78)) -> -44.877389
B86: Time decay: 1 − ((1+g)/(1+r))^N | C86: =1-((1+C78)/(1+C77))^C80 -> -0.48144973
B87: PVGO component (growth value) | C87: =C85*C86 -> 21.606206
B88: Mauboussin EV / NOPAT (steady-state + PVGO) | C88: =C83+C87 -> 32.918392
B90: VALUATION — Applied to FY2029E NOPAT | C90: USDm
B91: FY2029E Adj. EBIT less acquisition and severance / restructuring costs | C91: =Model!CB179-Model!CB181 -> 41783.081
B92: Tax rate (from WACC build) | C92: =$C$10 -> 0.185
B93: FY2029E NOPAT | C93: =C91*(1-C92) -> 34053.211
B94: × Mauboussin EV/NOPAT multiple | C94: =C88 -> 32.918392
B95: Implied Enterprise Value (FY2029E basis) | C95: =C93*C94 -> 1120976.9
B96: Less: FY2028E year-end net debt + NCI (Model) | C96: =Model!CA369+Model!CA287 -> 13825.011
B97: Implied Equity Value | C97: =C95-C96 -> 1107151.9
B98: Diluted as-converted shares FY2029E (m, Model) | C98: =Model!CB376 -> 1714.3877
B99: Implied share price FY2029 ($) | C99: =C97/C98 -> 645.8002
B101: Current share price ($) | C101: =C52 -> 389
B102: Implied upside / (downside) | C102: =C99/C101-1 -> 0.66015474
B104: MARKET-IMPLIED EV/NOPAT TODAY | C104: USDm
B105: Current market cap (spot × diluted shares) | C105: =C52*C50 -> 730890.75
B106: Plus: FY2026E year-end net debt + NCI | C106: =C48 -> 8583.0146
B107: Implied Enterprise Value (today) | C107: =C105+C106 -> 739473.76
B108: Visa market-implied EV/NOPAT (on FY2029E NOPAT) | C108: =C107/C93 -> 21.715243
B110: Multiple gap (Mauboussin − Market) | C110: =C88-C108 -> 11.203149
B111: Implied re-rating headroom | C111: =C88/C108-1 -> 0.51591172

Sheet Charts
B2: Visa Inc. — Operating Performance (FY2012–FY2025) and Model Forecast (FY2026E–FY2031E)
B3: USDm · fiscal years ended 30 September · Linked to Model. Bars = net revenue growth split into nominal payments volume growth and net revenue yield change. Adjusted EBITDA = model definition (non-GAAP operating income + D&A excl. acquired amortization); operating income = GAAP. ROIC / RONTA on adjusted EBIT (full-cost).
C7: 2012 | D7: 2013 | E7: 2014 | F7: 2015 | G7: 2016 | H7: 2017 | I7: 2018 | J7: 2019 | K7: 2020 | L7: 2021 | M7: 2022 | N7: 2023 | O7: 2024 | P7: 2025 | Q7: 2026E | R7: 2027E | S7: 2028E | T7: 2029E | U7: 2030E | V7: 2031E
B8: Payments volume growth (pp) | C8: =IFERROR(Model!G43+0,0) -> 0.10453258 | D8: =IFERROR(Model!L43+0,0) -> 0.076429854 | E8: =IFERROR(Model!Q43+0,0) -> 0.088158208 | F8: =IFERROR(Model!V43+0,0) -> 0.069410992 | G8: =IFERROR(Model!AA43+0,0) -> 0.15704341 | H8: =IFERROR(Model!AF43+0,0) -> 0.28561317 | I8: =IFERROR(Model!AK43+0,0) -> 0.10984171 | J8: =IFERROR(Model!AP43+0,0) -> 0.068956964 | K8: =IFERROR(Model!AU43+0,0) -> 0.010906138 | L8: =IFERROR(Model!AZ43+0,0) -> 0.14403764 | M8: =IFERROR(Model!BE43+0,0) -> 0.15008026 | N8: =IFERROR(Model!BJ43+0,0) -> 0.053210049 | O8: =IFERROR(Model!BO43+0,0) -> 0.075368561 | P8: =IFERROR(Model!BT43+0,0) -> 0.07008626 | Q8: =IFERROR(Model!BY43+0,0) -> 0.10428026 | R8: =IFERROR(Model!BZ43+0,0) -> 0.085 | S8: =IFERROR(Model!CA43+0,0) -> 0.08 | T8: =IFERROR(Model!CB43+0,0) -> 0.08 | U8: =IFERROR(Model!CC43+0,0) -> 0.075 | V8: =IFERROR(Model!CD43+0,0) -> 0.075
B9: Net revenue yield change (pp) | C9: =IFERROR(Model!G44+0,0) -> 0.026856791 | D9: =IFERROR(Model!L44+0,0) -> 0.049968863 | E9: =IFERROR(Model!Q44+0,0) -> -0.0089204476 | F9: =IFERROR(Model!V44+0,0) -> 0.021816036 | G9: =IFERROR(Model!AA44+0,0) -> -0.060882749 | H9: =IFERROR(Model!AF44+0,0) -> -0.053204647 | I9: =IFERROR(Model!AK44+0,0) -> 0.011510773 | J9: =IFERROR(Model!AP44+0,0) -> 0.042980489 | K9: =IFERROR(Model!AU44+0,0) -> -0.05948057 | L9: =IFERROR(Model!AZ44+0,0) -> -0.035516303 | M9: =IFERROR(Model!BE44+0,0) -> 0.057256916 | N9: =IFERROR(Model!BJ44+0,0) -> 0.057772509 | O9: =IFERROR(Model!BO44+0,0) -> 0.0231244 | P9: =IFERROR(Model!BT44+0,0) -> 0.040476649 | Q9: =IFERROR(Model!BY44+0,0) -> 0.038733586 | R9: =IFERROR(Model!BZ44+0,0) -> 0.01861866 | S9: =IFERROR(Model!CA44+0,0) -> 0.02669753 | T9: =IFERROR(Model!CB44+0,0) -> 0.019825508 | U9: =IFERROR(Model!CC44+0,0) -> 0.017935494 | V9: =IFERROR(Model!CD44+0,0) -> 0.014985325
C11: =C7 -> 2012 | D11: =D7 -> 2013 | E11: =E7 -> 2014 | F11: =F7 -> 2015 | G11: =G7 -> 2016 | H11: =H7 -> 2017 | I11: =I7 -> 2018 | J11: =J7 -> 2019 | ... V11: =V7 -> 2031E
B12: Adjusted EBITDA | C12: =Model!G174 -> 6570 | D12: =Model!L174 -> 7636 | E12: =Model!Q174 -> 8582 | F12: =Model!V174 -> 9558 | G12: =Model!AA174 -> 10524 | H12: =Model!AF174 -> 12892 | I12: =Model!AK174 -> 14362 | J12: =Model!AP174 -> 16027 | K12: =Model!AU174 -> 14865 | L12: =Model!AZ174 -> 16781 | M12: =Model!BE174 -> 20664 | N12: =Model!BJ174 -> 22939 | O12: =Model!BO174 -> 25173 | P12: =Model!BT174 -> 28096 | Q12: =Model!BY174 -> 32066.301 | R12: =Model!BZ174 -> 35529.645 | S12: =Model!CA174 -> 39500.032 | T12: =Model!CB174 -> 43676.913 | U12: =Model!CC174 -> 47794.801 | V12: =Model!CD174 -> 52285.56
B13: Operating income (GAAP) | C13: =Model!G125 -> 2139 | D13: =Model!L125 -> 7239 | E13: =Model!Q125 -> 7697 | F13: =Model!V125 -> 9064 | G13: =Model!AA125 -> 7883 | H13: =Model!AF125 -> 12144 | I13: =Model!AK125 -> 12954 | J13: =Model!AP125 -> 15001 | K13: =Model!AU125 -> 14081 | L13: =Model!AZ125 -> 15804 | M13: =Model!BE125 -> 18813 | N13: =Model!BJ125 -> 21000 | O13: =Model!BO125 -> 23595 | P13: =Model!BT125 -> 23994 | Q13: =Model!BY125 -> 28755.088 | R13: =Model!BZ125 -> 33890.702 | S13: =Model!CA125 -> 37732.651 | T13: =Model!CB125 -> 41783.081 | U13: =Model!CC125 -> 45757.749 | V13: =Model!CD125 -> 50098.484
B14: Adj. EBITDA Margin % | C14: =Model!G212 -> 0.63045773 | D14: =Model!L212 -> 0.64832739 | E14: =Model!Q212 -> 0.67564163 | F14: =Model!V212 -> 0.68861671 | G14: =Model!AA212 -> 0.69778544 | H14: =Model!AF212 -> 0.70225515 | I14: =Model!AK212 -> 0.69688 | J14: =Model!AP212 -> 0.69752361 | K14: =Model!AU212 -> 0.68044493 | L14: =Model!AZ212 -> 0.69616262 | M14: =Model!BE212 -> 0.70501535 | N14: =Model!BJ212 -> 0.70250819 | O14: =Model!BO212 -> 0.70069031 | P14: =Model!BT212 -> 0.7024 | Q14: =Model!BY212 -> 0.69888448 | R14: =Model!BZ212 -> 0.70065789 | S14: =Model!CA212 -> 0.7025 | T14: =Model!CB212 -> 0.70526316 | U14: =Model!CC212 -> 0.70526316 | V14: =Model!CD212 -> 0.70710526
B15: Operating Margin % | C15: =Model!G213 -> 0.20525861 | D15: =Model!L213 -> 0.61462048 | E15: =Model!Q213 -> 0.60596756 | F15: =Model!V213 -> 0.65302594 | G15: =Model!AA213 -> 0.52267604 | H15: =Model!AF213 -> 0.66150997 | I15: =Model!AK213 -> 0.62856034 | J15: =Model!AP213 -> 0.65287026 | K15: =Model!AU213 -> 0.64455736 | L15: =Model!AZ213 -> 0.65563161 | M15: =Model!BE213 -> 0.64186285 | N15: =Model!BJ213 -> 0.64312621 | O15: =Model!BO213 -> 0.65676669 | P15: =Model!BT213 -> 0.59985 | Q15: =Model!BY213 -> 0.62671665 | R15: =Model!BZ213 -> 0.66833733 | S15: =Model!CA213 -> 0.6710675 | T15: =Model!CB213 -> 0.67468293 | U15: =Model!CC213 -> 0.67520428 | V15: =Model!CD213 -> 0.67752745
C17: =C7 -> 2012 | D17: =D7 -> 2013 | E17: =E7 -> 2014 | F17: =F7 -> 2015 | G17: =G7 -> 2016 | H17: =H7 -> 2017 | I17: =I7 -> 2018 | J17: =J7 -> 2019 | ... V17: =V7 -> 2031E
B18: ROIC | C18: =IFERROR(Model!G352+0,NA()) -> 0.19301866 | D18: =IFERROR(Model!L352+0,NA()) -> 0.25019631 | E18: =IFERROR(Model!Q352+0,NA()) -> 0.2788587 | F18: =IFERROR(Model!V352+0,NA()) -> 0.31734019 | G18: =IFERROR(Model!AA352+0,NA()) -> 0.19781881 | H18: =IFERROR(Model!AF352+0,NA()) -> 0.24188576 | I18: =IFERROR(Model!AK352+0,NA()) -> 0.3157373 | J18: =IFERROR(Model!AP352+0,NA()) -> 0.33515831 | K18: =IFERROR(Model!AU352+0,NA()) -> 0.28680803 | L18: =IFERROR(Model!AZ352+0,NA()) -> 0.34594927 | M18: =IFERROR(Model!BE352+0,NA()) -> 0.43546939 | N18: =IFERROR(Model!BJ352+0,NA()) -> 0.48510773 | O18: =IFERROR(Model!BO352+0,NA()) -> 0.47097561 | P18: =IFERROR(Model!BT352+0,NA()) -> 0.51356067 | Q18: =IFERROR(Model!BY352+0,NA()) -> 0.57024299 | R18: =IFERROR(Model!BZ352+0,NA()) -> 0.6116478 | S18: =IFERROR(Model!CA352+0,NA()) -> 0.66269594 | T18: =IFERROR(Model!CB352+0,NA()) -> 0.7145087 | U18: =IFERROR(Model!CC352+0,NA()) -> 0.76155552 | V18: =IFERROR(Model!CD352+0,NA()) -> 0.81123259
B19: RONTA | C19: =IFERROR(Model!G363+0,NA()) -> 0.46390844 | D19: =IFERROR(Model!L363+0,NA()) -> 0.57837324 | E19: =IFERROR(Model!Q363+0,NA()) -> 0.6066712 | F19: =IFERROR(Model!V363+0,NA()) -> 0.55561712 | G19: =IFERROR(Model!AA363+0,NA()) -> 0.51914975 | H19: =IFERROR(Model!AF363+0,NA()) -> 0.51571243 | I19: =IFERROR(Model!AK363+0,NA()) -> 0.725334 | J19: =IFERROR(Model!AP363+0,NA()) -> 0.74519263 | K19: =IFERROR(Model!AU363+0,NA()) -> 0.44665689 | L19: =IFERROR(Model!AZ363+0,NA()) -> 0.54075195 | M19: =IFERROR(Model!BE363+0,NA()) -> 0.67681933 | N19: =IFERROR(Model!BJ363+0,NA()) -> 0.77340329 | O19: =IFERROR(Model!BO363+0,NA()) -> 0.89785834 | P19: =IFERROR(Model!BT363+0,NA()) -> 0.97804216 | Q19: =IFERROR(Model!BY363+0,NA()) -> 1.5185878 | R19: =IFERROR(Model!BZ363+0,NA()) -> 1.6684165 | S19: =IFERROR(Model!CA363+0,NA()) -> 1.8316609 | T19: =IFERROR(Model!CB363+0,NA()) -> 2.0009388 | U19: =IFERROR(Model!CC363+0,NA()) -> 2.1576028 | V19: =IFERROR(Model!CD363+0,NA()) -> 2.3201719
B20: Adj. EBITDA margin % | C20: =IFERROR(Model!G212+0,NA()) -> 0.63045773 | D20: =IFERROR(Model!L212+0,NA()) -> 0.64832739 | E20: =IFERROR(Model!Q212+0,NA()) -> 0.67564163 | F20: =IFERROR(Model!V212+0,NA()) -> 0.68861671 | G20: =IFERROR(Model!AA212+0,NA()) -> 0.69778544 | H20: =IFERROR(Model!AF212+0,NA()) -> 0.70225515 | I20: =IFERROR(Model!AK212+0,NA()) -> 0.69688 | J20: =IFERROR(Model!AP212+0,NA()) -> 0.69752361 | K20: =IFERROR(Model!AU212+0,NA()) -> 0.68044493 | L20: =IFERROR(Model!AZ212+0,NA()) -> 0.69616262 | M20: =IFERROR(Model!BE212+0,NA()) -> 0.70501535 | N20: =IFERROR(Model!BJ212+0,NA()) -> 0.70250819 | O20: =IFERROR(Model!BO212+0,NA()) -> 0.70069031 | P20: =IFERROR(Model!BT212+0,NA()) -> 0.7024 | Q20: =IFERROR(Model!BY212+0,NA()) -> 0.69888448 | R20: =IFERROR(Model!BZ212+0,NA()) -> 0.70065789 | S20: =IFERROR(Model!CA212+0,NA()) -> 0.7025 | T20: =IFERROR(Model!CB212+0,NA()) -> 0.70526316 | U20: =IFERROR(Model!CC212+0,NA()) -> 0.70526316 | V20: =IFERROR(Model!CD212+0,NA()) -> 0.70710526
B21: FCF margin % | C21: =IFERROR(Model!G244+0,NA()) -> 0.44458305 | D21: =IFERROR(Model!L244+0,NA()) -> 0.21659025 | E21: =IFERROR(Model!Q244+0,NA()) -> 0.52369706 | F21: =IFERROR(Model!V244+0,NA()) -> 0.4445245 | G21: =IFERROR(Model!AA244+0,NA()) -> 0.33490253 | H21: =IFERROR(Model!AF244+0,NA()) -> 0.46306787 | I21: =IFERROR(Model!AK244+0,NA()) -> 0.58202727 | J21: =IFERROR(Model!AP244+0,NA()) -> 0.52348 | K21: =IFERROR(Model!AU244+0,NA()) -> 0.44420031 | L21: =IFERROR(Model!AZ244+0,NA()) -> 0.60244762 | M21: =IFERROR(Model!BE244+0,NA()) -> 0.60999659 | N21: =IFERROR(Model!BJ244+0,NA()) -> 0.60319113 | O21: =IFERROR(Model!BO244+0,NA()) -> 0.52031955 | P21: =IFERROR(Model!BT244+0,NA()) -> 0.539425 | Q21: =IFERROR(Model!BY244+0,NA()) -> 0.49604981 | R21: =IFERROR(Model!BZ244+0,NA()) -> 0.56079739 | S21: =IFERROR(Model!CA244+0,NA()) -> 0.56110632 | T21: =IFERROR(Model!CB244+0,NA()) -> 0.56345182 | U21: =IFERROR(Model!CC244+0,NA()) -> 0.56292538 | V21: =IFERROR(Model!CD244+0,NA()) -> 0.56411306
