Workbook

Sheet Model
CF1: SCENARIO SWITCH ▼ (Bull / Base / Bear) — drives all scenario-linked forecast drivers
B2: Westinghouse Air Brake Technologies Corporation (Wabtec, NYSE: WAB) — 3-Statement Financial Model | CF2: Base
B3: US GAAP as reported · USD millions (per-share data in USD; shares in millions, split-adjusted) · Source: Wabtec Forms 10-K / 10-Q and Form 8-K earnings releases (Ex. 99.1) and earnings decks, deal 8-Ks, SEC EDGAR CIK 0000943452 (investor-relations releases are the same documents as filed on EDGAR)
B4: Basis notes: calendar fiscal year; all periods as originally reported. 2-for-1 stock split Jun-2013 (earlier shares / per-share data restated). Faiveley Transport from 30-Nov-2016; GE Transportation merger 25-Feb-2019 (segments recast Q4-19; product-line sales from 2019); adjusted results add back non-cash amortization from Q1-20 (2019 merger basis as reported). Inspection Technologies 1-Jul-2025; Frauscher 1-Dec-2025; Dellner Couplers 10-Feb-2026. Cash flow incl. restricted cash from 2018 (ASU 2016-18). Q3/26E–Q4/26E calibrated to FY26 sales and adjusted-EPS guidance.
CH5: Forecast | CI5: Historical | CJ5: Historical | CK5: Historical
B6: (USDm) | C6: 2006 | D6: 2007 | E6: 2008 | F6: 2009 | G6: 2010 | H6: 2011 | I6: 2012 | J6: Q1/13 | K6: Q2/13 | L6: Q3/13 | M6: Q4/13 | N6: 2013 | O6: Q1/14 | P6: Q2/14 | Q6: Q3/14 | R6: Q4/14 | S6: 2014 | T6: Q1/15 | U6: Q2/15 | V6: Q3/15 | W6: Q4/15 | X6: 2015 | Y6: Q1/16 | Z6: Q2/16 | AA6: Q3/16 | AB6: Q4/16 | AC6: 2016 | AD6: Q1/17 | AE6: Q2/17 | AF6: Q3/17 | AG6: Q4/17 | AH6: 2017 | AI6: Q1/18 | AJ6: Q2/18 | AK6: Q3/18 | AL6: Q4/18 | AM6: 2018 | AN6: Q1/19 | AO6: Q2/19 | AP6: Q3/19 | AQ6: Q4/19 | AR6: 2019 | AS6: Q1/20 | AT6: Q2/20 | AU6: Q3/20 | AV6: Q4/20 | AW6: 2020 | AX6: Q1/21 | AY6: Q2/21 | AZ6: Q3/21 | BA6: Q4/21 | BB6: 2021 | BC6: Q1/22 | BD6: Q2/22 | BE6: Q3/22 | BF6: Q4/22 | BG6: 2022 | BH6: Q1/23 | BI6: Q2/23 | BJ6: Q3/23 | BK6: Q4/23 | BL6: 2023 | BM6: Q1/24 | BN6: Q2/24 | BO6: Q3/24 | BP6: Q4/24 | BQ6: 2024 | BR6: Q1/25 | BS6: Q2/25 | BT6: Q3/25 | BU6: Q4/25 | BV6: 2025 | BW6: Q1/26 | BX6: Q2/26 | BY6: Q3/26E | BZ6: Q4/26E | CA6: 2026E | CB6: 2027E | CC6: 2028E | CD6: 2029E | CE6: 2030E | CF6: Modelling Notes | CH6: 5Y CAGR | CI6: 5Y CAGR | CJ6: 10Y CAGR | CK6: 19Y CAGR
CH7: 25-'30 | CI7: 20-'25 | CJ7: 15-'25 | CK7: 06-'25
B8: PRODUCT-LINE P&L — FREIGHT (SERVICES · EQUIPMENT · COMPONENTS · DIGITAL INTELLIGENCE) · TRANSIT (OE · AFTERMARKET) · BACKLOG | CF8: PRODUCT-LINE BUILD — modelling logic (product-line sales → segment sales × adjusted operating margin → adjusted operating income → Adjusted EBITDA / adjusted EPS)
CN9: SCENARIO INPUT TABLE — driver assumptions per Bull / Base / Bear | CO9: Bull | CP9: Base | CQ9: Bear | CR9: Bull / Bear = Base + Δ (Δ inputs on each block header). Outlook block = high / mid / low end of FY26 guidance ranges.
B10: Freight segment (locomotives & modernizations, services, components, digital intelligence; ~70% of sales) | CF10: FREIGHT — modelling logic
B11: 12-month backlog — Freight (period end) | C11: 192.8 | D11: 153.7 | E11: 148.6 | F11: 126.2 | G11: 297.2 | H11: 591.4 | I11: 413.8 | M11: 447.4 | N11: 447.4 | R11: 843.7 | S11: 843.7 | W11: 586 | X11: 586 | AB11: 396.2 | AC11: 396.2 | AE11: 413.2 | AF11: 419.7 | AG11: 423.8 | AH11: 423.8 | AI11: 501.4 | AJ11: 464.3 | AK11: 408.5 | AL11: 503.5 | AM11: 503.5 | AN11: 4061.3 | AO11: 3793.9 | AP11: 3914.2 | AQ11: 3911 | AR11: 3911 | AS11: 3819 | AT11: 3681.8 | AU11: 3626.7 | AV11: 3586.3 | AW11: 3586.3 | AX11: 3910.2 | AY11: 4098.1 | AZ11: 4060.2 | BA11: 4520 | BB11: 4520 | BC11: 4812 | BD11: 4821 | BE11: 4567 | BF11: 4901 | BG11: 4901 | BH11: 4978 | BI11: 5318 | BJ11: 5282 | BK11: 5450 | BL11: 5450 | BM11: 5667 | BN11: 5504 | BO11: 5589 | BP11: 5577 | BQ11: 5577 | BR11: 6069 | BS11: 6024 | BT11: 6085 | BU11: 6022 | BV11: 6022 | BW11: 6679 | BX11: 6638 | CF11: Company-reported 12-month backlog (subset of total backlog). Historical only; context for the Q3/Q4-26E growth inputs. | CN11: FY26 outlook — Q2-26 release (22-Jul-26) | CO11: High | CP11: Mid | CQ11: Low | CR11: Raised in the Q2-26 release (from $12.19–12.49bn / $10.25–10.65 in Q1-26; $10.05–10.45 in Feb-26). Includes Dellner (closed 10-Feb-26).
B12: Total (multi-year) backlog — Freight (period end) | C12: 261.8 | D12: 224.9 | E12: 195.7 | F12: 211.3 | G12: 383.6 | H12: 712.9 | I12: 491.8 | M12: 511.7 | N12: 511.7 | R12: 977.8 | S12: 977.8 | W12: 671.9 | X12: 671.9 | AB12: 575.9 | AC12: 575.9 | AE12: 611.2 | AF12: 610.7 | AG12: 549.2 | AH12: 549.2 | AI12: 631.6 | AJ12: 649.3 | AK12: 607.9 | AL12: 664.7 | AM12: 664.7 | AN12: 19466.1 | AO12: 18765.5 | AP12: 18257.6 | AQ12: 18945.3 | AR12: 18945.3 | AS12: 18099.6 | AT12: 17969.8 | AU12: 17840.5 | AV12: 17887.1 | AW12: 17887.1 | AX12: 18005.5 | AY12: 17836.3 | AZ12: 18211 | BA12: 18502 | BB12: 18502 | BC12: 19024 | BD12: 19679 | BE12: 19173 | BF12: 18641 | BG12: 18641 | BH12: 18362 | BI12: 18336 | BJ12: 17614 | BK12: 17831 | BL12: 17831 | BM12: 17898 | BN12: 17929 | BO12: 17756 | BP12: 17986 | BQ12: 17986 | BR12: 17851 | BS12: 17136 | BT12: 20907 | BU12: 22493 | BV12: 22493 | BW12: 25175 | BX12: 25332 | CN12: FY26 net sales ($m) | CO12: 12600 | CP12: 12450 | CQ12: 12300 | CR12: Guided $12.30–12.60bn (raised $110m at mid-point in Q2-26; +11.5% y/y).
B13: 12-month backlog ÷ annualised sales (x) | C13: =IF(AND(ISNUMBER(C11),ISNUMBER(C27)),IFERROR(C11/(C27*1),""),"") | D13: =IF(AND(ISNUMBER(D11),ISNUMBER(D27)),IFERROR(D11/(D27*1),""),"") | E13: =IF(AND(ISNUMBER(E11),ISNUMBER(E27)),IFERROR(E11/(E27*1),""),"") | F13: =IF(AND(ISNUMBER(F11),ISNUMBER(F27)),IFERROR(F11/(F27*1),""),"") | G13: =IF(AND(ISNUMBER(G11),ISNUMBER(G27)),IFERROR(G11/(G27*1),""),"") | H13: =IF(AND(ISNUMBER(H11),ISNUMBER(H27)),IFERROR(H11/(H27*1),""),"") | I13: =IF(AND(ISNUMBER(I11),ISNUMBER(I27)),IFERROR(I11/(I27*1),""),"") | J13: =IF(AND(ISNUMBER(J11),ISNUMBER(J27)),IFERROR(J11/(J27*4),""),"") | K13: =IF(AND(ISNUMBER(K11),ISNUMBER(K27)),IFERROR(K11/(K27*4),""),"") | L13: =IF(AND(ISNUMBER(L11),ISNUMBER(L27)),IFERROR(L11/(L27*4),""),"") | M13: =IF(AND(ISNUMBER(M11),ISNUMBER(M27)),IFERROR(M11/(M27*4),""),"") | N13: =IF(AND(ISNUMBER(N11),ISNUMBER(N27)),IFERROR(N11/(N27*1),""),"") | O13: =IF(AND(ISNUMBER(O11),ISNUMBER(O27)),IFERROR(O11/(O27*4),""),"") | P13: =IF(AND(ISNUMBER(P11),ISNUMBER(P27)),IFERROR(P11/(P27*4),""),"") | Q13: =IF(AND(ISNUMBER(Q11),ISNUMBER(Q27)),IFERROR(Q11/(Q27*4),""),"") | R13: =IF(AND(ISNUMBER(R11),ISNUMBER(R27)),IFERROR(R11/(R27*4),""),"") | S13: =IF(AND(ISNUMBER(S11),ISNUMBER(S27)),IFERROR(S11/(S27*1),""),"") | T13: =IF(AND(ISNUMBER(T11),ISNUMBER(T27)),IFERROR(T11/(T27*4),""),"") | U13: =IF(AND(ISNUMBER(U11),ISNUMBER(U27)),IFERROR(U11/(U27*4),""),"") | V13: =IF(AND(ISNUMBER(V11),ISNUMBER(V27)),IFERROR(V11/(V27*4),""),"") | W13: =IF(AND(ISNUMBER(W11),ISNUMBER(W27)),IFERROR(W11/(W27*4),""),"") | X13: =IF(AND(ISNUMBER(X11),ISNUMBER(X27)),IFERROR(X11/(X27*1),""),"") | Y13: =IF(AND(ISNUMBER(Y11),ISNUMBER(Y27)),IFERROR(Y11/(Y27*4),""),"") | Z13: =IF(AND(ISNUMBER(Z11),ISNUMBER(Z27)),IFERROR(Z11/(Z27*4),""),"") | AA13: =IF(AND(ISNUMBER(AA11),ISNUMBER(AA27)),IFERROR(AA11/(AA27*4),""),"") | AB13: =IF(AND(ISNUMBER(AB11),ISNUMBER(AB27)),IFERROR(AB11/(AB27*4),""),"") | AC13: =IF(AND(ISNUMBER(AC11),ISNUMBER(AC27)),IFERROR(AC11/(AC27*1),""),"") | AD13: =IF(AND(ISNUMBER(AD11),ISNUMBER(AD27)),IFERROR(AD11/(AD27*4),""),"") | AE13: =IF(AND(ISNUMBER(AE11),ISNUMBER(AE27)),IFERROR(AE11/(AE27*4),""),"") | AF13: =IF(AND(ISNUMBER(AF11),ISNUMBER(AF27)),IFERROR(AF11/(AF27*4),""),"") | AG13: =IF(AND(ISNUMBER(AG11),ISNUMBER(AG27)),IFERROR(AG11/(AG27*4),""),"") | AH13: =IF(AND(ISNUMBER(AH11),ISNUMBER(AH27)),IFERROR(AH11/(AH27*1),""),"") | AI13: =IF(AND(ISNUMBER(AI11),ISNUMBER(AI27)),IFERROR(AI11/(AI27*4),""),"") | AJ13: =IF(AND(ISNUMBER(AJ11),ISNUMBER(AJ27)),IFERROR(AJ11/(AJ27*4),""),"") | AK13: =IF(AND(ISNUMBER(AK11),ISNUMBER(AK27)),IFERROR(AK11/(AK27*4),""),"") | AL13: =IF(AND(ISNUMBER(AL11),ISNUMBER(AL27)),IFERROR(AL11/(AL27*4),""),"") | AM13: =IF(AND(ISNUMBER(AM11),ISNUMBER(AM27)),IFERROR(AM11/(AM27*1),""),"") | AN13: =IF(AND(ISNUMBER(AN11),ISNUMBER(AN27)),IFERROR(AN11/(AN27*4),""),"") | AO13: =IF(AND(ISNUMBER(AO11),ISNUMBER(AO27)),IFERROR(AO11/(AO27*4),""),"") | AP13: =IF(AND(ISNUMBER(AP11),ISNUMBER(AP27)),IFERROR(AP11/(AP27*4),""),"") | AQ13: =IF(AND(ISNUMBER(AQ11),ISNUMBER(AQ27)),IFERROR(AQ11/(AQ27*4),""),"") | AR13: =IF(AND(ISNUMBER(AR11),ISNUMBER(AR27)),IFERROR(AR11/(AR27*1),""),"") | AS13: =IF(AND(ISNUMBER(AS11),ISNUMBER(AS27)),IFERROR(AS11/(AS27*4),""),"") | AT13: =IF(AND(ISNUMBER(AT11),ISNUMBER(AT27)),IFERROR(AT11/(AT27*4),""),"") | AU13: =IF(AND(ISNUMBER(AU11),ISNUMBER(AU27)),IFERROR(AU11/(AU27*4),""),"") | AV13: =IF(AND(ISNUMBER(AV11),ISNUMBER(AV27)),IFERROR(AV11/(AV27*4),""),"") | AW13: =IF(AND(ISNUMBER(AW11),ISNUMBER(AW27)),IFERROR(AW11/(AW27*1),""),"") | AX13: =IF(AND(ISNUMBER(AX11),ISNUMBER(AX27)),IFERROR(AX11/(AX27*4),""),"") | AY13: =IF(AND(ISNUMBER(AY11),ISNUMBER(AY27)),IFERROR(AY11/(AY27*4),""),"") | AZ13: =IF(AND(ISNUMBER(AZ11),ISNUMBER(AZ27)),IFERROR(AZ11/(AZ27*4),""),"") | BA13: =IF(AND(ISNUMBER(BA11),ISNUMBER(BA27)),IFERROR(BA11/(BA27*4),""),"") | BB13: =IF(AND(ISNUMBER(BB11),ISNUMBER(BB27)),IFERROR(BB11/(BB27*1),""),"") | BC13: =IF(AND(ISNUMBER(BC11),ISNUMBER(BC27)),IFERROR(BC11/(BC27*4),""),"") | BD13: =IF(AND(ISNUMBER(BD11),ISNUMBER(BD27)),IFERROR(BD11/(BD27*4),""),"") | BE13: =IF(AND(ISNUMBER(BE11),ISNUMBER(BE27)),IFERROR(BE11/(BE27*4),""),"") | BF13: =IF(AND(ISNUMBER(BF11),ISNUMBER(BF27)),IFERROR(BF11/(BF27*4),""),"") | BG13: =IF(AND(ISNUMBER(BG11),ISNUMBER(BG27)),IFERROR(BG11/(BG27*1),""),"") | BH13: =IF(AND(ISNUMBER(BH11),ISNUMBER(BH27)),IFERROR(BH11/(BH27*4),""),"") | BI13: =IF(AND(ISNUMBER(BI11),ISNUMBER(BI27)),IFERROR(BI11/(BI27*4),""),"") | BJ13: =IF(AND(ISNUMBER(BJ11),ISNUMBER(BJ27)),IFERROR(BJ11/(BJ27*4),""),"") | BK13: =IF(AND(ISNUMBER(BK11),ISNUMBER(BK27)),IFERROR(BK11/(BK27*4),""),"") | BL13: =IF(AND(ISNUMBER(BL11),ISNUMBER(BL27)),IFERROR(BL11/(BL27*1),""),"") | BM13: =IF(AND(ISNUMBER(BM11),ISNUMBER(BM27)),IFERROR(BM11/(BM27*4),""),"") | BN13: =IF(AND(ISNUMBER(BN11),ISNUMBER(BN27)),IFERROR(BN11/(BN27*4),""),"") | BO13: =IF(AND(ISNUMBER(BO11),ISNUMBER(BO27)),IFERROR(BO11/(BO27*4),""),"") | BP13: =IF(AND(ISNUMBER(BP11),ISNUMBER(BP27)),IFERROR(BP11/(BP27*4),""),"") | BQ13: =IF(AND(ISNUMBER(BQ11),ISNUMBER(BQ27)),IFERROR(BQ11/(BQ27*1),""),"") | BR13: =IF(AND(ISNUMBER(BR11),ISNUMBER(BR27)),IFERROR(BR11/(BR27*4),""),"") | BS13: =IF(AND(ISNUMBER(BS11),ISNUMBER(BS27)),IFERROR(BS11/(BS27*4),""),"") | BT13: =IF(AND(ISNUMBER(BT11),ISNUMBER(BT27)),IFERROR(BT11/(BT27*4),""),"") | BU13: =IF(AND(ISNUMBER(BU11),ISNUMBER(BU27)),IFERROR(BU11/(BU27*4),""),"") | BV13: =IF(AND(ISNUMBER(BV11),ISNUMBER(BV27)),IFERROR(BV11/(BV27*1),""),"") | BW13: =IF(AND(ISNUMBER(BW11),ISNUMBER(BW27)),IFERROR(BW11/(BW27*4),""),"") | BX13: =IF(AND(ISNUMBER(BX11),ISNUMBER(BX27)),IFERROR(BX11/(BX27*4),""),"") | CF13: 12-month backlog over quarterly sales × 4 (annual columns: full-year sales). >1.0x = next-twelve-month sales largely covered. | CN13: FY26 adjusted diluted EPS ($) | CO13: 10.9 | CP13: 10.75 | CQ13: 10.6 | CR13: Guided $10.60–10.90 (+19.9% y/y at mid). Drives the Q3/Q4-26E adjusted-margin calibration.
B14: Services — sales | AN14: 231.4 | AO14: 556.5 | AP14: 635 | AQ14: 568.2 | AR14: 1991.1 | AS14: 499 | AT14: 508.8 | AU14: 512.8 | AV14: 547.5 | AW14: 2068.1 | AX14: 562.5 | AY14: 622 | AZ14: 582.5 | BA14: 663 | BB14: 2430 | BC14: 666 | BD14: 711 | BE14: 669 | BF14: 773 | BG14: 2819 | BH14: 707 | BI14: 810 | BJ14: 787 | BK14: 958 | BL14: 3262 | BM14: 829 | BN14: 829 | BO14: 917 | BP14: 806 | BQ14: 3381 | BR14: 863 | BS14: 781 | BT14: 744 | BU14: 667 | BV14: 3055 | BW14: 714 | BX14: 748 | BY14: =BT14*(1+BY15) | BZ14: =BU14*(1+BZ15) | CA14: =SUM(BW14,BX14,BY14,BZ14) | CB14: =CA14*(1+CB15) | CC14: =CB14*(1+CC15) | CD14: =CC14*(1+CD15) | CE14: =CD14*(1+CE15) | CF14: Product-line sales as published (from 2019, GE Transportation merger). Q3/Q4-26E: prior-year quarter × (1 + growth). 2027E+: prior year × (1 + scenario lever). | CH14: =IFERROR((CE14/BV14)^(1/5)-1,"n/m") | CI14: =IFERROR((BV14/AW14)^(1/5)-1,"n/m") | CJ14: =IFERROR((BV14/X14)^(1/10)-1,"n/m") | CK14: =IFERROR((BV14/C14)^(1/19)-1,"n/m") | CN14: 2H/26 share repurchases ($m) | CO14: 500 | CP14: 350 | CQ14: 200 | CR14: Authorization $760m remaining at 30-Jun-26 (1H/26: $457m, 1.80m shares).
B15: y/y % | D15: =IF(AND(ISNUMBER(D14),ISNUMBER(C14)),IFERROR(D14/C14-1,""),"") | E15: =IF(AND(ISNUMBER(E14),ISNUMBER(D14)),IFERROR(E14/D14-1,""),"") | F15: =IF(AND(ISNUMBER(F14),ISNUMBER(E14)),IFERROR(F14/E14-1,""),"") | G15: =IF(AND(ISNUMBER(G14),ISNUMBER(F14)),IFERROR(G14/F14-1,""),"") | H15: =IF(AND(ISNUMBER(H14),ISNUMBER(G14)),IFERROR(H14/G14-1,""),"") | I15: =IF(AND(ISNUMBER(I14),ISNUMBER(H14)),IFERROR(I14/H14-1,""),"") | N15: =IF(AND(ISNUMBER(N14),ISNUMBER(I14)),IFERROR(N14/I14-1,""),"") | O15: =IF(AND(ISNUMBER(O14),ISNUMBER(J14)),IFERROR(O14/J14-1,""),"") | P15: =IF(AND(ISNUMBER(P14),ISNUMBER(K14)),IFERROR(P14/K14-1,""),"") | Q15: =IF(AND(ISNUMBER(Q14),ISNUMBER(L14)),IFERROR(Q14/L14-1,""),"") | R15: =IF(AND(ISNUMBER(R14),ISNUMBER(M14)),IFERROR(R14/M14-1,""),"") | S15: =IF(AND(ISNUMBER(S14),ISNUMBER(N14)),IFERROR(S14/N14-1,""),"") | T15: =IF(AND(ISNUMBER(T14),ISNUMBER(O14)),IFERROR(T14/O14-1,""),"") | U15: =IF(AND(ISNUMBER(U14),ISNUMBER(P14)),IFERROR(U14/P14-1,""),"") | ... BX15: =IF(AND(ISNUMBER(BX14),ISNUMBER(BS14)),IFERROR(BX14/BS14-1,""),"") | BY15: =BY16+$BY$109 | BZ15: =BZ16+$BY$109 | CA15: =IF(AND(ISNUMBER(CA14),ISNUMBER(BV14)),IFERROR(CA14/BV14-1,""),"") | CB15: =CHOOSE(MATCH($CF$2,{"Bull","Base","Bear"},0),$CO$31,$CP$31,$CQ$31) | CC15: =CHOOSE(MATCH($CF$2,{"Bull","Base","Bear"},0),$CO$32,$CP$32,$CQ$32) | CD15: =CHOOSE(MATCH($CF$2,{"Bull","Base","Bear"},0),$CO$33,$CP$33,$CQ$33) | CE15: =CHOOSE(MATCH($CF$2,{"Bull","Base","Bear"},0),$CO$34,$CP$34,$CQ$34) | CF15: Q3/Q4-26E: growth input (row below) + revenue-outlook calibration Δ (Group block). 2027E–2030E: scenario lever (Bull/Base/Bear table →). | CN15: FY26 point estimates (all cases)
B16: Q3/Q4-26E growth input before revenue calibration | BY16: -0.04 | BZ16: -0.04 | CF16: Input −4%: 1H/26 −11% y/y (lower N.A. modernization deliveries, as guided), Q2/26 −4%. | CN16: Interest expense, net ($m) | CP16: 311 | CR16: 1H/26 $151m + Q2/26 run-rate ($80m) × 2 — Dellner financing on the revolver / receivables program; not guided.
B17: Equipment — sales | AN17: 267.1 | AO17: 531.3 | AP17: 263.3 | AQ17: 638 | AR17: 1699.7 | AS17: 408 | AT17: 334.9 | AU17: 355.3 | AV17: 433.3 | AW17: 1531.5 | AX17: 261.8 | AY17: 327.8 | AZ17: 335.2 | BA17: 377 | BB17: 1302 | BC17: 274 | BD17: 381 | BE17: 443 | BF17: 430 | BG17: 1528 | BH17: 393 | BI17: 415 | BJ17: 615 | BK17: 347 | BL17: 1770 | BM17: 526 | BN17: 570 | BO17: 513 | BP17: 499 | BQ17: 2108 | BR17: 476 | BS17: 546 | BT17: 677 | BU17: 666 | BV17: 2365 | BW17: 726 | BX17: 737 | BY17: =BT17*(1+BY18) | BZ17: =BU17*(1+BZ18) | CA17: =SUM(BW17,BX17,BY17,BZ17) | CB17: =CA17*(1+CB18) | CC17: =CB17*(1+CC18) | CD17: =CC17*(1+CD18) | CE17: =CD17*(1+CE18) | CF17: Product-line sales as published (from 2019, GE Transportation merger). Q3/Q4-26E: prior-year quarter × (1 + growth). 2027E+: prior year × (1 + scenario lever). | CH17: =IFERROR((CE17/BV17)^(1/5)-1,"n/m") | CI17: =IFERROR((BV17/AW17)^(1/5)-1,"n/m") | CJ17: =IFERROR((BV17/X17)^(1/10)-1,"n/m") | CK17: =IFERROR((BV17/C17)^(1/19)-1,"n/m") | CN17: Other income (expense), net ($m) | CP17: 21 | CR17: 1H/26 actual $21m; 2H/26 assumed nil (Q2/26 −$2m).
B18: y/y % | D18: =IF(AND(ISNUMBER(D17),ISNUMBER(C17)),IFERROR(D17/C17-1,""),"") | E18: =IF(AND(ISNUMBER(E17),ISNUMBER(D17)),IFERROR(E17/D17-1,""),"") | F18: =IF(AND(ISNUMBER(F17),ISNUMBER(E17)),IFERROR(F17/E17-1,""),"") | G18: =IF(AND(ISNUMBER(G17),ISNUMBER(F17)),IFERROR(G17/F17-1,""),"") | H18: =IF(AND(ISNUMBER(H17),ISNUMBER(G17)),IFERROR(H17/G17-1,""),"") | I18: =IF(AND(ISNUMBER(I17),ISNUMBER(H17)),IFERROR(I17/H17-1,""),"") | N18: =IF(AND(ISNUMBER(N17),ISNUMBER(I17)),IFERROR(N17/I17-1,""),"") | O18: =IF(AND(ISNUMBER(O17),ISNUMBER(J17)),IFERROR(O17/J17-1,""),"") | P18: =IF(AND(ISNUMBER(P17),ISNUMBER(K17)),IFERROR(P17/K17-1,""),"") | Q18: =IF(AND(ISNUMBER(Q17),ISNUMBER(L17)),IFERROR(Q17/L17-1,""),"") | R18: =IF(AND(ISNUMBER(R17),ISNUMBER(M17)),IFERROR(R17/M17-1,""),"") | S18: =IF(AND(ISNUMBER(S17),ISNUMBER(N17)),IFERROR(S17/N17-1,""),"") | T18: =IF(AND(ISNUMBER(T17),ISNUMBER(O17)),IFERROR(T17/O17-1,""),"") | U18: =IF(AND(ISNUMBER(U17),ISNUMBER(P17)),IFERROR(U17/P17-1,""),"") | ... BX18: =IF(AND(ISNUMBER(BX17),ISNUMBER(BS17)),IFERROR(BX17/BS17-1,""),"") | BY18: =BY19+$BY$109 | BZ18: =BZ19+$BY$109 | CA18: =IF(AND(ISNUMBER(CA17),ISNUMBER(BV17)),IFERROR(CA17/BV17-1,""),"") | CB18: =CHOOSE(MATCH($CF$2,{"Bull","Base","Bear"},0),$CO$36,$CP$36,$CQ$36) | CC18: =CHOOSE(MATCH($CF$2,{"Bull","Base","Bear"},0),$CO$37,$CP$37,$CQ$37) | CD18: =CHOOSE(MATCH($CF$2,{"Bull","Base","Bear"},0),$CO$38,$CP$38,$CQ$38) | CE18: =CHOOSE(MATCH($CF$2,{"Bull","Base","Bear"},0),$CO$39,$CP$39,$CQ$39) | CF18: Q3/Q4-26E: growth input (row below) + revenue-outlook calibration Δ (Group block). 2027E–2030E: scenario lever (Bull/Base/Bear table →). | CN18: Tax rate (GAAP & adjusted) | CP18: 0.245 | CR18: FY26 guidance slide: tax rate ~24.5%.
B19: Q3/Q4-26E growth input before revenue calibration | BY19: 0.12 | BZ19: 0.12 | CF19: Input +12%: 1H/26 +43% (international locomotive deliveries); tougher comparisons in 2H (Q3-25 $677m, Q4-25 $666m). | CN19: Capital expenditures ($m) | CP19: 250 | CR19: Guidance: capex ~2% of sales (≈$250m on the mid-point); 1H/26 $108m.
B20: Components — sales | AN20: 295.2 | AO20: 279.5 | AP20: 248.7 | AQ20: 250.1 | AR20: 1073.5 | AS20: 220.4 | AT20: 195.5 | AU20: 208.2 | AV20: 194.6 | AW20: 818.7 | AX20: 202.5 | AY20: 224.3 | AZ20: 222.1 | BA20: 218 | BB20: 867 | BC20: 229 | BD20: 234 | BE20: 232 | BF20: 241 | BG20: 936 | BH20: 279 | BI20: 288 | BJ20: 307 | BK20: 283 | BL20: 1157 | BM20: 293 | BN20: 322 | BO20: 296 | BP20: 282 | BQ20: 1193 | BR20: 381 | BS20: 401 | BT20: 375 | BU20: 429 | BV20: 1586 | BW20: 357 | BX20: 398 | BY20: =BT20*(1+BY21) | BZ20: =BU20*(1+BZ21) | CA20: =SUM(BW20,BX20,BY20,BZ20) | CB20: =CA20*(1+CB21) | CC20: =CB20*(1+CC21) | CD20: =CC20*(1+CD21) | CE20: =CD20*(1+CE21) | CF20: Product-line sales as published (from 2019, GE Transportation merger). Q3/Q4-26E: prior-year quarter × (1 + growth). 2027E+: prior year × (1 + scenario lever). | CH20: =IFERROR((CE20/BV20)^(1/5)-1,"n/m") | CI20: =IFERROR((BV20/AW20)^(1/5)-1,"n/m") | CJ20: =IFERROR((BV20/X20)^(1/10)-1,"n/m") | CK20: =IFERROR((BV20/C20)^(1/19)-1,"n/m") | CN20: Restructuring & portfolio optimization costs ($m) | CP20: 15 | CR20: 1H/26 $5m; Integration 3.0 / Portfolio Optimization; analyst point estimate.
B21: y/y % | D21: =IF(AND(ISNUMBER(D20),ISNUMBER(C20)),IFERROR(D20/C20-1,""),"") | E21: =IF(AND(ISNUMBER(E20),ISNUMBER(D20)),IFERROR(E20/D20-1,""),"") | F21: =IF(AND(ISNUMBER(F20),ISNUMBER(E20)),IFERROR(F20/E20-1,""),"") | G21: =IF(AND(ISNUMBER(G20),ISNUMBER(F20)),IFERROR(G20/F20-1,""),"") | H21: =IF(AND(ISNUMBER(H20),ISNUMBER(G20)),IFERROR(H20/G20-1,""),"") | I21: =IF(AND(ISNUMBER(I20),ISNUMBER(H20)),IFERROR(I20/H20-1,""),"") | N21: =IF(AND(ISNUMBER(N20),ISNUMBER(I20)),IFERROR(N20/I20-1,""),"") | O21: =IF(AND(ISNUMBER(O20),ISNUMBER(J20)),IFERROR(O20/J20-1,""),"") | P21: =IF(AND(ISNUMBER(P20),ISNUMBER(K20)),IFERROR(P20/K20-1,""),"") | Q21: =IF(AND(ISNUMBER(Q20),ISNUMBER(L20)),IFERROR(Q20/L20-1,""),"") | R21: =IF(AND(ISNUMBER(R20),ISNUMBER(M20)),IFERROR(R20/M20-1,""),"") | S21: =IF(AND(ISNUMBER(S20),ISNUMBER(N20)),IFERROR(S20/N20-1,""),"") | T21: =IF(AND(ISNUMBER(T20),ISNUMBER(O20)),IFERROR(T20/O20-1,""),"") | U21: =IF(AND(ISNUMBER(U20),ISNUMBER(P20)),IFERROR(U20/P20-1,""),"") | ... BX21: =IF(AND(ISNUMBER(BX20),ISNUMBER(BS20)),IFERROR(BX20/BS20-1,""),"") | BY21: =BY22+$BY$109 | BZ21: =BZ22+$BY$109 | CA21: =IF(AND(ISNUMBER(CA20),ISNUMBER(BV20)),IFERROR(CA20/BV20-1,""),"") | CB21: =CHOOSE(MATCH($CF$2,{"Bull","Base","Bear"},0),$CO$41,$CP$41,$CQ$41) | CC21: =CHOOSE(MATCH($CF$2,{"Bull","Base","Bear"},0),$CO$42,$CP$42,$CQ$42) | CD21: =CHOOSE(MATCH($CF$2,{"Bull","Base","Bear"},0),$CO$43,$CP$43,$CQ$43) | CE21: =CHOOSE(MATCH($CF$2,{"Bull","Base","Bear"},0),$CO$44,$CP$44,$CQ$44) | CF21: Q3/Q4-26E: growth input (row below) + revenue-outlook calibration Δ (Group block). 2027E–2030E: scenario lever (Bull/Base/Bear table →).
B22: Q3/Q4-26E growth input before revenue calibration | BY22: 0 | BZ22: 0 | CF22: Input 0%: 1H/26 −3% (N.A. railcar build down; industrial up).
B23: Digital Intelligence (Digital Electronics to 2023) — sales | AN23: 121.8 | AO23: 159 | AP23: 185.5 | AQ23: 210.8 | AR23: 677.1 | AS23: 173.6 | AT23: 165.5 | AU23: 161 | AV23: 163.9 | AW23: 664 | AX23: 156.5 | AY23: 161.8 | AZ23: 155.2 | BA23: 167 | BB23: 640 | BC23: 153 | BD23: 164 | BE23: 187 | BF23: 225 | BG23: 729 | BH23: 187 | BI23: 195 | BJ23: 181 | BK23: 210 | BL23: 773 | BM23: 176 | BN23: 199 | BO23: 204 | BP23: 207 | BQ23: 786 | BR23: 181 | BS23: 191 | BT23: 297 | BU23: 361 | BV23: 1030 | BW23: 318 | BX23: 360 | BY23: =BT23*(1+BY24) | BZ23: =BU23*(1+BZ24) | CA23: =SUM(BW23,BX23,BY23,BZ23) | CB23: =CA23*(1+CB24) | CC23: =CB23*(1+CC24) | CD23: =CC23*(1+CD24) | CE23: =CD23*(1+CE24) | CF23: Product-line sales as published (from 2019, GE Transportation merger). Q3/Q4-26E: prior-year quarter × (1 + growth). 2027E+: prior year × (1 + scenario lever). | CH23: =IFERROR((CE23/BV23)^(1/5)-1,"n/m") | CI23: =IFERROR((BV23/AW23)^(1/5)-1,"n/m") | CJ23: =IFERROR((BV23/X23)^(1/10)-1,"n/m") | CK23: =IFERROR((BV23/C23)^(1/19)-1,"n/m")
B24: y/y % | D24: =IF(AND(ISNUMBER(D23),ISNUMBER(C23)),IFERROR(D23/C23-1,""),"") | E24: =IF(AND(ISNUMBER(E23),ISNUMBER(D23)),IFERROR(E23/D23-1,""),"") | F24: =IF(AND(ISNUMBER(F23),ISNUMBER(E23)),IFERROR(F23/E23-1,""),"") | G24: =IF(AND(ISNUMBER(G23),ISNUMBER(F23)),IFERROR(G23/F23-1,""),"") | H24: =IF(AND(ISNUMBER(H23),ISNUMBER(G23)),IFERROR(H23/G23-1,""),"") | I24: =IF(AND(ISNUMBER(I23),ISNUMBER(H23)),IFERROR(I23/H23-1,""),"") | N24: =IF(AND(ISNUMBER(N23),ISNUMBER(I23)),IFERROR(N23/I23-1,""),"") | O24: =IF(AND(ISNUMBER(O23),ISNUMBER(J23)),IFERROR(O23/J23-1,""),"") | P24: =IF(AND(ISNUMBER(P23),ISNUMBER(K23)),IFERROR(P23/K23-1,""),"") | Q24: =IF(AND(ISNUMBER(Q23),ISNUMBER(L23)),IFERROR(Q23/L23-1,""),"") | R24: =IF(AND(ISNUMBER(R23),ISNUMBER(M23)),IFERROR(R23/M23-1,""),"") | S24: =IF(AND(ISNUMBER(S23),ISNUMBER(N23)),IFERROR(S23/N23-1,""),"") | T24: =IF(AND(ISNUMBER(T23),ISNUMBER(O23)),IFERROR(T23/O23-1,""),"") | U24: =IF(AND(ISNUMBER(U23),ISNUMBER(P23)),IFERROR(U23/P23-1,""),"") | ... BX24: =IF(AND(ISNUMBER(BX23),ISNUMBER(BS23)),IFERROR(BX23/BS23-1,""),"") | BY24: =BY25+$BY$109 | BZ24: =BZ25+$BY$109 | CA24: =IF(AND(ISNUMBER(CA23),ISNUMBER(BV23)),IFERROR(CA23/BV23-1,""),"") | CB24: =CHOOSE(MATCH($CF$2,{"Bull","Base","Bear"},0),$CO$46,$CP$46,$CQ$46) | CC24: =CHOOSE(MATCH($CF$2,{"Bull","Base","Bear"},0),$CO$47,$CP$47,$CQ$47) | CD24: =CHOOSE(MATCH($CF$2,{"Bull","Base","Bear"},0),$CO$48,$CP$48,$CQ$48) | CE24: =CHOOSE(MATCH($CF$2,{"Bull","Base","Bear"},0),$CO$49,$CP$49,$CQ$49) | CF24: Q3/Q4-26E: growth input (row below) + revenue-outlook calibration Δ (Group block). 2027E–2030E: scenario lever (Bull/Base/Bear table →).
B25: Q3/Q4-26E growth input before revenue calibration | BY25: 0.262 | BZ25: 0.171 | CF25: Input = 6% organic + Frauscher (closed 1-Dec-25) not yet in the prior-year quarter (~$60m in Q3, ~$40m in Q4; analyst estimate). Inspection Technologies anniversaries 1-Jul-26.
B26: Freight sales not split by product line (pre-2019 disclosure) | C26: =IF(ISNUMBER(C27),C27-(N(C14)+N(C17)+N(C20)+N(C23)),"") | D26: =IF(ISNUMBER(D27),D27-(N(D14)+N(D17)+N(D20)+N(D23)),"") | E26: =IF(ISNUMBER(E27),E27-(N(E14)+N(E17)+N(E20)+N(E23)),"") | F26: =IF(ISNUMBER(F27),F27-(N(F14)+N(F17)+N(F20)+N(F23)),"") | G26: =IF(ISNUMBER(G27),G27-(N(G14)+N(G17)+N(G20)+N(G23)),"") | H26: =IF(ISNUMBER(H27),H27-(N(H14)+N(H17)+N(H20)+N(H23)),"") | I26: =IF(ISNUMBER(I27),I27-(N(I14)+N(I17)+N(I20)+N(I23)),"") | J26: =IF(ISNUMBER(J27),J27-(N(J14)+N(J17)+N(J20)+N(J23)),"") | ... BX26: =IF(ISNUMBER(BX27),BX27-(N(BX14)+N(BX17)+N(BX20)+N(BX23)),"") | CF26: Historical segment sales less the product-line split (product lines are published from 2019; earlier years show the segment total here).
B27: Freight segment net sales | C27: 709.4 | D27: 734.2 | E27: 773.5 | F27: 588.4 | G27: 784.5 | H27: 1210.1 | I27: 1501.9 | J27: 305.9 | K27: 354.9 | L27: 340.5 | M27: 389 | N27: 1398.1 | O27: 385.5 | P27: 411.5 | Q27: 453.3 | R27: 481.1 | S27: 1731.5 | T27: 511.9 | U27: 534.7 | V27: 507.2 | W27: 501 | X27: 2054.7 | Y27: 442.7 | Z27: 397.1 | AA27: 362 | AB27: 341.4 | AC27: 1543.1 | AD27: 347.9 | AE27: 344.8 | AF27: 340.2 | AG27: 363.6 | AH27: 1396.6 | AI27: 379.6 | AJ27: 412.3 | AK27: 391.6 | AL27: 380.9 | AM27: 1564.3 | AN27: 876.4 | AO27: 1493.9 | AP27: 1295.7 | AQ27: 1667.1 | AR27: 5441.4 | AS27: 1301 | AT27: 1204.7 | AU27: 1237.3 | AV27: 1339.3 | AW27: 5082.3 | AX27: 1183.3 | AY27: 1335.9 | AZ27: 1295 | BA27: 1425 | BB27: 5239 | BC27: 1322 | BD27: 1490 | BE27: 1531 | BF27: 1669 | BG27: 6012 | BH27: 1566 | BI27: 1708 | BJ27: 1890 | BK27: 1798 | BL27: 6962 | BM27: 1824 | BN27: 1920 | BO27: 1930 | BP27: 1794 | BQ27: 7468 | BR27: 1901 | BS27: 1919 | BT27: 2093 | BU27: 2123 | BV27: 8036 | BW27: 2115 | BX27: 2243 | BY27: =N(BY14)+N(BY17)+N(BY20)+N(BY23) | BZ27: =N(BZ14)+N(BZ17)+N(BZ20)+N(BZ23) | CA27: =SUM(BW27,BX27,BY27,BZ27) | CB27: =N(CB14)+N(CB17)+N(CB20)+N(CB23) | CC27: =N(CC14)+N(CC17)+N(CC20)+N(CC23) | CD27: =N(CD14)+N(CD17)+N(CD20)+N(CD23) | CE27: =N(CE14)+N(CE17)+N(CE20)+N(CE23) | CF27: Historical = segment net sales as originally reported. Forecast = Σ product lines. | CH27: =IFERROR((CE27/BV27)^(1/5)-1,"n/m") | CI27: =IFERROR((BV27/AW27)^(1/5)-1,"n/m") | CJ27: =IFERROR((BV27/X27)^(1/10)-1,"n/m") | CK27: =IFERROR((BV27/C27)^(1/19)-1,"n/m")
B28: Segment net sales y/y % | D28: =IF(AND(ISNUMBER(D27),ISNUMBER(C27)),IFERROR(D27/C27-1,""),"") | E28: =IF(AND(ISNUMBER(E27),ISNUMBER(D27)),IFERROR(E27/D27-1,""),"") | F28: =IF(AND(ISNUMBER(F27),ISNUMBER(E27)),IFERROR(F27/E27-1,""),"") | G28: =IF(AND(ISNUMBER(G27),ISNUMBER(F27)),IFERROR(G27/F27-1,""),"") | H28: =IF(AND(ISNUMBER(H27),ISNUMBER(G27)),IFERROR(H27/G27-1,""),"") | I28: =IF(AND(ISNUMBER(I27),ISNUMBER(H27)),IFERROR(I27/H27-1,""),"") | N28: =IF(AND(ISNUMBER(N27),ISNUMBER(I27)),IFERROR(N27/I27-1,""),"") | O28: =IF(AND(ISNUMBER(O27),ISNUMBER(J27)),IFERROR(O27/J27-1,""),"") | P28: =IF(AND(ISNUMBER(P27),ISNUMBER(K27)),IFERROR(P27/K27-1,""),"") | Q28: =IF(AND(ISNUMBER(Q27),ISNUMBER(L27)),IFERROR(Q27/L27-1,""),"") | R28: =IF(AND(ISNUMBER(R27),ISNUMBER(M27)),IFERROR(R27/M27-1,""),"") | S28: =IF(AND(ISNUMBER(S27),ISNUMBER(N27)),IFERROR(S27/N27-1,""),"") | T28: =IF(AND(ISNUMBER(T27),ISNUMBER(O27)),IFERROR(T27/O27-1,""),"") | U28: =IF(AND(ISNUMBER(U27),ISNUMBER(P27)),IFERROR(U27/P27-1,""),"") | ... CA28: =IF(AND(ISNUMBER(CA27),ISNUMBER(BV27)),IFERROR(CA27/BV27-1,""),"") | CB28: =IF(AND(ISNUMBER(CB27),ISNUMBER(CA27)),IFERROR(CB27/CA27-1,""),"") | CC28: =IF(AND(ISNUMBER(CC27),ISNUMBER(CB27)),IFERROR(CC27/CB27-1,""),"") | CD28: =IF(AND(ISNUMBER(CD27),ISNUMBER(CC27)),IFERROR(CD27/CC27-1,""),"") | CE28: =IF(AND(ISNUMBER(CE27),ISNUMBER(CD27)),IFERROR(CE27/CD27-1,""),"") | CN28: Minimum net debt / Adjusted EBITDA (x) — buyback floor 2027E+ | CO28: 1.75 | CP28: 1.5 | CQ28: 1.25 | CR28: Wabtec targets net leverage of ~2.0–2.5x through the cycle; ~1.7x Adjusted EBITDA expected at YE26 (2.0x at 30-Jun-26 after Dellner). Floors leave headroom for bolt-on M&A; buybacks absorb free cash flow once leverage reaches the scenario floor.
B29: Segment gross profit (GAAP; published from 2019) | AQ29: 514.2 | AR29: 1581.4 | AX29: 356 | AY29: 414 | AZ29: 444 | BA29: 454 | BB29: 1667 | BC29: 424 | BD29: 493 | BE29: 497 | BF29: 482 | BG29: 1896 | BH29: 480 | BI29: 541 | BJ29: 611 | BK29: 558 | BL29: 2190 | BM29: 625 | BN29: 669 | BO29: 673 | BP29: 556 | BQ29: 2523 | BR29: 685 | BS29: 697 | BT29: 750 | BU29: 703 | BV29: 2835 | BW29: 788 | BX29: 854
B30: Segment gross margin % | C30: =IF(AND(ISNUMBER(C29),ISNUMBER(C27)),IFERROR(C29/C27,""),"") | D30: =IF(AND(ISNUMBER(D29),ISNUMBER(D27)),IFERROR(D29/D27,""),"") | E30: =IF(AND(ISNUMBER(E29),ISNUMBER(E27)),IFERROR(E29/E27,""),"") | F30: =IF(AND(ISNUMBER(F29),ISNUMBER(F27)),IFERROR(F29/F27,""),"") | G30: =IF(AND(ISNUMBER(G29),ISNUMBER(G27)),IFERROR(G29/G27,""),"") | H30: =IF(AND(ISNUMBER(H29),ISNUMBER(H27)),IFERROR(H29/H27,""),"") | I30: =IF(AND(ISNUMBER(I29),ISNUMBER(I27)),IFERROR(I29/I27,""),"") | J30: =IF(AND(ISNUMBER(J29),ISNUMBER(J27)),IFERROR(J29/J27,""),"") | ... BX30: =IF(AND(ISNUMBER(BX29),ISNUMBER(BX27)),IFERROR(BX29/BX27,""),"") | CH30: =IFERROR(AVERAGE(CA30,CB30,CC30,CD30,CE30),"n/m") | CI30: =IFERROR(AVERAGE(BB30,BG30,BL30,BQ30,BV30),"n/m") | CJ30: =IFERROR(AVERAGE(AC30,AH30,AM30,AR30,AW30,BB30,BG30,BL30,BQ30,BV30),"n/m") | CK30: =IFERROR(AVERAGE(C30,D30,E30,F30,G30,H30,I30,N30,S30,X30,AC30,AH30,AM30,AR30,AW30,BB30,BG30,BL30,BQ30,BV30),"n/m") | CN30: FRT_SVC (Freight Services sales y/y) | CO30: 0.02 | CP30: Δ → | CQ30: -0.02 | CR30: Modernizations (lumpy; N.A. mods down in 2026), overhauls, parts & long-term service agreements on the ~25,000 GE-built fleet.
B31: Freight adjusted income from operations (company definition) | AM31: 308 | AS31: 240.6 | AT31: 228.9 | AU31: 234.2 | AV31: 218.4 | AW31: 922.1 | AX31: 214.1 | AY31: 246.7 | AZ31: 266.2 | BA31: 267 | BB31: 993 | BC31: 259 | BD31: 301 | BE31: 307 | BF31: 284 | BG31: 1151 | BH31: 297 | BI31: 346 | BJ31: 399 | BK31: 347 | BL31: 1389 | BM31: 439 | BN31: 462 | BO31: 467 | BP31: 348 | BQ31: 1716 | BR31: 488 | BS31: 480 | BT31: 513 | BU31: 470 | BV31: 1951 | BW31: 550 | BX31: 579 | BY31: =BY27*BY32 | BZ31: =BZ27*BZ32 | CA31: =SUM(BW31,BX31,BY31,BZ31) | CB31: =CB27*CB32 | CC31: =CC27*CC32 | CD31: =CD27*CD32 | CE31: =CE27*CE32 | CF31: Segment adjusted operating income as published (segment Reported→Adjusted tables). Forecast = segment sales × adjusted operating margin. | CH31: =IFERROR((CE31/BV31)^(1/5)-1,"n/m") | CI31: =IFERROR((BV31/AW31)^(1/5)-1,"n/m") | CJ31: =IFERROR((BV31/X31)^(1/10)-1,"n/m") | CK31: =IFERROR((BV31/C31)^(1/19)-1,"n/m") | CN31: 2027E | CO31: =CP31+$CO$30 | CP31: 0.04 | CQ31: =CP31+$CQ$30
B32: Adjusted operating margin % | C32: =IF(AND(ISNUMBER(C31),ISNUMBER(C27)),IFERROR(C31/C27,""),"") | D32: =IF(AND(ISNUMBER(D31),ISNUMBER(D27)),IFERROR(D31/D27,""),"") | E32: =IF(AND(ISNUMBER(E31),ISNUMBER(E27)),IFERROR(E31/E27,""),"") | F32: =IF(AND(ISNUMBER(F31),ISNUMBER(F27)),IFERROR(F31/F27,""),"") | G32: =IF(AND(ISNUMBER(G31),ISNUMBER(G27)),IFERROR(G31/G27,""),"") | H32: =IF(AND(ISNUMBER(H31),ISNUMBER(H27)),IFERROR(H31/H27,""),"") | I32: =IF(AND(ISNUMBER(I31),ISNUMBER(I27)),IFERROR(I31/I27,""),"") | J32: =IF(AND(ISNUMBER(J31),ISNUMBER(J27)),IFERROR(J31/J27,""),"") | ... BX32: =IF(AND(ISNUMBER(BX31),ISNUMBER(BX27)),IFERROR(BX31/BX27,""),"") | BY32: =BY33+$BY$115 | BZ32: =BZ33+$BY$115 | CA32: =IF(AND(ISNUMBER(CA31),ISNUMBER(CA27)),IFERROR(CA31/CA27,""),"") | CB32: =CHOOSE(MATCH($CF$2,{"Bull","Base","Bear"},0),$CO$61,$CP$61,$CQ$61) | CC32: =CHOOSE(MATCH($CF$2,{"Bull","Base","Bear"},0),$CO$62,$CP$62,$CQ$62) | CD32: =CHOOSE(MATCH($CF$2,{"Bull","Base","Bear"},0),$CO$63,$CP$63,$CQ$63) | CE32: =CHOOSE(MATCH($CF$2,{"Bull","Base","Bear"},0),$CO$64,$CP$64,$CQ$64) | CF32: Q3/Q4-26E: margin before calibration + adjusted-EPS-outlook calibration Δ (Group block). 2027E–2030E: scenario lever. | CH32: =IFERROR(AVERAGE(CA32,CB32,CC32,CD32,CE32),"n/m") | CI32: =IFERROR(AVERAGE(BB32,BG32,BL32,BQ32,BV32),"n/m") | CJ32: =IFERROR(AVERAGE(AC32,AH32,AM32,AR32,AW32,BB32,BG32,BL32,BQ32,BV32),"n/m") | CK32: =IFERROR(AVERAGE(C32,D32,E32,F32,G32,H32,I32,N32,S32,X32,AC32,AH32,AM32,AR32,AW32,BB32,BG32,BL32,BQ32,BV32),"n/m") | CN32: 2028E | CO32: =CP32+$CO$30 | CP32: 0.05 | CQ32: =CP32+$CQ$30
B33: Adjusted operating margin before outlook calibration % (Q3/Q4-26E helper) | BY33: =BT32+((BW31+BX31)/(BW27+BX27)-(BR31+BS31)/(BR27+BS27)) | BZ33: =BU32+((BW31+BX31)/(BW27+BX27)-(BR31+BS31)/(BR27+BS27)) | CF33: Prior-year quarter margin + (1H/26 − 1H/25 adjusted margin drift). | CN33: 2029E | CO33: =CP33+$CO$30 | CP33: 0.05 | CQ33: =CP33+$CQ$30
B34: Incremental adjusted operating margin (Δ adj. op. income / Δ sales) | D34: =IFERROR((D31-C31)/(D27-C27),"") | E34: =IFERROR((E31-D31)/(E27-D27),"") | F34: =IFERROR((F31-E31)/(F27-E27),"") | G34: =IFERROR((G31-F31)/(G27-F27),"") | H34: =IFERROR((H31-G31)/(H27-G27),"") | I34: =IFERROR((I31-H31)/(I27-H27),"") | N34: =IFERROR((N31-I31)/(N27-I27),"") | O34: =IFERROR((O31-J31)/(O27-J27),"") | P34: =IFERROR((P31-K31)/(P27-K27),"") | Q34: =IFERROR((Q31-L31)/(Q27-L27),"") | R34: =IFERROR((R31-M31)/(R27-M27),"") | S34: =IFERROR((S31-N31)/(S27-N27),"") | T34: =IFERROR((T31-O31)/(T27-O27),"") | U34: =IFERROR((U31-P31)/(U27-P27),"") | ... CA34: =IFERROR((CA31-BV31)/(CA27-BV27),"") | CB34: =IFERROR((CB31-CA31)/(CB27-CA27),"") | CC34: =IFERROR((CC31-CB31)/(CC27-CB27),"") | CD34: =IFERROR((CD31-CC31)/(CD27-CC27),"") | CE34: =IFERROR((CE31-CD31)/(CE27-CD27),"") | CN34: 2030E | CO34: =CP34+$CO$30 | CP34: 0.05 | CQ34: =CP34+$CQ$30
B35: Adjusting items in segment (amortization, restructuring, purchase accounting, transaction) | C35: =IF(AND(ISNUMBER(C31),ISNUMBER(C37)),C31-C37,"") | D35: =IF(AND(ISNUMBER(D31),ISNUMBER(D37)),D31-D37,"") | E35: =IF(AND(ISNUMBER(E31),ISNUMBER(E37)),E31-E37,"") | F35: =IF(AND(ISNUMBER(F31),ISNUMBER(F37)),F31-F37,"") | G35: =IF(AND(ISNUMBER(G31),ISNUMBER(G37)),G31-G37,"") | H35: =IF(AND(ISNUMBER(H31),ISNUMBER(H37)),H31-H37,"") | I35: =IF(AND(ISNUMBER(I31),ISNUMBER(I37)),I31-I37,"") | J35: =IF(AND(ISNUMBER(J31),ISNUMBER(J37)),J31-J37,"") | ... BX35: =IF(AND(ISNUMBER(BX31),ISNUMBER(BX37)),BX31-BX37,"") | BY35: =BY213*BY36 | BZ35: =BZ213*BZ36 | CA35: =SUM(BW35,BX35,BY35,BZ35) | CB35: =CB213*CB36 | CC35: =CC213*CC36 | CD35: =CD213*CD36 | CE35: =CE213*CE36 | CF35: Historical = adjusted − GAAP segment operating income. Forecast = consolidated operating-level adjusting items × segment share. | CN35: FRT_EQ (Freight Equipment sales y/y) | CO35: 0.03 | CP35: Δ → | CQ35: -0.04 | CR35: New locomotives (international orders: Kazakhstan, India, Brazil, Africa) & mining; $25.3bn Freight backlog at 30-Jun-26.
B36: Segment share of consolidated operating-level adjusting items % | C36: =IF(ISNUMBER(C35),IFERROR(C35/C213,""),"") | D36: =IF(ISNUMBER(D35),IFERROR(D35/D213,""),"") | E36: =IF(ISNUMBER(E35),IFERROR(E35/E213,""),"") | F36: =IF(ISNUMBER(F35),IFERROR(F35/F213,""),"") | G36: =IF(ISNUMBER(G35),IFERROR(G35/G213,""),"") | H36: =IF(ISNUMBER(H35),IFERROR(H35/H213,""),"") | I36: =IF(ISNUMBER(I35),IFERROR(I35/I213,""),"") | J36: =IF(ISNUMBER(J35),IFERROR(J35/J213,""),"") | ... BX36: =IF(ISNUMBER(BX35),IFERROR(BX35/BX213,""),"") | BY36: =IFERROR((BW35+BX35)/(BW213+BX213),0) | BZ36: =IFERROR((BW35+BX35)/(BW213+BX213),0) | CA36: =IFERROR(CA35/CA213,"") | CB36: =$BZ$36 | CC36: =$BZ$36 | CD36: =$BZ$36 | CE36: =$BZ$36 | CF36: Forecast at the 1H/26 share (Freight carries most acquired-intangible amortization). | CN36: 2027E | CO36: =CP36+$CO$35 | CP36: 0.06 | CQ36: =CP36+$CQ$35
B37: Freight income from operations (GAAP) | C37: 109.8 | D37: 126.5 | E37: 133.5 | F37: 74.1 | G37: 122.1 | H37: 225.3 | I37: 316.1 | J37: 75.4 | K37: 78.6 | L37: 77.3 | M37: 83.4 | N37: 309.1 | O37: 91.9 | P37: 100.3 | Q37: 102.2 | R37: 108.1 | S37: 402.5 | T37: 111.6 | U37: 125.2 | V37: 119.9 | W37: 125.9 | X37: 482.6 | Y37: 106.7 | Z37: 92.3 | AA37: 78 | AB37: 67.5 | AC37: 344.5 | AD37: 71.4 | AE37: 63.3 | AF37: 61.6 | AG37: 68.3 | AH37: 264.6 | AI37: 69.6 | AJ37: 84.3 | AK37: 79.4 | AL37: 71.4 | AM37: 304.8 | AN37: 75.2 | AO37: 152 | AP37: 148.1 | AQ37: 239.2 | AR37: 642.9 | AS37: 161.7 | AT37: 141.5 | AU37: 160.2 | AV37: 120.5 | AW37: 583.9 | AX37: 141.8 | AY37: 173.2 | AZ37: 195.2 | BA37: 207 | BB37: 717 | BC37: 189 | BD37: 233 | BE37: 233 | BF37: 209 | BG37: 864 | BH37: 227 | BI37: 271 | BJ37: 327 | BK37: 246 | BL37: 1071 | BM37: 368 | BN37: 391 | BO37: 390 | BP37: 273 | BQ37: 1422 | BR37: 420 | BS37: 415 | BT37: 414 | BU37: 318 | BV37: 1567 | BW37: 450 | BX37: 504 | BY37: =BY31-BY35 | BZ37: =BZ31-BZ35 | CA37: =SUM(BW37,BX37,BY37,BZ37) | CB37: =CB31-CB35 | CC37: =CC31-CC35 | CD37: =CD31-CD35 | CE37: =CE31-CE35 | CN37: 2028E | CO37: =CP37+$CO$35 | CP37: 0.05 | CQ37: =CP37+$CQ$35
B38: GAAP operating margin % | C38: =IF(AND(ISNUMBER(C37),ISNUMBER(C27)),IFERROR(C37/C27,""),"") | D38: =IF(AND(ISNUMBER(D37),ISNUMBER(D27)),IFERROR(D37/D27,""),"") | E38: =IF(AND(ISNUMBER(E37),ISNUMBER(E27)),IFERROR(E37/E27,""),"") | F38: =IF(AND(ISNUMBER(F37),ISNUMBER(F27)),IFERROR(F37/F27,""),"") | G38: =IF(AND(ISNUMBER(G37),ISNUMBER(G27)),IFERROR(G37/G27,""),"") | H38: =IF(AND(ISNUMBER(H37),ISNUMBER(H27)),IFERROR(H37/H27,""),"") | I38: =IF(AND(ISNUMBER(I37),ISNUMBER(I27)),IFERROR(I37/I27,""),"") | J38: =IF(AND(ISNUMBER(J37),ISNUMBER(J27)),IFERROR(J37/J27,""),"") | ... CE38: =IF(AND(ISNUMBER(CE37),ISNUMBER(CE27)),IFERROR(CE37/CE27,""),"") | CN38: 2029E | CO38: =CP38+$CO$35 | CP38: 0.04 | CQ38: =CP38+$CQ$35
CN39: 2030E | CO39: =CP39+$CO$35 | CP39: 0.04 | CQ39: =CP39+$CQ$35
B40: Transit segment (passenger-rail original equipment & aftermarket: brakes, doors, HVAC, couplers, pantographs) | CF40: TRANSIT — modelling logic | CN40: FRT_COMP (Freight Components sales y/y) | CO40: 0.02 | CP40: Δ → | CQ40: -0.03 | CR40: N.A. railcar build (soft 2025–26) and industrial (L&M, cooling); North American freight car cycle recovery from 2027.
B41: 12-month backlog — Transit (period end) | C41: 346.8 | D41: 378.7 | E41: 417 | F41: 425.5 | G41: 292.7 | H41: 481.7 | I41: 703 | M41: 650.7 | N41: 650.7 | R41: 659.2 | S41: 659.2 | W41: 621.7 | X41: 621.7 | AB41: 1565.5 | AC41: 1565.5 | AE41: 1729.2 | AF41: 1822.2 | AG41: 1891.1 | AH41: 1891.1 | AI41: 1976.3 | AJ41: 2044.4 | AK41: 1791.9 | AL41: 1954.6 | AM41: 1954.6 | AN41: 2048.7 | AO41: 2058.9 | AP41: 1813.1 | AQ41: 1692.8 | AR41: 1692.8 | AS41: 1801 | AT41: 1648.9 | AU41: 1557.6 | AV41: 1934.4 | AW41: 1934.4 | AX41: 1796 | AY41: 1724.8 | AZ41: 1647.5 | BA41: 1748 | BB41: 1748 | BC41: 1819 | BD41: 1745 | BE41: 1700 | BF41: 1859 | BG41: 1859 | BH41: 1947 | BI41: 1902 | BJ41: 1809 | BK41: 2007 | BL41: 2007 | BM41: 2043 | BN41: 1830 | BO41: 2035 | BP41: 2104 | BQ41: 2104 | BR41: 2127 | BS41: 2186 | BT41: 2182 | BU41: 2212 | BV41: 2212 | BW41: 2568 | BX41: 2502 | CF41: Company-reported 12-month backlog (subset of total backlog). Historical only; context for the Q3/Q4-26E growth inputs. | CN41: 2027E | CO41: =CP41+$CO$40 | CP41: 0.03 | CQ41: =CP41+$CQ$40
B42: Total (multi-year) backlog — Transit (period end) | C42: 779.4 | D42: 796.3 | E42: 865 | F42: 739.3 | G42: 695.1 | H42: 836.5 | I42: 1167.7 | M42: 1182.2 | N42: 1182.2 | R42: 1344.2 | S42: 1344.2 | W42: 1475 | X42: 1475 | AB42: 3405.6 | AC42: 3405.6 | AE42: 3843 | AF42: 3920.3 | AG42: 4050.5 | AH42: 4050.5 | AI42: 4265.6 | AJ42: 4012 | AK42: 3959.4 | AL42: 3816.9 | AM42: 3816.9 | AN42: 3795.2 | AO42: 3847.8 | AP42: 3672.9 | AQ42: 3486.4 | AR42: 3486.4 | AS42: 3431.3 | AT42: 3432.8 | AU42: 3541.9 | AV42: 3704.2 | AW42: 3704.2 | AX42: 3666 | AY42: 3693.3 | AZ42: 3632.5 | BA42: 3667 | BB42: 3667 | BC42: 3735 | BD42: 3548 | BE42: 3437 | BF42: 3800 | BG42: 3800 | BH42: 3972 | BI42: 4095 | BJ42: 3869 | BK42: 4168 | BL42: 4168 | BM42: 4185 | BN42: 4146 | BO42: 4478 | BP42: 4286 | BQ42: 4286 | BR42: 4451 | BS42: 4692 | BT42: 4670 | BU42: 4914 | BV42: 4914 | BW42: 5627 | BX42: 5600 | CN42: 2028E | CO42: =CP42+$CO$40 | CP42: 0.04 | CQ42: =CP42+$CQ$40
B43: 12-month backlog ÷ annualised sales (x) | C43: =IF(AND(ISNUMBER(C41),ISNUMBER(C51)),IFERROR(C41/(C51*1),""),"") | D43: =IF(AND(ISNUMBER(D41),ISNUMBER(D51)),IFERROR(D41/(D51*1),""),"") | E43: =IF(AND(ISNUMBER(E41),ISNUMBER(E51)),IFERROR(E41/(E51*1),""),"") | F43: =IF(AND(ISNUMBER(F41),ISNUMBER(F51)),IFERROR(F41/(F51*1),""),"") | G43: =IF(AND(ISNUMBER(G41),ISNUMBER(G51)),IFERROR(G41/(G51*1),""),"") | H43: =IF(AND(ISNUMBER(H41),ISNUMBER(H51)),IFERROR(H41/(H51*1),""),"") | I43: =IF(AND(ISNUMBER(I41),ISNUMBER(I51)),IFERROR(I41/(I51*1),""),"") | J43: =IF(AND(ISNUMBER(J41),ISNUMBER(J51)),IFERROR(J41/(J51*4),""),"") | K43: =IF(AND(ISNUMBER(K41),ISNUMBER(K51)),IFERROR(K41/(K51*4),""),"") | L43: =IF(AND(ISNUMBER(L41),ISNUMBER(L51)),IFERROR(L41/(L51*4),""),"") | M43: =IF(AND(ISNUMBER(M41),ISNUMBER(M51)),IFERROR(M41/(M51*4),""),"") | N43: =IF(AND(ISNUMBER(N41),ISNUMBER(N51)),IFERROR(N41/(N51*1),""),"") | O43: =IF(AND(ISNUMBER(O41),ISNUMBER(O51)),IFERROR(O41/(O51*4),""),"") | P43: =IF(AND(ISNUMBER(P41),ISNUMBER(P51)),IFERROR(P41/(P51*4),""),"") | Q43: =IF(AND(ISNUMBER(Q41),ISNUMBER(Q51)),IFERROR(Q41/(Q51*4),""),"") | R43: =IF(AND(ISNUMBER(R41),ISNUMBER(R51)),IFERROR(R41/(R51*4),""),"") | S43: =IF(AND(ISNUMBER(S41),ISNUMBER(S51)),IFERROR(S41/(S51*1),""),"") | T43: =IF(AND(ISNUMBER(T41),ISNUMBER(T51)),IFERROR(T41/(T51*4),""),"") | U43: =IF(AND(ISNUMBER(U41),ISNUMBER(U51)),IFERROR(U41/(U51*4),""),"") | V43: =IF(AND(ISNUMBER(V41),ISNUMBER(V51)),IFERROR(V41/(V51*4),""),"") | W43: =IF(AND(ISNUMBER(W41),ISNUMBER(W51)),IFERROR(W41/(W51*4),""),"") | X43: =IF(AND(ISNUMBER(X41),ISNUMBER(X51)),IFERROR(X41/(X51*1),""),"") | Y43: =IF(AND(ISNUMBER(Y41),ISNUMBER(Y51)),IFERROR(Y41/(Y51*4),""),"") | Z43: =IF(AND(ISNUMBER(Z41),ISNUMBER(Z51)),IFERROR(Z41/(Z51*4),""),"") | AA43: =IF(AND(ISNUMBER(AA41),ISNUMBER(AA51)),IFERROR(AA41/(AA51*4),""),"") | AB43: =IF(AND(ISNUMBER(AB41),ISNUMBER(AB51)),IFERROR(AB41/(AB51*4),""),"") | AC43: =IF(AND(ISNUMBER(AC41),ISNUMBER(AC51)),IFERROR(AC41/(AC51*1),""),"") | AD43: =IF(AND(ISNUMBER(AD41),ISNUMBER(AD51)),IFERROR(AD41/(AD51*4),""),"") | AE43: =IF(AND(ISNUMBER(AE41),ISNUMBER(AE51)),IFERROR(AE41/(AE51*4),""),"") | AF43: =IF(AND(ISNUMBER(AF41),ISNUMBER(AF51)),IFERROR(AF41/(AF51*4),""),"") | AG43: =IF(AND(ISNUMBER(AG41),ISNUMBER(AG51)),IFERROR(AG41/(AG51*4),""),"") | AH43: =IF(AND(ISNUMBER(AH41),ISNUMBER(AH51)),IFERROR(AH41/(AH51*1),""),"") | AI43: =IF(AND(ISNUMBER(AI41),ISNUMBER(AI51)),IFERROR(AI41/(AI51*4),""),"") | AJ43: =IF(AND(ISNUMBER(AJ41),ISNUMBER(AJ51)),IFERROR(AJ41/(AJ51*4),""),"") | AK43: =IF(AND(ISNUMBER(AK41),ISNUMBER(AK51)),IFERROR(AK41/(AK51*4),""),"") | AL43: =IF(AND(ISNUMBER(AL41),ISNUMBER(AL51)),IFERROR(AL41/(AL51*4),""),"") | AM43: =IF(AND(ISNUMBER(AM41),ISNUMBER(AM51)),IFERROR(AM41/(AM51*1),""),"") | AN43: =IF(AND(ISNUMBER(AN41),ISNUMBER(AN51)),IFERROR(AN41/(AN51*4),""),"") | AO43: =IF(AND(ISNUMBER(AO41),ISNUMBER(AO51)),IFERROR(AO41/(AO51*4),""),"") | AP43: =IF(AND(ISNUMBER(AP41),ISNUMBER(AP51)),IFERROR(AP41/(AP51*4),""),"") | AQ43: =IF(AND(ISNUMBER(AQ41),ISNUMBER(AQ51)),IFERROR(AQ41/(AQ51*4),""),"") | AR43: =IF(AND(ISNUMBER(AR41),ISNUMBER(AR51)),IFERROR(AR41/(AR51*1),""),"") | AS43: =IF(AND(ISNUMBER(AS41),ISNUMBER(AS51)),IFERROR(AS41/(AS51*4),""),"") | AT43: =IF(AND(ISNUMBER(AT41),ISNUMBER(AT51)),IFERROR(AT41/(AT51*4),""),"") | AU43: =IF(AND(ISNUMBER(AU41),ISNUMBER(AU51)),IFERROR(AU41/(AU51*4),""),"") | AV43: =IF(AND(ISNUMBER(AV41),ISNUMBER(AV51)),IFERROR(AV41/(AV51*4),""),"") | AW43: =IF(AND(ISNUMBER(AW41),ISNUMBER(AW51)),IFERROR(AW41/(AW51*1),""),"") | AX43: =IF(AND(ISNUMBER(AX41),ISNUMBER(AX51)),IFERROR(AX41/(AX51*4),""),"") | AY43: =IF(AND(ISNUMBER(AY41),ISNUMBER(AY51)),IFERROR(AY41/(AY51*4),""),"") | AZ43: =IF(AND(ISNUMBER(AZ41),ISNUMBER(AZ51)),IFERROR(AZ41/(AZ51*4),""),"") | BA43: =IF(AND(ISNUMBER(BA41),ISNUMBER(BA51)),IFERROR(BA41/(BA51*4),""),"") | BB43: =IF(AND(ISNUMBER(BB41),ISNUMBER(BB51)),IFERROR(BB41/(BB51*1),""),"") | BC43: =IF(AND(ISNUMBER(BC41),ISNUMBER(BC51)),IFERROR(BC41/(BC51*4),""),"") | BD43: =IF(AND(ISNUMBER(BD41),ISNUMBER(BD51)),IFERROR(BD41/(BD51*4),""),"") | BE43: =IF(AND(ISNUMBER(BE41),ISNUMBER(BE51)),IFERROR(BE41/(BE51*4),""),"") | BF43: =IF(AND(ISNUMBER(BF41),ISNUMBER(BF51)),IFERROR(BF41/(BF51*4),""),"") | BG43: =IF(AND(ISNUMBER(BG41),ISNUMBER(BG51)),IFERROR(BG41/(BG51*1),""),"") | BH43: =IF(AND(ISNUMBER(BH41),ISNUMBER(BH51)),IFERROR(BH41/(BH51*4),""),"") | BI43: =IF(AND(ISNUMBER(BI41),ISNUMBER(BI51)),IFERROR(BI41/(BI51*4),""),"") | BJ43: =IF(AND(ISNUMBER(BJ41),ISNUMBER(BJ51)),IFERROR(BJ41/(BJ51*4),""),"") | BK43: =IF(AND(ISNUMBER(BK41),ISNUMBER(BK51)),IFERROR(BK41/(BK51*4),""),"") | BL43: =IF(AND(ISNUMBER(BL41),ISNUMBER(BL51)),IFERROR(BL41/(BL51*1),""),"") | BM43: =IF(AND(ISNUMBER(BM41),ISNUMBER(BM51)),IFERROR(BM41/(BM51*4),""),"") | BN43: =IF(AND(ISNUMBER(BN41),ISNUMBER(BN51)),IFERROR(BN41/(BN51*4),""),"") | BO43: =IF(AND(ISNUMBER(BO41),ISNUMBER(BO51)),IFERROR(BO41/(BO51*4),""),"") | BP43: =IF(AND(ISNUMBER(BP41),ISNUMBER(BP51)),IFERROR(BP41/(BP51*4),""),"") | BQ43: =IF(AND(ISNUMBER(BQ41),ISNUMBER(BQ51)),IFERROR(BQ41/(BQ51*1),""),"") | BR43: =IF(AND(ISNUMBER(BR41),ISNUMBER(BR51)),IFERROR(BR41/(BR51*4),""),"") | BS43: =IF(AND(ISNUMBER(BS41),ISNUMBER(BS51)),IFERROR(BS41/(BS51*4),""),"") | BT43: =IF(AND(ISNUMBER(BT41),ISNUMBER(BT51)),IFERROR(BT41/(BT51*4),""),"") | BU43: =IF(AND(ISNUMBER(BU41),ISNUMBER(BU51)),IFERROR(BU41/(BU51*4),""),"") | BV43: =IF(AND(ISNUMBER(BV41),ISNUMBER(BV51)),IFERROR(BV41/(BV51*1),""),"") | BW43: =IF(AND(ISNUMBER(BW41),ISNUMBER(BW51)),IFERROR(BW41/(BW51*4),""),"") | BX43: =IF(AND(ISNUMBER(BX41),ISNUMBER(BX51)),IFERROR(BX41/(BX51*4),""),"") | CF43: 12-month backlog over quarterly sales × 4 (annual columns: full-year sales). >1.0x = next-twelve-month sales largely covered. | CN43: 2029E | CO43: =CP43+$CO$40 | CP43: 0.04 | CQ43: =CP43+$CQ$40
B44: Original Equipment Manufacturer (OE) — sales | AN44: 327.3 | AO44: 335.7 | AP44: 309.8 | AQ44: 313.8 | AR44: 1286.6 | AS44: 287 | AT44: 227.3 | AU44: 303.1 | AV44: 321.2 | AW44: 1138.6 | AX44: 286.8 | AY44: 320.4 | AZ44: 286.9 | BA44: 299 | BB44: 1193 | BC44: 292 | BD44: 259 | BE44: 264 | BF44: 280 | BG44: 1095 | BH44: 282 | BI44: 325 | BJ44: 302 | BK44: 326 | BL44: 1235 | BM44: 310 | BN44: 310 | BO44: 349 | BP44: 339 | BQ44: 1308 | BR44: 322 | BS44: 353 | BT44: 367 | BU44: 351 | BV44: 1393 | BW44: 381 | BX44: 411 | BY44: =BT44*(1+BY45) | BZ44: =BU44*(1+BZ45) | CA44: =SUM(BW44,BX44,BY44,BZ44) | CB44: =CA44*(1+CB45) | CC44: =CB44*(1+CC45) | CD44: =CC44*(1+CD45) | CE44: =CD44*(1+CE45) | CF44: Product-line sales as published (from 2019, GE Transportation merger). Q3/Q4-26E: prior-year quarter × (1 + growth). 2027E+: prior year × (1 + scenario lever). | CH44: =IFERROR((CE44/BV44)^(1/5)-1,"n/m") | CI44: =IFERROR((BV44/AW44)^(1/5)-1,"n/m") | CJ44: =IFERROR((BV44/X44)^(1/10)-1,"n/m") | CK44: =IFERROR((BV44/C44)^(1/19)-1,"n/m") | CN44: 2030E | CO44: =CP44+$CO$40 | CP44: 0.04 | CQ44: =CP44+$CQ$40
B45: y/y % | D45: =IF(AND(ISNUMBER(D44),ISNUMBER(C44)),IFERROR(D44/C44-1,""),"") | E45: =IF(AND(ISNUMBER(E44),ISNUMBER(D44)),IFERROR(E44/D44-1,""),"") | F45: =IF(AND(ISNUMBER(F44),ISNUMBER(E44)),IFERROR(F44/E44-1,""),"") | G45: =IF(AND(ISNUMBER(G44),ISNUMBER(F44)),IFERROR(G44/F44-1,""),"") | H45: =IF(AND(ISNUMBER(H44),ISNUMBER(G44)),IFERROR(H44/G44-1,""),"") | I45: =IF(AND(ISNUMBER(I44),ISNUMBER(H44)),IFERROR(I44/H44-1,""),"") | N45: =IF(AND(ISNUMBER(N44),ISNUMBER(I44)),IFERROR(N44/I44-1,""),"") | O45: =IF(AND(ISNUMBER(O44),ISNUMBER(J44)),IFERROR(O44/J44-1,""),"") | P45: =IF(AND(ISNUMBER(P44),ISNUMBER(K44)),IFERROR(P44/K44-1,""),"") | Q45: =IF(AND(ISNUMBER(Q44),ISNUMBER(L44)),IFERROR(Q44/L44-1,""),"") | R45: =IF(AND(ISNUMBER(R44),ISNUMBER(M44)),IFERROR(R44/M44-1,""),"") | S45: =IF(AND(ISNUMBER(S44),ISNUMBER(N44)),IFERROR(S44/N44-1,""),"") | T45: =IF(AND(ISNUMBER(T44),ISNUMBER(O44)),IFERROR(T44/O44-1,""),"") | U45: =IF(AND(ISNUMBER(U44),ISNUMBER(P44)),IFERROR(U44/P44-1,""),"") | ... BX45: =IF(AND(ISNUMBER(BX44),ISNUMBER(BS44)),IFERROR(BX44/BS44-1,""),"") | BY45: =BY46+$BY$109 | BZ45: =BZ46+$BY$109 | CA45: =IF(AND(ISNUMBER(CA44),ISNUMBER(BV44)),IFERROR(CA44/BV44-1,""),"") | CB45: =CHOOSE(MATCH($CF$2,{"Bull","Base","Bear"},0),$CO$51,$CP$51,$CQ$51) | CC45: =CHOOSE(MATCH($CF$2,{"Bull","Base","Bear"},0),$CO$52,$CP$52,$CQ$52) | CD45: =CHOOSE(MATCH($CF$2,{"Bull","Base","Bear"},0),$CO$53,$CP$53,$CQ$53) | CE45: =CHOOSE(MATCH($CF$2,{"Bull","Base","Bear"},0),$CO$54,$CP$54,$CQ$54) | CF45: Q3/Q4-26E: growth input (row below) + revenue-outlook calibration Δ (Group block). 2027E–2030E: scenario lever (Bull/Base/Bear table →). | CN45: FRT_DIG (Freight Digital Intelligence sales y/y) | CO45: 0.03 | CP45: Δ → | CQ45: -0.03 | CR45: PTC / train control, signalling (Frauscher axle counters), inspection (Inspection Technologies), software; organic high-single digit.
B46: Q3/Q4-26E growth input before revenue calibration | BY46: 0.145 | BZ46: 0.15 | CF46: Input = 5% organic + ~half of Dellner (closed 10-Feb-26; $69m of sales in Q2/26) ≈ $35m per quarter. | CN46: 2027E | CO46: =CP46+$CO$45 | CP46: 0.08 | CQ46: =CP46+$CQ$45
B47: Aftermarket — sales | AN47: 350.8 | AO47: 374.3 | AP47: 359.4 | AQ47: 387.5 | AR47: 1472 | AS47: 341.9 | AT47: 305.4 | AU47: 324.7 | AV47: 363.2 | AW47: 1335.2 | AX47: 360.1 | AY47: 356 | AZ47: 325 | BA47: 349 | BB47: 1390 | BC47: 313 | BD47: 299 | BE47: 286 | BF47: 357 | BG47: 1255 | BH47: 346 | BI47: 374 | BJ47: 358 | BK47: 402 | BL47: 1480 | BM47: 363 | BN47: 414 | BO47: 384 | BP47: 450 | BQ47: 1611 | BR47: 387 | BS47: 434 | BT47: 426 | BU47: 491 | BV47: 1738 | BW47: 454 | BX47: 525 | BY47: =BT47*(1+BY48) | BZ47: =BU47*(1+BZ48) | CA47: =SUM(BW47,BX47,BY47,BZ47) | CB47: =CA47*(1+CB48) | CC47: =CB47*(1+CC48) | CD47: =CC47*(1+CD48) | CE47: =CD47*(1+CE48) | CF47: Product-line sales as published (from 2019, GE Transportation merger). Q3/Q4-26E: prior-year quarter × (1 + growth). 2027E+: prior year × (1 + scenario lever). | CH47: =IFERROR((CE47/BV47)^(1/5)-1,"n/m") | CI47: =IFERROR((BV47/AW47)^(1/5)-1,"n/m") | CJ47: =IFERROR((BV47/X47)^(1/10)-1,"n/m") | CK47: =IFERROR((BV47/C47)^(1/19)-1,"n/m") | CN47: 2028E | CO47: =CP47+$CO$45 | CP47: 0.08 | CQ47: =CP47+$CQ$45
B48: y/y % | D48: =IF(AND(ISNUMBER(D47),ISNUMBER(C47)),IFERROR(D47/C47-1,""),"") | E48: =IF(AND(ISNUMBER(E47),ISNUMBER(D47)),IFERROR(E47/D47-1,""),"") | F48: =IF(AND(ISNUMBER(F47),ISNUMBER(E47)),IFERROR(F47/E47-1,""),"") | G48: =IF(AND(ISNUMBER(G47),ISNUMBER(F47)),IFERROR(G47/F47-1,""),"") | H48: =IF(AND(ISNUMBER(H47),ISNUMBER(G47)),IFERROR(H47/G47-1,""),"") | I48: =IF(AND(ISNUMBER(I47),ISNUMBER(H47)),IFERROR(I47/H47-1,""),"") | N48: =IF(AND(ISNUMBER(N47),ISNUMBER(I47)),IFERROR(N47/I47-1,""),"") | O48: =IF(AND(ISNUMBER(O47),ISNUMBER(J47)),IFERROR(O47/J47-1,""),"") | P48: =IF(AND(ISNUMBER(P47),ISNUMBER(K47)),IFERROR(P47/K47-1,""),"") | Q48: =IF(AND(ISNUMBER(Q47),ISNUMBER(L47)),IFERROR(Q47/L47-1,""),"") | R48: =IF(AND(ISNUMBER(R47),ISNUMBER(M47)),IFERROR(R47/M47-1,""),"") | S48: =IF(AND(ISNUMBER(S47),ISNUMBER(N47)),IFERROR(S47/N47-1,""),"") | T48: =IF(AND(ISNUMBER(T47),ISNUMBER(O47)),IFERROR(T47/O47-1,""),"") | U48: =IF(AND(ISNUMBER(U47),ISNUMBER(P47)),IFERROR(U47/P47-1,""),"") | ... BX48: =IF(AND(ISNUMBER(BX47),ISNUMBER(BS47)),IFERROR(BX47/BS47-1,""),"") | BY48: =BY49+$BY$109 | BZ48: =BZ49+$BY$109 | CA48: =IF(AND(ISNUMBER(CA47),ISNUMBER(BV47)),IFERROR(CA47/BV47-1,""),"") | CB48: =CHOOSE(MATCH($CF$2,{"Bull","Base","Bear"},0),$CO$56,$CP$56,$CQ$56) | CC48: =CHOOSE(MATCH($CF$2,{"Bull","Base","Bear"},0),$CO$57,$CP$57,$CQ$57) | CD48: =CHOOSE(MATCH($CF$2,{"Bull","Base","Bear"},0),$CO$58,$CP$58,$CQ$58) | CE48: =CHOOSE(MATCH($CF$2,{"Bull","Base","Bear"},0),$CO$59,$CP$59,$CQ$59) | CF48: Q3/Q4-26E: growth input (row below) + revenue-outlook calibration Δ (Group block). 2027E–2030E: scenario lever (Bull/Base/Bear table →). | CN48: 2029E | CO48: =CP48+$CO$45 | CP48: 0.07 | CQ48: =CP48+$CQ$45
B49: Q3/Q4-26E growth input before revenue calibration | BY49: 0.142 | BZ49: 0.131 | CF49: Input = 6% organic + ~half of Dellner ≈ $35m per quarter. | CN49: 2030E | CO49: =CP49+$CO$45 | CP49: 0.07 | CQ49: =CP49+$CQ$45
B50: Transit sales not split by product line (pre-2019 disclosure) | C50: =IF(ISNUMBER(C51),C51-(N(C44)+N(C47)),"") | D50: =IF(ISNUMBER(D51),D51-(N(D44)+N(D47)),"") | E50: =IF(ISNUMBER(E51),E51-(N(E44)+N(E47)),"") | F50: =IF(ISNUMBER(F51),F51-(N(F44)+N(F47)),"") | G50: =IF(ISNUMBER(G51),G51-(N(G44)+N(G47)),"") | H50: =IF(ISNUMBER(H51),H51-(N(H44)+N(H47)),"") | I50: =IF(ISNUMBER(I51),I51-(N(I44)+N(I47)),"") | J50: =IF(ISNUMBER(J51),J51-(N(J44)+N(J47)),"") | ... BX50: =IF(ISNUMBER(BX51),BX51-(N(BX44)+N(BX47)),"") | CF50: Historical segment sales less the product-line split (product lines are published from 2019; earlier years show the segment total here). | CN50: TRN_OE (Transit original equipment sales y/y) | CO50: 0.025 | CP50: Δ → | CQ50: -0.03 | CR50: Car-builder backlogs (Europe, India); Dellner couplers anniversary in Feb-27.
B51: Transit segment net sales | C51: 378.3 | D51: 625.9 | E51: 801.2 | F51: 813.2 | G51: 722.5 | H51: 757.6 | I51: 889.2 | J51: 309.6 | K51: 283.1 | L51: 290.9 | M51: 292.4 | N51: 1168.3 | O51: 309.7 | P51: 319.6 | Q51: 343.9 | R51: 339.7 | S51: 1313 | T51: 306.7 | U51: 312.4 | V51: 302.4 | W51: 331.9 | X51: 1253.3 | Y51: 329.4 | Z51: 326.5 | AA51: 313.6 | AB51: 418.6 | AC51: 1388.1 | AD51: 568.1 | AE51: 587.4 | AF51: 617.7 | AG51: 711.9 | AH51: 2485.2 | AI51: 676.6 | AJ51: 699.4 | AK51: 686.2 | AL51: 737 | AM51: 2799.3 | AN51: 717.2 | AO51: 742.3 | AP51: 706 | AQ51: 701.3 | AR51: 2758.6 | AS51: 628.9 | AT51: 532.7 | AU51: 627.8 | AV51: 684.4 | AW51: 2473.8 | AX51: 646.9 | AY51: 676.4 | AZ51: 611.9 | BA51: 648 | BB51: 2583 | BC51: 605 | BD51: 558 | BE51: 550 | BF51: 637 | BG51: 2350 | BH51: 628 | BI51: 699 | BJ51: 660 | BK51: 728 | BL51: 2715 | BM51: 673 | BN51: 724 | BO51: 733 | BP51: 789 | BQ51: 2919 | BR51: 709 | BS51: 787 | BT51: 793 | BU51: 842 | BV51: 3131 | BW51: 835 | BX51: 936 | BY51: =N(BY44)+N(BY47) | BZ51: =N(BZ44)+N(BZ47) | CA51: =SUM(BW51,BX51,BY51,BZ51) | CB51: =N(CB44)+N(CB47) | CC51: =N(CC44)+N(CC47) | CD51: =N(CD44)+N(CD47) | CE51: =N(CE44)+N(CE47) | CF51: Historical = segment net sales as originally reported. Forecast = Σ product lines. | CH51: =IFERROR((CE51/BV51)^(1/5)-1,"n/m") | CI51: =IFERROR((BV51/AW51)^(1/5)-1,"n/m") | CJ51: =IFERROR((BV51/X51)^(1/10)-1,"n/m") | CK51: =IFERROR((BV51/C51)^(1/19)-1,"n/m") | CN51: 2027E | CO51: =CP51+$CO$50 | CP51: 0.05 | CQ51: =CP51+$CQ$50
B52: Segment net sales y/y % | D52: =IF(AND(ISNUMBER(D51),ISNUMBER(C51)),IFERROR(D51/C51-1,""),"") | E52: =IF(AND(ISNUMBER(E51),ISNUMBER(D51)),IFERROR(E51/D51-1,""),"") | F52: =IF(AND(ISNUMBER(F51),ISNUMBER(E51)),IFERROR(F51/E51-1,""),"") | G52: =IF(AND(ISNUMBER(G51),ISNUMBER(F51)),IFERROR(G51/F51-1,""),"") | H52: =IF(AND(ISNUMBER(H51),ISNUMBER(G51)),IFERROR(H51/G51-1,""),"") | I52: =IF(AND(ISNUMBER(I51),ISNUMBER(H51)),IFERROR(I51/H51-1,""),"") | N52: =IF(AND(ISNUMBER(N51),ISNUMBER(I51)),IFERROR(N51/I51-1,""),"") | O52: =IF(AND(ISNUMBER(O51),ISNUMBER(J51)),IFERROR(O51/J51-1,""),"") | P52: =IF(AND(ISNUMBER(P51),ISNUMBER(K51)),IFERROR(P51/K51-1,""),"") | Q52: =IF(AND(ISNUMBER(Q51),ISNUMBER(L51)),IFERROR(Q51/L51-1,""),"") | R52: =IF(AND(ISNUMBER(R51),ISNUMBER(M51)),IFERROR(R51/M51-1,""),"") | S52: =IF(AND(ISNUMBER(S51),ISNUMBER(N51)),IFERROR(S51/N51-1,""),"") | T52: =IF(AND(ISNUMBER(T51),ISNUMBER(O51)),IFERROR(T51/O51-1,""),"") | U52: =IF(AND(ISNUMBER(U51),ISNUMBER(P51)),IFERROR(U51/P51-1,""),"") | ... CA52: =IF(AND(ISNUMBER(CA51),ISNUMBER(BV51)),IFERROR(CA51/BV51-1,""),"") | CB52: =IF(AND(ISNUMBER(CB51),ISNUMBER(CA51)),IFERROR(CB51/CA51-1,""),"") | CC52: =IF(AND(ISNUMBER(CC51),ISNUMBER(CB51)),IFERROR(CC51/CB51-1,""),"") | CD52: =IF(AND(ISNUMBER(CD51),ISNUMBER(CC51)),IFERROR(CD51/CC51-1,""),"") | CE52: =IF(AND(ISNUMBER(CE51),ISNUMBER(CD51)),IFERROR(CE51/CD51-1,""),"") | CN52: 2028E | CO52: =CP52+$CO$50 | CP52: 0.05 | CQ52: =CP52+$CQ$50
B53: Segment gross profit (GAAP; published from 2019) | AQ53: 160.7 | AR53: 696.6 | AX53: 178 | AY53: 166 | AZ53: 159 | BA53: 198 | BB53: 702 | BC53: 171 | BD53: 152 | BE53: 151 | BF53: 170 | BG53: 644 | BH53: 185 | BI53: 182 | BJ53: 181 | BK53: 206 | BL53: 754 | BM53: 190 | BN53: 205 | BO53: 207 | BP53: 241 | BQ53: 843 | BR53: 215 | BS53: 241 | BT53: 252 | BU53: 263 | BV53: 971 | BW53: 273 | BX53: 307 | CN53: 2029E | CO53: =CP53+$CO$50 | CP53: 0.04 | CQ53: =CP53+$CQ$50
B54: Segment gross margin % | C54: =IF(AND(ISNUMBER(C53),ISNUMBER(C51)),IFERROR(C53/C51,""),"") | D54: =IF(AND(ISNUMBER(D53),ISNUMBER(D51)),IFERROR(D53/D51,""),"") | E54: =IF(AND(ISNUMBER(E53),ISNUMBER(E51)),IFERROR(E53/E51,""),"") | F54: =IF(AND(ISNUMBER(F53),ISNUMBER(F51)),IFERROR(F53/F51,""),"") | G54: =IF(AND(ISNUMBER(G53),ISNUMBER(G51)),IFERROR(G53/G51,""),"") | H54: =IF(AND(ISNUMBER(H53),ISNUMBER(H51)),IFERROR(H53/H51,""),"") | I54: =IF(AND(ISNUMBER(I53),ISNUMBER(I51)),IFERROR(I53/I51,""),"") | J54: =IF(AND(ISNUMBER(J53),ISNUMBER(J51)),IFERROR(J53/J51,""),"") | ... BX54: =IF(AND(ISNUMBER(BX53),ISNUMBER(BX51)),IFERROR(BX53/BX51,""),"") | CH54: =IFERROR(AVERAGE(CA54,CB54,CC54,CD54,CE54),"n/m") | CI54: =IFERROR(AVERAGE(BB54,BG54,BL54,BQ54,BV54),"n/m") | CJ54: =IFERROR(AVERAGE(AC54,AH54,AM54,AR54,AW54,BB54,BG54,BL54,BQ54,BV54),"n/m") | CK54: =IFERROR(AVERAGE(C54,D54,E54,F54,G54,H54,I54,N54,S54,X54,AC54,AH54,AM54,AR54,AW54,BB54,BG54,BL54,BQ54,BV54),"n/m") | CN54: 2030E | CO54: =CP54+$CO$50 | CP54: 0.04 | CQ54: =CP54+$CQ$50
B55: Transit adjusted income from operations (company definition) | AL55: 74 | AM55: 269 | AS55: 74.6 | AT55: 51.3 | AU55: 75.1 | AV55: 77.1 | AW55: 278.1 | AX55: 78.9 | AY55: 73.2 | AZ55: 76.5 | BA55: 88 | BB55: 317 | BC55: 74 | BD55: 58 | BE55: 60 | BF55: 95 | BG55: 287 | BH55: 83 | BI55: 76 | BJ55: 83 | BK55: 108 | BL55: 348 | BM55: 86 | BN55: 91 | BO55: 93 | BP55: 130 | BQ55: 400 | BR55: 103 | BS55: 120 | BT55: 123 | BU55: 118 | BV55: 464 | BW55: 138 | BX55: 166 | BY55: =BY51*BY56 | BZ55: =BZ51*BZ56 | CA55: =SUM(BW55,BX55,BY55,BZ55) | CB55: =CB51*CB56 | CC55: =CC51*CC56 | CD55: =CD51*CD56 | CE55: =CE51*CE56 | CF55: Segment adjusted operating income as published (segment Reported→Adjusted tables). Forecast = segment sales × adjusted operating margin. | CH55: =IFERROR((CE55/BV55)^(1/5)-1,"n/m") | CI55: =IFERROR((BV55/AW55)^(1/5)-1,"n/m") | CJ55: =IFERROR((BV55/X55)^(1/10)-1,"n/m") | CK55: =IFERROR((BV55/C55)^(1/19)-1,"n/m") | CN55: TRN_AM (Transit aftermarket sales y/y) | CO55: 0.02 | CP55: Δ → | CQ55: -0.02 | CR55: Installed-base aftermarket (~60% of Transit); pricing.
B56: Adjusted operating margin % | C56: =IF(AND(ISNUMBER(C55),ISNUMBER(C51)),IFERROR(C55/C51,""),"") | D56: =IF(AND(ISNUMBER(D55),ISNUMBER(D51)),IFERROR(D55/D51,""),"") | E56: =IF(AND(ISNUMBER(E55),ISNUMBER(E51)),IFERROR(E55/E51,""),"") | F56: =IF(AND(ISNUMBER(F55),ISNUMBER(F51)),IFERROR(F55/F51,""),"") | G56: =IF(AND(ISNUMBER(G55),ISNUMBER(G51)),IFERROR(G55/G51,""),"") | H56: =IF(AND(ISNUMBER(H55),ISNUMBER(H51)),IFERROR(H55/H51,""),"") | I56: =IF(AND(ISNUMBER(I55),ISNUMBER(I51)),IFERROR(I55/I51,""),"") | J56: =IF(AND(ISNUMBER(J55),ISNUMBER(J51)),IFERROR(J55/J51,""),"") | ... BX56: =IF(AND(ISNUMBER(BX55),ISNUMBER(BX51)),IFERROR(BX55/BX51,""),"") | BY56: =BY57+$BY$115 | BZ56: =BZ57+$BY$115 | CA56: =IF(AND(ISNUMBER(CA55),ISNUMBER(CA51)),IFERROR(CA55/CA51,""),"") | CB56: =CHOOSE(MATCH($CF$2,{"Bull","Base","Bear"},0),$CO$66,$CP$66,$CQ$66) | CC56: =CHOOSE(MATCH($CF$2,{"Bull","Base","Bear"},0),$CO$67,$CP$67,$CQ$67) | CD56: =CHOOSE(MATCH($CF$2,{"Bull","Base","Bear"},0),$CO$68,$CP$68,$CQ$68) | CE56: =CHOOSE(MATCH($CF$2,{"Bull","Base","Bear"},0),$CO$69,$CP$69,$CQ$69) | CF56: Q3/Q4-26E: margin before calibration + adjusted-EPS-outlook calibration Δ (Group block). 2027E–2030E: scenario lever. | CH56: =IFERROR(AVERAGE(CA56,CB56,CC56,CD56,CE56),"n/m") | CI56: =IFERROR(AVERAGE(BB56,BG56,BL56,BQ56,BV56),"n/m") | CJ56: =IFERROR(AVERAGE(AC56,AH56,AM56,AR56,AW56,BB56,BG56,BL56,BQ56,BV56),"n/m") | CK56: =IFERROR(AVERAGE(C56,D56,E56,F56,G56,H56,I56,N56,S56,X56,AC56,AH56,AM56,AR56,AW56,BB56,BG56,BL56,BQ56,BV56),"n/m") | CN56: 2027E | CO56: =CP56+$CO$55 | CP56: 0.06 | CQ56: =CP56+$CQ$55
B57: Adjusted operating margin before outlook calibration % (Q3/Q4-26E helper) | BY57: =BT56+((BW55+BX55)/(BW51+BX51)-(BR55+BS55)/(BR51+BS51)) | BZ57: =BU56+((BW55+BX55)/(BW51+BX51)-(BR55+BS55)/(BR51+BS51)) | CF57: Prior-year quarter margin + (1H/26 − 1H/25 adjusted margin drift). | CN57: 2028E | CO57: =CP57+$CO$55 | CP57: 0.05 | CQ57: =CP57+$CQ$55
B58: Incremental adjusted operating margin (Δ adj. op. income / Δ sales) | D58: =IFERROR((D55-C55)/(D51-C51),"") | E58: =IFERROR((E55-D55)/(E51-D51),"") | F58: =IFERROR((F55-E55)/(F51-E51),"") | G58: =IFERROR((G55-F55)/(G51-F51),"") | H58: =IFERROR((H55-G55)/(H51-G51),"") | I58: =IFERROR((I55-H55)/(I51-H51),"") | N58: =IFERROR((N55-I55)/(N51-I51),"") | O58: =IFERROR((O55-J55)/(O51-J51),"") | P58: =IFERROR((P55-K55)/(P51-K51),"") | Q58: =IFERROR((Q55-L55)/(Q51-L51),"") | R58: =IFERROR((R55-M55)/(R51-M51),"") | S58: =IFERROR((S55-N55)/(S51-N51),"") | T58: =IFERROR((T55-O55)/(T51-O51),"") | U58: =IFERROR((U55-P55)/(U51-P51),"") | ... CA58: =IFERROR((CA55-BV55)/(CA51-BV51),"") | CB58: =IFERROR((CB55-CA55)/(CB51-CA51),"") | CC58: =IFERROR((CC55-CB55)/(CC51-CB51),"") | CD58: =IFERROR((CD55-CC55)/(CD51-CC51),"") | CE58: =IFERROR((CE55-CD55)/(CE51-CD51),"") | CN58: 2029E | CO58: =CP58+$CO$55 | CP58: 0.05 | CQ58: =CP58+$CQ$55
B59: Adjusting items in segment (amortization, restructuring, purchase accounting, transaction) | C59: =IF(AND(ISNUMBER(C55),ISNUMBER(C61)),C55-C61,"") | D59: =IF(AND(ISNUMBER(D55),ISNUMBER(D61)),D55-D61,"") | E59: =IF(AND(ISNUMBER(E55),ISNUMBER(E61)),E55-E61,"") | F59: =IF(AND(ISNUMBER(F55),ISNUMBER(F61)),F55-F61,"") | G59: =IF(AND(ISNUMBER(G55),ISNUMBER(G61)),G55-G61,"") | H59: =IF(AND(ISNUMBER(H55),ISNUMBER(H61)),H55-H61,"") | I59: =IF(AND(ISNUMBER(I55),ISNUMBER(I61)),I55-I61,"") | J59: =IF(AND(ISNUMBER(J55),ISNUMBER(J61)),J55-J61,"") | ... BX59: =IF(AND(ISNUMBER(BX55),ISNUMBER(BX61)),BX55-BX61,"") | BY59: =BY213*BY60 | BZ59: =BZ213*BZ60 | CA59: =SUM(BW59,BX59,BY59,BZ59) | CB59: =CB213*CB60 | CC59: =CC213*CC60 | CD59: =CD213*CD60 | CE59: =CE213*CE60 | CF59: Historical = adjusted − GAAP segment operating income. Forecast = consolidated operating-level adjusting items × segment share. | CN59: 2030E | CO59: =CP59+$CO$55 | CP59: 0.05 | CQ59: =CP59+$CQ$55
B60: Segment share of consolidated operating-level adjusting items % | C60: =IF(ISNUMBER(C59),IFERROR(C59/C213,""),"") | D60: =IF(ISNUMBER(D59),IFERROR(D59/D213,""),"") | E60: =IF(ISNUMBER(E59),IFERROR(E59/E213,""),"") | F60: =IF(ISNUMBER(F59),IFERROR(F59/F213,""),"") | G60: =IF(ISNUMBER(G59),IFERROR(G59/G213,""),"") | H60: =IF(ISNUMBER(H59),IFERROR(H59/H213,""),"") | I60: =IF(ISNUMBER(I59),IFERROR(I59/I213,""),"") | J60: =IF(ISNUMBER(J59),IFERROR(J59/J213,""),"") | ... BX60: =IF(ISNUMBER(BX59),IFERROR(BX59/BX213,""),"") | BY60: =IFERROR((BW59+BX59)/(BW213+BX213),0) | BZ60: =IFERROR((BW59+BX59)/(BW213+BX213),0) | CA60: =IFERROR(CA59/CA213,"") | CB60: =$BZ$60 | CC60: =$BZ$60 | CD60: =$BZ$60 | CE60: =$BZ$60 | CF60: Forecast at the 1H/26 share (Freight carries most acquired-intangible amortization). | CN60: FRT_OPM (Freight adjusted operating margin) | CO60: 0.01 | CP60: Δ → | CQ60: -0.015 | CR60: FY25 24.3%; 1H/26 25.9%. Five-year outlook (2025–29): 350+ bps consolidated adjusted margin expansion.
B61: Transit income from operations (GAAP) | C61: 32.5 | D61: 69 | E61: 98.8 | F61: 128.8 | G61: 95.6 | H61: 83.8 | I61: 93.4 | J61: 43.6 | K61: 35.9 | L61: 36.3 | M61: 32.8 | N61: 143.6 | O61: 34.5 | P61: 36.8 | Q61: 40.7 | R61: 35.8 | S61: 147.8 | T61: 41.4 | U61: 37.5 | V61: 38.8 | W61: 33.3 | X61: 151 | Y61: 45 | Z61: 52.1 | AA61: 51.2 | AB61: 23.1 | AC61: 171.4 | AD61: 49.1 | AE61: 59.2 | AF61: 47.5 | AG61: 32.6 | AH61: 188.5 | AI61: 68.1 | AJ61: 58 | AK61: 60.7 | AL61: 41.1 | AM61: 227.9 | AN61: 58.9 | AO61: 71.2 | AP61: 55.8 | AQ61: 39 | AR61: 214.4 | AS61: 68.6 | AT61: 40.2 | AU61: 64.1 | AV61: 56.8 | AW61: 229.7 | AX61: 70.1 | AY61: 45.3 | AZ61: 43.9 | BA61: 79 | BB61: 238 | BC61: 65 | BD61: 50 | BE61: 53 | BF61: 63 | BG61: 231 | BH61: 69 | BI61: 66 | BJ61: 68 | BK61: 86 | BL61: 289 | BM61: 74 | BN61: 82 | BO61: 79 | BP61: 103 | BQ61: 338 | BR61: 90 | BS61: 109 | BT61: 115 | BU61: 108 | BV61: 422 | BW61: 121 | BX61: 146 | BY61: =BY55-BY59 | BZ61: =BZ55-BZ59 | CA61: =SUM(BW61,BX61,BY61,BZ61) | CB61: =CB55-CB59 | CC61: =CC55-CC59 | CD61: =CD55-CD59 | CE61: =CE55-CE59 | CN61: 2027E | CO61: =CP61+$CO$60 | CP61: 0.265 | CQ61: =CP61+$CQ$60
B62: GAAP operating margin % | C62: =IF(AND(ISNUMBER(C61),ISNUMBER(C51)),IFERROR(C61/C51,""),"") | D62: =IF(AND(ISNUMBER(D61),ISNUMBER(D51)),IFERROR(D61/D51,""),"") | E62: =IF(AND(ISNUMBER(E61),ISNUMBER(E51)),IFERROR(E61/E51,""),"") | F62: =IF(AND(ISNUMBER(F61),ISNUMBER(F51)),IFERROR(F61/F51,""),"") | G62: =IF(AND(ISNUMBER(G61),ISNUMBER(G51)),IFERROR(G61/G51,""),"") | H62: =IF(AND(ISNUMBER(H61),ISNUMBER(H51)),IFERROR(H61/H51,""),"") | I62: =IF(AND(ISNUMBER(I61),ISNUMBER(I51)),IFERROR(I61/I51,""),"") | J62: =IF(AND(ISNUMBER(J61),ISNUMBER(J51)),IFERROR(J61/J51,""),"") | ... CE62: =IF(AND(ISNUMBER(CE61),ISNUMBER(CE51)),IFERROR(CE61/CE51,""),"") | CN62: 2028E | CO62: =CP62+$CO$60 | CP62: 0.27 | CQ62: =CP62+$CQ$60
CN63: 2029E | CO63: =CP63+$CO$60 | CP63: 0.275 | CQ63: =CP63+$CQ$60
B64: 2025–26 acquired businesses (Frauscher · Inspection Technologies · Dellner Couplers · 2026 bolt-ons) & sales-change bridge | CF64: ACQUIRED BUSINESSES — sales-change bridge as published (acquisitions / portfolio optimization / FX / organic); purchase-price allocations in the BS schedules | CN64: 2030E | CO64: =CP64+$CO$60 | CP64: 0.28 | CQ64: =CP64+$CQ$60
B65: Sales change from acquisitions (y/y, as published) | F65: 114.9 | G65: 86.1 | H65: 128.3 | I65: 138.3 | J65: 41.4 | K65: 49 | L65: 34.8 | N65: 157.9 | O65: 20.7 | P65: 39.6 | Q65: 86.6 | S65: 229.4 | T65: 78 | U65: 82.5 | V65: 42.7 | X65: 262.8 | Y65: 20.2 | Z65: 16.8 | AA65: 15.3 | AC65: 189.2 | AD65: 307.2 | AE65: 326.7 | AF65: 330.6 | AG65: 219 | AH65: 1183.2 | AI65: 35 | AJ65: 39.2 | AK65: 32.2 | AL65: 28 | AM65: 134.7 | AN65: 509.7 | AO65: 1125 | AP65: 955.9 | AQ65: 1271.5 | AR65: 3863.5 | AS65: 509.4 | AT65: 18.5 | AU65: 8.9 | AV65: 10 | AW65: 546.4 | AY65: 38 | AZ65: 38 | BA65: 61 | BB65: 138 | BC65: 40 | BD65: 6 | BE65: 19 | BF65: 22 | BG65: 87 | BH65: 21 | BI65: 11 | BJ65: 45 | BK65: 32 | BL65: 109 | BM65: 36 | BN65: 34 | BO65: 2 | BP65: 9 | BQ65: 81 | BR65: 23 | BS65: 27 | BT65: 134 | BU65: 171 | BV65: 355 | BW65: 225 | BX65: 232 | BY65: 130 | BZ65: 110 | CA65: =SUM(BW65,BX65,BY65,BZ65) | CF65: Q3/Q4-26E inputs: Frauscher (~$60m / ~$40m) + Dellner (~$70m per quarter) not in the prior-year quarter (analyst estimate; Q2/26 published $232m incl. Inspection Technologies). | CN65: TRN_OPM (Transit adjusted operating margin) | CO65: 0.01 | CP65: Δ → | CQ65: -0.015 | CR65: FY25 14.8%; 1H/26 17.2% (Dellner mix, Integration 3.0, low-margin pruning).
B66: of which: Freight | F66: 103.1 | G66: 81.8 | H66: 47.6 | I66: 65.7 | J66: 2.1 | K66: 15 | L66: 14.8 | N66: 72.4 | O66: 20.7 | P66: 24.1 | Q66: 29.4 | S66: 93.3 | T66: 18.1 | U66: 40.3 | V66: 34 | X66: 145.5 | Y66: 14.5 | Z66: 10.5 | AA66: 13.2 | AC66: 55.1 | AD66: 36.9 | AE66: 43.7 | AF66: 40.6 | AG66: 27 | AH66: 148.1 | AI66: 22.6 | AJ66: 11.1 | AK66: 11 | AL66: 6 | AM66: 50.9 | AN66: 495 | AO66: 1122.1 | AP66: 953.9 | AQ66: 1269.5 | AR66: 3840.7 | AS66: 506.4 | AT66: 18.5 | AU66: 8.9 | AV66: 10 | AW66: 543.4 | AY66: 38 | AZ66: 38 | BA66: 61 | BB66: 138 | BC66: 39 | BD66: 5 | BE66: 18 | BF66: 21 | BG66: 83 | BH66: 21 | BI66: 11 | BJ66: 45 | BK66: 32 | BL66: 109 | BM66: 36 | BN66: 34 | BO66: 2 | BP66: 6 | BQ66: 78 | BR66: 15 | BS66: 18 | BT66: 128 | BU66: 167 | BV66: 328 | BW66: 184 | BX66: 163 | CN66: 2027E | CO66: =CP66+$CO$65 | CP66: 0.18 | CQ66: =CP66+$CQ$65
B67: of which: Transit | F67: 11.8 | G67: 4.3 | H67: 80.7 | I67: 72.6 | J67: 39.3 | K67: 34 | L67: 20 | N67: 85.5 | O67: 0 | P67: 15.5 | Q67: 57.2 | S67: 136.1 | T67: 59.8 | U67: 42.2 | V67: 8.7 | X67: 117.3 | Y67: 5.7 | Z67: 6.2 | AA67: 2.2 | AC67: 134.1 | AD67: 270.4 | AE67: 283 | AF67: 289.9 | AG67: 192 | AH67: 1035.1 | AI67: 12.3 | AJ67: 28.1 | AK67: 21.2 | AL67: 22 | AM67: 83.8 | AN67: 14.7 | AO67: 2.8 | AP67: 2 | AQ67: 2 | AR67: 22.8 | AS67: 3 | AT67: 0 | AU67: 0 | AW67: 3 | BA67: 0 | BB67: 0 | BC67: 1 | BD67: 1 | BE67: 1 | BF67: 1 | BG67: 4 | BH67: 0 | BI67: 0 | BJ67: 0 | BK67: 0 | BL67: 0 | BM67: 0 | BN67: 0 | BO67: 0 | BP67: 3 | BQ67: 3 | BR67: 8 | BS67: 9 | BT67: 6 | BU67: 4 | BV67: 27 | BW67: 41 | BX67: 69 | CN67: 2028E | CO67: =CP67+$CO$65 | CP67: 0.185 | CQ67: =CP67+$CQ$65
B68: Sales change from portfolio optimization / divestitures (y/y) | BT68: -13 | BU68: -21 | BV68: -72 | BW68: -13 | BX68: -12 | BY68: 0 | BZ68: 0 | CA68: =SUM(BW68,BX68,BY68,BZ68) | CN68: 2029E | CO68: =CP68+$CO$65 | CP68: 0.19 | CQ68: =CP68+$CQ$65
B69: Sales change from foreign exchange (y/y) | F69: -35.1 | G69: 4.2 | H69: 29.6 | I69: -19.9 | J69: -3.7 | K69: -3.7 | L69: -6.3 | N69: -15.6 | O69: 1.4 | P69: 11.3 | Q69: 12.8 | S69: 11.2 | T69: -38.7 | U69: -45.3 | V69: -38.8 | W69: -27 | X69: -151.8 | Y69: -17.7 | Z69: -9.2 | AA69: -18.1 | AB69: -22 | AC69: -71.1 | AD69: -24.8 | AE69: -14.7 | AF69: 6.9 | AG69: 17 | AH69: -5.3 | AI69: 70.3 | AJ69: 35 | AK69: -19.7 | AL69: -33 | AM69: 62.3 | AN69: -58.2 | AO69: -47.6 | AP69: -30.2 | AQ69: -18 | AR69: -154.4 | AS69: -31.4 | AT69: -43.1 | AU69: -2.1 | AV69: 26 | AW69: -50 | AY69: 84 | AZ69: 23 | BA69: -17 | BB69: 134 | BC69: -37 | BD69: -76 | BE69: -99 | BF69: -92 | BG69: -304 | BH69: -56 | BI69: -7 | BJ69: 32 | BK69: 33 | BL69: 2 | BM69: 5 | BN69: -18 | BO69: -3 | BP69: -17 | BQ69: -33 | BR69: -43 | BS69: 11 | BT69: 23 | BU69: 42 | BV69: 33 | BW69: 68 | BX69: 24 | BY69: 0 | BZ69: 0 | CA69: =SUM(BW69,BX69,BY69,BZ69) | CN69: 2030E | CO69: =CP69+$CO$65 | CP69: 0.195 | CQ69: =CP69+$CQ$65
B70: Organic sales change (y/y) | N70: 33 | O70: 57.6 | P70: 42.2 | Q70: 66.5 | S70: 237.5 | T70: 84.1 | U70: 78.7 | V70: 8.3 | X70: 152.5 | Y70: -49 | Z70: -131 | AA70: -131.1 | AC70: -494.9 | AD70: -138.5 | AE70: -103.3 | AF70: -55.1 | AG70: 80 | AH70: -227.4 | AI70: 34.9 | AJ70: 105.1 | AK70: 107.4 | AL70: 47 | AM70: 284.8 | AN70: 85.9 | AO70: 47.2 | AP70: -1.8 | AQ70: -3 | AR70: 127.4 | AS70: -141.7 | AT70: -474.3 | AU70: -143.4 | AV70: -381 | AW70: -1140.3 | AY70: 153 | AZ70: -19 | BA70: 5 | BB70: -6 | BC70: 94 | BD70: 106 | BE70: 254 | BF70: 303 | BG70: 757 | BH70: 302 | BI70: 355 | BJ70: 392 | BK70: 155 | BL70: 1204 | BM70: 262 | BN70: 221 | BO70: 114 | BP70: 65 | BQ70: 662 | BR70: 133 | BS70: 24 | BT70: 79 | BU70: 190 | BV70: 464 | BW70: 60 | BX70: 229 | BY70: =BY142-BT142-BY65-BY68-BY69 | BZ70: =BZ142-BU142-BZ65-BZ68-BZ69 | CA70: =SUM(BW70,BX70,BY70,BZ70) | CF70: Forecast = total change − acquisitions − divestitures − FX (FX assumed nil). | CN70: M&A_spend (bolt-on acquisitions, $m) | CO70: 500 | CP70: Δ → | CQ70: -500 | CR70: Wabtec deployed ~$2.5bn on acquisitions in 2025 and ~$1.1bn in 1H/26 (Dellner); Base assumes ~$0.75bn p.a. of bolt-ons.
B71: Organic sales growth % | D71: =IF(AND(ISNUMBER(D70),ISNUMBER(C142)),IFERROR(D70/C142,""),"") | E71: =IF(AND(ISNUMBER(E70),ISNUMBER(D142)),IFERROR(E70/D142,""),"") | F71: =IF(AND(ISNUMBER(F70),ISNUMBER(E142)),IFERROR(F70/E142,""),"") | G71: =IF(AND(ISNUMBER(G70),ISNUMBER(F142)),IFERROR(G70/F142,""),"") | H71: =IF(AND(ISNUMBER(H70),ISNUMBER(G142)),IFERROR(H70/G142,""),"") | I71: =IF(AND(ISNUMBER(I70),ISNUMBER(H142)),IFERROR(I70/H142,""),"") | N71: =IF(AND(ISNUMBER(N70),ISNUMBER(I142)),IFERROR(N70/I142,""),"") | O71: =IF(AND(ISNUMBER(O70),ISNUMBER(J142)),IFERROR(O70/J142,""),"") | P71: =IF(AND(ISNUMBER(P70),ISNUMBER(K142)),IFERROR(P70/K142,""),"") | Q71: =IF(AND(ISNUMBER(Q70),ISNUMBER(L142)),IFERROR(Q70/L142,""),"") | R71: =IF(AND(ISNUMBER(R70),ISNUMBER(M142)),IFERROR(R70/M142,""),"") | S71: =IF(AND(ISNUMBER(S70),ISNUMBER(N142)),IFERROR(S70/N142,""),"") | T71: =IF(AND(ISNUMBER(T70),ISNUMBER(O142)),IFERROR(T70/O142,""),"") | U71: =IF(AND(ISNUMBER(U70),ISNUMBER(P142)),IFERROR(U70/P142,""),"") | ... CA71: =IF(AND(ISNUMBER(CA70),ISNUMBER(BV142)),IFERROR(CA70/BV142,""),"") | CB71: =IFERROR((CB142-CB88-(CA142-CA88))/CA142,"") | CC71: =IFERROR((CC142-CC88-(CB142-CB88))/CB142,"") | CD71: =IFERROR((CD142-CD88-(CC142-CC88))/CC142,"") | CE71: =IFERROR((CE142-CE88-(CD142-CD88))/CD142,"") | CF71: 2027E+: growth excluding sales from future acquisitions (FX nil). | CH71: =IFERROR(AVERAGE(CA71,CB71,CC71,CD71,CE71),"n/m") | CI71: =IFERROR(AVERAGE(BB71,BG71,BL71,BQ71,BV71),"n/m") | CJ71: =IFERROR(AVERAGE(AC71,AH71,AM71,AR71,AW71,BB71,BG71,BL71,BQ71,BV71),"n/m") | CK71: =IFERROR(AVERAGE(C71,D71,E71,F71,G71,H71,I71,N71,S71,X71,AC71,AH71,AM71,AR71,AW71,BB71,BG71,BL71,BQ71,BV71),"n/m") | CN71: 2027E | CO71: =MAX(0,CP71+$CO$70) | CP71: 750 | CQ71: =MAX(0,CP71+$CQ$70)
B72: Acquisition contribution to growth % | D72: =IF(AND(ISNUMBER(D65),ISNUMBER(C142)),IFERROR(D65/C142,""),"") | E72: =IF(AND(ISNUMBER(E65),ISNUMBER(D142)),IFERROR(E65/D142,""),"") | F72: =IF(AND(ISNUMBER(F65),ISNUMBER(E142)),IFERROR(F65/E142,""),"") | G72: =IF(AND(ISNUMBER(G65),ISNUMBER(F142)),IFERROR(G65/F142,""),"") | H72: =IF(AND(ISNUMBER(H65),ISNUMBER(G142)),IFERROR(H65/G142,""),"") | I72: =IF(AND(ISNUMBER(I65),ISNUMBER(H142)),IFERROR(I65/H142,""),"") | N72: =IF(AND(ISNUMBER(N65),ISNUMBER(I142)),IFERROR(N65/I142,""),"") | O72: =IF(AND(ISNUMBER(O65),ISNUMBER(J142)),IFERROR(O65/J142,""),"") | P72: =IF(AND(ISNUMBER(P65),ISNUMBER(K142)),IFERROR(P65/K142,""),"") | Q72: =IF(AND(ISNUMBER(Q65),ISNUMBER(L142)),IFERROR(Q65/L142,""),"") | R72: =IF(AND(ISNUMBER(R65),ISNUMBER(M142)),IFERROR(R65/M142,""),"") | S72: =IF(AND(ISNUMBER(S65),ISNUMBER(N142)),IFERROR(S65/N142,""),"") | T72: =IF(AND(ISNUMBER(T65),ISNUMBER(O142)),IFERROR(T65/O142,""),"") | U72: =IF(AND(ISNUMBER(U65),ISNUMBER(P142)),IFERROR(U65/P142,""),"") | ... CA72: =IF(AND(ISNUMBER(CA65),ISNUMBER(BV142)),IFERROR(CA65/BV142,""),"") | CB72: =IFERROR((CB88-CA88)/CA142,"") | CC72: =IFERROR((CC88-CB88)/CB142,"") | CD72: =IFERROR((CD88-CC88)/CC142,"") | CE72: =IFERROR((CE88-CD88)/CD142,"") | CH72: =IFERROR(AVERAGE(CA72,CB72,CC72,CD72,CE72),"n/m") | CI72: =IFERROR(AVERAGE(BB72,BG72,BL72,BQ72,BV72),"n/m") | CJ72: =IFERROR(AVERAGE(AC72,AH72,AM72,AR72,AW72,BB72,BG72,BL72,BQ72,BV72),"n/m") | CK72: =IFERROR(AVERAGE(C72,D72,E72,F72,G72,H72,I72,N72,S72,X72,AC72,AH72,AM72,AR72,AW72,BB72,BG72,BL72,BQ72,BV72),"n/m") | CN72: 2028E | CO72: =MAX(0,CP72+$CO$70) | CP72: 750 | CQ72: =MAX(0,CP72+$CQ$70)
B73: FX contribution to growth % | D73: =IF(AND(ISNUMBER(D69),ISNUMBER(C142)),IFERROR(D69/C142,""),"") | E73: =IF(AND(ISNUMBER(E69),ISNUMBER(D142)),IFERROR(E69/D142,""),"") | F73: =IF(AND(ISNUMBER(F69),ISNUMBER(E142)),IFERROR(F69/E142,""),"") | G73: =IF(AND(ISNUMBER(G69),ISNUMBER(F142)),IFERROR(G69/F142,""),"") | H73: =IF(AND(ISNUMBER(H69),ISNUMBER(G142)),IFERROR(H69/G142,""),"") | I73: =IF(AND(ISNUMBER(I69),ISNUMBER(H142)),IFERROR(I69/H142,""),"") | N73: =IF(AND(ISNUMBER(N69),ISNUMBER(I142)),IFERROR(N69/I142,""),"") | O73: =IF(AND(ISNUMBER(O69),ISNUMBER(J142)),IFERROR(O69/J142,""),"") | P73: =IF(AND(ISNUMBER(P69),ISNUMBER(K142)),IFERROR(P69/K142,""),"") | Q73: =IF(AND(ISNUMBER(Q69),ISNUMBER(L142)),IFERROR(Q69/L142,""),"") | R73: =IF(AND(ISNUMBER(R69),ISNUMBER(M142)),IFERROR(R69/M142,""),"") | S73: =IF(AND(ISNUMBER(S69),ISNUMBER(N142)),IFERROR(S69/N142,""),"") | T73: =IF(AND(ISNUMBER(T69),ISNUMBER(O142)),IFERROR(T69/O142,""),"") | U73: =IF(AND(ISNUMBER(U69),ISNUMBER(P142)),IFERROR(U69/P142,""),"") | ... CA73: =IF(AND(ISNUMBER(CA69),ISNUMBER(BV142)),IFERROR(CA69/BV142,""),"") | CB73: =IF(AND(ISNUMBER(CB69),ISNUMBER(CA142)),IFERROR(CB69/CA142,""),"") | CC73: =IF(AND(ISNUMBER(CC69),ISNUMBER(CB142)),IFERROR(CC69/CB142,""),"") | CD73: =IF(AND(ISNUMBER(CD69),ISNUMBER(CC142)),IFERROR(CD69/CC142,""),"") | CE73: =IF(AND(ISNUMBER(CE69),ISNUMBER(CD142)),IFERROR(CE69/CD142,""),"") | CN73: 2029E | CO73: =MAX(0,CP73+$CO$70) | CP73: 750 | CQ73: =MAX(0,CP73+$CQ$70)
B74: Check: bridge vs reported sales change (should be 0) | D74: =IF(AND(ISNUMBER(D70),ISNUMBER(D65),ISNUMBER(C142)),ROUND(D142-C142-D65-N(D68)-N(D69)-D70,0),"n/p") | E74: =IF(AND(ISNUMBER(E70),ISNUMBER(E65),ISNUMBER(D142)),ROUND(E142-D142-E65-N(E68)-N(E69)-E70,0),"n/p") | F74: =IF(AND(ISNUMBER(F70),ISNUMBER(F65),ISNUMBER(E142)),ROUND(F142-E142-F65-N(F68)-N(F69)-F70,0),"n/p") | G74: =IF(AND(ISNUMBER(G70),ISNUMBER(G65),ISNUMBER(F142)),ROUND(G142-F142-G65-N(G68)-N(G69)-G70,0),"n/p") | H74: =IF(AND(ISNUMBER(H70),ISNUMBER(H65),ISNUMBER(G142)),ROUND(H142-G142-H65-N(H68)-N(H69)-H70,0),"n/p") | I74: =IF(AND(ISNUMBER(I70),ISNUMBER(I65),ISNUMBER(H142)),ROUND(I142-H142-I65-N(I68)-N(I69)-I70,0),"n/p") | N74: =IF(AND(ISNUMBER(N70),ISNUMBER(N65),ISNUMBER(I142)),ROUND(N142-I142-N65-N(N68)-N(N69)-N70,0),"n/p") | O74: =IF(AND(ISNUMBER(O70),ISNUMBER(O65),ISNUMBER(J142)),ROUND(O142-J142-O65-N(O68)-N(O69)-O70,0),"n/p") | P74: =IF(AND(ISNUMBER(P70),ISNUMBER(P65),ISNUMBER(K142)),ROUND(P142-K142-P65-N(P68)-N(P69)-P70,0),"n/p") | Q74: =IF(AND(ISNUMBER(Q70),ISNUMBER(Q65),ISNUMBER(L142)),ROUND(Q142-L142-Q65-N(Q68)-N(Q69)-Q70,0),"n/p") | R74: =IF(AND(ISNUMBER(R70),ISNUMBER(R65),ISNUMBER(M142)),ROUND(R142-M142-R65-N(R68)-N(R69)-R70,0),"n/p") | S74: =IF(AND(ISNUMBER(S70),ISNUMBER(S65),ISNUMBER(N142)),ROUND(S142-N142-S65-N(S68)-N(S69)-S70,0),"n/p") | T74: =IF(AND(ISNUMBER(T70),ISNUMBER(T65),ISNUMBER(O142)),ROUND(T142-O142-T65-N(T68)-N(T69)-T70,0),"n/p") | U74: =IF(AND(ISNUMBER(U70),ISNUMBER(U65),ISNUMBER(P142)),ROUND(U142-P142-U65-N(U68)-N(U69)-U70,0),"n/p") | ... BX74: =IF(AND(ISNUMBER(BX70),ISNUMBER(BX65),ISNUMBER(BS142)),ROUND(BX142-BS142-BX65-N(BX68)-N(BX69)-BX70,0),"n/p") | CN74: 2030E | CO74: =MAX(0,CP74+$CO$70) | CP74: 750 | CQ74: =MAX(0,CP74+$CQ$70)
B76: Corporate activities & elimination (unallocated) | CF76: CORPORATE & RECONCILING ITEMS
B77: Corporate adjusted income (loss) from operations | C77: =IF(AND(ISNUMBER(C216),ISNUMBER(C31),ISNUMBER(C55)),C216-C31-C55,"") | D77: =IF(AND(ISNUMBER(D216),ISNUMBER(D31),ISNUMBER(D55)),D216-D31-D55,"") | E77: =IF(AND(ISNUMBER(E216),ISNUMBER(E31),ISNUMBER(E55)),E216-E31-E55,"") | F77: =IF(AND(ISNUMBER(F216),ISNUMBER(F31),ISNUMBER(F55)),F216-F31-F55,"") | G77: =IF(AND(ISNUMBER(G216),ISNUMBER(G31),ISNUMBER(G55)),G216-G31-G55,"") | H77: =IF(AND(ISNUMBER(H216),ISNUMBER(H31),ISNUMBER(H55)),H216-H31-H55,"") | I77: =IF(AND(ISNUMBER(I216),ISNUMBER(I31),ISNUMBER(I55)),I216-I31-I55,"") | J77: =IF(AND(ISNUMBER(J216),ISNUMBER(J31),ISNUMBER(J55)),J216-J31-J55,"") | ... BX77: =IF(AND(ISNUMBER(BX216),ISNUMBER(BX31),ISNUMBER(BX55)),BX216-BX31-BX55,"") | BY77: =(BW77+BX77)/2 | BZ77: =(BW77+BX77)/2 | CA77: =SUM(BW77,BX77,BY77,BZ77) | CB77: =CB142*CB78 | CC77: =CC142*CC78 | CD77: =CD142*CD78 | CE77: =CE142*CE78 | CF77: Historical = published consolidated adjusted operating income − segment adjusted operating income. Q3/Q4-26E: 1H/26 run-rate; 2027E+: % of sales input.
B78: Corporate adjusted cost % of sales | C78: =IF(AND(ISNUMBER(C77),ISNUMBER(C142)),IFERROR(C77/C142,""),"") | D78: =IF(AND(ISNUMBER(D77),ISNUMBER(D142)),IFERROR(D77/D142,""),"") | E78: =IF(AND(ISNUMBER(E77),ISNUMBER(E142)),IFERROR(E77/E142,""),"") | F78: =IF(AND(ISNUMBER(F77),ISNUMBER(F142)),IFERROR(F77/F142,""),"") | G78: =IF(AND(ISNUMBER(G77),ISNUMBER(G142)),IFERROR(G77/G142,""),"") | H78: =IF(AND(ISNUMBER(H77),ISNUMBER(H142)),IFERROR(H77/H142,""),"") | I78: =IF(AND(ISNUMBER(I77),ISNUMBER(I142)),IFERROR(I77/I142,""),"") | J78: =IF(AND(ISNUMBER(J77),ISNUMBER(J142)),IFERROR(J77/J142,""),"") | ... BX78: =IF(AND(ISNUMBER(BX77),ISNUMBER(BX142)),IFERROR(BX77/BX142,""),"") | CA78: =IF(AND(ISNUMBER(CA77),ISNUMBER(CA142)),IFERROR(CA77/CA142,""),"") | CB78: -0.017 | CC78: -0.017 | CD78: -0.017 | CE78: -0.017
B79: Corporate adjusting items | C79: =IF(AND(ISNUMBER(C77),ISNUMBER(C80)),C77-C80,"") | D79: =IF(AND(ISNUMBER(D77),ISNUMBER(D80)),D77-D80,"") | E79: =IF(AND(ISNUMBER(E77),ISNUMBER(E80)),E77-E80,"") | F79: =IF(AND(ISNUMBER(F77),ISNUMBER(F80)),F77-F80,"") | G79: =IF(AND(ISNUMBER(G77),ISNUMBER(G80)),G77-G80,"") | H79: =IF(AND(ISNUMBER(H77),ISNUMBER(H80)),H77-H80,"") | I79: =IF(AND(ISNUMBER(I77),ISNUMBER(I80)),I77-I80,"") | J79: =IF(AND(ISNUMBER(J77),ISNUMBER(J80)),J77-J80,"") | ... BX79: =IF(AND(ISNUMBER(BX77),ISNUMBER(BX80)),BX77-BX80,"") | BY79: =BY213-BY35-BY59-N(BY95) | BZ79: =BZ213-BZ35-BZ59-N(BZ95) | CA79: =SUM(BW79,BX79,BY79,BZ79) | CB79: =CB213-CB35-CB59-N(CB95) | CC79: =CC213-CC35-CC59-N(CC95) | CD79: =CD213-CD35-CD59-N(CD95) | CE79: =CE213-CE35-CE59-N(CE95)
B80: Corporate income (loss) from operations (GAAP) | C80: -12.7 | D80: -15.8 | E80: -19.7 | F80: -22.9 | G80: -14.9 | H80: -38.3 | I80: -17.2 | J80: -15.3 | K80: -1.9 | L80: -3.8 | M80: -5 | N80: -15.5 | O80: -4.6 | P80: -4.7 | Q80: -6.9 | R80: -6.9 | S80: -23.2 | T80: -4.6 | U80: -6.9 | V80: -6.6 | W80: -8 | X80: -26.1 | Y80: -9.5 | Z80: -11.2 | AA80: -9.1 | AB80: -27.8 | AC80: -57.5 | AD80: -5.7 | AE80: -8.9 | AF80: -7.1 | AG80: -9.8 | AH80: -31.4 | AI80: -6.4 | AJ80: -18.8 | AK80: -15 | AL80: -19.1 | AM80: -59.3 | AN80: -66.8 | AO80: -22.6 | AP80: -34.8 | AQ80: -52.1 | AR80: -194.2 | AS80: -13 | AT80: -22.3 | AU80: -17.6 | AV80: -16.2 | AW80: -69.1 | AX80: -20.3 | AY80: -15.2 | AZ80: -22.1 | BA80: -22 | BB80: -79 | BC80: -15 | BD80: -19 | BE80: -25 | BF80: -25 | BG80: -84 | BH80: -20 | BI80: -25 | BJ80: -25 | BK80: -24 | BL80: -94 | BM80: -30 | BN80: -43 | BO80: -36 | BP80: -42 | BQ80: -151 | BR80: -36 | BS80: -52 | BT80: -38 | BU80: -70 | BV80: -196 | BW80: -54 | BX80: -50 | BY80: =BY77-BY79 | BZ80: =BZ77-BZ79 | CA80: =SUM(BW80,BX80,BY80,BZ80) | CB80: =CB77-CB79 | CC80: =CC77-CC79 | CD80: =CD77-CD79 | CE80: =CE77-CE79
B82: Future acquisitions (M&A lever — bolt-ons, unallocated; deals closed from 2027E) | CF82: M&A LEVER — acquired sales = spend ÷ EV/sales; mid-year convention
B83: Acquisition spend (USDm, scenario) | CA83: 0 | CB83: =MAX(0,CHOOSE(MATCH($CF$2,{"Bull","Base","Bear"},0),$CO$71,$CP$71,$CQ$71)) | CC83: =MAX(0,CHOOSE(MATCH($CF$2,{"Bull","Base","Bear"},0),$CO$72,$CP$72,$CQ$72)) | CD83: =MAX(0,CHOOSE(MATCH($CF$2,{"Bull","Base","Bear"},0),$CO$73,$CP$73,$CQ$73)) | CE83: =MAX(0,CHOOSE(MATCH($CF$2,{"Bull","Base","Bear"},0),$CO$74,$CP$74,$CQ$74)) | CF83: Scenario lever M&A_spend. Wabtec deployed ~$2.5bn (2025: Inspection Technologies, Frauscher) and ~$1.1bn (1H/26: Dellner); Base assumes ~$0.75bn p.a. of bolt-ons from 2027.
B84: Purchase multiple — EV / sales (x) | CA84: 0 | CB84: 3.5 | CC84: 3.5 | CD84: 3.5 | CE84: 3.5 | CF84: Wabtec bolt-ons: Inspection Technologies ~$1.78bn on ~$0.45bn sales (~4x), Dellner ~$0.96bn, Frauscher ~€0.68bn; 3.5x input.
B85: Annualised sales acquired in the year | CA85: 0 | CB85: =IFERROR(CB83/CB84,0) | CC85: =IFERROR(CC83/CC84,0) | CD85: =IFERROR(CD83/CD84,0) | CE85: =IFERROR(CE83/CE84,0)
B86: Growth of acquired businesses after acquisition % | CA86: 0 | CB86: 0.06 | CC86: 0.06 | CD86: 0.06 | CE86: 0.06
B87: Run-rate sales of businesses acquired (year end) | CA87: 0 | CB87: =CA87*(1+CB86)+CB85 | CC87: =CB87*(1+CC86)+CC85 | CD87: =CC87*(1+CD86)+CD85 | CE87: =CD87*(1+CE86)+CE85
B88: Sales from future acquisitions | CA88: 0 | CB88: =CA87*(1+CB86)+0.5*CB85 | CC88: =CB87*(1+CC86)+0.5*CC85 | CD88: =CC87*(1+CD86)+0.5*CD85 | CE88: =CD87*(1+CE86)+0.5*CE85 | CF88: Mid-year convention: deals close evenly through the year (half a year of sales in year 1). Allocated to neither segment (unallocated line in the Group build).
B89: Adjusted operating margin of acquired businesses % (before PPA amortization) | CA89: 0 | CB89: 0.22 | CC89: 0.22 | CD89: 0.22 | CE89: 0.22
B90: Adjusted operating income from future acquisitions | CA90: 0 | CB90: =CB88*CB89 | CC90: =CC88*CC89 | CD90: =CD88*CD89 | CE90: =CE88*CE89
B91: PP&E % of spend | CA91: 0 | CB91: 0.08 | CC91: 0.08 | CD91: 0.08 | CE91: 0.08
B92: Acquired intangibles % of spend | CA92: 0 | CB92: 0.35 | CC92: 0.35 | CD92: 0.35 | CE92: 0.35 | CF92: Inspection Technologies / Dellner PPAs: customer relationships, technology and trade names ~30–40% of consideration; balance goodwill.
B93: Intangible amortization life (years) | CA93: 0 | CB93: 15 | CC93: 15 | CD93: 15 | CE93: 15
B94: Cumulative acquired intangibles (gross) | CA94: 0 | CB94: =CA94+CB83*CB92 | CC94: =CB94+CC83*CC92 | CD94: =CC94+CD83*CD92 | CE94: =CD94+CE83*CE92
B95: Amortization of future-acquisition intangibles (within amortization expense) | CA95: 0 | CB95: =IFERROR((CA94+0.5*CB83*CB92)/CB93,0) | CC95: =IFERROR((CB94+0.5*CC83*CC92)/CC93,0) | CD95: =IFERROR((CC94+0.5*CD83*CD92)/CD93,0) | CE95: =IFERROR((CD94+0.5*CE83*CE92)/CE93,0) | CF95: Non-cash; added back in adjusted operating income / adjusted EPS (company definition).
B97: Group Total — net sales & adjusted operating income (product-line build) → FY26 outlook calibration | CF97: GROUP TOTAL (CONSOLIDATED) — modelling logic
B98: Net sales (product-line build) | C98: =IF(ISNUMBER(C27),N(C27)+N(C51),"") | D98: =IF(ISNUMBER(D27),N(D27)+N(D51),"") | E98: =IF(ISNUMBER(E27),N(E27)+N(E51),"") | F98: =IF(ISNUMBER(F27),N(F27)+N(F51),"") | G98: =IF(ISNUMBER(G27),N(G27)+N(G51),"") | H98: =IF(ISNUMBER(H27),N(H27)+N(H51),"") | I98: =IF(ISNUMBER(I27),N(I27)+N(I51),"") | J98: =IF(ISNUMBER(J27),N(J27)+N(J51),"") | ... BX98: =IF(ISNUMBER(BX27),N(BX27)+N(BX51),"") | BY98: =N(BY27)+N(BY51)+N(BY88) | BZ98: =N(BZ27)+N(BZ51)+N(BZ88) | CA98: =N(CA27)+N(CA51)+N(CA88) | CB98: =N(CB27)+N(CB51)+N(CB88) | CC98: =N(CC27)+N(CC51)+N(CC88) | CD98: =N(CD27)+N(CD51)+N(CD88) | CE98: =N(CE27)+N(CE51)+N(CE88) | CF98: Σ Freight + Transit segment sales (+ future acquisitions from 2027E). | CH98: =IFERROR((CE98/BV98)^(1/5)-1,"n/m") | CI98: =IFERROR((BV98/AW98)^(1/5)-1,"n/m") | CJ98: =IFERROR((BV98/X98)^(1/10)-1,"n/m") | CK98: =IFERROR((BV98/C98)^(1/19)-1,"n/m")
B99: Adjusted income from operations (product-line build) | C99: =IF(AND(ISNUMBER(C31),ISNUMBER(C77)),C31+C55+C77,"") | D99: =IF(AND(ISNUMBER(D31),ISNUMBER(D77)),D31+D55+D77,"") | E99: =IF(AND(ISNUMBER(E31),ISNUMBER(E77)),E31+E55+E77,"") | F99: =IF(AND(ISNUMBER(F31),ISNUMBER(F77)),F31+F55+F77,"") | G99: =IF(AND(ISNUMBER(G31),ISNUMBER(G77)),G31+G55+G77,"") | H99: =IF(AND(ISNUMBER(H31),ISNUMBER(H77)),H31+H55+H77,"") | I99: =IF(AND(ISNUMBER(I31),ISNUMBER(I77)),I31+I55+I77,"") | J99: =IF(AND(ISNUMBER(J31),ISNUMBER(J77)),J31+J55+J77,"") | ... BX99: =IF(AND(ISNUMBER(BX31),ISNUMBER(BX77)),BX31+BX55+BX77,"") | BY99: =BY31+BY55+BY77+N(BY90) | BZ99: =BZ31+BZ55+BZ77+N(BZ90) | CA99: =CA31+CA55+CA77+N(CA90) | CB99: =CB31+CB55+CB77+N(CB90) | CC99: =CC31+CC55+CC77+N(CC90) | CD99: =CD31+CD55+CD77+N(CD90) | CE99: =CE31+CE55+CE77+N(CE90) | CF99: Σ segment adjusted operating income + corporate (+ future acquisitions). Wabtec's primary profit KPI. | CH99: =IFERROR((CE99/BV99)^(1/5)-1,"n/m") | CI99: =IFERROR((BV99/AW99)^(1/5)-1,"n/m") | CJ99: =IFERROR((BV99/X99)^(1/10)-1,"n/m") | CK99: =IFERROR((BV99/C99)^(1/19)-1,"n/m")
B100: Adjusted operating margin % | C100: =IF(AND(ISNUMBER(C99),ISNUMBER(C98)),IFERROR(C99/C98,""),"") | D100: =IF(AND(ISNUMBER(D99),ISNUMBER(D98)),IFERROR(D99/D98,""),"") | E100: =IF(AND(ISNUMBER(E99),ISNUMBER(E98)),IFERROR(E99/E98,""),"") | F100: =IF(AND(ISNUMBER(F99),ISNUMBER(F98)),IFERROR(F99/F98,""),"") | G100: =IF(AND(ISNUMBER(G99),ISNUMBER(G98)),IFERROR(G99/G98,""),"") | H100: =IF(AND(ISNUMBER(H99),ISNUMBER(H98)),IFERROR(H99/H98,""),"") | I100: =IF(AND(ISNUMBER(I99),ISNUMBER(I98)),IFERROR(I99/I98,""),"") | J100: =IF(AND(ISNUMBER(J99),ISNUMBER(J98)),IFERROR(J99/J98,""),"") | ... CE100: =IF(AND(ISNUMBER(CE99),ISNUMBER(CE98)),IFERROR(CE99/CE98,""),"") | CH100: =IFERROR(AVERAGE(CA100,CB100,CC100,CD100,CE100),"n/m") | CI100: =IFERROR(AVERAGE(BB100,BG100,BL100,BQ100,BV100),"n/m") | CJ100: =IFERROR(AVERAGE(AC100,AH100,AM100,AR100,AW100,BB100,BG100,BL100,BQ100,BV100),"n/m") | CK100: =IFERROR(AVERAGE(C100,D100,E100,F100,G100,H100,I100,N100,S100,X100,AC100,AH100,AM100,AR100,AW100,BB100,BG100,BL100,BQ100,BV100),"n/m")
B101: Net sales y/y % | D101: =IF(AND(ISNUMBER(D98),ISNUMBER(C98)),IFERROR(D98/C98-1,""),"") | E101: =IF(AND(ISNUMBER(E98),ISNUMBER(D98)),IFERROR(E98/D98-1,""),"") | F101: =IF(AND(ISNUMBER(F98),ISNUMBER(E98)),IFERROR(F98/E98-1,""),"") | G101: =IF(AND(ISNUMBER(G98),ISNUMBER(F98)),IFERROR(G98/F98-1,""),"") | H101: =IF(AND(ISNUMBER(H98),ISNUMBER(G98)),IFERROR(H98/G98-1,""),"") | I101: =IF(AND(ISNUMBER(I98),ISNUMBER(H98)),IFERROR(I98/H98-1,""),"") | N101: =IF(AND(ISNUMBER(N98),ISNUMBER(I98)),IFERROR(N98/I98-1,""),"") | O101: =IF(AND(ISNUMBER(O98),ISNUMBER(J98)),IFERROR(O98/J98-1,""),"") | P101: =IF(AND(ISNUMBER(P98),ISNUMBER(K98)),IFERROR(P98/K98-1,""),"") | Q101: =IF(AND(ISNUMBER(Q98),ISNUMBER(L98)),IFERROR(Q98/L98-1,""),"") | R101: =IF(AND(ISNUMBER(R98),ISNUMBER(M98)),IFERROR(R98/M98-1,""),"") | S101: =IF(AND(ISNUMBER(S98),ISNUMBER(N98)),IFERROR(S98/N98-1,""),"") | T101: =IF(AND(ISNUMBER(T98),ISNUMBER(O98)),IFERROR(T98/O98-1,""),"") | U101: =IF(AND(ISNUMBER(U98),ISNUMBER(P98)),IFERROR(U98/P98-1,""),"") | ... CA101: =IF(AND(ISNUMBER(CA98),ISNUMBER(BV98)),IFERROR(CA98/BV98-1,""),"") | CB101: =IF(AND(ISNUMBER(CB98),ISNUMBER(CA98)),IFERROR(CB98/CA98-1,""),"") | CC101: =IF(AND(ISNUMBER(CC98),ISNUMBER(CB98)),IFERROR(CC98/CB98-1,""),"") | CD101: =IF(AND(ISNUMBER(CD98),ISNUMBER(CC98)),IFERROR(CD98/CC98-1,""),"") | CE101: =IF(AND(ISNUMBER(CE98),ISNUMBER(CD98)),IFERROR(CE98/CD98-1,""),"")
B102: Check: product-line build vs consolidated net sales (should be 0) | C102: =IF(ISNUMBER(C98),IF(ABS(C98-C142)<=0.15,0,ROUND(C98-C142,1)),"") | D102: =IF(ISNUMBER(D98),IF(ABS(D98-D142)<=0.15,0,ROUND(D98-D142,1)),"") | E102: =IF(ISNUMBER(E98),IF(ABS(E98-E142)<=0.15,0,ROUND(E98-E142,1)),"") | F102: =IF(ISNUMBER(F98),IF(ABS(F98-F142)<=0.15,0,ROUND(F98-F142,1)),"") | G102: =IF(ISNUMBER(G98),IF(ABS(G98-G142)<=0.15,0,ROUND(G98-G142,1)),"") | H102: =IF(ISNUMBER(H98),IF(ABS(H98-H142)<=0.15,0,ROUND(H98-H142,1)),"") | I102: =IF(ISNUMBER(I98),IF(ABS(I98-I142)<=0.15,0,ROUND(I98-I142,1)),"") | J102: =IF(ISNUMBER(J98),IF(ABS(J98-J142)<=0.15,0,ROUND(J98-J142,1)),"") | ... CE102: =IF(ISNUMBER(CE98),IF(ABS(CE98-CE142)<=0.15,0,ROUND(CE98-CE142,1)),"")
B103: Check: build vs adjusted income from operations bridge (should be 0) | C103: =IF(AND(ISNUMBER(C99),ISNUMBER(C214)),ROUND(C99-C214,1),"") | D103: =IF(AND(ISNUMBER(D99),ISNUMBER(D214)),ROUND(D99-D214,1),"") | E103: =IF(AND(ISNUMBER(E99),ISNUMBER(E214)),ROUND(E99-E214,1),"") | F103: =IF(AND(ISNUMBER(F99),ISNUMBER(F214)),ROUND(F99-F214,1),"") | G103: =IF(AND(ISNUMBER(G99),ISNUMBER(G214)),ROUND(G99-G214,1),"") | H103: =IF(AND(ISNUMBER(H99),ISNUMBER(H214)),ROUND(H99-H214,1),"") | I103: =IF(AND(ISNUMBER(I99),ISNUMBER(I214)),ROUND(I99-I214,1),"") | J103: =IF(AND(ISNUMBER(J99),ISNUMBER(J214)),ROUND(J99-J214,1),"") | ... CE103: =IF(AND(ISNUMBER(CE99),ISNUMBER(CE214)),ROUND(CE99-CE214,1),"")
...

Sheet Bull-Base-Bear
B2: Westinghouse Air Brake Technologies (WAB) — Bull / Base / Bear Case P&L Summary | J2: Share price ($): | K2: =Model!$CA$431
B3: Adjusted figures (company definitions: Adjusted EBITDA; adjusted EPS incl. add-back of non-cash amortization) · USD millions · Live panel linked to Model — toggle scenario via Model!CF2. Bull and Bear panels are value snapshots generated from the Model with the switch set to each case. 2026E includes Dellner Couplers from 10-Feb-2026. | J3: As of: | K3: =TODAY()
B5: Scenario: | C5: =Model!$CF$2 | N5: Scenario: | O5: Bull | P5: Snapshot (values) — Model run with switch = Bull | Z5: Scenario: | AA5: Bear | AB5: Snapshot (values) — Model run with switch = Bear
B7: (USDm, except EPS and shares) | C7: 2025A | D7: 2026E | E7: 2027E | F7: 2028E | G7: 2029E | H7: 2030E | I7: 25-'30 CAGR | J7: LT Hist Avg | K7: LT Hist Min | L7: LT Hist Max | N7: (USDm, except EPS and shares) | O7: 2025A | P7: 2026E | Q7: 2027E | R7: 2028E | S7: 2029E | T7: 2030E | U7: 25-'30 CAGR | V7: LT Hist Avg | W7: LT Hist Min | X7: LT Hist Max | Z7: (USDm, except EPS and shares) | AA7: 2025A | AB7: 2026E | AC7: 2027E | AD7: 2028E | AE7: 2029E | AF7: 2030E | AG7: 25-'30 CAGR | AH7: LT Hist Avg | AI7: LT Hist Min | AJ7: LT Hist Max
B9: Net Sales | C9: =Model!BV142 | D9: =Model!CA142 | E9: =Model!CB142 | F9: =Model!CC142 | G9: =Model!CD142 | H9: =Model!CE142 | I9: =IFERROR((H9/C9)^(1/5)-1,"n/m") | N9: Net Sales | O9: 11167 | P9: 12600 | Q9: 13748.765 | R9: 15168.395 | S9: 16620.599 | T9: 18174.291 | U9: 0.10231113 | Z9: Net Sales | AA9: 11167 | AB9: 12300 | AC9: 12634.634 | AD9: 13012.09 | AE9: 13340.55 | AF9: 13681.272 | AG9: 0.041448956
B10: Net sales y/y % | D10: =IFERROR(D9/C9-1,"") | E10: =IFERROR(E9/D9-1,"") | F10: =IFERROR(F9/E9-1,"") | G10: =IFERROR(G9/F9-1,"") | H10: =IFERROR(H9/G9-1,"") | N10: Net sales y/y % | P10: 0.12832453 | Q10: 0.091171793 | R10: 0.10325514 | S10: 0.095738795 | T10: 0.093479884 | Z10: Net sales y/y % | AB10: 0.10145966 | AC10: 0.027206041 | AD10: 0.029874692 | AE10: 0.025242668 | AF10: 0.025540291
B11: Organic sales growth % | C11: =Model!BV241 | D11: =Model!CA241 | E11: =Model!CB241 | F11: =Model!CC241 | G11: =Model!CD241 | H11: =Model!CE241 | N11: Organic sales growth % | O11: 0.044671224 | P11: 0.059908659 | Q11: 0.076999457 | R11: 0.075720195 | S11: 0.069283412 | T11: 0.067887373 | Z11: Organic sales growth % | AA11: 0.044671224 | AB11: 0.03304379 | AC11: 0.02430244 | AD11: 0.023882093 | AE11: 0.019074778 | AF11: 0.019163299
B12: Adjusted EBITDA | C12: =Model!BV194 | D12: =Model!CA194 | E12: =Model!CB194 | F12: =Model!CC194 | G12: =Model!CD194 | H12: =Model!CE194 | I12: =IFERROR((H12/C12)^(1/5)-1,"n/m") | N12: Adjusted EBITDA | O12: 2464 | P12: 2944.2271 | Q12: 3437.3406 | R12: 3854.9365 | S12: 4290.5795 | T12: 4762.7654 | U12: 0.1408898 | Z12: Adjusted EBITDA | AA12: 2464 | AB12: 2875.7214 | AC12: 2846.3296 | AD12: 2994.673 | AE12: 3134.3355 | AF12: 3279.3289 | AG12: 0.05883638
B13: Adjusted EBITDA margin % | C13: =IFERROR(C12/C9,"") | D13: =IFERROR(D12/D9,"") | E13: =IFERROR(E12/E9,"") | F13: =IFERROR(F12/F9,"") | G13: =IFERROR(G12/G9,"") | H13: =IFERROR(H12/H9,"") | J13: =IFERROR(AVERAGE(Model!C195,Model!D195,Model!E195,Model!F195,Model!G195,Model!H195,Model!I195,Model!N195,Model!S195,Model!X195,Model!AC195,Model!AH195,Model!AM195,Model!AR195,Model!AW195,Model!BB195,Model!BG195,Model!BL195,Model!BQ195,Model!BV195),"") | K13: =IFERROR(MIN(Model!C195,Model!D195,Model!E195,Model!F195,Model!G195,Model!H195,Model!I195,Model!N195,Model!S195,Model!X195,Model!AC195,Model!AH195,Model!AM195,Model!AR195,Model!AW195,Model!BB195,Model!BG195,Model!BL195,Model!BQ195,Model!BV195),"") | L13: =IFERROR(MAX(Model!C195,Model!D195,Model!E195,Model!F195,Model!G195,Model!H195,Model!I195,Model!N195,Model!S195,Model!X195,Model!AC195,Model!AH195,Model!AM195,Model!AR195,Model!AW195,Model!BB195,Model!BG195,Model!BL195,Model!BQ195,Model!BV195),"") | N13: Adjusted EBITDA margin % | O13: 0.22065013 | P13: 0.23366882 | Q13: 0.25001087 | R13: 0.25414267 | S13: 0.25814831 | T13: 0.26206059 | V13: 0.19446972 | W13: 0.1769299 | X13: 0.22065013 | Z13: Adjusted EBITDA margin % | AA13: 0.22065013 | AB13: 0.23379849 | AC13: 0.22527994 | AD13: 0.23014542 | AE13: 0.234948 | AF13: 0.23969475 | AH13: 0.19446972 | AI13: 0.1769299 | AJ13: 0.22065013
B15: Income from Operations (GAAP) | C15: =Model!BV150 | D15: =Model!CA150 | E15: =Model!CB150 | F15: =Model!CC150 | G15: =Model!CD150 | H15: =Model!CE150 | I15: =IFERROR((H15/C15)^(1/5)-1,"n/m") | N15: Income from Operations (GAAP) | O15: 1793 | P15: 2296.5913 | Q15: 2809.9027 | R15: 3176.908 | S15: 3561.4229 | T15: 3991.8062 | U15: 0.17359387 | Z15: Income from Operations (GAAP) | AA15: 1793 | AB15: 2233.0293 | AC15: 2248.9415 | AD15: 2387.2235 | AE15: 2517.6331 | AF15: 2664.1713 | AG15: 0.0824214
B16: Income from operations y/y % | D16: =IFERROR(D15/C15-1,"") | E16: =IFERROR(E15/D15-1,"") | F16: =IFERROR(F15/E15-1,"") | G16: =IFERROR(G15/F15-1,"") | H16: =IFERROR(H15/G15-1,"") | N16: Income from operations y/y % | P16: 0.2808652 | Q16: 0.22351012 | R16: 0.13061139 | S16: 0.12103433 | T16: 0.12084589 | Z16: Income from operations y/y % | AB16: 0.24541513 | AC16: 0.0071258142 | AD16: 0.061487599 | AE16: 0.054628165 | AF16: 0.05820472
B17: Operating margin (GAAP) % | C17: =IFERROR(C15/C9,"") | D17: =IFERROR(D15/D9,"") | E17: =IFERROR(E15/E9,"") | F17: =IFERROR(F15/F9,"") | G17: =IFERROR(G15/G9,"") | H17: =IFERROR(H15/H9,"") | J17: =IFERROR(AVERAGE(Model!C253,Model!D253,Model!E253,Model!F253,Model!G253,Model!H253,Model!I253,Model!N253,Model!S253,Model!X253,Model!AC253,Model!AH253,Model!AM253,Model!AR253,Model!AW253,Model!BB253,Model!BG253,Model!BL253,Model!BQ253,Model!BV253),"") | K17: =IFERROR(MIN(Model!C253,Model!D253,Model!E253,Model!F253,Model!G253,Model!H253,Model!I253,Model!N253,Model!S253,Model!X253,Model!AC253,Model!AH253,Model!AM253,Model!AR253,Model!AW253,Model!BB253,Model!BG253,Model!BL253,Model!BQ253,Model!BV253),"") | L17: =IFERROR(MAX(Model!C253,Model!D253,Model!E253,Model!F253,Model!G253,Model!H253,Model!I253,Model!N253,Model!S253,Model!X253,Model!AC253,Model!AH253,Model!AM253,Model!AR253,Model!AW253,Model!BB253,Model!BG253,Model!BL253,Model!BQ253,Model!BV253),"") | N17: Operating margin (GAAP) % | O17: 0.16056237 | P17: 0.18226915 | Q17: 0.20437492 | R17: 0.20944259 | S17: 0.21427765 | T17: 0.21964028 | V17: 0.13551085 | W17: 0.080865854 | X17: 0.18364571 | Z17: Operating margin (GAAP) % | AA17: 0.16056237 | AB17: 0.1815471 | AC17: 0.17799815 | AD17: 0.18346196 | AE17: 0.18872034 | AF17: 0.19473126 | AH17: 0.13551085 | AI17: 0.080865854 | AJ17: 0.18364571
B19: Adjusted Net Income (attributable to Wabtec) | C19: =Model!BV229 | D19: =Model!CA229 | E19: =Model!CB229 | F19: =Model!CC229 | G19: =Model!CD229 | H19: =Model!CE229 | I19: =IFERROR((H19/C19)^(1/5)-1,"n/m") | N19: Adjusted Net Income (attributable to Wabtec) | O19: 1537 | P19: 1846.7714 | Q19: 2226.548 | R19: 2488.2882 | S19: 2765.9242 | T19: 3072.9904 | U19: 0.14862289 | Z19: Adjusted Net Income (attributable to Wabtec) | AA19: 1537 | AB19: 1798.7821 | AC19: 1801.4129 | AD19: 1923.1879 | AE19: 2013.3865 | AF19: 2111.7984 | AG19: 0.065603699
B21: FDSO (m) | C21: =Model!BV168 | D21: =Model!CA168 | E21: =Model!CB168 | F21: =Model!CC168 | G21: =Model!CD168 | H21: =Model!CE168 | I21: =IFERROR((H21/C21)^(1/5)-1,"n/m") | N21: FDSO (m) | O21: 171.1 | P21: 169.42857 | Q21: 165.74154 | R21: 161.1977 | S21: 156.58483 | T21: 151.40998 | U21: -0.024154866 | Z21: FDSO (m) | AA21: 171.1 | AB21: 169.69643 | AC21: 169.38389 | AD21: 167.39055 | AE21: 163.07475 | AF21: 158.8794 | AG21: -0.014711266
B23: Adjusted EPS — Diluted ($) | C23: =Model!BV232 | D23: =Model!CA232 | E23: =Model!CB232 | F23: =Model!CC232 | G23: =Model!CD232 | H23: =Model!CE232 | I23: =IFERROR((H23/C23)^(1/5)-1,"n/m") | N23: Adjusted EPS — Diluted ($) | O23: 8.9830508 | P23: 10.9 | Q23: 13.433856 | R23: 15.436251 | S23: 17.664063 | T23: 20.295824 | U23: 0.17705448 | Z23: Adjusted EPS — Diluted ($) | AA23: 8.9830508 | AB23: 10.6 | AC23: 10.63509 | AD23: 11.489226 | AE23: 12.346403 | AF23: 13.291833 | AG23: 0.081514141
B24: EPS y/y % | D24: =IFERROR(D23/C23-1,"") | E24: =IFERROR(E23/D23-1,"") | F24: =IFERROR(F23/E23-1,"") | G24: =IFERROR(G23/F23-1,"") | H24: =IFERROR(H23/G23-1,"") | N24: EPS y/y % | P24: 0.21339623 | Q24: 0.23246388 | R24: 0.14905587 | S24: 0.14432333 | T24: 0.14898959 | Z24: EPS y/y % | AB24: 0.18 | AC24: 0.0033103417 | AD24: 0.080313053 | AE24: 0.074607014 | AF24: 0.076575325
B26: P / E (x) — assumed (adjusted EPS) | G26: 23 | H26: 23 | N26: P / E (x) — assumed (adjusted EPS) | S26: 27 | T26: 27 | Z26: P / E (x) — assumed (adjusted EPS) | AD26: 18 | AE26: 18 | AF26: 18
B27: Price Target ($) | G27: =G26*G23 | H27: =H26*H23 | N27: Price Target ($) | S27: =S26*S23 | T27: =T26*T23 | Z27: Price Target ($) | AD27: =AD26*AD23 | AE27: =AE26*AE23 | AF27: =AF26*AF23
B28: Upside / (Downside) vs current | G28: =IFERROR(G27/$K$2-1,"") | H28: =IFERROR(H27/$K$2-1,"") | N28: Upside / (Downside) vs current | S28: =IFERROR(S27/$K$2-1,"") | T28: =IFERROR(T27/$K$2-1,"") | Z28: Upside / (Downside) vs current | AD28: =IFERROR(AD27/$K$2-1,"") | AE28: =IFERROR(AE27/$K$2-1,"") | AF28: =IFERROR(AF27/$K$2-1,"")
B29: IRR (to Dec-Y-1) | G29: =IFERROR((G27/$K$2)^(1/((DATE(2029-1,12,31)-$K$3)/365.25))-1,"") | H29: =IFERROR((H27/$K$2)^(1/((DATE(2030-1,12,31)-$K$3)/365.25))-1,"") | N29: IRR (to Dec-Y-1) | S29: =IFERROR((S27/$K$2)^(1/((DATE(2029-1,12,31)-$K$3)/365.25))-1,"") | T29: =IFERROR((T27/$K$2)^(1/((DATE(2030-1,12,31)-$K$3)/365.25))-1,"") | Z29: IRR (to Dec-Y-1) | AD29: =IFERROR((AD27/$K$2)^(1/((DATE(2028-1,12,31)-$K$3)/365.25))-1,"") | AE29: =IFERROR((AE27/$K$2)^(1/((DATE(2029-1,12,31)-$K$3)/365.25))-1,"") | AF29: =IFERROR((AF27/$K$2)^(1/((DATE(2030-1,12,31)-$K$3)/365.25))-1,"")
B31: Free Cash Flow | C31: =Model!BV285 | D31: =Model!CA285 | E31: =Model!CB285 | F31: =Model!CC285 | G31: =Model!CD285 | H31: =Model!CE285 | I31: =IFERROR((H31/C31)^(1/5)-1,"n/m") | N31: Free Cash Flow | O31: 1499 | P31: 1954.4584 | Q31: 2191.6393 | R31: 2396.7116 | S31: 2684.5449 | T31: 2989.6766 | U31: 0.14805982 | Z31: Free Cash Flow | AA31: 1499 | AB31: 1944.2536 | AC31: 1820.5997 | AD31: 1964.8352 | AE31: 2065.2929 | AF31: 2162.0908 | AG31: 0.076005422
B32: FCF % | C32: =IFERROR(C31/C9,"") | D32: =IFERROR(D31/D9,"") | E32: =IFERROR(E31/E9,"") | F32: =IFERROR(F31/F9,"") | G32: =IFERROR(G31/G9,"") | H32: =IFERROR(H31/H9,"") | J32: =IFERROR(AVERAGE(Model!C287,Model!D287,Model!E287,Model!F287,Model!G287,Model!H287,Model!I287,Model!N287,Model!S287,Model!X287,Model!AC287,Model!AH287,Model!AM287,Model!AR287,Model!AW287,Model!BB287,Model!BG287,Model!BL287,Model!BQ287,Model!BV287),"") | K32: =IFERROR(MIN(Model!C287,Model!D287,Model!E287,Model!F287,Model!G287,Model!H287,Model!I287,Model!N287,Model!S287,Model!X287,Model!AC287,Model!AH287,Model!AM287,Model!AR287,Model!AW287,Model!BB287,Model!BG287,Model!BL287,Model!BQ287,Model!BV287),"") | L32: =IFERROR(MAX(Model!C287,Model!D287,Model!E287,Model!F287,Model!G287,Model!H287,Model!I287,Model!N287,Model!S287,Model!X287,Model!AC287,Model!AH287,Model!AM287,Model!AR287,Model!AW287,Model!BB287,Model!BG287,Model!BL287,Model!BQ287,Model!BV287),"") | N32: FCF % | O32: 0.1342348 | P32: 0.15511575 | Q32: 0.15940627 | R32: 0.15800694 | S32: 0.16151914 | T32: 0.16450032 | V32: 0.10258846 | W32: 0.025580916 | X32: 0.15663811 | Z32: FCF % | AA32: 0.1342348 | AB32: 0.1580694 | AC32: 0.14409595 | AD32: 0.15100074 | AE32: 0.15481317 | AF32: 0.15803289 | AH32: 0.10258846 | AI32: 0.025580916 | AJ32: 0.15663811
B33: FCF / share ($) | C33: =IFERROR(C31/C21,"") | D33: =IFERROR(D31/D21,"") | E33: =IFERROR(E31/E21,"") | F33: =IFERROR(F31/F21,"") | G33: =IFERROR(G31/G21,"") | H33: =IFERROR(H31/H21,"") | N33: FCF / share ($) | O33: 8.7609585 | P33: 11.535589 | Q33: 13.223235 | R33: 14.868151 | S33: 17.144348 | T33: 19.745571 | Z33: FCF / share ($) | AA33: 8.7609585 | AB33: 11.457245 | AC33: 10.748364 | AD33: 11.738029 | AE33: 12.664701 | AF33: 13.608377
B34: FCF Yield (on PT) | F34: =IFERROR(F33/F$27,"") | G34: =IFERROR(G33/G$27,"") | H34: =IFERROR(H33/H$27,"") | N34: FCF Yield (on PT) | R34: =IFERROR(R33/R$27,"") | S34: =IFERROR(S33/S$27,"") | T34: =IFERROR(T33/T$27,"") | Z34: FCF Yield (on PT) | AD34: =IFERROR(AD33/AD$27,"") | AE34: =IFERROR(AE33/AE$27,"") | AF34: =IFERROR(AF33/AF$27,"")
B35: Adjusted EBITDA (leverage basis) | C35: =Model!BV194 | D35: =Model!CA194 | E35: =Model!CB194 | F35: =Model!CC194 | G35: =Model!CD194 | H35: =Model!CE194 | I35: =IFERROR((H35/C35)^(1/5)-1,"n/m") | N35: Adjusted EBITDA (leverage basis) | O35: 2464 | P35: 2944.2271 | Q35: 3437.3406 | R35: 3854.9365 | S35: 4290.5795 | T35: 4762.7654 | U35: 0.1408898 | Z35: Adjusted EBITDA (leverage basis) | AA35: 2464 | AB35: 2875.7214 | AC35: 2846.3296 | AD35: 2994.673 | AE35: 3134.3355 | AF35: 3279.3289 | AG35: 0.05883638
B36: Adjusted EBITDA % of net sales | C36: =IFERROR(C35/C9,"") | D36: =IFERROR(D35/D9,"") | E36: =IFERROR(E35/E9,"") | F36: =IFERROR(F35/F9,"") | G36: =IFERROR(G35/G9,"") | H36: =IFERROR(H35/H9,"") | J36: =IFERROR(AVERAGE(Model!C251,Model!D251,Model!E251,Model!F251,Model!G251,Model!H251,Model!I251,Model!N251,Model!S251,Model!X251,Model!AC251,Model!AH251,Model!AM251,Model!AR251,Model!AW251,Model!BB251,Model!BG251,Model!BL251,Model!BQ251,Model!BV251),"") | K36: =IFERROR(MIN(Model!C251,Model!D251,Model!E251,Model!F251,Model!G251,Model!H251,Model!I251,Model!N251,Model!S251,Model!X251,Model!AC251,Model!AH251,Model!AM251,Model!AR251,Model!AW251,Model!BB251,Model!BG251,Model!BL251,Model!BQ251,Model!BV251),"") | L36: =IFERROR(MAX(Model!C251,Model!D251,Model!E251,Model!F251,Model!G251,Model!H251,Model!I251,Model!N251,Model!S251,Model!X251,Model!AC251,Model!AH251,Model!AM251,Model!AR251,Model!AW251,Model!BB251,Model!BG251,Model!BL251,Model!BQ251,Model!BV251),"") | N36: Adjusted EBITDA % of net sales | O36: 0.22065013 | P36: 0.23366882 | Q36: 0.25001087 | R36: 0.25414267 | S36: 0.25814831 | T36: 0.26206059 | V36: 0.19446972 | W36: 0.1769299 | X36: 0.22065013 | Z36: Adjusted EBITDA % of net sales | AA36: 0.22065013 | AB36: 0.23379849 | AC36: 0.22527994 | AD36: 0.23014542 | AE36: 0.234948 | AF36: 0.23969475 | AH36: 0.19446972 | AI36: 0.1769299 | AJ36: 0.22065013
B38: Net Debt | C38: =Model!BV426 | D38: =Model!CA426 | E38: =Model!CB426 | F38: =Model!CC426 | G38: =Model!CD426 | H38: =Model!CE426 | N38: Net Debt | O38: 4752 | P38: 5082.83 | Q38: 6015.3461 | R38: 6746.1389 | S38: 7508.5141 | T38: 8334.8394 | Z38: Net Debt | AA38: 4752 | AB38: 4793.367 | AC38: 3557.912 | AD38: 3743.3412 | AE38: 3917.9194 | AF38: 4099.1611
B39: Net Debt / Adjusted EBITDA (x) | C39: =IFERROR(C38/C35,"") | D39: =IFERROR(D38/D35,"") | E39: =IFERROR(E38/E35,"") | F39: =IFERROR(F38/F35,"") | G39: =IFERROR(G38/G35,"") | H39: =IFERROR(H38/H35,"") | N39: Net Debt / Adjusted EBITDA (x) | O39: 1.9285714 | P39: 1.7263716 | Q39: 1.75 | R39: 1.75 | S39: 1.75 | T39: 1.75 | Z39: Net Debt / Adjusted EBITDA (x) | AA39: 1.9285714 | AB39: 1.6668398 | AC39: 1.25 | AD39: 1.25 | AE39: 1.25 | AF39: 1.25
B41: ROIC | C41: =Model!BV409 | D41: =Model!CA409 | E41: =Model!CB409 | F41: =Model!CC409 | G41: =Model!CD409 | H41: =Model!CE409 | J41: =IFERROR(AVERAGE(Model!C409,Model!D409,Model!E409,Model!F409,Model!G409,Model!H409,Model!I409,Model!N409,Model!S409,Model!X409,Model!AC409,Model!AH409,Model!AM409,Model!AR409,Model!AW409,Model!BB409,Model!BG409,Model!BL409,Model!BQ409,Model!BV409),"") | K41: =IFERROR(MIN(Model!C409,Model!D409,Model!E409,Model!F409,Model!G409,Model!H409,Model!I409,Model!N409,Model!S409,Model!X409,Model!AC409,Model!AH409,Model!AM409,Model!AR409,Model!AW409,Model!BB409,Model!BG409,Model!BL409,Model!BQ409,Model!BV409),"") | L41: =IFERROR(MAX(Model!C409,Model!D409,Model!E409,Model!F409,Model!G409,Model!H409,Model!I409,Model!N409,Model!S409,Model!X409,Model!AC409,Model!AH409,Model!AM409,Model!AR409,Model!AW409,Model!BB409,Model!BG409,Model!BL409,Model!BQ409,Model!BV409),"") | N41: ROIC | O41: 0.091825881 | P41: 0.10943943 | Q41: 0.12147935 | R41: 0.12876988 | S41: 0.13601087 | T41: 0.14410167 | V41: 0.12316765 | W41: 0.04674643 | X41: 0.2098046 | Z41: ROIC | AA41: 0.091825881 | AB41: 0.10680366 | AC41: 0.10392801 | AD41: 0.11004491 | AE41: 0.11585647 | AF41: 0.12231639 | AH41: 0.12316765 | AI41: 0.04674643 | AJ41: 0.2098046
B42: RONTA | C42: =Model!BV420 | D42: =Model!CA420 | E42: =Model!CB420 | F42: =Model!CC420 | G42: =Model!CD420 | H42: =Model!CE420 | J42: =IFERROR(AVERAGE(Model!C420,Model!D420,Model!E420,Model!F420,Model!G420,Model!H420,Model!I420,Model!N420,Model!S420,Model!X420,Model!AC420,Model!AH420,Model!AM420,Model!AR420,Model!AW420,Model!BB420,Model!BG420,Model!BL420,Model!BQ420,Model!BV420),"") | K42: =IFERROR(MIN(Model!C420,Model!D420,Model!E420,Model!F420,Model!G420,Model!H420,Model!I420,Model!N420,Model!S420,Model!X420,Model!AC420,Model!AH420,Model!AM420,Model!AR420,Model!AW420,Model!BB420,Model!BG420,Model!BL420,Model!BQ420,Model!BV420),"") | L42: =IFERROR(MAX(Model!C420,Model!D420,Model!E420,Model!F420,Model!G420,Model!H420,Model!I420,Model!N420,Model!S420,Model!X420,Model!AC420,Model!AH420,Model!AM420,Model!AR420,Model!AW420,Model!BB420,Model!BG420,Model!BL420,Model!BQ420,Model!BV420),"") | N42: RONTA | O42: 0.3557444 | P42: 0.43275229 | Q42: 0.48077661 | R42: 0.50337256 | S42: 0.52464166 | T42: 0.54760299 | V42: 0.23875302 | W42: 0.10751575 | X42: 0.3557444 | Z42: RONTA | AA42: 0.3557444 | AB42: 0.4115263 | AC42: 0.30460099 | AD42: 0.32738441 | AE42: 0.34943777 | AF42: 0.37458158 | AH42: 0.23875302 | AI42: 0.10751575 | AJ42: 0.3557444
B44: Implied Market Cap (USDm) | F44: =F27*F21 | G44: =G27*G21 | H44: =H27*H21 | N44: Implied Market Cap (USDm) | R44: =R27*R21 | S44: =S27*S21 | T44: =T27*T21 | Z44: Implied Market Cap (USDm) | AD44: =AD27*AD21 | AE44: =AE27*AE21 | AF44: =AF27*AF21
B45: (+) Net Debt & NCI | F45: =F38+Model!CC337 | G45: =G38+Model!CD337 | H45: =H38+Model!CE337 | N45: (+) Net Debt & NCI | R45: =R38+Model!CC337 | S45: =S38+Model!CD337 | T45: =T38+Model!CE337 | Z45: (+) Net Debt & NCI | AD45: =AD38+Model!CC337 | AE45: =AE38+Model!CD337 | AF45: =AF38+Model!CE337
B46: Implied Enterprise Value (USDm) | F46: =F44+F45 | G46: =G44+G45 | H46: =H44+H45 | N46: Implied Enterprise Value (USDm) | R46: =R44+R45 | S46: =S44+S45 | T46: =T44+T45 | Z46: Implied Enterprise Value (USDm) | AD46: =AD44+AD45 | AE46: =AE44+AE45 | AF46: =AF44+AF45
B47: Implied EV / Adjusted EBITDA (x) | F47: =IFERROR(F46/F35,"") | G47: =IFERROR(G46/G35,"") | H47: =IFERROR(H46/H35,"") | N47: Implied EV / Adjusted EBITDA (x) | R47: =IFERROR(R46/R35,"") | S47: =IFERROR(S46/S35,"") | T47: =IFERROR(T46/T35,"") | Z47: Implied EV / Adjusted EBITDA (x) | AD47: =IFERROR(AD46/AD35,"") | AE47: =IFERROR(AE46/AE35,"") | AF47: =IFERROR(AF46/AF35,"")

Sheet DCF
B2: DCF VALUATION — WESTINGHOUSE AIR BRAKE TECHNOLOGIES (WAB)
B4: 1. WACC BUILD
B5: Risk-free rate (US 10Y govt) | C5: 0.055 | D5: Assumption (~US 10Y Treasury yield); update to market
B6: Equity risk premium | C6: 0.05 | D6: US implied ERP ~4.5–5.5% (Damodaran)
B7: Levered beta | C7: 1.05 | D7: Rail equipment / transportation-technology peers (Knorr-Bremse, Alstom, Siemens Mobility, Trinity, Greenbrier) ~0.9–1.2; 25,000+ locomotive installed base and multi-year backlog ($30.9bn) dampen cyclicality
B8: Cost of equity | C8: =C5+C7*C6
B9: Pre-tax cost of debt | C9: 0.055 | D9: Investment grade (BBB / Baa2); 5.50% 2035 and 4.90% 2030 notes issued 2025; marginal cost ~5.0–5.5%
B10: Tax rate | C10: 0.245 | D10: Model 2027E+ effective tax rate (FY26 guidance ~24.5%)
B11: After-tax cost of debt | C11: =C9*(1-C10)
B12: Target D/V | C12: 0.15 | D12: Net debt ~$5.9bn at 30-Jun-26 vs ~$47bn market cap ($280 × ~169m shares); ~2.0x Adjusted EBITDA, targeted 2.0–2.5x
B13: WACC | C13: =C8*(1-C12)+C11*C12
B15: Valuation date (live) | C15: =TODAY() | D15: Periods = (Dec-31-Year − today) / 365.25; cash flows assumed at year-end
B16: 2. UNLEVERED FREE CASH FLOW BUILD (USDm)
D17: 2026E | E17: 2027E | F17: 2028E | G17: 2029E | H17: 2030E | I17: 2031E | J17: 2032E | K17: 2033E | L17: 2034E | M17: 2035E | N17: Terminal | P17: CAGR 26–30E | Q17: CAGR 26–35E
B18: Adjusted EBIT (Model; Adjusted EBITDA − DD&A) | D18: =Model!CA201 | E18: =Model!CB201 | F18: =Model!CC201 | G18: =Model!CD201 | H18: =Model!CE201 | I18: =H18*(1+I$31) | J18: =I18*(1+J$31) | K18: =J18*(1+K$31) | L18: =K18*(1+L$31) | M18: =L18*(1+M$31) | P18: =IFERROR(($H18/$D18)^(1/(VALUE(LEFT($H$17,4))-VALUE(LEFT($D$17,4))))-1,"n/m") | Q18: =IFERROR(($M18/$D18)^(1/(VALUE(LEFT($M$17,4))-VALUE(LEFT($D$17,4))))-1,"n/m")
B19: y/y % | E19: =IFERROR(E18/D18-1,"") | F19: =IFERROR(F18/E18-1,"") | G19: =IFERROR(G18/F18-1,"") | H19: =IFERROR(H18/G18-1,"") | I19: =IFERROR(I18/H18-1,"") | J19: =IFERROR(J18/I18-1,"") | K19: =IFERROR(K18/J18-1,"") | L19: =IFERROR(L18/K18-1,"") | M19: =IFERROR(M18/L18-1,"")
B20: (−) Restructuring & transaction costs (cash; added back in Adjusted EBITDA) | D20: =-Model!CA208 | E20: =-Model!CB208 | F20: =-Model!CC208 | G20: =-Model!CD208 | H20: =-Model!CE208 | I20: =H20*(1+I$31) | J20: =I20*(1+J$31) | K20: =J20*(1+K$31) | L20: =K20*(1+L$31) | M20: =L20*(1+M$31)
B21: × (1 − tax rate) | D21: =1-$C$10 | E21: =1-$C$10 | F21: =1-$C$10 | G21: =1-$C$10 | H21: =1-$C$10 | I21: =1-$C$10 | J21: =1-$C$10 | K21: =1-$C$10 | ... M21: =1-$C$10
B22: NOPAT = (Adjusted EBIT − restructuring & transaction costs) × (1 − t) | D22: =(D18+D20)*D21 | E22: =(E18+E20)*E21 | F22: =(F18+F20)*F21 | G22: =(G18+G20)*G21 | H22: =(H18+H20)*H21 | I22: =(I18+I20)*I21 | J22: =(J18+J20)*J21 | K22: =(K18+K20)*K21 | ... M22: =(M18+M20)*M21
B23: plus depreciation & amortization (total, incl. acquired-intangible amortization) | D23: =Model!CA164 | E23: =Model!CB164 | F23: =Model!CC164 | G23: =Model!CD164 | H23: =Model!CE164 | I23: =H23*(1+I$31) | J23: =I23*(1+J$31) | K23: =J23*(1+K$31) | L23: =K23*(1+L$31) | M23: =L23*(1+M$31)
B24: − Capex (PP&E) and acquisitions (M&A lever, 2027E+) | D24: =D29 | E24: =E29+Model!CB268 | F24: =F29+Model!CC268 | G24: =G29+Model!CD268 | H24: =H29+Model!CE268 | I24: =I29 | J24: =J29 | K24: =K29 | L24: =L29 | M24: =M29
B25: − Δ Working capital (CF statement) | D25: =Model!CA265 | E25: =Model!CB265 | F25: =Model!CC265 | G25: =Model!CD265 | H25: =Model!CE265 | I25: =H25*(1+I$31) | J25: =I25*(1+J$31) | K25: =J25*(1+K$31) | L25: =K25*(1+L$31) | M25: =L25*(1+M$31)
B26: Unlevered FCF | D26: =D22+D23+D24+D25 | E26: =E22+E23+E24+E25 | F26: =F22+F23+F24+F25 | G26: =G22+G23+G24+G25 | H26: =H22+H23+H24+H25 | I26: =I22+I23+I24+I25 | J26: =J22+J23+J24+J25 | K26: =K22+K23+K24+K25 | ... M26: =M22+M23+M24+M25 | N26: =M26*(1+$C$32) | P26: =IFERROR(($H26/$D26)^(1/(VALUE(LEFT($H$17,4))-VALUE(LEFT($D$17,4))))-1,"n/m") | Q26: =IFERROR(($M26/$D26)^(1/(VALUE(LEFT($M$17,4))-VALUE(LEFT($D$17,4))))-1,"n/m")
B27: y/y % | E27: =IFERROR(E26/D26-1,"") | F27: =IFERROR(F26/E26-1,"") | G27: =IFERROR(G26/F26-1,"") | H27: =IFERROR(H26/G26-1,"") | I27: =IFERROR(I26/H26-1,"") | J27: =IFERROR(J26/I26-1,"") | K27: =IFERROR(K26/J26-1,"") | L27: =IFERROR(L26/K26-1,"") | M27: =IFERROR(M26/L26-1,"")
B28: Terminal Value (Gordon Growth) | N28: =N26/($C$13-$C$32)
B29: memo: PP&E capex only (fade years carry no new acquisitions) | D29: =Model!CA267 | E29: =Model!CB267 | F29: =Model!CC267 | G29: =Model!CD267 | H29: =Model!CE267 | I29: =H29*(1+I$31) | J29: =I29*(1+J$31) | K29: =J29*(1+K$31) | L29: =K29*(1+L$31) | M29: =L29*(1+M$31)
B31: Fade-period growth (2031E–35E) | I31: 0.06 | J31: =I31+($M$31-$I$31)/(COLUMNS($I$31:$M$31)-1) | K31: =J31+($M$31-$I$31)/(COLUMNS($I$31:$M$31)-1) | L31: =K31+($M$31-$I$31)/(COLUMNS($I$31:$M$31)-1) | M31: 0.05
B32: Terminal growth rate | C32: 0.04
B34: Discount period (years) | D34: =(DATE(2026,12,31)-$C$15)/365.25 | E34: =(DATE(2027,12,31)-$C$15)/365.25 | F34: =(DATE(2028,12,31)-$C$15)/365.25 | G34: =(DATE(2029,12,31)-$C$15)/365.25 | H34: =(DATE(2030,12,31)-$C$15)/365.25 | I34: =(DATE(2031,12,31)-$C$15)/365.25 | J34: =(DATE(2032,12,31)-$C$15)/365.25 | K34: =(DATE(2033,12,31)-$C$15)/365.25 | L34: =(DATE(2034,12,31)-$C$15)/365.25 | M34: =(DATE(2035,12,31)-$C$15)/365.25 | N34: =M34
B35: Discount factor | D35: =1/(1+$C$13)^D34 | E35: =1/(1+$C$13)^E34 | F35: =1/(1+$C$13)^F34 | G35: =1/(1+$C$13)^G34 | H35: =1/(1+$C$13)^H34 | I35: =1/(1+$C$13)^I34 | J35: =1/(1+$C$13)^J34 | K35: =1/(1+$C$13)^K34 | ... N35: =1/(1+$C$13)^N34
B36: PV of UFCF | D36: =D26*D35 | E36: =E26*E35 | F36: =F26*F35 | G36: =G26*G35 | H36: =H26*H35 | I36: =I26*I35 | J36: =J26*J35 | K36: =K26*K35 | ... M36: =M26*M35 | N36: =N28*N35
D37: Wabtec's Adjusted EBITDA expenses stock-based compensation; Adjusted EBIT deducts all D&A incl. ~$350m p.a. of acquired-intangible amortization (non-cash, added back in row 23). The 1H/26 Dellner cash consideration (~$1.06bn) is excluded from 2026E UFCF and added to opening invested capital.
B39: Implied ROIC & incremental ROIC (USDm) | D39: =D17 | E39: =E17 | F39: =F17 | G39: =G17 | H39: =H17 | I39: =I17 | J39: =J17 | K39: =K17 | ... M39: =M17 | N39: Terminal
B40: NOPAT (row 22) | D40: =D22 | E40: =E22 | F40: =F22 | G40: =G22 | H40: =H22 | I40: =I22 | J40: =J22 | K40: =K22 | ... M40: =M22 | N40: =M40*(1+$C$32)
B41: Net investment = NOPAT − UFCF | D41: =D40-D26 | E41: =E40-E26 | F41: =F40-F26 | G41: =G40-G26 | H41: =H40-H26 | I41: =I40-I26 | J41: =J40-J26 | K41: =K40-K26 | ... N41: =N40-N26
B42: Opening invested capital | D42: =Model!BV406-Model!CA268 | E42: =D43 | F42: =E43 | G42: =F43 | H42: =G43 | I42: =H43 | J42: =I43 | K42: =J43 | L42: =K43 | ... N42: =M43
B43: Closing invested capital | D43: =D42+D41 | E43: =E42+E41 | F43: =F42+F41 | G43: =G42+G41 | H43: =H42+H41 | I43: =I42+I41 | J43: =J42+J41 | K43: =K42+K41 | ... M43: =M42+M41
B44: Implied ROIC = NOPAT / opening IC | D44: =IFERROR(D40/D42,"") | E44: =IFERROR(E40/E42,"") | F44: =IFERROR(F40/F42,"") | G44: =IFERROR(G40/G42,"") | H44: =IFERROR(H40/H42,"") | I44: =IFERROR(I40/I42,"") | J44: =IFERROR(J40/J42,"") | K44: =IFERROR(K40/K42,"") | ... N44: =IFERROR(N40/N42,"")
B45: Reinvestment rate = net inv. / NOPAT | D45: =IFERROR(D41/D40,"") | E45: =IFERROR(E41/E40,"") | F45: =IFERROR(F41/F40,"") | G45: =IFERROR(G41/G40,"") | H45: =IFERROR(H41/H40,"") | I45: =IFERROR(I41/I40,"") | J45: =IFERROR(J41/J40,"") | K45: =IFERROR(K41/K40,"") | ... N45: =IFERROR(N41/N40,"")
B46: Incremental ROIC = Δ NOPAT / prior-yr net inv. | E46: =IFERROR((E40-D40)/D41,"") | F46: =IFERROR((F40-E40)/E41,"") | G46: =IFERROR((G40-F40)/F41,"") | H46: =IFERROR((H40-G40)/G41,"") | I46: =IFERROR((I40-H40)/H41,"") | J46: =IFERROR((J40-I40)/I41,"") | K46: =IFERROR((K40-J40)/J41,"") | L46: =IFERROR((L40-K40)/K41,"") | M46: =IFERROR((M40-L40)/L41,"") | N46: =IFERROR($C$32/N45,"")
B47: Cumulative incremental ROIC 2026E–35E | C47: =IFERROR((M40-D40)/SUM(D41:L41),"")
D48: Opening IC = Model 2025A book IC (equity + net debt) + 2026 acquisitions (Dellner, ~$1.06bn cash), rolled forward with DCF net investment (capex + M&A − D&A + ΔWC). Terminal incremental ROIC = g / reinvestment rate.
B49: 3. VALUATION SUMMARY
B50: Sum of PV (explicit + fade) | C50: =SUM(D36:M36)
B51: PV of Terminal Value | C51: =N36
B52: Enterprise Value | C52: =C50+C51
B53: Less: net debt (Model 2026E YE) | C53: =Model!CA426
B54: Less: non-controlling interests (Model 2026E) | C54: =Model!CA337
B55: Equity Value | C55: =C52-C53-C54
B56: Diluted shares (m, Model 2026E period end) | C56: =Model!CA432
B57: Implied share price ($) | C57: =C55/C56
B58: Current share price ($) | C58: =Model!CA431
B59: Implied upside / (downside) | C59: =C57/C58-1
B60: Required discount to DCF value for target IRR (discount closes over horizon; value compounds at WACC) | C60: =1-((1+C13)/(1+F60))^F61 | E60: Target IRR | F60: 0.15
B61: Max entry price for target IRR ($) — % vs. current share price shown right | C61: =C57*(1-C60) | D61: =C61/C58-1 | E61: Years for discount to close | F61: 3
B64: 4. SENSITIVITY: IMPLIED PRICE ($) — WACC × Terminal Growth
B65: WACC step (across) | C65: 0.005
B66: Terminal growth step (down) | C66: 0.005
B67: g (down) / WACC | D67: =E67-$C$65 | E67: =F67-$C$65 | F67: =$C$13 | G67: =F67+$C$65 | H67: =G67+$C$65
B68: =B69-$C$66 | D68: =IFERROR((SUMPRODUCT($D$26:$M$26/(1+D$67)^$D$34:$M$34)+($M$26*(1+$B68)/(D$67-$B68))/(1+D$67)^$M$34-$C$53-$C$54)/$C$56,"") | E68: =IFERROR((SUMPRODUCT($D$26:$M$26/(1+E$67)^$D$34:$M$34)+($M$26*(1+$B68)/(E$67-$B68))/(1+E$67)^$M$34-$C$53-$C$54)/$C$56,"") | F68: =IFERROR((SUMPRODUCT($D$26:$M$26/(1+F$67)^$D$34:$M$34)+($M$26*(1+$B68)/(F$67-$B68))/(1+F$67)^$M$34-$C$53-$C$54)/$C$56,"") | G68: =IFERROR((SUMPRODUCT($D$26:$M$26/(1+G$67)^$D$34:$M$34)+($M$26*(1+$B68)/(G$67-$B68))/(1+G$67)^$M$34-$C$53-$C$54)/$C$56,"") | H68: =IFERROR((SUMPRODUCT($D$26:$M$26/(1+H$67)^$D$34:$M$34)+($M$26*(1+$B68)/(H$67-$B68))/(1+H$67)^$M$34-$C$53-$C$54)/$C$56,"")
B69: =B70-$C$66 | D69: =IFERROR((SUMPRODUCT($D$26:$M$26/(1+D$67)^$D$34:$M$34)+($M$26*(1+$B69)/(D$67-$B69))/(1+D$67)^$M$34-$C$53-$C$54)/$C$56,"") | E69: =IFERROR((SUMPRODUCT($D$26:$M$26/(1+E$67)^$D$34:$M$34)+($M$26*(1+$B69)/(E$67-$B69))/(1+E$67)^$M$34-$C$53-$C$54)/$C$56,"") | F69: =IFERROR((SUMPRODUCT($D$26:$M$26/(1+F$67)^$D$34:$M$34)+($M$26*(1+$B69)/(F$67-$B69))/(1+F$67)^$M$34-$C$53-$C$54)/$C$56,"") | G69: =IFERROR((SUMPRODUCT($D$26:$M$26/(1+G$67)^$D$34:$M$34)+($M$26*(1+$B69)/(G$67-$B69))/(1+G$67)^$M$34-$C$53-$C$54)/$C$56,"") | H69: =IFERROR((SUMPRODUCT($D$26:$M$26/(1+H$67)^$D$34:$M$34)+($M$26*(1+$B69)/(H$67-$B69))/(1+H$67)^$M$34-$C$53-$C$54)/$C$56,"")
B70: =$C$32 | D70: =IFERROR((SUMPRODUCT($D$26:$M$26/(1+D$67)^$D$34:$M$34)+($M$26*(1+$B70)/(D$67-$B70))/(1+D$67)^$M$34-$C$53-$C$54)/$C$56,"") | E70: =IFERROR((SUMPRODUCT($D$26:$M$26/(1+E$67)^$D$34:$M$34)+($M$26*(1+$B70)/(E$67-$B70))/(1+E$67)^$M$34-$C$53-$C$54)/$C$56,"") | F70: =IFERROR((SUMPRODUCT($D$26:$M$26/(1+F$67)^$D$34:$M$34)+($M$26*(1+$B70)/(F$67-$B70))/(1+F$67)^$M$34-$C$53-$C$54)/$C$56,"") | G70: =IFERROR((SUMPRODUCT($D$26:$M$26/(1+G$67)^$D$34:$M$34)+($M$26*(1+$B70)/(G$67-$B70))/(1+G$67)^$M$34-$C$53-$C$54)/$C$56,"") | H70: =IFERROR((SUMPRODUCT($D$26:$M$26/(1+H$67)^$D$34:$M$34)+($M$26*(1+$B70)/(H$67-$B70))/(1+H$67)^$M$34-$C$53-$C$54)/$C$56,"")
B71: =B70+$C$66 | D71: =IFERROR((SUMPRODUCT($D$26:$M$26/(1+D$67)^$D$34:$M$34)+($M$26*(1+$B71)/(D$67-$B71))/(1+D$67)^$M$34-$C$53-$C$54)/$C$56,"") | E71: =IFERROR((SUMPRODUCT($D$26:$M$26/(1+E$67)^$D$34:$M$34)+($M$26*(1+$B71)/(E$67-$B71))/(1+E$67)^$M$34-$C$53-$C$54)/$C$56,"") | F71: =IFERROR((SUMPRODUCT($D$26:$M$26/(1+F$67)^$D$34:$M$34)+($M$26*(1+$B71)/(F$67-$B71))/(1+F$67)^$M$34-$C$53-$C$54)/$C$56,"") | G71: =IFERROR((SUMPRODUCT($D$26:$M$26/(1+G$67)^$D$34:$M$34)+($M$26*(1+$B71)/(G$67-$B71))/(1+G$67)^$M$34-$C$53-$C$54)/$C$56,"") | H71: =IFERROR((SUMPRODUCT($D$26:$M$26/(1+H$67)^$D$34:$M$34)+($M$26*(1+$B71)/(H$67-$B71))/(1+H$67)^$M$34-$C$53-$C$54)/$C$56,"")
B72: =B71+$C$66 | D72: =IFERROR((SUMPRODUCT($D$26:$M$26/(1+D$67)^$D$34:$M$34)+($M$26*(1+$B72)/(D$67-$B72))/(1+D$67)^$M$34-$C$53-$C$54)/$C$56,"") | E72: =IFERROR((SUMPRODUCT($D$26:$M$26/(1+E$67)^$D$34:$M$34)+($M$26*(1+$B72)/(E$67-$B72))/(1+E$67)^$M$34-$C$53-$C$54)/$C$56,"") | F72: =IFERROR((SUMPRODUCT($D$26:$M$26/(1+F$67)^$D$34:$M$34)+($M$26*(1+$B72)/(F$67-$B72))/(1+F$67)^$M$34-$C$53-$C$54)/$C$56,"") | G72: =IFERROR((SUMPRODUCT($D$26:$M$26/(1+G$67)^$D$34:$M$34)+($M$26*(1+$B72)/(G$67-$B72))/(1+G$67)^$M$34-$C$53-$C$54)/$C$56,"") | H72: =IFERROR((SUMPRODUCT($D$26:$M$26/(1+H$67)^$D$34:$M$34)+($M$26*(1+$B72)/(H$67-$B72))/(1+H$67)^$M$34-$C$53-$C$54)/$C$56,"")
B75: 5. REVERSE DCF
B76: To solve for the market-implied path: Data ▸ What-If Analysis ▸ Goal Seek — set C57 (implied price) to the current price (C58) by changing C32 (terminal growth) or the Model scenario levers (product-line growth, segment adjusted margins).
B78: 6. MAUBOUSSIN EV / NOPAT — TWO-STAGE FRAMEWORK
B79: EV/NOPAT = 1/r + [g × (1 − r/ROIIC) / (r × (r − g))] × [1 − ((1+g)/(1+r))^N]
B80: Formula source: Mauboussin & Rappaport, "Expectations Investing" (2021); Counterpoint Global, "What Does a Price-Earnings Multiple Mean?" (2020).
B82: Input | C82: Value | D82: Rationale (Wabtec characteristics)
B83: r (Cost of capital / WACC) | C83: =$C$13 | D83: Linked from Section 1 WACC build
B84: g (NOPAT growth, Stage 1) | C84: 0.09 | D84: Model Adjusted EBIT CAGR 2026–30E: mid-single-digit organic growth (locomotive & digital backlog), 50–100 bps p.a. margin expansion, bolt-on M&A → ~9–10% NOPAT growth
B85: ROIIC (Return on incremental invested capital) | C85: 0.14 | D85: Installed-base aftermarket (services ~25% of sales) and proprietary locomotive / brake / PTC technology earn high returns on organic investment (capex ~2% of sales); acquired growth earns ~7–9% after tax on purchase price
B86: N (Years of value creation / CAP) | C86: 12 | D86: Duopoly in N.A. freight locomotives with ~25,000-unit installed base, 20–30-year asset lives and multi-year backlog; disciplined Integration 3.0 / portfolio optimization
B88: Calculation | C88: Value
B89: Steady-state component: 1 / r | C89: =1/C83
B90: Value-creation factor: 1 − r / ROIIC | C90: =1-C83/C85
B91: Growth multiplier: g × (1 − r/ROIIC) / (r × (r − g)) | C91: =C84*C90/(C83*(C83-C84))
B92: Time decay: 1 − ((1+g)/(1+r))^N | C92: =1-((1+C84)/(1+C83))^C86
B93: PVGO component (growth value) | C93: =C91*C92
B94: Mauboussin EV / NOPAT (steady-state + PVGO) | C94: =C89+C93
B96: VALUATION — Applied to 2028E NOPAT | C96: USDm
B97: 2028E Adjusted EBIT (Model) | C97: =Model!CC201
B98: (−) 2028E restructuring & transaction costs | C98: =-Model!CC208
B99: Tax rate (from WACC build) | C99: =$C$10
B100: 2028E NOPAT = (Adj. EBIT − restructuring & transaction costs) × (1 − t) | C100: =(C97+C98)*(1-C99)
B101: × Mauboussin EV/NOPAT multiple | C101: =C94
B102: Implied Enterprise Value (2028E basis) | C102: =C100*C101
B103: Less: YE2027 net debt + NCI (Model) | C103: =Model!CB426+Model!CB337
B104: Implied Equity Value | C104: =C102-C103
B105: Diluted shares 2028E (m, Model) | C105: =Model!CC432
B106: Implied share price 2028 ($) | C106: =C104/C105
B108: Current share price ($) | C108: =C58
B109: Implied upside / (downside) | C109: =C106/C108-1
B111: MARKET-IMPLIED EV/NOPAT TODAY | C111: USDm
B112: Current market cap (spot × diluted shares) | C112: =C58*C56
B113: Plus: YE2026 net debt & NCI | C113: =C53+C54
B114: Implied Enterprise Value (today) | C114: =C112+C113
B115: WAB's market-implied EV/NOPAT (on 2028E NOPAT) | C115: =C114/C100
B117: Multiple gap (Mauboussin − Market) | C117: =C94-C115
...

Sheet Charts
B2: Westinghouse Air Brake Technologies (Wabtec) — Historical Operating Performance (2006–2025)
B3: All historicals · USDm · Linked to Model. Bars = Freight and Transit segment net sales y/y (as originally reported; 2019 includes GE Transportation from 25-Feb-2019). Adjusted EBITDA as reconciled by Wabtec in each period (published from 2019; EBITDA definition per Model). ROIC / RONTA on Adjusted EBIT.
C7: 2006 | D7: 2007 | E7: 2008 | F7: 2009 | G7: 2010 | H7: 2011 | I7: 2012 | J7: 2013 | K7: 2014 | L7: 2015 | M7: 2016 | N7: 2017 | O7: 2018 | P7: 2019 | Q7: 2020 | R7: 2021 | S7: 2022 | T7: 2023 | U7: 2024 | V7: 2025
B8: Freight segment sales y/y % | C8: =IFERROR(Model!C28+0,IFERROR(Model!C28+0,0)) | D8: =IFERROR(Model!D28+0,IFERROR(Model!D28+0,0)) | E8: =IFERROR(Model!E28+0,IFERROR(Model!E28+0,0)) | F8: =IFERROR(Model!F28+0,IFERROR(Model!F28+0,0)) | G8: =IFERROR(Model!G28+0,IFERROR(Model!G28+0,0)) | H8: =IFERROR(Model!H28+0,IFERROR(Model!H28+0,0)) | I8: =IFERROR(Model!I28+0,IFERROR(Model!I28+0,0)) | J8: =IFERROR(Model!N28+0,IFERROR(Model!N28+0,0)) | K8: =IFERROR(Model!S28+0,IFERROR(Model!S28+0,0)) | L8: =IFERROR(Model!X28+0,IFERROR(Model!X28+0,0)) | M8: =IFERROR(Model!AC28+0,IFERROR(Model!AC28+0,0)) | N8: =IFERROR(Model!AH28+0,IFERROR(Model!AH28+0,0)) | O8: =IFERROR(Model!AM28+0,IFERROR(Model!AM28+0,0)) | P8: =IFERROR(Model!AR28+0,IFERROR(Model!AR28+0,0)) | Q8: =IFERROR(Model!AW28+0,IFERROR(Model!AW28+0,0)) | R8: =IFERROR(Model!BB28+0,IFERROR(Model!BB28+0,0)) | S8: =IFERROR(Model!BG28+0,IFERROR(Model!BG28+0,0)) | T8: =IFERROR(Model!BL28+0,IFERROR(Model!BL28+0,0)) | U8: =IFERROR(Model!BQ28+0,IFERROR(Model!BQ28+0,0)) | V8: =IFERROR(Model!BV28+0,IFERROR(Model!BV28+0,0))
B9: Transit segment sales y/y % | C9: =IFERROR(Model!C52+0,IFERROR(Model!C52+0,0)) | D9: =IFERROR(Model!D52+0,IFERROR(Model!D52+0,0)) | E9: =IFERROR(Model!E52+0,IFERROR(Model!E52+0,0)) | F9: =IFERROR(Model!F52+0,IFERROR(Model!F52+0,0)) | G9: =IFERROR(Model!G52+0,IFERROR(Model!G52+0,0)) | H9: =IFERROR(Model!H52+0,IFERROR(Model!H52+0,0)) | I9: =IFERROR(Model!I52+0,IFERROR(Model!I52+0,0)) | J9: =IFERROR(Model!N52+0,IFERROR(Model!N52+0,0)) | K9: =IFERROR(Model!S52+0,IFERROR(Model!S52+0,0)) | L9: =IFERROR(Model!X52+0,IFERROR(Model!X52+0,0)) | M9: =IFERROR(Model!AC52+0,IFERROR(Model!AC52+0,0)) | N9: =IFERROR(Model!AH52+0,IFERROR(Model!AH52+0,0)) | O9: =IFERROR(Model!AM52+0,IFERROR(Model!AM52+0,0)) | P9: =IFERROR(Model!AR52+0,IFERROR(Model!AR52+0,0)) | Q9: =IFERROR(Model!AW52+0,IFERROR(Model!AW52+0,0)) | R9: =IFERROR(Model!BB52+0,IFERROR(Model!BB52+0,0)) | S9: =IFERROR(Model!BG52+0,IFERROR(Model!BG52+0,0)) | T9: =IFERROR(Model!BL52+0,IFERROR(Model!BL52+0,0)) | U9: =IFERROR(Model!BQ52+0,IFERROR(Model!BQ52+0,0)) | V9: =IFERROR(Model!BV52+0,IFERROR(Model!BV52+0,0))
C11: =C7 | D11: =D7 | E11: =E7 | F11: =F7 | G11: =G7 | H11: =H7 | I11: =I7 | J11: =J7 | ... V11: =V7
B12: Adjusted EBITDA | C12: =Model!C194 | D12: =Model!D194 | E12: =Model!E194 | F12: =Model!F194 | G12: =Model!G194 | H12: =Model!H194 | I12: =Model!I194 | J12: =Model!N194 | K12: =Model!S194 | L12: =Model!X194 | M12: =Model!AC194 | N12: =Model!AH194 | O12: =Model!AM194 | P12: =Model!AR194 | Q12: =Model!AW194 | R12: =Model!BB194 | S12: =Model!BG194 | T12: =Model!BL194 | U12: =Model!BQ194 | V12: =Model!BV194
B13: Income from Operations (GAAP) | C13: =Model!C150 | D13: =Model!D150 | E13: =Model!E150 | F13: =Model!F150 | G13: =Model!G150 | H13: =Model!H150 | I13: =Model!I150 | J13: =Model!N150 | K13: =Model!S150 | L13: =Model!X150 | M13: =Model!AC150 | N13: =Model!AH150 | O13: =Model!AM150 | P13: =Model!AR150 | Q13: =Model!AW150 | R13: =Model!BB150 | S13: =Model!BG150 | T13: =Model!BL150 | U13: =Model!BQ150 | V13: =Model!BV150
B14: Adj. EBITDA Margin % | C14: =Model!C251 | D14: =Model!D251 | E14: =Model!E251 | F14: =Model!F251 | G14: =Model!G251 | H14: =Model!H251 | I14: =Model!I251 | J14: =Model!N251 | K14: =Model!S251 | L14: =Model!X251 | M14: =Model!AC251 | N14: =Model!AH251 | O14: =Model!AM251 | P14: =Model!AR251 | Q14: =Model!AW251 | R14: =Model!BB251 | S14: =Model!BG251 | T14: =Model!BL251 | U14: =Model!BQ251 | V14: =Model!BV251
B15: GAAP Op. Margin % | C15: =Model!C253 | D15: =Model!D253 | E15: =Model!E253 | F15: =Model!F253 | G15: =Model!G253 | H15: =Model!H253 | I15: =Model!I253 | J15: =Model!N253 | K15: =Model!S253 | L15: =Model!X253 | M15: =Model!AC253 | N15: =Model!AH253 | O15: =Model!AM253 | P15: =Model!AR253 | Q15: =Model!AW253 | R15: =Model!BB253 | S15: =Model!BG253 | T15: =Model!BL253 | U15: =Model!BQ253 | V15: =Model!BV253
C17: =C7 | D17: =D7 | E17: =E7 | F17: =F7 | G17: =G7 | H17: =H7 | I17: =I7 | J17: =J7 | ... V17: =V7
B18: ROIC | C18: =IFERROR(Model!C409+0,NA()) | D18: =IFERROR(Model!D409+0,NA()) | E18: =IFERROR(Model!E409+0,NA()) | F18: =IFERROR(Model!F409+0,NA()) | G18: =IFERROR(Model!G409+0,NA()) | H18: =IFERROR(Model!H409+0,NA()) | I18: =IFERROR(Model!I409+0,NA()) | J18: =IFERROR(Model!N409+0,NA()) | K18: =IFERROR(Model!S409+0,NA()) | L18: =IFERROR(Model!X409+0,NA()) | M18: =IFERROR(Model!AC409+0,NA()) | N18: =IFERROR(Model!AH409+0,NA()) | O18: =IFERROR(Model!AM409+0,NA()) | P18: =IFERROR(Model!AR409+0,NA()) | Q18: =IFERROR(Model!AW409+0,NA()) | R18: =IFERROR(Model!BB409+0,NA()) | S18: =IFERROR(Model!BG409+0,NA()) | T18: =IFERROR(Model!BL409+0,NA()) | U18: =IFERROR(Model!BQ409+0,NA()) | V18: =IFERROR(Model!BV409+0,NA())
B19: RONTA | C19: =IFERROR(Model!C420+0,NA()) | D19: =IFERROR(Model!D420+0,NA()) | E19: =IFERROR(Model!E420+0,NA()) | F19: =IFERROR(Model!F420+0,NA()) | G19: =IFERROR(Model!G420+0,NA()) | H19: =IFERROR(Model!H420+0,NA()) | I19: =IFERROR(Model!I420+0,NA()) | J19: =IFERROR(Model!N420+0,NA()) | K19: =IFERROR(Model!S420+0,NA()) | L19: =IFERROR(Model!X420+0,NA()) | M19: =IFERROR(Model!AC420+0,NA()) | N19: =IFERROR(Model!AH420+0,NA()) | O19: =IFERROR(Model!AM420+0,NA()) | P19: =IFERROR(Model!AR420+0,NA()) | Q19: =IFERROR(Model!AW420+0,NA()) | R19: =IFERROR(Model!BB420+0,NA()) | S19: =IFERROR(Model!BG420+0,NA()) | T19: =IFERROR(Model!BL420+0,NA()) | U19: =IFERROR(Model!BQ420+0,NA()) | V19: =IFERROR(Model!BV420+0,NA())
B20: Adj. EBITDA margin % | C20: =IFERROR(Model!C251+0,NA()) | D20: =IFERROR(Model!D251+0,NA()) | E20: =IFERROR(Model!E251+0,NA()) | F20: =IFERROR(Model!F251+0,NA()) | G20: =IFERROR(Model!G251+0,NA()) | H20: =IFERROR(Model!H251+0,NA()) | I20: =IFERROR(Model!I251+0,NA()) | J20: =IFERROR(Model!N251+0,NA()) | K20: =IFERROR(Model!S251+0,NA()) | L20: =IFERROR(Model!X251+0,NA()) | M20: =IFERROR(Model!AC251+0,NA()) | N20: =IFERROR(Model!AH251+0,NA()) | O20: =IFERROR(Model!AM251+0,NA()) | P20: =IFERROR(Model!AR251+0,NA()) | Q20: =IFERROR(Model!AW251+0,NA()) | R20: =IFERROR(Model!BB251+0,NA()) | S20: =IFERROR(Model!BG251+0,NA()) | T20: =IFERROR(Model!BL251+0,NA()) | U20: =IFERROR(Model!BQ251+0,NA()) | V20: =IFERROR(Model!BV251+0,NA())
B21: FCF margin % | C21: =IFERROR(Model!C287+0,NA()) | D21: =IFERROR(Model!D287+0,NA()) | E21: =IFERROR(Model!E287+0,NA()) | F21: =IFERROR(Model!F287+0,NA()) | G21: =IFERROR(Model!G287+0,NA()) | H21: =IFERROR(Model!H287+0,NA()) | I21: =IFERROR(Model!I287+0,NA()) | J21: =IFERROR(Model!N287+0,NA()) | K21: =IFERROR(Model!S287+0,NA()) | L21: =IFERROR(Model!X287+0,NA()) | M21: =IFERROR(Model!AC287+0,NA()) | N21: =IFERROR(Model!AH287+0,NA()) | O21: =IFERROR(Model!AM287+0,NA()) | P21: =IFERROR(Model!AR287+0,NA()) | Q21: =IFERROR(Model!AW287+0,NA()) | R21: =IFERROR(Model!BB287+0,NA()) | S21: =IFERROR(Model!BG287+0,NA()) | T21: =IFERROR(Model!BL287+0,NA()) | U21: =IFERROR(Model!BQ287+0,NA()) | V21: =IFERROR(Model!BV287+0,NA())
