Workbook

Sheet Model
CF1: SCENARIO SWITCH ▼ (Bull / Base / Bear) — drives all scenario-linked forecast drivers
B2: Waste Connections, Inc. (NYSE / TSX: WCN) — 3-Statement Financial Model | CF2: Base
B3: US GAAP as reported · USD millions (per-share data in USD, restated to the current share basis; shares in millions) · Source: Waste Connections Forms 10-K / 10-Q (financial statements, MD&A revenue bridges, segment and debt notes) and Form 8-K earnings releases (Ex. 99.1 non-GAAP reconciliations, revenue breakdown, internal growth, outlook) on SEC EDGAR — legacy Waste Connections, Inc. (Delaware) CIK 0001057058 to Q1/16; Waste Connections, Inc. (Ontario) CIK 0001318220 from Q2/16 (investor-relations releases are the same documents as filed on EDGAR)
B4: Basis notes: calendar fiscal year. Old Waste Connections was the accounting acquirer in the 1-Jun-2016 Progressive Waste merger (WCN re-domiciled to Ontario; Canada segment from Q2/16; net 1:1 share exchange) — pre-merger periods are legacy WCN (US only). 3-for-2 share splits Mar-2007, Nov-2010 and Jun-2017: all share counts / per-share data restated to the current basis (factor row). Service-line revenues are gross of intercompany eliminations; recycling and intermodal / other reported combined to 2011; E&P separate from FY2012 (R360, Oct-2012). Q4 = FY − 9M where only annual figures are disclosed. Adjusted EBITDA / adjusted EPS / adjusted FCF per the company definition in force in each period (definition rows). FY26 outlook per the Q2-26 release (22-Jul-2026); Q3/26E onward are model estimates.
CH5: Forecast | CI5: Historical | CJ5: Historical | CK5: Historical
B6: (USDm) | C6: 2006 | D6: 2007 | E6: 2008 | F6: 2009 | G6: 2010 | H6: 2011 | I6: 2012 | J6: Q1/13 | K6: Q2/13 | L6: Q3/13 | M6: Q4/13 | N6: 2013 | O6: Q1/14 | P6: Q2/14 | Q6: Q3/14 | R6: Q4/14 | S6: 2014 | T6: Q1/15 | U6: Q2/15 | V6: Q3/15 | W6: Q4/15 | X6: 2015 | Y6: Q1/16 | Z6: Q2/16 | AA6: Q3/16 | AB6: Q4/16 | AC6: 2016 | AD6: Q1/17 | AE6: Q2/17 | AF6: Q3/17 | AG6: Q4/17 | AH6: 2017 | AI6: Q1/18 | AJ6: Q2/18 | AK6: Q3/18 | AL6: Q4/18 | AM6: 2018 | AN6: Q1/19 | AO6: Q2/19 | AP6: Q3/19 | AQ6: Q4/19 | AR6: 2019 | AS6: Q1/20 | AT6: Q2/20 | AU6: Q3/20 | AV6: Q4/20 | AW6: 2020 | AX6: Q1/21 | AY6: Q2/21 | AZ6: Q3/21 | BA6: Q4/21 | BB6: 2021 | BC6: Q1/22 | BD6: Q2/22 | BE6: Q3/22 | BF6: Q4/22 | BG6: 2022 | BH6: Q1/23 | BI6: Q2/23 | BJ6: Q3/23 | BK6: Q4/23 | BL6: 2023 | BM6: Q1/24 | BN6: Q2/24 | BO6: Q3/24 | BP6: Q4/24 | BQ6: 2024 | BR6: Q1/25 | BS6: Q2/25 | BT6: Q3/25 | BU6: Q4/25 | BV6: 2025 | BW6: Q1/26 | BX6: Q2/26 | BY6: Q3/26E | BZ6: Q4/26E | CA6: 2026E | CB6: 2027E | CC6: 2028E | CD6: 2029E | CE6: 2030E | CF6: Modelling Notes | CH6: 5Y CAGR | CI6: 5Y CAGR | CJ6: 10Y CAGR | CK6: 19Y CAGR
CH7: 25-'30 | CI7: 20-'25 | CJ7: 15-'25 | CK7: 06-'25
B8: SERVICE-LINE REVENUE BUILD — SOLID WASTE (collection · landfill & transfer · recycling) · E&P WASTE · INTERMODAL & OTHER (price × volume internal-growth build) | CF8: SERVICE-LINE BUILD — modelling logic (prior-year revenues × (1 + price + volume + recycled commodities + acquisitions) → revenues → cost of operations → Adjusted EBITDA)
CN9: SCENARIO INPUT TABLE — driver assumptions per Bull / Base / Bear | CO9: Bull | CP9: Base | CQ9: Bear | CR9: Bull / Bear = Base + Δ (Δ inputs on each block header). Outlook block = high / mid / low end of the FY26 outlook ranges.
B10: Solid waste — collection, disposal & transfer, recycling (gross revenues before intercompany eliminations) | CF10: SOLID WASTE — modelling logic
B11: Collection revenues (commercial + residential + industrial & construction roll-off) | C11: 602.762 | D11: 693.675 | E11: 787.713 | F11: 901.768 | G11: 951.327 | H11: 1069.065 | I11: 1176.333 | J11: 293.144 | K11: 306.472 | L11: 312.872 | M11: 306.603 | N11: 1219.091 | O11: 306.003 | P11: 322.763 | Q11: 333.917 | R11: 327.224 | S11: 1289.906 | T11: 327.005 | U11: 342.583 | V11: 354.49 | W11: 354.601 | X11: 1378.679 | Y11: 356.598 | Z11: 502.948 | AA11: 760.281 | AB11: 739.986 | AC11: 2359.813 | AD11: 768.346 | AE11: 797.131 | AF11: 815.344 | AG11: 800.625 | AH11: 3181.447 | AI11: 809.646 | AJ11: 854.719 | AK11: 871.7 | AL11: 874.601 | AM11: 3410.666 | AN11: 891.353 | AO11: 958.124 | AP11: 990.79 | AQ11: 974.886 | AR11: 3815.153 | AS11: 989.009 | AT11: 948.072 | AU11: 1010.497 | AV11: 1024.099 | AW11: 3971.678 | AX11: 1036.472 | AY11: 1098.319 | AZ11: 1137.206 | BA11: 1169.428 | BB11: 4441.426 | BC11: 1199.452 | BD11: 1297.402 | BE11: 1368.491 | BF11: 1385.682 | BG11: 5251.027 | BH11: 1434.647 | BI11: 1485.705 | BJ11: 1512.745 | BK11: 1501.882 | BL11: 5934.979 | BM11: 1515.06 | BN11: 1583.098 | BO11: 1622.308 | BP11: 1612.307 | BQ11: 6332.773 | BR11: 1621.077 | BS11: 1690.785 | BT11: 1730.339 | BU11: 1705.896 | BV11: 6748.096 | BW11: 1709.628 | BX11: 1789.235 | BY11: =BT11*(1+BY20) -> 1802.8064 | BZ11: =BU11*(1+BZ20) -> 1777.3397 | CA11: =SUM(BW11,BX11,BY11,BZ11) -> 7079.0091 | CB11: =CA11*(1+CB20) -> 7379.8669 | CC11: =CB11*(1+CC20) -> 7711.961 | CD11: =CC11*(1+CD20) -> 8078.2791 | CE11: =CD11*(1+CE20) -> 8441.8017 | CF11: Historical: earnings-release revenue breakdown (quarters; gross of intercompany) and 10-K service-line table (FY). Q3/Q4-26E: prior-year quarter × (1 + solid waste growth below). 2027E+: prior year × (1 + organic internal growth). | CH11: =IFERROR((CE11/BV11)^(1/5)-1,"n/m") -> 0.045805155 | CI11: =IFERROR((BV11/AW11)^(1/5)-1,"n/m") -> 0.11183782 | CJ11: =IFERROR((BV11/X11)^(1/10)-1,"n/m") -> 0.17211928 | CK11: =IFERROR((BV11/C11)^(1/19)-1,"n/m") -> 0.13556602 | CN11: FY26 outlook — Q2-26 release (22-Jul-26, "updated outlook") | CO11: High | CP11: Mid | CQ11: Low | CR11: WCN outlook "assumes no change in the current economic environment" and excludes transaction-related items and acquisitions not yet closed.
B12: Memo: commercial (from Q2/18) | M12: =IF(AND(ISNUMBER(N12),ISNUMBER(J12),ISNUMBER(K12),ISNUMBER(L12)),N12-J12-K12-L12,"") | R12: =IF(AND(ISNUMBER(S12),ISNUMBER(O12),ISNUMBER(P12),ISNUMBER(Q12)),S12-O12-P12-Q12,"") | W12: =IF(AND(ISNUMBER(X12),ISNUMBER(T12),ISNUMBER(U12),ISNUMBER(V12)),X12-T12-U12-V12,"") | AB12: =IF(AND(ISNUMBER(AC12),ISNUMBER(Y12),ISNUMBER(Z12),ISNUMBER(AA12)),AC12-Y12-Z12-AA12,"") | AG12: =IF(AND(ISNUMBER(AH12),ISNUMBER(AD12),ISNUMBER(AE12),ISNUMBER(AF12)),AH12-AD12-AE12-AF12,"") | AJ12: 360.364 | AK12: 369.543 | AL12: =IF(AND(ISNUMBER(AM12),ISNUMBER(AI12),ISNUMBER(AJ12),ISNUMBER(AK12)),AM12-AI12-AJ12-AK12,"") | AM12: 1452.831 | AN12: 381.509 | AO12: 396.641 | AP12: 408.415 | AQ12: =IF(AND(ISNUMBER(AR12),ISNUMBER(AN12),ISNUMBER(AO12),ISNUMBER(AP12)),AR12-AN12-AO12-AP12,"") -> 406.652 | AR12: 1593.217 | AS12: 416.507 | AT12: 375.427 | AU12: 406.037 | AV12: =IF(AND(ISNUMBER(AW12),ISNUMBER(AS12),ISNUMBER(AT12),ISNUMBER(AU12)),AW12-AS12-AT12-AU12,"") -> 412.342 | AW12: 1610.313 | AX12: 426.395 | AY12: 444.044 | AZ12: 465.246 | BA12: =IF(AND(ISNUMBER(BB12),ISNUMBER(AX12),ISNUMBER(AY12),ISNUMBER(AZ12)),BB12-AX12-AY12-AZ12,"") -> 477.741 | BB12: 1813.426 | BC12: 499.676 | BD12: 538.525 | BE12: 564.592 | BF12: =IF(AND(ISNUMBER(BG12),ISNUMBER(BC12),ISNUMBER(BD12),ISNUMBER(BE12)),BG12-BC12-BD12-BE12,"") -> 573.502 | BG12: 2176.295 | BH12: 602.279 | BI12: 615.803 | BJ12: 630.641 | BK12: =IF(AND(ISNUMBER(BL12),ISNUMBER(BH12),ISNUMBER(BI12),ISNUMBER(BJ12)),BL12-BH12-BI12-BJ12,"") -> 628.168 | BL12: 2476.891 | BM12: 642.859 | BN12: 656.926 | BO12: 680.444 | BP12: =IF(AND(ISNUMBER(BQ12),ISNUMBER(BM12),ISNUMBER(BN12),ISNUMBER(BO12)),BQ12-BM12-BN12-BO12,"") -> 690.32 | BQ12: 2670.549 | BR12: 712.46 | BS12: 731.573 | BT12: 750.384 | BU12: =IF(AND(ISNUMBER(BV12),ISNUMBER(BR12),ISNUMBER(BS12),ISNUMBER(BT12)),BV12-BR12-BS12-BT12,"") -> 749.862 | BV12: 2944.279 | BW12: 761.562 | BX12: 784.532 | CF12: 10-Q / 10-K disaggregation note (ASC 606) from Q2/18; Q4 = FY − 9M. | CN12: FY26 revenues ($m) | CO12: 10050 | CP12: 10035 | CQ12: 10020 | CR12: Raised to $10.02–10.05bn in the Q2-26 release (from $9.90–9.95bn, Feb-26). Drives the Q3/Q4-26E revenue calibration.
B13: Memo: residential (from Q2/18) | M13: =IF(AND(ISNUMBER(N13),ISNUMBER(J13),ISNUMBER(K13),ISNUMBER(L13)),N13-J13-K13-L13,"") | R13: =IF(AND(ISNUMBER(S13),ISNUMBER(O13),ISNUMBER(P13),ISNUMBER(Q13)),S13-O13-P13-Q13,"") | W13: =IF(AND(ISNUMBER(X13),ISNUMBER(T13),ISNUMBER(U13),ISNUMBER(V13)),X13-T13-U13-V13,"") | AB13: =IF(AND(ISNUMBER(AC13),ISNUMBER(Y13),ISNUMBER(Z13),ISNUMBER(AA13)),AC13-Y13-Z13-AA13,"") | AG13: =IF(AND(ISNUMBER(AH13),ISNUMBER(AD13),ISNUMBER(AE13),ISNUMBER(AF13)),AH13-AD13-AE13-AF13,"") | AJ13: 297.076 | AK13: 300.026 | AL13: =IF(AND(ISNUMBER(AM13),ISNUMBER(AI13),ISNUMBER(AJ13),ISNUMBER(AK13)),AM13-AI13-AJ13-AK13,"") | AM13: 1189.148 | AN13: 322.404 | AO13: 346.128 | AP13: 355.574 | AQ13: =IF(AND(ISNUMBER(AR13),ISNUMBER(AN13),ISNUMBER(AO13),ISNUMBER(AP13)),AR13-AN13-AO13-AP13,"") -> 356.657 | AR13: 1380.763 | AS13: 365.731 | AT13: 378.188 | AU13: 387.566 | AV13: =IF(AND(ISNUMBER(AW13),ISNUMBER(AS13),ISNUMBER(AT13),ISNUMBER(AU13)),AW13-AS13-AT13-AU13,"") -> 396.732 | AW13: 1528.217 | AX13: 400.819 | AY13: 416.975 | AZ13: 422.543 | BA13: =IF(AND(ISNUMBER(BB13),ISNUMBER(AX13),ISNUMBER(AY13),ISNUMBER(AZ13)),BB13-AX13-AY13-AZ13,"") -> 433.482 | BB13: 1673.819 | BC13: 440.288 | BD13: 463.32 | BE13: 487.995 | BF13: =IF(AND(ISNUMBER(BG13),ISNUMBER(BC13),ISNUMBER(BD13),ISNUMBER(BE13)),BG13-BC13-BD13-BE13,"") -> 499.505 | BG13: 1891.108 | BH13: 514.053 | BI13: 529.872 | BJ13: 538.364 | BK13: =IF(AND(ISNUMBER(BL13),ISNUMBER(BH13),ISNUMBER(BI13),ISNUMBER(BJ13)),BL13-BH13-BI13-BJ13,"") -> 542.779 | BL13: 2125.068 | BM13: 546.211 | BN13: 567.383 | BO13: 574.305 | BP13: =IF(AND(ISNUMBER(BQ13),ISNUMBER(BM13),ISNUMBER(BN13),ISNUMBER(BO13)),BQ13-BM13-BN13-BO13,"") -> 571.012 | BQ13: 2258.911 | BR13: 571.619 | BS13: 592.225 | BT13: 600.832 | BU13: =IF(AND(ISNUMBER(BV13),ISNUMBER(BR13),ISNUMBER(BS13),ISNUMBER(BT13)),BV13-BR13-BS13-BT13,"") -> 599.86 | BV13: 2364.536 | BW13: 600.117 | BX13: 619.691 | CN13: FY26 Adjusted EBITDA ($m) | CO13: 3340 | CP13: 3335 | CQ13: 3330 | CR13: Raised to $3.330–3.340bn (from $3.300–3.325bn). Drives the Q3/Q4-26E cost-of-operations calibration.
B14: Memo: industrial & construction roll-off (from Q2/18) | M14: =IF(AND(ISNUMBER(N14),ISNUMBER(J14),ISNUMBER(K14),ISNUMBER(L14)),N14-J14-K14-L14,"") | R14: =IF(AND(ISNUMBER(S14),ISNUMBER(O14),ISNUMBER(P14),ISNUMBER(Q14)),S14-O14-P14-Q14,"") | W14: =IF(AND(ISNUMBER(X14),ISNUMBER(T14),ISNUMBER(U14),ISNUMBER(V14)),X14-T14-U14-V14,"") | AB14: =IF(AND(ISNUMBER(AC14),ISNUMBER(Y14),ISNUMBER(Z14),ISNUMBER(AA14)),AC14-Y14-Z14-AA14,"") | AG14: =IF(AND(ISNUMBER(AH14),ISNUMBER(AD14),ISNUMBER(AE14),ISNUMBER(AF14)),AH14-AD14-AE14-AF14,"") | AJ14: 197.279 | AK14: 202.13 | AL14: =IF(AND(ISNUMBER(AM14),ISNUMBER(AI14),ISNUMBER(AJ14),ISNUMBER(AK14)),AM14-AI14-AJ14-AK14,"") | AM14: 768.687 | AN14: 187.44 | AO14: 215.355 | AP14: 226.801 | AQ14: =IF(AND(ISNUMBER(AR14),ISNUMBER(AN14),ISNUMBER(AO14),ISNUMBER(AP14)),AR14-AN14-AO14-AP14,"") -> 211.577 | AR14: 841.173 | AS14: 206.771 | AT14: 194.457 | AU14: 216.894 | AV14: =IF(AND(ISNUMBER(AW14),ISNUMBER(AS14),ISNUMBER(AT14),ISNUMBER(AU14)),AW14-AS14-AT14-AU14,"") -> 215.026 | AW14: 833.148 | AX14: 209.258 | AY14: 237.3 | AZ14: 249.417 | BA14: =IF(AND(ISNUMBER(BB14),ISNUMBER(AX14),ISNUMBER(AY14),ISNUMBER(AZ14)),BB14-AX14-AY14-AZ14,"") -> 258.206 | BB14: 954.181 | BC14: 259.488 | BD14: 295.557 | BE14: 315.904 | BF14: =IF(AND(ISNUMBER(BG14),ISNUMBER(BC14),ISNUMBER(BD14),ISNUMBER(BE14)),BG14-BC14-BD14-BE14,"") -> 312.675 | BG14: 1183.624 | BH14: 318.315 | BI14: 340.03 | BJ14: 343.74 | BK14: =IF(AND(ISNUMBER(BL14),ISNUMBER(BH14),ISNUMBER(BI14),ISNUMBER(BJ14)),BL14-BH14-BI14-BJ14,"") -> 330.935 | BL14: 1333.02 | BM14: 325.99 | BN14: 358.789 | BO14: 367.559 | BP14: =IF(AND(ISNUMBER(BQ14),ISNUMBER(BM14),ISNUMBER(BN14),ISNUMBER(BO14)),BQ14-BM14-BN14-BO14,"") -> 350.975 | BQ14: 1403.313 | BR14: 336.998 | BS14: 366.987 | BT14: 379.123 | BU14: =IF(AND(ISNUMBER(BV14),ISNUMBER(BR14),ISNUMBER(BS14),ISNUMBER(BT14)),BV14-BR14-BS14-BT14,"") -> 356.173 | BV14: 1439.281 | BW14: 347.949 | BX14: 385.012 | CN14: FY26 net income attributable ($m; outlook reconciliation) | CO14: 1173 | CP14: 1171 | CQ14: 1169 | CR14: Q2-26 outlook reconciliation (memo only; includes 1H/26 impairments & other items).
B15: Disposal & transfer revenues (landfill + transfer stations) | C15: 259.19 | D15: 298.954 | E15: 308.811 | F15: 392.497 | G15: 458.241 | H15: 510.33 | I15: 524.861 | J15: 122.772 | K15: 153.6 | L15: 158.142 | M15: 144.866 | N15: 579.379 | O15: 135.563 | P15: 158.913 | Q15: 167.129 | R15: 155.557 | S15: 617.161 | T15: 142.43 | U15: 171.932 | V15: 180.442 | W15: 175.565 | X15: 670.369 | Y15: 170.083 | Z15: 256.847 | AA15: 377.998 | AB15: 350.482 | AC15: 1155.41 | AD15: 357.025 | AE15: 416.176 | AF15: 416.764 | AG15: 388.01 | AH15: 1577.975 | AI15: 370.929 | AJ15: 440.537 | AK15: 473.906 | AL15: 447.998 | AM15: 1733.371 | AN15: 405.791 | AO15: 501.401 | AP15: 520.218 | AQ15: 476.84 | AR15: 1904.251 | AS15: 446.983 | AT15: 469.704 | AU15: 514.705 | AV15: 493.093 | AW15: 1924.486 | AX15: 461.259 | AY15: 544.257 | AZ15: 553.974 | BA15: 533.122 | BB15: 2092.612 | BC15: 517.722 | BD15: 601.194 | BE15: 616.9 | BF15: 619.176 | BG15: 2354.992 | BH15: 616.954 | BI15: 688.965 | BJ15: 703.544 | BK15: 672.318 | BL15: 2681.782 | BM15: 655.36 | BN15: 756.139 | BO15: 776.928 | BP15: 718.525 | BQ15: 2906.952 | BR15: 658.023 | BS15: 784.015 | BT15: 804.442 | BU15: 757.06 | BV15: 3003.54 | BW15: 714.624 | BX15: 829.536 | BY15: =BT15*(1+BY20) -> 838.13239 | BZ15: =BU15*(1+BZ20) -> 788.76601 | CA15: =SUM(BW15,BX15,BY15,BZ15) -> 3171.0584 | CB15: =CA15*(1+CB20) -> 3305.8284 | CC15: =CB15*(1+CC20) -> 3454.5907 | CD15: =CC15*(1+CD20) -> 3618.6837 | CE15: =CD15*(1+CE20) -> 3781.5245 | CF15: Gross of intercompany (~45–50% of landfill & transfer revenue is internalized volume from WCN collection, eliminated below). | CH15: =IFERROR((CE15/BV15)^(1/5)-1,"n/m") -> 0.047144701 | CI15: =IFERROR((BV15/AW15)^(1/5)-1,"n/m") -> 0.093109661 | CJ15: =IFERROR((BV15/X15)^(1/10)-1,"n/m") -> 0.16180155 | CK15: =IFERROR((BV15/C15)^(1/19)-1,"n/m") -> 0.13762938 | CN15: FY26 adjusted free cash flow ($m) | CO15: 1450 | CP15: 1425 | CQ15: 1400 | CR15: Reaffirmed $1.40–1.45bn (memo; compare with model Adjusted FCF).
B16: Memo: landfill (from Q2/18) | M16: =IF(AND(ISNUMBER(N16),ISNUMBER(J16),ISNUMBER(K16),ISNUMBER(L16)),N16-J16-K16-L16,"") | R16: =IF(AND(ISNUMBER(S16),ISNUMBER(O16),ISNUMBER(P16),ISNUMBER(Q16)),S16-O16-P16-Q16,"") | W16: =IF(AND(ISNUMBER(X16),ISNUMBER(T16),ISNUMBER(U16),ISNUMBER(V16)),X16-T16-U16-V16,"") | AB16: =IF(AND(ISNUMBER(AC16),ISNUMBER(Y16),ISNUMBER(Z16),ISNUMBER(AA16)),AC16-Y16-Z16-AA16,"") | AG16: =IF(AND(ISNUMBER(AH16),ISNUMBER(AD16),ISNUMBER(AE16),ISNUMBER(AF16)),AH16-AD16-AE16-AF16,"") | AJ16: 271.674 | AK16: 285.945 | AL16: =IF(AND(ISNUMBER(AM16),ISNUMBER(AI16),ISNUMBER(AJ16),ISNUMBER(AK16)),AM16-AI16-AJ16-AK16,"") | AM16: 1063.242 | AN16: 244.601 | AO16: 296.84 | AP16: 310.633 | AQ16: =IF(AND(ISNUMBER(AR16),ISNUMBER(AN16),ISNUMBER(AO16),ISNUMBER(AP16)),AR16-AN16-AO16-AP16,"") -> 280.861 | AR16: 1132.935 | AS16: 266.218 | AT16: 280.619 | AU16: 308.795 | AV16: =IF(AND(ISNUMBER(AW16),ISNUMBER(AS16),ISNUMBER(AT16),ISNUMBER(AU16)),AW16-AS16-AT16-AU16,"") -> 291.1 | AW16: 1146.732 | AX16: 271.936 | AY16: 327.124 | AZ16: 328.147 | BA16: =IF(AND(ISNUMBER(BB16),ISNUMBER(AX16),ISNUMBER(AY16),ISNUMBER(AZ16)),BB16-AX16-AY16-AZ16,"") -> 306.292 | BB16: 1233.499 | BC16: 299.765 | BD16: 339.719 | BE16: 345.215 | BF16: =IF(AND(ISNUMBER(BG16),ISNUMBER(BC16),ISNUMBER(BD16),ISNUMBER(BE16)),BG16-BC16-BD16-BE16,"") -> 344.243 | BG16: 1328.942 | BH16: 343.433 | BI16: 382.944 | BJ16: 390.33 | BK16: =IF(AND(ISNUMBER(BL16),ISNUMBER(BH16),ISNUMBER(BI16),ISNUMBER(BJ16)),BL16-BH16-BI16-BJ16,"") -> 366.69 | BL16: 1483.397 | BM16: 353.478 | BN16: 405.912 | BO16: 418.508 | BP16: =IF(AND(ISNUMBER(BQ16),ISNUMBER(BM16),ISNUMBER(BN16),ISNUMBER(BO16)),BQ16-BM16-BN16-BO16,"") -> 379.974 | BQ16: 1557.872 | BR16: 338.754 | BS16: 402.08 | BT16: 414.614 | BU16: =IF(AND(ISNUMBER(BV16),ISNUMBER(BR16),ISNUMBER(BS16),ISNUMBER(BT16)),BV16-BR16-BS16-BT16,"") -> 386.456 | BV16: 1541.904 | BW16: 360.448 | BX16: 417.541 | CN16: FY26 net cash provided by operating activities ($m) | CO16: 2680 | CP16: 2655 | CQ16: 2630 | CR16: Trimmed to $2.63–2.68bn (from $2.65–2.70bn) — memo.
B17: Memo: transfer (from Q2/18) | M17: =IF(AND(ISNUMBER(N17),ISNUMBER(J17),ISNUMBER(K17),ISNUMBER(L17)),N17-J17-K17-L17,"") | R17: =IF(AND(ISNUMBER(S17),ISNUMBER(O17),ISNUMBER(P17),ISNUMBER(Q17)),S17-O17-P17-Q17,"") | W17: =IF(AND(ISNUMBER(X17),ISNUMBER(T17),ISNUMBER(U17),ISNUMBER(V17)),X17-T17-U17-V17,"") | AB17: =IF(AND(ISNUMBER(AC17),ISNUMBER(Y17),ISNUMBER(Z17),ISNUMBER(AA17)),AC17-Y17-Z17-AA17,"") | AG17: =IF(AND(ISNUMBER(AH17),ISNUMBER(AD17),ISNUMBER(AE17),ISNUMBER(AF17)),AH17-AD17-AE17-AF17,"") | AJ17: 168.863 | AK17: 187.961 | AL17: =IF(AND(ISNUMBER(AM17),ISNUMBER(AI17),ISNUMBER(AJ17),ISNUMBER(AK17)),AM17-AI17-AJ17-AK17,"") | AM17: 670.129 | AN17: 161.191 | AO17: 204.561 | AP17: 209.585 | AQ17: =IF(AND(ISNUMBER(AR17),ISNUMBER(AN17),ISNUMBER(AO17),ISNUMBER(AP17)),AR17-AN17-AO17-AP17,"") -> 195.979 | AR17: 771.316 | AS17: 180.765 | AT17: 189.085 | AU17: 205.91 | AV17: =IF(AND(ISNUMBER(AW17),ISNUMBER(AS17),ISNUMBER(AT17),ISNUMBER(AU17)),AW17-AS17-AT17-AU17,"") -> 201.994 | AW17: 777.754 | AX17: 189.323 | AY17: 217.133 | AZ17: 225.827 | BA17: =IF(AND(ISNUMBER(BB17),ISNUMBER(AX17),ISNUMBER(AY17),ISNUMBER(AZ17)),BB17-AX17-AY17-AZ17,"") -> 226.83 | BB17: 859.113 | BC17: 217.957 | BD17: 261.475 | BE17: 271.685 | BF17: =IF(AND(ISNUMBER(BG17),ISNUMBER(BC17),ISNUMBER(BD17),ISNUMBER(BE17)),BG17-BC17-BD17-BE17,"") -> 274.933 | BG17: 1026.05 | BH17: 273.521 | BI17: 306.021 | BJ17: 313.214 | BK17: =IF(AND(ISNUMBER(BL17),ISNUMBER(BH17),ISNUMBER(BI17),ISNUMBER(BJ17)),BL17-BH17-BI17-BJ17,"") -> 305.629 | BL17: 1198.385 | BM17: 301.882 | BN17: 350.227 | BO17: 358.42 | BP17: =IF(AND(ISNUMBER(BQ17),ISNUMBER(BM17),ISNUMBER(BN17),ISNUMBER(BO17)),BQ17-BM17-BN17-BO17,"") -> 338.551 | BQ17: 1349.08 | BR17: 319.269 | BS17: 381.935 | BT17: 389.828 | BU17: =IF(AND(ISNUMBER(BV17),ISNUMBER(BR17),ISNUMBER(BS17),ISNUMBER(BT17)),BV17-BR17-BS17-BT17,"") -> 370.604 | BV17: 1461.636 | BW17: 354.176 | BX17: 411.995 | CN17: FY26 point estimates (all cases)
B18: Recycling revenues (recycled commodities; within "recycling & other" to 2011) | I18: 81.512 | J18: 18.794 | K18: 18.61 | L18: 18.402 | M18: 16.025 | N18: 71.831 | O18: 14.904 | P18: 14.836 | Q18: 14.973 | R18: 13.513 | S18: 58.226 | T18: 11.069 | U18: 12.332 | V18: 12.213 | W18: 11.678 | X18: 47.292 | Y18: 10.619 | Z18: 18.119 | AA18: 32.138 | AB18: 31.58 | AC18: 92.456 | AD18: 43.889 | AE18: 43.693 | AF18: 43.864 | AG18: 30.285 | AH18: 161.73 | AI18: 23.485 | AJ18: 22.703 | AK18: 23.37 | AL18: 23.075 | AM18: 92.634 | AN18: 19.804 | AO18: 16.73 | AP18: 14.142 | AQ18: 13.569 | AR18: 64.245 | AS18: 18.108 | AT18: 20.217 | AU18: 21.377 | AV18: 26.688 | AW18: 86.389 | AX18: 32.448 | AY18: 41.539 | AZ18: 55.772 | BA18: 75.317 | BB18: 205.076 | BC18: 63.094 | BD18: 67.504 | BE18: 48.246 | BF18: 26.031 | BG18: 204.876 | BH18: 31.301 | BI18: 38.319 | BJ18: 36.103 | BK18: 41.316 | BL18: 147.039 | BM18: 49.025 | BN18: 63.298 | BO18: 69.748 | BP18: 59.802 | BQ18: 241.873 | BR18: 61.341 | BS18: 69.163 | BT18: 58.351 | BU18: 51.202 | BV18: 240.057 | BW18: 53.649 | BX18: 63.946 | BY18: =BT18*(1+BY20) -> 60.794766 | BZ18: =BU18*(1+BZ20) -> 53.346363 | CA18: =SUM(BW18,BX18,BY18,BZ18) -> 231.73613 | CB18: =CA18*(1+CB20) -> 241.58491 | CC18: =CB18*(1+CC20) -> 252.45624 | CD18: =CC18*(1+CD20) -> 264.44791 | CE18: =CD18*(1+CE20) -> 276.34806 | CF18: Recycled-commodity price exposure (OCC, fibre, plastics); RINs / landfill gas sit in intermodal & other. Forecast grows with solid waste (recycled-commodity contribution input below). | CH18: =IFERROR((CE18/BV18)^(1/5)-1,"n/m") -> 0.028557108 | CI18: =IFERROR((BV18/AW18)^(1/5)-1,"n/m") -> 0.22679271 | CJ18: =IFERROR((BV18/X18)^(1/10)-1,"n/m") -> 0.17639364 | CK18: =IFERROR((BV18/C18)^(1/19)-1,"n/m") -> n/m | CN18: Interest expense, net of interest income ($m) | CP18: 358 | CR18: Q2-26 outlook reconciliation: "interest expense, net" $358m (was $330m in Feb).
B19: Solid waste revenues before intercompany eliminations | C19: =N(C11)+N(C15)+N(C18) -> 861.952 | D19: =N(D11)+N(D15)+N(D18) -> 992.629 | E19: =N(E11)+N(E15)+N(E18) -> 1096.524 | F19: =N(F11)+N(F15)+N(F18) -> 1294.265 | G19: =N(G11)+N(G15)+N(G18) -> 1409.568 | H19: =N(H11)+N(H15)+N(H18) -> 1579.395 | I19: =N(I11)+N(I15)+N(I18) -> 1782.706 | J19: =N(J11)+N(J15)+N(J18) -> 434.71 | ... CE19: =N(CE11)+N(CE15)+N(CE18) -> 12499.674 | CF19: 2006–11 excludes recycling (reported combined with intermodal & other — memo line below), so 2012 y/y is overstated by the reclassification. | CH19: =IFERROR((CE19/BV19)^(1/5)-1,"n/m") -> 0.04580791 | CI19: =IFERROR((BV19/AW19)^(1/5)-1,"n/m") -> 0.10802741 | CJ19: =IFERROR((BV19/X19)^(1/10)-1,"n/m") -> 0.16900868 | CK19: =IFERROR((BV19/C19)^(1/19)-1,"n/m") -> 0.13764879 | CN19: Tax rate (GAAP effective) | CP19: 0.231 | CR19: Q2-26 release footnote: FY26 effective tax rate ~23.1% (24.5% in Feb outlook).
B20: Solid waste revenues y/y % (gross) — forecast growth driver | D20: =IF(AND(ISNUMBER(D19),ISNUMBER(C19)),IFERROR(D19/C19-1,""),"") -> 0.15160589 | E20: =IF(AND(ISNUMBER(E19),ISNUMBER(D19)),IFERROR(E19/D19-1,""),"") -> 0.1046665 | F20: =IF(AND(ISNUMBER(F19),ISNUMBER(E19)),IFERROR(F19/E19-1,""),"") -> 0.1803344 | G20: =IF(AND(ISNUMBER(G19),ISNUMBER(F19)),IFERROR(G19/F19-1,""),"") -> 0.089087629 | H20: =IF(AND(ISNUMBER(H19),ISNUMBER(G19)),IFERROR(H19/G19-1,""),"") -> 0.12048159 | I20: =IF(AND(ISNUMBER(I19),ISNUMBER(H19)),IFERROR(I19/H19-1,""),"") -> 0.12872714 | N20: =IF(AND(ISNUMBER(N19),ISNUMBER(I19)),IFERROR(N19/I19-1,""),"") -> 0.049135976 | O20: =IF(AND(ISNUMBER(O19),ISNUMBER(J19)),IFERROR(O19/J19-1,""),"") -> 0.050056359 | P20: =IF(AND(ISNUMBER(P19),ISNUMBER(K19)),IFERROR(P19/K19-1,""),"") -> 0.03724811 | Q20: =IF(AND(ISNUMBER(Q19),ISNUMBER(L19)),IFERROR(Q19/L19-1,""),"") -> 0.054356621 | R20: =IF(AND(ISNUMBER(R19),ISNUMBER(M19)),IFERROR(R19/M19-1,""),"") -> 0.061605069 | S20: =IF(AND(ISNUMBER(S19),ISNUMBER(N19)),IFERROR(S19/N19-1,""),"") -> 0.050789686 | T20: =IF(AND(ISNUMBER(T19),ISNUMBER(O19)),IFERROR(T19/O19-1,""),"") -> 0.052651872 | U20: =IF(AND(ISNUMBER(U19),ISNUMBER(P19)),IFERROR(U19/P19-1,""),"") -> 0.061096207 | ... BX20: =IF(AND(ISNUMBER(BX19),ISNUMBER(BS19)),IFERROR(BX19/BS19-1,""),"") -> 0.05454246 | BY20: =$BX$21+BY87 -> 0.041880446 | BZ20: =$BX$21+BZ87 -> 0.041880446 | CA20: =IFERROR(CA19/BV19-1,"") -> 0.049051806 | CB20: =CB31 -> 0.0425 | CC20: =CC31 -> 0.045 | CD20: =CD31 -> 0.0475 | CE20: =CE31 -> 0.045 | CF20: Q3/Q4-26E: Q2/26 y/y (+price, −volume, + acquisition roll-over) + revenue-outlook calibration Δ (Group block). 2027E+: organic internal growth (price + volume + recycling + FX); bolt-ons in the future-acquisitions block. | CN20: Depreciation & depletion ($m) | CP20: 1112 | CR20: Q2-26 outlook reconciliation $1,110–1,114m (mid-point).
B21: Memo: Q2/26 y/y growth basis (trend input to Q3/Q4-26E) | BX21: =IFERROR(BX19/BS19-1,"") -> 0.05454246 | CN21: Amortization of intangibles ($m) | CP21: 192 | CR21: Q2-26 outlook reconciliation $192m.
CN22: Capital expenditures for property & equipment ($m) | CP22: 1250 | CR22: "Approximately $1.25 billion" (unchanged since Feb-26).
B23: Solid waste internal growth — company-reported % of prior-year solid waste revenues (price × volume) | CN23: Closure & post-closure accretion ($m) | CP23: 40.608 | CR23: Q2-26 outlook reconciliation line ($50m in Feb).
B24: Core price % (yield basis in the forecast) | C24: 0.051 | D24: 0.047 | E24: 0.056 | F24: 0.048 | G24: 0.027 | H24: 0.036 | I24: 0.032 | J24: 0.028 | K24: 0.026 | L24: 0.024 | M24: 0.026 | N24: 0.026 | O24: 0.029 | P24: 0.026 | Q24: 0.028 | R24: 0.029 | S24: 0.028 | T24: 0.028 | U24: 0.029 | V24: 0.027 | W24: 0.029 | X24: 0.028 | Y24: 0.031 | Z24: 0.029 | AA24: 0.026 | AB24: 0.027 | AC24: 0.028 | AD24: 0.026 | AE24: 0.031 | AF24: 0.033 | AG24: 0.035 | AH24: 0.031 | AI24: 0.041 | AJ24: 0.039 | AK24: 0.04 | AL24: 0.044 | AM24: 0.041 | AN24: 0.05 | AO24: 0.05 | AP24: 0.051 | AQ24: 0.054 | AR24: 0.051 | AS24: 0.055 | AT24: 0.045 | AU24: 0.041 | AV24: 0.043 | AW24: 0.045 | AX24: 0.045 | AY24: 0.047 | AZ24: 0.047 | BA24: 0.05 | BB24: 0.047 | BC24: 0.063 | BD24: 0.072 | BE24: 0.083 | BF24: 0.09 | BG24: 0.077 | BH24: 0.11 | BI24: 0.098 | BJ24: 0.088 | BK24: 0.087 | BL24: 0.095 | BM24: 0.078 | BN24: 0.07 | BO24: 0.068 | BP24: 0.067 | BQ24: 0.071 | BR24: 0.069 | BS24: 0.066 | BT24: 0.063 | BU24: 0.064 | BV24: 0.065 | BW24: 0.06 | BX24: 0.056 | CB24: =CHOOSE(MATCH($CF$2,{"Bull","Base","Bear"},0),$CO$29,$CP$29,$CQ$29) -> 0.0475 | CC24: =CHOOSE(MATCH($CF$2,{"Bull","Base","Bear"},0),$CO$30,$CP$30,$CQ$30) -> 0.045 | CD24: =CHOOSE(MATCH($CF$2,{"Bull","Base","Bear"},0),$CO$31,$CP$31,$CQ$31) -> 0.0425 | CE24: =CHOOSE(MATCH($CF$2,{"Bull","Base","Bear"},0),$CO$32,$CP$32,$CQ$32) -> 0.04 | CF24: Core price = price increases net of rollbacks on solid waste (company). 2006–08 = total price incl. surcharges. From Q1/26 the company total uses "yield"; core price is shown as memo. 2027E+: scenario lever SW_price (yield incl. surcharges). | CH24: =IFERROR(AVERAGE(CA24,CB24,CC24,CD24,CE24),"n/m") -> 0.04375 | CI24: =IFERROR(AVERAGE(BB24,BG24,BL24,BQ24,BV24),"n/m") -> 0.071 | CJ24: =IFERROR(AVERAGE(AC24,AH24,AM24,AR24,AW24,BB24,BG24,BL24,BQ24,BV24),"n/m") -> 0.0551 | CK24: =IFERROR(AVERAGE(C24,D24,E24,F24,G24,H24,I24,N24,S24,X24,AC24,AH24,AM24,AR24,AW24,BB24,BG24,BL24,BQ24,BV24),"n/m") -> 0.0465 | CN24: 2H/26 share repurchases ($m) | CO24: 600 | CP24: 400 | CQ24: 200 | CR24: 1H/26: 3.76m shares for $614.5m under the NCIB. 2H/26 is a scenario input (not guided).
B25: Surcharges % (fuel / materials / environmental) | F25: -0.021 | G25: 0.002 | J25: 0.004 | K25: 0.002 | L25: 0.003 | M25: 0.003 | N25: 0.003 | O25: 0.001 | P25: 0 | Q25: 0 | R25: 0 | S25: 0 | U25: -0.001 | V25: -0.002 | W25: -0.005 | X25: -0.002 | Y25: -0.004 | Z25: -0.003 | AA25: -0.003 | AB25: -0.001 | AC25: -0.003 | AD25: 0 | AE25: 0 | AF25: 0 | AG25: 0.001 | AH25: 0.001 | AI25: 0.002 | AJ25: 0.003 | AK25: 0.005 | AL25: 0.004 | AM25: 0.004 | AN25: 0.002 | AO25: 0.002 | AP25: 0.001 | AQ25: 0 | AR25: 0.001 | AS25: 0.001 | AT25: -0.002 | AU25: -0.004 | AV25: -0.005 | AW25: -0.002 | AX25: -0.003 | AY25: 0.002 | AZ25: 0.004 | BA25: 0.007 | BB25: 0.003 | BC25: 0.008 | BD25: 0.016 | BE25: 0.018 | BF25: 0.016 | BG25: 0.015 | BH25: 0.008 | BI25: -0.007 | BJ25: -0.011 | BK25: -0.008 | BL25: -0.005 | BM25: -0.007 | BN25: -0.002 | BO25: -0.003 | BP25: -0.005 | BQ25: -0.005 | BR25: -0.002 | BS25: -0.002 | BT25: -0.001 | BU25: 0 | BV25: -0.001 | BW25: -0.001 | BX25: 0.011 | CB25: 0 | CC25: 0 | CD25: 0 | CE25: 0 | CF25: Input 0% 2027E+ (surcharges captured in the yield lever). | CH25: =IFERROR(AVERAGE(CA25,CB25,CC25,CD25,CE25),"n/m") -> 0 | CI25: =IFERROR(AVERAGE(BB25,BG25,BL25,BQ25,BV25),"n/m") -> 0.0014 | CJ25: =IFERROR(AVERAGE(AC25,AH25,AM25,AR25,AW25,BB25,BG25,BL25,BQ25,BV25),"n/m") -> 0.0008 | CK25: =IFERROR(AVERAGE(C25,D25,E25,F25,G25,H25,I25,N25,S25,X25,AC25,AH25,AM25,AR25,AW25,BB25,BG25,BL25,BQ25,BV25),"n/m") -> -0.00066666667
B26: Volume % (unit volume from Q1/26) | C26: 0.028 | D26: 0.04 | E26: -0.019 | F26: -0.062 | G26: 0 | H26: -0.003 | I26: -0.021 | J26: -0.019 | K26: 0.009 | L26: 0.022 | M26: 0.014 | N26: 0.007 | O26: 0.025 | P26: 0.015 | Q26: 0.021 | R26: 0.023 | S26: 0.021 | T26: 0.016 | U26: 0.024 | V26: 0.026 | W26: 0.024 | X26: 0.022 | Y26: 0.032 | Z26: 0.024 | AA26: 0.011 | AB26: 0.01 | AC26: 0.019 | AD26: 0.021 | AE26: 0.02 | AF26: 0.005 | AG26: 0.007 | AH26: 0.012 | AI26: -0.011 | AJ26: -0.015 | AK26: -0.001 | AL26: 0.001 | AM26: -0.007 | AN26: -0.012 | AO26: 0.008 | AP26: 0.009 | AQ26: -0.014 | AR26: -0.002 | AS26: -0.004 | AT26: -0.096 | AU26: -0.057 | AV26: -0.031 | AW26: -0.048 | AX26: -0.032 | AY26: 0.065 | AZ26: 0.022 | BA26: 0.012 | BB26: 0.016 | BC26: 0.005 | BD26: -0.007 | BE26: -0.015 | BF26: -0.025 | BG26: -0.011 | BH26: -0.013 | BI26: -0.019 | BJ26: -0.024 | BK26: -0.023 | BL26: -0.02 | BM26: -0.038 | BN26: -0.028 | BO26: -0.019 | BP26: -0.032 | BQ26: -0.029 | BR26: -0.028 | BS26: -0.026 | BT26: -0.027 | BU26: -0.027 | BV26: -0.028 | BW26: -0.015 | BX26: -0.019 | CB26: =CHOOSE(MATCH($CF$2,{"Bull","Base","Bear"},0),$CO$34,$CP$34,$CQ$34) -> -0.005 | CC26: =CHOOSE(MATCH($CF$2,{"Bull","Base","Bear"},0),$CO$35,$CP$35,$CQ$35) -> 0 | CD26: =CHOOSE(MATCH($CF$2,{"Bull","Base","Bear"},0),$CO$36,$CP$36,$CQ$36) -> 0.005 | CE26: =CHOOSE(MATCH($CF$2,{"Bull","Base","Bear"},0),$CO$37,$CP$37,$CQ$37) -> 0.005 | CF26: 2027E+: scenario lever SW_vol. | CH26: =IFERROR(AVERAGE(CA26,CB26,CC26,CD26,CE26),"n/m") -> 0.00125 | CI26: =IFERROR(AVERAGE(BB26,BG26,BL26,BQ26,BV26),"n/m") -> -0.0144 | CJ26: =IFERROR(AVERAGE(AC26,AH26,AM26,AR26,AW26,BB26,BG26,BL26,BQ26,BV26),"n/m") -> -0.0098 | CK26: =IFERROR(AVERAGE(C26,D26,E26,F26,G26,H26,I26,N26,S26,X26,AC26,AH26,AM26,AR26,AW26,BB26,BG26,BL26,BQ26,BV26),"n/m") -> -0.00425 | CN26: Minimum net debt / Adjusted EBITDA (x) — buyback floor 2027E+ | CO26: 3 | CP26: 2.75 | CQ26: 2.5 | CR26: WCN targets leverage ~2.5–3.0x (2.75x at YE2025 per the Q4-25 release); surplus cash returned via buybacks once at the floor.
B27: Recycled commodities % | I27: -0.013 | J27: -0.006 | K27: -0.008 | L27: 0 | M27: -0.005 | N27: -0.005 | O27: -0.007 | P27: -0.006 | Q27: -0.005 | R27: -0.006 | S27: -0.006 | T27: -0.008 | U27: -0.005 | V27: -0.005 | W27: -0.004 | X27: -0.006 | Y27: -0.002 | Z27: -0.001 | AA27: 0.004 | AB27: 0.004 | AC27: 0.001 | AD27: 0.015 | AE27: 0.011 | AF27: 0.008 | AG27: -0.003 | AH27: 0.007 | AI27: -0.019 | AJ27: -0.018 | AK27: -0.018 | AL27: -0.008 | AM27: -0.016 | AN27: -0.005 | AO27: -0.007 | AP27: -0.008 | AQ27: -0.008 | AR27: -0.007 | AS27: -0.004 | AT27: 0 | AU27: 0.002 | AV27: 0.005 | AW27: 0.001 | AX27: 0.009 | AY27: 0.015 | AZ27: 0.021 | BA27: 0.026 | BB27: 0.018 | BC27: 0.011 | BD27: 0.004 | BE27: -0.013 | BF27: -0.029 | BG27: -0.007 | BH27: -0.019 | BI27: -0.015 | BJ27: -0.005 | BK27: 0.008 | BL27: -0.008 | BM27: 0.008 | BN27: 0.008 | BO27: 0.01 | BP27: 0.002 | BQ27: 0.007 | BR27: -0.001 | BS27: -0.003 | BT27: -0.008 | BU27: -0.006 | BV27: -0.005 | BW27: -0.005 | BX27: -0.002 | CB27: 0 | CC27: 0 | CD27: 0 | CE27: 0 | CF27: Input 0% (commodity prices assumed flat from 2H/26 levels). | CH27: =IFERROR(AVERAGE(CA27,CB27,CC27,CD27,CE27),"n/m") -> 0 | CI27: =IFERROR(AVERAGE(BB27,BG27,BL27,BQ27,BV27),"n/m") -> 0.001 | CJ27: =IFERROR(AVERAGE(AC27,AH27,AM27,AR27,AW27,BB27,BG27,BL27,BQ27,BV27),"n/m") -> -0.0009 | CK27: =IFERROR(AVERAGE(C27,D27,E27,F27,G27,H27,I27,N27,S27,X27,AC27,AH27,AM27,AR27,AW27,BB27,BG27,BL27,BQ27,BV27),"n/m") -> -0.0027857143
B28: Foreign exchange impact % (Canada; from Q2/17) | AE28: -0.002 | AF28: 0.007 | AG28: 0.008 | AI28: 0.007 | AJ28: 0.007 | AK28: -0.007 | AL28: -0.006 | AN28: -0.007 | AO28: -0.005 | AP28: -0.002 | AQ28: 0 | AS28: -0.001 | AT28: -0.005 | AU28: -0.001 | AV28: 0.002 | AX28: 0.007 | AY28: 0.015 | AZ28: 0.007 | BA28: 0.005 | BB28: 0.009 | BC28: 0 | BD28: -0.005 | BE28: -0.005 | BF28: -0.009 | BG28: -0.005 | BH28: -0.009 | BI28: -0.007 | BJ28: -0.004 | BK28: -0.001 | BL28: -0.005 | BM28: 0 | BN28: -0.002 | BO28: -0.002 | BP28: -0.003 | BQ28: -0.002 | BR28: -0.007 | BS28: -0.002 | BT28: -0.001 | BU28: 0 | BV28: -0.003 | BW28: 0.005 | BX28: 0 | CB28: 0 | CC28: 0 | CD28: 0 | CE28: 0 | CF28: Input 0% (flat CAD/USD). | CN28: SW_price (solid waste price / yield, % of prior-year solid waste revenue) | CO28: 0.0075 | CP28: Δ → | CQ28: -0.0075 | CR28: 1H/26 yield +4.6–4.7% (core price +5.6–6.0%); pricing decelerating with CPI and a lower cost-inflation backdrop.
B29: Closed operation % (Chiquita Canyon landfill, 2025) | BR29: -0.009 | BS29: -0.009 | BT29: -0.008 | BU29: -0.005 | BV29: -0.008 | CN29: 2027E | CO29: =CP29+$CO$28 -> 0.055 | CP29: 0.0475 | CQ29: =CP29+$CQ$28 -> 0.04
B30: Memo: yield % (company basis from Q1/26; replaces core price + surcharges) | BW30: 0.047 | BX30: 0.046 | CN30: 2028E | CO30: =CP30+$CO$28 -> 0.0525 | CP30: 0.045 | CQ30: =CP30+$CQ$28 -> 0.0375
B31: Solid waste internal growth % (company total) | C31: 0.076 | D31: 0.104 | E31: 0.03 | F31: -0.06 | G31: 0.055 | H31: 0.047 | I31: -0.001 | J31: 0.007 | K31: 0.029 | L31: 0.049 | M31: 0.038 | N31: 0.031 | O31: 0.048 | P31: 0.035 | Q31: 0.044 | R31: 0.046 | S31: 0.043 | T31: 0.036 | U31: 0.047 | V31: 0.046 | W31: 0.044 | X31: 0.042 | Y31: 0.057 | Z31: 0.049 | AA31: 0.038 | AB31: 0.04 | AC31: 0.045 | AD31: 0.062 | AE31: 0.06 | AF31: 0.053 | AG31: 0.048 | AH31: 0.051 | AI31: 0.02 | AJ31: 0.016 | AK31: 0.019 | AL31: 0.035 | AM31: 0.022 | AN31: 0.028 | AO31: 0.048 | AP31: 0.051 | AQ31: 0.032 | AR31: 0.043 | AS31: 0.047 | AT31: -0.058 | AU31: -0.019 | AV31: 0.014 | AW31: -0.004 | AX31: 0.026 | AY31: 0.144 | AZ31: 0.101 | BA31: 0.1 | BB31: 0.093 | BC31: 0.087 | BD31: 0.08 | BE31: 0.068 | BF31: 0.043 | BG31: 0.069 | BH31: 0.077 | BI31: 0.05 | BJ31: 0.044 | BK31: 0.063 | BL31: 0.057 | BM31: 0.041 | BN31: 0.046 | BO31: 0.054 | BP31: 0.029 | BQ31: 0.042 | BR31: 0.022 | BS31: 0.024 | BT31: 0.018 | BU31: 0.026 | BV31: 0.02 | BW31: 0.031 | BX31: 0.036 | CB31: =N(CB24)+N(CB25)+N(CB26)+N(CB27)+N(CB28) -> 0.0425 | CC31: =N(CC24)+N(CC25)+N(CC26)+N(CC27)+N(CC28) -> 0.045 | CD31: =N(CD24)+N(CD25)+N(CD26)+N(CD27)+N(CD28) -> 0.0475 | CE31: =N(CE24)+N(CE25)+N(CE26)+N(CE27)+N(CE28) -> 0.045 | CF31: Company-reported (releases; FY from 10-K MD&A). 2006–12 = company-wide internal growth incl. intermodal / recycling / other; 2013+ solid waste basis. Forecast = Σ components above. | CH31: =IFERROR(AVERAGE(CA31,CB31,CC31,CD31,CE31),"n/m") -> 0.045 | CI31: =IFERROR(AVERAGE(BB31,BG31,BL31,BQ31,BV31),"n/m") -> 0.0562 | CJ31: =IFERROR(AVERAGE(AC31,AH31,AM31,AR31,AW31,BB31,BG31,BL31,BQ31,BV31),"n/m") -> 0.0438 | CK31: =IFERROR(AVERAGE(C31,D31,E31,F31,G31,H31,I31,N31,S31,X31,AC31,AH31,AM31,AR31,AW31,BB31,BG31,BL31,BQ31,BV31),"n/m") -> 0.04025 | CN31: 2029E | CO31: =CP31+$CO$28 -> 0.05 | CP31: 0.0425 | CQ31: =CP31+$CQ$28 -> 0.035
B32: Acquisitions, net of divestitures — contribution to solid waste growth % (derived) | D32: =IF(AND(ISNUMBER(D20),ISNUMBER(D31)),D20-D31,"") -> 0.04760589 | E32: =IF(AND(ISNUMBER(E20),ISNUMBER(E31)),E20-E31,"") -> 0.074666497 | F32: =IF(AND(ISNUMBER(F20),ISNUMBER(F31)),F20-F31,"") -> 0.2403344 | G32: =IF(AND(ISNUMBER(G20),ISNUMBER(G31)),G20-G31,"") -> 0.034087629 | H32: =IF(AND(ISNUMBER(H20),ISNUMBER(H31)),H20-H31,"") -> 0.073481594 | I32: =IF(AND(ISNUMBER(I20),ISNUMBER(I31)),I20-I31,"") -> 0.12972714 | N32: =IF(AND(ISNUMBER(N20),ISNUMBER(N31)),N20-N31,"") -> 0.018135976 | O32: =IF(AND(ISNUMBER(O20),ISNUMBER(O31)),O20-O31,"") -> 0.0020563594 | P32: =IF(AND(ISNUMBER(P20),ISNUMBER(P31)),P20-P31,"") -> 0.0022481104 | Q32: =IF(AND(ISNUMBER(Q20),ISNUMBER(Q31)),Q20-Q31,"") -> 0.010356621 | R32: =IF(AND(ISNUMBER(R20),ISNUMBER(R31)),R20-R31,"") -> 0.015605069 | S32: =IF(AND(ISNUMBER(S20),ISNUMBER(S31)),S20-S31,"") -> 0.0077896857 | T32: =IF(AND(ISNUMBER(T20),ISNUMBER(T31)),T20-T31,"") -> 0.016651872 | U32: =IF(AND(ISNUMBER(U20),ISNUMBER(U31)),U20-U31,"") -> 0.014096207 | ... BX32: =IF(AND(ISNUMBER(BX20),ISNUMBER(BX31)),BX20-BX31,"") -> 0.01854246 | CF32: Derived: gross solid waste y/y − company internal growth (approximation; internal growth is measured on reported revenues). Forecast M&A sits in the future-acquisitions block. | CN32: 2030E | CO32: =CP32+$CO$28 -> 0.0475 | CP32: 0.04 | CQ32: =CP32+$CQ$28 -> 0.0325
CN33: SW_vol (solid waste unit volume y/y) | CO33: 0.01 | CP33: Δ → | CQ33: -0.01 | CR33: Unit volume −1.5% / −1.9% in Q1/Q2-26 (purposeful shedding, Chiquita Canyon closure, soft C&D / roll-off). Recovery assumed as shedding laps.
B34: Revenue change bridge y/y ($m) — company MD&A (10-Q quarters; Q4 = FY − Q1 − Q2 − Q3) | CN34: 2027E | CO34: =CP34+$CO$33 -> 0.005 | CP34: -0.005 | CQ34: =CP34+$CQ$33 -> -0.015
B35: Δ Total revenues y/y (company MD&A) | C35: 102.5 | D35: 134.1 | E35: 91.1 | F35: 141.8 | G35: 128.4 | H35: 185.6 | I35: 156.2 | J35: 73.5 | K35: 78.7 | L35: 77.9 | M35: =IF(AND(ISNUMBER(N35),ISNUMBER(J35),ISNUMBER(K35),ISNUMBER(L35)),N35-J35-K35-L35,"") -> 37.1 | N35: 267.2 | O35: 31.8 | P35: 35.3 | Q35: 43 | R35: =IF(AND(ISNUMBER(S35),ISNUMBER(O35),ISNUMBER(P35),ISNUMBER(Q35)),S35-O35-P35-Q35,"") -> 40.3 | S35: 150.4 | T35: 24.4 | U35: 6.6 | V35: 1.3 | W35: =IF(AND(ISNUMBER(X35),ISNUMBER(T35),ISNUMBER(U35),ISNUMBER(V35)),X35-T35-U35-V35,"") -> 5.8 | X35: 38.1 | Y35: 8.6 | Z35: 196.3 | AA35: 537 | AB35: =IF(AND(ISNUMBER(AC35),ISNUMBER(Y35),ISNUMBER(Z35),ISNUMBER(AA35)),AC35-Y35-Z35-AA35,"") -> 517.1 | AC35: 1259 | AD35: 576.6 | AE35: 448 | AF35: 121.6 | AG35: =IF(AND(ISNUMBER(AH35),ISNUMBER(AD35),ISNUMBER(AE35),ISNUMBER(AF35)),AH35-AD35-AE35-AF35,"") -> 108.8 | AH35: 1255 | AI35: 48.8 | AJ35: 64.4 | AK35: 74.6 | AL35: =IF(AND(ISNUMBER(AM35),ISNUMBER(AI35),ISNUMBER(AJ35),ISNUMBER(AK35)),AM35-AI35-AJ35-AK35,"") -> 104.6 | AM35: 292.4 | AN35: 104.5 | AO35: 129.6 | AP35: 131.3 | AQ35: =IF(AND(ISNUMBER(AR35),ISNUMBER(AN35),ISNUMBER(AO35),ISNUMBER(AP35)),AR35-AN35-AO35-AP35,"") -> 100.4 | AR35: 465.8 | AS35: 107.8 | AT35: -63.8 | AU35: -22.8 | AV35: =IF(AND(ISNUMBER(AW35),ISNUMBER(AS35),ISNUMBER(AT35),ISNUMBER(AU35)),AW35-AS35-AT35-AU35,"") -> 36.1 | AW35: 57.3 | AX35: 43.5 | AY35: 228.1 | AZ35: 207.6 | BA35: =IF(AND(ISNUMBER(BB35),ISNUMBER(AX35),ISNUMBER(AY35),ISNUMBER(AZ35)),BB35-AX35-AY35-AZ35,"") -> 226.2 | BB35: 705.4 | BC35: 250.3 | BD35: 282.5 | BE35: 282.7 | BF35: =IF(AND(ISNUMBER(BG35),ISNUMBER(BC35),ISNUMBER(BD35),ISNUMBER(BE35)),BG35-BC35-BD35-BE35,"") -> 244.5 | BG35: 1060 | BH35: 254.2 | BI35: 204.7 | BJ35: 184.9 | BK35: =IF(AND(ISNUMBER(BL35),ISNUMBER(BH35),ISNUMBER(BI35),ISNUMBER(BJ35)),BL35-BH35-BI35-BJ35,"") -> 166.3 | BL35: 810.1 | BM35: 172.2 | BN35: 227.1 | BO35: 273.7 | BP35: =IF(AND(ISNUMBER(BQ35),ISNUMBER(BM35),ISNUMBER(BN35),ISNUMBER(BO35)),BQ35-BM35-BN35-BO35,"") -> 224.6 | BQ35: 897.6 | BR35: 155.5 | BS35: 158.9 | BT35: 119.9 | BU35: =IF(AND(ISNUMBER(BV35),ISNUMBER(BR35),ISNUMBER(BS35),ISNUMBER(BT35)),BV35-BR35-BS35-BT35,"") -> 113 | BV35: 547.3 | BW35: 142.5 | BX35: 154.6 | CN35: 2028E | CO35: =CP35+$CO$33 -> 0.01 | CP35: 0 | CQ35: =CP35+$CQ$33 -> -0.01
B36: of which: acquisitions, net of divestitures & closed operations | C36: 47.7 | D36: 48.3 | E36: 62.1 | F36: 203.6 | G36: 62.9 | H36: 124.7 | I36: 158.8 | J36: 70.6 | K36: 68.9 | L36: 60.8 | M36: =IF(AND(ISNUMBER(N36),COUNT(J36,K36,L36)>0),N36-N(J36)-N(K36)-N(L36),"") -> 18.5 | N36: 218.8 | O36: 2.8 | P36: 3.7 | Q36: 6.6 | R36: =IF(AND(ISNUMBER(S36),COUNT(O36,P36,Q36)>0),S36-N(O36)-N(P36)-N(Q36),"") -> 8.7 | S36: 21.8 | T36: 13.9 | U36: 11.3 | V36: 11.6 | W36: =IF(AND(ISNUMBER(X36),COUNT(T36,U36,V36)>0),X36-N(T36)-N(U36)-N(V36),"") -> 20.8 | X36: 57.6 | Y36: 21.5 | Z36: 199.4 | AA36: 538.5 | AB36: =IF(AND(ISNUMBER(AC36),COUNT(Y36,Z36,AA36)>0),AC36-N(Y36)-N(Z36)-N(AA36),"") -> 507.3 | AC36: 1266.7 | AD36: 539 | AE36: 386.3 | AF36: 40.2 | AG36: =IF(AND(ISNUMBER(AH36),COUNT(AD36,AE36,AF36)>0),AH36-N(AD36)-N(AE36)-N(AF36),"") -> 37.5 | AH36: 1003 | AI36: 10.8 | AJ36: 32.7 | AK36: 48.1 | AL36: =IF(AND(ISNUMBER(AM36),COUNT(AI36,AJ36,AK36)>0),AM36-N(AI36)-N(AJ36)-N(AK36),"") -> 61.5 | AM36: 153.1 | AN36: 69 | AO36: 77.4 | AP36: 77 | AQ36: =IF(AND(ISNUMBER(AR36),COUNT(AN36,AO36,AP36)>0),AR36-N(AN36)-N(AO36)-N(AP36),"") -> 68.6 | AR36: 292 | AS36: 59.6 | AT36: 40.7 | AU36: 44.3 | AV36: =IF(AND(ISNUMBER(AW36),COUNT(AS36,AT36,AU36)>0),AW36-N(AS36)-N(AT36)-N(AU36),"") -> 52.6 | AW36: 197.2 | AX36: 40.5 | AY36: 44.1 | AZ36: 51.3 | BA36: =IF(AND(ISNUMBER(BB36),COUNT(AX36,AY36,AZ36)>0),BB36-N(AX36)-N(AY36)-N(AZ36),"") -> 79.5 | BB36: 215.4 | BC36: 110 | BD36: 141.4 | BE36: 150.7 | BF36: =IF(AND(ISNUMBER(BG36),COUNT(BC36,BD36,BE36)>0),BG36-N(BC36)-N(BD36)-N(BE36),"") -> 149.9 | BG36: 552 | BH36: 132.1 | BI36: 121.3 | BJ36: 102.9 | BK36: =IF(AND(ISNUMBER(BL36),COUNT(BH36,BI36,BJ36)>0),BL36-N(BH36)-N(BI36)-N(BJ36),"") -> 51 | BL36: 407.3 | BM36: 78 | BN36: 120.8 | BO36: 161 | BP36: =IF(AND(ISNUMBER(BQ36),COUNT(BM36,BN36,BO36)>0),BQ36-N(BM36)-N(BN36)-N(BO36),"") -> 169.2 | BQ36: 529 | BR36: 112.1 | BS36: 95.3 | BT36: 62.2 | BU36: =IF(AND(ISNUMBER(BV36),COUNT(BR36,BS36,BT36)>0),BV36-N(BR36)-N(BS36)-N(BT36),"") -> 48.2 | BV36: 317.8 | BW36: 55.2 | BX36: 45.8 | CN36: 2029E | CO36: =CP36+$CO$33 -> 0.015 | CP36: 0.005 | CQ36: =CP36+$CQ$33 -> -0.005
B37: of which: solid waste core price (total price incl. surcharges 2006–08) | C37: 37.2 | D37: 38.2 | E37: 53.6 | F37: 49.6 | G37: 31.8 | H37: 36.7 | I37: 45.1 | J37: 10.5 | K37: 10.8 | L37: 10.2 | M37: =IF(AND(ISNUMBER(N37),COUNT(J37,K37,L37)>0),N37-N(J37)-N(K37)-N(L37),"") -> 10.7 | N37: 42.2 | O37: 11.3 | P37: 11 | Q37: 12.1 | R37: =IF(AND(ISNUMBER(S37),COUNT(O37,P37,Q37)>0),S37-N(O37)-N(P37)-N(Q37),"") -> 12.2 | S37: 46.6 | T37: 11.7 | U37: 12.7 | V37: 12.7 | W37: =IF(AND(ISNUMBER(X37),COUNT(T37,U37,V37)>0),X37-N(T37)-N(U37)-N(V37),"") -> 12.9 | X37: 50 | Y37: 13.4 | Z37: 13.7 | AA37: 12.6 | AB37: =IF(AND(ISNUMBER(AC37),COUNT(Y37,Z37,AA37)>0),AC37-N(Y37)-N(Z37)-N(AA37),"") -> 12.9 | AC37: 52.6 | AD37: 12.4 | AE37: 20.5 | AF37: 32.6 | AG37: =IF(AND(ISNUMBER(AH37),COUNT(AD37,AE37,AF37)>0),AH37-N(AD37)-N(AE37)-N(AF37),"") -> 32.7 | AH37: 98.2 | AI37: 40.2 | AJ37: 42.1 | AK37: 43.4 | AL37: =IF(AND(ISNUMBER(AM37),COUNT(AI37,AJ37,AK37)>0),AM37-N(AI37)-N(AJ37)-N(AK37),"") -> 46.5 | AM37: 172.2 | AN37: 52 | AO37: 56.3 | AP37: 60.1 | AQ37: =IF(AND(ISNUMBER(AR37),COUNT(AN37,AO37,AP37)>0),AR37-N(AN37)-N(AO37)-N(AP37),"") -> 62.1 | AR37: 230.5 | AS37: 63 | AT37: 57.1 | AU37: 53.8 | AV37: =IF(AND(ISNUMBER(AW37),COUNT(AS37,AT37,AU37)>0),AW37-N(AS37)-N(AT37)-N(AU37),"") -> 53.8 | AW37: 227.7 | AX37: 55.9 | AY37: 58.3 | AZ37: 62 | BA37: =IF(AND(ISNUMBER(BB37),COUNT(AX37,AY37,AZ37)>0),BB37-N(AX37)-N(AY37)-N(AZ37),"") -> 67.3 | BB37: 243.5 | BC37: 83.5 | BD37: 105.6 | BE37: 126.3 | BF37: =IF(AND(ISNUMBER(BG37),COUNT(BC37,BD37,BE37)>0),BG37-N(BC37)-N(BD37)-N(BE37),"") -> 140.4 | BG37: 455.8 | BH37: 171.2 | BI37: 168.5 | BJ37: 156.6 | BK37: =IF(AND(ISNUMBER(BL37),COUNT(BH37,BI37,BJ37)>0),BL37-N(BH37)-N(BI37)-N(BJ37),"") -> 154.8 | BL37: 651.1 | BM37: 140.6 | BN37: 135.7 | BO37: 132.9 | BP37: =IF(AND(ISNUMBER(BQ37),COUNT(BM37,BN37,BO37)>0),BQ37-N(BM37)-N(BN37)-N(BO37),"") -> 129.8 | BQ37: 539 | BR37: 133.2 | BS37: 136.9 | BT37: 134.3 | BU37: =IF(AND(ISNUMBER(BV37),COUNT(BR37,BS37,BT37)>0),BV37-N(BR37)-N(BS37)-N(BT37),"") -> 132.6 | BV37: 537 | BW37: 121.3 | BX37: 121.8 | CN37: 2030E | CO37: =CP37+$CO$33 -> 0.015 | CP37: 0.005 | CQ37: =CP37+$CQ$33 -> -0.005
B38: of which: surcharges | F38: -21.9 | G38: 2.6 | H38: 10.3 | I38: 2.4 | J38: 1.5 | K38: 0.9 | L38: 1.2 | M38: =IF(AND(ISNUMBER(N38),COUNT(J38,K38,L38)>0),N38-N(J38)-N(K38)-N(L38),"") -> 0.9 | N38: 4.5 | O38: 0.3 | Q38: 0.3 | R38: =IF(AND(ISNUMBER(S38),COUNT(O38,P38,Q38)>0),S38-N(O38)-N(P38)-N(Q38),"") -> 0.1 | S38: 0.7 | U38: -0.4 | V38: -1 | W38: =IF(AND(ISNUMBER(X38),COUNT(T38,U38,V38)>0),X38-N(T38)-N(U38)-N(V38),"") -> -2.2 | X38: -3.6 | Y38: -1.7 | Z38: -1.5 | AA38: -1.3 | AB38: =IF(AND(ISNUMBER(AC38),COUNT(Y38,Z38,AA38)>0),AC38-N(Y38)-N(Z38)-N(AA38),"") -> -0.2 | AC38: -4.7 | AD38: 0.2 | AE38: 0.4 | AF38: 0.2 | AG38: =IF(AND(ISNUMBER(AH38),COUNT(AD38,AE38,AF38)>0),AH38-N(AD38)-N(AE38)-N(AF38),"") -> 1 | AH38: 1.8 | AI38: 2.1 | AJ38: 3.5 | AK38: 6.1 | AL38: =IF(AND(ISNUMBER(AM38),COUNT(AI38,AJ38,AK38)>0),AM38-N(AI38)-N(AJ38)-N(AK38),"") -> 4.7 | AM38: 16.4 | AN38: 2.8 | AO38: 2.2 | AP38: 1 | AQ38: =IF(AND(ISNUMBER(AR38),COUNT(AN38,AO38,AP38)>0),AR38-N(AN38)-N(AO38)-N(AP38),"") -> 0.5 | AR38: 6.5 | AS38: 1.5 | AT38: -2.7 | AU38: -4.7 | AV38: =IF(AND(ISNUMBER(AW38),COUNT(AS38,AT38,AU38)>0),AW38-N(AS38)-N(AT38)-N(AU38),"") -> -5.8 | AW38: -11.7 | AX38: -3.7 | AY38: 2.6 | AZ38: 5.7 | BA38: =IF(AND(ISNUMBER(BB38),COUNT(AX38,AY38,AZ38)>0),BB38-N(AX38)-N(AY38)-N(AZ38),"") -> 9.1 | BB38: 13.7 | BC38: 10.5 | BD38: 23 | BE38: 27.9 | BF38: =IF(AND(ISNUMBER(BG38),COUNT(BC38,BD38,BE38)>0),BG38-N(BC38)-N(BD38)-N(BE38),"") -> 24.5 | BG38: 85.9 | BH38: 12.3 | BI38: -12.7 | BJ38: -19.2 | BK38: =IF(AND(ISNUMBER(BL38),COUNT(BH38,BI38,BJ38)>0),BL38-N(BH38)-N(BI38)-N(BJ38),"") -> -14.9 | BL38: -34.5 | BM38: -12.1 | BN38: -4.5 | BO38: -5.2 | BP38: =IF(AND(ISNUMBER(BQ38),COUNT(BM38,BN38,BO38)>0),BQ38-N(BM38)-N(BN38)-N(BO38),"") -> -10.8 | BQ38: -32.6 | BR38: -3.7 | BS38: -4.1 | BT38: -2.2 | BU38: =IF(AND(ISNUMBER(BV38),COUNT(BR38,BS38,BT38)>0),BV38-N(BR38)-N(BS38)-N(BT38),"") -> -0.4 | BV38: -10.4 | BW38: -1.3 | BX38: 24.5 | CN38: EP_g (E&P waste revenues y/y) | CO38: 0.06 | CP38: Δ → | CQ38: -0.06 | CR38: E&P gross revenues +18% y/y in Q2/26 (Permian / Bakken activity, acquired E&P facilities); oil-price sensitive.
B39: of which: solid waste volume | C39: 20 | D39: 12.6 | E39: -22.2 | F39: -64.2 | G39: 0.5 | H39: -3.9 | I39: -31.4 | J39: -7.1 | K39: 3.3 | L39: 8.1 | M39: =IF(AND(ISNUMBER(N39),COUNT(J39,K39,L39)>0),N39-N(J39)-N(K39)-N(L39),"") -> 9.4 | N39: 13.7 | O39: 9.7 | P39: 6.3 | Q39: 9.1 | R39: =IF(AND(ISNUMBER(S39),COUNT(O39,P39,Q39)>0),S39-N(O39)-N(P39)-N(Q39),"") -> 10 | S39: 35.1 | T39: 6.5 | U39: 10.5 | V39: 11.8 | W39: =IF(AND(ISNUMBER(X39),COUNT(T39,U39,V39)>0),X39-N(T39)-N(U39)-N(V39),"") -> 10.7 | X39: 39.5 | Y39: 14.1 | Z39: 11.7 | AA39: 5.5 | AB39: =IF(AND(ISNUMBER(AC39),COUNT(Y39,Z39,AA39)>0),AC39-N(Y39)-N(Z39)-N(AA39),"") -> 5.2 | AC39: 36.5 | AD39: 10 | AE39: 13.6 | AF39: 5 | AG39: =IF(AND(ISNUMBER(AH39),COUNT(AD39,AE39,AF39)>0),AH39-N(AD39)-N(AE39)-N(AF39),"") -> 7.1 | AH39: 35.7 | AI39: -11.2 | AJ39: -15.6 | AK39: -1.4 | AL39: =IF(AND(ISNUMBER(AM39),COUNT(AI39,AJ39,AK39)>0),AM39-N(AI39)-N(AJ39)-N(AK39),"") -> 1.5 | AM39: -26.7 | AN39: -12.6 | AO39: 9.3 | AP39: 10.3 | AQ39: =IF(AND(ISNUMBER(AR39),COUNT(AN39,AO39,AP39)>0),AR39-N(AN39)-N(AO39)-N(AP39),"") -> -15.9 | AR39: -8.9 | AS39: -4 | AT39: -121.2 | AU39: -74.6 | AV39: =IF(AND(ISNUMBER(AW39),COUNT(AS39,AT39,AU39)>0),AW39-N(AS39)-N(AT39)-N(AU39),"") -> -39 | AW39: -238.8 | AX39: -40.5 | AY39: 80.2 | AZ39: 28.9 | BA39: =IF(AND(ISNUMBER(BB39),COUNT(AX39,AY39,AZ39)>0),BB39-N(AX39)-N(AY39)-N(AZ39),"") -> 16.4 | BB39: 85 | BC39: 7 | BD39: -10.4 | BE39: -22.3 | BF39: =IF(AND(ISNUMBER(BG39),COUNT(BC39,BD39,BE39)>0),BG39-N(BC39)-N(BD39)-N(BE39),"") -> -37.5 | BG39: -63.2 | BH39: -20.5 | BI39: -32.9 | BJ39: -42 | BK39: =IF(AND(ISNUMBER(BL39),COUNT(BH39,BI39,BJ39)>0),BL39-N(BH39)-N(BI39)-N(BJ39),"") -> -41.6 | BL39: -137 | BM39: -69.6 | BN39: -54.2 | BO39: -37.7 | BP39: =IF(AND(ISNUMBER(BQ39),COUNT(BM39,BN39,BO39)>0),BQ39-N(BM39)-N(BN39)-N(BO39),"") -> -61 | BQ39: -222.5 | BR39: -65.9 | BS39: -56.2 | BT39: -59.4 | BU39: =IF(AND(ISNUMBER(BV39),COUNT(BR39,BS39,BT39)>0),BV39-N(BR39)-N(BS39)-N(BT39),"") -> -56.5 | BV39: -238 | BW39: -57.9 | BX39: -64.1 | CN39: 2027E | CO39: =CP39+$CO$38 -> 0.12 | CP39: 0.06 | CQ39: =CP39+$CQ$38 -> 0
B40: of which: recycled commodities (incl. recycling-facility closures) | D40: 13 | E40: -3.3 | F40: -15.5 | G40: 24.6 | H40: 14 | I40: -20 | J40: -2.4 | K40: -3.3 | L40: -0.2 | M40: =IF(AND(ISNUMBER(N40),COUNT(J40,K40,L40)>0),N40-N(J40)-N(K40)-N(L40),"") -> -2 | N40: -7.9 | O40: -2.7 | P40: -2.5 | Q40: -2.3 | R40: =IF(AND(ISNUMBER(S40),COUNT(O40,P40,Q40)>0),S40-N(O40)-N(P40)-N(Q40),"") -> -2.3 | S40: -9.8 | T40: -3.5 | U40: -2.3 | V40: -2.4 | W40: =IF(AND(ISNUMBER(X40),COUNT(T40,U40,V40)>0),X40-N(T40)-N(U40)-N(V40),"") -> -1.7 | X40: -9.9 | Y40: -0.9 | Z40: -0.6 | AA40: 1.8 | AB40: =IF(AND(ISNUMBER(AC40),COUNT(Y40,Z40,AA40)>0),AC40-N(Y40)-N(Z40)-N(AA40),"") -> 1.9 | AC40: 2.2 | AD40: 7.1 | AE40: 7.6 | AF40: 7.9 | AG40: =IF(AND(ISNUMBER(AH40),COUNT(AD40,AE40,AF40)>0),AH40-N(AD40)-N(AE40)-N(AF40),"") -> -3.1 | AH40: 19.5 | AI40: -18.8 | AJ40: -19.7 | AK40: -19.5 | AL40: =IF(AND(ISNUMBER(AM40),COUNT(AI40,AJ40,AK40)>0),AM40-N(AI40)-N(AJ40)-N(AK40),"") -> -8.3 | AM40: -66.3 | AN40: -5.3 | AO40: -7.1 | AP40: -9.5 | AQ40: =IF(AND(ISNUMBER(AR40),COUNT(AN40,AO40,AP40)>0),AR40-N(AN40)-N(AO40)-N(AP40),"") -> -10 | AR40: -31.9 | AS40: -4.4 | AT40: -0.5 | AU40: 2.4 | AV40: =IF(AND(ISNUMBER(AW40),COUNT(AS40,AT40,AU40)>0),AW40-N(AS40)-N(AT40)-N(AU40),"") -> 6.8 | AW40: 4.3 | AX40: 11.3 | AY40: 18 | AZ40: 28.3 | BA40: =IF(AND(ISNUMBER(BB40),COUNT(AX40,AY40,AZ40)>0),BB40-N(AX40)-N(AY40)-N(AZ40),"") -> 35.1 | BB40: 92.7 | BC40: 15 | BD40: 5.7 | BE40: -19.5 | BF40: =IF(AND(ISNUMBER(BG40),COUNT(BC40,BD40,BE40)>0),BG40-N(BC40)-N(BD40)-N(BE40),"") -> -46.2 | BG40: -45 | BH40: -29.9 | BI40: -25.8 | BJ40: -9.5 | BK40: =IF(AND(ISNUMBER(BL40),COUNT(BH40,BI40,BJ40)>0),BL40-N(BH40)-N(BI40)-N(BJ40),"") -> 13.9 | BL40: -51.3 | BM40: 15.3 | BN40: 15.2 | BO40: 19.2 | BP40: =IF(AND(ISNUMBER(BQ40),COUNT(BM40,BN40,BO40)>0),BQ40-N(BM40)-N(BN40)-N(BO40),"") -> 4.3 | BQ40: 54 | BR40: -2.1 | BS40: -7 | BT40: -17.1 | BU40: =IF(AND(ISNUMBER(BV40),COUNT(BR40,BS40,BT40)>0),BV40-N(BR40)-N(BS40)-N(BT40),"") -> -11.5 | BV40: -37.7 | BW40: -9.2 | BX40: -4.8 | CN40: 2028E | CO40: =CP40+$CO$38 -> 0.11 | CP40: 0.05 | CQ40: =CP40+$CQ$38 -> -0.01
B41: of which: E&P waste (volume & price; incl. new facilities 2015) | J41: -0.4 | M41: =IF(AND(ISNUMBER(N41),COUNT(J41,K41,L41)>0),N41-N(J41)-N(K41)-N(L41),"") | O41: 11.6 | P41: 16.1 | Q41: 15.9 | R41: =IF(AND(ISNUMBER(S41),COUNT(O41,P41,Q41)>0),S41-N(O41)-N(P41)-N(Q41),"") -> 12.2 | S41: 55.8 | T41: -7.9 | U41: -31.5 | V41: -36.2 | W41: =IF(AND(ISNUMBER(X41),COUNT(T41,U41,V41)>0),X41-N(T41)-N(U41)-N(V41),"") -> -40.5 | X41: -116.1 | Y41: -38.1 | Z41: -25 | AA41: -21.1 | AB41: =IF(AND(ISNUMBER(AC41),COUNT(Y41,Z41,AA41)>0),AC41-N(Y41)-N(Z41)-N(AA41),"") -> -11 | AC41: -95.2 | AD41: 6.4 | AE41: 19.7 | AF41: 24.7 | AG41: =IF(AND(ISNUMBER(AH41),COUNT(AD41,AE41,AF41)>0),AH41-N(AD41)-N(AE41)-N(AF41),"") -> 21 | AH41: 71.8 | AI41: 18.7 | AJ41: 13 | AK41: 10.1 | AL41: =IF(AND(ISNUMBER(AM41),COUNT(AI41,AJ41,AK41)>0),AM41-N(AI41)-N(AJ41)-N(AK41),"") -> 10.8 | AM41: 52.6 | AN41: 7.5 | AO41: 3.5 | AP41: 1.4 | AQ41: =IF(AND(ISNUMBER(AR41),COUNT(AN41,AO41,AP41)>0),AR41-N(AN41)-N(AO41)-N(AP41),"") -> -1.6 | AR41: 10.8 | AS41: -3.9 | AT41: -28.5 | AU41: -42.8 | AV41: =IF(AND(ISNUMBER(AW41),COUNT(AS41,AT41,AU41)>0),AW41-N(AS41)-N(AT41)-N(AU41),"") -> -36.9 | AW41: -112.1 | AX41: -34.7 | AY41: -4.4 | AZ41: 11.3 | BA41: =IF(AND(ISNUMBER(BB41),COUNT(AX41,AY41,AZ41)>0),BB41-N(AX41)-N(AY41)-N(AZ41),"") -> 8.9 | BB41: -18.9 | BC41: 16.6 | BD41: 19.9 | BE41: 19.3 | BF41: =IF(AND(ISNUMBER(BG41),COUNT(BC41,BD41,BE41)>0),BG41-N(BC41)-N(BD41)-N(BE41),"") -> 20 | BG41: 75.8 | BH41: 7.8 | BI41: 3.6 | BJ41: 3.7 | BK41: =IF(AND(ISNUMBER(BL41),COUNT(BH41,BI41,BJ41)>0),BL41-N(BH41)-N(BI41)-N(BJ41),"") -> 2 | BL41: 17.1 | BM41: 8.6 | BN41: 9 | BO41: 5.5 | BP41: =IF(AND(ISNUMBER(BQ41),COUNT(BM41,BN41,BO41)>0),BQ41-N(BM41)-N(BN41)-N(BO41),"") -> 2.2 | BQ41: 25.3 | BR41: 0.4 | BS41: 2.8 | BT41: 10.4 | BU41: =IF(AND(ISNUMBER(BV41),COUNT(BR41,BS41,BT41)>0),BV41-N(BR41)-N(BS41)-N(BT41),"") -> 4 | BV41: 17.6 | BW41: 18.8 | BX41: 23.4 | CN41: 2029E | CO41: =CP41+$CO$38 -> 0.1 | CP41: 0.04 | CQ41: =CP41+$CQ$38 -> -0.02
B42: of which: intermodal, renewable fuels / landfill gas & other | C42: -2.4 | D42: 22 | E42: 0.8 | F42: -9.8 | G42: 6 | H42: 3.8 | I42: 1.3 | J42: 0.8 | K42: -1.9 | L42: -2.2 | M42: =IF(AND(ISNUMBER(N42),COUNT(J42,K42,L42)>0),N42-N(J42)-N(K42)-N(L42),"") -> -0.8 | N42: -4.1 | O42: -1.2 | P42: 0.7 | Q42: 1.3 | R42: =IF(AND(ISNUMBER(S42),COUNT(O42,P42,Q42)>0),S42-N(O42)-N(P42)-N(Q42),"") -> -0.6 | S42: 0.2 | T42: 3.7 | U42: 6.3 | V42: 4.8 | W42: =IF(AND(ISNUMBER(X42),COUNT(T42,U42,V42)>0),X42-N(T42)-N(U42)-N(V42),"") -> 5.8 | X42: 20.6 | Y42: 0.3 | Z42: -1.4 | AA42: 1 | AB42: =IF(AND(ISNUMBER(AC42),COUNT(Y42,Z42,AA42)>0),AC42-N(Y42)-N(Z42)-N(AA42),"") -> 0.9 | AC42: 0.8 | AD42: 1.5 | AE42: 1.7 | AF42: 3.4 | AG42: =IF(AND(ISNUMBER(AH42),COUNT(AD42,AE42,AF42)>0),AH42-N(AD42)-N(AE42)-N(AF42),"") -> 3.8 | AH42: 10.4 | AI42: -0.6 | AJ42: 0.7 | AK42: -4 | AL42: =IF(AND(ISNUMBER(AM42),COUNT(AI42,AJ42,AK42)>0),AM42-N(AI42)-N(AJ42)-N(AK42),"") -> -5.3 | AM42: -9.2 | AN42: -0.6 | AO42: -5.6 | AP42: -7.1 | AQ42: =IF(AND(ISNUMBER(AR42),COUNT(AN42,AO42,AP42)>0),AR42-N(AN42)-N(AO42)-N(AP42),"") -> -3.3 | AR42: -16.6 | AS42: -2.3 | AT42: -2.4 | AU42: 0.4 | AV42: =IF(AND(ISNUMBER(AW42),COUNT(AS42,AT42,AU42)>0),AW42-N(AS42)-N(AT42)-N(AU42),"") -> 2.1 | AW42: -2.2 | AX42: 4.4 | AY42: 8.8 | AZ42: 9.6 | BA42: =IF(AND(ISNUMBER(BB42),COUNT(AX42,AY42,AZ42)>0),BB42-N(AX42)-N(AY42)-N(AZ42),"") -> 3.1 | BB42: 25.9 | BC42: 7.7 | BD42: 5.8 | BE42: 8.1 | BF42: =IF(AND(ISNUMBER(BG42),COUNT(BC42,BD42,BE42)>0),BG42-N(BC42)-N(BD42)-N(BE42),"") -> 10 | BG42: 31.6 | BH42: -5.1 | BI42: -5 | BJ42: -1.1 | BK42: =IF(AND(ISNUMBER(BL42),COUNT(BH42,BI42,BJ42)>0),BL42-N(BH42)-N(BI42)-N(BJ42),"") -> 1.9 | BL42: -9.3 | BM42: 11 | BN42: 9.7 | BO42: 2.3 | BP42: =IF(AND(ISNUMBER(BQ42),COUNT(BM42,BN42,BO42)>0),BQ42-N(BM42)-N(BN42)-N(BO42),"") -> -2.9 | BQ42: 20.1 | BR42: -1.7 | BS42: -5.3 | BT42: -4.9 | BU42: =IF(AND(ISNUMBER(BV42),COUNT(BR42,BS42,BT42)>0),BV42-N(BR42)-N(BS42)-N(BT42),"") -> -3.9 | BV42: -15.8 | BW42: 1.6 | BX42: 7.9 | CN42: 2030E | CO42: =CP42+$CO$38 -> 0.1 | CP42: 0.04 | CQ42: =CP42+$CQ$38 -> -0.02
B43: of which: foreign exchange (Canadian dollar translation) | M43: =IF(AND(ISNUMBER(N43),COUNT(J43,K43,L43)>0),N43-N(J43)-N(K43)-N(L43),"") | R43: =IF(AND(ISNUMBER(S43),COUNT(O43,P43,Q43)>0),S43-N(O43)-N(P43)-N(Q43),"") | W43: =IF(AND(ISNUMBER(X43),COUNT(T43,U43,V43)>0),X43-N(T43)-N(U43)-N(V43),"") | AB43: =IF(AND(ISNUMBER(AC43),COUNT(Y43,Z43,AA43)>0),AC43-N(Y43)-N(Z43)-N(AA43),"") | AE43: -1.8 | AF43: 7.6 | AG43: =IF(AND(ISNUMBER(AH43),COUNT(AD43,AE43,AF43)>0),AH43-N(AD43)-N(AE43)-N(AF43),"") -> 8.4 | AH43: 14.2 | AI43: 7.6 | AJ43: 7.7 | AK43: -8.2 | AL43: =IF(AND(ISNUMBER(AM43),COUNT(AI43,AJ43,AK43)>0),AM43-N(AI43)-N(AJ43)-N(AK43),"") -> -6.9 | AM43: 0.2 | AN43: -8.3 | AO43: -6.4 | AP43: -1.9 | AQ43: =IF(AND(ISNUMBER(AR43),COUNT(AN43,AO43,AP43)>0),AR43-N(AN43)-N(AO43)-N(AP43),"") -> 0 | AR43: -16.6 | AS43: -1.7 | AT43: -6.3 | AU43: -1.6 | AV43: =IF(AND(ISNUMBER(AW43),COUNT(AS43,AT43,AU43)>0),AW43-N(AS43)-N(AT43)-N(AU43),"") -> 2.5 | AW43: -7.1 | AX43: 10.3 | AY43: 20.5 | AZ43: 10.5 | BA43: =IF(AND(ISNUMBER(BB43),COUNT(AX43,AY43,AZ43)>0),BB43-N(AX43)-N(AY43)-N(AZ43),"") -> 6.8 | BB43: 48.1 | BD43: -8.5 | BE43: -7.8 | BF43: =IF(AND(ISNUMBER(BG43),COUNT(BC43,BD43,BE43)>0),BG43-N(BC43)-N(BD43)-N(BE43),"") -> -16.1 | BG43: -32.4 | BH43: -13.7 | BI43: -12.3 | BJ43: -6.5 | BK43: =IF(AND(ISNUMBER(BL43),COUNT(BH43,BI43,BJ43)>0),BL43-N(BH43)-N(BI43)-N(BJ43),"") -> -0.8 | BL43: -33.3 | BM43: 0.4 | BN43: -4.6 | BO43: -4.3 | BP43: =IF(AND(ISNUMBER(BQ43),COUNT(BM43,BN43,BO43)>0),BQ43-N(BM43)-N(BN43)-N(BO43),"") -> -6.4 | BQ43: -14.9 | BR43: -16.8 | BS43: -3.5 | BT43: -3.4 | BU43: =IF(AND(ISNUMBER(BV43),COUNT(BR43,BS43,BT43)>0),BV43-N(BR43)-N(BS43)-N(BT43),"") -> 0.5 | BV43: -23.2 | BW43: 14 | BX43: 0.1 | CN43: COO_pct (cost of operations % of revenues, ex-D&A) | CO43: -0.0075 | CP43: Δ → | CQ43: 0.0075 | CR43: FY25 57.6%; 1H/26 57.6%. Bull = lower cost ratio (−Δ). Labor turnover / safety improvements and pricing > cost inflation drive ~20bp p.a. of margin expansion.
B44: Check: Σ components − Δ total revenues (unexplained / rounding; MD&A rounds to $0.1m) | C44: =IF(ISNUMBER(C35),ROUND(N(C36)+N(C37)+N(C38)+N(C39)+N(C40)+N(C41)+N(C42)+N(C43)-C35,1),"") -> 0 | D44: =IF(ISNUMBER(D35),ROUND(N(D36)+N(D37)+N(D38)+N(D39)+N(D40)+N(D41)+N(D42)+N(D43)-D35,1),"") -> 0 | E44: =IF(ISNUMBER(E35),ROUND(N(E36)+N(E37)+N(E38)+N(E39)+N(E40)+N(E41)+N(E42)+N(E43)-E35,1),"") -> -0.1 | F44: =IF(ISNUMBER(F35),ROUND(N(F36)+N(F37)+N(F38)+N(F39)+N(F40)+N(F41)+N(F42)+N(F43)-F35,1),"") -> 0 | G44: =IF(ISNUMBER(G35),ROUND(N(G36)+N(G37)+N(G38)+N(G39)+N(G40)+N(G41)+N(G42)+N(G43)-G35,1),"") -> 0 | H44: =IF(ISNUMBER(H35),ROUND(N(H36)+N(H37)+N(H38)+N(H39)+N(H40)+N(H41)+N(H42)+N(H43)-H35,1),"") -> 0 | I44: =IF(ISNUMBER(I35),ROUND(N(I36)+N(I37)+N(I38)+N(I39)+N(I40)+N(I41)+N(I42)+N(I43)-I35,1),"") -> 0 | J44: =IF(ISNUMBER(J35),ROUND(N(J36)+N(J37)+N(J38)+N(J39)+N(J40)+N(J41)+N(J42)+N(J43)-J35,1),"") -> 0 | ... BX44: =IF(ISNUMBER(BX35),ROUND(N(BX36)+N(BX37)+N(BX38)+N(BX39)+N(BX40)+N(BX41)+N(BX42)+N(BX43)-BX35,1),"") -> 0 | CF44: Q4 columns derived as FY − Q1 − Q2 − Q3 (WCN 10-Ks do not discuss Q4). 2006–08: price shown in total (incl. surcharges). | CN44: 2027E | CO44: =CP44+$CO$43 -> 0.5605 | CP44: 0.568 | CQ44: =CP44+$CQ$43 -> 0.5755
CN45: 2028E | CO45: =CP45+$CO$43 -> 0.5585 | CP45: 0.566 | CQ45: =CP45+$CQ$43 -> 0.5735
B46: E&P waste — treatment, recovery & disposal (oilfield waste; R360 from Oct-2012) | CF46: E&P WASTE — modelling logic | CN46: 2029E | CO46: =CP46+$CO$43 -> 0.5565 | CP46: 0.564 | CQ46: =CP46+$CQ$43 -> 0.5715
B47: E&P waste revenues (gross) | I47: 61.35 | J47: 59.931 | K47: 66.183 | L47: 68.605 | M47: 67.566 | N47: 262.286 | O47: 73.318 | P47: 82.646 | Q47: 86.085 | R47: 84.884 | S47: 326.934 | T47: 72.556 | U47: 55.851 | V47: 54.695 | W47: 45.427 | X47: 228.529 | Y47: 32.851 | Z47: 30.734 | AA47: 33.673 | AB47: 35.027 | AC47: 132.286 | AD47: 39.821 | AE47: 50.043 | AF47: 57.797 | AG47: 55.812 | AH47: 203.473 | AI47: 58.359 | AJ47: 62.663 | AK47: 68.049 | AL47: 67.192 | AM47: 256.262 | AN47: 66.831 | AO47: 68.039 | AP47: 70.874 | AQ47: 66.144 | AR47: 271.887 | AS47: 65.377 | AT47: 40.152 | AU47: 26.218 | AV47: 27.69 | AW47: 159.438 | AX47: 28.012 | AY47: 34.607 | AZ47: 38.519 | BA47: 37.57 | BB47: 138.707 | BC47: 43.555 | BD47: 54.155 | BE47: 56.995 | BF47: 55.857 | BG47: 210.562 | BH47: 51.759 | BI47: 58.607 | BJ47: 62.066 | BK47: 59.78 | BL47: 232.211 | BM47: 97.408 | BN47: 123.566 | BO47: 154.202 | BP47: 146.328 | BQ47: 521.504 | BR47: 150.899 | BS47: 178.117 | BT47: 188.679 | BU47: 171.066 | BV47: 688.761 | BW47: 187.572 | BX47: 211.153 | BY47: =BT47*(1+$BX$49+BY87) -> 221.28492 | BZ47: =BU47*(1+$BX$49+BZ87) -> 200.62819 | CA47: =SUM(BW47,BX47,BY47,BZ47) -> 820.6381 | CB47: =CA47*(1+CHOOSE(MATCH($CF$2,{"Bull","Base","Bear"},0),$CO$39,$CP$39,$CQ$39)) -> 869.87639 | CC47: =CB47*(1+CHOOSE(MATCH($CF$2,{"Bull","Base","Bear"},0),$CO$40,$CP$40,$CQ$40)) -> 913.37021 | CD47: =CC47*(1+CHOOSE(MATCH($CF$2,{"Bull","Base","Bear"},0),$CO$41,$CP$41,$CQ$41)) -> 949.90502 | CE47: =CD47*(1+CHOOSE(MATCH($CF$2,{"Bull","Base","Bear"},0),$CO$42,$CP$42,$CQ$42)) -> 987.90122 | CF47: Separate line from FY2012 (R360 acquisition; earlier E&P volumes sat in disposal & transfer). Q3/Q4-26E: prior-year quarter × (1 + Q2/26 y/y + calibration Δ). 2027E+: scenario lever EP_g. | CH47: =IFERROR((CE47/BV47)^(1/5)-1,"n/m") -> 0.074803308 | CI47: =IFERROR((BV47/AW47)^(1/5)-1,"n/m") -> 0.33997082 | CJ47: =IFERROR((BV47/X47)^(1/10)-1,"n/m") -> 0.11663882 | CK47: =IFERROR((BV47/C47)^(1/19)-1,"n/m") -> n/m | CN47: 2030E | CO47: =CP47+$CO$43 -> 0.5545 | CP47: 0.562 | CQ47: =CP47+$CQ$43 -> 0.5695
B48: E&P revenues y/y % | D48: =IF(AND(ISNUMBER(D47),ISNUMBER(C47)),IFERROR(D47/C47-1,""),"") | E48: =IF(AND(ISNUMBER(E47),ISNUMBER(D47)),IFERROR(E47/D47-1,""),"") | F48: =IF(AND(ISNUMBER(F47),ISNUMBER(E47)),IFERROR(F47/E47-1,""),"") | G48: =IF(AND(ISNUMBER(G47),ISNUMBER(F47)),IFERROR(G47/F47-1,""),"") | H48: =IF(AND(ISNUMBER(H47),ISNUMBER(G47)),IFERROR(H47/G47-1,""),"") | I48: =IF(AND(ISNUMBER(I47),ISNUMBER(H47)),IFERROR(I47/H47-1,""),"") | N48: =IF(AND(ISNUMBER(N47),ISNUMBER(I47)),IFERROR(N47/I47-1,""),"") -> 3.2752404 | O48: =IF(AND(ISNUMBER(O47),ISNUMBER(J47)),IFERROR(O47/J47-1,""),"") -> 0.22337355 | P48: =IF(AND(ISNUMBER(P47),ISNUMBER(K47)),IFERROR(P47/K47-1,""),"") -> 0.24874968 | Q48: =IF(AND(ISNUMBER(Q47),ISNUMBER(L47)),IFERROR(Q47/L47-1,""),"") -> 0.25479192 | R48: =IF(AND(ISNUMBER(R47),ISNUMBER(M47)),IFERROR(R47/M47-1,""),"") -> 0.25631235 | S48: =IF(AND(ISNUMBER(S47),ISNUMBER(N47)),IFERROR(S47/N47-1,""),"") -> 0.24647903 | T48: =IF(AND(ISNUMBER(T47),ISNUMBER(O47)),IFERROR(T47/O47-1,""),"") -> -0.010393082 | U48: =IF(AND(ISNUMBER(U47),ISNUMBER(P47)),IFERROR(U47/P47-1,""),"") -> -0.32421412 | ... BX48: =IF(AND(ISNUMBER(BX47),ISNUMBER(BS47)),IFERROR(BX47/BS47-1,""),"") -> 0.18547359 | BY48: =IFERROR(BY47/BT47-1,"") -> 0.17281158 | BZ48: =IFERROR(BZ47/BU47-1,"") -> 0.17281158 | CA48: =IFERROR(CA47/BV47-1,"") -> 0.19147005 | CB48: =IFERROR(CB47/CA47-1,"") -> 0.06 | CC48: =IFERROR(CC47/CB47-1,"") -> 0.05 | CD48: =IFERROR(CD47/CC47-1,"") -> 0.04 | CE48: =IFERROR(CE47/CD47-1,"") -> 0.04 | CH48: =IFERROR(AVERAGE(CA48,CB48,CC48,CD48,CE48),"n/m") -> 0.07629401 | CI48: =IFERROR(AVERAGE(BB48,BG48,BL48,BQ48,BV48),"n/m") -> 0.41147285 | CJ48: =IFERROR(AVERAGE(AC48,AH48,AM48,AR48,AW48,BB48,BG48,BL48,BQ48,BV48),"n/m") -> 0.20811778 | CK48: =IFERROR(AVERAGE(C48,D48,E48,F48,G48,H48,I48,N48,S48,X48,AC48,AH48,AM48,AR48,AW48,BB48,BG48,BL48,BQ48,BV48),"n/m") -> 0.40783875 | CN48: M&A_spend (acquisitions, net of cash acquired, $m) | CO48: 500 | CP48: Δ → | CQ48: -500 | CR48: 2018–25 average ~$1.1bn p.a. (range $0.4–2.2bn); 2025 $818m for ~$330m annualized revenue.
B49: Memo: Q2/26 y/y (trend input) | BX49: =IFERROR(BX47/BS47-1,"") -> 0.18547359 | CN49: 2027E | CO49: =CP49+$CO$48 -> 1500 | CP49: 1000 | CQ49: =CP49+$CQ$48 -> 500
CN50: 2028E | CO50: =CP50+$CO$48 -> 1500 | CP50: 1000 | CQ50: =CP50+$CQ$48 -> 500
B51: Intermodal & other (renewable fuels / landfill gas & RINs, intermodal rail, non-core) | CF51: INTERMODAL & OTHER — modelling logic | CN51: 2029E | CO51: =CP51+$CO$48 -> 1500 | CP51: 1000 | CQ51: =CP51+$CQ$48 -> 500
B52: Intermodal & other revenues (gross; "Other" from Q1/26) | I52: 50.321 | J52: 12.118 | K52: 11.255 | L52: 11.329 | M52: 11.336 | N52: 46.038 | O52: 10.872 | P52: 11.97 | Q52: 12.604 | R52: 10.845 | S52: 46.291 | T52: 14.504 | U52: 18.073 | V52: 17.344 | W52: 16.401 | X52: 66.321 | Y52: 14.889 | Z52: 22.358 | AA52: 34.155 | AB52: 34.962 | AC52: 106.363 | AD52: 33.765 | AE52: 35.432 | AF52: 38.221 | AG52: 39.331 | AH52: 146.749 | AI52: 34.004 | AJ52: 37.324 | AK52: 34.261 | AL52: 34.308 | AM52: 139.896 | AN52: 32.837 | AO52: 31.134 | AP52: 26.52 | AQ52: 30.646 | AR52: 121.137 | AS52: 30.018 | AT52: 27.811 | AU52: 27.141 | AV52: 33.427 | AW52: 118.396 | AX52: 35.634 | AY52: 38.59 | AZ52: 38.377 | BA52: 39.592 | BB52: 152.194 | BC52: 45.693 | BD52: 46.31 | BE52: 47.604 | BF52: 48.865 | BG52: 188.471 | BH52: 38.212 | BI52: 39.459 | BJ52: 44.984 | BK52: 49.066 | BL52: 171.721 | BM52: 49.541 | BN52: 49.096 | BO52: 47.341 | BP52: 45.908 | BQ52: 191.887 | BR52: 46.549 | BS52: 43.934 | BT52: 42.686 | BU52: 42.295 | BV52: 175.465 | BW52: 49.346 | BX52: 62.806 | BY52: =BT52*(1+$BX$54+BY87) -> 60.481427 | BZ52: =BU52*(1+$BX$54+BZ87) -> 59.927422 | CA52: =SUM(BW52,BX52,BY52,BZ52) -> 232.56085 | CB52: =CA52*(1+CB53) -> 239.53767 | CC52: =CB52*(1+CC53) -> 246.7238 | CD52: =CC52*(1+CD53) -> 254.12552 | CE52: =CD52*(1+CE53) -> 261.74928 | CF52: Q3/Q4-26E: prior-year quarter × (1 + Q2/26 y/y + calibration Δ). 2027E+: input growth (row below). | CH52: =IFERROR((CE52/BV52)^(1/5)-1,"n/m") -> 0.083275698 | CI52: =IFERROR((BV52/AW52)^(1/5)-1,"n/m") -> 0.081859079 | CJ52: =IFERROR((BV52/X52)^(1/10)-1,"n/m") -> 0.1021836 | CK52: =IFERROR((BV52/C52)^(1/19)-1,"n/m") -> n/m | CN52: 2030E | CO52: =CP52+$CO$48 -> 1500 | CP52: 1000 | CQ52: =CP52+$CQ$48 -> 500
B53: Intermodal & other y/y % | D53: =IF(AND(ISNUMBER(D52),ISNUMBER(C52)),IFERROR(D52/C52-1,""),"") | E53: =IF(AND(ISNUMBER(E52),ISNUMBER(D52)),IFERROR(E52/D52-1,""),"") | F53: =IF(AND(ISNUMBER(F52),ISNUMBER(E52)),IFERROR(F52/E52-1,""),"") | G53: =IF(AND(ISNUMBER(G52),ISNUMBER(F52)),IFERROR(G52/F52-1,""),"") | H53: =IF(AND(ISNUMBER(H52),ISNUMBER(G52)),IFERROR(H52/G52-1,""),"") | I53: =IF(AND(ISNUMBER(I52),ISNUMBER(H52)),IFERROR(I52/H52-1,""),"") | N53: =IF(AND(ISNUMBER(N52),ISNUMBER(I52)),IFERROR(N52/I52-1,""),"") -> -0.085113571 | O53: =IF(AND(ISNUMBER(O52),ISNUMBER(J52)),IFERROR(O52/J52-1,""),"") -> -0.10282225 | P53: =IF(AND(ISNUMBER(P52),ISNUMBER(K52)),IFERROR(P52/K52-1,""),"") -> 0.063527321 | Q53: =IF(AND(ISNUMBER(Q52),ISNUMBER(L52)),IFERROR(Q52/L52-1,""),"") -> 0.11254303 | R53: =IF(AND(ISNUMBER(R52),ISNUMBER(M52)),IFERROR(R52/M52-1,""),"") -> -0.043313338 | S53: =IF(AND(ISNUMBER(S52),ISNUMBER(N52)),IFERROR(S52/N52-1,""),"") -> 0.0054954603 | T53: =IF(AND(ISNUMBER(T52),ISNUMBER(O52)),IFERROR(T52/O52-1,""),"") -> 0.33406917 | U53: =IF(AND(ISNUMBER(U52),ISNUMBER(P52)),IFERROR(U52/P52-1,""),"") -> 0.50985798 | ... BX53: =IF(AND(ISNUMBER(BX52),ISNUMBER(BS52)),IFERROR(BX52/BS52-1,""),"") -> 0.42955342 | BY53: =IFERROR(BY52/BT52-1,"") -> 0.41689141 | BZ53: =IFERROR(BZ52/BU52-1,"") -> 0.41689141 | CA53: =IFERROR(CA52/BV52-1,"") -> 0.32539737 | CB53: 0.03 | CC53: 0.03 | CD53: 0.03 | CE53: 0.03 | CF53: 2027E+: 3% input (landfill-gas / RNG volumes partly offset by lower RIN pricing). | CH53: =IFERROR(AVERAGE(CA53,CB53,CC53,CD53,CE53),"n/m") -> 0.089079473 | CI53: =IFERROR(AVERAGE(BB53,BG53,BL53,BQ53,BV53),"n/m") -> 0.093361189 | CJ53: =IFERROR(AVERAGE(AC53,AH53,AM53,AR53,AW53,BB53,BG53,BL53,BQ53,BV53),"n/m") -> 0.12468476 | CK53: =IFERROR(AVERAGE(C53,D53,E53,F53,G53,H53,I53,N53,S53,X53,AC53,AH53,AM53,AR53,AW53,BB53,BG53,BL53,BQ53,BV53),"n/m") -> 0.12307131
B54: Memo: Q2/26 y/y (trend input) | BX54: =IFERROR(BX52/BS52-1,"") -> 0.42955342
B55: Memo: recycling, intermodal & other (reported combined, 2006–11) | C55: 77.202 | D55: 95.212 | E55: 89.594 | F55: 68.845 | G55: 103.974 | H55: 144.583 | CF55: Company reported recycling and intermodal/other as one line until FY2011 (included in the Group total).
B57: Intercompany eliminations
B58: Less: intercompany eliminations | C58: -114.8 | D58: -129.3 | E58: -136.515 | F58: -171.717 | G58: -193.785 | H58: -218.612 | I58: -232.759 | J58: -56.867 | K58: -66.739 | L58: -65.704 | M58: -60.519 | N58: -249.83 | O58: -58.95 | P58: -66.435 | Q58: -68.157 | R58: -65.81 | S58: -259.352 | T58: -61.464 | U58: -69.459 | V58: -71.246 | W58: -71.735 | X58: -273.903 | Y58: -70.36 | Z58: -103.367 | AA58: -153.323 | AB58: -143.415 | AC58: -470.465 | AD58: -151.58 | AE58: -166.906 | AF58: -165.512 | AG58: -156.888 | AH58: -640.886 | AI58: -156.292 | AJ58: -177.978 | AK58: -190.176 | AL58: -185.442 | AM58: -709.888 | AN58: -171.979 | AO58: -205.789 | AP58: -210.1 | AQ58: -200.125 | AR58: -787.994 | AS58: -197.091 | AT58: -200.174 | AU58: -210.386 | AV58: -206.746 | AW58: -814.397 | AX58: -197.883 | AY58: -223.381 | AZ58: -226.68 | BA58: -230.71 | BB58: -878.654 | BC58: -223.261 | BD58: -250.13 | BE58: -258.368 | BF58: -266.309 | BG58: -998.069 | BH58: -272.37 | BI58: -289.96 | BJ58: -294.698 | BK58: -288.753 | BL58: -1145.781 | BM58: -293.741 | BN58: -327.031 | BO58: -332.039 | BP58: -322.587 | BQ58: -1275.398 | BR58: -309.713 | BS58: -358.959 | BT58: -366.119 | BU58: -354.213 | BV58: -1389.004 | BW58: -344.188 | BX58: -395.069 | BY58: =-(N(BY11)+N(BY15)+N(BY18)+N(BY47)+N(BY52))*BY59 -> -386.72939 | BZ58: =-(N(BZ11)+N(BZ15)+N(BZ18)+N(BZ47)+N(BZ52))*BZ59 -> -374.01615 | CA58: =SUM(BW58,BX58,BY58,BZ58) -> -1500.0025 | CB58: =-(N(CB11)+N(CB15)+N(CB18)+N(CB47)+N(CB52))*CB59 -> -1565.2421 | CC58: =-(N(CC11)+N(CC15)+N(CC18)+N(CC47)+N(CC52))*CC59 -> -1635.7764 | CD58: =-(N(CD11)+N(CD15)+N(CD18)+N(CD47)+N(CD52))*CD59 -> -1712.0235 | CE58: =-(N(CE11)+N(CE15)+N(CE18)+N(CE47)+N(CE52))*CE59 -> -1787.9512 | CF58: Revenue on internalized volumes (WCN collection trucks tipping at WCN landfills / transfer stations). | CH58: =IFERROR((CE58/BV58)^(1/5)-1,"n/m") -> 0.051793383 | CI58: =IFERROR((BV58/AW58)^(1/5)-1,"n/m") -> 0.11268816 | CJ58: =IFERROR((BV58/X58)^(1/10)-1,"n/m") -> 0.17627989 | CK58: =IFERROR((BV58/C58)^(1/19)-1,"n/m") -> 0.14021685
B59: Intercompany eliminations % of gross revenues | C59: =IFERROR(-C58/(N(C11)+N(C15)+N(C18)+N(C55)+N(C47)+N(C52)),"") -> 0.12223767 | D59: =IFERROR(-D58/(N(D11)+N(D15)+N(D18)+N(D55)+N(D47)+N(D52)),"") -> 0.11885928 | E59: =IFERROR(-E58/(N(E11)+N(E15)+N(E18)+N(E55)+N(E47)+N(E52)),"") -> 0.11509395 | F59: =IFERROR(-F58/(N(F11)+N(F15)+N(F18)+N(F55)+N(F47)+N(F52)),"") -> 0.12597443 | G59: =IFERROR(-G58/(N(G11)+N(G15)+N(G18)+N(G55)+N(G47)+N(G52)),"") -> 0.12803411 | H59: =IFERROR(-H58/(N(H11)+N(H15)+N(H18)+N(H55)+N(H47)+N(H52)),"") -> 0.12680672 | I59: =IFERROR(-I58/(N(I11)+N(I15)+N(I18)+N(I55)+N(I47)+N(I52)),"") -> 0.12286836 | J59: =IFERROR(-J58/(N(J11)+N(J15)+N(J18)+N(J55)+N(J47)+N(J52)),"") -> 0.11221705 | ... BX59: =IFERROR(-BX58/(N(BX11)+N(BX15)+N(BX18)+N(BX55)+N(BX47)+N(BX52)),"") -> 0.13361931 | BY59: =BT59 -> 0.12962273 | BZ59: =BU59 -> 0.12986637 | CA59: =IFERROR(-CA58/(CA11+CA15+CA18+CA47+CA52),"") -> 0.1300392 | CB59: =CA59 -> 0.1300392 | CC59: =CB59 -> 0.1300392 | CD59: =CC59 -> 0.1300392 | CE59: =CD59 -> 0.1300392 | CF59: Forecast: prior-year (quarter) ratio. | CH59: =IFERROR(AVERAGE(CA59,CB59,CC59,CD59,CE59),"n/m") -> 0.1300392 | CI59: =IFERROR(AVERAGE(BB59,BG59,BL59,BQ59,BV59),"n/m") -> 0.12491677 | CJ59: =IFERROR(AVERAGE(AC59,AH59,AM59,AR59,AW59,BB59,BG59,BL59,BQ59,BV59),"n/m") -> 0.12521678 | CK59: =IFERROR(AVERAGE(C59,D59,E59,F59,G59,H59,I59,N59,S59,X59,AC59,AH59,AM59,AR59,AW59,BB59,BG59,BL59,BQ59,BV59),"n/m") -> 0.12260834
B61: Future acquisitions (M&A lever — tuck-in solid waste / E&P deals closed from 2027E; unallocated) | CF61: FUTURE ACQUISITIONS — modelling logic (spend ÷ EV/sales → annualized revenue; half-year convention in the year of purchase)
B62: Acquisition spend (USDm, scenario) | CB62: =MAX(0,CHOOSE(MATCH($CF$2,{"Bull","Base","Bear"},0),$CO$49,$CP$49,$CQ$49)) -> 1000 | CC62: =MAX(0,CHOOSE(MATCH($CF$2,{"Bull","Base","Bear"},0),$CO$50,$CP$50,$CQ$50)) -> 1000 | CD62: =MAX(0,CHOOSE(MATCH($CF$2,{"Bull","Base","Bear"},0),$CO$51,$CP$51,$CQ$51)) -> 1000 | CE62: =MAX(0,CHOOSE(MATCH($CF$2,{"Bull","Base","Bear"},0),$CO$52,$CP$52,$CQ$52)) -> 1000 | CF62: Scenario lever M&A_spend (cash consideration net of cash acquired).
B63: Purchase multiple — EV / annualized revenue (x) | CB63: 2.75 | CC63: 2.75 | CD63: 2.75 | CE63: 2.75 | CF63: WCN 2018–25: cash paid ÷ annualized revenue acquired ≈ 2.3–3.4x (2025: $818m / ~$330m = 2.5x; 2024: 2.8x). Input 2.75x.
B64: Annualized revenue acquired in the year | CB64: =IFERROR(CB62/CB63,0) -> 363.63636 | CC64: =IFERROR(CC62/CC63,0) -> 363.63636 | CD64: =IFERROR(CD62/CD63,0) -> 363.63636 | CE64: =IFERROR(CE62/CE63,0) -> 363.63636
B65: Growth of acquired businesses after acquisition % | CB65: 0.05 | CC65: 0.05 | CD65: 0.05 | CE65: 0.05 | CF65: Input: in line with solid waste price-led organic growth.
B66: Run-rate revenue of businesses acquired (year end) | CB66: =N(CA66)*(1+CB65)+CB64 -> 363.63636 | CC66: =N(CB66)*(1+CC65)+CC64 -> 745.45455 | CD66: =N(CC66)*(1+CD65)+CD64 -> 1146.3636 | CE66: =N(CD66)*(1+CE65)+CE64 -> 1567.3182
B67: Revenues from future acquisitions | CB67: =N(CA66)*(1+CB65)+0.5*CB64 -> 181.81818 | CC67: =N(CB66)*(1+CC65)+0.5*CC64 -> 563.63636 | CD67: =N(CC66)*(1+CD65)+0.5*CD64 -> 964.54545 | CE67: =N(CD66)*(1+CE65)+0.5*CE64 -> 1385.5
B68: Adjusted EBITDA margin of acquired businesses % | CB68: 0.3 | CC68: 0.3 | CD68: 0.3 | CE68: 0.3 | CF68: Input: acquired tuck-ins typically below WCN average at purchase, rising with route density / internalization.
B69: Adjusted EBITDA from future acquisitions | CB69: =CB67*CB68 -> 54.545455 | CC69: =CC67*CC68 -> 169.09091 | CD69: =CD67*CD68 -> 289.36364 | CE69: =CE67*CE68 -> 415.65
B70: Cost of operations & SG&A of acquired businesses | CB70: =CB67-CB69 -> 127.27273 | CC70: =CC67-CC69 -> 394.54545 | CD70: =CD67-CD69 -> 675.18182 | CE70: =CE67-CE69 -> 969.85
B71: Depreciation of acquired businesses % of revenues | CB71: 0.09 | CC71: 0.09 | CD71: 0.09 | CE71: 0.09
B72: Depreciation from future acquisitions | CB72: =CB67*CB71 -> 16.363636 | CC72: =CC67*CC71 -> 50.727273 | CD72: =CD67*CD71 -> 86.809091 | CE72: =CE67*CE71 -> 124.695
B73: PP&E (incl. landfill airspace) % of spend | CB73: 0.35 | CC73: 0.35 | CD73: 0.35 | CE73: 0.35 | CF73: 2021–25 purchase-price allocations: PP&E ~35–45%, intangibles ~15–30%, goodwill ~35–45% of consideration.
B74: Acquired intangibles % of spend (customer lists, franchise agreements, permits) | CB74: 0.25 | CC74: 0.25 | CD74: 0.25 | CE74: 0.25
B75: Intangible amortization life (years) | CB75: 10 | CC75: 10 | CD75: 10 | CE75: 10
B76: Cumulative acquired intangibles (gross) | CB76: =N(CA76)+CB62*CB74 -> 250 | CC76: =N(CB76)+CC62*CC74 -> 500 | CD76: =N(CC76)+CD62*CD74 -> 750 | CE76: =N(CD76)+CE62*CE74 -> 1000
B77: Amortization of future-acquisition intangibles | CB77: =(N(CA76)+0.5*CB62*CB74)/CB75 -> 12.5 | CC77: =(N(CB76)+0.5*CC62*CC74)/CC75 -> 37.5 | CD77: =(N(CC76)+0.5*CD62*CD74)/CD75 -> 62.5 | CE77: =(N(CD76)+0.5*CE62*CE74)/CE75 -> 87.5
B79: Group total — service-line build → consolidated revenues; FY26 outlook calibration (WCN's primary metrics: revenue, Adjusted EBITDA, adjusted FCF) | CF79: GROUP TOTAL & FY26 OUTLOOK CALIBRATION — modelling logic
B80: Revenues (service-line build) | C80: =N(C11)+N(C15)+N(C18)+N(C55)+N(C47)+N(C52)+N(C58)+N(C67) -> 824.354 | D80: =N(D11)+N(D15)+N(D18)+N(D55)+N(D47)+N(D52)+N(D58)+N(D67) -> 958.541 | E80: =N(E11)+N(E15)+N(E18)+N(E55)+N(E47)+N(E52)+N(E58)+N(E67) -> 1049.603 | F80: =N(F11)+N(F15)+N(F18)+N(F55)+N(F47)+N(F52)+N(F58)+N(F67) -> 1191.393 | G80: =N(G11)+N(G15)+N(G18)+N(G55)+N(G47)+N(G52)+N(G58)+N(G67) -> 1319.757 | H80: =N(H11)+N(H15)+N(H18)+N(H55)+N(H47)+N(H52)+N(H58)+N(H67) -> 1505.366 | I80: =N(I11)+N(I15)+N(I18)+N(I55)+N(I47)+N(I52)+N(I58)+N(I67) -> 1661.618 | J80: =N(J11)+N(J15)+N(J18)+N(J55)+N(J47)+N(J52)+N(J58)+N(J67) -> 449.892 | ... CE80: =N(CE11)+N(CE15)+N(CE18)+N(CE55)+N(CE47)+N(CE52)+N(CE58)+N(CE67) -> 13346.873 | CF80: Σ collection + disposal & transfer + recycling (+ combined line to 2011) + E&P + intermodal & other − intercompany eliminations + future M&A. | CH80: =IFERROR((CE80/BV80)^(1/5)-1,"n/m") -> 0.071110343 | CI80: =IFERROR((BV80/AW80)^(1/5)-1,"n/m") -> 0.11693096 | CJ80: =IFERROR((BV80/X80)^(1/10)-1,"n/m") -> 0.16156328 | CK80: =IFERROR((BV80/C80)^(1/19)-1,"n/m") -> 0.137089
B81: Revenues y/y % | D81: =IF(AND(ISNUMBER(D80),ISNUMBER(C80)),IFERROR(D80/C80-1,""),"") -> 0.16277837 | E81: =IF(AND(ISNUMBER(E80),ISNUMBER(D80)),IFERROR(E80/D80-1,""),"") -> 0.095000631 | F81: =IF(AND(ISNUMBER(F80),ISNUMBER(E80)),IFERROR(F80/E80-1,""),"") -> 0.13508917 | G81: =IF(AND(ISNUMBER(G80),ISNUMBER(F80)),IFERROR(G80/F80-1,""),"") -> 0.10774279 | H81: =IF(AND(ISNUMBER(H80),ISNUMBER(G80)),IFERROR(H80/G80-1,""),"") -> 0.14063877 | I81: =IF(AND(ISNUMBER(I80),ISNUMBER(H80)),IFERROR(I80/H80-1,""),"") -> 0.10379668 | N81: =IF(AND(ISNUMBER(N80),ISNUMBER(I80)),IFERROR(N80/I80-1,""),"") -> 0.16079327 | O81: =IF(AND(ISNUMBER(O80),ISNUMBER(J80)),IFERROR(O80/J80-1,""),"") -> 0.07072364 | P81: =IF(AND(ISNUMBER(P80),ISNUMBER(K80)),IFERROR(P80/K80-1,""),"") -> 0.072156459 | Q81: =IF(AND(ISNUMBER(Q80),ISNUMBER(L80)),IFERROR(Q80/L80-1,""),"") -> 0.085188803 | R81: =IF(AND(ISNUMBER(R80),ISNUMBER(M80)),IFERROR(R80/M80-1,""),"") -> 0.083016895 | S81: =IF(AND(ISNUMBER(S80),ISNUMBER(N80)),IFERROR(S80/N80-1,""),"") -> 0.07796111 | T81: =IF(AND(ISNUMBER(T80),ISNUMBER(O80)),IFERROR(T80/O80-1,""),"") -> 0.050632123 | U81: =IF(AND(ISNUMBER(U80),ISNUMBER(P80)),IFERROR(U80/P80-1,""),"") -> 0.012614996 | ... BX81: =IF(AND(ISNUMBER(BX80),ISNUMBER(BS80)),IFERROR(BX80/BS80-1,""),"") -> 0.064207922 | BY81: =IFERROR(BY80/BT80-1,"") -> 0.056294225 | BZ81: =IFERROR(BZ80/BU80-1,"") -> 0.055907463 | CA81: =IFERROR(CA80/BV80-1,"") -> 0.060007405 | CB81: =IFERROR(CB80/CA80-1,"") -> 0.061611395 | CC81: =IFERROR(CC80/CB80-1,"") -> 0.080134219 | CD81: =IFERROR(CD80/CC80-1,"") -> 0.079169584 | CE81: =IFERROR(CE80/CD80-1,"") -> 0.074803753
B82: Check: service-line build vs consolidated revenues (should be 0) | C82: =ROUND(C80-C128,1) -> 0 | D82: =ROUND(D80-D128,1) -> 0 | E82: =ROUND(E80-E128,1) -> 0 | F82: =ROUND(F80-F128,1) -> 0 | G82: =ROUND(G80-G128,1) -> 0 | H82: =ROUND(H80-H128,1) -> 0 | I82: =ROUND(I80-I128,1) -> 0 | J82: =ROUND(J80-J128,1) -> 0 | ... CE82: =ROUND(CE80-CE128,1) -> 0
B83: Memo: revenues — WCN ex future M&A | C83: =C80-N(C67) -> 824.354 | D83: =D80-N(D67) -> 958.541 | E83: =E80-N(E67) -> 1049.603 | F83: =F80-N(F67) -> 1191.393 | G83: =G80-N(G67) -> 1319.757 | H83: =H80-N(H67) -> 1505.366 | I83: =I80-N(I67) -> 1661.618 | J83: =J80-N(J67) -> 449.892 | ... CE83: =CE80-N(CE67) -> 11961.373
B84: Memo: FY26 revenue outlook (scenario end-point) | CA84: =CHOOSE(MATCH($CF$2,{"Bull","Base","Bear"},0),$CO$12,$CP$12,$CQ$12) -> 10035 | CF84: Q2-26 release (22-Jul-2026): revenue $10.02–10.05bn (Bull = high, Base = mid, Bear = low).
B85: Revenues before outlook calibration (Q3/Q4-26E helper) | BY85: =(1-BY59)*(BT11*(1+$BX$21)+BT15*(1+$BX$21)+BT18*(1+$BX$21)+BT47*(1+$BX$49)+BT52*(1+$BX$54)) -> 2627.8985 | BZ85: =(1-BZ59)*(BU11*(1+$BX$21)+BU15*(1+$BX$21)+BU18*(1+$BX$21)+BU47*(1+$BX$49)+BU52*(1+$BX$54)) -> 2536.0423 | CF85: Each service line: prior-year quarter × (1 + Q2/26 y/y trend), net of intercompany eliminations at the prior-year ratio.
B86: Revenue sensitivity to +1.00 of growth (Q3/Q4-26E helper) | BY86: =(1-BY59)*(BT11+BT15+BT18+BT47+BT52) -> 2458.378 | BZ86: =(1-BZ59)*(BU11+BU15+BU18+BU47+BU52) -> 2373.306
B87: Outlook calibration: Δ y/y growth applied to all service lines (Q3/Q4-26E) | BY87: =(CA84-BW128-BX128-BY85-BZ85)/(BY86+BZ86) -> -0.012662014 | BZ87: =BY87 -> -0.012662014 | CF87: Solves the uniform growth shift vs the Q2/26 y/y trend so that FY26 revenues = the outlook end-point for the active scenario.
B88: Check: FY26 revenues vs outlook end-point (should be 0) | CA88: =ROUND(CA128-CA84,1) -> 0
B89: Adjusted EBITDA before margin calibration (Q3/Q4-26E helper) | BY89: =BY128*(1-BY120)-BY130+BY171+N(BY174)+N(BY175) -> 883.7744 | BZ89: =BZ128*(1-BZ120)-BZ130+BZ171+N(BZ174)+N(BZ175) -> 845.00575 | CF89: Revenues × (1 − pre-calibration cost-of-operations ratio) − SG&A + closure accretion + transaction / equity-award add-backs (0 in the forecast).
B90: Outlook calibration: Δ cost-of-operations ratio applied (Q3/Q4-26E) | BY90: =(BY89+BZ89-(CA91-BW180-BX180))/(BY128+BZ128) -> 0.00066398308 | BZ90: =BY90 -> 0.00066398308 | CF90: Solves the uniform cost-ratio shift (vs prior-year quarter + 1H drift) so that FY26 Adjusted EBITDA = outlook end-point for the active scenario.
B91: Memo: FY26 Adjusted EBITDA outlook (scenario end-point) | CA91: =CHOOSE(MATCH($CF$2,{"Bull","Base","Bear"},0),$CO$13,$CP$13,$CQ$13) -> 3335 | CF91: Q2-26 release: $3,330–3,340m (raised from $3,300–3,325m).
B92: Check: FY26 Adjusted EBITDA vs outlook end-point (should be 0) | CA92: =ROUND(CA180-CA91,1) -> 0
B93: Memo: FY26 adjusted free cash flow outlook (scenario end-point) | CA93: =CHOOSE(MATCH($CF$2,{"Bull","Base","Bear"},0),$CO$15,$CP$15,$CQ$15) -> 1425 | CF93: $1.40–1.45bn; compare with model Adjusted FCF (row in the adjusted FCF bridge).
B94: Memo: FY26 net income outlook (scenario end-point) | CA94: =CHOOSE(MATCH($CF$2,{"Bull","Base","Bear"},0),$CO$14,$CP$14,$CQ$14) -> 1171
B95: Memo: FY26 net cash from operating activities outlook (scenario end-point) | CA95: =CHOOSE(MATCH($CF$2,{"Bull","Base","Bear"},0),$CO$16,$CP$16,$CQ$16) -> 2655 | CF95: $2.63–2.68bn (Q2-26 release). 2026E working-capital change is calibrated so that model CFO = this end-point (2H working capital absorbs the gap; receivables balance is the plug).
B96: Check: FY26 CFO vs outlook end-point (should be 0) | CA96: =ROUND(CA241-CA95,1) -> 0
B98: Reportable segments (memo; Segment EBITDA as reported — segments re-cut Q1/10, Q2/16 (Canada), Q3/20 (E&P into Southern), Q2/23 (MidSouth)) | CF98: Segment data as originally reported in each 10-Q / 10-K (Q4 = FY − Q1 − Q2 − Q3; not derived in re-cut years 2016, 2020, 2023 where the FY is on the new segment basis).
B99: Southern — revenues (reported, after intercompany) | D99: 224.043 | E99: 238.571 | F99: 282.263 | G99: 318.616 | M99: =IF(AND(ISNUMBER(N99),ISNUMBER(J99),ISNUMBER(K99),ISNUMBER(L99)),N99-J99-K99-L99,"") | R99: =IF(AND(ISNUMBER(S99),ISNUMBER(O99),ISNUMBER(P99),ISNUMBER(Q99)),S99-O99-P99-Q99,"") | W99: =IF(AND(ISNUMBER(X99),ISNUMBER(T99),ISNUMBER(U99),ISNUMBER(V99)),X99-T99-U99-V99,"") | Z99: 120.551 | AA99: 279.909 | AC99: 713.381 | AD99: 280.123 | AE99: 285.383 | AF99: 280.528 | AG99: =IF(AND(ISNUMBER(AH99),ISNUMBER(AD99),ISNUMBER(AE99),ISNUMBER(AF99)),AH99-AD99-AE99-AF99,"") -> 269.83 | AH99: 1115.864 | AI99: 273.339 | AJ99: 283.11 | AK99: 283.04 | AL99: =IF(AND(ISNUMBER(AM99),ISNUMBER(AI99),ISNUMBER(AJ99),ISNUMBER(AK99)),AM99-AI99-AJ99-AK99,"") -> 283.059 | AM99: 1122.548 | AN99: 287.329 | AO99: 298.015 | AP99: 305.188 | AQ99: =IF(AND(ISNUMBER(AR99),ISNUMBER(AN99),ISNUMBER(AO99),ISNUMBER(AP99)),AR99-AN99-AO99-AP99,"") -> 302.39 | AR99: 1192.922 | AS99: 309.387 | AT99: 297.099 | AU99: 330.575 | AW99: 1369.58 | AX99: 338.161 | AY99: 363.336 | AZ99: 370.958 | BA99: =IF(AND(ISNUMBER(BB99),ISNUMBER(AX99),ISNUMBER(AY99),ISNUMBER(AZ99)),BB99-AX99-AY99-AZ99,"") -> 374.291 | BB99: 1446.746 | BC99: 387.064 | BD99: 416.464 | BE99: 428.366 | BF99: =IF(AND(ISNUMBER(BG99),ISNUMBER(BC99),ISNUMBER(BD99),ISNUMBER(BE99)),BG99-BC99-BD99-BE99,"") -> 435.884 | BG99: 1667.778 | BH99: 447.04 | BI99: 414.061 | BJ99: 413.578 | BL99: 1642.274 | BM99: 418.946 | BN99: 439.275 | BO99: 453.215 | BP99: =IF(AND(ISNUMBER(BQ99),ISNUMBER(BM99),ISNUMBER(BN99),ISNUMBER(BO99)),BQ99-BM99-BN99-BO99,"") -> 445.757 | BQ99: 1757.193 | BR99: 453.403 | BS99: 476.945 | BT99: 485.394 | BU99: =IF(AND(ISNUMBER(BV99),ISNUMBER(BR99),ISNUMBER(BS99),ISNUMBER(BT99)),BV99-BR99-BS99-BT99,"") -> 492.067 | BV99: 1907.809 | BW99: 493.039 | BX99: 518.65
B100: Eastern — revenues (reported, after intercompany) | H100: 332.601 | I100: 366.825 | J100: 87.77 | K100: 95.725 | L100: 96.06 | M100: =IF(AND(ISNUMBER(N100),ISNUMBER(J100),ISNUMBER(K100),ISNUMBER(L100)),N100-J100-K100-L100,"") -> 92.217 | N100: 371.772 | O100: 91.326 | P100: 100.058 | Q100: 102.624 | R100: =IF(AND(ISNUMBER(S100),ISNUMBER(O100),ISNUMBER(P100),ISNUMBER(Q100)),S100-O100-P100-Q100,"") -> 99.813 | S100: 393.821 | T100: 98.024 | U100: 107.215 | V100: 109.03 | W100: =IF(AND(ISNUMBER(X100),ISNUMBER(T100),ISNUMBER(U100),ISNUMBER(V100)),X100-T100-U100-V100,"") -> 119.188 | X100: 433.457 | Y100: 122.502 | Z100: 142.584 | AA100: 194.806 | AC100: 636.652 | AD100: 231.487 | AE100: 246.31 | AF100: 246.267 | AG100: =IF(AND(ISNUMBER(AH100),ISNUMBER(AD100),ISNUMBER(AE100),ISNUMBER(AF100)),AH100-AD100-AE100-AF100,"") -> 235.15 | AH100: 959.214 | AI100: 241.879 | AJ100: 270.943 | AK100: 289.497 | AL100: =IF(AND(ISNUMBER(AM100),ISNUMBER(AI100),ISNUMBER(AJ100),ISNUMBER(AK100)),AM100-AI100-AJ100-AK100,"") -> 287.7 | AM100: 1090.019 | AN100: 292.827 | AO100: 323.621 | AP100: 330.887 | AQ100: =IF(AND(ISNUMBER(AR100),ISNUMBER(AN100),ISNUMBER(AO100),ISNUMBER(AP100)),AR100-AN100-AO100-AP100,"") -> 321.629 | AR100: 1268.964 | AS100: 332.202 | AT100: 318.891 | AU100: 344.353 | AW100: 1335.865 | AX100: 336.461 | AY100: 369.617 | AZ100: 396.229 | BA100: =IF(AND(ISNUMBER(BB100),ISNUMBER(AX100),ISNUMBER(AY100),ISNUMBER(AZ100)),BB100-AX100-AY100-AZ100,"") -> 418.981 | BB100: 1521.288 | BC100: 421.597 | BD100: 478.739 | BE100: 501.052 | BF100: =IF(AND(ISNUMBER(BG100),ISNUMBER(BC100),ISNUMBER(BD100),ISNUMBER(BE100)),BG100-BC100-BD100-BE100,"") -> 489.317 | BG100: 1890.705 | BH100: 491.418 | BI100: 343.424 | BJ100: 353.109 | BL100: 1380.233 | BM100: 360.063 | BN100: 386.103 | BO100: 407.668 | BP100: =IF(AND(ISNUMBER(BQ100),ISNUMBER(BM100),ISNUMBER(BN100),ISNUMBER(BO100)),BQ100-BM100-BN100-BO100,"") -> 410.377 | BQ100: 1564.211 | BR100: 403.27 | BS100: 442.213 | BT100: 440.77 | BU100: =IF(AND(ISNUMBER(BV100),ISNUMBER(BR100),ISNUMBER(BS100),ISNUMBER(BT100)),BV100-BR100-BS100-BT100,"") -> 415.994 | BV100: 1702.247 | BW100: 405.722 | BX100: 443.954
B101: Western — revenues (reported, after intercompany) | D101: 477.31 | E101: 511.979 | F101: 617.247 | G101: 709.821 | H101: 742.588 | I101: 782.134 | J101: 193.151 | K101: 202.833 | L101: 210.211 | M101: =IF(AND(ISNUMBER(N101),ISNUMBER(J101),ISNUMBER(K101),ISNUMBER(L101)),N101-J101-K101-L101,"") -> 199.595 | N101: 805.79 | O101: 195.355 | P101: 206.269 | Q101: 215.849 | R101: =IF(AND(ISNUMBER(S101),ISNUMBER(O101),ISNUMBER(P101),ISNUMBER(Q101)),S101-O101-P101-Q101,"") -> 206.449 | S101: 823.922 | T101: 205.626 | U101: 222.388 | V101: 230.454 | W101: =IF(AND(ISNUMBER(X101),ISNUMBER(T101),ISNUMBER(U101),ISNUMBER(V101)),X101-T101-U101-V101,"") -> 221.925 | X101: 880.393 | Y101: 219.234 | Z101: 236.431 | AA101: 246.891 | AC101: 935.319 | AD101: 235.59 | AE101: 257.492 | AF101: 261.877 | AG101: =IF(AND(ISNUMBER(AH101),ISNUMBER(AD101),ISNUMBER(AE101),ISNUMBER(AF101)),AH101-AD101-AE101-AF101,"") -> 252.271 | AH101: 1007.23 | AI101: 245.163 | AJ101: 263.699 | AK101: 271.018 | AL101: =IF(AND(ISNUMBER(AM101),ISNUMBER(AI101),ISNUMBER(AJ101),ISNUMBER(AK101)),AM101-AI101-AJ101-AK101,"") -> 264.048 | AM101: 1043.928 | AN101: 254.979 | AO101: 276.998 | AP101: 289.208 | AQ101: =IF(AND(ISNUMBER(AR101),ISNUMBER(AN101),ISNUMBER(AO101),ISNUMBER(AP101)),AR101-AN101-AO101-AP101,"") -> 277.664 | AR101: 1098.849 | AS101: 271.981 | AT101: 275.536 | AU101: 301.221 | AW101: 1149.762 | AX101: 297.004 | AY101: 313.789 | AZ101: 332.02 | BA101: =IF(AND(ISNUMBER(BB101),ISNUMBER(AX101),ISNUMBER(AY101),ISNUMBER(AZ101)),BB101-AX101-AY101-AZ101,"") -> 337.375 | BB101: 1280.188 | BC101: 346.71 | BD101: 360.923 | BE101: 385.479 | BF101: =IF(AND(ISNUMBER(BG101),ISNUMBER(BC101),ISNUMBER(BD101),ISNUMBER(BE101)),BG101-BC101-BD101-BE101,"") -> 391.52 | BG101: 1484.632 | BH101: 410.003 | BI101: 418.972 | BJ101: 432.462 | BL101: 1669.289 | BM101: 422.249 | BN101: 453.964 | BO101: 476.237 | BP101: =IF(AND(ISNUMBER(BQ101),ISNUMBER(BM101),ISNUMBER(BN101),ISNUMBER(BO101)),BQ101-BM101-BN101-BO101,"") -> 446.219 | BQ101: 1798.669 | BR101: 438.401 | BS101: 461.665 | BT101: 486.255 | BU101: =IF(AND(ISNUMBER(BV101),ISNUMBER(BR101),ISNUMBER(BS101),ISNUMBER(BT101)),BV101-BR101-BS101-BT101,"") -> 463.098 | BV101: 1849.419 | BW101: 462.448 | BX101: 492.725
B102: Central — revenues (reported, after intercompany) | D102: 257.188 | E102: 299.053 | F102: 291.883 | G102: 291.32 | H102: 430.177 | I102: 472.469 | J102: 114.593 | K102: 130.434 | L102: 134.333 | M102: =IF(AND(ISNUMBER(N102),ISNUMBER(J102),ISNUMBER(K102),ISNUMBER(L102)),N102-J102-K102-L102,"") -> 131.568 | N102: 510.928 | O102: 129.067 | P102: 141.916 | Q102: 149.213 | R102: =IF(AND(ISNUMBER(S102),ISNUMBER(O102),ISNUMBER(P102),ISNUMBER(Q102)),S102-O102-P102-Q102,"") -> 141.284 | S102: 561.48 | T102: 134.935 | U102: 149.812 | V102: 156.939 | W102: =IF(AND(ISNUMBER(X102),ISNUMBER(T102),ISNUMBER(U102),ISNUMBER(V102)),X102-T102-U102-V102,"") -> 147.981 | X102: 589.667 | Y102: 142.476 | Z102: 139.67 | AA102: 155.267 | AC102: 561.541 | AD102: 144.309 | AE102: 159.418 | AF102: 166.36 | AG102: =IF(AND(ISNUMBER(AH102),ISNUMBER(AD102),ISNUMBER(AE102),ISNUMBER(AF102)),AH102-AD102-AE102-AF102,"") -> 158.08 | AH102: 628.167 | AI102: 153.79 | AJ102: 175.02 | AK102: 185.271 | AL102: =IF(AND(ISNUMBER(AM102),ISNUMBER(AI102),ISNUMBER(AJ102),ISNUMBER(AK102)),AM102-AI102-AJ102-AK102,"") -> 179.444 | AM102: 693.525 | AN102: 177.877 | AO102: 218.361 | AP102: 230.074 | AQ102: =IF(AND(ISNUMBER(AR102),ISNUMBER(AN102),ISNUMBER(AO102),ISNUMBER(AP102)),AR102-AN102-AO102-AP102,"") -> 212.272 | AR102: 838.584 | AS102: 208.542 | AT102: 216.62 | AU102: 228.566 | AW102: 880.323 | AX102: 235.386 | AY102: 266.845 | AZ102: 273.682 | BA102: =IF(AND(ISNUMBER(BB102),ISNUMBER(AX102),ISNUMBER(AY102),ISNUMBER(AZ102)),BB102-AX102-AY102-AZ102,"") -> 270.503 | BB102: 1046.416 | BC102: 276.177 | BD102: 309.927 | BE102: 322.657 | BF102: =IF(AND(ISNUMBER(BG102),ISNUMBER(BC102),ISNUMBER(BD102),ISNUMBER(BE102)),BG102-BC102-BD102-BE102,"") -> 319.359 | BG102: 1228.12 | BH102: 324.886 | BI102: 369.185 | BJ102: 372.862 | BL102: 1440.157 | BM102: 360.927 | BN102: 386.041 | BO102: 391.74 | BP102: =IF(AND(ISNUMBER(BQ102),ISNUMBER(BM102),ISNUMBER(BN102),ISNUMBER(BO102)),BQ102-BM102-BN102-BO102,"") -> 376.194 | BQ102: 1514.902 | BR102: 373.383 | BS102: 402.087 | BT102: 413.389 | BU102: =IF(AND(ISNUMBER(BV102),ISNUMBER(BR102),ISNUMBER(BS102),ISNUMBER(BT102)),BV102-BR102-BS102-BT102,"") -> 401.026 | BV102: 1589.885 | BW102: 396.762 | BX102: 423.761
B103: Canada — revenues (reported, after intercompany) | M103: =IF(AND(ISNUMBER(N103),ISNUMBER(J103),ISNUMBER(K103),ISNUMBER(L103)),N103-J103-K103-L103,"") | R103: =IF(AND(ISNUMBER(S103),ISNUMBER(O103),ISNUMBER(P103),ISNUMBER(Q103)),S103-O103-P103-Q103,"") | W103: =IF(AND(ISNUMBER(X103),ISNUMBER(T103),ISNUMBER(U103),ISNUMBER(V103)),X103-T103-U103-V103,"") | Z103: 60.585 | AA103: 177.745 | AC103: 407.861 | AD103: 163.035 | AE103: 180.297 | AF103: 197.055 | AG103: =IF(AND(ISNUMBER(AH103),ISNUMBER(AD103),ISNUMBER(AE103),ISNUMBER(AF103)),AH103-AD103-AE103-AF103,"") -> 188.39 | AH103: 728.777 | AI103: 169.974 | AJ103: 186.838 | AK103: 187.054 | AL103: =IF(AND(ISNUMBER(AM103),ISNUMBER(AI103),ISNUMBER(AJ103),ISNUMBER(AK103)),AM103-AI103-AJ103-AK103,"") -> 183.347 | AM103: 727.213 | AN103: 168.347 | AO103: 188.527 | AP103: 190.82 | AQ103: =IF(AND(ISNUMBER(AR103),ISNUMBER(AN103),ISNUMBER(AO103),ISNUMBER(AP103)),AR103-AN103-AO103-AP103,"") -> 185.588 | AR103: 733.282 | AS103: 170.423 | AT103: 161.269 | AU103: 184.837 | AW103: 710.46 | AX103: 188.93 | AY103: 220.344 | AZ103: 224.279 | BA103: =IF(AND(ISNUMBER(BB103),ISNUMBER(AX103),ISNUMBER(AY103),ISNUMBER(AZ103)),BB103-AX103-AY103-AZ103,"") -> 223.17 | BB103: 856.723 | BC103: 214.707 | BD103: 250.382 | BE103: 242.314 | BF103: =IF(AND(ISNUMBER(BG103),ISNUMBER(BC103),ISNUMBER(BD103),ISNUMBER(BE103)),BG103-BC103-BD103-BE103,"") -> 233.221 | BG103: 940.624 | BH103: 227.156 | BI103: 248.705 | BJ103: 263.095 | BL103: 995.842 | BM103: 280.362 | BN103: 319.21 | BO103: 342.058 | BP103: =IF(AND(ISNUMBER(BQ103),ISNUMBER(BM103),ISNUMBER(BN103),ISNUMBER(BO103)),BQ103-BM103-BN103-BO103,"") -> 319.35 | BQ103: 1260.98 | BR103: 302.731 | BS103: 343.416 | BT103: 349.766 | BU103: =IF(AND(ISNUMBER(BV103),ISNUMBER(BR103),ISNUMBER(BS103),ISNUMBER(BT103)),BV103-BR103-BS103-BT103,"") -> 328.964 | BV103: 1324.877 | BW103: 344.828 | BX103: 385.767
B104: MidSouth (from Q2/23) — revenues (reported, after intercompany) | M104: =IF(AND(ISNUMBER(N104),ISNUMBER(J104),ISNUMBER(K104),ISNUMBER(L104)),N104-J104-K104-L104,"") | R104: =IF(AND(ISNUMBER(S104),ISNUMBER(O104),ISNUMBER(P104),ISNUMBER(Q104)),S104-O104-P104-Q104,"") | W104: =IF(AND(ISNUMBER(X104),ISNUMBER(T104),ISNUMBER(U104),ISNUMBER(V104)),X104-T104-U104-V104,"") | AG104: =IF(AND(ISNUMBER(AH104),ISNUMBER(AD104),ISNUMBER(AE104),ISNUMBER(AF104)),AH104-AD104-AE104-AF104,"") | AL104: =IF(AND(ISNUMBER(AM104),ISNUMBER(AI104),ISNUMBER(AJ104),ISNUMBER(AK104)),AM104-AI104-AJ104-AK104,"") | AQ104: =IF(AND(ISNUMBER(AR104),ISNUMBER(AN104),ISNUMBER(AO104),ISNUMBER(AP104)),AR104-AN104-AO104-AP104,"") | BA104: =IF(AND(ISNUMBER(BB104),ISNUMBER(AX104),ISNUMBER(AY104),ISNUMBER(AZ104)),BB104-AX104-AY104-AZ104,"") | BF104: =IF(AND(ISNUMBER(BG104),ISNUMBER(BC104),ISNUMBER(BD104),ISNUMBER(BE104)),BG104-BC104-BD104-BE104,"") | BI104: 226.748 | BJ104: 229.638 | BL104: 894.156 | BM104: 230.106 | BN104: 263.573 | BO104: 267.57 | BP104: =IF(AND(ISNUMBER(BQ104),ISNUMBER(BM104),ISNUMBER(BN104),ISNUMBER(BO104)),BQ104-BM104-BN104-BO104,"") -> 262.387 | BQ104: 1023.636 | BR104: 256.988 | BS104: 280.729 | BT104: 282.804 | BU104: =IF(AND(ISNUMBER(BV104),ISNUMBER(BR104),ISNUMBER(BS104),ISNUMBER(BT104)),BV104-BR104-BS104-BT104,"") -> 272.157 | BV104: 1092.678 | BW104: 267.832 | BX104: 296.75
...

Sheet Bull-Base-Bear
B2: Waste Connections (WCN) — Bull / Base / Bear Case P&L Summary | J2: Share price ($): | K2: =Model!$CA$425 -> 155
B3: Adjusted figures (company definitions: Adjusted EBITDA, adjusted net income / adjusted EPS, adjusted free cash flow) · USD millions · Live panel linked to Model — toggle scenario via Model!CF2. Bull and Bear panels are value snapshots generated from the Model with the switch set to each case. 2026E calibrated to the FY26 outlook (Q2-26 release) end-points. | J3: As of: | K3: =TODAY() -> 46301
B5: Scenario: | C5: =Model!$CF$2 -> Base | N5: Scenario: | O5: Bull | P5: Snapshot (values) — Model run with switch = Bull | Z5: Scenario: | AA5: Bear | AB5: Snapshot (values) — Model run with switch = Bear
B7: (USDm, except EPS and shares) | C7: 2025A | D7: 2026E | E7: 2027E | F7: 2028E | G7: 2029E | H7: 2030E | I7: 25-'30 CAGR | J7: LT Hist Avg | K7: LT Hist Min | L7: LT Hist Max | N7: (USDm, except EPS and shares) | O7: 2025A | P7: 2026E | Q7: 2027E | R7: 2028E | S7: 2029E | T7: 2030E | U7: 25-'30 CAGR | V7: LT Hist Avg | W7: LT Hist Min | X7: LT Hist Max | Z7: (USDm, except EPS and shares) | AA7: 2025A | AB7: 2026E | AC7: 2027E | AD7: 2028E | AE7: 2029E | AF7: 2030E | AG7: 25-'30 CAGR | AH7: LT Hist Avg | AI7: LT Hist Min | AJ7: LT Hist Max
B9: Revenues | C9: =Model!BV128 -> 9466.915 | D9: =Model!CA128 -> 10035 | E9: =Model!CB128 -> 10653.27 | F9: =Model!CC128 -> 11506.962 | G9: =Model!CD128 -> 12417.963 | H9: =Model!CE128 -> 13346.873 | I9: =IFERROR((H9/C9)^(1/5)-1,"n/m") -> 0.071110343 | N9: Revenues | O9: 9466.915 | P9: 10050 | Q9: 10962.545 | R9: 12234.637 | S9: 13599.884 | T9: 15020.35 | U9: 0.096716342 | Z9: Revenues | AA9: 9466.915 | AB9: 10020 | AC9: 10344.596 | AD9: 10791.266 | AE9: 11271.713 | AF9: 11746.596 | AG9: 0.044096667
B10: Revenues y/y % | D10: =IFERROR(D9/C9-1,"") -> 0.060007405 | E10: =IFERROR(E9/D9-1,"") -> 0.061611395 | F10: =IFERROR(F9/E9-1,"") -> 0.080134219 | G10: =IFERROR(G9/F9-1,"") -> 0.079169584 | H10: =IFERROR(H9/G9-1,"") -> 0.074803753 | N10: Revenues y/y % | P10: 0.06159187 | Q10: 0.090800449 | R10: 0.11603993 | S10: 0.1115886 | T10: 0.10444695 | Z10: Revenues y/y % | AB10: 0.058422939 | AC10: 0.032394787 | AD10: 0.043179086 | AE10: 0.04452183 | AF10: 0.042130505
B11: Solid waste revenues y/y % (organic from 2027E) | C11: =Model!BV20 -> 0.053798421 | D11: =Model!CA20 -> 0.049051806 | E11: =Model!CB20 -> 0.0425 | F11: =Model!CC20 -> 0.045 | G11: =Model!CD20 -> 0.0475 | H11: =Model!CE20 -> 0.045 | N11: Solid waste revenues y/y % (organic from 2027E) | O11: 0.053798421 | P11: 0.050638686 | Q11: 0.06 | R11: 0.0625 | S11: 0.065 | T11: 0.0625 | Z11: Solid waste revenues y/y % (organic from 2027E) | AA11: 0.053798421 | AB11: 0.047464926 | AC11: 0.025 | AD11: 0.0275 | AE11: 0.03 | AF11: 0.0275
B12: Adjusted EBITDA | C12: =Model!BV180 -> 3124.555 | D12: =Model!CA180 -> 3335 | E12: =Model!CB180 -> 3573.6807 | F12: =Model!CC180 -> 3870.1895 | G12: =Model!CD180 -> 4187.3839 | H12: =Model!CE180 -> 4511.9817 | I12: =IFERROR((H12/C12)^(1/5)-1,"n/m") -> 0.07625661 | N12: Adjusted EBITDA | O12: 3124.555 | P12: 3340 | Q12: 3754.8613 | R12: 4191.9809 | S12: 4663.023 | T12: 5155.0519 | U12: 0.10532241 | Z12: Adjusted EBITDA | AA12: 3124.555 | AB12: 3330 | AC12: 3395.9724 | AD12: 3559.0452 | AE12: 3734.0998 | AF12: 3908.1074 | AG12: 0.045768759
B13: Adjusted EBITDA margin % | C13: =IFERROR(C12/C9,"") -> 0.33004997 | D13: =IFERROR(D12/D9,"") -> 0.33233682 | E13: =IFERROR(E12/E9,"") -> 0.33545386 | F13: =IFERROR(F12/F9,"") -> 0.33633461 | G13: =IFERROR(G12/G9,"") -> 0.33720376 | H13: =IFERROR(H12/H9,"") -> 0.33805533 | J13: =IFERROR(AVERAGE(Model!C181,Model!D181,Model!E181,Model!F181,Model!G181,Model!H181,Model!I181,Model!N181,Model!S181,Model!X181,Model!AC181,Model!AH181,Model!AM181,Model!AR181,Model!AW181,Model!BB181,Model!BG181,Model!BL181,Model!BQ181,Model!BV181),"") -> 0.31777802 | K13: =IFERROR(MIN(Model!C181,Model!D181,Model!E181,Model!F181,Model!G181,Model!H181,Model!I181,Model!N181,Model!S181,Model!X181,Model!AC181,Model!AH181,Model!AM181,Model!AR181,Model!AW181,Model!BB181,Model!BG181,Model!BL181,Model!BQ181,Model!BV181),"") -> 0.29850715 | L13: =IFERROR(MAX(Model!C181,Model!D181,Model!E181,Model!F181,Model!G181,Model!H181,Model!I181,Model!N181,Model!S181,Model!X181,Model!AC181,Model!AH181,Model!AM181,Model!AR181,Model!AW181,Model!BB181,Model!BG181,Model!BL181,Model!BQ181,Model!BV181),"") -> 0.34488733 | N13: Adjusted EBITDA margin % | O13: 0.33004997 | P13: 0.33233831 | Q13: 0.34251732 | R13: 0.34263221 | S13: 0.34287227 | T13: 0.34320452 | V13: 0.31777802 | W13: 0.29850715 | X13: 0.34488733 | Z13: Adjusted EBITDA margin % | AA13: 0.33004997 | AB13: 0.33233533 | AC13: 0.32828469 | AD13: 0.32980794 | AE13: 0.3312806 | AF13: 0.33270128 | AH13: 0.31777802 | AI13: 0.29850715 | AJ13: 0.34488733
B15: Operating Income (GAAP) | C15: =Model!BV134 -> 1710.174 | D15: =Model!CA134 -> 1843.663 | E15: =Model!CB134 -> 2159.8727 | F15: =Model!CC134 -> 2353.2252 | G15: =Model!CD134 -> 2561.0735 | H15: =Model!CE134 -> 2773.6868 | I15: =IFERROR((H15/C15)^(1/5)-1,"n/m") -> 0.10154799 | N15: Operating Income (GAAP) | O15: 1710.174 | P15: 1848.663 | Q15: 2301.146 | R15: 2578.5021 | S15: 2879.6695 | T15: 3195.1049 | U15: 0.13315408 | Z15: Operating Income (GAAP) | AA15: 1710.174 | AB15: 1838.663 | AC15: 2022.003 | AD15: 2137.2178 | AE15: 2260.7305 | AF15: 2383.0467 | AG15: 0.068608069
B16: Operating income y/y % | D16: =IFERROR(D15/C15-1,"") -> 0.0780558 | E16: =IFERROR(E15/D15-1,"") -> 0.17151168 | F16: =IFERROR(F15/E15-1,"") -> 0.089520307 | G16: =IFERROR(G15/F15-1,"") -> 0.088324876 | H16: =IFERROR(H15/G15-1,"") -> 0.083017232 | N16: Operating income y/y % | P16: 0.080979479 | Q16: 0.24476228 | R16: 0.12052958 | S16: 0.11679936 | T16: 0.10953876 | Z16: Operating income y/y % | AB16: 0.075132121 | AC16: 0.099713767 | AD16: 0.056980528 | AE16: 0.057791343 | AF16: 0.054104704
B17: Operating margin (GAAP) % | C17: =IFERROR(C15/C9,"") -> 0.18064744 | D17: =IFERROR(D15/D9,"") -> 0.18372327 | E17: =IFERROR(E15/E9,"") -> 0.2027427 | F17: =IFERROR(F15/F9,"") -> 0.20450448 | G17: =IFERROR(G15/G9,"") -> 0.20623942 | H17: =IFERROR(H15/H9,"") -> 0.20781547 | J17: =IFERROR(AVERAGE(Model!C227,Model!D227,Model!E227,Model!F227,Model!G227,Model!H227,Model!I227,Model!N227,Model!S227,Model!X227,Model!AC227,Model!AH227,Model!AM227,Model!AR227,Model!AW227,Model!BB227,Model!BG227,Model!BL227,Model!BQ227,Model!BV227),"") -> 0.16420594 | K17: =IFERROR(MIN(Model!C227,Model!D227,Model!E227,Model!F227,Model!G227,Model!H227,Model!I227,Model!N227,Model!S227,Model!X227,Model!AC227,Model!AH227,Model!AM227,Model!AR227,Model!AW227,Model!BB227,Model!BG227,Model!BL227,Model!BQ227,Model!BV227),"") -> -0.029061719 | L17: =IFERROR(MAX(Model!C227,Model!D227,Model!E227,Model!F227,Model!G227,Model!H227,Model!I227,Model!N227,Model!S227,Model!X227,Model!AC227,Model!AH227,Model!AM227,Model!AR227,Model!AW227,Model!BB227,Model!BG227,Model!BL227,Model!BQ227,Model!BV227),"") -> 0.21608135 | N17: Operating margin (GAAP) % | O17: 0.18064744 | P17: 0.18394657 | Q17: 0.20990984 | R17: 0.21075427 | S17: 0.21174222 | T17: 0.21271841 | V17: 0.16420594 | W17: -0.029061719 | X17: 0.21608135 | Z17: Operating margin (GAAP) % | AA17: 0.18064744 | AB17: 0.1834993 | AC17: 0.19546467 | AD17: 0.1980507 | AE17: 0.20056672 | AF17: 0.20287126 | AH17: 0.16420594 | AI17: -0.029061719 | AJ17: 0.21608135
B19: Adjusted Net Income (attributable to WCN) | C19: =Model!BV206 -> 1328.334 | D19: =Model!CA206 -> 1427.4655 | E19: =Model!CB206 -> 1514.3873 | F19: =Model!CC206 -> 1643.7109 | G19: =Model!CD206 -> 1777.359 | H19: =Model!CE206 -> 1913.5626 | I19: =IFERROR((H19/C19)^(1/5)-1,"n/m") -> 0.075739403 | N19: Adjusted Net Income (attributable to WCN) | O19: 1328.334 | P19: 1431.3105 | Q19: 1620.872 | R19: 1783.116 | S19: 1981.2305 | T19: 2187.6904 | U19: 0.10493241 | Z19: Adjusted Net Income (attributable to WCN) | AA19: 1328.334 | AB19: 1423.6205 | AC19: 1410.4893 | AD19: 1508.1818 | AE19: 1581.3742 | AF19: 1653.451 | AG19: 0.044760651
B21: FDSO (m) | C21: =Model!BV153 -> 257.97674 | D21: =Model!CA153 -> 253.7157 | E21: =Model!CB153 -> 247.34321 | F21: =Model!CC153 -> 241.24552 | G21: =Model!CD153 -> 234.73886 | H21: =Model!CE153 -> 228.02568 | I21: =IFERROR((H21/C21)^(1/5)-1,"n/m") -> -0.024380122 | N21: FDSO (m) | O21: 257.97674 | P21: 253.39312 | Q21: 243.38563 | R21: 234.0843 | S21: 226.24249 | T21: 217.69864 | U21: -0.033381655 | Z21: FDSO (m) | AA21: 257.97674 | AB21: 254.03828 | AC21: 250.99409 | AD21: 247.5293 | AE21: 241.7867 | AF21: 236.24446 | AG21: -0.017446481
B23: Adjusted EPS — Diluted ($) | C23: =Model!BV210 -> 5.1490456 | D23: =Model!CA210 -> 5.6262405 | E23: =Model!CB210 -> 6.1226153 | F23: =Model!CC210 -> 6.8134358 | G23: =Model!CD210 -> 7.5716434 | H23: =Model!CE210 -> 8.3918733 | I23: =IFERROR((H23/C23)^(1/5)-1,"n/m") -> 0.10262145 | N23: Adjusted EPS — Diluted ($) | O23: 5.1490456 | P23: 5.648577 | Q23: 6.6596863 | R23: 7.6174097 | S23: 8.7571107 | T23: 10.049169 | U23: 0.14309067 | Z23: Adjusted EPS — Diluted ($) | AA23: 5.1490456 | AB23: 5.6039607 | AC23: 5.6196118 | AD23: 6.0929427 | AE23: 6.5403686 | AF23: 6.9988985 | AG23: 0.063311698
B24: EPS y/y % | D24: =IFERROR(D23/C23-1,"") -> 0.092676381 | E24: =IFERROR(E23/D23-1,"") -> 0.088224955 | F24: =IFERROR(F23/E23-1,"") -> 0.11283094 | G24: =IFERROR(G23/F23-1,"") -> 0.11128124 | H24: =IFERROR(H23/G23-1,"") -> 0.10832917 | N24: EPS y/y % | P24: 0.09701437 | Q24: 0.17900249 | R24: 0.14380908 | S24: 0.14961792 | T24: 0.14754387 | Z24: EPS y/y % | AB24: 0.088349409 | AC24: 0.0027928581 | AD24: 0.084228398 | AE24: 0.073433475 | AF24: 0.07010765
B26: P / E (x) — assumed (adjusted EPS) | F26: 30 | G26: 30 | H26: 30 | N26: P / E (x) — assumed (adjusted EPS) | R26: 34 | S26: 34 | T26: 34 | Z26: P / E (x) — assumed (adjusted EPS) | AD26: 24 | AE26: 24 | AF26: 24
B27: Price Target ($) | F27: =F26*F23 -> 204.40307 | G27: =G26*G23 -> 227.1493 | H27: =H26*H23 -> 251.7562 | N27: Price Target ($) | R27: =R26*R23 -> 258.99193 | S27: =S26*S23 -> 297.74176 | T27: =T26*T23 -> 341.67174 | Z27: Price Target ($) | AD27: =AD26*AD23 -> 146.23062 | AE27: =AE26*AE23 -> 156.96885 | AF27: =AF26*AF23 -> 167.97356
B28: Upside / (Downside) vs current | F28: =IFERROR(F27/$K$2-1,"") -> 0.31872951 | G28: =IFERROR(G27/$K$2-1,"") -> 0.46547937 | H28: =IFERROR(H27/$K$2-1,"") -> 0.62423354 | N28: Upside / (Downside) vs current | R28: =IFERROR(R27/$K$2-1,"") -> 0.67091567 | S28: =IFERROR(S27/$K$2-1,"") -> 0.9209146 | T28: =IFERROR(T27/$K$2-1,"") -> 1.2043338 | Z28: Upside / (Downside) vs current | AD28: =IFERROR(AD27/$K$2-1,"") -> -0.056576616 | AE28: =IFERROR(AE27/$K$2-1,"") -> 0.012702241 | AF28: =IFERROR(AF27/$K$2-1,"") -> 0.083700416
B29: IRR (to Dec-Y-1) | F29: =IFERROR((F27/$K$2)^(1/((DATE(2028-1,12,31)-$K$3)/365.25))-1,"") -> 0.25115222 | G29: =IFERROR((G27/$K$2)^(1/((DATE(2029-1,12,31)-$K$3)/365.25))-1,"") -> 0.18632393 | H29: =IFERROR((H27/$K$2)^(1/((DATE(2030-1,12,31)-$K$3)/365.25))-1,"") -> 0.16169606 | N29: IRR (to Dec-Y-1) | R29: =IFERROR((R27/$K$2)^(1/((DATE(2028-1,12,31)-$K$3)/365.25))-1,"") -> 0.51552641 | S29: =IFERROR((S27/$K$2)^(1/((DATE(2029-1,12,31)-$K$3)/365.25))-1,"") -> 0.33889278 | T29: =IFERROR((T27/$K$2)^(1/((DATE(2030-1,12,31)-$K$3)/365.25))-1,"") -> 0.27666275 | Z29: IRR (to Dec-Y-1) | AD29: =IFERROR((AD27/$K$2)^(1/((DATE(2028-1,12,31)-$K$3)/365.25))-1,"") -> -0.046071684 | AE29: =IFERROR((AE27/$K$2)^(1/((DATE(2029-1,12,31)-$K$3)/365.25))-1,"") -> 0.0056588824 | AF29: =IFERROR((AF27/$K$2)^(1/((DATE(2030-1,12,31)-$K$3)/365.25))-1,"") -> 0.025149749
B31: Free Cash Flow (CFO − all capex) | C31: =Model!BV265 -> 1219.703 | D31: =Model!CA265 -> 1353.951 | E31: =Model!CB265 -> 1727.1677 | F31: =Model!CC265 -> 1887.1776 | G31: =Model!CD265 -> 2027.7121 | H31: =Model!CE265 -> 2167.3156 | I31: =IFERROR((H31/C31)^(1/5)-1,"n/m") -> 0.12184695 | N31: Free Cash Flow (CFO − all capex) | O31: 1219.703 | P31: 1378.951 | Q31: 1855.6803 | R31: 2073.6663 | S31: 2284.0891 | T31: 2499.5554 | U31: 0.15430808 | Z31: Free Cash Flow (CFO − all capex) | AA31: 1219.703 | AB31: 1328.951 | AC31: 1602.0671 | AD31: 1706.8571 | AE31: 1782.8613 | AF31: 1854.318 | AG31: 0.087391727
B32: FCF % | C32: =IFERROR(C31/C9,"") -> 0.12883849 | D32: =IFERROR(D31/D9,"") -> 0.13492287 | E32: =IFERROR(E31/E9,"") -> 0.16212559 | F32: =IFERROR(F31/F9,"") -> 0.16400312 | G32: =IFERROR(G31/G9,"") -> 0.16328862 | H32: =IFERROR(H31/H9,"") -> 0.16238377 | J32: =IFERROR(AVERAGE(Model!C267,Model!D267,Model!E267,Model!F267,Model!G267,Model!H267,Model!I267,Model!N267,Model!S267,Model!X267,Model!AC267,Model!AH267,Model!AM267,Model!AR267,Model!AW267,Model!BB267,Model!BG267,Model!BL267,Model!BQ267,Model!BV267),"") -> 0.14623096 | K32: =IFERROR(MIN(Model!C267,Model!D267,Model!E267,Model!F267,Model!G267,Model!H267,Model!I267,Model!N267,Model!S267,Model!X267,Model!AC267,Model!AH267,Model!AM267,Model!AR267,Model!AW267,Model!BB267,Model!BG267,Model!BL267,Model!BQ267,Model!BV267),"") -> 0.098936822 | L32: =IFERROR(MAX(Model!C267,Model!D267,Model!E267,Model!F267,Model!G267,Model!H267,Model!I267,Model!N267,Model!S267,Model!X267,Model!AC267,Model!AH267,Model!AM267,Model!AR267,Model!AW267,Model!BB267,Model!BG267,Model!BL267,Model!BQ267,Model!BV267),"") -> 0.17572626 | N32: FCF % | O32: 0.12883849 | P32: 0.13720905 | Q32: 0.1692746 | R32: 0.16949144 | S32: 0.16794917 | T32: 0.16641126 | V32: 0.14623096 | W32: 0.098936822 | X32: 0.17572626 | Z32: FCF % | AA32: 0.12883849 | AB32: 0.13262984 | AC32: 0.15486995 | AD32: 0.15817024 | AE32: 0.15817128 | AF32: 0.15786003 | AH32: 0.14623096 | AI32: 0.098936822 | AJ32: 0.17572626
B33: FCF / share ($) | C33: =IFERROR(C31/C21,"") -> 4.7279572 | D33: =IFERROR(D31/D21,"") -> 5.3364889 | E33: =IFERROR(E31/E21,"") -> 6.9828792 | F33: =IFERROR(F31/F21,"") -> 7.822643 | G33: =IFERROR(G31/G21,"") -> 8.6381611 | H33: =IFERROR(H31/H21,"") -> 9.5046997 | N33: FCF / share ($) | O33: 4.7279572 | P33: 5.4419434 | Q33: 7.6244449 | R33: 8.8586307 | S33: 10.095757 | T33: 11.481723 | Z33: FCF / share ($) | AA33: 4.7279572 | AB33: 5.2313022 | AC33: 6.3828877 | AD33: 6.895576 | AE33: 7.3736945 | AF33: 7.8491492
B34: FCF Yield (on PT) | F34: =IFERROR(F33/F$27,"") -> 0.038270672 | G34: =IFERROR(G33/G$27,"") -> 0.038028561 | H34: =IFERROR(H33/H$27,"") -> 0.037753588 | N34: FCF Yield (on PT) | R34: =IFERROR(R33/R$27,"") -> 0.034204273 | S34: =IFERROR(S33/S$27,"") -> 0.033907761 | T34: =IFERROR(T33/T$27,"") -> 0.033604544 | Z34: FCF Yield (on PT) | AD34: =IFERROR(AD33/AD$27,"") -> 0.047155485 | AE34: =IFERROR(AE33/AE$27,"") -> 0.046975528 | AF34: =IFERROR(AF33/AF$27,"") -> 0.046728479
B35: Adjusted Free Cash Flow (company definition) | C35: =Model!BV289 -> 1259.293 | D35: =Model!CA289 -> 1422.166 | E35: =Model!CB289 -> 1727.1677 | F35: =Model!CC289 -> 1887.1776 | G35: =Model!CD289 -> 2027.7121 | H35: =Model!CE289 -> 2167.3156 | I35: =IFERROR((H35/C35)^(1/5)-1,"n/m") -> 0.11470275 | N35: Adjusted Free Cash Flow (company definition) | O35: 1259.293 | P35: 1447.166 | Q35: 1855.6803 | R35: 2073.6663 | S35: 2284.0891 | T35: 2499.5554 | U35: 0.14695716 | Z35: Adjusted Free Cash Flow (company definition) | AA35: 1259.293 | AB35: 1397.166 | AC35: 1602.0671 | AD35: 1706.8571 | AE35: 1782.8613 | AF35: 1854.318 | AG35: 0.080466945
B36: Adjusted FCF % of revenues | C36: =IFERROR(C35/C9,"") -> 0.13302042 | D36: =IFERROR(D35/D9,"") -> 0.14172058 | E36: =IFERROR(E35/E9,"") -> 0.16212559 | F36: =IFERROR(F35/F9,"") -> 0.16400312 | G36: =IFERROR(G35/G9,"") -> 0.16328862 | H36: =IFERROR(H35/H9,"") -> 0.16238377 | J36: =IFERROR(AVERAGE(Model!C290,Model!D290,Model!E290,Model!F290,Model!G290,Model!H290,Model!I290,Model!N290,Model!S290,Model!X290,Model!AC290,Model!AH290,Model!AM290,Model!AR290,Model!AW290,Model!BB290,Model!BG290,Model!BL290,Model!BQ290,Model!BV290),"") -> 0.1543922 | K36: =IFERROR(MIN(Model!C290,Model!D290,Model!E290,Model!F290,Model!G290,Model!H290,Model!I290,Model!N290,Model!S290,Model!X290,Model!AC290,Model!AH290,Model!AM290,Model!AR290,Model!AW290,Model!BB290,Model!BG290,Model!BL290,Model!BQ290,Model!BV290),"") -> 0.11077356 | L36: =IFERROR(MAX(Model!C290,Model!D290,Model!E290,Model!F290,Model!G290,Model!H290,Model!I290,Model!N290,Model!S290,Model!X290,Model!AC290,Model!AH290,Model!AM290,Model!AR290,Model!AW290,Model!BB290,Model!BG290,Model!BL290,Model!BQ290,Model!BV290),"") -> 0.17875575 | N36: Adjusted FCF % of revenues | O36: 0.13302042 | P36: 0.14399662 | Q36: 0.1692746 | R36: 0.16949144 | S36: 0.16794917 | T36: 0.16641126 | V36: 0.1543922 | W36: 0.11077356 | X36: 0.17875575 | Z36: Adjusted FCF % of revenues | AA36: 0.13302042 | AB36: 0.13943772 | AC36: 0.15486995 | AD36: 0.15817024 | AE36: 0.15817128 | AF36: 0.15786003 | AH36: 0.1543922 | AI36: 0.11077356 | AJ36: 0.17875575
B38: Net Debt | C38: =Model!BV420 -> 8773.803 | D38: =Model!CA420 -> 9053.9813 | E38: =Model!CB420 -> 9827.6218 | F38: =Model!CC420 -> 10643.021 | G38: =Model!CD420 -> 11515.306 | H38: =Model!CE420 -> 12407.95 | N38: Net Debt | O38: 8773.803 | P38: 9228.4958 | Q38: 11264.584 | R38: 12575.943 | S38: 13989.069 | T38: 15465.156 | Z38: Net Debt | AA38: 8773.803 | AB38: 8879.4668 | AC38: 8489.9311 | AD38: 8897.613 | AE38: 9335.2494 | AF38: 9770.2686
B39: Net Debt / Adjusted EBITDA (x) | C39: =IFERROR(C38/C12,"") -> 2.8080168 | D39: =IFERROR(D38/D12,"") -> 2.714837 | E39: =IFERROR(E38/E12,"") -> 2.75 | F39: =IFERROR(F38/F12,"") -> 2.75 | G39: =IFERROR(G38/G12,"") -> 2.75 | H39: =IFERROR(H38/H12,"") -> 2.75 | N39: Net Debt / Adjusted EBITDA (x) | O39: =IFERROR(O38/O12,"") -> 2.8080168 | P39: =IFERROR(P38/P12,"") -> 2.7630227 | Q39: =IFERROR(Q38/Q12,"") -> 3 | R39: =IFERROR(R38/R12,"") -> 3 | S39: =IFERROR(S38/S12,"") -> 3 | T39: =IFERROR(T38/T12,"") -> 3 | Z39: Net Debt / Adjusted EBITDA (x) | AA39: =IFERROR(AA38/AA12,"") -> 2.8080168 | AB39: =IFERROR(AB38/AB12,"") -> 2.6665065 | AC39: =IFERROR(AC38/AC12,"") -> 2.5 | AD39: =IFERROR(AD38/AD12,"") -> 2.5 | AE39: =IFERROR(AE38/AE12,"") -> 2.5 | AF39: =IFERROR(AF38/AF12,"") -> 2.5
B41: ROIC | C41: =Model!BV403 -> 0.084425176 | D41: =Model!CA403 -> 0.091612176 | E41: =Model!CB403 -> 0.093991533 | F41: =Model!CC403 -> 0.098576448 | G41: =Model!CD403 -> 0.10346836 | H41: =Model!CE403 -> 0.10824866 | J41: =IFERROR(AVERAGE(Model!C403,Model!D403,Model!E403,Model!F403,Model!G403,Model!H403,Model!I403,Model!N403,Model!S403,Model!X403,Model!AC403,Model!AH403,Model!AM403,Model!AR403,Model!AW403,Model!BB403,Model!BG403,Model!BL403,Model!BQ403,Model!BV403),"") -> 0.073580237 | K41: =IFERROR(MIN(Model!C403,Model!D403,Model!E403,Model!F403,Model!G403,Model!H403,Model!I403,Model!N403,Model!S403,Model!X403,Model!AC403,Model!AH403,Model!AM403,Model!AR403,Model!AW403,Model!BB403,Model!BG403,Model!BL403,Model!BQ403,Model!BV403),"") -> 0.045570892 | L41: =IFERROR(MAX(Model!C403,Model!D403,Model!E403,Model!F403,Model!G403,Model!H403,Model!I403,Model!N403,Model!S403,Model!X403,Model!AC403,Model!AH403,Model!AM403,Model!AR403,Model!AW403,Model!BB403,Model!BG403,Model!BL403,Model!BQ403,Model!BV403),"") -> 0.096421385 | N41: ROIC | O41: 0.084425176 | P41: 0.091950287 | Q41: 0.097582461 | R41: 0.10294913 | S41: 0.10873097 | T41: 0.11452401 | V41: 0.073580237 | W41: 0.045570892 | X41: 0.096421385 | Z41: ROIC | AA41: 0.084425176 | AB41: 0.091274898 | AC41: 0.090365919 | AD41: 0.094175634 | AE41: 0.098238896 | AF41: 0.10212462 | AH41: 0.073580237 | AI41: 0.045570892 | AJ41: 0.096421385
B42: RONTA | C42: =Model!BV414 -> 0.16677821 | D42: =Model!CA414 -> 0.17261128 | E42: =Model!CB414 -> 0.17679168 | F42: =Model!CC414 -> 0.18502929 | G42: =Model!CD414 -> 0.1935196 | H42: =Model!CE414 -> 0.20142617 | J42: =IFERROR(AVERAGE(Model!C414,Model!D414,Model!E414,Model!F414,Model!G414,Model!H414,Model!I414,Model!N414,Model!S414,Model!X414,Model!AC414,Model!AH414,Model!AM414,Model!AR414,Model!AW414,Model!BB414,Model!BG414,Model!BL414,Model!BQ414,Model!BV414),"") -> 0.12997541 | K42: =IFERROR(MIN(Model!C414,Model!D414,Model!E414,Model!F414,Model!G414,Model!H414,Model!I414,Model!N414,Model!S414,Model!X414,Model!AC414,Model!AH414,Model!AM414,Model!AR414,Model!AW414,Model!BB414,Model!BG414,Model!BL414,Model!BQ414,Model!BV414),"") -> 0.080214796 | L42: =IFERROR(MAX(Model!C414,Model!D414,Model!E414,Model!F414,Model!G414,Model!H414,Model!I414,Model!N414,Model!S414,Model!X414,Model!AC414,Model!AH414,Model!AM414,Model!AR414,Model!AW414,Model!BB414,Model!BG414,Model!BL414,Model!BQ414,Model!BV414),"") -> 0.1754766 | N42: RONTA | O42: 0.16677821 | P42: 0.17343476 | Q42: 0.18546798 | R42: 0.19689747 | S42: 0.20858528 | T42: 0.21970014 | V42: 0.12997541 | W42: 0.080214796 | X42: 0.1754766 | Z42: RONTA | AA42: 0.16677821 | AB42: 0.17179159 | AC42: 0.16814347 | AD42: 0.17323918 | AE42: 0.17863821 | AF42: 0.18351555 | AH42: 0.12997541 | AI42: 0.080214796 | AJ42: 0.1754766
B44: Implied Market Cap (USDm) | F44: =F27*F21 -> 49311.327 | G44: =G27*G21 -> 53320.769 | H44: =H27*H21 -> 57406.878 | N44: Implied Market Cap (USDm) | R44: =R27*R21 -> 60625.944 | S44: =S27*S21 -> 67361.839 | T44: =T27*T21 -> 74381.473 | Z44: Implied Market Cap (USDm) | AD44: =AD27*AD21 -> 36196.364 | AE44: =AE27*AE21 -> 37952.98 | AF44: =AF27*AF21 -> 39682.824
B45: (+) Net Debt & NCI | F45: =F38+Model!CC341 -> 10643.021 | G45: =G38+Model!CD341 -> 11515.306 | H45: =H38+Model!CE341 -> 12407.95 | N45: (+) Net Debt & NCI | R45: =R38+Model!CC341 -> 12575.943 | S45: =S38+Model!CD341 -> 13989.069 | T45: =T38+Model!CE341 -> 15465.156 | Z45: (+) Net Debt & NCI | AD45: =AD38+Model!CC341 -> 8897.613 | AE45: =AE38+Model!CD341 -> 9335.2494 | AF45: =AF38+Model!CE341 -> 9770.2686
B46: Implied Enterprise Value (USDm) | F46: =F44+F45 -> 59954.348 | G46: =G44+G45 -> 64836.074 | H46: =H44+H45 -> 69814.827 | N46: Implied Enterprise Value (USDm) | R46: =R44+R45 -> 73201.887 | S46: =S44+S45 -> 81350.907 | T46: =T44+T45 -> 89846.629 | Z46: Implied Enterprise Value (USDm) | AD46: =AD44+AD45 -> 45093.977 | AE46: =AE44+AE45 -> 47288.229 | AF46: =AF44+AF45 -> 49453.092
B47: Implied EV / Adjusted EBITDA (x) | F47: =IFERROR(F46/F12,"") -> 15.491321 | G47: =IFERROR(G46/G12,"") -> 15.483671 | H47: =IFERROR(H46/H12,"") -> 15.473207 | N47: Implied EV / Adjusted EBITDA (x) | R47: =IFERROR(R46/R12,"") -> 17.462362 | S47: =IFERROR(S46/S12,"") -> 17.445959 | T47: =IFERROR(T46/T12,"") -> 17.42885 | Z47: Implied EV / Adjusted EBITDA (x) | AD47: =IFERROR(AD46/AD12,"") -> 12.670246 | AE47: =IFERROR(AE46/AE12,"") -> 12.66389 | AF47: =IFERROR(AF46/AF12,"") -> 12.653975

Sheet DCF
B2: DCF VALUATION — WASTE CONNECTIONS (WCN)
B4: 1. WACC BUILD
B5: Risk-free rate (US 10Y govt) | C5: 0.0425 | D5: Assumption (~US 10Y Treasury yield); update to market
B6: Equity risk premium | C6: 0.05 | D6: US implied ERP ~4.5–5.5% (Damodaran)
B7: Levered beta | C7: 0.8 | D7: Solid-waste peers (WM, RSG, CWST, GFL) ~0.6–0.9: franchise / contracted collection, landfill scarcity and CPI-linked pricing dampen cyclicality
B8: Cost of equity | C8: =C5+C7*C6 -> 0.0825
B9: Pre-tax cost of debt | C9: 0.05 | D9: Investment grade (BBB+ / Baa1); 4.80% notes due 2036 issued 1H/26; revolver at SOFR / CORRA + margin (~3.4–4.5%); marginal cost ~5.0%
B10: Tax rate | C10: 0.24 | D10: Model 2027E+ effective tax rate
B11: After-tax cost of debt | C11: =C9*(1-C10) -> 0.038
B12: Target D/V | C12: 0.2 | D12: Net debt ~$9.1bn at YE2026E vs ~$39bn market cap ($155 × ~251m shares); ~2.7x Adjusted EBITDA (company target range ~2.5–3.0x)
B13: WACC | C13: =C8*(1-C12)+C11*C12 -> 0.0736
B15: Valuation date (live) | C15: =TODAY() -> 46301 | D15: Periods = (Dec-31-Year − today) / 365.25; cash flows assumed at year-end
B16: 2. UNLEVERED FREE CASH FLOW BUILD (USDm)
D17: 2026E | E17: 2027E | F17: 2028E | G17: 2029E | H17: 2030E | I17: 2031E | J17: 2032E | K17: 2033E | L17: 2034E | M17: 2035E | N17: Terminal | P17: CAGR 26–30E | Q17: CAGR 26–35E
B18: Adj. EBIT less transaction-related costs | D18: =Model!CA187-Model!CA174 -> 2021.052 | E18: =Model!CB187-Model!CB174 -> 2202.4858 | F18: =Model!CC187-Model!CC174 -> 2399.2531 | G18: =Model!CD187-Model!CD174 -> 2610.7454 | H18: =Model!CE187-Model!CE174 -> 2827.0743 | I18: =H18*(1+I$26) -> 3010.8341 | J18: =I18*(1+J$26) -> 3195.2477 | K18: =J18*(1+K$26) -> 3378.9744 | L18: =K18*(1+L$26) -> 3560.5943 | M18: =L18*(1+M$26) -> 3738.624 | P18: =(H18/D18)^(1/(COLUMNS(D18:H18)-1))-1 -> 0.087526711 | Q18: =(M18/D18)^(1/(COLUMNS(D18:M18)-1))-1 -> 0.07073399
B19: × (1 − tax rate) | D19: =1-$C$10 -> 0.76 | E19: =1-$C$10 -> 0.76 | F19: =1-$C$10 -> 0.76 | G19: =1-$C$10 -> 0.76 | H19: =1-$C$10 -> 0.76 | I19: =1-$C$10 -> 0.76 | J19: =1-$C$10 -> 0.76 | K19: =1-$C$10 -> 0.76 | ... M19: =1-$C$10 -> 0.76
B20: NOPAT | D20: =D18*D19 -> 1535.9995 | E20: =E18*E19 -> 1673.8892 | F20: =F18*F19 -> 1823.4323 | G20: =G18*G19 -> 1984.1665 | H20: =H18*H19 -> 2148.5764 | I20: =I18*I19 -> 2288.2339 | J20: =J18*J19 -> 2428.3882 | K20: =K18*K19 -> 2568.0206 | ... M20: =M18*M19 -> 2841.3543
B21: plus D&A (depreciation, depletion & amortization of intangibles) | D21: =Model!CA169 -> 1304 | E21: =Model!CB169 -> 1371.1948 | F21: =Model!CC169 -> 1470.9364 | G21: =Model!CD169 -> 1576.6385 | H21: =Model!CE169 -> 1684.9075 | I21: =H21*(1+I$26) -> 1794.4264 | J21: =I21*(1+J$26) -> 1904.3351 | K21: =J21*(1+K$26) -> 2013.8343 | L21: =K21*(1+L$26) -> 2122.0779 | M21: =L21*(1+M$26) -> 2228.1818
B22: − Capex (PP&E + undeveloped landfill land) and acquisitions (M&A 2027E–30E) | D22: =Model!CA242+Model!CA243 -> -1301.049 | E22: =Model!CB242+Model!CB243+Model!CB244 -> -2278.3924 | F22: =Model!CC242+Model!CC243+Model!CC244 -> -2380.8354 | G22: =Model!CD242+Model!CD243+Model!CD244 -> -2490.1556 | H22: =Model!CE242+Model!CE243+Model!CE244 -> -2601.6248 | I22: =(Model!CE242+Model!CE243)*(1+I$26) -> -1705.7304 | J22: =I22*(1+J$26) -> -1810.2064 | K22: =J22*(1+K$26) -> -1914.2933 | L22: =K22*(1+L$26) -> -2017.1866 | M22: =L22*(1+M$26) -> -2118.0459
B23: − Δ Working capital (CF statement) | D23: =Model!CA240 -> -158.72058 | E23: =Model!CB240 -> 49.92417 | F23: =Model!CC240 -> 78.713221 | G23: =Model!CD240 -> 83.796159 | H23: =Model!CE240 -> 85.450264 | I23: =H23*(1+I$26) -> 91.004531 | J23: =I23*(1+J$26) -> 96.578559 | K23: =J23*(1+K$26) -> 102.13183 | L23: =K23*(1+L$26) -> 107.62141 | M23: =L23*(1+M$26) -> 113.00248
B24: Unlevered FCF | D24: =D20+D21+D22+D23 -> 1380.2299 | E24: =E20+E21+E22+E23 -> 816.61578 | F24: =F20+F21+F22+F23 -> 992.24653 | G24: =G20+G21+G22+G23 -> 1154.4455 | H24: =H20+H21+H22+H23 -> 1317.3094 | I24: =I20+I21+I22+I23 -> 2467.9345 | J24: =J20+J21+J22+J23 -> 2619.0954 | K24: =K20+K21+K22+K23 -> 2769.6934 | ... M24: =M20+M21+M22+M23 -> 3064.4927 | N24: =M24*(1+$C$27) -> 3171.7499 | P24: =(H24/D24)^(1/(COLUMNS(D24:H24)-1))-1 -> -0.011596937 | Q24: =(M24/D24)^(1/(COLUMNS(D24:M24)-1))-1 -> 0.092671669
B25: Terminal Value (Gordon Growth) | N25: =N24/($C$13-$C$27) -> 82169.687
B26: Fade-period growth (2031E–35E; 6.5% → 5% linear) | I26: 0.065 | J26: =I26+($M$26-$I$26)/4 -> 0.06125 | K26: =J26+($M$26-$I$26)/4 -> 0.0575 | L26: =K26+($M$26-$I$26)/4 -> 0.05375 | M26: 0.05
B27: Terminal growth rate | C27: 0.035
B29: Discount period (years) | D29: =(DATE(2026,12,31)-$C$15)/365.25 -> 0.23545517 | E29: =(DATE(2027,12,31)-$C$15)/365.25 -> 1.2347707 | F29: =(DATE(2028,12,31)-$C$15)/365.25 -> 2.2368241 | G29: =(DATE(2029,12,31)-$C$15)/365.25 -> 3.2361396 | H29: =(DATE(2030,12,31)-$C$15)/365.25 -> 4.2354552 | I29: =(DATE(2031,12,31)-$C$15)/365.25 -> 5.2347707 | J29: =(DATE(2032,12,31)-$C$15)/365.25 -> 6.2368241 | K29: =(DATE(2033,12,31)-$C$15)/365.25 -> 7.2361396 | L29: =(DATE(2034,12,31)-$C$15)/365.25 -> 8.2354552 | M29: =(DATE(2035,12,31)-$C$15)/365.25 -> 9.2347707 | N29: =M29 -> 9.2347707
B30: Discount factor | D30: =1/(1+$C$13)^D29 -> 0.98341759 | E30: =1/(1+$C$13)^E29 -> 0.91604452 | F30: =1/(1+$C$13)^F29 -> 0.85312122 | G30: =1/(1+$C$13)^G29 -> 0.79467464 | H30: =1/(1+$C$13)^H29 -> 0.74023218 | I30: =1/(1+$C$13)^I29 -> 0.68951953 | J30: =1/(1+$C$13)^J29 -> 0.64215628 | K30: =1/(1+$C$13)^K29 -> 0.59816272 | ... N30: =1/(1+$C$13)^N29 -> 0.519011
B31: PV of UFCF | D31: =D24*D30 -> 1357.3424 | E31: =E24*E30 -> 748.05641 | F31: =F24*F30 -> 846.50658 | G31: =G24*G30 -> 917.40859 | H31: =H24*H30 -> 975.11477 | I31: =I24*I30 -> 1701.689 | J31: =J24*J30 -> 1681.8686 | K31: =K24*K30 -> 1656.7274 | ... M31: =M24*M30 -> 1590.5054 | N31: =N25*N30 -> 42646.971
D32: WCN's Adjusted EBITDA expenses share-based compensation; Adjusted EBIT deducts all D&A incl. ~$190m p.a. of amortization of acquired intangibles (non-cash, added back in row 21) and landfill depletion. Closure & post-closure accretion (non-cash) sits in cost of operations and is added back in Adjusted EBITDA but deducted in EBIT here only via D&A — capping / closure cash spend is inside CFO. Acquisition spend from the M&A lever is deducted in 2027E–30E; the fade period and terminal value assume no new acquisitions (organic reinvestment only). 1H/26 acquisitions ($310m) sit in YE2026E net debt. Transaction-related costs (cash; added back in Adjusted EBITDA) are deducted in row 18. Operating-lease costs sit inside operating income.
B33: IMPLIED ROIC — invested capital roll-forward (USDm)
B34: Opening invested capital | D34: =Model!BV400 -> 17019.184 | E34: =D38 -> 17174.954 | F34: =E38 -> 18032.227 | G34: =F38 -> 18863.413 | H34: =G38 -> 19693.134 | I34: =H38 -> 20524.401 | J34: =I38 -> 20344.7 | K34: =J38 -> 20153.993 | L34: =K38 -> 19952.32 | M34: =L38 -> 19739.808
B35: plus Capex and acquisitions | D35: =-D22 -> 1301.049 | E35: =-E22 -> 2278.3924 | F35: =-F22 -> 2380.8354 | G35: =-G22 -> 2490.1556 | H35: =-H22 -> 2601.6248 | I35: =-I22 -> 1705.7304 | J35: =-J22 -> 1810.2064 | K35: =-K22 -> 1914.2933 | ... M35: =-M22 -> 2118.0459
B36: less DD&A | D36: =-D21 -> -1304 | E36: =-E21 -> -1371.1948 | F36: =-F21 -> -1470.9364 | G36: =-G21 -> -1576.6385 | H36: =-H21 -> -1684.9075 | I36: =-I21 -> -1794.4264 | J36: =-J21 -> -1904.3351 | K36: =-K21 -> -2013.8343 | ... M36: =-M21 -> -2228.1818
B37: plus Δ Working capital investment | D37: =-D23 -> 158.72058 | E37: =-E23 -> -49.92417 | F37: =-F23 -> -78.713221 | G37: =-G23 -> -83.796159 | H37: =-H23 -> -85.450264 | I37: =-I23 -> -91.004531 | J37: =-J23 -> -96.578559 | K37: =-K23 -> -102.13183 | ... M37: =-M23 -> -113.00248
B38: Closing invested capital | D38: =SUM(D34:D37) -> 17174.954 | E38: =SUM(E34:E37) -> 18032.227 | F38: =SUM(F34:F37) -> 18863.413 | G38: =SUM(G34:G37) -> 19693.134 | H38: =SUM(H34:H37) -> 20524.401 | I38: =SUM(I34:I37) -> 20344.7 | J38: =SUM(J34:J37) -> 20153.993 | K38: =SUM(K34:K37) -> 19952.32 | ... M38: =SUM(M34:M37) -> 19516.669
B39: NOPAT (row 20) | D39: =D20 -> 1535.9995 | E39: =E20 -> 1673.8892 | F39: =F20 -> 1823.4323 | G39: =G20 -> 1984.1665 | H39: =H20 -> 2148.5764 | I39: =I20 -> 2288.2339 | J39: =J20 -> 2428.3882 | K39: =K20 -> 2568.0206 | ... M39: =M20 -> 2841.3543
B40: Implied ROIC (NOPAT / avg. invested capital) | D40: =IFERROR(D39/AVERAGE(D34,D38),"") -> 0.089839933 | E40: =IFERROR(E39/AVERAGE(E34,E38),"") -> 0.095087945 | F40: =IFERROR(F39/AVERAGE(F34,F38),"") -> 0.0988427 | G40: =IFERROR(G39/AVERAGE(G34,G38),"") -> 0.10292242 | H40: =IFERROR(H39/AVERAGE(H34,H38),"") -> 0.10684775 | I40: =IFERROR(I39/AVERAGE(I34,I38),"") -> 0.11197868 | J40: =IFERROR(J39/AVERAGE(J34,J38),"") -> 0.11992428 | K40: =IFERROR(K39/AVERAGE(K34,K38),"") -> 0.12806066 | ... M40: =IFERROR(M39/AVERAGE(M34,M38),"") -> 0.1447585
B41: Reinvestment rate (net investment / NOPAT) | D41: =IFERROR(SUM(D35:D37)/D39,"") -> 0.10141252 | E41: =IFERROR(SUM(E35:E37)/E39,"") -> 0.51214467 | F41: =IFERROR(SUM(F35:F37)/F39,"") -> 0.45583584 | G41: =IFERROR(SUM(G35:G37)/G39,"") -> 0.41817104 | H41: =IFERROR(SUM(H35:H37)/H39,"") -> 0.38689203 | I41: =IFERROR(SUM(I35:I37)/I39,"") -> -0.078532417 | J41: =IFERROR(SUM(J35:J37)/J39,"") -> -0.078532417 | K41: =IFERROR(SUM(K35:K37)/K39,"") -> -0.078532417 | ... M41: =IFERROR(SUM(M35:M37)/M39,"") -> -0.078532417
B42: Implied terminal RONIC (g / reinvestment rate) | N42: =IFERROR($C$27/M41,"") -> -0.44567583
D43: Opening IC = Model 2025A book invested capital (equity + net debt), rolled forward with capex + M&A − D&A + ΔWC.
B44: 3. VALUATION SUMMARY
B45: Sum of PV (explicit + fade) | C45: =SUM(D31:M31) -> 13101.394
B46: PV of Terminal Value | C46: =N31 -> 42646.971
B47: Enterprise Value | C47: =C45+C46 -> 55748.365
B48: Less: Net debt + NCI (Model 2026E YE) | C48: =Model!CA420+Model!CA341 -> 9053.9813 | D48: WCN-specific: no NCI from 2025 (interests sold 2024–25); YE2026E net debt includes 1H/26 acquisitions and buybacks.
B49: Equity Value | C49: =C47-C48 -> 46694.384
B50: Diluted shares (m, Model 2026E YE) | C50: =Model!CA426 -> 250.27314
B51: Implied share price ($) | C51: =C49/C50 -> 186.57369
B52: Current share price ($) | C52: =Model!CA425 -> 155
B53: Implied upside / (downside) | C53: =C51/C52-1 -> 0.20370122
B54: Required discount to DCF value for target IRR | C54: =1-((1+C13)/(1+H54))^H55 -> 0.18635682 | D54: vs. current | E54: Target IRR | H54: 0.15
B55: Max entry price for target IRR ($) | C55: =C51*(1-C54) -> 151.80441 | D55: =C55/C52-1 -> -0.02061671 | E55: Years for discount to close | H55: 3
B58: 4. SENSITIVITY: IMPLIED PRICE ($) — WACC × Terminal Growth
D60: WACC →
B61: Terminal growth ↓ | D61: =F61-0.01 -> 0.0636 | E61: =F61-0.005 -> 0.0686 | F61: =$C$13 -> 0.0736 | G61: =F61+0.005 -> 0.0786 | H61: =F61+0.01 -> 0.0836
B62: =B64-0.01 -> 0.025 | D62: {=IFERROR((SUMPRODUCT($D$24:$M$24/(1+D$61)^$D$29:$M$29)+($M$24*(1+$B62)/(D$61-$B62))/(1+D$61)^$M$29-$C$48)/$C$50,"")} -> 202.85158 | E62: {=IFERROR((SUMPRODUCT($D$24:$M$24/(1+E$61)^$D$29:$M$29)+($M$24*(1+$B62)/(E$61-$B62))/(1+E$61)^$M$29-$C$48)/$C$50,"")} -> 173.47715 | F62: {=IFERROR((SUMPRODUCT($D$24:$M$24/(1+F$61)^$D$29:$M$29)+($M$24*(1+$B62)/(F$61-$B62))/(1+F$61)^$M$29-$C$48)/$C$50,"")} -> 150.20398 | G62: {=IFERROR((SUMPRODUCT($D$24:$M$24/(1+G$61)^$D$29:$M$29)+($M$24*(1+$B62)/(G$61-$B62))/(1+G$61)^$M$29-$C$48)/$C$50,"")} -> 131.32296 | H62: {=IFERROR((SUMPRODUCT($D$24:$M$24/(1+H$61)^$D$29:$M$29)+($M$24*(1+$B62)/(H$61-$B62))/(1+H$61)^$M$29-$C$48)/$C$50,"")} -> 115.70834
B63: =B64-0.005 -> 0.03 | D63: {=IFERROR((SUMPRODUCT($D$24:$M$24/(1+D$61)^$D$29:$M$29)+($M$24*(1+$B63)/(D$61-$B63))/(1+D$61)^$M$29-$C$48)/$C$50,"")} -> 231.26179 | E63: {=IFERROR((SUMPRODUCT($D$24:$M$24/(1+E$61)^$D$29:$M$29)+($M$24*(1+$B63)/(E$61-$B63))/(1+E$61)^$M$29-$C$48)/$C$50,"")} -> 194.5418 | F63: {=IFERROR((SUMPRODUCT($D$24:$M$24/(1+F$61)^$D$29:$M$29)+($M$24*(1+$B63)/(F$61-$B63))/(1+F$61)^$M$29-$C$48)/$C$50,"")} -> 166.30342 | G63: {=IFERROR((SUMPRODUCT($D$24:$M$24/(1+G$61)^$D$29:$M$29)+($M$24*(1+$B63)/(G$61-$B63))/(1+G$61)^$M$29-$C$48)/$C$50,"")} -> 143.92716 | H63: {=IFERROR((SUMPRODUCT($D$24:$M$24/(1+H$61)^$D$29:$M$29)+($M$24*(1+$B63)/(H$61-$B63))/(1+H$61)^$M$29-$C$48)/$C$50,"")} -> 125.77102
B64: =$C$27 -> 0.035 | D64: {=IFERROR((SUMPRODUCT($D$24:$M$24/(1+D$61)^$D$29:$M$29)+($M$24*(1+$B64)/(D$61-$B64))/(1+D$61)^$M$29-$C$48)/$C$50,"")} -> 269.60563 | E64: {=IFERROR((SUMPRODUCT($D$24:$M$24/(1+E$61)^$D$29:$M$29)+($M$24*(1+$B64)/(E$61-$B64))/(1+E$61)^$M$29-$C$48)/$C$50,"")} -> 221.87569 | F64: {=IFERROR((SUMPRODUCT($D$24:$M$24/(1+F$61)^$D$29:$M$29)+($M$24*(1+$B64)/(F$61-$B64))/(1+F$61)^$M$29-$C$48)/$C$50,"")} -> 186.57369 | G64: {=IFERROR((SUMPRODUCT($D$24:$M$24/(1+G$61)^$D$29:$M$29)+($M$24*(1+$B64)/(G$61-$B64))/(1+G$61)^$M$29-$C$48)/$C$50,"")} -> 159.42223 | H64: {=IFERROR((SUMPRODUCT($D$24:$M$24/(1+H$61)^$D$29:$M$29)+($M$24*(1+$B64)/(H$61-$B64))/(1+H$61)^$M$29-$C$48)/$C$50,"")} -> 137.90422
B65: =B64+0.005 -> 0.04 | D65: {=IFERROR((SUMPRODUCT($D$24:$M$24/(1+D$61)^$D$29:$M$29)+($M$24*(1+$B65)/(D$61-$B65))/(1+D$61)^$M$29-$C$48)/$C$50,"")} -> 324.19686 | E65: {=IFERROR((SUMPRODUCT($D$24:$M$24/(1+E$61)^$D$29:$M$29)+($M$24*(1+$B65)/(E$61-$B65))/(1+E$61)^$M$29-$C$48)/$C$50,"")} -> 258.76688 | F65: {=IFERROR((SUMPRODUCT($D$24:$M$24/(1+F$61)^$D$29:$M$29)+($M$24*(1+$B65)/(F$61-$B65))/(1+F$61)^$M$29-$C$48)/$C$50,"")} -> 212.87678 | G65: {=IFERROR((SUMPRODUCT($D$24:$M$24/(1+G$61)^$D$29:$M$29)+($M$24*(1+$B65)/(G$61-$B65))/(1+G$61)^$M$29-$C$48)/$C$50,"")} -> 178.93157 | H65: {=IFERROR((SUMPRODUCT($D$24:$M$24/(1+H$61)^$D$29:$M$29)+($M$24*(1+$B65)/(H$61-$B65))/(1+H$61)^$M$29-$C$48)/$C$50,"")} -> 152.82025
B66: =B64+0.01 -> 0.045 | D66: {=IFERROR((SUMPRODUCT($D$24:$M$24/(1+D$61)^$D$29:$M$29)+($M$24*(1+$B66)/(D$61-$B66))/(1+D$61)^$M$29-$C$48)/$C$50,"")} -> 408.13822 | E66: {=IFERROR((SUMPRODUCT($D$24:$M$24/(1+E$61)^$D$29:$M$29)+($M$24*(1+$B66)/(E$61-$B66))/(1+E$61)^$M$29-$C$48)/$C$50,"")} -> 311.28994 | F66: {=IFERROR((SUMPRODUCT($D$24:$M$24/(1+F$61)^$D$29:$M$29)+($M$24*(1+$B66)/(F$61-$B66))/(1+F$61)^$M$29-$C$48)/$C$50,"")} -> 248.37676 | G66: {=IFERROR((SUMPRODUCT($D$24:$M$24/(1+G$61)^$D$29:$M$29)+($M$24*(1+$B66)/(G$61-$B66))/(1+G$61)^$M$29-$C$48)/$C$50,"")} -> 204.24726 | H66: {=IFERROR((SUMPRODUCT($D$24:$M$24/(1+H$61)^$D$29:$M$29)+($M$24*(1+$B66)/(H$61-$B66))/(1+H$61)^$M$29-$C$48)/$C$50,"")} -> 171.60055
B69: 5. REVERSE DCF
B70: To solve for the market-implied path: Data ▸ What-If Analysis ▸ Goal Seek — set C51 to the current price (C52) by changing C27 (terminal growth) or the fade-period growth inputs (I26:M26).
B72: 6. MAUBOUSSIN EV / NOPAT — TWO-STAGE FRAMEWORK
B73: EV/NOPAT = 1/r + [g × (1 − r/ROIIC) / (r × (r − g))] × [1 − ((1+g)/(1+r))^N]
B74: Formula source: Mauboussin & Rappaport, "Expectations Investing" (2021); Counterpoint Global, "What Does a Price-Earnings Multiple Mean?" (2020).
B76: Input | C76: Value | D76: Rationale (Martin Marietta characteristics)
B77: r (Cost of capital / WACC) | C77: =$C$13 -> 0.0736 | D77: Linked from Section 1 WACC build
B78: g (NOPAT growth, Stage 1) | C78: 0.065 | D78: Model NOPAT CAGR 2026–30E ~8–9% (mid-single-digit price / yield, flat-to-slightly-positive volume, ~20bp p.a. margin expansion, tuck-in M&A); fades over the 15-year CAP → 6.5% average (must stay below WACC)
B79: ROIIC (Return on incremental invested capital) | C79: 0.12 | D79: Price-led organic growth on a dense, vertically integrated (collection → transfer → owned landfill) footprint earns high returns on organic capex; tuck-in acquisitions at ~2.5–3x revenue (~8–10x EBITDA) earn ~8–10% after tax
B80: N (Years of value creation / CAP) | C80: 15 | D80: Landfill permits are scarce and multi-decade (secondary / rural markets with franchise or exclusive positions; ~70% internalization); E&P waste niche; consistent capital allocation (M&A + buybacks + dividend growth)
B82: Calculation | C82: Value
B83: Steady-state component: 1 / r | C83: =1/C77 -> 13.586957
B84: Value-creation factor: 1 − r / ROIIC | C84: =1-C77/C79 -> 0.38666667
B85: Growth multiplier: g × (1 − r/ROIIC) / (r × (r − g)) | C85: =C78*C84/(C77*(C77-C78)) -> 39.707617
B86: Time decay: 1 − ((1+g)/(1+r))^N | C86: =1-((1+C78)/(1+C77))^C80 -> 0.1136473
B87: PVGO component (growth value) | C87: =C85*C86 -> 4.5126633
B88: Mauboussin EV / NOPAT (steady-state + PVGO) | C88: =C83+C87 -> 18.09962
B90: VALUATION — Applied to 2028E NOPAT | C90: USDm
B91: 2028E Adj. EBIT less acquisition & integration costs | C91: =Model!CC187-Model!CC174 -> 2399.2531
B92: Tax rate (from WACC build) | C92: =$C$10 -> 0.24
B93: 2028E NOPAT | C93: =C91*(1-C92) -> 1823.4323
B94: × Mauboussin EV/NOPAT multiple | C94: =C88 -> 18.09962
B95: Implied Enterprise Value (2028E basis) | C95: =C93*C94 -> 33003.432
B96: Less: YE2027 net debt + NCI (Model) | C96: =Model!CB420+Model!CB341 -> 9827.6218
B97: Implied Equity Value | C97: =C95-C96 -> 23175.81
B98: Diluted shares 2028E (m, Model) | C98: =Model!CC426 -> 238.07777
B99: Implied share price 2028 ($) | C99: =C97/C98 -> 97.345543
B101: Current share price ($) | C101: =C52 -> 155
B102: Implied upside / (downside) | C102: =C99/C101-1 -> -0.37196424
B104: MARKET-IMPLIED EV/NOPAT TODAY | C104: USDm
B105: Current market cap (spot × diluted shares) | C105: =C52*C50 -> 38792.337
B106: Plus: YE2026 net debt + NCI | C106: =C48 -> 9053.9813
B107: Implied Enterprise Value (today) | C107: =C105+C106 -> 47846.318
B108: WCN market-implied EV/NOPAT (on 2028E NOPAT) | C108: =C107/C93 -> 26.239701
B110: Multiple gap (Mauboussin − Market) | C110: =C88-C108 -> -8.1400808
B111: Implied re-rating headroom | C111: =C88/C108-1 -> -0.31022003

Sheet Charts
B2: Waste Connections — Historical Operating Performance (2006–2025)
B3: All historicals · USDm · Linked to Model. Price / volume = company-reported solid waste internal growth (2006–08 price incl. surcharges; 2006–12 company-wide basis; 2013–16 FY = average of quarterly disclosures; 2026 company basis = yield / unit volume). Adjusted EBITDA as reconciled by WCN in each period ("adjusted operating income before D&A" FY2008–12; model bridge FY2006–07).
C7: 2006 | D7: 2007 | E7: 2008 | F7: 2009 | G7: 2010 | H7: 2011 | I7: 2012 | J7: 2013 | K7: 2014 | L7: 2015 | M7: 2016 | N7: 2017 | O7: 2018 | P7: 2019 | Q7: 2020 | R7: 2021 | S7: 2022 | T7: 2023 | U7: 2024 | V7: 2025
B8: Solid waste volume % | C8: =IFERROR(Model!C26+0,0) -> 0.028 | D8: =IFERROR(Model!D26+0,0) -> 0.04 | E8: =IFERROR(Model!E26+0,0) -> -0.019 | F8: =IFERROR(Model!F26+0,0) -> -0.062 | G8: =IFERROR(Model!G26+0,0) -> 0 | H8: =IFERROR(Model!H26+0,0) -> -0.003 | I8: =IFERROR(Model!I26+0,0) -> -0.021 | J8: =IFERROR(Model!N26+0,IFERROR(AVERAGE(Model!J26:M26),0)) -> 0.007 | K8: =IFERROR(Model!S26+0,IFERROR(AVERAGE(Model!O26:R26),0)) -> 0.021 | L8: =IFERROR(Model!X26+0,IFERROR(AVERAGE(Model!T26:W26),0)) -> 0.022 | M8: =IFERROR(Model!AC26+0,IFERROR(AVERAGE(Model!Y26:AB26),0)) -> 0.019 | N8: =IFERROR(Model!AH26+0,IFERROR(AVERAGE(Model!AD26:AG26),0)) -> 0.012 | O8: =IFERROR(Model!AM26+0,IFERROR(AVERAGE(Model!AI26:AL26),0)) -> -0.007 | P8: =IFERROR(Model!AR26+0,IFERROR(AVERAGE(Model!AN26:AQ26),0)) -> -0.002 | Q8: =IFERROR(Model!AW26+0,IFERROR(AVERAGE(Model!AS26:AV26),0)) -> -0.048 | R8: =IFERROR(Model!BB26+0,IFERROR(AVERAGE(Model!AX26:BA26),0)) -> 0.016 | S8: =IFERROR(Model!BG26+0,IFERROR(AVERAGE(Model!BC26:BF26),0)) -> -0.011 | T8: =IFERROR(Model!BL26+0,IFERROR(AVERAGE(Model!BH26:BK26),0)) -> -0.02 | U8: =IFERROR(Model!BQ26+0,IFERROR(AVERAGE(Model!BM26:BP26),0)) -> -0.029 | V8: =IFERROR(Model!BV26+0,IFERROR(AVERAGE(Model!BR26:BU26),0)) -> -0.028
B9: Solid waste price % | C9: =IFERROR(Model!C24+0,0) -> 0.051 | D9: =IFERROR(Model!D24+0,0) -> 0.047 | E9: =IFERROR(Model!E24+0,0) -> 0.056 | F9: =IFERROR(Model!F24+0,0) -> 0.048 | G9: =IFERROR(Model!G24+0,0) -> 0.027 | H9: =IFERROR(Model!H24+0,0) -> 0.036 | I9: =IFERROR(Model!I24+0,0) -> 0.032 | J9: =IFERROR(Model!N24+0,IFERROR(AVERAGE(Model!J24:M24),0)) -> 0.026 | K9: =IFERROR(Model!S24+0,IFERROR(AVERAGE(Model!O24:R24),0)) -> 0.028 | L9: =IFERROR(Model!X24+0,IFERROR(AVERAGE(Model!T24:W24),0)) -> 0.028 | M9: =IFERROR(Model!AC24+0,IFERROR(AVERAGE(Model!Y24:AB24),0)) -> 0.028 | N9: =IFERROR(Model!AH24+0,IFERROR(AVERAGE(Model!AD24:AG24),0)) -> 0.031 | O9: =IFERROR(Model!AM24+0,IFERROR(AVERAGE(Model!AI24:AL24),0)) -> 0.041 | P9: =IFERROR(Model!AR24+0,IFERROR(AVERAGE(Model!AN24:AQ24),0)) -> 0.051 | Q9: =IFERROR(Model!AW24+0,IFERROR(AVERAGE(Model!AS24:AV24),0)) -> 0.045 | R9: =IFERROR(Model!BB24+0,IFERROR(AVERAGE(Model!AX24:BA24),0)) -> 0.047 | S9: =IFERROR(Model!BG24+0,IFERROR(AVERAGE(Model!BC24:BF24),0)) -> 0.077 | T9: =IFERROR(Model!BL24+0,IFERROR(AVERAGE(Model!BH24:BK24),0)) -> 0.095 | U9: =IFERROR(Model!BQ24+0,IFERROR(AVERAGE(Model!BM24:BP24),0)) -> 0.071 | V9: =IFERROR(Model!BV24+0,IFERROR(AVERAGE(Model!BR24:BU24),0)) -> 0.065
C11: =C7 -> 2006 | D11: =D7 -> 2007 | E11: =E7 -> 2008 | F11: =F7 -> 2009 | G11: =G7 -> 2010 | H11: =H7 -> 2011 | I11: =I7 -> 2012 | J11: =J7 -> 2013 | ... V11: =V7 -> 2025
B12: Adjusted EBITDA | C12: =Model!C180 -> 247.047 | D12: =Model!D180 -> 292.887 | E12: =Model!E180 -> 313.314 | F12: =Model!F180 -> 368.833 | G12: =Model!G180 -> 424.257 | H12: =Model!H180 -> 489.53 | I12: =Model!I180 -> 528.419 | J12: =Model!N180 -> 657.002 | K12: =Model!S180 -> 717.078 | L12: =Model!X180 -> 710.607 | M12: =Model!AC180 -> 1071.089 | N12: =Model!AH180 -> 1460.525 | O12: =Model!AM180 -> 1566.418 | P12: =Model!AR180 -> 1673.554 | Q12: =Model!AW180 -> 1661.984 | R12: =Model!BB180 -> 1919.158 | S12: =Model!BG180 -> 2220.652 | T12: =Model!BL180 -> 2522.956 | U12: =Model!BQ180 -> 2901.865 | V12: =Model!BV180 -> 3124.555
B13: Operating Income (GAAP) | C13: =Model!C134 -> 171.386 | D13: =Model!D134 -> 207.009 | E13: =Model!E134 -> 212.356 | F13: =Model!F134 -> 230.675 | G13: =Model!G134 -> 272.383 | H13: =Model!H134 -> 317.062 | I13: =Model!I134 -> 316.147 | J13: =Model!N134 -> 394.72 | K13: =Model!S134 -> 449.269 | L13: =Model!X134 -> -61.532 | M13: =Model!AC134 -> 452.298 | N13: =Model!AH134 -> 627.098 | O13: =Model!AM134 -> 832.244 | P13: =Model!AR134 -> 837.778 | Q13: =Model!AW134 -> 412.428 | R13: =Model!BB134 -> 1039.625 | S13: =Model!BG134 -> 1242.19 | T13: =Model!BL134 -> 1236.312 | U13: =Model!BQ134 -> 1067.659 | V13: =Model!BV134 -> 1710.174
B14: Adj. EBITDA Margin % | C14: =Model!C225 -> 0.29968557 | D14: =Model!D225 -> 0.305555 | E14: =Model!E225 -> 0.29850715 | F14: =Model!F225 -> 0.30958131 | G14: =Model!G225 -> 0.321466 | H14: =Model!H225 -> 0.32519002 | I14: =Model!I225 -> 0.31801473 | J14: =Model!N225 -> 0.34062822 | K14: =Model!S225 -> 0.34488733 | L14: =Model!X225 -> 0.33562148 | M14: =Model!AC225 -> 0.31727857 | N14: =Model!AH225 -> 0.31541492 | O14: =Model!AM225 -> 0.31818744 | P14: =Model!AR225 -> 0.31056851 | Q14: =Model!AW225 -> 0.30517573 | R14: =Model!BB225 -> 0.31198917 | S14: =Model!BG225 -> 0.30791672 | T14: =Model!BL225 -> 0.31450653 | U14: =Model!BQ225 -> 0.32533611 | V14: =Model!BV225 -> 0.33004997
B15: GAAP Op. Margin % | C15: =Model!C227 -> 0.2079034 | D15: =Model!D227 -> 0.21596259 | E15: =Model!E227 -> 0.20232031 | F15: =Model!F227 -> 0.19361789 | G15: =Model!G227 -> 0.20638875 | H15: =Model!H227 -> 0.2106212 | I15: =Model!I227 -> 0.19026455 | J15: =Model!N227 -> 0.20464591 | K15: =Model!S227 -> 0.21608135 | L15: =Model!X227 -> -0.029061719 | M15: =Model!AC227 -> 0.13397996 | N15: =Model!AH227 -> 0.13542806 | O15: =Model!AM227 -> 0.16905423 | P15: =Model!AR227 -> 0.15547001 | Q15: =Model!AW227 -> 0.075730583 | R15: =Model!BB227 -> 0.16900731 | S15: =Model!BG227 -> 0.17224269 | T15: =Model!BL227 -> 0.15411612 | U15: =Model!BQ227 -> 0.1196982 | V15: =Model!BV227 -> 0.18064744
C17: =C7 -> 2006 | D17: =D7 -> 2007 | E17: =E7 -> 2008 | F17: =F7 -> 2009 | G17: =G7 -> 2010 | H17: =H7 -> 2011 | I17: =I7 -> 2012 | J17: =J7 -> 2013 | ... V17: =V7 -> 2025
B18: ROIC | C18: =IFERROR(Model!C403+0,NA()) -> 0.081652798 | D18: =IFERROR(Model!D403+0,NA()) -> 0.088903109 | E18: =IFERROR(Model!E403+0,NA()) -> 0.079059567 | F18: =IFERROR(Model!F403+0,NA()) -> 0.067834578 | G18: =IFERROR(Model!G403+0,NA()) -> 0.073523409 | H18: =IFERROR(Model!H403+0,NA()) -> 0.076456923 | I18: =IFERROR(Model!I403+0,NA()) -> 0.049198288 | J18: =IFERROR(Model!N403+0,NA()) -> 0.061429497 | K18: =IFERROR(Model!S403+0,NA()) -> 0.066154073 | L18: =IFERROR(Model!X403+0,NA()) -> 0.080097581 | M18: =IFERROR(Model!AC403+0,NA()) -> 0.045570892 | N18: =IFERROR(Model!AH403+0,NA()) -> 0.096421385 | O18: =IFERROR(Model!AM403+0,NA()) -> 0.066577868 | P18: =IFERROR(Model!AR403+0,NA()) -> 0.068056737 | Q18: =IFERROR(Model!AW403+0,NA()) -> 0.066655258 | R18: =IFERROR(Model!BB403+0,NA()) -> 0.074637812 | S18: =IFERROR(Model!BG403+0,NA()) -> 0.074463603 | T18: =IFERROR(Model!BL403+0,NA()) -> 0.082024964 | U18: =IFERROR(Model!BQ403+0,NA()) -> 0.08846123 | V18: =IFERROR(Model!BV403+0,NA()) -> 0.084425176
B19: RONTA | C19: =IFERROR(Model!C414+0,NA()) -> 0.14119552 | D19: =IFERROR(Model!D414+0,NA()) -> 0.15184686 | E19: =IFERROR(Model!E414+0,NA()) -> 0.1157883 | F19: =IFERROR(Model!F414+0,NA()) -> 0.11420827 | G19: =IFERROR(Model!G414+0,NA()) -> 0.12327392 | H19: =IFERROR(Model!H414+0,NA()) -> 0.13224651 | I19: =IFERROR(Model!I414+0,NA()) -> 0.080214796 | J19: =IFERROR(Model!N414+0,NA()) -> 0.098857503 | K19: =IFERROR(Model!S414+0,NA()) -> 0.10245485 | L19: =IFERROR(Model!X414+0,NA()) -> 0.11766117 | M19: =IFERROR(Model!AC414+0,NA()) -> 0.08236745 | N19: =IFERROR(Model!AH414+0,NA()) -> 0.17237995 | O19: =IFERROR(Model!AM414+0,NA()) -> 0.12223311 | P19: =IFERROR(Model!AR414+0,NA()) -> 0.12321259 | Q19: =IFERROR(Model!AW414+0,NA()) -> 0.11998649 | R19: =IFERROR(Model!BB414+0,NA()) -> 0.1495612 | S19: =IFERROR(Model!BG414+0,NA()) -> 0.14709959 | T19: =IFERROR(Model!BL414+0,NA()) -> 0.16266541 | U19: =IFERROR(Model!BQ414+0,NA()) -> 0.1754766 | V19: =IFERROR(Model!BV414+0,NA()) -> 0.16677821
B20: Adj. EBITDA margin % | C20: =IFERROR(Model!C225+0,NA()) -> 0.29968557 | D20: =IFERROR(Model!D225+0,NA()) -> 0.305555 | E20: =IFERROR(Model!E225+0,NA()) -> 0.29850715 | F20: =IFERROR(Model!F225+0,NA()) -> 0.30958131 | G20: =IFERROR(Model!G225+0,NA()) -> 0.321466 | H20: =IFERROR(Model!H225+0,NA()) -> 0.32519002 | I20: =IFERROR(Model!I225+0,NA()) -> 0.31801473 | J20: =IFERROR(Model!N225+0,NA()) -> 0.34062822 | K20: =IFERROR(Model!S225+0,NA()) -> 0.34488733 | L20: =IFERROR(Model!X225+0,NA()) -> 0.33562148 | M20: =IFERROR(Model!AC225+0,NA()) -> 0.31727857 | N20: =IFERROR(Model!AH225+0,NA()) -> 0.31541492 | O20: =IFERROR(Model!AM225+0,NA()) -> 0.31818744 | P20: =IFERROR(Model!AR225+0,NA()) -> 0.31056851 | Q20: =IFERROR(Model!AW225+0,NA()) -> 0.30517573 | R20: =IFERROR(Model!BB225+0,NA()) -> 0.31198917 | S20: =IFERROR(Model!BG225+0,NA()) -> 0.30791672 | T20: =IFERROR(Model!BL225+0,NA()) -> 0.31450653 | U20: =IFERROR(Model!BQ225+0,NA()) -> 0.32533611 | V20: =IFERROR(Model!BV225+0,NA()) -> 0.33004997
B21: Adj. FCF margin % | C21: =IFERROR(Model!C290+0,NA()) -> 0.11827686 | D21: =IFERROR(Model!D290+0,NA()) -> 0.11077356 | E21: =IFERROR(Model!E290+0,NA()) -> 0.14592374 | F21: =IFERROR(Model!F290+0,NA()) -> 0.16141021 | G21: =IFERROR(Model!G290+0,NA()) -> 0.16388244 | H21: =IFERROR(Model!H290+0,NA()) -> 0.16908911 | I21: =IFERROR(Model!I290+0,NA()) -> 0.16595812 | J21: =IFERROR(Model!N290+0,NA()) -> 0.15635617 | K21: =IFERROR(Model!S290+0,NA()) -> 0.1546649 | L21: =IFERROR(Model!X290+0,NA()) -> 0.16199363 | M21: =IFERROR(Model!AC290+0,NA()) -> 0.16320094 | N21: =IFERROR(Model!AH290+0,NA()) -> 0.16496987 | O21: =IFERROR(Model!AM290+0,NA()) -> 0.17875575 | P21: =IFERROR(Model!AR290+0,NA()) -> 0.17023597 | Q21: =IFERROR(Model!AW290+0,NA()) -> 0.15459044 | R21: =IFERROR(Model!BB290+0,NA()) -> 0.16412596 | S21: =IFERROR(Model!BG290+0,NA()) -> 0.16151786 | T21: =IFERROR(Model!BL290+0,NA()) -> 0.15259779 | U21: =IFERROR(Model!BQ290+0,NA()) -> 0.1365002 | V21: =IFERROR(Model!BV290+0,NA()) -> 0.13302042
