Workbook

Sheet Model
AV1: SCENARIO SWITCH ▼ (Bull / Base / Bear) — drives all scenario-linked forecast drivers
B2: Woodward, Inc. (NASDAQ: WWD) — 3-Statement Financial Model | AV2: Base
B3: US GAAP as reported · USD millions (per-share data in USD; shares in millions) · Fiscal years ended 30 September (2026 = Oct-2025 – Sep-2026) · Source: Woodward Forms 10-K / 10-Q, Form 8-K earnings releases (Ex. 99.1) and deal / financing 8-Ks, SEC EDGAR (CIK 108312); XBRL company facts; investor-relations releases at woodward.com are the same documents as filed on EDGAR
B4: Basis notes: as originally reported (FY2016 and FY2018 reclassifications not recast; FY2018 restated segment earnings in memo rows). Segments: Aerospace, Industrial (Energy to FY2015). Acquisitions: L'Orange Jun-18, Safran EMA Jul-25, Valve Research Apr-26; divestitures: renewable power systems May-20, product lines FY25, pilot controls (ONTIC, pending FY27). Q4/26E calibrated to FY26 sales-growth and adjusted-EPS guidance (29-Jul-2026).
AX5: Forecast | AY5: Historical | AZ5: Historical | BA5: Historical
B6: (USDm) | C6: 2011 | D6: 2012 | E6: 2013 | F6: 2014 | G6: 2015 | H6: 2016 | I6: 2017 | J6: 2018 | K6: 2019 | L6: 2020 | M6: Q1/21 | N6: Q2/21 | O6: Q3/21 | P6: Q4/21 | Q6: 2021 | R6: Q1/22 | S6: Q2/22 | T6: Q3/22 | U6: Q4/22 | V6: 2022 | W6: Q1/23 | X6: Q2/23 | Y6: Q3/23 | Z6: Q4/23 | AA6: 2023 | AB6: Q1/24 | AC6: Q2/24 | AD6: Q3/24 | AE6: Q4/24 | AF6: 2024 | AG6: Q1/25 | AH6: Q2/25 | AI6: Q3/25 | AJ6: Q4/25 | AK6: 2025 | AL6: Q1/26 | AM6: Q2/26 | AN6: Q3/26 | AO6: Q4/26E | AP6: 2026E | AQ6: 2027E | AR6: 2028E | AS6: 2029E | AT6: 2030E | AU6: 2031E | AV6: Modelling Notes | AX6: 5Y CAGR | AY6: 5Y CAGR | AZ6: 10Y CAGR | BA6: 14Y CAGR
AX7: 26-'31 | AY7: 20-'25 | AZ7: 15-'25 | BA7: 11-'25
B8: SEGMENT P&L — AEROSPACE · INDUSTRIAL (sales by primary market × segment earnings margin) | AV8: SEGMENT BUILD — modelling logic (sales by primary market → segment sales → segment earnings at the segment margin → + adjusted nonsegment expenses = adjusted EBIT → GAAP P&L)
BD9: SCENARIO INPUT TABLE — driver assumptions per Bull / Base / Bear | BE9: Bull | BF9: Base | BG9: Bear | BH9: Bull / Bear = Base + Δ (Δ inputs on each block header). Outlook block = high / mid / low end of the FY26 guidance ranges.
B10: Aerospace (fuel, combustion, actuation, motion & flight-control systems for commercial and defense aircraft, guided weapons; OEM and aftermarket) | AV10: AEROSPACE — modelling logic
B11: Commercial OEM sales | K11: 659.336 | L11: 434.306 | M11: 76.081 | N11: 101.907 | O11: 96.29 | P11: 112.265 | Q11: 386.543 | R11: 104.826 | S11: 122.889 | T11: 131.968 | U11: 139.755 | V11: 499.438 | W11: 138.875 | X11: 159.271 | Y11: 186.173 | Z11: 166.956 | AA11: 651.275 | AB11: 171.354 | AC11: 183.517 | AD11: 189.697 | AE11: 193.826 | AF11: 738.394 | AG11: 154.076 | AH11: 167.461 | AI11: 175.226 | AJ11: 194.199 | AK11: 690.962 | AL11: 187.939 | AM11: 218.015 | AN11: 234.398 | AO11: =AJ11*(1+AO12) -> 230.99782 | AP11: =SUM(AL11:AO11) -> 871.34982 | AQ11: =AP11*(1+AQ12) -> 993.33879 | AR11: =AQ11*(1+AR12) -> 1102.6061 | AS11: =AR11*(1+AS12) -> 1201.8406 | AT11: =AS11*(1+AT12) -> 1285.9695 | AU11: =AT11*(1+AU12) -> 1363.1276 | AV11: Sales by primary market (10-Q / 10-K revenue-disaggregation note, from FY2019; Q4 = fiscal year − nine months). Q4/26E: prior-year quarter × (1 + growth). 2027E+: prior year × (1 + scenario lever). | AX11: =IFERROR((AU11/AP11)^(1/5)-1,"n/m") -> 0.093625918 | AY11: =IFERROR((AK11/L11)^(1/5)-1,"n/m") -> 0.097315887 | AZ11: =IFERROR((AK11/G11)^(1/10)-1,"n/m") -> n/m | BA11: =IFERROR((AK11/C11)^(1/14)-1,"n/m") -> n/m | BD11: FY26 guidance — Q3 FY26 release (29-Jul-2026) | BE11: High | BF11: Mid | BG11: Low | BH11: Sales growth +20–23% (unchanged), adjusted EPS $9.30–9.50 (raised from $9.15–9.45), FCF $300–350m, capex ~$290m, ~61.5m shares, adjusted tax rate ~22.5%; Aerospace sales +21–23% at ~23.5% segment margin; Industrial sales +19–21% at ~19%.
B12: y/y % | D12: =IF(AND(ISNUMBER(D11),ISNUMBER(C11)),IFERROR(D11/C11-1,""),"") | E12: =IF(AND(ISNUMBER(E11),ISNUMBER(D11)),IFERROR(E11/D11-1,""),"") | F12: =IF(AND(ISNUMBER(F11),ISNUMBER(E11)),IFERROR(F11/E11-1,""),"") | G12: =IF(AND(ISNUMBER(G11),ISNUMBER(F11)),IFERROR(G11/F11-1,""),"") | H12: =IF(AND(ISNUMBER(H11),ISNUMBER(G11)),IFERROR(H11/G11-1,""),"") | I12: =IF(AND(ISNUMBER(I11),ISNUMBER(H11)),IFERROR(I11/H11-1,""),"") | J12: =IF(AND(ISNUMBER(J11),ISNUMBER(I11)),IFERROR(J11/I11-1,""),"") | K12: =IF(AND(ISNUMBER(K11),ISNUMBER(J11)),IFERROR(K11/J11-1,""),"") | L12: =IF(AND(ISNUMBER(L11),ISNUMBER(K11)),IFERROR(L11/K11-1,""),"") -> -0.34129791 | Q12: =IF(AND(ISNUMBER(Q11),ISNUMBER(L11)),IFERROR(Q11/L11-1,""),"") -> -0.10997546 | R12: =IF(AND(ISNUMBER(R11),ISNUMBER(M11)),IFERROR(R11/M11-1,""),"") -> 0.37782101 | S12: =IF(AND(ISNUMBER(S11),ISNUMBER(N11)),IFERROR(S11/N11-1,""),"") -> 0.20589361 | T12: =IF(AND(ISNUMBER(T11),ISNUMBER(O11)),IFERROR(T11/O11-1,""),"") -> 0.37052653 | U12: =IF(AND(ISNUMBER(U11),ISNUMBER(P11)),IFERROR(U11/P11-1,""),"") -> 0.24486706 | V12: =IF(AND(ISNUMBER(V11),ISNUMBER(Q11)),IFERROR(V11/Q11-1,""),"") -> 0.29206324 | W12: =IF(AND(ISNUMBER(W11),ISNUMBER(R11)),IFERROR(W11/R11-1,""),"") -> 0.32481445 | X12: =IF(AND(ISNUMBER(X11),ISNUMBER(S11)),IFERROR(X11/S11-1,""),"") -> 0.29605579 | ... AN12: =IF(AND(ISNUMBER(AN11),ISNUMBER(AI11)),IFERROR(AN11/AI11-1,""),"") -> 0.33768961 | AO12: =AO13+$AO$109 -> 0.18949026 | AP12: =IF(AND(ISNUMBER(AP11),ISNUMBER(AK11)),IFERROR(AP11/AK11-1,""),"") -> 0.26106764 | AQ12: =CHOOSE(MATCH($AV$2,{"Bull","Base","Bear"},0),$BE$34,$BF$34,$BG$34) -> 0.14 | AR12: =CHOOSE(MATCH($AV$2,{"Bull","Base","Bear"},0),$BE$35,$BF$35,$BG$35) -> 0.11 | AS12: =CHOOSE(MATCH($AV$2,{"Bull","Base","Bear"},0),$BE$36,$BF$36,$BG$36) -> 0.09 | AT12: =CHOOSE(MATCH($AV$2,{"Bull","Base","Bear"},0),$BE$37,$BF$37,$BG$37) -> 0.07 | AU12: =CHOOSE(MATCH($AV$2,{"Bull","Base","Bear"},0),$BE$38,$BF$38,$BG$38) -> 0.06 | AV12: Q4/26E: 9M FY26 y/y growth of the market + sales-guidance calibration Δ (Group block). 2027E–2031E: scenario lever (Bull/Base/Bear table →). | BD12: FY26 net sales growth | BE12: 0.23 | BF12: 0.215 | BG12: 0.2 | BH12: Guided +20–23%. Drives the Q4/26E sales calibration.
B13: Q4/26E growth before sales calibration (9M FY26 y/y) | AO13: =IFERROR(SUM(AL11:AN11)/SUM(AG11:AI11)-1,0) -> 0.28904931 | BD13: FY26 adjusted EPS ($) | BE13: 9.5 | BF13: 9.4 | BG13: 9.3 | BH13: Guided $9.30–9.50. Drives the Q4/26E segment-margin calibration.
B14: Commercial services (aftermarket) sales | K14: 497.795 | L14: 399.843 | M14: 65.515 | N14: 77.579 | O14: 75.508 | P14: 87.945 | Q14: 306.547 | R14: 86.086 | S14: 108.554 | T14: 108.695 | U14: 117.546 | V14: 420.881 | W14: 126.643 | X14: 139.445 | Y14: 139.518 | Z14: 142.019 | AA14: 547.625 | AB14: 137.544 | AC14: 163.886 | AD14: 165.718 | AE14: 173.675 | AF14: 640.823 | AG14: 163.85 | AH14: 201.861 | AI14: 215.451 | AJ14: 242.385 | AK14: 823.547 | AL14: 244.906 | AM14: 275.374 | AN14: 267.849 | AO14: =AJ14*(1+AO15) -> 304.57302 | AP14: =SUM(AL14:AO14) -> 1092.702 | AQ14: =AP14*(1+AQ15) -> 1191.0452 | AR14: =AQ14*(1+AR15) -> 1286.3288 | AS14: =AR14*(1+AS15) -> 1376.3718 | AT14: =AS14*(1+AT15) -> 1458.9542 | AU14: =AT14*(1+AU15) -> 1546.4914 | AX14: =IFERROR((AU14/AP14)^(1/5)-1,"n/m") -> 0.07193673 | AY14: =IFERROR((AK14/L14)^(1/5)-1,"n/m") -> 0.15547294 | AZ14: =IFERROR((AK14/G14)^(1/10)-1,"n/m") -> n/m | BA14: =IFERROR((AK14/C14)^(1/14)-1,"n/m") -> n/m | BD14: FY26 Aerospace sales growth — memo | BE14: 0.23 | BF14: 0.22 | BG14: 0.21 | BH14: Guided +21–23% (information row; compare the model).
B15: y/y % | D15: =IF(AND(ISNUMBER(D14),ISNUMBER(C14)),IFERROR(D14/C14-1,""),"") | E15: =IF(AND(ISNUMBER(E14),ISNUMBER(D14)),IFERROR(E14/D14-1,""),"") | F15: =IF(AND(ISNUMBER(F14),ISNUMBER(E14)),IFERROR(F14/E14-1,""),"") | G15: =IF(AND(ISNUMBER(G14),ISNUMBER(F14)),IFERROR(G14/F14-1,""),"") | H15: =IF(AND(ISNUMBER(H14),ISNUMBER(G14)),IFERROR(H14/G14-1,""),"") | I15: =IF(AND(ISNUMBER(I14),ISNUMBER(H14)),IFERROR(I14/H14-1,""),"") | J15: =IF(AND(ISNUMBER(J14),ISNUMBER(I14)),IFERROR(J14/I14-1,""),"") | K15: =IF(AND(ISNUMBER(K14),ISNUMBER(J14)),IFERROR(K14/J14-1,""),"") | L15: =IF(AND(ISNUMBER(L14),ISNUMBER(K14)),IFERROR(L14/K14-1,""),"") -> -0.19677176 | Q15: =IF(AND(ISNUMBER(Q14),ISNUMBER(L14)),IFERROR(Q14/L14-1,""),"") -> -0.23333158 | R15: =IF(AND(ISNUMBER(R14),ISNUMBER(M14)),IFERROR(R14/M14-1,""),"") -> 0.31398916 | S15: =IF(AND(ISNUMBER(S14),ISNUMBER(N14)),IFERROR(S14/N14-1,""),"") -> 0.39927042 | T15: =IF(AND(ISNUMBER(T14),ISNUMBER(O14)),IFERROR(T14/O14-1,""),"") -> 0.43951634 | U15: =IF(AND(ISNUMBER(U14),ISNUMBER(P14)),IFERROR(U14/P14-1,""),"") -> 0.33658537 | V15: =IF(AND(ISNUMBER(V14),ISNUMBER(Q14)),IFERROR(V14/Q14-1,""),"") -> 0.3729738 | W15: =IF(AND(ISNUMBER(W14),ISNUMBER(R14)),IFERROR(W14/R14-1,""),"") -> 0.4711219 | X15: =IF(AND(ISNUMBER(X14),ISNUMBER(S14)),IFERROR(X14/S14-1,""),"") -> 0.28456805 | ... AN15: =IF(AND(ISNUMBER(AN14),ISNUMBER(AI14)),IFERROR(AN14/AI14-1,""),"") -> 0.24320147 | AO15: =AO16+$AO$109 -> 0.25656713 | AP15: =IF(AND(ISNUMBER(AP14),ISNUMBER(AK14)),IFERROR(AP14/AK14-1,""),"") -> 0.32682412 | AQ15: =CHOOSE(MATCH($AV$2,{"Bull","Base","Bear"},0),$BE$40,$BF$40,$BG$40) -> 0.09 | AR15: =CHOOSE(MATCH($AV$2,{"Bull","Base","Bear"},0),$BE$41,$BF$41,$BG$41) -> 0.08 | AS15: =CHOOSE(MATCH($AV$2,{"Bull","Base","Bear"},0),$BE$42,$BF$42,$BG$42) -> 0.07 | AT15: =CHOOSE(MATCH($AV$2,{"Bull","Base","Bear"},0),$BE$43,$BF$43,$BG$43) -> 0.06 | AU15: =CHOOSE(MATCH($AV$2,{"Bull","Base","Bear"},0),$BE$44,$BF$44,$BG$44) -> 0.06 | BD15: FY26 Industrial sales growth — memo | BE15: 0.21 | BF15: 0.2 | BG15: 0.19 | BH15: Guided +19–21% (information row).
B16: Q4/26E growth before sales calibration (9M FY26 y/y) | AO16: =IFERROR(SUM(AL14:AN14)/SUM(AG14:AI14)-1,0) -> 0.35612617 | BD16: FY26 free cash flow ($m) — memo | BE16: 350 | BF16: 325 | BG16: 300 | BH16: Guided $300–350m (information row).
B17: Defense OEM sales | K17: 529.94 | L17: 526.264 | M17: 131.263 | N17: 135.63 | O17: 117.204 | P17: 125.718 | Q17: 509.815 | R17: 105.375 | S17: 97.812 | T17: 115.205 | U17: 103.624 | V17: 422.016 | W17: 89.762 | X17: 87.807 | Y17: 101.008 | Z17: 90.076 | AA17: 368.653 | AB17: 93.425 | AC17: 91.017 | AD17: 96.557 | AE17: 125.811 | AF17: 406.81 | AG17: 112.782 | AH17: 137.928 | AI17: 150.358 | AJ17: 160.22 | AK17: 561.288 | AL17: 138.233 | AM17: 150.932 | AN17: 140.725 | AO17: =AJ17*(1+AO18) -> 155.78256 | AP17: =SUM(AL17:AO17) -> 585.67256 | AQ17: =AP17*(1+AQ18) -> 626.66964 | AR17: =AQ17*(1+AR18) -> 664.26982 | AS17: =AR17*(1+AS18) -> 697.48331 | AT17: =AS17*(1+AT18) -> 732.35747 | AU17: =AT17*(1+AU18) -> 768.97535 | AX17: =IFERROR((AU17/AP17)^(1/5)-1,"n/m") -> 0.055969825 | AY17: =IFERROR((AK17/L17)^(1/5)-1,"n/m") -> 0.012969616 | AZ17: =IFERROR((AK17/G17)^(1/10)-1,"n/m") -> n/m | BA17: =IFERROR((AK17/C17)^(1/14)-1,"n/m") -> n/m | BD17: Q4/26E share repurchases ($m) | BE17: 300 | BF17: 200 | BG17: 100 | BH17: 9M FY26 $553.4m ($198m in Q3); $1,286m left on the $1.8bn 2026 Authorization at 30-Jun-2026.
B18: y/y % | D18: =IF(AND(ISNUMBER(D17),ISNUMBER(C17)),IFERROR(D17/C17-1,""),"") | E18: =IF(AND(ISNUMBER(E17),ISNUMBER(D17)),IFERROR(E17/D17-1,""),"") | F18: =IF(AND(ISNUMBER(F17),ISNUMBER(E17)),IFERROR(F17/E17-1,""),"") | G18: =IF(AND(ISNUMBER(G17),ISNUMBER(F17)),IFERROR(G17/F17-1,""),"") | H18: =IF(AND(ISNUMBER(H17),ISNUMBER(G17)),IFERROR(H17/G17-1,""),"") | I18: =IF(AND(ISNUMBER(I17),ISNUMBER(H17)),IFERROR(I17/H17-1,""),"") | J18: =IF(AND(ISNUMBER(J17),ISNUMBER(I17)),IFERROR(J17/I17-1,""),"") | K18: =IF(AND(ISNUMBER(K17),ISNUMBER(J17)),IFERROR(K17/J17-1,""),"") | L18: =IF(AND(ISNUMBER(L17),ISNUMBER(K17)),IFERROR(L17/K17-1,""),"") -> -0.0069366343 | Q18: =IF(AND(ISNUMBER(Q17),ISNUMBER(L17)),IFERROR(Q17/L17-1,""),"") -> -0.031256176 | R18: =IF(AND(ISNUMBER(R17),ISNUMBER(M17)),IFERROR(R17/M17-1,""),"") -> -0.19722237 | S18: =IF(AND(ISNUMBER(S17),ISNUMBER(N17)),IFERROR(S17/N17-1,""),"") -> -0.27883212 | T18: =IF(AND(ISNUMBER(T17),ISNUMBER(O17)),IFERROR(T17/O17-1,""),"") -> -0.017055732 | U18: =IF(AND(ISNUMBER(U17),ISNUMBER(P17)),IFERROR(U17/P17-1,""),"") -> -0.17574253 | V18: =IF(AND(ISNUMBER(V17),ISNUMBER(Q17)),IFERROR(V17/Q17-1,""),"") -> -0.17221737 | W18: =IF(AND(ISNUMBER(W17),ISNUMBER(R17)),IFERROR(W17/R17-1,""),"") -> -0.14816607 | X18: =IF(AND(ISNUMBER(X17),ISNUMBER(S17)),IFERROR(X17/S17-1,""),"") -> -0.10228806 | ... AN18: =IF(AND(ISNUMBER(AN17),ISNUMBER(AI17)),IFERROR(AN17/AI17-1,""),"") -> -0.064067093 | AO18: =AO19+$AO$109 -> -0.027695915 | AP18: =IF(AND(ISNUMBER(AP17),ISNUMBER(AK17)),IFERROR(AP17/AK17-1,""),"") -> 0.043443937 | AQ18: =CHOOSE(MATCH($AV$2,{"Bull","Base","Bear"},0),$BE$46,$BF$46,$BG$46) -> 0.07 | AR18: =CHOOSE(MATCH($AV$2,{"Bull","Base","Bear"},0),$BE$47,$BF$47,$BG$47) -> 0.06 | AS18: =CHOOSE(MATCH($AV$2,{"Bull","Base","Bear"},0),$BE$48,$BF$48,$BG$48) -> 0.05 | AT18: =CHOOSE(MATCH($AV$2,{"Bull","Base","Bear"},0),$BE$49,$BF$49,$BG$49) -> 0.05 | AU18: =CHOOSE(MATCH($AV$2,{"Bull","Base","Bear"},0),$BE$50,$BF$50,$BG$50) -> 0.05
B19: Q4/26E growth before sales calibration (9M FY26 y/y) | AO19: =IFERROR(SUM(AL17:AN17)/SUM(AG17:AI17)-1,0) -> 0.071863125 | BD19: Q4/26E and FY26 point estimates (all cases)
B20: Defense services (aftermarket) sales | K20: 193.449 | L20: 230.55 | M20: 48.808 | N20: 49.59 | O20: 51.91 | P20: 50.904 | Q20: 201.212 | R20: 40.148 | S20: 43.502 | T20: 45.844 | U20: 47.493 | V20: 176.987 | W20: 40.405 | X20: 50.494 | Y20: 53.832 | Z20: 55.819 | AA20: 200.55 | AB20: 58.433 | AC20: 59.092 | AD20: 65.588 | AE20: 59.478 | AF20: 242.591 | AG20: 63.174 | AH20: 54.479 | AI20: 54.955 | AJ20: 64.401 | AK20: 237.009 | AL20: 63.819 | AM20: 59 | AN20: 65.701 | AO20: =AJ20*(1+AO21) -> 63.926153 | AP20: =SUM(AL20:AO20) -> 252.44615 | AQ20: =AP20*(1+AQ21) -> 265.06846 | AR20: =AQ20*(1+AR21) -> 278.32188 | AS20: =AR20*(1+AS21) -> 289.45476 | AT20: =AS20*(1+AT21) -> 301.03295 | AU20: =AT20*(1+AU21) -> 313.07427 | AX20: =IFERROR((AU20/AP20)^(1/5)-1,"n/m") -> 0.04398852 | AY20: =IFERROR((AK20/L20)^(1/5)-1,"n/m") -> 0.0055413682 | AZ20: =IFERROR((AK20/G20)^(1/10)-1,"n/m") -> n/m | BA20: =IFERROR((AK20/C20)^(1/14)-1,"n/m") -> n/m | BD20: Q4/26E interest expense ($m) | BF20: 15.5 | BH20: Not guided; Q3 $14.8m; full quarter of the $250m term loan and the revolver (~$1.35bn debt at ~4.6%).
B21: y/y % | D21: =IF(AND(ISNUMBER(D20),ISNUMBER(C20)),IFERROR(D20/C20-1,""),"") | E21: =IF(AND(ISNUMBER(E20),ISNUMBER(D20)),IFERROR(E20/D20-1,""),"") | F21: =IF(AND(ISNUMBER(F20),ISNUMBER(E20)),IFERROR(F20/E20-1,""),"") | G21: =IF(AND(ISNUMBER(G20),ISNUMBER(F20)),IFERROR(G20/F20-1,""),"") | H21: =IF(AND(ISNUMBER(H20),ISNUMBER(G20)),IFERROR(H20/G20-1,""),"") | I21: =IF(AND(ISNUMBER(I20),ISNUMBER(H20)),IFERROR(I20/H20-1,""),"") | J21: =IF(AND(ISNUMBER(J20),ISNUMBER(I20)),IFERROR(J20/I20-1,""),"") | K21: =IF(AND(ISNUMBER(K20),ISNUMBER(J20)),IFERROR(K20/J20-1,""),"") | L21: =IF(AND(ISNUMBER(L20),ISNUMBER(K20)),IFERROR(L20/K20-1,""),"") -> 0.19178698 | Q21: =IF(AND(ISNUMBER(Q20),ISNUMBER(L20)),IFERROR(Q20/L20-1,""),"") -> -0.12725222 | R21: =IF(AND(ISNUMBER(R20),ISNUMBER(M20)),IFERROR(R20/M20-1,""),"") -> -0.17742993 | S21: =IF(AND(ISNUMBER(S20),ISNUMBER(N20)),IFERROR(S20/N20-1,""),"") -> -0.12276669 | T21: =IF(AND(ISNUMBER(T20),ISNUMBER(O20)),IFERROR(T20/O20-1,""),"") -> -0.1168561 | U21: =IF(AND(ISNUMBER(U20),ISNUMBER(P20)),IFERROR(U20/P20-1,""),"") -> -0.067008487 | V21: =IF(AND(ISNUMBER(V20),ISNUMBER(Q20)),IFERROR(V20/Q20-1,""),"") -> -0.1203954 | W21: =IF(AND(ISNUMBER(W20),ISNUMBER(R20)),IFERROR(W20/R20-1,""),"") -> 0.0064013151 | X21: =IF(AND(ISNUMBER(X20),ISNUMBER(S20)),IFERROR(X20/S20-1,""),"") -> 0.16072824 | ... AN21: =IF(AND(ISNUMBER(AN20),ISNUMBER(AI20)),IFERROR(AN20/AI20-1,""),"") -> 0.19554181 | AO21: =AO22+$AO$109 -> -0.0073732784 | AP21: =IF(AND(ISNUMBER(AP20),ISNUMBER(AK20)),IFERROR(AP20/AK20-1,""),"") -> 0.065133195 | AQ21: =CHOOSE(MATCH($AV$2,{"Bull","Base","Bear"},0),$BE$52,$BF$52,$BG$52) -> 0.05 | AR21: =CHOOSE(MATCH($AV$2,{"Bull","Base","Bear"},0),$BE$53,$BF$53,$BG$53) -> 0.05 | AS21: =CHOOSE(MATCH($AV$2,{"Bull","Base","Bear"},0),$BE$54,$BF$54,$BG$54) -> 0.04 | AT21: =CHOOSE(MATCH($AV$2,{"Bull","Base","Bear"},0),$BE$55,$BF$55,$BG$55) -> 0.04 | AU21: =CHOOSE(MATCH($AV$2,{"Bull","Base","Bear"},0),$BE$56,$BF$56,$BG$56) -> 0.04 | BD21: Q4/26E interest income ($m) | BF21: 0.6 | BH21: Q3 $0.6m.
B22: Q4/26E growth before sales calibration (9M FY26 y/y) | AO22: =IFERROR(SUM(AL20:AN20)/SUM(AG20:AI20)-1,0) -> 0.092185762 | BD22: Q4/26E other income, net ($m) | BF22: 20 | BH22: 9M FY26 $60.3m (~$20m a quarter; no divestiture gains).
B23: Aerospace — segment net sales | C23: =IF(ISNUMBER(C11),C11+C14+C17+C20,C27) -> 843.032 | D23: =IF(ISNUMBER(D11),D11+D14+D17+D20,D27) -> 896.083 | E23: =IF(ISNUMBER(E11),E11+E14+E17+E20,E27) -> 1061.477 | F23: =IF(ISNUMBER(F11),F11+F14+F17+F20,F27) -> 1084.025 | G23: =IF(ISNUMBER(G11),G11+G14+G17+G20,G27) -> 1160.883 | H23: =IF(ISNUMBER(H11),H11+H14+H17+H20,H27) -> 1233.176 | I23: =IF(ISNUMBER(I11),I11+I14+I17+I20,I27) -> 1342.339 | J23: =IF(ISNUMBER(J11),J11+J14+J17+J20,J27) -> 1557.988 | ... AN23: =IF(ISNUMBER(AN11),AN11+AN14+AN17+AN20,AN27) -> 708.673 | AO23: =AO11+AO14+AO17+AO20 -> 755.27956 | AP23: =AP11+AP14+AP17+AP20 -> 2802.1706 | AQ23: =AQ11+AQ14+AQ17+AQ20 -> 3076.1221 | AR23: =AR11+AR14+AR17+AR20 -> 3331.5266 | AS23: =AS11+AS14+AS17+AS20 -> 3565.1505 | AT23: =AT11+AT14+AT17+AT20 -> 3778.314 | AU23: =AU11+AU14+AU17+AU20 -> 3991.6686 | AV23: History: Σ primary markets where published, otherwise segment net sales as reported. | AX23: =IFERROR((AU23/AP23)^(1/5)-1,"n/m") -> 0.073326824 | AY23: =IFERROR((AK23/L23)^(1/5)-1,"n/m") -> 0.077694894 | AZ23: =IFERROR((AK23/G23)^(1/10)-1,"n/m") -> 0.071359131 | BA23: =IFERROR((AK23/C23)^(1/14)-1,"n/m") -> 0.074748372 | BD23: Q4/26E amortization of intangibles ($m) | BF23: 8.448 | BH23: Q3 FY26 10-Q schedule: $8.4m remaining in FY26.
B24: Segment sales y/y % | D24: =IF(AND(ISNUMBER(D23),ISNUMBER(C23)),IFERROR(D23/C23-1,""),"") -> 0.062928809 | E24: =IF(AND(ISNUMBER(E23),ISNUMBER(D23)),IFERROR(E23/D23-1,""),"") -> 0.18457442 | F24: =IF(AND(ISNUMBER(F23),ISNUMBER(E23)),IFERROR(F23/E23-1,""),"") -> 0.021242099 | G24: =IF(AND(ISNUMBER(G23),ISNUMBER(F23)),IFERROR(G23/F23-1,""),"") -> 0.070900579 | H24: =IF(AND(ISNUMBER(H23),ISNUMBER(G23)),IFERROR(H23/G23-1,""),"") -> 0.062274148 | I24: =IF(AND(ISNUMBER(I23),ISNUMBER(H23)),IFERROR(I23/H23-1,""),"") -> 0.088521833 | J24: =IF(AND(ISNUMBER(J23),ISNUMBER(I23)),IFERROR(J23/I23-1,""),"") -> 0.16065167 | K24: =IF(AND(ISNUMBER(K23),ISNUMBER(J23)),IFERROR(K23/J23-1,""),"") -> 0.20701828 | L24: =IF(AND(ISNUMBER(L23),ISNUMBER(K23)),IFERROR(L23/K23-1,""),"") -> -0.15397709 | Q24: =IF(AND(ISNUMBER(Q23),ISNUMBER(L23)),IFERROR(Q23/L23-1,""),"") -> -0.11744208 | R24: =IF(AND(ISNUMBER(R23),ISNUMBER(M23)),IFERROR(R23/M23-1,""),"") -> 0.045910833 | S24: =IF(AND(ISNUMBER(S23),ISNUMBER(N23)),IFERROR(S23/N23-1,""),"") -> 0.022075315 | T24: =IF(AND(ISNUMBER(T23),ISNUMBER(O23)),IFERROR(T23/O23-1,""),"") -> 0.17834514 | U24: =IF(AND(ISNUMBER(U23),ISNUMBER(P23)),IFERROR(U23/P23-1,""),"") -> 0.083819845 | V24: =IF(AND(ISNUMBER(V23),ISNUMBER(Q23)),IFERROR(V23/Q23-1,""),"") -> 0.082048006 | W24: =IF(AND(ISNUMBER(W23),ISNUMBER(R23)),IFERROR(W23/R23-1,""),"") -> 0.17611128 | X24: =IF(AND(ISNUMBER(X23),ISNUMBER(S23)),IFERROR(X23/S23-1,""),"") -> 0.17239113 | ... AP24: =IF(AND(ISNUMBER(AP23),ISNUMBER(AK23)),IFERROR(AP23/AK23-1,""),"") -> 0.21158911 | AQ24: =IF(AND(ISNUMBER(AQ23),ISNUMBER(AP23)),IFERROR(AQ23/AP23-1,""),"") -> 0.09776405 | AR24: =IF(AND(ISNUMBER(AR23),ISNUMBER(AQ23)),IFERROR(AR23/AQ23-1,""),"") -> 0.083028071 | AS24: =IF(AND(ISNUMBER(AS23),ISNUMBER(AR23)),IFERROR(AS23/AR23-1,""),"") -> 0.070125188 | AT24: =IF(AND(ISNUMBER(AT23),ISNUMBER(AS23)),IFERROR(AT23/AS23-1,""),"") -> 0.059790886 | AU24: =IF(AND(ISNUMBER(AU23),ISNUMBER(AT23)),IFERROR(AU23/AT23-1,""),"") -> 0.056468204 | BD24: Q4/26E depreciation ($m) | BF24: 23 | BH24: Q3 $22.5m; rising with capex.
B25: % of total net sales | C25: =IF(AND(ISNUMBER(C23),ISNUMBER(C99)),IFERROR(C23/C99,""),"") -> 0.49251096 | D25: =IF(AND(ISNUMBER(D23),ISNUMBER(D99)),IFERROR(D23/D99,""),"") -> 0.48031198 | E25: =IF(AND(ISNUMBER(E23),ISNUMBER(E99)),IFERROR(E23/E99,""),"") -> 0.54829037 | F25: =IF(AND(ISNUMBER(F23),ISNUMBER(F99)),IFERROR(F23/F99,""),"") -> 0.54167666 | G25: =IF(AND(ISNUMBER(G23),ISNUMBER(G99)),IFERROR(G23/G99,""),"") -> 0.56953407 | H25: =IF(AND(ISNUMBER(H23),ISNUMBER(H99)),IFERROR(H23/H99,""),"") -> 0.60955435 | I25: =IF(AND(ISNUMBER(I23),ISNUMBER(I99)),IFERROR(I23/I99,""),"") -> 0.63960957 | J25: =IF(AND(ISNUMBER(J23),ISNUMBER(J99)),IFERROR(J23/J99,""),"") -> 0.66985085 | ... AU25: =IF(AND(ISNUMBER(AU23),ISNUMBER(AU99)),IFERROR(AU23/AU99,""),"") -> 0.65185919 | BD25: Q4/26E tax rate (GAAP & adjusted) | BF25: 0.24 | BH25: FY26 adjusted rate guided ~22.5%; 9M FY26 adjusted 21.9% → Q4 ~24% (Q3 24.2%).
B26: Aftermarket (commercial + defense services) % of Aerospace sales | C26: =IF(ISNUMBER(C14),IFERROR((C14+C20)/C23,""),"") | D26: =IF(ISNUMBER(D14),IFERROR((D14+D20)/D23,""),"") | E26: =IF(ISNUMBER(E14),IFERROR((E14+E20)/E23,""),"") | F26: =IF(ISNUMBER(F14),IFERROR((F14+F20)/F23,""),"") | G26: =IF(ISNUMBER(G14),IFERROR((G14+G20)/G23,""),"") | H26: =IF(ISNUMBER(H14),IFERROR((H14+H20)/H23,""),"") | I26: =IF(ISNUMBER(I14),IFERROR((I14+I20)/I23,""),"") | J26: =IF(ISNUMBER(J14),IFERROR((J14+J20)/J23,""),"") | ... AU26: =IF(ISNUMBER(AU14),IFERROR((AU14+AU20)/AU23,""),"") -> 0.46586173 | AX26: =IFERROR(AVERAGE(AQ26,AR26,AS26,AT26,AU26),"n/m") -> 0.46838746 | AY26: =IFERROR(AVERAGE(Q26,V26,AA26,AF26,AK26),"n/m") -> 0.41446329 | AZ26: =IFERROR(AVERAGE(H26,I26,J26,K26,L26,Q26,V26,AA26,AF26,AK26),"n/m") -> 0.40516163 | BA26: =IFERROR(AVERAGE(C26,D26,E26,F26,G26,H26,I26,J26,K26,L26,Q26,V26,AA26,AF26,AK26),"n/m") -> 0.40516163 | BD26: FY26 capital expenditures ($m) | BF26: 290 | BH26: Guided ~$290m (9M $156.3m); Spartanburg, SC campus.
B27: Memo: Aerospace segment net sales as reported (segment schedule) | C27: 843.032 | D27: 896.083 | E27: 1061.477 | F27: 1084.025 | G27: 1160.883 | H27: 1233.176 | I27: 1342.339 | J27: 1557.988 | K27: 1880.52 | L27: 1590.963 | M27: 321.667 | N27: 364.706 | O27: 340.912 | P27: 376.832 | Q27: 1404.117 | R27: 336.435 | S27: 372.757 | T27: 401.712 | U27: 408.418 | V27: 1519.322 | W27: 395.685 | X27: 437.017 | Y27: 480.531 | Z27: 454.87 | AA27: 1768.103 | AB27: 460.756 | AC27: 497.512 | AD27: 517.56 | AE27: 552.79 | AF27: 2028.618 | AG27: 493.882 | AH27: 561.729 | AI27: 595.99 | AJ27: 661.205 | AK27: 2312.806 | AL27: 634.897 | AM27: 703.321 | AN27: 708.673 | BD27: Q4/26E restructuring charges ($m) | BF27: 6 | BH27: China OH wind-down complete; servo-valve transition (~$15m total) and the start of the Santa Clarita plan (8-K 21-Sep-2026).
B28: Check: primary markets vs segment net sales (should be 0) | C28: =IF(AND(ISNUMBER(C11),ISNUMBER(C27)),IF(ABS(C23-C27)<=0.15,0,ROUND(C23-C27,1)),"") | D28: =IF(AND(ISNUMBER(D11),ISNUMBER(D27)),IF(ABS(D23-D27)<=0.15,0,ROUND(D23-D27,1)),"") | E28: =IF(AND(ISNUMBER(E11),ISNUMBER(E27)),IF(ABS(E23-E27)<=0.15,0,ROUND(E23-E27,1)),"") | F28: =IF(AND(ISNUMBER(F11),ISNUMBER(F27)),IF(ABS(F23-F27)<=0.15,0,ROUND(F23-F27,1)),"") | G28: =IF(AND(ISNUMBER(G11),ISNUMBER(G27)),IF(ABS(G23-G27)<=0.15,0,ROUND(G23-G27,1)),"") | H28: =IF(AND(ISNUMBER(H11),ISNUMBER(H27)),IF(ABS(H23-H27)<=0.15,0,ROUND(H23-H27,1)),"") | I28: =IF(AND(ISNUMBER(I11),ISNUMBER(I27)),IF(ABS(I23-I27)<=0.15,0,ROUND(I23-I27,1)),"") | J28: =IF(AND(ISNUMBER(J11),ISNUMBER(J27)),IF(ABS(J23-J27)<=0.15,0,ROUND(J23-J27,1)),"") | ... AN28: =IF(AND(ISNUMBER(AN11),ISNUMBER(AN27)),IF(ABS(AN23-AN27)<=0.15,0,ROUND(AN23-AN27,1)),"") -> 0 | BD28: FY26 Aerospace segment margin guidance | BF28: 0.235 | BH28: Guided ~23.5% (information row).
B29: Aerospace segment earnings | C29: 129.502 | D29: 130.192 | E29: 166.122 | F29: 159.2 | G29: 187.747 | H29: 232.166 | I29: 257.813 | J29: 301.803 | K29: 389.126 | L29: 310.137 | M29: 46.466 | N29: 69.008 | O29: 53.167 | P29: 65.715 | Q29: 234.356 | R29: 51.083 | S29: 59.809 | T29: 56.566 | U29: 63.475 | V29: 230.933 | W29: 55.434 | X29: 73.314 | Y29: 83.075 | Z29: 78.281 | AA29: 290.104 | AB29: 79.002 | AC29: 98.451 | AD29: 101.842 | AE29: 106.065 | AF29: 385.36 | AG29: 94.725 | AH29: 124.616 | AI29: 125.74 | AJ29: 161.532 | AK29: 506.613 | AL29: 148.395 | AM29: 158.075 | AN29: 170.02 | AO29: =AO23*AO30 -> 185.66086 | AP29: =SUM(AL29:AO29) -> 662.15086 | AQ29: =AQ23*AQ30 -> 738.2693 | AR29: =AR23*AR30 -> 816.22401 | AS29: =AS23*AS30 -> 891.28763 | AT29: =AT23*AT30 -> 955.91345 | AU29: =AU23*AU30 -> 1017.8755 | AV29: Segment earnings as reported (company measure: after amortization of intangibles; excludes nonsegment expenses). Forecast = segment sales × segment margin. | AX29: =IFERROR((AU29/AP29)^(1/5)-1,"n/m") -> 0.089801857 | AY29: =IFERROR((AK29/L29)^(1/5)-1,"n/m") -> 0.10312455 | AZ29: =IFERROR((AK29/G29)^(1/10)-1,"n/m") -> 0.10435915 | BA29: =IFERROR((AK29/C29)^(1/14)-1,"n/m") -> 0.10233672 | BD29: FY26 Industrial segment margin guidance | BF29: 0.19 | BH29: Guided ~19% (information row).
B30: Segment margin % | C30: =IF(AND(ISNUMBER(C29),ISNUMBER(C23)),IFERROR(C29/C23,""),"") -> 0.15361457 | D30: =IF(AND(ISNUMBER(D29),ISNUMBER(D23)),IFERROR(D29/D23,""),"") -> 0.14529011 | E30: =IF(AND(ISNUMBER(E29),ISNUMBER(E23)),IFERROR(E29/E23,""),"") -> 0.1565008 | F30: =IF(AND(ISNUMBER(F29),ISNUMBER(F23)),IFERROR(F29/F23,""),"") -> 0.14686008 | G30: =IF(AND(ISNUMBER(G29),ISNUMBER(G23)),IFERROR(G29/G23,""),"") -> 0.16172775 | H30: =IF(AND(ISNUMBER(H29),ISNUMBER(H23)),IFERROR(H29/H23,""),"") -> 0.18826672 | I30: =IF(AND(ISNUMBER(I29),ISNUMBER(I23)),IFERROR(I29/I23,""),"") -> 0.19206251 | J30: =IF(AND(ISNUMBER(J29),ISNUMBER(J23)),IFERROR(J29/J23,""),"") -> 0.1937133 | ... AN30: =IF(AND(ISNUMBER(AN29),ISNUMBER(AN23)),IFERROR(AN29/AN23,""),"") -> 0.23991319 | AO30: =AO31+$AO$116 -> 0.2458174 | AP30: =IF(AND(ISNUMBER(AP29),ISNUMBER(AP23)),IFERROR(AP29/AP23,""),"") -> 0.23629927 | AQ30: =CHOOSE(MATCH($AV$2,{"Bull","Base","Bear"},0),$BE$76,$BF$76,$BG$76) -> 0.24 | AR30: =CHOOSE(MATCH($AV$2,{"Bull","Base","Bear"},0),$BE$77,$BF$77,$BG$77) -> 0.245 | AS30: =CHOOSE(MATCH($AV$2,{"Bull","Base","Bear"},0),$BE$78,$BF$78,$BG$78) -> 0.25 | AT30: =CHOOSE(MATCH($AV$2,{"Bull","Base","Bear"},0),$BE$79,$BF$79,$BG$79) -> 0.253 | AU30: =CHOOSE(MATCH($AV$2,{"Bull","Base","Bear"},0),$BE$80,$BF$80,$BG$80) -> 0.255 | AV30: Q4/26E: margin before calibration + adjusted-EPS-guidance calibration Δ (Group block). 2027E+: scenario lever. | AX30: =IFERROR(AVERAGE(AQ30,AR30,AS30,AT30,AU30),"n/m") -> 0.2486 | AY30: =IFERROR(AVERAGE(Q30,V30,AA30,AF30,AK30),"n/m") -> 0.17839778 | AZ30: =IFERROR(AVERAGE(H30,I30,J30,K30,L30,Q30,V30,AA30,AF30,AK30),"n/m") -> 0.18678927 | BA30: =IFERROR(AVERAGE(C30,D30,E30,F30,G30,H30,I30,J30,K30,L30,Q30,V30,AA30,AF30,AK30),"n/m") -> 0.17545907
B31: Q4/26E margin before EPS calibration (prior-year quarter + 9M FY26 y/y drift) | AO31: =AJ30+IFERROR(SUM(AL29:AN29)/SUM(AL23:AN23)-SUM(AG29:AI29)/SUM(AG23:AI23),0) -> 0.26814934 | BD31: Maximum net debt / adjusted EBITDA before buybacks (x) — buyback floor 2027E+ | BE31: 1.75 | BF31: 1.25 | BG31: 0.75 | BH31: Net debt $867m at 30-Jun-26 ≈ 1.0x adjusted EBITDA (FY2021–25 0.5–1.1x); company "EBITDA leverage" (total debt / TTM EBITDA) 1.6x. Target = leverage up to which surplus cash is returned via buybacks ($1.8bn three-year authorization to Nov-2028); below it free cash flow repays the revolver. Bull = more buybacks (higher target).
B32: Incremental segment margin (Δ earnings / Δ sales) | D32: =IFERROR((D29-C29)/(D23-C23),"") -> 0.013006352 | E32: =IFERROR((E29-D29)/(E23-D23),"") -> 0.21723884 | F32: =IFERROR((F29-E29)/(F23-E23),"") -> -0.30698953 | G32: =IFERROR((G29-F29)/(G23-F23),"") -> 0.37142523 | H32: =IFERROR((H29-G29)/(H23-G23),"") -> 0.61443017 | I32: =IFERROR((I29-H29)/(I23-H23),"") -> 0.23494224 | J32: =IFERROR((J29-I29)/(J23-I23),"") -> 0.20398889 | K32: =IFERROR((K29-J29)/(K23-J23),"") -> 0.27074213 | L32: =IFERROR((L29-K29)/(L23-K23),"") -> 0.27279258 | Q32: =IFERROR((Q29-L29)/(Q23-L23),"") -> 0.40558 | R32: =IFERROR((R29-M29)/(R23-M23),"") -> 0.31263543 | S32: =IFERROR((S29-N29)/(S23-N23),"") -> -1.142591 | T32: =IFERROR((T29-O29)/(T23-O23),"") -> 0.055904605 | U32: =IFERROR((U29-P29)/(U23-P23),"") -> -0.070917495 | V32: =IFERROR((V29-Q29)/(V23-Q23),"") -> -0.029712252 | W32: =IFERROR((W29-R29)/(W23-R23),"") -> 0.073434599 | X32: =IFERROR((X29-S29)/(X23-S23),"") -> 0.21016184 | ... AP32: =IFERROR((AP29-AK29)/(AP23-AK23),"") -> 0.31783637 | AQ32: =IFERROR((AQ29-AP29)/(AQ23-AP23),"") -> 0.2778537 | AR32: =IFERROR((AR29-AQ29)/(AR23-AQ23),"") -> 0.3052206 | AS32: =IFERROR((AS29-AR29)/(AS23-AR23),"") -> 0.32130106 | AT32: =IFERROR((AT29-AS29)/(AT23-AS23),"") -> 0.30317487 | AU32: =IFERROR((AU29-AT29)/(AU23-AT23),"") -> 0.29041816
B33: Memo: Aerospace segment earnings as restated in the following year's release (where different) | J33: 308.553 | AV33: FY2018 restated in the FY2019 release (pension-cost reclassification, ASU 2017-07); the model keeps the originally reported figure. | BD33: AERO_COEM (Commercial OEM y/y) | BE33: 0.04 | BF33: Δ → | BG33: -0.06 | BH33: 9M FY26 +29% (airframer rate increases after the FY25 Boeing work stoppage / inventory normalisation); 737 / A320 / 787 / A350 ramps, A350 spoiler actuation from Spartanburg (2027).
BD34: 2027E | BE34: =BF34+$BE$33 -> 0.18 | BF34: 0.14 | BG34: =BF34+$BG$33 -> 0.08
B35: Industrial ("Energy" to FY2015; fuel, combustion, ignition & control systems for gas turbines, reciprocating engines and compressors; L'Orange fuel injection from Jun-2018) | AV35: INDUSTRIAL — modelling logic | BD35: 2028E | BE35: =BF35+$BE$33 -> 0.15 | BF35: 0.11 | BG35: =BF35+$BG$33 -> 0.05
B36: Power generation sales | Q36: 292.47 | V36: 317.026 | W36: 81.577 | X36: 94.013 | Y36: 101.387 | Z36: 105.559 | AA36: 382.536 | AB36: 98.106 | AC36: 106.811 | AD36: 109.583 | AE36: 109.372 | AF36: 423.872 | AG36: 105.219 | AH36: 111.047 | AI36: 109.341 | AJ36: 163.333 | AK36: 488.94 | AL36: 122.84 | AM36: 135.87 | AN36: 144.675 | AO36: =AJ36*(1+AO37) -> 186.08721 | AP36: =SUM(AL36:AO36) -> 589.47221 | AQ36: =AP36*(1+AQ37) -> 660.20887 | AR36: =AQ36*(1+AR37) -> 726.22976 | AS36: =AR36*(1+AS37) -> 784.32814 | AT36: =AS36*(1+AT37) -> 831.38783 | AU36: =AT36*(1+AU37) -> 872.95722 | AV36: Sales by primary market (10-Q / 10-K revenue-disaggregation note, from FY2019; Q4 = fiscal year − nine months). Q4/26E: prior-year quarter × (1 + growth). 2027E+: prior year × (1 + scenario lever). | AX36: =IFERROR((AU36/AP36)^(1/5)-1,"n/m") -> 0.081697748 | AY36: =IFERROR((AK36/L36)^(1/5)-1,"n/m") -> n/m | AZ36: =IFERROR((AK36/G36)^(1/10)-1,"n/m") -> n/m | BA36: =IFERROR((AK36/C36)^(1/14)-1,"n/m") -> n/m | BD36: 2029E | BE36: =BF36+$BE$33 -> 0.13 | BF36: 0.09 | BG36: =BF36+$BG$33 -> 0.03
B37: y/y % | D37: =IF(AND(ISNUMBER(D36),ISNUMBER(C36)),IFERROR(D36/C36-1,""),"") | E37: =IF(AND(ISNUMBER(E36),ISNUMBER(D36)),IFERROR(E36/D36-1,""),"") | F37: =IF(AND(ISNUMBER(F36),ISNUMBER(E36)),IFERROR(F36/E36-1,""),"") | G37: =IF(AND(ISNUMBER(G36),ISNUMBER(F36)),IFERROR(G36/F36-1,""),"") | H37: =IF(AND(ISNUMBER(H36),ISNUMBER(G36)),IFERROR(H36/G36-1,""),"") | I37: =IF(AND(ISNUMBER(I36),ISNUMBER(H36)),IFERROR(I36/H36-1,""),"") | J37: =IF(AND(ISNUMBER(J36),ISNUMBER(I36)),IFERROR(J36/I36-1,""),"") | K37: =IF(AND(ISNUMBER(K36),ISNUMBER(J36)),IFERROR(K36/J36-1,""),"") | L37: =IF(AND(ISNUMBER(L36),ISNUMBER(K36)),IFERROR(L36/K36-1,""),"") | Q37: =IF(AND(ISNUMBER(Q36),ISNUMBER(L36)),IFERROR(Q36/L36-1,""),"") | R37: =IF(AND(ISNUMBER(R36),ISNUMBER(M36)),IFERROR(R36/M36-1,""),"") | S37: =IF(AND(ISNUMBER(S36),ISNUMBER(N36)),IFERROR(S36/N36-1,""),"") | T37: =IF(AND(ISNUMBER(T36),ISNUMBER(O36)),IFERROR(T36/O36-1,""),"") | U37: =IF(AND(ISNUMBER(U36),ISNUMBER(P36)),IFERROR(U36/P36-1,""),"") | V37: =IF(AND(ISNUMBER(V36),ISNUMBER(Q36)),IFERROR(V36/Q36-1,""),"") -> 0.083960748 | W37: =IF(AND(ISNUMBER(W36),ISNUMBER(R36)),IFERROR(W36/R36-1,""),"") | X37: =IF(AND(ISNUMBER(X36),ISNUMBER(S36)),IFERROR(X36/S36-1,""),"") | ... AN37: =IF(AND(ISNUMBER(AN36),ISNUMBER(AI36)),IFERROR(AN36/AI36-1,""),"") -> 0.32315417 | AO37: =AO38+$AO$109 -> 0.13931175 | AP37: =IF(AND(ISNUMBER(AP36),ISNUMBER(AK36)),IFERROR(AP36/AK36-1,""),"") -> 0.20561256 | AQ37: =CHOOSE(MATCH($AV$2,{"Bull","Base","Bear"},0),$BE$58,$BF$58,$BG$58) -> 0.12 | AR37: =CHOOSE(MATCH($AV$2,{"Bull","Base","Bear"},0),$BE$59,$BF$59,$BG$59) -> 0.1 | AS37: =CHOOSE(MATCH($AV$2,{"Bull","Base","Bear"},0),$BE$60,$BF$60,$BG$60) -> 0.08 | AT37: =CHOOSE(MATCH($AV$2,{"Bull","Base","Bear"},0),$BE$61,$BF$61,$BG$61) -> 0.06 | AU37: =CHOOSE(MATCH($AV$2,{"Bull","Base","Bear"},0),$BE$62,$BF$62,$BG$62) -> 0.05 | AV37: Q4/26E: 9M FY26 y/y growth of the market + sales-guidance calibration Δ (Group block). 2027E–2031E: scenario lever (Bull/Base/Bear table →). | BD37: 2030E | BE37: =BF37+$BE$33 -> 0.11 | BF37: 0.07 | BG37: =BF37+$BG$33 -> 0.01
B38: Q4/26E growth before sales calibration (9M FY26 y/y) | AO38: =IFERROR(SUM(AL36:AN36)/SUM(AG36:AI36)-1,0) -> 0.23887079 | BD38: 2031E | BE38: =BF38+$BE$33 -> 0.1 | BF38: 0.06 | BG38: =BF38+$BG$33 -> 0
B39: Transportation sales | Q39: 399.002 | V39: 354.682 | W39: 88.915 | X39: 118.777 | Y39: 158.039 | Z39: 161.767 | AA39: 527.498 | AB39: 174.469 | AC39: 173.786 | AD39: 163.31 | AE39: 130.609 | AF39: 642.174 | AG39: 116.606 | AH39: 141.734 | AI39: 143.652 | AJ39: 105.384 | AK39: 507.376 | AL39: 166.308 | AM39: 176.914 | AN39: 180.155 | AO39: =AJ39*(1+AO40) -> 126.71369 | AP39: =SUM(AL39:AO39) -> 650.09069 | AQ39: =AP39*(1+AQ40) -> 650.09069 | AR39: =AQ39*(1+AR40) -> 676.09432 | AS39: =AR39*(1+AS40) -> 703.13809 | AT39: =AS39*(1+AT40) -> 724.23223 | AU39: =AT39*(1+AU40) -> 745.9592 | AX39: =IFERROR((AU39/AP39)^(1/5)-1,"n/m") -> 0.027893751 | AY39: =IFERROR((AK39/L39)^(1/5)-1,"n/m") -> n/m | AZ39: =IFERROR((AK39/G39)^(1/10)-1,"n/m") -> n/m | BA39: =IFERROR((AK39/C39)^(1/14)-1,"n/m") -> n/m | BD39: AERO_CSERV (Commercial services y/y) | BE39: 0.03 | BF39: Δ → | BG39: -0.06 | BH39: 9M FY26 +36% (FY25 +29%, partly advance purchases); high utilisation of legacy fleets, price; normalising toward high-single digits.
B40: y/y % | D40: =IF(AND(ISNUMBER(D39),ISNUMBER(C39)),IFERROR(D39/C39-1,""),"") | E40: =IF(AND(ISNUMBER(E39),ISNUMBER(D39)),IFERROR(E39/D39-1,""),"") | F40: =IF(AND(ISNUMBER(F39),ISNUMBER(E39)),IFERROR(F39/E39-1,""),"") | G40: =IF(AND(ISNUMBER(G39),ISNUMBER(F39)),IFERROR(G39/F39-1,""),"") | H40: =IF(AND(ISNUMBER(H39),ISNUMBER(G39)),IFERROR(H39/G39-1,""),"") | I40: =IF(AND(ISNUMBER(I39),ISNUMBER(H39)),IFERROR(I39/H39-1,""),"") | J40: =IF(AND(ISNUMBER(J39),ISNUMBER(I39)),IFERROR(J39/I39-1,""),"") | K40: =IF(AND(ISNUMBER(K39),ISNUMBER(J39)),IFERROR(K39/J39-1,""),"") | L40: =IF(AND(ISNUMBER(L39),ISNUMBER(K39)),IFERROR(L39/K39-1,""),"") | Q40: =IF(AND(ISNUMBER(Q39),ISNUMBER(L39)),IFERROR(Q39/L39-1,""),"") | R40: =IF(AND(ISNUMBER(R39),ISNUMBER(M39)),IFERROR(R39/M39-1,""),"") | S40: =IF(AND(ISNUMBER(S39),ISNUMBER(N39)),IFERROR(S39/N39-1,""),"") | T40: =IF(AND(ISNUMBER(T39),ISNUMBER(O39)),IFERROR(T39/O39-1,""),"") | U40: =IF(AND(ISNUMBER(U39),ISNUMBER(P39)),IFERROR(U39/P39-1,""),"") | V40: =IF(AND(ISNUMBER(V39),ISNUMBER(Q39)),IFERROR(V39/Q39-1,""),"") -> -0.11107714 | W40: =IF(AND(ISNUMBER(W39),ISNUMBER(R39)),IFERROR(W39/R39-1,""),"") | X40: =IF(AND(ISNUMBER(X39),ISNUMBER(S39)),IFERROR(X39/S39-1,""),"") | ... AN40: =IF(AND(ISNUMBER(AN39),ISNUMBER(AI39)),IFERROR(AN39/AI39-1,""),"") -> 0.25410715 | AO40: =AO41+$AO$109 -> 0.20239971 | AP40: =IF(AND(ISNUMBER(AP39),ISNUMBER(AK39)),IFERROR(AP39/AK39-1,""),"") -> 0.28127994 | AQ40: =CHOOSE(MATCH($AV$2,{"Bull","Base","Bear"},0),$BE$64,$BF$64,$BG$64) -> 0 | AR40: =CHOOSE(MATCH($AV$2,{"Bull","Base","Bear"},0),$BE$65,$BF$65,$BG$65) -> 0.04 | AS40: =CHOOSE(MATCH($AV$2,{"Bull","Base","Bear"},0),$BE$66,$BF$66,$BG$66) -> 0.04 | AT40: =CHOOSE(MATCH($AV$2,{"Bull","Base","Bear"},0),$BE$67,$BF$67,$BG$67) -> 0.03 | AU40: =CHOOSE(MATCH($AV$2,{"Bull","Base","Bear"},0),$BE$68,$BF$68,$BG$68) -> 0.03 | BD40: 2027E | BE40: =BF40+$BE$39 -> 0.12 | BF40: 0.09 | BG40: =BF40+$BG$39 -> 0.03
B41: Q4/26E growth before sales calibration (9M FY26 y/y) | AO41: =IFERROR(SUM(AL39:AN39)/SUM(AG39:AI39)-1,0) -> 0.30195875 | BD41: 2028E | BE41: =BF41+$BE$39 -> 0.11 | BF41: 0.08 | BG41: =BF41+$BG$39 -> 0.02
B42: Oil and gas sales | Q42: 150.243 | V42: 191.76 | W42: 52.442 | X42: 68.407 | Y42: 60.706 | Z42: 54.874 | AA42: 236.429 | AB42: 53.399 | AC42: 57.234 | AD42: 57.235 | AE42: 61.717 | AF42: 229.585 | AG42: 57.018 | AH42: 69.119 | AI42: 66.463 | AJ42: 65.342 | AK42: 257.942 | AL42: 72.409 | AM42: 74.463 | AN42: 76.202 | AO42: =AJ42*(1+AO43) -> 69.175305 | AP42: =SUM(AL42:AO42) -> 292.24931 | AQ42: =AP42*(1+AQ43) -> 303.93928 | AR42: =AQ42*(1+AR43) -> 316.09685 | AS42: =AR42*(1+AS43) -> 325.57975 | AT42: =AS42*(1+AT43) -> 335.34715 | AU42: =AT42*(1+AU43) -> 345.40756 | AX42: =IFERROR((AU42/AP42)^(1/5)-1,"n/m") -> 0.033988409 | AY42: =IFERROR((AK42/L42)^(1/5)-1,"n/m") -> n/m | AZ42: =IFERROR((AK42/G42)^(1/10)-1,"n/m") -> n/m | BA42: =IFERROR((AK42/C42)^(1/14)-1,"n/m") -> n/m | BD42: 2029E | BE42: =BF42+$BE$39 -> 0.1 | BF42: 0.07 | BG42: =BF42+$BG$39 -> 0.01
B43: y/y % | D43: =IF(AND(ISNUMBER(D42),ISNUMBER(C42)),IFERROR(D42/C42-1,""),"") | E43: =IF(AND(ISNUMBER(E42),ISNUMBER(D42)),IFERROR(E42/D42-1,""),"") | F43: =IF(AND(ISNUMBER(F42),ISNUMBER(E42)),IFERROR(F42/E42-1,""),"") | G43: =IF(AND(ISNUMBER(G42),ISNUMBER(F42)),IFERROR(G42/F42-1,""),"") | H43: =IF(AND(ISNUMBER(H42),ISNUMBER(G42)),IFERROR(H42/G42-1,""),"") | I43: =IF(AND(ISNUMBER(I42),ISNUMBER(H42)),IFERROR(I42/H42-1,""),"") | J43: =IF(AND(ISNUMBER(J42),ISNUMBER(I42)),IFERROR(J42/I42-1,""),"") | K43: =IF(AND(ISNUMBER(K42),ISNUMBER(J42)),IFERROR(K42/J42-1,""),"") | L43: =IF(AND(ISNUMBER(L42),ISNUMBER(K42)),IFERROR(L42/K42-1,""),"") | Q43: =IF(AND(ISNUMBER(Q42),ISNUMBER(L42)),IFERROR(Q42/L42-1,""),"") | R43: =IF(AND(ISNUMBER(R42),ISNUMBER(M42)),IFERROR(R42/M42-1,""),"") | S43: =IF(AND(ISNUMBER(S42),ISNUMBER(N42)),IFERROR(S42/N42-1,""),"") | T43: =IF(AND(ISNUMBER(T42),ISNUMBER(O42)),IFERROR(T42/O42-1,""),"") | U43: =IF(AND(ISNUMBER(U42),ISNUMBER(P42)),IFERROR(U42/P42-1,""),"") | V43: =IF(AND(ISNUMBER(V42),ISNUMBER(Q42)),IFERROR(V42/Q42-1,""),"") -> 0.27633234 | W43: =IF(AND(ISNUMBER(W42),ISNUMBER(R42)),IFERROR(W42/R42-1,""),"") | X43: =IF(AND(ISNUMBER(X42),ISNUMBER(S42)),IFERROR(X42/S42-1,""),"") | ... AN43: =IF(AND(ISNUMBER(AN42),ISNUMBER(AI42)),IFERROR(AN42/AI42-1,""),"") -> 0.14653266 | AO43: =AO44+$AO$109 -> 0.058665259 | AP43: =IF(AND(ISNUMBER(AP42),ISNUMBER(AK42)),IFERROR(AP42/AK42-1,""),"") -> 0.13300395 | AQ43: =CHOOSE(MATCH($AV$2,{"Bull","Base","Bear"},0),$BE$70,$BF$70,$BG$70) -> 0.04 | AR43: =CHOOSE(MATCH($AV$2,{"Bull","Base","Bear"},0),$BE$71,$BF$71,$BG$71) -> 0.04 | AS43: =CHOOSE(MATCH($AV$2,{"Bull","Base","Bear"},0),$BE$72,$BF$72,$BG$72) -> 0.03 | AT43: =CHOOSE(MATCH($AV$2,{"Bull","Base","Bear"},0),$BE$73,$BF$73,$BG$73) -> 0.03 | AU43: =CHOOSE(MATCH($AV$2,{"Bull","Base","Bear"},0),$BE$74,$BF$74,$BG$74) -> 0.03 | BD43: 2030E | BE43: =BF43+$BE$39 -> 0.09 | BF43: 0.06 | BG43: =BF43+$BG$39 -> 0
B44: Q4/26E growth before sales calibration (9M FY26 y/y) | AO44: =IFERROR(SUM(AL42:AN42)/SUM(AG42:AI42)-1,0) -> 0.1582243 | BD44: 2031E | BE44: =BF44+$BE$39 -> 0.09 | BF44: 0.06 | BG44: =BF44+$BG$39 -> 0
B45: Industrial — segment net sales | C45: =IF(ISNUMBER(C36),C36+C39+C42,C48) -> 868.67 | D45: =IF(ISNUMBER(D36),D36+D39+D42,D48) -> 969.544 | E45: =IF(ISNUMBER(E36),E36+E39+E42,E48) -> 874.499 | F45: =IF(ISNUMBER(F36),F36+F39+F42,F48) -> 917.215 | G45: =IF(ISNUMBER(G36),G36+G39+G42,G48) -> 877.42 | H45: =IF(ISNUMBER(H36),H36+H39+H42,H48) -> 789.902 | I45: =IF(ISNUMBER(I36),I36+I39+I42,I48) -> 756.346 | J45: =IF(ISNUMBER(J36),J36+J39+J42,J48) -> 767.885 | ... AN45: =IF(ISNUMBER(AN36),AN36+AN39+AN42,AN48) -> 401.032 | AO45: =AO36+AO39+AO42 -> 381.9762 | AP45: =AP36+AP39+AP42 -> 1531.8122 | AQ45: =AQ36+AQ39+AQ42 -> 1614.2388 | AR45: =AR36+AR39+AR42 -> 1718.4209 | AS45: =AS36+AS39+AS42 -> 1813.046 | AT45: =AT36+AT39+AT42 -> 1890.9672 | AU45: =AU36+AU39+AU42 -> 1964.324 | AX45: =IFERROR((AU45/AP45)^(1/5)-1,"n/m") -> 0.050997103 | AY45: =IFERROR((AK45/L45)^(1/5)-1,"n/m") -> 0.067520604 | AZ45: =IFERROR((AK45/G45)^(1/10)-1,"n/m") -> 0.036377403 | BA45: =IFERROR((AK45/C45)^(1/14)-1,"n/m") -> 0.02658555 | BD45: AERO_DOEM (Defense OEM y/y) | BE45: 0.03 | BF45: Δ → | BG45: -0.04 | BH45: 9M FY26 +7% (FY25 +38%: smart-defense / guided-weapons demand, price).
B46: Segment sales y/y % | D46: =IF(AND(ISNUMBER(D45),ISNUMBER(C45)),IFERROR(D45/C45-1,""),"") -> 0.11612465 | E46: =IF(AND(ISNUMBER(E45),ISNUMBER(D45)),IFERROR(E45/D45-1,""),"") -> -0.098030621 | F46: =IF(AND(ISNUMBER(F45),ISNUMBER(E45)),IFERROR(F45/E45-1,""),"") -> 0.048846254 | G46: =IF(AND(ISNUMBER(G45),ISNUMBER(F45)),IFERROR(G45/F45-1,""),"") -> -0.043386774 | H46: =IF(AND(ISNUMBER(H45),ISNUMBER(G45)),IFERROR(H45/G45-1,""),"") -> -0.099744706 | I46: =IF(AND(ISNUMBER(I45),ISNUMBER(H45)),IFERROR(I45/H45-1,""),"") -> -0.042481219 | J46: =IF(AND(ISNUMBER(J45),ISNUMBER(I45)),IFERROR(J45/I45-1,""),"") -> 0.015256245 | K46: =IF(AND(ISNUMBER(K45),ISNUMBER(J45)),IFERROR(K45/J45-1,""),"") -> 0.32790327 | L46: =IF(AND(ISNUMBER(L45),ISNUMBER(K45)),IFERROR(L45/K45-1,""),"") -> -0.11275629 | Q46: =IF(AND(ISNUMBER(Q45),ISNUMBER(L45)),IFERROR(Q45/L45-1,""),"") -> -0.06962182 | R46: =IF(AND(ISNUMBER(R45),ISNUMBER(M45)),IFERROR(R45/M45-1,""),"") -> -0.050015744 | S46: =IF(AND(ISNUMBER(S45),ISNUMBER(N45)),IFERROR(S45/N45-1,""),"") -> -0.011693558 | T46: =IF(AND(ISNUMBER(T45),ISNUMBER(O45)),IFERROR(T45/O45-1,""),"") -> -0.014566909 | U46: =IF(AND(ISNUMBER(U45),ISNUMBER(P45)),IFERROR(U45/P45-1,""),"") -> 0.19768855 | V46: =IF(AND(ISNUMBER(V45),ISNUMBER(Q45)),IFERROR(V45/Q45-1,""),"") -> 0.025843664 | W46: =IF(AND(ISNUMBER(W45),ISNUMBER(R45)),IFERROR(W45/R45-1,""),"") -> 0.086682492 | X46: =IF(AND(ISNUMBER(X45),ISNUMBER(S45)),IFERROR(X45/S45-1,""),"") -> 0.31350137 | ... AP46: =IF(AND(ISNUMBER(AP45),ISNUMBER(AK45)),IFERROR(AP45/AK45-1,""),"") -> 0.22128956 | AQ46: =IF(AND(ISNUMBER(AQ45),ISNUMBER(AP45)),IFERROR(AQ45/AP45-1,""),"") -> 0.053809884 | AR46: =IF(AND(ISNUMBER(AR45),ISNUMBER(AQ45)),IFERROR(AR45/AQ45-1,""),"") -> 0.064539449 | AS46: =IF(AND(ISNUMBER(AS45),ISNUMBER(AR45)),IFERROR(AS45/AR45-1,""),"") -> 0.055065123 | AT46: =IF(AND(ISNUMBER(AT45),ISNUMBER(AS45)),IFERROR(AT45/AS45-1,""),"") -> 0.042978074 | AU46: =IF(AND(ISNUMBER(AU45),ISNUMBER(AT45)),IFERROR(AU45/AT45-1,""),"") -> 0.038793255 | BD46: 2027E | BE46: =BF46+$BE$45 -> 0.1 | BF46: 0.07 | BG46: =BF46+$BG$45 -> 0.03
B47: % of total net sales | C47: =IF(AND(ISNUMBER(C45),ISNUMBER(C99)),IFERROR(C45/C99,""),"") -> 0.50748904 | D47: =IF(AND(ISNUMBER(D45),ISNUMBER(D99)),IFERROR(D45/D99,""),"") -> 0.51968802 | E47: =IF(AND(ISNUMBER(E45),ISNUMBER(E99)),IFERROR(E45/E99,""),"") -> 0.45170963 | F47: =IF(AND(ISNUMBER(F45),ISNUMBER(F99)),IFERROR(F45/F99,""),"") -> 0.45832334 | G47: =IF(AND(ISNUMBER(G45),ISNUMBER(G99)),IFERROR(G45/G99,""),"") -> 0.43046593 | H47: =IF(AND(ISNUMBER(H45),ISNUMBER(H99)),IFERROR(H45/H99,""),"") -> 0.39044565 | I47: =IF(AND(ISNUMBER(I45),ISNUMBER(I99)),IFERROR(I45/I99,""),"") -> 0.36039043 | J47: =IF(AND(ISNUMBER(J45),ISNUMBER(J99)),IFERROR(J45/J99,""),"") -> 0.33014915 | ... AU47: =IF(AND(ISNUMBER(AU45),ISNUMBER(AU99)),IFERROR(AU45/AU99,""),"") -> 0.3207838 | BD47: 2028E | BE47: =BF47+$BE$45 -> 0.09 | BF47: 0.06 | BG47: =BF47+$BG$45 -> 0.02
B48: Memo: Industrial segment net sales as reported (segment schedule) | C48: 868.67 | D48: 969.544 | E48: 874.499 | F48: 917.215 | G48: 877.42 | H48: 789.902 | I48: 756.346 | J48: 767.885 | K48: 1019.677 | L48: 904.702 | M48: 215.952 | N48: 216.615 | O48: 215.763 | P48: 193.385 | Q48: 841.715 | R48: 205.151 | S48: 214.082 | T48: 212.62 | U48: 231.615 | V48: 863.468 | W48: 222.934 | X48: 281.197 | Y48: 320.132 | Z48: 322.2 | AA48: 1146.463 | AB48: 325.974 | AC48: 337.831 | AD48: 330.128 | AE48: 301.698 | AF48: 1295.631 | AG48: 278.843 | AH48: 321.9 | AI48: 319.456 | AJ48: 334.059 | AK48: 1254.258 | AL48: 361.557 | AM48: 387.247 | AN48: 401.032 | BD48: 2029E | BE48: =BF48+$BE$45 -> 0.08 | BF48: 0.05 | BG48: =BF48+$BG$45 -> 0.01
B49: Check: primary markets vs segment net sales (should be 0) | C49: =IF(AND(ISNUMBER(C36),ISNUMBER(C48)),IF(ABS(C45-C48)<=0.15,0,ROUND(C45-C48,1)),"") | D49: =IF(AND(ISNUMBER(D36),ISNUMBER(D48)),IF(ABS(D45-D48)<=0.15,0,ROUND(D45-D48,1)),"") | E49: =IF(AND(ISNUMBER(E36),ISNUMBER(E48)),IF(ABS(E45-E48)<=0.15,0,ROUND(E45-E48,1)),"") | F49: =IF(AND(ISNUMBER(F36),ISNUMBER(F48)),IF(ABS(F45-F48)<=0.15,0,ROUND(F45-F48,1)),"") | G49: =IF(AND(ISNUMBER(G36),ISNUMBER(G48)),IF(ABS(G45-G48)<=0.15,0,ROUND(G45-G48,1)),"") | H49: =IF(AND(ISNUMBER(H36),ISNUMBER(H48)),IF(ABS(H45-H48)<=0.15,0,ROUND(H45-H48,1)),"") | I49: =IF(AND(ISNUMBER(I36),ISNUMBER(I48)),IF(ABS(I45-I48)<=0.15,0,ROUND(I45-I48,1)),"") | J49: =IF(AND(ISNUMBER(J36),ISNUMBER(J48)),IF(ABS(J45-J48)<=0.15,0,ROUND(J45-J48,1)),"") | ... AN49: =IF(AND(ISNUMBER(AN36),ISNUMBER(AN48)),IF(ABS(AN45-AN48)<=0.15,0,ROUND(AN45-AN48,1)),"") -> 0 | BD49: 2030E | BE49: =BF49+$BE$45 -> 0.08 | BF49: 0.05 | BG49: =BF49+$BG$45 -> 0.01
B50: Industrial segment earnings | C50: 113.872 | D50: 126.441 | E50: 98.94 | F50: 134.278 | G50: 126.641 | H50: 82.237 | I50: 78.991 | J50: 47.938 | K50: 93.521 | L50: 100.321 | M50: 32.888 | N50: 27.871 | O50: 27.166 | P50: 20.747 | Q50: 108.672 | R50: 23.693 | S50: 17.234 | T50: 21.102 | U50: 20.759 | V50: 82.788 | W50: 11.402 | X50: 37.571 | Y50: 58.197 | Z50: 54.451 | AA50: 161.622 | AB50: 66.881 | AC50: 65.244 | AD50: 59.717 | AE50: 38.015 | AF50: 229.857 | AG50: 40.197 | AH50: 45.967 | AI50: 47.622 | AJ50: 48.738 | AK50: 182.524 | AL50: 66.994 | AM50: 65.721 | AN50: 88.484 | AO50: =AO45*AO51 -> 65.146313 | AP50: =SUM(AL50:AO50) -> 286.34531 | AQ50: =AQ45*AQ51 -> 306.70538 | AR50: =AR45*AR51 -> 329.93682 | AS50: =AS45*AS51 -> 353.54397 | AT50: =AT45*AT51 -> 372.52054 | AU50: =AU45*AU51 -> 392.8648 | AX50: =IFERROR((AU50/AP50)^(1/5)-1,"n/m") -> 0.065296762 | AY50: =IFERROR((AK50/L50)^(1/5)-1,"n/m") -> 0.12716015 | AZ50: =IFERROR((AK50/G50)^(1/10)-1,"n/m") -> 0.037228794 | BA50: =IFERROR((AK50/C50)^(1/14)-1,"n/m") -> 0.03427477 | BD50: 2031E | BE50: =BF50+$BE$45 -> 0.08 | BF50: 0.05 | BG50: =BF50+$BG$45 -> 0.01
B51: Segment margin % | C51: =IF(AND(ISNUMBER(C50),ISNUMBER(C45)),IFERROR(C50/C45,""),"") -> 0.13108775 | D51: =IF(AND(ISNUMBER(D50),ISNUMBER(D45)),IFERROR(D50/D45,""),"") -> 0.13041285 | E51: =IF(AND(ISNUMBER(E50),ISNUMBER(E45)),IFERROR(E50/E45,""),"") -> 0.11313907 | F51: =IF(AND(ISNUMBER(F50),ISNUMBER(F45)),IFERROR(F50/F45,""),"") -> 0.14639752 | G51: =IF(AND(ISNUMBER(G50),ISNUMBER(G45)),IFERROR(G50/G45,""),"") -> 0.14433339 | H51: =IF(AND(ISNUMBER(H50),ISNUMBER(H45)),IFERROR(H50/H45,""),"") -> 0.10411038 | I51: =IF(AND(ISNUMBER(I50),ISNUMBER(I45)),IFERROR(I50/I45,""),"") -> 0.10443765 | J51: =IF(AND(ISNUMBER(J50),ISNUMBER(J45)),IFERROR(J50/J45,""),"") -> 0.062428619 | ... AN51: =IF(AND(ISNUMBER(AN50),ISNUMBER(AN45)),IFERROR(AN50/AN45,""),"") -> 0.22064075 | AO51: =AO52+$AO$116 -> 0.17055071 | AP51: =IF(AND(ISNUMBER(AP50),ISNUMBER(AP45)),IFERROR(AP50/AP45,""),"") -> 0.18693239 | AQ51: =CHOOSE(MATCH($AV$2,{"Bull","Base","Bear"},0),$BE$82,$BF$82,$BG$82) -> 0.19 | AR51: =CHOOSE(MATCH($AV$2,{"Bull","Base","Bear"},0),$BE$83,$BF$83,$BG$83) -> 0.192 | AS51: =CHOOSE(MATCH($AV$2,{"Bull","Base","Bear"},0),$BE$84,$BF$84,$BG$84) -> 0.195 | AT51: =CHOOSE(MATCH($AV$2,{"Bull","Base","Bear"},0),$BE$85,$BF$85,$BG$85) -> 0.197 | AU51: =CHOOSE(MATCH($AV$2,{"Bull","Base","Bear"},0),$BE$86,$BF$86,$BG$86) -> 0.2 | AX51: =IFERROR(AVERAGE(AQ51,AR51,AS51,AT51,AU51),"n/m") -> 0.1948 | AY51: =IFERROR(AVERAGE(Q51,V51,AA51,AF51,AK51),"n/m") -> 0.13777871 | AZ51: =IFERROR(AVERAGE(H51,I51,J51,K51,L51,Q51,V51,AA51,AF51,AK51),"n/m") -> 0.1162475 | BA51: =IFERROR(AVERAGE(C51,D51,E51,F51,G51,H51,I51,J51,K51,L51,Q51,V51,AA51,AF51,AK51),"n/m") -> 0.12185637 | BD51: AERO_DSERV (Defense services y/y) | BE51: 0.02 | BF51: Δ → | BG51: -0.04 | BH51: 9M FY26 +9%; FY25 −2% (mix).
B52: Q4/26E margin before EPS calibration (prior-year quarter + 9M FY26 y/y drift) | AO52: =AJ51+IFERROR(SUM(AL50:AN50)/SUM(AL45:AN45)-SUM(AG50:AI50)/SUM(AG45:AI45),0) -> 0.19288266 | BD52: 2027E | BE52: =BF52+$BE$51 -> 0.07 | BF52: 0.05 | BG52: =BF52+$BG$51 -> 0.01
B53: Incremental segment margin (Δ earnings / Δ sales) | D53: =IFERROR((D50-C50)/(D45-C45),"") -> 0.12460099 | E53: =IFERROR((E50-D50)/(E45-D45),"") -> 0.28934715 | F53: =IFERROR((F50-E50)/(F45-E45),"") -> 0.82727784 | G53: =IFERROR((G50-F50)/(G45-F45),"") -> 0.19190853 | H53: =IFERROR((H50-G50)/(H45-G45),"") -> 0.50736991 | I53: =IFERROR((I50-H50)/(I45-H45),"") -> 0.096733818 | J53: =IFERROR((J50-I50)/(J45-I45),"") -> -2.6911344 | K53: =IFERROR((K50-J50)/(K45-J45),"") -> 0.18103435 | L53: =IFERROR((L50-K50)/(L45-K45),"") -> -0.059143292 | Q53: =IFERROR((Q50-L50)/(Q45-L45),"") -> -0.13258291 | R53: =IFERROR((R50-M50)/(R45-M45),"") -> 0.85131006 | S53: =IFERROR((S50-N50)/(S45-N45),"") -> 4.1993683 | T53: =IFERROR((T50-O50)/(T45-O45),"") -> 1.9293668 | U53: =IFERROR((U50-P50)/(U45-P45),"") -> 0.00031388962 | V53: =IFERROR((V50-Q50)/(V45-Q45),"") -> -1.1899048 | W53: =IFERROR((W50-R50)/(W45-R45),"") -> -0.69116572 | X53: =IFERROR((X50-S50)/(X45-S45),"") -> 0.30301721 | ... AP53: =IFERROR((AP50-AK50)/(AP45-AK45),"") -> 0.3740578 | AQ53: =IFERROR((AQ50-AP50)/(AQ45-AP45),"") -> 0.24700834 | AR53: =IFERROR((AR50-AQ50)/(AR45-AQ45),"") -> 0.2229888 | AS53: =IFERROR((AS50-AR50)/(AS45-AR45),"") -> 0.24948095 | AT53: =IFERROR((AT50-AS50)/(AT45-AS45),"") -> 0.24353536 | AU53: =IFERROR((AU50-AT50)/(AU45-AT45),"") -> 0.27733303 | BD53: 2028E | BE53: =BF53+$BE$51 -> 0.07 | BF53: 0.05 | BG53: =BF53+$BG$51 -> 0.01
B54: Memo: Industrial segment earnings as restated in the following year's release (where different) | J54: 49.894 | BD54: 2029E | BE54: =BF54+$BE$51 -> 0.06 | BF54: 0.04 | BG54: =BF54+$BG$51 -> 0
B55: Legacy primary markets (as originally reported FY2019–FY2022; replaced in the FY2023 10-K): | BD55: 2030E | BE55: =BF55+$BE$51 -> 0.06 | BF55: 0.04 | BG55: =BF55+$BG$51 -> 0
B56: Reciprocating engines | K56: 751.136 | L56: 632.555 | M56: 164.922 | N56: 163.034 | O56: 166.143 | P56: 145.847 | Q56: 639.946 | R56: 158.334 | S56: 156.663 | T56: 154.09 | U56: 167.779 | V56: 636.866 | W56: 161.377 | X56: 209.238 | Y56: 242.04 | BD56: 2031E | BE56: =BF56+$BE$51 -> 0.06 | BF56: 0.04 | BG56: =BF56+$BG$51 -> 0
B57: Industrial turbines | K57: 210.064 | L57: 222.366 | M57: 51.03 | N57: 53.581 | O57: 49.62 | P57: 47.538 | Q57: 201.769 | R57: 46.817 | S57: 57.419 | T57: 58.53 | U57: 63.836 | V57: 226.602 | W57: 61.557 | X57: 71.959 | Y57: 78.092 | BD57: IND_PG (Power generation y/y) | BE57: 0.04 | BF57: Δ → | BG57: -0.06 | BH57: 9M FY26 +11%; FY25 +10%: gas turbines and reciprocating gensets (data-centre and grid demand).
B58: Renewables (sold May-2020) | K58: 58.477 | L58: 49.781 | M58: 0 | N58: 0 | O58: 0 | P58: 0 | Q58: 0 | V58: 0 | BD58: 2027E | BE58: =BF58+$BE$57 -> 0.16 | BF58: 0.12 | BG58: =BF58+$BG$57 -> 0.06
B59: Check: legacy markets vs segment net sales (should be 0) | C59: =IF(ISNUMBER(C56),IF(ABS(C56+N(C57)+N(C58)-C48)<=0.15,0,ROUND(C56+N(C57)+N(C58)-C48,1)),"") | D59: =IF(ISNUMBER(D56),IF(ABS(D56+N(D57)+N(D58)-D48)<=0.15,0,ROUND(D56+N(D57)+N(D58)-D48,1)),"") | E59: =IF(ISNUMBER(E56),IF(ABS(E56+N(E57)+N(E58)-E48)<=0.15,0,ROUND(E56+N(E57)+N(E58)-E48,1)),"") | F59: =IF(ISNUMBER(F56),IF(ABS(F56+N(F57)+N(F58)-F48)<=0.15,0,ROUND(F56+N(F57)+N(F58)-F48,1)),"") | G59: =IF(ISNUMBER(G56),IF(ABS(G56+N(G57)+N(G58)-G48)<=0.15,0,ROUND(G56+N(G57)+N(G58)-G48,1)),"") | H59: =IF(ISNUMBER(H56),IF(ABS(H56+N(H57)+N(H58)-H48)<=0.15,0,ROUND(H56+N(H57)+N(H58)-H48,1)),"") | I59: =IF(ISNUMBER(I56),IF(ABS(I56+N(I57)+N(I58)-I48)<=0.15,0,ROUND(I56+N(I57)+N(I58)-I48,1)),"") | J59: =IF(ISNUMBER(J56),IF(ABS(J56+N(J57)+N(J58)-J48)<=0.15,0,ROUND(J56+N(J57)+N(J58)-J48,1)),"") | ... AN59: =IF(ISNUMBER(AN56),IF(ABS(AN56+N(AN57)+N(AN58)-AN48)<=0.15,0,ROUND(AN56+N(AN57)+N(AN58)-AN48,1)),"") | BD59: 2028E | BE59: =BF59+$BE$57 -> 0.14 | BF59: 0.1 | BG59: =BF59+$BG$57 -> 0.04
BD60: 2029E | BE60: =BF60+$BE$57 -> 0.12 | BF60: 0.08 | BG60: =BF60+$BG$57 -> 0.02
B61: Nonsegment expenses (corporate costs, restructuring and other items not allocated to the segments) | AV61: NONSEGMENT — corporate office costs (compensation, benefits, depreciation, administration); adjusting items are recorded here | BD61: 2030E | BE61: =BF61+$BE$57 -> 0.1 | BF61: 0.06 | BG61: =BF61+$BG$57 -> 0
B62: Nonsegment expenses, as reported (incl. adjusting items) | C62: -30.942 | D62: -33.365 | E62: -39.061 | F62: -43.701 | G62: -49.362 | H62: -63.166 | I62: -58.352 | J62: -100.067 | K62: -119.447 | L62: -94.53 | M62: -23.359 | N62: -10.426 | O62: -13.546 | P62: -17.111 | Q62: -64.442 | R62: -29.365 | S62: -15.25 | T62: -19.201 | U62: -17.276 | V62: -81.092 | W62: -24.311 | X62: -58.307 | Y62: -23.875 | Z62: -24.317 | AA62: -130.811 | AB62: -26.2 | AC62: -32.834 | AD62: -29.675 | AE62: -31.036 | AF62: -119.745 | AG62: -22.104 | AH62: -26.752 | AI62: -36.13 | AJ62: -41.24 | AK62: -126.226 | AL62: -36.595 | AM62: -45.049 | AN62: -50.776 | AO62: =AO63-AO191 -> -47.11547 | AP62: =SUM(AL62:AO62) -> -179.53547 | AQ62: =AQ63-AQ191 -> -33.109966 | AR62: =AR63-AR191 -> -195.5565 | AS62: =AS63-AS191 -> -193.33146 | AT62: =AT63-AT191 -> -204.86999 | AU62: =AU63-AU191 -> -216.32298 | BD62: 2031E | BE62: =BF62+$BE$57 -> 0.09 | BF62: 0.05 | BG62: =BF62+$BG$57 -> -0.01
B63: Adjusted nonsegment expenses (model: as reported + adjusting items) | C63: =IF(ISNUMBER(C62),C62+C191,"") -> -30.942 | D63: =IF(ISNUMBER(D62),D62+D191,"") -> -33.365 | E63: =IF(ISNUMBER(E62),E62+E191,"") -> -39.061 | F63: =IF(ISNUMBER(F62),F62+F191,"") -> -43.701 | G63: =IF(ISNUMBER(G62),G62+G191,"") -> -49.362 | H63: =IF(ISNUMBER(H62),H62+H191,"") -> -63.166 | I63: =IF(ISNUMBER(I62),I62+I191,"") -> -58.352 | J63: =IF(ISNUMBER(J62),J62+J191,"") -> -24.075 | ... AN63: =IF(ISNUMBER(AN62),AN62+AN191,"") -> -41.512 | AO63: =AJ63*(1+AO64) -> -41.11547 | AP63: =SUM(AL63:AO63) -> -157.45647 | AQ63: =AQ150*AQ65 -> -164.74597 | AR63: =AR150*AR65 -> -178.5565 | AS63: =AS150*AS65 -> -191.33146 | AT63: =AT150*AT65 -> -202.86999 | AU63: =AU150*AU65 -> -214.32298 | AV63: Equals the company's adjusted nonsegment expenses where all adjusting items sit in nonsegment (FY2021+); FY2018–19 L'Orange purchase accounting sat in Industrial segment earnings. Q4/26E: prior-year quarter × (1 + 9M FY26 y/y). 2027E+: % of net sales. | BD63: IND_TRANS (Transportation y/y) | BE63: 0.04 | BF63: Δ → | BG63: -0.08 | BH63: 9M FY26 +42% (marine, rail, China OH last-time buys); China OH wound down by end of FY26 → flat FY27.
B64: Adjusted nonsegment expenses y/y % | D64: =IF(AND(ISNUMBER(D63),ISNUMBER(C63)),IFERROR(D63/C63-1,""),"") -> 0.078307802 | E64: =IF(AND(ISNUMBER(E63),ISNUMBER(D63)),IFERROR(E63/D63-1,""),"") -> 0.17071782 | F64: =IF(AND(ISNUMBER(F63),ISNUMBER(E63)),IFERROR(F63/E63-1,""),"") -> 0.11878856 | G64: =IF(AND(ISNUMBER(G63),ISNUMBER(F63)),IFERROR(G63/F63-1,""),"") -> 0.12953937 | H64: =IF(AND(ISNUMBER(H63),ISNUMBER(G63)),IFERROR(H63/G63-1,""),"") -> 0.27964831 | I64: =IF(AND(ISNUMBER(I63),ISNUMBER(H63)),IFERROR(I63/H63-1,""),"") -> -0.076211886 | J64: =IF(AND(ISNUMBER(J63),ISNUMBER(I63)),IFERROR(J63/I63-1,""),"") -> -0.58741774 | K64: =IF(AND(ISNUMBER(K63),ISNUMBER(J63)),IFERROR(K63/J63-1,""),"") -> 1.4364278 | L64: =IF(AND(ISNUMBER(L63),ISNUMBER(K63)),IFERROR(L63/K63-1,""),"") -> 0.14734814 | Q64: =IF(AND(ISNUMBER(Q63),ISNUMBER(L63)),IFERROR(Q63/L63-1,""),"") -> -0.11687964 | R64: =IF(AND(ISNUMBER(R63),ISNUMBER(M63)),IFERROR(R63/M63-1,""),"") -> -0.084592662 | S64: =IF(AND(ISNUMBER(S63),ISNUMBER(N63)),IFERROR(S63/N63-1,""),"") -> 0.62842893 | T64: =IF(AND(ISNUMBER(T63),ISNUMBER(O63)),IFERROR(T63/O63-1,""),"") -> 0.41746641 | U64: =IF(AND(ISNUMBER(U63),ISNUMBER(P63)),IFERROR(U63/P63-1,""),"") -> 0.70998926 | V64: =IF(AND(ISNUMBER(V63),ISNUMBER(Q63)),IFERROR(V63/Q63-1,""),"") -> 0.31672107 | W64: =IF(AND(ISNUMBER(W63),ISNUMBER(R63)),IFERROR(W63/R63-1,""),"") -> 0.13693121 | X64: =IF(AND(ISNUMBER(X63),ISNUMBER(S63)),IFERROR(X63/S63-1,""),"") -> 0.3800801 | ... AN64: =IF(AND(ISNUMBER(AN63),ISNUMBER(AI63)),IFERROR(AN63/AI63-1,""),"") -> 0.14896208 | AO64: =IFERROR(SUM(AL63:AN63)/SUM(AG63:AI63)-1,0) -> 0.1847473 | AP64: =IF(AND(ISNUMBER(AP63),ISNUMBER(AK63)),IFERROR(AP63/AK63-1,""),"") -> 0.18473838 | AQ64: =IF(AND(ISNUMBER(AQ63),ISNUMBER(AP63)),IFERROR(AQ63/AP63-1,""),"") -> 0.046295309 | AR64: =IF(AND(ISNUMBER(AR63),ISNUMBER(AQ63)),IFERROR(AR63/AQ63-1,""),"") -> 0.083829245 | AS64: =IF(AND(ISNUMBER(AS63),ISNUMBER(AR63)),IFERROR(AS63/AR63-1,""),"") -> 0.071545784 | AT64: =IF(AND(ISNUMBER(AT63),ISNUMBER(AS63)),IFERROR(AT63/AS63-1,""),"") -> 0.060306486 | AU64: =IF(AND(ISNUMBER(AU63),ISNUMBER(AT63)),IFERROR(AU63/AT63-1,""),"") -> 0.056454821 | BD64: 2027E | BE64: =BF64+$BE$63 -> 0.04 | BF64: 0 | BG64: =BF64+$BG$63 -> -0.08
B65: Adjusted nonsegment expenses % of net sales | C65: =IF(AND(ISNUMBER(C63),ISNUMBER(C150)),IFERROR(C63/C150,""),"") -> -0.018076745 | D65: =IF(AND(ISNUMBER(D63),ISNUMBER(D150)),IFERROR(D63/D150,""),"") -> -0.017884068 | E65: =IF(AND(ISNUMBER(E63),ISNUMBER(E150)),IFERROR(E63/E150,""),"") -> -0.020176386 | F65: =IF(AND(ISNUMBER(F63),ISNUMBER(F150)),IFERROR(F63/F150,""),"") -> -0.021836961 | G65: =IF(AND(ISNUMBER(G63),ISNUMBER(G150)),IFERROR(G63/G150,""),"") -> -0.024217204 | H65: =IF(AND(ISNUMBER(H63),ISNUMBER(H150)),IFERROR(H63/H150,""),"") -> -0.031222721 | I65: =IF(AND(ISNUMBER(I63),ISNUMBER(I150)),IFERROR(I63/I150,""),"") -> -0.027804077 | J65: =IF(AND(ISNUMBER(J63),ISNUMBER(J150)),IFERROR(J63/J150,""),"") -> -0.010350952 | ... AP65: =IF(AND(ISNUMBER(AP63),ISNUMBER(AP150)),IFERROR(AP63/AP150,""),"") -> -0.036330664 | AQ65: -0.035 | AR65: -0.035 | AS65: -0.035 | AT65: -0.035 | AU65: -0.035 | AX65: =IFERROR(AVERAGE(AQ65,AR65,AS65,AT65,AU65),"n/m") -> -0.035 | AY65: =IFERROR(AVERAGE(Q65,V65,AA65,AF65,AK65),"n/m") -> -0.03261072 | AZ65: =IFERROR(AVERAGE(H65,I65,J65,K65,L65,Q65,V65,AA65,AF65,AK65),"n/m") -> -0.027962329 | BA65: =IFERROR(AVERAGE(C65,D65,E65,F65,G65,H65,I65,J65,K65,L65,Q65,V65,AA65,AF65,AK65),"n/m") -> -0.02545431 | BD65: 2028E | BE65: =BF65+$BE$63 -> 0.08 | BF65: 0.04 | BG65: =BF65+$BG$63 -> -0.04
BD66: 2029E | BE66: =BF66+$BE$63 -> 0.08 | BF66: 0.04 | BG66: =BF66+$BG$63 -> -0.04
B67: Sales by end market (outputs) | AV67: MIX — outputs | BD67: 2030E | BE67: =BF67+$BE$63 -> 0.07 | BF67: 0.03 | BG67: =BF67+$BG$63 -> -0.05
B68: Commercial aerospace (OEM + services) | C68: =IF(ISNUMBER(C11),C11+C14,"") | D68: =IF(ISNUMBER(D11),D11+D14,"") | E68: =IF(ISNUMBER(E11),E11+E14,"") | F68: =IF(ISNUMBER(F11),F11+F14,"") | G68: =IF(ISNUMBER(G11),G11+G14,"") | H68: =IF(ISNUMBER(H11),H11+H14,"") | I68: =IF(ISNUMBER(I11),I11+I14,"") | J68: =IF(ISNUMBER(J11),J11+J14,"") | ... AU68: =IF(ISNUMBER(AU11),AU11+AU14,"") -> 2909.619 | AX68: =IFERROR((AU68/AP68)^(1/5)-1,"n/m") -> 0.081774241 | AY68: =IFERROR((AK68/L68)^(1/5)-1,"n/m") -> 0.12669313 | AZ68: =IFERROR((AK68/G68)^(1/10)-1,"n/m") -> n/m | BA68: =IFERROR((AK68/C68)^(1/14)-1,"n/m") -> n/m | BD68: 2031E | BE68: =BF68+$BE$63 -> 0.07 | BF68: 0.03 | BG68: =BF68+$BG$63 -> -0.05
B69: Defense (OEM + services) | C69: =IF(ISNUMBER(C17),C17+C20,"") | D69: =IF(ISNUMBER(D17),D17+D20,"") | E69: =IF(ISNUMBER(E17),E17+E20,"") | F69: =IF(ISNUMBER(F17),F17+F20,"") | G69: =IF(ISNUMBER(G17),G17+G20,"") | H69: =IF(ISNUMBER(H17),H17+H20,"") | I69: =IF(ISNUMBER(I17),I17+I20,"") | J69: =IF(ISNUMBER(J17),J17+J20,"") | ... AU69: =IF(ISNUMBER(AU17),AU17+AU20,"") -> 1082.0496 | AX69: =IFERROR((AU69/AP69)^(1/5)-1,"n/m") -> 0.052418146 | AY69: =IFERROR((AK69/L69)^(1/5)-1,"n/m") -> 0.010729794 | AZ69: =IFERROR((AK69/G69)^(1/10)-1,"n/m") -> n/m | BA69: =IFERROR((AK69/C69)^(1/14)-1,"n/m") -> n/m | BD69: IND_OG (Oil and gas y/y) | BE69: 0.03 | BF69: Δ → | BG69: -0.06 | BH69: 9M FY26 +18%; FY25 +14%: gas compression / midstream.
B70: Commercial aerospace % of total sales | C70: =IF(ISNUMBER(C68),IFERROR(C68/C99,""),"") | D70: =IF(ISNUMBER(D68),IFERROR(D68/D99,""),"") | E70: =IF(ISNUMBER(E68),IFERROR(E68/E99,""),"") | F70: =IF(ISNUMBER(F68),IFERROR(F68/F99,""),"") | G70: =IF(ISNUMBER(G68),IFERROR(G68/G99,""),"") | H70: =IF(ISNUMBER(H68),IFERROR(H68/H99,""),"") | I70: =IF(ISNUMBER(I68),IFERROR(I68/I99,""),"") | J70: =IF(ISNUMBER(J68),IFERROR(J68/J99,""),"") | ... AU70: =IF(ISNUMBER(AU68),IFERROR(AU68/AU99,""),"") -> 0.47515514 | AX70: =IFERROR(AVERAGE(AQ70,AR70,AS70,AT70,AU70),"n/m") -> 0.47053781 | AY70: =IFERROR(AVERAGE(Q70,V70,AA70,AF70,AK70),"n/m") -> 0.38913449 | AZ70: =IFERROR(AVERAGE(H70,I70,J70,K70,L70,Q70,V70,AA70,AF70,AK70),"n/m") -> 0.38269932 | BA70: =IFERROR(AVERAGE(C70,D70,E70,F70,G70,H70,I70,J70,K70,L70,Q70,V70,AA70,AF70,AK70),"n/m") -> 0.38269932 | BD70: 2027E | BE70: =BF70+$BE$69 -> 0.07 | BF70: 0.04 | BG70: =BF70+$BG$69 -> -0.02
B71: Defense % of total sales | C71: =IF(ISNUMBER(C69),IFERROR(C69/C99,""),"") | D71: =IF(ISNUMBER(D69),IFERROR(D69/D99,""),"") | E71: =IF(ISNUMBER(E69),IFERROR(E69/E99,""),"") | F71: =IF(ISNUMBER(F69),IFERROR(F69/F99,""),"") | G71: =IF(ISNUMBER(G69),IFERROR(G69/G99,""),"") | H71: =IF(ISNUMBER(H69),IFERROR(H69/H99,""),"") | I71: =IF(ISNUMBER(I69),IFERROR(I69/I99,""),"") | J71: =IF(ISNUMBER(J69),IFERROR(J69/J99,""),"") | ... AU71: =IF(ISNUMBER(AU69),IFERROR(AU69/AU99,""),"") -> 0.17670404 | AX71: =IFERROR(AVERAGE(AQ71,AR71,AS71,AT71,AU71),"n/m") -> 0.18194797 | AY71: =IFERROR(AVERAGE(Q71,V71,AA71,AF71,AK71),"n/m") -> 0.23648621 | AZ71: =IFERROR(AVERAGE(H71,I71,J71,K71,L71,Q71,V71,AA71,AF71,AK71),"n/m") -> 0.24787286 | BA71: =IFERROR(AVERAGE(C71,D71,E71,F71,G71,H71,I71,J71,K71,L71,Q71,V71,AA71,AF71,AK71),"n/m") -> 0.24787286 | BD71: 2028E | BE71: =BF71+$BE$69 -> 0.07 | BF71: 0.04 | BG71: =BF71+$BG$69 -> -0.02
B72: Commercial aerospace y/y % | D72: =IF(AND(ISNUMBER(D68),ISNUMBER(C68)),IFERROR(D68/C68-1,""),"") | E72: =IF(AND(ISNUMBER(E68),ISNUMBER(D68)),IFERROR(E68/D68-1,""),"") | F72: =IF(AND(ISNUMBER(F68),ISNUMBER(E68)),IFERROR(F68/E68-1,""),"") | G72: =IF(AND(ISNUMBER(G68),ISNUMBER(F68)),IFERROR(G68/F68-1,""),"") | H72: =IF(AND(ISNUMBER(H68),ISNUMBER(G68)),IFERROR(H68/G68-1,""),"") | I72: =IF(AND(ISNUMBER(I68),ISNUMBER(H68)),IFERROR(I68/H68-1,""),"") | J72: =IF(AND(ISNUMBER(J68),ISNUMBER(I68)),IFERROR(J68/I68-1,""),"") | K72: =IF(AND(ISNUMBER(K68),ISNUMBER(J68)),IFERROR(K68/J68-1,""),"") | L72: =IF(AND(ISNUMBER(L68),ISNUMBER(K68)),IFERROR(L68/K68-1,""),"") -> -0.27912311 | Q72: =IF(AND(ISNUMBER(Q68),ISNUMBER(L68)),IFERROR(Q68/L68-1,""),"") -> -0.16910528 | R72: =IF(AND(ISNUMBER(R68),ISNUMBER(M68)),IFERROR(R68/M68-1,""),"") -> 0.34828667 | S72: =IF(AND(ISNUMBER(S68),ISNUMBER(N68)),IFERROR(S68/N68-1,""),"") -> 0.28947662 | T72: =IF(AND(ISNUMBER(T68),ISNUMBER(O68)),IFERROR(T68/O68-1,""),"") -> 0.40084867 | U72: =IF(AND(ISNUMBER(U68),ISNUMBER(P68)),IFERROR(U68/P68-1,""),"") -> 0.28515559 | V72: =IF(AND(ISNUMBER(V68),ISNUMBER(Q68)),IFERROR(V68/Q68-1,""),"") -> 0.3278492 | W72: =IF(AND(ISNUMBER(W68),ISNUMBER(R68)),IFERROR(W68/R68-1,""),"") -> 0.39078738 | X72: =IF(AND(ISNUMBER(X68),ISNUMBER(S68)),IFERROR(X68/S68-1,""),"") -> 0.29066768 | ... AP72: =IF(AND(ISNUMBER(AP68),ISNUMBER(AK68)),IFERROR(AP68/AK68-1,""),"") -> 0.29682415 | AQ72: =IF(AND(ISNUMBER(AQ68),ISNUMBER(AP68)),IFERROR(AQ68/AP68-1,""),"") -> 0.11218245 | AR72: =IF(AND(ISNUMBER(AR68),ISNUMBER(AQ68)),IFERROR(AR68/AQ68-1,""),"") -> 0.093642365 | AS72: =IF(AND(ISNUMBER(AS68),ISNUMBER(AR68)),IFERROR(AS68/AR68-1,""),"") -> 0.079230943 | AT72: =IF(AND(ISNUMBER(AT68),ISNUMBER(AS68)),IFERROR(AT68/AS68-1,""),"") -> 0.064661527 | AU72: =IF(AND(ISNUMBER(AU68),ISNUMBER(AT68)),IFERROR(AU68/AT68-1,""),"") -> 0.06 | BD72: 2029E | BE72: =BF72+$BE$69 -> 0.06 | BF72: 0.03 | BG72: =BF72+$BG$69 -> -0.03
B73: Defense y/y % | D73: =IF(AND(ISNUMBER(D69),ISNUMBER(C69)),IFERROR(D69/C69-1,""),"") | E73: =IF(AND(ISNUMBER(E69),ISNUMBER(D69)),IFERROR(E69/D69-1,""),"") | F73: =IF(AND(ISNUMBER(F69),ISNUMBER(E69)),IFERROR(F69/E69-1,""),"") | G73: =IF(AND(ISNUMBER(G69),ISNUMBER(F69)),IFERROR(G69/F69-1,""),"") | H73: =IF(AND(ISNUMBER(H69),ISNUMBER(G69)),IFERROR(H69/G69-1,""),"") | I73: =IF(AND(ISNUMBER(I69),ISNUMBER(H69)),IFERROR(I69/H69-1,""),"") | J73: =IF(AND(ISNUMBER(J69),ISNUMBER(I69)),IFERROR(J69/I69-1,""),"") | K73: =IF(AND(ISNUMBER(K69),ISNUMBER(J69)),IFERROR(K69/J69-1,""),"") | L73: =IF(AND(ISNUMBER(L69),ISNUMBER(K69)),IFERROR(L69/K69-1,""),"") -> 0.046206121 | Q73: =IF(AND(ISNUMBER(Q69),ISNUMBER(L69)),IFERROR(Q69/L69-1,""),"") -> -0.060499674 | R73: =IF(AND(ISNUMBER(R69),ISNUMBER(M69)),IFERROR(R69/M69-1,""),"") -> -0.19185766 | S73: =IF(AND(ISNUMBER(S69),ISNUMBER(N69)),IFERROR(S69/N69-1,""),"") -> -0.23704784 | T73: =IF(AND(ISNUMBER(T69),ISNUMBER(O69)),IFERROR(T69/O69-1,""),"") -> -0.047689724 | U73: =IF(AND(ISNUMBER(U69),ISNUMBER(P69)),IFERROR(U69/P69-1,""),"") -> -0.14440443 | V73: =IF(AND(ISNUMBER(V69),ISNUMBER(Q69)),IFERROR(V69/Q69-1,""),"") -> -0.15755239 | W73: =IF(AND(ISNUMBER(W69),ISNUMBER(R69)),IFERROR(W69/R69-1,""),"") -> -0.10552284 | X73: =IF(AND(ISNUMBER(X69),ISNUMBER(S69)),IFERROR(X69/S69-1,""),"") -> -0.021321313 | ... AP73: =IF(AND(ISNUMBER(AP69),ISNUMBER(AK69)),IFERROR(AP69/AK69-1,""),"") -> 0.049883332 | AQ73: =IF(AND(ISNUMBER(AQ69),ISNUMBER(AP69)),IFERROR(AQ69/AP69-1,""),"") -> 0.063975886 | AR73: =IF(AND(ISNUMBER(AR69),ISNUMBER(AQ69)),IFERROR(AR69/AQ69-1,""),"") -> 0.057027508 | AS73: =IF(AND(ISNUMBER(AS69),ISNUMBER(AR69)),IFERROR(AS69/AR69-1,""),"") -> 0.04704727 | AT73: =IF(AND(ISNUMBER(AT69),ISNUMBER(AS69)),IFERROR(AT69/AS69-1,""),"") -> 0.047067144 | AU73: =IF(AND(ISNUMBER(AU69),ISNUMBER(AT69)),IFERROR(AU69/AT69-1,""),"") -> 0.047086939 | BD73: 2030E | BE73: =BF73+$BE$69 -> 0.06 | BF73: 0.03 | BG73: =BF73+$BG$69 -> -0.03
B74: Contribution to total sales growth — Aerospace (pp) | D74: =IFERROR((D23-C23)/C99,"") -> 0.030993128 | E74: =IFERROR((E23-D23)/D99,"") -> 0.088653305 | F74: =IFERROR((F23-E23)/E99,"") -> 0.011646839 | G74: =IFERROR((G23-F23)/F99,"") -> 0.038405189 | H74: =IFERROR((H23-G23)/G99,"") -> 0.035467249 | I74: =IFERROR((I23-H23)/H99,"") -> 0.053958869 | J74: =IFERROR((J23-I23)/I99,"") -> 0.10275434 | K74: =IFERROR((K23-J23)/J99,"") -> 0.13867137 | L74: =IFERROR((L23-K23)/K99,"") -> -0.099840459 | Q74: =IFERROR((Q23-L23)/L99,"") -> -0.074868221 | R74: =IFERROR((R23-M23)/M99,"") -> 0.027469267 | S74: =IFERROR((S23-N23)/N99,"") -> 0.013849491 | T74: =IFERROR((T23-O23)/O99,"") -> 0.10921992 | U74: =IFERROR((U23-P23)/P99,"") -> 0.055392947 | V74: =IFERROR((V23-Q23)/Q99,"") -> 0.051297248 | W74: =IFERROR((W23-R23)/R99,"") -> 0.10940091 | X74: =IFERROR((X23-S23)/S99,"") -> 0.10950192 | ... AP74: =IFERROR((AP23-AK23)/AK99,"") -> 0.13718973 | AQ74: =IFERROR((AQ23-AP23)/AP99,"") -> 0.063210114 | AR74: =IFERROR((AR23-AQ23)/AQ99,"") -> 0.054260248 | AS74: =IFERROR((AS23-AR23)/AR99,"") -> 0.04579412 | AT74: =IFERROR((AT23-AS23)/AS99,"") -> 0.038993706 | AU74: =IFERROR((AU23-AT23)/AT99,"") -> 0.036808851 | BD74: 2031E | BE74: =BF74+$BE$69 -> 0.06 | BF74: 0.03 | BG74: =BF74+$BG$69 -> -0.03
B75: Contribution to total sales growth — Industrial (pp) | D75: =IFERROR((D45-C45)/C99,"") -> 0.058931987 | E75: =IFERROR((E45-D45)/D99,"") -> -0.050945339 | F75: =IFERROR((F45-E45)/E99,"") -> 0.022064323 | G75: =IFERROR((G45-F45)/F99,"") -> -0.019885171 | H75: =IFERROR((H45-G45)/G99,"") -> -0.042936698 | I75: =IFERROR((I45-H45)/H99,"") -> -0.016586607 | J75: =IFERROR((J45-I45)/I99,"") -> 0.0054982048 | K75: =IFERROR((K45-J45)/J99,"") -> 0.10825699 | L75: =IFERROR((L45-K45)/K99,"") -> -0.039643859 | Q75: =IFERROR((Q45-L45)/L99,"") -> -0.025238564 | R75: =IFERROR((R45-M45)/M99,"") -> -0.020090436 | S75: =IFERROR((S45-N45)/N99,"") -> -0.0043573172 | T75: =IFERROR((T45-O45)/O99,"") -> -0.0056460233 | U75: =IFERROR((U45-P45)/P99,"") -> 0.067044651 | V75: =IFERROR((V45-Q45)/Q99,"") -> 0.0096859427 | W75: =IFERROR((W45-R45)/R99,"") -> 0.032835044 | X75: =IFERROR((X45-S45)/S99,"") -> 0.11436697 | ... AP75: =IFERROR((AP45-AK45)/AK99,"") -> 0.077810267 | AQ75: =IFERROR((AQ45-AP45)/AP99,"") -> 0.019018681 | AR75: =IFERROR((AR45-AQ45)/AQ99,"") -> 0.022133307 | AS75: =IFERROR((AS45-AR45)/AR99,"") -> 0.018548063 | AT75: =IFERROR((AT45-AS45)/AS99,"") -> 0.014254022 | AU75: =IFERROR((AU45-AT45)/AT99,"") -> 0.012655825 | BD75: AERO_M (Aerospace segment margin) | BE75: 0.01 | BF75: Δ → | BG75: -0.02 | BH75: FY26 guided ~23.5% (FY25 21.9%, FY19 peak 20.7%); price and volume leverage vs Spartanburg start-up costs (2027).
BD76: 2027E | BE76: =BF76+$BE$75 -> 0.25 | BF76: 0.24 | BG76: =BF76+$BG$75 -> 0.22
B77: Future acquisitions (M&A lever — Aerospace / Industrial bolt-ons, unallocated; deals closed from 2027E) | AV77: M&A LEVER — acquired revenue = spend ÷ EV/sales; mid-year convention | BD77: 2028E | BE77: =BF77+$BE$75 -> 0.255 | BF77: 0.245 | BG77: =BF77+$BG$75 -> 0.225
B78: Acquisition spend (USDm, scenario) | AP78: 0 | AQ78: =MAX(0,CHOOSE(MATCH($AV$2,{"Bull","Base","Bear"},0),$BE$88,$BF$88,$BG$88)) -> 100 | AR78: =MAX(0,CHOOSE(MATCH($AV$2,{"Bull","Base","Bear"},0),$BE$89,$BF$89,$BG$89)) -> 100 | AS78: =MAX(0,CHOOSE(MATCH($AV$2,{"Bull","Base","Bear"},0),$BE$90,$BF$90,$BG$90)) -> 100 | AT78: =MAX(0,CHOOSE(MATCH($AV$2,{"Bull","Base","Bear"},0),$BE$91,$BF$91,$BG$91)) -> 100 | AU78: =MAX(0,CHOOSE(MATCH($AV$2,{"Bull","Base","Bear"},0),$BE$92,$BF$92,$BG$92)) -> 100 | AV78: Scenario lever M&A_spend (Base $100m p.a. of bolt-ons). Funded from cash / revolver (debt schedule). | BD78: 2029E | BE78: =BF78+$BE$75 -> 0.26 | BF78: 0.25 | BG78: =BF78+$BG$75 -> 0.23
B79: Purchase multiple — EV / sales (x) | AP79: 0 | AQ79: 3 | AR79: 3 | AS79: 3 | AT79: 3 | AU79: 3 | AV79: L'Orange (Jun-2018) $771m on ~$290m annual sales (~2.7x); Valve Research (Apr-2026) $121m; Safran EMA (Jul-2025) $40m. 3.0x input (assumption). | BD79: 2030E | BE79: =BF79+$BE$75 -> 0.263 | BF79: 0.253 | BG79: =BF79+$BG$75 -> 0.233
B80: Annualised revenue acquired in the year | AP80: 0 | AQ80: =IFERROR(AQ78/AQ79,0) -> 33.333333 | AR80: =IFERROR(AR78/AR79,0) -> 33.333333 | AS80: =IFERROR(AS78/AS79,0) -> 33.333333 | AT80: =IFERROR(AT78/AT79,0) -> 33.333333 | AU80: =IFERROR(AU78/AU79,0) -> 33.333333 | BD80: 2031E | BE80: =BF80+$BE$75 -> 0.265 | BF80: 0.255 | BG80: =BF80+$BG$75 -> 0.235
B81: Growth of acquired businesses after acquisition % | AP81: 0 | AQ81: 0.05 | AR81: 0.05 | AS81: 0.05 | AT81: 0.05 | AU81: 0.05 | BD81: IND_M (Industrial segment margin) | BE81: 0.01 | BF81: Δ → | BG81: -0.03 | BH81: FY26 guided ~19% (FY25 14.6%, FY24 17.7%); China OH exit accretive; cyclical downside (FY18 6.2%).
B82: Run-rate revenue of businesses acquired (year end) | AP82: 0 | AQ82: =AP82*(1+AQ81)+AQ80 -> 33.333333 | AR82: =AQ82*(1+AR81)+AR80 -> 68.333333 | AS82: =AR82*(1+AS81)+AS80 -> 105.08333 | AT82: =AS82*(1+AT81)+AT80 -> 143.67083 | AU82: =AT82*(1+AU81)+AU80 -> 184.18771 | BD82: 2027E | BE82: =BF82+$BE$81 -> 0.2 | BF82: 0.19 | BG82: =BF82+$BG$81 -> 0.16
B83: Revenue from future acquisitions | AP83: 0 | AQ83: =AP82*(1+AQ81)+0.5*AQ80 -> 16.666667 | AR83: =AQ82*(1+AR81)+0.5*AR80 -> 51.666667 | AS83: =AR82*(1+AS81)+0.5*AS80 -> 88.416667 | AT83: =AS82*(1+AT81)+0.5*AT80 -> 127.00417 | AU83: =AT82*(1+AU81)+0.5*AU80 -> 167.52104 | AV83: Mid-year convention. | BD83: 2028E | BE83: =BF83+$BE$81 -> 0.202 | BF83: 0.192 | BG83: =BF83+$BG$81 -> 0.162
B84: Earnings margin of acquired businesses (after amortization) % | AP84: 0 | AQ84: 0.15 | AR84: 0.15 | AS84: 0.15 | AT84: 0.15 | AU84: 0.15 | BD84: 2029E | BE84: =BF84+$BE$81 -> 0.205 | BF84: 0.195 | BG84: =BF84+$BG$81 -> 0.165
B85: Earnings from future acquisitions | AP85: 0 | AQ85: =AQ83*AQ84 -> 2.5 | AR85: =AR83*AR84 -> 7.75 | AS85: =AS83*AS84 -> 13.2625 | AT85: =AT83*AT84 -> 19.050625 | AU85: =AU83*AU84 -> 25.128156 | BD85: 2030E | BE85: =BF85+$BE$81 -> 0.207 | BF85: 0.197 | BG85: =BF85+$BG$81 -> 0.167
B86: PP&E % of spend | AP86: 0 | AQ86: 0.1 | AR86: 0.1 | AS86: 0.1 | AT86: 0.1 | AU86: 0.1 | BD86: 2031E | BE86: =BF86+$BE$81 -> 0.21 | BF86: 0.2 | BG86: =BF86+$BG$81 -> 0.17
B87: Acquired intangibles % of spend | AP87: 0 | AQ87: 0.4 | AR87: 0.4 | AS87: 0.4 | AT87: 0.4 | AU87: 0.4 | AV87: PPAs: L'Orange 74% of the purchase price in intangibles, Valve Research 30%, Safran EMA 0%. | BD87: M&A_spend (bolt-on acquisitions, $m) | BE87: 100 | BF87: Δ → | BG87: -100 | BH87: Woodward spent $40m (Safran EMA, FY25) and $121m (Valve Research, FY26) on bolt-ons besides L'Orange ($771m, FY18). Base $100m p.a. (assumption).
B88: Intangible amortization life (years) | AP88: 0 | AQ88: 15 | AR88: 15 | AS88: 15 | AT88: 15 | AU88: 15 | BD88: 2027E | BE88: =MAX(0,BF88+$BE$87) -> 200 | BF88: 100 | BG88: =MAX(0,BF88+$BG$87) -> 0
B89: Cumulative acquired intangibles (gross) | AP89: 0 | AQ89: =AP89+AQ78*AQ87 -> 40 | AR89: =AQ89+AR78*AR87 -> 80 | AS89: =AR89+AS78*AS87 -> 120 | AT89: =AS89+AT78*AT87 -> 160 | AU89: =AT89+AU78*AU87 -> 200 | BD89: 2028E | BE89: =MAX(0,BF89+$BE$87) -> 200 | BF89: 100 | BG89: =MAX(0,BF89+$BG$87) -> 0
B90: Amortization of future-acquisition intangibles (inside segment earnings) | AP90: 0 | AQ90: =IFERROR((AP89+0.5*AQ78*AQ87)/AQ88,0) -> 1.3333333 | AR90: =IFERROR((AQ89+0.5*AR78*AR87)/AR88,0) -> 4 | AS90: =IFERROR((AR89+0.5*AS78*AS87)/AS88,0) -> 6.6666667 | AT90: =IFERROR((AS89+0.5*AT78*AT87)/AT88,0) -> 9.3333333 | AU90: =IFERROR((AT89+0.5*AU78*AU87)/AU88,0) -> 12 | AV90: Woodward does not adjust out amortization; the acquired-business margin above is after amortization. | BD90: 2029E | BE90: =MAX(0,BF90+$BE$87) -> 200 | BF90: 100 | BG90: =MAX(0,BF90+$BG$87) -> 0
BD91: 2030E | BE91: =MAX(0,BF91+$BE$87) -> 200 | BF91: 100 | BG91: =MAX(0,BF91+$BG$87) -> 0
B92: Pending divestitures — Aerospace pilot controls (to ONTIC, $180m; close expected FY2027) · Santa Clarita product lines & campus (terms not disclosed) | AV92: DIVESTITURES — gain recorded in other income, net and excluded from adjusted earnings (company practice for divestitures) | BD92: 2031E | BE92: =MAX(0,BF92+$BE$87) -> 200 | BF92: 100 | BG92: =MAX(0,BF92+$BG$87) -> 0
B93: Cash proceeds (USDm; ONTIC $180m in 2027E) | AP93: 0 | AQ93: 180 | AR93: 0 | AS93: 0 | AT93: 0 | AU93: 0 | AV93: Sale of the Aerospace pilot controls product line to ONTIC for $180.0m (definitive agreement 15-Apr-2026; close expected FY27, accounting gain expected). Held for sale at 30-Jun-2026: assets $20.0m, liabilities $3.6m (Q3 FY26 10-Q Note 10). Revenue of the product line not disclosed.
B94: Net assets held for sale (30-Jun-2026: assets $20.0m − liabilities $3.6m) | AP94: 0 | AQ94: 16.364 | AR94: 0 | AS94: 0 | AT94: 0 | AU94: 0
B95: Pre-tax gain on sale (assumption: proceeds − net assets held for sale; goodwill allocation not disclosed) | AP95: 0 | AQ95: =AQ93-AQ94 -> 163.636 | AR95: =AR93-AR94 -> 0 | AS95: =AS93-AS94 -> 0 | AT95: =AT93-AT94 -> 0 | AU95: =AU93-AU94 -> 0
B96: Sales of the divested product lines (not disclosed — input 0; flag) | AP96: 0 | AQ96: 0 | AR96: 0 | AS96: 0 | AT96: 0 | AU96: 0 | AV96: Neither the pilot-controls nor the Santa Clarita product-line sales are disclosed; no revenue is removed from the Aerospace build (assumption).
B98: Group Total — net sales & adjusted EBIT (segment build) → FY26 guidance calibration | AV98: GROUP TOTAL (CONSOLIDATED) — modelling logic
B99: Net sales (segment build) | C99: =IF(ISNUMBER(C23),C23+C45,C150) -> 1711.702 | D99: =IF(ISNUMBER(D23),D23+D45,D150) -> 1865.627 | E99: =IF(ISNUMBER(E23),E23+E45,E150) -> 1935.976 | F99: =IF(ISNUMBER(F23),F23+F45,F150) -> 2001.24 | G99: =IF(ISNUMBER(G23),G23+G45,G150) -> 2038.303 | H99: =IF(ISNUMBER(H23),H23+H45,H150) -> 2023.078 | I99: =IF(ISNUMBER(I23),I23+I45,I150) -> 2098.685 | J99: =IF(ISNUMBER(J23),J23+J45,J150) -> 2325.873 | ... AN99: =IF(ISNUMBER(AN23),AN23+AN45,AN150) -> 1109.705 | AO99: =AO23+AO45+N(AO83)-N(AO96) -> 1137.2558 | AP99: =AP23+AP45+N(AP83)-N(AP96) -> 4333.9828 | AQ99: =AQ23+AQ45+N(AQ83)-N(AQ96) -> 4707.0276 | AR99: =AR23+AR45+N(AR83)-N(AR96) -> 5101.6142 | AS99: =AS23+AS45+N(AS83)-N(AS96) -> 5466.6132 | AT99: =AT23+AT45+N(AT83)-N(AT96) -> 5796.2854 | AU99: =AU23+AU45+N(AU83)-N(AU96) -> 6123.5137 | AV99: Σ segment sales (+ future acquisitions − divested product lines from 2027E). | AX99: =IFERROR((AU99/AP99)^(1/5)-1,"n/m") -> 0.071575319 | AY99: =IFERROR((AK99/L99)^(1/5)-1,"n/m") -> 0.074051047 | AZ99: =IFERROR((AK99/G99)^(1/10)-1,"n/m") -> 0.057558051 | BA99: =IFERROR((AK99/C99)^(1/14)-1,"n/m") -> 0.053846455
B100: Net sales y/y % | D100: =IF(AND(ISNUMBER(D99),ISNUMBER(C99)),IFERROR(D99/C99-1,""),"") -> 0.089925115 | E100: =IF(AND(ISNUMBER(E99),ISNUMBER(D99)),IFERROR(E99/D99-1,""),"") -> 0.037707966 | F100: =IF(AND(ISNUMBER(F99),ISNUMBER(E99)),IFERROR(F99/E99-1,""),"") -> 0.033711162 | G100: =IF(AND(ISNUMBER(G99),ISNUMBER(F99)),IFERROR(G99/F99-1,""),"") -> 0.018520018 | H100: =IF(AND(ISNUMBER(H99),ISNUMBER(G99)),IFERROR(H99/G99-1,""),"") -> -0.0074694489 | I100: =IF(AND(ISNUMBER(I99),ISNUMBER(H99)),IFERROR(I99/H99-1,""),"") -> 0.037372261 | J100: =IF(AND(ISNUMBER(J99),ISNUMBER(I99)),IFERROR(J99/I99-1,""),"") -> 0.10825255 | K100: =IF(AND(ISNUMBER(K99),ISNUMBER(J99)),IFERROR(K99/J99-1,""),"") -> 0.24692836 | L100: =IF(AND(ISNUMBER(L99),ISNUMBER(K99)),IFERROR(L99/K99-1,""),"") -> -0.13948432 | Q100: =IF(AND(ISNUMBER(Q99),ISNUMBER(L99)),IFERROR(Q99/L99-1,""),"") -> -0.10010679 | R100: =IF(AND(ISNUMBER(R99),ISNUMBER(M99)),IFERROR(R99/M99-1,""),"") -> 0.0073788315 | S100: =IF(AND(ISNUMBER(S99),ISNUMBER(N99)),IFERROR(S99/N99-1,""),"") -> 0.0094921739 | T100: =IF(AND(ISNUMBER(T99),ISNUMBER(O99)),IFERROR(T99/O99-1,""),"") -> 0.1035739 | U100: =IF(AND(ISNUMBER(U99),ISNUMBER(P99)),IFERROR(U99/P99-1,""),"") -> 0.1224376 | V100: =IF(AND(ISNUMBER(V99),ISNUMBER(Q99)),IFERROR(V99/Q99-1,""),"") -> 0.06098319 | W100: =IF(AND(ISNUMBER(W99),ISNUMBER(R99)),IFERROR(W99/R99-1,""),"") -> 0.14223595 | X100: =IF(AND(ISNUMBER(X99),ISNUMBER(S99)),IFERROR(X99/S99-1,""),"") -> 0.2238689 | ... AP100: =IF(AND(ISNUMBER(AP99),ISNUMBER(AK99)),IFERROR(AP99/AK99-1,""),"") -> 0.215 | AQ100: =IF(AND(ISNUMBER(AQ99),ISNUMBER(AP99)),IFERROR(AQ99/AP99-1,""),"") -> 0.086074373 | AR100: =IF(AND(ISNUMBER(AR99),ISNUMBER(AQ99)),IFERROR(AR99/AQ99-1,""),"") -> 0.083829245 | AS100: =IF(AND(ISNUMBER(AS99),ISNUMBER(AR99)),IFERROR(AS99/AR99-1,""),"") -> 0.071545784 | AT100: =IF(AND(ISNUMBER(AT99),ISNUMBER(AS99)),IFERROR(AT99/AS99-1,""),"") -> 0.060306486 | AU100: =IF(AND(ISNUMBER(AU99),ISNUMBER(AT99)),IFERROR(AU99/AT99-1,""),"") -> 0.056454821
B101: Check: segment build vs consolidated net sales (should be 0) | C101: =IF(ISNUMBER(C99),IF(ABS(C99-C150)<=0.15,0,ROUND(C99-C150,1)),"") -> 0 | D101: =IF(ISNUMBER(D99),IF(ABS(D99-D150)<=0.15,0,ROUND(D99-D150,1)),"") -> 0 | E101: =IF(ISNUMBER(E99),IF(ABS(E99-E150)<=0.15,0,ROUND(E99-E150,1)),"") -> 0 | F101: =IF(ISNUMBER(F99),IF(ABS(F99-F150)<=0.15,0,ROUND(F99-F150,1)),"") -> 0 | G101: =IF(ISNUMBER(G99),IF(ABS(G99-G150)<=0.15,0,ROUND(G99-G150,1)),"") -> 0 | H101: =IF(ISNUMBER(H99),IF(ABS(H99-H150)<=0.15,0,ROUND(H99-H150,1)),"") -> 0 | I101: =IF(ISNUMBER(I99),IF(ABS(I99-I150)<=0.15,0,ROUND(I99-I150,1)),"") -> 0 | J101: =IF(ISNUMBER(J99),IF(ABS(J99-J150)<=0.15,0,ROUND(J99-J150,1)),"") -> 0 | ... AU101: =IF(ISNUMBER(AU99),IF(ABS(AU99-AU150)<=0.15,0,ROUND(AU99-AU150,1)),"") -> 0
...

Sheet Bull-Base-Bear
B2: Woodward, Inc. (WWD) — Bull / Base / Bear Case P&L Summary | J2: Share price ($): | K2: =Model!$AQ$420 -> 382.17
B3: Adjusted figures (company definitions: adjusted EBIT, adjusted EBITDA, adjusted EPS) · USD millions · fiscal years ended 30 September · Live panel linked to Model — toggle scenario via Model!AV2. Bull and Bear panels are value snapshots generated from the Model with the switch set to each case. FY2026E = Q1–Q3 actual + Q4 calibrated to the FY26 guidance (sales +20–23%, adjusted EPS $9.30–9.50). | J3: As of: | K3: =TODAY() -> 2026-10-07 00:00:00
B5: Scenario: | C5: =Model!$AV$2 -> Base | N5: Scenario: | O5: Bull | P5: Snapshot (values) — Model run with switch = Bull | Z5: Scenario: | AA5: Bear | AB5: Snapshot (values) — Model run with switch = Bear
B7: (USDm, except EPS and shares) | C7: 2026E | D7: 2027E | E7: 2028E | F7: 2029E | G7: 2030E | H7: 2031E | I7: 26-'31 CAGR | J7: LT Hist Avg | K7: LT Hist Min | L7: LT Hist Max | N7: (USDm, except EPS and shares) | O7: 2026E | P7: 2027E | Q7: 2028E | R7: 2029E | S7: 2030E | T7: 2031E | U7: 26-'31 CAGR | V7: LT Hist Avg | W7: LT Hist Min | X7: LT Hist Max | Z7: (USDm, except EPS and shares) | AA7: 2026E | AB7: 2027E | AC7: 2028E | AD7: 2029E | AE7: 2030E | AF7: 2031E | AG7: 26-'31 CAGR | AH7: LT Hist Avg | AI7: LT Hist Min | AJ7: LT Hist Max
B9: Net sales | C9: =Model!AP150 -> 4333.9828 | D9: =Model!AQ150 -> 4707.0276 | E9: =Model!AR150 -> 5101.6142 | F9: =Model!AS150 -> 5466.6132 | G9: =Model!AT150 -> 5796.2854 | H9: =Model!AU150 -> 6123.5137 | I9: =IFERROR((H9/C9)^(1/5)-1,"n/m") -> 0.071575319 | N9: Net sales | O9: 4387.4887 | P9: 4932.2285 | Q9: 5546.4013 | R9: 6161.6821 | S9: 6769.7071 | T9: 7405.5381 | U9: 0.11037103 | Z9: Net sales | AA9: 4280.4768 | AB9: 4379.054 | AC9: 4457.4338 | AD9: 4485.8453 | AE9: 4466.6351 | AF9: 4432.509 | AG9: 0.0070046959
B10: Net sales y/y % | D10: =IFERROR(D9/C9-1,"") -> 0.086074373 | E10: =IFERROR(E9/D9-1,"") -> 0.083829245 | F10: =IFERROR(F9/E9-1,"") -> 0.071545784 | G10: =IFERROR(G9/F9-1,"") -> 0.060306486 | H10: =IFERROR(H9/G9-1,"") -> 0.056454821 | N10: Net sales y/y % | P10: 0.12415753 | Q10: 0.12452237 | R10: 0.11093335 | S10: 0.098678399 | T10: 0.093922973 | Z10: Net sales y/y % | AB10: 0.023029502 | AC10: 0.017898781 | AD10: 0.0063739604 | AE10: -0.0042824042 | AF10: -0.0076402208
B11: Aerospace segment sales y/y % | C11: =Model!AP242 -> 0.21158911 | D11: =Model!AQ242 -> 0.09776405 | E11: =Model!AR242 -> 0.083028071 | F11: =Model!AS242 -> 0.070125188 | G11: =Model!AT242 -> 0.059790886 | H11: =Model!AU242 -> 0.056468204 | N11: Aerospace segment sales y/y % | O11: 0.22695865 | P11: 0.12994682 | Q11: 0.11548682 | R11: 0.10277544 | S11: 0.09254294 | T11: 0.08926244 | Z11: Aerospace segment sales y/y % | AA11: 0.19621957 | AB11: 0.043758936 | AC11: 0.028788598 | AD11: 0.015717458 | AE11: 0.0053616325 | AF11: 0.0020385845
B12: Adjusted EBITDA | C12: =Model!AP214 -> 913.5007 | D12: =Model!AQ214 -> 1024.7817 | E12: =Model!AR214 -> 1139.0037 | F12: =Model!AS214 -> 1246.7652 | G12: =Model!AT214 -> 1335.8274 | H12: =Model!AU214 -> 1422.7568 | I12: =IFERROR((H12/C12)^(1/5)-1,"n/m") -> 0.092658275 | N12: Adjusted EBITDA | O12: 921.13377 | P12: 1121.0404 | Q12: 1289.2138 | R12: 1459.4421 | S12: 1617.0928 | T12: 1780.5846 | U12: 0.14090105 | Z12: Adjusted EBITDA | AA12: 905.85902 | AB12: 853.8193 | AC12: 896.80065 | AD12: 927.13431 | AE12: 937.12811 | AF12: 941.22601 | AG12: 0.0076893323
B13: Adjusted EBITDA margin % | C13: =IFERROR(C12/C9,"") -> 0.21077626 | D13: =IFERROR(D12/D9,"") -> 0.21771312 | E13: =IFERROR(E12/E9,"") -> 0.22326339 | F13: =IFERROR(F12/F9,"") -> 0.22806904 | G13: =IFERROR(G12/G9,"") -> 0.23046266 | H13: =IFERROR(H12/H9,"") -> 0.23234321 | J13: =IFERROR(AVERAGE(Model!C215,Model!D215,Model!E215,Model!F215,Model!G215,Model!H215,Model!I215,Model!J215,Model!K215,Model!L215,Model!Q215,Model!V215,Model!AA215,Model!AF215,Model!AK215),"") -> 0.17136239 | K13: =IFERROR(MIN(Model!C215,Model!D215,Model!E215,Model!F215,Model!G215,Model!H215,Model!I215,Model!J215,Model!K215,Model!L215,Model!Q215,Model!V215,Model!AA215,Model!AF215,Model!AK215),"") -> 0.14944288 | L13: =IFERROR(MAX(Model!C215,Model!D215,Model!E215,Model!F215,Model!G215,Model!H215,Model!I215,Model!J215,Model!K215,Model!L215,Model!Q215,Model!V215,Model!AA215,Model!AF215,Model!AK215),"") -> 0.19005596 | N13: Adjusted EBITDA margin % | O13: 0.20994556 | P13: 0.22728883 | Q13: 0.23244149 | R13: 0.23685773 | S13: 0.2388719 | T13: 0.24043959 | V13: 0.17136239 | W13: 0.14944288 | X13: 0.19005596 | Z13: Adjusted EBITDA margin % | AA13: 0.21162573 | AB13: 0.19497802 | AC13: 0.20119214 | AD13: 0.20667996 | AE13: 0.20980628 | AF13: 0.2123461 | AH13: 0.17136239 | AI13: 0.14944288 | AJ13: 0.19005596
B15: EBIT (GAAP) | C15: =Model!AP160 -> 768.9607 | D15: =Model!AQ160 -> 1014.3647 | E15: =Model!AR160 -> 958.35434 | F15: =Model!AS160 -> 1064.7626 | G15: =Model!AT160 -> 1142.6146 | H15: =Model!AU160 -> 1219.5455 | I15: =IFERROR((H15/C15)^(1/5)-1,"n/m") -> 0.096626588 | N15: EBIT (GAAP) | O15: 776.59377 | P15: 1102.1105 | Q15: 1091.4447 | R15: 1250.701 | S15: 1387.2377 | T15: 1530.0406 | U15: 0.14525398 | Z15: EBIT (GAAP) | AA15: 761.31902 | AB15: 854.27906 | AC15: 738.2558 | AD15: 779.29833 | AE15: 789.81959 | AF15: 795.98077 | AG15: 0.0089442727
B16: EBIT y/y % | D16: =IFERROR(D15/C15-1,"") -> 0.31913727 | E16: =IFERROR(E15/D15-1,"") -> -0.055217203 | F16: =IFERROR(F15/E15-1,"") -> 0.11103231 | G16: =IFERROR(G15/F15-1,"") -> 0.073116755 | H16: =IFERROR(H15/G15-1,"") -> 0.067328782 | N16: EBIT y/y % | P16: 0.41915962 | Q16: -0.009677598 | R16: 0.14591325 | S16: 0.10916819 | T16: 0.10294042 | Z16: EBIT y/y % | AB16: 0.12210392 | AC16: -0.13581423 | AD16: 0.055593918 | AE16: 0.013500939 | AF16: 0.0078007433
B17: EBIT margin (GAAP) % | C17: =IFERROR(C15/C9,"") -> 0.17742588 | D17: =IFERROR(D15/D9,"") -> 0.21550006 | E17: =IFERROR(E15/E9,"") -> 0.18785316 | F17: =IFERROR(F15/F9,"") -> 0.19477556 | G17: =IFERROR(G15/G9,"") -> 0.19712877 | H17: =IFERROR(H15/H9,"") -> 0.19915779 | J17: =IFERROR(AVERAGE(Model!C253,Model!D253,Model!E253,Model!F253,Model!G253,Model!H253,Model!I253,Model!J253,Model!K253,Model!L253,Model!Q253,Model!V253,Model!AA253,Model!AF253,Model!AK253),"") -> 0.12466827 | K17: =IFERROR(MIN(Model!C253,Model!D253,Model!E253,Model!F253,Model!G253,Model!H253,Model!I253,Model!J253,Model!K253,Model!L253,Model!Q253,Model!V253,Model!AA253,Model!AF253,Model!AK253),"") -> 0.09762883 | L17: =IFERROR(MAX(Model!C253,Model!D253,Model!E253,Model!F253,Model!G253,Model!H253,Model!I253,Model!J253,Model!K253,Model!L253,Model!Q253,Model!V253,Model!AA253,Model!AF253,Model!AK253),"") -> 0.15780793 | N17: EBIT margin (GAAP) % | O17: 0.17700188 | P17: 0.22345082 | Q17: 0.19678431 | R17: 0.20298045 | S17: 0.20491843 | T17: 0.20660762 | V17: 0.12466827 | W17: 0.09762883 | X17: 0.15780793 | Z17: EBIT margin (GAAP) % | AA17: 0.17785846 | AB17: 0.19508301 | AC17: 0.1656235 | AD17: 0.17372385 | AE17: 0.17682653 | AF17: 0.17957793 | AH17: 0.12466827 | AI17: 0.09762883 | AJ17: 0.15780793
B19: Adjusted Net Earnings | C19: =Model!AP228 -> 574.51469 | D19: =Model!AQ228 -> 637.49725 | E19: =Model!AR228 -> 698.27579 | F19: =Model!AS228 -> 763.02328 | G19: =Model!AT228 -> 817.55878 | H19: =Model!AU228 -> 872.23181 | I19: =IFERROR((H19/C19)^(1/5)-1,"n/m") -> 0.087091643 | N19: Adjusted Net Earnings | O19: 580.31582 | P19: 703.16758 | Q19: 778.17112 | R19: 878.35644 | S19: 972.42817 | T19: 1072.1578 | U19: 0.13062573 | Z19: Adjusted Net Earnings | AA19: 568.70702 | AB19: 515.76324 | AC19: 542.73977 | AD19: 561.87956 | AE19: 569.03448 | AF19: 572.88127 | AG19: 0.0014636894
B21: FDSO (m) | C21: =Model!AP175 -> 61.118584 | D21: =Model!AQ175 -> 59.757613 | E21: =Model!AR175 -> 58.510436 | F21: =Model!AS175 -> 57.46884 | G21: =Model!AT175 -> 56.394854 | H21: =Model!AU175 -> 55.342988 | I21: =IFERROR((H21/C21)^(1/5)-1,"n/m") -> -0.019657425 | N21: FDSO (m) | O21: 61.085876 | P21: 58.885371 | Q21: 56.930665 | R21: 55.654596 | S21: 54.27666 | T21: 52.853958 | U21: -0.028534592 | Z21: FDSO (m) | AA21: 61.151292 | AB21: 60.627819 | AC21: 60.099639 | AD21: 59.321887 | AE21: 58.585025 | AF21: 57.936397 | AG21: -0.010742916
B23: Adjusted EPS — Diluted ($) | C23: =Model!AP231 -> 9.4 | D23: =Model!AQ231 -> 10.668051 | E23: =Model!AR231 -> 11.934209 | F23: =Model!AS231 -> 13.277165 | G23: =Model!AT231 -> 14.497046 | H23: =Model!AU231 -> 15.760476 | I23: =IFERROR((H23/C23)^(1/5)-1,"n/m") -> 0.10888956 | N23: Adjusted EPS — Diluted ($) | O23: 9.5 | P23: 11.941295 | Q23: 13.668752 | R23: 15.78228 | S23: 17.916139 | T23: 20.28529 | U23: 0.16383529 | Z23: Adjusted EPS — Diluted ($) | AA23: 9.3 | AB23: 8.5070393 | AC23: 9.030666 | AD23: 9.4717075 | AE23: 9.7129682 | AF23: 9.8881066 | AG23: 0.012339164
B24: EPS y/y % | D24: =IFERROR(D23/C23-1,"") -> 0.13489902 | E24: =IFERROR(E23/D23-1,"") -> 0.11868697 | F24: =IFERROR(F23/E23-1,"") -> 0.11252994 | G24: =IFERROR(G23/F23-1,"") -> 0.091878101 | H24: =IFERROR(H23/G23-1,"") -> 0.087150839 | N24: EPS y/y % | P24: 0.2569784 | Q24: 0.14466243 | R24: 0.15462486 | S24: 0.13520597 | T24: 0.13223557 | Z24: EPS y/y % | AB24: -0.085264588 | AC24: 0.061552158 | AD24: 0.048838212 | AE24: 0.025471713 | AF24: 0.018031407
B26: P / E (x) — assumed (adjusted EPS) | G26: 32 | H26: 32 | N26: P / E (x) — assumed (adjusted EPS) | S26: 36 | T26: 36 | Z26: P / E (x) — assumed (adjusted EPS) | AD26: 25 | AE26: 25 | AF26: 25
B27: Price Target ($) | G27: =G26*G23 -> 463.90547 | H27: =H26*H23 -> 504.33522 | N27: Price Target ($) | S27: =S26*S23 -> 644.981 | T27: =T26*T23 -> 730.27043 | Z27: Price Target ($) | AD27: =AD26*AD23 -> 236.79269 | AE27: =AE26*AE23 -> 242.8242 | AF27: =AF26*AF23 -> 247.20267
B28: Upside / (Downside) vs current | G28: =IFERROR(G27/$K$2-1,"") -> 0.21387202 | H28: =IFERROR(H27/$K$2-1,"") -> 0.31966198 | N28: Upside / (Downside) vs current | S28: =IFERROR(S27/$K$2-1,"") -> 0.68768088 | T28: =IFERROR(T27/$K$2-1,"") -> 0.91085233 | Z28: Upside / (Downside) vs current | AD28: =IFERROR(AD27/$K$2-1,"") -> -0.38039959 | AE28: =IFERROR(AE27/$K$2-1,"") -> -0.36461731 | AF28: =IFERROR(AF27/$K$2-1,"") -> -0.35316046
B29: IRR (to 30-Sep of Y-1) | G29: =IFERROR((G27/$K$2)^(1/((DATE(2030-1,9,30)-$K$3)/365.25))-1,"") -> 0.067164929 | H29: =IFERROR((H27/$K$2)^(1/((DATE(2031-1,9,30)-$K$3)/365.25))-1,"") -> 0.072162621 | N29: IRR (to 30-Sep of Y-1) | S29: =IFERROR((S27/$K$2)^(1/((DATE(2030-1,9,30)-$K$3)/365.25))-1,"") -> 0.19188142 | T29: =IFERROR((T27/$K$2)^(1/((DATE(2031-1,9,30)-$K$3)/365.25))-1,"") -> 0.17664447 | Z29: IRR (to 30-Sep of Y-1) | AD29: =IFERROR((AD27/$K$2)^(1/((DATE(2029-1,9,30)-$K$3)/365.25))-1,"") -> -0.21454258 | AE29: =IFERROR((AE27/$K$2)^(1/((DATE(2030-1,9,30)-$K$3)/365.25))-1,"") -> -0.14110876 | AF29: =IFERROR((AF27/$K$2)^(1/((DATE(2031-1,9,30)-$K$3)/365.25))-1,"") -> -0.1036628
B31: Free Cash Flow | C31: =Model!AP285 -> 292.75614 | D31: =Model!AQ285 -> 420.65842 | E31: =Model!AR285 -> 606.49127 | F31: =Model!AS285 -> 713.13048 | G31: =Model!AT285 -> 789.61244 | H31: =Model!AU285 -> 848.51378 | I31: =IFERROR((H31/C31)^(1/5)-1,"n/m") -> 0.23717341 | N31: Free Cash Flow | O31: 286.12095 | P31: 450.07557 | Q31: 639.17503 | R31: 779.57821 | S31: 894.5731 | T31: 996.06585 | U31: 0.28335757 | Z31: Free Cash Flow | AA31: 299.38356 | AB31: 352.69877 | AC31: 520.77733 | AD31: 580.19836 | AE31: 606.0242 | AF31: 612.32828 | AG31: 0.1538551
B32: FCF % | C32: =IFERROR(C31/C9,"") -> 0.067548985 | D32: =IFERROR(D31/D9,"") -> 0.089368164 | E32: =IFERROR(E31/E9,"") -> 0.11888223 | F32: =IFERROR(F31/F9,"") -> 0.13045197 | G32: =IFERROR(G31/G9,"") -> 0.13622732 | H32: =IFERROR(H31/H9,"") -> 0.13856649 | J32: =IFERROR(AVERAGE(Model!C289,Model!D289,Model!E289,Model!F289,Model!G289,Model!H289,Model!I289,Model!J289,Model!K289,Model!L289,Model!Q289,Model!V289,Model!AA289,Model!AF289,Model!AK289),"") -> 0.080527366 | K32: =IFERROR(MIN(Model!C289,Model!D289,Model!E289,Model!F289,Model!G289,Model!H289,Model!I289,Model!J289,Model!K289,Model!L289,Model!Q289,Model!V289,Model!AA289,Model!AF289,Model!AK289),"") -> 0.00040082363 | L32: =IFERROR(MAX(Model!C289,Model!D289,Model!E289,Model!F289,Model!G289,Model!H289,Model!I289,Model!J289,Model!K289,Model!L289,Model!Q289,Model!V289,Model!AA289,Model!AF289,Model!AK289),"") -> 0.19012108 | N32: FCF % | O32: 0.06521292 | P32: 0.091251971 | Q32: 0.1152414 | R32: 0.12652035 | S32: 0.13214355 | T32: 0.13450283 | V32: 0.080527366 | W32: 0.00040082363 | X32: 0.19012108 | Z32: FCF % | AA32: 0.069941637 | AB32: 0.080542228 | AC32: 0.11683344 | AD32: 0.12933981 | AE32: 0.13567802 | AF32: 0.13814485 | AH32: 0.080527366 | AI32: 0.00040082363 | AJ32: 0.19012108
B33: FCF / share ($) | C33: =IFERROR(C31/C21,"") -> 4.7899692 | D33: =IFERROR(D31/D21,"") -> 7.0394113 | E33: =IFERROR(E31/E21,"") -> 10.365523 | F33: =IFERROR(F31/F21,"") -> 12.408994 | G33: =IFERROR(G31/G21,"") -> 14.001498 | H33: =IFERROR(H31/H21,"") -> 15.331911 | N33: FCF / share ($) | O33: 4.6839134 | P33: 7.6432493 | Q33: 11.227254 | R33: 14.007436 | S33: 16.481727 | T33: 18.845625 | Z33: FCF / share ($) | AA33: 4.8957846 | AB33: 5.8174412 | AC33: 8.6652323 | AD33: 9.7805108 | AE33: 10.344353 | AF33: 10.568974
B34: FCF Yield (on PT) | F34: =IFERROR(F33/F$27,"") | G34: =IFERROR(G33/G$27,"") -> 0.030181791 | H34: =IFERROR(H33/H$27,"") -> 0.030400239 | N34: FCF Yield (on PT) | R34: =IFERROR(R33/R$27,"") | S34: =IFERROR(S33/S$27,"") -> 0.025553818 | T34: =IFERROR(T33/T$27,"") -> 0.025806364 | Z34: FCF Yield (on PT) | AD34: =IFERROR(AD33/AD$27,"") -> 0.041304108 | AE34: =IFERROR(AE33/AE$27,"") -> 0.042600174 | AF34: =IFERROR(AF33/AF$27,"") -> 0.042754288
B35: Adjusted EBITDA (leverage basis) | C35: =Model!AP214 -> 913.5007 | D35: =Model!AQ214 -> 1024.7817 | E35: =Model!AR214 -> 1139.0037 | F35: =Model!AS214 -> 1246.7652 | G35: =Model!AT214 -> 1335.8274 | H35: =Model!AU214 -> 1422.7568 | I35: =IFERROR((H35/C35)^(1/5)-1,"n/m") -> 0.092658275 | N35: Adjusted EBITDA (leverage basis) | O35: 921.13377 | P35: 1121.0404 | Q35: 1289.2138 | R35: 1459.4421 | S35: 1617.0928 | T35: 1780.5846 | U35: 0.14090105 | Z35: Adjusted EBITDA (leverage basis) | AA35: 905.85902 | AB35: 853.8193 | AC35: 896.80065 | AD35: 927.13431 | AE35: 937.12811 | AF35: 941.22601 | AG35: 0.0076893323
B36: Adjusted EBITDA % of net sales | C36: =IFERROR(C35/C9,"") -> 0.21077626 | D36: =IFERROR(D35/D9,"") -> 0.21771312 | E36: =IFERROR(E35/E9,"") -> 0.22326339 | F36: =IFERROR(F35/F9,"") -> 0.22806904 | G36: =IFERROR(G35/G9,"") -> 0.23046266 | H36: =IFERROR(H35/H9,"") -> 0.23234321 | J36: =IFERROR(AVERAGE(Model!C252,Model!D252,Model!E252,Model!F252,Model!G252,Model!H252,Model!I252,Model!J252,Model!K252,Model!L252,Model!Q252,Model!V252,Model!AA252,Model!AF252,Model!AK252),"") -> 0.17136239 | K36: =IFERROR(MIN(Model!C252,Model!D252,Model!E252,Model!F252,Model!G252,Model!H252,Model!I252,Model!J252,Model!K252,Model!L252,Model!Q252,Model!V252,Model!AA252,Model!AF252,Model!AK252),"") -> 0.14944288 | L36: =IFERROR(MAX(Model!C252,Model!D252,Model!E252,Model!F252,Model!G252,Model!H252,Model!I252,Model!J252,Model!K252,Model!L252,Model!Q252,Model!V252,Model!AA252,Model!AF252,Model!AK252),"") -> 0.19005596 | N36: Adjusted EBITDA % of net sales | O36: 0.20994556 | P36: 0.22728883 | Q36: 0.23244149 | R36: 0.23685773 | S36: 0.2388719 | T36: 0.24043959 | V36: 0.17136239 | W36: 0.14944288 | X36: 0.19005596 | Z36: Adjusted EBITDA % of net sales | AA36: 0.21162573 | AB36: 0.19497802 | AC36: 0.20119214 | AD36: 0.20667996 | AE36: 0.20980628 | AF36: 0.2123461 | AH36: 0.17136239 | AI36: 0.14944288 | AJ36: 0.19005596
B38: Net Debt | C38: =Model!AP414 -> 978.81341 | D38: =Model!AQ414 -> 1280.9771 | E38: =Model!AR414 -> 1423.7546 | F38: =Model!AS414 -> 1558.4566 | G38: =Model!AT414 -> 1669.7842 | H38: =Model!AU414 -> 1778.446 | N38: Net Debt | O38: 1085.4067 | P38: 1961.8208 | Q38: 2256.1241 | R38: 2554.0236 | S38: 2829.9124 | T38: 3116.023 | Z38: Net Debt | AA38: 872.22786 | AB38: 640.36447 | AC38: 672.60048 | AD38: 695.35073 | AE38: 702.84608 | AF38: 705.91951
B39: Net Debt / Adjusted EBITDA (x) | C39: =IFERROR(C38/C35,"") -> 1.0714972 | D39: =IFERROR(D38/D35,"") -> 1.25 | E39: =IFERROR(E38/E35,"") -> 1.25 | F39: =IFERROR(F38/F35,"") -> 1.25 | G39: =IFERROR(G38/G35,"") -> 1.25 | H39: =IFERROR(H38/H35,"") -> 1.25 | N39: Net Debt / Adjusted EBITDA (x) | O39: 1.1783378 | P39: 1.75 | Q39: 1.75 | R39: 1.75 | S39: 1.75 | T39: 1.75 | Z39: Net Debt / Adjusted EBITDA (x) | AA39: 0.96287373 | AB39: 0.75 | AC39: 0.75 | AD39: 0.75 | AE39: 0.75 | AF39: 0.75
B40: Share repurchases ($m; FY2026E = Q4) | D40: =Model!AQ299 -> 782.61118 | E40: =Model!AR299 -> 623.28152 | F40: =Model!AS299 -> 714.89397 | G40: =Model!AT299 -> 760.67753 | H40: =Model!AU299 -> 809.00964 | N40: Share repurchases ($m; FY2026E = Q4) | P40: 1286.6356 | Q40: 709.71592 | R40: 847.3066 | S40: 933.74272 | T40: 1038.573 | AB40: 280.26754 | AC40: 524.80738 | AD40: 567.20497 | AE40: 569.61432 | AF40: 562.49498
B41: Implied avg buyback price ($) | D41: =Model!AQ298 -> 412.7436 | E41: =Model!AR298 -> 445.76309 | F41: =Model!AS298 -> 481.42414 | G41: =Model!AT298 -> 519.93807 | H41: =Model!AU298 -> 561.53311 | N41: Implied avg buyback price ($) | P41: 412.7436 | Q41: 445.76309 | R41: 481.42414 | S41: 519.93807 | T41: 561.53311 | AB41: 412.7436 | AC41: 445.76309 | AD41: 481.42414 | AE41: 519.93807 | AF41: 561.53311
B42: Shares repurchased (m) | D42: =Model!AQ300 -> 1.8961195 | E42: =Model!AR300 -> 1.3982349 | F42: =Model!AS300 -> 1.4849567 | G42: =Model!AT300 -> 1.4630157 | H42: =Model!AU300 -> 1.4407158 | N42: Shares repurchased (m) | P42: 3.1172757 | Q42: 1.592137 | R42: 1.7600002 | S42: 1.795873 | T42: 1.8495311 | AB42: 0.67903546 | AC42: 1.1773235 | AD42: 1.1781814 | AE42: 1.0955426 | AF42: 1.0017129
B44: ROIC | C44: =Model!AP397 -> 0.180706 | D44: =Model!AQ397 -> 0.18625395 | E44: =Model!AR397 -> 0.19406949 | F44: =Model!AS397 -> 0.20214688 | G44: =Model!AT397 -> 0.20796692 | H44: =Model!AU397 -> 0.21323528 | J44: =IFERROR(AVERAGE(Model!C397,Model!D397,Model!E397,Model!F397,Model!G397,Model!H397,Model!I397,Model!J397,Model!K397,Model!L397,Model!Q397,Model!V397,Model!AA397,Model!AF397,Model!AK397),"") -> 0.11381492 | K44: =IFERROR(MIN(Model!C397,Model!D397,Model!E397,Model!F397,Model!G397,Model!H397,Model!I397,Model!J397,Model!K397,Model!L397,Model!Q397,Model!V397,Model!AA397,Model!AF397,Model!AK397),"") -> 0.080656647 | L44: =IFERROR(MAX(Model!C397,Model!D397,Model!E397,Model!F397,Model!G397,Model!H397,Model!I397,Model!J397,Model!K397,Model!L397,Model!Q397,Model!V397,Model!AA397,Model!AF397,Model!AK397),"") -> 0.16769573 | N44: ROIC | O44: 0.18174692 | P44: 0.19718811 | Q44: 0.20522156 | R44: 0.21411076 | S44: 0.22122374 | T44: 0.22820186 | V44: 0.11381492 | W44: 0.080656647 | X44: 0.16769573 | Z44: ROIC | AA44: 0.17965549 | AB44: 0.15931723 | AC44: 0.16426734 | AD44: 0.16900448 | AE44: 0.1712394 | AF44: 0.17266072 | AH44: 0.11381492 | AI44: 0.080656647 | AJ44: 0.16769573
B45: RONTA | C45: =Model!AP408 -> 0.20142276 | D45: =Model!AQ408 -> 0.21064484 | E45: =Model!AR408 -> 0.22259846 | F45: =Model!AS408 -> 0.23497117 | G45: =Model!AT408 -> 0.24473416 | H45: =Model!AU408 -> 0.25374714 | J45: =IFERROR(AVERAGE(Model!C408,Model!D408,Model!E408,Model!F408,Model!G408,Model!H408,Model!I408,Model!J408,Model!K408,Model!L408,Model!Q408,Model!V408,Model!AA408,Model!AF408,Model!AK408),"") -> 0.14677544 | K45: =IFERROR(MIN(Model!C408,Model!D408,Model!E408,Model!F408,Model!G408,Model!H408,Model!I408,Model!J408,Model!K408,Model!L408,Model!Q408,Model!V408,Model!AA408,Model!AF408,Model!AK408),"") -> 0.099246509 | L45: =IFERROR(MAX(Model!C408,Model!D408,Model!E408,Model!F408,Model!G408,Model!H408,Model!I408,Model!J408,Model!K408,Model!L408,Model!Q408,Model!V408,Model!AA408,Model!AF408,Model!AK408),"") -> 0.19011194 | N45: RONTA | O45: 0.20249826 | P45: 0.2278247 | Q45: 0.24451295 | R45: 0.261944 | S45: 0.27686442 | T45: 0.29108591 | V45: 0.14677544 | W45: 0.099246509 | X45: 0.19011194 | Z45: RONTA | AA45: 0.20033626 | AB45: 0.16517865 | AC45: 0.17123084 | AD45: 0.17672245 | AE45: 0.17886462 | AF45: 0.17998872 | AH45: 0.14677544 | AI45: 0.099246509 | AJ45: 0.19011194
B47: Implied Market Cap (USDm) | F47: =F27*F21 -> 0 | G47: =G27*G21 -> 26161.881 | H47: =H27*H21 -> 27911.418 | N47: Implied Market Cap (USDm) | R47: =R27*R21 -> 0 | S47: =S27*S21 -> 35007.414 | T47: =T27*T21 -> 38597.683 | Z47: Implied Market Cap (USDm) | AD47: =AD27*AD21 -> 14046.989 | AE47: =AE27*AE21 -> 14225.862 | AF47: =AF27*AF21 -> 14322.032
B48: (+) Net Debt & NCI | F48: =F38+Model!AS328 -> 1558.4566 | G48: =G38+Model!AT328 -> 1669.7842 | H48: =H38+Model!AU328 -> 1778.446 | N48: (+) Net Debt & NCI | R48: =R38+Model!AS328 -> 2554.0236 | S48: =S38+Model!AT328 -> 2829.9124 | T48: =T38+Model!AU328 -> 3116.023 | Z48: (+) Net Debt & NCI | AD48: =AD38+Model!AS328 -> 695.35073 | AE48: =AE38+Model!AT328 -> 702.84608 | AF48: =AF38+Model!AU328 -> 705.91951
B49: Implied Enterprise Value (USDm) | F49: =F47+F48 -> 1558.4566 | G49: =G47+G48 -> 27831.665 | H49: =H47+H48 -> 29689.864 | N49: Implied Enterprise Value (USDm) | R49: =R47+R48 -> 2554.0236 | S49: =S47+S48 -> 37837.327 | T49: =T47+T48 -> 41713.706 | Z49: Implied Enterprise Value (USDm) | AD49: =AD47+AD48 -> 14742.34 | AE49: =AE47+AE48 -> 14928.708 | AF49: =AF47+AF48 -> 15027.951
B50: Implied EV / Adjusted EBITDA (x) | F50: =IFERROR(F49/F35,"") -> 1.25 | G50: =IFERROR(G49/G35,"") -> 20.834777 | H50: =IFERROR(H49/H35,"") -> 20.867842 | N50: Implied EV / Adjusted EBITDA (x) | R50: =IFERROR(R49/R35,"") -> 1.75 | S50: =IFERROR(S49/S35,"") -> 23.398364 | T50: =IFERROR(T49/T35,"") -> 23.426972 | Z50: Implied EV / Adjusted EBITDA (x) | AD50: =IFERROR(AD49/AD35,"") -> 15.900975 | AE50: =IFERROR(AE49/AE35,"") -> 15.930275 | AF50: =IFERROR(AF49/AF35,"") -> 15.966358

Sheet DCF
B2: DCF VALUATION — WOODWARD, INC. (WWD)
B4: 1. WACC BUILD
B5: Risk-free rate (US 10Y govt) | C5: 0.0425 | D5: Assumption (~US 10Y Treasury yield, Oct-2026; government rate sources not reachable from the build environment); update to market
B6: Equity risk premium | C6: 0.05 | D6: Assumption: US implied ERP ~4.5–5.5%
B7: Levered beta | C7: 1.05 | D7: Assumption: aerospace & defense components peers (HEI, TDG, CW, MOG, PH aerospace) ~0.9–1.2; ~30% of sales Industrial (cyclical power generation / transportation / oil & gas)
B8: Cost of equity | C8: =C5+C7*C6 -> 0.095
B9: Pre-tax cost of debt | C9: 0.055 | D9: Aug-2026 Series U / V / W private-placement notes at 5.34% / 5.39% / 5.64% (8-K 21-Aug-2026); revolver at SOFR + 0.875–1.75% (4.73% at 30-Jun-2026)
B10: Tax rate | C10: 0.225 | D10: Model FY2027E+ effective tax rate (FY26 adjusted-rate guidance ~22.5%)
B11: After-tax cost of debt | C11: =C9*(1-C10) -> 0.042625
B12: Target D/V | C12: 0.06 | D12: Net debt ~$0.9bn at 30-Jun-2026 vs ~$23bn market cap ($382.17 × ~61m diluted shares); ~1.0x adjusted EBITDA
B13: WACC | C13: =C8*(1-C12)+C11*C12 -> 0.0918575
B15: Valuation date (live) | C15: =TODAY() -> 2026-10-07 00:00:00 | D15: Periods = (30-Sep of fiscal year − today) / 365.25; cash flows assumed at fiscal year-end (30 September); FY2026E (ended 30-Sep-2026) is the base year
B16: 2. UNLEVERED FREE CASH FLOW BUILD (USDm)
D17: 2027E | E17: 2028E | F17: 2029E | G17: 2030E | H17: 2031E | I17: 2032E | J17: 2033E | K17: 2034E | L17: 2035E | M17: 2036E | N17: Terminal | P17: CAGR 27–31E | Q17: CAGR 27–36E
B18: Adj. EBIT (full-cost) less acquisition, integration & restructuring costs | D18: =Model!AQ220-Model!AQ222 -> 850.72872 | E18: =Model!AR220-Model!AR222 -> 958.35434 | F18: =Model!AS220-Model!AS222 -> 1064.7626 | G18: =Model!AT220-Model!AT222 -> 1142.6146 | H18: =Model!AU220-Model!AU222 -> 1219.5455 | I18: =H18*(1+I$26) -> 1304.9137 | J18: =I18*(1+J$26) -> 1389.733 | K18: =J18*(1+K$26) -> 1473.117 | L18: =K18*(1+L$26) -> 1554.1385 | M18: =L18*(1+M$26) -> 1631.8454 | P18: =(H18/D18)^(1/(COLUMNS(D18:H18)-1))-1 -> 0.094212638 | Q18: =(M18/D18)^(1/(COLUMNS(D18:M18)-1))-1 -> 0.075058236
B19: × (1 − tax rate) | D19: =1-$C$10 -> 0.775 | E19: =1-$C$10 -> 0.775 | F19: =1-$C$10 -> 0.775 | G19: =1-$C$10 -> 0.775 | H19: =1-$C$10 -> 0.775 | I19: =1-$C$10 -> 0.775 | J19: =1-$C$10 -> 0.775 | K19: =1-$C$10 -> 0.775 | ... M19: =1-$C$10 -> 0.775
B20: NOPAT | D20: =D18*D19 -> 659.31476 | E20: =E18*E19 -> 742.72461 | F20: =F18*F19 -> 825.19104 | G20: =G18*G19 -> 885.52633 | H20: =H18*H19 -> 945.14774 | I20: =I18*I19 -> 1011.3081 | J20: =J18*J19 -> 1077.0431 | K20: =K18*K19 -> 1141.6657 | ... M20: =M18*M19 -> 1264.6802
B21: plus D&A (depreciation + amortization of intangibles) | D21: =Model!AQ171 -> 142.05297 | E21: =Model!AR171 -> 163.64935 | F21: =Model!AS171 -> 180.00261 | G21: =Model!AT171 -> 191.21275 | H21: =Model!AU171 -> 201.21136 | I21: =H21*(1+I$26) -> 215.29615 | J21: =I21*(1+J$26) -> 229.2904 | K21: =J21*(1+K$26) -> 243.04782 | L21: =K21*(1+L$26) -> 256.41545 | M21: =L21*(1+M$26) -> 269.23623
B22: − Capex (PP&E) and acquisitions (bolt-ons; M&A lever 2027E–31E) | D22: =Model!AQ267+Model!AQ268 -> -335.35138 | E22: =Model!AR267+Model!AR268 -> -278.5565 | F22: =Model!AS267+Model!AS268 -> -274.93162 | G22: =Model!AT267+Model!AT268 -> -273.88856 | H22: =Model!AU267+Model!AU268 -> -283.70541 | I22: =Model!AU267*(1+I$26) -> -196.56479 | J22: =I22*(1+J$26) -> -209.3415 | K22: =J22*(1+K$26) -> -221.90199 | L22: =K22*(1+L$26) -> -234.1066 | M22: =L22*(1+M$26) -> -245.81193
B23: − Δ Working capital (CF statement) | D23: =Model!AQ265 -> -65.568054 | E23: =Model!AR265 -> -87.0661 | F23: =Model!AS265 -> -79.879997 | G23: =Model!AT265 -> -72.988962 | H23: =Model!AU265 -> -71.723845 | I23: =H23*(1+I$26) -> -76.744514 | J23: =I23*(1+J$26) -> -81.732907 | K23: =J23*(1+K$26) -> -86.636882 | L23: =K23*(1+L$26) -> -91.40191 | M23: =L23*(1+M$26) -> -95.972006
B24: Unlevered FCF | D24: =D20+D21+D22+D23 -> 400.44829 | E24: =E20+E21+E22+E23 -> 540.75137 | F24: =F20+F21+F22+F23 -> 650.38203 | G24: =G20+G21+G22+G23 -> 729.86156 | H24: =H20+H21+H22+H23 -> 790.92984 | I24: =I20+I21+I22+I23 -> 953.29493 | J24: =J20+J21+J22+J23 -> 1015.2591 | K24: =K20+K21+K22+K23 -> 1076.1747 | ... M24: =M20+M21+M22+M23 -> 1192.1325 | N24: =M24*(1+$C$27) -> 1239.8178 | P24: =(H24/D24)^(1/(COLUMNS(D24:H24)-1))-1 -> 0.18548996 | Q24: =(M24/D24)^(1/(COLUMNS(D24:M24)-1))-1 -> 0.128865
B25: Terminal Value (Gordon Growth) | N25: =N24/($C$13-$C$27) -> 23908.167
B26: Fade-period growth (2032E–36E; 7.0% → 5.0% linear) | I26: 0.07 | J26: =I26+($M$26-$I$26)/4 -> 0.065 | K26: =J26+($M$26-$I$26)/4 -> 0.06 | L26: =K26+($M$26-$I$26)/4 -> 0.055 | M26: 0.05
B27: Terminal growth rate | C27: 0.04
B29: Discount period (years) | D29: =(DATE(2027,9,30)-$C$15)/365.25 -> 0.98015058 | E29: =(DATE(2028,9,30)-$C$15)/365.25 -> 1.982204 | F29: =(DATE(2029,9,30)-$C$15)/365.25 -> 2.9815195 | G29: =(DATE(2030,9,30)-$C$15)/365.25 -> 3.980835 | H29: =(DATE(2031,9,30)-$C$15)/365.25 -> 4.9801506 | I29: =(DATE(2032,9,30)-$C$15)/365.25 -> 5.982204 | J29: =(DATE(2033,9,30)-$C$15)/365.25 -> 6.9815195 | K29: =(DATE(2034,9,30)-$C$15)/365.25 -> 7.980835 | L29: =(DATE(2035,9,30)-$C$15)/365.25 -> 8.9801506 | M29: =(DATE(2036,9,30)-$C$15)/365.25 -> 9.982204 | N29: =M29 -> 9.982204
B30: Discount factor | D30: =1/(1+$C$13)^D29 -> 0.91746945 | E30: =1/(1+$C$13)^E29 -> 0.84013152 | F30: =1/(1+$C$13)^F29 -> 0.7694979 | G30: =1/(1+$C$13)^G29 -> 0.70480277 | H30: =1/(1+$C$13)^H29 -> 0.64554685 | I30: =1/(1+$C$13)^I29 -> 0.59113059 | J30: =1/(1+$C$13)^J29 -> 0.54143159 | K30: =1/(1+$C$13)^K29 -> 0.49591102 | ... N30: =1/(1+$C$13)^N29 -> 0.41592937
B31: PV of UFCF | D31: =D24*D30 -> 367.39907 | E31: =E24*E30 -> 454.30227 | F31: =F24*F30 -> 500.46761 | G31: =G24*G30 -> 514.40845 | H31: =H24*H30 -> 510.58227 | I31: =I24*I30 -> 563.5218 | J31: =J24*J30 -> 549.69336 | K31: =K24*K30 -> 533.68686 | ... M31: =M24*M30 -> 495.8429 | N31: =N25*N30 -> 9944.1088
D32: Woodward's adjusted EBIT already deducts amortization of intangibles and share-based compensation (neither is adjusted out); D&A is added back in row 21. Restructuring and acquisition / business-development costs (cash; adjusted out by the company, incl. the China OH, servo-valve and Santa Clarita actions) are deducted inside row 18. Row 22 includes bolt-on acquisitions in FY2027E–31E; the fade period and terminal value assume no new acquisitions. The pending $180m pilot-controls sale (FY27) is excluded from UFCF (the business is kept in the build).
B33: IMPLIED ROIC — invested capital roll-forward (USDm)
B34: Opening invested capital | D34: =Model!AP394 -> 3394.1549 | E34: =D38 -> 3653.0214 | F34: =E38 -> 3854.9946 | G34: =F38 -> 4029.8036 | H34: =G38 -> 4185.4684 | I34: =H38 -> 4339.6863 | J34: =I38 -> 4397.6995 | K34: =J38 -> 4459.4835 | L34: =K38 -> 4524.9745 | M34: =L38 -> 4594.0676
B35: plus Capex and acquisitions | D35: =-D22 -> 335.35138 | E35: =-E22 -> 278.5565 | F35: =-F22 -> 274.93162 | G35: =-G22 -> 273.88856 | H35: =-H22 -> 283.70541 | I35: =-I22 -> 196.56479 | J35: =-J22 -> 209.3415 | K35: =-K22 -> 221.90199 | ... M35: =-M22 -> 245.81193
B36: less DD&A | D36: =-D21 -> -142.05297 | E36: =-E21 -> -163.64935 | F36: =-F21 -> -180.00261 | G36: =-G21 -> -191.21275 | H36: =-H21 -> -201.21136 | I36: =-I21 -> -215.29615 | J36: =-J21 -> -229.2904 | K36: =-K21 -> -243.04782 | ... M36: =-M21 -> -269.23623
B37: plus Δ Working capital investment | D37: =-D23 -> 65.568054 | E37: =-E23 -> 87.0661 | F37: =-F23 -> 79.879997 | G37: =-G23 -> 72.988962 | H37: =-H23 -> 71.723845 | I37: =-I23 -> 76.744514 | J37: =-J23 -> 81.732907 | K37: =-K23 -> 86.636882 | ... M37: =-M23 -> 95.972006
B38: Closing invested capital | D38: =SUM(D34:D37) -> 3653.0214 | E38: =SUM(E34:E37) -> 3854.9946 | F38: =SUM(F34:F37) -> 4029.8036 | G38: =SUM(G34:G37) -> 4185.4684 | H38: =SUM(H34:H37) -> 4339.6863 | I38: =SUM(I34:I37) -> 4397.6995 | J38: =SUM(J34:J37) -> 4459.4835 | K38: =SUM(K34:K37) -> 4524.9745 | ... M38: =SUM(M34:M37) -> 4666.6153
B39: NOPAT (row 20) | D39: =D20 -> 659.31476 | E39: =E20 -> 742.72461 | F39: =F20 -> 825.19104 | G39: =G20 -> 885.52633 | H39: =H20 -> 945.14774 | I39: =I20 -> 1011.3081 | J39: =J20 -> 1077.0431 | K39: =K20 -> 1141.6657 | ... M39: =M20 -> 1264.6802
B40: Implied ROIC (NOPAT / avg. invested capital) | D40: =IFERROR(D39/AVERAGE(D34,D38),"") -> 0.18711459 | E40: =IFERROR(E39/AVERAGE(E34,E38),"") -> 0.19784844 | F40: =IFERROR(F39/AVERAGE(F34,F38),"") -> 0.2093119 | G40: =IFERROR(G39/AVERAGE(G34,G38),"") -> 0.21558053 | H40: =IFERROR(H39/AVERAGE(H34,H38),"") -> 0.22173152 | I40: =IFERROR(I39/AVERAGE(I34,I38),"") -> 0.23148986 | J40: =IFERROR(J39/AVERAGE(J34,J38),"") -> 0.24320218 | K40: =IFERROR(K39/AVERAGE(K34,K38),"") -> 0.25414237 | ... M40: =IFERROR(M39/AVERAGE(M34,M38),"") -> 0.27312893
B41: Reinvestment rate (net investment / NOPAT) | D41: =IFERROR(SUM(D35:D37)/D39,"") -> 0.39262957 | E41: =IFERROR(SUM(E35:E37)/E39,"") -> 0.27193557 | F41: =IFERROR(SUM(F35:F37)/F39,"") -> 0.21184065 | G41: =IFERROR(SUM(G35:G37)/G39,"") -> 0.17578785 | H41: =IFERROR(SUM(H35:H37)/H39,"") -> 0.16316803 | I41: =IFERROR(SUM(I35:I37)/I39,"") -> 0.05736447 | J41: =IFERROR(SUM(J35:J37)/J39,"") -> 0.05736447 | K41: =IFERROR(SUM(K35:K37)/K39,"") -> 0.05736447 | ... M41: =IFERROR(SUM(M35:M37)/M39,"") -> 0.05736447
B42: Implied terminal RONIC (g / reinvestment rate) | N42: =IFERROR($C$27/M41,"") -> 0.69729573
D43: Opening IC = Model FY2026E book IC (equity + net debt at 30-Sep-2026), rolled forward with capex + M&A − D&A + ΔWC.
B44: 3. VALUATION SUMMARY
B45: Sum of PV (explicit + fade) | C45: =SUM(D31:M31) -> 5005.607
B46: PV of Terminal Value | C46: =N31 -> 9944.1088
B47: Enterprise Value | C47: =C45+C46 -> 14949.716
B48: Less: Net debt + NCI (Model FY2026E year end, 30-Sep-2026) | C48: =Model!AP414+Model!AP328 -> 978.81341 | D48: WWD: no noncontrolling interests; net debt at the base-year end (≈ valuation date) so that FY2027E+ cash flows are not double counted.
B49: Equity Value | C49: =C47-C48 -> 13970.902
B50: Diluted shares (m, Model FY2026E period end) | C50: =Model!AP421 -> 60.378673
B51: Implied share price ($) | C51: =C49/C50 -> 231.38803
B52: Current share price ($) | C52: =Model!AP420 -> 382.17
B53: Implied upside / (downside) | C53: =C51/C52-1 -> -0.39454161
B54: Required discount to DCF value for target IRR | C54: =1-((1+C13)/(1+H54))^H55 -> 0.14413678 | D54: vs. current | E54: Target IRR | H54: 0.15
B55: Max entry price for target IRR ($) | C55: =C51*(1-C54) -> 198.03651 | D55: =C55/C52-1 -> -0.48181043 | E55: Years for discount to close | H55: 3
B58: 4. SENSITIVITY: IMPLIED PRICE ($) — WACC × Terminal Growth
D60: WACC →
B61: Terminal growth ↓ | D61: =F61-0.01 -> 0.0818575 | E61: =F61-0.005 -> 0.0868575 | F61: =$C$13 -> 0.0918575 | G61: =F61+0.005 -> 0.0968575 | H61: =F61+0.01 -> 0.1018575
B62: =B64-0.01 -> 0.03 | D62: {=IFERROR((SUMPRODUCT($D$24:$M$24/(1+D$61)^$D$29:$M$29)+($M$24*(1+$B62)/(D$61-$B62))/(1+D$61)^$M$29-$C$48)/$C$50,"")} -> 249.96477 | E62: {=IFERROR((SUMPRODUCT($D$24:$M$24/(1+E$61)^$D$29:$M$29)+($M$24*(1+$B62)/(E$61-$B62))/(1+E$61)^$M$29-$C$48)/$C$50,"")} -> 224.62866 | F62: {=IFERROR((SUMPRODUCT($D$24:$M$24/(1+F$61)^$D$29:$M$29)+($M$24*(1+$B62)/(F$61-$B62))/(1+F$61)^$M$29-$C$48)/$C$50,"")} -> 203.43541 | G62: {=IFERROR((SUMPRODUCT($D$24:$M$24/(1+G$61)^$D$29:$M$29)+($M$24*(1+$B62)/(G$61-$B62))/(1+G$61)^$M$29-$C$48)/$C$50,"")} -> 185.45403 | H62: {=IFERROR((SUMPRODUCT($D$24:$M$24/(1+H$61)^$D$29:$M$29)+($M$24*(1+$B62)/(H$61-$B62))/(1+H$61)^$M$29-$C$48)/$C$50,"")} -> 170.01271
B63: =B64-0.005 -> 0.035 | D63: {=IFERROR((SUMPRODUCT($D$24:$M$24/(1+D$61)^$D$29:$M$29)+($M$24*(1+$B63)/(D$61-$B63))/(1+D$61)^$M$29-$C$48)/$C$50,"")} -> 270.00477 | E63: {=IFERROR((SUMPRODUCT($D$24:$M$24/(1+E$61)^$D$29:$M$29)+($M$24*(1+$B63)/(E$61-$B63))/(1+E$61)^$M$29-$C$48)/$C$50,"")} -> 240.47402 | F63: {=IFERROR((SUMPRODUCT($D$24:$M$24/(1+F$61)^$D$29:$M$29)+($M$24*(1+$B63)/(F$61-$B63))/(1+F$61)^$M$29-$C$48)/$C$50,"")} -> 216.18266 | G63: {=IFERROR((SUMPRODUCT($D$24:$M$24/(1+G$61)^$D$29:$M$29)+($M$24*(1+$B63)/(G$61-$B63))/(1+G$61)^$M$29-$C$48)/$C$50,"")} -> 195.85877 | H63: {=IFERROR((SUMPRODUCT($D$24:$M$24/(1+H$61)^$D$29:$M$29)+($M$24*(1+$B63)/(H$61-$B63))/(1+H$61)^$M$29-$C$48)/$C$50,"")} -> 178.61095
B64: =$C$27 -> 0.04 | D64: {=IFERROR((SUMPRODUCT($D$24:$M$24/(1+D$61)^$D$29:$M$29)+($M$24*(1+$B64)/(D$61-$B64))/(1+D$61)^$M$29-$C$48)/$C$50,"")} -> 294.83245 | E64: {=IFERROR((SUMPRODUCT($D$24:$M$24/(1+E$61)^$D$29:$M$29)+($M$24*(1+$B64)/(E$61-$B64))/(1+E$61)^$M$29-$C$48)/$C$50,"")} -> 259.70097 | F64: {=IFERROR((SUMPRODUCT($D$24:$M$24/(1+F$61)^$D$29:$M$29)+($M$24*(1+$B64)/(F$61-$B64))/(1+F$61)^$M$29-$C$48)/$C$50,"")} -> 231.38803 | G64: {=IFERROR((SUMPRODUCT($D$24:$M$24/(1+G$61)^$D$29:$M$29)+($M$24*(1+$B64)/(G$61-$B64))/(1+G$61)^$M$29-$C$48)/$C$50,"")} -> 208.09347 | H64: {=IFERROR((SUMPRODUCT($D$24:$M$24/(1+H$61)^$D$29:$M$29)+($M$24*(1+$B64)/(H$61-$B64))/(1+H$61)^$M$29-$C$48)/$C$50,"")} -> 188.5992
B65: =B64+0.005 -> 0.045 | D65: {=IFERROR((SUMPRODUCT($D$24:$M$24/(1+D$61)^$D$29:$M$29)+($M$24*(1+$B65)/(D$61-$B65))/(1+D$61)^$M$29-$C$48)/$C$50,"")} -> 326.39626 | E65: {=IFERROR((SUMPRODUCT($D$24:$M$24/(1+E$61)^$D$29:$M$29)+($M$24*(1+$B65)/(E$61-$B65))/(1+E$61)^$M$29-$C$48)/$C$50,"")} -> 283.52136 | F65: {=IFERROR((SUMPRODUCT($D$24:$M$24/(1+F$61)^$D$29:$M$29)+($M$24*(1+$B65)/(F$61-$B65))/(1+F$61)^$M$29-$C$48)/$C$50,"")} -> 249.83843 | G65: {=IFERROR((SUMPRODUCT($D$24:$M$24/(1+G$61)^$D$29:$M$29)+($M$24*(1+$B65)/(G$61-$B65))/(1+G$61)^$M$29-$C$48)/$C$50,"")} -> 222.68747 | H65: {=IFERROR((SUMPRODUCT($D$24:$M$24/(1+H$61)^$D$29:$M$29)+($M$24*(1+$B65)/(H$61-$B65))/(1+H$61)^$M$29-$C$48)/$C$50,"")} -> 200.34416
B66: =B64+0.01 -> 0.05 | D66: {=IFERROR((SUMPRODUCT($D$24:$M$24/(1+D$61)^$D$29:$M$29)+($M$24*(1+$B66)/(D$61-$B66))/(1+D$61)^$M$29-$C$48)/$C$50,"")} -> 367.86787 | E66: {=IFERROR((SUMPRODUCT($D$24:$M$24/(1+E$61)^$D$29:$M$29)+($M$24*(1+$B66)/(E$61-$B66))/(1+E$61)^$M$29-$C$48)/$C$50,"")} -> 313.80458 | F66: {=IFERROR((SUMPRODUCT($D$24:$M$24/(1+F$61)^$D$29:$M$29)+($M$24*(1+$B66)/(F$61-$B66))/(1+F$61)^$M$29-$C$48)/$C$50,"")} -> 272.69674 | G66: {=IFERROR((SUMPRODUCT($D$24:$M$24/(1+G$61)^$D$29:$M$29)+($M$24*(1+$B66)/(G$61-$B66))/(1+G$61)^$M$29-$C$48)/$C$50,"")} -> 240.39601 | H66: {=IFERROR((SUMPRODUCT($D$24:$M$24/(1+H$61)^$D$29:$M$29)+($M$24*(1+$B66)/(H$61-$B66))/(1+H$61)^$M$29-$C$48)/$C$50,"")} -> 214.35397
B69: 5. REVERSE DCF
B70: To solve for the market-implied path: Data ▸ What-If Analysis ▸ Goal Seek — set C51 to the current price (C52) by changing C27 (terminal growth) or the fade-period growth inputs (I26:M26).
B72: 6. MAUBOUSSIN EV / NOPAT — TWO-STAGE FRAMEWORK
B73: EV/NOPAT = 1/r + [g × (1 − r/ROIIC) / (r × (r − g))] × [1 − ((1+g)/(1+r))^N]
B74: Formula source: Mauboussin & Rappaport, "Expectations Investing" (2021); Counterpoint Global, "What Does a Price-Earnings Multiple Mean?" (2020).
B76: Input | C76: Value | D76: Rationale (Woodward characteristics)
B77: r (Cost of capital / WACC) | C77: =$C$13 -> 0.0918575 | D77: Linked from Section 1 WACC build
B78: g (NOPAT growth, Stage 1) | C78: 0.1 | D78: Model adjusted EBIT CAGR FY2026–31E: high-single-digit sales growth (commercial OEM rate ramps, aftermarket, power generation) with margin expansion → ~10% NOPAT growth
B79: ROIIC (Return on incremental invested capital) | C79: 0.2 | D79: Sole-source, certified content on long-lived aircraft and engine platforms drives 20–30-year aftermarket annuities at high incremental returns; Industrial returns are cyclical; L'Orange (2018) earned below WACC for years
B80: N (Years of value creation / CAP) | C80: 15 | D80: Certification barriers and installed-base aftermarket (commercial services ~25% of sales) sustain a long competitive-advantage period; exposure to aircraft production rates and Industrial cyclicality
B82: Calculation | C82: Value
B83: Steady-state component: 1 / r | C83: =1/C77 -> 10.886427
B84: Value-creation factor: 1 − r / ROIIC | C84: =1-C77/C79 -> 0.5407125
B85: Growth multiplier: g × (1 − r/ROIIC) / (r × (r − g)) | C85: =C78*C84/(C77*(C77-C78)) -> -72.292629
B86: Time decay: 1 − ((1+g)/(1+r))^N | C86: =1-((1+C78)/(1+C77))^C80 -> -0.11789459
B87: PVGO component (growth value) | C87: =C85*C86 -> 8.5229096
B88: Mauboussin EV / NOPAT (steady-state + PVGO) | C88: =C83+C87 -> 19.409337
B90: VALUATION — Applied to FY2029E NOPAT | C90: USDm
B91: FY2029E Adj. EBIT less acquisition, integration & restructuring costs | C91: =Model!AS220-Model!AS222 -> 1064.7626
B92: Tax rate (from WACC build) | C92: =$C$10 -> 0.225
B93: FY2029E NOPAT | C93: =C91*(1-C92) -> 825.19104
B94: × Mauboussin EV/NOPAT multiple | C94: =C88 -> 19.409337
B95: Implied Enterprise Value (FY2029E basis) | C95: =C93*C94 -> 16016.411
B96: Less: FY2028E year-end net debt + NCI (Model) | C96: =Model!AR414+Model!AR328 -> 1423.7546
B97: Implied Equity Value | C97: =C95-C96 -> 14592.656
B98: Diluted shares FY2029E (m, Model) | C98: =Model!AS421 -> 56.926362
B99: Implied share price FY2029 ($) | C99: =C97/C98 -> 256.34269
B101: Current share price ($) | C101: =C52 -> 382.17
B102: Implied upside / (downside) | C102: =C99/C101-1 -> -0.32924435
B104: MARKET-IMPLIED EV/NOPAT TODAY | C104: USDm
B105: Current market cap (spot × diluted shares) | C105: =C52*C50 -> 23074.917
B106: Plus: FY2026E year-end net debt + NCI | C106: =C48 -> 978.81341
B107: Implied Enterprise Value (today) | C107: =C105+C106 -> 24053.731
B108: WWD market-implied EV/NOPAT (on FY2029E NOPAT) | C108: =C107/C93 -> 29.149287
B110: Multiple gap (Mauboussin − Market) | C110: =C88-C108 -> -9.7399503
B111: Implied re-rating headroom | C111: =C88/C108-1 -> -0.33414026

Sheet Charts
B2: Woodward, Inc. — Operating Performance (FY2012–FY2025) and Model Forecast (FY2026E–FY2031E)
B3: USDm · fiscal years ended 30 September · Linked to Model. Bars = contribution of each segment to total net-sales growth (pp). Adjusted EBITDA and EBIT = company definitions (adjusted measures published from FY2018; earlier years = EBITDA / EBIT). ROIC / RONTA on adjusted EBIT (full-cost).
C7: 2012 | D7: 2013 | E7: 2014 | F7: 2015 | G7: 2016 | H7: 2017 | I7: 2018 | J7: 2019 | K7: 2020 | L7: 2021 | M7: 2022 | N7: 2023 | O7: 2024 | P7: 2025 | Q7: 2026E | R7: 2027E | S7: 2028E | T7: 2029E | U7: 2030E | V7: 2031E
B8: Aerospace contribution to growth (pp) | C8: =IFERROR(Model!D74+0,0) -> 0.030993128 | D8: =IFERROR(Model!E74+0,0) -> 0.088653305 | E8: =IFERROR(Model!F74+0,0) -> 0.011646839 | F8: =IFERROR(Model!G74+0,0) -> 0.038405189 | G8: =IFERROR(Model!H74+0,0) -> 0.035467249 | H8: =IFERROR(Model!I74+0,0) -> 0.053958869 | I8: =IFERROR(Model!J74+0,0) -> 0.10275434 | J8: =IFERROR(Model!K74+0,0) -> 0.13867137 | K8: =IFERROR(Model!L74+0,0) -> -0.099840459 | L8: =IFERROR(Model!Q74+0,0) -> -0.074868221 | M8: =IFERROR(Model!V74+0,0) -> 0.051297248 | N8: =IFERROR(Model!AA74+0,0) -> 0.10440744 | O8: =IFERROR(Model!AF74+0,0) -> 0.089383805 | P8: =IFERROR(Model!AK74+0,0) -> 0.085489384 | Q8: =IFERROR(Model!AP74+0,0) -> 0.13718973 | R8: =IFERROR(Model!AQ74+0,0) -> 0.063210114 | S8: =IFERROR(Model!AR74+0,0) -> 0.054260248 | T8: =IFERROR(Model!AS74+0,0) -> 0.04579412 | U8: =IFERROR(Model!AT74+0,0) -> 0.038993706 | V8: =IFERROR(Model!AU74+0,0) -> 0.036808851
B9: Industrial contribution to growth (pp) | C9: =IFERROR(Model!D75+0,0) -> 0.058931987 | D9: =IFERROR(Model!E75+0,0) -> -0.050945339 | E9: =IFERROR(Model!F75+0,0) -> 0.022064323 | F9: =IFERROR(Model!G75+0,0) -> -0.019885171 | G9: =IFERROR(Model!H75+0,0) -> -0.042936698 | H9: =IFERROR(Model!I75+0,0) -> -0.016586607 | I9: =IFERROR(Model!J75+0,0) -> 0.0054982048 | J9: =IFERROR(Model!K75+0,0) -> 0.10825699 | K9: =IFERROR(Model!L75+0,0) -> -0.039643859 | L9: =IFERROR(Model!Q75+0,0) -> -0.025238564 | M9: =IFERROR(Model!V75+0,0) -> 0.0096859427 | N9: =IFERROR(Model!AA75+0,0) -> 0.11876624 | O9: =IFERROR(Model!AF75+0,0) -> 0.051180176 | P9: =IFERROR(Model!AK75+0,0) -> -0.012445819 | Q9: =IFERROR(Model!AP75+0,0) -> 0.077810267 | R9: =IFERROR(Model!AQ75+0,0) -> 0.019018681 | S9: =IFERROR(Model!AR75+0,0) -> 0.022133307 | T9: =IFERROR(Model!AS75+0,0) -> 0.018548063 | U9: =IFERROR(Model!AT75+0,0) -> 0.014254022 | V9: =IFERROR(Model!AU75+0,0) -> 0.012655825
C11: =C7 -> 2012 | D11: =D7 -> 2013 | E11: =E7 -> 2014 | F11: =F7 -> 2015 | G11: =G7 -> 2016 | H11: =H7 -> 2017 | I11: =I7 -> 2018 | J11: =J7 -> 2019 | ... V11: =V7 -> 2031E
B12: Adjusted EBITDA | C12: =Model!D214 -> 291.885 | D12: =Model!E214 -> 300.234 | E12: =Model!F214 -> 327.13 | F12: =Model!G214 -> 340.261 | G12: =Model!H214 -> 320.273 | H12: =Model!I214 -> 359.369 | I12: =Model!J214 -> 423.736 | J12: =Model!K214 -> 544.894 | K12: =Model!L214 -> 474.316 | L12: =Model!Q214 -> 413.118 | M12: =Model!V214 -> 356.091 | N12: =Model!AA214 -> 475.534 | O12: =Model!AF214 -> 619.785 | P12: =Model!AK214 -> 669.511 | Q12: =Model!AP214 -> 913.5007 | R12: =Model!AQ214 -> 1024.7817 | S12: =Model!AR214 -> 1139.0037 | T12: =Model!AS214 -> 1246.7652 | U12: =Model!AT214 -> 1335.8274 | V12: =Model!AU214 -> 1422.7568
B13: EBIT (GAAP) | C13: =Model!D160 -> 223.268 | D13: =Model!E160 -> 226.001 | E13: =Model!F160 -> 249.777 | F13: =Model!G160 -> 265.026 | G13: =Model!H160 -> 251.237 | H13: =Model!I160 -> 278.452 | I13: =Model!J160 -> 249.674 | J13: =Model!K160 -> 363.2 | K13: =Model!L160 -> 315.928 | L13: =Model!Q160 -> 278.586 | M13: =Model!V160 -> 232.629 | N13: =Model!AA160 -> 320.915 | O13: =Model!AF160 -> 495.472 | P13: =Model!AK160 -> 562.911 | Q13: =Model!AP160 -> 768.9607 | R13: =Model!AQ160 -> 1014.3647 | S13: =Model!AR160 -> 958.35434 | T13: =Model!AS160 -> 1064.7626 | U13: =Model!AT160 -> 1142.6146 | V13: =Model!AU160 -> 1219.5455
B14: Adj. EBITDA Margin % | C14: =Model!D252 -> 0.1564541 | D14: =Model!E252 -> 0.15508147 | E14: =Model!F252 -> 0.16346365 | F14: =Model!G252 -> 0.16693347 | G14: =Model!H252 -> 0.15830976 | H14: =Model!I252 -> 0.17123532 | I14: =Model!J252 -> 0.18218364 | J14: =Model!K252 -> 0.18788172 | K14: =Model!L252 -> 0.19005596 | L14: =Model!Q252 -> 0.18394875 | M14: =Model!V252 -> 0.14944288 | N14: =Model!AA252 -> 0.16315774 | O14: =Model!AF252 -> 0.18644361 | P14: =Model!AK252 -> 0.18769246 | Q14: =Model!AP252 -> 0.21077626 | R14: =Model!AQ252 -> 0.21771312 | S14: =Model!AR252 -> 0.22326339 | T14: =Model!AS252 -> 0.22806904 | U14: =Model!AT252 -> 0.23046266 | V14: =Model!AU252 -> 0.23234321
B15: EBIT Margin % | C15: =Model!D253 -> 0.11967451 | D15: =Model!E253 -> 0.1167375 | E15: =Model!F253 -> 0.12481112 | F15: =Model!G253 -> 0.13002287 | G15: =Model!H253 -> 0.12418552 | H15: =Model!I253 -> 0.13267927 | I15: =Model!J253 -> 0.10734636 | J15: =Model!K253 -> 0.12523287 | K15: =Model!L253 -> 0.12659071 | L15: =Model!Q253 -> 0.12404579 | M15: =Model!V253 -> 0.09762883 | N15: =Model!AA253 -> 0.1101073 | O15: =Model!AF253 -> 0.1490478 | P15: =Model!AK253 -> 0.15780793 | Q15: =Model!AP253 -> 0.17742588 | R15: =Model!AQ253 -> 0.21550006 | S15: =Model!AR253 -> 0.18785316 | T15: =Model!AS253 -> 0.19477556 | U15: =Model!AT253 -> 0.19712877 | V15: =Model!AU253 -> 0.19915779
C17: =C7 -> 2012 | D17: =D7 -> 2013 | E17: =E7 -> 2014 | F17: =F7 -> 2015 | G17: =G7 -> 2016 | H17: =H7 -> 2017 | I17: =I7 -> 2018 | J17: =J7 -> 2019 | ... V17: =V7 -> 2031E
B18: ROIC | C18: =IFERROR(Model!D397+0,NA()) -> 0.11939859 | D18: =IFERROR(Model!E397+0,NA()) -> 0.10052968 | E18: =IFERROR(Model!F397+0,NA()) -> 0.10382934 | F18: =IFERROR(Model!G397+0,NA()) -> 0.10376977 | G18: =IFERROR(Model!H397+0,NA()) -> 0.10792758 | H18: =IFERROR(Model!I397+0,NA()) -> 0.1164639 | I18: =IFERROR(Model!J397+0,NA()) -> 0.094774961 | J18: =IFERROR(Model!K397+0,NA()) -> 0.1224646 | K18: =IFERROR(Model!L397+0,NA()) -> 0.10531347 | L18: =IFERROR(Model!Q397+0,NA()) -> 0.096014801 | M18: =IFERROR(Model!V397+0,NA()) -> 0.080656647 | N18: =IFERROR(Model!AA397+0,NA()) -> 0.11482239 | O18: =IFERROR(Model!AF397+0,NA()) -> 0.16769573 | P18: =IFERROR(Model!AK397+0,NA()) -> 0.15561939 | Q18: =IFERROR(Model!AP397+0,NA()) -> 0.180706 | R18: =IFERROR(Model!AQ397+0,NA()) -> 0.18625395 | S18: =IFERROR(Model!AR397+0,NA()) -> 0.19406949 | T18: =IFERROR(Model!AS397+0,NA()) -> 0.20214688 | U18: =IFERROR(Model!AT397+0,NA()) -> 0.20796692 | V18: =IFERROR(Model!AU397+0,NA()) -> 0.21323528
B19: RONTA | C19: =IFERROR(Model!D408+0,NA()) -> 0.17936698 | D19: =IFERROR(Model!E408+0,NA()) -> 0.15662568 | E19: =IFERROR(Model!F408+0,NA()) -> 0.14668881 | F19: =IFERROR(Model!G408+0,NA()) -> 0.14034851 | G19: =IFERROR(Model!H408+0,NA()) -> 0.12872082 | H19: =IFERROR(Model!I408+0,NA()) -> 0.13518517 | I19: =IFERROR(Model!J408+0,NA()) -> 0.13917755 | J19: =IFERROR(Model!K408+0,NA()) -> 0.16131807 | K19: =IFERROR(Model!L408+0,NA()) -> 0.12832556 | L19: =IFERROR(Model!Q408+0,NA()) -> 0.10172139 | M19: =IFERROR(Model!V408+0,NA()) -> 0.099246509 | N19: =IFERROR(Model!AA408+0,NA()) -> 0.13779968 | O19: =IFERROR(Model!AF408+0,NA()) -> 0.18795293 | P19: =IFERROR(Model!AK408+0,NA()) -> 0.16904206 | Q19: =IFERROR(Model!AP408+0,NA()) -> 0.20142276 | R19: =IFERROR(Model!AQ408+0,NA()) -> 0.21064484 | S19: =IFERROR(Model!AR408+0,NA()) -> 0.22259846 | T19: =IFERROR(Model!AS408+0,NA()) -> 0.23497117 | U19: =IFERROR(Model!AT408+0,NA()) -> 0.24473416 | V19: =IFERROR(Model!AU408+0,NA()) -> 0.25374714
B20: Adj. EBITDA margin % | C20: =IFERROR(Model!D252+0,NA()) -> 0.1564541 | D20: =IFERROR(Model!E252+0,NA()) -> 0.15508147 | E20: =IFERROR(Model!F252+0,NA()) -> 0.16346365 | F20: =IFERROR(Model!G252+0,NA()) -> 0.16693347 | G20: =IFERROR(Model!H252+0,NA()) -> 0.15830976 | H20: =IFERROR(Model!I252+0,NA()) -> 0.17123532 | I20: =IFERROR(Model!J252+0,NA()) -> 0.18218364 | J20: =IFERROR(Model!K252+0,NA()) -> 0.18788172 | K20: =IFERROR(Model!L252+0,NA()) -> 0.19005596 | L20: =IFERROR(Model!Q252+0,NA()) -> 0.18394875 | M20: =IFERROR(Model!V252+0,NA()) -> 0.14944288 | N20: =IFERROR(Model!AA252+0,NA()) -> 0.16315774 | O20: =IFERROR(Model!AF252+0,NA()) -> 0.18644361 | P20: =IFERROR(Model!AK252+0,NA()) -> 0.18769246 | Q20: =IFERROR(Model!AP252+0,NA()) -> 0.21077626 | R20: =IFERROR(Model!AQ252+0,NA()) -> 0.21771312 | S20: =IFERROR(Model!AR252+0,NA()) -> 0.22326339 | T20: =IFERROR(Model!AS252+0,NA()) -> 0.22806904 | U20: =IFERROR(Model!AT252+0,NA()) -> 0.23046266 | V20: =IFERROR(Model!AU252+0,NA()) -> 0.23234321
B21: FCF margin % | C21: =IFERROR(Model!D289+0,NA()) -> 0.042459184 | D21: =IFERROR(Model!E289+0,NA()) -> 0.041835229 | E21: =IFERROR(Model!F289+0,NA()) -> 0.030469609 | F21: =IFERROR(Model!G289+0,NA()) -> 0.00040082363 | G21: =IFERROR(Model!H289+0,NA()) -> 0.12836233 | H21: =IFERROR(Model!I289+0,NA()) -> 0.10254088 | I21: =IFERROR(Model!J289+0,NA()) -> 0.074016079 | J21: =IFERROR(Model!K289+0,NA()) -> 0.1005249 | K21: =IFERROR(Model!L289+0,NA()) -> 0.12117171 | L21: =IFERROR(Model!Q289+0,NA()) -> 0.19012108 | M21: =IFERROR(Model!V289+0,NA()) -> 0.059077804 | N21: =IFERROR(Model!AA289+0,NA()) -> 0.079614941 | O21: =IFERROR(Model!AF289+0,NA()) -> 0.10312374 | P21: =IFERROR(Model!AK289+0,NA()) -> 0.09541909 | Q21: =IFERROR(Model!AP289+0,NA()) -> 0.067548985 | R21: =IFERROR(Model!AQ289+0,NA()) -> 0.089368164 | S21: =IFERROR(Model!AR289+0,NA()) -> 0.11888223 | T21: =IFERROR(Model!AS289+0,NA()) -> 0.13045197 | U21: =IFERROR(Model!AT289+0,NA()) -> 0.13622732 | V21: =IFERROR(Model!AU289+0,NA()) -> 0.13856649
